{
  "type": "Feature",
  "properties": {
    "iso:country":"FR",
    "sg:address":"Parc d'Activit\u00e9s de la Caille",
    "sg:city":"Allonzier la Caille",
    "sg:orig_category":"Non-Classified Establishments",
    "sg:phone":"+33 4 50 46 46 40",
    "sg:postcode":"74350",
    "sg:province":"Rhone-Alpes",
    "wof:name":"Usidiam S.a.r.l.",
    "wof:placetype":"venue"
},
  "geometry": {"coordinates":[6.035224,45.977737],"type":"Point"}
}