{
  "type": "Feature",
  "properties": {
    "addr:full":"B.P. 110 Saint Just en Chauss\u00e9e C\u00e9dex^^60131 Saint Just en Chauss\u00e9e Basse Normandie 60131",
    "addr:housenumber":"b.p. 110",
    "addr:postcode":"saint;60131",
    "addr:street":"Saint Just En Chausse\u0301E Ce\u0301Dex^^60131;Chausse\u0301E Basse",
    "iso:country":"FR",
    "sg:address":"B.P. 110",
    "sg:city":"Saint Just en Chauss\u00e9e C\u00e9dex^^60131 Saint Just en Chauss\u00e9e",
    "sg:orig_category":"Non-Classified Establishments",
    "sg:phone":"+33 3 44 77 59 00",
    "sg:postcode":"60131",
    "sg:province":"Basse Normandie",
    "wof:name":"Kaysersberg Packaging S.a.",
    "wof:placetype":"venue"
},
  "geometry": {"coordinates":[2.373278,49.516033],"type":"Point"}
}