{
  "type": "Feature",
  "properties": {
    "iso:country":"FR",
    "sg:address":"9, Rue Condorcet, 91350 Grigny",
    "sg:orig_category":"Unclassifiable Establishments",
    "sg:phone":"+33 1 69 02 76 30",
    "sg:province":"Ile de France",
    "wof:name":"Marble Technics Exploitation S.a.r.l.",
    "wof:placetype":"venue"
},
  "geometry": {"coordinates":[2.37522,48.647961],"type":"Point"}
}