{
  "type": "Feature",
  "properties": {
    "addr:full":"22 Rue Poincar\u00e9 57600 Forbach Lorraine 57600",
    "addr:housenumber":"22",
    "addr:postcode":"57600;57600",
    "addr:street":"Rue Poincare\u0301",
    "iso:country":"FR",
    "sg:address":"22 Rue Poincar\u00e9 57600 Forbach",
    "sg:classifiers":[
        {
            "category":"Home & Garden",
            "subcategory":"Furniture",
            "type":"Retail Goods"
        }
    ],
    "sg:phone":"+33 3 87 87 62 15",
    "sg:postcode":"57600",
    "sg:province":"Lorraine",
    "sg:tags":[
        "household",
        "wood"
    ],
    "wof:name":"Joseph Wolff Sa",
    "wof:placetype":"venue"
},
  "geometry": {"coordinates":[6.906732,49.186523],"type":"Point"}
}