{
  "type": "Feature",
  "properties": {
    "addr:full":"38 all\u00e9e Marines; Bayonne; 64112 Champagne",
    "addr:housenumber":"38",
    "addr:postcode":"64112",
    "addr:street":"Alle\u0301E Marines",
    "iso:country":"FR",
    "sg:address":"38 all\u00e9e Marines; Bayonne; 64112",
    "sg:classifiers":[
        {
            "category":"Banks & Credit Unions",
            "subcategory":"Bank",
            "type":"Services"
        }
    ],
    "sg:phone":"+33 5 59 44 75 55",
    "sg:province":"Champagne",
    "wof:name":"Banque Francaise, De Cr\u00e9dit Cooperatif",
    "wof:placetype":"venue"
},
  "geometry": {"coordinates":[-1.478469,43.495216],"type":"Point"}
}