{
  "type": "Feature",
  "properties": {
    "addr:full":"Catussou 81160 Saint Ju\u00e9ry Midi Pyr\u00e9n\u00e9es",
    "addr:postcode":"81160",
    "addr:street":"Catussou",
    "iso:country":"FR",
    "sg:address":"Catussou 81160 Saint Ju\u00e9ry",
    "sg:orig_category":"Unclassifiable Establishments",
    "sg:phone":"+33 5 63 45 37 29",
    "sg:province":"Midi Pyr\u00e9n\u00e9es",
    "wof:name":"Dubosclard Nettoyage S.a.r.l.",
    "wof:placetype":"venue"
},
  "geometry": {"coordinates":[2.213698,43.951466],"type":"Point"}
}