{
  "type": "Feature",
  "properties": {
    "addr:full":"72 Av Du Baron Lacrosse Zac De Kergaradec 29850 Gouesnou Gouesnou Bretagne 29850",
    "addr:postcode":"29850;29850",
    "addr:street":"72 Av Du Baron Lacrosse Zac De Kergaradec",
    "iso:country":"FR",
    "sg:address":"72 Av Du Baron Lacrosse Zac De Kergaradec 29850 Gouesnou",
    "sg:city":"Gouesnou",
    "sg:classifiers":[
        {
            "category":"Professional",
            "subcategory":"Engineering",
            "type":"Services"
        }
    ],
    "sg:phone":"+33 2 98 41 44 41",
    "sg:postcode":"29850",
    "sg:province":"Bretagne",
    "sg:tags":[
        "machine",
        "-",
        "environment",
        "equipment",
        "machinery",
        "mechanical"
    ],
    "wof:name":"Cerberus",
    "wof:placetype":"venue"
},
  "geometry": {"coordinates":[-4.465689,48.44989],"type":"Point"}
}