{
  "type": "Feature",
  "properties": {
    "addr:full":"141, Rue du 8 Mai 1945, 42153 Riorges Rhone-Alpes",
    "addr:housenumber":"141",
    "addr:postcode":"42153",
    "addr:street":"Rue Du 8 Mai 1945",
    "iso:country":"FR",
    "sg:address":"141, Rue du 8 Mai 1945, 42153 Riorges",
    "sg:orig_category":"Unclassifiable Establishments",
    "sg:phone":"+33 4 77 72 05 21",
    "sg:province":"Rhone-Alpes",
    "wof:name":"M.3.d. S.a.r.l.",
    "wof:placetype":"venue"
},
  "geometry": {"coordinates":[4.029456,46.044212],"type":"Point"}
}