{
  "type": "Feature",
  "properties": {
    "iso:country":"FR",
    "sg:address":"56 Rue Frederic Fays 69100 Villeurbanne",
    "sg:classifiers":[
        {
            "category":"Shopping",
            "type":"Retail Goods"
        }
    ],
    "sg:phone":"+33 4 72 91 23 60",
    "sg:postcode":"69100",
    "sg:province":"Rhone-Alpes",
    "sg:tags":[
        "metallurgy",
        "finished",
        "-",
        "metalworking",
        "metallic"
    ],
    "wof:name":"Ets Louis Vallet",
    "wof:placetype":"venue"
},
  "geometry": {"coordinates":[4.90553,45.760632],"type":"Point"}
}