{
  "type": "Feature",
  "properties": {
    "iso:country":"FR",
    "sg:address":"B.P. 235, 95523 Cergy C\u00e9dex^^14, Chauss\u00e9e Jules C\u00e9sar - Immeuble le Pr\u00e9sident, 95520 Cergy",
    "sg:orig_category":"Non-Classified Establishments",
    "sg:phone":"+33 1 30 75 37 37",
    "sg:postcode":"95520",
    "sg:province":"Ile de France",
    "wof:name":"Apave Parisienne",
    "wof:placetype":"venue"
},
  "geometry": {"coordinates":[2.064945,49.064018],"type":"Point"}
}