{
  "type": "Feature",
  "properties": {
    "iso:country":"FR",
    "sg:address":"28 Rue Gambetta 50200 Coutances",
    "sg:city":"Coutances",
    "sg:classifiers":[
        {
            "category":"Wholesale",
            "subcategory":"Medical Equipment & Supplies",
            "type":"Manufacturing & Wholesale Goods"
        }
    ],
    "sg:phone":"+33 2 33 45 08 02",
    "sg:postcode":"50200",
    "sg:province":"Basse Normandie",
    "sg:tags":[
        "instrument",
        "health",
        "-",
        "precision"
    ],
    "wof:name":"Cfl Creation Dentaire",
    "wof:placetype":"venue"
},
  "geometry": {"coordinates":[-1.442399,49.052078],"type":"Point"}
}