{
  "type": "Feature",
  "properties": {
    "addr:full":"Les Brandeaux 24430 Coursac Coursac Aquitaine 24430",
    "addr:postcode":"24430;24430",
    "iso:country":"FR",
    "sg:address":"Les Brandeaux 24430 Coursac",
    "sg:city":"Coursac",
    "sg:orig_category":"Non-Classified Establishments",
    "sg:phone":"+33 5 53 54 62 16",
    "sg:postcode":"24430",
    "sg:province":"Aquitaine",
    "wof:name":"J Lacoste S.a.",
    "wof:placetype":"venue"
},
  "geometry": {"coordinates":[0.638874,45.128197],"type":"Point"}
}