{
  "type": "Feature",
  "properties": {
    "iso:country":"FR",
    "sg:address":"170 Rue De La R\u00e9publique 68502 Guebwiller Cedex",
    "sg:city":"Guebwiller",
    "sg:classifiers":[
        {
            "category":"Professional",
            "subcategory":"Engineering",
            "type":"Services"
        }
    ],
    "sg:phone":"+33 3 89 74 41 41",
    "sg:postcode":"68500",
    "sg:province":"Alsace",
    "sg:tags":[
        "machine",
        "-",
        "mechanical"
    ],
    "wof:name":"Nsc Groupe",
    "wof:placetype":"venue"
},
  "geometry": {"coordinates":[7.205797,47.913773],"type":"Point"}
}