{
  "type": "Feature",
  "properties": {
    "iso:country":"FR",
    "sg:address":"36, Quai Charles Guinot, 37400 Amboise",
    "sg:city":"Amboise",
    "sg:orig_category":"Unclassifiable Establishments",
    "sg:phone":"+33 2 47 30 45 45",
    "sg:postcode":"37400",
    "sg:province":"Centre",
    "wof:name":"Le Choiseul",
    "wof:placetype":"venue"
},
  "geometry": {"coordinates":[0.988617,47.415138],"type":"Point"}
}