{
  "type": "Feature",
  "properties": {
    "addr:full":"rue Grange Morin 69400 Arnas Rhone-Alpes",
    "addr:postcode":"69400",
    "addr:street":"Rue Grange Morin",
    "iso:country":"FR",
    "sg:address":"rue Grange Morin 69400 Arnas",
    "sg:classifiers":[
        {
            "category":"Manufacturing",
            "subcategory":"Motor Vehicles & Parts",
            "type":"Manufacturing & Wholesale Goods"
        }
    ],
    "sg:phone":"+33 4 74 65 60 80",
    "sg:province":"Rhone-Alpes",
    "sg:tags":[
        "automotive",
        "industry",
        "component",
        "plastic"
    ],
    "wof:name":"Plastohm S.a.",
    "wof:placetype":"venue"
},
  "geometry": {"coordinates":[4.724295,45.999889],"type":"Point"}
}