{
  "type": "Feature",
  "properties": {
    "addr:full":"ZA Plan Cumin Les Marches Rhone-Alpes 73800",
    "addr:postcode":"73800",
    "addr:street":"Za Plan Cumin Les;Rhone-Alpes",
    "iso:country":"FR",
    "sg:address":"ZA Plan Cumin",
    "sg:city":"Les Marches",
    "sg:orig_category":"Non-Classified Establishments",
    "sg:phone":"+33 4 79 28 11 48",
    "sg:postcode":"73800",
    "sg:province":"Rhone-Alpes",
    "wof:name":"Adrien Vacher S.a.",
    "wof:placetype":"venue"
},
  "geometry": {"coordinates":[6.00053,45.498459],"type":"Point"}
}