{
  "type": "Feature",
  "properties": {
    "iso:country":"FR",
    "sg:address":"166, Av de Denain, 59300 Valenciennes",
    "sg:orig_category":"Unclassifiable Establishments",
    "sg:phone":"+33 3 27 46 40 00",
    "sg:province":"Nord Pas-de-Calais",
    "wof:name":"Sergeant 59 S.a.",
    "wof:placetype":"venue"
},
  "geometry": {"coordinates":[3.49655,50.353302],"type":"Point"}
}