{
  "type": "Feature",
  "properties": {
    "addr:full":"166, Av de Denain, 59300 Valenciennes Nord Pas-de-Calais",
    "addr:postcode":"59300",
    "addr:street":"166 Av De Denain",
    "iso:country":"FR",
    "sg:address":"166, Av de Denain, 59300 Valenciennes",
    "sg:orig_category":"Unclassifiable Establishments",
    "sg:phone":"+33 3 27 46 40 00",
    "sg:province":"Nord Pas-de-Calais",
    "wof:name":"Sergeant 59 S.a.",
    "wof:placetype":"venue"
},
  "geometry": {"coordinates":[3.49655,50.353302],"type":"Point"}
}