{
  "type": "Feature",
  "properties": {
    "iso:country":"FR",
    "sg:address":"50 Av Carnot 21120 Is Sur Tille",
    "sg:city":"Avelanges",
    "sg:orig_category":"Goods handling - material and equipment Mechanical Engineering - machines Packaging materials - plas",
    "sg:phone":"+33 3 80 95 69 00",
    "sg:postcode":"21120",
    "sg:province":"Bourgogne",
    "wof:name":"Linpac Mh France Sa",
    "wof:placetype":"venue"
},
  "geometry": {"coordinates":[5.123712,47.520542],"type":"Point"}
}