{
  "type": "Feature",
  "properties": {
    "addr:full":"6, Rue du Colonel Clarenthal, 54300 Lun\u00e9ville Lorraine",
    "addr:housenumber":"6",
    "addr:postcode":"54300",
    "addr:street":"Rue Du Colonel Clarenthal",
    "iso:country":"FR",
    "sg:address":"6, Rue du Colonel Clarenthal, 54300 Lun\u00e9ville",
    "sg:orig_category":"Unclassifiable Establishments",
    "sg:phone":"+33 3 83 76 64 60",
    "sg:province":"Lorraine",
    "wof:name":"C.m.l. - Centre De Mesures Lorrain",
    "wof:placetype":"venue"
},
  "geometry": {"coordinates":[6.499119,48.592892],"type":"Point"}
}