{
  "type": "Feature",
  "properties": {
    "addr:full":"Ch\u00e2teau Monluc 32310 ST PUY Midi Pyr\u00e9n\u00e9es",
    "addr:postcode":"32310",
    "iso:country":"FR",
    "sg:address":"Ch\u00e2teau Monluc 32310 ST PUY",
    "sg:classifiers":[
        {
            "category":"Home & Garden",
            "subcategory":"Hardware",
            "type":"Retail Goods"
        }
    ],
    "sg:phone":"+33 5 62 28 94 00",
    "sg:province":"Midi Pyr\u00e9n\u00e9es",
    "sg:tags":[
        "produced",
        "spirit",
        "specialities"
    ],
    "wof:name":"Monluc S.a.",
    "wof:placetype":"venue"
},
  "geometry": {"coordinates":[0.346515,43.82272],"type":"Point"}
}