{
  "type": "Feature",
  "properties": {
    "addr:full":"B.P. 98, 77871 Montereau Fault Yonne Cedex^^60, Rue Jean Jaur\u00e8s, 77130 Montereau Fault Yonne Ile de France",
    "addr:postcode":"77871;77130",
    "addr:street":"B.P. 98;Rue Jean Jaure\u0300S",
    "iso:country":"FR",
    "sg:address":"B.P. 98, 77871 Montereau Fault Yonne Cedex^^60, Rue Jean Jaur\u00e8s, 77130 Montereau Fault Yonne",
    "sg:orig_category":"Non-Classified Establishments",
    "sg:phone":"+33 1 64 32 05 75",
    "sg:province":"Ile de France",
    "wof:name":"Tourisme Lepape S.a.",
    "wof:placetype":"venue"
},
  "geometry": {"coordinates":[2.891333,48.303902],"type":"Point"}
}