{
  "type": "Feature",
  "properties": {
    "addr:full":"avenue de Pi\u00e9mont 52100 Valcourt Champagne",
    "addr:postcode":"52100",
    "addr:street":"Avenue De Pie\u0301Mont",
    "iso:country":"FR",
    "sg:address":"avenue de Pi\u00e9mont 52100 Valcourt",
    "sg:classifiers":[
        {
            "category":"Manufacturing",
            "subcategory":"Rubber & Plastics",
            "type":"Manufacturing & Wholesale Goods"
        }
    ],
    "sg:phone":"+33 3 25 05 20 30",
    "sg:province":"Champagne",
    "sg:tags":[
        "packaging",
        "mean"
    ],
    "wof:name":"Sofibo Emballages Sa",
    "wof:placetype":"venue"
},
  "geometry": {"coordinates":[4.899785,48.618793],"type":"Point"}
}