{
  "type": "Feature",
  "properties": {
    "addr:full":"29, Rue Etienne Marey, 75020 Paris Ile de France",
    "addr:housenumber":"29",
    "addr:postcode":"75020",
    "addr:street":"Rue Etienne Marey",
    "iso:country":"FR",
    "sg:address":"29, Rue Etienne Marey, 75020 Paris",
    "sg:orig_category":"Unclassifiable Establishments",
    "sg:phone":"+33 1 43 61 72 49",
    "sg:province":"Ile de France",
    "wof:name":"G.k. Productions S.a.",
    "wof:placetype":"venue"
},
  "geometry": {"coordinates":[2.405441,48.867867],"type":"Point"}
}