{
  "type": "Feature",
  "properties": {
    "iso:country":"FR",
    "sg:address":"344 rue de la Belle Etoile 95948 Roissy Charles de Gaulle",
    "sg:classifiers":[
        {
            "category":"Professional",
            "type":"Services"
        }
    ],
    "sg:phone":"+33 1 48 63 64 64",
    "sg:province":"Picardie",
    "sg:tags":[
        "transport"
    ],
    "wof:name":"Calverson Sa",
    "wof:placetype":"venue"
},
  "geometry": {"coordinates":[0.15853,47.900101],"type":"Point"}
}