{
  "type": "Feature",
  "properties": {
    "iso:country":"FR",
    "sg:address":"96, Rue de Montalieu, 33320 Eysines",
    "sg:city":"Eysines",
    "sg:orig_category":"Non-Classified Establishments",
    "sg:phone":"+33 5 56 28 61 70",
    "sg:postcode":"33320",
    "sg:province":"Aquitaine",
    "wof:name":"Ateliers Bigata S.a.",
    "wof:placetype":"venue"
},
  "geometry": {"coordinates":[-0.665109,44.877888],"type":"Point"}
}