{
  "type": "Feature",
  "properties": {
    "iso:country":"FR",
    "sg:address":"32 Rue Etienne Marcel 75002 Paris",
    "sg:classifiers":[
        {
            "category":"Manufacturing",
            "subcategory":"Textiles",
            "type":"Manufacturing & Wholesale Goods"
        }
    ],
    "sg:phone":"+33 1 42 36 56 55",
    "sg:postcode":"75002",
    "sg:province":"Ile de France",
    "sg:tags":[
        "clothing",
        "accessory"
    ],
    "wof:name":"Industries Du Cuirs Sarl",
    "wof:placetype":"venue"
},
  "geometry": {"coordinates":[2.346376,48.864586],"type":"Point"}
}