{
  "type": "Feature",
  "properties": {
    "iso:country":"FR",
    "sg:address":"32, Av. G\u00e9n\u00e9ral de Gaulle, 67000 Strasbourg",
    "sg:city":"Strasbourg",
    "sg:orig_category":"Unclassifiable Establishments",
    "sg:phone":"+33 4 67 06 20 07",
    "sg:postcode":"67000",
    "sg:province":"Alsace",
    "wof:name":"Bio Alsace Produits S.a.r.l.",
    "wof:placetype":"venue"
},
  "geometry": {"coordinates":[7.768843,48.576931],"type":"Point"}
}