{
  "type": "Feature",
  "properties": {
    "iso:country":"FR",
    "sg:address":"ZAC du Baconnet 69700 Montagny",
    "sg:classifiers":[
        {
            "category":"Wholesale",
            "subcategory":"Meat",
            "type":"Manufacturing & Wholesale Goods"
        }
    ],
    "sg:phone":"+33 4 78 07 15 32",
    "sg:postcode":"69700",
    "sg:province":"Rhone-Alpes",
    "sg:tags":[
        "sausage",
        "casing",
        "natural"
    ],
    "wof:name":"Boyauderie Panier S.a.",
    "wof:placetype":"venue"
},
  "geometry": {"coordinates":[4.747478,45.620735],"type":"Point"}
}