{
  "type": "Feature",
  "properties": {
    "addr:full":"21 Boulevard Victor Hugo Le Winston 87000 Limoges Limousin 87000",
    "addr:housenumber":"21",
    "addr:postcode":"87000;87000",
    "addr:street":"Boulevard Victor Hugo Le Winston",
    "iso:country":"FR",
    "sg:address":"21 Boulevard Victor Hugo Le Winston 87000 Limoges",
    "sg:classifiers":[
        {
            "category":"Banks & Credit Unions",
            "subcategory":"Financial Services",
            "type":"Services"
        }
    ],
    "sg:phone":"+33 5 44 00 01 03",
    "sg:postcode":"87000",
    "sg:province":"Limousin",
    "sg:tags":[
        "banking",
        "finance",
        "insurance"
    ],
    "wof:name":"Credit Mutuel Centre Ouest",
    "wof:placetype":"venue"
},
  "geometry": {"coordinates":[1.254706,45.831238],"type":"Point"}
}