{
  "type": "Feature",
  "properties": {
    "addr:full":"6 Avenue Reille 75014 Paris Ile de France",
    "addr:housenumber":"6",
    "addr:postcode":"75014",
    "addr:street":"Avenue Reille",
    "iso:country":"FR",
    "sg:address":"6 Avenue Reille 75014 Paris",
    "sg:classifiers":[
        {
            "category":"Professional",
            "subcategory":"Printing & Photocopies",
            "type":"Services"
        }
    ],
    "sg:phone":"+33 1 58 10 31 00",
    "sg:province":"Ile de France",
    "sg:tags":[
        "publishing"
    ],
    "wof:name":"Presses Universitaires De France",
    "wof:placetype":"venue"
},
  "geometry": {"coordinates":[2.341026,48.825977],"type":"Point"}
}