{
  "type": "Feature",
  "properties": {
    "iso:country":"FR",
    "sg:address":"Zone D'Activite De La Vote 76650 Petit Couronne",
    "sg:classifiers":[
        {
            "category":"Professional",
            "type":"Services"
        }
    ],
    "sg:phone":"+33 2 35 67 60 00",
    "sg:province":"Haute Normandie",
    "sg:tags":[
        "-",
        "related",
        "road",
        "transport"
    ],
    "wof:name":"Ste Rouennaise De Services Sa",
    "wof:placetype":"venue"
},
  "geometry": {"coordinates":[1.03412,49.381748],"type":"Point"}
}