{
  "type": "Feature",
  "properties": {
    "iso:country":"FR",
    "sg:address":"Lieu Dit Panorama De La Bruyere 14350 Le Beny Bocage",
    "sg:city":"Dampierre",
    "sg:classifiers":[
        {
            "category":"Farming",
            "subcategory":"Farm & Veterinary Services",
            "type":"Manufacturing & Wholesale Goods"
        }
    ],
    "sg:phone":"+33 2 31 68 69 68",
    "sg:postcode":"14350",
    "sg:province":"Basse Normandie",
    "sg:tags":[
        "advice",
        "agriculture",
        "livestock",
        "business"
    ],
    "wof:name":"Pepinieres Conseil Sarl",
    "wof:placetype":"venue"
},
  "geometry": {"coordinates":[-0.88973,48.892654],"type":"Point"}
}