{
  "type": "Feature",
  "properties": {
    "iso:country":"FR",
    "sg:address":"13, Av. Morane Saulnier - Espace V\u00e9lizy le Nungesser, 78140 V\u00e9lizy Villacoublay",
    "sg:orig_category":"Unclassifiable Establishments",
    "sg:phone":"+33 1 34 63 04 80",
    "sg:province":"Ile de France",
    "wof:name":"E.c.i. T\u00e9l\u00e9com S.a.r.l.",
    "wof:placetype":"venue"
},
  "geometry": {"coordinates":[2.18246,48.78503],"type":"Point"}
}