{
  "type": "Feature",
  "properties": {
    "addr:full":"Av de Washington - Zone Industrielle B\u00e9thune Nord Pas-de-Calais 62400",
    "addr:postcode":"62400",
    "addr:street":"Av De Washington;Industrielle Be\u0301Thune Nord",
    "iso:country":"FR",
    "sg:address":"Av de Washington - Zone Industrielle",
    "sg:city":"B\u00e9thune",
    "sg:orig_category":"Unclassifiable Establishments",
    "sg:phone":"+33 3 21 57 09 76",
    "sg:postcode":"62400",
    "sg:province":"Nord Pas-de-Calais",
    "wof:name":"Coquel G\u00e9rard",
    "wof:placetype":"venue"
},
  "geometry": {"coordinates":[2.63787,50.530472],"type":"Point"}
}