{
  "type": "Feature",
  "properties": {
    "iso:country":"FR",
    "sg:address":"4 Cs Michelet Immeuble Iris 92800 Puteaux",
    "sg:classifiers":[
        {
            "category":"Farming",
            "subcategory":"Farm",
            "type":"Manufacturing & Wholesale Goods"
        }
    ],
    "sg:phone":"+33 1 47 96 97 66",
    "sg:postcode":"92800",
    "sg:province":"Ile de France",
    "sg:tags":[
        "horticulture",
        "agriculture",
        "livestock"
    ],
    "wof:name":"Grande Paroisse Sa",
    "wof:placetype":"venue"
},
  "geometry": {"coordinates":[2.248353,48.888062],"type":"Point"}
}