{
  "type": "Feature",
  "properties": {
    "iso:country":"FR",
    "sg:address":"Avenue De L Europe Station De Bailleul 59270 Bailleul",
    "sg:classifiers":[
        {
            "category":"Manufacturing",
            "subcategory":"Wood Products",
            "type":"Manufacturing & Wholesale Goods"
        }
    ],
    "sg:phone":"+33 3 28 50 97 97",
    "sg:province":"Nord Pas-de-Calais",
    "sg:tags":[
        "professional",
        "furniture"
    ],
    "wof:name":"Lavec Sarl",
    "wof:placetype":"venue"
},
  "geometry": {"coordinates":[2.679175,50.711166],"type":"Point"}
}