{
  "type": "Feature",
  "properties": {
    "addr:full":"95 Av Du G\u00e9n\u00e9ral De Gaulle 88300 Neufch\u00e2teau Lorraine 88300",
    "addr:postcode":"88300;88300",
    "addr:street":"95 Av Du Ge\u0301Ne\u0301Ral De Gaulle",
    "iso:country":"FR",
    "sg:address":"95 Av Du G\u00e9n\u00e9ral De Gaulle 88300 Neufch\u00e2teau",
    "sg:classifiers":[
        {
            "category":"Autos & Motor Vehicles",
            "subcategory":"Automobile Sales",
            "type":"Retail Goods"
        }
    ],
    "sg:phone":"+33 3 29 94 19 20",
    "sg:postcode":"88300",
    "sg:province":"Lorraine",
    "sg:tags":[
        "equipment",
        "motor-cars",
        "transport"
    ],
    "wof:name":"Reuchet Agences Sa",
    "wof:placetype":"venue"
},
  "geometry": {"coordinates":[5.692745,48.347546],"type":"Point"}
}