{
  "type": "Feature",
  "properties": {
    "addr:full":"Site Industriel Leurette 59820 Gravelines Nord Pas-de-Calais 59820",
    "addr:postcode":"59820;59820",
    "addr:street":"Gravelines Nord",
    "iso:country":"FR",
    "sg:address":"Site Industriel Leurette 59820 Gravelines",
    "sg:classifiers":[
        {
            "category":"Shopping",
            "subcategory":"Gifts & Souvenirs",
            "type":"Retail Goods"
        }
    ],
    "sg:phone":"+33 3 28 51 81 81",
    "sg:postcode":"59820",
    "sg:province":"Nord Pas-de-Calais",
    "sg:tags":[
        "product",
        "miscellaneous"
    ],
    "wof:name":"Dunkerquoise Des Blends (ddb)",
    "wof:placetype":"venue"
},
  "geometry": {"coordinates":[2.13518,50.990211],"type":"Point"}
}