{
  "type": "Feature",
  "properties": {
    "addr:full":"Rue Delamare; Louviers; 27400 Haute Normandie 27400",
    "addr:postcode":"27400;27400",
    "addr:street":"Rue Delamare;Normandie",
    "iso:country":"FR",
    "sg:address":"Rue Delamare; Louviers; 27400",
    "sg:classifiers":[
        {
            "category":"Banks & Credit Unions",
            "subcategory":"Bank",
            "type":"Services"
        }
    ],
    "sg:phone":"+33 32255252",
    "sg:postcode":"27400",
    "sg:province":"Haute Normandie",
    "wof:name":"Cr\u00e9dit Agricole De L'eure",
    "wof:placetype":"venue"
},
  "geometry": {"coordinates":[1.169296,49.216148],"type":"Point"}
}