{
  "type": "Feature",
  "properties": {
    "addr:full":"320, Rue Andr\u00e9 Lasquin, 74700 Sallanches Rhone-Alpes",
    "addr:housenumber":"320",
    "addr:postcode":"74700",
    "addr:street":"Rue Andre\u0301 Lasquin",
    "iso:country":"FR",
    "sg:address":"320, Rue Andr\u00e9 Lasquin, 74700 Sallanches",
    "sg:orig_category":"Unclassifiable Establishments",
    "sg:phone":"+33 4 50 58 03 15",
    "sg:province":"Rhone-Alpes",
    "wof:name":"Rossat Georges S.a.",
    "wof:placetype":"venue"
},
  "geometry": {"coordinates":[6.638506,45.942059],"type":"Point"}
}