{
  "type": "Feature",
  "properties": {
    "iso:country":"FR",
    "sg:address":"Ch\u00e2teau Peyrolan 33710 Saint Ciers de Canesse",
    "sg:city":"Bayon-sur-Gironde",
    "sg:orig_category":"Unclassifiable Establishments",
    "sg:phone":"+33 5 57 64 92 49",
    "sg:postcode":"33710",
    "sg:province":"Aquitaine",
    "wof:name":"De Pardieu Fran\u00e7ois",
    "wof:placetype":"venue"
},
  "geometry": {"coordinates":[-0.61162,45.0868],"type":"Point"}
}