{
  "type": "Feature",
  "properties": {
    "iso:country":"FR",
    "sg:address":"10, Rue des Champs Fourgons, 92230 Gennevilliers",
    "sg:orig_category":"Non-Classified Establishments",
    "sg:phone":"+33 1 41 47 11 00",
    "sg:province":"Ile de France",
    "wof:name":"Grenelle Service S.a.",
    "wof:placetype":"venue"
},
  "geometry": {"coordinates":[2.297031,48.942463],"type":"Point"}
}