{
  "type": "Feature",
  "properties": {
    "iso:country":"FR",
    "sg:address":"340, Rue Aristide Berg\u00e8s - ZAC du Pr\u00e9 Millet, 38330 Montbonnot Saint Martin",
    "sg:orig_category":"Unclassifiable Establishments",
    "sg:phone":"+33 4 76 52 29 40",
    "sg:postcode":"38330",
    "sg:province":"Rhone-Alpes",
    "wof:name":"Gr\u00e9silog S.a.",
    "wof:placetype":"venue"
},
  "geometry": {"coordinates":[5.817105,45.221626],"type":"Point"}
}