{
  "type": "Feature",
  "properties": {
    "iso:country":"FR",
    "sg:address":"15bis, Av. de l'Alma, 94214 La Varenne Saint Hilaire C\u00e9dex",
    "sg:orig_category":"Non-Classified Establishments",
    "sg:phone":"+33 1 48 85 71 46",
    "sg:province":"\u00cele-de-France",
    "wof:name":"Hubert Cloix S.a.",
    "wof:placetype":"venue"
},
  "geometry": {"coordinates":[2.504725,48.801537],"type":"Point"}
}