{
  "type": "Feature",
  "properties": {
    "addr:full":"Zone Artisanale 39400 Longchaumois Franche Comt\u00e9 39400",
    "addr:postcode":"39400;39400",
    "addr:street":"Zone Artisanale;Franche Comte\u0301",
    "iso:country":"FR",
    "sg:address":"Zone Artisanale 39400 Longchaumois",
    "sg:classifiers":[
        {
            "category":"Shopping",
            "subcategory":"Computers & Home Electronics",
            "type":"Retail Goods"
        }
    ],
    "sg:phone":"+33 3 84 60 60 46",
    "sg:postcode":"39400",
    "sg:province":"Franche Comt\u00e9",
    "sg:tags":[
        "equipment",
        "electrical",
        "component",
        "electric",
        "electronic"
    ],
    "wof:name":"Sarl Moulages Plastique Samardia",
    "wof:placetype":"venue"
},
  "geometry": {"coordinates":[5.933755,46.462059],"type":"Point"}
}