{
  "type": "Feature",
  "properties": {
    "addr:full":"16 Square De La Poterne 91300 Massy Ile de France 91300",
    "addr:housenumber":"16",
    "addr:postcode":"91300;91300",
    "addr:street":"Square De La Poterne;Ile De France",
    "iso:country":"FR",
    "sg:address":"16 Square De La Poterne 91300 Massy",
    "sg:classifiers":[
        {
            "category":"Professional",
            "subcategory":"Engineering",
            "type":"Services"
        }
    ],
    "sg:phone":"+33 1 69 20 69 21",
    "sg:postcode":"91300",
    "sg:province":"Ile de France",
    "sg:tags":[
        "machine",
        "-",
        "mechanical"
    ],
    "wof:name":"Symex Sa",
    "wof:placetype":"venue"
},
  "geometry": {"coordinates":[2.27036,48.735619],"type":"Point"}
}