{
  "type": "Feature",
  "properties": {
    "addr:full":"91712 Sainte Genevi\u00e8ve des Bois C\u00e9dex^^Rue Cl\u00e9ment Ader - ZAC des Ciroliers Fleury M\u00e9rogis Ile de France 91700",
    "addr:postcode":"91712;91700",
    "addr:street":"Des;Zac Des Ciroliers Fleury Me\u0301Rogis Ile De France",
    "iso:country":"FR",
    "sg:address":"91712 Sainte Genevi\u00e8ve des Bois C\u00e9dex^^Rue Cl\u00e9ment Ader - ZAC des Ciroliers",
    "sg:city":"Fleury M\u00e9rogis",
    "sg:orig_category":"Non-Classified Establishments",
    "sg:phone":"+33 1 69 46 56 00",
    "sg:postcode":"91700",
    "sg:province":"Ile de France",
    "wof:name":"Informater S.a.",
    "wof:placetype":"venue"
},
  "geometry": {"coordinates":[2.326545,48.640656],"type":"Point"}
}