{
  "type": "Feature",
  "properties": {
    "addr:full":"Pl De La Vigne Aux Loups 91160 Longjumeau Ile de France 91160",
    "addr:postcode":"91160;ile;91160",
    "addr:street":"Pl De La Vigne Aux Loups;France",
    "iso:country":"FR",
    "sg:address":"Pl De La Vigne Aux Loups 91160 Longjumeau",
    "sg:classifiers":[
        {
            "category":"Professional",
            "subcategory":"Advertising",
            "type":"Services"
        }
    ],
    "sg:phone":"+33 1 69 10 85 85",
    "sg:postcode":"91160",
    "sg:province":"Ile de France",
    "sg:tags":[
        "marketing",
        "medium",
        "communication"
    ],
    "wof:name":"Publi Trans",
    "wof:placetype":"venue"
},
  "geometry": {"coordinates":[2.297335,48.704174],"type":"Point"}
}