{
  "type": "Feature",
  "properties": {
    "addr:full":"Rue des Mines Staffelfelden Alsace 68850",
    "addr:postcode":"68850",
    "addr:street":"Rue Des Mines",
    "iso:country":"FR",
    "sg:address":"Rue des Mines",
    "sg:city":"Staffelfelden",
    "sg:orig_category":"Unclassifiable Establishments",
    "sg:phone":"+33 3 89 57 83 60",
    "sg:postcode":"68850",
    "sg:province":"Alsace",
    "wof:name":"Mines De Potasse D'alsace S.a.",
    "wof:placetype":"venue"
},
  "geometry": {"coordinates":[7.26031,47.828606],"type":"Point"}
}