{
  "type": "Feature",
  "properties": {
    "addr:full":"34, Bd Maxime Gorki, 94808 Villejuif C\u00e9dex \u00cele-de-France",
    "addr:housenumber":"34",
    "addr:postcode":"94808",
    "addr:street":"Bd Maxime Gorki;Ce\u0301Dex",
    "iso:country":"FR",
    "sg:address":"34, Bd Maxime Gorki, 94808 Villejuif C\u00e9dex",
    "sg:orig_category":"Non-Classified Establishments",
    "sg:phone":"+33 1 46 77 40 40",
    "sg:province":"\u00cele-de-France",
    "wof:name":"I.n.h.n.i. - Institut National Hygi\u00e8ne Nettoyage Industriel",
    "wof:placetype":"venue"
},
  "geometry": {"coordinates":[2.367522,48.797577],"type":"Point"}
}