{
  "type": "Feature",
  "properties": {
    "addr:full":"31, Rue Alphonse Daudet, 80230 Vaudricourt Picardie",
    "addr:housenumber":"31",
    "addr:postcode":"80230",
    "addr:street":"Rue Alphonse Daudet",
    "iso:country":"FR",
    "sg:address":"31, Rue Alphonse Daudet, 80230 Vaudricourt",
    "sg:orig_category":"Unclassifiable Establishments",
    "sg:phone":"+33 3 22 30 20 88",
    "sg:province":"Picardie",
    "wof:name":"Sanichrome S.a.r.l.",
    "wof:placetype":"venue"
},
  "geometry": {"coordinates":[1.547056,50.117538],"type":"Point"}
}