{
  "type": "Feature",
  "properties": {
    "iso:country":"FR",
    "sg:address":"67 Rue Racine 93230 Romainville",
    "sg:classifiers":[
        {
            "category":"Utilities",
            "subcategory":"Electric",
            "type":"Services"
        }
    ],
    "sg:phone":"+33 1 48 57 30 91",
    "sg:postcode":"93230",
    "sg:province":"Ile de France",
    "sg:tags":[
        "electricity",
        "electronic",
        "electrical",
        "equipment"
    ],
    "wof:name":"Soselec",
    "wof:placetype":"venue"
},
  "geometry": {"coordinates":[2.437364,48.872879],"type":"Point"}
}