{
  "type": "Feature",
  "properties": {
    "addr:full":"14, Av. de Paris, 41600 Nouan le Fuzelier Chaon Centre 41600",
    "addr:postcode":"41600;41600",
    "addr:street":"14 Av. De Paris",
    "iso:country":"FR",
    "sg:address":"14, Av. de Paris, 41600 Nouan le Fuzelier",
    "sg:city":"Chaon",
    "sg:orig_category":"Non-Classified Establishments",
    "sg:phone":"+33 2 54 96 86 16",
    "sg:postcode":"41600",
    "sg:province":"Centre",
    "wof:name":"Atelier La Platine Martin Pascal",
    "wof:placetype":"venue"
},
  "geometry": {"coordinates":[2.035222,47.536743],"type":"Point"}
}