{
  "type": "Feature",
  "properties": {
    "iso:country":"FR",
    "sg:address":"1, Les Basses Usti\u00e8res, 41220 Crouy sur Cosson",
    "sg:city":"Crouy-sur-Cosson",
    "sg:orig_category":"Unclassifiable Establishments",
    "sg:phone":"+33 2 54 87 51 36",
    "sg:postcode":"41220",
    "sg:province":"Centre",
    "wof:name":"Pothon Platrerie Construction De Sologne S.a.r.l.",
    "wof:placetype":"venue"
},
  "geometry": {"coordinates":[1.657628,47.58931],"type":"Point"}
}