{
  "type": "Feature",
  "properties": {
    "addr:full":"8 Rue Laferri\u00e8re 75009 Paris Ile de France 75009",
    "addr:housenumber":"8",
    "addr:postcode":"75009;75009",
    "addr:street":"Rue Laferrie\u0300Re",
    "iso:country":"FR",
    "sg:address":"8 Rue Laferri\u00e8re 75009 Paris",
    "sg:classifiers":[
        {
            "category":"Travel",
            "subcategory":"Hotels & Motels",
            "type":"Entertainment"
        }
    ],
    "sg:phone":"+33 1 48 78 60 92",
    "sg:postcode":"75009",
    "sg:province":"Ile de France",
    "sg:tags":[
        "hotels",
        "business",
        "restaurant"
    ],
    "wof:name":"Hotel Arvor",
    "wof:placetype":"venue"
},
  "geometry": {"coordinates":[2.338504,48.878342],"type":"Point"}
}