{
  "type": "Feature",
  "properties": {
    "addr:full":"Za La Condamine 26400 Aouste Sur Sye Rhone-Alpes 26400",
    "addr:postcode":"26400;26400",
    "addr:street":"Za La;Rhone-Alpes",
    "iso:country":"FR",
    "sg:address":"Za La Condamine 26400 Aouste Sur Sye",
    "sg:classifiers":[
        {
            "category":"Manufacturing",
            "subcategory":"Chemicals & Compounds",
            "type":"Manufacturing & Wholesale Goods"
        }
    ],
    "sg:phone":"+33 4 75 25 41 44",
    "sg:postcode":"26400",
    "sg:province":"Rhone-Alpes",
    "sg:tags":[
        "pharmaceutical",
        "chemistry",
        "-",
        "by-product"
    ],
    "wof:name":"Poli Film France",
    "wof:placetype":"venue"
},
  "geometry": {"coordinates":[5.051145,44.716274],"type":"Point"}
}