{
  "type": "Feature",
  "properties": {
    "iso:country":"FR",
    "sg:address":"ZA de Bel Air",
    "sg:city":"Bourg des Comptes",
    "sg:orig_category":"Non-Classified Establishments",
    "sg:phone":"+33 2 99 42 48 48",
    "sg:postcode":"35890",
    "sg:province":"Bretagne",
    "wof:name":"Th\u00e9ard S.a.",
    "wof:placetype":"venue"
},
  "geometry": {"coordinates":[-1.747344,47.930679],"type":"Point"}
}