{
  "type": "Feature",
  "properties": {
    "iso:country":"FR",
    "sg:address":"Zi Du Petit Lapin 49230 St Germain Sur Moine",
    "sg:classifiers":[
        {
            "category":"Manufacturing",
            "subcategory":"Chemicals & Compounds",
            "type":"Manufacturing & Wholesale Goods"
        }
    ],
    "sg:phone":"+33 2 41 55 33 81",
    "sg:postcode":"49230",
    "sg:province":"Pays de Loire",
    "sg:tags":[
        "pharmaceutical",
        "chemistry"
    ],
    "wof:name":"Equimat Service",
    "wof:placetype":"venue"
},
  "geometry": {"coordinates":[-1.123896,47.118645],"type":"Point"}
}