{
  "type": "Feature",
  "properties": {
    "addr:full":"220, Rue de Poissy, 78670 Villennes sur Seine Ile de France",
    "addr:housenumber":"220",
    "addr:postcode":"78670",
    "addr:street":"Rue De Poissy",
    "iso:country":"FR",
    "sg:address":"220, Rue de Poissy, 78670 Villennes sur Seine",
    "sg:orig_category":"Unclassifiable Establishments",
    "sg:phone":"+33 1 39 75 80 83",
    "sg:province":"Ile de France",
    "wof:name":"Edler Von Graeve S.a.",
    "wof:placetype":"venue"
},
  "geometry": {"coordinates":[2.004504,48.929825],"type":"Point"}
}