{
  "type": "Feature",
  "properties": {
    "addr:full":"1, Rue de l'Industrie - ZAE la Semeuse, 59820 Gravelines Nord Pas-de-Calais",
    "addr:housenumber":"1",
    "addr:postcode":"59820",
    "addr:street":"Rue De L'Industrie Zae La Semeuse",
    "iso:country":"FR",
    "sg:address":"1, Rue de l'Industrie - ZAE la Semeuse, 59820 Gravelines",
    "sg:orig_category":"PANNEAUX PUBLICITAIRES, ENSEIGNES, CALICOTS, B\u00c2CHES, MARQUAGE INDUSTRIEL, PEINTURES PUBLICITAIRES SU",
    "sg:phone":"+33 3 28 51 99 33",
    "sg:province":"Nord Pas-de-Calais",
    "wof:name":"Cam\u00e9l\u00e9on S.a.r.l.",
    "wof:placetype":"venue"
},
  "geometry": {"coordinates":[2.121793,50.977947],"type":"Point"}
}