{
  "type": "Feature",
  "properties": {
    "iso:country":"FR",
    "sg:address":"12, Rue Louis Courrier, 77100 Meaux",
    "sg:orig_category":"Unclassifiable Establishments",
    "sg:phone":"+33 1 60 38 10 70",
    "sg:province":"Ile de France",
    "wof:name":"Henri Bieth Et Humber Industrie S.a.",
    "wof:placetype":"venue"
},
  "geometry": {"coordinates":[2.90142,48.949982],"type":"Point"}
}