{
  "type": "Feature",
  "properties": {
    "addr:full":"B.P. 15, 24160 Excideuil C\u00e9dex^^Av. Andr\u00e9 Audy, 24160 Excideuil Excideuil Aquitaine 24160",
    "addr:postcode":"24160;24160;24160",
    "addr:street":"B.P. 15",
    "iso:country":"FR",
    "sg:address":"B.P. 15, 24160 Excideuil C\u00e9dex^^Av. Andr\u00e9 Audy, 24160 Excideuil",
    "sg:city":"Excideuil",
    "sg:orig_category":"Non-Classified Establishments",
    "sg:phone":"+33 5 53 62 40 16",
    "sg:postcode":"24160",
    "sg:province":"Aquitaine",
    "wof:name":"Diana V\u00e9g\u00e9tal S.a.",
    "wof:placetype":"venue"
},
  "geometry": {"coordinates":[1.196755,45.299549],"type":"Point"}
}