{
  "type": "Feature",
  "properties": {
    "addr:full":"17, Rue Camille Lenoir, 51100 Reims Champagne",
    "addr:housenumber":"17",
    "addr:postcode":"51100",
    "addr:street":"Rue Camille Lenoir",
    "iso:country":"FR",
    "sg:address":"17, Rue Camille Lenoir, 51100 Reims",
    "sg:orig_category":"Non-Classified Establishments",
    "sg:phone":"+33 3 26 40 29 73",
    "sg:province":"Champagne",
    "wof:name":"Jpl Coulon S.a.",
    "wof:placetype":"venue"
},
  "geometry": {"coordinates":[4.039127,49.258732],"type":"Point"}
}