{
  "type": "Feature",
  "properties": {
    "addr:full":"2, Rue Denis Papin - ZAC Saint-Christophe II, 04000 Digne les Bains Auvergne",
    "addr:housenumber":"2",
    "addr:postcode":"04000",
    "addr:street":"Rue Denis Papin Zac Saint-Christophe Ii",
    "iso:country":"FR",
    "sg:address":"2, Rue Denis Papin - ZAC Saint-Christophe II, 04000 Digne les Bains",
    "sg:orig_category":"Non-Classified Establishments",
    "sg:phone":"+33 4 92 31 05 41",
    "sg:province":"Auvergne",
    "wof:name":"C\u00e9g\u00e9lec S.a.",
    "wof:placetype":"venue"
},
  "geometry": {"coordinates":[6.185154,44.076557],"type":"Point"}
}