{
  "type": "Feature",
  "properties": {
    "addr:full":"78, Rue Gambetta, 51100 Reims Champagne",
    "addr:housenumber":"78",
    "addr:postcode":"51100",
    "addr:street":"Rue Gambetta",
    "iso:country":"FR",
    "sg:address":"78, Rue Gambetta, 51100 Reims",
    "sg:orig_category":"Non-Classified Establishments",
    "sg:phone":"+33 3 26 82 91 21",
    "sg:province":"Champagne",
    "wof:name":"Paginove S.a.",
    "wof:placetype":"venue"
},
  "geometry": {"coordinates":[4.037905,49.247715],"type":"Point"}
}