{
  "type": "Feature",
  "properties": {
    "iso:country":"FR",
    "sg:address":"979 rue Debout 59310 Faumont",
    "sg:classifiers":[
        {
            "category":"Food & Beverages",
            "subcategory":"Fruits & Vegetables",
            "type":"Retail Goods"
        }
    ],
    "sg:phone":"+33 3 20 59 22 07",
    "sg:postcode":"59310",
    "sg:province":"Nord Pas-de-Calais",
    "wof:name":"Ets Lagache Sa",
    "wof:placetype":"venue"
},
  "geometry": {"coordinates":[3.122895,50.449986],"type":"Point"}
}