{
  "type": "Feature",
  "properties": {
    "addr:full":"3, Impasse de la Blanchisserie, 51100 Reims Champagne",
    "addr:housenumber":"3",
    "addr:postcode":"51100",
    "addr:street":"Impasse De La Blanchisserie",
    "iso:country":"FR",
    "sg:address":"3, Impasse de la Blanchisserie, 51100 Reims",
    "sg:orig_category":"Unclassifiable Establishments",
    "sg:phone":"+33 3 26 85 74 00",
    "sg:province":"Champagne",
    "wof:name":"Citel 2 C.p. S.a.",
    "wof:placetype":"venue"
},
  "geometry": {"coordinates":[4.034428,49.240978],"type":"Point"}
}