{
  "type": "Feature",
  "properties": {
    "addr:full":"33 rue de Gondevin 21110 LONGEAULT Longeault Bourgogne 21110",
    "addr:housenumber":"33",
    "addr:postcode":"21110;21110",
    "addr:street":"Rue De Gondevin",
    "iso:country":"FR",
    "sg:address":"33 rue de Gondevin 21110 LONGEAULT",
    "sg:city":"Longeault",
    "sg:classifiers":[
        {
            "category":"Banks & Credit Unions",
            "subcategory":"Investment Brokerage",
            "type":"Services"
        }
    ],
    "sg:phone":"+33 3 80 31 54 22",
    "sg:postcode":"21110",
    "sg:province":"Bourgogne",
    "sg:tags":[
        "support",
        "scaffolding"
    ],
    "wof:name":"Mts Manutention Technique De Stockage S.a.r.l.",
    "wof:placetype":"venue"
},
  "geometry": {"coordinates":[5.25206,47.220135],"type":"Point"}
}