{
  "type": "Feature",
  "properties": {
    "iso:country":"FR",
    "sg:address":"Rue Marcelin Berthelot - Immeuble Ant\u00e9lios - Les Milles",
    "sg:city":"Aix en Provence",
    "sg:orig_category":"Unclassifiable Establishments",
    "sg:phone":"+33 4 42 39 44 10",
    "sg:postcode":"13850",
    "sg:province":"Nord Pas-de-Calais",
    "wof:name":"Absis S.a.r.l.",
    "wof:placetype":"venue"
},
  "geometry": {"coordinates":[5.541299,43.434277],"type":"Point"}
}