{
  "type": "Feature",
  "properties": {
    "addr:full":"2, Rue Hilaire Colombel, 76600 Le Havre Haute Normandie",
    "addr:housenumber":"2",
    "addr:postcode":"76600",
    "addr:street":"Rue Hilaire Colombel",
    "iso:country":"FR",
    "sg:address":"2, Rue Hilaire Colombel, 76600 Le Havre",
    "sg:orig_category":"Unclassifiable Establishments",
    "sg:phone":"+33 2 35 24 67 67",
    "sg:province":"Haute Normandie",
    "wof:name":"Euroguard S.a.",
    "wof:placetype":"venue"
},
  "geometry": {"coordinates":[0.134523,49.495972],"type":"Point"}
}