{
  "type": "Feature",
  "properties": {
    "addr:full":"BP 147; Avignon cedex 1; France; 84008 Aquitaine",
    "addr:housenumber":"147",
    "addr:postcode":"84008",
    "addr:street":"Avignon Cedex",
    "iso:country":"FR",
    "sg:address":"BP 147; Avignon cedex 1; France; 84008",
    "sg:classifiers":[
        {
            "category":"Travel",
            "subcategory":"Travel Agent",
            "type":"Entertainment"
        }
    ],
    "sg:phone":"+33 3349080470",
    "sg:province":"Aquitaine",
    "wof:name":"Vaucluse - Provence - Avignon",
    "wof:placetype":"venue"
},
  "geometry": {"coordinates":[4.80597,43.948608],"type":"Point"}
}