{
  "type": "Feature",
  "properties": {
    "addr:full":"27, R l'Escadrille des Cigognes, 59640 Dunkerque Cigogn\u00e9 Centre 37310",
    "addr:housenumber":"27",
    "addr:postcode":"59640;37310",
    "addr:street":"R L'Escadrille Des Cigognes;Cigogne\u0301",
    "iso:country":"FR",
    "sg:address":"27, R l'Escadrille des Cigognes, 59640 Dunkerque",
    "sg:city":"Cigogn\u00e9",
    "sg:orig_category":"Unclassifiable Establishments",
    "sg:phone":"+33 3 28 60 05 23",
    "sg:postcode":"37310",
    "sg:province":"Centre",
    "wof:name":"Loonis S.a.r.l.",
    "wof:placetype":"venue"
},
  "geometry": {"coordinates":[2.354322,51.02277],"type":"Point"}
}