{
  "type": "Feature",
  "properties": {
    "iso:country":"FR",
    "sg:address":"555, Bd Mar\u00e9chal Joffre, 83100 Toulon",
    "sg:orig_category":"Unclassifiable Establishments",
    "sg:phone":"+33 4 94 36 53 72",
    "sg:province":"Outre-Mer",
    "wof:name":"Soci\u00e9t\u00e9 Entreprise Comptabilit\u00e9 Midivar S.a.",
    "wof:placetype":"venue"
},
  "geometry": {"coordinates":[5.95475,43.124359],"type":"Point"}
}