{
  "type": "Feature",
  "properties": {
    "addr:full":"2 Chem Du Pr\u00e9 Carr\u00e9 38241 Meylan Cedex Languedoc-Roussillon",
    "addr:housenumber":"2",
    "addr:postcode":"38241;cedex",
    "addr:street":"Chem Du Pre\u0301 Carre\u0301",
    "iso:country":"FR",
    "sg:address":"2 Chem Du Pr\u00e9 Carr\u00e9 38241 Meylan Cedex",
    "sg:classifiers":[
        {
            "category":"Professional",
            "subcategory":"Engineering",
            "type":"Services"
        }
    ],
    "sg:phone":"+33 4 76 90 11 54",
    "sg:province":"Languedoc-Roussillon",
    "sg:tags":[
        "machine",
        "-",
        "mechanical"
    ],
    "wof:name":"Alsthom Sa",
    "wof:placetype":"venue"
},
  "geometry": {"coordinates":[5.781992,45.207279],"type":"Point"}
}