{
  "type": "Feature",
  "properties": {
    "addr:full":"5 Rue Du Mar\u00e9chal Leclerc 49280 La Tessoualle Pays de Loire 49280",
    "addr:housenumber":"5",
    "addr:postcode":"49280;49280",
    "addr:street":"Rue Du Mare\u0301Chal Leclerc",
    "iso:country":"FR",
    "sg:address":"5 Rue Du Mar\u00e9chal Leclerc 49280 La Tessoualle",
    "sg:classifiers":[
        {
            "category":"Shopping",
            "subcategory":"Luggage & Leather Goods",
            "type":"Retail Goods"
        }
    ],
    "sg:phone":"+33 2 41 56 46 49",
    "sg:postcode":"49280",
    "sg:province":"Pays de Loire",
    "sg:tags":[
        "shoe"
    ],
    "wof:name":"Matipier Sarl",
    "wof:placetype":"venue"
},
  "geometry": {"coordinates":[-0.844635,47.005783],"type":"Point"}
}