{
  "type": "Feature",
  "properties": {
    "iso:country":"FR",
    "sg:address":"B.P. 109",
    "sg:city":"Poligny C\u00e9dex^^39800 Grozon",
    "sg:orig_category":"Non-Classified Establishments",
    "sg:phone":"+33 3 84 73 67 00",
    "sg:postcode":"39802",
    "sg:province":"Franche Comt\u00e9",
    "wof:name":"Placopl\u00e2tre S.a.",
    "wof:placetype":"venue"
},
  "geometry": {"coordinates":[5.708668,46.834393],"type":"Point"}
}