{
  "type": "Feature",
  "properties": {
    "addr:full":"Rue Hippolyte Foucault 72000 Le Mans Pays de Loire 72000",
    "addr:postcode":"72000;72000",
    "addr:street":"Rue Hippolyte Foucault",
    "iso:country":"FR",
    "sg:address":"Rue Hippolyte Foucault 72000 Le Mans",
    "sg:classifiers":[
        {
            "category":"Professional",
            "subcategory":"Engineering",
            "type":"Services"
        }
    ],
    "sg:phone":"+33 2 43 21 78 88",
    "sg:postcode":"72000",
    "sg:province":"Pays de Loire",
    "sg:tags":[
        "machine",
        "-",
        "mechanical"
    ],
    "wof:name":"Saunier Duval Eau Chaude Chauffage France (sdeccf)",
    "wof:placetype":"venue"
},
  "geometry": {"coordinates":[0.176093,48.027096],"type":"Point"}
}