{
  "type": "Feature",
  "properties": {
    "addr:full":"24 Rue Baron 75017 Paris Ile de France",
    "addr:housenumber":"24",
    "addr:postcode":"75017",
    "addr:street":"Rue Baron",
    "iso:country":"FR",
    "sg:address":"24 Rue Baron 75017 Paris",
    "sg:classifiers":[
        {
            "category":"Manufacturing",
            "subcategory":"Wood Products",
            "type":"Manufacturing & Wholesale Goods"
        }
    ],
    "sg:phone":"+33 1 53 06 22 50",
    "sg:province":"Ile de France",
    "sg:tags":[
        "professional",
        "furniture"
    ],
    "wof:name":"Atal Sa",
    "wof:placetype":"venue"
},
  "geometry": {"coordinates":[2.323278,48.895004],"type":"Point"}
}