{
  "type": "Feature",
  "properties": {
    "addr:full":"B.P. 16, 54670 Custines^^ZA Le Pr\u00e9 \u00e0 Varois, 54670 Custines Lorraine",
    "addr:postcode":"54670;54670",
    "addr:street":"B.P. 16;Le",
    "iso:country":"FR",
    "sg:address":"B.P. 16, 54670 Custines^^ZA Le Pr\u00e9 \u00e0 Varois, 54670 Custines",
    "sg:orig_category":"Non-Classified Establishments",
    "sg:phone":"+33 3 83 49 20 00",
    "sg:province":"Lorraine",
    "wof:name":"S.d. Services - Groupe Samsic S.a.",
    "wof:placetype":"venue"
},
  "geometry": {"coordinates":[6.142335,48.791302],"type":"Point"}
}