{
  "type": "Feature",
  "properties": {
    "addr:full":"B.P. 51, 74371 Metz Tessy C\u00e9dex^^Parc Nord, 74370 Metz Tessy Rhone-Alpes 74370",
    "addr:postcode":"74371;74370;74370",
    "addr:street":"B.P. 51;Rhone-Alpes",
    "iso:country":"FR",
    "sg:address":"B.P. 51, 74371 Metz Tessy C\u00e9dex^^Parc Nord, 74370 Metz Tessy",
    "sg:orig_category":"Non-Classified Establishments",
    "sg:phone":"+33 4 50 66 91 91",
    "sg:postcode":"74370",
    "sg:province":"Rhone-Alpes",
    "wof:name":"Robotic S.a.",
    "wof:placetype":"venue"
},
  "geometry": {"coordinates":[6.109395,45.934166],"type":"Point"}
}