{
  "type": "Feature",
  "properties": {
    "iso:country":"FR",
    "sg:address":"Rue des Charpentiers - ZI de Bel Air",
    "sg:city":"Rodez",
    "sg:orig_category":"Unclassifiable Establishments",
    "sg:phone":"+33 5 65 67 03 06",
    "sg:postcode":"12000",
    "sg:province":"Midi Pyr\u00e9n\u00e9es",
    "wof:name":"C.i.s.o. S.a.",
    "wof:placetype":"venue"
},
  "geometry": {"coordinates":[2.57289,44.349735],"type":"Point"}
}