{
  "type": "Feature",
  "properties": {
    "iso:country":"FR",
    "sg:address":"5 Av De L'Arm\u00e9e Leclerq 91600 Savigny Sur Orge",
    "sg:classifiers":[
        {
            "category":"Health Services",
            "subcategory":"Podiatrist",
            "type":"Services"
        }
    ],
    "sg:phone":"+33 1 69 05 92 03",
    "sg:postcode":"91600",
    "sg:province":"Ile de France",
    "sg:tags":[
        "equipment",
        "electrical",
        "-",
        "electronic",
        "instrument"
    ],
    "wof:name":"Geyre Electronique Sa",
    "wof:placetype":"venue"
},
  "geometry": {"coordinates":[2.348442,48.699642],"type":"Point"}
}