{
  "type": "Feature",
  "properties": {
    "iso:country":"FR",
    "sg:address":"150 Rte Neuville Ld La Gare 01250 Villereversure",
    "sg:classifiers":[
        {
            "category":"Manufacturing",
            "subcategory":"Rubber & Plastics",
            "type":"Manufacturing & Wholesale Goods"
        }
    ],
    "sg:phone":"+33 4 74 30 66 00",
    "sg:postcode":"01250",
    "sg:province":"Rhone-Alpes",
    "sg:tags":[
        "metallurgy",
        "finished",
        "-",
        "metalworking",
        "metallic"
    ],
    "wof:name":"M. Cleard Gilbert",
    "wof:placetype":"venue"
},
  "geometry": {"coordinates":[5.364134,46.19091],"type":"Point"}
}