{
  "type": "Feature",
  "properties": {
    "addr:full":"Avenue Robert Brun 83500 La Seyne Sur Mer Auvergne",
    "addr:postcode":"83500",
    "addr:street":"Avenue Robert Brun",
    "iso:country":"FR",
    "sg:address":"Avenue Robert Brun 83500 La Seyne Sur Mer",
    "sg:orig_category":"Food processing - machinery and equipment Mechanical Engineering - machines Professional goods Wood ",
    "sg:phone":"+33 4 94 06 00 17",
    "sg:province":"Auvergne",
    "wof:name":"Tout Technique Sa",
    "wof:placetype":"venue"
},
  "geometry": {"coordinates":[5.877,43.11771],"type":"Point"}
}