{
  "type": "Feature",
  "properties": {
    "addr:full":"B.P. 304, 91958 Courtaboeuf C\u00e9dex^^3, Av. du Canada, 91940 Les Ulis Ile de France",
    "addr:housenumber":"b.p. 304",
    "addr:postcode":"91958;91940",
    "addr:street":"Av. Du Canada",
    "iso:country":"FR",
    "sg:address":"B.P. 304, 91958 Courtaboeuf C\u00e9dex^^3, Av. du Canada, 91940 Les Ulis",
    "sg:orig_category":"Non-Classified Establishments",
    "sg:phone":"+33 1 69 29 57 00",
    "sg:province":"Ile de France",
    "wof:name":"Motorola S.a.",
    "wof:placetype":"venue"
},
  "geometry": {"coordinates":[2.169475,48.68161],"type":"Point"}
}