{
  "type": "Feature",
  "properties": {
    "iso:country":"FR",
    "sg:address":"B.P. 24, 10700 Arcis sur Aube^^30, Rue de Paris, 10700 Arcis sur Aube",
    "sg:orig_category":"Non-Classified Establishments",
    "sg:phone":"+33 3 25 37 81 10",
    "sg:postcode":"10700",
    "sg:province":"Champagne",
    "wof:name":"Defrance S.a.r.l.",
    "wof:placetype":"venue"
},
  "geometry": {"coordinates":[4.138695,48.536194],"type":"Point"}
}