{
  "type": "Feature",
  "properties": {
    "iso:country":"FR",
    "sg:address":"125/129, Rue Casimir P\u00e9rier, 95870 Bezons",
    "sg:orig_category":"Unclassifiable Establishments",
    "sg:phone":"+33 1 39 47 40 40",
    "sg:province":"Ile de France",
    "wof:name":"Agie S.a.r.l.",
    "wof:placetype":"venue"
},
  "geometry": {"coordinates":[2.204791,48.918095],"type":"Point"}
}