{
  "type": "Feature",
  "properties": {
    "addr:full":"Za Les Remblais 73220 Epierre Rhone-Alpes 73220",
    "addr:postcode":"73220;73220",
    "addr:street":"Za Les Remblais;Rhone-Alpes",
    "iso:country":"FR",
    "sg:address":"Za Les Remblais 73220 Epierre",
    "sg:classifiers":[
        {
            "category":"Transit Center",
            "subcategory":"Freight",
            "type":"Transportation"
        }
    ],
    "sg:phone":"+33 4 79 36 46 06",
    "sg:postcode":"73220",
    "sg:province":"Rhone-Alpes",
    "sg:tags":[
        "metallurgy",
        "pipe",
        "metalworking",
        "sheet"
    ],
    "wof:name":"Ste Electronique De Maurienne",
    "wof:placetype":"venue"
},
  "geometry": {"coordinates":[6.292945,45.457634],"type":"Point"}
}