{
  "type": "Feature",
  "properties": {
    "addr:full":"Quai Graou Sud 06530 ST CEZAIRE SUR SIAGNE Provence-Alpes-C\u00f4te d'Azur",
    "addr:postcode":"06530",
    "addr:street":"Quai Graou Sud;Siagne",
    "iso:country":"FR",
    "sg:address":"Quai Graou Sud 06530 ST CEZAIRE SUR SIAGNE",
    "sg:classifiers":[
        {
            "category":"Manufacturing",
            "subcategory":"Building Materials",
            "type":"Manufacturing & Wholesale Goods"
        }
    ],
    "sg:phone":"+33 4 93 60 86 80",
    "sg:province":"Provence-Alpes-C\u00f4te d'Azur",
    "sg:tags":[
        "raw",
        "perfume"
    ],
    "wof:name":"Pcma-flor S.a.",
    "wof:placetype":"venue"
},
  "geometry": {"coordinates":[6.814453,43.65263],"type":"Point"}
}