{
  "type": "Feature",
  "properties": {
    "iso:country":"FR",
    "sg:address":"22, Rue des Ingrains, 36000 Ch\u00e2teauroux",
    "sg:city":"Ch\u00e2teauroux",
    "sg:orig_category":"Unclassifiable Establishments",
    "sg:phone":"+33 2 54 53 15 15",
    "sg:postcode":"36000",
    "sg:province":"Centre",
    "wof:name":"Groupama",
    "wof:placetype":"venue"
},
  "geometry": {"coordinates":[1.713411,46.794811],"type":"Point"}
}