{
  "type": "Feature",
  "properties": {
    "iso:country":"FR",
    "sg:address":"22 Rue De La Commune De Paris 59760 Grande Synthe",
    "sg:classifiers":[
        {
            "category":"Professional",
            "type":"Services"
        }
    ],
    "sg:phone":"+33 3 28 21 21 00",
    "sg:province":"Nord Pas-de-Calais",
    "sg:tags":[
        "transport",
        "road"
    ],
    "wof:name":"Littoral Evasion Sarl",
    "wof:placetype":"venue"
},
  "geometry": {"coordinates":[2.30587,51.013142],"type":"Point"}
}