{
  "type": "Feature",
  "properties": {
    "iso:country":"FR",
    "sg:address":"17 Rue Du Moulin A Vent 60510 Bresles",
    "sg:classifiers":[
        {
            "category":"Manufacturing",
            "subcategory":"Paper Products",
            "type":"Manufacturing & Wholesale Goods"
        }
    ],
    "sg:phone":"+33 3 44 07 90 17",
    "sg:province":"Picardie",
    "sg:tags":[
        "packaging",
        "material",
        "-",
        "cardboard"
    ],
    "wof:name":"Sas Reims Emballages Papeterie De L'oise",
    "wof:placetype":"venue"
},
  "geometry": {"coordinates":[2.251661,49.41296],"type":"Point"}
}