{
  "type": "Feature",
  "properties": {
    "addr:full":"58, Bd D\u00e9odat de S\u00e9verac, 31300 Toulouse Midi Pyr\u00e9n\u00e9es",
    "addr:housenumber":"58",
    "addr:postcode":"31300",
    "addr:street":"Bd De\u0301Odat De Se\u0301Verac",
    "iso:country":"FR",
    "sg:address":"58, Bd D\u00e9odat de S\u00e9verac, 31300 Toulouse",
    "sg:orig_category":"Unclassifiable Establishments",
    "sg:phone":"+33 5 62 48 06 00",
    "sg:province":"Midi Pyr\u00e9n\u00e9es",
    "wof:name":"Synergie S.a.",
    "wof:placetype":"venue"
},
  "geometry": {"coordinates":[1.422233,43.589378],"type":"Point"}
}