{
  "type": "Feature",
  "properties": {
    "iso:country":"FR",
    "sg:address":"41 Rue Casimir Perier 95870 Bezons",
    "sg:classifiers":[
        {
            "category":"Manufacturing",
            "subcategory":"Paper Products",
            "type":"Manufacturing & Wholesale Goods"
        }
    ],
    "sg:phone":"+33 1 34 34 16 34",
    "sg:province":"Ile de France",
    "sg:tags":[
        "raw",
        "material",
        "-",
        "cardboard"
    ],
    "wof:name":"Arco Carton",
    "wof:placetype":"venue"
},
  "geometry": {"coordinates":[2.210912,48.921356],"type":"Point"}
}