{
  "type": "Feature",
  "properties": {
    "addr:full":"12 Rue Jules Marey 71150 Chagny Chagny Bourgogne 71150",
    "addr:housenumber":"12",
    "addr:postcode":"71150;71150",
    "addr:street":"Rue Jules Marey",
    "iso:country":"FR",
    "sg:address":"12 Rue Jules Marey 71150 Chagny",
    "sg:city":"Chagny",
    "sg:classifiers":[
        {
            "category":"Farming",
            "subcategory":"Farm",
            "type":"Manufacturing & Wholesale Goods"
        }
    ],
    "sg:phone":"+33 3 85 87 18 28",
    "sg:postcode":"71150",
    "sg:province":"Bourgogne",
    "sg:tags":[
        "horticulture",
        "agriculture",
        "livestock"
    ],
    "wof:name":"Cedest Engrais",
    "wof:placetype":"venue"
},
  "geometry": {"coordinates":[4.752162,46.905163],"type":"Point"}
}