{
  "type": "Feature",
  "properties": {
    "iso:country":"FR",
    "sg:address":"121 Rn 102 07200 Lab\u00e9gude",
    "sg:classifiers":[
        {
            "category":"Wholesale",
            "subcategory":"Machinery & Supplies",
            "type":"Manufacturing & Wholesale Goods"
        }
    ],
    "sg:phone":"+33 4 75 37 40 05",
    "sg:postcode":"07200",
    "sg:province":"Rhone-Alpes",
    "sg:tags":[
        "handling",
        "material",
        "-",
        "machine",
        "equipment",
        "engineering",
        "mechanical"
    ],
    "wof:name":"Etablissements Laganier Sarl",
    "wof:placetype":"venue"
},
  "geometry": {"coordinates":[4.39409,44.613361],"type":"Point"}
}