{
  "type": "Feature",
  "properties": {
    "iso:country":"FR",
    "sg:address":"23 Rue De La Lun\u00e9ville 02100 St Quentin",
    "sg:classifiers":[
        {
            "category":"Manufacturing",
            "subcategory":"Printing",
            "type":"Manufacturing & Wholesale Goods"
        }
    ],
    "sg:phone":"+33 3 23 62 95 95",
    "sg:province":"Picardie",
    "sg:tags":[
        "publishing"
    ],
    "wof:name":"Imprimerie Maulde Renou Aisne Sa",
    "wof:placetype":"venue"
},
  "geometry": {"coordinates":[3.297625,49.85392],"type":"Point"}
}