{
  "type": "Feature",
  "properties": {
    "iso:country":"FR",
    "sg:address":"6, Rue Vincent Van Gogh, 93364 Neuilly Plaisance C\u00e9dex",
    "sg:orig_category":"Non-Classified Establishments",
    "sg:phone":"+33 1 49 44 22 22",
    "sg:province":"Aquitaine",
    "wof:name":"Genrad Europ Limited",
    "wof:placetype":"venue"
},
  "geometry": {"coordinates":[2.516313,48.852322],"type":"Point"}
}