{
  "type": "Feature",
  "properties": {
    "iso:country":"FR",
    "sg:address":"27, Villa Wagram Saint Honor\u00e9, 75008 Paris",
    "sg:orig_category":"Non-Classified Establishments",
    "sg:phone":"+33 1 53 81 96 00",
    "sg:province":"Ile de France",
    "wof:name":"Majors Consultants Sa",
    "wof:placetype":"venue"
},
  "geometry": {"coordinates":[2.298388,48.876659],"type":"Point"}
}