{
  "type": "Feature",
  "properties": {
    "addr:full":"B.P. 62, 57270 Uckange^^Rte de Vitry, 57270 Uckange Lorraine",
    "addr:postcode":"57270;57270",
    "addr:street":"B.P. 62;Vitry",
    "iso:country":"FR",
    "sg:address":"B.P. 62, 57270 Uckange^^Rte de Vitry, 57270 Uckange",
    "sg:orig_category":"Non-Classified Establishments",
    "sg:phone":"+33 3 82 57 41 00",
    "sg:province":"Lorraine",
    "wof:name":"Heckett Multiserv France S.a.",
    "wof:placetype":"venue"
},
  "geometry": {"coordinates":[6.158114,49.300732],"type":"Point"}
}