{
  "type": "Feature",
  "properties": {
    "addr:full":"183/187, Av. Henri Barbusse, 93700 Drancy Ile de France",
    "addr:housenumber":"183 / 187",
    "addr:postcode":"93700;ile",
    "addr:street":"Av. Henri Barbusse",
    "iso:country":"FR",
    "sg:address":"183/187, Av. Henri Barbusse, 93700 Drancy",
    "sg:orig_category":"Unclassifiable Establishments",
    "sg:phone":"+33 1 48 32 01 90",
    "sg:province":"Ile de France",
    "wof:name":"Drancy Mat\u00e9riaux S.a.r.l.",
    "wof:placetype":"venue"
},
  "geometry": {"coordinates":[2.453848,48.921219],"type":"Point"}
}