{
  "type": "Feature",
  "properties": {
    "addr:full":"6, Rue Jean Mermoz - Z.I. des Bruy\u00e8res, 71000 M\u00e2con Sanc\u00e9 Bourgogne 71000",
    "addr:housenumber":"6",
    "addr:postcode":"71000;71000",
    "addr:street":"Rue Jean Mermoz;Des Bruye\u0300Res",
    "iso:country":"FR",
    "sg:address":"6, Rue Jean Mermoz - Z.I. des Bruy\u00e8res, 71000 M\u00e2con",
    "sg:city":"Sanc\u00e9",
    "sg:orig_category":"Unclassifiable Establishments",
    "sg:phone":"+33 3 85 29 26 36",
    "sg:postcode":"71000",
    "sg:province":"Bourgogne",
    "wof:name":"Macon Balance",
    "wof:placetype":"venue"
},
  "geometry": {"coordinates":[4.833055,46.303043],"type":"Point"}
}