{
  "type": "Feature",
  "properties": {
    "iso:country":"FR",
    "sg:address":"8, Rue de la Vologne, 88600 Laveline devant Bruy\u00e8res",
    "sg:orig_category":"Unclassifiable Establishments",
    "sg:phone":"+33 3 29 58 51 33",
    "sg:province":"Lorraine",
    "wof:name":"Laveline E.u.r.l.",
    "wof:placetype":"venue"
},
  "geometry": {"coordinates":[6.757096,48.179035],"type":"Point"}
}