{
  "type": "Feature",
  "properties": {
    "addr:full":"B.P. 72, 57220 Boulay Moselle^^64, Rue du G\u00e9n\u00e9ral Newinger, 57220 Boulay Moselle Lorraine",
    "addr:postcode":"57220;57220",
    "addr:street":"B.P. 72;Rue Du Ge\u0301Ne\u0301Ral Newinger",
    "iso:country":"FR",
    "sg:address":"B.P. 72, 57220 Boulay Moselle^^64, Rue du G\u00e9n\u00e9ral Newinger, 57220 Boulay Moselle",
    "sg:orig_category":"Non-Classified Establishments",
    "sg:phone":"+33 3 87 79 11 00",
    "sg:province":"Lorraine",
    "wof:name":"Sotralec S.a.r.l. - Soci\u00e9t\u00e9 De Travaux D'electrification",
    "wof:placetype":"venue"
},
  "geometry": {"coordinates":[6.4927,49.183735],"type":"Point"}
}