{
  "type": "Feature",
  "properties": {
    "iso:country":"FR",
    "sg:address":"492 Chemin Des Incapis BP 89 83300 Draguignan Cedex",
    "sg:classifiers":[
        {
            "category":"Health Services",
            "subcategory":"Medical Lab",
            "type":"Services"
        }
    ],
    "sg:phone":"+33 4 94 68 52 96",
    "sg:province":"Franche Comt\u00e9",
    "sg:tags":[
        "chemical",
        "pharmaceutical",
        "pharmacy"
    ],
    "wof:name":"Sieco Sarl",
    "wof:placetype":"venue"
},
  "geometry": {"coordinates":[6.46464,43.52256],"type":"Point"}
}