{
  "type": "Feature",
  "properties": {
    "addr:full":"59 Av Du G\u00e9n\u00e9ral De Gaulle 93170 Bagnolet Ile de France 93170",
    "addr:postcode":"93170;ile;93170",
    "addr:street":"59 Av Du Ge\u0301Ne\u0301Ral De Gaulle;France",
    "iso:country":"FR",
    "sg:address":"59 Av Du G\u00e9n\u00e9ral De Gaulle 93170 Bagnolet",
    "sg:orig_category":"Miscellaneous Products",
    "sg:phone":"+33 1 43 60 33 00",
    "sg:postcode":"93170",
    "sg:province":"Ile de France",
    "wof:name":"Bronze Eurofrance Diffusion Sa",
    "wof:placetype":"venue"
},
  "geometry": {"coordinates":[2.416434,48.862595],"type":"Point"}
}