{
  "type": "Feature",
  "properties": {
    "addr:full":"55, Rte de Fontaine les Clercs, 02680 Dallon Picardie",
    "addr:housenumber":"55",
    "addr:postcode":"02680",
    "addr:street":"Rte De Fontaine Les Clercs",
    "iso:country":"FR",
    "sg:address":"55, Rte de Fontaine les Clercs, 02680 Dallon",
    "sg:orig_category":"Non-Classified Establishments",
    "sg:phone":"+33 3 23 67 39 05",
    "sg:province":"Picardie",
    "wof:name":"J.c. Legrand Chauffage Service S.a.",
    "wof:placetype":"venue"
},
  "geometry": {"coordinates":[3.235643,49.814705],"type":"Point"}
}