{
  "type": "Feature",
  "properties": {
    "addr:full":"B.P. 149, 57504 Saint Avold C\u00e9dex^^76b, Rue du G\u00e9n\u00e9ral Altmayerr, 57500 Saint Avold Lorraine",
    "addr:housenumber":"b.p. 149",
    "addr:postcode":"57504;57500",
    "addr:street":"Avold;Rue Du Ge\u0301Ne\u0301Ral Altmayerr;Avold",
    "iso:country":"FR",
    "sg:address":"B.P. 149, 57504 Saint Avold C\u00e9dex^^76b, Rue du G\u00e9n\u00e9ral Altmayerr, 57500 Saint Avold",
    "sg:orig_category":"Non-Classified Establishments",
    "sg:phone":"+33 3 87 91 19 13",
    "sg:province":"Lorraine",
    "wof:name":"Guermont Weber S.a.",
    "wof:placetype":"venue"
},
  "geometry": {"coordinates":[6.705505,49.104275],"type":"Point"}
}