{
  "type": "Feature",
  "properties": {
    "addr:full":"Zone Industrielle Pontailler sur Sa\u00f4ne Bourgogne 21270",
    "addr:postcode":"21270",
    "addr:street":"Zone Industrielle",
    "iso:country":"FR",
    "sg:address":"Zone Industrielle",
    "sg:city":"Pontailler sur Sa\u00f4ne",
    "sg:orig_category":"Non-Classified Establishments",
    "sg:phone":"+33 3 80 36 13 63",
    "sg:postcode":"21270",
    "sg:province":"Bourgogne",
    "wof:name":"Laurent S.a.",
    "wof:placetype":"venue"
},
  "geometry": {"coordinates":[5.41543,47.304733],"type":"Point"}
}