{
  "type": "Feature",
  "properties": {
    "addr:full":"45 chauss\u00e9e Watt 59200 Tourcoing Nord Pas-de-Calais",
    "addr:housenumber":"45",
    "addr:postcode":"59200",
    "addr:street":"Chausse\u0301E Watt",
    "iso:country":"FR",
    "sg:address":"45 chauss\u00e9e Watt 59200 Tourcoing",
    "sg:classifiers":[
        {
            "category":"Utilities",
            "subcategory":"Natural Gas",
            "type":"Services"
        }
    ],
    "sg:phone":"+33 3 26 84 87 50",
    "sg:province":"Nord Pas-de-Calais",
    "sg:tags":[
        "building",
        "electricity",
        "oil"
    ],
    "wof:name":"Mondial Installations Sa",
    "wof:placetype":"venue"
},
  "geometry": {"coordinates":[3.135738,50.727238],"type":"Point"}
}