{
  "type": "Feature",
  "properties": {
    "addr:full":"61, Chemin de la Muette - Quartier Croix de Fer , 07100 Annonay Rhone-Alpes 07100",
    "addr:housenumber":"61",
    "addr:postcode":"07100;07100",
    "addr:street":"Chemin De La Muette",
    "iso:country":"FR",
    "sg:address":"61, Chemin de la Muette - Quartier Croix de Fer , 07100 Annonay",
    "sg:orig_category":"Non-Classified Establishments",
    "sg:phone":"+33 4 75 33 21 22",
    "sg:postcode":"07100",
    "sg:province":"Rhone-Alpes",
    "wof:name":"Balandreau Fr\u00e8res S.a.r.l.",
    "wof:placetype":"venue"
},
  "geometry": {"coordinates":[4.662016,45.247375],"type":"Point"}
}