{
  "type": "Feature",
  "properties": {
    "addr:full":"Poissons 52230 POISSONS Champagne",
    "addr:postcode":"52230",
    "addr:street":"Poissons",
    "iso:country":"FR",
    "sg:address":"Poissons 52230 POISSONS",
    "sg:classifiers":[
        {
            "category":"Military Area",
            "subcategory":"Army Base",
            "type":"Public Place"
        }
    ],
    "sg:phone":"+33 3 25 94 06 49",
    "sg:province":"Champagne",
    "sg:tags":[
        "frame",
        "sieve"
    ],
    "wof:name":"Millot Et Collot Sa",
    "wof:placetype":"venue"
},
  "geometry": {"coordinates":[5.21827,48.424309],"type":"Point"}
}