{
  "type": "Feature",
  "properties": {
    "addr:full":"15 R Alfred Kastler Parc De La Vatine 76130 Mont St Aignan Haute Normandie 76130",
    "addr:housenumber":"15",
    "addr:postcode":"76130;76130",
    "addr:street":"R Alfred Kastler Parc De La Vatine;Mont St;Normandie",
    "iso:country":"FR",
    "sg:address":"15 R Alfred Kastler Parc De La Vatine 76130 Mont St Aignan",
    "sg:classifiers":[
        {
            "category":"Professional",
            "subcategory":"Engineering",
            "type":"Services"
        }
    ],
    "sg:phone":"+33 2 35 12 25 10",
    "sg:postcode":"76130",
    "sg:province":"Haute Normandie",
    "sg:tags":[
        "machine",
        "-",
        "mechanical"
    ],
    "wof:name":"Rockwell Automation Sa",
    "wof:placetype":"venue"
},
  "geometry": {"coordinates":[1.096618,49.474545],"type":"Point"}
}