{
  "type": "Feature",
  "properties": {
    "addr:full":"39 rue Esquirol 75013 Paris Ile de France 75013",
    "addr:housenumber":"39",
    "addr:postcode":"75013;75013",
    "addr:street":"Rue Esquirol",
    "iso:country":"FR",
    "sg:address":"39 rue Esquirol 75013 Paris",
    "sg:classifiers":[
        {
            "category":"Wholesale",
            "subcategory":"Office Equipment",
            "type":"Manufacturing & Wholesale Goods"
        }
    ],
    "sg:phone":"+33 1 53 61 17 98",
    "sg:postcode":"75013",
    "sg:province":"Ile de France",
    "sg:tags":[
        "agency",
        "internet"
    ],
    "wof:name":"H\u00e9cate & Design S.a.r.l.",
    "wof:placetype":"venue"
},
  "geometry": {"coordinates":[2.359813,48.835545],"type":"Point"}
}