{
  "type": "Feature",
  "properties": {
    "iso:country":"FR",
    "sg:address":"Rue Du Champ Boby BP 153 Pessat Villeneuve 63200 Riom",
    "sg:city":"Riom",
    "sg:classifiers":[
        {
            "category":"Manufacturing",
            "subcategory":"Rubber & Plastics",
            "type":"Manufacturing & Wholesale Goods"
        }
    ],
    "sg:phone":"+33 4 73 63 03 03",
    "sg:postcode":"63200",
    "sg:province":"Auvergne",
    "sg:tags":[
        "packaging",
        "material",
        "-"
    ],
    "wof:name":"Plastyrobel",
    "wof:placetype":"venue"
},
  "geometry": {"coordinates":[3.052114,45.84782],"type":"Point"}
}