{
  "type": "Feature",
  "properties": {
    "addr:full":"Rue Gutemberg - ZI les Vignes Bobigny Ile de France 93000",
    "addr:postcode":"93000",
    "addr:street":"Rue Gutemberg Zi Les Vignes;Ile De France",
    "iso:country":"FR",
    "sg:address":"Rue Gutemberg - ZI les Vignes",
    "sg:city":"Bobigny",
    "sg:orig_category":"Non-Classified Establishments",
    "sg:phone":"+33 1 48 44 06 50",
    "sg:postcode":"93000",
    "sg:province":"Ile de France",
    "wof:name":"Laboratoires Pourquery S.a.",
    "wof:placetype":"venue"
},
  "geometry": {"coordinates":[2.445785,48.90477],"type":"Point"}
}