{
  "type": "Feature",
  "properties": {
    "iso:country":"FR",
    "sg:address":"ZI Zinsel",
    "sg:city":"Schweighouse sur Moder",
    "sg:orig_category":"Unclassifiable Establishments",
    "sg:phone":"+33 3 88 07 26 00",
    "sg:postcode":"67590",
    "sg:province":"Alsace",
    "wof:name":"Sulzer Pompes Process S.a.",
    "wof:placetype":"venue"
},
  "geometry": {"coordinates":[7.73517,48.82151],"type":"Point"}
}