{
  "type": "Feature",
  "properties": {
    "addr:full":"4 R De La Casse Aux Chevaux 17700 Puyravault Poitou-Charentes 17700",
    "addr:housenumber":"4",
    "addr:postcode":"17700;17700",
    "addr:street":"R De La Casse Aux Chevaux",
    "iso:country":"FR",
    "sg:address":"4 R De La Casse Aux Chevaux 17700 Puyravault",
    "sg:orig_category":"Animals and breeding Food and Related Products Mechanical Engineering - machines",
    "sg:phone":"+33 5 46 68 93 79",
    "sg:postcode":"17700",
    "sg:province":"Poitou-Charentes",
    "wof:name":"Mme Ravaud Renaud",
    "wof:placetype":"venue"
},
  "geometry": {"coordinates":[-0.813679,46.132969],"type":"Point"}
}