{
  "type": "Feature",
  "properties": {
    "iso:country":"FR",
    "sg:address":"27, Bd Louise Michel, 92230 Gennevilliers",
    "sg:orig_category":"Unclassifiable Establishments",
    "sg:phone":"+33 1 41 11 45 22",
    "sg:province":"Ile de France",
    "wof:name":"Polypore Europe S.a.",
    "wof:placetype":"venue"
},
  "geometry": {"coordinates":[2.319756,48.922169],"type":"Point"}
}