{
  "type": "Feature",
  "properties": {
    "iso:country":"FR",
    "sg:address":"22 rue du Ch\u00e2teau des Rentiers 75013 Paris",
    "sg:classifiers":[
        {
            "category":"Shopping",
            "subcategory":"Books",
            "type":"Retail Goods"
        }
    ],
    "sg:phone":"+33 1 45 83 50 54",
    "sg:postcode":"75013",
    "sg:province":"Ile de France",
    "wof:name":"Ste Francaise D' Editions Medicales Sa",
    "wof:placetype":"venue"
},
  "geometry": {"coordinates":[2.370629,48.824051],"type":"Point"}
}