{
  "type": "Feature",
  "properties": {
    "addr:full":"37, Bd Jeanne d'Arc, 93100 Montreuil Ile de France",
    "addr:housenumber":"37",
    "addr:postcode":"93100",
    "addr:street":"Bd Jeanne D'Arc",
    "iso:country":"FR",
    "sg:address":"37, Bd Jeanne d'Arc, 93100 Montreuil",
    "sg:orig_category":"Non-Classified Establishments",
    "sg:phone":"+33 1 48 18 14 00",
    "sg:province":"Ile de France",
    "wof:name":"S.o.s. Cintres S.a.",
    "wof:placetype":"venue"
},
  "geometry": {"coordinates":[2.445025,48.853477],"type":"Point"}
}