{
  "type": "Feature",
  "properties": {
    "addr:full":"1 Rue Des Vergers 69760 Limonest Rhone-Alpes 69760",
    "addr:housenumber":"1",
    "addr:postcode":"69760;69760",
    "addr:street":"Rue Des Vergers",
    "iso:country":"FR",
    "sg:address":"1 Rue Des Vergers 69760 Limonest",
    "sg:classifiers":[
        {
            "category":"Wholesale",
            "subcategory":"Medical Equipment & Supplies",
            "type":"Manufacturing & Wholesale Goods"
        }
    ],
    "sg:phone":"+33 4 72 52 02 52",
    "sg:postcode":"69760",
    "sg:province":"Rhone-Alpes",
    "sg:tags":[
        "instrument",
        "health",
        "-",
        "precision"
    ],
    "wof:name":"Laerdal Medical France Sa",
    "wof:placetype":"venue"
},
  "geometry": {"coordinates":[4.77387,45.807426],"type":"Point"}
}