{
  "type": "Feature",
  "properties": {
    "iso:country":"FR",
    "sg:address":"B.P. 29",
    "sg:city":"Roubaix C\u00e9dex 1",
    "sg:orig_category":"Non-Classified Establishments",
    "sg:phone":"+33 3 20 69 11 70",
    "sg:postcode":"59051",
    "sg:province":"Nord Pas-de-Calais",
    "wof:name":"Assurances Ren\u00e9 Masurel S.a.r.l.",
    "wof:placetype":"venue"
},
  "geometry": {"coordinates":[3.17924,50.694778],"type":"Point"}
}