{
  "type": "Feature",
  "properties": {
    "addr:full":"16, Bd de la Lib\u00e9ration, 05000 Gap Provence-Alpes-C\u00f4te d'Azur",
    "addr:housenumber":"16",
    "addr:postcode":"05000",
    "addr:street":"Bd De La Libe\u0301Ration",
    "iso:country":"FR",
    "sg:address":"16, Bd de la Lib\u00e9ration, 05000 Gap",
    "sg:orig_category":"Unclassifiable Establishments",
    "sg:phone":"+33 4 92 53 81 14",
    "sg:province":"Provence-Alpes-C\u00f4te d'Azur",
    "wof:name":"F.d.g. Sud-est S.a. - France Distribution Gestion",
    "wof:placetype":"venue"
},
  "geometry": {"coordinates":[6.078136,44.560848],"type":"Point"}
}