{
  "type": "Feature",
  "properties": {
    "addr:full":"Clos Drieux 50600 St Hilaire Du Harcou\u00ebt Ch\u00e8vreville Basse Normandie 50600",
    "addr:postcode":"50600;50600",
    "addr:street":"Clos;Basse",
    "iso:country":"FR",
    "sg:address":"Clos Drieux 50600 St Hilaire Du Harcou\u00ebt",
    "sg:city":"Ch\u00e8vreville",
    "sg:classifiers":[
        {
            "category":"Farming",
            "subcategory":"Farm",
            "type":"Manufacturing & Wholesale Goods"
        }
    ],
    "sg:phone":"+33 2 33 49 10 90",
    "sg:postcode":"50600",
    "sg:province":"Basse Normandie",
    "sg:tags":[
        "horticulture",
        "agriculture",
        "livestock"
    ],
    "wof:name":"Earl Du Clos Normand",
    "wof:placetype":"venue"
},
  "geometry": {"coordinates":[-1.091154,48.539909],"type":"Point"}
}