{
  "type": "Feature",
  "properties": {
    "iso:country":"FR",
    "sg:address":"B.P. 17, 64260 Arudy C\u00e9dex^^ZI le Touya, 64260 Arudy",
    "sg:city":"Arudy",
    "sg:orig_category":"Non-Classified Establishments",
    "sg:phone":"+33 5 59 05 60 34",
    "sg:postcode":"64260",
    "sg:province":"Aquitaine",
    "wof:name":"S.n.h. S.a.r.l. - Soci\u00e9t\u00e9 Nouvelle Hydrom\u00e9tal",
    "wof:placetype":"venue"
},
  "geometry": {"coordinates":[-0.412953,43.024239],"type":"Point"}
}