{
  "type": "Feature",
  "properties": {
    "addr:full":"B.P. 7, 26120 Chabeuil C\u00e9dex^^ZA Les Gouvernaux Sud, 26120 Chabeuil Rhone-Alpes 26120",
    "addr:housenumber":"7",
    "addr:postcode":"26120;26120;26120",
    "addr:street":"B.P.",
    "iso:country":"FR",
    "sg:address":"B.P. 7, 26120 Chabeuil C\u00e9dex^^ZA Les Gouvernaux Sud, 26120 Chabeuil",
    "sg:orig_category":"Non-Classified Establishments",
    "sg:phone":"+33 4 75 59 42 40",
    "sg:postcode":"26120",
    "sg:province":"Rhone-Alpes",
    "wof:name":"Epiphar S.a.r.l.",
    "wof:placetype":"venue"
},
  "geometry": {"coordinates":[4.980202,44.804939],"type":"Point"}
}