{
  "type": "Feature",
  "properties": {
    "addr:full":"11, Rue Verte Voie, 08090 Saint Laurent Aiglemont Champagne 08090",
    "addr:housenumber":"11",
    "addr:postcode":"08090;08090",
    "addr:street":"Rue Verte Voie;Champagne",
    "iso:country":"FR",
    "sg:address":"11, Rue Verte Voie, 08090 Saint Laurent",
    "sg:city":"Aiglemont",
    "sg:orig_category":"Non-Classified Establishments",
    "sg:phone":"+33 3 24 58 18 60",
    "sg:postcode":"08090",
    "sg:province":"Champagne",
    "wof:name":"Inter Print S.a.r.l.",
    "wof:placetype":"venue"
},
  "geometry": {"coordinates":[4.772923,49.765106],"type":"Point"}
}