{
  "type": "Feature",
  "properties": {
    "iso:country":"FR",
    "sg:address":"179, All\u00e9e de Brantes, 84700 Sorgues",
    "sg:orig_category":"Unclassifiable Establishments",
    "sg:phone":"+33 4 90 39 33 33",
    "sg:province":"Provence-Alpes-C\u00f4te d'Azur",
    "wof:name":"Armasud S.a.s.",
    "wof:placetype":"venue"
},
  "geometry": {"coordinates":[4.871935,43.999039],"type":"Point"}
}