{
  "type": "Feature",
  "properties": {
    "iso:country":"FR",
    "sg:address":"226, Av. Jean Mermoz, 63000 Clermont Ferrand",
    "sg:city":"Clermont-Ferrand",
    "sg:orig_category":"Unclassifiable Establishments",
    "sg:phone":"+33 4 73 91 08 54",
    "sg:postcode":"63000",
    "sg:province":"Auvergne",
    "wof:name":"Nouvelle Fourey Galland S.a.",
    "wof:placetype":"venue"
},
  "geometry": {"coordinates":[3.08183,45.777618],"type":"Point"}
}