{
  "type": "Feature",
  "properties": {
    "iso:country":"FR",
    "sg:address":"1, Rue Carnot, 51530 Pierry",
    "sg:orig_category":"Unclassifiable Establishments",
    "sg:phone":"+33 3 26 54 03 23",
    "sg:province":"Languedoc-Roussillon",
    "wof:name":"Champagne Vincent D'astr\u00e9e S.a.",
    "wof:placetype":"venue"
},
  "geometry": {"coordinates":[3.938879,49.019951],"type":"Point"}
}