{
  "type": "Feature",
  "properties": {
    "addr:full":"B.P. 215, 82032 Montauban C\u00e9dex^^1, Rue Voltaire, 82000 Montauban Midi Pyr\u00e9n\u00e9es 82000",
    "addr:housenumber":"b.p. 215",
    "addr:postcode":"82032;82000;82000",
    "addr:street":"Rue Voltaire",
    "iso:country":"FR",
    "sg:address":"B.P. 215, 82032 Montauban C\u00e9dex^^1, Rue Voltaire, 82000 Montauban",
    "sg:orig_category":"Non-Classified Establishments",
    "sg:phone":"+33 5 63 21 32 00",
    "sg:postcode":"82000",
    "sg:province":"Midi Pyr\u00e9n\u00e9es",
    "wof:name":"Doumenge S.a.",
    "wof:placetype":"venue"
},
  "geometry": {"coordinates":[1.352205,44.016762],"type":"Point"}
}