{
  "type": "Feature",
  "properties": {
    "addr:full":"Rte de Pamiers Mirepoix Midi Pyr\u00e9n\u00e9es 09500",
    "addr:postcode":"09500",
    "addr:street":"Rte De Pamiers",
    "iso:country":"FR",
    "sg:address":"Rte de Pamiers",
    "sg:city":"Mirepoix",
    "sg:orig_category":"Non-Classified Establishments",
    "sg:phone":"+33 5 61 68 29 99",
    "sg:postcode":"09500",
    "sg:province":"Midi Pyr\u00e9n\u00e9es",
    "wof:name":"S.c.a.p. S.a.r.l.",
    "wof:placetype":"venue"
},
  "geometry": {"coordinates":[1.862676,43.088272],"type":"Point"}
}