{
  "type": "Feature",
  "properties": {
    "addr:full":". 63480 BERTIGNAT Bertignat Auvergne 63480",
    "addr:postcode":"63480;63480",
    "addr:street":"Bertignat",
    "iso:country":"FR",
    "sg:address":". 63480 BERTIGNAT",
    "sg:city":"Bertignat",
    "sg:orig_category":"Braided Glass-Fibre Sheaths",
    "sg:phone":"+33 4 73 82 12 93",
    "sg:postcode":"63480",
    "sg:province":"Auvergne",
    "wof:name":"Ets Favier-tresses & Plastique Livradois Sarl",
    "wof:placetype":"venue"
},
  "geometry": {"coordinates":[3.682702,45.618797],"type":"Point"}
}