{
  "type": "Feature",
  "properties": {
    "addr:full":"28, Bd Jacques Cartier, 56100 Lorient Lorient Bretagne 56100",
    "addr:housenumber":"28",
    "addr:postcode":"56100;56100",
    "addr:street":"Bd Jacques Cartier",
    "iso:country":"FR",
    "sg:address":"28, Bd Jacques Cartier, 56100 Lorient",
    "sg:city":"Lorient",
    "sg:orig_category":"Unclassifiable Establishments",
    "sg:phone":"+33 2 97 37 82 10",
    "sg:postcode":"56100",
    "sg:province":"Bretagne",
    "wof:name":"Omnium Maritime Armoricain S.a.s.",
    "wof:placetype":"venue"
},
  "geometry": {"coordinates":[-3.356422,47.736668],"type":"Point"}
}