{
  "type": "Feature",
  "properties": {
    "iso:country":"FR",
    "sg:address":"1, Rue du Puits, 25400 Audincourt",
    "sg:orig_category":"Unclassifiable Establishments",
    "sg:phone":"+33 3 81 34 54 57",
    "sg:province":"Franche Comt\u00e9",
    "wof:name":"Thourot Jacques S.a.",
    "wof:placetype":"venue"
},
  "geometry": {"coordinates":[6.838728,47.481384],"type":"Point"}
}