{
  "type": "Feature",
  "properties": {
    "addr:full":"RN 88 - ZA le Peyreret Calmont Midi Pyr\u00e9n\u00e9es 12450",
    "addr:postcode":"12450",
    "addr:street":"Rn 88 Za Le Peyreret",
    "iso:country":"FR",
    "sg:address":"RN 88 - ZA le Peyreret",
    "sg:city":"Calmont",
    "sg:orig_category":"Non-Classified Establishments",
    "sg:phone":"+33 5 65 69 78 11",
    "sg:postcode":"12450",
    "sg:province":"Midi Pyr\u00e9n\u00e9es",
    "wof:name":"Occamat S.a.",
    "wof:placetype":"venue"
},
  "geometry": {"coordinates":[2.544625,44.245583],"type":"Point"}
}