{
  "type": "Feature",
  "properties": {
    "addr:full":"B.P. 452, 93618 Aulnay sous Bois C\u00e9dex^^B\u00e2t. 5, 93600 Aulnay sous Bois Ile de France",
    "addr:housenumber":"b.p. 452;5",
    "addr:postcode":"93618;93600",
    "addr:street":"Ce\u0301Dex^^Ba\u0302T",
    "iso:country":"FR",
    "sg:address":"B.P. 452, 93618 Aulnay sous Bois C\u00e9dex^^B\u00e2t. 5, 93600 Aulnay sous Bois",
    "sg:orig_category":"Non-Classified Establishments",
    "sg:phone":"+33 1 48 14 99 00",
    "sg:province":"Ile de France",
    "wof:name":"Transports Vaquier S.a.",
    "wof:placetype":"venue"
},
  "geometry": {"coordinates":[2.49124,48.927509],"type":"Point"}
}