{
  "type": "Feature",
  "properties": {
    "iso:country":"FR",
    "sg:address":"93, Rue Jean Jaur\u00e8s, 92800 Puteaux",
    "sg:orig_category":"Unclassifiable Establishments",
    "sg:phone":"+33 1 47 78 11 09",
    "sg:province":"Ile de France",
    "wof:name":"Pertinence Communication Cr\u00e9ation S.a.r.l.",
    "wof:placetype":"venue"
},
  "geometry": {"coordinates":[2.240453,48.882603],"type":"Point"}
}