{
  "type": "Feature",
  "properties": {
    "iso:country":"FR",
    "sg:address":"47 Avenue Gambetta 83500 La Seyne Sur Mer",
    "sg:classifiers":[
        {
            "category":"Professional",
            "type":"Services"
        }
    ],
    "sg:phone":"+33 4 94 94 83 15",
    "sg:province":"Provence-Alpes-C\u00f4te d'Azur",
    "sg:tags":[
        "transport",
        "road"
    ],
    "wof:name":"Sauvat Multiservice Sarl",
    "wof:placetype":"venue"
},
  "geometry": {"coordinates":[5.878961,43.104401],"type":"Point"}
}