{
  "type": "Feature",
  "properties": {
    "addr:full":"244 Rue Du Vert Touquet 62350 CALONNE SUR LA LYS Nord Pas-de-Calais 62350",
    "addr:housenumber":"244",
    "addr:postcode":"62350;62350",
    "addr:street":"Rue Du Vert Touquet;La Lys Nord",
    "iso:country":"FR",
    "sg:address":"244 Rue Du Vert Touquet 62350 CALONNE SUR LA LYS",
    "sg:classifiers":[
        {
            "category":"Food & Beverages",
            "subcategory":"Meat & Fish",
            "type":"Retail Goods"
        }
    ],
    "sg:phone":"+33 3 21 27 51 77",
    "sg:postcode":"62350",
    "sg:province":"Nord Pas-de-Calais",
    "sg:tags":[
        "domestic",
        "animal"
    ],
    "wof:name":"Premix Inve France Nord Sa",
    "wof:placetype":"venue"
},
  "geometry": {"coordinates":[2.612122,50.62257],"type":"Point"}
}