{
  "type": "Feature",
  "properties": {
    "iso:country":"FR",
    "sg:address":"B.P. 328, 22403 Lamballe C\u00e9dex^^Rue de la Jeannaie - ZI - la Jaunaie Marou\u00e9 , 22400 Lamballe",
    "sg:city":"Lamballe",
    "sg:orig_category":"Non-Classified Establishments",
    "sg:phone":"+33 2 96 30 70 00",
    "sg:postcode":"22400",
    "sg:province":"Bretagne",
    "wof:name":"Cooperl Hunaudaye",
    "wof:placetype":"venue"
},
  "geometry": {"coordinates":[-2.539697,48.428795],"type":"Point"}
}