{
  "type": "Feature",
  "properties": {
    "iso:country":"FR",
    "sg:address":"144 Boulevard Jules Durand Site Tecnor 76600 Le Havre",
    "sg:classifiers":[
        {
            "category":"Professional",
            "type":"Services"
        }
    ],
    "sg:phone":"+33 2 35 53 10 11",
    "sg:province":"Haute Normandie",
    "sg:tags":[
        "transport"
    ],
    "wof:name":"Geologistics Sa",
    "wof:placetype":"venue"
},
  "geometry": {"coordinates":[0.158605,49.490147],"type":"Point"}
}