{
  "type": "Feature",
  "properties": {
    "addr:full":"25, Rte de Rohrwiller, 67410 Drusenheim Rohrwiller Alsace 67410",
    "addr:housenumber":"25",
    "addr:postcode":"67410;67410",
    "addr:street":"Rte De Rohrwiller;Rohrwiller",
    "iso:country":"FR",
    "sg:address":"25, Rte de Rohrwiller, 67410 Drusenheim",
    "sg:city":"Rohrwiller",
    "sg:orig_category":"Non-Classified Establishments",
    "sg:phone":"+33 3 90 29 18 88",
    "sg:postcode":"67410",
    "sg:province":"Alsace",
    "wof:name":"Socobat S.a.r.l.",
    "wof:placetype":"venue"
},
  "geometry": {"coordinates":[7.941088,48.765575],"type":"Point"}
}