{
  "type": "Feature",
  "properties": {
    "addr:full":"ZI Le Paradis Pellevoisin Centre 36180",
    "addr:postcode":"36180",
    "addr:street":"Zi",
    "iso:country":"FR",
    "sg:address":"ZI Le Paradis",
    "sg:city":"Pellevoisin",
    "sg:orig_category":"Unclassifiable Establishments",
    "sg:phone":"+33 2 54 39 03 52",
    "sg:postcode":"36180",
    "sg:province":"Centre",
    "wof:name":"Camail Silos S.a.",
    "wof:placetype":"venue"
},
  "geometry": {"coordinates":[1.4143,46.983109],"type":"Point"}
}