{
  "type": "Feature",
  "properties": {
    "iso:country":"FR",
    "sg:address":"B.P. 10, 32100 Condom^^18, Rue Honor\u00e9 Cazaubon, 32100 Condom",
    "sg:orig_category":"Non-Classified Establishments",
    "sg:phone":"+33 5 62 28 00 55",
    "sg:province":"Midi Pyr\u00e9n\u00e9es",
    "wof:name":"Les Imprimeries De Gascogne S.a.r.l.",
    "wof:placetype":"venue"
},
  "geometry": {"coordinates":[0.334099,43.908184],"type":"Point"}
}