{
  "type": "Feature",
  "properties": {
    "iso:country":"FR",
    "sg:address":"435, Rue du Mas Saint Pierre - ZAC de Tournesy, 34000 Montpellier",
    "sg:orig_category":"Non-Classified Establishments",
    "sg:phone":"+33 4 67 47 30 19",
    "sg:province":"Languedoc-Roussillon",
    "wof:name":"Sud Energie Thermi Caupert S.a.r.l.",
    "wof:placetype":"venue"
},
  "geometry": {"coordinates":[3.87609,43.610855],"type":"Point"}
}