{
  "type": "Feature",
  "properties": {
    "addr:full":"2 Rue Hennape 92735 Nanterre Cedex Languedoc-Roussillon",
    "addr:housenumber":"2",
    "addr:postcode":"92735;cedex",
    "addr:street":"Rue Hennape",
    "iso:country":"FR",
    "sg:address":"2 Rue Hennape 92735 Nanterre Cedex",
    "sg:classifiers":[
        {
            "category":"Autos & Motor Vehicles",
            "subcategory":"Automobile Sales",
            "type":"Retail Goods"
        }
    ],
    "sg:phone":"+33 1 72 36 70 00",
    "sg:province":"Languedoc-Roussillon",
    "sg:tags":[
        "equipment",
        "motor-cars",
        "transport"
    ],
    "wof:name":"Faurecia",
    "wof:placetype":"venue"
},
  "geometry": {"coordinates":[2.215244,48.886616],"type":"Point"}
}