{
  "type": "Feature",
  "properties": {
    "addr:full":"17 Rue Des Fr\u00e8res Lumi\u00e8re Zi Mitry Compans 77292 Mitry Mory Compans Ile de France 77290",
    "addr:housenumber":"17",
    "addr:postcode":"77292;77290",
    "addr:street":"Rue Des Fre\u0300Res Lumie\u0300Re Zi Mitry",
    "iso:country":"FR",
    "sg:address":"17 Rue Des Fr\u00e8res Lumi\u00e8re Zi Mitry Compans 77292 Mitry Mory",
    "sg:city":"Compans",
    "sg:classifiers":[
        {
            "category":"Professional",
            "subcategory":"Engineering",
            "type":"Services"
        }
    ],
    "sg:phone":"+33 1 60 93 70 00",
    "sg:postcode":"77290",
    "sg:province":"Ile de France",
    "sg:tags":[
        "machine",
        "-",
        "mechanical"
    ],
    "wof:name":"Bonnet Cidelcem Grande Cuisine",
    "wof:placetype":"venue"
},
  "geometry": {"coordinates":[2.855448,50.157646],"type":"Point"}
}