{
  "type": "Feature",
  "properties": {
    "addr:full":"La Gare 85150 Landeronde Pays de Loire 85150",
    "addr:postcode":"85150;85150",
    "addr:street":"Landeronde",
    "iso:country":"FR",
    "sg:address":"La Gare 85150 Landeronde",
    "sg:classifiers":[
        {
            "category":"Wholesale",
            "subcategory":"Farm Supplies",
            "type":"Manufacturing & Wholesale Goods"
        }
    ],
    "sg:phone":"+33 2 51 40 37 46",
    "sg:postcode":"85150",
    "sg:province":"Pays de Loire",
    "sg:tags":[
        "-",
        "machine",
        "equipment",
        "engineering",
        "machinery",
        "mechanical",
        "agriculture"
    ],
    "wof:name":"Ms Maintenance (msm)",
    "wof:placetype":"venue"
},
  "geometry": {"coordinates":[-1.534814,46.638088],"type":"Point"}
}