{
  "type": "Feature",
  "properties": {
    "iso:country":"FR",
    "sg:address":"Fbg des Quatre Moulins",
    "sg:city":"Chaumont C\u00e9dex",
    "sg:orig_category":"Non-Classified Establishments",
    "sg:phone":"+33 3 25 03 20 53",
    "sg:postcode":"52001",
    "sg:province":"Franche Comt\u00e9",
    "wof:name":"B.g.i.e. S.a. - B\u00e9ton Granul\u00e9 Isle De France Et Est",
    "wof:placetype":"venue"
},
  "geometry": {"coordinates":[5.145165,48.122581],"type":"Point"}
}