{
  "type": "Feature",
  "properties": {
    "addr:full":"57, Rue de Malacombe - Parc d'Activit\u00e9s de Chesnes, 38290 Saint Quentin Fallavier Rhone-Alpes 38290",
    "addr:housenumber":"57",
    "addr:postcode":"38290;38290",
    "addr:street":"Rue De Malacombe Parc D'Activite \u0301S De Chesnes",
    "iso:country":"FR",
    "sg:address":"57, Rue de Malacombe - Parc d'Activit\u00e9s de Chesnes, 38290 Saint Quentin Fallavier",
    "sg:orig_category":"Unclassifiable Establishments",
    "sg:phone":"+33 4 74 82 15 15",
    "sg:postcode":"38290",
    "sg:province":"Rhone-Alpes",
    "wof:name":"Pompes Grundfos Distribution S.a.",
    "wof:placetype":"venue"
},
  "geometry": {"coordinates":[5.12862,45.64465],"type":"Point"}
}