{
  "type": "Feature",
  "properties": {
    "iso:country":"FR",
    "sg:address":"1, Rue Antonin Magne - ZAC de Lignerolles, 45400 Fleury les Aubrais",
    "sg:city":"Chanteau",
    "sg:orig_category":"Unclassifiable Establishments",
    "sg:phone":"+33 2 38 70 95 20",
    "sg:postcode":"45400",
    "sg:province":"Centre",
    "wof:name":"G\u00e9odis Logistics Euromatic S.a.",
    "wof:placetype":"venue"
},
  "geometry": {"coordinates":[1.920976,47.931038],"type":"Point"}
}