{
  "type": "Feature",
  "properties": {
    "addr:full":"Chemin Champlet Vitr\u00e9 Bretagne 35500",
    "addr:postcode":"35500",
    "addr:street":"Chemin Champlet;Bretagne",
    "iso:country":"FR",
    "sg:address":"Chemin Champlet",
    "sg:city":"Vitr\u00e9",
    "sg:orig_category":"Unclassifiable Establishments",
    "sg:phone":"+33 2 99 75 05 77",
    "sg:postcode":"35500",
    "sg:province":"Bretagne",
    "wof:name":"Bilheude Ange S.a.r.l.",
    "wof:placetype":"venue"
},
  "geometry": {"coordinates":[-1.220415,48.128365],"type":"Point"}
}