{
  "type": "Feature",
  "properties": {
    "addr:full":"B.P. 9, 88401 G\u00e9rardmer C\u00e9dex^^6, Place de la Gare, 88400 G\u00e9rardmer Lorraine",
    "addr:housenumber":"9",
    "addr:postcode":"88401;88400",
    "addr:street":"B.P.;Place De La Gare",
    "iso:country":"FR",
    "sg:address":"B.P. 9, 88401 G\u00e9rardmer C\u00e9dex^^6, Place de la Gare, 88400 G\u00e9rardmer",
    "sg:orig_category":"Non-Classified Establishments",
    "sg:phone":"+33 3 29 60 11 00",
    "sg:province":"Lorraine",
    "wof:name":"Linvosges S.a.",
    "wof:placetype":"venue"
},
  "geometry": {"coordinates":[6.877125,48.070274],"type":"Point"}
}