{
  "type": "Feature",
  "properties": {
    "iso:country":"FR",
    "sg:address":"B.P. 77, 67802 Bischheim C\u00e9dex^^23, Rue de la Robertsau, 67800 Bischheim",
    "sg:city":"Bischheim",
    "sg:orig_category":"Non-Classified Establishments",
    "sg:phone":"+33 3 88 33 50 15",
    "sg:postcode":"67800",
    "sg:province":"Alsace",
    "wof:name":"I.c.a. S.a. - Industrie Chimique D'alsace",
    "wof:placetype":"venue"
},
  "geometry": {"coordinates":[7.752544,48.61483],"type":"Point"}
}