{
  "type": "Feature",
  "properties": {
    "iso:country":"FR",
    "sg:address":"B.P. 87, 62220 Carvin^^Rte de Courri\u00e8res, 62220 Carvin",
    "sg:orig_category":"Non-Classified Establishments",
    "sg:phone":"+33 3 21 74 41 10",
    "sg:postcode":"62220",
    "sg:province":"Nord Pas-de-Calais",
    "wof:name":"Artifor - Baby France S.a.",
    "wof:placetype":"venue"
},
  "geometry": {"coordinates":[2.95784,50.490471],"type":"Point"}
}