{
  "type": "Feature",
  "properties": {
    "iso:country":"FR",
    "sg:address":"4 R De La Mare 71530 Crissey",
    "sg:city":"Crissey",
    "sg:classifiers":[
        {
            "category":"Shopping",
            "type":"Retail Goods"
        }
    ],
    "sg:phone":"+33 3 85 97 28 60",
    "sg:postcode":"71530",
    "sg:province":"Bourgogne",
    "sg:tags":[
        "metallurgy",
        "finished",
        "-",
        "metalworking",
        "metallic"
    ],
    "wof:name":"Amo Sa",
    "wof:placetype":"venue"
},
  "geometry": {"coordinates":[4.867718,46.821926],"type":"Point"}
}