{
  "type": "Feature",
  "properties": {
    "iso:country":"FR",
    "sg:address":"19 rue Jean Lolive 93170 Bagnolet",
    "sg:classifiers":[
        {
            "category":"Manufacturing",
            "subcategory":"Metals",
            "type":"Manufacturing & Wholesale Goods"
        }
    ],
    "sg:phone":"+33 1 43 62 18 81",
    "sg:postcode":"93170",
    "sg:province":"Ile de France",
    "sg:tags":[
        "blanking",
        "dy"
    ],
    "wof:name":"Fibro Sarl",
    "wof:placetype":"venue"
},
  "geometry": {"coordinates":[2.426369,48.865868],"type":"Point"}
}