{
  "type": "Feature",
  "properties": {
    "addr:full":"41, Cit\u00e9 Ad\u00e9la\u00efde, 67660 Betschdorf Betschdorf Alsace 67660",
    "addr:housenumber":"41",
    "addr:postcode":"67660;67660",
    "addr:street":"Cite\u0301 Ade\u0301Lai\u0308De",
    "iso:country":"FR",
    "sg:address":"41, Cit\u00e9 Ad\u00e9la\u00efde, 67660 Betschdorf",
    "sg:city":"Betschdorf",
    "sg:orig_category":"Unclassifiable Establishments",
    "sg:phone":"+33 3 88 54 42 07",
    "sg:postcode":"67660",
    "sg:province":"Alsace",
    "wof:name":"Soci\u00e9t\u00e9 Alsacienne De Nettoyage S.a.r.l.",
    "wof:placetype":"venue"
},
  "geometry": {"coordinates":[7.926831,48.892628],"type":"Point"}
}