{
  "type": "Feature",
  "properties": {
    "addr:full":"73, Parc d'Activit\u00e9 de l'Argile, 06370 Mouans Sartoux Provence-Alpes-C\u00f4te d'Azur",
    "addr:housenumber":"73",
    "addr:postcode":"06370",
    "addr:street":"Parc D'Activite \u0301 De L'Argile;Sartoux",
    "iso:country":"FR",
    "sg:address":"73, Parc d'Activit\u00e9 de l'Argile, 06370 Mouans Sartoux",
    "sg:orig_category":"Unclassifiable Establishments",
    "sg:phone":"+33 4 92 28 38 30",
    "sg:province":"Provence-Alpes-C\u00f4te d'Azur",
    "wof:name":"I.c.s. S.a. - Informatique Conseils Services",
    "wof:placetype":"venue"
},
  "geometry": {"coordinates":[6.95661,43.611614],"type":"Point"}
}