{
  "type": "Feature",
  "properties": {
    "iso:country":"FR",
    "sg:address":"46 Av Jean Jaur\u00e8s 94110 Arcueil",
    "sg:classifiers":[
        {
            "category":"Manufacturing",
            "subcategory":"Metals",
            "type":"Manufacturing & Wholesale Goods"
        }
    ],
    "sg:phone":"+33 1 47 35 02 68",
    "sg:postcode":"94110",
    "sg:province":"Ile de France",
    "sg:tags":[
        "-",
        "machine",
        "equipment",
        "engineering",
        "machinery",
        "mechanical"
    ],
    "wof:name":"Stpm Et Zindy Sa",
    "wof:placetype":"venue"
},
  "geometry": {"coordinates":[2.331888,48.810467],"type":"Point"}
}