{
  "type": "Feature",
  "properties": {
    "addr:full":"63, Rue de la Cloche, 59509 Douai C\u00e9dex Nord-Pas-de-Calais",
    "addr:housenumber":"63",
    "addr:postcode":"59509;ce\u0301dex",
    "addr:street":"Rue De La Cloche",
    "iso:country":"FR",
    "sg:address":"63, Rue de la Cloche, 59509 Douai C\u00e9dex",
    "sg:orig_category":"Unclassifiable Establishments",
    "sg:phone":"+33 3 27 99 77 11",
    "sg:province":"Nord-Pas-de-Calais",
    "wof:name":"Degand Marquage S.a.",
    "wof:placetype":"venue"
},
  "geometry": {"coordinates":[3.07836,50.368759],"type":"Point"}
}