{
  "type": "Feature",
  "properties": {
    "addr:full":"Zone de la Vialette 81150 MARSSAC SUR TARN Midi Pyr\u00e9n\u00e9es 81150",
    "addr:postcode":"81150;81150",
    "addr:street":"De;Vialette",
    "iso:country":"FR",
    "sg:address":"Zone de la Vialette 81150 MARSSAC SUR TARN",
    "sg:classifiers":[
        {
            "category":"Professional",
            "subcategory":"Art Services",
            "type":"Services"
        }
    ],
    "sg:phone":"+33 5 63 53 25 50",
    "sg:postcode":"81150",
    "sg:province":"Midi Pyr\u00e9n\u00e9es",
    "sg:tags":[
        "framing"
    ],
    "wof:name":"Compobaie S.a.",
    "wof:placetype":"venue"
},
  "geometry": {"coordinates":[2.02965,43.917301],"type":"Point"}
}