{
  "type": "Feature",
  "properties": {
    "iso:country":"FR",
    "sg:address":"2, Bd de Bellechasse, 94100 Saint Maur des Foss\u00e9s",
    "sg:orig_category":"Non-Classified Establishments",
    "sg:phone":"+33 1 42 83 68 84",
    "sg:province":"Ile de France",
    "wof:name":"Mat\u00e9riaux Guy P\u00e8re Et Fils S.a.r.l.",
    "wof:placetype":"venue"
},
  "geometry": {"coordinates":[2.478903,48.793301],"type":"Point"}
}