{
  "type": "Feature",
  "properties": {
    "addr:full":"140, Rue du Paradis, 59500 Douai Nord Pas-de-Calais",
    "addr:housenumber":"140",
    "addr:postcode":"59500",
    "addr:street":"Rue Du Paradis",
    "iso:country":"FR",
    "sg:address":"140, Rue du Paradis, 59500 Douai",
    "sg:orig_category":"Unclassifiable Establishments",
    "sg:phone":"+33 3 27 93 49 49",
    "sg:province":"Nord Pas-de-Calais",
    "wof:name":"Arbel Fauvet Rail, S.a.",
    "wof:placetype":"venue"
},
  "geometry": {"coordinates":[3.098634,50.369026],"type":"Point"}
}