{
  "type": "Feature",
  "properties": {
    "iso:country":"FR",
    "sg:address":"Av. de la Promenade",
    "sg:city":"Boulogne sur Gesse",
    "sg:orig_category":"Unclassifiable Establishments",
    "sg:phone":"+33 5 61 88 21 38",
    "sg:postcode":"31350",
    "sg:province":"Midi Pyr\u00e9n\u00e9es",
    "wof:name":"Soci\u00e9t\u00e9 Boub\u00e9e G\u00e9rard Et Compagnie S.a.",
    "wof:placetype":"venue"
},
  "geometry": {"coordinates":[0.6473,43.28912],"type":"Point"}
}