{
  "type": "Feature",
  "properties": {
    "addr:full":"137, Rue de Versailles, 78150 Le Chesnay Ile de France",
    "addr:housenumber":"137",
    "addr:postcode":"78150",
    "addr:street":"Rue De Versailles",
    "iso:country":"FR",
    "sg:address":"137, Rue de Versailles, 78150 Le Chesnay",
    "sg:orig_category":"Unclassifiable Establishments",
    "sg:phone":"+33 1 39 63 23 28",
    "sg:province":"Ile de France",
    "wof:name":"Caljan Loading Systems S.a.r.l.",
    "wof:placetype":"venue"
},
  "geometry": {"coordinates":[2.128216,48.826241],"type":"Point"}
}