{
  "type": "Feature",
  "properties": {
    "addr:full":"B.P. 51, 59510 Hem^^106, Rue des 3 Baudets, 59510 Hem Nord Pas-de-Calais",
    "addr:postcode":"59510;59510",
    "addr:street":"B.P. 51;Rue Des 3 Baudets",
    "iso:country":"FR",
    "sg:address":"B.P. 51, 59510 Hem^^106, Rue des 3 Baudets, 59510 Hem",
    "sg:orig_category":"Non-Classified Establishments",
    "sg:phone":"+33 3 20 75 26 83",
    "sg:province":"Nord Pas-de-Calais",
    "wof:name":"I.b.b. S.a.r.l. - Imprimerie Brissart Bruno",
    "wof:placetype":"venue"
},
  "geometry": {"coordinates":[3.184105,50.653839],"type":"Point"}
}