{
  "type": "Feature",
  "properties": {
    "iso:country":"FR",
    "sg:address":"13, Rue du Soleil, 68600 Neuf Brisach",
    "sg:city":"Algolsheim",
    "sg:orig_category":"Unclassifiable Establishments",
    "sg:phone":"+33 3 89 72 52 39",
    "sg:postcode":"68600",
    "sg:province":"Alsace",
    "wof:name":"Deppen S.a.",
    "wof:placetype":"venue"
},
  "geometry": {"coordinates":[7.531582,48.017784],"type":"Point"}
}