{
  "type": "Feature",
  "properties": {
    "addr:full":"Rue Danton - ZI des Vignettes La Chapelle Saint Luc Champagne 10600",
    "addr:postcode":"10600",
    "addr:street":"Rue Danton Zi Des Vignettes La Chapelle Saint Luc Champagne",
    "iso:country":"FR",
    "sg:address":"Rue Danton - ZI des Vignettes",
    "sg:city":"La Chapelle Saint Luc",
    "sg:orig_category":"Non-Classified Establishments",
    "sg:phone":"+33 3 25 71 24 60",
    "sg:postcode":"10600",
    "sg:province":"Champagne",
    "wof:name":"M\u00e9tal Giron S.a.",
    "wof:placetype":"venue"
},
  "geometry": {"coordinates":[3.988404,48.401478],"type":"Point"}
}