{
  "type": "Feature",
  "properties": {
    "iso:country":"FR",
    "sg:address":"Rte Landouville",
    "sg:city":"Tremblay les Villages",
    "sg:orig_category":"Unclassifiable Establishments",
    "sg:phone":"+33 2 37 65 24 39",
    "sg:postcode":"28170",
    "sg:province":"Centre",
    "wof:name":"Maillard Jean-fran\u00e7ois",
    "wof:placetype":"venue"
},
  "geometry": {"coordinates":[1.403417,48.582996],"type":"Point"}
}