{
  "type": "Feature",
  "properties": {
    "addr:full":"63 Rue Paul Et Marc Barbezat 69150 Decines Charpieu Rhone-Alpes 69150",
    "addr:housenumber":"63",
    "addr:postcode":"69150;69150",
    "addr:street":"Rue Paul Et Marc Barbezat;Rhone-Alpes",
    "iso:country":"FR",
    "sg:address":"63 Rue Paul Et Marc Barbezat 69150 Decines Charpieu",
    "sg:classifiers":[
        {
            "category":"Manufacturing",
            "subcategory":"Chemicals & Compounds",
            "type":"Manufacturing & Wholesale Goods"
        }
    ],
    "sg:phone":"+33 4 72 93 33 04",
    "sg:postcode":"69150",
    "sg:province":"Rhone-Alpes",
    "sg:tags":[
        "pharmaceutical",
        "chemistry",
        "-",
        "by-product"
    ],
    "wof:name":"Starc",
    "wof:placetype":"venue"
},
  "geometry": {"coordinates":[4.939422,45.75531],"type":"Point"}
}