{
  "type": "Feature",
  "properties": {
    "addr:full":"4 rue des Falaisi\u00e8res 36220 FONTGOMBAULT Fontgombault Centre 36220",
    "addr:housenumber":"4;fontgombault",
    "addr:postcode":"36220;36220",
    "addr:street":"Rue Des Falaisie\u0300Res",
    "iso:country":"FR",
    "sg:address":"4 rue des Falaisi\u00e8res 36220 FONTGOMBAULT",
    "sg:city":"Fontgombault",
    "sg:classifiers":[
        {
            "category":"Wholesale",
            "subcategory":"Electrical",
            "type":"Manufacturing & Wholesale Goods"
        }
    ],
    "sg:phone":"+33 2 54 37 09 80",
    "sg:postcode":"36220",
    "sg:province":"Centre",
    "sg:tags":[
        "component"
    ],
    "wof:name":"Blanc M\u00e9ca Electronique Sas",
    "wof:placetype":"venue"
},
  "geometry": {"coordinates":[0.97906,46.678967],"type":"Point"}
}