{
  "type": "Feature",
  "properties": {
    "addr:full":"Rue Basse 08430 Touligny Champigneul-sur-Vence Champagne 08430",
    "addr:postcode":"08430;08430",
    "addr:street":"Rue Basse;Champagne",
    "iso:country":"FR",
    "sg:address":"Rue Basse 08430 Touligny",
    "sg:city":"Champigneul-sur-Vence",
    "sg:classifiers":[
        {
            "category":"Home & Garden",
            "subcategory":"Furniture",
            "type":"Retail Goods"
        }
    ],
    "sg:phone":"+33 3 24 35 60 70",
    "sg:postcode":"08430",
    "sg:province":"Champagne",
    "sg:tags":[
        "wood"
    ],
    "wof:name":"Rohart Sarl",
    "wof:placetype":"venue"
},
  "geometry": {"coordinates":[4.616693,49.670555],"type":"Point"}
}