{
  "type": "Feature",
  "properties": {
    "iso:country":"FR",
    "sg:address":"Les Jacous 31340 VILLEMUR SUR TARN",
    "sg:orig_category":"Materials Testing Machines And Equipment",
    "sg:phone":"+33 5 61 35 37 25",
    "sg:postcode":"31340",
    "sg:province":"Midi Pyr\u00e9n\u00e9es",
    "wof:name":"Jfc S.a.r.l.",
    "wof:placetype":"venue"
},
  "geometry": {"coordinates":[1.486095,43.8563],"type":"Point"}
}