{
  "type": "Feature",
  "properties": {
    "iso:country":"FR",
    "sg:address":"Rue Du Chemin De Fer Zi Rammelplatz 2 67116 Reichstett",
    "sg:city":"Reichstett",
    "sg:classifiers":[
        {
            "category":"Wholesale",
            "subcategory":"Meat",
            "type":"Manufacturing & Wholesale Goods"
        }
    ],
    "sg:phone":"+33 3 88 19 06 66",
    "sg:postcode":"67116",
    "sg:province":"Alsace",
    "sg:tags":[
        "food",
        "cooked",
        "product",
        "related"
    ],
    "wof:name":"Hermann Boucherie Charcuterie Traiteur",
    "wof:placetype":"venue"
},
  "geometry": {"coordinates":[7.753589,48.648308],"type":"Point"}
}