{
  "type": "Feature",
  "properties": {
    "iso:country":"FR",
    "sg:address":"61 Av Paul Langevin 13570 Barbentane",
    "sg:classifiers":[
        {
            "category":"Farming",
            "subcategory":"Farm",
            "type":"Manufacturing & Wholesale Goods"
        }
    ],
    "sg:phone":"+33 4 90 94 93 00",
    "sg:province":"Centre",
    "sg:tags":[
        "horticulture",
        "agriculture",
        "livestock"
    ],
    "wof:name":"Du Roure Sa (j P )",
    "wof:placetype":"venue"
},
  "geometry": {"coordinates":[4.745885,43.899456],"type":"Point"}
}