{
  "type": "Feature",
  "properties": {
    "iso:country":"FR",
    "sg:address":"Zone Industrielle de Chavanon 43120 MONISTROL SUR LOIRE",
    "sg:city":"Monistrol-sur-Loire",
    "sg:classifiers":[
        {
            "category":"Manufacturing",
            "subcategory":"Rubber & Plastics",
            "type":"Manufacturing & Wholesale Goods"
        }
    ],
    "sg:phone":"+33 4 71 75 43 61",
    "sg:postcode":"43120",
    "sg:province":"Auvergne",
    "sg:tags":[
        "packaging",
        "mean"
    ],
    "wof:name":"Emballages Du Lignon Soci\u00e9t\u00e9 Nouvelle Sarl",
    "wof:placetype":"venue"
},
  "geometry": {"coordinates":[4.172515,45.292206],"type":"Point"}
}