{
  "type": "Feature",
  "properties": {
    "addr:full":"Rue Gerleinkirchen Zi 29300 Quimperl\u00e9 Quimperl\u00e9 Bretagne 29300",
    "addr:postcode":"29300;29300",
    "addr:street":"Rue Gerleinkirchen Zi",
    "iso:country":"FR",
    "sg:address":"Rue Gerleinkirchen Zi 29300 Quimperl\u00e9",
    "sg:city":"Quimperl\u00e9",
    "sg:classifiers":[
        {
            "category":"Manufacturing",
            "subcategory":"Metals",
            "type":"Manufacturing & Wholesale Goods"
        }
    ],
    "sg:phone":"+33 2 98 96 03 88",
    "sg:postcode":"29300",
    "sg:province":"Bretagne",
    "sg:tags":[
        "metallurgy",
        "metalworking"
    ],
    "wof:name":"Guyader Sas",
    "wof:placetype":"venue"
},
  "geometry": {"coordinates":[-3.461656,47.859921],"type":"Point"}
}