{
  "type": "Feature",
  "properties": {
    "iso:country":"FR",
    "sg:address":"8, Rue de la Vrilli\u00e8re, 75001 Paris",
    "sg:orig_category":"Unclassifiable Establishments",
    "sg:phone":"+33 1 42 97 49 60",
    "sg:province":"Ile de France",
    "wof:name":"Martine Leherpeur Conseil S.a.",
    "wof:placetype":"venue"
},
  "geometry": {"coordinates":[2.340222,48.865761],"type":"Point"}
}