{
  "type": "Feature",
  "properties": {
    "addr:full":"445, Rte de Talair - ZI, 01100 Martignat Rhone-Alpes 01100",
    "addr:housenumber":"445",
    "addr:postcode":"01100;01100",
    "addr:street":"Rte De Talair Zi;Rhone-Alpes",
    "iso:country":"FR",
    "sg:address":"445, Rte de Talair - ZI, 01100 Martignat",
    "sg:orig_category":"Unclassifiable Establishments",
    "sg:phone":"+33 4 74 81 42 79",
    "sg:postcode":"01100",
    "sg:province":"Rhone-Alpes",
    "wof:name":"D\u00e9cographie S.a.r.l.",
    "wof:placetype":"venue"
},
  "geometry": {"coordinates":[5.64399,46.24971],"type":"Point"}
}