{
  "type": "Feature",
  "properties": {
    "iso:country":"FR",
    "sg:address":"B.P. 120, 71305 Montceau les Mines C\u00e9dex^^ZA Sainte Elisabeth, 71300 Montceau les Mines",
    "sg:city":"Saint-Berain-sous-Sanvignes",
    "sg:orig_category":"Non-Classified Establishments",
    "sg:phone":"+33 3 85 57 41 23",
    "sg:postcode":"71300",
    "sg:province":"Bourgogne",
    "wof:name":"Advens S.a.",
    "wof:placetype":"venue"
},
  "geometry": {"coordinates":[4.498485,46.618446],"type":"Point"}
}