{
  "type": "Feature",
  "properties": {
    "iso:country":"FR",
    "sg:address":"10 Boulevard De La Bastille 75012 Paris",
    "sg:classifiers":[
        {
            "category":"Professional",
            "subcategory":"Printing & Photocopies",
            "type":"Services"
        }
    ],
    "sg:phone":"+33 1 44 75 10 00",
    "sg:province":"Ile de France",
    "sg:tags":[
        "publishing"
    ],
    "wof:name":"Flohic Editions",
    "wof:placetype":"venue"
},
  "geometry": {"coordinates":[2.367504,48.847252],"type":"Point"}
}