{
  "type": "Feature",
  "properties": {
    "addr:full":"B.P. 39, 02170 Le Nouvion en Thi\u00e9rache^^28, Rue de la Croix, 02170 Le Nouvion en Thi\u00e9rache Picardie",
    "addr:postcode":"02170;02170",
    "addr:street":"B.P. 39;Nouvion;Rue De La Croix;Nouvion",
    "iso:country":"FR",
    "sg:address":"B.P. 39, 02170 Le Nouvion en Thi\u00e9rache^^28, Rue de la Croix, 02170 Le Nouvion en Thi\u00e9rache",
    "sg:orig_category":"Non-Classified Establishments",
    "sg:phone":"+33 3 23 98 35 70",
    "sg:province":"Picardie",
    "wof:name":"Les Fromagers De Thi\u00e9rache S.a.",
    "wof:placetype":"venue"
},
  "geometry": {"coordinates":[3.78054,50.00227],"type":"Point"}
}