{
  "type": "Feature",
  "properties": {
    "addr:full":"Rue du Val - Zone Artisanale Confortland Melesse Bretagne 35520",
    "addr:postcode":"35520",
    "addr:street":"Rue Du Val Zone Artisanale Confortland Melesse Bretagne",
    "iso:country":"FR",
    "sg:address":"Rue du Val - Zone Artisanale Confortland",
    "sg:city":"Melesse",
    "sg:orig_category":"Unclassifiable Establishments",
    "sg:phone":"+33 2 99 13 23 00",
    "sg:postcode":"35520",
    "sg:province":"Bretagne",
    "wof:name":"Etablissements Tardif - Vassal S.a.",
    "wof:placetype":"venue"
},
  "geometry": {"coordinates":[-1.734432,48.178051],"type":"Point"}
}