{
  "type": "Feature",
  "properties": {
    "iso:country":"FR",
    "sg:address":"157 av XVI E J Olympiques Hiver 73200 Albertville",
    "sg:classifiers":[
        {
            "category":"Manufacturing",
            "subcategory":"Metals",
            "type":"Manufacturing & Wholesale Goods"
        }
    ],
    "sg:phone":"+33 4 79 32 04 65",
    "sg:postcode":"73200",
    "sg:province":"Rhone-Alpes",
    "sg:tags":[
        "sheet",
        "thin",
        "working"
    ],
    "wof:name":"Gardet Sa",
    "wof:placetype":"venue"
},
  "geometry": {"coordinates":[6.359874,45.63168],"type":"Point"}
}