{
  "type": "Feature",
  "properties": {
    "iso:country":"FR",
    "sg:address":"32, Av. Antoine Becquerel, 83130 La Garde",
    "sg:city":"La Garde",
    "sg:orig_category":"Unclassifiable Establishments",
    "sg:phone":"+33 4 94 01 71 40",
    "sg:postcode":"38520",
    "sg:province":"Rhone-Alpes",
    "wof:name":"Sodatec I.m.t. S.a.",
    "wof:placetype":"venue"
},
  "geometry": {"coordinates":[6.03375,43.138561],"type":"Point"}
}