{
  "type": "Feature",
  "properties": {
    "addr:full":"zone industrielle 62290 Noeux les Mines Nord Pas-de-Calais 62290",
    "addr:postcode":"62290;62290",
    "addr:street":"Zone Industrielle;Mines",
    "iso:country":"FR",
    "sg:address":"zone industrielle 62290 Noeux les Mines",
    "sg:orig_category":"Led Indicators",
    "sg:phone":"+33 3 21 02 88 04",
    "sg:postcode":"62290",
    "sg:province":"Nord Pas-de-Calais",
    "wof:name":"Centaure Systems Sa",
    "wof:placetype":"venue"
},
  "geometry": {"coordinates":[2.661913,50.480907],"type":"Point"}
}