{
  "type": "Feature",
  "properties": {
    "iso:country":"FR",
    "sg:address":"7, All\u00e9e James Joule - ZI des Aur\u00e9ats, 26000 Valence",
    "sg:orig_category":"Unclassifiable Establishments",
    "sg:phone":"+33 4 75 40 10 02",
    "sg:postcode":"26000",
    "sg:province":"Rhone-Alpes",
    "wof:name":"R.t.m. International S.a.",
    "wof:placetype":"venue"
},
  "geometry": {"coordinates":[4.889246,44.930458],"type":"Point"}
}