{
  "type": "Feature",
  "properties": {
    "addr:full":"9, Rue de la Grassinais, 35400 Saint Malo Saint-Malo Bretagne 35400",
    "addr:housenumber":"9",
    "addr:postcode":"35400;35400",
    "addr:street":"Rue De La Grassinais;Saint-Malo",
    "iso:country":"FR",
    "sg:address":"9, Rue de la Grassinais, 35400 Saint Malo",
    "sg:city":"Saint-Malo",
    "sg:orig_category":"Non-Classified Establishments",
    "sg:phone":"+33 2 99 81 89 26",
    "sg:postcode":"35400",
    "sg:province":"Bretagne",
    "wof:name":"Transports Michel Gautier S.a.r.l.",
    "wof:placetype":"venue"
},
  "geometry": {"coordinates":[-1.98653,48.621601],"type":"Point"}
}