{
  "type": "Feature",
  "properties": {
    "addr:full":"62, Quai des Carri\u00e8res, 94220 Charenton le Pont Ile de France",
    "addr:housenumber":"62",
    "addr:postcode":"94220",
    "addr:street":"Quai Des Carrie\u0300Res",
    "iso:country":"FR",
    "sg:address":"62, Quai des Carri\u00e8res, 94220 Charenton le Pont",
    "sg:orig_category":"Non-Classified Establishments",
    "sg:phone":"+33 1 43 78 87 22",
    "sg:province":"Ile de France",
    "wof:name":"Ireq S.a. - Institut De Recherches Et D'etudes Qualitatives E",
    "wof:placetype":"venue"
},
  "geometry": {"coordinates":[2.405897,48.819736],"type":"Point"}
}