{
  "type": "Feature",
  "properties": {
    "addr:full":"27, Rue du Cerf, 67200 Strasbourg Strasbourg Alsace 67200",
    "addr:housenumber":"27",
    "addr:postcode":"67200;67200",
    "addr:street":"Rue Du Cerf",
    "iso:country":"FR",
    "sg:address":"27, Rue du Cerf, 67200 Strasbourg",
    "sg:city":"Strasbourg",
    "sg:orig_category":"Non-Classified Establishments",
    "sg:phone":"+33 3 88 29 70 30",
    "sg:postcode":"67200",
    "sg:province":"Alsace",
    "wof:name":"Mad Design",
    "wof:placetype":"venue"
},
  "geometry": {"coordinates":[7.718065,48.593925],"type":"Point"}
}