{
  "type": "Feature",
  "properties": {
    "iso:country":"FR",
    "sg:address":"149-165 avenue Gallieni 93170 Bagnolet",
    "sg:classifiers":[
        {
            "category":"Shopping",
            "subcategory":"Computers & Home Electronics",
            "type":"Retail Goods"
        }
    ],
    "sg:phone":"+33 1 49 72 81 81",
    "sg:postcode":"93170",
    "sg:province":"Ile de France",
    "sg:tags":[
        "rom",
        "chip",
        "ram",
        "modules",
        "module",
        "memory"
    ],
    "wof:name":"Dane Elec Memory S.a.",
    "wof:placetype":"venue"
},
  "geometry": {"coordinates":[2.415234,48.859524],"type":"Point"}
}