{
  "type": "Feature",
  "properties": {
    "addr:full":"13 rue des Fontaines du Temple 75003 Paris Ile de France 75003",
    "addr:housenumber":"13",
    "addr:postcode":"75003;75003",
    "addr:street":"Rue Des Fontaines Du Temple",
    "iso:country":"FR",
    "sg:address":"13 rue des Fontaines du Temple 75003 Paris",
    "sg:classifiers":[
        {
            "category":"Professional",
            "subcategory":"Accounting & Tax Preparation",
            "type":"Services"
        }
    ],
    "sg:phone":"+33 1 48 87 84 76",
    "sg:postcode":"75003",
    "sg:province":"Ile de France",
    "sg:tags":[
        "christmas",
        "celebration",
        "easter",
        "accessories",
        "accessory"
    ],
    "wof:name":"Decomann Sa",
    "wof:placetype":"venue"
},
  "geometry": {"coordinates":[2.358867,48.865582],"type":"Point"}
}