{
  "type": "Feature",
  "properties": {
    "addr:full":"Rue S\u00e9verine Rib\u00e9court Dreslincourt Picardie 60170",
    "addr:postcode":"60170",
    "addr:street":"Rue Se\u0301Verine Ribe\u0301Court Dreslincourt Picardie",
    "iso:country":"FR",
    "sg:address":"Rue S\u00e9verine",
    "sg:city":"Rib\u00e9court Dreslincourt",
    "sg:orig_category":"Unclassifiable Establishments",
    "sg:phone":"+33 3 44 75 75 00",
    "sg:postcode":"60170",
    "sg:province":"Picardie",
    "wof:name":"S.e.c.o. S.a. - Engrais Chimiques Et Organiques",
    "wof:placetype":"venue"
},
  "geometry": {"coordinates":[2.918791,49.504154],"type":"Point"}
}