{
  "type": "Feature",
  "properties": {
    "iso:country":"FR",
    "sg:address":"Les Penons",
    "sg:city":"M\u00e9ry sur Cher",
    "sg:orig_category":"Unclassifiable Establishments",
    "sg:phone":"+33 2 48 75 03 49",
    "sg:postcode":"18100",
    "sg:province":"Centre",
    "wof:name":"Structures Outillages S.a.r.l.",
    "wof:placetype":"venue"
},
  "geometry": {"coordinates":[1.967034,47.252605],"type":"Point"}
}