{
  "type": "Feature",
  "properties": {
    "iso:country":"FR",
    "sg:address":"26 Route Troyes 10240 Avant L\u00e8s Ramerupt",
    "sg:classifiers":[
        {
            "category":"Professional",
            "type":"Services"
        }
    ],
    "sg:phone":"+33 3 25 37 61 00",
    "sg:province":"Champagne",
    "sg:tags":[
        "transport",
        "road"
    ],
    "wof:name":"Transports Bojko Sarl",
    "wof:placetype":"venue"
},
  "geometry": {"coordinates":[4.28435,48.444614],"type":"Point"}
}