{
  "type": "Feature",
  "properties": {
    "addr:full":"26 rue Blaise Pascal 79000 Niort Poitou-Charentes 79000",
    "addr:housenumber":"26",
    "addr:postcode":"79000;79000",
    "addr:street":"Rue Blaise Pascal",
    "iso:country":"FR",
    "sg:address":"26 rue Blaise Pascal 79000 Niort",
    "sg:classifiers":[
        {
            "category":"Bars & Pubs",
            "subcategory":"Biergarten",
            "type":"Food & Drink"
        }
    ],
    "sg:phone":"+33 5 49 17 23 70",
    "sg:postcode":"79000",
    "sg:province":"Poitou-Charentes",
    "sg:tags":[
        "cover",
        "swimming-pool"
    ],
    "wof:name":"L Abrimobile Sarl",
    "wof:placetype":"venue"
},
  "geometry": {"coordinates":[-0.492815,46.313759],"type":"Point"}
}