{
  "type": "Feature",
  "properties": {
    "iso:country":"FR",
    "sg:address":"21, All\u00e9e Louis Br\u00e9guet, 93420 Villepinte",
    "sg:orig_category":"Unclassifiable Establishments",
    "sg:phone":"+33 1 48 60 50 10",
    "sg:province":"Ile de France",
    "wof:name":"Phem Produit Hygi\u00e8ne S.a.",
    "wof:placetype":"venue"
},
  "geometry": {"coordinates":[2.562741,48.955769],"type":"Point"}
}