{
  "type": "Feature",
  "properties": {
    "addr:full":"Parc de la Vall\u00e9e du Saule Tremblay les Villages Centre 28170",
    "addr:postcode":"villages;28170",
    "addr:street":"Parc De La Valle\u0301E Du Saule Tremblay",
    "iso:country":"FR",
    "sg:address":"Parc de la Vall\u00e9e du Saule",
    "sg:city":"Tremblay les Villages",
    "sg:orig_category":"Non-Classified Establishments",
    "sg:phone":"+33 2 37 65 25 25",
    "sg:postcode":"28170",
    "sg:province":"Centre",
    "wof:name":"V.h.p. S.a. - Verrerie Haute Pr\u00e9cision",
    "wof:placetype":"venue"
},
  "geometry": {"coordinates":[1.227045,48.52977],"type":"Point"}
}