{
  "type": "Feature",
  "properties": {
    "addr:full":"Langeote 35150 Janz\u00e9 Janz\u00e9 Bretagne 35150",
    "addr:postcode":"35150;35150",
    "addr:street":"Langeote",
    "iso:country":"FR",
    "sg:address":"Langeote 35150 Janz\u00e9",
    "sg:city":"Janz\u00e9",
    "sg:classifiers":[
        {
            "category":"Building & Trades",
            "subcategory":"Equipment Rental",
            "type":"Services"
        }
    ],
    "sg:phone":"+33 2 99 47 08 07",
    "sg:postcode":"35150",
    "sg:province":"Bretagne",
    "sg:tags":[
        "wood",
        "transport",
        "furniture"
    ],
    "wof:name":"Transports Briand Et Fils Sarl",
    "wof:placetype":"venue"
},
  "geometry": {"coordinates":[-1.492719,47.926353],"type":"Point"}
}