{
  "type": "Feature",
  "properties": {
    "addr:full":"4 pl du Martroi; Malesherbes; 45330 Coudray Centre 45330",
    "addr:housenumber":"4;coudray",
    "addr:postcode":"45330;45330",
    "addr:street":"Pl Du Martroi Malesherbes",
    "iso:country":"FR",
    "sg:address":"4 pl du Martroi; Malesherbes; 45330",
    "sg:city":"Coudray",
    "sg:classifiers":[
        {
            "category":"Banks & Credit Unions",
            "subcategory":"Bank",
            "type":"Services"
        }
    ],
    "sg:phone":"+33 3338348797",
    "sg:postcode":"45330",
    "sg:province":"Centre",
    "wof:name":"Soci\u00e9t\u00e9 G\u00e9n\u00e9rale",
    "wof:placetype":"venue"
},
  "geometry": {"coordinates":[2.41545,48.29697],"type":"Point"}
}