{
  "type": "Feature",
  "properties": {
    "iso:country":"FR",
    "sg:address":"9, Rue Andr\u00e9 Amp\u00e8re - ZA de la Mare du Milieu, 91630 Guibeville",
    "sg:orig_category":"Unclassifiable Establishments",
    "sg:phone":"+33 1 64 90 94 00",
    "sg:province":"Ile de France",
    "wof:name":"I.t.i.f. Et Associ\u00e9s S.a.r.l. - Innovation Technique Industrielle Ile De France",
    "wof:placetype":"venue"
},
  "geometry": {"coordinates":[2.30128,48.561611],"type":"Point"}
}