{
  "type": "Feature",
  "properties": {
    "addr:full":"15 Rue Trebois 92300 Levallois Perret Ile de France 92300",
    "addr:housenumber":"15",
    "addr:postcode":"92300;ile;92300",
    "addr:street":"Rue Trebois;France",
    "iso:country":"FR",
    "sg:address":"15 Rue Trebois 92300 Levallois Perret",
    "sg:classifiers":[
        {
            "category":"Professional",
            "subcategory":"Advertising",
            "type":"Services"
        }
    ],
    "sg:phone":"+33 1 47 59 88 88",
    "sg:postcode":"92300",
    "sg:province":"Ile de France",
    "sg:tags":[
        "communication",
        "medium"
    ],
    "wof:name":"Actima Sa",
    "wof:placetype":"venue"
},
  "geometry": {"coordinates":[2.290237,48.890472],"type":"Point"}
}