{
  "type": "Feature",
  "properties": {
    "addr:full":"175 rue G\u00e9n\u00e9ral de Gaulle 27160 BRETEUIL SUR ITON Haute Normandie 27160",
    "addr:housenumber":"175",
    "addr:postcode":"27160;27160",
    "addr:street":"Rue Ge\u0301Ne\u0301Ral De Gaulle;Haute Normandie",
    "iso:country":"FR",
    "sg:address":"175 rue G\u00e9n\u00e9ral de Gaulle 27160 BRETEUIL SUR ITON",
    "sg:classifiers":[
        {
            "category":"Building & Trades",
            "subcategory":"Landfill",
            "type":"Services"
        }
    ],
    "sg:phone":"+33 2 32 29 74 81",
    "sg:postcode":"27160",
    "sg:province":"Haute Normandie",
    "sg:tags":[
        "fa\u00e7ades",
        "metal"
    ],
    "wof:name":"Merlet Plastiques S.a.",
    "wof:placetype":"venue"
},
  "geometry": {"coordinates":[0.85262,48.788513],"type":"Point"}
}