{
  "type": "Feature",
  "properties": {
    "addr:full":"2 Rue Du Pa 88470 St Michel Sur Meurthe Lorraine",
    "addr:housenumber":"2",
    "addr:postcode":"88470",
    "addr:street":"Rue Du Pa;Michel;Meurthe",
    "iso:country":"FR",
    "sg:address":"2 Rue Du Pa 88470 St Michel Sur Meurthe",
    "sg:classifiers":[
        {
            "category":"Manufacturing",
            "subcategory":"Rubber & Plastics",
            "type":"Manufacturing & Wholesale Goods"
        }
    ],
    "sg:phone":"+33 3 29 53 40 00",
    "sg:province":"Lorraine",
    "wof:name":"Faurecia Interieur Industrie",
    "wof:placetype":"venue"
},
  "geometry": {"coordinates":[6.889527,48.320232],"type":"Point"}
}