{
  "type": "Feature",
  "properties": {
    "iso:country":"FR",
    "sg:address":"B.P. 2251, 27950 Saint Marcel^^26, Rue de la Croix Blanche - ZAC de la Grande Garenne, 27950 Saint M",
    "sg:orig_category":"Non-Classified Establishments",
    "sg:phone":"+33 2 32 51 12 94",
    "sg:province":"Haute Normandie",
    "wof:name":"Euraubat S.a.r.l.",
    "wof:placetype":"venue"
},
  "geometry": {"coordinates":[-89.949692,37.879566],"type":"Point"}
}