{
  "type": "Feature",
  "properties": {
    "iso:country":"FR",
    "sg:address":"All\u00e9e Mouesca - ZAC Redon",
    "sg:city":"Anglet",
    "sg:orig_category":"Unclassifiable Establishments",
    "sg:phone":"+33 5 59 58 09 00",
    "sg:postcode":"64600",
    "sg:province":"Aquitaine",
    "wof:name":"A.c.k. S.a.",
    "wof:placetype":"venue"
},
  "geometry": {"coordinates":[-1.514707,43.481705],"type":"Point"}
}