{
  "type": "Feature",
  "properties": {
    "iso:country":"FR",
    "sg:address":"Z.I. Riante Borie",
    "sg:city":"Malemort sur Corr\u00e8ze",
    "sg:orig_category":"Unclassifiable Establishments",
    "sg:phone":"+33 5 55 92 36 70",
    "sg:postcode":"19360",
    "sg:province":"Limousin",
    "wof:name":"Lachaise S.a.",
    "wof:placetype":"venue"
},
  "geometry": {"coordinates":[1.585306,45.135616],"type":"Point"}
}