{
  "type": "Feature",
  "properties": {
    "addr:full":"Rte de Lezoux Orl\u00e9at Auvergne 63190",
    "addr:postcode":"63190",
    "addr:street":"Rte De Lezoux",
    "iso:country":"FR",
    "sg:address":"Rte de Lezoux",
    "sg:city":"Orl\u00e9at",
    "sg:orig_category":"Unclassifiable Establishments",
    "sg:phone":"+33 4 73 53 61 06",
    "sg:postcode":"63190",
    "sg:province":"Auvergne",
    "wof:name":"Debarges S.a.r.l.",
    "wof:placetype":"venue"
},
  "geometry": {"coordinates":[3.422805,45.862419],"type":"Point"}
}