{
  "type": "Feature",
  "properties": {
    "addr:full":"Rte De Bacqueville 76560 St Laurent En Caux Haute Normandie",
    "addr:postcode":"76560",
    "addr:street":"Rte De Bacqueville;St Laurent En Caux Haute Normandie",
    "iso:country":"FR",
    "sg:address":"Rte De Bacqueville 76560 St Laurent En Caux",
    "sg:classifiers":[
        {
            "category":"Manufacturing",
            "subcategory":"Rubber & Plastics",
            "type":"Manufacturing & Wholesale Goods"
        }
    ],
    "sg:phone":"+33 2 35 96 51 03",
    "sg:province":"Haute Normandie",
    "wof:name":"Maletras Thermoformage Sa",
    "wof:placetype":"venue"
},
  "geometry": {"coordinates":[0.81018,49.689823],"type":"Point"}
}