{
  "type": "Feature",
  "properties": {
    "iso:country":"FR",
    "sg:address":"1 rue Gay Lussac 25000 Besancon",
    "sg:classifiers":[
        {
            "category":"Banks & Credit Unions",
            "subcategory":"Investment Brokerage",
            "type":"Services"
        }
    ],
    "sg:phone":"+33 3 81 50 23 87",
    "sg:province":"Franche Comt\u00e9",
    "sg:tags":[
        "repair",
        "watch",
        "clock"
    ],
    "wof:name":"Ste Reparalux Sa",
    "wof:placetype":"venue"
},
  "geometry": {"coordinates":[5.989174,47.237965],"type":"Point"}
}