{
  "type": "Feature",
  "properties": {
    "addr:full":"46/48, Rue Gay Lussac, 94430 Chennevi\u00e8res sur Marne Ile de France",
    "addr:housenumber":"46 / 48",
    "addr:postcode":"94430",
    "addr:street":"Rue Gay Lussac",
    "iso:country":"FR",
    "sg:address":"46/48, Rue Gay Lussac, 94430 Chennevi\u00e8res sur Marne",
    "sg:orig_category":"Unclassifiable Establishments",
    "sg:phone":"+33 1 49 62 13 85",
    "sg:province":"Ile de France",
    "wof:name":"Etirex Chromalox S.a.",
    "wof:placetype":"venue"
},
  "geometry": {"coordinates":[2.545279,48.793247],"type":"Point"}
}