{
  "type": "Feature",
  "properties": {
    "addr:full":"Place Voltaire BP 142 19200 Ussel Limousin 19200",
    "addr:housenumber":"142",
    "addr:postcode":"19200;19200",
    "addr:street":"Place Voltaire Bp",
    "iso:country":"FR",
    "sg:address":"Place Voltaire BP 142 19200 Ussel",
    "sg:classifiers":[
        {
            "category":"Professional",
            "subcategory":"Business Services",
            "type":"Services"
        }
    ],
    "sg:phone":"+33 5 55 94 10 00",
    "sg:postcode":"19200",
    "sg:province":"Limousin",
    "sg:tags":[
        "training",
        "advice"
    ],
    "wof:name":"Coll\u00c9ge Plage Volt\u00c9re",
    "wof:placetype":"venue"
},
  "geometry": {"coordinates":[2.30775,45.546101],"type":"Point"}
}