{
  "type": "Feature",
  "properties": {
    "iso:country":"FR",
    "sg:address":"18, Bd Richaud, 13500 Martigues",
    "sg:orig_category":"Unclassifiable Establishments",
    "sg:phone":"+33 4 42 07 22 92",
    "sg:province":"Provence-Alpes-C\u00f4te d'Azur",
    "wof:name":"Adia France S.a.",
    "wof:placetype":"venue"
},
  "geometry": {"coordinates":[5.053714,43.403713],"type":"Point"}
}