{
  "type": "Feature",
  "properties": {
    "addr:full":"61 chemin du Vieux Ch\u00eane 38240 Meylan Rhone-Alpes",
    "addr:housenumber":"61",
    "addr:postcode":"38240",
    "addr:street":"Chemin Du Vieux Che\u0302Ne",
    "iso:country":"FR",
    "sg:address":"61 chemin du Vieux Ch\u00eane 38240 Meylan",
    "sg:orig_category":"Split Optics",
    "sg:phone":"+33 4 76 04 05 06",
    "sg:province":"Rhone-Alpes",
    "wof:name":"Teem Photonics S.a.r.l.",
    "wof:placetype":"venue"
},
  "geometry": {"coordinates":[5.797536,45.208698],"type":"Point"}
}