{
  "type": "Feature",
  "properties": {
    "iso:country":"FR",
    "sg:address":"Rte De Samoens 74440 Taninges",
    "sg:classifiers":[
        {
            "category":"Home & Garden",
            "subcategory":"Furniture",
            "type":"Retail Goods"
        }
    ],
    "sg:phone":"+33 4 50 34 25 88",
    "sg:postcode":"74440",
    "sg:province":"Rhone-Alpes",
    "sg:tags":[
        "household",
        "wood"
    ],
    "wof:name":"Meubles Les Fontaines",
    "wof:placetype":"venue"
},
  "geometry": {"coordinates":[6.669727,46.067295],"type":"Point"}
}