{
  "type": "Feature",
  "properties": {
    "iso:country":"FR",
    "sg:address":"Route De La Clastre 26400 Aouste Sur Sye",
    "sg:classifiers":[
        {
            "category":"Professional",
            "type":"Services"
        }
    ],
    "sg:phone":"+33 4 75 25 56 00",
    "sg:province":"Rhone-Alpes",
    "sg:tags":[
        "transport",
        "road"
    ],
    "wof:name":"Transports Perrenot",
    "wof:placetype":"venue"
},
  "geometry": {"coordinates":[5.084799,44.623848],"type":"Point"}
}