{
  "type": "Feature",
  "properties": {
    "iso:country":"FR",
    "sg:address":"56 Rte Les Pouli\u00e8res 88600 La Chapelle Devant Bruy\u00e8res",
    "sg:classifiers":[
        {
            "category":"Shopping",
            "subcategory":"Crafts & Fabrics",
            "type":"Retail Goods"
        }
    ],
    "sg:phone":"+33 3 29 58 59 77",
    "sg:postcode":"88600",
    "sg:province":"Lorraine",
    "sg:tags":[
        "textile",
        "clothing"
    ],
    "wof:name":"Yeramex International Sa",
    "wof:placetype":"venue"
},
  "geometry": {"coordinates":[6.65109,48.168644],"type":"Point"}
}