{
  "type": "Feature",
  "properties": {
    "addr:full":"Zone Bertholet Duni\u00e8res Auvergne 43220",
    "addr:postcode":"43220",
    "addr:street":"Dunie\u0300Res",
    "iso:country":"FR",
    "sg:address":"Zone Bertholet",
    "sg:city":"Duni\u00e8res",
    "sg:orig_category":"Unclassifiable Establishments",
    "sg:phone":"+33 4 71 66 85 98",
    "sg:postcode":"43220",
    "sg:province":"Auvergne",
    "wof:name":"Nergeco S.a.",
    "wof:placetype":"venue"
},
  "geometry": {"coordinates":[4.343615,45.216541],"type":"Point"}
}