{
  "type": "Feature",
  "properties": {
    "addr:full":"1, Av. Adolphe Max, 69005 Lyon Rhone-Alpes",
    "addr:postcode":"69005",
    "addr:street":"Av. Adolphe Max",
    "iso:country":"FR",
    "sg:address":"1, Av. Adolphe Max, 69005 Lyon",
    "sg:orig_category":"Unclassifiable Establishments",
    "sg:phone":"+33 4 78 37 96 16",
    "sg:province":"Rhone-Alpes",
    "wof:name":"Charlestown S.a.",
    "wof:placetype":"venue"
},
  "geometry": {"coordinates":[4.82738,45.759789],"type":"Point"}
}