{
  "type": "Feature",
  "properties": {
    "iso:country":"FR",
    "sg:address":"12 av Auguste Renoir; Cagnes sur Mer",
    "sg:classifiers":[
        {
            "category":"Banks & Credit Unions",
            "subcategory":"Bank",
            "type":"Services"
        }
    ],
    "sg:phone":"+33 3393206464",
    "sg:province":"Centre",
    "wof:name":"Cr\u00e9dit Agricole Des Alpes Maritimes",
    "wof:placetype":"venue"
},
  "geometry": {"coordinates":[7.14976,43.662769],"type":"Point"}
}