{
  "type": "Feature",
  "properties": {
    "addr:full":"Saint Caprais 31330 Grenade Midi Pyr\u00e9n\u00e9es",
    "addr:postcode":"31330",
    "iso:country":"FR",
    "sg:address":"Saint Caprais 31330 Grenade",
    "sg:orig_category":"Unclassifiable Establishments",
    "sg:phone":"+33 5 62 22 08 90",
    "sg:province":"Midi Pyr\u00e9n\u00e9es",
    "wof:name":"Rossi-a\u00e9ro-equipements S.a.",
    "wof:placetype":"venue"
},
  "geometry": {"coordinates":[1.33612,43.758961],"type":"Point"}
}