{
  "type": "Feature",
  "properties": {
    "addr:full":"ZI des Quatre Vents Nord Beaumont Hague Basse Normandie 50440",
    "addr:postcode":"50440",
    "addr:street":"Des Quatre Vents Nord",
    "iso:country":"FR",
    "sg:address":"ZI des Quatre Vents Nord",
    "sg:city":"Beaumont Hague",
    "sg:orig_category":"Unclassifiable Establishments",
    "sg:phone":"+33 2 33 08 40 51",
    "sg:postcode":"50440",
    "sg:province":"Basse Normandie",
    "wof:name":"B.e.e. S.a.r.l. - Bureau Etude Etasse",
    "wof:placetype":"venue"
},
  "geometry": {"coordinates":[-1.836334,49.663555],"type":"Point"}
}