{
  "type": "Feature",
  "properties": {
    "iso:country":"FR",
    "sg:address":"3, Rue Jean-Jacques Rousseau, 62290 Noeux les Mines",
    "sg:orig_category":"Non-Classified Establishments",
    "sg:phone":"+33 3 21 61 47 97",
    "sg:postcode":"62290",
    "sg:province":"Nord Pas-de-Calais",
    "wof:name":"A.n.p.e.",
    "wof:placetype":"venue"
},
  "geometry": {"coordinates":[2.669149,50.471256],"type":"Point"}
}