{
  "type": "Feature",
  "properties": {
    "addr:full":"Le Pigeon Blanc 130 Rue De Nantes 44119 Treilli\u00e8res Pays de Loire 44119",
    "addr:housenumber":"130",
    "addr:postcode":"44119;44119",
    "addr:street":"Rue De Nantes",
    "iso:country":"FR",
    "sg:address":"Le Pigeon Blanc 130 Rue De Nantes 44119 Treilli\u00e8res",
    "sg:classifiers":[
        {
            "category":"Manufacturing",
            "subcategory":"Metals",
            "type":"Manufacturing & Wholesale Goods"
        }
    ],
    "sg:phone":"+33 2 40 94 56 45",
    "sg:postcode":"44119",
    "sg:province":"Pays de Loire",
    "sg:tags":[
        "metallurgy",
        "metalworking",
        "processing"
    ],
    "wof:name":"Rocametal Sarl",
    "wof:placetype":"venue"
},
  "geometry": {"coordinates":[-1.622475,47.330029],"type":"Point"}
}