{
  "type": "Feature",
  "properties": {
    "iso:country":"FR",
    "sg:address":"Rte De Troyes Zi 51120 S\u00e9zanne",
    "sg:classifiers":[
        {
            "category":"Wholesale",
            "subcategory":"Machinery & Supplies",
            "type":"Manufacturing & Wholesale Goods"
        }
    ],
    "sg:phone":"+33 3 26 80 76 76",
    "sg:postcode":"51120",
    "sg:province":"Champagne",
    "sg:tags":[
        "handling",
        "material",
        "-",
        "machine",
        "equipment",
        "engineering",
        "mechanical"
    ],
    "wof:name":"Feralco Sa",
    "wof:placetype":"venue"
},
  "geometry": {"coordinates":[3.718915,48.72324],"type":"Point"}
}