{
  "type": "Feature",
  "properties": {
    "addr:full":"28, Rte de Pathernay, 86000 Poitiers Poitou-Charentes 86000",
    "addr:housenumber":"28",
    "addr:postcode":"86000;86000",
    "addr:street":"Rte De Pathernay",
    "iso:country":"FR",
    "sg:address":"28, Rte de Pathernay, 86000 Poitiers",
    "sg:orig_category":"Non-Classified Establishments",
    "sg:phone":"+33 5 49 58 50 57",
    "sg:postcode":"86000",
    "sg:province":"Poitou-Charentes",
    "wof:name":"Etablissement Jacquet S.a.r.l.",
    "wof:placetype":"venue"
},
  "geometry": {"coordinates":[0.34169,46.58057],"type":"Point"}
}