{
  "type": "Feature",
  "properties": {
    "iso:country":"FR",
    "sg:address":"B.P. 57, 94222 Charenton le Pont C\u00e9dex^^24, Rue du Cadran, 94220 Charenton le Pont",
    "sg:orig_category":"Non-Classified Establishments",
    "sg:phone":"+33 1 43 53 55 55",
    "sg:province":"Ile de France",
    "wof:name":"S.i.p.l.a.n.s. S.a.r.l.",
    "wof:placetype":"venue"
},
  "geometry": {"coordinates":[2.41364,48.821571],"type":"Point"}
}