{
  "type": "Feature",
  "properties": {
    "addr:full":"13 Rue Bois Fleuri 44118 La Chevroli\u00e8re Pays de Loire 44118",
    "addr:housenumber":"13",
    "addr:postcode":"44118;44118",
    "addr:street":"Rue Bois Fleuri;Chevrolie\u0300Re",
    "iso:country":"FR",
    "sg:address":"13 Rue Bois Fleuri 44118 La Chevroli\u00e8re",
    "sg:classifiers":[
        {
            "category":"Shopping",
            "type":"Retail Goods"
        }
    ],
    "sg:phone":"+33 2 40 04 31 01",
    "sg:postcode":"44118",
    "sg:province":"Pays de Loire",
    "sg:tags":[
        "metallurgy",
        "finished",
        "-",
        "metalworking",
        "metallic"
    ],
    "wof:name":"Gtim",
    "wof:placetype":"venue"
},
  "geometry": {"coordinates":[-1.597254,47.102051],"type":"Point"}
}