{
  "type": "Feature",
  "properties": {
    "iso:country":"FR",
    "sg:address":"rue de la Valserine 01200 Confort",
    "sg:classifiers":[
        {
            "category":"Government",
            "subcategory":"Department Of Motor Vehicles",
            "type":"Public Place"
        }
    ],
    "sg:phone":"+33 4 50 56 51 16",
    "sg:postcode":"01200",
    "sg:province":"Rhone-Alpes",
    "sg:tags":[
        "engine"
    ],
    "wof:name":"Altiplast S.a.",
    "wof:placetype":"venue"
},
  "geometry": {"coordinates":[5.822198,46.151356],"type":"Point"}
}