{
  "type": "Feature",
  "properties": {
    "addr:full":"8, Rte de Stains, 94380 Bonneuil sur Marne Ile de France",
    "addr:housenumber":"8",
    "addr:postcode":"94380",
    "addr:street":"Rte De Stains",
    "iso:country":"FR",
    "sg:address":"8, Rte de Stains, 94380 Bonneuil sur Marne",
    "sg:orig_category":"Unclassifiable Establishments",
    "sg:phone":"+33 1 45 13 44 20",
    "sg:province":"Ile de France",
    "wof:name":"Cofrafer S.a.",
    "wof:placetype":"venue"
},
  "geometry": {"coordinates":[2.49427,48.781189],"type":"Point"}
}