{
  "type": "Feature",
  "properties": {
    "addr:full":"4, Impasse des Granges, 38290 La Verpilli\u00e8re Rhone-Alpes 38290",
    "addr:housenumber":"4",
    "addr:postcode":"38290;38290",
    "addr:street":"Impasse Des Granges;Verpillie\u0300Re Rhone-Alpes",
    "iso:country":"FR",
    "sg:address":"4, Impasse des Granges, 38290 La Verpilli\u00e8re",
    "sg:orig_category":"Non-Classified Establishments",
    "sg:phone":"+33 4 74 94 50 05",
    "sg:postcode":"38290",
    "sg:province":"Rhone-Alpes",
    "wof:name":"Egger Pompes Turo S.a.r.l.",
    "wof:placetype":"venue"
},
  "geometry": {"coordinates":[5.135958,45.643791],"type":"Point"}
}