{
  "type": "Feature",
  "properties": {
    "iso:country":"FR",
    "sg:address":"Terre Plein Port 29100 Douarnenez",
    "sg:city":"Douarnenez",
    "sg:classifiers":[
        {
            "category":"Farming",
            "subcategory":"Livestock Farm",
            "type":"Manufacturing & Wholesale Goods"
        }
    ],
    "sg:phone":"+33 2 98 92 42 55",
    "sg:postcode":"29100",
    "sg:province":"Bretagne",
    "sg:tags":[
        "breeding",
        "agriculture",
        "animal"
    ],
    "wof:name":"Ansel Et Cie Sa",
    "wof:placetype":"venue"
},
  "geometry": {"coordinates":[-4.341404,48.095181],"type":"Point"}
}