{
  "type": "Feature",
  "properties": {
    "addr:full":"46 Quai Alphonse Le Gallo 92648 Boulogne Billancourt Cedex Ancourt Haute Normandie 76370",
    "addr:housenumber":"46",
    "addr:postcode":"92648;76370",
    "addr:street":"Quai Alphonse Le Gallo;Haute Normandie",
    "iso:country":"FR",
    "sg:address":"46 Quai Alphonse Le Gallo 92648 Boulogne Billancourt Cedex",
    "sg:city":"Ancourt",
    "sg:classifiers":[
        {
            "category":"Professional",
            "subcategory":"Advertising",
            "type":"Services"
        }
    ],
    "sg:phone":"+33 1 55 19 44 00",
    "sg:postcode":"76370",
    "sg:province":"Haute Normandie",
    "sg:tags":[
        "communication",
        "medium"
    ],
    "wof:name":"Publicis Dialog",
    "wof:placetype":"venue"
},
  "geometry": {"coordinates":[2.223746,48.837807],"type":"Point"}
}