{
  "type": "Feature",
  "properties": {
    "iso:country":"FR",
    "sg:address":"1, Rue Jean Monnet, 86100 Chatellerault",
    "sg:orig_category":"Unclassifiable Establishments",
    "sg:phone":"+33 5 49 93 58 00",
    "sg:province":"Poitou-Charentes",
    "wof:name":"Ites",
    "wof:placetype":"venue"
},
  "geometry": {"coordinates":[0.534278,46.812702],"type":"Point"}
}