{
  "type": "Feature",
  "properties": {
    "addr:full":"106 Rue Du Bac 75007 Paris Ile de France 75007",
    "addr:housenumber":"106",
    "addr:postcode":"75007;75007",
    "addr:street":"Rue Du Bac",
    "iso:country":"FR",
    "sg:address":"106 Rue Du Bac 75007 Paris",
    "sg:classifiers":[
        {
            "category":"Professional",
            "subcategory":"Business Services",
            "type":"Services"
        }
    ],
    "sg:phone":"+33 1 45 49 73 00",
    "sg:postcode":"75007",
    "sg:province":"Ile de France",
    "sg:tags":[
        "body",
        "advice"
    ],
    "wof:name":"Secours Catholique",
    "wof:placetype":"venue"
},
  "geometry": {"coordinates":[2.32358,48.852577],"type":"Point"}
}