{
  "type": "Feature",
  "properties": {
    "iso:country":"FR",
    "sg:address":"RN 31",
    "sg:city":"Montigny Lengrain",
    "sg:orig_category":"Unclassifiable Establishments",
    "sg:phone":"+33 3 23 55 44 33",
    "sg:postcode":"02290",
    "sg:province":"Picardie",
    "wof:name":"Vico S.a.",
    "wof:placetype":"venue"
},
  "geometry": {"coordinates":[3.16768,49.407619],"type":"Point"}
}