{
  "type": "Feature",
  "properties": {
    "addr:full":"85, Rue de Bagnolet, 75020 Paris Ile de France",
    "addr:housenumber":"85",
    "addr:postcode":"75020",
    "addr:street":"Rue De Bagnolet",
    "iso:country":"FR",
    "sg:address":"85, Rue de Bagnolet, 75020 Paris",
    "sg:orig_category":"Unclassifiable Establishments",
    "sg:phone":"+33 1 43 70 52 73",
    "sg:province":"Ile de France",
    "wof:name":"Etablissement Botterman",
    "wof:placetype":"venue"
},
  "geometry": {"coordinates":[2.400917,48.858624],"type":"Point"}
}