{
  "type": "Feature",
  "properties": {
    "addr:full":"11, Rue Rontgen, 29000 Quimper Quimper Bretagne 29000",
    "addr:housenumber":"11",
    "addr:postcode":"29000;29000",
    "addr:street":"Rue Rontgen",
    "iso:country":"FR",
    "sg:address":"11, Rue Rontgen, 29000 Quimper",
    "sg:city":"Quimper",
    "sg:orig_category":"Unclassifiable Establishments",
    "sg:phone":"+33 2 98 53 54 55",
    "sg:postcode":"29000",
    "sg:province":"Bretagne",
    "wof:name":"Girex S.a.",
    "wof:placetype":"venue"
},
  "geometry": {"coordinates":[-4.14472,48.002468],"type":"Point"}
}