{
  "type": "Feature",
  "properties": {
    "iso:country":"FR",
    "sg:address":"3 Rue Heilmann 68800 Vieux Thann",
    "sg:city":"Thann",
    "sg:classifiers":[
        {
            "category":"Shopping",
            "type":"Retail Goods"
        }
    ],
    "sg:phone":"+33 3 89 37 33 75",
    "sg:postcode":"68800",
    "sg:province":"Alsace",
    "sg:tags":[
        "metallurgy",
        "finished",
        "-",
        "metalworking",
        "metallic"
    ],
    "wof:name":"Metallerie Christen Freres",
    "wof:placetype":"venue"
},
  "geometry": {"coordinates":[7.133555,47.8022],"type":"Point"}
}