{
  "type": "Feature",
  "properties": {
    "iso:country":"FR",
    "sg:address":"1-9 Av Du Gal De Gaulle Imm Le Pascal-C C Creteil 94007 Creteil Cedex",
    "sg:classifiers":[
        {
            "category":"Banks & Credit Unions",
            "subcategory":"Financial Services",
            "type":"Services"
        }
    ],
    "sg:phone":"+33 810 40 44 04",
    "sg:province":"Pays de Loire",
    "sg:tags":[
        "banking",
        "finance",
        "insurance"
    ],
    "wof:name":"La Mondiale",
    "wof:placetype":"venue"
},
  "geometry": {"coordinates":[2.455115,48.777866],"type":"Point"}
}