{
  "type": "Feature",
  "properties": {
    "addr:full":"2, Cours Monseigneur Rom\u00e9ro, 91000 Evry Ile de France",
    "addr:housenumber":"2",
    "addr:postcode":"91000",
    "addr:street":"Cours Monseigneur Rome\u0301Ro",
    "iso:country":"FR",
    "sg:address":"2, Cours Monseigneur Rom\u00e9ro, 91000 Evry",
    "sg:orig_category":"Unclassifiable Establishments",
    "sg:phone":"+33 1 60 87 19 31",
    "sg:province":"Ile de France",
    "wof:name":"Coface",
    "wof:placetype":"venue"
},
  "geometry": {"coordinates":[2.430578,48.624428],"type":"Point"}
}