{
  "type": "Feature",
  "properties": {
    "iso:country":"FR",
    "sg:address":"12, Rue Pasteur, 03200 Abrest",
    "sg:city":"Abrest",
    "sg:orig_category":"Non-Classified Establishments",
    "sg:phone":"+33 4 70 97 41 55",
    "sg:postcode":"03200",
    "sg:province":"Auvergne",
    "wof:name":"Rosetti Transports S.a.r.l.",
    "wof:placetype":"venue"
},
  "geometry": {"coordinates":[3.433045,46.122326],"type":"Point"}
}