{
  "type": "Feature",
  "properties": {
    "addr:full":"12, Rue Pasteur, 03200 Abrest Abrest Auvergne 03200",
    "addr:housenumber":"12",
    "addr:postcode":"03200;03200",
    "addr:street":"Rue Pasteur",
    "iso:country":"FR",
    "sg:address":"12, Rue Pasteur, 03200 Abrest",
    "sg:city":"Abrest",
    "sg:orig_category":"Non-Classified Establishments",
    "sg:phone":"+33 4 70 97 41 55",
    "sg:postcode":"03200",
    "sg:province":"Auvergne",
    "wof:name":"Rosetti Transports S.a.r.l.",
    "wof:placetype":"venue"
},
  "geometry": {"coordinates":[3.433045,46.122326],"type":"Point"}
}