{
  "type": "Feature",
  "properties": {
    "iso:country":"FR",
    "sg:address":"1025, Rte de Civrieux, 01600 Massieux",
    "sg:orig_category":"Non-Classified Establishments",
    "sg:phone":"+33 4 78 98 06 39",
    "sg:postcode":"01600",
    "sg:province":"Rhone-Alpes",
    "wof:name":"J.c. D\u00e9co",
    "wof:placetype":"venue"
},
  "geometry": {"coordinates":[4.837361,45.910183],"type":"Point"}
}