{
  "type": "Feature",
  "properties": {
    "iso:country":"FR",
    "sg:address":"R Du Prof Andr\u00e9 Lavignolle Mini Parc",
    "sg:city":"Bordeaux",
    "sg:classifiers":[
        {
            "category":"Wholesale",
            "subcategory":"Medical Equipment & Supplies",
            "type":"Manufacturing & Wholesale Goods"
        }
    ],
    "sg:phone":"+33 5 56 69 24 60",
    "sg:postcode":"33300",
    "sg:province":"Aquitaine",
    "sg:tags":[
        "instrument",
        "health",
        "-",
        "precision"
    ],
    "wof:name":"Getinge Sas",
    "wof:placetype":"venue"
},
  "geometry": {"coordinates":[-0.568844,44.88448],"type":"Point"}
}