{
  "type": "Feature",
  "properties": {
    "addr:full":"14 rue Francine Fromont 69120 Vaulx en Velin Rhone-Alpes 69120",
    "addr:housenumber":"14",
    "addr:postcode":"69120;69120",
    "addr:street":"Rue Francine",
    "iso:country":"FR",
    "sg:address":"14 rue Francine Fromont 69120 Vaulx en Velin",
    "sg:orig_category":"Inductances, Fixed",
    "sg:phone":"+33 4 78 79 50 20",
    "sg:postcode":"69120",
    "sg:province":"Rhone-Alpes",
    "wof:name":"Boige Et Vignal Sa",
    "wof:placetype":"venue"
},
  "geometry": {"coordinates":[4.937259,45.777828],"type":"Point"}
}