{
  "type": "Feature",
  "properties": {
    "addr:full":"chemin du Fau 63309 THIERS Franche Comt\u00e9",
    "addr:postcode":"63309",
    "addr:street":"Chemin Du Fau;Franche Comte\u0301",
    "iso:country":"FR",
    "sg:address":"chemin du Fau 63309 THIERS",
    "sg:classifiers":[
        {
            "category":"Organizations",
            "subcategory":"Labor Organization",
            "type":"Services"
        }
    ],
    "sg:phone":"+33 4 73 80 10 46",
    "sg:province":"Franche Comt\u00e9",
    "sg:tags":[
        "work",
        "industrial",
        "forging"
    ],
    "wof:name":"Forges Et Plastiques Pinay Sas",
    "wof:placetype":"venue"
},
  "geometry": {"coordinates":[3.513349,45.855175],"type":"Point"}
}