{
  "type": "Feature",
  "properties": {
    "iso:country":"FR",
    "sg:address":"B.P. 19, 95240 Cormeilles en Parisis C\u00e9dex^^59, Bd Cl\u00e9menceau, 95240 Cormeilles en Parisis",
    "sg:orig_category":"Non-Classified Establishments",
    "sg:phone":"+33 1 39 78 26 31",
    "sg:postcode":"95240",
    "sg:province":"Ile de France",
    "wof:name":"D.e.r.f.i. S.a. - D\u00e9sign Equipements Repr\u00e9sentation France International",
    "wof:placetype":"venue"
},
  "geometry": {"coordinates":[2.199898,48.976402],"type":"Point"}
}