{
  "type": "Feature",
  "properties": {
    "addr:full":"27, Rue Andr\u00e9 Theuriet, 55000 Bar le Duc Lorraine 55000",
    "addr:housenumber":"27",
    "addr:postcode":"55000;55000",
    "addr:street":"Rue Andre\u0301 Theuriet;Le Duc Lorraine",
    "iso:country":"FR",
    "sg:address":"27, Rue Andr\u00e9 Theuriet, 55000 Bar le Duc",
    "sg:orig_category":"Non-Classified Establishments",
    "sg:phone":"+33 3 29 45 44 44",
    "sg:postcode":"55000",
    "sg:province":"Lorraine",
    "wof:name":"Agire S\u00e9rigraphie S.a.r.l.",
    "wof:placetype":"venue"
},
  "geometry": {"coordinates":[5.165118,48.773205],"type":"Point"}
}