{
  "type": "Feature",
  "properties": {
    "iso:country":"FR",
    "sg:address":"chemin de Silvange 57280 Maizieres les Metz",
    "sg:classifiers":[
        {
            "category":"Utilities",
            "subcategory":"Natural Gas",
            "type":"Services"
        }
    ],
    "sg:phone":"+33 3 87 80 24 25",
    "sg:province":"Lorraine",
    "sg:tags":[
        "mechanics",
        "precision"
    ],
    "wof:name":"Soudure Mecanique Industrielle S.a.",
    "wof:placetype":"venue"
},
  "geometry": {"coordinates":[6.157788,49.215256],"type":"Point"}
}