{
  "type": "Feature",
  "properties": {
    "addr:full":"3, Rte de Belfort, 70200 Lure Franche Comt\u00e9",
    "addr:housenumber":"3",
    "addr:postcode":"70200",
    "addr:street":"Rte De Belfort;Franche Comte\u0301",
    "iso:country":"FR",
    "sg:address":"3, Rte de Belfort, 70200 Lure",
    "sg:orig_category":"Unclassifiable Establishments",
    "sg:phone":"+33 3 84 30 19 56",
    "sg:province":"Franche Comt\u00e9",
    "wof:name":"Tissage De Lure S.a.r.l.",
    "wof:placetype":"venue"
},
  "geometry": {"coordinates":[6.520883,47.675129],"type":"Point"}
}