{
  "type": "Feature",
  "properties": {
    "addr:full":"ZI de la Gu\u00e9naudi\u00e8re Foug\u00e8res Bretagne 35300",
    "addr:postcode":"35300",
    "addr:street":"Zi De La Gue\u0301Naudie\u0300Re Fouge\u0300Res",
    "iso:country":"FR",
    "sg:address":"ZI de la Gu\u00e9naudi\u00e8re",
    "sg:city":"Foug\u00e8res",
    "sg:orig_category":"Non-Classified Establishments",
    "sg:phone":"+33 2 99 94 32 62",
    "sg:postcode":"35300",
    "sg:province":"Bretagne",
    "wof:name":"Soprofame S.a.r.l.",
    "wof:placetype":"venue"
},
  "geometry": {"coordinates":[-1.200204,48.35429],"type":"Point"}
}