{
  "type": "Feature",
  "properties": {
    "addr:full":"B.P. 106, 69591 L'Arbresle C\u00e9dex^^Rte de la Chanade - ZI de la Ponchonni\u00e8re, 69210 Savigny Rhone-Alpes",
    "addr:housenumber":"b.p. 106",
    "addr:postcode":"69591;69210",
    "addr:street":"Zi De La Ponchonnie\u0300Re",
    "iso:country":"FR",
    "sg:address":"B.P. 106, 69591 L'Arbresle C\u00e9dex^^Rte de la Chanade - ZI de la Ponchonni\u00e8re, 69210 Savigny",
    "sg:orig_category":"Non-Classified Establishments",
    "sg:phone":"+33 4 74 01 60 00",
    "sg:province":"Rhone-Alpes",
    "wof:name":"S.m.a.d. S.a.",
    "wof:placetype":"venue"
},
  "geometry": {"coordinates":[4.588778,45.82164],"type":"Point"}
}