{
  "type": "Feature",
  "properties": {
    "addr:full":"182 Quai George 5 Ccal 76600 Le Havre Haute Normandie 76600",
    "addr:housenumber":"182;5",
    "addr:postcode":"76600;76600",
    "addr:street":"Quai George",
    "iso:country":"FR",
    "sg:address":"182 Quai George 5 Ccal 76600 Le Havre",
    "sg:classifiers":[
        {
            "category":"Banks & Credit Unions",
            "subcategory":"Financial Services",
            "type":"Services"
        }
    ],
    "sg:phone":"+33 2 32 74 08 00",
    "sg:postcode":"76600",
    "sg:province":"Haute Normandie",
    "sg:tags":[
        "banking",
        "finance",
        "insurance"
    ],
    "wof:name":"Assurances Generales De France Vie (agf Vie) Agf Vie",
    "wof:placetype":"venue"
},
  "geometry": {"coordinates":[0.101405,49.493511],"type":"Point"}
}