{
  "type": "Feature",
  "properties": {
    "iso:country":"FR",
    "sg:address":"B.P. 317, 92107 Boulogne Billancourt C\u00e9dex^^55, Quai Alphonse le Gallo, 92100 Boulogne Billancourt",
    "sg:orig_category":"Non-Classified Establishments",
    "sg:phone":"+33 1 49 09 61 20",
    "sg:postcode":"92100",
    "sg:province":"Ile de France",
    "wof:name":"Comexpo Paris S.a.",
    "wof:placetype":"venue"
},
  "geometry": {"coordinates":[2.24102,48.835155],"type":"Point"}
}