{
  "type": "Feature",
  "properties": {
    "addr:full":"Rte d'Aspach Cernay Alsace 68700",
    "addr:postcode":"68700",
    "addr:street":"Rte D'Aspach Cernay",
    "iso:country":"FR",
    "sg:address":"Rte d'Aspach",
    "sg:city":"Cernay",
    "sg:orig_category":"Unclassifiable Establishments",
    "sg:phone":"+33 3 89 75 74 49",
    "sg:postcode":"68700",
    "sg:province":"Alsace",
    "wof:name":"G\u00e9ny Cernay S.c.e.a.",
    "wof:placetype":"venue"
},
  "geometry": {"coordinates":[7.13352,47.77692],"type":"Point"}
}