{
  "type": "Feature",
  "properties": {
    "addr:full":"443, Rue des Cordineaux, 69380 Dommartin Rhone-Alpes 69380",
    "addr:housenumber":"443",
    "addr:postcode":"69380;69380",
    "addr:street":"Rue Des Cordineaux",
    "iso:country":"FR",
    "sg:address":"443, Rue des Cordineaux, 69380 Dommartin",
    "sg:orig_category":"Unclassifiable Establishments",
    "sg:phone":"+33 4 78 43 51 95",
    "sg:postcode":"69380",
    "sg:province":"Rhone-Alpes",
    "wof:name":"Isolation Dommartinoise S.a.r.l.",
    "wof:placetype":"venue"
},
  "geometry": {"coordinates":[4.704456,45.830124],"type":"Point"}
}