{
  "type": "Feature",
  "properties": {
    "iso:country":"FR",
    "sg:address":"Zi De La Brassi\u00e8re 26240 Saint Vallier",
    "sg:classifiers":[
        {
            "category":"Shopping",
            "type":"Retail Goods"
        }
    ],
    "sg:phone":"+33 4 75 23 67 00",
    "sg:postcode":"26240",
    "sg:province":"Rhone-Alpes",
    "sg:tags":[
        "metallurgy",
        "finished",
        "-",
        "metalworking",
        "metallic"
    ],
    "wof:name":"Vanatome Sa",
    "wof:placetype":"venue"
},
  "geometry": {"coordinates":[4.817855,45.174755],"type":"Point"}
}