{
  "type": "Feature",
  "properties": {
    "addr:full":"8BIS rue du Lion d'Or 59497 LINSELLES CEDEX Nord-Pas-de-Calais",
    "addr:housenumber":"8bis",
    "addr:postcode":"59497;cedex",
    "addr:street":"Rue Du Lion D'Or",
    "iso:country":"FR",
    "sg:address":"8BIS rue du Lion d'Or 59497 LINSELLES CEDEX",
    "sg:classifiers":[
        {
            "category":"Building & Trades",
            "subcategory":"Landscaping Services",
            "type":"Services"
        }
    ],
    "sg:phone":"+33 3 20 23 13 13",
    "sg:province":"Nord-Pas-de-Calais",
    "sg:tags":[
        "sculpturing",
        "stone-carving"
    ],
    "wof:name":"Structure Marbre Sa",
    "wof:placetype":"venue"
},
  "geometry": {"coordinates":[3.074888,50.736271],"type":"Point"}
}