{
  "type": "Feature",
  "properties": {
    "addr:full":"B.P. 101, 02600 Villers Cotter\u00eats C\u00e9dex^^63, Av de la Fert\u00e9 Milon, 02600 Villers Cotter\u00eats Picardie",
    "addr:housenumber":"b.p. 101",
    "addr:postcode":"02600;02600",
    "addr:street":"Av De La Ferte\u0301 Milon",
    "iso:country":"FR",
    "sg:address":"B.P. 101, 02600 Villers Cotter\u00eats C\u00e9dex^^63, Av de la Fert\u00e9 Milon, 02600 Villers Cotter\u00eats",
    "sg:orig_category":"Non-Classified Establishments",
    "sg:phone":"+33 3 23 72 57 77",
    "sg:province":"Picardie",
    "wof:name":"Valois Fruits",
    "wof:placetype":"venue"
},
  "geometry": {"coordinates":[3.12171,49.269051],"type":"Point"}
}