{
  "type": "Feature",
  "properties": {
    "addr:full":"Cd 900 04530 Larche Limousin",
    "addr:housenumber":"cd 900",
    "addr:postcode":"04530",
    "iso:country":"FR",
    "sg:address":"Cd 900 04530 Larche",
    "sg:classifiers":[
        {
            "category":"Professional",
            "type":"Services"
        }
    ],
    "sg:phone":"+33 4 92 84 31 43",
    "sg:province":"Limousin",
    "sg:tags":[
        "transport"
    ],
    "wof:name":"Sdf Transit Palluel",
    "wof:placetype":"venue"
},
  "geometry": {"coordinates":[6.787682,44.477386],"type":"Point"}
}