{
  "type": "Feature",
  "properties": {
    "addr:full":"Avant Port Nord Poste 143 A Marseille Poitou-Charentes 13016",
    "addr:housenumber":"143",
    "addr:postcode":"13016",
    "addr:street":"A Marseille",
    "iso:country":"FR",
    "sg:address":"Avant Port Nord Poste 143 A",
    "sg:city":"Marseille",
    "sg:orig_category":"Unclassifiable Establishments",
    "sg:phone":"+33 4 91 09 58 88",
    "sg:postcode":"13016",
    "sg:province":"Poitou-Charentes",
    "wof:name":"Compagnie Navale Fran\u00e7aise",
    "wof:placetype":"venue"
},
  "geometry": {"coordinates":[5.321475,43.362785],"type":"Point"}
}