{
  "type": "Feature",
  "properties": {
    "addr:full":"B.P. 1182, 27950 Saint Marcel^^36, rue des Pr\u00e9s, 27950 Saint Marcel Haute Normandie",
    "addr:housenumber":"1182",
    "addr:postcode":"27950;27950",
    "addr:street":"B.P.;Rue Des Pre\u0301S;Marcel Haute Normandie",
    "iso:country":"FR",
    "sg:address":"B.P. 1182, 27950 Saint Marcel^^36, rue des Pr\u00e9s, 27950 Saint Marcel",
    "sg:orig_category":"Non-Classified Establishments",
    "sg:phone":"+33 2 32 21 25 08",
    "sg:province":"Haute Normandie",
    "wof:name":"Menuiserie Steurebaut S.a.r.l.",
    "wof:placetype":"venue"
},
  "geometry": {"coordinates":[1.452536,49.102634],"type":"Point"}
}