{
  "type": "Feature",
  "properties": {
    "addr:full":"8, Rue du Ch\u00e2let, 25140 Charquemont Franche Comt\u00e9 25140",
    "addr:housenumber":"8",
    "addr:postcode":"25140;25140",
    "addr:street":"Rue Du Cha\u0302Let;Franche Comte\u0301",
    "iso:country":"FR",
    "sg:address":"8, Rue du Ch\u00e2let, 25140 Charquemont",
    "sg:orig_category":"Non-Classified Establishments",
    "sg:phone":"+33 3 81 44 01 38",
    "sg:postcode":"25140",
    "sg:province":"Franche Comt\u00e9",
    "wof:name":"Coop\u00e9rative De Fromagerie",
    "wof:placetype":"venue"
},
  "geometry": {"coordinates":[6.825442,47.211407],"type":"Point"}
}