{
  "type": "Feature",
  "properties": {
    "addr:full":"B.P. 558, 93621 Aulnay sous Bois C\u00e9dex^^Garonor Tour D, 93620 Aulnay sous Bois Pays de Loire",
    "addr:housenumber":"b.p. 558",
    "addr:postcode":"93621;93620",
    "addr:street":"Sous Bois Pays",
    "iso:country":"FR",
    "sg:address":"B.P. 558, 93621 Aulnay sous Bois C\u00e9dex^^Garonor Tour D, 93620 Aulnay sous Bois",
    "sg:orig_category":"Non-Classified Establishments",
    "sg:phone":"+33 1 48 62 81 75",
    "sg:province":"Pays de Loire",
    "wof:name":"Avia Partener Cargo S.a.s.",
    "wof:placetype":"venue"
},
  "geometry": {"coordinates":[0.654042,44.715748],"type":"Point"}
}