{
  "type": "Feature",
  "properties": {
    "iso:country":"FR",
    "sg:address":"B.P. 14, 78373 Plaisir C\u00e9dex^^Av. de Dreux, 78370 Plaisir",
    "sg:orig_category":"Non-Classified Establishments",
    "sg:phone":"+33 1 30 81 77 77",
    "sg:province":"Ile de France",
    "wof:name":"Labor Hako S.a.",
    "wof:placetype":"venue"
},
  "geometry": {"coordinates":[1.949255,48.816689],"type":"Point"}
}