{
  "type": "Feature",
  "properties": {
    "addr:full":"8, Rue du Docteur Ramon, 37540 Saint Cyr sur Loire Saint-Cyr-sur-Loire Centre 37540",
    "addr:housenumber":"8",
    "addr:postcode":"37540;37540",
    "addr:street":"Rue Du Docteur Ramon;Cyr",
    "iso:country":"FR",
    "sg:address":"8, Rue du Docteur Ramon, 37540 Saint Cyr sur Loire",
    "sg:city":"Saint-Cyr-sur-Loire",
    "sg:orig_category":"Non-Classified Establishments",
    "sg:phone":"+33 2 47 51 08 55",
    "sg:postcode":"37540",
    "sg:province":"Centre",
    "wof:name":"Division Evolya",
    "wof:placetype":"venue"
},
  "geometry": {"coordinates":[0.673408,47.414349],"type":"Point"}
}