{
  "type": "Feature",
  "properties": {
    "addr:full":"Rue des Bosquets - ZAC Les Ponts de Baillet Baillet en France Ile de France 95560",
    "addr:postcode":"95560",
    "addr:street":"Rue Des Bosquets Zac Les Ponts De Baillet",
    "iso:country":"FR",
    "sg:address":"Rue des Bosquets - ZAC Les Ponts de Baillet",
    "sg:city":"Baillet en France",
    "sg:orig_category":"Non-Classified Establishments",
    "sg:phone":"+33 1 34 69 95 56",
    "sg:postcode":"95560",
    "sg:province":"Ile de France",
    "wof:name":"Ecodis S.a.",
    "wof:placetype":"venue"
},
  "geometry": {"coordinates":[2.309886,49.070625],"type":"Point"}
}