{
  "type": "Feature",
  "properties": {
    "addr:full":"Route Wardrecques Zi 59173 Blaringhem Nord Pas-de-Calais 59173",
    "addr:postcode":"59173;59173",
    "addr:street":"Route Wardrecques Zi",
    "iso:country":"FR",
    "sg:address":"Route Wardrecques Zi 59173 Blaringhem",
    "sg:orig_category":"Fabrics Paper and Cardboard Paper and cardboard - finished goods Textiles and Clothing",
    "sg:phone":"+33 3 28 43 91 00",
    "sg:postcode":"59173",
    "sg:province":"Nord Pas-de-Calais",
    "wof:name":"Plage Sa",
    "wof:placetype":"venue"
},
  "geometry": {"coordinates":[2.403063,50.692665],"type":"Point"}
}