{
  "type": "Feature",
  "properties": {
    "iso:country":"FR",
    "sg:address":"9, Rue de la Toscane - ZAC de la Berangerais, 44240 La Chapelle sur Erdre",
    "sg:orig_category":"Unclassifiable Establishments",
    "sg:phone":"+33 825 31 18 04",
    "sg:province":"Pays de Loire",
    "wof:name":"Creib Omr S.a.",
    "wof:placetype":"venue"
},
  "geometry": {"coordinates":[-1.536342,47.28133],"type":"Point"}
}