{
  "type": "Feature",
  "properties": {
    "iso:country":"FR",
    "sg:address":"B.P. CE 2308, 91923 Bondoufle Cedex^^20, Rue Henri Dunant - ZI des Bordes, 91070 Bondoufle",
    "sg:orig_category":"Non-Classified Establishments",
    "sg:phone":"+33 1 69 91 40 00",
    "sg:postcode":"91070",
    "sg:province":"Ile de France",
    "wof:name":"Anfa S.a.",
    "wof:placetype":"venue"
},
  "geometry": {"coordinates":[2.379516,48.615681],"type":"Point"}
}