{
  "type": "Feature",
  "properties": {
    "addr:full":"3, Av. Doyen Louis Weil - Immeuble Grenat, 38000 Grenoble Rhone-Alpes 38000",
    "addr:postcode":"38000;38000",
    "addr:street":"Av. Doyen Louis Weil;Grenat",
    "iso:country":"FR",
    "sg:address":"3, Av. Doyen Louis Weil - Immeuble Grenat, 38000 Grenoble",
    "sg:orig_category":"Unclassifiable Establishments",
    "sg:phone":"+33 4 76 84 27 40",
    "sg:postcode":"38000",
    "sg:province":"Rhone-Alpes",
    "wof:name":"I.d. 9 Prima S.a.",
    "wof:placetype":"venue"
},
  "geometry": {"coordinates":[5.711651,45.194164],"type":"Point"}
}