{
  "type": "Feature",
  "properties": {
    "addr:full":"Z.I. les Ports 82800 Negrepelisse Midi Pyr\u00e9n\u00e9es 82800",
    "addr:postcode":"82800;82800",
    "addr:street":"Z.I. Les Ports",
    "iso:country":"FR",
    "sg:address":"Z.I. les Ports 82800 Negrepelisse",
    "sg:classifiers":[
        {
            "category":"Wholesale",
            "subcategory":"Metals & Minerals",
            "type":"Manufacturing & Wholesale Goods"
        }
    ],
    "sg:phone":"+33 5 63 64 29 29",
    "sg:postcode":"82800",
    "sg:province":"Midi Pyr\u00e9n\u00e9es",
    "sg:tags":[
        "decoration",
        "article",
        "wood"
    ],
    "wof:name":"Newell Window Fashions France Sa",
    "wof:placetype":"venue"
},
  "geometry": {"coordinates":[1.641945,44.023071],"type":"Point"}
}