{
  "type": "Feature",
  "properties": {
    "addr:full":"Hameau Pr\u00e9s 27910 Perriers Sur Andelle Haute Normandie",
    "addr:postcode":"27910",
    "addr:street":"Hameau Pre\u0301S;Andelle Haute Normandie",
    "iso:country":"FR",
    "sg:address":"Hameau Pr\u00e9s 27910 Perriers Sur Andelle",
    "sg:classifiers":[
        {
            "category":"Professional",
            "type":"Services"
        }
    ],
    "sg:phone":"+33 2 32 49 24 53",
    "sg:province":"Haute Normandie",
    "sg:tags":[
        "transport",
        "road"
    ],
    "wof:name":"Ghesquiere Willy Benoit Nestor",
    "wof:placetype":"venue"
},
  "geometry": {"coordinates":[1.370516,49.412148],"type":"Point"}
}