{
  "type": "Feature",
  "properties": {
    "addr:full":"Avenue Victoire Zi 13106 Rousset Cedex Aquitaine",
    "addr:postcode":"13106",
    "addr:street":"Avenue Victoire Zi",
    "iso:country":"FR",
    "sg:address":"Avenue Victoire Zi 13106 Rousset Cedex",
    "sg:classifiers":[
        {
            "category":"Shopping",
            "subcategory":"Computers & Home Electronics",
            "type":"Retail Goods"
        }
    ],
    "sg:phone":"+33 4 42 29 13 00",
    "sg:province":"Aquitaine",
    "sg:tags":[
        "equipment",
        "electrical",
        "component",
        "electric",
        "electronic"
    ],
    "wof:name":"Dupont Photomasks France",
    "wof:placetype":"venue"
},
  "geometry": {"coordinates":[5.62164,43.48209],"type":"Point"}
}