{
  "type": "Feature",
  "properties": {
    "addr:full":"Rue Du Docteur Guerin Zone Industrielle 83210 La Farlede Nord Pas-de-Calais",
    "addr:postcode":"83210",
    "addr:street":"Rue Du Docteur Guerin Zone Industrielle;Farlede Nord",
    "iso:country":"FR",
    "sg:address":"Rue Du Docteur Guerin Zone Industrielle 83210 La Farlede",
    "sg:classifiers":[
        {
            "category":"Manufacturing",
            "subcategory":"Chemicals & Compounds",
            "type":"Manufacturing & Wholesale Goods"
        }
    ],
    "sg:phone":"+33 4 94 08 01 11",
    "sg:province":"Nord Pas-de-Calais",
    "sg:tags":[
        "pharmaceutical",
        "chemistry"
    ],
    "wof:name":"Precis",
    "wof:placetype":"venue"
},
  "geometry": {"coordinates":[6.042811,43.166992],"type":"Point"}
}