{
  "type": "Feature",
  "properties": {
    "addr:full":"Lyc\u00e9e Priv\u00e9 De La Sauque BP 20 33650 La Br\u00e8de La Br\u00e8de Aquitaine 33650",
    "addr:housenumber":"bp 20",
    "addr:postcode":"33650;33650",
    "iso:country":"FR",
    "sg:address":"Lyc\u00e9e Priv\u00e9 De La Sauque BP 20 33650 La Br\u00e8de",
    "sg:city":"La Br\u00e8de",
    "sg:classifiers":[
        {
            "category":"Professional",
            "subcategory":"Business Services",
            "type":"Services"
        }
    ],
    "sg:phone":"+33 5 56 20 26 26",
    "sg:postcode":"33650",
    "sg:province":"Aquitaine",
    "sg:tags":[
        "training",
        "advice"
    ],
    "wof:name":"Ass Culture Education Aquitaine",
    "wof:placetype":"venue"
},
  "geometry": {"coordinates":[-0.594689,44.569355],"type":"Point"}
}