{
  "type": "Feature",
  "properties": {
    "iso:country":"FR",
    "sg:address":"Parc Artisanal du Gasset",
    "sg:city":"Chanteloup en Brie",
    "sg:orig_category":"Unclassifiable Establishments",
    "sg:phone":"+33 1 64 12 40 30",
    "sg:postcode":"77600",
    "sg:province":"Ile de France",
    "wof:name":"Arcol S.a.",
    "wof:placetype":"venue"
},
  "geometry": {"coordinates":[2.739407,48.853394],"type":"Point"}
}