{
  "type": "Feature",
  "properties": {
    "iso:country":"FR",
    "sg:address":"30 rue de la R\u00e9publique; Orl\u00e9ans; 45006",
    "sg:city":"Orl\u00e9ans",
    "sg:classifiers":[
        {
            "category":"Banks & Credit Unions",
            "subcategory":"Bank",
            "type":"Services"
        }
    ],
    "sg:phone":"+33 2 38 77 78 78",
    "sg:postcode":"45000",
    "sg:province":"Centre",
    "wof:name":"Banque De France",
    "wof:placetype":"venue"
},
  "geometry": {"coordinates":[1.904931,47.905472],"type":"Point"}
}