{
  "type": "Feature",
  "properties": {
    "addr:full":"5 Rue Hedouin Heullant 76410 St Aubin Les Elbeuf Haute Normandie 76410",
    "addr:housenumber":"5",
    "addr:postcode":"76410;76410",
    "addr:street":"Rue Hedouin Heullant;St Aubin Les;Haute Normandie",
    "iso:country":"FR",
    "sg:address":"5 Rue Hedouin Heullant 76410 St Aubin Les Elbeuf",
    "sg:classifiers":[
        {
            "category":"Manufacturing",
            "subcategory":"Metals",
            "type":"Manufacturing & Wholesale Goods"
        }
    ],
    "sg:phone":"+33 2 35 77 77 60",
    "sg:postcode":"76410",
    "sg:province":"Haute Normandie",
    "sg:tags":[
        "-",
        "machine",
        "equipment",
        "engineering",
        "machinery",
        "mechanical"
    ],
    "wof:name":"Sarl Confection Dp",
    "wof:placetype":"venue"
},
  "geometry": {"coordinates":[1.007053,49.300045],"type":"Point"}
}