{
  "type": "Feature",
  "properties": {
    "addr:full":"Rue Sourdeac Nantes Pays de Loire 44000",
    "addr:postcode":"44000",
    "addr:street":"Rue Sourdeac",
    "iso:country":"FR",
    "sg:address":"Rue Sourdeac",
    "sg:city":"Nantes",
    "sg:orig_category":"Unclassifiable Establishments",
    "sg:phone":"+33 2 40 89 57 10",
    "sg:postcode":"44000",
    "sg:province":"Pays de Loire",
    "wof:name":"Boisti\u00e8re Et Compagnie S.a.r.l.",
    "wof:placetype":"venue"
},
  "geometry": {"coordinates":[-1.563899,47.207199],"type":"Point"}
}