{
  "type": "Feature",
  "properties": {
    "iso:country":"FR",
    "sg:address":"A\u00e9roport B\u00e2le Mulhouse 68300 St Louis",
    "sg:city":"Saint-Louis",
    "sg:classifiers":[
        {
            "category":"Airport",
            "type":"Transportation"
        }
    ],
    "sg:phone":"+33 3 89 90 32 96",
    "sg:postcode":"68300",
    "sg:province":"Alsace",
    "sg:tags":[
        "transport",
        "air"
    ],
    "wof:name":"Klm",
    "wof:placetype":"venue"
},
  "geometry": {"coordinates":[7.53134,47.599789],"type":"Point"}
}