{
  "type": "Feature",
  "properties": {
    "iso:country":"FR",
    "sg:address":"16 Bis, Rue Marius Faure, 69630 Chaponost",
    "sg:orig_category":"Non-Classified Establishments",
    "sg:phone":"+33 4 78 05 37 85",
    "sg:province":"Rhone-Alpes",
    "wof:name":"Transport Morellon S.a.r.l.",
    "wof:placetype":"venue"
},
  "geometry": {"coordinates":[4.760053,45.71476],"type":"Point"}
}