{
  "type": "Feature",
  "properties": {
    "addr:full":"Village Boucher 44690 Monni\u00e8res Pays de Loire 44690",
    "addr:postcode":"44690;44690",
    "addr:street":"Monnie\u0300Res",
    "iso:country":"FR",
    "sg:address":"Village Boucher 44690 Monni\u00e8res",
    "sg:orig_category":"Non-Classified Establishments",
    "sg:phone":"+33 2 40 54 62 18",
    "sg:postcode":"44690",
    "sg:province":"Pays de Loire",
    "wof:name":"Ch\u00e9reau Fr\u00e8res G.a.e.c.",
    "wof:placetype":"venue"
},
  "geometry": {"coordinates":[-1.335754,47.120426],"type":"Point"}
}