{
  "type": "Feature",
  "properties": {
    "iso:country":"FR",
    "sg:address":"12, Quai Duguay Trouin, 35000 Rennes",
    "sg:city":"Rennes",
    "sg:orig_category":"Non-Classified Establishments",
    "sg:phone":"+33 2 99 30 23 88",
    "sg:postcode":"35000",
    "sg:province":"Bretagne",
    "wof:name":"Coface - Compagnie Fran\u00e7aise D'assurance Pour Le Commerce",
    "wof:placetype":"venue"
},
  "geometry": {"coordinates":[-1.681414,48.110363],"type":"Point"}
}