{
  "type": "Feature",
  "properties": {
    "iso:country":"FR",
    "sg:address":"4, Rue Montchr\u00e9tien de Watteville, 14700 Falaise",
    "sg:city":"Falaise",
    "sg:orig_category":"Non-Classified Establishments",
    "sg:phone":"+33 2 31 90 08 78",
    "sg:postcode":"14700",
    "sg:province":"Basse Normandie",
    "wof:name":"Felp Enseignes S.a.r.l.",
    "wof:placetype":"venue"
},
  "geometry": {"coordinates":[-0.189719,48.89439],"type":"Point"}
}