{
  "type": "Feature",
  "properties": {
    "addr:full":"1 Rue Condamines 07300 Mauves Rhone-Alpes 07300",
    "addr:housenumber":"1",
    "addr:postcode":"07300;07300",
    "addr:street":"Rue Condamines",
    "iso:country":"FR",
    "sg:address":"1 Rue Condamines 07300 Mauves",
    "sg:classifiers":[
        {
            "category":"Professional",
            "subcategory":"Engineering",
            "type":"Services"
        }
    ],
    "sg:phone":"+33 4 75 08 03 51",
    "sg:postcode":"07300",
    "sg:province":"Rhone-Alpes",
    "sg:tags":[
        "machine",
        "-",
        "mechanical"
    ],
    "wof:name":"Grange Sarl",
    "wof:placetype":"venue"
},
  "geometry": {"coordinates":[4.831746,45.033707],"type":"Point"}
}