{
  "type": "Feature",
  "properties": {
    "iso:country":"FR",
    "sg:address":"rue de l'Industrie 25410 St Vit",
    "sg:classifiers":[
        {
            "category":"Manufacturing",
            "subcategory":"Rubber & Plastics",
            "type":"Manufacturing & Wholesale Goods"
        }
    ],
    "sg:phone":"+33 3 81 55 12 12",
    "sg:province":"Franche Comt\u00e9",
    "sg:tags":[
        "technical",
        "parts"
    ],
    "wof:name":"Decotech S.a.",
    "wof:placetype":"venue"
},
  "geometry": {"coordinates":[5.809787,47.184196],"type":"Point"}
}