{
  "type": "Feature",
  "properties": {
    "addr:full":"22, Rue Henri de Boppard, 57430 Sarralbe Lorraine",
    "addr:housenumber":"22",
    "addr:postcode":"57430",
    "addr:street":"Rue Henri De Boppard",
    "iso:country":"FR",
    "sg:address":"22, Rue Henri de Boppard, 57430 Sarralbe",
    "sg:orig_category":"Non-Classified Establishments",
    "sg:phone":"+33 3 87 97 86 32",
    "sg:province":"Lorraine",
    "wof:name":"Sodremat S.a.",
    "wof:placetype":"venue"
},
  "geometry": {"coordinates":[7.03013,49.000999],"type":"Point"}
}