{
  "type": "Feature",
  "properties": {
    "iso:country":"FR",
    "sg:address":"16 Rue Gustave Fouillaron 49300 Cholet",
    "sg:classifiers":[
        {
            "category":"Utilities",
            "subcategory":"Electric",
            "type":"Services"
        }
    ],
    "sg:phone":"+33 2 41 58 16 00",
    "sg:postcode":"49300",
    "sg:province":"Pays de Loire",
    "sg:tags":[
        "electricity",
        "electronic",
        "electrical",
        "equipment"
    ],
    "wof:name":"Cholet Cablage Sarl",
    "wof:placetype":"venue"
},
  "geometry": {"coordinates":[-0.929364,47.026146],"type":"Point"}
}