{
  "type": "Feature",
  "properties": {
    "iso:country":"FR",
    "sg:address":"3, Rue Newton - ZI du Mar\u00e9chat, 63200 Riom",
    "sg:city":"Riom",
    "sg:orig_category":"Non-Classified Establishments",
    "sg:phone":"+33 4 73 38 75 10",
    "sg:postcode":"63200",
    "sg:province":"Auvergne",
    "wof:name":"U.m.c. S.a.r.l. - Usinage M\u00e9canique Du Centre",
    "wof:placetype":"venue"
},
  "geometry": {"coordinates":[3.052114,45.84782],"type":"Point"}
}