{
  "type": "Feature",
  "properties": {
    "iso:country":"FR",
    "sg:address":"Rue Du Pr\u00e9 Aux Boeufs 76800 St Etienne Du Rouvray",
    "sg:classifiers":[
        {
            "category":"Utilities",
            "subcategory":"Electric",
            "type":"Services"
        }
    ],
    "sg:phone":"+33 2 32 95 91 50",
    "sg:postcode":"76800",
    "sg:province":"Haute Normandie",
    "sg:tags":[
        "electricity",
        "electronic",
        "electrical",
        "equipment"
    ],
    "wof:name":"Cge Distribution",
    "wof:placetype":"venue"
},
  "geometry": {"coordinates":[1.117875,49.393608],"type":"Point"}
}