{
  "type": "Feature",
  "properties": {
    "addr:full":"55 rue de la F\u00e9d\u00e9ration 75015 Paris Ile de France 75015",
    "addr:housenumber":"55",
    "addr:postcode":"75015;75015",
    "addr:street":"Rue De La Fe\u0301De\u0301Ration",
    "iso:country":"FR",
    "sg:address":"55 rue de la F\u00e9d\u00e9ration 75015 Paris",
    "sg:orig_category":"Caoutchouc",
    "sg:phone":"+33 1 42 73 90 90",
    "sg:postcode":"75015",
    "sg:province":"Ile de France",
    "wof:name":"General Industries Sa",
    "wof:placetype":"venue"
},
  "geometry": {"coordinates":[2.295773,48.853462],"type":"Point"}
}