{
  "type": "Feature",
  "properties": {
    "iso:country":"FR",
    "sg:address":"9-11 R De L'Industrie 72320 Valennes",
    "sg:classifiers":[
        {
            "category":"Manufacturing",
            "subcategory":"Motor Vehicles & Parts",
            "type":"Manufacturing & Wholesale Goods"
        }
    ],
    "sg:phone":"+33 2 43 35 19 07",
    "sg:postcode":"72320",
    "sg:province":"Pays de Loire",
    "sg:tags":[
        "industrial",
        "-",
        "machine",
        "equipment",
        "engineering",
        "machinery",
        "mechanical",
        "agriculture"
    ],
    "wof:name":"Socova Lebis Pere Et Fils Sarl",
    "wof:placetype":"venue"
},
  "geometry": {"coordinates":[0.810905,47.996792],"type":"Point"}
}