{
  "type": "Feature",
  "properties": {
    "addr:full":"4, Impasse Charles Petit, 75011 Paris Ile de France 75011",
    "addr:housenumber":"4",
    "addr:postcode":"75011;75011",
    "addr:street":"Impasse Charles Petit",
    "iso:country":"FR",
    "sg:address":"4, Impasse Charles Petit, 75011 Paris",
    "sg:orig_category":"Non-Classified Establishments",
    "sg:phone":"+33 1 43 71 25 32",
    "sg:postcode":"75011",
    "sg:province":"Ile de France",
    "wof:name":"Etablissement Laurent Virot S.a.",
    "wof:placetype":"venue"
},
  "geometry": {"coordinates":[2.384811,48.851124],"type":"Point"}
}