{
  "type": "Feature",
  "properties": {
    "addr:full":"17 B Rue Guilleminot 60500 Chantilly Picardie 60500",
    "addr:housenumber":"17 b",
    "addr:postcode":"60500;60500",
    "addr:street":"Rue Guilleminot",
    "iso:country":"FR",
    "sg:address":"17 B Rue Guilleminot 60500 Chantilly",
    "sg:classifiers":[
        {
            "category":"Manufacturing",
            "subcategory":"Jewelry",
            "type":"Manufacturing & Wholesale Goods"
        }
    ],
    "sg:phone":"+33 3 44 57 95 95",
    "sg:postcode":"60500",
    "sg:province":"Picardie",
    "sg:tags":[
        "product",
        "miscellaneous",
        "jewellery"
    ],
    "wof:name":"Prestations Metaux Precieux (pmp)",
    "wof:placetype":"venue"
},
  "geometry": {"coordinates":[2.460496,49.197792],"type":"Point"}
}