{
  "type": "Feature",
  "properties": {
    "addr:full":"9 route Nationale Arcis 37600 VERNEUIL SUR INDRE Betz-le-Ch\u00e2teau Centre 37600",
    "addr:housenumber":"9",
    "addr:postcode":"37600;37600",
    "addr:street":"Route Nationale Arcis;Indre",
    "iso:country":"FR",
    "sg:address":"9 route Nationale Arcis 37600 VERNEUIL SUR INDRE",
    "sg:city":"Betz-le-Ch\u00e2teau",
    "sg:classifiers":[
        {
            "category":"Food & Beverages",
            "subcategory":"Dairy",
            "type":"Retail Goods"
        }
    ],
    "sg:phone":"+33 2 47 94 71 02",
    "sg:postcode":"37600",
    "sg:province":"Centre",
    "sg:tags":[
        "product",
        "milk"
    ],
    "wof:name":"Coop\u00e9rative Laiti\u00e8re De La R\u00e9gion Lochoise Verneuil-reignac Coop.",
    "wof:placetype":"venue"
},
  "geometry": {"coordinates":[1.02702,46.968109],"type":"Point"}
}