{
  "type": "Feature",
  "properties": {
    "addr:full":"ZI la Thur Pulversheim Alsace 68840",
    "addr:postcode":"68840",
    "addr:street":"Zi La Thur",
    "iso:country":"FR",
    "sg:address":"ZI la Thur",
    "sg:city":"Pulversheim",
    "sg:orig_category":"Unclassifiable Establishments",
    "sg:phone":"+33 3 89 62 81 00",
    "sg:postcode":"68840",
    "sg:province":"Alsace",
    "wof:name":"Foss Europe S.a.s.",
    "wof:placetype":"venue"
},
  "geometry": {"coordinates":[7.30181,47.834324],"type":"Point"}
}