{
  "type": "Feature",
  "properties": {
    "addr:full":"9 All Romain Rolland 76410 St Aubin Les Elbeuf Haute Normandie 76410",
    "addr:housenumber":"9",
    "addr:postcode":"76410;76410",
    "addr:street":"All Romain Rolland;St Aubin Les;Haute Normandie",
    "iso:country":"FR",
    "sg:address":"9 All Romain Rolland 76410 St Aubin Les Elbeuf",
    "sg:classifiers":[
        {
            "category":"Professional",
            "subcategory":"Engineering",
            "type":"Services"
        }
    ],
    "sg:phone":"+33 2 35 81 94 58",
    "sg:postcode":"76410",
    "sg:province":"Haute Normandie",
    "sg:tags":[
        "machine",
        "-",
        "mechanical"
    ],
    "wof:name":"Industrialisat Concept Materiels France Sarl",
    "wof:placetype":"venue"
},
  "geometry": {"coordinates":[1.038923,49.305565],"type":"Point"}
}