{
  "type": "Feature",
  "properties": {
    "addr:full":"52 Rue Copernic Paris Ile de France 75116",
    "addr:housenumber":"52",
    "addr:postcode":"75116",
    "addr:street":"Rue Copernic",
    "iso:country":"FR",
    "sg:address":"52 Rue Copernic",
    "sg:city":"Paris",
    "sg:classifiers":[
        {
            "category":"Banks & Credit Unions",
            "subcategory":"Financial Services",
            "type":"Services"
        }
    ],
    "sg:phone":"+33 1 45 01 50 50",
    "sg:postcode":"75116",
    "sg:province":"Ile de France",
    "sg:tags":[
        "banking",
        "finance",
        "insurance"
    ],
    "wof:name":"Moquin Fadlallam",
    "wof:placetype":"venue"
},
  "geometry": {"coordinates":[2.286106,48.869709],"type":"Point"}
}