{
  "type": "Feature",
  "properties": {
    "iso:country":"FR",
    "sg:address":"B.P. 58, 69684 Chassieu C\u00e9dex^^19, Rue Jacquard, 69680 Chassieu",
    "sg:orig_category":"Non-Classified Establishments",
    "sg:phone":"+33 4 72 79 04 60",
    "sg:postcode":"69680",
    "sg:province":"Rhone-Alpes",
    "wof:name":"Diamix S.a.",
    "wof:placetype":"venue"
},
  "geometry": {"coordinates":[4.972185,45.743477],"type":"Point"}
}