{
  "type": "Feature",
  "properties": {
    "addr:full":"10 rue de Paris 93130 Noisy le Sec Ile de France 93130",
    "addr:housenumber":"10",
    "addr:postcode":"93130;93130",
    "addr:street":"Rue De Paris",
    "iso:country":"FR",
    "sg:address":"10 rue de Paris 93130 Noisy le Sec",
    "sg:classifiers":[
        {
            "category":"Manufacturing",
            "subcategory":"Metals",
            "type":"Manufacturing & Wholesale Goods"
        }
    ],
    "sg:phone":"+33 1 48 44 92 42",
    "sg:postcode":"93130",
    "sg:province":"Ile de France",
    "sg:tags":[
        "ironmongery"
    ],
    "wof:name":"L'outillage Europeen Sa",
    "wof:placetype":"venue"
},
  "geometry": {"coordinates":[2.44445,48.898911],"type":"Point"}
}