{
  "type": "Feature",
  "properties": {
    "iso:country":"FR",
    "sg:address":"12, Bd de l'Ouest, 76000 Rouen",
    "sg:orig_category":"Non-Classified Establishments",
    "sg:phone":"+33 2 35 98 17 22",
    "sg:province":"Haute Normandie",
    "wof:name":"S.g.a.e. S.a. - Soci\u00e9t\u00e9 G\u00e9n\u00e9rale Avitaillement D'approvisionnement Et Equipement",
    "wof:placetype":"venue"
},
  "geometry": {"coordinates":[1.047889,49.446892],"type":"Point"}
}