{
  "type": "Feature",
  "properties": {
    "iso:country":"FR",
    "sg:address":"15, Rue de Mayence, 21000 Dijon",
    "sg:city":"Dijon",
    "sg:orig_category":"Unclassifiable Establishments",
    "sg:phone":"+33 3 80 30 03 81",
    "sg:postcode":"21000",
    "sg:province":"Bourgogne",
    "wof:name":"Piretti Et Compagnie S.a.",
    "wof:placetype":"venue"
},
  "geometry": {"coordinates":[5.062516,47.350399],"type":"Point"}
}