{
  "type": "Feature",
  "properties": {
    "iso:country":"FR",
    "sg:address":"B.P. 2",
    "sg:city":"Veyrins Thuellin^^Le Grimaud 38630 Veyrins Thuellin",
    "sg:orig_category":"Non-Classified Establishments",
    "sg:phone":"+33 4 74 88 93 90",
    "sg:postcode":"38630",
    "sg:province":"Rhone-Alpes",
    "wof:name":"C.m.g. S.a.r.l. - Constructions M\u00e9caniques Du Grimaud",
    "wof:placetype":"venue"
},
  "geometry": {"coordinates":[5.562497,45.635681],"type":"Point"}
}