{
  "type": "Feature",
  "properties": {
    "addr:full":"105 Avenue Parmentier 75011 Paris Ile de France 75011",
    "addr:housenumber":"105",
    "addr:postcode":"75011;75011",
    "addr:street":"Avenue Parmentier",
    "iso:country":"FR",
    "sg:address":"105 Avenue Parmentier 75011 Paris",
    "sg:classifiers":[
        {
            "category":"Shopping",
            "subcategory":"Clothing, Apparel, & Fashions",
            "type":"Retail Goods"
        }
    ],
    "sg:phone":"+33 1 48 05 19 11",
    "sg:postcode":"75011",
    "sg:province":"Ile de France",
    "sg:tags":[
        "textile",
        "clothing",
        "clothes"
    ],
    "wof:name":"Parmentex Cent Cinq",
    "wof:placetype":"venue"
},
  "geometry": {"coordinates":[2.372857,48.867188],"type":"Point"}
}