{
  "type": "Feature",
  "properties": {
    "addr:full":"Rte de Lyon - ZA du Pont Saint Charles Cognin Rhone-Alpes 73160",
    "addr:postcode":"73160",
    "addr:street":"Rte De Lyon Za Du Pont;Rhone-Alpes",
    "iso:country":"FR",
    "sg:address":"Rte de Lyon - ZA du Pont Saint Charles",
    "sg:city":"Cognin",
    "sg:orig_category":"Non-Classified Establishments",
    "sg:phone":"+33 4 79 62 58 18",
    "sg:postcode":"73160",
    "sg:province":"Rhone-Alpes",
    "wof:name":"Compassi Fr\u00e8res S.a.r.l.",
    "wof:placetype":"venue"
},
  "geometry": {"coordinates":[5.823435,45.429111],"type":"Point"}
}