{
  "type": "Feature",
  "properties": {
    "iso:country":"FR",
    "sg:address":"Rue Des Fr\u00e8res Lumi\u00e8re Zi De La Pomme 31250 Revel",
    "sg:classifiers":[
        {
            "category":"Professional",
            "type":"Services"
        }
    ],
    "sg:phone":"+33 5 61 27 52 03",
    "sg:province":"Midi Pyr\u00e9n\u00e9es",
    "sg:tags":[
        "transport",
        "road"
    ],
    "wof:name":"Vieu Antoine",
    "wof:placetype":"venue"
},
  "geometry": {"coordinates":[1.981125,43.426174],"type":"Point"}
}