{
  "type": "Feature",
  "properties": {
    "iso:country":"FR",
    "sg:address":"106 Avenue Edouard Michelin 63100 Clermont Ferrand",
    "sg:city":"Clermont-Ferrand",
    "sg:classifiers":[
        {
            "category":"Government",
            "subcategory":"Department Of Motor Vehicles",
            "type":"Public Place"
        }
    ],
    "sg:phone":"+33 4 73 98 50 00",
    "sg:postcode":"63100",
    "sg:province":"Auvergne",
    "sg:tags":[
        "equipment",
        "industrial",
        "transport",
        "motor-cars"
    ],
    "wof:name":"Comptoir Service Automobile Clermontois",
    "wof:placetype":"venue"
},
  "geometry": {"coordinates":[3.111665,45.780338],"type":"Point"}
}