{
  "type": "Feature",
  "properties": {
    "addr:full":"8, Rue Regnault, 02100 Saint Quentin Picardie 02100",
    "addr:housenumber":"8",
    "addr:postcode":"02100;02100",
    "addr:street":"Rue Regnault",
    "iso:country":"FR",
    "sg:address":"8, Rue Regnault, 02100 Saint Quentin",
    "sg:orig_category":"Non-Classified Establishments",
    "sg:phone":"+33 3 23 62 25 35",
    "sg:postcode":"02100",
    "sg:province":"Picardie",
    "wof:name":"Chabroux Fr\u00e8res",
    "wof:placetype":"venue"
},
  "geometry": {"coordinates":[3.273968,49.849808],"type":"Point"}
}