{
  "type": "Feature",
  "properties": {
    "iso:country":"FR",
    "sg:address":"5, Rue Gustave Eiffel, 94510 La Queue en Brie",
    "sg:orig_category":"Unclassifiable Establishments",
    "sg:phone":"+33 1 45 93 14 14",
    "sg:province":"Ile de France",
    "wof:name":"Antelec S.a.",
    "wof:placetype":"venue"
},
  "geometry": {"coordinates":[2.572058,48.779819],"type":"Point"}
}