{
  "type": "Feature",
  "properties": {
    "addr:full":"24 Rue Charcot 75013 Paris Ile de France 75013",
    "addr:housenumber":"24",
    "addr:postcode":"75013;75013",
    "addr:street":"Rue Charcot",
    "iso:country":"FR",
    "sg:address":"24 Rue Charcot 75013 Paris",
    "sg:classifiers":[
        {
            "category":"Professional",
            "subcategory":"Business Services",
            "type":"Services"
        }
    ],
    "sg:phone":"+33 1 45 85 58 94",
    "sg:postcode":"75013",
    "sg:province":"Ile de France",
    "sg:tags":[
        "training",
        "advice"
    ],
    "wof:name":"Cours Etienne Saint Hilaire",
    "wof:placetype":"venue"
},
  "geometry": {"coordinates":[2.371081,48.830868],"type":"Point"}
}