{
  "type": "Feature",
  "properties": {
    "addr:full":"Za La Forche 35830 Betton Betton Bretagne 35830",
    "addr:postcode":"35830;35830",
    "addr:street":"Za La Forche",
    "iso:country":"FR",
    "sg:address":"Za La Forche 35830 Betton",
    "sg:city":"Betton",
    "sg:classifiers":[
        {
            "category":"Wholesale",
            "subcategory":"Farm Supplies",
            "type":"Manufacturing & Wholesale Goods"
        }
    ],
    "sg:phone":"+33 2 99 55 74 88",
    "sg:postcode":"35830",
    "sg:province":"Bretagne",
    "sg:tags":[
        "-",
        "machine",
        "equipment",
        "engineering",
        "machinery",
        "mechanical",
        "agriculture"
    ],
    "wof:name":"Vert Import Sa",
    "wof:placetype":"venue"
},
  "geometry": {"coordinates":[-1.647044,48.18317],"type":"Point"}
}