{
  "type": "Feature",
  "properties": {
    "iso:country":"FR",
    "sg:address":"17 Rue President Robert Schuman 59170 Croix",
    "sg:orig_category":"Mechanical Engineering - machines Transport services",
    "sg:phone":"+33 3 20 68 12 69",
    "sg:postcode":"59170",
    "sg:province":"Nord Pas-de-Calais",
    "wof:name":"Technitex",
    "wof:placetype":"venue"
},
  "geometry": {"coordinates":[3.170351,50.67057],"type":"Point"}
}