{
  "type": "Feature",
  "properties": {
    "addr:full":"8 Bld Des Capucines 75009 Paris Ile de France 75009",
    "addr:housenumber":"8",
    "addr:postcode":"75009;75009",
    "addr:street":"Bld Des Capucines",
    "iso:country":"FR",
    "sg:address":"8 Bld Des Capucines 75009 Paris",
    "sg:classifiers":[
        {
            "category":"Manufacturing",
            "subcategory":"Jewelry",
            "type":"Manufacturing & Wholesale Goods"
        }
    ],
    "sg:phone":"+33 1 42 66 27 09",
    "sg:postcode":"75009",
    "sg:province":"Ile de France",
    "sg:tags":[
        "product",
        "miscellaneous",
        "jewellery"
    ],
    "wof:name":"Ste Bijoux Burma",
    "wof:placetype":"venue"
},
  "geometry": {"coordinates":[2.332722,48.870857],"type":"Point"}
}