{
  "type": "Feature",
  "properties": {
    "addr:full":"B.P. 56, 01980 Loyettes C\u00e9dex^^Site Nucl\u00e9aire du Bugey, 01150 Saint Vulbas Rhone-Alpes 01150",
    "addr:postcode":"01980;01150;01150",
    "addr:street":"B.P. 56;Bugey;Rhone-Alpes",
    "iso:country":"FR",
    "sg:address":"B.P. 56, 01980 Loyettes C\u00e9dex^^Site Nucl\u00e9aire du Bugey, 01150 Saint Vulbas",
    "sg:orig_category":"Non-Classified Establishments",
    "sg:phone":"+33 4 74 34 10 10",
    "sg:postcode":"01150",
    "sg:province":"Rhone-Alpes",
    "wof:name":"E.d.f",
    "wof:placetype":"venue"
},
  "geometry": {"coordinates":[5.3382,45.88237],"type":"Point"}
}