{
  "type": "Feature",
  "properties": {
    "addr:full":"9 passage Gerbay 42300 Roanne Rhone-Alpes 42300",
    "addr:housenumber":"9",
    "addr:postcode":"42300;42300",
    "addr:street":"Passage Gerbay;Rhone-Alpes",
    "iso:country":"FR",
    "sg:address":"9 passage Gerbay 42300 Roanne",
    "sg:classifiers":[
        {
            "category":"Wholesale",
            "subcategory":"Farm Supplies",
            "type":"Manufacturing & Wholesale Goods"
        }
    ],
    "sg:phone":"+33 4 77 68 32 88",
    "sg:postcode":"42300",
    "sg:province":"Rhone-Alpes",
    "sg:tags":[
        "equipment",
        "slaughtering",
        "slaughter",
        "machines"
    ],
    "wof:name":"Linco France Sas",
    "wof:placetype":"venue"
},
  "geometry": {"coordinates":[4.071654,46.030029],"type":"Point"}
}