{
  "type": "Feature",
  "properties": {
    "addr:full":"Z Artisanale La Gare 43800 ST VINCENT Malrevers Auvergne 43800",
    "addr:postcode":"43800;43800",
    "iso:country":"FR",
    "sg:address":"Z Artisanale La Gare 43800 ST VINCENT",
    "sg:city":"Malrevers",
    "sg:orig_category":"Furniture, General",
    "sg:phone":"+33 4 71 08 15 52",
    "sg:postcode":"43800",
    "sg:province":"Auvergne",
    "wof:name":"Jean Paul Beldon Ateliers De L' Emblavez Eurl",
    "wof:placetype":"venue"
},
  "geometry": {"coordinates":[3.967025,45.099289],"type":"Point"}
}