{
  "type": "Feature",
  "properties": {
    "iso:country":"FR",
    "sg:address":"24, Rue de la Montagne, 44100 Nantes",
    "sg:orig_category":"Unclassifiable Establishments",
    "sg:phone":"+33 2 40 44 28 28",
    "sg:province":"Pays de Loire",
    "wof:name":"D.e.f. Ouest S.a.",
    "wof:placetype":"venue"
},
  "geometry": {"coordinates":[-1.580899,47.21167],"type":"Point"}
}