{
  "type": "Feature",
  "properties": {
    "iso:country":"FR",
    "sg:address":"3 rue des A\u00e9rostiers 93160 Noisy le Grand",
    "sg:classifiers":[
        {
            "category":"Utilities",
            "subcategory":"Natural Gas",
            "type":"Services"
        }
    ],
    "sg:phone":"+33 1 48 15 53 10",
    "sg:postcode":"93160",
    "sg:province":"Ile de France",
    "sg:tags":[
        "measuring",
        "instrument"
    ],
    "wof:name":"Compteurs Magnol Sa",
    "wof:placetype":"venue"
},
  "geometry": {"coordinates":[2.582275,48.831734],"type":"Point"}
}