{
  "type": "Feature",
  "properties": {
    "iso:country":"FR",
    "sg:address":"rue Denis Papin 62220 Carvin",
    "sg:classifiers":[
        {
            "category":"Farming",
            "subcategory":"Fish & Marine Products",
            "type":"Manufacturing & Wholesale Goods"
        }
    ],
    "sg:phone":"+33 3 21 08 66 00",
    "sg:postcode":"62220",
    "sg:province":"Nord Pas-de-Calais",
    "sg:tags":[
        "egg"
    ],
    "wof:name":"Karea Sa",
    "wof:placetype":"venue"
},
  "geometry": {"coordinates":[2.970175,50.478828],"type":"Point"}
}