{
  "type": "Feature",
  "properties": {
    "iso:country":"FR",
    "sg:address":"911, Rue Christophe Colomb, 75008 Paris",
    "sg:orig_category":"Non-Classified Establishments",
    "sg:phone":"+33 1 40 69 77 00",
    "sg:province":"Ile de France",
    "wof:name":"Transnucl\u00e9aire S.a.",
    "wof:placetype":"venue"
},
  "geometry": {"coordinates":[2.29837,48.869621],"type":"Point"}
}