{
  "type": "Feature",
  "properties": {
    "iso:country":"FR",
    "sg:address":"9, Rue Saint Mathieu, 69008 Lyon",
    "sg:orig_category":"Unclassifiable Establishments",
    "sg:phone":"+33 4 78 01 26 22",
    "sg:province":"Rhone-Alpes",
    "wof:name":"Mb M\u00e9tal S.a.",
    "wof:placetype":"venue"
},
  "geometry": {"coordinates":[4.862349,45.743103],"type":"Point"}
}