{
  "type": "Feature",
  "properties": {
    "addr:full":"ZI des Trois Pigeons Chantonnay Pays de Loire 85110",
    "addr:postcode":"85110",
    "addr:street":"Des Trois Pigeons",
    "iso:country":"FR",
    "sg:address":"ZI des Trois Pigeons",
    "sg:city":"Chantonnay",
    "sg:orig_category":"Non-Classified Establishments",
    "sg:phone":"+33 2 51 48 56 10",
    "sg:postcode":"85110",
    "sg:province":"Pays de Loire",
    "wof:name":"Gautier France S.a.",
    "wof:placetype":"venue"
},
  "geometry": {"coordinates":[-1.048249,46.685089],"type":"Point"}
}