{
  "type": "Feature",
  "properties": {
    "addr:full":"29 rue Henry; Elbeuf; 76500 Haute Normandie 76500",
    "addr:housenumber":"29",
    "addr:postcode":"76500;76500",
    "addr:street":"Rue Henry Elbeuf;Normandie",
    "iso:country":"FR",
    "sg:address":"29 rue Henry; Elbeuf; 76500",
    "sg:classifiers":[
        {
            "category":"Banks & Credit Unions",
            "subcategory":"Bank",
            "type":"Services"
        }
    ],
    "sg:phone":"+33 3335774683",
    "sg:postcode":"76500",
    "sg:province":"Haute Normandie",
    "wof:name":"Soci\u00e9t\u00e9 G\u00e9n\u00e9rale",
    "wof:placetype":"venue"
},
  "geometry": {"coordinates":[1.0054,49.289322],"type":"Point"}
}