{
  "type": "Feature",
  "properties": {
    "iso:country":"FR",
    "sg:address":"14, Rue d'Ignerelles, 49430 L\u00e9zign\u00e9",
    "sg:orig_category":"Unclassifiable Establishments",
    "sg:phone":"+33 2 41 76 92 19",
    "sg:province":"Pays de Loire",
    "wof:name":"Carpenter S.a.s.",
    "wof:placetype":"venue"
},
  "geometry": {"coordinates":[-0.29496,47.636742],"type":"Point"}
}