{
  "type": "Feature",
  "properties": {
    "addr:full":"1 Rue De L Industrie 77173 Chevry Cossigny Ile de France",
    "addr:housenumber":"1",
    "addr:postcode":"77173;ile",
    "addr:street":"Rue De L Industrie",
    "iso:country":"FR",
    "sg:address":"1 Rue De L Industrie 77173 Chevry Cossigny",
    "sg:classifiers":[
        {
            "category":"Manufacturing",
            "subcategory":"Paper Products",
            "type":"Manufacturing & Wholesale Goods"
        }
    ],
    "sg:phone":"+33 1 64 05 43 41",
    "sg:province":"Ile de France",
    "sg:tags":[
        "finished",
        "cardboard",
        "-"
    ],
    "wof:name":"Disproreg Sa",
    "wof:placetype":"venue"
},
  "geometry": {"coordinates":[2.654145,48.725986],"type":"Point"}
}