{
  "type": "Feature",
  "properties": {
    "iso:country":"FR",
    "sg:address":"38 rue d'\u00c9pinal; Golbey; 88190",
    "sg:classifiers":[
        {
            "category":"Banks & Credit Unions",
            "subcategory":"Bank",
            "type":"Services"
        }
    ],
    "sg:phone":"+33 29341075",
    "sg:postcode":"88190",
    "sg:province":"Lorraine",
    "wof:name":"Soci\u00e9t\u00e9 G\u00e9n\u00e9rale",
    "wof:placetype":"venue"
},
  "geometry": {"coordinates":[6.437885,48.19455],"type":"Point"}
}