{
  "type": "Feature",
  "properties": {
    "addr:full":"30, Esplanade Fl\u00e9chambault, 51100 Reims Champagne",
    "addr:housenumber":"30",
    "addr:postcode":"51100",
    "addr:street":"Esplanade Fle\u0301Chambault",
    "iso:country":"FR",
    "sg:address":"30, Esplanade Fl\u00e9chambault, 51100 Reims",
    "sg:orig_category":"Unclassifiable Establishments",
    "sg:phone":"+33 3 26 85 87 90",
    "sg:province":"Champagne",
    "wof:name":"I.s.s. Abilis Est S.a.s.",
    "wof:placetype":"venue"
},
  "geometry": {"coordinates":[4.038724,49.242477],"type":"Point"}
}