{
  "type": "Feature",
  "properties": {
    "addr:full":"19, Rue Cujas, 75005 Paris Ile de France",
    "addr:housenumber":"19",
    "addr:postcode":"75005",
    "addr:street":"Rue Cujas",
    "iso:country":"FR",
    "sg:address":"19, Rue Cujas, 75005 Paris",
    "sg:orig_category":"Non-Classified Establishments",
    "sg:phone":"+33 1 46 33 33 02",
    "sg:province":"Ile de France",
    "wof:name":"Grand H\u00f4tel Saint Michel",
    "wof:placetype":"venue"
},
  "geometry": {"coordinates":[2.342158,48.847797],"type":"Point"}
}