{
  "type": "Feature",
  "properties": {
    "addr:full":"20, Bd de la M\u00e9rindole - ZI la Grand'Colle, 13110 Port de Bouc Centre",
    "addr:housenumber":"20;13110",
    "addr:street":"Bd De La Me\u0301Rindole Zi La Grand'Colle",
    "iso:country":"FR",
    "sg:address":"20, Bd de la M\u00e9rindole - ZI la Grand'Colle, 13110 Port de Bouc",
    "sg:orig_category":"Unclassifiable Establishments",
    "sg:phone":"+33 4 42 40 51 60",
    "sg:province":"Centre",
    "wof:name":"Spie Trindel",
    "wof:placetype":"venue"
},
  "geometry": {"coordinates":[4.981587,43.42078],"type":"Point"}
}