{
  "type": "Feature",
  "properties": {
    "addr:full":"Rue Des Longs R\u00e9ages BP 25 28231 Epernon Cedex \u00c9pernon Centre 28230",
    "addr:housenumber":"25",
    "addr:postcode":"28231;28230",
    "addr:street":"Rue Des Longs Re\u0301Ages Bp",
    "iso:country":"FR",
    "sg:address":"Rue Des Longs R\u00e9ages BP 25 28231 Epernon Cedex",
    "sg:city":"\u00c9pernon",
    "sg:classifiers":[
        {
            "category":"Government",
            "subcategory":"Department Of Motor Vehicles",
            "type":"Public Place"
        }
    ],
    "sg:phone":"+33 2 37 18 76 00",
    "sg:postcode":"28230",
    "sg:province":"Centre",
    "sg:tags":[
        "equipment",
        "industrial",
        "transport",
        "motor-cars"
    ],
    "wof:name":"Fci Automative France",
    "wof:placetype":"venue"
},
  "geometry": {"coordinates":[1.683085,48.601357],"type":"Point"}
}