{
  "type": "Feature",
  "properties": {
    "iso:country":"FR",
    "sg:address":"Rue Saint Girons",
    "sg:city":"Hagetmau",
    "sg:orig_category":"Unclassifiable Establishments",
    "sg:phone":"+33 5 58 79 40 06",
    "sg:postcode":"40700",
    "sg:province":"Aquitaine",
    "wof:name":"Baillet Paul Et Fils S.a.",
    "wof:placetype":"venue"
},
  "geometry": {"coordinates":[-0.594984,43.656891],"type":"Point"}
}