{
  "type": "Feature",
  "properties": {
    "iso:country":"FR",
    "sg:address":"Route De Mandres",
    "sg:city":"Industrielle 52800 Nogent",
    "sg:classifiers":[
        {
            "category":"Banks & Credit Unions",
            "subcategory":"Financial Services",
            "type":"Services"
        }
    ],
    "sg:phone":"+33 3 25 02 28 28",
    "sg:postcode":"52800",
    "sg:province":"Champagne",
    "sg:tags":[
        "finance",
        "-",
        "institution",
        "machine",
        "banking",
        "engineering",
        "mechanical",
        "insurance"
    ],
    "wof:name":"Accessoires Pratiques Pour Automobiles",
    "wof:placetype":"venue"
},
  "geometry": {"coordinates":[5.335895,48.024647],"type":"Point"}
}