{
  "type": "Feature",
  "properties": {
    "addr:full":"943 Rue Pasteur Zone D Activite 60700 Pont Ste Maxence Picardie 60700",
    "addr:housenumber":"943",
    "addr:postcode":"60700;60700",
    "addr:street":"Rue Pasteur Zone D Activite;Maxence Picardie",
    "iso:country":"FR",
    "sg:address":"943 Rue Pasteur Zone D Activite 60700 Pont Ste Maxence",
    "sg:classifiers":[
        {
            "category":"Professional",
            "subcategory":"Engineering",
            "type":"Services"
        }
    ],
    "sg:phone":"+33 3 44 31 05 38",
    "sg:postcode":"60700",
    "sg:province":"Picardie",
    "sg:tags":[
        "machine",
        "-",
        "environment",
        "equipment",
        "machinery",
        "mechanical"
    ],
    "wof:name":"Erma Flux Etudes Realisations Materiels Aerauliques",
    "wof:placetype":"venue"
},
  "geometry": {"coordinates":[2.604419,49.302036],"type":"Point"}
}