{
  "type": "Feature",
  "properties": {
    "addr:full":"Lot L'Aire Des Moissons 10410 St Parres Aux Tertres Champagne 10410",
    "addr:housenumber":"10410",
    "addr:postcode":"10410",
    "addr:street":"St Parres Aux Tertres Champagne",
    "iso:country":"FR",
    "sg:address":"Lot L'Aire Des Moissons 10410 St Parres Aux Tertres",
    "sg:classifiers":[
        {
            "category":"Travel",
            "subcategory":"Hotels & Motels",
            "type":"Entertainment"
        }
    ],
    "sg:phone":"+33 3 25 76 94 57",
    "sg:postcode":"10410",
    "sg:province":"Champagne",
    "sg:tags":[
        "hotels",
        "business",
        "restaurant"
    ],
    "wof:name":"Buffalo Grill",
    "wof:placetype":"venue"
},
  "geometry": {"coordinates":[4.127524,48.294796],"type":"Point"}
}