{
  "type": "Feature",
  "properties": {
    "iso:country":"FR",
    "sg:address":"B.P. 10, 19300 Egletons C\u00e9dex^^21, Av. Charles de Gaulle, 19300 Egletons",
    "sg:orig_category":"Non-Classified Establishments",
    "sg:phone":"+33 5 55 93 00 25",
    "sg:province":"Limousin",
    "wof:name":"Etablissements Paul Mazeyrat S.a.",
    "wof:placetype":"venue"
},
  "geometry": {"coordinates":[2.034005,45.32111],"type":"Point"}
}