{
  "type": "Feature",
  "properties": {
    "iso:country":"FR",
    "sg:address":"2 bis, Rue Marcel Doret - B\u00e2t. 1, 31700 Blagnac",
    "sg:orig_category":"Non-Classified Establishments",
    "sg:phone":"+33 5 61 16 49 60",
    "sg:postcode":"31700",
    "sg:province":"Midi Pyr\u00e9n\u00e9es",
    "wof:name":"A.i.n.f. S.a.",
    "wof:placetype":"venue"
},
  "geometry": {"coordinates":[1.378557,43.63343],"type":"Point"}
}