{
  "type": "Feature",
  "properties": {
    "addr:full":"9, Rue du Limousin, 91220 Br\u00e9tigny sur Orge Ile de France",
    "addr:housenumber":"9",
    "addr:postcode":"91220",
    "addr:street":"Rue Du Limousin",
    "iso:country":"FR",
    "sg:address":"9, Rue du Limousin, 91220 Br\u00e9tigny sur Orge",
    "sg:orig_category":"Unclassifiable Establishments",
    "sg:phone":"+33 1 60 85 38 00",
    "sg:province":"Ile de France",
    "wof:name":"Servtel S.a.r.l.",
    "wof:placetype":"venue"
},
  "geometry": {"coordinates":[2.304755,48.594646],"type":"Point"}
}