{
  "type": "Feature",
  "properties": {
    "addr:full":"Route D'Agen 32000 Auch Midi Pyr\u00e9n\u00e9es",
    "addr:postcode":"32000",
    "addr:street":"Route D'Agen",
    "iso:country":"FR",
    "sg:address":"Route D'Agen 32000 Auch",
    "sg:classifiers":[
        {
            "category":"Manufacturing",
            "subcategory":"Rubber & Plastics",
            "type":"Manufacturing & Wholesale Goods"
        }
    ],
    "sg:phone":"+33 5 62 60 23 85",
    "sg:province":"Midi Pyr\u00e9n\u00e9es",
    "wof:name":"Euromaster France",
    "wof:placetype":"venue"
},
  "geometry": {"coordinates":[0.601285,43.663429],"type":"Point"}
}