{
  "type": "Feature",
  "properties": {
    "addr:full":"Fiquefleur Equainville 27210 Beuzeville Haute Normandie",
    "addr:postcode":"27210",
    "addr:street":"Haute Normandie",
    "iso:country":"FR",
    "sg:address":"Fiquefleur Equainville 27210 Beuzeville",
    "sg:orig_category":"Unclassifiable Establishments",
    "sg:phone":"+33 2 32 57 61 09",
    "sg:province":"Haute Normandie",
    "wof:name":"Bosquer Bois S.a.r.l.",
    "wof:placetype":"venue"
},
  "geometry": {"coordinates":[0.30909,49.391869],"type":"Point"}
}