{
  "type": "Feature",
  "properties": {
    "iso:country":"FR",
    "sg:address":"2bis, Rue de la cr\u00eadence, 54600 Villers l\u00e8s Nancy",
    "sg:orig_category":"Non-Classified Establishments",
    "sg:phone":"+33 3 83 28 46 46",
    "sg:postcode":"54600",
    "sg:province":"Lorraine",
    "wof:name":"(centre D'etudes Sup\u00e9rieures Industrielles ), Lorraine Champagne Ardenne",
    "wof:placetype":"venue"
},
  "geometry": {"coordinates":[6.117747,48.656052],"type":"Point"}
}