{
  "type": "Feature",
  "properties": {
    "addr:full":"6, Rue de Rungis, 67000 Strasbourg Strasbourg Alsace 67000",
    "addr:housenumber":"6",
    "addr:postcode":"67000;67000",
    "addr:street":"Rue De Rungis",
    "iso:country":"FR",
    "sg:address":"6, Rue de Rungis, 67000 Strasbourg",
    "sg:city":"Strasbourg",
    "sg:orig_category":"Non-Classified Establishments",
    "sg:phone":"+33 3 90 20 67 20",
    "sg:postcode":"67000",
    "sg:province":"Alsace",
    "wof:name":"Innetis",
    "wof:placetype":"venue"
},
  "geometry": {"coordinates":[7.73643,48.585079],"type":"Point"}
}