{
  "type": "Feature",
  "properties": {
    "iso:country":"FR",
    "sg:address":"5 Bd Oyon 72019 Le Mans",
    "sg:city":"Le Mans",
    "sg:classifiers":[
        {
            "category":"Professional",
            "subcategory":"Computer Services",
            "type":"Services"
        }
    ],
    "sg:phone":"+33 2 43 57 42 00",
    "sg:postcode":"72100",
    "sg:province":"Pays de Loire",
    "sg:tags":[
        "information",
        "technology",
        "software"
    ],
    "wof:name":"Gie Sesam Vitale",
    "wof:placetype":"venue"
},
  "geometry": {"coordinates":[4.29189,46.374798],"type":"Point"}
}