{
  "type": "Feature",
  "properties": {
    "addr:full":"9, Rue Saint Henri, 31000 Toulouse Midi Pyr\u00e9n\u00e9es",
    "addr:housenumber":"9",
    "addr:postcode":"31000",
    "addr:street":"Rue Saint Henri",
    "iso:country":"FR",
    "sg:address":"9, Rue Saint Henri, 31000 Toulouse",
    "sg:orig_category":"Unclassifiable Establishments",
    "sg:phone":"+33 5 61 62 88 52",
    "sg:province":"Midi Pyr\u00e9n\u00e9es",
    "wof:name":"Etablissement Oksman S.a.r.l.",
    "wof:placetype":"venue"
},
  "geometry": {"coordinates":[1.447373,43.61293],"type":"Point"}
}