{
  "type": "Feature",
  "properties": {
    "addr:full":"8, Place du G\u00e9n\u00e9ral de Gaulle, 92330 Sceaux Ile de France 92330",
    "addr:housenumber":"8",
    "addr:postcode":"92330;ile;92330",
    "addr:street":"Place Du Ge\u0301Ne\u0301Ral De Gaulle;France",
    "iso:country":"FR",
    "sg:address":"8, Place du G\u00e9n\u00e9ral de Gaulle, 92330 Sceaux",
    "sg:orig_category":"Non-Classified Establishments",
    "sg:phone":"+33 820 33 69 71",
    "sg:postcode":"92330",
    "sg:province":"Ile de France",
    "wof:name":"Bics",
    "wof:placetype":"venue"
},
  "geometry": {"coordinates":[2.291163,48.778271],"type":"Point"}
}