{
  "type": "Feature",
  "properties": {
    "addr:full":"B.P. 4010, 01104 Oyonnax C\u00e9dex^^42, Rte de Dortan, 01100 Oyonnax Rhone-Alpes 01100",
    "addr:postcode":"01104;01100;01100",
    "addr:street":"B.P. 4010;Rte De Dortan",
    "iso:country":"FR",
    "sg:address":"B.P. 4010, 01104 Oyonnax C\u00e9dex^^42, Rte de Dortan, 01100 Oyonnax",
    "sg:orig_category":"Non-Classified Establishments",
    "sg:phone":"+33 4 74 81 94 00",
    "sg:postcode":"01100",
    "sg:province":"Rhone-Alpes",
    "wof:name":"A.i.s. S.a. - Aries Industries Structures",
    "wof:placetype":"venue"
},
  "geometry": {"coordinates":[5.64405,46.24968],"type":"Point"}
}