{
  "type": "Feature",
  "properties": {
    "addr:full":"7 Av Du Pr\u00e9 Robert Sud 74200 Anthy Sur Leman Rhone-Alpes 74200",
    "addr:postcode":"74200;74200",
    "addr:street":"Av Du Pre\u0301 Robert Sud",
    "iso:country":"FR",
    "sg:address":"7 Av Du Pr\u00e9 Robert Sud 74200 Anthy Sur Leman",
    "sg:classifiers":[
        {
            "category":"Professional",
            "subcategory":"Engineering",
            "type":"Services"
        }
    ],
    "sg:phone":"+33 4 50 70 30 91",
    "sg:postcode":"74200",
    "sg:province":"Rhone-Alpes",
    "sg:tags":[
        "machine",
        "-",
        "mechanical"
    ],
    "wof:name":"Richardson Freres",
    "wof:placetype":"venue"
},
  "geometry": {"coordinates":[6.432206,46.348236],"type":"Point"}
}