{
  "type": "Feature",
  "properties": {
    "addr:full":"B.P. 28, 45130 Meung sur Loire^^Quatri\u00e8me Avenue - Zone Synergie, 45130 Meung sur Loire Baule Centre 45130",
    "addr:housenumber":"baule",
    "addr:postcode":"45130;45130;45130",
    "addr:street":"B.P. 28;Loire^^Quatrie\u0300Me Avenue;Synergie",
    "iso:country":"FR",
    "sg:address":"B.P. 28, 45130 Meung sur Loire^^Quatri\u00e8me Avenue - Zone Synergie, 45130 Meung sur Loire",
    "sg:city":"Baule",
    "sg:orig_category":"Non-Classified Establishments",
    "sg:phone":"+33 2 38 44 32 03",
    "sg:postcode":"45130",
    "sg:province":"Centre",
    "wof:name":"Lacroix S.a.",
    "wof:placetype":"venue"
},
  "geometry": {"coordinates":[1.671607,47.811596],"type":"Point"}
}