{
  "type": "Feature",
  "properties": {
    "addr:full":"80084 Amiens C\u00e9dex 2^^Rue de la Croix de Pierre - ZI Nord Amiens Picardie 80000",
    "addr:housenumber":"80084",
    "addr:postcode":"80000",
    "addr:street":"La;De Pierre Zi Nord",
    "iso:country":"FR",
    "sg:address":"80084 Amiens C\u00e9dex 2^^Rue de la Croix de Pierre - ZI Nord",
    "sg:city":"Amiens",
    "sg:orig_category":"Non-Classified Establishments",
    "sg:phone":"+33 3 22 67 52 00",
    "sg:postcode":"80000",
    "sg:province":"Picardie",
    "wof:name":"Amiens Injection S.a.",
    "wof:placetype":"venue"
},
  "geometry": {"coordinates":[2.293165,49.894733],"type":"Point"}
}