{
  "type": "Feature",
  "properties": {
    "iso:country":"FR",
    "sg:address":"8, Rue Anatole France, 59300 Valenciennes",
    "sg:orig_category":"Non-Classified Establishments",
    "sg:phone":"+33 3 27 29 64 64",
    "sg:postcode":"59300",
    "sg:province":"Nord Pas-de-Calais",
    "wof:name":"Acl Nord Picardie S.a.r.l.",
    "wof:placetype":"venue"
},
  "geometry": {"coordinates":[3.504376,50.354248],"type":"Point"}
}