{
  "type": "Feature",
  "properties": {
    "iso:country":"FR",
    "sg:address":"Chemin de Creve Coeur 10380 PLANCY L ABBAYE",
    "sg:orig_category":"Fresh Vegetables, Lettuces, And Potatoes",
    "sg:phone":"+33 3 25 37 40 10",
    "sg:postcode":"10380",
    "sg:province":"Champagne",
    "wof:name":"V\u00e9getable Industrie S.a.",
    "wof:placetype":"venue"
},
  "geometry": {"coordinates":[3.970565,48.57386],"type":"Point"}
}