{
  "type": "Feature",
  "properties": {
    "addr:full":"ZI EST 01700 Beynost Rhone-Alpes 01700",
    "addr:postcode":"01700;01700",
    "addr:street":"Zi Est",
    "iso:country":"FR",
    "sg:address":"ZI EST 01700 Beynost",
    "sg:classifiers":[
        {
            "category":"Manufacturing",
            "subcategory":"Rubber & Plastics",
            "type":"Manufacturing & Wholesale Goods"
        }
    ],
    "sg:phone":"+33 4 78 55 41 15",
    "sg:postcode":"01700",
    "sg:province":"Rhone-Alpes",
    "sg:tags":[
        "injection",
        "part",
        "moulded"
    ],
    "wof:name":"Mip Sarl",
    "wof:placetype":"venue"
},
  "geometry": {"coordinates":[5.002065,45.840061],"type":"Point"}
}