{
  "type": "Feature",
  "properties": {
    "addr:full":"Les Renardi\u00e8res 01370 Treffort Cuisiat Rhone-Alpes 01370",
    "addr:postcode":"01370;01370",
    "addr:street":"Renardie\u0300Res;Rhone-Alpes",
    "iso:country":"FR",
    "sg:address":"Les Renardi\u00e8res 01370 Treffort Cuisiat",
    "sg:classifiers":[
        {
            "category":"Farming",
            "subcategory":"Livestock Farm",
            "type":"Manufacturing & Wholesale Goods"
        }
    ],
    "sg:phone":"+33 4 74 30 54 65",
    "sg:postcode":"01370",
    "sg:province":"Rhone-Alpes",
    "sg:tags":[
        "agriculture"
    ],
    "wof:name":"Or Brun",
    "wof:placetype":"venue"
},
  "geometry": {"coordinates":[5.338984,46.29031],"type":"Point"}
}