{
  "type": "Feature",
  "properties": {
    "iso:country":"FR",
    "sg:address":"11, Rue du Plain, 70250 Ronchamp",
    "sg:orig_category":"Non-Classified Establishments",
    "sg:phone":"+33 3 84 20 62 50",
    "sg:postcode":"70250",
    "sg:province":"Franche Comt\u00e9",
    "wof:name":"Boisseaux Est S.a.r.l.",
    "wof:placetype":"venue"
},
  "geometry": {"coordinates":[6.646597,47.697704],"type":"Point"}
}