{
  "type": "Feature",
  "properties": {
    "addr:full":"34, Av du G\u00e9n\u00e9ral de Gaulle, 54210 Saint Nicolas de Port Lorraine",
    "addr:postcode":"54210",
    "addr:street":"34 Av Du Ge\u0301Ne\u0301Ral De Gaulle;Port",
    "iso:country":"FR",
    "sg:address":"34, Av du G\u00e9n\u00e9ral de Gaulle, 54210 Saint Nicolas de Port",
    "sg:orig_category":"Unclassifiable Establishments",
    "sg:phone":"+33 3 83 45 26 02",
    "sg:province":"Lorraine",
    "wof:name":"Atelier 54 S.a.r.l.",
    "wof:placetype":"venue"
},
  "geometry": {"coordinates":[6.287381,48.620491],"type":"Point"}
}