{
  "type": "Feature",
  "properties": {
    "addr:full":"110 Rue De Rivoli 75001 Paris Ile de France 75001",
    "addr:housenumber":"110",
    "addr:postcode":"75001;75001",
    "addr:street":"Rue De Rivoli",
    "iso:country":"FR",
    "sg:address":"110 Rue De Rivoli 75001 Paris",
    "sg:classifiers":[
        {
            "category":"Shopping",
            "subcategory":"Clothing, Apparel, & Fashions",
            "type":"Retail Goods"
        }
    ],
    "sg:phone":"+33 1 40 39 09 24",
    "sg:postcode":"75001",
    "sg:province":"Ile de France",
    "sg:tags":[
        "textile",
        "clothing",
        "clothes"
    ],
    "wof:name":"Promod",
    "wof:placetype":"venue"
},
  "geometry": {"coordinates":[2.346702,48.859093],"type":"Point"}
}