{
  "type": "Feature",
  "properties": {
    "iso:country":"FR",
    "sg:address":"25 rue Emile Zola 39400 Morez",
    "sg:classifiers":[
        {
            "category":"Health Services",
            "subcategory":"Optometrist",
            "type":"Services"
        }
    ],
    "sg:phone":"+33 3 84 33 48 00",
    "sg:province":"Franche Comt\u00e9",
    "sg:tags":[
        "glass",
        "ready-made"
    ],
    "wof:name":"Paget Diffusion Sa",
    "wof:placetype":"venue"
},
  "geometry": {"coordinates":[6.026205,46.513725],"type":"Point"}
}