{
  "type": "Feature",
  "properties": {
    "iso:country":"FR",
    "sg:address":"53, Rue de la Procession, 75015 Paris",
    "sg:orig_category":"Unclassifiable Establishments",
    "sg:phone":"+33 1 44 38 55 00",
    "sg:province":"Ile de France",
    "wof:name":"Aureus Sarl",
    "wof:placetype":"venue"
},
  "geometry": {"coordinates":[2.308948,48.837185],"type":"Point"}
}