{
  "type": "Feature",
  "properties": {
    "iso:country":"FR",
    "sg:address":"844, Av. de Colomby - ZI des Grands Pr\u00e9s, 74300 Cluses",
    "sg:orig_category":"Non-Classified Establishments",
    "sg:phone":"+33 4 50 98 16 43",
    "sg:postcode":"74300",
    "sg:province":"Rhone-Alpes",
    "wof:name":"Eclide S.a.r.l.",
    "wof:placetype":"venue"
},
  "geometry": {"coordinates":[6.633185,45.987919],"type":"Point"}
}