{
  "type": "Feature",
  "properties": {
    "iso:country":"FR",
    "sg:address":"Za Les Barthes 82600 Verdun Sur Garonne",
    "sg:classifiers":[
        {
            "category":"Manufacturing",
            "subcategory":"Wood Products",
            "type":"Manufacturing & Wholesale Goods"
        }
    ],
    "sg:phone":"+33 5 63 02 69 20",
    "sg:province":"Midi Pyr\u00e9n\u00e9es",
    "sg:tags":[
        "furniture"
    ],
    "wof:name":"Sn Meubles Vallee Du Tarn Sarl (mvt)",
    "wof:placetype":"venue"
},
  "geometry": {"coordinates":[1.225745,43.854012],"type":"Point"}
}