{
  "type": "Feature",
  "properties": {
    "addr:full":"11, Rue du Pont, 25420 Voujeaucourt Franche Comt\u00e9",
    "addr:housenumber":"11",
    "addr:postcode":"25420",
    "addr:street":"Rue Du Pont;Franche Comte\u0301",
    "iso:country":"FR",
    "sg:address":"11, Rue du Pont, 25420 Voujeaucourt",
    "sg:orig_category":"Non-Classified Establishments",
    "sg:phone":"+33 3 81 98 59 39",
    "sg:province":"Franche Comt\u00e9",
    "wof:name":"Menetrier S.a.",
    "wof:placetype":"venue"
},
  "geometry": {"coordinates":[6.767283,47.476131],"type":"Point"}
}