{
  "type": "Feature",
  "properties": {
    "addr:full":"Chef Lieu 73155 Val D'Is\u00e8re Haute Normandie",
    "addr:postcode":"73155",
    "addr:street":"Lieu;D'Ise \u0300Re Haute Normandie",
    "iso:country":"FR",
    "sg:address":"Chef Lieu 73155 Val D'Is\u00e8re",
    "sg:classifiers":[
        {
            "category":"Travel",
            "subcategory":"Hotels & Motels",
            "type":"Entertainment"
        }
    ],
    "sg:phone":"+33 4 79 06 12 13",
    "sg:province":"Haute Normandie",
    "sg:tags":[
        "hotels",
        "business",
        "restaurant"
    ],
    "wof:name":"Ste Expl Hotel Tsanteleina",
    "wof:placetype":"venue"
},
  "geometry": {"coordinates":[6.978991,45.450043],"type":"Point"}
}