{
  "type": "Feature",
  "properties": {
    "iso:country":"FR",
    "sg:address":"16 Chemin Des Carrieres 74940 Annecy Le Vieux",
    "sg:classifiers":[
        {
            "category":"Professional",
            "subcategory":"Engineering",
            "type":"Services"
        }
    ],
    "sg:phone":"+33 4 50 46 02 54",
    "sg:postcode":"74940",
    "sg:province":"Rhone-Alpes",
    "sg:tags":[
        "machine",
        "-",
        "environment",
        "equipment",
        "machinery",
        "mechanical"
    ],
    "wof:name":"Ecograv",
    "wof:placetype":"venue"
},
  "geometry": {"coordinates":[6.123182,45.924755],"type":"Point"}
}