{
  "type": "Feature",
  "properties": {
    "addr:full":"Rte de Flavacourt Eragny sur Epte Picardie 60590",
    "addr:postcode":"60590",
    "addr:street":"Rte De Flavacourt Eragny Sur Epte Picardie",
    "iso:country":"FR",
    "sg:address":"Rte de Flavacourt",
    "sg:city":"Eragny sur Epte",
    "sg:orig_category":"Non-Classified Establishments",
    "sg:phone":"+33 2 32 27 65 65",
    "sg:postcode":"60590",
    "sg:province":"Picardie",
    "wof:name":"Milleret S.a.",
    "wof:placetype":"venue"
},
  "geometry": {"coordinates":[1.820488,49.285877],"type":"Point"}
}