{
  "type": "Feature",
  "properties": {
    "addr:full":"54, Bd. Robert Schuman, 93891 Livry Gargan C\u00e9dex Auvergne",
    "addr:housenumber":"54",
    "addr:postcode":"93891;ce\u0301dex",
    "addr:street":"Bd. Robert Schuman",
    "iso:country":"FR",
    "sg:address":"54, Bd. Robert Schuman, 93891 Livry Gargan C\u00e9dex",
    "sg:orig_category":"Non-Classified Establishments",
    "sg:phone":"+33 1 49 36 51 15",
    "sg:province":"Auvergne",
    "wof:name":"Entreprise E. Touzet S.a.r.l.",
    "wof:placetype":"venue"
},
  "geometry": {"coordinates":[2.549799,48.928192],"type":"Point"}
}