{
  "type": "Feature",
  "properties": {
    "addr:full":"All\u00e9e des Tertiales; Compi\u00e8gne; 60200 Picardie 60200",
    "addr:postcode":"60200;60200",
    "addr:street":"Alle\u0301E Des Tertiales",
    "iso:country":"FR",
    "sg:address":"All\u00e9e des Tertiales; Compi\u00e8gne; 60200",
    "sg:classifiers":[
        {
            "category":"Banks & Credit Unions",
            "subcategory":"Bank",
            "type":"Services"
        }
    ],
    "sg:phone":"+33 2 44 30 21 40",
    "sg:postcode":"60200",
    "sg:province":"Picardie",
    "wof:name":"Banque Scalbert, Dupont Sa",
    "wof:placetype":"venue"
},
  "geometry": {"coordinates":[2.788654,49.391014],"type":"Point"}
}