{
  "type": "Feature",
  "properties": {
    "iso:country":"FR",
    "sg:address":"10/24, Rue Moulin le Roy - ZAC des Rives de Seine, 10800 Saint Julien les Villas",
    "sg:orig_category":"Non-Classified Establishments",
    "sg:phone":"+33 3 25 72 90 31",
    "sg:postcode":"10800",
    "sg:province":"Champagne",
    "wof:name":"A.g.s. - Aube Gravure Service",
    "wof:placetype":"venue"
},
  "geometry": {"coordinates":[4.115572,48.237026],"type":"Point"}
}