{
  "type": "Feature",
  "properties": {
    "addr:full":"Rte De Buffard 25440 Liesle Franche Comt\u00e9 25440",
    "addr:postcode":"25440;25440",
    "addr:street":"Rte De Buffard;Franche Comte\u0301",
    "iso:country":"FR",
    "sg:address":"Rte De Buffard 25440 Liesle",
    "sg:classifiers":[
        {
            "category":"Farming",
            "subcategory":"Crops",
            "type":"Manufacturing & Wholesale Goods"
        }
    ],
    "sg:phone":"+33 3 81 57 43 34",
    "sg:postcode":"25440",
    "sg:province":"Franche Comt\u00e9",
    "sg:tags":[
        "horticulture",
        "agriculture",
        "grain",
        "livestock",
        "cereal"
    ],
    "wof:name":"Coopadou",
    "wof:placetype":"venue"
},
  "geometry": {"coordinates":[5.818894,47.059967],"type":"Point"}
}