{
  "type": "Feature",
  "properties": {
    "iso:country":"FR",
    "sg:address":"Pont de Cers 34420 Villeneuve les B\u00e9ziers",
    "sg:orig_category":"Unclassifiable Establishments",
    "sg:phone":"+33 4 67 39 47 82",
    "sg:province":"Languedoc-Roussillon",
    "wof:name":"Jardins Alain Chaignes S.a.r.l.",
    "wof:placetype":"venue"
},
  "geometry": {"coordinates":[3.301058,43.3167],"type":"Point"}
}