{
  "type": "Feature",
  "properties": {
    "iso:country":"FR",
    "sg:address":"56, Bd de Courcerin, 77183 Croissy Beaubourg",
    "sg:orig_category":"Non-Classified Establishments",
    "sg:phone":"+33 1 64 80 16 00",
    "sg:province":"Ile de France",
    "wof:name":"K-tron France S.a.r.l.",
    "wof:placetype":"venue"
},
  "geometry": {"coordinates":[2.630618,48.82476],"type":"Point"}
}