{
  "type": "Feature",
  "properties": {
    "iso:country":"FR",
    "sg:address":"31 R Victor Hugo 71000 Macon",
    "sg:city":"Sanc\u00e9",
    "sg:classifiers":[
        {
            "category":"Professional",
            "subcategory":"Printing & Photocopies",
            "type":"Services"
        }
    ],
    "sg:phone":"+33 3 85 39 11 00",
    "sg:postcode":"71000",
    "sg:province":"Bourgogne",
    "sg:tags":[
        "publishing"
    ],
    "wof:name":"Info Regie",
    "wof:placetype":"venue"
},
  "geometry": {"coordinates":[4.828497,46.304989],"type":"Point"}
}