{
  "type": "Feature",
  "properties": {
    "addr:full":"ZA de Lourmet Castelmaurou Midi Pyr\u00e9n\u00e9es 31180",
    "addr:postcode":"31180",
    "addr:street":"Za De Lourmet",
    "iso:country":"FR",
    "sg:address":"ZA de Lourmet",
    "sg:city":"Castelmaurou",
    "sg:orig_category":"Non-Classified Establishments",
    "sg:phone":"+33 5 61 09 63 45",
    "sg:postcode":"31180",
    "sg:province":"Midi Pyr\u00e9n\u00e9es",
    "wof:name":"Canilas S.a.r.l.",
    "wof:placetype":"venue"
},
  "geometry": {"coordinates":[1.53196,43.678017],"type":"Point"}
}