{
  "type": "Feature",
  "properties": {
    "iso:country":"FR",
    "sg:address":"8 Allee Du Closeau Zi Des Richardets 93160 Noisy Le Grand",
    "sg:classifiers":[
        {
            "category":"Shopping",
            "subcategory":"Clothing, Apparel, & Fashions",
            "type":"Retail Goods"
        }
    ],
    "sg:phone":"+33 1 43 05 55 66",
    "sg:postcode":"93160",
    "sg:province":"Ile de France",
    "sg:tags":[
        "textile",
        "clothing",
        "clothes"
    ],
    "wof:name":"Cotton Shirt Studio",
    "wof:placetype":"venue"
},
  "geometry": {"coordinates":[2.553644,48.848892],"type":"Point"}
}