{
  "type": "Feature",
  "properties": {
    "iso:country":"FR",
    "sg:address":"79 Avenue Edouard Vaillant 92100 Boulogne Billancourt",
    "sg:classifiers":[
        {
            "category":"Professional",
            "subcategory":"Advertising",
            "type":"Services"
        }
    ],
    "sg:phone":"+33 1 46 20 04 04",
    "sg:postcode":"92100",
    "sg:province":"Ile de France",
    "sg:tags":[
        "marketing",
        "medium",
        "communication"
    ],
    "wof:name":"Armatis Sa",
    "wof:placetype":"venue"
},
  "geometry": {"coordinates":[2.246996,48.834427],"type":"Point"}
}