{
  "type": "Feature",
  "properties": {
    "addr:full":"672 Rue Des Merci\u00e8res 69140 Rillieux La Pape Rhone-Alpes 69140",
    "addr:housenumber":"672",
    "addr:postcode":"69140;69140",
    "addr:street":"Rue Des Mercie\u0300Res",
    "iso:country":"FR",
    "sg:address":"672 Rue Des Merci\u00e8res 69140 Rillieux La Pape",
    "sg:classifiers":[
        {
            "category":"Shopping",
            "subcategory":"Crafts & Fabrics",
            "type":"Retail Goods"
        }
    ],
    "sg:phone":"+33 4 78 88 29 45",
    "sg:postcode":"69140",
    "sg:province":"Rhone-Alpes",
    "sg:tags":[
        "textile",
        "clothing"
    ],
    "wof:name":"Solytem (ste D'exploitation Des Ets) Sarl",
    "wof:placetype":"venue"
},
  "geometry": {"coordinates":[4.879454,45.816162],"type":"Point"}
}