{
  "type": "Feature",
  "properties": {
    "addr:full":"2 bis, Rue Villiers - Les Hauts de Villiers , 92300 Levallois Perret Ile de France",
    "addr:housenumber":"2 bis",
    "addr:postcode":"92300;ile",
    "addr:street":"Rue Villiers Les Hauts De Villiers",
    "iso:country":"FR",
    "sg:address":"2 bis, Rue Villiers - Les Hauts de Villiers , 92300 Levallois Perret",
    "sg:orig_category":"Non-Classified Establishments",
    "sg:phone":"+33 1 47 48 81 50",
    "sg:province":"Ile de France",
    "wof:name":"Kpmg S.a.",
    "wof:placetype":"venue"
},
  "geometry": {"coordinates":[2.28505,48.890995],"type":"Point"}
}