{
  "type": "Feature",
  "properties": {
    "addr:full":"6, Rue Amp\u00e8re, 38000 Grenoble Rhone-Alpes",
    "addr:housenumber":"6",
    "addr:postcode":"38000",
    "addr:street":"Rue Ampe\u0300Re",
    "iso:country":"FR",
    "sg:address":"6, Rue Amp\u00e8re, 38000 Grenoble",
    "sg:orig_category":"Non-Classified Establishments",
    "sg:phone":"+33 4 76 70 51 51",
    "sg:province":"Rhone-Alpes",
    "wof:name":"Isouris.com S.a.r.l.",
    "wof:placetype":"venue"
},
  "geometry": {"coordinates":[5.709393,45.190426],"type":"Point"}
}