{
  "type": "Feature",
  "properties": {
    "addr:full":"26 Rue Emile Zola 59227 Saulzoir Nord Pas-de-Calais 59227",
    "addr:housenumber":"26",
    "addr:postcode":"59227;59227",
    "addr:street":"Rue Emile Zola",
    "iso:country":"FR",
    "sg:address":"26 Rue Emile Zola 59227 Saulzoir",
    "sg:orig_category":"Miscellaneous Products",
    "sg:phone":"+33 3 27 74 00 93",
    "sg:postcode":"59227",
    "sg:province":"Nord Pas-de-Calais",
    "wof:name":"Cercueils Gesserand",
    "wof:placetype":"venue"
},
  "geometry": {"coordinates":[3.44585,50.239136],"type":"Point"}
}