{
  "type": "Feature",
  "properties": {
    "addr:full":"50-54, Rue Silly, 92513 Boulogne Billancourt C\u00e9dex Ancourt Haute Normandie 76370",
    "addr:housenumber":"50-54",
    "addr:postcode":"92513;76370",
    "addr:street":"Rue Silly;Haute Normandie",
    "iso:country":"FR",
    "sg:address":"50-54, Rue Silly, 92513 Boulogne Billancourt C\u00e9dex",
    "sg:city":"Ancourt",
    "sg:orig_category":"Unclassifiable Establishments",
    "sg:phone":"+33 1 49 09 75 00",
    "sg:postcode":"76370",
    "sg:province":"Haute Normandie",
    "wof:name":"Auditoire S.a.",
    "wof:placetype":"venue"
},
  "geometry": {"coordinates":[2.231999,48.837833],"type":"Point"}
}