{
  "type": "Feature",
  "properties": {
    "iso:country":"FR",
    "sg:address":"ZI Les Petites Landes",
    "sg:city":"Cordemais",
    "sg:orig_category":"Unclassifiable Establishments",
    "sg:phone":"+33 2 40 57 84 59",
    "sg:postcode":"44360",
    "sg:province":"Pays de Loire",
    "wof:name":"Seico S.a.r.l.",
    "wof:placetype":"venue"
},
  "geometry": {"coordinates":[-1.878809,47.290016],"type":"Point"}
}