{
  "type": "Feature",
  "properties": {
    "addr:full":"14 Rue De La Lucque Zae De La Garrigue 34725 St Andr\u00e9 De Sangonis Languedoc-Roussillon 34725",
    "addr:housenumber":"14",
    "addr:postcode":"34725;34725",
    "addr:street":"Rue De La Lucque Zae De La Garrigue;Sangonis",
    "iso:country":"FR",
    "sg:address":"14 Rue De La Lucque Zae De La Garrigue 34725 St Andr\u00e9 De Sangonis",
    "sg:classifiers":[
        {
            "category":"Wholesale",
            "subcategory":"Drugs",
            "type":"Manufacturing & Wholesale Goods"
        }
    ],
    "sg:phone":"+33 4 67 57 27 27",
    "sg:postcode":"34725",
    "sg:province":"Languedoc-Roussillon",
    "sg:tags":[
        "chemical",
        "pharmaceutical"
    ],
    "wof:name":"Astrochim Laboratoire",
    "wof:placetype":"venue"
},
  "geometry": {"coordinates":[3.503939,43.650146],"type":"Point"}
}