{
  "type": "Feature",
  "properties": {
    "iso:country":"FR",
    "sg:address":"Autoport de Fr\u00e9jus - Le Freney",
    "sg:city":"Modane",
    "sg:orig_category":"Unclassifiable Establishments",
    "sg:phone":"+33 4 79 05 40 00",
    "sg:postcode":"73500",
    "sg:province":"Rhone-Alpes",
    "wof:name":"Lacombe Transports Internationaux S.a.r.l.",
    "wof:placetype":"venue"
},
  "geometry": {"coordinates":[6.658225,45.179089],"type":"Point"}
}