{
  "type": "Feature",
  "properties": {
    "iso:country":"FR",
    "sg:address":"5, Rue des Reitres, 80400 Eppeville",
    "sg:orig_category":"Unclassifiable Establishments",
    "sg:phone":"+33 3 23 81 09 22",
    "sg:province":"Picardie",
    "wof:name":"Crampon Claude S.a.r.l.",
    "wof:placetype":"venue"
},
  "geometry": {"coordinates":[3.050113,49.735703],"type":"Point"}
}