{
  "type": "Feature",
  "properties": {
    "iso:country":"FR",
    "sg:address":"8, Av. Henry Freville, 35000 Rennes",
    "sg:city":"Rennes",
    "sg:orig_category":"Non-Classified Establishments",
    "sg:phone":"+33 2 99 53 36 36",
    "sg:postcode":"35000",
    "sg:province":"Bretagne",
    "wof:name":"C.r. 2 A - Di",
    "wof:placetype":"venue"
},
  "geometry": {"coordinates":[-1.684477,48.107521],"type":"Point"}
}