{
  "type": "Feature",
  "properties": {
    "addr:full":"B.P. 1537, 87021 Limoges C\u00e9dex 9^^Rue Barth\u00e9l\u00e9my Thimonnier, 87280 Limoges Limousin",
    "addr:postcode":"87021;87280",
    "addr:street":"B.P. 1537;9^^Rue Barthe\u0301Le\u0301My Thimonnier",
    "iso:country":"FR",
    "sg:address":"B.P. 1537, 87021 Limoges C\u00e9dex 9^^Rue Barth\u00e9l\u00e9my Thimonnier, 87280 Limoges",
    "sg:orig_category":"Non-Classified Establishments",
    "sg:phone":"+33 5 55 37 53 54",
    "sg:province":"Limousin",
    "wof:name":"L.c.m. S.a.s. - Laboratoire De Cosm\u00e9tique Moderne",
    "wof:placetype":"venue"
},
  "geometry": {"coordinates":[1.299435,45.914837],"type":"Point"}
}