{
  "type": "Feature",
  "properties": {
    "iso:country":"FR",
    "sg:address":"50 Place De Beaune",
    "sg:city":"Chalon Sur Saone",
    "sg:classifiers":[
        {
            "category":"Banks & Credit Unions",
            "subcategory":"Financial Services",
            "type":"Services"
        }
    ],
    "sg:phone":"+33 3 85 45 81 72",
    "sg:postcode":"71100",
    "sg:province":"Bourgogne",
    "sg:tags":[
        "banking",
        "finance",
        "insurance"
    ],
    "wof:name":"Caisse D Epargne Et De Prevoyance De Bourgogne",
    "wof:placetype":"venue"
},
  "geometry": {"coordinates":[4.856347,46.785194],"type":"Point"}
}