{
  "type": "Feature",
  "properties": {
    "iso:country":"FR",
    "sg:address":"13, Rte de Varanval, 60680 Jonqui\u00e8res",
    "sg:orig_category":"Unclassifiable Establishments",
    "sg:phone":"+33 3 44 37 31 00",
    "sg:province":"Picardie",
    "wof:name":"Farm-frites France S.a.",
    "wof:placetype":"venue"
},
  "geometry": {"coordinates":[2.740717,49.389065],"type":"Point"}
}