{
  "type": "Feature",
  "properties": {
    "addr:full":"8, Rue Jasmin, 75016 Paris Ile de France 75016",
    "addr:housenumber":"8",
    "addr:postcode":"75016;75016",
    "addr:street":"Rue Jasmin",
    "iso:country":"FR",
    "sg:address":"8, Rue Jasmin, 75016 Paris",
    "sg:orig_category":"Non-Classified Establishments",
    "sg:phone":"+33 1 45 20 42 42",
    "sg:postcode":"75016",
    "sg:province":"Ile de France",
    "wof:name":"Cabinet Beno\u00eet S.a.",
    "wof:placetype":"venue"
},
  "geometry": {"coordinates":[2.267264,48.852367],"type":"Point"}
}