{
  "type": "Feature",
  "properties": {
    "addr:full":"Rte de Quaedryper Wylder Nord Pas-de-Calais 59380",
    "addr:postcode":"59380",
    "addr:street":"Rte De Quaedryper",
    "iso:country":"FR",
    "sg:address":"Rte de Quaedryper",
    "sg:city":"Wylder",
    "sg:orig_category":"Non-Classified Establishments",
    "sg:phone":"+33 3 28 65 64 19",
    "sg:postcode":"59380",
    "sg:province":"Nord Pas-de-Calais",
    "wof:name":"Pannier S.a.",
    "wof:placetype":"venue"
},
  "geometry": {"coordinates":[2.492839,50.912811],"type":"Point"}
}