{
  "type": "Feature",
  "properties": {
    "addr:full":"7 rue Dreyfus Dupont 57050 Metz Lorraine 57050",
    "addr:housenumber":"7",
    "addr:postcode":"57050;57050",
    "addr:street":"Rue Dreyfus Dupont",
    "iso:country":"FR",
    "sg:address":"7 rue Dreyfus Dupont 57050 Metz",
    "sg:classifiers":[
        {
            "category":"Building & Trades",
            "subcategory":"Construction",
            "type":"Services"
        }
    ],
    "sg:phone":"+33 3 87 31 13 48",
    "sg:postcode":"57050",
    "sg:province":"Lorraine",
    "sg:tags":[
        "machine",
        "hiring"
    ],
    "wof:name":"Ste Auxiliaire Garzotto S.a.",
    "wof:placetype":"venue"
},
  "geometry": {"coordinates":[6.17839,49.142929],"type":"Point"}
}