{
  "type": "Feature",
  "properties": {
    "iso:country":"FR",
    "sg:address":"Lieu Dit Le Bois Paris",
    "sg:city":"De Mondetour 28630 Nogent Le Phaye",
    "sg:classifiers":[
        {
            "category":"Professional",
            "subcategory":"Advertising",
            "type":"Services"
        }
    ],
    "sg:phone":"+33 2 37 91 29 29",
    "sg:postcode":"28630",
    "sg:province":"Centre",
    "sg:tags":[
        "communication",
        "medium"
    ],
    "wof:name":"Auzou Publicite",
    "wof:placetype":"venue"
},
  "geometry": {"coordinates":[1.49045,48.429531],"type":"Point"}
}