{
  "type": "Feature",
  "properties": {
    "iso:country":"FR",
    "sg:address":"424, Rue de la Basse C\u00f4te, 60880 Armancourt",
    "sg:orig_category":"Non-Classified Establishments",
    "sg:phone":"+33 3 44 83 05 05",
    "sg:province":"Picardie",
    "wof:name":"Transform\u00e9tal S.a.s.",
    "wof:placetype":"venue"
},
  "geometry": {"coordinates":[2.761652,49.369137],"type":"Point"}
}