{
  "type": "Feature",
  "properties": {
    "addr:full":"247, Rue de Belleville, 75019 Paris Ile de France",
    "addr:housenumber":"247",
    "addr:postcode":"75019",
    "addr:street":"Rue De Belleville",
    "iso:country":"FR",
    "sg:address":"247, Rue de Belleville, 75019 Paris",
    "sg:orig_category":"Unclassifiable Establishments",
    "sg:phone":"+33 1 42 08 71 00",
    "sg:province":"Ile de France",
    "wof:name":"Codefo S.a.r.l.",
    "wof:placetype":"venue"
},
  "geometry": {"coordinates":[2.397318,48.87569],"type":"Point"}
}