{
  "type": "Feature",
  "properties": {
    "iso:country":"FR",
    "sg:address":"247, Rue de Belleville, 75019 Paris",
    "sg:orig_category":"Unclassifiable Establishments",
    "sg:phone":"+33 1 42 08 71 00",
    "sg:province":"Ile de France",
    "wof:name":"Codefo S.a.r.l.",
    "wof:placetype":"venue"
},
  "geometry": {"coordinates":[2.397318,48.87569],"type":"Point"}
}