{
  "type": "Feature",
  "properties": {
    "addr:full":"RD 61 - Ch\u00e2teau Minuty Gassin Provence-Alpes-C\u00f4te d'Azur 83580",
    "addr:postcode":"83580",
    "addr:street":"Rd 61 Cha\u0302Teau Minuty Gassin",
    "iso:country":"FR",
    "sg:address":"RD 61 - Ch\u00e2teau Minuty",
    "sg:city":"Gassin",
    "sg:orig_category":"Non-Classified Establishments",
    "sg:phone":"+33 4 94 56 12 09",
    "sg:postcode":"83580",
    "sg:province":"Provence-Alpes-C\u00f4te d'Azur",
    "wof:name":"Matton Farnet S.a.",
    "wof:placetype":"venue"
},
  "geometry": {"coordinates":[6.5854,43.23101],"type":"Point"}
}