{
  "type": "Feature",
  "properties": {
    "iso:country":"FR",
    "sg:address":"Rue Barth\u00e9l\u00e9my Thimonnier - Zone d'Activit\u00e9s du Bois Vert",
    "sg:city":"Plo\u00ebrmel",
    "sg:orig_category":"Non-Classified Establishments",
    "sg:phone":"+33 2 97 73 32 00",
    "sg:postcode":"56800",
    "sg:province":"Bretagne",
    "wof:name":"Sipropre S.a.r.l.",
    "wof:placetype":"venue"
},
  "geometry": {"coordinates":[-2.375393,47.933212],"type":"Point"}
}