{
  "type": "Feature",
  "properties": {
    "iso:country":"FR",
    "sg:address":"61, Rue Charles Rivi\u00e8re, 44400 Rez\u00e9",
    "sg:orig_category":"Unclassifiable Establishments",
    "sg:phone":"+33 2 40 84 44 44",
    "sg:province":"Pays de Loire",
    "wof:name":"Cofratel Ouest S.a.",
    "wof:placetype":"venue"
},
  "geometry": {"coordinates":[-1.542993,47.17115],"type":"Point"}
}