{
  "type": "Feature",
  "properties": {
    "iso:country":"FR",
    "sg:address":"Rte de Taisnil - ZI Le Capron",
    "sg:city":"Saleux",
    "sg:orig_category":"Unclassifiable Establishments",
    "sg:phone":"+33 3 22 95 77 01",
    "sg:postcode":"80480",
    "sg:province":"Picardie",
    "wof:name":"S.i.m.m. 80 S.a.r.l.",
    "wof:placetype":"venue"
},
  "geometry": {"coordinates":[2.243165,49.870926],"type":"Point"}
}