{
  "type": "Feature",
  "properties": {
    "iso:country":"FR",
    "sg:address":"Route De Bain De Bretagne Le Faux 35480 Messac",
    "sg:city":"Messac",
    "sg:classifiers":[
        {
            "category":"Autos & Motor Vehicles",
            "subcategory":"Automobile Sales",
            "type":"Retail Goods"
        }
    ],
    "sg:phone":"+33 2 99 34 63 58",
    "sg:postcode":"35480",
    "sg:province":"Bretagne",
    "sg:tags":[
        "equipment",
        "motor-cars",
        "transport"
    ],
    "wof:name":"Morice Constructeur",
    "wof:placetype":"venue"
},
  "geometry": {"coordinates":[-1.805804,47.824043],"type":"Point"}
}