{
  "type": "Feature",
  "properties": {
    "addr:full":"38 Avenue Normandie 94597 Rungis Cedex Rhone-Alpes",
    "addr:housenumber":"38",
    "addr:postcode":"94597",
    "addr:street":"Avenue Normandie",
    "iso:country":"FR",
    "sg:address":"38 Avenue Normandie 94597 Rungis Cedex",
    "sg:classifiers":[
        {
            "category":"Food & Beverages",
            "subcategory":"Groceries & Convenience Stores",
            "type":"Retail Goods"
        }
    ],
    "sg:phone":"+33 1 46 86 97 07",
    "sg:province":"Rhone-Alpes",
    "sg:tags":[
        "product",
        "related"
    ],
    "wof:name":"Quality Import Sa",
    "wof:placetype":"venue"
},
  "geometry": {"coordinates":[2.358027,48.760098],"type":"Point"}
}