{
  "type": "Feature",
  "properties": {
    "addr:full":"5 De La Paix 34340 Marseillan Languedoc-Roussillon 34340",
    "addr:housenumber":"5",
    "addr:postcode":"34340;34340",
    "addr:street":"De La Paix",
    "iso:country":"FR",
    "sg:address":"5 De La Paix 34340 Marseillan",
    "sg:classifiers":[
        {
            "category":"Food Court",
            "type":"Food & Drink"
        }
    ],
    "sg:phone":"+33 4 67 77 97 78",
    "sg:postcode":"34340",
    "sg:province":"Languedoc-Roussillon",
    "sg:tags":[
        "product",
        "related"
    ],
    "wof:name":"Societe De Distributions D Eau Intercommunales (sdei)",
    "wof:placetype":"venue"
},
  "geometry": {"coordinates":[3.528203,43.353718],"type":"Point"}
}