{
  "type": "Feature",
  "properties": {
    "addr:full":"Rte de Toulouse - ZI Poumad\u00e8res L'Isle Jourdain Midi Pyr\u00e9n\u00e9es 32600",
    "addr:postcode":"32600",
    "addr:street":"Rte De Toulouse Zi Poumade\u0300Res",
    "iso:country":"FR",
    "sg:address":"Rte de Toulouse - ZI Poumad\u00e8res",
    "sg:city":"L'Isle Jourdain",
    "sg:orig_category":"Non-Classified Establishments",
    "sg:phone":"+33 5 62 07 26 26",
    "sg:postcode":"32600",
    "sg:province":"Midi Pyr\u00e9n\u00e9es",
    "wof:name":"S.e.u.t. S.a. - Soci\u00e9t\u00e9 Des Equipements Union Technique",
    "wof:placetype":"venue"
},
  "geometry": {"coordinates":[1.431061,43.611042],"type":"Point"}
}