{
  "type": "Feature",
  "properties": {
    "addr:full":"11 Rue Paul Baudry 75008 Paris Ile de France 75008",
    "addr:housenumber":"11",
    "addr:postcode":"75008;75008",
    "addr:street":"Rue Paul Baudry",
    "iso:country":"FR",
    "sg:address":"11 Rue Paul Baudry 75008 Paris",
    "sg:classifiers":[
        {
            "category":"Professional",
            "subcategory":"Advertising",
            "type":"Services"
        }
    ],
    "sg:phone":"+33 1 53 83 93 13",
    "sg:postcode":"75008",
    "sg:province":"Ile de France",
    "sg:tags":[
        "marketing",
        "medium",
        "communication"
    ],
    "wof:name":"Gavin Anderson & Co",
    "wof:placetype":"venue"
},
  "geometry": {"coordinates":[2.307522,48.872646],"type":"Point"}
}