{
  "type": "Feature",
  "properties": {
    "addr:full":"Micropolis Immeuble Isatis Gap Haute Normandie 05000",
    "addr:postcode":"05000",
    "iso:country":"FR",
    "sg:address":"Micropolis Immeuble Isatis",
    "sg:city":"Gap",
    "sg:orig_category":"Non-Classified Establishments",
    "sg:phone":"+33 4 92 51 79 53",
    "sg:postcode":"05000",
    "sg:province":"Haute Normandie",
    "wof:name":"Alcatel R\u00e9seaux D'entreprise S.a.",
    "wof:placetype":"venue"
},
  "geometry": {"coordinates":[6.07483,44.554939],"type":"Point"}
}