{
  "type": "Feature",
  "properties": {
    "addr:full":"20, Av Gambetta, 12100 Millau Midi Pyr\u00e9n\u00e9es",
    "addr:postcode":"12100",
    "addr:street":"20 Av Gambetta",
    "iso:country":"FR",
    "sg:address":"20, Av Gambetta, 12100 Millau",
    "sg:orig_category":"Non-Classified Establishments",
    "sg:phone":"+33 5 65 60 58 24",
    "sg:province":"Midi Pyr\u00e9n\u00e9es",
    "wof:name":"Maison Fabre S.a.r.l.",
    "wof:placetype":"venue"
},
  "geometry": {"coordinates":[3.082678,44.10141],"type":"Point"}
}