{
  "type": "Feature",
  "properties": {
    "addr:full":"11, Rue du 14 Juillet, 90000 Belfort Franche Comt\u00e9",
    "addr:housenumber":"11",
    "addr:postcode":"90000",
    "addr:street":"Rue Du 14 Juillet;Franche Comte\u0301",
    "iso:country":"FR",
    "sg:address":"11, Rue du 14 Juillet, 90000 Belfort",
    "sg:orig_category":"Unclassifiable Establishments",
    "sg:phone":"+33 3 84 21 43 02",
    "sg:province":"Franche Comt\u00e9",
    "wof:name":"Soci\u00e9t\u00e9 Civile Professionnelle Jean Marc Gomez Et Robert Gomez Architecters Associ\u00e9s S.c.p.a.",
    "wof:placetype":"venue"
},
  "geometry": {"coordinates":[6.851375,47.64864],"type":"Point"}
}