{
  "type": "Feature",
  "properties": {
    "addr:full":"20, Av Jean Foucault - ZI du Capiscol, 34500 B\u00e9ziers Languedoc-Roussillon",
    "addr:postcode":"34500",
    "addr:street":"20 Av Jean Foucault Zi Du Capiscol",
    "iso:country":"FR",
    "sg:address":"20, Av Jean Foucault - ZI du Capiscol, 34500 B\u00e9ziers",
    "sg:orig_category":"Unclassifiable Establishments",
    "sg:phone":"+33 4 67 76 18 20",
    "sg:province":"Languedoc-Roussillon",
    "wof:name":"Sicma S.a.r.l.",
    "wof:placetype":"venue"
},
  "geometry": {"coordinates":[3.216105,43.344234],"type":"Point"}
}