{
  "type": "Feature",
  "properties": {
    "addr:full":"4 Cray\u00e8re 51150 Bisseuil Champagne 51150",
    "addr:housenumber":"4",
    "addr:postcode":"51150;51150",
    "addr:street":"Craye\u0300Re;Champagne",
    "iso:country":"FR",
    "sg:address":"4",
    "sg:city":"Cray\u00e8re 51150 Bisseuil",
    "sg:classifiers":[
        {
            "category":"Food Court",
            "type":"Food & Drink"
        }
    ],
    "sg:phone":"+33 3 26 58 92 12",
    "sg:postcode":"51150",
    "sg:province":"Champagne",
    "sg:tags":[
        "product",
        "related"
    ],
    "wof:name":"Bauchet Freres",
    "wof:placetype":"venue"
},
  "geometry": {"coordinates":[4.08711,49.047421],"type":"Point"}
}