{
  "type": "Feature",
  "properties": {
    "addr:full":"5, Place des Otages - 1er Etage, 29600 Morlaix Morlaix Bretagne 29600",
    "addr:housenumber":"5",
    "addr:postcode":"29600;29600",
    "addr:street":"Place Des Otages 1Er Etage",
    "iso:country":"FR",
    "sg:address":"5, Place des Otages - 1er Etage, 29600 Morlaix",
    "sg:city":"Morlaix",
    "sg:orig_category":"Non-Classified Establishments",
    "sg:phone":"+33 2 98 63 28 29",
    "sg:postcode":"29600",
    "sg:province":"Bretagne",
    "wof:name":"First Atlantique S.a.r.l.",
    "wof:placetype":"venue"
},
  "geometry": {"coordinates":[-3.828099,48.577984],"type":"Point"}
}