{
  "type": "Feature",
  "properties": {
    "addr:full":"B.P. 12, 38560 Jarrie^^291, Rte du Marais, 38560 Jarrie Rhone-Alpes 38560",
    "addr:postcode":"38560;38560;38560",
    "addr:street":"B.P. 12;Rte Du Marais",
    "iso:country":"FR",
    "sg:address":"B.P. 12, 38560 Jarrie^^291, Rte du Marais, 38560 Jarrie",
    "sg:orig_category":"Non-Classified Establishments",
    "sg:phone":"+33 4 76 68 56 56",
    "sg:postcode":"38560",
    "sg:province":"Rhone-Alpes",
    "wof:name":"C.e.z.u.s. Jarrie S.a.",
    "wof:placetype":"venue"
},
  "geometry": {"coordinates":[5.757725,45.115635],"type":"Point"}
}