{
  "type": "Feature",
  "properties": {
    "iso:country":"FR",
    "sg:address":"5, Rue Denis Papin - ZA des 50 Arpents, 77680 Roissy en Brie",
    "sg:orig_category":"Non-Classified Establishments",
    "sg:phone":"+33 1 60 28 58 58",
    "sg:postcode":"77680",
    "sg:province":"Ile de France",
    "wof:name":"Dimalev S.a.r.l.",
    "wof:placetype":"venue"
},
  "geometry": {"coordinates":[2.639538,48.797466],"type":"Point"}
}