{
  "type": "Feature",
  "properties": {
    "addr:full":"24, Rue Davoust, 93698 Pantin C\u00e9dex \u00cele-de-France",
    "addr:housenumber":"24",
    "addr:postcode":"93698",
    "addr:street":"Rue Davoust;Ce\u0301Dex",
    "iso:country":"FR",
    "sg:address":"24, Rue Davoust, 93698 Pantin C\u00e9dex",
    "sg:orig_category":"Non-Classified Establishments",
    "sg:phone":"+33 1 48 91 02 69",
    "sg:province":"\u00cele-de-France",
    "wof:name":"Timsa S.a.",
    "wof:placetype":"venue"
},
  "geometry": {"coordinates":[2.395232,48.899681],"type":"Point"}
}