{
  "type": "Feature",
  "properties": {
    "addr:full":"34 Rue De Conde 59000 Lille Nord Pas-de-Calais",
    "addr:housenumber":"34",
    "addr:postcode":"59000",
    "addr:street":"Rue De Conde",
    "iso:country":"FR",
    "sg:address":"34 Rue De Conde 59000 Lille",
    "sg:classifiers":[
        {
            "category":"Manufacturing",
            "subcategory":"Printing",
            "type":"Manufacturing & Wholesale Goods"
        }
    ],
    "sg:phone":"+33 3 20 52 86 01",
    "sg:province":"Nord Pas-de-Calais",
    "sg:tags":[
        "publishing"
    ],
    "wof:name":"Scan (pld)",
    "wof:placetype":"venue"
},
  "geometry": {"coordinates":[3.061627,50.61972],"type":"Point"}
}