{
  "type": "Feature",
  "properties": {
    "iso:country":"FR",
    "sg:address":"B.P. 40008, 57200 Sarreguemines^^122, Rte de Bitche, 57200 Sarreguemines",
    "sg:orig_category":"Non-Classified Establishments",
    "sg:phone":"+33 3 87 95 01 23",
    "sg:province":"Lorraine",
    "wof:name":"Sotram S.a.",
    "wof:placetype":"venue"
},
  "geometry": {"coordinates":[7.070569,49.108246],"type":"Point"}
}