{
  "type": "Feature",
  "properties": {
    "iso:country":"FR",
    "sg:address":"49 B Avenue Du President Rooseve 77210 Avon",
    "sg:classifiers":[
        {
            "category":"Manufacturing",
            "subcategory":"Rubber & Plastics",
            "type":"Manufacturing & Wholesale Goods"
        }
    ],
    "sg:phone":"+33 1 60 74 99 69",
    "sg:province":"Ile de France",
    "wof:name":"Gsm",
    "wof:placetype":"venue"
},
  "geometry": {"coordinates":[2.720798,48.415749],"type":"Point"}
}