{
  "type": "Feature",
  "properties": {
    "addr:full":"Rte De Vannes 35600 Redon Redon Bretagne 35600",
    "addr:postcode":"35600;35600",
    "addr:street":"Rte De Vannes;Redon",
    "iso:country":"FR",
    "sg:address":"Rte De Vannes 35600 Redon",
    "sg:city":"Redon",
    "sg:classifiers":[
        {
            "category":"Wholesale",
            "subcategory":"Machinery & Supplies",
            "type":"Manufacturing & Wholesale Goods"
        }
    ],
    "sg:phone":"+33 2 99 72 25 25",
    "sg:postcode":"35600",
    "sg:province":"Bretagne",
    "sg:tags":[
        "handling",
        "material",
        "-",
        "machine",
        "equipment",
        "engineering",
        "mechanical"
    ],
    "wof:name":"Bretagne Manutention",
    "wof:placetype":"venue"
},
  "geometry": {"coordinates":[-2.091546,47.643948],"type":"Point"}
}