{
  "type": "Feature",
  "properties": {
    "iso:country":"FR",
    "sg:address":"49, Av. de l'Europe - Villa la Malnotte B\u00e2t. D4, 77184 Emerainville",
    "sg:orig_category":"Unclassifiable Establishments",
    "sg:phone":"+33 1 64 61 08 97",
    "sg:province":"Ile de France",
    "wof:name":"Atos",
    "wof:placetype":"venue"
},
  "geometry": {"coordinates":[2.60801,48.818619],"type":"Point"}
}