{
  "type": "Feature",
  "properties": {
    "addr:full":"Rte De Vendeville 59175 Templemars Nord Pas-de-Calais 59175",
    "addr:postcode":"59175;59175",
    "addr:street":"Rte De Vendeville",
    "iso:country":"FR",
    "sg:address":"Rte De Vendeville 59175 Templemars",
    "sg:classifiers":[
        {
            "category":"Building & Trades",
            "subcategory":"Construction",
            "type":"Services"
        }
    ],
    "sg:phone":"+33 3 20 62 59 00",
    "sg:postcode":"59175",
    "sg:province":"Nord Pas-de-Calais",
    "sg:tags":[
        "work",
        "public"
    ],
    "wof:name":"Sgtn Snc",
    "wof:placetype":"venue"
},
  "geometry": {"coordinates":[3.064453,50.570766],"type":"Point"}
}