{
  "type": "Feature",
  "properties": {
    "addr:full":"160, Rte de Sandillon, 45650 Saint Jean le Blanc Saint-Jean-le-Blanc Centre 45650",
    "addr:housenumber":"160",
    "addr:postcode":"45650;45650",
    "addr:street":"Rte De Sandillon;Saint-Jean-Le-Blanc",
    "iso:country":"FR",
    "sg:address":"160, Rte de Sandillon, 45650 Saint Jean le Blanc",
    "sg:city":"Saint-Jean-le-Blanc",
    "sg:orig_category":"Non-Classified Establishments",
    "sg:phone":"+33 2 38 51 11 69",
    "sg:postcode":"45650",
    "sg:province":"Centre",
    "wof:name":"Mp 45 Automatismes E.u.r.l.",
    "wof:placetype":"venue"
},
  "geometry": {"coordinates":[1.939533,47.877403],"type":"Point"}
}