{
  "type": "Feature",
  "properties": {
    "iso:country":"FR",
    "sg:address":"B.P. 50157, 57403 Sarrebourg C\u00e9dex^^Rte de Niderviller - ZA, 57400 Sarrebourg",
    "sg:orig_category":"Non-Classified Establishments",
    "sg:phone":"+33 3 87 03 53 73",
    "sg:province":"Lorraine",
    "wof:name":"Imprimest S.a.",
    "wof:placetype":"venue"
},
  "geometry": {"coordinates":[7.052015,48.73254],"type":"Point"}
}