{
  "type": "Feature",
  "properties": {
    "addr:full":"150/154, Bd de Verdun, 92413 Courbevoie C\u00e9dex \u00cele-de-France",
    "addr:housenumber":"150 / 154",
    "addr:postcode":"92413",
    "addr:street":"Bd De Verdun;Ce\u0301Dex",
    "iso:country":"FR",
    "sg:address":"150/154, Bd de Verdun, 92413 Courbevoie C\u00e9dex",
    "sg:orig_category":"Non-Classified Establishments",
    "sg:phone":"+33 1 49 04 40 40",
    "sg:province":"\u00cele-de-France",
    "wof:name":"Logicsoft S.a.s.",
    "wof:placetype":"venue"
},
  "geometry": {"coordinates":[2.257615,48.903915],"type":"Point"}
}