{
  "type": "Feature",
  "properties": {
    "addr:full":"13 rue de Belzunce 75010 Paris Ile de France",
    "addr:housenumber":"13",
    "addr:postcode":"75010",
    "addr:street":"Rue De Belzunce",
    "iso:country":"FR",
    "sg:address":"13 rue de Belzunce 75010 Paris",
    "sg:orig_category":"Online Marketing",
    "sg:phone":"+33 1 48 74 72 74",
    "sg:province":"Ile de France",
    "wof:name":"Framar International S.a.r.l.",
    "wof:placetype":"venue"
},
  "geometry": {"coordinates":[2.35013,48.879444],"type":"Point"}
}