{
  "type": "Feature",
  "properties": {
    "addr:full":"13, Rue Guynemer, 95500 Le Thillay Ile de France",
    "addr:housenumber":"13",
    "addr:postcode":"95500",
    "addr:street":"Rue Guynemer",
    "iso:country":"FR",
    "sg:address":"13, Rue Guynemer, 95500 Le Thillay",
    "sg:orig_category":"Unclassifiable Establishments",
    "sg:phone":"+33 1 39 88 38 00",
    "sg:province":"Ile de France",
    "wof:name":"Mc Distribution S.a.r.l.",
    "wof:placetype":"venue"
},
  "geometry": {"coordinates":[2.47773,49.009857],"type":"Point"}
}