{
  "type": "Feature",
  "properties": {
    "iso:country":"FR",
    "sg:address":"37, Rue du Montoir, 78500 Sartrouville",
    "sg:orig_category":"Non-Classified Establishments",
    "sg:phone":"+33 1 39 13 27 12",
    "sg:province":"Ile de France",
    "wof:name":"S.t.a.c. S.a.r.l. - Soci\u00e9t\u00e9 Travaux Am\u00e9nagement Construction",
    "wof:placetype":"venue"
},
  "geometry": {"coordinates":[2.177082,48.939564],"type":"Point"}
}