{
  "type": "Feature",
  "properties": {
    "addr:full":"All\u00e9e De Coulanges 41000 Blois Blois Centre 41000",
    "addr:postcode":"41000;41000",
    "addr:street":"Alle\u0301E De Coulanges",
    "iso:country":"FR",
    "sg:address":"All\u00e9e De Coulanges 41000 Blois",
    "sg:city":"Blois",
    "sg:classifiers":[
        {
            "category":"Manufacturing",
            "subcategory":"Wood Products",
            "type":"Manufacturing & Wholesale Goods"
        }
    ],
    "sg:phone":"+33 2 54 51 41 00",
    "sg:postcode":"41000",
    "sg:province":"Centre",
    "sg:tags":[
        "professional",
        "furniture"
    ],
    "wof:name":"Seib",
    "wof:placetype":"venue"
},
  "geometry": {"coordinates":[1.300078,47.576412],"type":"Point"}
}