{
  "type": "Feature",
  "properties": {
    "addr:full":"B.P. 2907, 41029 Blois C\u00e9dex^^3, Rue des Alli\u00e9es, 41000 Blois Blois Centre 41000",
    "addr:postcode":"41029;41000;41000",
    "addr:street":"B.P. 2907;Rue Des Allie\u0301Es",
    "iso:country":"FR",
    "sg:address":"B.P. 2907, 41029 Blois C\u00e9dex^^3, Rue des Alli\u00e9es, 41000 Blois",
    "sg:city":"Blois",
    "sg:orig_category":"Non-Classified Establishments",
    "sg:phone":"+33 2 54 78 41 46",
    "sg:postcode":"41000",
    "sg:province":"Centre",
    "wof:name":"Bip S.a.",
    "wof:placetype":"venue"
},
  "geometry": {"coordinates":[1.331433,47.586849],"type":"Point"}
}