{
  "type": "Feature",
  "properties": {
    "addr:full":"5, Rue de M\u00e9ons - ZI Molina Nord, 42000 Saint Etienne Rhone-Alpes 42000",
    "addr:housenumber":"5",
    "addr:postcode":"42000;42000",
    "addr:street":"Rue De Me\u0301Ons Zi Molina Nord",
    "iso:country":"FR",
    "sg:address":"5, Rue de M\u00e9ons - ZI Molina Nord, 42000 Saint Etienne",
    "sg:orig_category":"Unclassifiable Establishments",
    "sg:phone":"+33 4 77 25 12 06",
    "sg:postcode":"42000",
    "sg:province":"Rhone-Alpes",
    "wof:name":"Banc Officiel D'epreuve Armes \u00e0 Feu",
    "wof:placetype":"venue"
},
  "geometry": {"coordinates":[4.387921,45.439053],"type":"Point"}
}