{
  "type": "Feature",
  "properties": {
    "iso:country":"FR",
    "sg:address":"1, Rue Pasteur, 51190 Avize",
    "sg:orig_category":"Unclassifiable Establishments",
    "sg:phone":"+33 3 26 57 50 88",
    "sg:province":"Champagne",
    "wof:name":"Waris Et Chenayer Champagne S.a.r.l.",
    "wof:placetype":"venue"
},
  "geometry": {"coordinates":[4.011183,48.973],"type":"Point"}
}