{
  "type": "Feature",
  "properties": {
    "addr:full":"2, Rue de la Fonderie - ZI, 44477 Carquefou C\u00e9dex Carquefou Pays de Loire 44470",
    "addr:housenumber":"2",
    "addr:postcode":"44477;44470",
    "addr:street":"Rue De La Fonderie Zi",
    "iso:country":"FR",
    "sg:address":"2, Rue de la Fonderie - ZI, 44477 Carquefou C\u00e9dex",
    "sg:city":"Carquefou",
    "sg:orig_category":"Non-Classified Establishments",
    "sg:phone":"+33 2 40 52 99 30",
    "sg:postcode":"44470",
    "sg:province":"Pays de Loire",
    "wof:name":"Esox S.a.",
    "wof:placetype":"venue"
},
  "geometry": {"coordinates":[-1.492114,47.297066],"type":"Point"}
}