{
  "type": "Feature",
  "properties": {
    "addr:full":"60, Rue Boucher de Perthes, 59100 Roubaix Nord Pas-de-Calais",
    "addr:housenumber":"60",
    "addr:postcode":"59100",
    "addr:street":"Rue Boucher De Perthes",
    "iso:country":"FR",
    "sg:address":"60, Rue Boucher de Perthes, 59100 Roubaix",
    "sg:orig_category":"Unclassifiable Establishments",
    "sg:phone":"+33 3 20 26 55 44",
    "sg:province":"Nord Pas-de-Calais",
    "wof:name":"Dumortier S.a.",
    "wof:placetype":"venue"
},
  "geometry": {"coordinates":[3.155936,50.69257],"type":"Point"}
}