{
  "type": "Feature",
  "properties": {
    "iso:country":"FR",
    "sg:address":"2e Av du Port Fluvial de Santes",
    "sg:city":"Haubourdin",
    "sg:orig_category":"Non-Classified Establishments",
    "sg:phone":"+33 3 20 50 57 67",
    "sg:postcode":"59320",
    "sg:province":"Nord Pas-de-Calais",
    "wof:name":"Loxam S.a.",
    "wof:placetype":"venue"
},
  "geometry": {"coordinates":[2.984869,50.61124],"type":"Point"}
}