{
  "type": "Feature",
  "properties": {
    "addr:full":"Faubourg de Cambrai Le Cateau Cambr\u00e9sis Nord Pas-de-Calais 59360",
    "addr:postcode":"59360",
    "addr:street":"Faubourg De Cambrai;Pas-De-Calais",
    "iso:country":"FR",
    "sg:address":"Faubourg de Cambrai",
    "sg:city":"Le Cateau Cambr\u00e9sis",
    "sg:orig_category":"Unclassifiable Establishments",
    "sg:phone":"+33 3 27 84 00 25",
    "sg:postcode":"59360",
    "sg:province":"Nord Pas-de-Calais",
    "wof:name":"Caffiaux Et Debatte S.a.",
    "wof:placetype":"venue"
},
  "geometry": {"coordinates":[3.543052,50.105213],"type":"Point"}
}