{
  "type": "Feature",
  "properties": {
    "iso:country":"FR",
    "sg:address":"87, Rue Ambroise Croizat, 08700 Nouzonville",
    "sg:city":"Gespunsart",
    "sg:orig_category":"Unclassifiable Establishments",
    "sg:phone":"+33 3 24 53 17 23",
    "sg:postcode":"08700",
    "sg:province":"Champagne",
    "wof:name":"Aceti S.a.r.l.",
    "wof:placetype":"venue"
},
  "geometry": {"coordinates":[4.759826,49.816708],"type":"Point"}
}