{
  "type": "Feature",
  "properties": {
    "addr:full":"142, Rue du Bac, 75007 Paris Ile de France",
    "addr:housenumber":"142",
    "addr:postcode":"75007",
    "addr:street":"Rue Du Bac",
    "iso:country":"FR",
    "sg:address":"142, Rue du Bac, 75007 Paris",
    "sg:orig_category":"Non-Classified Establishments",
    "sg:phone":"+33 1 44 39 11 11",
    "sg:province":"Ile de France",
    "wof:name":"Point De Vue S.a.r.l.",
    "wof:placetype":"venue"
},
  "geometry": {"coordinates":[2.323672,48.850819],"type":"Point"}
}