{
  "type": "Feature",
  "properties": {
    "addr:full":"Avenue De Monthorin 35420 Louvigne Du Desert La Bazouge-du-D\u00e9sert Bretagne 35420",
    "addr:postcode":"35420;35420",
    "addr:street":"Avenue De Monthorin;Bazouge-Du-De\u0301Sert",
    "iso:country":"FR",
    "sg:address":"Avenue De Monthorin 35420 Louvigne Du Desert",
    "sg:city":"La Bazouge-du-D\u00e9sert",
    "sg:classifiers":[
        {
            "category":"Manufacturing",
            "subcategory":"Wood Products",
            "type":"Manufacturing & Wholesale Goods"
        }
    ],
    "sg:phone":"+33 2 99 98 55 05",
    "sg:postcode":"35420",
    "sg:province":"Bretagne",
    "sg:tags":[
        "professional",
        "furniture"
    ],
    "wof:name":"Adaf Somatherm",
    "wof:placetype":"venue"
},
  "geometry": {"coordinates":[-1.133197,48.473816],"type":"Point"}
}