{
  "type": "Feature",
  "properties": {
    "addr:full":"10 bis, Rue des Noualles, 21240 Talant Talant Bourgogne 21240",
    "addr:housenumber":"10 bis",
    "addr:postcode":"21240;21240",
    "addr:street":"Rue Des Noualles;Bourgogne",
    "iso:country":"FR",
    "sg:address":"10 bis, Rue des Noualles, 21240 Talant",
    "sg:city":"Talant",
    "sg:orig_category":"Non-Classified Establishments",
    "sg:phone":"+33 3 80 55 01 15",
    "sg:postcode":"21240",
    "sg:province":"Bourgogne",
    "wof:name":"Doggher Company S.a.r.l.",
    "wof:placetype":"venue"
},
  "geometry": {"coordinates":[5.004677,47.335678],"type":"Point"}
}