{
  "type": "Feature",
  "properties": {
    "iso:country":"FR",
    "sg:address":"r Fieuzal ZAC BP 16 33520 Bruges",
    "sg:city":"Bruges",
    "sg:classifiers":[
        {
            "category":"Government",
            "subcategory":"Department Of Motor Vehicles",
            "type":"Public Place"
        }
    ],
    "sg:phone":"+33 5 57 92 18 18",
    "sg:postcode":"33520",
    "sg:province":"Aquitaine",
    "sg:tags":[
        "equipment",
        "industrial",
        "transport",
        "motor-cars"
    ],
    "wof:name":"Bacqueyrisses",
    "wof:placetype":"venue"
},
  "geometry": {"coordinates":[-0.597205,44.887089],"type":"Point"}
}