{
  "type": "Feature",
  "properties": {
    "iso:country":"FR",
    "sg:address":"10, Rue d'Ouessant - ZA le Pontay, 35760 Saint Gr\u00e9goire",
    "sg:city":"Montgermont",
    "sg:orig_category":"Non-Classified Establishments",
    "sg:phone":"+33 2 23 25 05 80",
    "sg:postcode":"35760",
    "sg:province":"Bretagne",
    "wof:name":"I.n.f.r.e.p. S.n.c.",
    "wof:placetype":"venue"
},
  "geometry": {"coordinates":[-1.690742,48.159409],"type":"Point"}
}