{
  "type": "Feature",
  "properties": {
    "addr:full":"Zi De Feuqui\u00e8res 60960 Feuqui\u00e8res Picardie",
    "addr:postcode":"60960",
    "addr:street":"Zi De Feuquie\u0300Res",
    "iso:country":"FR",
    "sg:address":"Zi De Feuqui\u00e8res 60960 Feuqui\u00e8res",
    "sg:classifiers":[
        {
            "category":"Professional",
            "type":"Services"
        }
    ],
    "sg:phone":"+33 3 44 46 09 52",
    "sg:province":"Picardie",
    "sg:tags":[
        "transport",
        "road"
    ],
    "wof:name":"Dael Jean Michel Gabriel Alphonse",
    "wof:placetype":"venue"
},
  "geometry": {"coordinates":[1.844635,49.647308],"type":"Point"}
}