{
  "type": "Feature",
  "properties": {
    "addr:full":"Zi De Bellevue 22970 Ploumagoar Ploumagoar Bretagne 22970",
    "addr:postcode":"22970;ploumagoar;22970",
    "addr:street":"Zi De Bellevue",
    "iso:country":"FR",
    "sg:address":"Zi De Bellevue 22970 Ploumagoar",
    "sg:city":"Ploumagoar",
    "sg:orig_category":"Miscellaneous Products",
    "sg:phone":"+33 2 96 43 92 32",
    "sg:postcode":"22970",
    "sg:province":"Bretagne",
    "wof:name":"Sarl Calvez Publicite",
    "wof:placetype":"venue"
},
  "geometry": {"coordinates":[-3.13226,48.54538],"type":"Point"}
}