{
  "type": "Feature",
  "properties": {
    "addr:full":"Centre Internation de Fr\u00eat Montoir de Bretagne Pays de Loire 44550",
    "addr:postcode":"44550",
    "iso:country":"FR",
    "sg:address":"Centre Internation de Fr\u00eat",
    "sg:city":"Montoir de Bretagne",
    "sg:orig_category":"Non-Classified Establishments",
    "sg:phone":"+33 2 40 90 06 00",
    "sg:postcode":"44550",
    "sg:province":"Pays de Loire",
    "wof:name":"Philippe Fauveder Et Compagnie S.a.r.l.",
    "wof:placetype":"venue"
},
  "geometry": {"coordinates":[-2.153179,47.327759],"type":"Point"}
}