{
  "type": "Feature",
  "properties": {
    "addr:full":"76 Rue Du Devau 88340 Le Val D'Ajol Lorraine 88340",
    "addr:housenumber":"76",
    "addr:postcode":"88340;88340",
    "addr:street":"Rue Du Devau;D'Ajol Lorraine",
    "iso:country":"FR",
    "sg:address":"76 Rue Du Devau 88340 Le Val D'Ajol",
    "sg:classifiers":[
        {
            "category":"Shopping",
            "subcategory":"Clothing, Apparel, & Fashions",
            "type":"Retail Goods"
        }
    ],
    "sg:phone":"+33 3 29 66 50 11",
    "sg:postcode":"88340",
    "sg:province":"Lorraine",
    "sg:tags":[
        "textile",
        "clothing",
        "clothes"
    ],
    "wof:name":"Manuval Sarl",
    "wof:placetype":"venue"
},
  "geometry": {"coordinates":[6.462279,47.95203],"type":"Point"}
}