{
  "type": "Feature",
  "properties": {
    "addr:full":"61 Rue Pierre Charron 75008 Paris Ile de France 75008",
    "addr:housenumber":"61",
    "addr:postcode":"75008;75008",
    "addr:street":"Rue Pierre Charron",
    "iso:country":"FR",
    "sg:address":"61 Rue Pierre Charron 75008 Paris",
    "sg:classifiers":[
        {
            "category":"Professional",
            "subcategory":"Business Services",
            "type":"Services"
        }
    ],
    "sg:phone":"+33 1 53 76 88 00",
    "sg:postcode":"75008",
    "sg:province":"Ile de France",
    "sg:tags":[
        "training",
        "advice"
    ],
    "wof:name":"Groupe Edh",
    "wof:placetype":"venue"
},
  "geometry": {"coordinates":[2.304024,48.87006],"type":"Point"}
}