{
  "type": "Feature",
  "properties": {
    "addr:full":"Rte D'Anor Zi 59610 Fourmies Nord Pas-de-Calais 59610",
    "addr:postcode":"59610;59610",
    "addr:street":"Rte D'Anor Zi",
    "iso:country":"FR",
    "sg:address":"Rte D'Anor Zi 59610 Fourmies",
    "sg:classifiers":[
        {
            "category":"Wholesale",
            "subcategory":"Medical Equipment & Supplies",
            "type":"Manufacturing & Wholesale Goods"
        }
    ],
    "sg:phone":"+33 3 27 56 46 00",
    "sg:postcode":"59610",
    "sg:province":"Nord Pas-de-Calais",
    "sg:tags":[
        "instrument",
        "health",
        "-",
        "precision"
    ],
    "wof:name":"Medtronic France",
    "wof:placetype":"venue"
},
  "geometry": {"coordinates":[4.052324,50.004627],"type":"Point"}
}