{
  "type": "Feature",
  "properties": {
    "addr:full":"3, All\u00e9e de la Combe, 69380 Lissieu Rhone-Alpes 69380",
    "addr:housenumber":"3",
    "addr:postcode":"69380;69380",
    "addr:street":"Alle\u0301E De La Combe",
    "iso:country":"FR",
    "sg:address":"3, All\u00e9e de la Combe, 69380 Lissieu",
    "sg:orig_category":"Unclassifiable Establishments",
    "sg:phone":"+33 4 78 47 05 54",
    "sg:postcode":"69380",
    "sg:province":"Rhone-Alpes",
    "wof:name":"R.b. Technologies S.a.r.l. - Roland Bolle Technologies",
    "wof:placetype":"venue"
},
  "geometry": {"coordinates":[4.739114,45.840839],"type":"Point"}
}