{
  "type": "Feature",
  "properties": {
    "iso:country":"FR",
    "sg:address":"3bis, Rue du Havre, 67100 Strasbourg",
    "sg:city":"Strasbourg",
    "sg:orig_category":"Unclassifiable Establishments",
    "sg:phone":"+33 3 88 41 52 52",
    "sg:postcode":"67100",
    "sg:province":"Alsace",
    "wof:name":"Pro Hygi\u00e8ne Service Est S.a.s",
    "wof:placetype":"venue"
},
  "geometry": {"coordinates":[7.785727,48.563782],"type":"Point"}
}