{
  "type": "Feature",
  "properties": {
    "addr:full":"39, Rue Waldeck Rousseau - Carrefour des Biards, 50540 Isigny le Buat Isigny-le-Buat Basse Normandie 50540",
    "addr:housenumber":"39",
    "addr:postcode":"50540;50540",
    "addr:street":"Rue Waldeck Rousseau;Isigny-Le-Buat Basse",
    "iso:country":"FR",
    "sg:address":"39, Rue Waldeck Rousseau - Carrefour des Biards, 50540 Isigny le Buat",
    "sg:city":"Isigny-le-Buat",
    "sg:orig_category":"Unclassifiable Establishments",
    "sg:phone":"+33 2 33 49 85 50",
    "sg:postcode":"50540",
    "sg:province":"Basse Normandie",
    "wof:name":"C.b.m. Maryves S.a.r.l.",
    "wof:placetype":"venue"
},
  "geometry": {"coordinates":[-1.185579,48.584629],"type":"Point"}
}