{
  "type": "Feature",
  "properties": {
    "addr:full":"Rue de Paray 91490 MILLY LA FORET Ile de France 91490",
    "addr:postcode":"91490;91490",
    "addr:street":"Rue De Paray",
    "iso:country":"FR",
    "sg:address":"Rue de Paray 91490 MILLY LA FORET",
    "sg:classifiers":[
        {
            "category":"Food & Beverages",
            "subcategory":"Meat & Fish",
            "type":"Retail Goods"
        }
    ],
    "sg:phone":"+33 1 64 98 80 23",
    "sg:postcode":"91490",
    "sg:province":"Ile de France",
    "sg:tags":[
        "meal"
    ],
    "wof:name":"Ets Charvet P\u00e8re Et Fils Sa",
    "wof:placetype":"venue"
},
  "geometry": {"coordinates":[2.480723,48.402084],"type":"Point"}
}