{
  "type": "Feature",
  "properties": {
    "addr:full":"8 Rue Du Chesnay Beauregard 35760 St Gr\u00e9goire Montgermont Bretagne 35760",
    "addr:housenumber":"8",
    "addr:postcode":"35760;montgermont;35760",
    "addr:street":"Rue Du Chesnay Beauregard",
    "iso:country":"FR",
    "sg:address":"8 Rue Du Chesnay Beauregard 35760 St Gr\u00e9goire",
    "sg:city":"Montgermont",
    "sg:orig_category":"Information Technology Office equipment Paper and Cardboard Paper and cardboard - finished goods Per",
    "sg:phone":"+33 2 23 20 04 60",
    "sg:postcode":"35760",
    "sg:province":"Bretagne",
    "wof:name":"Office Depot France Snc",
    "wof:placetype":"venue"
},
  "geometry": {"coordinates":[-1.690513,48.137127],"type":"Point"}
}