{
  "type": "Feature",
  "properties": {
    "addr:full":"B.P. 4, 67760 Gambsheim^^Rte d'Offendorf, 67760 Gambsheim Gambsheim Alsace 67760",
    "addr:housenumber":"4",
    "addr:postcode":"67760;67760;67760",
    "addr:street":"B.P.;D'Offendorf",
    "iso:country":"FR",
    "sg:address":"B.P. 4, 67760 Gambsheim^^Rte d'Offendorf, 67760 Gambsheim",
    "sg:city":"Gambsheim",
    "sg:orig_category":"Non-Classified Establishments",
    "sg:phone":"+33 3 88 59 79 79",
    "sg:postcode":"67760",
    "sg:province":"Alsace",
    "wof:name":"S.a.s.i. S.a. - Soci\u00e9t\u00e9 Alsacienne De Services Industriels",
    "wof:placetype":"venue"
},
  "geometry": {"coordinates":[7.883,48.690681],"type":"Point"}
}