{
  "type": "Feature",
  "properties": {
    "addr:full":"74370 Pringy Rhone-Alpes 74370",
    "addr:postcode":"74370;74370",
    "iso:country":"FR",
    "sg:address":"74370 Pringy",
    "sg:orig_category":"Unclassifiable Establishments",
    "sg:phone":"+33 4 50 27 28 94",
    "sg:postcode":"74370",
    "sg:province":"Rhone-Alpes",
    "wof:name":"Sitel S.a.",
    "wof:placetype":"venue"
},
  "geometry": {"coordinates":[6.16005,45.961311],"type":"Point"}
}