{
  "type": "Feature",
  "properties": {
    "iso:country":"FR",
    "sg:address":"81, Av. d'Orl\u00e9ans, 41300 Salbris",
    "sg:city":"Salbris",
    "sg:orig_category":"Unclassifiable Establishments",
    "sg:phone":"+33 2 54 97 17 76",
    "sg:postcode":"41300",
    "sg:province":"Centre",
    "wof:name":"La Sauldraie S.a.r.l.",
    "wof:placetype":"venue"
},
  "geometry": {"coordinates":[2.05198,47.426991],"type":"Point"}
}