{
  "type": "Feature",
  "properties": {
    "addr:full":"Zi De Bel Air 34570 Vailhauques Languedoc-Roussillon 34570",
    "addr:postcode":"34570;34570",
    "addr:street":"Zi De Bel Air",
    "iso:country":"FR",
    "sg:address":"Zi De Bel Air 34570 Vailhauques",
    "sg:classifiers":[
        {
            "category":"Shopping",
            "subcategory":"Computers & Home Electronics",
            "type":"Retail Goods"
        }
    ],
    "sg:phone":"+33 4 67 10 40 40",
    "sg:postcode":"34570",
    "sg:province":"Languedoc-Roussillon",
    "sg:tags":[
        "equipment",
        "electrical",
        "component",
        "electric",
        "electronic"
    ],
    "wof:name":"Gespach Industrie",
    "wof:placetype":"venue"
},
  "geometry": {"coordinates":[3.717265,43.671635],"type":"Point"}
}