{
  "type": "Feature",
  "properties": {
    "iso:country":"FR",
    "sg:address":"Zi Du Coin 42400 St Chamond",
    "sg:classifiers":[
        {
            "category":"Manufacturing",
            "subcategory":"Tools & Machinery",
            "type":"Manufacturing & Wholesale Goods"
        }
    ],
    "sg:phone":"+33 4 77 22 61 55",
    "sg:postcode":"42400",
    "sg:province":"Rhone-Alpes",
    "sg:tags":[
        "metallurgy",
        "metalworking"
    ],
    "wof:name":"Dolex Sarl",
    "wof:placetype":"venue"
},
  "geometry": {"coordinates":[4.512304,45.473969],"type":"Point"}
}