{
  "type": "Feature",
  "properties": {
    "addr:full":"84/88, Bd de la Mission Marchand, 92411 Courbevoie C\u00e9dex \u00cele-de-France",
    "addr:housenumber":"84 / 88",
    "addr:postcode":"92411",
    "addr:street":"Bd De La Mission Marchand;Ce\u0301Dex",
    "iso:country":"FR",
    "sg:address":"84/88, Bd de la Mission Marchand, 92411 Courbevoie C\u00e9dex",
    "sg:orig_category":"Non-Classified Establishments",
    "sg:phone":"+33 1 49 04 70 70",
    "sg:province":"\u00cele-de-France",
    "wof:name":"Technologies Gid S.a.",
    "wof:placetype":"venue"
},
  "geometry": {"coordinates":[2.23986,48.901314],"type":"Point"}
}