{
  "type": "Feature",
  "properties": {
    "addr:full":"51 Grand Rue 68000 Colmar Colmar Alsace 68000",
    "addr:housenumber":"51",
    "addr:postcode":"68000;68000",
    "addr:street":"Grand Rue",
    "iso:country":"FR",
    "sg:address":"51 Grand Rue 68000 Colmar",
    "sg:city":"Colmar",
    "sg:classifiers":[
        {
            "category":"Wholesale",
            "subcategory":"Meat",
            "type":"Manufacturing & Wholesale Goods"
        }
    ],
    "sg:phone":"+33 3 89 41 30 83",
    "sg:postcode":"68000",
    "sg:province":"Alsace",
    "sg:tags":[
        "food",
        "cooked",
        "product",
        "related"
    ],
    "wof:name":"Gustave Tempe Et Fils",
    "wof:placetype":"venue"
},
  "geometry": {"coordinates":[7.357245,48.074726],"type":"Point"}
}