{
  "type": "Feature",
  "properties": {
    "addr:full":"6 rue de la R\u00e9publique; Bolbec; 76210 Haute Normandie 76210",
    "addr:housenumber":"6",
    "addr:postcode":"76210;76210",
    "addr:street":"Rue De La Re\u0301Publique;Normandie",
    "iso:country":"FR",
    "sg:address":"6 rue de la R\u00e9publique; Bolbec; 76210",
    "sg:classifiers":[
        {
            "category":"Banks & Credit Unions",
            "subcategory":"Bank",
            "type":"Services"
        }
    ],
    "sg:phone":"+33 3335310055",
    "sg:postcode":"76210",
    "sg:province":"Haute Normandie",
    "wof:name":"Banque Nationale De Paris",
    "wof:placetype":"venue"
},
  "geometry": {"coordinates":[0.471634,49.571712],"type":"Point"}
}