{
  "type": "Feature",
  "properties": {
    "iso:country":"FR",
    "sg:address":"Rue Vieux Moulins Prolongee Zac De Choisy 88200 Remiremont",
    "sg:classifiers":[
        {
            "category":"Autos & Motor Vehicles",
            "subcategory":"Boat Sales",
            "type":"Retail Goods"
        }
    ],
    "sg:phone":"+33 3 29 23 00 66",
    "sg:postcode":"88200",
    "sg:province":"Lorraine",
    "sg:tags":[
        "metallurgy",
        "-",
        "processing",
        "metal",
        "engineering",
        "metallic",
        "machine",
        "finished",
        "mechanical",
        "metalwor"
    ],
    "wof:name":"Althoffer",
    "wof:placetype":"venue"
},
  "geometry": {"coordinates":[6.592083,48.021435],"type":"Point"}
}