{
  "type": "Feature",
  "properties": {
    "addr:full":"St Amand 32800 Eauze Midi Pyr\u00e9n\u00e9es 32800",
    "addr:postcode":"32800;32800",
    "addr:street":"St Amand",
    "iso:country":"FR",
    "sg:address":"St Amand 32800 Eauze",
    "sg:classifiers":[
        {
            "category":"Food Court",
            "type":"Food & Drink"
        }
    ],
    "sg:phone":"+33 5 62 09 87 82",
    "sg:postcode":"32800",
    "sg:province":"Midi Pyr\u00e9n\u00e9es",
    "sg:tags":[
        "product",
        "related"
    ],
    "wof:name":"Ste Civile Viticole Chateau Du Tariquet",
    "wof:placetype":"venue"
},
  "geometry": {"coordinates":[0.143145,43.845226],"type":"Point"}
}