{
  "type": "Feature",
  "properties": {
    "iso:country":"FR",
    "sg:address":"26 Bd De Courtais 03100 Montlu\u00e7on",
    "sg:city":"Montlu\u00e7on",
    "sg:classifiers":[
        {
            "category":"Travel",
            "subcategory":"Hotels & Motels",
            "type":"Entertainment"
        }
    ],
    "sg:phone":"+33 4 70 05 88 52",
    "sg:postcode":"03100",
    "sg:province":"Auvergne",
    "sg:tags":[
        "hotels",
        "business",
        "restaurant"
    ],
    "wof:name":"Patapain",
    "wof:placetype":"venue"
},
  "geometry": {"coordinates":[2.601564,46.339138],"type":"Point"}
}