{
  "type": "Feature",
  "properties": {
    "iso:country":"FR",
    "sg:address":"26, Mail Ouest, 45300 Pithiviers",
    "sg:city":"Courcelles",
    "sg:orig_category":"Unclassifiable Establishments",
    "sg:phone":"+33 2 38 30 00 61",
    "sg:postcode":"45300",
    "sg:province":"Centre",
    "wof:name":"Fraisy S.a.",
    "wof:placetype":"venue"
},
  "geometry": {"coordinates":[2.252805,48.172359],"type":"Point"}
}