{
  "type": "Feature",
  "properties": {
    "addr:full":"Domaine de Maridan 32100 Condom Midi Pyr\u00e9n\u00e9es",
    "addr:postcode":"32100",
    "iso:country":"FR",
    "sg:address":"Domaine de Maridan 32100 Condom",
    "sg:orig_category":"Unclassifiable Establishments",
    "sg:phone":"+33 5 62 28 26 88",
    "sg:province":"Midi Pyr\u00e9n\u00e9es",
    "wof:name":"B.s.a.d. S.a.",
    "wof:placetype":"venue"
},
  "geometry": {"coordinates":[0.359707,43.933029],"type":"Point"}
}