{
  "type": "Feature",
  "properties": {
    "addr:full":"10 Route Nationale 89190 PONT SUR VANNE Bagneaux Bourgogne 89190",
    "addr:housenumber":"10",
    "addr:postcode":"89190;89190",
    "addr:street":"Route Nationale",
    "iso:country":"FR",
    "sg:address":"10 Route Nationale 89190 PONT SUR VANNE",
    "sg:city":"Bagneaux",
    "sg:classifiers":[
        {
            "category":"Professional",
            "subcategory":"Business Services",
            "type":"Services"
        }
    ],
    "sg:phone":"+33 3 86 88 20 26",
    "sg:postcode":"89190",
    "sg:province":"Bourgogne",
    "sg:tags":[
        "agency",
        "export"
    ],
    "wof:name":"Afa Trading Sas",
    "wof:placetype":"venue"
},
  "geometry": {"coordinates":[3.43426,48.181992],"type":"Point"}
}