{
  "type": "Feature",
  "properties": {
    "addr:full":"1 Rue Des Tanneries 87300 Bellac Limousin 87300",
    "addr:housenumber":"1",
    "addr:postcode":"87300;87300",
    "addr:street":"Rue Des Tanneries",
    "iso:country":"FR",
    "sg:address":"1 Rue Des Tanneries 87300 Bellac",
    "sg:classifiers":[
        {
            "category":"Real Estate",
            "subcategory":"Surveying",
            "type":"Services"
        }
    ],
    "sg:phone":"+33 5 55 68 06 25",
    "sg:postcode":"87300",
    "sg:province":"Limousin",
    "sg:tags":[
        "leather",
        "raw",
        "material",
        "-",
        "shoe"
    ],
    "wof:name":"Tannerie Gal Sarl",
    "wof:placetype":"venue"
},
  "geometry": {"coordinates":[1.048684,46.116425],"type":"Point"}
}