{
  "type": "Feature",
  "properties": {
    "addr:full":"22, Rue Jabouret, 69250 Fleurieu sur Sa\u00f4ne Rhone-Alpes 69250",
    "addr:housenumber":"22",
    "addr:postcode":"69250;69250",
    "addr:street":"Rue Jabouret",
    "iso:country":"FR",
    "sg:address":"22, Rue Jabouret, 69250 Fleurieu sur Sa\u00f4ne",
    "sg:orig_category":"Unclassifiable Establishments",
    "sg:phone":"+33 4 72 08 72 00",
    "sg:postcode":"69250",
    "sg:province":"Rhone-Alpes",
    "wof:name":"S.d.e.m. S.a.",
    "wof:placetype":"venue"
},
  "geometry": {"coordinates":[4.849301,45.865505],"type":"Point"}
}