{
  "type": "Feature",
  "properties": {
    "addr:full":"82 Bd Haussmann 75008 Paris Ile de France 75008",
    "addr:housenumber":"82",
    "addr:postcode":"75008;75008",
    "addr:street":"Bd Haussmann",
    "iso:country":"FR",
    "sg:address":"82 Bd Haussmann 75008 Paris",
    "sg:classifiers":[
        {
            "category":"Professional",
            "subcategory":"Advertising",
            "type":"Services"
        }
    ],
    "sg:phone":"+33 1 44 70 65 10",
    "sg:postcode":"75008",
    "sg:province":"Ile de France",
    "sg:tags":[
        "marketing",
        "medium",
        "communication"
    ],
    "wof:name":"Rbc Associes",
    "wof:placetype":"venue"
},
  "geometry": {"coordinates":[2.325228,48.874172],"type":"Point"}
}