{
  "type": "Feature",
  "properties": {
    "addr:full":"Ld La Duquerie 37390 Chanceaux Sur Choisille La Membrolle-sur-Choisille Centre 37390",
    "addr:housenumber":"membrolle-sur-choisille",
    "addr:postcode":"37390;37390",
    "addr:street":"Ld",
    "iso:country":"FR",
    "sg:address":"Ld La Duquerie 37390 Chanceaux Sur Choisille",
    "sg:city":"La Membrolle-sur-Choisille",
    "sg:classifiers":[
        {
            "category":"Manufacturing",
            "subcategory":"Glass & Minerals",
            "type":"Manufacturing & Wholesale Goods"
        }
    ],
    "sg:phone":"+33 2 47 55 11 11",
    "sg:postcode":"37390",
    "sg:province":"Centre",
    "sg:tags":[
        "building",
        "material"
    ],
    "wof:name":"Beton Chantiers De L'ouest Bco",
    "wof:placetype":"venue"
},
  "geometry": {"coordinates":[0.692235,47.461201],"type":"Point"}
}