{
  "type": "Feature",
  "properties": {
    "iso:country":"FR",
    "sg:address":"172, Rte d'Orl\u00e9ans - ZI Ingr\u00e9, 45140 Ingr\u00e9",
    "sg:city":"Ingr\u00e9",
    "sg:orig_category":"Unclassifiable Establishments",
    "sg:phone":"+33 2 38 22 33 66",
    "sg:postcode":"45140",
    "sg:province":"Centre",
    "wof:name":"Express Terminals Limited",
    "wof:placetype":"venue"
},
  "geometry": {"coordinates":[1.8278,47.919689],"type":"Point"}
}