{
  "type": "Feature",
  "properties": {
    "addr:full":"20 avenue Carnot 78800 Houilles Ile de France 78800",
    "addr:housenumber":"20",
    "addr:postcode":"78800;ile;78800",
    "addr:street":"Avenue Carnot;France",
    "iso:country":"FR",
    "sg:address":"20 avenue Carnot 78800 Houilles",
    "sg:classifiers":[
        {
            "category":"Home & Garden",
            "subcategory":"Building Materials",
            "type":"Retail Goods"
        }
    ],
    "sg:phone":"+33 1 39 68 22 16",
    "sg:postcode":"78800",
    "sg:province":"Ile de France",
    "sg:tags":[
        "slab",
        "marble"
    ],
    "wof:name":"Marbres Galrao France Sa",
    "wof:placetype":"venue"
},
  "geometry": {"coordinates":[2.188481,48.922962],"type":"Point"}
}