{
  "type": "Feature",
  "properties": {
    "addr:full":"Rte de Taulignan Grillon Provence-Alpes-C\u00f4te d'Azur 84600",
    "addr:postcode":"84600",
    "addr:street":"Rte De Taulignan Grillon",
    "iso:country":"FR",
    "sg:address":"Rte de Taulignan",
    "sg:city":"Grillon",
    "sg:orig_category":"Unclassifiable Establishments",
    "sg:phone":"+33 4 90 28 42 42",
    "sg:postcode":"84600",
    "sg:province":"Provence-Alpes-C\u00f4te d'Azur",
    "wof:name":"Les Plastiques De Grillon S.n.c.",
    "wof:placetype":"venue"
},
  "geometry": {"coordinates":[4.929575,44.396133],"type":"Point"}
}