{
  "type": "Feature",
  "properties": {
    "addr:full":"35, Rue L\u00e9on Blum, 31140 Saint Alban Midi Pyr\u00e9n\u00e9es",
    "addr:housenumber":"35",
    "addr:postcode":"31140",
    "addr:street":"Rue Le\u0301On Blum",
    "iso:country":"FR",
    "sg:address":"35, Rue L\u00e9on Blum, 31140 Saint Alban",
    "sg:orig_category":"Unclassifiable Establishments",
    "sg:phone":"+33 5 61 70 34 55",
    "sg:province":"Midi Pyr\u00e9n\u00e9es",
    "wof:name":"Biophoton S.a.",
    "wof:placetype":"venue"
},
  "geometry": {"coordinates":[1.419989,43.686775],"type":"Point"}
}