{
  "type": "Feature",
  "properties": {
    "iso:country":"FR",
    "sg:address":"La Grange A Pr\u00e9vaud 17150 Mirambeau",
    "sg:classifiers":[
        {
            "category":"Shopping",
            "type":"Retail Goods"
        }
    ],
    "sg:phone":"+33 5 46 49 61 07",
    "sg:postcode":"17150",
    "sg:province":"Poitou-Charentes",
    "sg:tags":[
        "metallurgy",
        "finished",
        "-",
        "metalworking",
        "metallic"
    ],
    "wof:name":"Sorin Sa",
    "wof:placetype":"venue"
},
  "geometry": {"coordinates":[-0.561945,45.382015],"type":"Point"}
}