{
  "type": "Feature",
  "properties": {
    "addr:full":"Rue De L Egalite Centre Commercial Auchan Cel 53 59155 Faches Thumesnil Nord Pas-de-Calais 59155",
    "addr:housenumber":"53",
    "addr:postcode":"59155;59155",
    "addr:street":"Rue De L Egalite Centre;Thumesnil",
    "iso:country":"FR",
    "sg:address":"Rue De L Egalite Centre Commercial Auchan Cel 53 59155 Faches Thumesnil",
    "sg:classifiers":[
        {
            "category":"Shopping",
            "subcategory":"Clothing, Apparel, & Fashions",
            "type":"Retail Goods"
        }
    ],
    "sg:phone":"+33 3 20 97 97 13",
    "sg:postcode":"59155",
    "sg:province":"Nord Pas-de-Calais",
    "sg:tags":[
        "textile",
        "clothing",
        "clothes"
    ],
    "wof:name":"Promod",
    "wof:placetype":"venue"
},
  "geometry": {"coordinates":[3.069715,50.602951],"type":"Point"}
}