{
  "type": "Feature",
  "properties": {
    "addr:full":"ZI du Sans Souci Roques Midi Pyr\u00e9n\u00e9es 31120",
    "addr:postcode":"31120",
    "addr:street":"Zi Du Sans Souci Roques",
    "iso:country":"FR",
    "sg:address":"ZI du Sans Souci",
    "sg:city":"Roques",
    "sg:orig_category":"Non-Classified Establishments",
    "sg:phone":"+33 5 61 56 77 88",
    "sg:postcode":"31120",
    "sg:province":"Midi Pyr\u00e9n\u00e9es",
    "wof:name":"Saint-gobain Stradal S.a.",
    "wof:placetype":"venue"
},
  "geometry": {"coordinates":[1.375523,43.508945],"type":"Point"}
}