{
  "type": "Feature",
  "properties": {
    "addr:full":"Marennes 17270 Montguyon Poitou-Charentes",
    "addr:postcode":"17270",
    "iso:country":"FR",
    "sg:address":"Marennes 17270 Montguyon",
    "sg:classifiers":[
        {
            "category":"Professional",
            "type":"Services"
        }
    ],
    "sg:phone":"+33 5 46 04 11 38",
    "sg:province":"Poitou-Charentes",
    "sg:tags":[
        "transport",
        "road"
    ],
    "wof:name":"Bastere Freres Sarl",
    "wof:placetype":"venue"
},
  "geometry": {"coordinates":[-0.172815,45.231823],"type":"Point"}
}