{
  "type": "Feature",
  "properties": {
    "addr:full":"2, Rue Pichou, 27400 Louviers Haute Normandie 27400",
    "addr:housenumber":"2",
    "addr:postcode":"27400;27400",
    "addr:street":"Rue Pichou;Haute Normandie",
    "iso:country":"FR",
    "sg:address":"2, Rue Pichou, 27400 Louviers",
    "sg:orig_category":"Non-Classified Establishments",
    "sg:phone":"+33 2 32 40 28 68",
    "sg:postcode":"27400",
    "sg:province":"Haute Normandie",
    "wof:name":"Dutheil S.a.r.l.",
    "wof:placetype":"venue"
},
  "geometry": {"coordinates":[1.166965,49.204777],"type":"Point"}
}