{
  "type": "Feature",
  "properties": {
    "addr:full":"B.P. 2099, 13745 Vitrolles C\u00e9dex^^Impasse Thal\u00e8s - ZI de la Couperigne, 13127 Vitrolles Provence-Alpes-C\u00f4te d'Azur",
    "addr:housenumber":"2099",
    "addr:postcode":"13745;13127",
    "addr:street":"B.P.;Zi De La Couperigne",
    "iso:country":"FR",
    "sg:address":"B.P. 2099, 13745 Vitrolles C\u00e9dex^^Impasse Thal\u00e8s - ZI de la Couperigne, 13127 Vitrolles",
    "sg:orig_category":"Non-Classified Establishments",
    "sg:phone":"+33 4 42 10 01 80",
    "sg:province":"Provence-Alpes-C\u00f4te d'Azur",
    "wof:name":"Loreste France S.a.",
    "wof:placetype":"venue"
},
  "geometry": {"coordinates":[5.253005,43.449944],"type":"Point"}
}