{
  "type": "Feature",
  "properties": {
    "iso:country":"FR",
    "sg:address":"84 Rue Des Acieries 42000 St Etienne",
    "sg:classifiers":[
        {
            "category":"Professional",
            "subcategory":"Engineering",
            "type":"Services"
        }
    ],
    "sg:phone":"+33 4 77 91 37 91",
    "sg:postcode":"42000",
    "sg:province":"Rhone-Alpes",
    "sg:tags":[
        "machine",
        "-",
        "environment",
        "equipment",
        "machinery",
        "mechanical"
    ],
    "wof:name":"Prosegur Systemes (c2s)",
    "wof:placetype":"venue"
},
  "geometry": {"coordinates":[4.394202,45.45779],"type":"Point"}
}