{
  "type": "Feature",
  "properties": {
    "iso:country":"FR",
    "sg:address":"47, Rue de la Division Leclerc, 78460 Chevreuse",
    "sg:orig_category":"Unclassifiable Establishments",
    "sg:phone":"+33 1 30 52 15 41",
    "sg:province":"Ile de France",
    "wof:name":"Coutancier Et Fils S.a.r.l.",
    "wof:placetype":"venue"
},
  "geometry": {"coordinates":[2.040838,48.707336],"type":"Point"}
}