{
  "type": "Feature",
  "properties": {
    "addr:full":"1 Rue Herv\u00e9 De Gu\u00e9briant Landerneau Bretagne 29800",
    "addr:housenumber":"1",
    "addr:postcode":"29800",
    "addr:street":"Rue Herve\u0301 De Gue\u0301Briant Landerneau Bretagne",
    "iso:country":"FR",
    "sg:address":"1 Rue Herv\u00e9 De Gu\u00e9briant",
    "sg:city":"Landerneau",
    "sg:classifiers":[
        {
            "category":"Banks & Credit Unions",
            "subcategory":"Financial Services",
            "type":"Services"
        }
    ],
    "sg:phone":"+33 2 98 85 70 00",
    "sg:postcode":"29800",
    "sg:province":"Bretagne",
    "sg:tags":[
        "banking",
        "finance",
        "insurance"
    ],
    "wof:name":"Gie Groupama Gestion D Armor",
    "wof:placetype":"venue"
},
  "geometry": {"coordinates":[-4.257799,48.450768],"type":"Point"}
}