{
  "type": "Feature",
  "properties": {
    "iso:country":"FR",
    "sg:address":"ZI 21420 SAVIGNY LES BEAUNE",
    "sg:city":"Aloxe-Corton",
    "sg:classifiers":[
        {
            "category":"Recreation",
            "subcategory":"Fishing",
            "type":"Entertainment"
        }
    ],
    "sg:phone":"+33 3 80 22 94 21",
    "sg:postcode":"21420",
    "sg:province":"Bourgogne",
    "sg:tags":[
        "equipment"
    ],
    "wof:name":"Whitney Bfc Sarl",
    "wof:placetype":"venue"
},
  "geometry": {"coordinates":[4.825039,47.060619],"type":"Point"}
}