{
  "type": "Feature",
  "properties": {
    "addr:full":"81, Cours de Verdun - R\u00e9sidence le Moli\u00e8re, 01100 Oyonnax Rhone-Alpes 01100",
    "addr:housenumber":"81",
    "addr:postcode":"01100;01100",
    "addr:street":"Cours De Verdun Re\u0301Sidence Le Molie\u0300Re",
    "iso:country":"FR",
    "sg:address":"81, Cours de Verdun - R\u00e9sidence le Moli\u00e8re, 01100 Oyonnax",
    "sg:orig_category":"Unclassifiable Establishments",
    "sg:phone":"+33 4 74 73 52 67",
    "sg:postcode":"01100",
    "sg:province":"Rhone-Alpes",
    "wof:name":"Japlan S.a.r.l.",
    "wof:placetype":"venue"
},
  "geometry": {"coordinates":[5.646455,46.258595],"type":"Point"}
}