{
  "type": "Feature",
  "properties": {
    "iso:country":"FR",
    "sg:address":"148 Av Jean Lorrain 76400 F\u00e9camp",
    "sg:classifiers":[
        {
            "category":"Bakery",
            "type":"Food & Drink"
        }
    ],
    "sg:phone":"+33 2 35 28 01 08",
    "sg:postcode":"76400",
    "sg:province":"Haute Normandie",
    "sg:tags":[
        "cake",
        "product",
        "related",
        "bread"
    ],
    "wof:name":"Barray Richard Sarl",
    "wof:placetype":"venue"
},
  "geometry": {"coordinates":[0.380608,49.761925],"type":"Point"}
}