{
  "type": "Feature",
  "properties": {
    "iso:country":"FR",
    "sg:address":"61, Rue Charles le Goffic, 29000 Quimper",
    "sg:city":"Quimper",
    "sg:orig_category":"Non-Classified Establishments",
    "sg:phone":"+33 2 98 52 21 40",
    "sg:postcode":"29000",
    "sg:province":"Bretagne",
    "wof:name":"Quimper Portage Distribution S.a.r.l.",
    "wof:placetype":"venue"
},
  "geometry": {"coordinates":[-4.064414,47.985588],"type":"Point"}
}