{
  "type": "Feature",
  "properties": {
    "addr:full":"327, Rue des Merci\u00e8res, 69140 Rillieux la Pape Rhone-Alpes",
    "addr:housenumber":"327",
    "addr:postcode":"69140",
    "addr:street":"Rue Des Mercie\u0300Res",
    "iso:country":"FR",
    "sg:address":"327, Rue des Merci\u00e8res, 69140 Rillieux la Pape",
    "sg:orig_category":"Non-Classified Establishments",
    "sg:phone":"+33 4 72 01 81 81",
    "sg:province":"Rhone-Alpes",
    "wof:name":"G.r.s. Valtech S.a.",
    "wof:placetype":"venue"
},
  "geometry": {"coordinates":[4.8734,45.815411],"type":"Point"}
}