{
  "type": "Feature",
  "properties": {
    "addr:full":"Rue de Bruscos Sauvagnon Aquitaine 64230",
    "addr:postcode":"64230",
    "addr:street":"Rue De Bruscos",
    "iso:country":"FR",
    "sg:address":"Rue de Bruscos",
    "sg:city":"Sauvagnon",
    "sg:orig_category":"Non-Classified Establishments",
    "sg:phone":"+33 5 59 33 70 36",
    "sg:postcode":"64230",
    "sg:province":"Aquitaine",
    "wof:name":"Syclope Electronique S.a.",
    "wof:placetype":"venue"
},
  "geometry": {"coordinates":[-0.410669,43.383751],"type":"Point"}
}