{
  "type": "Feature",
  "properties": {
    "addr:full":"Ld Les Chezeaux 18300 Bannay Bannay Centre 18300",
    "addr:housenumber":"bannay",
    "addr:postcode":"18300;18300",
    "addr:street":"Ld",
    "iso:country":"FR",
    "sg:address":"Ld Les Chezeaux 18300 Bannay",
    "sg:city":"Bannay",
    "sg:classifiers":[
        {
            "category":"Professional",
            "subcategory":"Engineering",
            "type":"Services"
        }
    ],
    "sg:phone":"+33 2 48 72 40 42",
    "sg:postcode":"18300",
    "sg:province":"Centre",
    "sg:tags":[
        "machine",
        "-",
        "mechanical"
    ],
    "wof:name":"Picoty Sa Picoty Fioul Services",
    "wof:placetype":"venue"
},
  "geometry": {"coordinates":[2.858315,47.230389],"type":"Point"}
}