{
  "type": "Feature",
  "properties": {
    "iso:country":"FR",
    "sg:address":"Boulevard Jean Xxiii 85303 Challans Cedex",
    "sg:classifiers":[
        {
            "category":"Professional",
            "subcategory":"Business Services",
            "type":"Services"
        }
    ],
    "sg:phone":"+33 2 51 49 54 54",
    "sg:province":"Rhone-Alpes",
    "sg:tags":[
        "training",
        "advice"
    ],
    "wof:name":"College Prive Saint Joseph",
    "wof:placetype":"venue"
},
  "geometry": {"coordinates":[-1.870615,46.836163],"type":"Point"}
}