{
  "type": "Feature",
  "properties": {
    "iso:country":"FR",
    "sg:address":"126 avenue de Marseille 26000 Valence",
    "sg:classifiers":[
        {
            "category":"Industrial Area",
            "type":"Public Place"
        }
    ],
    "sg:phone":"+33 4 75 57 49 49",
    "sg:postcode":"26000",
    "sg:province":"Rhone-Alpes",
    "sg:tags":[
        "box",
        "cardboard"
    ],
    "wof:name":"Cie Europ\u00e9enne De Cartonnages",
    "wof:placetype":"venue"
},
  "geometry": {"coordinates":[4.881903,44.900871],"type":"Point"}
}