{
  "type": "Feature",
  "properties": {
    "iso:country":"FR",
    "sg:address":"B.P. 138, 31676 Lab\u00e8ge C\u00e9dex^^Rue Garance - B\u00e2t. B, 31670 Lab\u00e8ge",
    "sg:orig_category":"Non-Classified Establishments",
    "sg:phone":"+33 5 62 24 88 28",
    "sg:province":"Midi Pyr\u00e9n\u00e9es",
    "wof:name":"Hexalis S.a.",
    "wof:placetype":"venue"
},
  "geometry": {"coordinates":[1.527111,43.529713],"type":"Point"}
}