{
  "type": "Feature",
  "properties": {
    "iso:country":"FR",
    "sg:address":"Zi Croix D'Hins 33380 Marcheprime",
    "sg:city":"Marcheprime",
    "sg:classifiers":[
        {
            "category":"Professional",
            "subcategory":"Engineering",
            "type":"Services"
        }
    ],
    "sg:phone":"+33 5 57 71 11 79",
    "sg:postcode":"33380",
    "sg:province":"Aquitaine",
    "sg:tags":[
        "machine",
        "-",
        "mechanical"
    ],
    "wof:name":"Plastim -aquitaine Sarl",
    "wof:placetype":"venue"
},
  "geometry": {"coordinates":[-0.837088,44.678364],"type":"Point"}
}