{
  "type": "Feature",
  "properties": {
    "iso:country":"FR",
    "sg:address":"16 B Rue Auguste Naudin 86440 Migne Auxances",
    "sg:classifiers":[
        {
            "category":"Wholesale",
            "subcategory":"Medical Equipment & Supplies",
            "type":"Manufacturing & Wholesale Goods"
        }
    ],
    "sg:phone":"+33 5 49 51 64 17",
    "sg:postcode":"86440",
    "sg:province":"Poitou-Charentes",
    "sg:tags":[
        "instrument",
        "health",
        "-",
        "precision"
    ],
    "wof:name":"Sarl Soreau",
    "wof:placetype":"venue"
},
  "geometry": {"coordinates":[0.30602,46.62225],"type":"Point"}
}