{
  "type": "Feature",
  "properties": {
    "addr:full":"Zi Satanne 61190 Tourouvre Tourouvre Basse Normandie 61190",
    "addr:postcode":"61190;61190",
    "iso:country":"FR",
    "sg:address":"Zi Satanne 61190 Tourouvre",
    "sg:city":"Tourouvre",
    "sg:classifiers":[
        {
            "category":"Farming",
            "subcategory":"Farm & Veterinary Services",
            "type":"Manufacturing & Wholesale Goods"
        }
    ],
    "sg:phone":"+33 2 33 85 30 00",
    "sg:postcode":"61190",
    "sg:province":"Basse Normandie",
    "sg:tags":[
        "livestock",
        "business",
        "advice",
        "wood",
        "agriculture",
        "furniture"
    ],
    "wof:name":"Perche (scierie Exploitation Forestiere Du) Sa",
    "wof:placetype":"venue"
},
  "geometry": {"coordinates":[0.651295,48.590485],"type":"Point"}
}