{
  "type": "Feature",
  "properties": {
    "addr:full":"B.P. 221, 60002 Beauvais C\u00e9dex^^18, Rue Joseph Cugnot, 60000 Beauvais Picardie 60000",
    "addr:housenumber":"b.p. 221",
    "addr:postcode":"60002;60000;60000",
    "addr:street":"Rue Joseph Cugnot",
    "iso:country":"FR",
    "sg:address":"B.P. 221, 60002 Beauvais C\u00e9dex^^18, Rue Joseph Cugnot, 60000 Beauvais",
    "sg:orig_category":"Non-Classified Establishments",
    "sg:phone":"+33 3 44 10 30 30",
    "sg:postcode":"60000",
    "sg:province":"Picardie",
    "wof:name":"Bouvet Magne Picardie S.a.",
    "wof:placetype":"venue"
},
  "geometry": {"coordinates":[2.08322,49.429558],"type":"Point"}
}