{
  "type": "Feature",
  "properties": {
    "addr:full":"Rte de Castelnaudary - Forum d'Entreprise Revel Midi Pyr\u00e9n\u00e9es 31250",
    "addr:postcode":"31250",
    "addr:street":"Rte De",
    "iso:country":"FR",
    "sg:address":"Rte de Castelnaudary - Forum d'Entreprise",
    "sg:city":"Revel",
    "sg:orig_category":"Non-Classified Establishments",
    "sg:phone":"+33 5 62 26 80 07",
    "sg:postcode":"31250",
    "sg:province":"Midi Pyr\u00e9n\u00e9es",
    "wof:name":"Agrotest France S.a.r.l.",
    "wof:placetype":"venue"
},
  "geometry": {"coordinates":[2.00395,43.458408],"type":"Point"}
}