{
  "type": "Feature",
  "properties": {
    "addr:full":"35 Rue Georges Cl\u00e9menceau 41200 Romorantin Lanthenay Villefranche-sur-Cher Centre 41200",
    "addr:housenumber":"35",
    "addr:postcode":"41200;41200",
    "addr:street":"Rue Georges Cle\u0301Menceau",
    "iso:country":"FR",
    "sg:address":"35 Rue Georges Cl\u00e9menceau 41200 Romorantin Lanthenay",
    "sg:city":"Villefranche-sur-Cher",
    "sg:classifiers":[
        {
            "category":"Banks & Credit Unions",
            "subcategory":"Financial Services",
            "type":"Services"
        }
    ],
    "sg:phone":"+33 2 54 94 60 00",
    "sg:postcode":"41200",
    "sg:province":"Centre",
    "sg:tags":[
        "banking",
        "insurance",
        "institution",
        "finance"
    ],
    "wof:name":"Credit Lyonnais",
    "wof:placetype":"venue"
},
  "geometry": {"coordinates":[1.744588,47.359161],"type":"Point"}
}