{
  "type": "Feature",
  "properties": {
    "addr:full":"1, Rte Nationale 113 - Ponchut , 47130 Port Sainte Marie Bazens Aquitaine 47130",
    "addr:housenumber":"1",
    "addr:postcode":"47130;47130",
    "addr:street":"Rte Nationale 113 Ponchut",
    "iso:country":"FR",
    "sg:address":"1, Rte Nationale 113 - Ponchut , 47130 Port Sainte Marie",
    "sg:city":"Bazens",
    "sg:orig_category":"Unclassifiable Establishments",
    "sg:phone":"+33 5 53 67 43 27",
    "sg:postcode":"47130",
    "sg:province":"Aquitaine",
    "wof:name":"Cabso S.a.r.l.",
    "wof:placetype":"venue"
},
  "geometry": {"coordinates":[0.438146,44.203495],"type":"Point"}
}