{
  "type": "Feature",
  "properties": {
    "iso:country":"FR",
    "sg:address":"131, Rue de Pfastatt, 68260 Kingersheim",
    "sg:city":"Kingersheim",
    "sg:orig_category":"Unclassifiable Establishments",
    "sg:phone":"+33 3 89 50 57 07",
    "sg:postcode":"68260",
    "sg:province":"Alsace",
    "wof:name":"Euro Fa\u00e7ade S.a.r.l.",
    "wof:placetype":"venue"
},
  "geometry": {"coordinates":[7.31055,47.78511],"type":"Point"}
}