{
  "type": "Feature",
  "properties": {
    "iso:country":"FR",
    "sg:address":"21, Rte de Ferolles, 77170 Brie Comte Robert",
    "sg:orig_category":"Unclassifiable Establishments",
    "sg:phone":"+33 1 64 05 18 22",
    "sg:province":"Ile de France",
    "wof:name":"J.s.d. S.a.r.l.",
    "wof:placetype":"venue"
},
  "geometry": {"coordinates":[2.626022,48.710773],"type":"Point"}
}