{
  "type": "Feature",
  "properties": {
    "iso:country":"FR",
    "sg:address":"Rue de l'Eclipse",
    "sg:city":"Cergy",
    "sg:orig_category":"Unclassifiable Establishments",
    "sg:phone":"+33 1 34 25 41 00",
    "sg:postcode":"95000",
    "sg:province":"Ile de France",
    "wof:name":"Penauille Poliservice Alliance S.a.",
    "wof:placetype":"venue"
},
  "geometry": {"coordinates":[2.088471,49.03215],"type":"Point"}
}