{
  "type": "Feature",
  "properties": {
    "addr:full":"62 bis, Av. Andr\u00e9 Morizet, 92100 Boulogne Billancourt Ile de France",
    "addr:housenumber":"62 bis",
    "addr:postcode":"92100",
    "addr:street":"Av. Andre\u0301 Morizet",
    "iso:country":"FR",
    "sg:address":"62 bis, Av. Andr\u00e9 Morizet, 92100 Boulogne Billancourt",
    "sg:orig_category":"Non-Classified Establishments",
    "sg:phone":"+33 1 55 60 88 00",
    "sg:province":"Ile de France",
    "wof:name":"R.c.i. S.n.c. - R\u00e9gie Club International",
    "wof:placetype":"venue"
},
  "geometry": {"coordinates":[2.235655,48.837479],"type":"Point"}
}