{
  "type": "Feature",
  "properties": {
    "addr:full":"169, Rue Paradis, 13006 Marseille Provence-Alpes-C\u00f4te d'Azur",
    "addr:housenumber":"169",
    "addr:postcode":"13006",
    "addr:street":"Rue Paradis",
    "iso:country":"FR",
    "sg:address":"169, Rue Paradis, 13006 Marseille",
    "sg:orig_category":"Non-Classified Establishments",
    "sg:phone":"+33 4 91 00 37 37",
    "sg:province":"Provence-Alpes-C\u00f4te d'Azur",
    "wof:name":"Provence System S.a.",
    "wof:placetype":"venue"
},
  "geometry": {"coordinates":[5.38324,43.290806],"type":"Point"}
}