{
  "type": "Feature",
  "properties": {
    "addr:full":"23, Rue Ren\u00e9 Magne, 33300 Bordeaux Bordeaux Aquitaine 33300",
    "addr:housenumber":"23",
    "addr:postcode":"33300;33300",
    "addr:street":"Rue Rene\u0301 Magne",
    "iso:country":"FR",
    "sg:address":"23, Rue Ren\u00e9 Magne, 33300 Bordeaux",
    "sg:city":"Bordeaux",
    "sg:orig_category":"Unclassifiable Establishments",
    "sg:phone":"+33 5 57 19 11 40",
    "sg:postcode":"33300",
    "sg:province":"Aquitaine",
    "wof:name":"Paxor S.a.",
    "wof:placetype":"venue"
},
  "geometry": {"coordinates":[-0.544274,44.888786],"type":"Point"}
}