{
  "type": "Feature",
  "properties": {
    "iso:country":"FR",
    "sg:address":"Carrefour de l'Europe 81301 GRAULHET CEDEX",
    "sg:classifiers":[
        {
            "category":"Wholesale",
            "subcategory":"Vending Machines",
            "type":"Manufacturing & Wholesale Goods"
        }
    ],
    "sg:phone":"+33 5 63 34 52 29",
    "sg:province":"Languedoc-Roussillon",
    "sg:tags":[
        "leather",
        "shredding",
        "hide"
    ],
    "wof:name":"Rouzi\u00e8res Edmond & Cie Sa",
    "wof:placetype":"venue"
},
  "geometry": {"coordinates":[2.001428,43.76416],"type":"Point"}
}