{
  "type": "Feature",
  "properties": {
    "addr:full":"13 ave Auber; Nice Basse Normandie",
    "addr:street":"13 Ave Auber;Basse Normandie",
    "iso:country":"FR",
    "sg:address":"13 ave Auber; Nice",
    "sg:classifiers":[
        {
            "category":"Banks & Credit Unions",
            "subcategory":"Bank",
            "type":"Services"
        }
    ],
    "sg:phone":"+33 3393874349",
    "sg:province":"Basse Normandie",
    "wof:name":"Cr\u00e9dit Lyonnais, Agence Mozart",
    "wof:placetype":"venue"
},
  "geometry": {"coordinates":[-122.8386,39.121292],"type":"Point"}
}