{
  "type": "Feature",
  "properties": {
    "addr:full":"Centre Actival - 301 de Lille 59437 Roncq Nord Pas-de-Calais",
    "addr:housenumber":"301",
    "addr:postcode":"59437",
    "addr:street":"De Lille",
    "iso:country":"FR",
    "sg:address":"Centre Actival - 301",
    "sg:city":"de Lille 59437 Roncq",
    "sg:orig_category":"Security Seals",
    "sg:phone":"+33 3 20 28 87 30",
    "sg:province":"Nord Pas-de-Calais",
    "wof:name":"Facdem Sarl S\u00e9curit\u00e9 Et Fixation",
    "wof:placetype":"venue"
},
  "geometry": {"coordinates":[3.117482,50.743378],"type":"Point"}
}