{
  "type": "Feature",
  "properties": {
    "addr:full":"Rte de Vernoux Boffres Rhone-Alpes 07440",
    "addr:postcode":"07440",
    "addr:street":"Rte De Vernoux;Rhone-Alpes",
    "iso:country":"FR",
    "sg:address":"Rte de Vernoux",
    "sg:city":"Boffres",
    "sg:orig_category":"Non-Classified Establishments",
    "sg:phone":"+33 4 75 58 29 00",
    "sg:postcode":"07440",
    "sg:province":"Rhone-Alpes",
    "wof:name":"Calixte Producteur S.n.c.",
    "wof:placetype":"venue"
},
  "geometry": {"coordinates":[4.7255,44.944832],"type":"Point"}
}