{
  "type": "Feature",
  "properties": {
    "iso:country":"FR",
    "sg:address":"B.P. 33, 81370 Saint Sulpice^^ZI des Terres Noires, 81370 Saint Sulpice",
    "sg:orig_category":"Non-Classified Establishments",
    "sg:phone":"+33 5 63 41 87 55",
    "sg:province":"Midi Pyr\u00e9n\u00e9es",
    "wof:name":"Soflac S.a.r.l. - Sud-ouest Flaconnage",
    "wof:placetype":"venue"
},
  "geometry": {"coordinates":[1.68578,43.77404],"type":"Point"}
}