{
  "type": "Feature",
  "properties": {
    "iso:country":"FR",
    "sg:address":"1, Rue Abel Gance, 44300 Nantes",
    "sg:orig_category":"Unclassifiable Establishments",
    "sg:phone":"+33 2 40 14 40 24",
    "sg:province":"Pays de Loire",
    "wof:name":"Rep\u00e8res Et Management",
    "wof:placetype":"venue"
},
  "geometry": {"coordinates":[-1.532307,47.247021],"type":"Point"}
}