{
  "type": "Feature",
  "properties": {
    "addr:full":"11 rue Charles Le Hir; Guilers; 29820 Guilers Bretagne 29820",
    "addr:housenumber":"11",
    "addr:postcode":"29820;29820",
    "addr:street":"Rue Charles Le Hir;Bretagne",
    "iso:country":"FR",
    "sg:address":"11 rue Charles Le Hir; Guilers; 29820",
    "sg:city":"Guilers",
    "sg:classifiers":[
        {
            "category":"Banks & Credit Unions",
            "subcategory":"Bank",
            "type":"Services"
        }
    ],
    "sg:phone":"+33 2 98 07 63 43",
    "sg:postcode":"29820",
    "sg:province":"Bretagne",
    "wof:name":"Cr\u00e9dit Mutuel De Bretagne",
    "wof:placetype":"venue"
},
  "geometry": {"coordinates":[-4.559359,48.424389],"type":"Point"}
}