{
  "type": "Feature",
  "properties": {
    "iso:country":"FR",
    "sg:address":"13, Av. de l'Arroussaire, 84000 Avignon",
    "sg:orig_category":"Non-Classified Establishments",
    "sg:phone":"+33 4 90 82 34 13",
    "sg:province":"Provence-Alpes-C\u00f4te d'Azur",
    "wof:name":"Soci\u00e9t\u00e9 Durand Fils S.a.r.l.",
    "wof:placetype":"venue"
},
  "geometry": {"coordinates":[4.813245,43.939144],"type":"Point"}
}