{
  "type": "Feature",
  "properties": {
    "iso:country":"FR",
    "sg:address":"B.P. 48",
    "sg:city":"Avon C\u00e9dex",
    "sg:orig_category":"Non-Classified Establishments",
    "sg:phone":"+33 1 64 22 49 20",
    "sg:postcode":"77212",
    "sg:province":"Poitou-Charentes",
    "wof:name":"Primeurs 77 S.a.",
    "wof:placetype":"venue"
},
  "geometry": {"coordinates":[2.72196,48.415936],"type":"Point"}
}