{
  "type": "Feature",
  "properties": {
    "iso:country":"FR",
    "sg:address":"52 Rue Vierzon 41400 Montrichard",
    "sg:city":"Montrichard",
    "sg:classifiers":[
        {
            "category":"Professional",
            "subcategory":"Printing & Photocopies",
            "type":"Services"
        }
    ],
    "sg:phone":"+33 2 54 32 28 73",
    "sg:postcode":"41400",
    "sg:province":"Centre",
    "sg:tags":[
        "publishing"
    ],
    "wof:name":"Spiral Sa",
    "wof:placetype":"venue"
},
  "geometry": {"coordinates":[1.2074,47.345428],"type":"Point"}
}