{
  "type": "Feature",
  "properties": {
    "iso:country":"FR",
    "sg:address":"Ch\u00e2teau Feuillet 73260 La L\u00e9ch\u00e8re",
    "sg:classifiers":[
        {
            "category":"Manufacturing",
            "subcategory":"Metals",
            "type":"Manufacturing & Wholesale Goods"
        }
    ],
    "sg:phone":"+33 4 79 22 69 00",
    "sg:postcode":"73260",
    "sg:province":"Rhone-Alpes",
    "sg:tags":[
        "metallurgy",
        "steel",
        "metalworking"
    ],
    "wof:name":"Pechiney Electrometallurgie",
    "wof:placetype":"venue"
},
  "geometry": {"coordinates":[6.484056,45.521091],"type":"Point"}
}