{
  "type": "Feature",
  "properties": {
    "addr:full":"Rue Kleindorf Lutterbach Alsace 68460",
    "addr:postcode":"68460",
    "addr:street":"Rue Kleindorf",
    "iso:country":"FR",
    "sg:address":"Rue Kleindorf",
    "sg:city":"Lutterbach",
    "sg:orig_category":"Unclassifiable Establishments",
    "sg:phone":"+33 3 89 57 10 40",
    "sg:postcode":"68460",
    "sg:province":"Alsace",
    "wof:name":"T.m. S.a. - Tissage Du Moulin",
    "wof:placetype":"venue"
},
  "geometry": {"coordinates":[7.271409,47.758884],"type":"Point"}
}