{
  "type": "Feature",
  "properties": {
    "addr:full":"ZI de l'Ayguelonge Montardon Aquitaine 64121",
    "addr:postcode":"64121",
    "addr:street":"Zi De L'Ayguelonge",
    "iso:country":"FR",
    "sg:address":"ZI de l'Ayguelonge",
    "sg:city":"Montardon",
    "sg:orig_category":"Non-Classified Establishments",
    "sg:phone":"+33 5 59 33 00 90",
    "sg:postcode":"64121",
    "sg:province":"Aquitaine",
    "wof:name":"Ecila S.a.",
    "wof:placetype":"venue"
},
  "geometry": {"coordinates":[-0.37999,43.353981],"type":"Point"}
}