{
  "type": "Feature",
  "properties": {
    "iso:country":"FR",
    "sg:address":"6, Rte Cablanc, 24100 Creysse",
    "sg:city":"Creysse",
    "sg:orig_category":"Non-Classified Establishments",
    "sg:phone":"+33 5 53 74 45 50",
    "sg:postcode":"24100",
    "sg:province":"Aquitaine",
    "wof:name":"Vilgo S.a.",
    "wof:placetype":"venue"
},
  "geometry": {"coordinates":[0.532817,44.855701],"type":"Point"}
}