{
  "type": "Feature",
  "properties": {
    "iso:country":"FR",
    "sg:address":"Z I de la Plaine 88510 Eloyes",
    "sg:classifiers":[
        {
            "category":"Professional",
            "subcategory":"Engineering",
            "type":"Services"
        }
    ],
    "sg:phone":"+33 3 29 64 45 45",
    "sg:postcode":"88510",
    "sg:province":"Lorraine",
    "sg:tags":[
        "machine",
        "steel"
    ],
    "wof:name":"Viry S.a.",
    "wof:placetype":"venue"
},
  "geometry": {"coordinates":[6.610609,48.093906],"type":"Point"}
}