{
  "type": "Feature",
  "properties": {
    "addr:full":"6 Rue Emile Path\u00e9 BP 65 78403 Chatou Cedex Ile de France",
    "addr:housenumber":"6;bp 65",
    "addr:postcode":"78403;ile",
    "addr:street":"Rue Emile Pathe\u0301",
    "iso:country":"FR",
    "sg:address":"6 Rue Emile Path\u00e9 BP 65 78403 Chatou Cedex",
    "sg:classifiers":[
        {
            "category":"Utilities",
            "subcategory":"Electric",
            "type":"Services"
        }
    ],
    "sg:phone":"+33 1 34 80 28 00",
    "sg:province":"Ile de France",
    "sg:tags":[
        "electricity",
        "electronic",
        "electrical",
        "equipment"
    ],
    "wof:name":"Energizer",
    "wof:placetype":"venue"
},
  "geometry": {"coordinates":[2.15131,48.895054],"type":"Point"}
}