{
  "type": "Feature",
  "properties": {
    "iso:country":"FR",
    "sg:address":"59910 Bondues",
    "sg:orig_category":"Unclassifiable Establishments",
    "sg:phone":"+33 3 20 37 45 90",
    "sg:province":"Nord Pas-de-Calais",
    "wof:name":"I.d.s. S.a. - Industrie Distribution Service",
    "wof:placetype":"venue"
},
  "geometry": {"coordinates":[3.10018,50.70607],"type":"Point"}
}