{
  "type": "Feature",
  "properties": {
    "iso:country":"FR",
    "sg:address":"B.P. 38, 78164 Marly le Roi C\u00e9dex^^4, Rue Mansart, 78100 Marly le Roi",
    "sg:orig_category":"Non-Classified Establishments",
    "sg:phone":"+33 1 39 16 70 18",
    "sg:province":"Ile de France",
    "wof:name":"Maqbar Diffusion S.a.r.l.",
    "wof:placetype":"venue"
},
  "geometry": {"coordinates":[2.091955,48.898411],"type":"Point"}
}