{
  "type": "Feature",
  "properties": {
    "addr:full":"13 Rue Jean Goujon 28260 Anet Anet Centre 28260",
    "addr:housenumber":"13",
    "addr:postcode":"28260;28260",
    "addr:street":"Rue Jean Goujon",
    "iso:country":"FR",
    "sg:address":"13 Rue Jean Goujon 28260 Anet",
    "sg:city":"Anet",
    "sg:classifiers":[
        {
            "category":"Shopping",
            "type":"Retail Goods"
        }
    ],
    "sg:phone":"+33 2 37 41 90 21",
    "sg:postcode":"28260",
    "sg:province":"Centre",
    "sg:tags":[
        "metallurgy",
        "finished",
        "-",
        "metalworking",
        "metallic"
    ],
    "wof:name":"Boudeville Et Fontaine Sa",
    "wof:placetype":"venue"
},
  "geometry": {"coordinates":[1.437902,48.855881],"type":"Point"}
}