{
  "type": "Feature",
  "properties": {
    "iso:country":"FR",
    "sg:address":"7, Rue Francis Poulenc, 13200 Arles",
    "sg:orig_category":"Unclassifiable Establishments",
    "sg:phone":"+33 4 90 96 88 87",
    "sg:province":"Picardie",
    "wof:name":"D.s.",
    "wof:placetype":"venue"
},
  "geometry": {"coordinates":[4.641686,43.695747],"type":"Point"}
}