{
  "type": "Feature",
  "properties": {
    "addr:full":"2 Av De Bordeaux 47110 Ste Livrade Sur Lot Allez-et-Cazeneuve Aquitaine 47110",
    "addr:postcode":"47110;47110",
    "addr:street":"Av De Bordeaux;Livrade",
    "iso:country":"FR",
    "sg:address":"2 Av De Bordeaux 47110 Ste Livrade Sur Lot",
    "sg:city":"Allez-et-Cazeneuve",
    "sg:classifiers":[
        {
            "category":"Health Services",
            "subcategory":"Medical Lab",
            "type":"Services"
        }
    ],
    "sg:phone":"+33 5 53 01 33 80",
    "sg:postcode":"47110",
    "sg:province":"Aquitaine",
    "sg:tags":[
        "chemical",
        "pharmaceutical",
        "pharmacy"
    ],
    "wof:name":"Audevard Sa",
    "wof:placetype":"venue"
},
  "geometry": {"coordinates":[0.588757,44.362614],"type":"Point"}
}