{
  "type": "Feature",
  "properties": {
    "addr:full":"Le Village 26270 Cliousclat Rhone-Alpes 26270",
    "addr:postcode":"26270;26270",
    "addr:street":"Le Village;Rhone-Alpes",
    "iso:country":"FR",
    "sg:address":"Le Village 26270 Cliousclat",
    "sg:classifiers":[
        {
            "category":"Home & Garden",
            "subcategory":"Furniture",
            "type":"Retail Goods"
        }
    ],
    "sg:phone":"+33 4 75 63 05 69",
    "sg:postcode":"26270",
    "sg:province":"Rhone-Alpes",
    "sg:tags":[
        "household",
        "wood"
    ],
    "wof:name":"Poterie De Cliousclat",
    "wof:placetype":"venue"
},
  "geometry": {"coordinates":[4.797704,44.692307],"type":"Point"}
}