{
  "type": "Feature",
  "properties": {
    "iso:country":"FR",
    "sg:address":"12, Rue Amp\u00e8re, 38000 Grenoble",
    "sg:orig_category":"Unclassifiable Establishments",
    "sg:phone":"+33 4 76 70 13 78",
    "sg:postcode":"38000",
    "sg:province":"Rhone-Alpes",
    "wof:name":"Digimind S.a.",
    "wof:placetype":"venue"
},
  "geometry": {"coordinates":[5.705505,45.184967],"type":"Point"}
}