{
  "type": "Feature",
  "properties": {
    "iso:country":"FR",
    "sg:address":"4, Rte de Douai, 62159 Vaulx Vraucourt",
    "sg:orig_category":"Unclassifiable Establishments",
    "sg:phone":"+33 3 21 07 78 36",
    "sg:province":"Nord Pas-de-Calais",
    "wof:name":"Coopavril S.c.a.",
    "wof:placetype":"venue"
},
  "geometry": {"coordinates":[2.891375,50.156548],"type":"Point"}
}