{
  "type": "Feature",
  "properties": {
    "addr:full":"Av. de Lattre de Tassigny Pessac Aquitaine 33600",
    "addr:postcode":"33600",
    "addr:street":"Av. De Lattre De Tassigny",
    "iso:country":"FR",
    "sg:address":"Av. de Lattre de Tassigny",
    "sg:city":"Pessac",
    "sg:orig_category":"Non-Classified Establishments",
    "sg:phone":"+33 5 56 36 90 99",
    "sg:postcode":"33600",
    "sg:province":"Aquitaine",
    "wof:name":"Etablissement Gabriel Beaumartin S.a.",
    "wof:placetype":"venue"
},
  "geometry": {"coordinates":[-0.694404,44.779804],"type":"Point"}
}