{
  "type": "Feature",
  "properties": {
    "addr:full":"B.P. 106, 60771 Cambronne l\u00e8s Rib\u00e9court C\u00e9dex^^Rue Roger Duquesnois, 60170 Cambronne l\u00e8s Rib\u00e9court Picardie 60170",
    "addr:housenumber":"b.p. 106",
    "addr:postcode":"60771;60170;60170",
    "addr:street":"Picardie",
    "iso:country":"FR",
    "sg:address":"B.P. 106, 60771 Cambronne l\u00e8s Rib\u00e9court C\u00e9dex^^Rue Roger Duquesnois, 60170 Cambronne l\u00e8s Rib\u00e9court",
    "sg:orig_category":"Non-Classified Establishments",
    "sg:phone":"+33 3 44 76 89 64",
    "sg:postcode":"60170",
    "sg:province":"Picardie",
    "wof:name":"B.f.m.e.c.a. S.a.r.l.",
    "wof:placetype":"venue"
},
  "geometry": {"coordinates":[2.92245,49.509705],"type":"Point"}
}