{
  "type": "Feature",
  "properties": {
    "iso:country":"FR",
    "sg:address":"B.P. 15, 70001 Vesoul C\u00e9dex^^19, Place Pierre Renet, 70000 Vesoul",
    "sg:orig_category":"Non-Classified Establishments",
    "sg:phone":"+33 3 84 96 75 00",
    "sg:province":"Franche Comt\u00e9",
    "wof:name":"I.m.b. Imprimeur S.a.",
    "wof:placetype":"venue"
},
  "geometry": {"coordinates":[6.034054,47.524078],"type":"Point"}
}