{
  "type": "Feature",
  "properties": {
    "addr:full":"B.P. 8707, 31312 Lab\u00e8ge C\u00e9dex^^2, Rue Amp\u00e8re - Prologue, 31670 Lab\u00e8ge Midi Pyr\u00e9n\u00e9es",
    "addr:postcode":"31312;31670",
    "addr:street":"B.P. 8707;Rue Ampe\u0300Re Prologue",
    "iso:country":"FR",
    "sg:address":"B.P. 8707, 31312 Lab\u00e8ge C\u00e9dex^^2, Rue Amp\u00e8re - Prologue, 31670 Lab\u00e8ge",
    "sg:orig_category":"Non-Classified Establishments",
    "sg:phone":"+33 5 61 39 29 96",
    "sg:province":"Midi Pyr\u00e9n\u00e9es",
    "wof:name":"Quatri\u00e8me Dimension S.a.r.l.",
    "wof:placetype":"venue"
},
  "geometry": {"coordinates":[1.527111,43.529713],"type":"Point"}
}