{
  "type": "Feature",
  "properties": {
    "iso:country":"FR",
    "sg:address":"55 Av De Paris 92320 Ch\u00e2tillon",
    "sg:classifiers":[
        {
            "category":"Manufacturing",
            "subcategory":"Rubber & Plastics",
            "type":"Manufacturing & Wholesale Goods"
        }
    ],
    "sg:phone":"+33 1 42 53 73 70",
    "sg:postcode":"92320",
    "sg:province":"Ile de France",
    "sg:tags":[
        "textile",
        "linen",
        "clothing",
        "fabric"
    ],
    "wof:name":"Ste Modernerev\u00catements De Sols Sarl",
    "wof:placetype":"venue"
},
  "geometry": {"coordinates":[2.292432,48.806431],"type":"Point"}
}