{
  "type": "Feature",
  "properties": {
    "addr:full":"Le Lievreau 44260 Malville Pays de Loire 44260",
    "addr:postcode":"44260;44260",
    "addr:street":"Malville",
    "iso:country":"FR",
    "sg:address":"Le Lievreau 44260 Malville",
    "sg:classifiers":[
        {
            "category":"Home & Garden",
            "subcategory":"Furniture",
            "type":"Retail Goods"
        }
    ],
    "sg:phone":"+33 2 40 56 09 11",
    "sg:postcode":"44260",
    "sg:province":"Pays de Loire",
    "sg:tags":[
        "household",
        "wood"
    ],
    "wof:name":"Unit Industrie Navale",
    "wof:placetype":"venue"
},
  "geometry": {"coordinates":[-1.837042,47.346867],"type":"Point"}
}