{
  "type": "Feature",
  "properties": {
    "iso:country":"FR",
    "sg:address":"7 Rue De Metz 63000 Clermont Ferrand",
    "sg:city":"Clermont-Ferrand",
    "sg:classifiers":[
        {
            "category":"Professional",
            "subcategory":"Business Services",
            "type":"Services"
        }
    ],
    "sg:phone":"+33 4 73 91 36 01",
    "sg:postcode":"63000",
    "sg:province":"Auvergne",
    "sg:tags":[
        "training",
        "advice"
    ],
    "wof:name":"Association Groupe Scolaire Monages",
    "wof:placetype":"venue"
},
  "geometry": {"coordinates":[3.097847,45.780556],"type":"Point"}
}