{
  "type": "Feature",
  "properties": {
    "addr:full":"129/131, Av. L\u00e9on Blum, 38100 Grenoble Rhone-Alpes 38100",
    "addr:housenumber":"129 / 131",
    "addr:postcode":"38100;38100",
    "addr:street":"Av. Le\u0301On Blum",
    "iso:country":"FR",
    "sg:address":"129/131, Av. L\u00e9on Blum, 38100 Grenoble",
    "sg:orig_category":"Unclassifiable Establishments",
    "sg:phone":"+33 4 76 33 65 30",
    "sg:postcode":"38100",
    "sg:province":"Rhone-Alpes",
    "wof:name":"Airisol S.a.",
    "wof:placetype":"venue"
},
  "geometry": {"coordinates":[5.715137,45.16098],"type":"Point"}
}