{
  "type": "Feature",
  "properties": {
    "addr:full":"9 Rue Du H\u00e9ron 67300 Schiltigheim Schiltigheim Alsace 67300",
    "addr:housenumber":"9",
    "addr:postcode":"67300;67300",
    "addr:street":"Rue Du He\u0301Ron",
    "iso:country":"FR",
    "sg:address":"9 Rue Du H\u00e9ron 67300 Schiltigheim",
    "sg:city":"Schiltigheim",
    "sg:classifiers":[
        {
            "category":"Professional",
            "subcategory":"Engineering",
            "type":"Services"
        }
    ],
    "sg:phone":"+33 3 88 33 11 48",
    "sg:postcode":"67300",
    "sg:province":"Alsace",
    "sg:tags":[
        "machine",
        "-",
        "mechanical"
    ],
    "wof:name":"Gd Sagem Sa",
    "wof:placetype":"venue"
},
  "geometry": {"coordinates":[7.76941,48.619907],"type":"Point"}
}