{
  "type": "Feature",
  "properties": {
    "addr:full":"Za Les Plantes 79600 Louin Poitou-Charentes 79600",
    "addr:postcode":"79600;79600",
    "addr:street":"Za Les Plantes",
    "iso:country":"FR",
    "sg:address":"Za Les Plantes 79600 Louin",
    "sg:classifiers":[
        {
            "category":"Shopping",
            "type":"Retail Goods"
        }
    ],
    "sg:phone":"+33 5 49 64 89 04",
    "sg:postcode":"79600",
    "sg:province":"Poitou-Charentes",
    "sg:tags":[
        "metallurgy",
        "finished",
        "-",
        "metalworking",
        "metallic"
    ],
    "wof:name":"Cmi Sarl",
    "wof:placetype":"venue"
},
  "geometry": {"coordinates":[-0.16118,46.801975],"type":"Point"}
}