{
  "type": "Feature",
  "properties": {
    "addr:full":"3 Pl. Jean Achard 38000 Grenoble Rhone-Alpes 38000",
    "addr:housenumber":"3",
    "addr:postcode":"38000;38000",
    "addr:street":"Pl. Jean Achard",
    "iso:country":"FR",
    "sg:address":"3 Pl. Jean Achard 38000 Grenoble",
    "sg:classifiers":[
        {
            "category":"Shopping",
            "subcategory":"Crafts & Fabrics",
            "type":"Retail Goods"
        }
    ],
    "sg:phone":"+33 4 76 42 73 73",
    "sg:postcode":"38000",
    "sg:province":"Rhone-Alpes",
    "sg:tags":[
        "textile",
        "clothing"
    ],
    "wof:name":"Neuftex - Toto",
    "wof:placetype":"venue"
},
  "geometry": {"coordinates":[5.729312,45.189632],"type":"Point"}
}