{
  "type": "Feature",
  "properties": {
    "addr:full":"113, Bd des Vosges, 57700 Hayange Lorraine",
    "addr:housenumber":"113",
    "addr:postcode":"57700",
    "addr:street":"Bd Des Vosges",
    "iso:country":"FR",
    "sg:address":"113, Bd des Vosges, 57700 Hayange",
    "sg:orig_category":"Unclassifiable Establishments",
    "sg:phone":"+33 3 82 52 90 60",
    "sg:province":"Lorraine",
    "wof:name":"Quantum Conseil E.u.r.l.",
    "wof:placetype":"venue"
},
  "geometry": {"coordinates":[6.072341,49.315544],"type":"Point"}
}