{
  "type": "Feature",
  "properties": {
    "iso:country":"FR",
    "sg:address":"100 rue de R\u00e9aumur, 75002 Paris, Dept 75",
    "sg:classifiers":[
        {
            "category":"Banks & Credit Unions",
            "subcategory":"Bank",
            "type":"Services"
        }
    ],
    "sg:phone":"+33 1 42 21 25 25",
    "sg:postcode":"75002",
    "sg:province":"Ile de France",
    "wof:name":"Natexis Capital",
    "wof:placetype":"venue"
},
  "geometry": {"coordinates":[2.34114,48.867649],"type":"Point"}
}