{
  "type": "Feature",
  "properties": {
    "addr:full":"2 Av Gallienie 93250 Villemomble Ile de France 93250",
    "addr:postcode":"93250;ile;93250",
    "addr:street":"Av Gallienie;France",
    "iso:country":"FR",
    "sg:address":"2 Av Gallienie 93250 Villemomble",
    "sg:classifiers":[
        {
            "category":"Wholesale",
            "subcategory":"Medical Equipment & Supplies",
            "type":"Manufacturing & Wholesale Goods"
        }
    ],
    "sg:phone":"+33 1 41 53 06 06",
    "sg:postcode":"93250",
    "sg:province":"Ile de France",
    "sg:tags":[
        "instrument",
        "health",
        "-",
        "precision"
    ],
    "wof:name":"Centre D'imagerie Medicale De La Gare",
    "wof:placetype":"venue"
},
  "geometry": {"coordinates":[2.506309,48.891914],"type":"Point"}
}