{
  "type": "Feature",
  "properties": {
    "iso:country":"FR",
    "sg:address":"44 Rue De La R\u00e9publique 68040 Ingersheim",
    "sg:city":"Ingersheim",
    "sg:classifiers":[
        {
            "category":"Wholesale",
            "subcategory":"Meat",
            "type":"Manufacturing & Wholesale Goods"
        }
    ],
    "sg:phone":"+33 3 89 27 01 75",
    "sg:postcode":"68040",
    "sg:province":"Alsace",
    "sg:tags":[
        "food",
        "cooked",
        "product",
        "related"
    ],
    "wof:name":"Sigmann Boucherie Charcuterie",
    "wof:placetype":"venue"
},
  "geometry": {"coordinates":[7.30287,48.096767],"type":"Point"}
}