{
  "type": "Feature",
  "properties": {
    "addr:full":"Rue De La Centrale 59138 Pont Sur Sambre Nord Pas-de-Calais 59138",
    "addr:postcode":"59138;59138",
    "addr:street":"Rue De La Centrale;Sambre Nord",
    "iso:country":"FR",
    "sg:address":"Rue De La Centrale 59138 Pont Sur Sambre",
    "sg:classifiers":[
        {
            "category":"Professional",
            "subcategory":"Engineering",
            "type":"Services"
        }
    ],
    "sg:phone":"+33 3 27 67 47 09",
    "sg:postcode":"59138",
    "sg:province":"Nord Pas-de-Calais",
    "sg:tags":[
        "machine",
        "-",
        "mechanical"
    ],
    "wof:name":"E O D A Realisations Sa",
    "wof:placetype":"venue"
},
  "geometry": {"coordinates":[3.846925,50.221619],"type":"Point"}
}