{
  "type": "Feature",
  "properties": {
    "addr:full":"29, Av. Jean Joxe, 49000 Angers Pays de Loire",
    "addr:postcode":"49000",
    "addr:street":"29 Av. Jean Joxe",
    "iso:country":"FR",
    "sg:address":"29, Av. Jean Joxe, 49000 Angers",
    "sg:orig_category":"Unclassifiable Establishments",
    "sg:phone":"+33 2 41 33 66 66",
    "sg:province":"Pays de Loire",
    "wof:name":"Centre Gestion Maine Et Loire",
    "wof:placetype":"venue"
},
  "geometry": {"coordinates":[-0.54151,47.483727],"type":"Point"}
}