{
  "type": "Feature",
  "properties": {
    "iso:country":"FR",
    "sg:address":"45 Avenue Des Confignes 13831 CHATEAURENARD CEDEX",
    "sg:classifiers":[
        {
            "category":"Home & Garden",
            "subcategory":"Carpets & Floor Coverings",
            "type":"Retail Goods"
        }
    ],
    "sg:phone":"+33 4 90 24 27 00",
    "sg:province":"Provence-Alpes-C\u00f4te d'Azur",
    "sg:tags":[
        "tile"
    ],
    "wof:name":"Atrium Sas",
    "wof:placetype":"venue"
},
  "geometry": {"coordinates":[4.874746,43.897766],"type":"Point"}
}