{
  "type": "Feature",
  "properties": {
    "iso:country":"FR",
    "sg:address":"33112 Saint Laurent M\u00e9doc",
    "sg:city":"Saint-Laurent-M\u00e9doc",
    "sg:orig_category":"Unclassifiable Establishments",
    "sg:phone":"+33 5 56 59 41 69",
    "sg:postcode":"33112",
    "sg:province":"Aquitaine",
    "wof:name":"Ch\u00e2teau De Camensac S.a.",
    "wof:placetype":"venue"
},
  "geometry": {"coordinates":[-0.821959,45.150249],"type":"Point"}
}