{
  "type": "Feature",
  "properties": {
    "addr:full":"11 Rue Jean Moulin 39230 Selli\u00e8res Franche Comt\u00e9",
    "addr:housenumber":"11",
    "addr:postcode":"39230",
    "addr:street":"Rue Jean Moulin;Franche Comte\u0301",
    "iso:country":"FR",
    "sg:address":"11 Rue Jean Moulin 39230 Selli\u00e8res",
    "sg:classifiers":[
        {
            "category":"Professional",
            "type":"Services"
        }
    ],
    "sg:phone":"+33 3 84 85 51 05",
    "sg:province":"Franche Comt\u00e9",
    "sg:tags":[
        "transport",
        "road"
    ],
    "wof:name":"Milloux (transports) Sarl",
    "wof:placetype":"venue"
},
  "geometry": {"coordinates":[5.56583,46.827663],"type":"Point"}
}