{
  "type": "Feature",
  "properties": {
    "addr:full":"B.P. 713, 53007 Laval C\u00e9dex^^40, Rue L\u00e9on Jouhaux, 53000 Laval Pays de Loire",
    "addr:housenumber":"b.p. 713",
    "addr:postcode":"53007;53000",
    "addr:street":"Rue Le\u0301On Jouhaux",
    "iso:country":"FR",
    "sg:address":"B.P. 713, 53007 Laval C\u00e9dex^^40, Rue L\u00e9on Jouhaux, 53000 Laval",
    "sg:orig_category":"Non-Classified Establishments",
    "sg:phone":"+33 2 43 69 07 80",
    "sg:province":"Pays de Loire",
    "wof:name":"Papeterie D'entrammes S.a.r.l.",
    "wof:placetype":"venue"
},
  "geometry": {"coordinates":[-0.756451,48.036293],"type":"Point"}
}