{
  "type": "Feature",
  "properties": {
    "addr:full":"21, Rue de la Montjoie, 93200 Saint Denis Ile de France",
    "addr:housenumber":"21",
    "addr:postcode":"93200",
    "addr:street":"Rue De La Montjoie",
    "iso:country":"FR",
    "sg:address":"21, Rue de la Montjoie, 93200 Saint Denis",
    "sg:orig_category":"Non-Classified Establishments",
    "sg:phone":"+33 1 49 46 97 65",
    "sg:province":"Ile de France",
    "wof:name":"Gk Plast S.a.r.l.",
    "wof:placetype":"venue"
},
  "geometry": {"coordinates":[2.364431,48.911354],"type":"Point"}
}