{
  "type": "Feature",
  "properties": {
    "addr:full":"Chemin Estaquebiau Saint Jean Midi Pyr\u00e9n\u00e9es 31240",
    "addr:postcode":"31240",
    "addr:street":"Chemin Estaquebiau Saint Jean Midi Pyre\u0301Ne\u0301Es",
    "iso:country":"FR",
    "sg:address":"Chemin Estaquebiau",
    "sg:city":"Saint Jean",
    "sg:orig_category":"Non-Classified Establishments",
    "sg:phone":"+33 5 61 74 36 57",
    "sg:postcode":"31240",
    "sg:province":"Midi Pyr\u00e9n\u00e9es",
    "wof:name":"Durrieu Mobilier S.a.r.l.",
    "wof:placetype":"venue"
},
  "geometry": {"coordinates":[1.485636,43.668137],"type":"Point"}
}