{
  "type": "Feature",
  "properties": {
    "addr:full":"10 Rue Marguerite Fournier 42600 Montbrison Rhone-Alpes 42600",
    "addr:housenumber":"10",
    "addr:postcode":"42600;42600",
    "addr:street":"Rue Marguerite Fournier",
    "iso:country":"FR",
    "sg:address":"10 Rue Marguerite Fournier 42600 Montbrison",
    "sg:classifiers":[
        {
            "category":"Banks & Credit Unions",
            "subcategory":"Financial Services",
            "type":"Services"
        }
    ],
    "sg:phone":"+33 4 77 96 85 85",
    "sg:postcode":"42600",
    "sg:province":"Rhone-Alpes",
    "sg:tags":[
        "banking",
        "insurance",
        "institution",
        "finance"
    ],
    "wof:name":"Caisse D'epargne Loire Drome Ardeche",
    "wof:placetype":"venue"
},
  "geometry": {"coordinates":[4.067227,45.605858],"type":"Point"}
}