{
  "type": "Feature",
  "properties": {
    "addr:full":"84, Av. du Mar\u00e9chal Leclerc, 95000 Boisemont Ile de France",
    "addr:postcode":"95000",
    "addr:street":"84 Av. Du Mare\u0301Chal Leclerc;Ile De France",
    "iso:country":"FR",
    "sg:address":"84, Av. du Mar\u00e9chal Leclerc, 95000 Boisemont",
    "sg:orig_category":"Non-Classified Establishments",
    "sg:phone":"+33 1 34 46 98 00",
    "sg:province":"Ile de France",
    "wof:name":"Siremballage S.a.",
    "wof:placetype":"venue"
},
  "geometry": {"coordinates":[2.00357,49.011169],"type":"Point"}
}