{
  "type": "Feature",
  "properties": {
    "addr:full":"Fond de la Vau 54470 Beaumont Lorraine",
    "addr:postcode":"54470",
    "addr:street":"De La Vau",
    "iso:country":"FR",
    "sg:address":"Fond de la Vau 54470 Beaumont",
    "sg:orig_category":"Unclassifiable Establishments",
    "sg:phone":"+33 3 29 90 42 09",
    "sg:province":"Lorraine",
    "wof:name":"Ciolli Fr\u00e8res S.a.",
    "wof:placetype":"venue"
},
  "geometry": {"coordinates":[5.862805,48.955154],"type":"Point"}
}