{
  "type": "Feature",
  "properties": {
    "addr:full":"2 Rue Bochet 25170 Lavernay Franche Comt\u00e9 25170",
    "addr:housenumber":"2",
    "addr:postcode":"25170;25170",
    "addr:street":"Rue Bochet;Franche Comte\u0301",
    "iso:country":"FR",
    "sg:address":"2 Rue Bochet 25170 Lavernay",
    "sg:classifiers":[
        {
            "category":"Food & Beverages",
            "subcategory":"Dairy",
            "type":"Retail Goods"
        }
    ],
    "sg:phone":"+33 3 81 58 19 91",
    "sg:postcode":"25170",
    "sg:province":"Franche Comt\u00e9",
    "sg:tags":[
        "product",
        "related"
    ],
    "wof:name":"Jouffroy Sa",
    "wof:placetype":"venue"
},
  "geometry": {"coordinates":[5.82061,47.247784],"type":"Point"}
}