{
  "type": "Feature",
  "properties": {
    "iso:country":"FR",
    "sg:address":"2 Rue Bochet 25170 Lavernay",
    "sg:classifiers":[
        {
            "category":"Food & Beverages",
            "subcategory":"Dairy",
            "type":"Retail Goods"
        }
    ],
    "sg:phone":"+33 3 81 58 19 91",
    "sg:postcode":"25170",
    "sg:province":"Franche Comt\u00e9",
    "sg:tags":[
        "product",
        "related"
    ],
    "wof:name":"Jouffroy Sa",
    "wof:placetype":"venue"
},
  "geometry": {"coordinates":[5.82061,47.247784],"type":"Point"}
}