{
  "type": "Feature",
  "properties": {
    "addr:full":"Rue De Villechien 49124 St Barth\u00e9l\u00e9my D'Anjou Pays de Loire 49124",
    "addr:postcode":"49124;49124",
    "addr:street":"Rue De Villechien;D'Anjou",
    "iso:country":"FR",
    "sg:address":"Rue De Villechien 49124 St Barth\u00e9l\u00e9my D'Anjou",
    "sg:classifiers":[
        {
            "category":"Manufacturing",
            "subcategory":"Glass & Minerals",
            "type":"Manufacturing & Wholesale Goods"
        }
    ],
    "sg:phone":"+33 2 41 47 25 25",
    "sg:postcode":"49124",
    "sg:province":"Pays de Loire",
    "sg:tags":[
        "building",
        "material"
    ],
    "wof:name":"Beton Chantier De L'ouest (bco)",
    "wof:placetype":"venue"
},
  "geometry": {"coordinates":[-0.513854,47.460781],"type":"Point"}
}