{
  "type": "Feature",
  "properties": {
    "iso:country":"FR",
    "sg:address":"Avenue De Roquefavour 13580 LA FARE LES OLIVIERS",
    "sg:classifiers":[
        {
            "category":"Wholesale",
            "subcategory":"Wine & Distilled Alcoholic Beverages",
            "type":"Manufacturing & Wholesale Goods"
        }
    ],
    "sg:phone":"+33 4 90 42 61 47",
    "sg:province":"Languedoc-Roussillon",
    "sg:tags":[
        "french"
    ],
    "wof:name":"Cave Cooperative Vinicole",
    "wof:placetype":"venue"
},
  "geometry": {"coordinates":[5.20054,43.550652],"type":"Point"}
}