{
  "type": "Feature",
  "properties": {
    "addr:full":"17, Rte de Lisle, 55000 Ville sur Saulx Lorraine",
    "addr:housenumber":"17",
    "addr:postcode":"55000",
    "addr:street":"Rte De Lisle",
    "iso:country":"FR",
    "sg:address":"17, Rte de Lisle, 55000 Ville sur Saulx",
    "sg:orig_category":"Unclassifiable Establishments",
    "sg:phone":"+33 3 29 70 21 80",
    "sg:province":"Lorraine",
    "wof:name":"Canova M\u00e9canique S.a.",
    "wof:placetype":"venue"
},
  "geometry": {"coordinates":[5.055702,48.713455],"type":"Point"}
}