{
  "type": "Feature",
  "properties": {
    "iso:country":"FR",
    "sg:address":"30 rue du Chardonnet 59150 Wattrelos",
    "sg:classifiers":[
        {
            "category":"Professional",
            "subcategory":"Management & Consulting",
            "type":"Services"
        }
    ],
    "sg:phone":"+33 3 20 76 93 30",
    "sg:postcode":"59150",
    "sg:province":"Nord Pas-de-Calais",
    "sg:tags":[
        "logistics"
    ],
    "wof:name":"Frans Maas Logistique Lille Snc",
    "wof:placetype":"venue"
},
  "geometry": {"coordinates":[3.187413,50.71608],"type":"Point"}
}