{
  "type": "Feature",
  "properties": {
    "addr:full":"Grande Arche de la D\u00e9fense - Paroi Nord BC Paris la D\u00e9fense C\u00e9dex Haute Normandie 92044",
    "addr:postcode":"92044",
    "addr:street":"De\u0301Fense Paroi Nord",
    "iso:country":"FR",
    "sg:address":"Grande Arche de la D\u00e9fense - Paroi Nord BC",
    "sg:city":"Paris la D\u00e9fense C\u00e9dex",
    "sg:orig_category":"Non-Classified Establishments",
    "sg:phone":"+33 1 40 90 30 45",
    "sg:postcode":"92044",
    "sg:province":"Haute Normandie",
    "wof:name":"Kimoce S.a.",
    "wof:placetype":"venue"
},
  "geometry": {"coordinates":[2.24119,48.888939],"type":"Point"}
}