{
  "type": "Feature",
  "properties": {
    "addr:full":"Le Forum - B\u00e2t. 14 Bayonne Aquitaine 64100",
    "addr:housenumber":"14",
    "addr:postcode":"64100",
    "iso:country":"FR",
    "sg:address":"Le Forum - B\u00e2t. 14",
    "sg:city":"Bayonne",
    "sg:orig_category":"Unclassifiable Establishments",
    "sg:phone":"+33 5 59 58 38 00",
    "sg:postcode":"64100",
    "sg:province":"Aquitaine",
    "wof:name":"An\u00e9lia S.a.",
    "wof:placetype":"venue"
},
  "geometry": {"coordinates":[-1.494033,43.493565],"type":"Point"}
}