{
  "type": "Feature",
  "properties": {
    "iso:country":"FR",
    "sg:address":"Av. du G\u00e9n\u00e9ral de Gaulle",
    "sg:city":"La Calmette",
    "sg:orig_category":"Unclassifiable Establishments",
    "sg:phone":"+33 4 66 63 17 60",
    "sg:postcode":"30190",
    "sg:province":"Languedoc-Roussillon",
    "wof:name":"Clavel Bruyas S.a.",
    "wof:placetype":"venue"
},
  "geometry": {"coordinates":[4.261203,43.925053],"type":"Point"}
}