{
  "type": "Feature",
  "properties": {
    "addr:full":"B.P. 5, 57150 Creutzwald^^Angle rue de Royan et 1 rue d'Orodour, 57150 Creutzwald Lorraine",
    "addr:housenumber":"5;1",
    "addr:postcode":"57150;57150",
    "addr:street":"B.P.;Rue De Royan Et;Rue D'Orodour",
    "iso:country":"FR",
    "sg:address":"B.P. 5, 57150 Creutzwald^^Angle rue de Royan et 1 rue d'Orodour, 57150 Creutzwald",
    "sg:orig_category":"Non-Classified Establishments",
    "sg:phone":"+33 3 87 29 87 29",
    "sg:province":"Lorraine",
    "wof:name":"Turnwald S.a.r.l.",
    "wof:placetype":"venue"
},
  "geometry": {"coordinates":[6.691629,49.192879],"type":"Point"}
}