{
  "type": "Feature",
  "properties": {
    "iso:country":"FR",
    "sg:address":"92/94 boulevard Richard-Lenoir 75011 Paris",
    "sg:classifiers":[
        {
            "category":"Manufacturing",
            "subcategory":"Tools & Machinery",
            "type":"Manufacturing & Wholesale Goods"
        }
    ],
    "sg:phone":"+33 1 43 14 30 00",
    "sg:province":"Ile de France",
    "sg:tags":[
        "machine",
        "special"
    ],
    "wof:name":"H-k Et Silca Unican S.a.r.l.",
    "wof:placetype":"venue"
},
  "geometry": {"coordinates":[2.372554,48.86264],"type":"Point"}
}