{
  "type": "Feature",
  "properties": {
    "iso:country":"FR",
    "sg:address":"63, Rte d'Ingwiller, 67290 La Petite Pierre",
    "sg:city":"Volksberg",
    "sg:orig_category":"Non-Classified Establishments",
    "sg:phone":"+33 3 88 71 75 00",
    "sg:postcode":"67290",
    "sg:province":"Alsace",
    "wof:name":"La Clairi\u00e8re",
    "wof:placetype":"venue"
},
  "geometry": {"coordinates":[7.321657,48.858002],"type":"Point"}
}