{
  "type": "Feature",
  "properties": {
    "iso:country":"FR",
    "sg:address":"Zi D'Etriche 49500 Segr\u00e9",
    "sg:classifiers":[
        {
            "category":"Wholesale",
            "subcategory":"Meat",
            "type":"Manufacturing & Wholesale Goods"
        }
    ],
    "sg:phone":"+33 2 41 94 71 00",
    "sg:postcode":"49500",
    "sg:province":"Pays de Loire",
    "sg:tags":[
        "food",
        "cooked",
        "product",
        "related"
    ],
    "wof:name":"Toque Angevine (la)",
    "wof:placetype":"venue"
},
  "geometry": {"coordinates":[-0.859661,47.69688],"type":"Point"}
}