{
  "type": "Feature",
  "properties": {
    "addr:full":"80 av R\u00e9publique; Tassin",
    "addr:street":"80 Av Re\u0301Publique",
    "iso:country":"FR",
    "sg:address":"80 av R\u00e9publique; Tassin",
    "sg:classifiers":[
        {
            "category":"Banks & Credit Unions",
            "subcategory":"Bank",
            "type":"Services"
        }
    ],
    "sg:phone":"+33 3378342991",
    "wof:name":"Cr\u00e9dit Agricole Du Sud Est",
    "wof:placetype":"venue"
},
  "geometry": {"coordinates":[8.813945,41.758347],"type":"Point"}
}