{
  "type": "Feature",
  "properties": {
    "addr:full":"6, Rte de Lutzelbourg, 67700 Saverne Saverne Alsace 67700",
    "addr:housenumber":"6",
    "addr:postcode":"67700;67700",
    "addr:street":"Rte De Lutzelbourg",
    "iso:country":"FR",
    "sg:address":"6, Rte de Lutzelbourg, 67700 Saverne",
    "sg:city":"Saverne",
    "sg:orig_category":"Unclassifiable Establishments",
    "sg:phone":"+33 3 88 03 11 03",
    "sg:postcode":"67700",
    "sg:province":"Alsace",
    "wof:name":"Sumar S.a.r.l.",
    "wof:placetype":"venue"
},
  "geometry": {"coordinates":[7.29244,48.73019],"type":"Point"}
}