{
  "type": "Feature",
  "properties": {
    "addr:full":"B.P. 17, 69240 Bourg de Thizy C\u00e9dex^^La Chassi\u00e8re, 69240 Bourg de Thizy Rhone-Alpes",
    "addr:postcode":"69240;69240",
    "addr:street":"B.P. 17;Chassie\u0300Re",
    "iso:country":"FR",
    "sg:address":"B.P. 17, 69240 Bourg de Thizy C\u00e9dex^^La Chassi\u00e8re, 69240 Bourg de Thizy",
    "sg:orig_category":"Non-Classified Establishments",
    "sg:phone":"+33 4 74 64 04 03",
    "sg:province":"Rhone-Alpes",
    "wof:name":"Thoviste S.a.",
    "wof:placetype":"venue"
},
  "geometry": {"coordinates":[4.315778,46.028179],"type":"Point"}
}