{
  "type": "Feature",
  "properties": {
    "addr:full":"26, Rte de Toulouse, 31620 Fronton Midi Pyr\u00e9n\u00e9es",
    "addr:housenumber":"26",
    "addr:postcode":"31620",
    "addr:street":"Rte De Toulouse",
    "iso:country":"FR",
    "sg:address":"26, Rte de Toulouse, 31620 Fronton",
    "sg:orig_category":"Non-Classified Establishments",
    "sg:phone":"+33 5 61 82 62 03",
    "sg:province":"Midi Pyr\u00e9n\u00e9es",
    "wof:name":"Laulanie Jolivet Midi-pyr\u00e9n\u00e9es S.a.r.l.",
    "wof:placetype":"venue"
},
  "geometry": {"coordinates":[1.391221,43.833183],"type":"Point"}
}