{
  "type": "Feature",
  "properties": {
    "iso:country":"FR",
    "sg:address":"La Gare 47300 Villeneuve sur Lot",
    "sg:city":"Villeneuve-sur-Lot",
    "sg:orig_category":"Unclassifiable Establishments",
    "sg:phone":"+33 5 53 49 09 45",
    "sg:postcode":"47300",
    "sg:province":"Aquitaine",
    "wof:name":"Terres Du Sud S.c.a.",
    "wof:placetype":"venue"
},
  "geometry": {"coordinates":[0.757642,44.367058],"type":"Point"}
}