{
  "type": "Feature",
  "properties": {
    "iso:country":"FR",
    "sg:address":"2, Rue du Colonel Chabonnet, 69500 Bron",
    "sg:orig_category":"Non-Classified Establishments",
    "sg:phone":"+33 4 72 14 28 80",
    "sg:postcode":"69500",
    "sg:province":"Rhone-Alpes",
    "wof:name":"Gessi Groupe S.a.",
    "wof:placetype":"venue"
},
  "geometry": {"coordinates":[4.924389,45.727745],"type":"Point"}
}