{
  "type": "Feature",
  "properties": {
    "addr:full":"76 Rue St Jean 31130 Balma Midi Pyr\u00e9n\u00e9es 31130",
    "addr:housenumber":"76",
    "addr:postcode":"31130;31130",
    "addr:street":"Rue St Jean",
    "iso:country":"FR",
    "sg:address":"76 Rue St Jean 31130 Balma",
    "sg:classifiers":[
        {
            "category":"Banks & Credit Unions",
            "subcategory":"Financial Services",
            "type":"Services"
        }
    ],
    "sg:phone":"+33 5 62 57 33 00",
    "sg:postcode":"31130",
    "sg:province":"Midi Pyr\u00e9n\u00e9es",
    "sg:tags":[
        "banking",
        "finance",
        "insurance"
    ],
    "wof:name":"Cabinet Oreglia Et Christophe Sarl",
    "wof:placetype":"venue"
},
  "geometry": {"coordinates":[1.484393,43.626701],"type":"Point"}
}