{
  "type": "Feature",
  "properties": {
    "iso:country":"FR",
    "sg:address":"47, Quai de Champagne, 94170 Le Perreux sur Marne",
    "sg:orig_category":"Unclassifiable Establishments",
    "sg:phone":"+33 1 48 72 97 79",
    "sg:province":"Ile de France",
    "wof:name":"Mirabelle S.a.",
    "wof:placetype":"venue"
},
  "geometry": {"coordinates":[2.511986,48.841206],"type":"Point"}
}