{
  "type": "Feature",
  "properties": {
    "iso:country":"FR",
    "sg:address":"Av. de Paris",
    "sg:city":"Ern\u00e9e",
    "sg:orig_category":"Non-Classified Establishments",
    "sg:phone":"+33 2 43 05 15 68",
    "sg:postcode":"53500",
    "sg:province":"Pays de Loire",
    "wof:name":"Tenneco Automotive France S.a.",
    "wof:placetype":"venue"
},
  "geometry": {"coordinates":[-1.027721,48.273811],"type":"Point"}
}