{
  "type": "Feature",
  "properties": {
    "iso:country":"FR",
    "sg:address":"B.P. 2022, 30904 N\u00eemes C\u00e9dex 2^^556, Chemin du Cheylon, 30900 N\u00eemes",
    "sg:orig_category":"Non-Classified Establishments",
    "sg:phone":"+33 4 66 38 77 77",
    "sg:postcode":"30900",
    "sg:province":"Languedoc-Roussillon",
    "wof:name":"Conserves France S.a.",
    "wof:placetype":"venue"
},
  "geometry": {"coordinates":[4.356115,43.830025],"type":"Point"}
}