{
  "type": "Feature",
  "properties": {
    "iso:country":"FR",
    "sg:address":"4 Rte De Malay Le Grand 89100 Maillot",
    "sg:city":"Maillot",
    "sg:classifiers":[
        {
            "category":"Manufacturing",
            "subcategory":"Metals",
            "type":"Manufacturing & Wholesale Goods"
        }
    ],
    "sg:phone":"+33 3 86 83 77 80",
    "sg:postcode":"89100",
    "sg:province":"Bourgogne",
    "sg:tags":[
        "processing",
        "-",
        "metalworking",
        "metallic",
        "metallurgy",
        "finished"
    ],
    "wof:name":"Sa Mecanique Et Chaudronnerie De Bourgogne (mcb)",
    "wof:placetype":"venue"
},
  "geometry": {"coordinates":[3.3115,48.150352],"type":"Point"}
}