{
  "type": "Feature",
  "properties": {
    "addr:full":"81, Av. de la Lib\u00e9ration, 74950 Scionzier Rhone-Alpes 74950",
    "addr:postcode":"74950;74950",
    "addr:street":"81 Av. De La Libe\u0301Ration;Rhone-Alpes",
    "iso:country":"FR",
    "sg:address":"81, Av. de la Lib\u00e9ration, 74950 Scionzier",
    "sg:orig_category":"Unclassifiable Establishments",
    "sg:phone":"+33 4 50 98 03 10",
    "sg:postcode":"74950",
    "sg:province":"Rhone-Alpes",
    "wof:name":"Delevaud Denis",
    "wof:placetype":"venue"
},
  "geometry": {"coordinates":[6.540585,46.05648],"type":"Point"}
}