{
  "type": "Feature",
  "properties": {
    "iso:country":"FR",
    "sg:address":"81, Av. de la Lib\u00e9ration, 74950 Scionzier",
    "sg:orig_category":"Unclassifiable Establishments",
    "sg:phone":"+33 4 50 98 03 10",
    "sg:postcode":"74950",
    "sg:province":"Rhone-Alpes",
    "wof:name":"Delevaud Denis",
    "wof:placetype":"venue"
},
  "geometry": {"coordinates":[6.540585,46.05648],"type":"Point"}
}