{
  "type": "Feature",
  "properties": {
    "addr:full":"Zi Sauni\u00e8re 89600 St Florentin Ch\u00e9u Bourgogne 89600",
    "addr:postcode":"89600;89600",
    "iso:country":"FR",
    "sg:address":"Zi Sauni\u00e8re 89600 St Florentin",
    "sg:city":"Ch\u00e9u",
    "sg:classifiers":[
        {
            "category":"Professional",
            "subcategory":"Engineering",
            "type":"Services"
        }
    ],
    "sg:phone":"+33 3 86 43 79 30",
    "sg:postcode":"89600",
    "sg:province":"Bourgogne",
    "sg:tags":[
        "machine",
        "-",
        "environment",
        "equipment",
        "machinery",
        "mechanical"
    ],
    "wof:name":"Sicli (cie Centrale) Sa",
    "wof:placetype":"venue"
},
  "geometry": {"coordinates":[3.72972,48.002575],"type":"Point"}
}