{
  "type": "Feature",
  "properties": {
    "iso:country":"FR",
    "sg:address":"341, Rue Gambetta, 59000 Lille",
    "sg:orig_category":"Non-Classified Establishments",
    "sg:phone":"+33 3 20 57 66 40",
    "sg:province":"Nord Pas-de-Calais",
    "wof:name":"Etic S.a.",
    "wof:placetype":"venue"
},
  "geometry": {"coordinates":[3.04839,50.626701],"type":"Point"}
}