{
  "type": "Feature",
  "properties": {
    "addr:full":"11 Boulevard De La R\u00e9publique 13100 Aix En Provence Nord Pas-de-Calais",
    "addr:housenumber":"11",
    "addr:postcode":"13100",
    "addr:street":"Boulevard De La Re\u0301Publique;En Provence Nord",
    "iso:country":"FR",
    "sg:address":"11 Boulevard De La R\u00e9publique 13100 Aix En Provence",
    "sg:classifiers":[
        {
            "category":"Bakery",
            "type":"Food & Drink"
        }
    ],
    "sg:phone":"+33 4 42 26 08 13",
    "sg:province":"Nord Pas-de-Calais",
    "sg:tags":[
        "cake",
        "product",
        "related",
        "bread"
    ],
    "wof:name":"Sarl La Fournaise",
    "wof:placetype":"venue"
},
  "geometry": {"coordinates":[5.444549,43.526844],"type":"Point"}
}