{
  "type": "Feature",
  "properties": {
    "iso:country":"FR",
    "sg:address":"Rte Des Falaises 27100 Le Vaudreuil",
    "sg:classifiers":[
        {
            "category":"Manufacturing",
            "subcategory":"Rubber & Plastics",
            "type":"Manufacturing & Wholesale Goods"
        }
    ],
    "sg:phone":"+33 2 32 63 73 73",
    "sg:postcode":"27100",
    "sg:province":"Haute Normandie",
    "sg:tags":[
        "machine",
        "engineering",
        "-",
        "mechanical"
    ],
    "wof:name":"Valois Sas",
    "wof:placetype":"venue"
},
  "geometry": {"coordinates":[1.194895,49.2565],"type":"Point"}
}