{
  "type": "Feature",
  "properties": {
    "addr:full":"13 Rue Du Caire 56300 Pontivy Pontivy Bretagne 56300",
    "addr:housenumber":"13",
    "addr:postcode":"56300;56300",
    "addr:street":"Rue Du Caire;Pontivy",
    "iso:country":"FR",
    "sg:address":"13 Rue Du Caire 56300 Pontivy",
    "sg:city":"Pontivy",
    "sg:classifiers":[
        {
            "category":"Manufacturing",
            "subcategory":"Printing",
            "type":"Manufacturing & Wholesale Goods"
        }
    ],
    "sg:phone":"+33 2 97 25 34 27",
    "sg:postcode":"56300",
    "sg:province":"Bretagne",
    "sg:tags":[
        "publishing"
    ],
    "wof:name":"Le Noheh Imprimeurs",
    "wof:placetype":"venue"
},
  "geometry": {"coordinates":[-2.965022,48.059414],"type":"Point"}
}