{
  "type": "Feature",
  "properties": {
    "addr:full":"Rue Andr\u00e9 Citr\u00f6en Le Mans Pays de Loire 72000",
    "addr:postcode":"72000",
    "addr:street":"Rue Andre\u0301 Citroeen",
    "iso:country":"FR",
    "sg:address":"Rue Andr\u00e9 Citr\u00f6en",
    "sg:city":"Le Mans",
    "sg:orig_category":"Unclassifiable Establishments",
    "sg:phone":"+33 2 43 28 64 55",
    "sg:postcode":"72000",
    "sg:province":"Pays de Loire",
    "wof:name":"Buro'mag S.a.r.l.",
    "wof:placetype":"venue"
},
  "geometry": {"coordinates":[0.173552,48.028774],"type":"Point"}
}