{
  "type": "Feature",
  "properties": {
    "addr:full":"7bis, Rue des Champs Pacaud, 58000 Nevers Nevers Bourgogne 58000",
    "addr:housenumber":"7bis",
    "addr:postcode":"58000;58000",
    "addr:street":"Rue Des Champs Pacaud",
    "iso:country":"FR",
    "sg:address":"7bis, Rue des Champs Pacaud, 58000 Nevers",
    "sg:city":"Nevers",
    "sg:orig_category":"Unclassifiable Establishments",
    "sg:phone":"+33 3 86 71 92 70",
    "sg:postcode":"58000",
    "sg:province":"Bourgogne",
    "wof:name":"Cat - Centre D'aide Par Le Travail",
    "wof:placetype":"venue"
},
  "geometry": {"coordinates":[3.182809,46.993401],"type":"Point"}
}