{
  "type": "Feature",
  "properties": {
    "addr:full":"Rue Oberwald 68360 Soultz Haut Rhin Soultz-Haut-Rhin Alsace 68360",
    "addr:postcode":"68360;68360",
    "addr:street":"Rue Oberwald;Soultz-Haut-Rhin",
    "iso:country":"FR",
    "sg:address":"Rue Oberwald 68360 Soultz Haut Rhin",
    "sg:city":"Soultz-Haut-Rhin",
    "sg:classifiers":[
        {
            "category":"Bakery",
            "type":"Food & Drink"
        }
    ],
    "sg:phone":"+33 3 89 74 75 20",
    "sg:postcode":"68360",
    "sg:province":"Alsace",
    "sg:tags":[
        "cake",
        "product",
        "related",
        "bread"
    ],
    "wof:name":"Sevenday Cereals Sa",
    "wof:placetype":"venue"
},
  "geometry": {"coordinates":[7.238481,47.893761],"type":"Point"}
}