{
  "type": "Feature",
  "properties": {
    "addr:full":"139, Av. Paul Vaillant Couturier, 93120 La Courneuve Ile de France",
    "addr:postcode":"93120",
    "addr:street":"139 Av. Paul Vaillant Couturier",
    "iso:country":"FR",
    "sg:address":"139, Av. Paul Vaillant Couturier, 93120 La Courneuve",
    "sg:orig_category":"Non-Classified Establishments",
    "sg:phone":"+33 1 43 11 15 26",
    "sg:province":"Ile de France",
    "wof:name":"H.t.& C. S.a.r.l. - High-tech Et Communications",
    "wof:placetype":"venue"
},
  "geometry": {"coordinates":[2.415326,48.92535],"type":"Point"}
}