{
  "type": "Feature",
  "properties": {
    "iso:country":"FR",
    "sg:address":"1 Place Des Degres Tour Voltaire La Def 7",
    "sg:city":"Puteaux",
    "sg:classifiers":[
        {
            "category":"Banks & Credit Unions",
            "subcategory":"Financial Services",
            "type":"Services"
        }
    ],
    "sg:phone":"+33 1 49 07 50 50",
    "sg:postcode":"92800",
    "sg:province":"Ile de France",
    "sg:tags":[
        "banking",
        "finance",
        "insurance"
    ],
    "wof:name":"Banque Worms",
    "wof:placetype":"venue"
},
  "geometry": {"coordinates":[2.236102,48.890079],"type":"Point"}
}