{
  "type": "Feature",
  "properties": {
    "iso:country":"FR",
    "sg:address":"7 Av Champagne 91420 Morangis",
    "sg:classifiers":[
        {
            "category":"Wholesale",
            "subcategory":"Machinery & Supplies",
            "type":"Manufacturing & Wholesale Goods"
        }
    ],
    "sg:phone":"+33 1 64 54 91 91",
    "sg:postcode":"91420",
    "sg:province":"Ile de France",
    "sg:tags":[
        "handling",
        "material",
        "-",
        "machine",
        "equipment",
        "engineering",
        "mechanical"
    ],
    "wof:name":"Chantiers Levage Manutention",
    "wof:placetype":"venue"
},
  "geometry": {"coordinates":[2.34068,48.705109],"type":"Point"}
}