{
  "type": "Feature",
  "properties": {
    "iso:country":"FR",
    "sg:address":"16 bis, Rue Victor Grignard, 42000 Saint Etienne",
    "sg:orig_category":"Non-Classified Establishments",
    "sg:phone":"+33 4 77 93 57 58",
    "sg:postcode":"42000",
    "sg:province":"Rhone-Alpes",
    "wof:name":"Bennes Rh\u00f4ne Alpes S.a.",
    "wof:placetype":"venue"
},
  "geometry": {"coordinates":[4.400625,45.46022],"type":"Point"}
}