{
  "type": "Feature",
  "properties": {
    "iso:country":"FR",
    "sg:address":"L'Etang 42440 Noi\u00e9table",
    "sg:classifiers":[
        {
            "category":"Shopping",
            "subcategory":"Crafts & Fabrics",
            "type":"Retail Goods"
        }
    ],
    "sg:phone":"+33 4 77 24 72 45",
    "sg:postcode":"42440",
    "sg:province":"Rhone-Alpes",
    "sg:tags":[
        "textile",
        "clothing"
    ],
    "wof:name":"B B A Borrel Bouvard Arthaud",
    "wof:placetype":"venue"
},
  "geometry": {"coordinates":[-97.821732,35.04409],"type":"Point"}
}