{
  "type": "Feature",
  "properties": {
    "addr:full":"40 Av Bugeaud 75116 Paris Centre",
    "addr:postcode":"75116",
    "addr:street":"40 Av Bugeaud",
    "iso:country":"FR",
    "sg:address":"40 Av Bugeaud 75116 Paris",
    "sg:classifiers":[
        {
            "category":"Professional",
            "subcategory":"Printing & Photocopies",
            "type":"Services"
        }
    ],
    "sg:phone":"+33 1 56 26 50 00",
    "sg:province":"Centre",
    "sg:tags":[
        "publishing"
    ],
    "wof:name":"I D Information Dentaire Id",
    "wof:placetype":"venue"
},
  "geometry": {"coordinates":[2.280292,48.870899],"type":"Point"}
}