{
  "type": "Feature",
  "properties": {
    "iso:country":"FR",
    "sg:address":"La Source 07310 Arcens",
    "sg:classifiers":[
        {
            "category":"Food Court",
            "type":"Food & Drink"
        }
    ],
    "sg:phone":"+33 4 75 30 42 00",
    "sg:postcode":"07310",
    "sg:province":"Rhone-Alpes",
    "sg:tags":[
        "product",
        "related"
    ],
    "wof:name":"Sources Darcens (sa D'exploitation Des)",
    "wof:placetype":"venue"
},
  "geometry": {"coordinates":[4.29611,44.928581],"type":"Point"}
}