{
  "type": "Feature",
  "properties": {
    "addr:full":"15, Quai de la P\u00eacherie, 60700 Pont Sainte Maxence Picardie",
    "addr:housenumber":"15",
    "addr:postcode":"60700",
    "addr:street":"Quai De La Pe\u0302Cherie",
    "iso:country":"FR",
    "sg:address":"15, Quai de la P\u00eacherie, 60700 Pont Sainte Maxence",
    "sg:orig_category":"Unclassifiable Establishments",
    "sg:phone":"+33 3 44 72 21 06",
    "sg:province":"Picardie",
    "wof:name":"Steco S.a. - Soci\u00e9t\u00e9 De Transports Et Camionnage De L'oise",
    "wof:placetype":"venue"
},
  "geometry": {"coordinates":[2.60698,49.302635],"type":"Point"}
}