{
  "type": "Feature",
  "properties": {
    "addr:full":"B.P. 2, 59806 Lille C\u00e9dex^^5, Rue Deschodt, 59800 Lille Nord Pas-de-Calais",
    "addr:housenumber":"2",
    "addr:postcode":"59806",
    "addr:street":"B.P.;Rue Deschodt;Lille;Pas-De-Calais",
    "iso:country":"FR",
    "sg:address":"B.P. 2, 59806 Lille C\u00e9dex^^5, Rue Deschodt, 59800 Lille",
    "sg:orig_category":"Non-Classified Establishments",
    "sg:phone":"+33 3 20 57 48 79",
    "sg:province":"Nord Pas-de-Calais",
    "wof:name":"Steverlynck S.n.c.",
    "wof:placetype":"venue"
},
  "geometry": {"coordinates":[3.08024,50.636189],"type":"Point"}
}