{
  "type": "Feature",
  "properties": {
    "iso:country":"FR",
    "sg:address":"ZI de Rosarge",
    "sg:city":"Les Echets",
    "sg:orig_category":"Unclassifiable Establishments",
    "sg:phone":"+33 4 72 26 57 57",
    "sg:postcode":"01700",
    "sg:province":"Rhone-Alpes",
    "wof:name":"S.a.c.l.a. S.a.",
    "wof:placetype":"venue"
},
  "geometry": {"coordinates":[4.912065,45.872379],"type":"Point"}
}