{
  "type": "Feature",
  "properties": {
    "addr:full":"RN 562 - Quartier la Lombardie Tourrettes Provence-Alpes-C\u00f4te d'Azur 83440",
    "addr:postcode":"83440",
    "addr:street":"Rn 562;La Lombardie Tourrettes",
    "iso:country":"FR",
    "sg:address":"RN 562 - Quartier la Lombardie",
    "sg:city":"Tourrettes",
    "sg:orig_category":"Non-Classified Establishments",
    "sg:phone":"+33 4 94 39 09 70",
    "sg:postcode":"83440",
    "sg:province":"Provence-Alpes-C\u00f4te d'Azur",
    "wof:name":"Soci\u00e9t\u00e9 D'exploitation Des Entreprises Bertrand S.a.",
    "wof:placetype":"venue"
},
  "geometry": {"coordinates":[6.704845,43.607235],"type":"Point"}
}