{
  "type": "Feature",
  "properties": {
    "iso:country":"FR",
    "sg:address":"B.P. 309, 47008 Agen C\u00e9dex^^750, Av. du Docteur Jean Bru, 47000 Agen",
    "sg:city":"Agen",
    "sg:orig_category":"Non-Classified Establishments",
    "sg:phone":"+33 5 53 77 03 00",
    "sg:postcode":"47000",
    "sg:province":"Aquitaine",
    "wof:name":"Imprimerie Moderne S.a.",
    "wof:placetype":"venue"
},
  "geometry": {"coordinates":[0.62061,44.205109],"type":"Point"}
}