{
  "type": "Feature",
  "properties": {
    "addr:full":"158, Av. de Verdun, 92130 Issy les Moulineaux Ile de France",
    "addr:postcode":"92130",
    "addr:street":"158 Av. De Verdun",
    "iso:country":"FR",
    "sg:address":"158, Av. de Verdun, 92130 Issy les Moulineaux",
    "sg:orig_category":"Non-Classified Establishments",
    "sg:phone":"+33 1 46 62 85 85",
    "sg:province":"Ile de France",
    "wof:name":"G.f.i. S.a.s",
    "wof:placetype":"venue"
},
  "geometry": {"coordinates":[2.253372,48.818882],"type":"Point"}
}