{
  "type": "Feature",
  "properties": {
    "addr:full":"B.P. 13, 62122 Lapugnoy^^Rue Jules Ferry - ZI, 62122 Lapugnoy Nord Pas-de-Calais",
    "addr:postcode":"62122;62122",
    "addr:street":"B.P. 13;Jules Ferry Zi",
    "iso:country":"FR",
    "sg:address":"B.P. 13, 62122 Lapugnoy^^Rue Jules Ferry - ZI, 62122 Lapugnoy",
    "sg:orig_category":"Non-Classified Establishments",
    "sg:phone":"+33 3 21 64 65 65",
    "sg:province":"Nord Pas-de-Calais",
    "wof:name":"G.t.i. S.a.",
    "wof:placetype":"venue"
},
  "geometry": {"coordinates":[2.53987,50.515865],"type":"Point"}
}