{
  "type": "Feature",
  "properties": {
    "addr:full":"B.P. 27 Bressure C\u00e9dex^^La Faye Br\u00e9tignolles 79140 Br\u00e9tignolles Poitou-Charentes 79301",
    "addr:postcode":"79140;79301",
    "addr:street":"B.P. 27 Bressure Ce\u0301Dex^^La Faye Bre\u0301Tignolles;Bre\u0301Tignolles",
    "iso:country":"FR",
    "sg:address":"B.P. 27",
    "sg:city":"Bressure C\u00e9dex^^La Faye Br\u00e9tignolles 79140 Br\u00e9tignolles",
    "sg:orig_category":"Non-Classified Establishments",
    "sg:phone":"+33 5 49 74 55 60",
    "sg:postcode":"79301",
    "sg:province":"Poitou-Charentes",
    "wof:name":"Millet Et Compagnie S.a.",
    "wof:placetype":"venue"
},
  "geometry": {"coordinates":[-0.684999,46.808239],"type":"Point"}
}