{
  "type": "Feature",
  "properties": {
    "iso:country":"FR",
    "sg:address":"Rue Pasteur",
    "sg:city":"Les Prunus 69780 Mions",
    "sg:classifiers":[
        {
            "category":"Shopping",
            "type":"Retail Goods"
        }
    ],
    "sg:phone":"+33 4 78 21 82 26",
    "sg:postcode":"69780",
    "sg:province":"Rhone-Alpes",
    "sg:tags":[
        "metallurgy",
        "finished",
        "-",
        "metalworking",
        "metallic"
    ],
    "wof:name":"Ste Lyon Tuyauterie Tolerie Industrielle",
    "wof:placetype":"venue"
},
  "geometry": {"coordinates":[4.954582,45.662968],"type":"Point"}
}