{
  "type": "Feature",
  "properties": {
    "addr:full":"B.P. 18, 84603 Valr\u00e9as C\u00e9dex^^5, Rue Chasse Coquin, 84600 Valr\u00e9as Auvergne",
    "addr:postcode":"84603;84600",
    "addr:street":"B.P. 18;Rue Chasse Coquin",
    "iso:country":"FR",
    "sg:address":"B.P. 18, 84603 Valr\u00e9as C\u00e9dex^^5, Rue Chasse Coquin, 84600 Valr\u00e9as",
    "sg:orig_category":"Non-Classified Establishments",
    "sg:phone":"+33 4 90 28 58 58",
    "sg:province":"Auvergne",
    "wof:name":"Imcarvau",
    "wof:placetype":"venue"
},
  "geometry": {"coordinates":[4.911945,44.359257],"type":"Point"}
}