{
  "type": "Feature",
  "properties": {
    "addr:full":"Lieu dit La Place 71170 Coublanc Coublanc Bourgogne 71170",
    "addr:postcode":"71170;71170",
    "addr:street":"Lieu Dit La Place",
    "iso:country":"FR",
    "sg:address":"Lieu dit La Place 71170 Coublanc",
    "sg:city":"Coublanc",
    "sg:orig_category":"Non-Classified Establishments",
    "sg:phone":"+33 3 85 26 31 07",
    "sg:postcode":"71170",
    "sg:province":"Bourgogne",
    "wof:name":"Coublanc Textiles S.a.r.l.",
    "wof:placetype":"venue"
},
  "geometry": {"coordinates":[4.266825,46.167316],"type":"Point"}
}