{
  "type": "Feature",
  "properties": {
    "addr:full":"19 Rue Des Mines 54800 Jarny Lorraine",
    "addr:housenumber":"19",
    "addr:postcode":"54800",
    "addr:street":"Rue Des Mines",
    "iso:country":"FR",
    "sg:address":"19 Rue Des Mines 54800 Jarny",
    "sg:classifiers":[
        {
            "category":"Professional",
            "type":"Services"
        }
    ],
    "sg:phone":"+33 3 82 33 09 54",
    "sg:province":"Lorraine",
    "sg:tags":[
        "transport",
        "road"
    ],
    "wof:name":"Ets Chollot Sa",
    "wof:placetype":"venue"
},
  "geometry": {"coordinates":[5.88713,49.157776],"type":"Point"}
}