{
  "type": "Feature",
  "properties": {
    "addr:full":"BP 57 87202 St Junien Cedex Limousin",
    "addr:housenumber":"bp 57",
    "addr:postcode":"87202",
    "iso:country":"FR",
    "sg:address":"BP 57 87202 St Junien Cedex",
    "sg:classifiers":[
        {
            "category":"Home & Garden",
            "subcategory":"Furniture",
            "type":"Retail Goods"
        }
    ],
    "sg:phone":"+33 5 55 02 13 38",
    "sg:province":"Limousin",
    "sg:tags":[
        "wood"
    ],
    "wof:name":"Fougere Sa Bois Et Derives Sa",
    "wof:placetype":"venue"
},
  "geometry": {"coordinates":[0.901046,45.887379],"type":"Point"}
}