{
  "type": "Feature",
  "properties": {
    "iso:country":"FR",
    "sg:address":"Rue Denis Papin Za D'Arvigny 77550 Moissy Cramayel",
    "sg:classifiers":[
        {
            "category":"Professional",
            "type":"Services"
        }
    ],
    "sg:phone":"+33 1 64 13 70 70",
    "sg:province":"Ile de France",
    "sg:tags":[
        "transport",
        "road"
    ],
    "wof:name":"Via Location",
    "wof:placetype":"venue"
},
  "geometry": {"coordinates":[2.587582,48.611679],"type":"Point"}
}