{
  "type": "Feature",
  "properties": {
    "addr:full":"46, Bd de la Prairie au Duc, 44200 Nantes Pays de Loire",
    "addr:housenumber":"46",
    "addr:postcode":"44200",
    "addr:street":"Bd De La Prairie Au Duc",
    "iso:country":"FR",
    "sg:address":"46, Bd de la Prairie au Duc, 44200 Nantes",
    "sg:orig_category":"Unclassifiable Establishments",
    "sg:phone":"+33 2 40 41 00 50",
    "sg:province":"Pays de Loire",
    "wof:name":"Rineau Exploitation S.a.r.l.",
    "wof:placetype":"venue"
},
  "geometry": {"coordinates":[-1.561852,47.204643],"type":"Point"}
}