{
  "type": "Feature",
  "properties": {
    "iso:country":"FR",
    "sg:address":"18 Rue Du Vert Buisson 69100 Villeurbanne",
    "sg:classifiers":[
        {
            "category":"Manufacturing",
            "subcategory":"Rubber & Plastics",
            "type":"Manufacturing & Wholesale Goods"
        }
    ],
    "sg:phone":"+33 4 78 79 42 80",
    "sg:province":"Rhone-Alpes",
    "wof:name":"Contitech Anoflex Sas",
    "wof:placetype":"venue"
},
  "geometry": {"coordinates":[4.901702,45.784153],"type":"Point"}
}