{
  "type": "Feature",
  "properties": {
    "addr:full":"8, Rue des Deux C\u00e8dres - Roissy A\u00e9roport Charles de Gaulle - Roissy en France , 95711 Roissy A\u00e9ropor Aquitaine",
    "addr:housenumber":"8",
    "addr:postcode":"95711",
    "addr:street":"Rue Des Deux Ce\u0300Dres;Charles De Gaulle",
    "iso:country":"FR",
    "sg:address":"8, Rue des Deux C\u00e8dres - Roissy A\u00e9roport Charles de Gaulle - Roissy en France , 95711 Roissy A\u00e9ropor",
    "sg:orig_category":"Non-Classified Establishments",
    "sg:phone":"+33 1 48 62 52 95",
    "sg:province":"Aquitaine",
    "wof:name":"95 Express Mg Transports",
    "wof:placetype":"venue"
},
  "geometry": {"coordinates":[2.51524,49.004028],"type":"Point"}
}