{
  "type": "Feature",
  "properties": {
    "addr:full":"5/9, Rue des Foug\u00e8res - Parc Atlantique - Ormeau de Pied , 17100 Saintes Poitou-Charentes 17100",
    "addr:housenumber":"5 / 9",
    "addr:postcode":"17100;17100",
    "addr:street":"Rue Des Fouge\u0300Res Parc;Pied",
    "iso:country":"FR",
    "sg:address":"5/9, Rue des Foug\u00e8res - Parc Atlantique - Ormeau de Pied , 17100 Saintes",
    "sg:orig_category":"Non-Classified Establishments",
    "sg:phone":"+33 5 46 74 20 00",
    "sg:postcode":"17100",
    "sg:province":"Poitou-Charentes",
    "wof:name":"J.b. Constructions S.a.",
    "wof:placetype":"venue"
},
  "geometry": {"coordinates":[-0.663856,45.742168],"type":"Point"}
}