{
  "type": "Feature",
  "properties": {
    "iso:country":"FR",
    "sg:address":"5/9, Rue des Foug\u00e8res - Parc Atlantique - Ormeau de Pied , 17100 Saintes",
    "sg:orig_category":"Non-Classified Establishments",
    "sg:phone":"+33 5 46 74 20 00",
    "sg:postcode":"17100",
    "sg:province":"Poitou-Charentes",
    "wof:name":"J.b. Constructions S.a.",
    "wof:placetype":"venue"
},
  "geometry": {"coordinates":[-0.663856,45.742168],"type":"Point"}
}