{
  "type": "Feature",
  "properties": {
    "addr:full":"B.P. 36, 10150 Pont Sainte Marie^^Rue Saint Aventin, 10150 Creney pr\u00e8s Troyes Champagne",
    "addr:postcode":"10150;10150;pre\u0300s",
    "addr:street":"B.P. 36;Saint Aventin",
    "iso:country":"FR",
    "sg:address":"B.P. 36, 10150 Pont Sainte Marie^^Rue Saint Aventin, 10150 Creney pr\u00e8s Troyes",
    "sg:orig_category":"Non-Classified Establishments",
    "sg:phone":"+33 3 25 76 22 70",
    "sg:province":"Champagne",
    "wof:name":"Filix Lastex S.a.",
    "wof:placetype":"venue"
},
  "geometry": {"coordinates":[4.09298,48.317806],"type":"Point"}
}