{
  "type": "Feature",
  "properties": {
    "iso:country":"FR",
    "sg:address":"ZI Rogerville-Oudalle",
    "sg:city":"Oudalle",
    "sg:orig_category":"Unclassifiable Establishments",
    "sg:phone":"+33 2 35 13 43 10",
    "sg:postcode":"76430",
    "sg:province":"Haute Normandie",
    "wof:name":"Quille S.a.",
    "wof:placetype":"venue"
},
  "geometry": {"coordinates":[0.301672,49.506947],"type":"Point"}
}