{
  "type": "Feature",
  "properties": {
    "addr:full":"10 place Henri Barbusse; Ales; 30106 Languedoc-Roussillon",
    "addr:housenumber":"10",
    "addr:postcode":"30106",
    "addr:street":"Place Henri Barbusse",
    "iso:country":"FR",
    "sg:address":"10 place Henri Barbusse; Ales; 30106",
    "sg:classifiers":[
        {
            "category":"Banks & Credit Unions",
            "subcategory":"Bank",
            "type":"Services"
        }
    ],
    "sg:phone":"+33 3366785400",
    "sg:province":"Languedoc-Roussillon",
    "wof:name":"Banque De France",
    "wof:placetype":"venue"
},
  "geometry": {"coordinates":[4.079973,44.124096],"type":"Point"}
}