{
  "type": "Feature",
  "properties": {
    "addr:full":"Rue Corneille - ZI Neuilly l\u00e8s Dijon Bourgogne 21800",
    "addr:postcode":"21800",
    "addr:street":"Rue Corneille Zi",
    "iso:country":"FR",
    "sg:address":"Rue Corneille - ZI",
    "sg:city":"Neuilly l\u00e8s Dijon",
    "sg:orig_category":"Unclassifiable Establishments",
    "sg:phone":"+33 3 80 47 35 18",
    "sg:postcode":"21800",
    "sg:province":"Bourgogne",
    "wof:name":"Giacomel Agriculture S.a.",
    "wof:placetype":"venue"
},
  "geometry": {"coordinates":[5.135262,47.301807],"type":"Point"}
}