{
  "type": "Feature",
  "properties": {
    "addr:full":"Sous la Penotte zone emploi 16410 Garat Poitou-Charentes 16410",
    "addr:postcode":"16410;16410",
    "addr:street":"Sous La Penotte;Emploi;Garat",
    "iso:country":"FR",
    "sg:address":"Sous la Penotte zone emploi 16410 Garat",
    "sg:classifiers":[
        {
            "category":"Manufacturing",
            "subcategory":"Paper Products",
            "type":"Manufacturing & Wholesale Goods"
        }
    ],
    "sg:phone":"+33 5 45 25 06 06",
    "sg:postcode":"16410",
    "sg:province":"Poitou-Charentes",
    "sg:tags":[
        "packaging",
        "pape",
        "material",
        "-",
        "machine",
        "engineering",
        "mechanical",
        "cardboard"
    ],
    "wof:name":"Mecanelec",
    "wof:placetype":"venue"
},
  "geometry": {"coordinates":[0.210937,45.527626],"type":"Point"}
}