{
  "type": "Feature",
  "properties": {
    "addr:full":"B.P. 402, 27404 Louviers C\u00e9dex^^16, Rue de l'Abreuvoir, 27400 Louviers Haute Normandie 27400",
    "addr:housenumber":"b.p. 402",
    "addr:postcode":"27404;27400;27400",
    "addr:street":"Rue De L'Abreuvoir;Haute Normandie",
    "iso:country":"FR",
    "sg:address":"B.P. 402, 27404 Louviers C\u00e9dex^^16, Rue de l'Abreuvoir, 27400 Louviers",
    "sg:orig_category":"Non-Classified Establishments",
    "sg:phone":"+33 2 32 40 59 51",
    "sg:postcode":"27400",
    "sg:province":"Haute Normandie",
    "wof:name":"A.t.i.m. S.a. - Application Technique Industrielle M\u00e9canique",
    "wof:placetype":"venue"
},
  "geometry": {"coordinates":[1.15324,49.184261],"type":"Point"}
}