{
  "type": "Feature",
  "properties": {
    "addr:full":"Rte de Pont d'Ain Chalamont Rhone-Alpes 01320",
    "addr:postcode":"01320",
    "addr:street":"Rte De Pont D'Ain;Rhone-Alpes",
    "iso:country":"FR",
    "sg:address":"Rte de Pont d'Ain",
    "sg:city":"Chalamont",
    "sg:orig_category":"Non-Classified Establishments",
    "sg:phone":"+33 4 74 46 99 00",
    "sg:postcode":"01320",
    "sg:province":"Rhone-Alpes",
    "wof:name":"Agri Oeuf S.a.r.l.",
    "wof:placetype":"venue"
},
  "geometry": {"coordinates":[5.17109,45.99691],"type":"Point"}
}