{
  "type": "Feature",
  "properties": {
    "iso:country":"FR",
    "sg:address":"108 rue Pierre Brossolette 62110 HENIN BEAUMONT",
    "sg:orig_category":"Trailers, Semi-Trailers",
    "sg:phone":"+33 3 21 79 43 00",
    "sg:province":"Nord Pas-de-Calais",
    "wof:name":"General Trailers Sa",
    "wof:placetype":"venue"
},
  "geometry": {"coordinates":[2.945758,50.414562],"type":"Point"}
}