{
  "type": "Feature",
  "properties": {
    "addr:full":"3, Rue de Gramont, 75002 Paris Ile de France",
    "addr:housenumber":"3",
    "addr:postcode":"75002",
    "addr:street":"Rue De Gramont",
    "iso:country":"FR",
    "sg:address":"3, Rue de Gramont, 75002 Paris",
    "sg:orig_category":"Unclassifiable Establishments",
    "sg:phone":"+33 1 44 77 15 15",
    "sg:province":"Ile de France",
    "wof:name":"C.l.c. Bourse S.a.",
    "wof:placetype":"venue"
},
  "geometry": {"coordinates":[2.336516,48.869209],"type":"Point"}
}