{
  "type": "Feature",
  "properties": {
    "addr:full":"3, Rue Marthe Nollet, 59250 Halluin Nord Pas-de-Calais",
    "addr:housenumber":"3",
    "addr:postcode":"59250",
    "addr:street":"Rue Marthe Nollet",
    "iso:country":"FR",
    "sg:address":"3, Rue Marthe Nollet, 59250 Halluin",
    "sg:orig_category":"Non-Classified Establishments",
    "sg:phone":"+33 3 20 23 71 29",
    "sg:province":"Nord Pas-de-Calais",
    "wof:name":"La Voix Du Nord S.a.",
    "wof:placetype":"venue"
},
  "geometry": {"coordinates":[3.125699,50.782574],"type":"Point"}
}