{
  "type": "Feature",
  "properties": {
    "iso:country":"FR",
    "sg:address":"93, Bd L\u00e9on Gambetta, 46000 Cahors",
    "sg:orig_category":"Unclassifiable Establishments",
    "sg:phone":"+33 5 65 20 80 00",
    "sg:province":"Midi Pyr\u00e9n\u00e9es",
    "wof:name":"Comareg",
    "wof:placetype":"venue"
},
  "geometry": {"coordinates":[1.441678,44.445114],"type":"Point"}
}