{
  "type": "Feature",
  "properties": {
    "addr:full":"3, Rue P\u00e9roux - Lot. Plein Soleil, 26800 Etoile sur Rh\u00f4ne Rhone-Alpes",
    "addr:housenumber":"3",
    "addr:postcode":"26800",
    "addr:street":"Rue Pe\u0301Roux Lot. Plein Soleil",
    "iso:country":"FR",
    "sg:address":"3, Rue P\u00e9roux - Lot. Plein Soleil, 26800 Etoile sur Rh\u00f4ne",
    "sg:orig_category":"Unclassifiable Establishments",
    "sg:phone":"+33 4 75 60 61 09",
    "sg:province":"Rhone-Alpes",
    "wof:name":"Discolor S.a.",
    "wof:placetype":"venue"
},
  "geometry": {"coordinates":[4.907647,44.794395],"type":"Point"}
}