{
  "type": "Feature",
  "properties": {
    "iso:country":"FR",
    "sg:address":"149, Rue des Bruy\u00e8res - ZI de la Saussaye, 45075 Orl\u00e9ans C\u00e9dex 2^^149, Rue des Bruy\u00e8res - ZI de la S",
    "sg:orig_category":"Non-Classified Establishments",
    "sg:phone":"+33 2 38 76 02 11",
    "sg:province":"Champagne",
    "wof:name":"Prohygiena S.a.",
    "wof:placetype":"venue"
},
  "geometry": {"coordinates":[1.90398,47.90139],"type":"Point"}
}