{
  "type": "Feature",
  "properties": {
    "iso:country":"FR",
    "sg:address":"ZAD - La Grange Rouge",
    "sg:city":"Bourr\u00e9",
    "sg:orig_category":"Unclassifiable Establishments",
    "sg:phone":"+33 2 54 71 46 97",
    "sg:postcode":"41400",
    "sg:province":"Centre",
    "wof:name":"Bl\u00e9net S.a.s.",
    "wof:placetype":"venue"
},
  "geometry": {"coordinates":[1.226175,47.345715],"type":"Point"}
}