{
  "type": "Feature",
  "properties": {
    "addr:full":"Rue de la Guillauderie - Parc d'Activit\u00e9s Tournebride La Chevroli\u00e8re Pays de Loire 44118",
    "addr:postcode":"44118",
    "addr:street":"Rue De La Guillauderie Parc D'Activite \u0301S Tournebride",
    "iso:country":"FR",
    "sg:address":"Rue de la Guillauderie - Parc d'Activit\u00e9s Tournebride",
    "sg:city":"La Chevroli\u00e8re",
    "sg:orig_category":"Non-Classified Establishments",
    "sg:phone":"+33 2 51 70 92 00",
    "sg:postcode":"44118",
    "sg:province":"Pays de Loire",
    "wof:name":"Soci\u00e9t\u00e9 Impression De Grandlieu S.a.r.l.",
    "wof:placetype":"venue"
},
  "geometry": {"coordinates":[-1.561948,47.085838],"type":"Point"}
}