{
  "type": "Feature",
  "properties": {
    "addr:full":"18, Rue de J\u00e9rusalem, 37000 Tours Tours Centre 37000",
    "addr:housenumber":"18",
    "addr:postcode":"37000;37000",
    "addr:street":"Rue De Je\u0301Rusalem",
    "iso:country":"FR",
    "sg:address":"18, Rue de J\u00e9rusalem, 37000 Tours",
    "sg:city":"Tours",
    "sg:orig_category":"Non-Classified Establishments",
    "sg:phone":"+33 2 47 61 20 80",
    "sg:postcode":"37000",
    "sg:province":"Centre",
    "wof:name":"C.r.i.t. Int\u00e9rim S.a.",
    "wof:placetype":"venue"
},
  "geometry": {"coordinates":[0.684769,47.392567],"type":"Point"}
}