{
  "type": "Feature",
  "properties": {
    "addr:full":"Bellevue De Glane 87200 St Junien Limousin 87200",
    "addr:postcode":"87200;87200",
    "addr:street":"De Glane",
    "iso:country":"FR",
    "sg:address":"Bellevue De Glane 87200 St Junien",
    "sg:classifiers":[
        {
            "category":"Professional",
            "subcategory":"Business Services",
            "type":"Services"
        }
    ],
    "sg:phone":"+33 5 55 02 21 61",
    "sg:postcode":"87200",
    "sg:province":"Limousin",
    "sg:tags":[
        "training",
        "advice"
    ],
    "wof:name":"Lycee Polyvalent Paul Eluard",
    "wof:placetype":"venue"
},
  "geometry": {"coordinates":[0.89171,45.895157],"type":"Point"}
}