{
  "type": "Feature",
  "properties": {
    "iso:country":"FR",
    "sg:address":"Rte de Remiremont - Moulin",
    "sg:city":"Saint Nabord",
    "sg:orig_category":"Unclassifiable Establishments",
    "sg:phone":"+33 3 29 62 52 72",
    "sg:postcode":"88200",
    "sg:province":"Lorraine",
    "wof:name":"Gr\u00e9goire Papeteries S.a.",
    "wof:placetype":"venue"
},
  "geometry": {"coordinates":[6.5814,48.049309],"type":"Point"}
}