{
  "type": "Feature",
  "properties": {
    "addr:full":"25-31 boulevard des Bouvets 92000 Nanterre Ile de France 92000",
    "addr:housenumber":"25-31",
    "addr:postcode":"92000;92000",
    "addr:street":"Boulevard Des Bouvets",
    "iso:country":"FR",
    "sg:address":"25-31 boulevard des Bouvets 92000 Nanterre",
    "sg:classifiers":[
        {
            "category":"Wholesale",
            "subcategory":"Electrical",
            "type":"Manufacturing & Wholesale Goods"
        }
    ],
    "sg:phone":"+33 1 55 68 55 68",
    "sg:postcode":"92000",
    "sg:province":"Ile de France",
    "sg:tags":[
        "component"
    ],
    "wof:name":"Mitsubishi Electric Telecom Europe Sa",
    "wof:placetype":"venue"
},
  "geometry": {"coordinates":[2.224657,48.896767],"type":"Point"}
}