{
  "type": "Feature",
  "properties": {
    "iso:country":"FR",
    "sg:address":"Zone Industrielle Ruitz",
    "sg:city":"Meuret 62620 Barlin",
    "sg:classifiers":[
        {
            "category":"Autos & Motor Vehicles",
            "subcategory":"Fuel & Gas Station",
            "type":"Retail Goods"
        }
    ],
    "sg:phone":"+33 3 21 01 76 50",
    "sg:postcode":"62620",
    "sg:province":"Nord Pas-de-Calais",
    "sg:tags":[
        "pump",
        "high-pressure"
    ],
    "wof:name":"Sacavi S.a.",
    "wof:placetype":"venue"
},
  "geometry": {"coordinates":[2.616605,50.456985],"type":"Point"}
}