{
  "type": "Feature",
  "properties": {
    "iso:country":"FR",
    "sg:address":"4 Rue Cl\u00e9mence 13006 Marseille",
    "sg:classifiers":[
        {
            "category":"Manufacturing",
            "subcategory":"Jewelry",
            "type":"Manufacturing & Wholesale Goods"
        }
    ],
    "sg:phone":"+33 4 91 37 50 49",
    "sg:province":"Poitou-Charentes",
    "sg:tags":[
        "product",
        "miscellaneous",
        "jewellery"
    ],
    "wof:name":"Sas Gas Bijoux",
    "wof:placetype":"venue"
},
  "geometry": {"coordinates":[5.38324,43.290806],"type":"Point"}
}