{
  "type": "Feature",
  "properties": {
    "addr:full":"1, Rue Jacquard, 25000 Besan\u00e7on Franche Comt\u00e9",
    "addr:housenumber":"1",
    "addr:postcode":"25000",
    "addr:street":"Rue Jacquard;Franche Comte\u0301",
    "iso:country":"FR",
    "sg:address":"1, Rue Jacquard, 25000 Besan\u00e7on",
    "sg:orig_category":"Unclassifiable Establishments",
    "sg:phone":"+33 3 81 85 01 05",
    "sg:province":"Franche Comt\u00e9",
    "wof:name":"F.m.i. S.a.r.l. - Forma Mousse Industrie",
    "wof:placetype":"venue"
},
  "geometry": {"coordinates":[5.993907,47.2384],"type":"Point"}
}