{
  "type": "Feature",
  "properties": {
    "addr:full":"Rte de Beaucaire Rodilhan Languedoc-Roussillon 30230",
    "addr:postcode":"30230",
    "addr:street":"Rte De Beaucaire",
    "iso:country":"FR",
    "sg:address":"Rte de Beaucaire",
    "sg:city":"Rodilhan",
    "sg:orig_category":"Unclassifiable Establishments",
    "sg:phone":"+33 4 66 02 13 13",
    "sg:postcode":"30230",
    "sg:province":"Languedoc-Roussillon",
    "wof:name":"Legouez",
    "wof:placetype":"venue"
},
  "geometry": {"coordinates":[4.429795,43.832783],"type":"Point"}
}