{
  "type": "Feature",
  "properties": {
    "addr:full":"2, Rue de la Ville Neuve, 75002 Paris Ile de France",
    "addr:housenumber":"2",
    "addr:postcode":"75002",
    "addr:street":"Rue De La Ville Neuve",
    "iso:country":"FR",
    "sg:address":"2, Rue de la Ville Neuve, 75002 Paris",
    "sg:orig_category":"Unclassifiable Establishments",
    "sg:phone":"+33 1 42 33 58 76",
    "sg:province":"Ile de France",
    "wof:name":"Alexandre Textiles S.a.r.l.",
    "wof:placetype":"venue"
},
  "geometry": {"coordinates":[2.348691,48.86935],"type":"Point"}
}