{
  "type": "Feature",
  "properties": {
    "iso:country":"FR",
    "sg:address":"Rue de la Cerisaie",
    "sg:city":"Saint Gr\u00e9goire",
    "sg:orig_category":"Unclassifiable Establishments",
    "sg:phone":"+33 2 99 84 21 21",
    "sg:postcode":"35760",
    "sg:province":"Bretagne",
    "wof:name":"Chapin Mat\u00e9riel S.a.",
    "wof:placetype":"venue"
},
  "geometry": {"coordinates":[-1.690023,48.138409],"type":"Point"}
}