{
  "type": "Feature",
  "properties": {
    "iso:country":"FR",
    "sg:address":"7 Rue Gare 88160 Le Thillot",
    "sg:classifiers":[
        {
            "category":"Manufacturing",
            "subcategory":"Metals",
            "type":"Manufacturing & Wholesale Goods"
        }
    ],
    "sg:phone":"+33 3 29 23 80 80",
    "sg:postcode":"88160",
    "sg:province":"Lorraine",
    "sg:tags":[
        "-",
        "machine",
        "equipment",
        "engineering",
        "machinery",
        "mechanical"
    ],
    "wof:name":"Epac Le Thillot Sa",
    "wof:placetype":"venue"
},
  "geometry": {"coordinates":[6.7656,47.878075],"type":"Point"}
}