{
  "type": "Feature",
  "properties": {
    "addr:full":"ZAC d'Ennery - Enceinte Garolor Ennery Lorraine 57365",
    "addr:postcode":"57365",
    "addr:street":"Zac D'Ennery Enceinte Garolor",
    "iso:country":"FR",
    "sg:address":"ZAC d'Ennery - Enceinte Garolor",
    "sg:city":"Ennery",
    "sg:orig_category":"Unclassifiable Establishments",
    "sg:phone":"+33 3 87 73 77 66",
    "sg:postcode":"57365",
    "sg:province":"Lorraine",
    "wof:name":"N.t.s. Transports Internationaux S.a.",
    "wof:placetype":"venue"
},
  "geometry": {"coordinates":[6.21459,49.231377],"type":"Point"}
}