{
  "type": "Feature",
  "properties": {
    "addr:full":"9, Rue Marcel Sembat, 21000 Dijon Dijon Bourgogne 21000",
    "addr:housenumber":"9",
    "addr:postcode":"21000;21000",
    "addr:street":"Rue Marcel Sembat",
    "iso:country":"FR",
    "sg:address":"9, Rue Marcel Sembat, 21000 Dijon",
    "sg:city":"Dijon",
    "sg:orig_category":"Unclassifiable Establishments",
    "sg:phone":"+33 3 80 52 56 59",
    "sg:postcode":"21000",
    "sg:province":"Bourgogne",
    "wof:name":"Guillerme Stores S.a.r.l.",
    "wof:placetype":"venue"
},
  "geometry": {"coordinates":[5.022893,47.299698],"type":"Point"}
}