{
  "type": "Feature",
  "properties": {
    "iso:country":"FR",
    "sg:address":"28, Rue Vignon, 75009 Paris",
    "sg:orig_category":"Non-Classified Establishments",
    "sg:phone":"+33 1 49 24 08 10",
    "sg:province":"Ile de France",
    "wof:name":"Intersoft S.a.",
    "wof:placetype":"venue"
},
  "geometry": {"coordinates":[2.326609,48.871944],"type":"Point"}
}