{
  "type": "Feature",
  "properties": {
    "addr:full":"Saint Eloi 16150 Exideuil Poitou-Charentes",
    "addr:postcode":"16150",
    "addr:street":"Saint Eloi",
    "iso:country":"FR",
    "sg:address":"Saint Eloi 16150 Exideuil",
    "sg:orig_category":"Unclassifiable Establishments",
    "sg:phone":"+33 5 45 89 01 49",
    "sg:province":"Poitou-Charentes",
    "wof:name":"Soci\u00e9t\u00e9 Des Carri\u00e8res D'exideuil Saint Eloi S.a.s.",
    "wof:placetype":"venue"
},
  "geometry": {"coordinates":[0.68447,45.872093],"type":"Point"}
}