{
  "type": "Feature",
  "properties": {
    "addr:full":"25 rue Dagorno 75012 Paris Ile de France",
    "addr:housenumber":"25",
    "addr:postcode":"75012",
    "addr:street":"Rue Dagorno",
    "iso:country":"FR",
    "sg:address":"25 rue Dagorno 75012 Paris",
    "sg:classifiers":[
        {
            "category":"Professional",
            "type":"Services"
        }
    ],
    "sg:phone":"+33 1 44 67 67 67",
    "sg:province":"Ile de France",
    "sg:tags":[
        "transport"
    ],
    "wof:name":"Les Nouveaux Coursier S.a.r.l.",
    "wof:placetype":"venue"
},
  "geometry": {"coordinates":[2.400526,48.842644],"type":"Point"}
}