{
  "type": "Feature",
  "properties": {
    "iso:country":"FR",
    "sg:address":"27, Rue du Portail Louis, 49400 Saumur",
    "sg:orig_category":"Unclassifiable Establishments",
    "sg:phone":"+33 2 41 51 10 76",
    "sg:province":"Pays de Loire",
    "wof:name":"La Nouvelle R\u00e9publique Du Centre Ouest",
    "wof:placetype":"venue"
},
  "geometry": {"coordinates":[-0.078584,47.258614],"type":"Point"}
}