{
  "type": "Feature",
  "properties": {
    "addr:full":"6 bis, Rue de Laferri\u00e8re, 75009 Paris Ile de France",
    "addr:housenumber":"6 bis",
    "addr:postcode":"75009",
    "addr:street":"Rue De Laferrie\u0300Re",
    "iso:country":"FR",
    "sg:address":"6 bis, Rue de Laferri\u00e8re, 75009 Paris",
    "sg:orig_category":"Unclassifiable Establishments",
    "sg:phone":"+33 1 44 53 36 80",
    "sg:province":"Ile de France",
    "wof:name":"T\u00e9lergo S.a.",
    "wof:placetype":"venue"
},
  "geometry": {"coordinates":[2.338456,48.878258],"type":"Point"}
}