{
  "type": "Feature",
  "properties": {
    "addr:full":"91953 Les Ulis C\u00e9dex^^19, Av. de Norv\u00e8ge - ZAC Courtaboeuf 1, 91940 Les Ulis Ile de France",
    "addr:housenumber":"91953;1",
    "addr:postcode":"91940",
    "addr:street":"Av. De Norve\u0300Ge Zac Courtaboeuf",
    "iso:country":"FR",
    "sg:address":"91953 Les Ulis C\u00e9dex^^19, Av. de Norv\u00e8ge - ZAC Courtaboeuf 1, 91940 Les Ulis",
    "sg:orig_category":"Non-Classified Establishments",
    "sg:phone":"+33 1 60 92 39 00",
    "sg:province":"Ile de France",
    "wof:name":"Osir\u00e9s S.a.",
    "wof:placetype":"venue"
},
  "geometry": {"coordinates":[2.169475,48.68161],"type":"Point"}
}