{
  "type": "Feature",
  "properties": {
    "addr:full":"28 Rue Du 22 Novembre 67440 Marmoutier Marmoutier Alsace 67440",
    "addr:housenumber":"28",
    "addr:postcode":"67440;67440",
    "addr:street":"Rue Du 22 Novembre",
    "iso:country":"FR",
    "sg:address":"28 Rue Du 22 Novembre 67440 Marmoutier",
    "sg:city":"Marmoutier",
    "sg:classifiers":[
        {
            "category":"Shopping",
            "subcategory":"Clothing, Apparel, & Fashions",
            "type":"Retail Goods"
        }
    ],
    "sg:phone":"+33 3 88 71 48 00",
    "sg:postcode":"67440",
    "sg:province":"Alsace",
    "sg:tags":[
        "textile",
        "clothing",
        "clothes"
    ],
    "wof:name":"Societe Nouvelle Tricotage Marmotier",
    "wof:placetype":"venue"
},
  "geometry": {"coordinates":[7.380765,48.690956],"type":"Point"}
}