{
  "type": "Feature",
  "properties": {
    "iso:country":"FR",
    "sg:address":"10 Voie Des Pr\u00e9aux 89310 Nitry",
    "sg:city":"Nitry",
    "sg:classifiers":[
        {
            "category":"Manufacturing",
            "subcategory":"Printing",
            "type":"Manufacturing & Wholesale Goods"
        }
    ],
    "sg:phone":"+33 3 86 34 91 61",
    "sg:postcode":"89310",
    "sg:province":"Bourgogne",
    "sg:tags":[
        "publishing"
    ],
    "wof:name":"Filigrane Imprimerie Sarl",
    "wof:placetype":"venue"
},
  "geometry": {"coordinates":[3.996665,47.692291],"type":"Point"}
}