{
  "type": "Feature",
  "properties": {
    "addr:full":"19 Rue Meslay 75003 Paris Ile de France 75003",
    "addr:housenumber":"19",
    "addr:postcode":"75003;75003",
    "addr:street":"Rue Meslay",
    "iso:country":"FR",
    "sg:address":"19 Rue Meslay 75003 Paris",
    "sg:classifiers":[
        {
            "category":"Shopping",
            "subcategory":"Luggage & Leather Goods",
            "type":"Retail Goods"
        }
    ],
    "sg:phone":"+33 1 48 87 43 27",
    "sg:postcode":"75003",
    "sg:province":"Ile de France",
    "sg:tags":[
        "shoe"
    ],
    "wof:name":"Menport Sarl",
    "wof:placetype":"venue"
},
  "geometry": {"coordinates":[2.360895,48.867443],"type":"Point"}
}