{
  "type": "Feature",
  "properties": {
    "iso:country":"FR",
    "sg:address":"36 rue du Louvre; Paris; 75001",
    "sg:classifiers":[
        {
            "category":"Banks & Credit Unions",
            "subcategory":"Bank",
            "type":"Services"
        }
    ],
    "sg:phone":"+33 1 42 36 43 83",
    "sg:postcode":"75001",
    "sg:province":"Ile de France",
    "wof:name":"Caja De Madrid",
    "wof:placetype":"venue"
},
  "geometry": {"coordinates":[2.341632,48.862068],"type":"Point"}
}