{
  "type": "Feature",
  "properties": {
    "iso:country":"FR",
    "sg:address":"58",
    "sg:city":"Gustave Roch 44200 Nantes",
    "sg:classifiers":[
        {
            "category":"Farming",
            "subcategory":"Farm",
            "type":"Manufacturing & Wholesale Goods"
        }
    ],
    "sg:phone":"+33 2 40 47 75 69",
    "sg:postcode":"44200",
    "sg:province":"Pays de Loire",
    "sg:tags":[
        "horticulture",
        "agriculture",
        "livestock"
    ],
    "wof:name":"Rossiflor",
    "wof:placetype":"venue"
},
  "geometry": {"coordinates":[-1.555667,47.200958],"type":"Point"}
}