{
  "type": "Feature",
  "properties": {
    "addr:full":"8 bis, Rue du pr\u00e9sident Kennedy - ZI du Ch\u00eane Sorcier, 78340 Les Clayes sous Bois Ile de France",
    "addr:housenumber":"8 bis",
    "addr:postcode":"78340",
    "addr:street":"Rue Du Pre\u0301Sident Kennedy Zi Du Che\u0302Ne Sorcier",
    "iso:country":"FR",
    "sg:address":"8 bis, Rue du pr\u00e9sident Kennedy - ZI du Ch\u00eane Sorcier, 78340 Les Clayes sous Bois",
    "sg:orig_category":"Unclassifiable Establishments",
    "sg:phone":"+33 1 30 79 16 61",
    "sg:province":"Ile de France",
    "wof:name":"Soneo S.a. - Soci\u00e9t\u00e9 Nouvelle D'etudes D'outillages",
    "wof:placetype":"venue"
},
  "geometry": {"coordinates":[1.986455,48.822639],"type":"Point"}
}