{
  "type": "Feature",
  "properties": {
    "addr:full":"Av Jacques Preiss 68340 Riquewihr Riquewihr Alsace 68340",
    "addr:postcode":"68340;68340",
    "addr:street":"Av Jacques Preiss",
    "iso:country":"FR",
    "sg:address":"Av Jacques Preiss 68340 Riquewihr",
    "sg:city":"Riquewihr",
    "sg:classifiers":[
        {
            "category":"Food Court",
            "type":"Food & Drink"
        }
    ],
    "sg:phone":"+33 3 89 47 91 21",
    "sg:postcode":"68340",
    "sg:province":"Alsace",
    "sg:tags":[
        "product",
        "related"
    ],
    "wof:name":"Preiss Ernest Sarl",
    "wof:placetype":"venue"
},
  "geometry": {"coordinates":[7.302625,48.16605],"type":"Point"}
}