{
  "type": "Feature",
  "properties": {
    "addr:full":"34 R Th\u00e9odule Gu\u00e9rin 76390 Vieux Rouen Sur Bresle Haute Normandie 76390",
    "addr:housenumber":"34",
    "addr:postcode":"76390;76390",
    "addr:street":"R The\u0301Odule Gue\u0301Rin;Rouen;Haute Normandie",
    "iso:country":"FR",
    "sg:address":"34 R Th\u00e9odule Gu\u00e9rin 76390 Vieux Rouen Sur Bresle",
    "sg:classifiers":[
        {
            "category":"Manufacturing",
            "subcategory":"Glass & Minerals",
            "type":"Manufacturing & Wholesale Goods"
        }
    ],
    "sg:phone":"+33 2 35 93 45 02",
    "sg:postcode":"76390",
    "sg:province":"Haute Normandie",
    "sg:tags":[
        "building",
        "material"
    ],
    "wof:name":"Verreries Bross Sas",
    "wof:placetype":"venue"
},
  "geometry": {"coordinates":[1.71925,49.83466],"type":"Point"}
}