{
  "type": "Feature",
  "properties": {
    "iso:country":"FR",
    "sg:address":"10 rue Aristide Briand; Belfort; 90006",
    "sg:city":"Belfort",
    "sg:classifiers":[
        {
            "category":"Banks & Credit Unions",
            "subcategory":"Bank",
            "type":"Services"
        }
    ],
    "sg:phone":"+33 3 84 57 54 00",
    "sg:postcode":"90000",
    "sg:province":"Franche Comt\u00e9",
    "wof:name":"Banque De France",
    "wof:placetype":"venue"
},
  "geometry": {"coordinates":[6.855784,47.632893],"type":"Point"}
}