{
  "type": "Feature",
  "properties": {
    "addr:full":"133 Rue Bataille 69008 Lyon Rhone-Alpes 69008",
    "addr:housenumber":"133",
    "addr:postcode":"69008;69008",
    "addr:street":"Rue Bataille",
    "iso:country":"FR",
    "sg:address":"133 Rue Bataille 69008 Lyon",
    "sg:classifiers":[
        {
            "category":"Manufacturing",
            "subcategory":"Paper Products",
            "type":"Manufacturing & Wholesale Goods"
        }
    ],
    "sg:phone":"+33 4 72 78 59 60",
    "sg:postcode":"69008",
    "sg:province":"Rhone-Alpes",
    "sg:tags":[
        "finished",
        "cardboard",
        "-"
    ],
    "wof:name":"Papeteries Navarre",
    "wof:placetype":"venue"
},
  "geometry": {"coordinates":[4.872945,45.735241],"type":"Point"}
}