{
  "type": "Feature",
  "properties": {
    "iso:country":"FR",
    "sg:address":"Lieu-dit La Briquetterie 08220 Vaux l\u00e8s Rubigny",
    "sg:city":"Banogne-Recouvrance",
    "sg:orig_category":"Unclassifiable Establishments",
    "sg:phone":"+33 3 24 59 28 56",
    "sg:postcode":"08220",
    "sg:province":"Champagne",
    "wof:name":"Cynophile Ardennaise De S\u00e9curit\u00e9 S.a.r.l.",
    "wof:placetype":"venue"
},
  "geometry": {"coordinates":[4.183487,49.698441],"type":"Point"}
}