{
  "type": "Feature",
  "properties": {
    "addr:full":"Za De La Kruysstraete 59470 Wormhout Nord Pas-de-Calais 59470",
    "addr:postcode":"59470;59470",
    "addr:street":"Za De La Kruysstraete",
    "iso:country":"FR",
    "sg:address":"Za De La Kruysstraete 59470 Wormhout",
    "sg:classifiers":[
        {
            "category":"Manufacturing",
            "subcategory":"Metals",
            "type":"Manufacturing & Wholesale Goods"
        }
    ],
    "sg:phone":"+33 3 28 62 80 07",
    "sg:postcode":"59470",
    "sg:province":"Nord Pas-de-Calais",
    "sg:tags":[
        "-",
        "machine",
        "equipment",
        "engineering",
        "machinery",
        "mechanical"
    ],
    "wof:name":"Haco Sa",
    "wof:placetype":"venue"
},
  "geometry": {"coordinates":[2.468422,50.882675],"type":"Point"}
}