{
  "type": "Feature",
  "properties": {
    "addr:full":"B.P. 14 Fresnoy le Grand^^Vall\u00e9e d'Epinois 02230 Fresnoy le Grand Picardie 02230",
    "addr:postcode":"02230;02230",
    "addr:street":"B.P. 14 Fresnoy Le;D'Epinois;Picardie",
    "iso:country":"FR",
    "sg:address":"B.P. 14",
    "sg:city":"Fresnoy le Grand^^Vall\u00e9e d'Epinois 02230 Fresnoy le Grand",
    "sg:orig_category":"Non-Classified Establishments",
    "sg:phone":"+33 3 23 09 36 00",
    "sg:postcode":"02230",
    "sg:province":"Picardie",
    "wof:name":"Tubeurop France",
    "wof:placetype":"venue"
},
  "geometry": {"coordinates":[3.41728,49.955551],"type":"Point"}
}