{
  "type": "Feature",
  "properties": {
    "addr:full":"2, Rue des Entrepreneurs - ZI des Amandiers, 78420 Carri\u00e8res sur Seine Ile de France",
    "addr:housenumber":"2",
    "addr:postcode":"78420",
    "addr:street":"Rue Des Entrepreneurs Zi Des Amandiers",
    "iso:country":"FR",
    "sg:address":"2, Rue des Entrepreneurs - ZI des Amandiers, 78420 Carri\u00e8res sur Seine",
    "sg:orig_category":"Unclassifiable Establishments",
    "sg:phone":"+33 1 39 14 03 00",
    "sg:province":"Ile de France",
    "wof:name":"Initial B.t.b. S.a.",
    "wof:placetype":"venue"
},
  "geometry": {"coordinates":[2.174915,48.90715],"type":"Point"}
}