{
  "type": "Feature",
  "properties": {
    "addr:full":"Av. de l'Europe Montauban Midi Pyr\u00e9n\u00e9es 82000",
    "addr:postcode":"82000",
    "addr:street":"Av. De L'Europe",
    "iso:country":"FR",
    "sg:address":"Av. de l'Europe",
    "sg:city":"Montauban",
    "sg:orig_category":"Unclassifiable Establishments",
    "sg:phone":"+33 5 63 23 27 00",
    "sg:postcode":"82000",
    "sg:province":"Midi Pyr\u00e9n\u00e9es",
    "wof:name":"G.m.t. S.a. - G\u00e9n\u00e9rale De Montage Et Tuyauterie",
    "wof:placetype":"venue"
},
  "geometry": {"coordinates":[1.334655,43.996849],"type":"Point"}
}