{
  "type": "Feature",
  "properties": {
    "addr:full":"22 Voie Notre Dame De Lorette 62000 Arras Nord Pas-de-Calais 62000",
    "addr:housenumber":"22",
    "addr:postcode":"62000;62000",
    "addr:street":"Voie Notre Dame De Lorette",
    "iso:country":"FR",
    "sg:address":"22 Voie Notre Dame De Lorette 62000 Arras",
    "sg:classifiers":[
        {
            "category":"Wholesale",
            "subcategory":"Medical Equipment & Supplies",
            "type":"Manufacturing & Wholesale Goods"
        }
    ],
    "sg:phone":"+33 3 21 71 17 51",
    "sg:postcode":"62000",
    "sg:province":"Nord Pas-de-Calais",
    "sg:tags":[
        "instrument",
        "health",
        "-",
        "precision"
    ],
    "wof:name":"Societe Nouvelle Des Anciens Etablissements Bayart",
    "wof:placetype":"venue"
},
  "geometry": {"coordinates":[2.768784,50.298004],"type":"Point"}
}