{
  "type": "Feature",
  "properties": {
    "addr:full":"15, Rue du Mar\u00e9chal Foch, 33460 Margaux Margaux Aquitaine 33460",
    "addr:housenumber":"15",
    "addr:postcode":"33460;33460",
    "addr:street":"Rue Du Mare\u0301Chal Foch",
    "iso:country":"FR",
    "sg:address":"15, Rue du Mar\u00e9chal Foch, 33460 Margaux",
    "sg:city":"Margaux",
    "sg:orig_category":"Unclassifiable Establishments",
    "sg:phone":"+33 5 57 88 30 64",
    "sg:postcode":"33460",
    "sg:province":"Aquitaine",
    "wof:name":"Bergey Robert S.a.",
    "wof:placetype":"venue"
},
  "geometry": {"coordinates":[-0.683679,45.035702],"type":"Point"}
}