{
  "type": "Feature",
  "properties": {
    "iso:country":"FR",
    "sg:address":"18, Rue Boudeville - ZI de Thibaud, 31100 Toulouse",
    "sg:orig_category":"Unclassifiable Establishments",
    "sg:phone":"+33 5 61 41 61 08",
    "sg:province":"Midi Pyr\u00e9n\u00e9es",
    "wof:name":"Anitech S.a.r.l.",
    "wof:placetype":"venue"
},
  "geometry": {"coordinates":[1.39859,43.56786],"type":"Point"}
}