{
  "type": "Feature",
  "properties": {
    "addr:full":"B.P. 141, 53201 Az\u00e9 C\u00e9dex^^ZI de Bellitourne, 53200 Az\u00e9 Pays de Loire",
    "addr:housenumber":"b.p. 141",
    "addr:postcode":"53201;53200",
    "iso:country":"FR",
    "sg:address":"B.P. 141, 53201 Az\u00e9 C\u00e9dex^^ZI de Bellitourne, 53200 Az\u00e9",
    "sg:orig_category":"Non-Classified Establishments",
    "sg:phone":"+33 2 43 09 20 76",
    "sg:province":"Pays de Loire",
    "wof:name":"Maisonneuve S.a.",
    "wof:placetype":"venue"
},
  "geometry": {"coordinates":[-0.638464,47.749775],"type":"Point"}
}