{
  "type": "Feature",
  "properties": {
    "iso:country":"FR",
    "sg:address":"5, Rue Alain le Grand, 56230 Questembert",
    "sg:city":"Questembert",
    "sg:orig_category":"Unclassifiable Establishments",
    "sg:phone":"+33 2 97 26 11 43",
    "sg:postcode":"56230",
    "sg:province":"Bretagne",
    "wof:name":"Etablissements Grimaud S.a.",
    "wof:placetype":"venue"
},
  "geometry": {"coordinates":[-2.453871,47.660133],"type":"Point"}
}