{
  "type": "Feature",
  "properties": {
    "addr:full":"53 avenue Henri IV 64290 GAN Gan Aquitaine 64290",
    "addr:housenumber":"53",
    "addr:postcode":"64290;64290",
    "addr:street":"Avenue Henri Iv",
    "iso:country":"FR",
    "sg:address":"53 avenue Henri IV 64290 GAN",
    "sg:city":"Gan",
    "sg:classifiers":[
        {
            "category":"Wholesale",
            "subcategory":"Wine & Distilled Alcoholic Beverages",
            "type":"Manufacturing & Wholesale Goods"
        }
    ],
    "sg:phone":"+33 5 59 21 57 03",
    "sg:postcode":"64290",
    "sg:province":"Aquitaine",
    "sg:tags":[
        "french"
    ],
    "wof:name":"La Cave Des Producteurs De Juran\u00e7on Coop.",
    "wof:placetype":"venue"
},
  "geometry": {"coordinates":[-0.388796,43.233051],"type":"Point"}
}