{
  "type": "Feature",
  "properties": {
    "addr:full":"Voie des Alli\u00e9s 14440 DOUVRES LA DELIVRANDE B\u00e9ny-sur-Mer Basse Normandie 14440",
    "addr:postcode":"14440;14440",
    "addr:street":"Voie Des Allie\u0301S",
    "iso:country":"FR",
    "sg:address":"Voie des Alli\u00e9s 14440 DOUVRES LA DELIVRANDE",
    "sg:city":"B\u00e9ny-sur-Mer",
    "sg:orig_category":"Temporary Doors",
    "sg:phone":"+33 2 31 36 31 36",
    "sg:postcode":"14440",
    "sg:province":"Basse Normandie",
    "wof:name":"Batimetal S.a.s.",
    "wof:placetype":"venue"
},
  "geometry": {"coordinates":[-0.381489,49.299236],"type":"Point"}
}