{
  "type": "Feature",
  "properties": {
    "addr:full":"B.P. 48, 63015 Clermont Ferrand C\u00e9dex^^10, Rue Louis Bl\u00e9riot, 63100 Clermont Ferrand Clermont-Ferrand Auvergne 63100",
    "addr:postcode":"63015;63100;63100",
    "addr:street":"B.P. 48;Rue Louis Ble\u0301Riot",
    "iso:country":"FR",
    "sg:address":"B.P. 48, 63015 Clermont Ferrand C\u00e9dex^^10, Rue Louis Bl\u00e9riot, 63100 Clermont Ferrand",
    "sg:city":"Clermont-Ferrand",
    "sg:orig_category":"Non-Classified Establishments",
    "sg:phone":"+33 4 73 99 99 99",
    "sg:postcode":"63100",
    "sg:province":"Auvergne",
    "wof:name":"Sansac S.a.",
    "wof:placetype":"venue"
},
  "geometry": {"coordinates":[2.09017,43.151814],"type":"Point"}
}