{
  "type": "Feature",
  "properties": {
    "iso:country":"FR",
    "sg:address":"5 Rue Georges Guynemer",
    "sg:city":"Des Rampes 22193 Pl\u00e9rin Cedex",
    "sg:classifiers":[
        {
            "category":"Shopping Center",
            "type":"Public Place"
        }
    ],
    "sg:phone":"+33 2 96 79 98 00",
    "sg:province":"Nord Pas-de-Calais",
    "sg:tags":[
        "product",
        "meat",
        "cooked",
        "frozen",
        "related",
        "food"
    ],
    "wof:name":"Sovigel",
    "wof:placetype":"venue"
},
  "geometry": {"coordinates":[-2.767949,48.534985],"type":"Point"}
}