{
  "type": "Feature",
  "properties": {
    "addr:full":"7, Rue de la Louvi\u00e8re - ZI, 25480 Pirey Franche Comt\u00e9",
    "addr:housenumber":"7",
    "addr:postcode":"25480",
    "addr:street":"Rue De La Louvie\u0300Re Zi;Franche Comte\u0301",
    "iso:country":"FR",
    "sg:address":"7, Rue de la Louvi\u00e8re - ZI, 25480 Pirey",
    "sg:orig_category":"Non-Classified Establishments",
    "sg:phone":"+33 3 81 88 03 58",
    "sg:province":"Franche Comt\u00e9",
    "wof:name":"M\u00e9ca-pr\u00e9cis S.a.r.l.",
    "wof:placetype":"venue"
},
  "geometry": {"coordinates":[5.982078,47.27187],"type":"Point"}
}