{
  "type": "Feature",
  "properties": {
    "addr:full":"B.P. 2, 59235 Bers\u00e9e C\u00e9dex^^2, Rue du Bourgeon, 59235 Bers\u00e9e Nord Pas-de-Calais",
    "addr:housenumber":"2",
    "addr:postcode":"59235;59235",
    "addr:street":"B.P.;Rue Du Bourgeon",
    "iso:country":"FR",
    "sg:address":"B.P. 2, 59235 Bers\u00e9e C\u00e9dex^^2, Rue du Bourgeon, 59235 Bers\u00e9e",
    "sg:orig_category":"Non-Classified Establishments",
    "sg:phone":"+33 3 20 59 22 11",
    "sg:province":"Nord Pas-de-Calais",
    "wof:name":"Soci\u00e9t\u00e9 Des Etablissements Victor Carbon S.a.r.l.",
    "wof:placetype":"venue"
},
  "geometry": {"coordinates":[3.141663,50.480789],"type":"Point"}
}