{
  "type": "Feature",
  "properties": {
    "iso:country":"FR",
    "sg:address":"Lieu-Dit Pari Gagne 71520 TRAMBLY",
    "sg:city":"Trambly",
    "sg:orig_category":"Slaughter-Houses, Abattoirs",
    "sg:phone":"+33 3 85 50 43 65",
    "sg:postcode":"71520",
    "sg:province":"Bourgogne",
    "wof:name":"Palmi D Or Bourgogne Sa",
    "wof:placetype":"venue"
},
  "geometry": {"coordinates":[4.553766,46.329082],"type":"Point"}
}