{
  "type": "Feature",
  "properties": {
    "iso:country":"FR",
    "sg:address":"4 Av De L'Europe 30200 Bagnols-Sur-C\u00e8ze",
    "sg:classifiers":[
        {
            "category":"Utilities",
            "subcategory":"Telephone",
            "type":"Services"
        }
    ],
    "sg:phone":"+33 4 66 89 46 45",
    "sg:province":"Languedoc-Roussillon",
    "sg:tags":[
        "telecommunication"
    ],
    "wof:name":"Image 3007 Sarl",
    "wof:placetype":"venue"
},
  "geometry": {"coordinates":[4.619086,44.167324],"type":"Point"}
}