{
  "type": "Feature",
  "properties": {
    "addr:full":"20 Rue Leon Blum 26000 Valence Rhone-Alpes 26000",
    "addr:housenumber":"20",
    "addr:postcode":"26000;26000",
    "addr:street":"Rue Leon Blum",
    "iso:country":"FR",
    "sg:address":"20 Rue Leon Blum 26000 Valence",
    "sg:classifiers":[
        {
            "category":"Health Services",
            "subcategory":"Medical Lab",
            "type":"Services"
        }
    ],
    "sg:phone":"+33 4 75 41 91 91",
    "sg:postcode":"26000",
    "sg:province":"Rhone-Alpes",
    "sg:tags":[
        "chemical",
        "pharmaceutical",
        "pharmacy"
    ],
    "wof:name":"Latoxan Laboratoire Des Toxines Animales Et Animaux Venimeux",
    "wof:placetype":"venue"
},
  "geometry": {"coordinates":[4.88337,44.91354],"type":"Point"}
}