{
  "type": "Feature",
  "properties": {
    "addr:full":"B.P. 195, 70004 Quincey^^Rte de Villersexel, 70000 Quincey Franche Comt\u00e9",
    "addr:housenumber":"b.p. 195",
    "addr:postcode":"70004;70000",
    "addr:street":"Franche Comte\u0301",
    "iso:country":"FR",
    "sg:address":"B.P. 195, 70004 Quincey^^Rte de Villersexel, 70000 Quincey",
    "sg:orig_category":"Non-Classified Establishments",
    "sg:phone":"+33 3 84 75 64 44",
    "sg:province":"Franche Comt\u00e9",
    "wof:name":"Lamboley Garage S.a.",
    "wof:placetype":"venue"
},
  "geometry": {"coordinates":[6.034054,47.524078],"type":"Point"}
}