{
  "type": "Feature",
  "properties": {
    "addr:full":"9 avenue de l'Entreprise 12000 Rodez Midi Pyr\u00e9n\u00e9es",
    "addr:housenumber":"9",
    "addr:postcode":"12000",
    "addr:street":"Avenue De L'Entreprise",
    "iso:country":"FR",
    "sg:address":"9 avenue de l'Entreprise 12000 Rodez",
    "sg:classifiers":[
        {
            "category":"Community Center",
            "subcategory":"Ethnic",
            "type":"Public Place"
        }
    ],
    "sg:phone":"+33 5 65 67 20 17",
    "sg:province":"Midi Pyr\u00e9n\u00e9es",
    "sg:tags":[
        "postcard",
        "picture",
        "landscapes",
        "interest"
    ],
    "wof:name":"Editions Subervie S.a.",
    "wof:placetype":"venue"
},
  "geometry": {"coordinates":[2.569609,44.361977],"type":"Point"}
}