{
  "type": "Feature",
  "properties": {
    "iso:country":"FR",
    "sg:address":"84, Cours de Verdun, 33000 Bordeaux",
    "sg:city":"Bordeaux",
    "sg:orig_category":"Non-Classified Establishments",
    "sg:phone":"+33 5 56 52 62 62",
    "sg:postcode":"33000",
    "sg:province":"Aquitaine",
    "wof:name":"Brain Search Consultants S.a.r.l.",
    "wof:placetype":"venue"
},
  "geometry": {"coordinates":[-0.574406,44.850414],"type":"Point"}
}