{
  "type": "Feature",
  "properties": {
    "addr:full":"Immeuble Platon Saint Aubin Ile de France 91190",
    "addr:postcode":"91190",
    "addr:street":"Saint",
    "iso:country":"FR",
    "sg:address":"Immeuble Platon",
    "sg:city":"Saint Aubin",
    "sg:orig_category":"Unclassifiable Establishments",
    "sg:phone":"+33 1 69 33 78 00",
    "sg:postcode":"91190",
    "sg:province":"Ile de France",
    "wof:name":"Aulafi S.a.",
    "wof:placetype":"venue"
},
  "geometry": {"coordinates":[2.140755,48.714863],"type":"Point"}
}