{
  "type": "Feature",
  "properties": {
    "addr:full":"Zi R Des Casernes 55400 Etain Lorraine 55400",
    "addr:postcode":"55400;55400",
    "addr:street":"R Des Casernes",
    "iso:country":"FR",
    "sg:address":"Zi R Des Casernes 55400 Etain",
    "sg:classifiers":[
        {
            "category":"Manufacturing",
            "subcategory":"Chemicals & Compounds",
            "type":"Manufacturing & Wholesale Goods"
        }
    ],
    "sg:phone":"+33 3 29 87 03 08",
    "sg:postcode":"55400",
    "sg:province":"Lorraine",
    "sg:tags":[
        "pharmaceutical",
        "chemistry",
        "-",
        "by-product"
    ],
    "wof:name":"Reichhold Chimie Sa",
    "wof:placetype":"venue"
},
  "geometry": {"coordinates":[5.634616,49.213356],"type":"Point"}
}