{
  "type": "Feature",
  "properties": {
    "addr:full":"21, Rue Alexis Lep\u00e8re, 93100 Montreuil Ile de France",
    "addr:housenumber":"21",
    "addr:postcode":"93100",
    "addr:street":"Rue Alexis Lepe\u0300Re",
    "iso:country":"FR",
    "sg:address":"21, Rue Alexis Lep\u00e8re, 93100 Montreuil",
    "sg:orig_category":"Unclassifiable Establishments",
    "sg:phone":"+33 1 42 87 43 39",
    "sg:province":"Ile de France",
    "wof:name":"S.f.m. Cochois S.a.r.l. - Soci\u00e9t\u00e9 Fran\u00e7aise De Marbrerie Cochois",
    "wof:placetype":"venue"
},
  "geometry": {"coordinates":[2.440429,48.864216],"type":"Point"}
}