{
  "type": "Feature",
  "properties": {
    "addr:full":"80 Rue Sedaine 75011 Paris Ile de France 75011",
    "addr:housenumber":"80",
    "addr:postcode":"75011;75011",
    "addr:street":"Rue Sedaine",
    "iso:country":"FR",
    "sg:address":"80 Rue Sedaine 75011 Paris",
    "sg:classifiers":[
        {
            "category":"Shopping",
            "subcategory":"Clothing, Apparel, & Fashions",
            "type":"Retail Goods"
        }
    ],
    "sg:phone":"+33 1 47 00 91 28",
    "sg:postcode":"75011",
    "sg:province":"Ile de France",
    "sg:tags":[
        "textile",
        "clothing",
        "clothes"
    ],
    "wof:name":"My Design Paris",
    "wof:placetype":"venue"
},
  "geometry": {"coordinates":[2.378465,48.858482],"type":"Point"}
}