{
  "type": "Feature",
  "properties": {
    "addr:full":"107, RN Napollon, 13400 Aubagne Languedoc-Roussillon",
    "addr:housenumber":"107",
    "addr:postcode":"13400",
    "addr:street":"Rn Napollon",
    "iso:country":"FR",
    "sg:address":"107, RN Napollon, 13400 Aubagne",
    "sg:orig_category":"Unclassifiable Establishments",
    "sg:phone":"+33 4 42 03 11 55",
    "sg:province":"Languedoc-Roussillon",
    "wof:name":"Levray Construction M\u00e9tallique Serrurerie S.a.r.l.",
    "wof:placetype":"venue"
},
  "geometry": {"coordinates":[5.5687,43.292141],"type":"Point"}
}