{
  "type": "Feature",
  "properties": {
    "addr:full":"6, Rue des Tilleuls - ZA Merantais, 78960 Voisins le Bretonneux Ile de France",
    "addr:housenumber":"6",
    "addr:postcode":"78960",
    "addr:street":"Rue Des Tilleuls Za Merantais",
    "iso:country":"FR",
    "sg:address":"6, Rue des Tilleuls - ZA Merantais, 78960 Voisins le Bretonneux",
    "sg:orig_category":"Non-Classified Establishments",
    "sg:phone":"+33 1 30 43 72 73",
    "sg:province":"Ile de France",
    "wof:name":"Parvalux S.a.",
    "wof:placetype":"venue"
},
  "geometry": {"coordinates":[2.051481,48.758369],"type":"Point"}
}