{
  "type": "Feature",
  "properties": {
    "addr:full":"B.P. 6, 94371 Sucy en Brie C\u00e9dex^^1, Av. Grande All\u00e9e - ZAC des Petits Carreaux, 94370 Sucy en Brie Ile de France",
    "addr:housenumber":"6",
    "addr:postcode":"94371;94370",
    "addr:street":"B.P.;Av. Grande Alle\u0301E Zac Des Petits Carreaux",
    "iso:country":"FR",
    "sg:address":"B.P. 6, 94371 Sucy en Brie C\u00e9dex^^1, Av. Grande All\u00e9e - ZAC des Petits Carreaux, 94370 Sucy en Brie",
    "sg:orig_category":"Non-Classified Establishments",
    "sg:phone":"+33 1 45 13 47 00",
    "sg:province":"Ile de France",
    "wof:name":"Hydrotechnic S.a.s.",
    "wof:placetype":"venue"
},
  "geometry": {"coordinates":[2.52074,48.771431],"type":"Point"}
}