{
  "type": "Feature",
  "properties": {
    "iso:country":"FR",
    "sg:address":"Valrose 20290 Borgo",
    "sg:orig_category":"Unclassifiable Establishments",
    "sg:phone":"+33 4 95 30 77 24",
    "sg:province":"Corse",
    "wof:name":"Sports Loisirs Corse S.a.r.l.",
    "wof:placetype":"venue"
},
  "geometry": {"coordinates":[9.42341,42.581169],"type":"Point"}
}