{
  "type": "Feature",
  "properties": {
    "iso:country":"FR",
    "sg:address":"147, Rue Rouet, 13008 Marseille",
    "sg:orig_category":"Unclassifiable Establishments",
    "sg:phone":"+33 4 91 79 12 19",
    "sg:province":"Provence-Alpes-C\u00f4te d'Azur",
    "wof:name":"S.m.a. S.a.r.l. - Soci\u00e9t\u00e9 Mat\u00e9riel Alimentaire",
    "wof:placetype":"venue"
},
  "geometry": {"coordinates":[5.39209,43.278915],"type":"Point"}
}