{
  "type": "Feature",
  "properties": {
    "addr:full":"4, Bd d'Alsace, 68128 Village Neuf Rosenau Alsace 68128",
    "addr:housenumber":"4",
    "addr:postcode":"68128;68128",
    "addr:street":"Bd D'Alsace;Village Neuf Rosenau",
    "iso:country":"FR",
    "sg:address":"4, Bd d'Alsace, 68128 Village Neuf",
    "sg:city":"Rosenau",
    "sg:orig_category":"Non-Classified Establishments",
    "sg:phone":"+33 3 89 70 35 00",
    "sg:postcode":"68128",
    "sg:province":"Alsace",
    "wof:name":"K.n.f. Neuberger S.a.",
    "wof:placetype":"venue"
},
  "geometry": {"coordinates":[7.57146,47.605289],"type":"Point"}
}