{
  "type": "Feature",
  "properties": {
    "addr:full":"10, Rue du Bois Chaland, 91090 Lisses Ile de France",
    "addr:housenumber":"10",
    "addr:postcode":"91090;ile",
    "addr:street":"Rue Du Bois Chaland",
    "iso:country":"FR",
    "sg:address":"10, Rue du Bois Chaland, 91090 Lisses",
    "sg:orig_category":"Unclassifiable Establishments",
    "sg:phone":"+33 1 60 86 26 41",
    "sg:province":"Ile de France",
    "wof:name":"C.e.e.r.i. S.a.r.l.",
    "wof:placetype":"venue"
},
  "geometry": {"coordinates":[2.431703,48.604774],"type":"Point"}
}