{
  "type": "Feature",
  "properties": {
    "addr:full":"Ch\u00e2teau Rieutort Roquelaure Midi Pyr\u00e9n\u00e9es 32810",
    "addr:postcode":"32810",
    "iso:country":"FR",
    "sg:address":"Ch\u00e2teau Rieutort",
    "sg:city":"Roquelaure",
    "sg:orig_category":"Unclassifiable Establishments",
    "sg:phone":"+33 5 62 65 58 45",
    "sg:postcode":"32810",
    "sg:province":"Midi Pyr\u00e9n\u00e9es",
    "wof:name":"C.g.p. - S.a. - Compagnie Produits De Cascogne",
    "wof:placetype":"venue"
},
  "geometry": {"coordinates":[0.678244,43.6591],"type":"Point"}
}