{
  "type": "Feature",
  "properties": {
    "addr:full":"14 Rue Jules Lequier 22190 Pl\u00e9rin Sur Mer Pl\u00e9rin Bretagne 22190",
    "addr:housenumber":"14",
    "addr:postcode":"22190;22190",
    "addr:street":"Rue Jules Lequier",
    "iso:country":"FR",
    "sg:address":"14 Rue Jules Lequier 22190 Pl\u00e9rin Sur Mer",
    "sg:city":"Pl\u00e9rin",
    "sg:classifiers":[
        {
            "category":"Professional",
            "subcategory":"Engineering",
            "type":"Services"
        }
    ],
    "sg:phone":"+33 2 96 74 54 90",
    "sg:postcode":"22190",
    "sg:province":"Bretagne",
    "sg:tags":[
        "machine",
        "-",
        "mechanical"
    ],
    "wof:name":"Ets Le Goff",
    "wof:placetype":"venue"
},
  "geometry": {"coordinates":[-2.746364,48.524429],"type":"Point"}
}