{
  "type": "Feature",
  "properties": {
    "addr:full":"La Ville Der 56460 Le Roc St Andre Chapelle-Caro Bretagne 56460",
    "addr:postcode":"56460;56460",
    "addr:street":"La;Le Roc St Andre Chapelle-Caro Bretagne",
    "iso:country":"FR",
    "sg:address":"La Ville Der 56460 Le Roc St Andre",
    "sg:city":"Chapelle-Caro",
    "sg:classifiers":[
        {
            "category":"Manufacturing",
            "subcategory":"Printing",
            "type":"Manufacturing & Wholesale Goods"
        }
    ],
    "sg:phone":"+33 2 97 74 88 34",
    "sg:postcode":"56460",
    "sg:province":"Bretagne",
    "sg:tags":[
        "publishing"
    ],
    "wof:name":"L'atelier Serigraphique",
    "wof:placetype":"venue"
},
  "geometry": {"coordinates":[-2.464283,47.868301],"type":"Point"}
}