{
  "type": "Feature",
  "properties": {
    "addr:full":"12, Bd Jules Ferry, 75011 Paris Ile de France",
    "addr:housenumber":"12",
    "addr:postcode":"75011",
    "addr:street":"Bd Jules Ferry",
    "iso:country":"FR",
    "sg:address":"12, Bd Jules Ferry, 75011 Paris",
    "sg:orig_category":"Unclassifiable Establishments",
    "sg:phone":"+33 1 40 21 80 72",
    "sg:province":"Ile de France",
    "wof:name":"Etablissement Guetta Richard",
    "wof:placetype":"venue"
},
  "geometry": {"coordinates":[2.368877,48.867451],"type":"Point"}
}