{
  "type": "Feature",
  "properties": {
    "iso:country":"FR",
    "sg:address":"60 rue du Ruisseau 38070 ST QUENTIN FALLAVIER",
    "sg:classifiers":[
        {
            "category":"Utilities",
            "subcategory":"Electric",
            "type":"Services"
        }
    ],
    "sg:phone":"+33 4 74 94 33 33",
    "sg:postcode":"38070",
    "sg:province":"Rhone-Alpes",
    "sg:tags":[
        "drive"
    ],
    "wof:name":"Acore Industrie S.a.",
    "wof:placetype":"venue"
},
  "geometry": {"coordinates":[5.099156,45.641872],"type":"Point"}
}