{
  "type": "Feature",
  "properties": {
    "addr:full":"B.P. 17, 10220 Piney^^Rte de G\u00e9raudot, 10220 Piney Champagne 10220",
    "addr:housenumber":"10220",
    "addr:postcode":"10220;10220",
    "addr:street":"B.P. 17;Piney Champagne",
    "iso:country":"FR",
    "sg:address":"B.P. 17, 10220 Piney^^Rte de G\u00e9raudot, 10220 Piney",
    "sg:orig_category":"Non-Classified Establishments",
    "sg:phone":"+33 3 25 46 30 09",
    "sg:postcode":"10220",
    "sg:province":"Champagne",
    "wof:name":"A.f.m.p. S.a.r.l.",
    "wof:placetype":"venue"
},
  "geometry": {"coordinates":[4.32583,48.363701],"type":"Point"}
}