{
  "type": "Feature",
  "properties": {
    "addr:full":"B.P. 26, 68220 H\u00e9singue^^7, Rue de Nancy, 68220 H\u00e9singue H\u00e9singue Alsace 68220",
    "addr:postcode":"68220;68220;68220",
    "addr:street":"B.P. 26;Rue De Nancy",
    "iso:country":"FR",
    "sg:address":"B.P. 26, 68220 H\u00e9singue^^7, Rue de Nancy, 68220 H\u00e9singue",
    "sg:city":"H\u00e9singue",
    "sg:orig_category":"Non-Classified Establishments",
    "sg:phone":"+33 3 89 70 95 55",
    "sg:postcode":"68220",
    "sg:province":"Alsace",
    "wof:name":"Euro Production S.a.",
    "wof:placetype":"venue"
},
  "geometry": {"coordinates":[7.52344,47.561153],"type":"Point"}
}