{
  "type": "Feature",
  "properties": {
    "addr:full":"Rue Victor Hugo Valence Midi Pyr\u00e9n\u00e9es 26000",
    "addr:postcode":"26000",
    "addr:street":"Rue Victor Hugo",
    "iso:country":"FR",
    "sg:address":"Rue Victor Hugo",
    "sg:city":"Valence",
    "sg:orig_category":"Non-Classified Establishments",
    "sg:phone":"+33 4 75 41 22 47",
    "sg:postcode":"26000",
    "sg:province":"Midi Pyr\u00e9n\u00e9es",
    "wof:name":"Les Vergers De Valence S.c.a.",
    "wof:placetype":"venue"
},
  "geometry": {"coordinates":[4.8913,44.930286],"type":"Point"}
}