{
  "type": "Feature",
  "properties": {
    "addr:full":"Rte de la Previ\u00e8re - ZA Pouanc\u00e9 Pays de Loire 49420",
    "addr:postcode":"49420",
    "addr:street":"Rte De La Previe\u0300Re Za Pouance\u0301 Pays",
    "iso:country":"FR",
    "sg:address":"Rte de la Previ\u00e8re - ZA",
    "sg:city":"Pouanc\u00e9",
    "sg:orig_category":"Non-Classified Establishments",
    "sg:phone":"+33 2 41 92 49 60",
    "sg:postcode":"49420",
    "sg:province":"Pays de Loire",
    "wof:name":"Poly - Trans S.a.r.l.",
    "wof:placetype":"venue"
},
  "geometry": {"coordinates":[-1.131229,47.681171],"type":"Point"}
}