{
  "type": "Feature",
  "properties": {
    "addr:full":"52, Rue Victor Lagrange, 69007 Lyon Rhone-Alpes 69007",
    "addr:housenumber":"52",
    "addr:postcode":"69007;69007",
    "addr:street":"Rue Victor Lagrange",
    "iso:country":"FR",
    "sg:address":"52, Rue Victor Lagrange, 69007 Lyon",
    "sg:orig_category":"Non-Classified Establishments",
    "sg:phone":"+33 4 78 58 68 77",
    "sg:postcode":"69007",
    "sg:province":"Rhone-Alpes",
    "wof:name":"Transfilm S.a.r.l.",
    "wof:placetype":"venue"
},
  "geometry": {"coordinates":[4.837458,45.743988],"type":"Point"}
}