{
  "type": "Feature",
  "properties": {
    "iso:country":"FR",
    "sg:address":"70 Rue De La Paix 10000 Troyes",
    "sg:classifiers":[
        {
            "category":"Shopping",
            "subcategory":"Computers & Home Electronics",
            "type":"Retail Goods"
        }
    ],
    "sg:phone":"+33 3 25 79 84 84",
    "sg:postcode":"10000",
    "sg:province":"Champagne",
    "sg:tags":[
        "household",
        "appliance",
        "telecommunication",
        "audio-visual"
    ],
    "wof:name":"Davis Acoustics Sa",
    "wof:placetype":"venue"
},
  "geometry": {"coordinates":[4.063284,48.308125],"type":"Point"}
}