{
  "type": "Feature",
  "properties": {
    "iso:country":"FR",
    "sg:address":"Z.I. de Pouldavid",
    "sg:city":"Douarnenez",
    "sg:orig_category":"Non-Classified Establishments",
    "sg:phone":"+33 2 98 92 47 10",
    "sg:postcode":"29100",
    "sg:province":"Bretagne",
    "wof:name":"Isobox Technologies S.a.",
    "wof:placetype":"venue"
},
  "geometry": {"coordinates":[-4.327149,48.043324],"type":"Point"}
}