{
  "type": "Feature",
  "properties": {
    "iso:country":"FR",
    "sg:address":"12, Rue des Cr\u00e9ssonni\u00e8res - ZI Nord, 95500 Gonesse",
    "sg:orig_category":"Non-Classified Establishments",
    "sg:phone":"+33 1 34 45 90 45",
    "sg:postcode":"95500",
    "sg:province":"Ile de France",
    "wof:name":"Art\u00e9on S.a.",
    "wof:placetype":"venue"
},
  "geometry": {"coordinates":[2.449633,48.986462],"type":"Point"}
}