{
  "type": "Feature",
  "properties": {
    "addr:full":"56 Rte De Pugny 73101 Aix Les Bains Cedex Nord Pas-de-Calais",
    "addr:housenumber":"56",
    "addr:postcode":"73101;les",
    "addr:street":"Rte De Pugny;Cedex;Pas-De-Calais",
    "iso:country":"FR",
    "sg:address":"56 Rte De Pugny 73101 Aix Les Bains Cedex",
    "sg:classifiers":[
        {
            "category":"Autos & Motor Vehicles",
            "subcategory":"Automobile Sales",
            "type":"Retail Goods"
        }
    ],
    "sg:phone":"+33 4 79 61 42 45",
    "sg:province":"Nord Pas-de-Calais",
    "sg:tags":[
        "equipment",
        "motor-cars",
        "transport"
    ],
    "wof:name":"Aixam Production Sa",
    "wof:placetype":"venue"
},
  "geometry": {"coordinates":[5.914763,45.68808],"type":"Point"}
}