{
  "type": "Feature",
  "properties": {
    "iso:country":"FR",
    "sg:address":"B.P. 90, 33083 Bordeaux C\u00e9dex^^Rue Yves Glotin, 33300 Bordeaux",
    "sg:city":"Bordeaux",
    "sg:orig_category":"Non-Classified Establishments",
    "sg:phone":"+33 5 57 19 11 11",
    "sg:postcode":"33300",
    "sg:province":"Aquitaine",
    "wof:name":"Decaup S.a.",
    "wof:placetype":"venue"
},
  "geometry": {"coordinates":[-0.56244,44.87672],"type":"Point"}
}