{
  "type": "Feature",
  "properties": {
    "iso:country":"FR",
    "sg:address":"B.P. 141, 78001 Versailles C\u00e9dex^^8, Impasse de Toulouse, 78000 Versailles",
    "sg:orig_category":"Non-Classified Establishments",
    "sg:phone":"+33 1 39 07 28 28",
    "sg:province":"Ile de France",
    "wof:name":"F.s.2.i. Logitram S.a. - France Solution Informatique International",
    "wof:placetype":"venue"
},
  "geometry": {"coordinates":[2.13112,48.801933],"type":"Point"}
}