{
  "type": "Feature",
  "properties": {
    "addr:full":"La Croix de la Barre 35130 Rann\u00e9e Rann\u00e9e Bretagne 35130",
    "addr:postcode":"35130;35130",
    "addr:street":"La Croix De La Barre;Ranne\u0301E",
    "iso:country":"FR",
    "sg:address":"La Croix de la Barre 35130 Rann\u00e9e",
    "sg:city":"Rann\u00e9e",
    "sg:orig_category":"Non-Classified Establishments",
    "sg:phone":"+33 2 99 96 23 79",
    "sg:postcode":"35130",
    "sg:province":"Bretagne",
    "wof:name":"Piquet S.a.r.l.",
    "wof:placetype":"venue"
},
  "geometry": {"coordinates":[-1.234569,47.931656],"type":"Point"}
}