{
  "type": "Feature",
  "properties": {
    "iso:country":"FR",
    "sg:address":"8 rue des Augustins 57000 Metz",
    "sg:classifiers":[
        {
            "category":"Manufacturing",
            "subcategory":"Jewelry",
            "type":"Manufacturing & Wholesale Goods"
        }
    ],
    "sg:phone":"+33 3 87 75 57 87",
    "sg:postcode":"57000",
    "sg:province":"Lorraine",
    "sg:tags":[
        "gemstone",
        "gold",
        "jewellery"
    ],
    "wof:name":"Fabior Sa",
    "wof:placetype":"venue"
},
  "geometry": {"coordinates":[6.178623,49.113216],"type":"Point"}
}