{
  "type": "Feature",
  "properties": {
    "addr:full":"Quai fonds de Veuze - ZI Chimours Saint Sorlin en Valloire Rhone-Alpes 26210",
    "addr:postcode":"26210",
    "addr:street":"Quai Fonds De Veuze Zi Chimours Saint",
    "iso:country":"FR",
    "sg:address":"Quai fonds de Veuze - ZI Chimours",
    "sg:city":"Saint Sorlin en Valloire",
    "sg:orig_category":"Non-Classified Establishments",
    "sg:phone":"+33 4 75 31 61 21",
    "sg:postcode":"26210",
    "sg:province":"Rhone-Alpes",
    "wof:name":"S.a.m.m. S.a.r.l. - Soci\u00e9t\u00e9 Assemblage Montage M\u00e9taux",
    "wof:placetype":"venue"
},
  "geometry": {"coordinates":[4.951355,45.288761],"type":"Point"}
}