{
  "type": "Feature",
  "properties": {
    "addr:full":"64 Rue Armand Dupont 28500 Vernouillet Vernouillet Centre 28500",
    "addr:housenumber":"64",
    "addr:postcode":"28500;28500",
    "addr:street":"Rue Armand Dupont;Vernouillet",
    "iso:country":"FR",
    "sg:address":"64 Rue Armand Dupont 28500 Vernouillet",
    "sg:city":"Vernouillet",
    "sg:classifiers":[
        {
            "category":"Wholesale",
            "subcategory":"Farm Supplies",
            "type":"Manufacturing & Wholesale Goods"
        }
    ],
    "sg:phone":"+33 2 37 46 15 36",
    "sg:postcode":"28500",
    "sg:province":"Centre",
    "sg:tags":[
        "-",
        "machine",
        "equipment",
        "engineering",
        "machinery",
        "mechanical",
        "agriculture"
    ],
    "wof:name":"L'hermite Ruelle Roland",
    "wof:placetype":"venue"
},
  "geometry": {"coordinates":[1.36526,48.718349],"type":"Point"}
}