{
  "type": "Feature",
  "properties": {
    "addr:full":"B.P. 4, 85640 Mouchamps C\u00e9dex^^Rte de Vendrennes - ZI, 85640 Mouchamps Pays de Loire",
    "addr:housenumber":"4",
    "addr:postcode":"85640;85640",
    "addr:street":"B.P.;Zi",
    "iso:country":"FR",
    "sg:address":"B.P. 4, 85640 Mouchamps C\u00e9dex^^Rte de Vendrennes - ZI, 85640 Mouchamps",
    "sg:orig_category":"Non-Classified Establishments",
    "sg:phone":"+33 2 51 63 91 91",
    "sg:province":"Pays de Loire",
    "wof:name":"S\u00e9ralu S.a.",
    "wof:placetype":"venue"
},
  "geometry": {"coordinates":[-1.061704,46.781715],"type":"Point"}
}