{
  "type": "Feature",
  "properties": {
    "addr:full":"B.P. 60090, 14401 Saint Martin des Entr\u00e9es^^6, Rte de Caen, 14400 Saint Martin des Entr\u00e9es Cond\u00e9-sur-Seulles Basse Normandie 14400",
    "addr:housenumber":"14401",
    "addr:postcode":"14400;14400",
    "addr:street":"Saint Martin Des Entre\u0301Es^^6 Rte De Caen;Martin Des Entre\u0301Es",
    "iso:country":"FR",
    "sg:address":"B.P. 60090, 14401 Saint Martin des Entr\u00e9es^^6, Rte de Caen, 14400 Saint Martin des Entr\u00e9es",
    "sg:city":"Cond\u00e9-sur-Seulles",
    "sg:orig_category":"Non-Classified Establishments",
    "sg:phone":"+33 2 31 51 48 48",
    "sg:postcode":"14400",
    "sg:province":"Basse Normandie",
    "wof:name":"Frial S.a.",
    "wof:placetype":"venue"
},
  "geometry": {"coordinates":[-0.675291,49.26841],"type":"Point"}
}