{
  "type": "Feature",
  "properties": {
    "iso:country":"FR",
    "sg:address":"B.P. 269, 69802 Saint Priest C\u00e9dex^^23, Rue du Progr\u00e8s, 69800 Saint Priest",
    "sg:orig_category":"Non-Classified Establishments",
    "sg:phone":"+33 4 72 22 94 00",
    "sg:province":"Rhone-Alpes",
    "wof:name":"S.n.a.a.m. S.a. - Soci\u00e9t\u00e9 Nouvelle Des Armatures Assembl\u00e9es Mure",
    "wof:placetype":"venue"
},
  "geometry": {"coordinates":[4.958692,45.717896],"type":"Point"}
}