{
  "type": "Feature",
  "properties": {
    "addr:full":"35, Rue de Berne, 75008 Paris Ile de France 75008",
    "addr:housenumber":"35",
    "addr:postcode":"75008;75008",
    "addr:street":"Rue De Berne",
    "iso:country":"FR",
    "sg:address":"35, Rue de Berne, 75008 Paris",
    "sg:orig_category":"Non-Classified Establishments",
    "sg:phone":"+33 1 43 87 34 34",
    "sg:postcode":"75008",
    "sg:province":"Ile de France",
    "wof:name":"Cabinet Faber",
    "wof:placetype":"venue"
},
  "geometry": {"coordinates":[2.322297,48.881607],"type":"Point"}
}