{
  "type": "Feature",
  "properties": {
    "addr:full":"68-76 Quai De La Rap\u00e9e 75606 Paris Cedex 12 Ile de France",
    "addr:housenumber":"68-76",
    "addr:postcode":"75606;france",
    "addr:street":"Quai De La Rape\u0301E",
    "iso:country":"FR",
    "sg:address":"68-76 Quai De La Rap\u00e9e 75606 Paris Cedex 12",
    "sg:classifiers":[
        {
            "category":"Banks & Credit Unions",
            "subcategory":"Financial Services",
            "type":"Services"
        }
    ],
    "sg:phone":"+33 1 49 96 90 00",
    "sg:province":"Ile de France",
    "sg:tags":[
        "banking",
        "finance",
        "insurance"
    ],
    "wof:name":"Fructivie Sa",
    "wof:placetype":"venue"
},
  "geometry": {"coordinates":[2.370624,48.843567],"type":"Point"}
}