{
  "type": "Feature",
  "properties": {
    "addr:full":"12 rue Jean Antoine de Ba\u00eff 75013 Paris Ile de France 75013",
    "addr:housenumber":"12",
    "addr:postcode":"75013;75013",
    "addr:street":"Rue Jean Antoine De Bai\u0308F",
    "iso:country":"FR",
    "sg:address":"12 rue Jean Antoine de Ba\u00eff 75013 Paris",
    "sg:classifiers":[
        {
            "category":"Farming",
            "subcategory":"Fish & Marine Products",
            "type":"Manufacturing & Wholesale Goods"
        }
    ],
    "sg:phone":"+33 1 53 94 58 58",
    "sg:postcode":"75013",
    "sg:province":"Ile de France",
    "sg:tags":[
        "caviar",
        "roe"
    ],
    "wof:name":"Caviar House Sa",
    "wof:placetype":"venue"
},
  "geometry": {"coordinates":[2.383411,48.827587],"type":"Point"}
}