{
  "type": "Feature",
  "properties": {
    "addr:full":"Rue du Clos Courtel - Z.I. Atalante Cesson S\u00e9vign\u00e9 C\u00e9dex Midi Pyr\u00e9n\u00e9es 35517",
    "addr:postcode":"35517",
    "addr:street":"Rue Du Clos Courtel",
    "iso:country":"FR",
    "sg:address":"Rue du Clos Courtel - Z.I. Atalante",
    "sg:city":"Cesson S\u00e9vign\u00e9 C\u00e9dex",
    "sg:orig_category":"Unclassifiable Establishments",
    "sg:phone":"+33 2 99 27 30 30",
    "sg:postcode":"35517",
    "sg:province":"Midi Pyr\u00e9n\u00e9es",
    "wof:name":"Thomson Broadcast Systems S.a.",
    "wof:placetype":"venue"
},
  "geometry": {"coordinates":[-1.604404,48.117016],"type":"Point"}
}