{
  "type": "Feature",
  "properties": {
    "iso:country":"FR",
    "sg:address":"Quartier Georgeonnes - ZI",
    "sg:city":"Bourg de P\u00e9age",
    "sg:orig_category":"Unclassifiable Establishments",
    "sg:phone":"+33 4 75 05 64 04",
    "sg:postcode":"26300",
    "sg:province":"Rhone-Alpes",
    "wof:name":"Lambert Equipements S.a.",
    "wof:placetype":"venue"
},
  "geometry": {"coordinates":[5.09157,44.938511],"type":"Point"}
}