{
  "type": "Feature",
  "properties": {
    "addr:full":"429, Av. du March\u00e9 Gare, 34000 Montpellier Languedoc-Roussillon",
    "addr:postcode":"34000",
    "addr:street":"429 Av. Du Marche\u0301 Gare",
    "iso:country":"FR",
    "sg:address":"429, Av. du March\u00e9 Gare, 34000 Montpellier",
    "sg:orig_category":"Unclassifiable Establishments",
    "sg:phone":"+33 4 67 92 40 40",
    "sg:province":"Languedoc-Roussillon",
    "wof:name":"Dyneff S.a.",
    "wof:placetype":"venue"
},
  "geometry": {"coordinates":[3.881665,43.58543],"type":"Point"}
}