{
  "type": "Feature",
  "properties": {
    "addr:full":"11 B Rue Jean Grimaud 56230 Questembert Questembert Bretagne 56230",
    "addr:housenumber":"11 b",
    "addr:postcode":"56230;56230",
    "addr:street":"Rue Jean Grimaud",
    "iso:country":"FR",
    "sg:address":"11 B Rue Jean Grimaud 56230 Questembert",
    "sg:city":"Questembert",
    "sg:classifiers":[
        {
            "category":"Building & Trades",
            "subcategory":"Construction",
            "type":"Services"
        }
    ],
    "sg:phone":"+33 2 97 26 66 39",
    "sg:postcode":"56230",
    "sg:province":"Bretagne",
    "sg:tags":[
        "livestock",
        "business",
        "advice",
        "animal",
        "breeding",
        "agriculture"
    ],
    "wof:name":"Ornis Sarl",
    "wof:placetype":"venue"
},
  "geometry": {"coordinates":[-2.458799,47.662182],"type":"Point"}
}