{
  "type": "Feature",
  "properties": {
    "addr:full":"Ld A\u00e9rodrome A\u00e9rogare De Fr\u00eat 59810 Lesquin Nord Pas-de-Calais 59810",
    "addr:postcode":"59810;59810",
    "addr:street":"Ld;Ae\u0301Rogare",
    "iso:country":"FR",
    "sg:address":"Ld A\u00e9rodrome A\u00e9rogare De Fr\u00eat 59810 Lesquin",
    "sg:classifiers":[
        {
            "category":"Banks & Credit Unions",
            "subcategory":"Investment Brokerage",
            "type":"Services"
        }
    ],
    "sg:phone":"+33 3 20 86 20 06",
    "sg:postcode":"59810",
    "sg:province":"Nord Pas-de-Calais",
    "sg:tags":[
        "-",
        "transport",
        "related",
        "air"
    ],
    "wof:name":"Geologistics Sa",
    "wof:placetype":"venue"
},
  "geometry": {"coordinates":[3.11003,50.588009],"type":"Point"}
}