{
  "type": "Feature",
  "properties": {
    "addr:full":"37, Rue Aim\u00e9 Bouchayer, 38170 Seyssinet Pariset Rhone-Alpes",
    "addr:housenumber":"37",
    "addr:postcode":"38170",
    "addr:street":"Rue Aime\u0301 Bouchayer",
    "iso:country":"FR",
    "sg:address":"37, Rue Aim\u00e9 Bouchayer, 38170 Seyssinet Pariset",
    "sg:orig_category":"Unclassifiable Establishments",
    "sg:phone":"+33 4 76 96 41 54",
    "sg:province":"Rhone-Alpes",
    "wof:name":"T.c.s. S.a. - T\u00f4lerie Sur Plans",
    "wof:placetype":"venue"
},
  "geometry": {"coordinates":[5.694655,45.182209],"type":"Point"}
}