{
  "type": "Feature",
  "properties": {
    "iso:country":"FR",
    "sg:address":"Zi De La Gare 51230 Connantre",
    "sg:classifiers":[
        {
            "category":"Shopping",
            "type":"Retail Goods"
        }
    ],
    "sg:phone":"+33 1 60 24 24 00",
    "sg:postcode":"51230",
    "sg:province":"Champagne",
    "sg:tags":[
        "metallurgy",
        "finished",
        "-",
        "metalworking",
        "metallic"
    ],
    "wof:name":"Sarl Nugue",
    "wof:placetype":"venue"
},
  "geometry": {"coordinates":[3.924956,48.729034],"type":"Point"}
}