{
  "type": "Feature",
  "properties": {
    "iso:country":"FR",
    "sg:address":"B.P. CP 708, 69256 Lyon C\u00e9dex 09^^110, Av. Barth\u00e9l\u00e9my Buyer, 69009 Lyon",
    "sg:orig_category":"Non-Classified Establishments",
    "sg:phone":"+33 4 72 57 50 00",
    "sg:postcode":"69009",
    "sg:province":"Rhone-Alpes",
    "wof:name":"Communication Active S.a.r.l.",
    "wof:placetype":"venue"
},
  "geometry": {"coordinates":[4.805335,45.774105],"type":"Point"}
}