{
  "type": "Feature",
  "properties": {
    "iso:country":"FR",
    "sg:address":"32 chemin de la Violette 31240 L UNION",
    "sg:classifiers":[
        {
            "category":"Shopping",
            "subcategory":"Clothing, Apparel, & Fashions",
            "type":"Retail Goods"
        }
    ],
    "sg:phone":"+33 5 34 27 42 64",
    "sg:postcode":"31240",
    "sg:province":"Midi Pyr\u00e9n\u00e9es",
    "sg:tags":[
        "clothing",
        "leisure"
    ],
    "wof:name":"St\u00e9 313 Bullrot Sarl",
    "wof:placetype":"venue"
},
  "geometry": {"coordinates":[-87.905098,32.996254],"type":"Point"}
}