{
  "type": "Feature",
  "properties": {
    "iso:country":"FR",
    "sg:address":"Rue du Petit Landau",
    "sg:city":"Habsheim",
    "sg:orig_category":"Unclassifiable Establishments",
    "sg:phone":"+33 3 89 65 23 77",
    "sg:postcode":"68440",
    "sg:province":"Alsace",
    "wof:name":"Voyages Cars Est S.a.r.l.",
    "wof:placetype":"venue"
},
  "geometry": {"coordinates":[7.42311,47.728294],"type":"Point"}
}