{
  "type": "Feature",
  "properties": {
    "addr:full":"56, Rue de Strasbourg, 55500 Ligny en Barrois Lorraine",
    "addr:housenumber":"56",
    "addr:postcode":"55500",
    "addr:street":"Rue De Strasbourg",
    "iso:country":"FR",
    "sg:address":"56, Rue de Strasbourg, 55500 Ligny en Barrois",
    "sg:orig_category":"Unclassifiable Establishments",
    "sg:phone":"+33 3 29 78 42 32",
    "sg:province":"Lorraine",
    "wof:name":"Sotrae S.a. - Soci\u00e9t\u00e9 De Travaux Et D'adduction D'eau",
    "wof:placetype":"venue"
},
  "geometry": {"coordinates":[5.328785,48.690231],"type":"Point"}
}