{
  "type": "Feature",
  "properties": {
    "addr:full":"1, Place Alfred Sauvy, 31270 Cugnaux Midi Pyr\u00e9n\u00e9es 31270",
    "addr:housenumber":"1",
    "addr:postcode":"31270;31270",
    "addr:street":"Place Alfred Sauvy",
    "iso:country":"FR",
    "sg:address":"1, Place Alfred Sauvy, 31270 Cugnaux",
    "sg:orig_category":"Non-Classified Establishments",
    "sg:phone":"+33 5 61 92 85 38",
    "sg:postcode":"31270",
    "sg:province":"Midi Pyr\u00e9n\u00e9es",
    "wof:name":"Arize S.a.",
    "wof:placetype":"venue"
},
  "geometry": {"coordinates":[1.363334,43.536098],"type":"Point"}
}