{
  "type": "Feature",
  "properties": {
    "iso:country":"FR",
    "sg:address":"Place Liberation",
    "sg:city":"Bozel",
    "sg:classifiers":[
        {
            "category":"Banks & Credit Unions",
            "subcategory":"Financial Services",
            "type":"Services"
        }
    ],
    "sg:phone":"+33 4 79 22 12 11",
    "sg:postcode":"73350",
    "sg:province":"Rhone-Alpes",
    "sg:tags":[
        "banking",
        "finance",
        "insurance"
    ],
    "wof:name":"Savoie Revision",
    "wof:placetype":"venue"
},
  "geometry": {"coordinates":[6.648847,45.442635],"type":"Point"}
}