{
  "type": "Feature",
  "properties": {
    "iso:country":"FR",
    "sg:address":"Rue Victor Hugo 08120 Bogny Sur Meuse",
    "sg:city":"Bogny-sur-Meuse",
    "sg:classifiers":[
        {
            "category":"Manufacturing",
            "subcategory":"Metals",
            "type":"Manufacturing & Wholesale Goods"
        }
    ],
    "sg:phone":"+33 3 24 32 03 05",
    "sg:postcode":"08120",
    "sg:province":"Champagne",
    "sg:tags":[
        "metallurgy",
        "steel",
        "metalworking"
    ],
    "wof:name":"Acs (ardennes Coffrage Soudure Sarl9",
    "wof:placetype":"venue"
},
  "geometry": {"coordinates":[4.768487,49.848854],"type":"Point"}
}