{
  "type": "Feature",
  "properties": {
    "addr:full":"ZA de la Tannerie Ancerville Lorraine 55170",
    "addr:postcode":"55170",
    "addr:street":"Za De La Tannerie",
    "iso:country":"FR",
    "sg:address":"ZA de la Tannerie",
    "sg:city":"Ancerville",
    "sg:orig_category":"Non-Classified Establishments",
    "sg:phone":"+33 3 29 75 39 39",
    "sg:postcode":"55170",
    "sg:province":"Lorraine",
    "wof:name":"Scrib'elec S.a.r.l.",
    "wof:placetype":"venue"
},
  "geometry": {"coordinates":[5.020695,48.636955],"type":"Point"}
}