{
  "type": "Feature",
  "properties": {
    "addr:full":"11 blvd de la R\u00e9publique; Chalon sur Sa\u00f4ne; 71100 Chalon-sur-Sa\u00f4ne Bourgogne 71100",
    "addr:postcode":"71100;71100",
    "addr:street":"11 Blvd De La Re\u0301Publique;Bourgogne",
    "iso:country":"FR",
    "sg:address":"11 blvd de la R\u00e9publique; Chalon sur Sa\u00f4ne; 71100",
    "sg:city":"Chalon-sur-Sa\u00f4ne",
    "sg:classifiers":[
        {
            "category":"Banks & Credit Unions",
            "subcategory":"Bank",
            "type":"Services"
        }
    ],
    "sg:phone":"+33 3 85 48 23 47",
    "sg:postcode":"71100",
    "sg:province":"Bourgogne",
    "wof:name":"Banque Rh\u00f4ne-alpes",
    "wof:placetype":"venue"
},
  "geometry": {"coordinates":[4.851325,46.783772],"type":"Point"}
}