{
  "type": "Feature",
  "properties": {
    "addr:full":"5, Rue Beaujon, 75008 Paris Ile de France",
    "addr:housenumber":"5",
    "addr:postcode":"75008",
    "addr:street":"Rue Beaujon",
    "iso:country":"FR",
    "sg:address":"5, Rue Beaujon, 75008 Paris",
    "sg:orig_category":"Unclassifiable Establishments",
    "sg:phone":"+33 1 53 81 51 00",
    "sg:province":"Ile de France",
    "wof:name":"Logfi S.a. - Logiciels Financiers",
    "wof:placetype":"venue"
},
  "geometry": {"coordinates":[2.299879,48.874901],"type":"Point"}
}