{
  "type": "Feature",
  "properties": {
    "addr:full":"7 Rue Du Mont Aigoual  Paris Ile de France 75015",
    "addr:housenumber":"7",
    "addr:postcode":"75015",
    "addr:street":"Rue Du Mont Aigoual",
    "iso:country":"FR",
    "sg:address":"7 Rue Du Mont Aigoual ",
    "sg:city":"Paris",
    "sg:orig_category":"\\N",
    "sg:postcode":"75015",
    "sg:province":"Ile de France",
    "wof:name":"Tom's daughter in Paris",
    "wof:placetype":"venue"
},
  "geometry": {"coordinates":[2.275426,48.842445],"type":"Point"}
}