{
  "type": "Feature",
  "properties": {
    "addr:full":"31, Rue des Bouchers, 67000 Strasbourg Strasbourg Alsace 67000",
    "addr:housenumber":"31",
    "addr:postcode":"67000;67000",
    "addr:street":"Rue Des Bouchers",
    "iso:country":"FR",
    "sg:address":"31, Rue des Bouchers, 67000 Strasbourg",
    "sg:city":"Strasbourg",
    "sg:orig_category":"Unclassifiable Establishments",
    "sg:phone":"+33 3 88 36 06 61",
    "sg:postcode":"67000",
    "sg:province":"Alsace",
    "wof:name":"Odsj S.a.r.l.",
    "wof:placetype":"venue"
},
  "geometry": {"coordinates":[7.750617,48.577633],"type":"Point"}
}