{
  "type": "Feature",
  "properties": {
    "addr:full":"26, Chemin de Barrico, 33760 Targon Targon Aquitaine 33760",
    "addr:housenumber":"26",
    "addr:postcode":"33760;33760",
    "addr:street":"Chemin De Barrico",
    "iso:country":"FR",
    "sg:address":"26, Chemin de Barrico, 33760 Targon",
    "sg:city":"Targon",
    "sg:orig_category":"Unclassifiable Establishments",
    "sg:phone":"+33 5 56 23 90 52",
    "sg:postcode":"33760",
    "sg:province":"Aquitaine",
    "wof:name":"Entreprise Lapeyronnie S.a.r.l.",
    "wof:placetype":"venue"
},
  "geometry": {"coordinates":[-0.264228,44.748489],"type":"Point"}
}