{
  "type": "Feature",
  "properties": {
    "addr:full":"3, Chemin des Babylones - ZI du Tumulus, 39100 Dole Franche Comt\u00e9",
    "addr:housenumber":"3",
    "addr:postcode":"39100",
    "addr:street":"Chemin Des Babylones Zi Du Tumulus;Franche Comte\u0301",
    "iso:country":"FR",
    "sg:address":"3, Chemin des Babylones - ZI du Tumulus, 39100 Dole",
    "sg:orig_category":"Non-Classified Establishments",
    "sg:phone":"+33 3 84 79 19 77",
    "sg:province":"Franche Comt\u00e9",
    "wof:name":"Sa.ju.mo. S.a. - Jurassienne De Modelage",
    "wof:placetype":"venue"
},
  "geometry": {"coordinates":[5.49014,47.089756],"type":"Point"}
}