{
  "type": "Feature",
  "properties": {
    "addr:full":"2 Rue Charles Fourier 59760 Grande Synthe Nord Pas-de-Calais 59760",
    "addr:housenumber":"2",
    "addr:postcode":"59760;59760",
    "addr:street":"Rue Charles Fourier;Pas-De-Calais",
    "iso:country":"FR",
    "sg:address":"2 Rue Charles Fourier 59760 Grande Synthe",
    "sg:classifiers":[
        {
            "category":"Manufacturing",
            "subcategory":"Metals",
            "type":"Manufacturing & Wholesale Goods"
        }
    ],
    "sg:phone":"+33 3 28 25 02 25",
    "sg:postcode":"59760",
    "sg:province":"Nord Pas-de-Calais",
    "sg:tags":[
        "-",
        "machine",
        "equipment",
        "engineering",
        "machinery",
        "mechanical"
    ],
    "wof:name":"Protection Metallique (la) Sarl",
    "wof:placetype":"venue"
},
  "geometry": {"coordinates":[2.306992,50.994148],"type":"Point"}
}