{
  "type": "Feature",
  "properties": {
    "addr:full":"1, Rue de la Tour Garnier, 16000 Angoul\u00eame Poitou-Charentes 16000",
    "addr:housenumber":"1",
    "addr:postcode":"16000;16000",
    "addr:street":"Rue De La Tour Garnier",
    "iso:country":"FR",
    "sg:address":"1, Rue de la Tour Garnier, 16000 Angoul\u00eame",
    "sg:orig_category":"Non-Classified Establishments",
    "sg:phone":"+33 5 45 95 11 95",
    "sg:postcode":"16000",
    "sg:province":"Poitou-Charentes",
    "wof:name":"Adia France",
    "wof:placetype":"venue"
},
  "geometry": {"coordinates":[0.166532,45.647839],"type":"Point"}
}