{
  "type": "Feature",
  "properties": {
    "addr:full":"18 Place Bellecour Lyon Rhone-Alpes 69002",
    "addr:housenumber":"18",
    "addr:postcode":"69002",
    "addr:street":"Place Bellecour;Rhone-Alpes",
    "iso:country":"FR",
    "sg:address":"18 Place Bellecour",
    "sg:city":"Lyon",
    "sg:classifiers":[
        {
            "category":"Banks & Credit Unions",
            "subcategory":"Financial Services",
            "type":"Services"
        }
    ],
    "sg:phone":"+33 4 78 92 31 00",
    "sg:postcode":"69002",
    "sg:province":"Rhone-Alpes",
    "sg:tags":[
        "banking",
        "finance",
        "insurance"
    ],
    "wof:name":"Banque Hervet",
    "wof:placetype":"venue"
},
  "geometry": {"coordinates":[4.833892,45.757164],"type":"Point"}
}