{
  "type": "Feature",
  "properties": {
    "iso:country":"FR",
    "sg:address":"Rte de Bordeaux",
    "sg:city":"Corbeilles",
    "sg:orig_category":"Unclassifiable Establishments",
    "sg:phone":"+33 2 38 92 20 73",
    "sg:postcode":"45490",
    "sg:province":"Centre",
    "wof:name":"Etablissements Deffaugt Et Fils S.a.",
    "wof:placetype":"venue"
},
  "geometry": {"coordinates":[2.536249,48.084126],"type":"Point"}
}