{
  "type": "Feature",
  "properties": {
    "iso:country":"FR",
    "sg:address":"Za Les Regains 43100 Vieille Brioude",
    "sg:city":"Brioude",
    "sg:classifiers":[
        {
            "category":"Wholesale",
            "subcategory":"Meat",
            "type":"Manufacturing & Wholesale Goods"
        }
    ],
    "sg:phone":"+33 4 71 74 93 93",
    "sg:postcode":"43100",
    "sg:province":"Auvergne",
    "sg:tags":[
        "food",
        "cooked",
        "product",
        "related"
    ],
    "wof:name":"Ets Philis Sarl",
    "wof:placetype":"venue"
},
  "geometry": {"coordinates":[3.405964,45.262169],"type":"Point"}
}