{
  "type": "Feature",
  "properties": {
    "addr:full":"Za Mourillon 56530 Qu\u00e9ven Qu\u00e9ven Bretagne 56530",
    "addr:postcode":"56530;56530",
    "addr:street":"Za Mourillon;Que\u0301Ven",
    "iso:country":"FR",
    "sg:address":"Za Mourillon 56530 Qu\u00e9ven",
    "sg:city":"Qu\u00e9ven",
    "sg:classifiers":[
        {
            "category":"Food Court",
            "type":"Food & Drink"
        }
    ],
    "sg:phone":"+33 2 97 80 12 60",
    "sg:postcode":"56530",
    "sg:province":"Bretagne",
    "sg:tags":[
        "product",
        "related"
    ],
    "wof:name":"V Mane Et Fils",
    "wof:placetype":"venue"
},
  "geometry": {"coordinates":[-3.416069,47.788921],"type":"Point"}
}