{
  "type": "Feature",
  "properties": {
    "addr:full":"85 Boulevard De Port Royal 75013 Paris Ile de France",
    "addr:housenumber":"85",
    "addr:postcode":"75013",
    "addr:street":"Boulevard De Port Royal",
    "iso:country":"FR",
    "sg:address":"85 Boulevard De Port Royal 75013 Paris",
    "sg:classifiers":[
        {
            "category":"Professional",
            "type":"Services"
        }
    ],
    "sg:phone":"+33 1 47 07 37 39",
    "sg:province":"Ile de France",
    "sg:tags":[
        "transport",
        "road"
    ],
    "wof:name":"Ambulances Port Royal Sa",
    "wof:placetype":"venue"
},
  "geometry": {"coordinates":[2.343135,48.837875],"type":"Point"}
}