{
  "type": "Feature",
  "properties": {
    "addr:full":"1025, Rue Henri Becquerel - Parc Club du Mill\u00e9naire - B\u00e2t. 15, 34036 Montpellier C\u00e9dex 1 Champagne",
    "addr:housenumber":"1025;15;1",
    "addr:postcode":"34036",
    "addr:street":"Rue Henri Becquerel Parc Club Du Mille\u0301Naire Ba\u0302T;Ce\u0301Dex",
    "iso:country":"FR",
    "sg:address":"1025, Rue Henri Becquerel - Parc Club du Mill\u00e9naire - B\u00e2t. 15, 34036 Montpellier C\u00e9dex 1",
    "sg:orig_category":"Non-Classified Establishments",
    "sg:phone":"+33 4 67 65 39 74",
    "sg:province":"Champagne",
    "wof:name":"Pour Votre Service S.a.s.",
    "wof:placetype":"venue"
},
  "geometry": {"coordinates":[3.914558,43.609131],"type":"Point"}
}