{
  "type": "Feature",
  "properties": {
    "addr:full":"Rte Orthez Saint Mont Midi Pyr\u00e9n\u00e9es 32400",
    "addr:postcode":"32400",
    "addr:street":"Rte Orthez Saint Mont Midi Pyre\u0301Ne\u0301Es",
    "iso:country":"FR",
    "sg:address":"Rte Orthez",
    "sg:city":"Saint Mont",
    "sg:orig_category":"Unclassifiable Establishments",
    "sg:phone":"+33 5 62 69 62 87",
    "sg:postcode":"32400",
    "sg:province":"Midi Pyr\u00e9n\u00e9es",
    "wof:name":"Producteurs De Plaimont",
    "wof:placetype":"venue"
},
  "geometry": {"coordinates":[-0.13978,43.598343],"type":"Point"}
}