{
  "type": "Feature",
  "properties": {
    "addr:full":"Rte De Metz 57300 Mondelange Lorraine 57300",
    "addr:postcode":"57300;57300",
    "addr:street":"Rte De Metz",
    "iso:country":"FR",
    "sg:address":"Rte De Metz 57300 Mondelange",
    "sg:classifiers":[
        {
            "category":"Manufacturing",
            "subcategory":"Metals",
            "type":"Manufacturing & Wholesale Goods"
        }
    ],
    "sg:phone":"+33 3 87 70 60 00",
    "sg:postcode":"57300",
    "sg:province":"Lorraine",
    "sg:tags":[
        "metallurgy",
        "metalworking"
    ],
    "wof:name":"Ispat Unimetal",
    "wof:placetype":"venue"
},
  "geometry": {"coordinates":[6.170132,49.267284],"type":"Point"}
}