{
  "type": "Feature",
  "properties": {
    "addr:full":"ZI les Visaubes La Couronne Poitou-Charentes 16400",
    "addr:postcode":"16400",
    "addr:street":"Zi Les Visaubes La Couronne",
    "iso:country":"FR",
    "sg:address":"ZI les Visaubes",
    "sg:city":"La Couronne",
    "sg:orig_category":"Non-Classified Establishments",
    "sg:phone":"+33 5 45 67 45 00",
    "sg:postcode":"16400",
    "sg:province":"Poitou-Charentes",
    "wof:name":"T.v.i. S.a. - Techniques Vibratoires Industrielles",
    "wof:placetype":"venue"
},
  "geometry": {"coordinates":[0.102157,45.608215],"type":"Point"}
}