{
  "type": "Feature",
  "properties": {
    "iso:country":"FR",
    "sg:address":"24 rue des Rotondes 71880 Chatenoy le Royal",
    "sg:city":"Ch\u00e2tenoy-le-Royal",
    "sg:classifiers":[
        {
            "category":"Banks & Credit Unions",
            "subcategory":"Investment Brokerage",
            "type":"Services"
        }
    ],
    "sg:phone":"+33 3 85 87 93 50",
    "sg:postcode":"71880",
    "sg:province":"Bourgogne",
    "sg:tags":[
        "wooden",
        "packaging"
    ],
    "wof:name":"Ste Emballage Industriel Du Chalonnais Sarl",
    "wof:placetype":"venue"
},
  "geometry": {"coordinates":[4.824306,46.790562],"type":"Point"}
}