{
  "type": "Feature",
  "properties": {
    "addr:full":"Rue Gilbert Romme 72200 La Fleche Pays de Loire 72200",
    "addr:postcode":"72200;72200",
    "addr:street":"Rue Gilbert Romme;Fleche",
    "iso:country":"FR",
    "sg:address":"Rue Gilbert Romme 72200 La Fleche",
    "sg:classifiers":[
        {
            "category":"Wholesale",
            "subcategory":"Machinery & Supplies",
            "type":"Manufacturing & Wholesale Goods"
        }
    ],
    "sg:phone":"+33 2 43 48 17 00",
    "sg:postcode":"72200",
    "sg:province":"Pays de Loire",
    "sg:tags":[
        "food",
        "processing",
        "-",
        "machine",
        "equipment",
        "engineering",
        "mechanical"
    ],
    "wof:name":"Agro Minerai Industrie",
    "wof:placetype":"venue"
},
  "geometry": {"coordinates":[-0.107219,47.713024],"type":"Point"}
}