{
  "type": "Feature",
  "properties": {
    "addr:full":"21 rue Bouquet, 76007 Rouen, Dept 76 Centre",
    "addr:housenumber":"21;76",
    "addr:postcode":"76007",
    "addr:street":"Rue Bouquet",
    "iso:country":"FR",
    "sg:address":"21 rue Bouquet, 76007 Rouen, Dept 76",
    "sg:classifiers":[
        {
            "category":"Banks & Credit Unions",
            "subcategory":"Bank",
            "type":"Services"
        }
    ],
    "sg:phone":"+33 2 35 59 42 00",
    "sg:province":"Centre",
    "wof:name":"Caisse D'epargne De Haute-normandie",
    "wof:placetype":"venue"
},
  "geometry": {"coordinates":[1.091725,49.448055],"type":"Point"}
}