{
  "type": "Feature",
  "properties": {
    "addr:full":"11 B Route De Charentay 69220 Belleville Rhone-Alpes",
    "addr:housenumber":"11 b",
    "addr:postcode":"69220",
    "addr:street":"Route De Charentay",
    "iso:country":"FR",
    "sg:address":"11 B Route De Charentay 69220 Belleville",
    "sg:classifiers":[
        {
            "category":"Home & Garden",
            "subcategory":"Furniture",
            "type":"Retail Goods"
        }
    ],
    "sg:phone":"+33 4 74 06 49 49",
    "sg:province":"Rhone-Alpes",
    "sg:tags":[
        "wood"
    ],
    "wof:name":"Parqueterie Gagnieu",
    "wof:placetype":"venue"
},
  "geometry": {"coordinates":[4.72862,46.112801],"type":"Point"}
}