{
  "type": "Feature",
  "properties": {
    "addr:full":"96 Rue Gambetta 33230 Coutras Coutras Aquitaine 33230",
    "addr:housenumber":"96",
    "addr:postcode":"33230;33230",
    "addr:street":"Rue Gambetta",
    "iso:country":"FR",
    "sg:address":"96 Rue Gambetta 33230 Coutras",
    "sg:city":"Coutras",
    "sg:classifiers":[
        {
            "category":"Farming",
            "subcategory":"Farm",
            "type":"Manufacturing & Wholesale Goods"
        }
    ],
    "sg:phone":"+33 820 06 43 88",
    "sg:postcode":"33230",
    "sg:province":"Aquitaine",
    "sg:tags":[
        "horticulture",
        "agriculture",
        "livestock"
    ],
    "wof:name":"Euralis Agro Vigne",
    "wof:placetype":"venue"
},
  "geometry": {"coordinates":[-0.128999,45.044334],"type":"Point"}
}