{
  "type": "Feature",
  "properties": {
    "iso:country":"FR",
    "sg:address":"11 villa Gaudelet 75011 Paris",
    "sg:orig_category":"Pressure Reducers And Reducing Systems For Ultra-Pure Gases",
    "sg:phone":"+33 1 43 14 82 90",
    "sg:province":"Ile de France",
    "wof:name":"Briffault Sa",
    "wof:placetype":"venue"
},
  "geometry": {"coordinates":[2.380154,48.865181],"type":"Point"}
}