{
  "type": "Feature",
  "properties": {
    "iso:country":"FR",
    "sg:address":"22, Rte de la Roche sur Yon - Parc d'Activit\u00e9 de Viais, 44860 Pont Saint Martin",
    "sg:orig_category":"Non-Classified Establishments",
    "sg:phone":"+33 2 40 32 72 60",
    "sg:province":"Pays de Loire",
    "wof:name":"T.a.o. S.a. - Techniques Appliqu\u00e9es De L'ouest",
    "wof:placetype":"venue"
},
  "geometry": {"coordinates":[-1.53128,47.121861],"type":"Point"}
}