{
  "type": "Feature",
  "properties": {
    "addr:full":"28 Av Marcel Pagnol 81300 Graulhet Midi Pyr\u00e9n\u00e9es 81300",
    "addr:postcode":"81300;81300",
    "addr:street":"28 Av Marcel Pagnol",
    "iso:country":"FR",
    "sg:address":"28 Av Marcel Pagnol 81300 Graulhet",
    "sg:classifiers":[
        {
            "category":"Manufacturing",
            "subcategory":"Leather Goods",
            "type":"Manufacturing & Wholesale Goods"
        }
    ],
    "sg:phone":"+33 5 63 34 52 17",
    "sg:postcode":"81300",
    "sg:province":"Midi Pyr\u00e9n\u00e9es",
    "sg:tags":[
        "shoe"
    ],
    "wof:name":"Ets Robert Frandi",
    "wof:placetype":"venue"
},
  "geometry": {"coordinates":[1.996584,43.767357],"type":"Point"}
}