{
  "type": "Feature",
  "properties": {
    "iso:country":"FR",
    "sg:address":"Ch\u00e2teau Pintoucat 24240 Monbazillac",
    "sg:city":"Monbazillac",
    "sg:orig_category":"Unclassifiable Establishments",
    "sg:phone":"+33 5 53 57 00 84",
    "sg:postcode":"24240",
    "sg:province":"Aquitaine",
    "wof:name":"Beaudoin Georges",
    "wof:placetype":"venue"
},
  "geometry": {"coordinates":[0.431681,44.744911],"type":"Point"}
}