{
  "type": "Feature",
  "properties": {
    "addr:full":"44 Rue Saint-Ladre 57950 Montigny-L\u00e8s-Metz Ile de France",
    "addr:housenumber":"44",
    "addr:postcode":"57950;ile",
    "addr:street":"Rue Saint-Ladre",
    "iso:country":"FR",
    "sg:address":"44 Rue Saint-Ladre 57950 Montigny-L\u00e8s-Metz",
    "sg:classifiers":[
        {
            "category":"Wholesale",
            "subcategory":"Meat",
            "type":"Manufacturing & Wholesale Goods"
        }
    ],
    "sg:phone":"+33 3 87 62 33 64",
    "sg:province":"Ile de France",
    "sg:tags":[
        "food",
        "cooked",
        "product",
        "related"
    ],
    "wof:name":"Gall Boucherie",
    "wof:placetype":"venue"
},
  "geometry": {"coordinates":[6.152029,49.093735],"type":"Point"}
}