{
  "type": "Feature",
  "properties": {
    "addr:full":"Le Champ du Roy 33930 Vendays Montalivet Vendays-Montalivet Aquitaine 33930",
    "addr:postcode":"33930;33930",
    "addr:street":"Le Champ Du Roy",
    "iso:country":"FR",
    "sg:address":"Le Champ du Roy 33930 Vendays Montalivet",
    "sg:city":"Vendays-Montalivet",
    "sg:orig_category":"Non-Classified Establishments",
    "sg:phone":"+33 5 56 41 70 21",
    "sg:postcode":"33930",
    "sg:province":"Aquitaine",
    "wof:name":"C.d.r. S.a.r.l. - Champ Du Roy",
    "wof:placetype":"venue"
},
  "geometry": {"coordinates":[-1.095479,45.36834],"type":"Point"}
}