{
  "type": "Feature",
  "properties": {
    "iso:country":"FR",
    "sg:address":"21 B Rue Ingenieur Verriere 56100 Lorient",
    "sg:city":"Lorient",
    "sg:classifiers":[
        {
            "category":"Farming",
            "subcategory":"Livestock Farm",
            "type":"Manufacturing & Wholesale Goods"
        }
    ],
    "sg:phone":"+33 2 97 83 90 13",
    "sg:postcode":"56100",
    "sg:province":"Bretagne",
    "sg:tags":[
        "breeding",
        "agriculture",
        "animal"
    ],
    "wof:name":"Nouvelle Societe Prestigel",
    "wof:placetype":"venue"
},
  "geometry": {"coordinates":[-3.371071,47.732929],"type":"Point"}
}