{
  "type": "Feature",
  "properties": {
    "iso:country":"FR",
    "sg:address":"20, Chemin du Vieux Pav\u00e9, 91220 Br\u00e9tigny sur Orge",
    "sg:orig_category":"Unclassifiable Establishments",
    "sg:phone":"+33 1 60 84 60 54",
    "sg:province":"Ile de France",
    "wof:name":"Peltrax Hydraulique S.a.",
    "wof:placetype":"venue"
},
  "geometry": {"coordinates":[2.31628,48.622009],"type":"Point"}
}