{
  "type": "Feature",
  "properties": {
    "iso:country":"FR",
    "sg:address":"20 Av Amp\u00e8re 91320 Wissous",
    "sg:orig_category":"Mechanical Engineering - machines Paper and cardboard - raw materials Precision Equipment",
    "sg:phone":"+33 1 60 13 56 60",
    "sg:postcode":"91320",
    "sg:province":"Ile de France",
    "wof:name":"Marbach France Sa",
    "wof:placetype":"venue"
},
  "geometry": {"coordinates":[2.319794,48.728104],"type":"Point"}
}