{
  "type": "Feature",
  "properties": {
    "addr:full":"Ld Lardimalie D\u00e9coupage 87260 Vicq Sur Breuilh Limousin 87260",
    "addr:postcode":"87260;87260",
    "addr:street":"Ld;De\u0301Coupage",
    "iso:country":"FR",
    "sg:address":"Ld Lardimalie D\u00e9coupage 87260 Vicq Sur Breuilh",
    "sg:classifiers":[
        {
            "category":"Manufacturing",
            "subcategory":"Metals",
            "type":"Manufacturing & Wholesale Goods"
        }
    ],
    "sg:phone":"+33 5 55 00 86 16",
    "sg:postcode":"87260",
    "sg:province":"Limousin",
    "sg:tags":[
        "metallurgy",
        "metalworking",
        "processing"
    ],
    "wof:name":"L R D Sarl",
    "wof:placetype":"venue"
},
  "geometry": {"coordinates":[1.440101,45.630219],"type":"Point"}
}