{
  "type": "Feature",
  "properties": {
    "addr:full":"6, Av. Charles de Gaulle, 95700 Roissy en France Ile de France",
    "addr:postcode":"95700",
    "addr:street":"Av. Charles De Gaulle",
    "iso:country":"FR",
    "sg:address":"6, Av. Charles de Gaulle, 95700 Roissy en France",
    "sg:orig_category":"Unclassifiable Establishments",
    "sg:phone":"+33 1 34 29 84 29",
    "sg:province":"Ile de France",
    "wof:name":"S.i.r.e.f. S.a. - Soci\u00e9t\u00e9 Industrielle De Roissy En France",
    "wof:placetype":"venue"
},
  "geometry": {"coordinates":[2.515195,49.000942],"type":"Point"}
}