{
  "type": "Feature",
  "properties": {
    "iso:country":"FR",
    "sg:address":"29, Av. des Sources - B\u00e2t. le Trait d'Union, 69009 Lyon",
    "sg:orig_category":"Non-Classified Establishments",
    "sg:phone":"+33 4 37 49 68 49",
    "sg:province":"Rhone-Alpes",
    "wof:name":"V\u00e9ronesi France S.a.r.l.",
    "wof:placetype":"venue"
},
  "geometry": {"coordinates":[4.785211,45.788139],"type":"Point"}
}