{
  "type": "Feature",
  "properties": {
    "iso:country":"FR",
    "sg:address":"B.P. 4, 28140 Org\u00e8res en Beauce^^ZI, 28140 Org\u00e8res en Beauce",
    "sg:city":"Germignonville",
    "sg:orig_category":"Non-Classified Establishments",
    "sg:phone":"+33 2 37 99 75 45",
    "sg:postcode":"28140",
    "sg:province":"Centre",
    "wof:name":"Entreprise Robert Dhennin S.a.",
    "wof:placetype":"venue"
},
  "geometry": {"coordinates":[1.583935,48.063595],"type":"Point"}
}