{
  "type": "Feature",
  "properties": {
    "addr:full":"87 rue Jean Jaur\u00e8s 44600 ST NAZAIRE Pays de Loire 44600",
    "addr:housenumber":"87",
    "addr:postcode":"44600 st nazaire;44600",
    "addr:street":"Rue Jean Jaure\u0300S",
    "iso:country":"FR",
    "sg:address":"87 rue Jean Jaur\u00e8s 44600 ST NAZAIRE",
    "sg:classifiers":[
        {
            "category":"Wholesale",
            "subcategory":"Wine & Distilled Alcoholic Beverages",
            "type":"Manufacturing & Wholesale Goods"
        }
    ],
    "sg:phone":"+33 2 40 66 55 57",
    "sg:postcode":"44600",
    "sg:province":"Pays de Loire",
    "sg:tags":[
        "french"
    ],
    "wof:name":"Le Tastevin Sa",
    "wof:placetype":"venue"
},
  "geometry": {"coordinates":[-2.215178,47.280025],"type":"Point"}
}