{
  "type": "Feature",
  "properties": {
    "iso:country":"FR",
    "sg:address":"47 boulevard d'Arras 13004 Marseille",
    "sg:orig_category":"Menswear, Suits, Trousers, Sports Jackets",
    "sg:phone":"+33 4 91 34 03 30",
    "sg:province":"Nord Pas-de-Calais",
    "wof:name":"Albenco Sarl",
    "wof:placetype":"venue"
},
  "geometry": {"coordinates":[5.401081,43.308769],"type":"Point"}
}