{
  "type": "Feature",
  "properties": {
    "addr:full":"113/117, Bd Aristide Briand, 91600 Savigny sur Orge Ile de France 91600",
    "addr:housenumber":"113 / 117",
    "addr:postcode":"91600;91600",
    "addr:street":"Bd Aristide Briand",
    "iso:country":"FR",
    "sg:address":"113/117, Bd Aristide Briand, 91600 Savigny sur Orge",
    "sg:orig_category":"Non-Classified Establishments",
    "sg:phone":"+33 1 69 96 00 21",
    "sg:postcode":"91600",
    "sg:province":"Ile de France",
    "wof:name":"B.i.c.s. S.a.",
    "wof:placetype":"venue"
},
  "geometry": {"coordinates":[2.358864,48.688454],"type":"Point"}
}