{
  "type": "Feature",
  "properties": {
    "addr:full":"2 Pl Giraud 54440 Longwy Lorraine 54440",
    "addr:housenumber":"2",
    "addr:postcode":"54440;54440",
    "addr:street":"Pl Giraud",
    "iso:country":"FR",
    "sg:address":"2 Pl Giraud 54440 Longwy",
    "sg:classifiers":[
        {
            "category":"Manufacturing",
            "subcategory":"Building Materials",
            "type":"Manufacturing & Wholesale Goods"
        }
    ],
    "sg:phone":"+33 3 82 23 26 50",
    "sg:postcode":"54440",
    "sg:province":"Lorraine",
    "sg:tags":[
        "glass",
        "ceramic"
    ],
    "wof:name":"Emaux Des Recollets Sarl",
    "wof:placetype":"venue"
},
  "geometry": {"coordinates":[5.769336,49.514568],"type":"Point"}
}