{
  "type": "Feature",
  "properties": {
    "iso:country":"FR",
    "sg:address":"ZI",
    "sg:city":"Reuilly",
    "sg:orig_category":"Non-Classified Establishments",
    "sg:phone":"+33 2 54 49 24 83",
    "sg:postcode":"36260",
    "sg:province":"Centre",
    "wof:name":"Amca Noval",
    "wof:placetype":"venue"
},
  "geometry": {"coordinates":[2.04051,47.085072],"type":"Point"}
}