{
  "type": "Feature",
  "properties": {
    "iso:country":"FR",
    "sg:address":"9, Rue Kl\u00e9ber, 92130 Issy les Moulineaux",
    "sg:orig_category":"Non-Classified Establishments",
    "sg:phone":"+33 1 46 42 85 37",
    "sg:postcode":"92130",
    "sg:province":"Ile de France",
    "wof:name":"Etablissements Cerclet S.a.r.l.",
    "wof:placetype":"venue"
},
  "geometry": {"coordinates":[2.272876,48.826588],"type":"Point"}
}