{
  "type": "Feature",
  "properties": {
    "addr:full":"299, Av. du G\u00e9n\u00e9ral Patton, 49000 Angers Pays de Loire",
    "addr:postcode":"49000",
    "addr:street":"299 Av. Du Ge\u0301Ne\u0301Ral Patton",
    "iso:country":"FR",
    "sg:address":"299, Av. du G\u00e9n\u00e9ral Patton, 49000 Angers",
    "sg:orig_category":"Unclassifiable Establishments",
    "sg:phone":"+33 2 41 36 47 00",
    "sg:province":"Pays de Loire",
    "wof:name":"Nec Computers Angers S.a.r.l.",
    "wof:placetype":"venue"
},
  "geometry": {"coordinates":[-0.598544,47.473049],"type":"Point"}
}