{
  "type": "Feature",
  "properties": {
    "addr:full":"229 Rue De Falaise 14000 Caen Caen Basse Normandie 14000",
    "addr:housenumber":"229",
    "addr:postcode":"14000;14000",
    "addr:street":"Rue De Falaise",
    "iso:country":"FR",
    "sg:address":"229 Rue De Falaise 14000 Caen",
    "sg:city":"Caen",
    "sg:classifiers":[
        {
            "category":"Professional",
            "subcategory":"Business Services",
            "type":"Services"
        }
    ],
    "sg:phone":"+33 2 31 82 60 78",
    "sg:postcode":"14000",
    "sg:province":"Basse Normandie",
    "sg:tags":[
        "travel",
        "transport",
        "sea"
    ],
    "wof:name":"Bosse Philippe",
    "wof:placetype":"venue"
},
  "geometry": {"coordinates":[-0.349008,49.163219],"type":"Point"}
}