{
  "type": "Feature",
  "properties": {
    "addr:full":"Z I Les Hautes Vallieres 69530 BRIGNAIS Rhone-Alpes",
    "addr:postcode":"69530",
    "addr:street":"Z I Les Hautes Vallieres",
    "iso:country":"FR",
    "sg:address":"Z I Les Hautes Vallieres 69530 BRIGNAIS",
    "sg:classifiers":[
        {
            "category":"Bus Stop",
            "subcategory":"None",
            "type":"Transportation"
        }
    ],
    "sg:phone":"+33 4 72 31 81 31",
    "sg:province":"Rhone-Alpes",
    "sg:tags":[
        "period",
        "furniture"
    ],
    "wof:name":"Le Meuble Artisanal Geka S.a.",
    "wof:placetype":"venue"
},
  "geometry": {"coordinates":[4.753949,45.674034],"type":"Point"}
}