{
  "type": "Feature",
  "properties": {
    "iso:country":"FR",
    "sg:address":"93, Chemin de la Buyre, 84170 Monteux",
    "sg:orig_category":"Unclassifiable Establishments",
    "sg:phone":"+33 4 90 66 39 95",
    "sg:province":"Centre",
    "wof:name":"Provence Packaging S.a.r.l.",
    "wof:placetype":"venue"
},
  "geometry": {"coordinates":[4.993563,44.03949],"type":"Point"}
}