{
  "type": "Feature",
  "properties": {
    "addr:full":"12, Av. du 1er Mai, 91127 Palaiseau C\u00e9dex Palaiseau Ile de France 91120",
    "addr:postcode":"91127;91120",
    "addr:street":"12 Av. Du 1Er Mai",
    "iso:country":"FR",
    "sg:address":"12, Av. du 1er Mai, 91127 Palaiseau C\u00e9dex",
    "sg:city":"Palaiseau",
    "sg:orig_category":"Non-Classified Establishments",
    "sg:phone":"+33 1 69 31 69 00",
    "sg:postcode":"91120",
    "sg:province":"Ile de France",
    "wof:name":"Charmilles Technologies France S.a.",
    "wof:placetype":"venue"
},
  "geometry": {"coordinates":[2.256728,48.711208],"type":"Point"}
}