{
  "type": "Feature",
  "properties": {
    "addr:full":"B.P. 194, 95106 Argenteuil C\u00e9dex^^24, Bd des Martyrs de Ch\u00e2teaubriand, 95100 Argenteuil Ile de France",
    "addr:housenumber":"b.p. 194",
    "addr:postcode":"95106;ce\u0301dex^^24;95100;ile",
    "addr:street":"Bd Des Martyrs De Cha\u0302Teaubriand",
    "iso:country":"FR",
    "sg:address":"B.P. 194, 95106 Argenteuil C\u00e9dex^^24, Bd des Martyrs de Ch\u00e2teaubriand, 95100 Argenteuil",
    "sg:orig_category":"Non-Classified Establishments",
    "sg:phone":"+33 1 30 25 96 96",
    "sg:province":"Ile de France",
    "wof:name":"Sig Positec S.a.",
    "wof:placetype":"venue"
},
  "geometry": {"coordinates":[2.245075,48.942097],"type":"Point"}
}