{
  "type": "Feature",
  "properties": {
    "iso:country":"FR",
    "sg:address":"18-20 Rte De Piscop 95350 St Brice Sous For\u00eat",
    "sg:classifiers":[
        {
            "category":"Manufacturing",
            "subcategory":"Metals",
            "type":"Manufacturing & Wholesale Goods"
        }
    ],
    "sg:phone":"+33 1 39 90 35 44",
    "sg:postcode":"95350",
    "sg:province":"Ile de France",
    "sg:tags":[
        "-",
        "machine",
        "equipment",
        "engineering",
        "machinery",
        "mechanical"
    ],
    "wof:name":"Grare Freres Sa",
    "wof:placetype":"venue"
},
  "geometry": {"coordinates":[2.3488,49.00684],"type":"Point"}
}