{
  "type": "Feature",
  "properties": {
    "addr:full":"La Maladi\u00e8re 01240 St Paul De Varax Rhone-Alpes 01240",
    "addr:postcode":"01240;01240",
    "addr:street":"Rhone-Alpes",
    "iso:country":"FR",
    "sg:address":"La Maladi\u00e8re 01240 St Paul De Varax",
    "sg:classifiers":[
        {
            "category":"Autos & Motor Vehicles",
            "subcategory":"Automobile Sales",
            "type":"Retail Goods"
        }
    ],
    "sg:phone":"+33 4 74 42 53 46",
    "sg:postcode":"01240",
    "sg:province":"Rhone-Alpes",
    "sg:tags":[
        "equipment",
        "industrial",
        "transport"
    ],
    "wof:name":"Sa Dereur",
    "wof:placetype":"venue"
},
  "geometry": {"coordinates":[5.16483,46.100128],"type":"Point"}
}