{
  "type": "Feature",
  "properties": {
    "iso:country":"FR",
    "sg:address":"chemin Roc plan 30210 VERS PONT DU GARD",
    "sg:classifiers":[
        {
            "category":"Landmark",
            "subcategory":"City Walls",
            "type":"Public Place"
        }
    ],
    "sg:phone":"+33 4 66 88 25 93",
    "sg:province":"Languedoc-Roussillon",
    "sg:tags":[
        "stone",
        "working"
    ],
    "wof:name":"Silex",
    "wof:placetype":"venue"
},
  "geometry": {"coordinates":[4.551335,43.910404],"type":"Point"}
}