{
  "type": "Feature",
  "properties": {
    "iso:country":"FR",
    "sg:address":"18, Rue Latarenne, 41120 Cellettes",
    "sg:city":"Cellettes",
    "sg:orig_category":"Unclassifiable Establishments",
    "sg:phone":"+33 2 54 70 36 82",
    "sg:postcode":"41120",
    "sg:province":"Centre",
    "wof:name":"R\u00e9sidence Du Centre S.a.r.l.",
    "wof:placetype":"venue"
},
  "geometry": {"coordinates":[1.276185,47.416473],"type":"Point"}
}