{
  "type": "Feature",
  "properties": {
    "addr:full":"205, Rte de Millau, 81013 Albi Midi Pyr\u00e9n\u00e9es",
    "addr:housenumber":"205",
    "addr:postcode":"81013",
    "addr:street":"Rte De Millau",
    "iso:country":"FR",
    "sg:address":"205, Rte de Millau, 81013 Albi",
    "sg:orig_category":"Non-Classified Establishments",
    "sg:phone":"+33 5 63 45 43 22",
    "sg:province":"Midi Pyr\u00e9n\u00e9es",
    "wof:name":"Teddy Smith S.a.",
    "wof:placetype":"venue"
},
  "geometry": {"coordinates":[2.199652,43.927746],"type":"Point"}
}