{
  "type": "Feature",
  "properties": {
    "addr:full":"16 Rue Rochettes 91150 Morigny Champigny Ile de France 91150",
    "addr:housenumber":"16",
    "addr:postcode":"91150;ile;91150",
    "addr:street":"Rue Rochettes;France",
    "iso:country":"FR",
    "sg:address":"16 Rue Rochettes 91150 Morigny Champigny",
    "sg:classifiers":[
        {
            "category":"Wholesale",
            "subcategory":"Farm Supplies",
            "type":"Manufacturing & Wholesale Goods"
        }
    ],
    "sg:phone":"+33 1 60 80 70 70",
    "sg:postcode":"91150",
    "sg:province":"Ile de France",
    "sg:tags":[
        "-",
        "machine",
        "equipment",
        "engineering",
        "machinery",
        "mechanical",
        "agriculture"
    ],
    "wof:name":"Case New Holland France",
    "wof:placetype":"venue"
},
  "geometry": {"coordinates":[2.171407,48.455776],"type":"Point"}
}