{
  "type": "Feature",
  "properties": {
    "iso:country":"FR",
    "sg:address":"11, Rue des Tilleuls, 39700 La Barre",
    "sg:orig_category":"Non-Classified Establishments",
    "sg:phone":"+33 3 84 81 23 99",
    "sg:postcode":"39700",
    "sg:province":"Franche Comt\u00e9",
    "wof:name":"D.m.g. S.a. - D\u00e9coupage Et M\u00e9canique G\u00e9n\u00e9rale",
    "wof:placetype":"venue"
},
  "geometry": {"coordinates":[5.684029,47.148315],"type":"Point"}
}