{
  "type": "Feature",
  "properties": {
    "iso:country":"FR",
    "sg:address":"Le Mollard 01370 B\u00e9ny",
    "sg:orig_category":"Unclassifiable Establishments",
    "sg:phone":"+33 4 74 51 05 73",
    "sg:postcode":"01370",
    "sg:province":"Rhone-Alpes",
    "wof:name":"Entreprise Seve Robert",
    "wof:placetype":"venue"
},
  "geometry": {"coordinates":[5.29544,46.324051],"type":"Point"}
}