{
  "type": "Feature",
  "properties": {
    "addr:full":"Parc d'Activit\u00e9 Limonest Rhone-Alpes 69760",
    "addr:postcode":"69760",
    "iso:country":"FR",
    "sg:address":"Parc d'Activit\u00e9",
    "sg:city":"Limonest",
    "sg:orig_category":"Unclassifiable Establishments",
    "sg:phone":"+33 4 78 66 42 66",
    "sg:postcode":"69760",
    "sg:province":"Rhone-Alpes",
    "wof:name":"Polti Distribution S.a.",
    "wof:placetype":"venue"
},
  "geometry": {"coordinates":[4.76822,45.826691],"type":"Point"}
}