{
  "type": "Feature",
  "properties": {
    "iso:country":"FR",
    "sg:address":"Domaine de Fleurenne",
    "sg:city":"Blanquefort",
    "sg:orig_category":"Unclassifiable Establishments",
    "sg:phone":"+33 5 56 95 55 20",
    "sg:postcode":"33290",
    "sg:province":"Aquitaine",
    "wof:name":"Parrot Et Compagnie S.a.",
    "wof:placetype":"venue"
},
  "geometry": {"coordinates":[-0.615539,44.927422],"type":"Point"}
}