{
  "type": "Feature",
  "properties": {
    "addr:full":"28 Rue Charles Domercq 33800 Bordeaux Bordeaux Aquitaine 33800",
    "addr:housenumber":"28",
    "addr:postcode":"33800;33800",
    "addr:street":"Rue Charles Domercq",
    "iso:country":"FR",
    "sg:address":"28 Rue Charles Domercq 33800 Bordeaux",
    "sg:city":"Bordeaux",
    "sg:classifiers":[
        {
            "category":"Travel",
            "subcategory":"Hotels & Motels",
            "type":"Entertainment"
        }
    ],
    "sg:phone":"+33 5 56 91 54 52",
    "sg:postcode":"33800",
    "sg:province":"Aquitaine",
    "sg:tags":[
        "hotels",
        "business",
        "restaurant"
    ],
    "wof:name":"H\u00d4tel Arcantis Le Faisan",
    "wof:placetype":"venue"
},
  "geometry": {"coordinates":[-0.556837,44.826469],"type":"Point"}
}