{
  "type": "Feature",
  "properties": {
    "addr:full":"4, Av. des Tissonvilliers, 95400 Villiers le Bel Ile de France",
    "addr:postcode":"95400",
    "addr:street":"Av. Des Tissonvilliers",
    "iso:country":"FR",
    "sg:address":"4, Av. des Tissonvilliers, 95400 Villiers le Bel",
    "sg:orig_category":"Unclassifiable Establishments",
    "sg:phone":"+33 1 39 90 06 75",
    "sg:province":"Ile de France",
    "wof:name":"S.i.t.m.a. S.a. - Soci\u00e9t\u00e9 Industrielle De Taillage Et De M\u00e9canique",
    "wof:placetype":"venue"
},
  "geometry": {"coordinates":[2.389553,49.000652],"type":"Point"}
}