{
  "type": "Feature",
  "properties": {
    "iso:country":"FR",
    "sg:address":"34, Rue du Gouvernement, 02100 Saint Quentin",
    "sg:orig_category":"Unclassifiable Establishments",
    "sg:phone":"+33 3 23 62 37 91",
    "sg:province":"Picardie",
    "wof:name":"Soci\u00e9t\u00e9 D'expertise Comptable S.a.",
    "wof:placetype":"venue"
},
  "geometry": {"coordinates":[3.291277,49.848419],"type":"Point"}
}