{
  "type": "Feature",
  "properties": {
    "addr:full":"19, Av. Ambroise Croizat, 03410 Domerat Dom\u00e9rat Auvergne 03410",
    "addr:postcode":"03410;03410",
    "addr:street":"19 Av. Ambroise Croizat",
    "iso:country":"FR",
    "sg:address":"19, Av. Ambroise Croizat, 03410 Domerat",
    "sg:city":"Dom\u00e9rat",
    "sg:orig_category":"Unclassifiable Establishments",
    "sg:phone":"+33 4 70 05 31 69",
    "sg:postcode":"03410",
    "sg:province":"Auvergne",
    "wof:name":"Morlans Euroma",
    "wof:placetype":"venue"
},
  "geometry": {"coordinates":[2.574891,46.367432],"type":"Point"}
}