{
  "type": "Feature",
  "properties": {
    "iso:country":"FR",
    "sg:address":"Rd 302 67610 La Wantzenau",
    "sg:city":"La Wantzenau",
    "sg:classifiers":[
        {
            "category":"Shopping",
            "type":"Retail Goods"
        }
    ],
    "sg:phone":"+33 3 90 29 21 92",
    "sg:postcode":"67610",
    "sg:province":"Alsace",
    "sg:tags":[
        "metallurgy",
        "finished",
        "-",
        "metalworking",
        "metallic"
    ],
    "wof:name":"Mbs Signaletique",
    "wof:placetype":"venue"
},
  "geometry": {"coordinates":[7.825742,48.65926],"type":"Point"}
}