{
  "type": "Feature",
  "properties": {
    "iso:country":"FR",
    "sg:address":"14, Chemin du Soleil, 60200 Compi\u00e8gne",
    "sg:orig_category":"Non-Classified Establishments",
    "sg:phone":"+33 3 44 23 04 04",
    "sg:province":"Picardie",
    "wof:name":"Soci\u00e9t\u00e9 Droog S.a.r.l.",
    "wof:placetype":"venue"
},
  "geometry": {"coordinates":[2.817674,49.421043],"type":"Point"}
}