{
  "type": "Feature",
  "properties": {
    "iso:country":"FR",
    "sg:address":"Le Patio 01170 Gex",
    "sg:orig_category":"Non-Classified Establishments",
    "sg:phone":"+33 4 50 41 87 29",
    "sg:postcode":"01170",
    "sg:province":"Rhone-Alpes",
    "wof:name":"Entreprise Bortolli Paul S.a.r.l.",
    "wof:placetype":"venue"
},
  "geometry": {"coordinates":[6.058843,46.331882],"type":"Point"}
}