{
  "type": "Feature",
  "properties": {
    "addr:full":"19 Rue De Nantes 44270 St Etienne De Mer Morte Pays de Loire 44270",
    "addr:housenumber":"19",
    "addr:postcode":"44270;44270",
    "addr:street":"Rue De Nantes;Morte",
    "iso:country":"FR",
    "sg:address":"19 Rue De Nantes 44270 St Etienne De Mer Morte",
    "sg:classifiers":[
        {
            "category":"Wholesale",
            "subcategory":"Farm Supplies",
            "type":"Manufacturing & Wholesale Goods"
        }
    ],
    "sg:phone":"+33 2 40 31 16 39",
    "sg:postcode":"44270",
    "sg:province":"Pays de Loire",
    "sg:tags":[
        "-",
        "machine",
        "equipment",
        "engineering",
        "machinery",
        "mechanical",
        "agriculture"
    ],
    "wof:name":"Ets Jarny Sa",
    "wof:placetype":"venue"
},
  "geometry": {"coordinates":[-1.741524,46.934994],"type":"Point"}
}