{
  "type": "Feature",
  "properties": {
    "iso:country":"FR",
    "sg:address":"53 Rue Danielle Casanova 76410 Tourville La Rivi\u00e8re",
    "sg:classifiers":[
        {
            "category":"Manufacturing",
            "subcategory":"Metals",
            "type":"Manufacturing & Wholesale Goods"
        }
    ],
    "sg:phone":"+33 2 32 96 09 70",
    "sg:postcode":"76410",
    "sg:province":"Haute Normandie",
    "sg:tags":[
        "metallurgy",
        "metalworking",
        "processing"
    ],
    "wof:name":"Cattoire Sa",
    "wof:placetype":"venue"
},
  "geometry": {"coordinates":[1.108,49.326641],"type":"Point"}
}