{
  "type": "Feature",
  "properties": {
    "addr:full":"56, Av. du 11 Novembre 1918 - Les Bureaux du Parc, 69160 Tassin la Demi Lune Rhone-Alpes 69160",
    "addr:postcode":"69160;69160",
    "addr:street":"56 Av. Du 11 Novembre 1918 Les Bureaux Du Parc",
    "iso:country":"FR",
    "sg:address":"56, Av. du 11 Novembre 1918 - Les Bureaux du Parc, 69160 Tassin la Demi Lune",
    "sg:orig_category":"Unclassifiable Establishments",
    "sg:phone":"+33 4 72 59 23 23",
    "sg:postcode":"69160",
    "sg:province":"Rhone-Alpes",
    "wof:name":"Ausy France S.a.",
    "wof:placetype":"venue"
},
  "geometry": {"coordinates":[4.757272,45.764889],"type":"Point"}
}