{
  "type": "Feature",
  "properties": {
    "iso:country":"FR",
    "sg:address":"Rue des Mousserons - ZI Polaris Nord",
    "sg:city":"Chantonnay",
    "sg:orig_category":"Non-Classified Establishments",
    "sg:phone":"+33 2 51 94 38 53",
    "sg:postcode":"85110",
    "sg:province":"Pays de Loire",
    "wof:name":"A.b. Construction M\u00e9tallique S.a.r.l. - Annick Brevet Construction M\u00e9tallique",
    "wof:placetype":"venue"
},
  "geometry": {"coordinates":[-0.963094,46.642857],"type":"Point"}
}