{
  "type": "Feature",
  "properties": {
    "iso:country":"FR",
    "sg:address":"74, Rte d'H\u00e9ricy, 77870 Vulaines sur Seine",
    "sg:orig_category":"Non-Classified Establishments",
    "sg:phone":"+33 1 64 23 90 18",
    "sg:postcode":"77870",
    "sg:province":"Ile de France",
    "wof:name":"A.c.d. France - Assistance Conseils D\u00e9veloppement",
    "wof:placetype":"venue"
},
  "geometry": {"coordinates":[2.755545,48.438965],"type":"Point"}
}