{
  "type": "Feature",
  "properties": {
    "addr:full":"214 Rue De Vieux Berquin 59190 Hazebrouck Nord Pas-de-Calais 59190",
    "addr:housenumber":"214",
    "addr:postcode":"59190;59190",
    "addr:street":"Rue De Vieux Berquin",
    "iso:country":"FR",
    "sg:address":"214 Rue De Vieux Berquin 59190 Hazebrouck",
    "sg:classifiers":[
        {
            "category":"Autos & Motor Vehicles",
            "subcategory":"Automobile Sales",
            "type":"Retail Goods"
        }
    ],
    "sg:phone":"+33 3 28 41 85 89",
    "sg:postcode":"59190",
    "sg:province":"Nord Pas-de-Calais",
    "sg:tags":[
        "equipment",
        "motor-cars",
        "transport"
    ],
    "wof:name":"La Confection Des Housses (lcdh)",
    "wof:placetype":"venue"
},
  "geometry": {"coordinates":[2.551623,50.717754],"type":"Point"}
}