{
  "type": "Feature",
  "properties": {
    "iso:country":"FR",
    "sg:address":"16, Villa de Lourcine, 75014 Paris",
    "sg:orig_category":"Non-Classified Establishments",
    "sg:phone":"+33 1 45 65 33 83",
    "sg:postcode":"75014",
    "sg:province":"Ile de France",
    "wof:name":"Belka Informatique S.a.r.l.",
    "wof:placetype":"venue"
},
  "geometry": {"coordinates":[2.338338,48.83144],"type":"Point"}
}