{
  "type": "Feature",
  "properties": {
    "iso:country":"FR",
    "sg:address":"2, Rue du Commandant Pilot, 92200 Neuilly sur Seine",
    "sg:orig_category":"Non-Classified Establishments",
    "sg:phone":"+33 1 46 24 52 78",
    "sg:province":"Ile de France",
    "wof:name":"S.r.j. S.a.r.l. - Sor\u00e9graph Reprographie Jonor",
    "wof:placetype":"venue"
},
  "geometry": {"coordinates":[2.277484,48.880436],"type":"Point"}
}