{
  "type": "Feature",
  "properties": {
    "addr:full":"73, La Canebi\u00e8re, 13001 Marseille Poitou-Charentes",
    "addr:housenumber":"73",
    "addr:postcode":"13001",
    "addr:street":"La Canebie\u0300Re",
    "iso:country":"FR",
    "sg:address":"73, La Canebi\u00e8re, 13001 Marseille",
    "sg:orig_category":"Non-Classified Establishments",
    "sg:phone":"+33 4 91 91 90 02",
    "sg:province":"Poitou-Charentes",
    "wof:name":"Agence Valadou Protour S.a.",
    "wof:placetype":"venue"
},
  "geometry": {"coordinates":[5.380489,43.297611],"type":"Point"}
}