{
  "type": "Feature",
  "properties": {
    "iso:country":"FR",
    "sg:address":"9 Rue De La Batterie 67118 Geispolsheim",
    "sg:city":"Geispolsheim",
    "sg:classifiers":[
        {
            "category":"Shopping",
            "type":"Retail Goods"
        }
    ],
    "sg:phone":"+33 3 88 55 59 00",
    "sg:postcode":"67400",
    "sg:province":"Alsace",
    "sg:tags":[
        "metallurgy",
        "finished",
        "-",
        "metalworking",
        "metallic"
    ],
    "wof:name":"Le Ressort Industriel",
    "wof:placetype":"venue"
},
  "geometry": {"coordinates":[7.685526,48.537453],"type":"Point"}
}