{
  "type": "Feature",
  "properties": {
    "addr:full":"79 rue Philibert Guide 71100 Chalon Sur Saone Chalon-sur-Sa\u00f4ne Bourgogne 71100",
    "addr:housenumber":"79",
    "addr:postcode":"71100;71100",
    "addr:street":"Rue Philibert Guide",
    "iso:country":"FR",
    "sg:address":"79 rue Philibert Guide 71100 Chalon Sur Saone",
    "sg:city":"Chalon-sur-Sa\u00f4ne",
    "sg:classifiers":[
        {
            "category":"Manufacturing",
            "subcategory":"Motor Vehicles & Parts",
            "type":"Manufacturing & Wholesale Goods"
        }
    ],
    "sg:phone":"+33 3 85 48 15 27",
    "sg:postcode":"71100",
    "sg:province":"Bourgogne",
    "sg:tags":[
        "precision",
        "mechanic"
    ],
    "wof:name":"Ets Andr\u00e9 Chaumont Sa",
    "wof:placetype":"venue"
},
  "geometry": {"coordinates":[4.849557,46.787086],"type":"Point"}
}