{
  "type": "Feature",
  "properties": {
    "addr:full":"1bis, Rue Jangot, 69007 Lyon Rhone-Alpes",
    "addr:housenumber":"1bis",
    "addr:postcode":"69007",
    "addr:street":"Rue Jangot",
    "iso:country":"FR",
    "sg:address":"1bis, Rue Jangot, 69007 Lyon",
    "sg:orig_category":"Non-Classified Establishments",
    "sg:phone":"+33 4 72 73 17 88",
    "sg:province":"Rhone-Alpes",
    "wof:name":"R.s.a. S.a.",
    "wof:placetype":"venue"
},
  "geometry": {"coordinates":[4.841459,45.752411],"type":"Point"}
}