{
  "type": "Feature",
  "properties": {
    "addr:full":"69, rte de Soufflenheim, 67500 Haguenau Haguenau Alsace 67500",
    "addr:housenumber":"69",
    "addr:postcode":"67500;67500",
    "addr:street":"Rte De Soufflenheim",
    "iso:country":"FR",
    "sg:address":"69, rte de Soufflenheim, 67500 Haguenau",
    "sg:city":"Haguenau",
    "sg:orig_category":"Unclassifiable Establishments",
    "sg:phone":"+33 3 88 90 99 90",
    "sg:postcode":"67500",
    "sg:province":"Alsace",
    "wof:name":"Graphequip S.a.r.l.",
    "wof:placetype":"venue"
},
  "geometry": {"coordinates":[7.799644,48.824387],"type":"Point"}
}