{
  "type": "Feature",
  "properties": {
    "addr:full":"1, Rue Paul Langevin - Immeuble Pluton-P\u00f4le 2000, 07130 Saint P\u00e9ray Rhone-Alpes",
    "addr:housenumber":"1;2000",
    "addr:postcode":"07130",
    "addr:street":"Rue Paul Langevin",
    "iso:country":"FR",
    "sg:address":"1, Rue Paul Langevin - Immeuble Pluton-P\u00f4le 2000, 07130 Saint P\u00e9ray",
    "sg:orig_category":"Unclassifiable Establishments",
    "sg:phone":"+33 4 75 81 09 99",
    "sg:province":"Rhone-Alpes",
    "wof:name":"Acacia S.a.",
    "wof:placetype":"venue"
},
  "geometry": {"coordinates":[4.862395,44.938927],"type":"Point"}
}