{
  "type": "Feature",
  "properties": {
    "addr:full":"Rue Louis Bl\u00e9riot Za Maison Neuve 44980 Ste Luce Sur Loire Pays de Loire 44980",
    "addr:postcode":"44980;luce;loire 44980",
    "addr:street":"Rue Louis Ble\u0301Riot Za Maison Neuve",
    "iso:country":"FR",
    "sg:address":"Rue Louis Bl\u00e9riot Za Maison Neuve 44980 Ste Luce Sur Loire",
    "sg:classifiers":[
        {
            "category":"Manufacturing",
            "subcategory":"Glass & Minerals",
            "type":"Manufacturing & Wholesale Goods"
        }
    ],
    "sg:phone":"+33 2 40 25 85 86",
    "sg:postcode":"44980",
    "sg:province":"Pays de Loire",
    "sg:tags":[
        "building",
        "material"
    ],
    "wof:name":"Nouvelle Societe Des Vitrages Isolants Du Val De Loire",
    "wof:placetype":"venue"
},
  "geometry": {"coordinates":[-1.464994,47.271526],"type":"Point"}
}