{
  "type": "Feature",
  "properties": {
    "iso:country":"FR",
    "sg:address":"Rte de Montfort - ZA",
    "sg:city":"Maurepas",
    "sg:orig_category":"Unclassifiable Establishments",
    "sg:phone":"+33 1 30 62 44 22",
    "sg:postcode":"78310",
    "sg:province":"Ile de France",
    "wof:name":"Concept Num\u00e9rique S.a.r.l.",
    "wof:placetype":"venue"
},
  "geometry": {"coordinates":[1.944855,48.761749],"type":"Point"}
}