{
  "type": "Feature",
  "properties": {
    "addr:full":"Rte Des Pap\u00e9teries 38148 Rives Cedex Basse Normandie",
    "addr:postcode":"38148",
    "addr:street":"Rte Des Pape\u0301Teries",
    "iso:country":"FR",
    "sg:address":"Rte Des Pap\u00e9teries 38148 Rives Cedex",
    "sg:classifiers":[
        {
            "category":"Manufacturing",
            "subcategory":"Paper Products",
            "type":"Manufacturing & Wholesale Goods"
        }
    ],
    "sg:phone":"+33 4 76 91 20 20",
    "sg:province":"Basse Normandie",
    "sg:tags":[
        "raw",
        "material",
        "-",
        "cardboard"
    ],
    "wof:name":"Arjo Wiggins Sa",
    "wof:placetype":"venue"
},
  "geometry": {"coordinates":[5.497639,45.344048],"type":"Point"}
}