{
  "type": "Feature",
  "properties": {
    "addr:full":"101 Bd Murat 75016 Paris Ile de France 75016",
    "addr:housenumber":"101",
    "addr:postcode":"75016;75016",
    "addr:street":"Bd Murat",
    "iso:country":"FR",
    "sg:address":"101 Bd Murat 75016 Paris",
    "sg:classifiers":[
        {
            "category":"Professional",
            "subcategory":"Advertising",
            "type":"Services"
        }
    ],
    "sg:phone":"+33 1 53 84 30 00",
    "sg:postcode":"75016",
    "sg:province":"Ile de France",
    "sg:tags":[
        "information",
        "medium",
        "communication"
    ],
    "wof:name":"Reservoir Prod Sa",
    "wof:placetype":"venue"
},
  "geometry": {"coordinates":[2.256558,48.839855],"type":"Point"}
}