{
  "type": "Feature",
  "properties": {
    "iso:country":"FR",
    "sg:address":"B.P. 385, 62205 Boulogne sur Mer C\u00e9dex^^160, Rue des Margats, 62480 Le Portel",
    "sg:orig_category":"Non-Classified Establishments",
    "sg:phone":"+33 3 21 87 11 33",
    "sg:province":"Nord Pas-de-Calais",
    "wof:name":"Norfrigo S.a.",
    "wof:placetype":"venue"
},
  "geometry": {"coordinates":[1.574208,50.706753],"type":"Point"}
}