{
  "type": "Feature",
  "properties": {
    "addr:full":"3, Chemin de Bordeneuve - ZI, 31150 Lespinasse Midi Pyr\u00e9n\u00e9es",
    "addr:housenumber":"3",
    "addr:postcode":"31150",
    "addr:street":"Chemin De Bordeneuve Zi",
    "iso:country":"FR",
    "sg:address":"3, Chemin de Bordeneuve - ZI, 31150 Lespinasse",
    "sg:orig_category":"Unclassifiable Establishments",
    "sg:phone":"+33 5 61 35 50 96",
    "sg:province":"Midi Pyr\u00e9n\u00e9es",
    "wof:name":"Sud Pr\u00e9fac S.a.",
    "wof:placetype":"venue"
},
  "geometry": {"coordinates":[1.411975,43.726673],"type":"Point"}
}