{
  "type": "Feature",
  "properties": {
    "addr:full":"Z Aeronautique Breguet Z Militaire 78140 Velizy Villacoublay Ile de France 78140",
    "addr:postcode":"78140;78140",
    "iso:country":"FR",
    "sg:address":"Z Aeronautique Breguet Z Militaire 78140 Velizy Villacoublay",
    "sg:classifiers":[
        {
            "category":"Banks & Credit Unions",
            "subcategory":"Bureau De Change",
            "type":"Services"
        }
    ],
    "sg:phone":"+33 1 46 29 18 10",
    "sg:postcode":"78140",
    "sg:province":"Ile de France",
    "sg:tags":[
        "brake",
        "systems",
        "mechanical"
    ],
    "wof:name":"Messier-dowty Sa",
    "wof:placetype":"venue"
},
  "geometry": {"coordinates":[2.18246,48.78503],"type":"Point"}
}