{
  "type": "Feature",
  "properties": {
    "iso:country":"FR",
    "sg:address":"Rue des Serves - ZA",
    "sg:city":"Montrevel en Bresse",
    "sg:orig_category":"Unclassifiable Establishments",
    "sg:phone":"+33 4 74 30 81 17",
    "sg:postcode":"01340",
    "sg:province":"Rhone-Alpes",
    "wof:name":"Entreprise Michelard Pierre",
    "wof:placetype":"venue"
},
  "geometry": {"coordinates":[5.13661,46.33744],"type":"Point"}
}