{
  "type": "Feature",
  "properties": {
    "iso:country":"FR",
    "sg:address":"B.P. 30",
    "sg:city":"Saint Livrade^^Monplaisir 47110 Allez et Cazeneuve",
    "sg:orig_category":"Non-Classified Establishments",
    "sg:phone":"+33 5 53 41 25 25",
    "sg:postcode":"47110",
    "sg:province":"Aquitaine",
    "wof:name":"Barb\u00e8s Et Fils S.a.r.l.",
    "wof:placetype":"venue"
},
  "geometry": {"coordinates":[0.588757,44.362614],"type":"Point"}
}