{
  "type": "Feature",
  "properties": {
    "iso:country":"FR",
    "sg:address":"Rue du Lieutenant Colonel Dubois",
    "sg:city":"Rennes",
    "sg:orig_category":"Unclassifiable Establishments",
    "sg:phone":"+33 2 99 59 11 46",
    "sg:postcode":"35000",
    "sg:province":"Bretagne",
    "wof:name":"Chapin S.a.",
    "wof:placetype":"venue"
},
  "geometry": {"coordinates":[-1.734965,48.10688],"type":"Point"}
}