{
  "type": "Feature",
  "properties": {
    "addr:full":"B.P. 1, 86190 Ayron^^ZI les Cartes, 86190 Ayron Poitou-Charentes",
    "addr:housenumber":"1",
    "addr:postcode":"86190;86190",
    "addr:street":"B.P.",
    "iso:country":"FR",
    "sg:address":"B.P. 1, 86190 Ayron^^ZI les Cartes, 86190 Ayron",
    "sg:orig_category":"Non-Classified Establishments",
    "sg:phone":"+33 5 49 60 12 83",
    "sg:province":"Poitou-Charentes",
    "wof:name":"Transports Laurentin S.a.",
    "wof:placetype":"venue"
},
  "geometry": {"coordinates":[0.20983,46.549515],"type":"Point"}
}