{
  "type": "Feature",
  "properties": {
    "addr:full":"10, Rue de l'Avenir - ZI Inova 3000, 88150 Thaon les Vosges Lorraine 88150",
    "addr:housenumber":"10;3000",
    "addr:postcode":"88150;88150",
    "addr:street":"Rue De L'Avenir Zi Inova",
    "iso:country":"FR",
    "sg:address":"10, Rue de l'Avenir - ZI Inova 3000, 88150 Thaon les Vosges",
    "sg:orig_category":"Etudes et fabrications de machines sp\u00e9ciales Montage de sous-ensembles M\u00e9canique de pr\u00e9cision M\u00e9cani",
    "sg:phone":"+33 3 29 39 25 61",
    "sg:postcode":"88150",
    "sg:province":"Lorraine",
    "wof:name":"M\u00e9cavosges S.a.r.l.",
    "wof:placetype":"venue"
},
  "geometry": {"coordinates":[6.402621,48.25367],"type":"Point"}
}