{
  "type": "Feature",
  "properties": {
    "addr:full":"60 rue Jacques Mugnier 68200 Mulhouse Mulhouse Alsace 68200",
    "addr:housenumber":"60",
    "addr:postcode":"68200;68200",
    "addr:street":"Rue Jacques Mugnier",
    "iso:country":"FR",
    "sg:address":"60 rue Jacques Mugnier 68200 Mulhouse",
    "sg:city":"Mulhouse",
    "sg:classifiers":[
        {
            "category":"Industrial Area",
            "type":"Public Place"
        }
    ],
    "sg:phone":"+33 3 89 59 24 30",
    "sg:postcode":"68200",
    "sg:province":"Alsace",
    "sg:tags":[
        "ovens",
        "heated",
        "furnace",
        "electrically"
    ],
    "wof:name":"Abctherm S.a.r.l.",
    "wof:placetype":"venue"
},
  "geometry": {"coordinates":[7.289908,47.729671],"type":"Point"}
}