{
  "type": "Feature",
  "properties": {
    "addr:full":"24 Av D'Aubi\u00e8re 63804 Cournon D'Auvergne Cedex Aubi\u00e8re Auvergne 63170",
    "addr:postcode":"63804;d'auvergne cedex;63170",
    "addr:street":"24 Av D'Aubie \u0300Re",
    "iso:country":"FR",
    "sg:address":"24 Av D'Aubi\u00e8re 63804 Cournon D'Auvergne Cedex",
    "sg:city":"Aubi\u00e8re",
    "sg:classifiers":[
        {
            "category":"Shopping",
            "subcategory":"Pharmacy",
            "type":"Retail Goods"
        }
    ],
    "sg:phone":"+33 4 73 84 21 84",
    "sg:postcode":"63170",
    "sg:province":"Auvergne",
    "sg:tags":[
        "chemical",
        "pharmaceutical",
        "chemistry"
    ],
    "wof:name":"Ferlux Sa",
    "wof:placetype":"venue"
},
  "geometry": {"coordinates":[3.19657,45.742359],"type":"Point"}
}