{
  "type": "Feature",
  "properties": {
    "addr:full":"Za Est Ld Grube 67730 Chatenois Ch\u00e2tenois Alsace 67730",
    "addr:postcode":"67730;67730",
    "addr:street":"Za Est",
    "iso:country":"FR",
    "sg:address":"Za Est Ld Grube 67730 Chatenois",
    "sg:city":"Ch\u00e2tenois",
    "sg:classifiers":[
        {
            "category":"Professional",
            "type":"Services"
        }
    ],
    "sg:phone":"+33 3 88 92 00 27",
    "sg:postcode":"67730",
    "sg:province":"Alsace",
    "sg:tags":[
        "transport",
        "road"
    ],
    "wof:name":"Transports Herbrich Sa",
    "wof:placetype":"venue"
},
  "geometry": {"coordinates":[7.399195,48.271835],"type":"Point"}
}