{
  "type": "Feature",
  "properties": {
    "addr:full":"14 rue Victor Hugo; Boulogne sur Mer; 62200 Nord Pas-de-Calais 62200",
    "addr:housenumber":"14",
    "addr:postcode":"62200;62200",
    "addr:street":"Rue Victor Hugo;Mer",
    "iso:country":"FR",
    "sg:address":"14 rue Victor Hugo; Boulogne sur Mer; 62200",
    "sg:classifiers":[
        {
            "category":"Banks & Credit Unions",
            "subcategory":"Bank",
            "type":"Services"
        }
    ],
    "sg:phone":"+33 21300733",
    "sg:postcode":"62200",
    "sg:province":"Nord Pas-de-Calais",
    "wof:name":"Banque Nationale De Paris",
    "wof:placetype":"venue"
},
  "geometry": {"coordinates":[1.604986,50.723286],"type":"Point"}
}