{
  "type": "Feature",
  "properties": {
    "iso:country":"FR",
    "sg:address":"110 Rte de Saint-Leu; Villetaneuse; 93430",
    "sg:classifiers":[
        {
            "category":"Banks & Credit Unions",
            "subcategory":"Bank",
            "type":"Services"
        }
    ],
    "sg:phone":"+33 18216119",
    "sg:postcode":"93430",
    "sg:province":"Ile de France",
    "wof:name":"Banque Nationale De Paris",
    "wof:placetype":"venue"
},
  "geometry": {"coordinates":[2.334907,48.954414],"type":"Point"}
}