{
  "type": "Feature",
  "properties": {
    "iso:country":"FR",
    "sg:address":"12, Chemin des Hauts de Claire Fontaine, 78580 Maule",
    "sg:orig_category":"Non-Classified Establishments",
    "sg:phone":"+33 1 34 75 13 65",
    "sg:province":"Ile de France",
    "wof:name":"Excem S.a.",
    "wof:placetype":"venue"
},
  "geometry": {"coordinates":[1.853816,48.918758],"type":"Point"}
}