{
  "type": "Feature",
  "properties": {
    "iso:country":"FR",
    "sg:address":"8 rue Auber; Paris; 75009",
    "sg:classifiers":[
        {
            "category":"Banks & Credit Unions",
            "subcategory":"Bank",
            "type":"Services"
        }
    ],
    "sg:phone":"+33 14744948437",
    "sg:postcode":"75009",
    "sg:province":"Ile de France",
    "wof:name":"Banque Francaise Commerciale, Ocean Indien Bfc",
    "wof:placetype":"venue"
},
  "geometry": {"coordinates":[2.329494,48.872562],"type":"Point"}
}