{
  "type": "Feature",
  "properties": {
    "iso:country":"FR",
    "sg:address":"Rte de M\u00e2con - Le Peleux",
    "sg:city":"Montmerle sur Sa\u00f4ne",
    "sg:orig_category":"Unclassifiable Establishments",
    "sg:phone":"+33 4 74 69 66 40",
    "sg:postcode":"01090",
    "sg:province":"Rhone-Alpes",
    "wof:name":"Les Fils De Beno\u00eet Diennet Charcuterie Salaison S.a.",
    "wof:placetype":"venue"
},
  "geometry": {"coordinates":[4.77954,46.093819],"type":"Point"}
}