{
  "type": "Feature",
  "properties": {
    "iso:country":"FR",
    "sg:address":"117, Rue de la Lib\u00e9ration, 27140 Gisors",
    "sg:orig_category":"Unclassifiable Establishments",
    "sg:phone":"+33 2 32 55 26 39",
    "sg:province":"Haute Normandie",
    "wof:name":"Eurofeu S.a.",
    "wof:placetype":"venue"
},
  "geometry": {"coordinates":[1.78246,49.26931],"type":"Point"}
}