{
  "type": "Feature",
  "properties": {
    "iso:country":"FR",
    "sg:address":"14, Av. de l'Etang, 84000 Avignon",
    "sg:orig_category":"Non-Classified Establishments",
    "sg:phone":"+33 4 90 21 41 60",
    "wof:name":"Sami S.a.",
    "wof:placetype":"venue"
},
  "geometry": {"coordinates":[4.852292,43.934158],"type":"Point"}
}