{
  "type": "Feature",
  "properties": {
    "addr:full":"15, Rue de la Coupote, 25410 Saint Vit Franche Comt\u00e9 25410",
    "addr:housenumber":"15",
    "addr:postcode":"25410;25410",
    "addr:street":"Rue De La Coupote;Franche Comte\u0301",
    "iso:country":"FR",
    "sg:address":"15, Rue de la Coupote, 25410 Saint Vit",
    "sg:orig_category":"Non-Classified Establishments",
    "sg:phone":"+33 3 81 87 55 52",
    "sg:postcode":"25410",
    "sg:province":"Franche Comt\u00e9",
    "wof:name":"Ebim S.a.r.l.",
    "wof:placetype":"venue"
},
  "geometry": {"coordinates":[5.803341,47.184017],"type":"Point"}
}