{
  "type": "Feature",
  "properties": {
    "addr:full":"384 Rue D'Alger 59100 Roubaix Nord Pas-de-Calais",
    "addr:housenumber":"384",
    "addr:postcode":"59100",
    "addr:street":"Rue D'Alger",
    "iso:country":"FR",
    "sg:address":"384 Rue D'Alger 59100 Roubaix",
    "sg:classifiers":[
        {
            "category":"Manufacturing",
            "subcategory":"Rubber & Plastics",
            "type":"Manufacturing & Wholesale Goods"
        }
    ],
    "sg:phone":"+33 3 20 11 36 00",
    "sg:province":"Nord Pas-de-Calais",
    "wof:name":"Pennel Et Flipo Sa",
    "wof:placetype":"venue"
},
  "geometry": {"coordinates":[3.195265,50.696369],"type":"Point"}
}