{
  "type": "Feature",
  "properties": {
    "iso:country":"FR",
    "sg:address":"B.P. 13",
    "sg:city":"Argent sur Sauldre^^Les Vallots 18410 Argent sur Sauldre",
    "sg:orig_category":"Non-Classified Establishments",
    "sg:phone":"+33 2 48 73 33 07",
    "sg:postcode":"18410",
    "sg:province":"Centre",
    "wof:name":"Roby S.a.r.l.",
    "wof:placetype":"venue"
},
  "geometry": {"coordinates":[2.52848,47.532764],"type":"Point"}
}