{
  "type": "Feature",
  "properties": {
    "addr:full":"1, Rue Max Wallet, 66160 Le Boulou Languedoc-Roussillon",
    "addr:housenumber":"1",
    "addr:postcode":"66160",
    "addr:street":"Rue Max",
    "iso:country":"FR",
    "sg:address":"1, Rue Max Wallet, 66160 Le Boulou",
    "sg:orig_category":"Non-Classified Establishments",
    "sg:phone":"+33 4 68 87 25 19",
    "sg:province":"Languedoc-Roussillon",
    "wof:name":"M\u00e9ta France S.a.r.l.",
    "wof:placetype":"venue"
},
  "geometry": {"coordinates":[2.833081,42.522469],"type":"Point"}
}