{
  "type": "Feature",
  "properties": {
    "iso:country":"FR",
    "sg:address":"Av De Beaupr\u00e9 BP 79 59481 Haubourdin",
    "sg:classifiers":[
        {
            "category":"Professional",
            "subcategory":"Business Services",
            "type":"Services"
        }
    ],
    "sg:phone":"+33 3 20 07 22 55",
    "sg:province":"Centre",
    "sg:tags":[
        "training",
        "advice"
    ],
    "wof:name":"Lycee General Et Technologique",
    "wof:placetype":"venue"
},
  "geometry": {"coordinates":[2.991445,50.602474],"type":"Point"}
}