{
  "type": "Feature",
  "properties": {
    "iso:country":"FR",
    "sg:address":"29 Rue Larmodieu 83000 Toulon",
    "sg:orig_category":"Miscellaneous Products",
    "sg:phone":"+33 4 94 89 13 07",
    "sg:province":"Rhone-Alpes",
    "wof:name":"L'art Graphique",
    "wof:placetype":"venue"
},
  "geometry": {"coordinates":[5.930883,43.123257],"type":"Point"}
}