{
  "type": "Feature",
  "properties": {
    "addr:full":"2 Rue De La Butte Aux Cailles 75013 Paris Ile de France 75013",
    "addr:housenumber":"2",
    "addr:postcode":"75013;75013",
    "addr:street":"Rue De La Butte Aux Cailles",
    "iso:country":"FR",
    "sg:address":"2 Rue De La Butte Aux Cailles 75013 Paris",
    "sg:classifiers":[
        {
            "category":"Bakery",
            "type":"Food & Drink"
        }
    ],
    "sg:phone":"+33 1 45 80 58 39",
    "sg:postcode":"75013",
    "sg:province":"Ile de France",
    "sg:tags":[
        "cake",
        "product",
        "related",
        "bread"
    ],
    "wof:name":"Sarl Couzigou",
    "wof:placetype":"venue"
},
  "geometry": {"coordinates":[2.352533,48.828194],"type":"Point"}
}