{
  "type": "Feature",
  "properties": {
    "iso:country":"FR",
    "sg:address":"13, Rue du Bain aux Plantes, 67000 Strasbourg",
    "sg:city":"Strasbourg",
    "sg:orig_category":"Non-Classified Establishments",
    "sg:phone":"+33 3 88 66 04 98",
    "sg:postcode":"67000",
    "sg:province":"Alsace",
    "wof:name":"Formes Structures Et Communication S.a.",
    "wof:placetype":"venue"
},
  "geometry": {"coordinates":[7.740084,48.581596],"type":"Point"}
}