{
  "type": "Feature",
  "properties": {
    "addr:full":"6, Rue de la Source - Le Verger , 95650 Courcelles sur Viosne Ile de France",
    "addr:housenumber":"6",
    "addr:postcode":"95650",
    "addr:street":"Rue De La Source Le Verger",
    "iso:country":"FR",
    "sg:address":"6, Rue de la Source - Le Verger , 95650 Courcelles sur Viosne",
    "sg:orig_category":"Non-Classified Establishments",
    "sg:phone":"+33 1 34 42 18 78",
    "sg:province":"Ile de France",
    "wof:name":"N.b. Et Partner's S.a.r.l.",
    "wof:placetype":"venue"
},
  "geometry": {"coordinates":[2.029391,49.076973],"type":"Point"}
}