{
  "type": "Feature",
  "properties": {
    "iso:country":"FR",
    "sg:address":"182, Quai Georges V, 76085 Le Havre C\u00e9dex",
    "sg:city":"Le Havre",
    "sg:orig_category":"Non-Classified Establishments",
    "sg:phone":"+33 2 35 19 25 54",
    "sg:postcode":"76600",
    "sg:province":"Haute Normandie",
    "wof:name":"So.get. S.a. - Soci\u00e9t\u00e9 De Gestion De Terminaux Informatiques",
    "wof:placetype":"venue"
},
  "geometry": {"coordinates":[0.13231,49.498619],"type":"Point"}
}