{
  "type": "Feature",
  "properties": {
    "iso:country":"FR",
    "sg:address":"Zac La Mine D'Or 79170 Brioux Sur Boutonne",
    "sg:classifiers":[
        {
            "category":"Bakery",
            "type":"Food & Drink"
        }
    ],
    "sg:phone":"+33 5 49 07 15 82",
    "sg:postcode":"79170",
    "sg:province":"Poitou-Charentes",
    "sg:tags":[
        "cake",
        "product",
        "related",
        "bread"
    ],
    "wof:name":"Baillon Et Cie Sarl",
    "wof:placetype":"venue"
},
  "geometry": {"coordinates":[-0.21823,46.14349],"type":"Point"}
}