{
  "type": "Feature",
  "properties": {
    "addr:full":"8 Louis Braille 69100 Villeurbanne Rhone-Alpes 69100",
    "addr:housenumber":"8",
    "addr:postcode":"69100;69100",
    "addr:street":"Louis Braille",
    "iso:country":"FR",
    "sg:address":"8",
    "sg:city":"Louis Braille 69100 Villeurbanne",
    "sg:classifiers":[
        {
            "category":"Manufacturing",
            "subcategory":"Wood Products",
            "type":"Manufacturing & Wholesale Goods"
        }
    ],
    "sg:phone":"+33 4 78 84 43 72",
    "sg:postcode":"69100",
    "sg:province":"Rhone-Alpes",
    "sg:tags":[
        "professional",
        "furniture"
    ],
    "wof:name":"Decograph (sarl)",
    "wof:placetype":"venue"
},
  "geometry": {"coordinates":[4.88185,45.76104],"type":"Point"}
}