{
  "type": "Feature",
  "properties": {
    "addr:full":"18-22 rue Rampal 75019 Paris Ile de France 75019",
    "addr:housenumber":"18-22",
    "addr:postcode":"75019;75019",
    "addr:street":"Rue Rampal",
    "iso:country":"FR",
    "sg:address":"18-22 rue Rampal 75019 Paris",
    "sg:orig_category":"Ladies' Trousers Suits, Suits, Jackets, Skirts, And Trousers",
    "sg:phone":"+33 1 53 38 00 00",
    "sg:postcode":"75019",
    "sg:province":"Ile de France",
    "wof:name":"Ned Sa",
    "wof:placetype":"venue"
},
  "geometry": {"coordinates":[2.379845,48.874237],"type":"Point"}
}