{
  "type": "Feature",
  "properties": {
    "iso:country":"FR",
    "sg:address":"83, Rue Youri Gagarine, 92700 Colombes",
    "sg:orig_category":"Non-Classified Establishments",
    "sg:phone":"+33 1 41 19 05 21",
    "sg:postcode":"92700",
    "sg:province":"Ile de France",
    "wof:name":"Bena\u00efssa Benmouna Zahra S.a.r.l.",
    "wof:placetype":"venue"
},
  "geometry": {"coordinates":[2.241592,48.924824],"type":"Point"}
}