{
  "type": "Feature",
  "properties": {
    "addr:full":"83, Rue Youri Gagarine, 92700 Colombes Ile de France 92700",
    "addr:housenumber":"83",
    "addr:postcode":"92700;ile;92700",
    "addr:street":"Rue Youri Gagarine;France",
    "iso:country":"FR",
    "sg:address":"83, Rue Youri Gagarine, 92700 Colombes",
    "sg:orig_category":"Non-Classified Establishments",
    "sg:phone":"+33 1 41 19 05 21",
    "sg:postcode":"92700",
    "sg:province":"Ile de France",
    "wof:name":"Bena\u00efssa Benmouna Zahra S.a.r.l.",
    "wof:placetype":"venue"
},
  "geometry": {"coordinates":[2.241592,48.924824],"type":"Point"}
}