{
  "type": "Feature",
  "properties": {
    "addr:full":"63 rue Victor Hugo 94700 Maisons Alfort Ile de France",
    "addr:housenumber":"63",
    "addr:postcode":"94700",
    "addr:street":"Rue Victor Hugo",
    "iso:country":"FR",
    "sg:address":"63 rue Victor Hugo 94700 Maisons Alfort",
    "sg:classifiers":[
        {
            "category":"Manufacturing",
            "subcategory":"Rubber & Plastics",
            "type":"Manufacturing & Wholesale Goods"
        }
    ],
    "sg:phone":"+33 1 60 62 58 88",
    "sg:province":"Ile de France",
    "sg:tags":[
        "processing"
    ],
    "wof:name":"S.i.o.m. Plastique Sa",
    "wof:placetype":"venue"
},
  "geometry": {"coordinates":[2.439321,48.799854],"type":"Point"}
}