{
  "type": "Feature",
  "properties": {
    "addr:full":"B.P. 46 Quillan C\u00e9dex^^Usine de la Plaine 11500 Quillan Languedoc-Roussillon 11500",
    "addr:postcode":"11500;11500",
    "addr:street":"B.P. 46;La Plaine",
    "iso:country":"FR",
    "sg:address":"B.P. 46",
    "sg:city":"Quillan C\u00e9dex^^Usine de la Plaine 11500 Quillan",
    "sg:orig_category":"Non-Classified Establishments",
    "sg:phone":"+33 4 68 20 18 30",
    "sg:postcode":"11500",
    "sg:province":"Languedoc-Roussillon",
    "wof:name":"Formica S.a.",
    "wof:placetype":"venue"
},
  "geometry": {"coordinates":[2.182374,42.87534],"type":"Point"}
}