{
  "type": "Feature",
  "properties": {
    "iso:country":"FR",
    "sg:address":"B.P. 2003, 52901 Chaumont C\u00e9dex 9^^ZA Neuilly sur Suize, 52901 Chaumont",
    "sg:orig_category":"Non-Classified Establishments",
    "sg:phone":"+33 3 25 03 09 16",
    "sg:province":"Champagne-Ardenne",
    "wof:name":"F\u00e8vre Eric S.a.r.l.",
    "wof:placetype":"venue"
},
  "geometry": {"coordinates":[5.1435,48.104141],"type":"Point"}
}