{
  "type": "Feature",
  "properties": {
    "addr:full":"36160 Pouligny Notre Dame Champillet Centre 36160",
    "addr:postcode":"36160;36160",
    "iso:country":"FR",
    "sg:address":"36160 Pouligny Notre Dame",
    "sg:city":"Champillet",
    "sg:orig_category":"Non-Classified Establishments",
    "sg:phone":"+33 2 54 06 60 60",
    "sg:postcode":"36160",
    "sg:province":"Centre",
    "wof:name":"R\u00e9sidence Du Golf Des Dryades Pays De Georges Sand S.a.",
    "wof:placetype":"venue"
},
  "geometry": {"coordinates":[2.011597,46.488564],"type":"Point"}
}