{
  "type": "Feature",
  "properties": {
    "addr:full":"ZI Grands Marais - Garosud Cr\u00e9teil Ile de France 94000",
    "addr:postcode":"94000",
    "addr:street":"Zi",
    "iso:country":"FR",
    "sg:address":"ZI Grands Marais - Garosud",
    "sg:city":"Cr\u00e9teil",
    "sg:orig_category":"Unclassifiable Establishments",
    "sg:phone":"+33 1 43 53 24 24",
    "sg:postcode":"94000",
    "sg:province":"Ile de France",
    "wof:name":"Locamion S.a.",
    "wof:placetype":"venue"
},
  "geometry": {"coordinates":[2.455115,48.777866],"type":"Point"}
}