{
  "type": "Feature",
  "properties": {
    "addr:full":"Route de la Gare 07210 CHOMERAC Rhone-Alpes 07210",
    "addr:postcode":"07210;07210",
    "addr:street":"Route De La Gare;Rhone-Alpes",
    "iso:country":"FR",
    "sg:address":"Route de la Gare 07210 CHOMERAC",
    "sg:classifiers":[
        {
            "category":"Professional",
            "subcategory":"Business Services",
            "type":"Services"
        }
    ],
    "sg:phone":"+33 4 75 66 76 76",
    "sg:postcode":"07210",
    "sg:province":"Rhone-Alpes",
    "sg:tags":[
        "high-precision",
        "mechanic"
    ],
    "wof:name":"Ets Suchier Sa",
    "wof:placetype":"venue"
},
  "geometry": {"coordinates":[4.661515,44.706367],"type":"Point"}
}