{
  "type": "Feature",
  "properties": {
    "addr:full":"17/21, Rue Saint Mathieu - ZI, 78550 Houdan Ile de France",
    "addr:housenumber":"17 / 21",
    "addr:postcode":"78550;ile",
    "addr:street":"Rue Saint Mathieu Zi",
    "iso:country":"FR",
    "sg:address":"17/21, Rue Saint Mathieu - ZI, 78550 Houdan",
    "sg:orig_category":"Unclassifiable Establishments",
    "sg:phone":"+33 1 30 88 17 20",
    "sg:province":"Ile de France",
    "wof:name":"Laboratoires Ethypharm S.a.",
    "wof:placetype":"venue"
},
  "geometry": {"coordinates":[1.60191,48.788956],"type":"Point"}
}