{
  "type": "Feature",
  "properties": {
    "iso:country":"FR",
    "sg:address":"Rue Pierre Berthier - P.A. les Milles - Domaine Saint Hilaire",
    "sg:city":"Aix en Provence",
    "sg:orig_category":"Unclassifiable Establishments",
    "sg:phone":"+33 4 42 97 62 97",
    "sg:postcode":"13790",
    "sg:province":"Champagne",
    "wof:name":"S.e.p. Industrie S.a.r.l.",
    "wof:placetype":"venue"
},
  "geometry": {"coordinates":[5.439156,43.509697],"type":"Point"}
}