{
  "type": "Feature",
  "properties": {
    "addr:full":"Rue du Santerre - Zone Industrielle d'Amiens Amiens Picardie 80000",
    "addr:postcode":"80000",
    "addr:street":"Rue Du Santerre;Industrielle D'Amiens",
    "iso:country":"FR",
    "sg:address":"Rue du Santerre - Zone Industrielle d'Amiens",
    "sg:city":"Amiens",
    "sg:orig_category":"Unclassifiable Establishments",
    "sg:phone":"+33 3 22 54 63 80",
    "sg:postcode":"80000",
    "sg:province":"Picardie",
    "wof:name":"Friedlander S.a.",
    "wof:placetype":"venue"
},
  "geometry": {"coordinates":[2.318592,49.8689],"type":"Point"}
}