{
  "type": "Feature",
  "properties": {
    "addr:full":"41 Rue Joachim Du Bellay 49122 Le May Sur Evre Pays de Loire 49122",
    "addr:housenumber":"41",
    "addr:postcode":"49122;49122",
    "addr:street":"Rue Joachim Du Bellay;May;Evre",
    "iso:country":"FR",
    "sg:address":"41 Rue Joachim Du Bellay 49122 Le May Sur Evre",
    "sg:classifiers":[
        {
            "category":"Shopping",
            "subcategory":"Luggage & Leather Goods",
            "type":"Retail Goods"
        }
    ],
    "sg:phone":"+33 2 41 75 61 80",
    "sg:postcode":"49122",
    "sg:province":"Pays de Loire",
    "sg:tags":[
        "shoe"
    ],
    "wof:name":"Chupin Penot Sa",
    "wof:placetype":"venue"
},
  "geometry": {"coordinates":[-0.892274,47.134209],"type":"Point"}
}