{
  "type": "Feature",
  "properties": {
    "iso:country":"FR",
    "sg:address":"B.P. 326",
    "sg:city":"La Forest Landerneau^^Aux Quatre Vents 29820 La Forest Landerneau",
    "sg:orig_category":"Non-Classified Establishments",
    "sg:phone":"+33 2 98 20 20 33",
    "sg:postcode":"29413",
    "sg:province":"Bretagne",
    "wof:name":"Sobredim S.a.",
    "wof:placetype":"venue"
},
  "geometry": {"coordinates":[-79.931602,32.781151],"type":"Point"}
}