{
  "type": "Feature",
  "properties": {
    "iso:country":"FR",
    "sg:address":"Zi De St Didier 01140 Thoissey",
    "sg:classifiers":[
        {
            "category":"Farming",
            "subcategory":"Fish & Marine Products",
            "type":"Manufacturing & Wholesale Goods"
        }
    ],
    "sg:phone":"+33 4 74 69 71 98",
    "sg:postcode":"01140",
    "sg:province":"Rhone-Alpes",
    "sg:tags":[
        "horticulture",
        "miscellaneous"
    ],
    "wof:name":"Fermob",
    "wof:placetype":"venue"
},
  "geometry": {"coordinates":[4.80302,46.172539],"type":"Point"}
}