{
  "type": "Feature",
  "properties": {
    "addr:full":"Za De La Lande 49360 Toutlemonde Pays de Loire 49360",
    "addr:postcode":"49360;49360",
    "addr:street":"Za De La Lande",
    "iso:country":"FR",
    "sg:address":"Za De La Lande 49360 Toutlemonde",
    "sg:classifiers":[
        {
            "category":"Professional",
            "subcategory":"Business Services",
            "type":"Services"
        }
    ],
    "sg:phone":"+33 2 41 55 53 91",
    "sg:postcode":"49360",
    "sg:province":"Pays de Loire",
    "sg:tags":[
        "advice",
        "clothes"
    ],
    "wof:name":"Lecarpentier Ste Pret A Porter",
    "wof:placetype":"venue"
},
  "geometry": {"coordinates":[-0.765859,47.054905],"type":"Point"}
}