{
  "type": "Feature",
  "properties": {
    "addr:full":"52 R Eug\u00e8ne Beaune 42000 St \u00c9tienne Rhone-Alpes 42000",
    "addr:housenumber":"52",
    "addr:postcode":"42000;42000",
    "addr:street":"R Euge\u0300Ne Beaune;Rhone-Alpes",
    "iso:country":"FR",
    "sg:address":"52 R Eug\u00e8ne Beaune 42000 St \u00c9tienne",
    "sg:classifiers":[
        {
            "category":"Professional",
            "subcategory":"Engineering",
            "type":"Services"
        }
    ],
    "sg:phone":"+33 4 77 38 74 15",
    "sg:postcode":"42000",
    "sg:province":"Rhone-Alpes",
    "sg:tags":[
        "machine",
        "-",
        "mechanical"
    ],
    "wof:name":"Constructions Mecaniques Et Medicales",
    "wof:placetype":"venue"
},
  "geometry": {"coordinates":[4.402774,45.454422],"type":"Point"}
}