{
  "type": "Feature",
  "properties": {
    "iso:country":"FR",
    "sg:address":"B.P. 28, 86281 Saint Beno\u00eet C\u00e9dex^^90, Av. des Hauts de Chaume, 86280 Saint Beno\u00eet",
    "sg:orig_category":"Non-Classified Establishments",
    "sg:phone":"+33 5 49 57 04 04",
    "sg:postcode":"86280",
    "sg:province":"Poitou-Charentes",
    "wof:name":"Cephac Europe S.a.",
    "wof:placetype":"venue"
},
  "geometry": {"coordinates":[0.333858,46.552601],"type":"Point"}
}