{
  "type": "Feature",
  "properties": {
    "addr:full":"2 Chem De La Milli\u00e8re A St Menet 13396 Marseille Cedex 11 Provence-Alpes-C\u00f4te d'Azur",
    "addr:housenumber":"2",
    "addr:postcode":"13396;11",
    "addr:street":"Chem De La Millie\u0300Re A St",
    "iso:country":"FR",
    "sg:address":"2 Chem De La Milli\u00e8re A St Menet 13396 Marseille Cedex 11",
    "sg:classifiers":[
        {
            "category":"Utilities",
            "subcategory":"Telephone",
            "type":"Services"
        }
    ],
    "sg:phone":"+33 4 91 18 57 00",
    "sg:province":"Provence-Alpes-C\u00f4te d'Azur",
    "sg:tags":[
        "telecommunication"
    ],
    "wof:name":"Tenovis Sas",
    "wof:placetype":"venue"
},
  "geometry": {"coordinates":[5.50389,43.292229],"type":"Point"}
}