{
  "type": "Feature",
  "properties": {
    "addr:full":"c\u00f4te de l'Eglise 27550 Nassandres Haute Normandie 27550",
    "addr:postcode":"27550;27550",
    "addr:street":"Co\u0302Te De L'Eglise;Haute Normandie",
    "iso:country":"FR",
    "sg:address":"c\u00f4te de l'Eglise 27550 Nassandres",
    "sg:orig_category":"Bakers' And Cooks' Uniforms",
    "sg:phone":"+33 2 32 44 80 83",
    "sg:postcode":"27550",
    "sg:province":"Haute Normandie",
    "wof:name":"Cochet Pere Et Fils S.a.r.l.",
    "wof:placetype":"venue"
},
  "geometry": {"coordinates":[0.737053,49.124107],"type":"Point"}
}