{
  "type": "Feature",
  "properties": {
    "iso:country":"FR",
    "sg:address":"24, Chemin du Pontet, 69380 Civrieux d'Azergues",
    "sg:orig_category":"Unclassifiable Establishments",
    "sg:phone":"+33 4 78 43 12 75",
    "sg:postcode":"69380",
    "sg:province":"Rhone-Alpes",
    "wof:name":"All Tec S.a.r.l.",
    "wof:placetype":"venue"
},
  "geometry": {"coordinates":[4.705944,45.858753],"type":"Point"}
}