{
  "type": "Feature",
  "properties": {
    "iso:country":"FR",
    "sg:address":"2 Av Des Thermes 04000 Digne Les Bains",
    "sg:classifiers":[
        {
            "category":"Professional",
            "subcategory":"Business Services",
            "type":"Services"
        }
    ],
    "sg:phone":"+33 4 92 30 58 60",
    "sg:province":"Auvergne",
    "sg:tags":[
        "training",
        "advice"
    ],
    "wof:name":"Ogec Sacre Coeur",
    "wof:placetype":"venue"
},
  "geometry": {"coordinates":[6.241421,44.091343],"type":"Point"}
}