{
  "type": "Feature",
  "properties": {
    "addr:full":"23 Rue R\u00e9oule 32500 Fleurance Midi Pyr\u00e9n\u00e9es",
    "addr:housenumber":"23",
    "addr:postcode":"32500",
    "addr:street":"Rue Re\u0301Oule",
    "iso:country":"FR",
    "sg:address":"23 Rue R\u00e9oule 32500 Fleurance",
    "sg:classifiers":[
        {
            "category":"Professional",
            "type":"Services"
        }
    ],
    "sg:phone":"+33 5 62 06 11 63",
    "sg:province":"Midi Pyr\u00e9n\u00e9es",
    "sg:tags":[
        "transport",
        "road"
    ],
    "wof:name":"Lou Rey Et Fils Sarl",
    "wof:placetype":"venue"
},
  "geometry": {"coordinates":[0.657814,43.846634],"type":"Point"}
}