{
  "type": "Feature",
  "properties": {
    "iso:country":"FR",
    "sg:address":"B.P. 226, 51361 Vitry le Fran\u00e7ois C\u00e9dex^^Rue du Moulin, 51300 Vavray le Grand",
    "sg:orig_category":"Non-Classified Establishments",
    "sg:phone":"+33 3 26 73 95 02",
    "sg:province":"Champagne",
    "wof:name":"Gibeaux S.a.",
    "wof:placetype":"venue"
},
  "geometry": {"coordinates":[4.563456,48.648991],"type":"Point"}
}