{
  "type": "Feature",
  "properties": {
    "iso:country":"FR",
    "sg:address":"10, Av. de l'Entreprise - Parc Saint Christophe, 95865 Cergy C\u00e9dex",
    "sg:orig_category":"Non-Classified Establishments",
    "sg:phone":"+33 1 34 24 40 58",
    "sg:province":"\u00cele-de-France",
    "wof:name":"S.o.f.r.e.t.e.n. S.a. - Soci\u00e9t\u00e9 Fran\u00e7aise D'etudes Et D'ingineering",
    "wof:placetype":"venue"
},
  "geometry": {"coordinates":[2.09101,49.035709],"type":"Point"}
}