{
  "type": "Feature",
  "properties": {
    "addr:full":"18-20 Av Du Garigliano 91602 Savigny Sur Orge Cedex Ile de France",
    "addr:housenumber":"18-20",
    "addr:postcode":"91602;ile",
    "addr:street":"Av Du Garigliano",
    "iso:country":"FR",
    "sg:address":"18-20 Av Du Garigliano 91602 Savigny Sur Orge Cedex",
    "sg:classifiers":[
        {
            "category":"Manufacturing",
            "subcategory":"Glass & Minerals",
            "type":"Manufacturing & Wholesale Goods"
        }
    ],
    "sg:phone":"+33 1 69 21 61 62",
    "sg:province":"Ile de France",
    "sg:tags":[
        "building",
        "material"
    ],
    "wof:name":"Miroiterie Spp",
    "wof:placetype":"venue"
},
  "geometry": {"coordinates":[2.334793,48.693066],"type":"Point"}
}