{
  "type": "Feature",
  "properties": {
    "addr:full":"3 Rue De La Renaissance 92184 Antony Cedex Aquitaine",
    "addr:housenumber":"3",
    "addr:postcode":"92184",
    "addr:street":"Rue De La Renaissance",
    "iso:country":"FR",
    "sg:address":"3 Rue De La Renaissance 92184 Antony Cedex",
    "sg:orig_category":"Information Technology Peripherals - information technology Precision Equipment",
    "sg:phone":"+33 1 40 96 52 00",
    "sg:province":"Aquitaine",
    "wof:name":"Symbol Technologies Sa",
    "wof:placetype":"venue"
},
  "geometry": {"coordinates":[2.29984,48.760883],"type":"Point"}
}