{
  "type": "Feature",
  "properties": {
    "addr:full":"Col de Fontailles Saint F\u00e9licien Rhone-Alpes 07410",
    "addr:postcode":"07410",
    "addr:street":"Col De Fontailles Saint Fe\u0301Licien Rhone-Alpes",
    "iso:country":"FR",
    "sg:address":"Col de Fontailles",
    "sg:city":"Saint F\u00e9licien",
    "sg:orig_category":"Unclassifiable Establishments",
    "sg:phone":"+33 4 75 06 05 78",
    "sg:postcode":"07410",
    "sg:province":"Rhone-Alpes",
    "wof:name":"Besnier Saint F\u00e9licien S.n.c.",
    "wof:placetype":"venue"
},
  "geometry": {"coordinates":[4.646977,45.096672],"type":"Point"}
}