{
  "type": "Feature",
  "properties": {
    "iso:country":"FR",
    "sg:address":"5, Rue d'Ernemont, 76000 Rouen",
    "sg:orig_category":"Non-Classified Establishments",
    "sg:phone":"+33 2 35 15 43 15",
    "sg:postcode":"76000",
    "sg:province":"Haute Normandie",
    "wof:name":"Biplan S.a.r.l.",
    "wof:placetype":"venue"
},
  "geometry": {"coordinates":[1.103198,49.451698],"type":"Point"}
}