{
  "type": "Feature",
  "properties": {
    "addr:full":"230, Rue de la Pr\u00e9cision - ZI les Pr\u00e9s Paris, 74970 Marignier Rhone-Alpes 74970",
    "addr:housenumber":"230",
    "addr:postcode":"74970;74970",
    "addr:street":"Rue De La Pre\u0301Cision Zi Les Pre\u0301S;Rhone-Alpes",
    "iso:country":"FR",
    "sg:address":"230, Rue de la Pr\u00e9cision - ZI les Pr\u00e9s Paris, 74970 Marignier",
    "sg:orig_category":"Unclassifiable Establishments",
    "sg:phone":"+33 4 50 34 58 04",
    "sg:postcode":"74970",
    "sg:province":"Rhone-Alpes",
    "wof:name":"Riou Fr\u00e8res S.a.",
    "wof:placetype":"venue"
},
  "geometry": {"coordinates":[6.500625,46.090221],"type":"Point"}
}