{
  "type": "Feature",
  "properties": {
    "addr:full":"Place du Sud - Tour Eve D\u00e9fense 9 Puteaux C\u00e9dex Midi Pyr\u00e9n\u00e9es 92806",
    "addr:housenumber":"9",
    "addr:postcode":"92806",
    "addr:street":"Place Du Sud Tour Eve De\u0301Fense",
    "iso:country":"FR",
    "sg:address":"Place du Sud - Tour Eve D\u00e9fense 9",
    "sg:city":"Puteaux C\u00e9dex",
    "sg:orig_category":"Non-Classified Establishments",
    "sg:phone":"+33 1 46 93 01 90",
    "sg:postcode":"92806",
    "sg:province":"Midi Pyr\u00e9n\u00e9es",
    "wof:name":"Francepac S.a.",
    "wof:placetype":"venue"
},
  "geometry": {"coordinates":[2.240737,48.888309],"type":"Point"}
}