{
  "type": "Feature",
  "properties": {
    "addr:full":"7 Allee De L Esperance 93110 Rosny Sous Bois Ile de France",
    "addr:housenumber":"7",
    "addr:postcode":"93110",
    "addr:street":"Allee De L Esperance",
    "iso:country":"FR",
    "sg:address":"7 Allee De L Esperance 93110 Rosny Sous Bois",
    "sg:classifiers":[
        {
            "category":"Manufacturing",
            "subcategory":"Wood Products",
            "type":"Manufacturing & Wholesale Goods"
        }
    ],
    "sg:phone":"+33 1 48 12 18 18",
    "sg:province":"Ile de France",
    "sg:tags":[
        "professional",
        "furniture"
    ],
    "wof:name":"Europe Mobilier Decoration (emd)",
    "wof:placetype":"venue"
},
  "geometry": {"coordinates":[2.49441,48.884911],"type":"Point"}
}