{
  "type": "Feature",
  "properties": {
    "addr:full":"7 avenue du Hoggar 91944 COURTABOEUF CEDEX Aquitaine",
    "addr:housenumber":"7",
    "addr:postcode":"91944",
    "addr:street":"Avenue Du Hoggar",
    "iso:country":"FR",
    "sg:address":"7 avenue du Hoggar 91944 COURTABOEUF CEDEX",
    "sg:classifiers":[
        {
            "category":"Wholesale",
            "subcategory":"Books, Periodicals, & Newspapers",
            "type":"Manufacturing & Wholesale Goods"
        }
    ],
    "sg:phone":"+33 1 69 18 75 75",
    "sg:province":"Aquitaine",
    "sg:tags":[
        "publisher",
        "journal"
    ],
    "wof:name":"Edp Sciences Sa",
    "wof:placetype":"venue"
},
  "geometry": {"coordinates":[-117.023537,32.766079],"type":"Point"}
}