{
  "type": "Feature",
  "properties": {
    "addr:full":"Chemin de Fleuriais Mortagne sur S\u00e8vre Pays de Loire 85290",
    "addr:postcode":"85290",
    "addr:street":"Chemin De Fleuriais Mortagne;Se\u0300Vre",
    "iso:country":"FR",
    "sg:address":"Chemin de Fleuriais",
    "sg:city":"Mortagne sur S\u00e8vre",
    "sg:orig_category":"Unclassifiable Establishments",
    "sg:phone":"+33 2 51 65 11 65",
    "sg:postcode":"85290",
    "sg:province":"Pays de Loire",
    "wof:name":"Soci\u00e9t\u00e9 Nouvelle De Tannerie De Fleuriais S.a.",
    "wof:placetype":"venue"
},
  "geometry": {"coordinates":[-0.957427,46.98547],"type":"Point"}
}