{
  "type": "Feature",
  "properties": {
    "addr:full":"95 Rue Du Temple De Blosne 35136 St Jacques De La Lande Saint-Jacques-de-la-Lande Bretagne 35136",
    "addr:housenumber":"95",
    "addr:postcode":"35136;35136",
    "addr:street":"Rue Du Temple De Blosne;St Jacques De La Lande Saint-Jacques-De-La-Lande Bretagne",
    "iso:country":"FR",
    "sg:address":"95 Rue Du Temple De Blosne 35136 St Jacques De La Lande",
    "sg:city":"Saint-Jacques-de-la-Lande",
    "sg:classifiers":[
        {
            "category":"Farming",
            "subcategory":"Farm",
            "type":"Manufacturing & Wholesale Goods"
        }
    ],
    "sg:phone":"+33 2 99 31 29 31",
    "sg:postcode":"35136",
    "sg:province":"Bretagne",
    "sg:tags":[
        "horticulture",
        "agriculture",
        "livestock"
    ],
    "wof:name":"Sarl Etablissements Horticole Aj Cruble",
    "wof:placetype":"venue"
},
  "geometry": {"coordinates":[-1.699867,48.087669],"type":"Point"}
}