{
  "type": "Feature",
  "properties": {
    "addr:full":"163, Rue de Menchecourt, 80100 Abbeville Picardie",
    "addr:housenumber":"163",
    "addr:postcode":"80100",
    "addr:street":"Rue De Menchecourt",
    "iso:country":"FR",
    "sg:address":"163, Rue de Menchecourt, 80100 Abbeville",
    "sg:orig_category":"Unclassifiable Establishments",
    "sg:phone":"+33 3 22 20 70 60",
    "sg:province":"Picardie",
    "wof:name":"Leclerc Imprimerie S.a.r.l.",
    "wof:placetype":"venue"
},
  "geometry": {"coordinates":[1.818194,50.118362],"type":"Point"}
}