{
  "type": "Feature",
  "properties": {
    "addr:full":"2 Rue Edouard Belin 61002 Alen\u00e7on Basse-Normandie",
    "addr:housenumber":"2",
    "addr:postcode":"61002",
    "addr:street":"Rue Edouard Belin",
    "iso:country":"FR",
    "sg:address":"2 Rue Edouard Belin 61002 Alen\u00e7on",
    "sg:classifiers":[
        {
            "category":"Manufacturing",
            "subcategory":"Printing",
            "type":"Manufacturing & Wholesale Goods"
        }
    ],
    "sg:phone":"+33 2 33 80 32 50",
    "sg:province":"Basse-Normandie",
    "sg:tags":[
        "publishing"
    ],
    "wof:name":"L'imprimerie Alen\u00c7onnaise Sa",
    "wof:placetype":"venue"
},
  "geometry": {"coordinates":[0.090066,48.443195],"type":"Point"}
}