{
  "type": "Feature",
  "properties": {
    "addr:full":"ZI de la Croix Blanche Malville Pays de Loire 44260",
    "addr:postcode":"44260",
    "addr:street":"Zi De La Croix Blanche",
    "iso:country":"FR",
    "sg:address":"ZI de la Croix Blanche",
    "sg:city":"Malville",
    "sg:orig_category":"Unclassifiable Establishments",
    "sg:phone":"+33 2 40 56 45 44",
    "sg:postcode":"44260",
    "sg:province":"Pays de Loire",
    "wof:name":"Atlantec Technologies S.a.",
    "wof:placetype":"venue"
},
  "geometry": {"coordinates":[-1.863199,47.359871],"type":"Point"}
}