{
  "type": "Feature",
  "properties": {
    "iso:country":"FR",
    "sg:address":"Za 27220 Grossoeuvre",
    "sg:classifiers":[
        {
            "category":"Manufacturing",
            "subcategory":"Metals",
            "type":"Manufacturing & Wholesale Goods"
        }
    ],
    "sg:phone":"+33 2 32 32 86 86",
    "sg:postcode":"27220",
    "sg:province":"Haute Normandie",
    "sg:tags":[
        "-",
        "machine",
        "equipment",
        "engineering",
        "machinery",
        "mechanical"
    ],
    "wof:name":"Atelier De Mecanique Generale Amg",
    "wof:placetype":"venue"
},
  "geometry": {"coordinates":[1.317003,48.845207],"type":"Point"}
}