{
  "type": "Feature",
  "properties": {
    "addr:full":"33, Rue de l'Est, 92100 Boulogne Billancourt Ile de France",
    "addr:housenumber":"33",
    "addr:postcode":"92100",
    "addr:street":"Rue De L'Est",
    "iso:country":"FR",
    "sg:address":"33, Rue de l'Est, 92100 Boulogne Billancourt",
    "sg:orig_category":"Non-Classified Establishments",
    "sg:phone":"+33 1 46 04 67 67",
    "sg:province":"Ile de France",
    "wof:name":"Socomat S.a.",
    "wof:placetype":"venue"
},
  "geometry": {"coordinates":[2.244107,48.841747],"type":"Point"}
}