{
  "type": "Feature",
  "properties": {
    "addr:full":"78, Bd Saint Marcel, 75005 Paris Ile de France 75005",
    "addr:housenumber":"78",
    "addr:postcode":"75005;75005",
    "addr:street":"Bd Saint Marcel",
    "iso:country":"FR",
    "sg:address":"78, Bd Saint Marcel, 75005 Paris",
    "sg:orig_category":"Non-Classified Establishments",
    "sg:phone":"+33 1 45 87 71 90",
    "sg:postcode":"75005",
    "sg:province":"Ile de France",
    "wof:name":"Datalog S.a.",
    "wof:placetype":"venue"
},
  "geometry": {"coordinates":[2.353495,48.837486],"type":"Point"}
}