{
  "type": "Feature",
  "properties": {
    "addr:full":"Avenue Yvon Delbos 24300 Nontron Nontron Aquitaine 24300",
    "addr:postcode":"24300;24300",
    "addr:street":"Avenue;Delbos",
    "iso:country":"FR",
    "sg:address":"Avenue Yvon Delbos 24300 Nontron",
    "sg:city":"Nontron",
    "sg:classifiers":[
        {
            "category":"Manufacturing",
            "subcategory":"Leather Goods",
            "type":"Manufacturing & Wholesale Goods"
        }
    ],
    "sg:phone":"+33 5 53 56 18 70",
    "sg:postcode":"24300",
    "sg:province":"Aquitaine",
    "sg:tags":[
        "shoe"
    ],
    "wof:name":"La Maroquinerie Nontronnaise",
    "wof:placetype":"venue"
},
  "geometry": {"coordinates":[0.66537,45.536591],"type":"Point"}
}