{
  "type": "Feature",
  "properties": {
    "iso:country":"FR",
    "sg:address":"11 Route BP 752 44186 Nantes Cedex 4",
    "sg:orig_category":"Energy Energy and Raw Materials Miscellaneous Products",
    "sg:phone":"+33 2 40 95 90 00",
    "sg:province":"Midi Pyr\u00e9n\u00e9es",
    "wof:name":"Compagnie Commerciale Et Petroliere De L'ouest (cpo)",
    "wof:placetype":"venue"
},
  "geometry": {"coordinates":[-1.54947,47.219791],"type":"Point"}
}