{
  "type": "Feature",
  "properties": {
    "iso:country":"FR",
    "sg:address":"249 R De Crim\u00e9e 75019 Paris",
    "sg:classifiers":[
        {
            "category":"Professional",
            "subcategory":"Printing & Photocopies",
            "type":"Services"
        }
    ],
    "sg:phone":"+33 1 53 35 20 00",
    "sg:province":"Ile de France",
    "sg:tags":[
        "publishing"
    ],
    "wof:name":"Techniques De L'ingenieur",
    "wof:placetype":"venue"
},
  "geometry": {"coordinates":[2.372437,48.894436],"type":"Point"}
}