{
  "type": "Feature",
  "properties": {
    "addr:full":"Za Les Chaumes Du Pl\u00e9ssis 16440 Roullet St Estephe Poitou-Charentes",
    "addr:postcode":"16440",
    "addr:street":"Za Les Chaumes Du Ple\u0301Ssis;St Estephe",
    "iso:country":"FR",
    "sg:address":"Za Les Chaumes Du Pl\u00e9ssis 16440 Roullet St Estephe",
    "sg:classifiers":[
        {
            "category":"Banks & Credit Unions",
            "subcategory":"Investment Brokerage",
            "type":"Services"
        }
    ],
    "sg:phone":"+33 5 45 67 77 83",
    "sg:province":"Poitou-Charentes",
    "sg:tags":[
        "-",
        "transport",
        "related"
    ],
    "wof:name":"Lafarge Platres",
    "wof:placetype":"venue"
},
  "geometry": {"coordinates":[0.046818,45.582775],"type":"Point"}
}