{
  "type": "Feature",
  "properties": {
    "addr:full":"33 quai de Dion Bouton 92800 Puteaux Ile de France 92800",
    "addr:housenumber":"33",
    "addr:postcode":"92800;92800",
    "addr:street":"Quai De Dion Bouton",
    "iso:country":"FR",
    "sg:address":"33 quai de Dion Bouton 92800 Puteaux",
    "sg:orig_category":"Engineering Offices For Gas Technology",
    "sg:phone":"+33 1 46 98 10 20",
    "sg:postcode":"92800",
    "sg:province":"Ile de France",
    "wof:name":"Process Systems S.a.",
    "wof:placetype":"venue"
},
  "geometry": {"coordinates":[2.245191,48.880997],"type":"Point"}
}