{
  "type": "Feature",
  "properties": {
    "addr:full":"P.A.E. les Longeray Metz Tessy Rhone-Alpes 74370",
    "addr:postcode":"74370",
    "addr:street":"P.A.E.",
    "iso:country":"FR",
    "sg:address":"P.A.E. les Longeray",
    "sg:city":"Metz Tessy",
    "sg:orig_category":"Unclassifiable Establishments",
    "sg:phone":"+33 4 50 27 38 44",
    "sg:postcode":"74370",
    "sg:province":"Rhone-Alpes",
    "wof:name":"I.c.e.f. S.a. - Importations Charcuteries Et Fromages",
    "wof:placetype":"venue"
},
  "geometry": {"coordinates":[6.109395,45.934166],"type":"Point"}
}