{
  "type": "Feature",
  "properties": {
    "addr:full":"28, Rue Fr\u00e9micourt, 75015 Paris Ile de France",
    "addr:housenumber":"28",
    "addr:postcode":"75015",
    "addr:street":"Rue Fre\u0301Micourt",
    "iso:country":"FR",
    "sg:address":"28, Rue Fr\u00e9micourt, 75015 Paris",
    "sg:orig_category":"Unclassifiable Establishments",
    "sg:phone":"+33 1 53 69 54 30",
    "sg:province":"Ile de France",
    "wof:name":"A.g.n. S.a.r.l. - Arts Graphiques Num\u00e9riques",
    "wof:placetype":"venue"
},
  "geometry": {"coordinates":[2.299122,48.847389],"type":"Point"}
}