{
  "type": "Feature",
  "properties": {
    "addr:full":"24 Rue Thomas Edison 92230 Gennevilliers Ile de France 92230",
    "addr:housenumber":"24",
    "addr:postcode":"92230;ile;92230",
    "addr:street":"Rue Thomas Edison;France",
    "iso:country":"FR",
    "sg:address":"24 Rue Thomas Edison 92230 Gennevilliers",
    "sg:classifiers":[
        {
            "category":"Shopping",
            "subcategory":"Gifts & Souvenirs",
            "type":"Retail Goods"
        }
    ],
    "sg:phone":"+33 1 40 85 04 00",
    "sg:postcode":"92230",
    "sg:province":"Ile de France",
    "sg:tags":[
        "product",
        "miscellaneous"
    ],
    "wof:name":"Cecop Sa",
    "wof:placetype":"venue"
},
  "geometry": {"coordinates":[2.312207,48.931335],"type":"Point"}
}