{
  "type": "Feature",
  "properties": {
    "addr:full":"Rue Gustave Courbet Calais Nord Pas-de-Calais 62100",
    "addr:postcode":"62100",
    "addr:street":"Rue Gustave Courbet Calais Nord",
    "iso:country":"FR",
    "sg:address":"Rue Gustave Courbet",
    "sg:city":"Calais",
    "sg:orig_category":"Non-Classified Establishments",
    "sg:phone":"+33 3 21 96 56 30",
    "sg:postcode":"62100",
    "sg:province":"Nord Pas-de-Calais",
    "wof:name":"Ateliers Du D\u00e9troit - C.a.t.",
    "wof:placetype":"venue"
},
  "geometry": {"coordinates":[1.908275,50.948841],"type":"Point"}
}