{
  "type": "Feature",
  "properties": {
    "addr:full":"601 Rue Du Marechal Foch 77006 Melun Cedex Outre-Mer",
    "addr:housenumber":"601",
    "addr:postcode":"77006",
    "addr:street":"Rue Du Marechal Foch",
    "iso:country":"FR",
    "sg:address":"601 Rue Du Marechal Foch 77006 Melun Cedex",
    "sg:classifiers":[
        {
            "category":"Building & Trades",
            "subcategory":"Electrical",
            "type":"Services"
        }
    ],
    "sg:phone":"+33 1 64 10 30 60",
    "sg:province":"Outre-Mer",
    "sg:tags":[
        "electronic",
        "lighting",
        "equipment"
    ],
    "wof:name":"Lumalux",
    "wof:placetype":"venue"
},
  "geometry": {"coordinates":[2.664085,48.539577],"type":"Point"}
}