{
  "type": "Feature",
  "properties": {
    "iso:country":"FR",
    "sg:address":"1 Rue Des Deux Montagnes 74100 Ville La Grand",
    "sg:classifiers":[
        {
            "category":"Home & Garden",
            "subcategory":"Furniture",
            "type":"Retail Goods"
        }
    ],
    "sg:phone":"+33 4 50 95 05 00",
    "sg:postcode":"74100",
    "sg:province":"Rhone-Alpes",
    "sg:tags":[
        "household",
        "wood"
    ],
    "wof:name":"Meubles Wieder Sa",
    "wof:placetype":"venue"
},
  "geometry": {"coordinates":[6.281645,46.203827],"type":"Point"}
}