{
  "type": "Feature",
  "properties": {
    "addr:full":"10 Rue Rebuffat 91140 Villejust Ile de France 91140",
    "addr:housenumber":"10",
    "addr:postcode":"91140;91140",
    "addr:street":"Rue Rebuffat;Ile De France",
    "iso:country":"FR",
    "sg:address":"10 Rue Rebuffat 91140 Villejust",
    "sg:classifiers":[
        {
            "category":"Shopping",
            "subcategory":"Computers & Home Electronics",
            "type":"Retail Goods"
        }
    ],
    "sg:phone":"+33 1 69 31 79 79",
    "sg:postcode":"91140",
    "sg:province":"Ile de France",
    "sg:tags":[
        "equipment",
        "electrical",
        "component",
        "electric",
        "electronic"
    ],
    "wof:name":"Conception Electronique Et Production (cep)",
    "wof:placetype":"venue"
},
  "geometry": {"coordinates":[2.227225,48.700069],"type":"Point"}
}