{
  "type": "Feature",
  "properties": {
    "addr:full":"15 rue de Mar\u00e9chal Foch; Pau; 64000 Pau Aquitaine 64000",
    "addr:housenumber":"15",
    "addr:postcode":"64000;64000",
    "addr:street":"Rue De Mare\u0301Chal Foch Pau",
    "iso:country":"FR",
    "sg:address":"15 rue de Mar\u00e9chal Foch; Pau; 64000",
    "sg:city":"Pau",
    "sg:classifiers":[
        {
            "category":"Banks & Credit Unions",
            "subcategory":"Bank",
            "type":"Services"
        }
    ],
    "sg:phone":"+33 3359270345",
    "sg:postcode":"64000",
    "sg:province":"Aquitaine",
    "wof:name":"Banque Nationale De Paris",
    "wof:placetype":"venue"
},
  "geometry": {"coordinates":[-0.367559,43.296375],"type":"Point"}
}