{
  "type": "Feature",
  "properties": {
    "addr:full":"9 bis rue de Presbourg; Paris Cedex; 75016 Ile de France",
    "addr:housenumber":"9 bis",
    "addr:postcode":"75016 ile",
    "addr:street":"Rue De Presbourg",
    "iso:country":"FR",
    "sg:address":"9 bis rue de Presbourg; Paris Cedex; 75016",
    "sg:classifiers":[
        {
            "category":"Industrial Area",
            "type":"Public Place"
        }
    ],
    "sg:phone":"+33 1 40 67 29 29",
    "sg:province":"Ile de France",
    "sg:tags":[
        "large",
        "private"
    ],
    "wof:name":"Sopra Group",
    "wof:placetype":"venue"
},
  "geometry": {"coordinates":[2.25657,48.857079],"type":"Point"}
}