{
  "type": "Feature",
  "properties": {
    "addr:full":"677 Route De Marceau 74210 Doussard Rhone-Alpes",
    "addr:housenumber":"677",
    "addr:postcode":"74210",
    "addr:street":"Route De Marceau",
    "iso:country":"FR",
    "sg:address":"677 Route De Marceau 74210 Doussard",
    "sg:orig_category":"Miscellaneous Products",
    "sg:phone":"+33 4 50 32 94 00",
    "sg:province":"Rhone-Alpes",
    "wof:name":"Pointille Sarl",
    "wof:placetype":"venue"
},
  "geometry": {"coordinates":[6.213322,45.774548],"type":"Point"}
}