{
  "type": "Feature",
  "properties": {
    "addr:full":"5, Rue Charles Martigny, 94700 Maisons Alfort Ile de France",
    "addr:housenumber":"5",
    "addr:postcode":"94700",
    "addr:street":"Rue Charles Martigny",
    "iso:country":"FR",
    "sg:address":"5, Rue Charles Martigny, 94700 Maisons Alfort",
    "sg:orig_category":"Unclassifiable Establishments",
    "sg:phone":"+33 1 42 07 97 04",
    "sg:province":"Ile de France",
    "wof:name":"Laboratoire Ratiopharm S.a.r.l.",
    "wof:placetype":"venue"
},
  "geometry": {"coordinates":[2.436634,48.789837],"type":"Point"}
}