{
  "type": "Feature",
  "properties": {
    "addr:full":"16 Rue De La Roberdi\u00e8re 35039 Rennes Cedex Rhone-Alpes",
    "addr:housenumber":"16",
    "addr:postcode":"35039",
    "addr:street":"Rue De La Roberdie\u0300Re",
    "iso:country":"FR",
    "sg:address":"16 Rue De La Roberdi\u00e8re 35039 Rennes Cedex",
    "sg:classifiers":[
        {
            "category":"Government",
            "subcategory":"Department Of Motor Vehicles",
            "type":"Public Place"
        }
    ],
    "sg:phone":"+33 2 99 59 26 08",
    "sg:province":"Rhone-Alpes",
    "sg:tags":[
        "equipment",
        "industrial",
        "transport",
        "motor-cars"
    ],
    "wof:name":"Besnard Et Gerard",
    "wof:placetype":"venue"
},
  "geometry": {"coordinates":[-1.72575,48.106274],"type":"Point"}
}