{
  "type": "Feature",
  "properties": {
    "addr:full":"10 Rue De Mulhouse 67100 Strasbourg Strasbourg Alsace 67100",
    "addr:housenumber":"10",
    "addr:postcode":"67100;67100",
    "addr:street":"Rue De Mulhouse",
    "iso:country":"FR",
    "sg:address":"10 Rue De Mulhouse 67100 Strasbourg",
    "sg:city":"Strasbourg",
    "sg:classifiers":[
        {
            "category":"Wholesale",
            "subcategory":"Medical Equipment & Supplies",
            "type":"Manufacturing & Wholesale Goods"
        }
    ],
    "sg:phone":"+33 3 88 84 80 10",
    "sg:postcode":"67100",
    "sg:province":"Alsace",
    "sg:tags":[
        "instrument",
        "health",
        "-",
        "precision"
    ],
    "wof:name":"Laboratoire Dentaire Siro Michelli",
    "wof:placetype":"venue"
},
  "geometry": {"coordinates":[7.755869,48.568531],"type":"Point"}
}