{
  "type": "Feature",
  "properties": {
    "iso:country":"FR",
    "sg:address":"Zae Cap Nord",
    "sg:city":"Dijon",
    "sg:classifiers":[
        {
            "category":"Professional",
            "subcategory":"Engineering",
            "type":"Services"
        }
    ],
    "sg:phone":"+33 3 80 74 92 40",
    "sg:postcode":"21000",
    "sg:province":"Bourgogne",
    "sg:tags":[
        "machine",
        "-",
        "environment",
        "equipment",
        "machinery",
        "mechanical"
    ],
    "wof:name":"Desautel",
    "wof:placetype":"venue"
},
  "geometry": {"coordinates":[5.044195,47.326458],"type":"Point"}
}