{
  "type": "Feature",
  "properties": {
    "addr:full":"B.P. 14, 62142 Colembert^^38, Rue le Communal, 62142 Colembert Nord Pas-de-Calais",
    "addr:postcode":"62142;62142",
    "addr:street":"B.P. 14;Rue Le Communal",
    "iso:country":"FR",
    "sg:address":"B.P. 14, 62142 Colembert^^38, Rue le Communal, 62142 Colembert",
    "sg:orig_category":"Non-Classified Establishments",
    "sg:phone":"+33 3 21 33 30 63",
    "sg:province":"Nord Pas-de-Calais",
    "wof:name":"Novebat S.a.r.l.",
    "wof:placetype":"venue"
},
  "geometry": {"coordinates":[1.760535,50.742695],"type":"Point"}
}