{
  "type": "Feature",
  "properties": {
    "addr:full":"5, Rue Ambroise Par\u00e9, 22360 Langueux Langueux Bretagne 22360",
    "addr:housenumber":"5",
    "addr:postcode":"22360;22360",
    "addr:street":"Rue Ambroise Pare\u0301",
    "iso:country":"FR",
    "sg:address":"5, Rue Ambroise Par\u00e9, 22360 Langueux",
    "sg:city":"Langueux",
    "sg:orig_category":"Non-Classified Establishments",
    "sg:phone":"+33 2 96 33 93 93",
    "sg:postcode":"22360",
    "sg:province":"Bretagne",
    "wof:name":"Repro Conseil S.a.",
    "wof:placetype":"venue"
},
  "geometry": {"coordinates":[-2.730025,48.499878],"type":"Point"}
}