{
  "type": "Feature",
  "properties": {
    "iso:country":"FR",
    "sg:address":"B.P. 35",
    "sg:city":"Strasbourg C\u00e9dex",
    "sg:orig_category":"Non-Classified Establishments",
    "sg:phone":"+33 3 88 48 43 66",
    "sg:postcode":"67023",
    "sg:province":"Alsace",
    "wof:name":"Anstett Bretzels D'alsace S.a.r.l.",
    "wof:placetype":"venue"
},
  "geometry": {"coordinates":[7.74983,48.58176],"type":"Point"}
}