{
  "type": "Feature",
  "properties": {
    "addr:full":"Rue Sarthe S\u00e9vigny la For\u00eat Champagne 08230",
    "addr:postcode":"08230",
    "addr:street":"Rue Sarthe Se\u0301Vigny La;Champagne",
    "iso:country":"FR",
    "sg:address":"Rue Sarthe",
    "sg:city":"S\u00e9vigny la For\u00eat",
    "sg:orig_category":"Non-Classified Establishments",
    "sg:phone":"+33 3 24 54 12 67",
    "sg:postcode":"08230",
    "sg:province":"Champagne",
    "wof:name":"Denys S.a.r.l.",
    "wof:placetype":"venue"
},
  "geometry": {"coordinates":[4.491318,49.891521],"type":"Point"}
}