{
  "type": "Feature",
  "properties": {
    "addr:full":"251-253 blvd Pereire; Paris; 75017 Ile de France 75017",
    "addr:postcode":"251-253;75017 ile;france 75017",
    "addr:street":"Blvd Pereire",
    "iso:country":"FR",
    "sg:address":"251-253 blvd Pereire; Paris; 75017",
    "sg:classifiers":[
        {
            "category":"Banks & Credit Unions",
            "subcategory":"Bank",
            "type":"Services"
        }
    ],
    "sg:phone":"+33 1 40 55 30 30",
    "sg:postcode":"75017",
    "sg:province":"Ile de France",
    "wof:name":"Banque Du B\u00e2timent, Et Des Travaux Publics",
    "wof:placetype":"venue"
},
  "geometry": {"coordinates":[2.318885,48.883629],"type":"Point"}
}