{
  "type": "Feature",
  "properties": {
    "addr:full":"71 bis, Rue Alexandre B\u00e9nard, 01500 Amb\u00e9rieu en Bugey Rhone-Alpes 01500",
    "addr:housenumber":"71 bis",
    "addr:postcode":"01500;01500",
    "addr:street":"Rue Alexandre Be\u0301Nard",
    "iso:country":"FR",
    "sg:address":"71 bis, Rue Alexandre B\u00e9nard, 01500 Amb\u00e9rieu en Bugey",
    "sg:orig_category":"Unclassifiable Establishments",
    "sg:phone":"+33 4 74 38 07 11",
    "sg:postcode":"01500",
    "sg:province":"Rhone-Alpes",
    "wof:name":"Bugey Electricit\u00e9 S.a.r.l.",
    "wof:placetype":"venue"
},
  "geometry": {"coordinates":[5.356309,45.962872],"type":"Point"}
}