{
  "type": "Feature",
  "properties": {
    "addr:full":"27, Av. des Champs Pierreux, 92735 Nanterre C\u00e9dex Auvergne",
    "addr:postcode":"92735;ce\u0301dex",
    "addr:street":"27 Av. Des Champs Pierreux",
    "iso:country":"FR",
    "sg:address":"27, Av. des Champs Pierreux, 92735 Nanterre C\u00e9dex",
    "sg:orig_category":"Non-Classified Establishments",
    "sg:phone":"+33 1 47 21 05 05",
    "sg:province":"Auvergne",
    "wof:name":"Praxion S.a.",
    "wof:placetype":"venue"
},
  "geometry": {"coordinates":[2.21341,48.888985],"type":"Point"}
}