{
  "type": "Feature",
  "properties": {
    "iso:country":"FR",
    "sg:address":"B.P. 49, 67220 Vill\u00e9^^Rue du Climont - Neuve Eglise , 67220 Vill\u00e9",
    "sg:city":"Vill\u00e9",
    "sg:orig_category":"Non-Classified Establishments",
    "sg:phone":"+33 3 88 58 99 17",
    "sg:postcode":"67220",
    "sg:province":"Alsace",
    "wof:name":"Eurodic S.a.r.l.",
    "wof:placetype":"venue"
},
  "geometry": {"coordinates":[7.302732,48.342537],"type":"Point"}
}