{
  "type": "Feature",
  "properties": {
    "iso:country":"FR",
    "sg:address":"9 bis, All\u00e9e du Textile, 69120 Vaulx en Velin",
    "sg:orig_category":"Non-Classified Establishments",
    "sg:phone":"+33 4 72 37 18 02",
    "sg:postcode":"69120",
    "sg:province":"Rhone-Alpes",
    "wof:name":"C.p.m. S.a.r.l. - Construction Pr\u00e9cision M\u00e9canique",
    "wof:placetype":"venue"
},
  "geometry": {"coordinates":[4.926519,45.759876],"type":"Point"}
}