{
  "type": "Feature",
  "properties": {
    "addr:full":"7 rue des Chapelles 94350 Villiers sur Marne Ile de France 94350",
    "addr:housenumber":"7",
    "addr:postcode":"94350;94350",
    "addr:street":"Rue Des Chapelles",
    "iso:country":"FR",
    "sg:address":"7 rue des Chapelles 94350 Villiers sur Marne",
    "sg:orig_category":"Insect And Flying Insect Destruction Devices",
    "sg:phone":"+33 1 49 30 02 88",
    "sg:postcode":"94350",
    "sg:province":"Ile de France",
    "wof:name":"G.l. Equipements Sarl",
    "wof:placetype":"venue"
},
  "geometry": {"coordinates":[2.546065,48.826214],"type":"Point"}
}