{
  "type": "Feature",
  "properties": {
    "addr:full":"Rte de Fouger\u00e9 Les Rairies Pays de Loire 49430",
    "addr:postcode":"49430",
    "addr:street":"Rte De Fougere\u0301 Les",
    "iso:country":"FR",
    "sg:address":"Rte de Fouger\u00e9",
    "sg:city":"Les Rairies",
    "sg:orig_category":"Unclassifiable Establishments",
    "sg:phone":"+33 2 41 21 15 20",
    "sg:postcode":"49430",
    "sg:province":"Pays de Loire",
    "wof:name":"Montrieux Ernest S.a.",
    "wof:placetype":"venue"
},
  "geometry": {"coordinates":[-0.203972,47.6511],"type":"Point"}
}