{
  "type": "Feature",
  "properties": {
    "addr:full":"69 Grande Rue; Vaison la Romaine; 84110 Haute Normandie",
    "addr:housenumber":"69",
    "addr:postcode":"84110",
    "addr:street":"Grande Rue Vaison La Romaine",
    "iso:country":"FR",
    "sg:address":"69 Grande Rue; Vaison la Romaine; 84110",
    "sg:classifiers":[
        {
            "category":"Banks & Credit Unions",
            "subcategory":"Bank",
            "type":"Services"
        }
    ],
    "sg:phone":"+33 3390360027",
    "sg:province":"Haute Normandie",
    "wof:name":"Soci\u00e9t\u00e9 Marseillaise De Cr\u00e9dit",
    "wof:placetype":"venue"
},
  "geometry": {"coordinates":[5.008068,44.190483],"type":"Point"}
}