{
  "type": "Feature",
  "properties": {
    "addr:full":"ZI de la Gare Coligny Rhone-Alpes 01270",
    "addr:postcode":"01270",
    "addr:street":"Zi De La Gare;Rhone-Alpes",
    "iso:country":"FR",
    "sg:address":"ZI de la Gare",
    "sg:city":"Coligny",
    "sg:orig_category":"Unclassifiable Establishments",
    "sg:phone":"+33 4 74 30 15 53",
    "sg:postcode":"01270",
    "sg:province":"Rhone-Alpes",
    "wof:name":"Ereca Jarrier S.a.r.l.",
    "wof:placetype":"venue"
},
  "geometry": {"coordinates":[5.34516,46.382038],"type":"Point"}
}