{
  "type": "Feature",
  "properties": {
    "addr:full":"1045, Rte de Saint R\u00e9my 571, 13160 Ch\u00e2teaurenard Provence-Alpes-C\u00f4te d'Azur",
    "addr:housenumber":"1045;571",
    "addr:postcode":"13160",
    "addr:street":"Rte De Saint Re\u0301My",
    "iso:country":"FR",
    "sg:address":"1045, Rte de Saint R\u00e9my 571, 13160 Ch\u00e2teaurenard",
    "sg:orig_category":"Unclassifiable Establishments",
    "sg:phone":"+33 4 90 94 11 90",
    "sg:province":"Provence-Alpes-C\u00f4te d'Azur",
    "wof:name":"P\u00e9pini\u00e8res Meffre S.c.e.a.",
    "wof:placetype":"venue"
},
  "geometry": {"coordinates":[4.850344,43.869923],"type":"Point"}
}