{
  "type": "Feature",
  "properties": {
    "iso:country":"FR",
    "sg:address":"23 All Du Mons 69100 Villeurbanne",
    "sg:classifiers":[
        {
            "category":"Utilities",
            "subcategory":"Telephone",
            "type":"Services"
        }
    ],
    "sg:phone":"+33 4 78 79 50 30",
    "sg:province":"Rhone-Alpes",
    "sg:tags":[
        "telecommunication"
    ],
    "wof:name":"Lenoir Services Sa",
    "wof:placetype":"venue"
},
  "geometry": {"coordinates":[4.903755,45.780163],"type":"Point"}
}