{
  "type": "Feature",
  "properties": {
    "iso:country":"FR",
    "sg:address":"12, Rue Romelet, 21600 Longvic",
    "sg:city":"Longvic",
    "sg:orig_category":"Non-Classified Establishments",
    "sg:phone":"+33 3 80 66 87 93",
    "sg:postcode":"21600",
    "sg:province":"Bourgogne",
    "wof:name":"Michaud Chailly S.a.",
    "wof:placetype":"venue"
},
  "geometry": {"coordinates":[5.037191,47.289425],"type":"Point"}
}