{
  "type": "Feature",
  "properties": {
    "iso:country":"FR",
    "sg:address":"B.P. 57, 13714 Cassis C\u00e9dex^^Rte D\u00e9partementale 559, 13710 Cassis",
    "sg:orig_category":"Non-Classified Establishments",
    "sg:phone":"+33 4 42 01 00 74",
    "wof:name":"Domaine De La Ferme Blanche E.a.r.l.",
    "wof:placetype":"venue"
},
  "geometry": {"coordinates":[5.562885,43.453346],"type":"Point"}
}