{
  "type": "Feature",
  "properties": {
    "iso:country":"FR",
    "sg:address":"14 R De La L\u00e8verie 59510 Hem",
    "sg:classifiers":[
        {
            "category":"Shopping",
            "type":"Retail Goods"
        }
    ],
    "sg:phone":"+33 3 20 02 52 82",
    "sg:postcode":"59510",
    "sg:province":"Nord Pas-de-Calais",
    "sg:tags":[
        "metallurgy",
        "finished",
        "-",
        "metalworking",
        "metallic"
    ],
    "wof:name":"Sa Erick Debusschere",
    "wof:placetype":"venue"
},
  "geometry": {"coordinates":[3.20426,50.665329],"type":"Point"}
}