{
  "type": "Feature",
  "properties": {
    "addr:full":"25 Rue Des Capucins 69001 Lyon Rhone-Alpes 69001",
    "addr:housenumber":"25",
    "addr:postcode":"69001;69001",
    "addr:street":"Rue Des Capucins",
    "iso:country":"FR",
    "sg:address":"25 Rue Des Capucins 69001 Lyon",
    "sg:classifiers":[
        {
            "category":"Shopping",
            "subcategory":"Clothing, Apparel, & Fashions",
            "type":"Retail Goods"
        }
    ],
    "sg:phone":"+33 4 78 28 34 07",
    "sg:postcode":"69001",
    "sg:province":"Rhone-Alpes",
    "sg:tags":[
        "textile",
        "clothing",
        "clothes"
    ],
    "wof:name":"Tricots Maurice Sarl",
    "wof:placetype":"venue"
},
  "geometry": {"coordinates":[4.835158,45.769642],"type":"Point"}
}