{
  "type": "Feature",
  "properties": {
    "addr:full":"B.P. 8, 60250 Balagny sur Th\u00e9rain^^Rue de la Gare, 60250 Balagny sur Th\u00e9rain Picardie 60250",
    "addr:housenumber":"8",
    "addr:postcode":"60250;60250;60250",
    "addr:street":"B.P.;La Gare",
    "iso:country":"FR",
    "sg:address":"B.P. 8, 60250 Balagny sur Th\u00e9rain^^Rue de la Gare, 60250 Balagny sur Th\u00e9rain",
    "sg:orig_category":"Non-Classified Establishments",
    "sg:phone":"+33 3 44 26 25 28",
    "sg:postcode":"60250",
    "sg:province":"Picardie",
    "wof:name":"Blispac S.a.",
    "wof:placetype":"venue"
},
  "geometry": {"coordinates":[2.322815,49.320976],"type":"Point"}
}