{
  "type": "Feature",
  "properties": {
    "addr:full":"Zi 620 Av Pavlov 30900 Nimes Languedoc-Roussillon 30900",
    "addr:housenumber":"620",
    "addr:postcode":"30900;30900",
    "addr:street":"Zi;Av Pavlov",
    "iso:country":"FR",
    "sg:address":"Zi 620 Av Pavlov 30900 Nimes",
    "sg:classifiers":[
        {
            "category":"Manufacturing",
            "subcategory":"Chemicals & Compounds",
            "type":"Manufacturing & Wholesale Goods"
        }
    ],
    "sg:phone":"+33 4 66 64 68 91",
    "sg:postcode":"30900",
    "sg:province":"Languedoc-Roussillon",
    "sg:tags":[
        "metallurgy",
        "pharmaceutical",
        "metalworking",
        "processing",
        "metal"
    ],
    "wof:name":"Atelier Nimois De Metallisation Plasticolor",
    "wof:placetype":"venue"
},
  "geometry": {"coordinates":[4.356115,43.830025],"type":"Point"}
}