{
  "type": "Feature",
  "properties": {
    "iso:country":"FR",
    "sg:address":"Rue Jean Monnet - ZAC du Min",
    "sg:city":"Cavaillon",
    "sg:orig_category":"Unclassifiable Establishments",
    "sg:phone":"+33 4 90 76 37 37",
    "sg:postcode":"84300",
    "sg:province":"Provence-Alpes-C\u00f4te d'Azur",
    "wof:name":"Norton Mat\u00e9riaux Avanc\u00e9s S.a.",
    "wof:placetype":"venue"
},
  "geometry": {"coordinates":[5.044605,43.819695],"type":"Point"}
}