{
  "type": "Feature",
  "properties": {
    "iso:country":"FR",
    "sg:address":"Rue Louis Bl\u00e9riot Za La Chauveli\u00e8re 35150 Janz\u00e9",
    "sg:city":"Janz\u00e9",
    "sg:classifiers":[
        {
            "category":"Utilities",
            "subcategory":"Electric",
            "type":"Services"
        }
    ],
    "sg:phone":"+33 2 99 47 01 03",
    "sg:postcode":"35150",
    "sg:province":"Bretagne",
    "sg:tags":[
        "electricity",
        "electronic",
        "electrical",
        "equipment"
    ],
    "wof:name":"Sdel Janze",
    "wof:placetype":"venue"
},
  "geometry": {"coordinates":[-1.495007,47.958996],"type":"Point"}
}