{
  "type": "Feature",
  "properties": {
    "addr:full":"6, Rte d'Avize, 51190 Oger Champagne 51190",
    "addr:housenumber":"6",
    "addr:postcode":"51190;51190",
    "addr:street":"Rte D'Avize;Champagne",
    "iso:country":"FR",
    "sg:address":"6, Rte d'Avize, 51190 Oger",
    "sg:orig_category":"Non-Classified Establishments",
    "sg:phone":"+33 3 26 57 50 09",
    "sg:postcode":"51190",
    "sg:province":"Champagne",
    "wof:name":"Champagne Milan",
    "wof:placetype":"venue"
},
  "geometry": {"coordinates":[4.0063,48.9701],"type":"Point"}
}