{
  "type": "Feature",
  "properties": {
    "iso:country":"FR",
    "sg:address":"2, Rue Gambetta, 77210 Avon",
    "sg:orig_category":"Unclassifiable Establishments",
    "sg:phone":"+33 1 60 72 22 00",
    "sg:province":"Ile de France",
    "wof:name":"T\u00e9l\u00e9alarme 77 S.a.r.l.",
    "wof:placetype":"venue"
},
  "geometry": {"coordinates":[2.719342,48.400928],"type":"Point"}
}