{
  "type": "Feature",
  "properties": {
    "iso:country":"FR",
    "sg:address":"60 bd de la Mission Marchand 92400 Courbevoie",
    "sg:classifiers":[
        {
            "category":"Manufacturing",
            "subcategory":"Metals",
            "type":"Manufacturing & Wholesale Goods"
        }
    ],
    "sg:phone":"+33 1 43 34 27 92",
    "sg:postcode":"92400",
    "sg:province":"Ile de France",
    "sg:tags":[
        "ironmongery"
    ],
    "wof:name":"Jmb Pro Sa",
    "wof:placetype":"venue"
},
  "geometry": {"coordinates":[2.240138,48.899193],"type":"Point"}
}