{
  "type": "Feature",
  "properties": {
    "addr:full":"18, Av. de Pennouet, 44600 Saint Nazaire Pays de Loire",
    "addr:postcode":"44600",
    "addr:street":"18 Av. De Pennouet;Nazaire",
    "iso:country":"FR",
    "sg:address":"18, Av. de Pennouet, 44600 Saint Nazaire",
    "sg:orig_category":"Unclassifiable Establishments",
    "sg:phone":"+33 2 40 66 81 82",
    "sg:province":"Pays de Loire",
    "wof:name":"S.i.m.i. - Soci\u00e9t\u00e9 D'intervention En Maintenance Industriell",
    "wof:placetype":"venue"
},
  "geometry": {"coordinates":[-2.278494,47.240322],"type":"Point"}
}