{
  "type": "Feature",
  "properties": {
    "iso:country":"FR",
    "sg:address":"112 bis, Rue Eug\u00e8ne Pottier, 35000 Rennes",
    "sg:city":"Rennes",
    "sg:orig_category":"Unclassifiable Establishments",
    "sg:phone":"+33 2 99 35 01 01",
    "sg:postcode":"35000",
    "sg:province":"Bretagne",
    "wof:name":"Romi S.a.",
    "wof:placetype":"venue"
},
  "geometry": {"coordinates":[-1.711379,48.10318],"type":"Point"}
}