{
  "type": "Feature",
  "properties": {
    "iso:country":"FR",
    "sg:address":"20, Rue Raymond Aron, 76130 Mont Saint Aignan",
    "sg:orig_category":"Non-Classified Establishments",
    "sg:phone":"+33 2 35 59 95 05",
    "sg:province":"Haute Normandie",
    "wof:name":"Normatec Equipement Industriel S.a.r.l.",
    "wof:placetype":"venue"
},
  "geometry": {"coordinates":[1.09474,49.473988],"type":"Point"}
}