{
  "type": "Feature",
  "properties": {
    "addr:full":"ZI des Epinettes Barby Rhone-Alpes 73230",
    "addr:postcode":"73230",
    "addr:street":"Des Epinettes;Rhone-Alpes",
    "iso:country":"FR",
    "sg:address":"ZI des Epinettes",
    "sg:city":"Barby",
    "sg:orig_category":"Unclassifiable Establishments",
    "sg:phone":"+33 4 79 71 32 45",
    "sg:postcode":"73230",
    "sg:province":"Rhone-Alpes",
    "wof:name":"A.m.s.c. E.u.r.l. - Alpes Multi Services Charvet",
    "wof:placetype":"venue"
},
  "geometry": {"coordinates":[5.977465,45.571201],"type":"Point"}
}