{
  "type": "Feature",
  "properties": {
    "iso:country":"FR",
    "sg:address":"6BIS av Paul-Vaillant Couturier 93120 La Courneuve",
    "sg:classifiers":[
        {
            "category":"Manufacturing",
            "subcategory":"Textiles",
            "type":"Manufacturing & Wholesale Goods"
        }
    ],
    "sg:phone":"+33 1 49 92 13 70",
    "sg:postcode":"93120",
    "sg:province":"Ile de France",
    "sg:tags":[
        "natural"
    ],
    "wof:name":"Ste F E V A M Sa",
    "wof:placetype":"venue"
},
  "geometry": {"coordinates":[2.408585,48.918583],"type":"Point"}
}