{
  "type": "Feature",
  "properties": {
    "iso:country":"FR",
    "sg:address":"65 bis, Chemin Neuf - Parc d'Activit\u00e9s - Logis Neuf , 69780 Toussieu",
    "sg:orig_category":"Non-Classified Establishments",
    "sg:phone":"+33 4 72 48 03 73",
    "sg:postcode":"69780",
    "sg:province":"Rhone-Alpes",
    "wof:name":"Datec S.a.r.l.",
    "wof:placetype":"venue"
},
  "geometry": {"coordinates":[4.99177,45.65134],"type":"Point"}
}