{
  "type": "Feature",
  "properties": {
    "iso:country":"FR",
    "sg:address":"14 Av Gal Moreau 08230 Rocroi",
    "sg:city":"Bourg-Fid\u00e8le",
    "sg:classifiers":[
        {
            "category":"Building & Trades",
            "subcategory":"Construction",
            "type":"Services"
        }
    ],
    "sg:phone":"+33 3 24 52 62 00",
    "sg:postcode":"08230",
    "sg:province":"Champagne",
    "sg:tags":[
        "work",
        "public"
    ],
    "wof:name":"Fievet Snc",
    "wof:placetype":"venue"
},
  "geometry": {"coordinates":[4.518914,49.921513],"type":"Point"}
}