{
  "type": "Feature",
  "properties": {
    "addr:full":"396, Chemin de Leyriat - Noyer , 74200 Allinges Rhone-Alpes",
    "addr:housenumber":"396",
    "addr:postcode":"74200",
    "addr:street":"Chemin De Leyriat Noyer",
    "iso:country":"FR",
    "sg:address":"396, Chemin de Leyriat - Noyer , 74200 Allinges",
    "sg:orig_category":"Unclassifiable Establishments",
    "sg:phone":"+33 4 50 70 50 74",
    "sg:province":"Rhone-Alpes",
    "wof:name":"Peillex-delph S.a.r.l.",
    "wof:placetype":"venue"
},
  "geometry": {"coordinates":[6.61462,46.305523],"type":"Point"}
}