{
  "type": "Feature",
  "properties": {
    "iso:country":"FR",
    "sg:address":"B.P. 448, 38317 Bourgoin Jallieu C\u00e9dex^^40, Bd de Champaret, 38300 Bourgoin Jallieu",
    "sg:orig_category":"Non-Classified Establishments",
    "sg:phone":"+33 4 74 93 87 00",
    "sg:postcode":"38300",
    "sg:province":"Rhone-Alpes",
    "wof:name":"Patheon France S.a.",
    "wof:placetype":"venue"
},
  "geometry": {"coordinates":[5.30075,45.4981],"type":"Point"}
}