{
  "type": "Feature",
  "properties": {
    "iso:country":"FR",
    "sg:address":"B.P. 4, 88650 Saint L\u00e9onard^^8, Rue de la Meurthe, 88650 Saint L\u00e9onard",
    "sg:orig_category":"Non-Classified Establishments",
    "sg:phone":"+33 3 29 51 93 93",
    "sg:province":"Lorraine",
    "wof:name":"L\u00e9opack S.a.r.l.",
    "wof:placetype":"venue"
},
  "geometry": {"coordinates":[6.952637,48.18932],"type":"Point"}
}