{
  "type": "Feature",
  "properties": {
    "addr:full":"220 Av Des Aureats 26000 Valence Rhone-Alpes 26000",
    "addr:housenumber":"220",
    "addr:postcode":"26000;26000",
    "addr:street":"Av Des Aureats",
    "iso:country":"FR",
    "sg:address":"220 Av Des Aureats 26000 Valence",
    "sg:classifiers":[
        {
            "category":"Shopping",
            "subcategory":"Crafts & Fabrics",
            "type":"Retail Goods"
        }
    ],
    "sg:phone":"+33 4 75 57 60 80",
    "sg:postcode":"26000",
    "sg:province":"Rhone-Alpes",
    "sg:tags":[
        "textile",
        "clothing"
    ],
    "wof:name":"Setila",
    "wof:placetype":"venue"
},
  "geometry": {"coordinates":[4.88462,44.889801],"type":"Point"}
}