{
  "type": "Feature",
  "properties": {
    "addr:full":"30, Rue des Ch\u00e2teaux - ZI de la Pilaterie, 59290 Wasquehal Nord Pas-de-Calais",
    "addr:housenumber":"30",
    "addr:postcode":"59290",
    "addr:street":"Rue Des Cha\u0302Teaux Zi De La Pilaterie",
    "iso:country":"FR",
    "sg:address":"30, Rue des Ch\u00e2teaux - ZI de la Pilaterie, 59290 Wasquehal",
    "sg:orig_category":"Unclassifiable Establishments",
    "sg:phone":"+33 3 20 45 36 36",
    "sg:province":"Nord Pas-de-Calais",
    "wof:name":"Van Melle France S.a.",
    "wof:placetype":"venue"
},
  "geometry": {"coordinates":[3.132085,50.669395],"type":"Point"}
}