{
  "type": "Feature",
  "properties": {
    "addr:full":"ZI de Pierre Longue Amancy Rhone-Alpes 74800",
    "addr:postcode":"74800",
    "addr:street":"Zi De Pierre Longue;Rhone-Alpes",
    "iso:country":"FR",
    "sg:address":"ZI de Pierre Longue",
    "sg:city":"Amancy",
    "sg:orig_category":"Unclassifiable Establishments",
    "sg:phone":"+33 4 50 03 48 35",
    "sg:postcode":"74800",
    "sg:province":"Rhone-Alpes",
    "wof:name":"Seditube S.a.r.l.",
    "wof:placetype":"venue"
},
  "geometry": {"coordinates":[6.3298,46.073593],"type":"Point"}
}