{
  "type": "Feature",
  "properties": {
    "iso:country":"FR",
    "sg:address":"Rue de Diss\u00e9e",
    "sg:city":"Airvault",
    "sg:orig_category":"Unclassifiable Establishments",
    "sg:phone":"+33 5 49 70 85 70",
    "sg:postcode":"79600",
    "sg:province":"Poitou-Charentes",
    "wof:name":"Filec S.a.s.",
    "wof:placetype":"venue"
},
  "geometry": {"coordinates":[-0.134971,46.818661],"type":"Point"}
}