{
  "type": "Feature",
  "properties": {
    "addr:full":"120, Rue du Foss\u00e9 Blanc, 92230 Gennevilliers Ile de France",
    "addr:housenumber":"120",
    "addr:postcode":"92230;ile",
    "addr:street":"Rue Du Fosse\u0301 Blanc",
    "iso:country":"FR",
    "sg:address":"120, Rue du Foss\u00e9 Blanc, 92230 Gennevilliers",
    "sg:orig_category":"Unclassifiable Establishments",
    "sg:phone":"+33 1 47 98 82 14",
    "sg:province":"Ile de France",
    "wof:name":"Pum Plastiques S.a.",
    "wof:placetype":"venue"
},
  "geometry": {"coordinates":[2.308625,48.927979],"type":"Point"}
}