{
  "type": "Feature",
  "properties": {
    "addr:full":"800, Rte d'Annecy - La Culaz , 74370 Charvonnex Rhone-Alpes",
    "addr:housenumber":"800",
    "addr:postcode":"74370",
    "addr:street":"Rte D'Annecy La Culaz",
    "iso:country":"FR",
    "sg:address":"800, Rte d'Annecy - La Culaz , 74370 Charvonnex",
    "sg:orig_category":"Non-Classified Establishments",
    "sg:phone":"+33 4 50 60 12 98",
    "sg:province":"Rhone-Alpes",
    "wof:name":"Segros S.a.r.l.",
    "wof:placetype":"venue"
},
  "geometry": {"coordinates":[6.122654,45.939808],"type":"Point"}
}