{
  "type": "Feature",
  "properties": {
    "iso:country":"FR",
    "sg:address":"25 rue Jean Rostand 81000 Albi",
    "sg:classifiers":[
        {
            "category":"Professional",
            "subcategory":"Accounting & Tax Preparation",
            "type":"Services"
        }
    ],
    "sg:phone":"+33 5 63 77 80 60",
    "sg:postcode":"81000",
    "sg:province":"Midi Pyr\u00e9n\u00e9es",
    "sg:tags":[
        "mixed",
        "feed"
    ],
    "wof:name":"Phod\u00e9 Sa",
    "wof:placetype":"venue"
},
  "geometry": {"coordinates":[2.17648,43.92942],"type":"Point"}
}