{
  "type": "Feature",
  "properties": {
    "iso:country":"FR",
    "sg:address":"6, Rue des Clos - Z.I. Nord, 77100 Meaux",
    "sg:orig_category":"Unclassifiable Establishments",
    "sg:phone":"+33 1 60 09 79 60",
    "sg:province":"Ile de France",
    "wof:name":"A.b. Industrie S.a.",
    "wof:placetype":"venue"
},
  "geometry": {"coordinates":[2.883054,48.959351],"type":"Point"}
}