{
  "type": "Feature",
  "properties": {
    "addr:full":"2, Av. Thomas Edison, 86360 Chasseneuil du Poitou Poitou-Charentes",
    "addr:postcode":"86360",
    "addr:street":"Av. Thomas Edison",
    "iso:country":"FR",
    "sg:address":"2, Av. Thomas Edison, 86360 Chasseneuil du Poitou",
    "sg:orig_category":"Unclassifiable Establishments",
    "sg:phone":"+33 5 49 49 43 50",
    "sg:province":"Poitou-Charentes",
    "wof:name":"Easier S.a.",
    "wof:placetype":"venue"
},
  "geometry": {"coordinates":[0.362155,46.668926],"type":"Point"}
}