{
  "type": "Feature",
  "properties": {
    "addr:full":"14, Rue des Dominicaines, 13001 Marseille Poitou-Charentes",
    "addr:housenumber":"14",
    "addr:postcode":"13001",
    "addr:street":"Rue Des Dominicaines",
    "iso:country":"FR",
    "sg:address":"14, Rue des Dominicaines, 13001 Marseille",
    "sg:orig_category":"Non-Classified Establishments",
    "sg:phone":"+33 4 91 15 17 17",
    "sg:province":"Poitou-Charentes",
    "wof:name":"A.c.e.c.i. - Assistance Cr\u00e9ation Entreprises Et Coop\u00e9ratives I",
    "wof:placetype":"venue"
},
  "geometry": {"coordinates":[5.376663,43.299988],"type":"Point"}
}