{
  "type": "Feature",
  "properties": {
    "iso:country":"FR",
    "sg:address":"45 Av L\u00e9o Lagrange 63306 Thiers Cedex",
    "sg:classifiers":[
        {
            "category":"Shopping",
            "type":"Retail Goods"
        }
    ],
    "sg:phone":"+33 4 73 80 05 33",
    "sg:province":"Centre",
    "sg:tags":[
        "metallurgy",
        "finished",
        "-",
        "metalworking",
        "metallic"
    ],
    "wof:name":"Preciforge Sas",
    "wof:placetype":"venue"
},
  "geometry": {"coordinates":[3.532561,45.848423],"type":"Point"}
}