{
  "type": "Feature",
  "properties": {
    "addr:full":"38, Rue Mozart, 92587 Clichy C\u00e9dex Ile de France",
    "addr:housenumber":"38",
    "addr:postcode":"92587",
    "addr:street":"Rue Mozart",
    "iso:country":"FR",
    "sg:address":"38, Rue Mozart, 92587 Clichy C\u00e9dex",
    "sg:orig_category":"Non-Classified Establishments",
    "sg:phone":"+33 1 49 68 17 77",
    "sg:province":"Ile de France",
    "wof:name":"C.t. Environnement",
    "wof:placetype":"venue"
},
  "geometry": {"coordinates":[2.315341,48.906166],"type":"Point"}
}