{
  "type": "Feature",
  "properties": {
    "addr:full":"Les Ajoncs d'Or 35210 Montreuil des Landes Combourtill\u00e9 Bretagne 35210",
    "addr:postcode":"35210;35210",
    "addr:street":"Combourtille\u0301 Bretagne",
    "iso:country":"FR",
    "sg:address":"Les Ajoncs d'Or 35210 Montreuil des Landes",
    "sg:city":"Combourtill\u00e9",
    "sg:orig_category":"Non-Classified Establishments",
    "sg:phone":"+33 2 99 76 05 11",
    "sg:postcode":"35210",
    "sg:province":"Bretagne",
    "wof:name":"Etablissements Joseph Froc S.a.",
    "wof:placetype":"venue"
},
  "geometry": {"coordinates":[-1.22412,48.24712],"type":"Point"}
}