{
  "type": "Feature",
  "properties": {
    "addr:full":"B.P. 39, 78681 Ep\u00f4ne C\u00e9dex^^734, Av. de la Mauldre - Z.A. de la Couronne des Pr\u00e9s, 78680 Ep\u00f4ne Ile de France",
    "addr:postcode":"78681;78680",
    "addr:street":"B.P. 39;Av. De La Mauldre Z.A. De La Couronne Des Pre\u0301S;Ile De France",
    "iso:country":"FR",
    "sg:address":"B.P. 39, 78681 Ep\u00f4ne C\u00e9dex^^734, Av. de la Mauldre - Z.A. de la Couronne des Pr\u00e9s, 78680 Ep\u00f4ne",
    "sg:orig_category":"Non-Classified Establishments",
    "sg:phone":"+33 1 30 95 40 60",
    "sg:province":"Ile de France",
    "wof:name":"P.i.f. S.a.r.l. - Premier Industrial France",
    "wof:placetype":"venue"
},
  "geometry": {"coordinates":[-97.727592,30.519621],"type":"Point"}
}