{
  "type": "Feature",
  "properties": {
    "addr:full":"B.P. 60524, 60115 M\u00e9ru C\u00e9dex^^46, Rue Aristide Briand, 60110 M\u00e9ru Picardie",
    "addr:postcode":"60115;60110",
    "addr:street":"Rue Aristide Briand",
    "iso:country":"FR",
    "sg:address":"B.P. 60524, 60115 M\u00e9ru C\u00e9dex^^46, Rue Aristide Briand, 60110 M\u00e9ru",
    "sg:orig_category":"Non-Classified Establishments",
    "sg:phone":"+33 3 44 52 63 00",
    "sg:province":"Picardie",
    "wof:name":"Pr\u00e9vot\u00e9 Expedis S.a.s.",
    "wof:placetype":"venue"
},
  "geometry": {"coordinates":[2.135155,49.235676],"type":"Point"}
}