{
  "type": "Feature",
  "properties": {
    "addr:full":"105 Rue De Constantine 62200 Boulogne Sur Mer Nord Pas-de-Calais",
    "addr:housenumber":"105",
    "addr:postcode":"62200",
    "addr:street":"Rue De Constantine;Sur Mer Nord",
    "iso:country":"FR",
    "sg:address":"105 Rue De Constantine 62200 Boulogne Sur Mer",
    "sg:classifiers":[
        {
            "category":"Professional",
            "type":"Services"
        }
    ],
    "sg:phone":"+33 3 21 30 27 00",
    "sg:province":"Nord Pas-de-Calais",
    "sg:tags":[
        "transport",
        "road"
    ],
    "wof:name":"Transports Mounier Sa",
    "wof:placetype":"venue"
},
  "geometry": {"coordinates":[1.59326,50.717171],"type":"Point"}
}