{
  "type": "Feature",
  "properties": {
    "addr:full":"Avenue Roland Garros 56230 Questembert Questembert Bretagne 56230",
    "addr:postcode":"56230;56230",
    "addr:street":"Avenue Roland Garros",
    "iso:country":"FR",
    "sg:address":"Avenue Roland Garros 56230 Questembert",
    "sg:city":"Questembert",
    "sg:classifiers":[
        {
            "category":"Professional",
            "subcategory":"Business Services",
            "type":"Services"
        }
    ],
    "sg:phone":"+33 2 97 26 10 63",
    "sg:postcode":"56230",
    "sg:province":"Bretagne",
    "sg:tags":[
        "training",
        "advice"
    ],
    "wof:name":"College Jean Loup Chretien",
    "wof:placetype":"venue"
},
  "geometry": {"coordinates":[-2.460544,47.6623],"type":"Point"}
}