{
  "type": "Feature",
  "properties": {
    "addr:full":"6 Rue 10360 Fontette Champagne 10360",
    "addr:housenumber":"6",
    "addr:postcode":"10360;10360",
    "addr:street":"Rue;Champagne",
    "iso:country":"FR",
    "sg:address":"6",
    "sg:city":"Rue 10360 Fontette",
    "sg:classifiers":[
        {
            "category":"Food Court",
            "type":"Food & Drink"
        }
    ],
    "sg:phone":"+33 3 25 29 60 62",
    "sg:postcode":"10360",
    "sg:province":"Champagne",
    "sg:tags":[
        "product",
        "related"
    ],
    "wof:name":"Senez",
    "wof:placetype":"venue"
},
  "geometry": {"coordinates":[4.608211,48.081451],"type":"Point"}
}