{
  "type": "Feature",
  "properties": {
    "addr:full":"B.P. 6, 06331 Grasse C\u00e9dex^^Av. Michel Chevalier - Les Bois Mur\u00e9s , 06130 Grasse Poitou-Charentes",
    "addr:housenumber":"6",
    "addr:postcode":"06331;06130",
    "addr:street":"B.P.;Grasse",
    "iso:country":"FR",
    "sg:address":"B.P. 6, 06331 Grasse C\u00e9dex^^Av. Michel Chevalier - Les Bois Mur\u00e9s , 06130 Grasse",
    "sg:orig_category":"Non-Classified Establishments",
    "sg:phone":"+33 4 93 70 90 60",
    "sg:province":"Poitou-Charentes",
    "wof:name":"Jeanne Arth\u00e8s S.a.",
    "wof:placetype":"venue"
},
  "geometry": {"coordinates":[6.931647,43.649738],"type":"Point"}
}