{
  "type": "Feature",
  "properties": {
    "addr:full":"4, Rue Vaucanson - ZAC de Merci\u00e8res, 60200 Compi\u00e8gne Picardie 60200",
    "addr:housenumber":"4",
    "addr:postcode":"60200;60200",
    "addr:street":"Rue Vaucanson Zac De Mercie\u0300Res",
    "iso:country":"FR",
    "sg:address":"4, Rue Vaucanson - ZAC de Merci\u00e8res, 60200 Compi\u00e8gne",
    "sg:orig_category":"Non-Classified Establishments",
    "sg:phone":"+33 3 44 30 33 33",
    "sg:postcode":"60200",
    "sg:province":"Picardie",
    "wof:name":"E.t.i. S.a.",
    "wof:placetype":"venue"
},
  "geometry": {"coordinates":[2.787879,49.393848],"type":"Point"}
}