{
  "type": "Feature",
  "properties": {
    "iso:country":"FR",
    "sg:address":"5, Rue Jean Mermoz, 95740 Fr\u00e9pillon",
    "sg:orig_category":"Non-Classified Establishments",
    "sg:phone":"+33 1 30 40 79 77",
    "sg:province":"Ile de France",
    "wof:name":"Parcs Et Jardins Messina S.a.r.l.",
    "wof:placetype":"venue"
},
  "geometry": {"coordinates":[2.19744,49.050991],"type":"Point"}
}