{
  "type": "Feature",
  "properties": {
    "iso:country":"FR",
    "sg:address":"45 avenue Kl\u00e9ber 75116 Paris",
    "sg:classifiers":[
        {
            "category":"Banks & Credit Unions",
            "subcategory":"Investment Brokerage",
            "type":"Services"
        }
    ],
    "sg:phone":"+33 1 53 65 01 10",
    "sg:province":"Ile de France",
    "sg:tags":[
        "consulting"
    ],
    "wof:name":"Altium Capital S.a.r.l.",
    "wof:placetype":"venue"
},
  "geometry": {"coordinates":[2.291299,48.868286],"type":"Point"}
}