{
  "type": "Feature",
  "properties": {
    "iso:country":"FR",
    "sg:address":"Zone Industrielle",
    "sg:city":"Blendecques",
    "sg:orig_category":"Unclassifiable Establishments",
    "sg:phone":"+33 3 21 98 68 96",
    "sg:postcode":"62570",
    "sg:province":"Nord Pas-de-Calais",
    "wof:name":"C.f.c. S.a. - Compagnie Fran\u00e7aise De Chaudronnerie",
    "wof:placetype":"venue"
},
  "geometry": {"coordinates":[2.22875,50.710316],"type":"Point"}
}