{
  "type": "Feature",
  "properties": {
    "addr:full":"11, Rue du Faubourg Poissonni\u00e8re, 75009 Paris Ile de France 75009",
    "addr:housenumber":"11",
    "addr:postcode":"75009;75009",
    "addr:street":"Rue Du Faubourg Poissonnie\u0300Re",
    "iso:country":"FR",
    "sg:address":"11, Rue du Faubourg Poissonni\u00e8re, 75009 Paris",
    "sg:orig_category":"Non-Classified Establishments",
    "sg:phone":"+33 1 48 24 04 44",
    "sg:postcode":"75009",
    "sg:province":"Ile de France",
    "wof:name":"Air France",
    "wof:placetype":"venue"
},
  "geometry": {"coordinates":[2.347846,48.871773],"type":"Point"}
}