{
  "type": "Feature",
  "properties": {
    "iso:country":"FR",
    "sg:address":"La Foux 83580 Gassin",
    "sg:classifiers":[
        {
            "category":"Wholesale",
            "subcategory":"Wine & Distilled Alcoholic Beverages",
            "type":"Manufacturing & Wholesale Goods"
        }
    ],
    "sg:phone":"+33 4 94 56 32 04",
    "sg:province":"Centre",
    "sg:tags":[
        "french"
    ],
    "wof:name":"Les Ma\u00eetres Vignerons De La Presqu'ile De St Tropez (coop\u00e9rative Agricole)",
    "wof:placetype":"venue"
},
  "geometry": {"coordinates":[6.579258,43.263466],"type":"Point"}
}