{
  "type": "Feature",
  "properties": {
    "iso:country":"FR",
    "sg:address":"21b Av Louis Lumi\u00e9re 17187 Perigny",
    "sg:classifiers":[
        {
            "category":"Manufacturing",
            "subcategory":"Tools & Machinery",
            "type":"Manufacturing & Wholesale Goods"
        }
    ],
    "sg:phone":"+33 5 46 30 65 65",
    "sg:province":"Ile de France",
    "sg:tags":[
        "metallurgy",
        "metalworking"
    ],
    "wof:name":"Sefi Sa",
    "wof:placetype":"venue"
},
  "geometry": {"coordinates":[-1.104617,46.161499],"type":"Point"}
}