{
  "type": "Feature",
  "properties": {
    "iso:country":"FR",
    "sg:address":"1087 Rue De France 64300 Sault De Navailles",
    "sg:city":"Argagnon",
    "sg:classifiers":[
        {
            "category":"Wholesale",
            "subcategory":"Meat",
            "type":"Manufacturing & Wholesale Goods"
        }
    ],
    "sg:phone":"+33 5 59 67 50 07",
    "sg:postcode":"64300",
    "sg:province":"Aquitaine",
    "sg:tags":[
        "food",
        "cooked",
        "product",
        "related"
    ],
    "wof:name":"Etablissements Michel Dupuy Sa",
    "wof:placetype":"venue"
},
  "geometry": {"coordinates":[-0.666779,43.557415],"type":"Point"}
}