{
  "type": "Feature",
  "properties": {
    "addr:full":"Za Les Pins 43620 St Pal De Mons Saint-Romain-Lachalm Auvergne 43620",
    "addr:postcode":"43620;43620",
    "addr:street":"Za Les Pins;Mons Saint-Romain-Lachalm",
    "iso:country":"FR",
    "sg:address":"Za Les Pins 43620 St Pal De Mons",
    "sg:city":"Saint-Romain-Lachalm",
    "sg:classifiers":[
        {
            "category":"Manufacturing",
            "subcategory":"Rubber & Plastics",
            "type":"Manufacturing & Wholesale Goods"
        }
    ],
    "sg:phone":"+33 4 71 66 62 32",
    "sg:postcode":"43620",
    "sg:province":"Auvergne",
    "sg:tags":[
        "packaging",
        "material",
        "-"
    ],
    "wof:name":"Janu'sac",
    "wof:placetype":"venue"
},
  "geometry": {"coordinates":[4.274325,45.246166],"type":"Point"}
}