{
  "type": "Feature",
  "properties": {
    "addr:full":"Av. du District - Z.I. Faulquemont Lorraine 57380",
    "addr:postcode":"57380",
    "addr:street":"Av. Du District",
    "iso:country":"FR",
    "sg:address":"Av. du District - Z.I.",
    "sg:city":"Faulquemont",
    "sg:orig_category":"SERVICES: INSTALLATION ROBOTIQUE SUR CHA\u00ceNE DE MONTAGE AUTOMOBILE, R\u00c9FECTION DE BLOCS DE CHANTIER, I",
    "sg:phone":"+33 6 72 14 59 30",
    "sg:postcode":"57380",
    "sg:province":"Lorraine",
    "wof:name":"E.m.s.i S.a.r.l.",
    "wof:placetype":"venue"
},
  "geometry": {"coordinates":[6.599175,49.042831],"type":"Point"}
}