{
  "type": "Feature",
  "properties": {
    "iso:country":"FR",
    "sg:address":"113 Chemin Du Milon 69126 Brindas",
    "sg:classifiers":[
        {
            "category":"Manufacturing",
            "subcategory":"Metals",
            "type":"Manufacturing & Wholesale Goods"
        }
    ],
    "sg:phone":"+33 4 78 45 47 27",
    "sg:postcode":"69126",
    "sg:province":"Rhone-Alpes",
    "sg:tags":[
        "metallurgy",
        "metalworking",
        "processing"
    ],
    "wof:name":"Cintrag Industrie Cintrag Industrie",
    "wof:placetype":"venue"
},
  "geometry": {"coordinates":[4.709004,45.70575],"type":"Point"}
}