{
  "type": "Feature",
  "properties": {
    "iso:country":"FR",
    "sg:address":"129, Rue Ganzau, 67100 Strasbourg",
    "sg:city":"Strasbourg",
    "sg:orig_category":"Unclassifiable Establishments",
    "sg:phone":"+33 3 88 65 95 65",
    "sg:postcode":"67100",
    "sg:province":"Alsace",
    "wof:name":"Metz S.a.",
    "wof:placetype":"venue"
},
  "geometry": {"coordinates":[7.760753,48.533539],"type":"Point"}
}