{
  "type": "Feature",
  "properties": {
    "addr:full":"B.P. 1, 68600 Volgelsheim^^2, Rue du Pourquoi Pas - Z.A., 68600 Volgelsheim Volgelsheim Alsace 68600",
    "addr:housenumber":"1",
    "addr:postcode":"68600;68600;68600",
    "addr:street":"B.P.;Rue Du Pourquoi Pas",
    "iso:country":"FR",
    "sg:address":"B.P. 1, 68600 Volgelsheim^^2, Rue du Pourquoi Pas - Z.A., 68600 Volgelsheim",
    "sg:city":"Volgelsheim",
    "sg:orig_category":"Non-Classified Establishments",
    "sg:phone":"+33 3 89 30 30 20",
    "sg:postcode":"68600",
    "sg:province":"Alsace",
    "wof:name":"Ab\u00e9dis S.a.",
    "wof:placetype":"venue"
},
  "geometry": {"coordinates":[7.552925,48.01693],"type":"Point"}
}