{
  "type": "Feature",
  "properties": {
    "addr:full":"95/101, Rue des Solets, 94150 Rungis Ile de France",
    "addr:housenumber":"95 / 101",
    "addr:postcode":"94150",
    "addr:street":"Rue Des Solets",
    "iso:country":"FR",
    "sg:address":"95/101, Rue des Solets, 94150 Rungis",
    "sg:orig_category":"Unclassifiable Establishments",
    "sg:phone":"+33 1 45 60 30 00",
    "sg:province":"Ile de France",
    "wof:name":"Intergraph France S.a.",
    "wof:placetype":"venue"
},
  "geometry": {"coordinates":[2.358515,48.744316],"type":"Point"}
}