{
  "type": "Feature",
  "properties": {
    "iso:country":"FR",
    "sg:address":"50-52 rue Louveau 92320 Chatillon",
    "sg:orig_category":"Skim Milk Powder",
    "sg:phone":"+33 1 46 42 14 14",
    "sg:province":"Ile de France",
    "wof:name":"Elecrem S.a.",
    "wof:placetype":"venue"
},
  "geometry": {"coordinates":[2.29465,48.802879],"type":"Point"}
}