{
  "type": "Feature",
  "properties": {
    "addr:full":"B.P. 197, 70004 Vesoul C\u00e9dex^^Z.A.A.T. Ouest, 70000 Vesoul Franche Comt\u00e9 70000",
    "addr:housenumber":"b.p. 197",
    "addr:postcode":"70004;70000;70000",
    "addr:street":"A.A.T. Ouest;Franche Comte\u0301",
    "iso:country":"FR",
    "sg:address":"B.P. 197, 70004 Vesoul C\u00e9dex^^Z.A.A.T. Ouest, 70000 Vesoul",
    "sg:orig_category":"Non-Classified Establishments",
    "sg:phone":"+33 3 84 97 18 50",
    "sg:postcode":"70000",
    "sg:province":"Franche Comt\u00e9",
    "wof:name":"Calberson S.m. S.a.",
    "wof:placetype":"venue"
},
  "geometry": {"coordinates":[6.034054,47.524078],"type":"Point"}
}