{
  "type": "Feature",
  "properties": {
    "addr:full":"87, Av. du G\u00e9n\u00e9ral Galli\u00e9ni, 10300 Sainte Savine Champagne",
    "addr:postcode":"10300",
    "addr:street":"87 Av. Du Ge\u0301Ne\u0301Ral Gallie\u0301Ni",
    "iso:country":"FR",
    "sg:address":"87, Av. du G\u00e9n\u00e9ral Galli\u00e9ni, 10300 Sainte Savine",
    "sg:orig_category":"Unclassifiable Establishments",
    "sg:phone":"+33 3 25 45 10 66",
    "sg:province":"Champagne",
    "wof:name":"Flash Service S.a.r.l.",
    "wof:placetype":"venue"
},
  "geometry": {"coordinates":[4.052662,48.293652],"type":"Point"}
}