{
  "type": "Feature",
  "properties": {
    "iso:country":"FR",
    "sg:address":"Av. de l'Europe - ZAC de la Thalie",
    "sg:city":"Ch\u00e2lon sur Sa\u00f4ne",
    "sg:orig_category":"Unclassifiable Establishments",
    "sg:phone":"+33 4 73 23 10 10",
    "sg:postcode":"71100",
    "sg:province":"Bourgogne",
    "wof:name":"Ineo Com Centre Est S.n.c.",
    "wof:placetype":"venue"
},
  "geometry": {"coordinates":[2.481493,48.891426],"type":"Point"}
}