{
  "type": "Feature",
  "properties": {
    "addr:full":"Av Ariane Parc Cadera Sud Bat O 33700 Merignac M\u00e9rignac Aquitaine 33700",
    "addr:housenumber":"o",
    "addr:postcode":"33700;33700",
    "addr:street":"Av Ariane Parc Cadera Sud",
    "iso:country":"FR",
    "sg:address":"Av Ariane Parc Cadera Sud Bat O 33700 Merignac",
    "sg:city":"M\u00e9rignac",
    "sg:classifiers":[
        {
            "category":"Wholesale",
            "subcategory":"Farm Supplies",
            "type":"Manufacturing & Wholesale Goods"
        }
    ],
    "sg:phone":"+33 5 56 47 89 54",
    "sg:postcode":"33700",
    "sg:province":"Aquitaine",
    "sg:tags":[
        "-",
        "machine",
        "equipment",
        "engineering",
        "machinery",
        "mechanical",
        "agriculture"
    ],
    "wof:name":"Andreas Stihl Sarl",
    "wof:placetype":"venue"
},
  "geometry": {"coordinates":[-0.68435,44.833637],"type":"Point"}
}