{
  "type": "Feature",
  "properties": {
    "iso:country":"FR",
    "sg:address":"7, Rue Pierre S\u00e9mard, 27930 Gravigny",
    "sg:orig_category":"Non-Classified Establishments",
    "sg:phone":"+33 2 32 29 27 27",
    "sg:province":"Haute Normandie",
    "wof:name":"Sernam - Service Nationale De Messagerie",
    "wof:placetype":"venue"
},
  "geometry": {"coordinates":[1.16792,49.054756],"type":"Point"}
}