{
  "type": "Feature",
  "properties": {
    "addr:full":"4 rue des Terres Rouges 57100 Thionville Lorraine",
    "addr:housenumber":"4",
    "addr:postcode":"57100",
    "addr:street":"Rue Des Terres Rouges",
    "iso:country":"FR",
    "sg:address":"4 rue des Terres Rouges 57100 Thionville",
    "sg:classifiers":[
        {
            "category":"Manufacturing",
            "subcategory":"Motor Vehicles & Parts",
            "type":"Manufacturing & Wholesale Goods"
        }
    ],
    "sg:phone":"+33 3 82 82 83 44",
    "sg:province":"Lorraine",
    "sg:tags":[
        "precision",
        "mechanic"
    ],
    "wof:name":"Bouster Industries S.a.r.l",
    "wof:placetype":"venue"
},
  "geometry": {"coordinates":[6.101493,49.364487],"type":"Point"}
}