{
  "type": "Feature",
  "properties": {
    "iso:country":"FR",
    "sg:address":"10, Place de la Joliette - Les Docks Atrium 104, 13002 Marseille",
    "sg:orig_category":"Non-Classified Establishments",
    "sg:phone":"+33 4 91 99 03 00",
    "sg:province":"Poitou-Charentes",
    "wof:name":"Danzas Aei Danzas Intercontinental",
    "wof:placetype":"venue"
},
  "geometry": {"coordinates":[5.37001,43.296101],"type":"Point"}
}