{
  "type": "Feature",
  "properties": {
    "addr:full":"B.P. 13, 29880 Plouguerneau^^ZI des Helles, 29880 Plouguerneau Plouguerneau Bretagne 29880",
    "addr:postcode":"29880;29880;29880",
    "addr:street":"B.P. 13;Des Helles",
    "iso:country":"FR",
    "sg:address":"B.P. 13, 29880 Plouguerneau^^ZI des Helles, 29880 Plouguerneau",
    "sg:city":"Plouguerneau",
    "sg:orig_category":"Non-Classified Establishments",
    "sg:phone":"+33 2 98 04 79 94",
    "sg:postcode":"29880",
    "sg:province":"Bretagne",
    "wof:name":"Embal'jet S.a.",
    "wof:placetype":"venue"
},
  "geometry": {"coordinates":[-4.462985,48.591148],"type":"Point"}
}