{
  "type": "Feature",
  "properties": {
    "addr:full":"B.P. 11, 59374 Loos C\u00e9dex^^128, Chemin des Postes, 59120 Loos Nord Pas-de-Calais 59120",
    "addr:postcode":"59374;59120;59120",
    "addr:street":"B.P. 11;Chemin Des Postes",
    "iso:country":"FR",
    "sg:address":"B.P. 11, 59374 Loos C\u00e9dex^^128, Chemin des Postes, 59120 Loos",
    "sg:orig_category":"Non-Classified Establishments",
    "sg:phone":"+33 3 20 62 99 62",
    "sg:postcode":"59120",
    "sg:province":"Nord Pas-de-Calais",
    "wof:name":"Cuppens S.a.",
    "wof:placetype":"venue"
},
  "geometry": {"coordinates":[3.015711,50.615021],"type":"Point"}
}