{
  "type": "Feature",
  "properties": {
    "iso:country":"FR",
    "sg:address":"12",
    "sg:city":"Napol\u00e9on 1er 57170 Ch\u00e2teau Salins",
    "sg:classifiers":[
        {
            "category":"Manufacturing",
            "subcategory":"Wood Products",
            "type":"Manufacturing & Wholesale Goods"
        }
    ],
    "sg:phone":"+33 3 87 05 18 65",
    "sg:province":"Lorraine",
    "sg:tags":[
        "professional",
        "furniture"
    ],
    "wof:name":"Stand'est Concept Expo",
    "wof:placetype":"venue"
},
  "geometry": {"coordinates":[6.51447,48.818859],"type":"Point"}
}