{
  "type": "Feature",
  "properties": {
    "addr:full":"14 Rue Du Petit Albi 95801 Cergy Pontoise Cedex Midi Pyr\u00e9n\u00e9es",
    "addr:housenumber":"14",
    "addr:postcode":"95801",
    "addr:street":"Rue Du Petit Albi",
    "iso:country":"FR",
    "sg:address":"14 Rue Du Petit Albi 95801 Cergy Pontoise Cedex",
    "sg:classifiers":[
        {
            "category":"Professional",
            "subcategory":"Computer Services",
            "type":"Services"
        }
    ],
    "sg:phone":"+33 1 34 24 88 11",
    "sg:province":"Midi Pyr\u00e9n\u00e9es",
    "sg:tags":[
        "information",
        "technology"
    ],
    "wof:name":"Maxell France Sa",
    "wof:placetype":"venue"
},
  "geometry": {"coordinates":[2.035065,49.056],"type":"Point"}
}