{
  "type": "Feature",
  "properties": {
    "iso:country":"FR",
    "sg:address":"7, Rue du 8 Mai 1940, 64300 Orthez",
    "sg:city":"Orthez",
    "sg:orig_category":"Non-Classified Establishments",
    "sg:phone":"+33 5 59 69 06 20",
    "sg:postcode":"64300",
    "sg:province":"Aquitaine",
    "wof:name":"Point P Sud Ouest S.a.",
    "wof:placetype":"venue"
},
  "geometry": {"coordinates":[-0.773174,43.48735],"type":"Point"}
}