{
  "type": "Feature",
  "properties": {
    "iso:country":"FR",
    "sg:address":"RN 13 - La Blanchuquet",
    "sg:city":"Tollevast",
    "sg:orig_category":"Non-Classified Establishments",
    "sg:phone":"+33 2 33 22 54 22",
    "sg:postcode":"50470",
    "sg:province":"Basse Normandie",
    "wof:name":"Brudan' Paysages S.a.r.l.",
    "wof:placetype":"venue"
},
  "geometry": {"coordinates":[-1.603544,49.614346],"type":"Point"}
}