{
  "type": "Feature",
  "properties": {
    "iso:country":"FR",
    "sg:address":"3, Cour de la Brocante, 44000 Nantes",
    "sg:orig_category":"Unclassifiable Establishments",
    "sg:phone":"+33 2 51 82 38 23",
    "sg:province":"Pays de Loire",
    "wof:name":"Oki Syst\u00e8mes France S.a.",
    "wof:placetype":"venue"
},
  "geometry": {"coordinates":[-1.562988,47.221867],"type":"Point"}
}