{
  "type": "Feature",
  "properties": {
    "iso:country":"FR",
    "sg:address":"B.P. 53, 73802 Montm\u00e9lian Cedex^^22, Rue Dupuy, 73800 Montm\u00e9lian",
    "sg:orig_category":"Non-Classified Establishments",
    "sg:phone":"+33 4 79 65 24 63",
    "sg:postcode":"73800",
    "sg:province":"Rhone-Alpes",
    "wof:name":"A.l.t.e.a. M.s.o. S.a. - Alpes Techniques Equipements Aciers",
    "wof:placetype":"venue"
},
  "geometry": {"coordinates":[6.038695,45.448456],"type":"Point"}
}