{
  "type": "Feature",
  "properties": {
    "addr:full":"39 Rue Nationale 57800 Rosbruck Lorraine 57800",
    "addr:housenumber":"39",
    "addr:postcode":"57800;57800",
    "addr:street":"Rue Nationale",
    "iso:country":"FR",
    "sg:address":"39 Rue Nationale 57800 Rosbruck",
    "sg:classifiers":[
        {
            "category":"Autos & Motor Vehicles",
            "subcategory":"Automobile Sales",
            "type":"Retail Goods"
        }
    ],
    "sg:phone":"+33 3 87 00 28 30",
    "sg:postcode":"57800",
    "sg:province":"Lorraine",
    "sg:tags":[
        "equipment",
        "motor-cars",
        "transport"
    ],
    "wof:name":"Hale France",
    "wof:placetype":"venue"
},
  "geometry": {"coordinates":[6.858166,49.163536],"type":"Point"}
}