{
  "type": "Feature",
  "properties": {
    "addr:full":"41 Rue De La Tour La Tour 77410 Villevaude Ile de France 77410",
    "addr:housenumber":"41",
    "addr:postcode":"77410;77410",
    "addr:street":"Rue De La Tour La;Ile De France",
    "iso:country":"FR",
    "sg:address":"41 Rue De La Tour",
    "sg:city":"La Tour 77410 Villevaude",
    "sg:classifiers":[
        {
            "category":"Building & Trades",
            "subcategory":"Construction",
            "type":"Services"
        }
    ],
    "sg:phone":"+33 1 60 26 92 70",
    "sg:postcode":"77410",
    "sg:province":"Ile de France",
    "sg:tags":[
        "work",
        "public"
    ],
    "wof:name":"Jardem",
    "wof:placetype":"venue"
},
  "geometry": {"coordinates":[2.68843,48.945576],"type":"Point"}
}