{
  "type": "Feature",
  "properties": {
    "addr:full":"Av. de l'Arm\u00e9e des Alpes - ZI de la Croix Sarrians Provence-Alpes-C\u00f4te d'Azur 84260",
    "addr:postcode":"84260",
    "addr:street":"Av. De L'Arme;Sarrians",
    "iso:country":"FR",
    "sg:address":"Av. de l'Arm\u00e9e des Alpes - ZI de la Croix",
    "sg:city":"Sarrians",
    "sg:orig_category":"Unclassifiable Establishments",
    "sg:phone":"+33 4 90 12 26 00",
    "sg:postcode":"84260",
    "sg:province":"Provence-Alpes-C\u00f4te d'Azur",
    "wof:name":"Scampi S.a.",
    "wof:placetype":"venue"
},
  "geometry": {"coordinates":[4.970531,44.081364],"type":"Point"}
}