{
  "type": "Feature",
  "properties": {
    "iso:country":"FR",
    "sg:address":"80 Rue De Vesle 51100 Reims",
    "sg:classifiers":[
        {
            "category":"Bakery",
            "type":"Food & Drink"
        }
    ],
    "sg:phone":"+33 3 26 47 40 20",
    "sg:postcode":"51100",
    "sg:province":"Champagne",
    "sg:tags":[
        "cake",
        "product",
        "related",
        "bread"
    ],
    "wof:name":"Societe A Responsabilite Limitee Le Four A Bois",
    "wof:placetype":"venue"
},
  "geometry": {"coordinates":[4.026956,49.252968],"type":"Point"}
}