{
  "type": "Feature",
  "properties": {
    "addr:full":"B.P. 30566, 57010 Metz C\u00e9dex 1^^2, Place Saint Martin, 57000 Metz Lorraine",
    "addr:housenumber":"1 ^ ^ 2",
    "addr:postcode":"57010;57000",
    "addr:street":"Ce\u0301Dex;Place Saint Martin",
    "iso:country":"FR",
    "sg:address":"B.P. 30566, 57010 Metz C\u00e9dex 1^^2, Place Saint Martin, 57000 Metz",
    "sg:orig_category":"Non-Classified Establishments",
    "sg:phone":"+33 3 87 39 58 58",
    "sg:province":"Lorraine",
    "wof:name":"Financi\u00e8re R\u00e9gionale De Cr\u00e9dits Immobiliers De L'est",
    "wof:placetype":"venue"
},
  "geometry": {"coordinates":[6.183995,49.07645],"type":"Point"}
}