{
  "type": "Feature",
  "properties": {
    "addr:full":"Impasse du Renivet Salaise sur Sanne Rhone-Alpes 38150",
    "addr:postcode":"38150",
    "addr:street":"Impasse Du Renivet Salaise Sur;Rhone-Alpes",
    "iso:country":"FR",
    "sg:address":"Impasse du Renivet",
    "sg:city":"Salaise sur Sanne",
    "sg:orig_category":"Non-Classified Establishments",
    "sg:phone":"+33 4 74 29 71 29",
    "sg:postcode":"38150",
    "sg:province":"Rhone-Alpes",
    "wof:name":"Entreprise Lafaury S.a.r.l.",
    "wof:placetype":"venue"
},
  "geometry": {"coordinates":[4.804031,45.350933],"type":"Point"}
}