{
  "type": "Feature",
  "properties": {
    "addr:full":"6, Rue du Commerce, 67550 Vendenheim Vendenheim Alsace 67550",
    "addr:housenumber":"6",
    "addr:postcode":"67550;67550",
    "addr:street":"Rue Du Commerce",
    "iso:country":"FR",
    "sg:address":"6, Rue du Commerce, 67550 Vendenheim",
    "sg:city":"Vendenheim",
    "sg:orig_category":"Unclassifiable Establishments",
    "sg:phone":"+33 3 88 81 81 52",
    "sg:postcode":"67550",
    "sg:province":"Alsace",
    "wof:name":"Rowastores E.u.r.l.",
    "wof:placetype":"venue"
},
  "geometry": {"coordinates":[7.728688,48.659115],"type":"Point"}
}