{
  "type": "Feature",
  "properties": {
    "addr:full":"1, Bd de l'Oc\u00e9an - Parc Silic - B\u00e2t C1, 13009 Marseille Poitou-Charentes",
    "addr:housenumber":"1;ba\u0302t c1",
    "addr:postcode":"13009",
    "addr:street":"Bd De L'Oce \u0301An Parc Silic",
    "iso:country":"FR",
    "sg:address":"1, Bd de l'Oc\u00e9an - Parc Silic - B\u00e2t C1, 13009 Marseille",
    "sg:orig_category":"Unclassifiable Establishments",
    "sg:phone":"+33 4 91 72 04 00",
    "sg:province":"Poitou-Charentes",
    "wof:name":"Ingerop M\u00e9diterran\u00e9e S.a.s.",
    "wof:placetype":"venue"
},
  "geometry": {"coordinates":[5.440713,43.413174],"type":"Point"}
}