{
  "type": "Feature",
  "properties": {
    "addr:full":"Tr\u00e9moulis 48500 La Canourgue Languedoc-Roussillon",
    "addr:postcode":"48500",
    "addr:street":"Tre\u0301Moulis",
    "iso:country":"FR",
    "sg:address":"Tr\u00e9moulis 48500 La Canourgue",
    "sg:orig_category":"Unclassifiable Establishments",
    "sg:phone":"+33 4 66 32 80 63",
    "sg:province":"Languedoc-Roussillon",
    "wof:name":"Deltour S.a.",
    "wof:placetype":"venue"
},
  "geometry": {"coordinates":[3.222417,44.427361],"type":"Point"}
}