{
  "type": "Feature",
  "properties": {
    "addr:full":"6 Pl St B\u00e9nigne 21000 Dijon Dijon Bourgogne 21000",
    "addr:housenumber":"6",
    "addr:postcode":"21000;21000",
    "addr:street":"Pl St",
    "iso:country":"FR",
    "sg:address":"6 Pl St B\u00e9nigne 21000 Dijon",
    "sg:city":"Dijon",
    "sg:classifiers":[
        {
            "category":"Health Services",
            "subcategory":"Podiatrist",
            "type":"Services"
        }
    ],
    "sg:phone":"+33 3 80 30 58 51",
    "sg:postcode":"21000",
    "sg:province":"Bourgogne",
    "sg:tags":[
        "equipment",
        "electrical",
        "-",
        "electronic",
        "instrument"
    ],
    "wof:name":"Scm Docteurs Leflot Savioli Tainturier",
    "wof:placetype":"venue"
},
  "geometry": {"coordinates":[5.033956,47.32127],"type":"Point"}
}