{
  "type": "Feature",
  "properties": {
    "addr:full":"Zi 76870 Gaillefontaine Haute Normandie 76870",
    "addr:postcode":"76870;76870",
    "addr:street":"Zi;Haute Normandie",
    "iso:country":"FR",
    "sg:address":"Zi 76870 Gaillefontaine",
    "sg:classifiers":[
        {
            "category":"Manufacturing",
            "subcategory":"Glass & Minerals",
            "type":"Manufacturing & Wholesale Goods"
        }
    ],
    "sg:phone":"+33 2 32 89 93 93",
    "sg:postcode":"76870",
    "sg:province":"Haute Normandie",
    "sg:tags":[
        "building",
        "material"
    ],
    "wof:name":"Pilkington France Sa",
    "wof:placetype":"venue"
},
  "geometry": {"coordinates":[1.61683,49.65324],"type":"Point"}
}