{
  "type": "Feature",
  "properties": {
    "addr:full":"91, Rue Racine, 69100 Villeurbanne Rhone-Alpes 69100",
    "addr:housenumber":"91",
    "addr:postcode":"69100;69100",
    "addr:street":"Rue Racine",
    "iso:country":"FR",
    "sg:address":"91, Rue Racine, 69100 Villeurbanne",
    "sg:orig_category":"Non-Classified Establishments",
    "sg:phone":"+33 4 78 85 93 43",
    "sg:postcode":"69100",
    "sg:province":"Rhone-Alpes",
    "wof:name":"C.m.l. Pascal S.a. - Cartonnage Des Monts Du Lyonnais Pascal",
    "wof:placetype":"venue"
},
  "geometry": {"coordinates":[4.878404,45.763332],"type":"Point"}
}