{
  "type": "Feature",
  "properties": {
    "addr:full":"B.P. 323, 73375 Le Bourget du Lac C\u00e9dex^^Savoie Technolac - l'Alouette II, 73370 Le Bourget du Lac Rhone-Alpes 73370",
    "addr:housenumber":"b.p. 323",
    "addr:postcode":"73375;73370;73370",
    "addr:street":"L'Alouette",
    "iso:country":"FR",
    "sg:address":"B.P. 323, 73375 Le Bourget du Lac C\u00e9dex^^Savoie Technolac - l'Alouette II, 73370 Le Bourget du Lac",
    "sg:orig_category":"Non-Classified Establishments",
    "sg:phone":"+33 4 79 25 39 60",
    "sg:postcode":"73370",
    "sg:province":"Rhone-Alpes",
    "wof:name":"1\u00e8re Position S.a.",
    "wof:placetype":"venue"
},
  "geometry": {"coordinates":[5.866376,45.643951],"type":"Point"}
}