{
  "type": "Feature",
  "properties": {
    "iso:country":"FR",
    "sg:address":"R.N. 66 - Techno Park",
    "sg:city":"Schlierbach",
    "sg:orig_category":"Unclassifiable Establishments",
    "sg:phone":"+33 3 89 81 37 47",
    "sg:postcode":"68440",
    "sg:province":"Alsace",
    "wof:name":"Enderlin S.a.r.l.",
    "wof:placetype":"venue"
},
  "geometry": {"coordinates":[7.416665,47.728642],"type":"Point"}
}