{
  "type": "Feature",
  "properties": {
    "addr:full":"11 rue Bailly 92200 Neuilly sur Seine Ile de France 92200",
    "addr:housenumber":"11",
    "addr:postcode":"92200;92200",
    "addr:street":"Rue Bailly",
    "iso:country":"FR",
    "sg:address":"11 rue Bailly 92200 Neuilly sur Seine",
    "sg:classifiers":[
        {
            "category":"Professional",
            "subcategory":"Advertising",
            "type":"Services"
        }
    ],
    "sg:phone":"+33 1 40 88 07 08",
    "sg:postcode":"92200",
    "sg:province":"Ile de France",
    "sg:tags":[
        "image"
    ],
    "wof:name":"Amadeus International Sarl",
    "wof:placetype":"venue"
},
  "geometry": {"coordinates":[2.260104,48.886307],"type":"Point"}
}