{
  "type": "Feature",
  "properties": {
    "iso:country":"FR",
    "sg:address":"18 Rue De La R\u00e9publique 92190 Meudon",
    "sg:classifiers":[
        {
            "category":"Professional",
            "subcategory":"Business Services",
            "type":"Services"
        }
    ],
    "sg:phone":"+33 1 41 14 34 56",
    "sg:postcode":"92190",
    "sg:province":"Ile de France",
    "sg:tags":[
        "training",
        "advice"
    ],
    "wof:name":"Institution Notre Dame",
    "wof:placetype":"venue"
},
  "geometry": {"coordinates":[2.235956,48.809063],"type":"Point"}
}