{
  "type": "Feature",
  "properties": {
    "iso:country":"FR",
    "sg:address":"11 avenue de la Paix 69650 St Germain au Mont d'Or",
    "sg:classifiers":[
        {
            "category":"Shopping",
            "subcategory":"Stationery & Office Supplies",
            "type":"Retail Goods"
        }
    ],
    "sg:phone":"+33 4 72 08 19 19",
    "sg:province":"Rhone-Alpes",
    "sg:tags":[
        "packaging"
    ],
    "wof:name":"Thimonnier Sa",
    "wof:placetype":"venue"
},
  "geometry": {"coordinates":[4.801279,45.883884],"type":"Point"}
}