{
  "type": "Feature",
  "properties": {
    "addr:full":"8 Bis Rue Escudier 92100 Boulogne Billancourt Ile de France 92100",
    "addr:housenumber":"8 bis",
    "addr:postcode":"92100;92100",
    "addr:street":"Rue Escudier",
    "iso:country":"FR",
    "sg:address":"8 Bis Rue Escudier 92100 Boulogne Billancourt",
    "sg:classifiers":[
        {
            "category":"Banks & Credit Unions",
            "subcategory":"Financial Services",
            "type":"Services"
        }
    ],
    "sg:phone":"+33 1 47 12 42 12",
    "sg:postcode":"92100",
    "sg:province":"Ile de France",
    "sg:tags":[
        "finance",
        "-",
        "institution",
        "machine",
        "banking",
        "engineering",
        "mechanical",
        "insurance"
    ],
    "wof:name":"Idex Sa",
    "wof:placetype":"venue"
},
  "geometry": {"coordinates":[2.233278,48.843185],"type":"Point"}
}