{
  "type": "Feature",
  "properties": {
    "addr:full":"21 Rue De Ch\u00e2tillon 75014 Paris Ile de France 75014",
    "addr:housenumber":"21",
    "addr:postcode":"75014;75014",
    "addr:street":"Rue De Cha\u0302Tillon",
    "iso:country":"FR",
    "sg:address":"21 Rue De Ch\u00e2tillon 75014 Paris",
    "sg:classifiers":[
        {
            "category":"Professional",
            "subcategory":"Printing & Photocopies",
            "type":"Services"
        }
    ],
    "sg:phone":"+33 1 45 41 52 60",
    "sg:postcode":"75014",
    "sg:province":"Ile de France",
    "sg:tags":[
        "information",
        "technology",
        "publishing",
        "software"
    ],
    "wof:name":"Bussiere Sarl",
    "wof:placetype":"venue"
},
  "geometry": {"coordinates":[2.321868,48.827782],"type":"Point"}
}