{
  "type": "Feature",
  "properties": {
    "addr:full":"5, Bd de la Prague, 30000 N\u00eemes Languedoc-Roussillon 30000",
    "addr:housenumber":"5",
    "addr:postcode":"30000;30000",
    "addr:street":"Bd De La Prague",
    "iso:country":"FR",
    "sg:address":"5, Bd de la Prague, 30000 N\u00eemes",
    "sg:orig_category":"Non-Classified Establishments",
    "sg:phone":"+33 4 66 76 58 00",
    "sg:postcode":"30000",
    "sg:province":"Languedoc-Roussillon",
    "wof:name":"A.i.a.c. - Association D'aide \u00e0 La Construction",
    "wof:placetype":"venue"
},
  "geometry": {"coordinates":[4.363473,43.835342],"type":"Point"}
}