{
  "type": "Feature",
  "properties": {
    "addr:full":"4, Rte de Versailles, 78150 Rocquencourt Ile de France",
    "addr:housenumber":"4",
    "addr:postcode":"78150;ile",
    "addr:street":"Rte De Versailles",
    "iso:country":"FR",
    "sg:address":"4, Rte de Versailles, 78150 Rocquencourt",
    "sg:orig_category":"Non-Classified Establishments",
    "sg:phone":"+33 1 39 54 96 12",
    "sg:province":"Ile de France",
    "wof:name":"Systherm S.a.r.l.",
    "wof:placetype":"venue"
},
  "geometry": {"coordinates":[2.110988,48.838135],"type":"Point"}
}