{
  "type": "Feature",
  "properties": {
    "addr:full":"4 Rue Bellevue 67870 Griesheim Pr\u00e8s Molsheim Bischoffsheim Alsace 67870",
    "addr:housenumber":"4",
    "addr:postcode":"67870;67870",
    "addr:street":"Rue Bellevue;Bischoffsheim",
    "iso:country":"FR",
    "sg:address":"4 Rue Bellevue 67870 Griesheim Pr\u00e8s Molsheim",
    "sg:city":"Bischoffsheim",
    "sg:classifiers":[
        {
            "category":"Professional",
            "type":"Services"
        }
    ],
    "sg:phone":"+33 3 88 38 62 25",
    "sg:postcode":"67870",
    "sg:province":"Alsace",
    "sg:tags":[
        "transport",
        "road"
    ],
    "wof:name":"Transports Geissel",
    "wof:placetype":"venue"
},
  "geometry": {"coordinates":[7.53041,48.507153],"type":"Point"}
}