{
  "type": "Feature",
  "properties": {
    "iso:country":"FR",
    "sg:address":"250, Rue Gireaudeau, 37000 Tours",
    "sg:city":"Tours",
    "sg:orig_category":"Unclassifiable Establishments",
    "sg:phone":"+33 2 47 36 28 28",
    "sg:postcode":"37000",
    "sg:province":"Centre",
    "wof:name":"C.g.e Distribution S.a.r.l.",
    "wof:placetype":"venue"
},
  "geometry": {"coordinates":[0.67751,47.378139],"type":"Point"}
}