{
  "type": "Feature",
  "properties": {
    "iso:country":"FR",
    "sg:address":"Rte de Mayac - Le Vignaud",
    "sg:city":"Mayac",
    "sg:orig_category":"Unclassifiable Establishments",
    "sg:phone":"+33 5 53 05 01 53",
    "sg:postcode":"24420",
    "sg:province":"Aquitaine",
    "wof:name":"S.e.c.a. S.a.r.l. - Soci\u00e9t\u00e9 D'equipement Et De Construction Agricoles",
    "wof:placetype":"venue"
},
  "geometry": {"coordinates":[0.845065,45.207329],"type":"Point"}
}