{
  "type": "Feature",
  "properties": {
    "addr:full":"LA BOURSIDIERE BP 159 LE PLESSIS ROBINSON 92350",
    "addr:housenumber":"bp 159",
    "addr:postcode":"92350",
    "iso:country":"FR",
    "sg:address":"LA BOURSIDIERE BP 159",
    "sg:city":"LE PLESSIS ROBINSON",
    "sg:classifiers":[
        {
            "category":"Professional",
            "subcategory":"Management & Consulting",
            "type":"Services"
        }
    ],
    "sg:postcode":"92350",
    "sg:tags":[
        "intranet",
        "internet",
        "databases",
        "information-systems",
        "design",
        "web-agency",
        "consulting",
        "business-intelligence"
    ],
    "sg:website":"http://www.kleegroup.com",
    "wof:name":"KLEE",
    "wof:placetype":"venue"
},
  "geometry": {"coordinates":[2.239393,48.774699],"type":"Point"}
}