{
  "type": "Feature",
  "properties": {
    "iso:country":"FR",
    "sg:address":"Zi Des 5 Chemins 56520 Guidel",
    "sg:city":"Guidel",
    "sg:orig_category":"Miscellaneous Products",
    "sg:phone":"+33 2 97 65 97 98",
    "sg:postcode":"56520",
    "sg:province":"Bretagne",
    "wof:name":"Sibjet Technologies",
    "wof:placetype":"venue"
},
  "geometry": {"coordinates":[-3.516364,47.77565],"type":"Point"}
}