{
  "type": "Feature",
  "properties": {
    "iso:country":"FR",
    "sg:address":"9",
    "sg:city":"Zyckelin 59492 Hoymille",
    "sg:classifiers":[
        {
            "category":"Wholesale",
            "subcategory":"Farm Supplies",
            "type":"Manufacturing & Wholesale Goods"
        }
    ],
    "sg:phone":"+33 3 28 65 97 78",
    "sg:postcode":"59492",
    "sg:province":"Nord Pas-de-Calais",
    "sg:tags":[
        "-",
        "machine",
        "equipment",
        "engineering",
        "machinery",
        "mechanical",
        "agriculture"
    ],
    "wof:name":"Systemes E",
    "wof:placetype":"venue"
},
  "geometry": {"coordinates":[2.449216,50.977451],"type":"Point"}
}