{
  "type": "Feature",
  "properties": {
    "iso:country":"FR",
    "sg:address":"56460 La Chapelle Caro",
    "sg:city":"Chapelle-Caro",
    "sg:orig_category":"Unclassifiable Establishments",
    "sg:phone":"+33 2 97 74 72 72",
    "sg:postcode":"56460",
    "sg:province":"Bretagne",
    "wof:name":"S.b.g. S.a. - Soci\u00e9t\u00e9 Bretonne De Galvanisation",
    "wof:placetype":"venue"
},
  "geometry": {"coordinates":[-2.422344,47.865635],"type":"Point"}
}