{
  "type": "Feature",
  "properties": {
    "addr:full":"Rte de Mage Longny au Perche Basse Normandie 61290",
    "addr:postcode":"61290",
    "addr:street":"Rte De Mage;Basse",
    "iso:country":"FR",
    "sg:address":"Rte de Mage",
    "sg:city":"Longny au Perche",
    "sg:orig_category":"Unclassifiable Establishments",
    "sg:phone":"+33 2 33 73 48 78",
    "sg:postcode":"61290",
    "sg:province":"Basse Normandie",
    "wof:name":"Prod\u00e9co S.a.r.l.",
    "wof:placetype":"venue"
},
  "geometry": {"coordinates":[0.750574,48.495316],"type":"Point"}
}