{
  "type": "Feature",
  "properties": {
    "addr:full":"ZI - Quartier la Baou Sanary sur Mer Provence-Alpes-C\u00f4te d'Azur 83110",
    "addr:postcode":"83110",
    "addr:street":"Zi Quartier La Baou Sanary;Mer",
    "iso:country":"FR",
    "sg:address":"ZI - Quartier la Baou",
    "sg:city":"Sanary sur Mer",
    "sg:orig_category":"Unclassifiable Establishments",
    "sg:phone":"+33 4 94 74 26 00",
    "sg:postcode":"83110",
    "sg:province":"Provence-Alpes-C\u00f4te d'Azur",
    "wof:name":"G.r.p. Menuiseries Charpentes S.a.r.l",
    "wof:placetype":"venue"
},
  "geometry": {"coordinates":[5.80096,43.117786],"type":"Point"}
}