{
  "type": "Feature",
  "properties": {
    "addr:full":"B.P. 6, 53150 Montsurs^^3, Rue Fr\u00e8res Lem\u00e9e, 53150 Montsurs Pays de Loire",
    "addr:housenumber":"6",
    "addr:postcode":"53150;53150",
    "addr:street":"B.P.;Rue Fre\u0300Res Leme\u0301E;Montsurs",
    "iso:country":"FR",
    "sg:address":"B.P. 6, 53150 Montsurs^^3, Rue Fr\u00e8res Lem\u00e9e, 53150 Montsurs",
    "sg:orig_category":"Non-Classified Establishments",
    "sg:phone":"+33 2 43 01 01 26",
    "sg:province":"Pays de Loire",
    "wof:name":"Imprimerie Kayser",
    "wof:placetype":"venue"
},
  "geometry": {"coordinates":[-0.519726,48.098911],"type":"Point"}
}