{
  "type": "Feature",
  "properties": {
    "addr:full":"32, Av. du G\u00e9n\u00e9ral de Gaulle, 47000 Agen Agen Aquitaine 47000",
    "addr:postcode":"47000;47000",
    "addr:street":"32 Av. Du Ge\u0301Ne\u0301Ral De Gaulle",
    "iso:country":"FR",
    "sg:address":"32, Av. du G\u00e9n\u00e9ral de Gaulle, 47000 Agen",
    "sg:city":"Agen",
    "sg:orig_category":"Non-Classified Establishments",
    "sg:phone":"+33 5 53 47 27 85",
    "sg:postcode":"47000",
    "sg:province":"Aquitaine",
    "wof:name":"G. Delsol Et Compagnie S.a.r.l.",
    "wof:placetype":"venue"
},
  "geometry": {"coordinates":[0.61197,44.204987],"type":"Point"}
}