{
  "type": "Feature",
  "properties": {
    "iso:country":"FR",
    "sg:address":"29, Rue Saint Maur, 75011 Paris",
    "sg:orig_category":"Non-Classified Establishments",
    "sg:phone":"+33 1 53 36 11 11",
    "sg:postcode":"75011",
    "sg:province":"Ile de France",
    "wof:name":"Addit S.a.",
    "wof:placetype":"venue"
},
  "geometry": {"coordinates":[2.381196,48.86084],"type":"Point"}
}