{
  "type": "Feature",
  "properties": {
    "addr:full":"Les Grangers 24210 Thenon Thenon Aquitaine 24210",
    "addr:postcode":"24210;24210",
    "iso:country":"FR",
    "sg:address":"Les Grangers 24210 Thenon",
    "sg:city":"Thenon",
    "sg:classifiers":[
        {
            "category":"Shopping",
            "type":"Retail Goods"
        }
    ],
    "sg:phone":"+33 5 53 05 11 34",
    "sg:postcode":"24210",
    "sg:province":"Aquitaine",
    "sg:tags":[
        "metallurgy",
        "finished",
        "-",
        "metalworking",
        "metallic"
    ],
    "wof:name":"Delmas Patrick",
    "wof:placetype":"venue"
},
  "geometry": {"coordinates":[1.097583,45.117813],"type":"Point"}
}