{
  "type": "Feature",
  "properties": {
    "addr:full":"Chemin D\u00e9partemental 132 - ZI Mas d'Astre Montpellier C\u00e9dex Languedoc-Roussillon 34070",
    "addr:housenumber":"132",
    "addr:postcode":"zi;ce\u0301dex;34070",
    "addr:street":"Chemin De\u0301Partemental;D'Astre",
    "iso:country":"FR",
    "sg:address":"Chemin D\u00e9partemental 132 - ZI Mas d'Astre",
    "sg:city":"Montpellier C\u00e9dex",
    "sg:orig_category":"Non-Classified Establishments",
    "sg:phone":"+33 4 67 42 90 10",
    "sg:postcode":"34070",
    "sg:province":"Languedoc-Roussillon",
    "wof:name":"Synair Languedoc Roussillon S.a.",
    "wof:placetype":"venue"
},
  "geometry": {"coordinates":[3.859938,43.575352],"type":"Point"}
}