{
  "type": "Feature",
  "properties": {
    "iso:country":"FR",
    "sg:address":"Zi De Malleprat 33650 Martillac",
    "sg:city":"Martillac",
    "sg:classifiers":[
        {
            "category":"Social Services",
            "subcategory":"Job Training",
            "type":"Services"
        }
    ],
    "sg:phone":"+33 5 56 72 63 13",
    "sg:postcode":"33650",
    "sg:province":"Aquitaine",
    "sg:tags":[
        "good",
        "business",
        "advice",
        "-",
        "metalworking",
        "metallic",
        "metallurgy",
        "finished"
    ],
    "wof:name":"Cie De Tuyauterie Et Mecanique Reunies (cotumer)",
    "wof:placetype":"venue"
},
  "geometry": {"coordinates":[-0.543289,44.712605],"type":"Point"}
}