{
  "type": "Feature",
  "properties": {
    "iso:country":"FR",
    "sg:address":"Zone D'Activit\u00e9s Pied Sec 17260 G\u00e9mozac",
    "sg:classifiers":[
        {
            "category":"Shopping",
            "type":"Retail Goods"
        }
    ],
    "sg:phone":"+33 5 46 94 68 79",
    "sg:postcode":"17260",
    "sg:province":"Poitou-Charentes",
    "sg:tags":[
        "metallurgy",
        "finished",
        "-",
        "metalworking",
        "metallic"
    ],
    "wof:name":"Etablissements Philipps Bourgeois Sarl",
    "wof:placetype":"venue"
},
  "geometry": {"coordinates":[-0.618131,45.652756],"type":"Point"}
}