{
  "type": "Feature",
  "properties": {
    "addr:full":"R De Sains 62130 Maisnil Nord Pas-de-Calais 62130",
    "addr:postcode":"62130;62130",
    "addr:street":"Maisnil Nord",
    "iso:country":"FR",
    "sg:address":"R De Sains 62130 Maisnil",
    "sg:classifiers":[
        {
            "category":"Autos & Motor Vehicles",
            "subcategory":"Automobile Sales",
            "type":"Retail Goods"
        }
    ],
    "sg:phone":"+33 3 21 03 00 41",
    "sg:postcode":"62130",
    "sg:province":"Nord Pas-de-Calais",
    "sg:tags":[
        "equipment",
        "motor-cars",
        "transport"
    ],
    "wof:name":"M. Theret Marcel",
    "wof:placetype":"venue"
},
  "geometry": {"coordinates":[2.365582,50.345467],"type":"Point"}
}