{
  "type": "Feature",
  "properties": {
    "addr:full":"3, Av. Louis de Broglie - Synergie Park, 59260 Lezennes Nord Pas-de-Calais",
    "addr:postcode":"59260",
    "addr:street":"Av. Louis De Broglie Synergie Park",
    "iso:country":"FR",
    "sg:address":"3, Av. Louis de Broglie - Synergie Park, 59260 Lezennes",
    "sg:orig_category":"Non-Classified Establishments",
    "sg:phone":"+33 3 20 19 76 76",
    "sg:province":"Nord Pas-de-Calais",
    "wof:name":"Setsys S.a.r.l.",
    "wof:placetype":"venue"
},
  "geometry": {"coordinates":[3.11705,50.614567],"type":"Point"}
}