{
  "type": "Feature",
  "properties": {
    "iso:country":"FR",
    "sg:address":"12, Rte Saint Mathieu, 06130 Grasse",
    "sg:orig_category":"Unclassifiable Establishments",
    "sg:phone":"+33 4 93 36 00 06",
    "sg:province":"Provence-Alpes-C\u00f4te d'Azur",
    "wof:name":"Arco S.a.s.",
    "wof:placetype":"venue"
},
  "geometry": {"coordinates":[6.930312,43.655823],"type":"Point"}
}