{
  "type": "Feature",
  "properties": {
    "iso:country":"FR",
    "sg:address":"ZI de Saint Eloi",
    "sg:city":"Saint Eloi",
    "sg:orig_category":"Unclassifiable Establishments",
    "sg:phone":"+33 3 86 61 57 47",
    "sg:postcode":"58000",
    "sg:province":"Bourgogne",
    "wof:name":"Soci\u00e9t\u00e9 Thuel S.a.r.l.",
    "wof:placetype":"venue"
},
  "geometry": {"coordinates":[3.216681,46.975315],"type":"Point"}
}