{
  "type": "Feature",
  "properties": {
    "iso:country":"FR",
    "sg:address":"La Grave 06440 Blausasc",
    "sg:orig_category":"Unclassifiable Establishments",
    "sg:phone":"+33 4 93 91 71 00",
    "sg:province":"Ile de France",
    "wof:name":"Vicat",
    "wof:placetype":"venue"
},
  "geometry": {"coordinates":[7.375535,43.790764],"type":"Point"}
}