{
  "type": "Feature",
  "properties": {
    "iso:country":"FR",
    "sg:address":"ZAC de la Banqui\u00e8re",
    "sg:city":"Lattes",
    "sg:orig_category":"Non-Classified Establishments",
    "sg:phone":"+33 4 67 22 22 00",
    "sg:postcode":"34970",
    "sg:province":"Languedoc-Roussillon",
    "wof:name":"France Antennes Et Protections S.a.r.l.",
    "wof:placetype":"venue"
},
  "geometry": {"coordinates":[3.90524,43.570381],"type":"Point"}
}