{
  "type": "Feature",
  "properties": {
    "iso:country":"FR",
    "sg:address":"107 Rue Charles De Gaulle 68370 Orbey",
    "sg:city":"Orbey",
    "sg:classifiers":[
        {
            "category":"Wholesale",
            "subcategory":"Farm Supplies",
            "type":"Manufacturing & Wholesale Goods"
        }
    ],
    "sg:phone":"+33 3 89 71 21 01",
    "sg:postcode":"68370",
    "sg:province":"Alsace",
    "sg:tags":[
        "-",
        "machine",
        "equipment",
        "engineering",
        "machinery",
        "mechanical",
        "agriculture"
    ],
    "wof:name":"Andre Balthazard Et Fils (ets)",
    "wof:placetype":"venue"
},
  "geometry": {"coordinates":[7.156376,48.126163],"type":"Point"}
}