{
  "type": "Feature",
  "properties": {
    "addr:full":"17 - 19, Rue Charles Friedel, 75020 Paris Ile de France 75020",
    "addr:housenumber":"19",
    "addr:postcode":"75020;75020",
    "addr:street":"Rue Charles Friedel",
    "iso:country":"FR",
    "sg:address":"17 - 19, Rue Charles Friedel, 75020 Paris",
    "sg:orig_category":"Non-Classified Establishments",
    "sg:phone":"+33 1 40 33 60 00",
    "sg:postcode":"75020",
    "sg:province":"Ile de France",
    "wof:name":"Afranett S.a.r.l.",
    "wof:placetype":"venue"
},
  "geometry": {"coordinates":[2.395691,48.872761],"type":"Point"}
}