{
  "type": "Feature",
  "properties": {
    "iso:country":"FR",
    "sg:address":"9, Rue Champtraine - Z.I., 60870 Rieux",
    "sg:orig_category":"Non-Classified Establishments",
    "sg:phone":"+33 3 44 72 91 61",
    "sg:province":"Picardie",
    "wof:name":"Rieux R\u00e9fractaires",
    "wof:placetype":"venue"
},
  "geometry": {"coordinates":[2.487537,49.288544],"type":"Point"}
}