{
  "type": "Feature",
  "properties": {
    "addr:full":"8, Rue des Quinze Arpents, 94310 Orly Ile de France",
    "addr:housenumber":"8",
    "addr:postcode":"94310",
    "addr:street":"Rue Des Quinze Arpents;Ile De France",
    "iso:country":"FR",
    "sg:address":"8, Rue des Quinze Arpents, 94310 Orly",
    "sg:orig_category":"Unclassifiable Establishments",
    "sg:phone":"+33 1 41 80 74 00",
    "sg:province":"Ile de France",
    "wof:name":"Via Location Ile De France S.a.",
    "wof:placetype":"venue"
},
  "geometry": {"coordinates":[2.377903,48.747997],"type":"Point"}
}