{
  "type": "Feature",
  "properties": {
    "addr:full":"Quartier les gr\u00e8s Grignan Rhone-Alpes 26230",
    "addr:postcode":"26230",
    "addr:street":"Quartier;Rhone-Alpes",
    "iso:country":"FR",
    "sg:address":"Quartier les gr\u00e8s",
    "sg:city":"Grignan",
    "sg:orig_category":"Unclassifiable Establishments",
    "sg:phone":"+33 4 75 46 51 84",
    "sg:postcode":"26230",
    "sg:province":"Rhone-Alpes",
    "wof:name":"Lavandin De Grignan",
    "wof:placetype":"venue"
},
  "geometry": {"coordinates":[4.83743,44.413456],"type":"Point"}
}