{
  "type": "Feature",
  "properties": {
    "addr:full":"Zone Industrielle 07270 Lamastre Rhone-Alpes 07270",
    "addr:postcode":"07270;07270",
    "addr:street":"Zone Industrielle;Rhone-Alpes",
    "iso:country":"FR",
    "sg:address":"Zone Industrielle 07270 Lamastre",
    "sg:classifiers":[
        {
            "category":"Shopping",
            "subcategory":"Clothing, Apparel, & Fashions",
            "type":"Retail Goods"
        }
    ],
    "sg:phone":"+33 4 75 06 43 11",
    "sg:postcode":"07270",
    "sg:province":"Rhone-Alpes",
    "sg:tags":[
        "textile",
        "clothing",
        "clothes"
    ],
    "wof:name":"Societe Pour L'injection De Chaussures (sic)",
    "wof:placetype":"venue"
},
  "geometry": {"coordinates":[4.58205,44.98587],"type":"Point"}
}