{
  "type": "Feature",
  "properties": {
    "addr:full":"Rue Georges Claude Zi Du Teinchurier 19100 Brive La Gaillarde Limousin 19100",
    "addr:postcode":"19100;19100",
    "addr:street":"Rue Georges Claude Zi Du Teinchurier",
    "iso:country":"FR",
    "sg:address":"Rue Georges Claude Zi Du Teinchurier 19100 Brive La Gaillarde",
    "sg:classifiers":[
        {
            "category":"Food & Beverages",
            "subcategory":"Groceries & Convenience Stores",
            "type":"Retail Goods"
        }
    ],
    "sg:phone":"+33 5 55 86 03 85",
    "sg:postcode":"19100",
    "sg:province":"Limousin",
    "sg:tags":[
        "product",
        "related"
    ],
    "wof:name":"La Noix Gaillarde Cerneaux Elabores",
    "wof:placetype":"venue"
},
  "geometry": {"coordinates":[1.53587,45.157036],"type":"Point"}
}