{
  "type": "Feature",
  "properties": {
    "addr:full":"B.P. 217, 69336 Lyon C\u00e9dex 9^^100, Rue des Foug\u00e8res, 69009 Lyon Rhone-Alpes 69009",
    "addr:housenumber":"b.p. 217;9 ^ ^ 100",
    "addr:postcode":"69336;69009;69009",
    "addr:street":"Ce\u0301Dex;Rue Des Fouge\u0300Res",
    "iso:country":"FR",
    "sg:address":"B.P. 217, 69336 Lyon C\u00e9dex 9^^100, Rue des Foug\u00e8res, 69009 Lyon",
    "sg:orig_category":"Non-Classified Establishments",
    "sg:phone":"+33 4 78 66 88 30",
    "sg:postcode":"69009",
    "sg:province":"Rhone-Alpes",
    "wof:name":"Entreprise Nouvelle L'avenir S.n.c.",
    "wof:placetype":"venue"
},
  "geometry": {"coordinates":[4.805335,45.774105],"type":"Point"}
}