{
  "type": "Feature",
  "properties": {
    "iso:country":"FR",
    "sg:address":"Za St Mathieu 28320 Gallardon",
    "sg:city":"Gallardon",
    "sg:classifiers":[
        {
            "category":"Professional",
            "subcategory":"Engineering",
            "type":"Services"
        }
    ],
    "sg:phone":"+33 2 37 33 38 60",
    "sg:postcode":"28320",
    "sg:province":"Centre",
    "sg:tags":[
        "machine",
        "-",
        "mechanical"
    ],
    "wof:name":"Ste Indus Systeme Production (sisp)",
    "wof:placetype":"venue"
},
  "geometry": {"coordinates":[1.68767,48.52486],"type":"Point"}
}