{
  "type": "Feature",
  "properties": {
    "addr:full":"B.P. 155, 78312 Maurepas C\u00e9dex^^5, RN 10, 78310 Coigni\u00e8res Ile de France",
    "addr:housenumber":"b.p. 155",
    "addr:postcode":"78312;78310;ile",
    "addr:street":"Rn 10",
    "iso:country":"FR",
    "sg:address":"B.P. 155, 78312 Maurepas C\u00e9dex^^5, RN 10, 78310 Coigni\u00e8res",
    "sg:orig_category":"Non-Classified Establishments",
    "sg:phone":"+33 1 30 16 57 57",
    "sg:province":"Ile de France",
    "wof:name":"G.p.s. S.a.",
    "wof:placetype":"venue"
},
  "geometry": {"coordinates":[1.944855,48.761749],"type":"Point"}
}