{
  "type": "Feature",
  "properties": {
    "iso:country":"FR",
    "sg:address":"Rue Louis Joseph Gras 42100 St \u00c9tienne",
    "sg:classifiers":[
        {
            "category":"Manufacturing",
            "subcategory":"Metals",
            "type":"Manufacturing & Wholesale Goods"
        }
    ],
    "sg:phone":"+33 4 77 57 35 68",
    "sg:postcode":"42100",
    "sg:province":"Rhone-Alpes",
    "sg:tags":[
        "metallurgy",
        "metalworking",
        "processing"
    ],
    "wof:name":"Ets Prevost Sarl",
    "wof:placetype":"venue"
},
  "geometry": {"coordinates":[4.381693,45.419342],"type":"Point"}
}