{
  "type": "Feature",
  "properties": {
    "addr:full":"3, Rue Gattefoss\u00e9 - Parc d'Affaires de la Bandonnier, 69800 Saint Priest Rhone-Alpes",
    "addr:housenumber":"3",
    "addr:postcode":"69800",
    "addr:street":"Rue Gattefosse\u0301 Parc D'Affaires De La Bandonnier;Priest Rhone-Alpes",
    "iso:country":"FR",
    "sg:address":"3, Rue Gattefoss\u00e9 - Parc d'Affaires de la Bandonnier, 69800 Saint Priest",
    "sg:orig_category":"Unclassifiable Establishments",
    "sg:phone":"+33 4 78 21 67 58",
    "sg:province":"Rhone-Alpes",
    "wof:name":"C.e.g.r.e.m. S.a. - Centre Etude Gestion R\u00e9alisation Edition Micograph",
    "wof:placetype":"venue"
},
  "geometry": {"coordinates":[4.94758,45.701408],"type":"Point"}
}