{
  "type": "Feature",
  "properties": {
    "addr:full":"B.P. 7, 62320 Drocourt^^1, Rue Georges Capelle, 62320 Rouvroy Nord Pas-de-Calais 62320",
    "addr:housenumber":"7",
    "addr:postcode":"62320;62320;62320",
    "addr:street":"B.P.;Rue Georges Capelle",
    "iso:country":"FR",
    "sg:address":"B.P. 7, 62320 Drocourt^^1, Rue Georges Capelle, 62320 Rouvroy",
    "sg:orig_category":"Non-Classified Establishments",
    "sg:phone":"+33 3 21 74 81 00",
    "sg:postcode":"62320",
    "sg:province":"Nord Pas-de-Calais",
    "wof:name":"Cokes De Drocourt S.a.",
    "wof:placetype":"venue"
},
  "geometry": {"coordinates":[2.903608,50.39307],"type":"Point"}
}