{
  "type": "Feature",
  "properties": {
    "addr:full":"quart les Virieux BP 27 26600 Pont de l'Is\u00e8re Rhone-Alpes 26600",
    "addr:housenumber":"bp 27",
    "addr:postcode":"26600;26600",
    "addr:street":"Quart;Rhone-Alpes",
    "iso:country":"FR",
    "sg:address":"quart les Virieux BP 27 26600 Pont de l'Is\u00e8re",
    "sg:classifiers":[
        {
            "category":"Wholesale",
            "subcategory":"Machinery & Supplies",
            "type":"Manufacturing & Wholesale Goods"
        }
    ],
    "sg:phone":"+33 4 75 84 86 00",
    "sg:postcode":"26600",
    "sg:province":"Rhone-Alpes",
    "sg:tags":[
        "handling",
        "material",
        "-",
        "machine",
        "equipment",
        "engineering",
        "mechanical"
    ],
    "wof:name":"Sodimas",
    "wof:placetype":"venue"
},
  "geometry": {"coordinates":[5.33987,45.062679],"type":"Point"}
}