{
  "type": "Feature",
  "properties": {
    "addr:full":"10 Rue Nationale 56300 Pontivy Pontivy Bretagne 56300",
    "addr:housenumber":"10",
    "addr:postcode":"56300;56300",
    "addr:street":"Rue Nationale;Pontivy",
    "iso:country":"FR",
    "sg:address":"10 Rue Nationale 56300 Pontivy",
    "sg:city":"Pontivy",
    "sg:classifiers":[
        {
            "category":"Professional",
            "subcategory":"Advertising",
            "type":"Services"
        }
    ],
    "sg:phone":"+33 2 97 25 39 08",
    "sg:postcode":"56300",
    "sg:province":"Bretagne",
    "sg:tags":[
        "information",
        "medium",
        "communication"
    ],
    "wof:name":"Regicom - La Centrale",
    "wof:placetype":"venue"
},
  "geometry": {"coordinates":[-2.965437,48.067661],"type":"Point"}
}