{
  "type": "Feature",
  "properties": {
    "addr:full":"18, Chemin Combe Martin, 69300 Caluire et Cuire Rhone-Alpes 69300",
    "addr:housenumber":"18",
    "addr:postcode":"69300;69300",
    "addr:street":"Chemin Combe Martin",
    "iso:country":"FR",
    "sg:address":"18, Chemin Combe Martin, 69300 Caluire et Cuire",
    "sg:orig_category":"Non-Classified Establishments",
    "sg:phone":"+33 4 78 23 00 66",
    "sg:postcode":"69300",
    "sg:province":"Rhone-Alpes",
    "wof:name":"Erome M G",
    "wof:placetype":"venue"
},
  "geometry": {"coordinates":[4.864354,45.793667],"type":"Point"}
}