{
  "type": "Feature",
  "properties": {
    "iso:country":"FR",
    "sg:address":"B.P. 242, 95523 Cergy Pontoise C\u00e9dex^^6, Chauss\u00e9e Jules C\u00e9sar, 95520 Osny",
    "sg:orig_category":"Non-Classified Establishments",
    "sg:phone":"+33 1 34 41 95 60",
    "sg:province":"Ile de France",
    "wof:name":"Salva Location S.a.s.",
    "wof:placetype":"venue"
},
  "geometry": {"coordinates":[2.064945,49.064018],"type":"Point"}
}