{
  "type": "Feature",
  "properties": {
    "iso:country":"FR",
    "sg:address":"10 rue des Usines 44100 Nantes",
    "sg:classifiers":[
        {
            "category":"Banks & Credit Unions",
            "subcategory":"Investment Brokerage",
            "type":"Services"
        }
    ],
    "sg:phone":"+33 2 40 95 96 97",
    "sg:province":"Pays de Loire",
    "sg:tags":[
        "plant",
        "waste",
        "incineration"
    ],
    "wof:name":"Leroux \u00a0et Lotz Sa",
    "wof:placetype":"venue"
},
  "geometry": {"coordinates":[-1.602134,47.195107],"type":"Point"}
}