{
  "type": "Feature",
  "properties": {
    "iso:country":"FR",
    "sg:address":"11, Rue Porte \u00e0 Bateaux, 27540 Ivry la Bataille",
    "sg:orig_category":"Unclassifiable Establishments",
    "sg:phone":"+33 2 32 36 41 51",
    "sg:province":"Haute Normandie",
    "wof:name":"Dubreil Et Auffray S.a.r.l.",
    "wof:placetype":"venue"
},
  "geometry": {"coordinates":[1.462325,48.884174],"type":"Point"}
}