{
  "type": "Feature",
  "properties": {
    "addr:full":"6/10, Bd des Monts d'Or, 69580 Sathonay Camp Rhone-Alpes 69580",
    "addr:housenumber":"6 / 10",
    "addr:postcode":"69580;69580",
    "addr:street":"Bd Des Monts D'Or;Rhone-Alpes",
    "iso:country":"FR",
    "sg:address":"6/10, Bd des Monts d'Or, 69580 Sathonay Camp",
    "sg:orig_category":"Unclassifiable Establishments",
    "sg:phone":"+33 4 72 27 21 21",
    "sg:postcode":"69580",
    "sg:province":"Rhone-Alpes",
    "wof:name":"Sunkiss S.a.",
    "wof:placetype":"venue"
},
  "geometry": {"coordinates":[4.866407,45.824371],"type":"Point"}
}