{
  "type": "Feature",
  "properties": {
    "iso:country":"FR",
    "sg:address":"ZI de la Valli\u00e8re",
    "sg:city":"Saint Andr\u00e9",
    "sg:orig_category":"Unclassifiable Establishments",
    "sg:phone":"+33 4 93 54 54 54",
    "sg:postcode":"06730",
    "sg:province":"Midi Pyr\u00e9n\u00e9es",
    "wof:name":"L'imp\u00e9ratrice S.a.r.l.",
    "wof:placetype":"venue"
},
  "geometry": {"coordinates":[7.284408,43.754208],"type":"Point"}
}