{
  "type": "Feature",
  "properties": {
    "addr:full":"Rte du Moulin Saint Omer en Chauss\u00e9e Picardie 60860",
    "addr:postcode":"60860",
    "addr:street":"Rte Du Moulin Saint Omer En Chausse\u0301E Picardie",
    "iso:country":"FR",
    "sg:address":"Rte du Moulin",
    "sg:city":"Saint Omer en Chauss\u00e9e",
    "sg:orig_category":"Unclassifiable Establishments",
    "sg:phone":"+33 3 44 84 50 36",
    "sg:postcode":"60860",
    "sg:province":"Picardie",
    "wof:name":"Ventm\u00e9ca S.a.",
    "wof:placetype":"venue"
},
  "geometry": {"coordinates":[1.95417,49.573685],"type":"Point"}
}