{
  "type": "Feature",
  "properties": {
    "iso:country":"FR",
    "sg:address":"Rue De La Petite Poire 39300 Sapois",
    "sg:classifiers":[
        {
            "category":"Professional",
            "type":"Services"
        }
    ],
    "sg:phone":"+33 3 84 52 63 53",
    "sg:province":"Franche Comt\u00e9",
    "sg:tags":[
        "transport",
        "road"
    ],
    "wof:name":"Transports Robin Sarl",
    "wof:placetype":"venue"
},
  "geometry": {"coordinates":[5.943611,46.750233],"type":"Point"}
}