{
  "type": "Feature",
  "properties": {
    "iso:country":"FR",
    "sg:address":"36 boulevard De Vincennes 94120 Fontenay Sous Bois",
    "sg:classifiers":[
        {
            "category":"Banks & Credit Unions",
            "subcategory":"Bank",
            "type":"Services"
        }
    ],
    "sg:phone":"+33 1 43 94 94 01",
    "sg:province":"Ile de France",
    "sg:tags":[
        "banking",
        "form",
        "software"
    ],
    "wof:name":"Sab Ingenierie Informatique Sa",
    "wof:placetype":"venue"
},
  "geometry": {"coordinates":[2.461103,48.844814],"type":"Point"}
}