{
  "type": "Feature",
  "properties": {
    "addr:full":"Brezalou 29400 Plouneventer Ploun\u00e9venter Bretagne 29400",
    "addr:postcode":"29400;29400",
    "addr:street":"Brezalou;Ploune\u0301Venter",
    "iso:country":"FR",
    "sg:address":"Brezalou 29400 Plouneventer",
    "sg:city":"Ploun\u00e9venter",
    "sg:classifiers":[
        {
            "category":"Farming",
            "subcategory":"Livestock Farm",
            "type":"Manufacturing & Wholesale Goods"
        }
    ],
    "sg:phone":"+33 2 98 20 40 64",
    "sg:postcode":"29400",
    "sg:province":"Bretagne",
    "sg:tags":[
        "breeding",
        "agriculture",
        "animal"
    ],
    "wof:name":"Elevage De Brezal Sa",
    "wof:placetype":"venue"
},
  "geometry": {"coordinates":[-4.004424,48.445419],"type":"Point"}
}