{
  "type": "Feature",
  "properties": {
    "addr:full":"Rte de Rennes Ch\u00e2teaubourg Bretagne 35220",
    "addr:postcode":"35220",
    "addr:street":"Rte De Rennes Cha\u0302Teaubourg Bretagne",
    "iso:country":"FR",
    "sg:address":"Rte de Rennes",
    "sg:city":"Ch\u00e2teaubourg",
    "sg:orig_category":"Unclassifiable Establishments",
    "sg:phone":"+33 2 99 28 23 70",
    "sg:postcode":"35220",
    "sg:province":"Bretagne",
    "wof:name":"Alcyon S.a.",
    "wof:placetype":"venue"
},
  "geometry": {"coordinates":[-1.405252,48.108192],"type":"Point"}
}