{
  "type": "Feature",
  "properties": {
    "iso:country":"FR",
    "sg:address":"37 Route Nationale 80260 Talmas",
    "sg:classifiers":[
        {
            "category":"Professional",
            "subcategory":"Engineering",
            "type":"Services"
        }
    ],
    "sg:phone":"+33 3 22 93 73 70",
    "sg:postcode":"80260",
    "sg:province":"Picardie",
    "sg:tags":[
        "machine",
        "-",
        "mechanical"
    ],
    "wof:name":"Autelec",
    "wof:placetype":"venue"
},
  "geometry": {"coordinates":[2.309245,49.944965],"type":"Point"}
}