{
  "type": "Feature",
  "properties": {
    "iso:country":"FR",
    "sg:address":"816 Av Montaigne 77190 Dammarie Les Lys",
    "sg:classifiers":[
        {
            "category":"Shopping",
            "subcategory":"Computers & Home Electronics",
            "type":"Retail Goods"
        }
    ],
    "sg:phone":"+33 1 64 37 92 05",
    "sg:postcode":"77190",
    "sg:province":"Ile de France",
    "sg:tags":[
        "electric",
        "electricity",
        "component",
        "equipment",
        "electrical",
        "electronic"
    ],
    "wof:name":"Bmm Sa",
    "wof:placetype":"venue"
},
  "geometry": {"coordinates":[2.633486,48.521404],"type":"Point"}
}