{
  "type": "Feature",
  "properties": {
    "addr:full":"33503 Libourne C\u00e9dex^^125, Av. Georges Pompidou, 33500 Libourne Libourne Aquitaine 33500",
    "addr:postcode":"33503;33500;33500",
    "addr:street":"Av. Georges Pompidou",
    "iso:country":"FR",
    "sg:address":"33503 Libourne C\u00e9dex^^125, Av. Georges Pompidou, 33500 Libourne",
    "sg:city":"Libourne",
    "sg:orig_category":"Non-Classified Establishments",
    "sg:phone":"+33 5 57 25 40 00",
    "sg:postcode":"33500",
    "sg:province":"Aquitaine",
    "wof:name":"C.c.i. De Libourne - Chambre De Commerce Et D'industrie De Libourne",
    "wof:placetype":"venue"
},
  "geometry": {"coordinates":[-0.286437,44.884071],"type":"Point"}
}