{
  "type": "Feature",
  "properties": {
    "addr:full":"Rue de la Mine Montois la Montagne Lorraine 57860",
    "addr:postcode":"57860",
    "addr:street":"Rue De La Mine Montois La Montagne Lorraine",
    "iso:country":"FR",
    "sg:address":"Rue de la Mine",
    "sg:city":"Montois la Montagne",
    "sg:orig_category":"Unclassifiable Establishments",
    "sg:phone":"+33 3 82 45 16 97",
    "sg:postcode":"57860",
    "sg:province":"Lorraine",
    "wof:name":"Sablemat S.a.",
    "wof:placetype":"venue"
},
  "geometry": {"coordinates":[6.017475,49.21611],"type":"Point"}
}