{
  "type": "Feature",
  "properties": {
    "addr:full":"880 Rte De Vernets 71500 Branges Branges Bourgogne 71500",
    "addr:housenumber":"880",
    "addr:postcode":"71500;71500",
    "addr:street":"Rte De Vernets",
    "iso:country":"FR",
    "sg:address":"880 Rte De Vernets 71500 Branges",
    "sg:city":"Branges",
    "sg:classifiers":[
        {
            "category":"Professional",
            "type":"Services"
        }
    ],
    "sg:phone":"+33 3 85 75 25 72",
    "sg:postcode":"71500",
    "sg:province":"Bourgogne",
    "sg:tags":[
        "transport",
        "road"
    ],
    "wof:name":"Transport Delarche Sarl",
    "wof:placetype":"venue"
},
  "geometry": {"coordinates":[5.152254,46.646259],"type":"Point"}
}