{
  "type": "Feature",
  "properties": {
    "iso:country":"FR",
    "sg:address":"A\u00e9roport Nantes Atlantique",
    "sg:city":"Bouguenais",
    "sg:orig_category":"Unclassifiable Establishments",
    "sg:phone":"+33 2 40 84 81 64",
    "sg:postcode":"44340",
    "sg:province":"Pays de Loire",
    "wof:name":"G\u00e9odis Overseas",
    "wof:placetype":"venue"
},
  "geometry": {"coordinates":[-1.60205,47.157318],"type":"Point"}
}