{
  "type": "Feature",
  "properties": {
    "iso:country":"FR",
    "sg:address":"rue Bleue 63118 Cebazat",
    "sg:city":"C\u00e9bazat",
    "sg:classifiers":[
        {
            "category":"Professional",
            "type":"Services"
        }
    ],
    "sg:phone":"+33 4 73 23 63 83",
    "sg:postcode":"63118",
    "sg:province":"Auvergne",
    "sg:tags":[
        "transport"
    ],
    "wof:name":"Transports Auvergne M\u00e9diterran\u00e9e Sarl",
    "wof:placetype":"venue"
},
  "geometry": {"coordinates":[3.1189,45.842899],"type":"Point"}
}