{
  "type": "Feature",
  "properties": {
    "addr:full":"Zone Industrielle 14540 Bourguebus Bourgu\u00e9bus Basse Normandie 14540",
    "addr:postcode":"14540;14540",
    "addr:street":"Zone Industrielle",
    "iso:country":"FR",
    "sg:address":"Zone Industrielle 14540 Bourguebus",
    "sg:city":"Bourgu\u00e9bus",
    "sg:classifiers":[
        {
            "category":"Manufacturing",
            "subcategory":"Rubber & Plastics",
            "type":"Manufacturing & Wholesale Goods"
        }
    ],
    "sg:phone":"+33 2 31 23 11 76",
    "sg:postcode":"14540",
    "sg:province":"Basse Normandie",
    "wof:name":"Capelli Plastique",
    "wof:placetype":"venue"
},
  "geometry": {"coordinates":[-0.299665,49.123943],"type":"Point"}
}