{
  "type": "Feature",
  "properties": {
    "addr:full":"10/12, Rue Pierre Nicolau, 95583 Saint Ouen l'Aum\u00f4ne C\u00e9dex \u00cele-de-France",
    "addr:housenumber":"10 / 12;95583",
    "addr:street":"Rue Pierre Nicolau;Saint;Ce\u0301Dex",
    "iso:country":"FR",
    "sg:address":"10/12, Rue Pierre Nicolau, 95583 Saint Ouen l'Aum\u00f4ne C\u00e9dex",
    "sg:orig_category":"Non-Classified Establishments",
    "sg:phone":"+33 1 49 45 23 23",
    "sg:province":"\u00cele-de-France",
    "wof:name":"S.e.c.c. Entreprise S.a.",
    "wof:placetype":"venue"
},
  "geometry": {"coordinates":[2.336121,48.920784],"type":"Point"}
}