{
  "type": "Feature",
  "properties": {
    "iso:country":"FR",
    "sg:address":"Quartier Les Doyats",
    "sg:city":"Ch\u00e2teauneuf De Galaure",
    "sg:classifiers":[
        {
            "category":"Banks & Credit Unions",
            "subcategory":"Financial Services",
            "type":"Services"
        }
    ],
    "sg:phone":"+33 4 75 68 60 59",
    "sg:postcode":"26330",
    "sg:province":"Rhone-Alpes",
    "sg:tags":[
        "banking",
        "finance",
        "insurance"
    ],
    "wof:name":"Sa Dofipac",
    "wof:placetype":"venue"
},
  "geometry": {"coordinates":[4.944763,45.222912],"type":"Point"}
}