{
  "type": "Feature",
  "properties": {
    "addr:full":"19, Rue des Beaux Soleils, 95520 Osny Ile de France",
    "addr:housenumber":"19",
    "addr:postcode":"95520",
    "addr:street":"Rue Des Beaux Soleils;Ile De France",
    "iso:country":"FR",
    "sg:address":"19, Rue des Beaux Soleils, 95520 Osny",
    "sg:orig_category":"Unclassifiable Establishments",
    "sg:phone":"+33 1 30 73 54 44",
    "sg:province":"Ile de France",
    "wof:name":"Green Tweed Co France S.a.",
    "wof:placetype":"venue"
},
  "geometry": {"coordinates":[2.070553,49.052338],"type":"Point"}
}