{
  "type": "Feature",
  "properties": {
    "addr:full":"Rue des Rouhauds Aytr\u00e9 Poitou-Charentes 17440",
    "addr:postcode":"17440",
    "addr:street":"Rue Des Rouhauds Aytre\u0301",
    "iso:country":"FR",
    "sg:address":"Rue des Rouhauds",
    "sg:city":"Aytr\u00e9",
    "sg:orig_category":"Unclassifiable Establishments",
    "sg:phone":"+33 5 46 30 06 30",
    "sg:postcode":"17440",
    "sg:province":"Poitou-Charentes",
    "wof:name":"M\u00e9gnien Distribution S.n.c.",
    "wof:placetype":"venue"
},
  "geometry": {"coordinates":[-1.110171,46.137558],"type":"Point"}
}