{
  "type": "Feature",
  "properties": {
    "iso:country":"FR",
    "sg:address":"3-5 Av De Fondeyre 31200 Toulouse",
    "sg:classifiers":[
        {
            "category":"Manufacturing",
            "subcategory":"Printing",
            "type":"Manufacturing & Wholesale Goods"
        }
    ],
    "sg:phone":"+33 5 61 13 51 35",
    "sg:province":"Midi Pyr\u00e9n\u00e9es",
    "sg:tags":[
        "publishing"
    ],
    "wof:name":"Imprimerie Du Sud Sa",
    "wof:placetype":"venue"
},
  "geometry": {"coordinates":[1.427001,43.642025],"type":"Point"}
}