{
  "type": "Feature",
  "properties": {
    "iso:country":"FR",
    "sg:address":"La Galmandiere 35220 Chateaubourg",
    "sg:city":"Ch\u00e2teaubourg",
    "sg:classifiers":[
        {
            "category":"Food & Beverages",
            "subcategory":"Dairy",
            "type":"Retail Goods"
        }
    ],
    "sg:phone":"+33 2 99 04 63 63",
    "sg:postcode":"35220",
    "sg:province":"Bretagne",
    "sg:tags":[
        "product",
        "related"
    ],
    "wof:name":"Laiterie Triballat",
    "wof:placetype":"venue"
},
  "geometry": {"coordinates":[-1.371241,48.095028],"type":"Point"}
}