{
  "type": "Feature",
  "properties": {
    "iso:country":"FR",
    "sg:address":"B.P. 21, 89144 Ligny le Ch\u00e2tel^^ZA, 89144 Ligny le Ch\u00e2tel",
    "sg:city":"Ligny-le-Ch\u00e2tel",
    "sg:orig_category":"Non-Classified Establishments",
    "sg:phone":"+33 3 86 47 51 77",
    "sg:postcode":"89144",
    "sg:province":"Bourgogne",
    "wof:name":"T.p.i.l. S.a.",
    "wof:placetype":"venue"
},
  "geometry": {"coordinates":[3.756533,47.901741],"type":"Point"}
}