{
  "type": "Feature",
  "properties": {
    "iso:country":"FR",
    "sg:address":"4 Rue Nicephore Niepce 29200 Brest",
    "sg:city":"Brest",
    "sg:classifiers":[
        {
            "category":"Manufacturing",
            "subcategory":"Wood Products",
            "type":"Manufacturing & Wholesale Goods"
        }
    ],
    "sg:phone":"+33 2 98 03 32 49",
    "sg:postcode":"29200",
    "sg:province":"Bretagne",
    "sg:tags":[
        "professional",
        "furniture"
    ],
    "wof:name":"Menuiserie Bretonne",
    "wof:placetype":"venue"
},
  "geometry": {"coordinates":[-4.485237,48.425606],"type":"Point"}
}