{
  "type": "Feature",
  "properties": {
    "addr:full":"33, Rue Fortuni, 75017 Paris Ile de France",
    "addr:housenumber":"33",
    "addr:postcode":"75017",
    "addr:street":"Rue Fortuni",
    "iso:country":"FR",
    "sg:address":"33, Rue Fortuni, 75017 Paris",
    "sg:orig_category":"Unclassifiable Establishments",
    "sg:phone":"+33 1 46 22 44 45",
    "sg:province":"Ile de France",
    "wof:name":"Bracer-cerf S.a.",
    "wof:placetype":"venue"
},
  "geometry": {"coordinates":[2.307764,48.882938],"type":"Point"}
}