{
  "type": "Feature",
  "properties": {
    "iso:country":"FR",
    "sg:address":"B.P. 61, 87202 Saint Junien C\u00e9dex^^Cit\u00e9 Administrative Martial Pascaud, 87200 Saint Junien",
    "sg:orig_category":"Non-Classified Establishments",
    "sg:phone":"+33 5 55 02 05 71",
    "sg:postcode":"87200",
    "sg:province":"Limousin",
    "wof:name":"Elaboration Charte Intercomunale De Vienne Glane",
    "wof:placetype":"venue"
},
  "geometry": {"coordinates":[0.871925,45.87748],"type":"Point"}
}