{
  "type": "Feature",
  "properties": {
    "addr:full":"16, Rte de Castelnaux, 33480 Avensan Avensan Aquitaine 33480",
    "addr:housenumber":"16",
    "addr:postcode":"33480;33480",
    "addr:street":"Rte De Castelnaux",
    "iso:country":"FR",
    "sg:address":"16, Rte de Castelnaux, 33480 Avensan",
    "sg:city":"Avensan",
    "sg:orig_category":"Unclassifiable Establishments",
    "sg:phone":"+33 5 56 58 10 77",
    "sg:postcode":"33480",
    "sg:province":"Aquitaine",
    "wof:name":"Ch\u00e2teau Meyre S.a.",
    "wof:placetype":"venue"
},
  "geometry": {"coordinates":[-0.77429,45.030926],"type":"Point"}
}