{
  "type": "Feature",
  "properties": {
    "addr:full":"rue Barth\u00e9l\u00e9my Thimonnier 42334 Roanne Bourgogne",
    "addr:postcode":"42334",
    "addr:street":"Rue Barthe\u0301Le\u0301My Thimonnier",
    "iso:country":"FR",
    "sg:address":"rue Barth\u00e9l\u00e9my Thimonnier 42334 Roanne",
    "sg:classifiers":[
        {
            "category":"Manufacturing",
            "subcategory":"Building Materials",
            "type":"Manufacturing & Wholesale Goods"
        }
    ],
    "sg:phone":"+33 4 77 23 67 90",
    "sg:province":"Bourgogne",
    "sg:tags":[
        "filter",
        "dust",
        "separation",
        "air"
    ],
    "wof:name":"Genevet S.a.",
    "wof:placetype":"venue"
},
  "geometry": {"coordinates":[4.07187,46.039181],"type":"Point"}
}