{
  "type": "Feature",
  "properties": {
    "addr:full":"1 rue Jean Corona 69120 Vaulx en Velin Rhone-Alpes 69120",
    "addr:housenumber":"1",
    "addr:postcode":"69120;69120",
    "addr:street":"Rue Jean Corona",
    "iso:country":"FR",
    "sg:address":"1 rue Jean Corona 69120 Vaulx en Velin",
    "sg:orig_category":"Pressure Regulators",
    "sg:phone":"+33 4 72 04 75 00",
    "sg:postcode":"69120",
    "sg:province":"Rhone-Alpes",
    "wof:name":"Samson Sa",
    "wof:placetype":"venue"
},
  "geometry": {"coordinates":[4.907895,45.777199],"type":"Point"}
}