{
  "type": "Feature",
  "properties": {
    "addr:full":"716, Av Eisenhower, 54700 Montauville Lorraine",
    "addr:postcode":"54700",
    "addr:street":"716 Av Eisenhower",
    "iso:country":"FR",
    "sg:address":"716, Av Eisenhower, 54700 Montauville",
    "sg:orig_category":"Non-Classified Establishments",
    "sg:phone":"+33 3 83 81 03 26",
    "sg:province":"Lorraine",
    "wof:name":"Loritec S.a.r.l.",
    "wof:placetype":"venue"
},
  "geometry": {"coordinates":[6.028842,48.900925],"type":"Point"}
}