{
  "type": "Feature",
  "properties": {
    "iso:country":"FR",
    "sg:address":"ZI la Combe",
    "sg:city":"Surg\u00e8res",
    "sg:orig_category":"Unclassifiable Establishments",
    "sg:phone":"+33 5 46 07 01 81",
    "sg:postcode":"17700",
    "sg:province":"Poitou-Charentes",
    "wof:name":"Trillaud Jean",
    "wof:placetype":"venue"
},
  "geometry": {"coordinates":[-0.752141,46.105919],"type":"Point"}
}