{
  "type": "Feature",
  "properties": {
    "addr:full":"61, Rue Rispal, 76600 Le Havre Haute Normandie 76600",
    "addr:housenumber":"61",
    "addr:postcode":"76600;76600",
    "addr:street":"Rue Rispal",
    "iso:country":"FR",
    "sg:address":"61, Rue Rispal, 76600 Le Havre",
    "sg:orig_category":"Non-Classified Establishments",
    "sg:phone":"+33 2 35 66 99 39",
    "sg:postcode":"76600",
    "sg:province":"Haute Normandie",
    "wof:name":"Carri\u00e8re Orefi S.a.",
    "wof:placetype":"venue"
},
  "geometry": {"coordinates":[0.142177,49.492992],"type":"Point"}
}