{
  "type": "Feature",
  "properties": {
    "addr:full":"1 bd de la Boissonnette 42110 FEURS Rhone-Alpes",
    "addr:housenumber":"1",
    "addr:postcode":"42110",
    "addr:street":"Bd De La Boissonnette",
    "iso:country":"FR",
    "sg:address":"1 bd de la Boissonnette 42110 FEURS",
    "sg:classifiers":[
        {
            "category":"Retail",
            "subcategory":"Event Space",
            "type":"Services"
        }
    ],
    "sg:phone":"+33 4 77 27 41 11",
    "sg:province":"Rhone-Alpes",
    "sg:tags":[
        "steel",
        "casting"
    ],
    "wof:name":"Feursmetal S.a.",
    "wof:placetype":"venue"
},
  "geometry": {"coordinates":[4.22818,45.733227],"type":"Point"}
}