{
  "type": "Feature",
  "properties": {
    "iso:country":"FR",
    "sg:address":"16, Rue de la carri\u00e8re - ZI la Praz, 74130 Vougy",
    "sg:orig_category":"Non-Classified Establishments",
    "sg:phone":"+33 4 50 34 59 22",
    "sg:province":"Rhone-Alpes",
    "wof:name":"Isotec Industrie S.a.r.l.",
    "wof:placetype":"venue"
},
  "geometry": {"coordinates":[6.388322,45.95652],"type":"Point"}
}