{
  "type": "Feature",
  "properties": {
    "addr:full":"2 Boulevard Aristide Briand 66000 Perpignan Languedoc-Roussillon 66000",
    "addr:housenumber":"2",
    "addr:postcode":"66000;66000",
    "addr:street":"Boulevard Aristide Briand",
    "iso:country":"FR",
    "sg:address":"2 Boulevard Aristide Briand 66000 Perpignan",
    "sg:classifiers":[
        {
            "category":"Banks & Credit Unions",
            "subcategory":"Financial Services",
            "type":"Services"
        }
    ],
    "sg:phone":"+33 4 68 50 30 52",
    "sg:postcode":"66000",
    "sg:province":"Languedoc-Roussillon",
    "sg:tags":[
        "banking",
        "insurance",
        "institution",
        "finance"
    ],
    "wof:name":"Banque Populaire Des Pyrenees-orientales De L'aude Et (bppoaa)",
    "wof:placetype":"venue"
},
  "geometry": {"coordinates":[2.903072,42.696476],"type":"Point"}
}