{
  "type": "Feature",
  "properties": {
    "iso:country":"FR",
    "sg:address":"4 rue du Moulin Cailloux 94567 Orly",
    "sg:classifiers":[
        {
            "category":"Food & Beverages",
            "subcategory":"Chocolate",
            "type":"Retail Goods"
        }
    ],
    "sg:phone":"+33 1 45 12 09 10",
    "sg:province":"Languedoc-Roussillon",
    "sg:tags":[
        "export"
    ],
    "wof:name":"Daniel Loiseau Gamme Sa",
    "wof:placetype":"venue"
},
  "geometry": {"coordinates":[2.391669,48.748634],"type":"Point"}
}