{
  "type": "Feature",
  "properties": {
    "iso:country":"FR",
    "sg:address":"16, Av Carnot, 76250 D\u00e9ville l\u00e8s Rouen",
    "sg:orig_category":"Unclassifiable Establishments",
    "sg:phone":"+33 2 32 10 74 74",
    "sg:province":"Haute Normandie",
    "wof:name":"L.c. Cuisines S.a. - Groupe L.a.n.e.f. - Les Applications Nouvelles Electriques Du Froid",
    "wof:placetype":"venue"
},
  "geometry": {"coordinates":[1.050431,49.469139],"type":"Point"}
}