{
  "type": "Feature",
  "properties": {
    "addr:full":"22, Rue Berlioz, 19100 Brive la Gaillarde Limousin",
    "addr:housenumber":"22",
    "addr:postcode":"19100",
    "addr:street":"Rue Berlioz",
    "iso:country":"FR",
    "sg:address":"22, Rue Berlioz, 19100 Brive la Gaillarde",
    "sg:orig_category":"Non-Classified Establishments",
    "sg:phone":"+33 5 55 17 65 10",
    "sg:province":"Limousin",
    "wof:name":"Syndicat Intercommunal De Ramassage De Traitement D'ordures M\u00e9nag\u00e8res De La R\u00e9gion De Brive",
    "wof:placetype":"venue"
},
  "geometry": {"coordinates":[1.538636,45.168095],"type":"Point"}
}