{
  "type": "Feature",
  "properties": {
    "addr:full":"Rue Gay Lussac Immeuble Le Jupiter Viriat Rhone-Alpes 01440",
    "addr:housenumber":"immeuble",
    "addr:postcode":"01440",
    "addr:street":"Rue Gay Lussac",
    "iso:country":"FR",
    "sg:address":"Rue Gay Lussac Immeuble Le Jupiter",
    "sg:city":"Viriat",
    "sg:classifiers":[
        {
            "category":"Banks & Credit Unions",
            "subcategory":"Financial Services",
            "type":"Services"
        }
    ],
    "sg:phone":"+33 4 74 22 95 00",
    "sg:postcode":"01440",
    "sg:province":"Rhone-Alpes",
    "sg:tags":[
        "banking",
        "finance",
        "insurance"
    ],
    "wof:name":"Assurances Generales De France Vie (agf Vie)",
    "wof:placetype":"venue"
},
  "geometry": {"coordinates":[5.208474,46.221073],"type":"Point"}
}