{
  "type": "Feature",
  "properties": {
    "addr:full":"B.P. 40, 44550 Montoir de Bretagne^^ZI des No\u00ebs, 44550 Montoir de Bretagne Pays de Loire 44550",
    "addr:postcode":"44550;44550;44550",
    "addr:street":"B.P. 40",
    "iso:country":"FR",
    "sg:address":"B.P. 40, 44550 Montoir de Bretagne^^ZI des No\u00ebs, 44550 Montoir de Bretagne",
    "sg:orig_category":"Non-Classified Establishments",
    "sg:phone":"+33 2 40 45 11 47",
    "sg:postcode":"44550",
    "sg:province":"Pays de Loire",
    "wof:name":"Entreprise Philippe Lassarat S.a.",
    "wof:placetype":"venue"
},
  "geometry": {"coordinates":[-2.177519,47.308414],"type":"Point"}
}