{
  "type": "Feature",
  "properties": {
    "addr:full":"11 du Canal 18500 MEHUN SUR YEVRE Centre",
    "addr:housenumber":"11",
    "addr:postcode":"18500",
    "addr:street":"Du Canal;Yevre",
    "iso:country":"FR",
    "sg:address":"11",
    "sg:city":"du Canal 18500 MEHUN SUR YEVRE",
    "sg:orig_category":"Reeds For Woodwind Instruments And Saxophones",
    "sg:phone":"+33 2 48 57 31 78",
    "sg:province":"Centre",
    "wof:name":"Ets Riffault Et Fils",
    "wof:placetype":"venue"
},
  "geometry": {"coordinates":[2.21027,47.142872],"type":"Point"}
}