{
  "type": "Feature",
  "properties": {
    "addr:full":"3, Rue Labouche - ZI de Thibaut, 31084 Toulouse C\u00e9dex Centre",
    "addr:housenumber":"3",
    "addr:postcode":"31084",
    "addr:street":"Rue Labouche Zi De Thibaut",
    "iso:country":"FR",
    "sg:address":"3, Rue Labouche - ZI de Thibaut, 31084 Toulouse C\u00e9dex",
    "sg:orig_category":"Non-Classified Establishments",
    "sg:phone":"+33 5 61 40 10 15",
    "sg:province":"Centre",
    "wof:name":"Agirec S.a.",
    "wof:placetype":"venue"
},
  "geometry": {"coordinates":[1.44301,43.604359],"type":"Point"}
}