{
  "type": "Feature",
  "properties": {
    "iso:country":"FR",
    "sg:address":"B.P. 3",
    "sg:city":"Pont l'Ev\u00eaque^^60400 Pont l'Ev\u00eaque",
    "sg:orig_category":"Non-Classified Establishments",
    "sg:phone":"+33 3 44 09 08 22",
    "sg:postcode":"60400",
    "sg:province":"Picardie",
    "wof:name":"Rousseaux Et Debacker",
    "wof:placetype":"venue"
},
  "geometry": {"coordinates":[-111.964462,46.250797],"type":"Point"}
}