{
  "type": "Feature",
  "properties": {
    "iso:country":"FR",
    "sg:address":"Rue du Claret - ZI",
    "sg:city":"Charvieu Chavagneux",
    "sg:orig_category":"Unclassifiable Establishments",
    "sg:phone":"+33 4 72 02 91 17",
    "sg:postcode":"38230",
    "sg:province":"Rhone-Alpes",
    "wof:name":"E.g.n. S.a. - Entreprise G\u00e9n\u00e9rale De N\u00e9goce",
    "wof:placetype":"venue"
},
  "geometry": {"coordinates":[5.160112,45.745178],"type":"Point"}
}