{
  "type": "Feature",
  "properties": {
    "iso:country":"FR",
    "sg:address":"Za Rue Paul Richet 22120 Pommeret",
    "sg:city":"Pommeret",
    "sg:orig_category":"Industrial vehicles Metal processing Metallurgy and Metalworking Vehicles and Transport Equipment",
    "sg:phone":"+33 2 96 51 10 10",
    "sg:postcode":"22120",
    "sg:province":"Bretagne",
    "wof:name":"Soci\u00c9t\u00c9 Armoricaine M\u00c9canique De Pr\u00c9cision",
    "wof:placetype":"venue"
},
  "geometry": {"coordinates":[-2.626505,48.463249],"type":"Point"}
}