{
  "type": "Feature",
  "properties": {
    "iso:country":"FR",
    "sg:address":"B.P. 9",
    "sg:city":"Vacqueyras^^Les Roques 84190 Vacqueyras",
    "sg:orig_category":"Non-Classified Establishments",
    "sg:phone":"+33 4 90 65 85 16",
    "sg:postcode":"84190",
    "sg:province":"Nord Pas-de-Calais",
    "wof:name":"Ch\u00e2teau Des Roques S.c.e.a.",
    "wof:placetype":"venue"
},
  "geometry": {"coordinates":[5.059316,44.113422],"type":"Point"}
}