{
  "type": "Feature",
  "properties": {
    "iso:country":"FR",
    "sg:address":"56 Rue De Billancourt 92100 Boulogne Billancourt",
    "sg:classifiers":[
        {
            "category":"Shopping",
            "subcategory":"Gifts & Souvenirs",
            "type":"Retail Goods"
        }
    ],
    "sg:phone":"+33 1 46 04 14 42",
    "sg:postcode":"92100",
    "sg:province":"Ile de France",
    "sg:tags":[
        "product",
        "miscellaneous"
    ],
    "wof:name":"Cp Heng Et A Feliciano Sa",
    "wof:placetype":"venue"
},
  "geometry": {"coordinates":[2.235911,48.838779],"type":"Point"}
}