{
  "type": "Feature",
  "properties": {
    "iso:country":"FR",
    "sg:address":"91, Square Uranus, 34080 Montpellier",
    "sg:orig_category":"Non-Classified Establishments",
    "sg:phone":"+33 4 67 45 45 66",
    "sg:postcode":"34080",
    "sg:province":"Languedoc-Roussillon",
    "wof:name":"Chroma E.u.r.l.",
    "wof:placetype":"venue"
},
  "geometry": {"coordinates":[3.820481,43.628967],"type":"Point"}
}