{
  "type": "Feature",
  "properties": {
    "addr:full":"43, Rue Vineuse, 75016 Paris Ile de France",
    "addr:housenumber":"43",
    "addr:postcode":"75016",
    "addr:street":"Rue Vineuse",
    "iso:country":"FR",
    "sg:address":"43, Rue Vineuse, 75016 Paris",
    "sg:orig_category":"Unclassifiable Establishments",
    "sg:phone":"+33 1 55 73 22 22",
    "sg:province":"Ile de France",
    "wof:name":"Banque Arjil S.c.a.",
    "wof:placetype":"venue"
},
  "geometry": {"coordinates":[2.285535,48.861111],"type":"Point"}
}