{
  "type": "Feature",
  "properties": {
    "addr:full":"B.P. 62162, 35221 Ch\u00e2teaubourg C\u00e9dex^^ZI de Bellevue, 35220 Ch\u00e2teaubourg Ch\u00e2teaubourg Nord Pas-de-Calais 35220",
    "addr:postcode":"35221;35220;35220",
    "addr:street":"Bellevue",
    "iso:country":"FR",
    "sg:address":"B.P. 62162, 35221 Ch\u00e2teaubourg C\u00e9dex^^ZI de Bellevue, 35220 Ch\u00e2teaubourg",
    "sg:city":"Ch\u00e2teaubourg",
    "sg:orig_category":"Non-Classified Establishments",
    "sg:phone":"+33 2 99 00 93 30",
    "sg:postcode":"35220",
    "sg:province":"Nord Pas-de-Calais",
    "wof:name":"Schock France S.a.r.l.",
    "wof:placetype":"venue"
},
  "geometry": {"coordinates":[-1.371241,48.095028],"type":"Point"}
}