{
  "type": "Feature",
  "properties": {
    "addr:full":"24, Av. Joann\u00e8s Masset, 69009 Lyon Rhone-Alpes 69009",
    "addr:postcode":"69009;69009",
    "addr:street":"24 Av. Joanne\u0300S Masset",
    "iso:country":"FR",
    "sg:address":"24, Av. Joann\u00e8s Masset, 69009 Lyon",
    "sg:orig_category":"Unclassifiable Establishments",
    "sg:phone":"+33 4 72 19 83 30",
    "sg:postcode":"69009",
    "sg:province":"Rhone-Alpes",
    "wof:name":"Editions \u00e0 Coeur Joie S.a.r.l.",
    "wof:placetype":"venue"
},
  "geometry": {"coordinates":[4.800193,45.770794],"type":"Point"}
}