{
  "type": "Feature",
  "properties": {
    "iso:country":"FR",
    "sg:address":"B.P. 107",
    "sg:city":"Reims C\u00e9dex 2",
    "sg:orig_category":"Non-Classified Establishments",
    "sg:phone":"+33 3 26 87 72 20",
    "sg:postcode":"51684",
    "sg:province":"Champagne-Ardenne",
    "wof:name":"Eurovia Champagne Ardenne Lorraine S.n.c.",
    "wof:placetype":"venue"
},
  "geometry": {"coordinates":[4.03384,49.25415],"type":"Point"}
}