{
  "type": "Feature",
  "properties": {
    "iso:country":"FR",
    "sg:address":"Av Saint Quenin 84110 Vaison La Romaine",
    "sg:classifiers":[
        {
            "category":"Food Court",
            "type":"Food & Drink"
        }
    ],
    "sg:phone":"+33 4 90 36 00 43",
    "sg:province":"Poitou-Charentes",
    "sg:tags":[
        "product",
        "related"
    ],
    "wof:name":"Cave Coop La Romaine",
    "wof:placetype":"venue"
},
  "geometry": {"coordinates":[5.067276,44.244198],"type":"Point"}
}