{
  "type": "Feature",
  "properties": {
    "iso:country":"FR",
    "sg:address":"B.P. 1, 14630 Cagny C\u00e9dex^^Rte de Paris, 14630 Cagny",
    "sg:city":"Cagny",
    "sg:orig_category":"Non-Classified Establishments",
    "sg:phone":"+33 2 31 39 49 18",
    "sg:postcode":"14630",
    "sg:province":"Basse Normandie",
    "wof:name":"Lyven S.a.",
    "wof:placetype":"venue"
},
  "geometry": {"coordinates":[-0.256599,49.14735],"type":"Point"}
}