{
  "type": "Feature",
  "properties": {
    "addr:full":"38, Rue Vauthier, 92774 Boulogne Billancourt C\u00e9dex Ancourt Haute Normandie 76370",
    "addr:housenumber":"38",
    "addr:postcode":"92774;76370",
    "addr:street":"Rue Vauthier;Haute Normandie",
    "iso:country":"FR",
    "sg:address":"38, Rue Vauthier, 92774 Boulogne Billancourt C\u00e9dex",
    "sg:city":"Ancourt",
    "sg:orig_category":"Non-Classified Establishments",
    "sg:phone":"+33 1 46 99 36 16",
    "sg:postcode":"76370",
    "sg:province":"Haute Normandie",
    "wof:name":"Lincoln S.a.",
    "wof:placetype":"venue"
},
  "geometry": {"coordinates":[2.24224,48.845104],"type":"Point"}
}