{
  "type": "Feature",
  "properties": {
    "addr:full":"39 Pl Jean Jaur\u00e8s 10000 Troyes Champagne",
    "addr:housenumber":"39",
    "addr:postcode":"10000",
    "addr:street":"Pl Jean Jaure\u0300S",
    "iso:country":"FR",
    "sg:address":"39 Pl Jean Jaur\u00e8s 10000 Troyes",
    "sg:classifiers":[
        {
            "category":"Professional",
            "subcategory":"Printing & Photocopies",
            "type":"Services"
        }
    ],
    "sg:phone":"+33 3 25 82 68 50",
    "sg:province":"Champagne",
    "sg:tags":[
        "publishing"
    ],
    "wof:name":"Liberation Champagne Sa",
    "wof:placetype":"venue"
},
  "geometry": {"coordinates":[4.070297,48.294384],"type":"Point"}
}