{
  "type": "Feature",
  "properties": {
    "iso:country":"FR",
    "sg:address":"ZI",
    "sg:city":"Emile Romanet BP 9428 73000 Chamb\u00e9ry",
    "sg:classifiers":[
        {
            "category":"Food Court",
            "type":"Food & Drink"
        }
    ],
    "sg:phone":"+33 4 79 25 68 76",
    "sg:postcode":"73000",
    "sg:province":"Rhone-Alpes",
    "sg:tags":[
        "product",
        "related"
    ],
    "wof:name":"Routin",
    "wof:placetype":"venue"
},
  "geometry": {"coordinates":[5.92092,45.566647],"type":"Point"}
}