{
  "type": "Feature",
  "properties": {
    "addr:full":"B.P. 70, 76202 Dieppe C\u00e9dex^^Av Normandy Sussex, 76200 Dieppe Haute Normandie",
    "addr:postcode":"76202;76200",
    "addr:street":"B.P. 70",
    "iso:country":"FR",
    "sg:address":"B.P. 70, 76202 Dieppe C\u00e9dex^^Av Normandy Sussex, 76200 Dieppe",
    "sg:orig_category":"Non-Classified Establishments",
    "sg:phone":"+33 2 32 90 51 51",
    "sg:province":"Haute Normandie",
    "wof:name":"Marchand S.a.",
    "wof:placetype":"venue"
},
  "geometry": {"coordinates":[1.07936,49.927204],"type":"Point"}
}