{
  "type": "Feature",
  "properties": {
    "addr:full":"3, Rue de Champ Pillard, 77400 Saint Thibault des Vignes Ile de France",
    "addr:housenumber":"3",
    "addr:postcode":"77400;ile",
    "addr:street":"Rue De Champ Pillard",
    "iso:country":"FR",
    "sg:address":"3, Rue de Champ Pillard, 77400 Saint Thibault des Vignes",
    "sg:orig_category":"Unclassifiable Establishments",
    "sg:phone":"+33 1 60 35 02 20",
    "sg:province":"Ile de France",
    "wof:name":"S.a.e.m.e. S.a. - Soci\u00e9t\u00e9 D'application Et D'etudes De Mat\u00e9riel Electronique",
    "wof:placetype":"venue"
},
  "geometry": {"coordinates":[2.664731,48.854233],"type":"Point"}
}