{
  "type": "Feature",
  "properties": {
    "iso:country":"FR",
    "sg:address":"151, Av. des Aygalades - B\u00e2t. Jacques Remezan, 13015 Marseille",
    "sg:orig_category":"Unclassifiable Establishments",
    "sg:phone":"+33 4 91 03 25 65",
    "sg:province":"Nord Pas-de-Calais",
    "wof:name":"Affiche Europ\u00e9enne S\u00e9rigraphie S.a.",
    "wof:placetype":"venue"
},
  "geometry": {"coordinates":[5.366048,43.345402],"type":"Point"}
}