{
  "type": "Feature",
  "properties": {
    "iso:country":"FR",
    "sg:address":"5 rue de Rome; Paris; 75008",
    "sg:classifiers":[
        {
            "category":"Banks & Credit Unions",
            "subcategory":"Bank",
            "type":"Services"
        }
    ],
    "sg:phone":"+33 1 45 22 94 11",
    "sg:postcode":"75008",
    "sg:province":"Ile de France",
    "wof:name":"Akbank Tas",
    "wof:placetype":"venue"
},
  "geometry": {"coordinates":[2.325166,48.874336],"type":"Point"}
}