{
  "type": "Feature",
  "properties": {
    "addr:full":"Chemin des Paquottiers - ZI de la Vendue Chaumont Champagne 52000",
    "addr:postcode":"52000",
    "addr:street":"Chemin Des Paquottiers Zi De La Vendue;Champagne",
    "iso:country":"FR",
    "sg:address":"Chemin des Paquottiers - ZI de la Vendue",
    "sg:city":"Chaumont",
    "sg:orig_category":"Unclassifiable Establishments",
    "sg:phone":"+33 3 25 32 06 66",
    "sg:postcode":"52000",
    "sg:province":"Champagne",
    "wof:name":"Loueurs De France - Division Locatra S.a.",
    "wof:placetype":"venue"
},
  "geometry": {"coordinates":[5.135536,48.110767],"type":"Point"}
}