{
  "type": "Feature",
  "properties": {
    "iso:country":"FR",
    "sg:address":"54 Route De Noailles Zi D Angleterre 60570 Andeville",
    "sg:classifiers":[
        {
            "category":"Manufacturing",
            "subcategory":"Rubber & Plastics",
            "type":"Manufacturing & Wholesale Goods"
        }
    ],
    "sg:phone":"+33 3 44 52 40 00",
    "sg:province":"Picardie",
    "wof:name":"Sarl Auger Baudier Bourel Plastiques",
    "wof:placetype":"venue"
},
  "geometry": {"coordinates":[2.166016,49.259056],"type":"Point"}
}