{
  "type": "Feature",
  "properties": {
    "addr:full":"Av Du Port J\u00e9rome Rte De Seine 76330 Notre Dame De Gravenchon Haute Normandie 76330",
    "addr:postcode":"76330;76330",
    "addr:street":"Av Du Port Je\u0301Rome Rte De Seine;Dame",
    "iso:country":"FR",
    "sg:address":"Av Du Port J\u00e9rome Rte De Seine 76330 Notre Dame De Gravenchon",
    "sg:classifiers":[
        {
            "category":"Building & Trades",
            "subcategory":"Construction",
            "type":"Services"
        }
    ],
    "sg:phone":"+33 2 32 84 57 57",
    "sg:postcode":"76330",
    "sg:province":"Haute Normandie",
    "sg:tags":[
        "work",
        "public"
    ],
    "wof:name":"Ouest Tp Snc",
    "wof:placetype":"venue"
},
  "geometry": {"coordinates":[0.5674,49.489555],"type":"Point"}
}