{
  "type": "Feature",
  "properties": {
    "addr:full":"B.P. 121, 25201 Montb\u00e9liard C\u00e9dex^^1, Rue de la Schliffe, 25200 Montb\u00e9liard Franche Comt\u00e9",
    "addr:housenumber":"b.p. 121",
    "addr:postcode":"25201;25200",
    "addr:street":"Rue De La Schliffe;Franche Comte\u0301",
    "iso:country":"FR",
    "sg:address":"B.P. 121, 25201 Montb\u00e9liard C\u00e9dex^^1, Rue de la Schliffe, 25200 Montb\u00e9liard",
    "sg:orig_category":"Non-Classified Establishments",
    "sg:phone":"+33 3 81 96 71 32",
    "sg:province":"Franche Comt\u00e9",
    "wof:name":"I.f.p.a. Centre Nord Franche-comt\u00e9",
    "wof:placetype":"venue"
},
  "geometry": {"coordinates":[6.80297,47.508614],"type":"Point"}
}