{
  "type": "Feature",
  "properties": {
    "addr:full":"ZA des Combaches 73103 Aix les Bains Auvergne",
    "addr:postcode":"73103",
    "addr:street":"Za Des Combaches",
    "iso:country":"FR",
    "sg:address":"ZA des Combaches 73103 Aix les Bains",
    "sg:orig_category":"Yoghurt And Yoghurt Preparations",
    "sg:phone":"+33 4 79 61 23 33",
    "sg:province":"Auvergne",
    "wof:name":"Savoie Yaourt Sarl",
    "wof:placetype":"venue"
},
  "geometry": {"coordinates":[3.7829,45.010288],"type":"Point"}
}