{
  "type": "Feature",
  "properties": {
    "addr:full":"1 R De La Gla\u00e7i\u00e8re 42510 Balbigny Rhone-Alpes 42510",
    "addr:housenumber":"1",
    "addr:postcode":"42510;42510",
    "addr:street":"R De La Glac\u0327Ie\u0300Re;Rhone-Alpes",
    "iso:country":"FR",
    "sg:address":"1 R De La Gla\u00e7i\u00e8re 42510 Balbigny",
    "sg:classifiers":[
        {
            "category":"Bakery",
            "type":"Food & Drink"
        }
    ],
    "sg:phone":"+33 4 77 28 14 49",
    "sg:postcode":"42510",
    "sg:province":"Rhone-Alpes",
    "sg:tags":[
        "cake",
        "product",
        "related",
        "bread"
    ],
    "wof:name":"Au Pecher Gourmand",
    "wof:placetype":"venue"
},
  "geometry": {"coordinates":[4.181,45.82032],"type":"Point"}
}