{
  "type": "Feature",
  "properties": {
    "addr:full":"49 bis, Av. du Pr\u00e9sident Roosevelt, 77210 Avon Ile de France",
    "addr:housenumber":"49 bis",
    "addr:postcode":"77210",
    "addr:street":"Av. Du Pre\u0301Sident Roosevelt;Ile De France",
    "iso:country":"FR",
    "sg:address":"49 bis, Av. du Pr\u00e9sident Roosevelt, 77210 Avon",
    "sg:orig_category":"Unclassifiable Establishments",
    "sg:phone":"+33 1 60 74 99 22",
    "sg:province":"Ile de France",
    "wof:name":"Presti Web.com S.a.r.l.",
    "wof:placetype":"venue"
},
  "geometry": {"coordinates":[2.720798,48.415749],"type":"Point"}
}