{
  "type": "Feature",
  "properties": {
    "iso:country":"FR",
    "sg:address":"B.P. 7",
    "sg:city":"Pl\u00e9neuf Val Andr\u00e9^^La Croix des Landes 22370 Pl\u00e9neuf Val Andr\u00e9",
    "sg:orig_category":"Non-Classified Establishments",
    "sg:phone":"+33 2 96 72 96 39",
    "sg:postcode":"22370",
    "sg:province":"Bretagne",
    "wof:name":"Transports Davoust S.a.",
    "wof:placetype":"venue"
},
  "geometry": {"coordinates":[-0.838414,49.09343],"type":"Point"}
}