{
  "type": "Feature",
  "properties": {
    "addr:full":"37370 Saint Christophe sur le Nais Bueil-en-Touraine Centre 37370",
    "addr:housenumber":"37370",
    "addr:postcode":"37370",
    "addr:street":"Saint Christophe Sur Le;Bueil-En-Touraine",
    "iso:country":"FR",
    "sg:address":"37370 Saint Christophe sur le Nais",
    "sg:city":"Bueil-en-Touraine",
    "sg:orig_category":"Unclassifiable Establishments",
    "sg:phone":"+33 2 47 29 21 32",
    "sg:postcode":"37370",
    "sg:province":"Centre",
    "wof:name":"F.s.p. - Coop\u00e9rative Fruits De Saint Paterne Racan",
    "wof:placetype":"venue"
},
  "geometry": {"coordinates":[0.475796,47.6166],"type":"Point"}
}