{
  "type": "Feature",
  "properties": {
    "addr:full":"Les Bruy\u00e8res 01340 Malafretaz Rhone-Alpes",
    "addr:postcode":"01340",
    "iso:country":"FR",
    "sg:address":"Les Bruy\u00e8res 01340 Malafretaz",
    "sg:orig_category":"Unclassifiable Establishments",
    "sg:phone":"+33 4 74 30 84 65",
    "sg:province":"Rhone-Alpes",
    "wof:name":"Arban Chauffage Sanitaire S.a.r.l.",
    "wof:placetype":"venue"
},
  "geometry": {"coordinates":[5.14279,46.312237],"type":"Point"}
}