{
  "type": "Feature",
  "properties": {
    "iso:country":"FR",
    "sg:address":"10 Rue Paulin Charron 17800 Pons",
    "sg:classifiers":[
        {
            "category":"Food & Beverages",
            "subcategory":"Fruits & Vegetables",
            "type":"Retail Goods"
        }
    ],
    "sg:phone":"+33 5 46 91 47 47",
    "sg:postcode":"17800",
    "sg:province":"Poitou-Charentes",
    "sg:tags":[
        "preserve",
        "cake",
        "product",
        "related",
        "bread"
    ],
    "wof:name":"Service Et Distribution",
    "wof:placetype":"venue"
},
  "geometry": {"coordinates":[-0.537589,45.580753],"type":"Point"}
}