{
  "type": "Feature",
  "properties": {
    "addr:full":"164, Bd Jean Jaur\u00e8s, 42170 Saint Just Saint Rambert Rhone-Alpes 42170",
    "addr:housenumber":"164",
    "addr:postcode":"42170;42170",
    "addr:street":"Bd Jean Jaure\u0300S",
    "iso:country":"FR",
    "sg:address":"164, Bd Jean Jaur\u00e8s, 42170 Saint Just Saint Rambert",
    "sg:orig_category":"Unclassifiable Establishments",
    "sg:phone":"+33 4 77 52 70 50",
    "sg:postcode":"42170",
    "sg:province":"Rhone-Alpes",
    "wof:name":"J.b. S.a. - Etablissements Bros",
    "wof:placetype":"venue"
},
  "geometry": {"coordinates":[4.263755,45.513088],"type":"Point"}
}