{
  "type": "Feature",
  "properties": {
    "iso:country":"FR",
    "sg:address":"1 bis, Rue Victor Magniez, 80000 Amiens",
    "sg:orig_category":"Unclassifiable Establishments",
    "sg:phone":"+33 3 22 33 11 73",
    "sg:province":"Picardie",
    "wof:name":"Habitat 2000 S.a.r.l.",
    "wof:placetype":"venue"
},
  "geometry": {"coordinates":[2.27877,49.882244],"type":"Point"}
}