{
  "type": "Feature",
  "properties": {
    "addr:full":"Zone Industrielle Geule 64370 Arthez De B\u00e9arn Arnos Aquitaine 64370",
    "addr:postcode":"64370;64370",
    "addr:street":"Zone Industrielle Geule",
    "iso:country":"FR",
    "sg:address":"Zone Industrielle Geule 64370 Arthez De B\u00e9arn",
    "sg:city":"Arnos",
    "sg:classifiers":[
        {
            "category":"Shopping",
            "type":"Retail Goods"
        }
    ],
    "sg:phone":"+33 5 59 67 76 11",
    "sg:postcode":"64370",
    "sg:province":"Aquitaine",
    "sg:tags":[
        "metallurgy",
        "finished",
        "-",
        "metalworking",
        "metallic"
    ],
    "wof:name":"Citba Sa",
    "wof:placetype":"venue"
},
  "geometry": {"coordinates":[-0.615139,43.4646],"type":"Point"}
}