{
  "type": "Feature",
  "properties": {
    "addr:full":"11, Rue Gambey, 10000 Troyes Champagne",
    "addr:housenumber":"11",
    "addr:postcode":"10000",
    "addr:street":"Rue Gambey",
    "iso:country":"FR",
    "sg:address":"11, Rue Gambey, 10000 Troyes",
    "sg:orig_category":"Non-Classified Establishments",
    "sg:phone":"+33 3 25 73 70 27",
    "sg:province":"Champagne",
    "wof:name":"Gestetner S.a.",
    "wof:placetype":"venue"
},
  "geometry": {"coordinates":[4.076188,48.299091],"type":"Point"}
}