{
  "type": "Feature",
  "properties": {
    "iso:country":"FR",
    "sg:address":"100, Rte de N\u00eemes - L'Atrium, 30132 Caissargues",
    "sg:orig_category":"Unclassifiable Establishments",
    "sg:phone":"+33 4 66 38 35 36",
    "sg:province":"Languedoc-Roussillon",
    "wof:name":"Isor S.a.",
    "wof:placetype":"venue"
},
  "geometry": {"coordinates":[4.374589,43.800999],"type":"Point"}
}