{
  "type": "Feature",
  "properties": {
    "addr:full":"14, Av. de l'Europe, 31520 Ramonville Saint Agne Midi Pyr\u00e9n\u00e9es",
    "addr:postcode":"31520",
    "addr:street":"14 Av. De L'Europe",
    "iso:country":"FR",
    "sg:address":"14, Av. de l'Europe, 31520 Ramonville Saint Agne",
    "sg:orig_category":"Unclassifiable Establishments",
    "sg:phone":"+33 5 62 19 05 34",
    "sg:province":"Midi Pyr\u00e9n\u00e9es",
    "wof:name":"G\u00e9nigraph",
    "wof:placetype":"venue"
},
  "geometry": {"coordinates":[1.485891,43.552814],"type":"Point"}
}