{
  "type": "Feature",
  "properties": {
    "iso:country":"FR",
    "sg:address":"B.P. 15, 74301 Cluses C\u00e9dex^^51, Av. du Docteur Jacques Arnaud, 74300 Cluses",
    "sg:orig_category":"Non-Classified Establishments",
    "sg:phone":"+33 4 50 98 46 99",
    "sg:postcode":"74300",
    "sg:province":"Rhone-Alpes",
    "wof:name":"Gaillard S.a.",
    "wof:placetype":"venue"
},
  "geometry": {"coordinates":[6.633185,45.987919],"type":"Point"}
}