{
  "type": "Feature",
  "properties": {
    "addr:full":"194 Avenue De Prades 66000 Perpignan Languedoc-Roussillon 66000",
    "addr:housenumber":"194",
    "addr:postcode":"66000;66000",
    "addr:street":"Avenue De Prades",
    "iso:country":"FR",
    "sg:address":"194 Avenue De Prades 66000 Perpignan",
    "sg:classifiers":[
        {
            "category":"Wholesale",
            "subcategory":"Farm Supplies",
            "type":"Manufacturing & Wholesale Goods"
        }
    ],
    "sg:phone":"+33 4 68 68 33 55",
    "sg:postcode":"66000",
    "sg:province":"Languedoc-Roussillon",
    "sg:tags":[
        "-",
        "machine",
        "equipment",
        "engineering",
        "machinery",
        "mechanical",
        "agriculture"
    ],
    "wof:name":"Irri 66",
    "wof:placetype":"venue"
},
  "geometry": {"coordinates":[2.846701,42.692909],"type":"Point"}
}