{
  "type": "Feature",
  "properties": {
    "iso:country":"FR",
    "sg:address":"Quai Du Port 94130 Nogent Sur Marne",
    "sg:classifiers":[
        {
            "category":"Travel",
            "subcategory":"Hotels & Motels",
            "type":"Entertainment"
        }
    ],
    "sg:phone":"+33 1 48 72 51 98",
    "sg:postcode":"94130",
    "sg:province":"Ile de France",
    "sg:tags":[
        "hotels",
        "business",
        "restaurant"
    ],
    "wof:name":"Hotel-grill Campanile",
    "wof:placetype":"venue"
},
  "geometry": {"coordinates":[2.494325,48.832245],"type":"Point"}
}