{
  "type": "Feature",
  "properties": {
    "iso:country":"FR",
    "sg:address":"13/14, Rue Jules Guesde - ZI du Bois de l'Epine, 91130 Ris Orangis",
    "sg:orig_category":"Unclassifiable Establishments",
    "sg:phone":"+33 1 60 77 25 66",
    "sg:province":"Ile de France",
    "wof:name":"Fonderie De Gentilly S.a.",
    "wof:placetype":"venue"
},
  "geometry": {"coordinates":[2.41432,48.656807],"type":"Point"}
}