{
  "type": "Feature",
  "properties": {
    "iso:country":"FR",
    "sg:address":"2, Av. de Paris - Immeuble le Primat, 45000 Orl\u00e9ans",
    "sg:city":"Orl\u00e9ans",
    "sg:orig_category":"Non-Classified Establishments",
    "sg:phone":"+33 2 38 42 00 60",
    "sg:postcode":"45000",
    "sg:province":"Centre",
    "wof:name":"Imagine L Informatique S.a.",
    "wof:placetype":"venue"
},
  "geometry": {"coordinates":[1.909303,47.900215],"type":"Point"}
}