{
  "type": "Feature",
  "properties": {
    "iso:country":"FR",
    "sg:address":"15, Rue de Saint Denis, 93125 La Courneuve C\u00e9dex",
    "sg:orig_category":"Non-Classified Establishments",
    "sg:phone":"+33 1 48 35 72 65",
    "sg:province":"Haute Normandie",
    "wof:name":"Insituform France S.a.",
    "wof:placetype":"venue"
},
  "geometry": {"coordinates":[2.384501,48.930298],"type":"Point"}
}