{
  "type": "Feature",
  "properties": {
    "iso:country":"FR",
    "sg:address":"B.P. 22, 71210 Montchanin^^7, Rue Macon, 71210 Montchanin",
    "sg:city":"Montchanin",
    "sg:orig_category":"Non-Classified Establishments",
    "sg:phone":"+33 3 85 78 10 82",
    "sg:postcode":"71210",
    "sg:province":"Bourgogne",
    "wof:name":"Laboratoire Pierre Chatonnier S.a.",
    "wof:placetype":"venue"
},
  "geometry": {"coordinates":[4.463261,46.713284],"type":"Point"}
}