{
  "type": "Feature",
  "properties": {
    "addr:full":"B.P. 405, 07004 Privas C\u00e9dex^^Av. de l'Usine - ZI, 07000 Privas Rhone-Alpes 07000",
    "addr:housenumber":"b.p. 405",
    "addr:postcode":"07004;07000;07000",
    "addr:street":"Zi",
    "iso:country":"FR",
    "sg:address":"B.P. 405, 07004 Privas C\u00e9dex^^Av. de l'Usine - ZI, 07000 Privas",
    "sg:orig_category":"Non-Classified Establishments",
    "sg:phone":"+33 4 75 64 16 16",
    "sg:postcode":"07000",
    "sg:province":"Rhone-Alpes",
    "wof:name":"Artemis S.a.",
    "wof:placetype":"venue"
},
  "geometry": {"coordinates":[4.65211,44.705601],"type":"Point"}
}