{
  "type": "Feature",
  "properties": {
    "iso:country":"FR",
    "sg:address":"62200 Boulogne sur Mer C\u00e9dex^^8, Rue d'Alsace, 62200 Boulogne sur Mer",
    "sg:orig_category":"Non-Classified Establishments",
    "sg:phone":"+33 3 21 30 08 16",
    "sg:province":"Nord Pas-de-Calais",
    "wof:name":"Facomar, S.a.",
    "wof:placetype":"venue"
},
  "geometry": {"coordinates":[1.597258,50.719219],"type":"Point"}
}