{
  "type": "Feature",
  "properties": {
    "addr:full":"8, Rue de Coetquen, 35000 Rennes Rennes Bretagne 35000",
    "addr:housenumber":"8",
    "addr:postcode":"35000;35000",
    "addr:street":"Rue De Coetquen",
    "iso:country":"FR",
    "sg:address":"8, Rue de Coetquen, 35000 Rennes",
    "sg:city":"Rennes",
    "sg:orig_category":"Unclassifiable Establishments",
    "sg:phone":"+33 2 99 79 33 80",
    "sg:postcode":"35000",
    "sg:province":"Bretagne",
    "wof:name":"Infratest Burke",
    "wof:placetype":"venue"
},
  "geometry": {"coordinates":[-1.678478,48.11087],"type":"Point"}
}