{
  "type": "Feature",
  "properties": {
    "addr:full":"6, Rue Denis Papin, 44600 Saint Nazaire Pays de Loire",
    "addr:housenumber":"6",
    "addr:postcode":"44600",
    "addr:street":"Rue Denis Papin;Nazaire",
    "iso:country":"FR",
    "sg:address":"6, Rue Denis Papin, 44600 Saint Nazaire",
    "sg:orig_category":"Unclassifiable Establishments",
    "sg:phone":"+33 2 51 10 60 70",
    "sg:province":"Pays de Loire",
    "wof:name":"Elyo Centre Ouest",
    "wof:placetype":"venue"
},
  "geometry": {"coordinates":[-2.296892,47.302799],"type":"Point"}
}