{
  "type": "Feature",
  "properties": {
    "iso:country":"FR",
    "sg:address":"Rue Franklin Roosevelt 38500 Voiron",
    "sg:classifiers":[
        {
            "category":"Food & Beverages",
            "subcategory":"Fruits & Vegetables",
            "type":"Retail Goods"
        }
    ],
    "sg:phone":"+33 4 76 65 95 75",
    "sg:postcode":"38500",
    "sg:province":"Rhone-Alpes",
    "sg:tags":[
        "frozen",
        "product",
        "related"
    ],
    "wof:name":"Brake Sa",
    "wof:placetype":"venue"
},
  "geometry": {"coordinates":[5.59467,45.361225],"type":"Point"}
}