{
  "type": "Feature",
  "properties": {
    "addr:full":"1176 Avenue Aristide Briand 38220 Vizille Rhone-Alpes",
    "addr:housenumber":"1176",
    "addr:postcode":"38220",
    "addr:street":"Avenue Aristide Briand",
    "iso:country":"FR",
    "sg:address":"1176 Avenue Aristide Briand 38220 Vizille",
    "sg:classifiers":[
        {
            "category":"Manufacturing",
            "subcategory":"Paper Products",
            "type":"Manufacturing & Wholesale Goods"
        }
    ],
    "sg:phone":"+33 4 76 68 54 07",
    "sg:province":"Rhone-Alpes",
    "sg:tags":[
        "raw",
        "material",
        "-",
        "cardboard"
    ],
    "wof:name":"Vicat",
    "wof:placetype":"venue"
},
  "geometry": {"coordinates":[5.77145,45.070541],"type":"Point"}
}