{
  "type": "Feature",
  "properties": {
    "addr:full":"B.P. 3, 44260 Savenay^^Bd des Acacias, 44260 Savenay Pays de Loire",
    "addr:housenumber":"3",
    "addr:postcode":"44260;44260",
    "addr:street":"B.P.;Des Acacias",
    "iso:country":"FR",
    "sg:address":"B.P. 3, 44260 Savenay^^Bd des Acacias, 44260 Savenay",
    "sg:orig_category":"Non-Classified Establishments",
    "sg:phone":"+33 2 40 58 39 05",
    "sg:province":"Pays de Loire",
    "wof:name":"Trouvay & Cauvin S.a.",
    "wof:placetype":"venue"
},
  "geometry": {"coordinates":[-1.965349,47.30954],"type":"Point"}
}