{
  "type": "Feature",
  "properties": {
    "addr:full":"B.P. 85, 85690 Notre Dame de Monts^^ZA, 85690 Notre Dame de Monts Pays de Loire",
    "addr:postcode":"85690;85690",
    "addr:street":"B.P. 85;Dame;De",
    "iso:country":"FR",
    "sg:address":"B.P. 85, 85690 Notre Dame de Monts^^ZA, 85690 Notre Dame de Monts",
    "sg:orig_category":"Non-Classified Establishments",
    "sg:phone":"+33 2 51 58 45 03",
    "sg:province":"Pays de Loire",
    "wof:name":"Gastromer S.a.",
    "wof:placetype":"venue"
},
  "geometry": {"coordinates":[-2.131849,46.828014],"type":"Point"}
}