{
  "type": "Feature",
  "properties": {
    "iso:country":"FR",
    "sg:address":"234, Rue Pierre Legrand, 59800 Lille",
    "sg:orig_category":"Unclassifiable Establishments",
    "sg:phone":"+33 3 20 56 74 07",
    "sg:province":"Nord Pas-de-Calais",
    "wof:name":"Delesalle - Les Amis Du Boulanger",
    "wof:placetype":"venue"
},
  "geometry": {"coordinates":[3.093353,50.631824],"type":"Point"}
}