{
  "type": "Feature",
  "properties": {
    "iso:country":"FR",
    "sg:address":"6, Rue de la Douett\u00e9e, 44230 Saint S\u00e9bastien sur Loire",
    "sg:orig_category":"Non-Classified Establishments",
    "sg:phone":"+33 2 40 80 71 33",
    "sg:postcode":"44230",
    "sg:province":"Pays de Loire",
    "wof:name":"Couillaud Pierre",
    "wof:placetype":"venue"
},
  "geometry": {"coordinates":[-1.498029,47.208027],"type":"Point"}
}