{
  "type": "Feature",
  "properties": {
    "iso:country":"FR",
    "sg:address":"Lieu Dit Le Boissard 73520 St Beron",
    "sg:classifiers":[
        {
            "category":"Utilities",
            "subcategory":"Mobile Phone",
            "type":"Services"
        }
    ],
    "sg:phone":"+33 4 76 31 23 00",
    "sg:postcode":"73520",
    "sg:province":"Rhone-Alpes",
    "sg:tags":[
        "good",
        "telecommunication",
        "-",
        "metalworking",
        "metallic",
        "metallurgy",
        "finished"
    ],
    "wof:name":"Sa Pic Bois Gravures",
    "wof:placetype":"venue"
},
  "geometry": {"coordinates":[5.734835,45.511154],"type":"Point"}
}