{
  "type": "Feature",
  "properties": {
    "addr:full":"Rue les Pr\u00e9s Liats Gannat Auvergne 03800",
    "addr:postcode":"03800",
    "addr:street":"Rue Les Pre\u0301S Liats Gannat",
    "iso:country":"FR",
    "sg:address":"Rue les Pr\u00e9s Liats",
    "sg:city":"Gannat",
    "sg:orig_category":"Unclassifiable Establishments",
    "sg:phone":"+33 4 70 07 07 07",
    "sg:postcode":"03800",
    "sg:province":"Auvergne",
    "wof:name":"S.n.b. S.a.r.l. - Soci\u00e9t\u00e9 Nouvelle Brousse",
    "wof:placetype":"venue"
},
  "geometry": {"coordinates":[3.184762,46.096634],"type":"Point"}
}