{
  "type": "Feature",
  "properties": {
    "iso:country":"FR",
    "sg:address":"Rn 8 Le Charel 13400 Aubagne",
    "sg:classifiers":[
        {
            "category":"Bakery",
            "type":"Food & Drink"
        }
    ],
    "sg:phone":"+33 4 42 03 50 88",
    "sg:tags":[
        "cake",
        "product",
        "related",
        "bread"
    ],
    "wof:name":"Nougandine Sarl",
    "wof:placetype":"venue"
},
  "geometry": {"coordinates":[5.5687,43.292141],"type":"Point"}
}