{
  "type": "Feature",
  "properties": {
    "addr:full":"ZI 64511 Bordes Cedex Midi Pyr\u00e9n\u00e9es",
    "addr:postcode":"64511",
    "addr:street":"Zi",
    "iso:country":"FR",
    "sg:address":"ZI 64511 Bordes Cedex",
    "sg:classifiers":[
        {
            "category":"Airport",
            "subcategory":"General Aviation",
            "type":"Transportation"
        }
    ],
    "sg:phone":"+33 5 59 12 50 00",
    "sg:province":"Midi Pyr\u00e9n\u00e9es",
    "sg:tags":[
        "engine"
    ],
    "wof:name":"Turbomeca Sa",
    "wof:placetype":"venue"
},
  "geometry": {"coordinates":[-0.282025,43.235577],"type":"Point"}
}