{
  "type": "Feature",
  "properties": {
    "addr:full":"2791, Rte de Saint Bernard, 06225 Vallauris C\u00e9dex Rhone-Alpes",
    "addr:housenumber":"2791",
    "addr:postcode":"06225",
    "addr:street":"Rte De Saint Bernard",
    "iso:country":"FR",
    "sg:address":"2791, Rte de Saint Bernard, 06225 Vallauris C\u00e9dex",
    "sg:orig_category":"Non-Classified Establishments",
    "sg:phone":"+33 4 93 65 43 60",
    "sg:province":"Rhone-Alpes",
    "wof:name":"Moneconcept S.a.r.l.",
    "wof:placetype":"venue"
},
  "geometry": {"coordinates":[7.0601,43.600765],"type":"Point"}
}