{
  "type": "Feature",
  "properties": {
    "iso:country":"FR",
    "sg:address":"ZAC Le Ch\u00e2teau",
    "sg:city":"Charmes",
    "sg:orig_category":"Non-Classified Establishments",
    "sg:phone":"+33 3 23 56 69 69",
    "sg:postcode":"02800",
    "sg:province":"Picardie",
    "wof:name":"Sodepack S.a.r.l.",
    "wof:placetype":"venue"
},
  "geometry": {"coordinates":[3.377645,49.654861],"type":"Point"}
}