{
  "type": "Feature",
  "properties": {
    "iso:country":"FR",
    "sg:address":"Zone D'Activit\u00e9 La Defraisse 30150 Roquemaure",
    "sg:classifiers":[
        {
            "category":"Home & Garden",
            "subcategory":"Furniture",
            "type":"Retail Goods"
        }
    ],
    "sg:phone":"+33 4 66 82 65 70",
    "sg:province":"Languedoc-Roussillon",
    "sg:tags":[
        "wood"
    ],
    "wof:name":"Crb",
    "wof:placetype":"venue"
},
  "geometry": {"coordinates":[4.784967,44.046623],"type":"Point"}
}