{
  "type": "Feature",
  "properties": {
    "iso:country":"FR",
    "sg:address":"21 Chem D\u00e9fois 39100 Dole",
    "sg:classifiers":[
        {
            "category":"Utilities",
            "subcategory":"Electric",
            "type":"Services"
        }
    ],
    "sg:phone":"+33 3 84 82 94 00",
    "sg:postcode":"39100",
    "sg:province":"Franche Comt\u00e9",
    "sg:tags":[
        "electricity",
        "electronic",
        "electrical",
        "equipment"
    ],
    "wof:name":"Amphenol Socapex Sa",
    "wof:placetype":"venue"
},
  "geometry": {"coordinates":[5.496325,47.10714],"type":"Point"}
}