{
  "type": "Feature",
  "properties": {
    "addr:full":"68 rue Pierre Charron 75008 Paris Ile de France 75008",
    "addr:housenumber":"68",
    "addr:postcode":"75008;75008",
    "addr:street":"Rue Pierre Charron",
    "iso:country":"FR",
    "sg:address":"68 rue Pierre Charron 75008 Paris",
    "sg:classifiers":[
        {
            "category":"Food & Beverages",
            "subcategory":"Groceries & Convenience Stores",
            "type":"Retail Goods"
        }
    ],
    "sg:phone":"+33 1 56 88 37 37",
    "sg:postcode":"75008",
    "sg:province":"Ile de France",
    "sg:tags":[
        "dietetic",
        "foodstuff"
    ],
    "wof:name":"Angliss International Sa",
    "wof:placetype":"venue"
},
  "geometry": {"coordinates":[2.304601,48.870026],"type":"Point"}
}