{
  "type": "Feature",
  "properties": {
    "addr:full":"12 Rue Alexandre Henrot 51100 Reims Champagne 51100",
    "addr:housenumber":"12",
    "addr:postcode":"51100;51100",
    "addr:street":"Rue Alexandre Henrot",
    "iso:country":"FR",
    "sg:address":"12 Rue Alexandre Henrot 51100 Reims",
    "sg:classifiers":[
        {
            "category":"Home & Garden",
            "subcategory":"Furniture",
            "type":"Retail Goods"
        }
    ],
    "sg:phone":"+33 3 26 47 44 09",
    "sg:postcode":"51100",
    "sg:province":"Champagne",
    "sg:tags":[
        "household",
        "wood"
    ],
    "wof:name":"Etss Seraine Et Compagnie Manufacture Remoise De Meubles",
    "wof:placetype":"venue"
},
  "geometry": {"coordinates":[4.018043,49.266113],"type":"Point"}
}