{
  "type": "Feature",
  "properties": {
    "iso:country":"FR",
    "sg:address":"Z I De La Pocherie BP 7 72120 St Calais",
    "sg:classifiers":[
        {
            "category":"Manufacturing",
            "subcategory":"Metals",
            "type":"Manufacturing & Wholesale Goods"
        }
    ],
    "sg:phone":"+33 2 43 63 12 12",
    "sg:postcode":"72120",
    "sg:province":"Pays de Loire",
    "sg:tags":[
        "metallurgy",
        "metalworking",
        "processing"
    ],
    "wof:name":"Sarl Marlier Gravure",
    "wof:placetype":"venue"
},
  "geometry": {"coordinates":[0.760084,47.925213],"type":"Point"}
}