{
  "type": "Feature",
  "properties": {
    "addr:full":"10 Rue De La Ferme St Ladre 95470 Fosses Ile de France 95470",
    "addr:housenumber":"10",
    "addr:postcode":"95470;95470",
    "addr:street":"Rue De La Ferme St Ladre;Ile De France",
    "iso:country":"FR",
    "sg:address":"10 Rue De La Ferme St Ladre 95470 Fosses",
    "sg:classifiers":[
        {
            "category":"Shopping",
            "subcategory":"Clothing, Apparel, & Fashions",
            "type":"Retail Goods"
        }
    ],
    "sg:phone":"+33 1 34 68 25 72",
    "sg:postcode":"95470",
    "sg:province":"Ile de France",
    "sg:tags":[
        "textile",
        "clothing",
        "clothes"
    ],
    "wof:name":"Dorotennis",
    "wof:placetype":"venue"
},
  "geometry": {"coordinates":[2.528439,49.097595],"type":"Point"}
}