{
  "type": "Feature",
  "properties": {
    "iso:country":"FR",
    "sg:address":"18, Rue Jules Ferry - ZI du Bas Pontet, 69360 Saint Symphorien d'Ozon",
    "sg:orig_category":"Non-Classified Establishments",
    "sg:phone":"+33 4 78 02 04 52",
    "sg:postcode":"69360",
    "sg:province":"Rhone-Alpes",
    "wof:name":"S.o.a. S.a.r.l. - Solution Organisation Agencement",
    "wof:placetype":"venue"
},
  "geometry": {"coordinates":[4.85609,45.634979],"type":"Point"}
}