{
  "type": "Feature",
  "properties": {
    "iso:country":"FR",
    "sg:address":"8, All\u00e9e de Valmy - ZAC de Malnou\u00e9, 77184 Emerainville",
    "sg:orig_category":"Unclassifiable Establishments",
    "sg:phone":"+33 1 64 61 75 75",
    "sg:province":"Ile de France",
    "wof:name":"A.r.c. S.a. - Adressage Routage Colisage",
    "wof:placetype":"venue"
},
  "geometry": {"coordinates":[2.622175,48.811619],"type":"Point"}
}