{
  "type": "Feature",
  "properties": {
    "addr:full":"Balvay 01340 Cras sur Reyssouze Rhone-Alpes 01340",
    "addr:postcode":"01340;01340",
    "addr:street":"Balvay;Rhone-Alpes",
    "iso:country":"FR",
    "sg:address":"Balvay 01340 Cras sur Reyssouze",
    "sg:orig_category":"Unclassifiable Establishments",
    "sg:phone":"+33 4 74 25 90 11",
    "sg:postcode":"01340",
    "sg:province":"Rhone-Alpes",
    "wof:name":"Entreprise Jouvent Alain",
    "wof:placetype":"venue"
},
  "geometry": {"coordinates":[5.197908,46.311092],"type":"Point"}
}