{
  "type": "Feature",
  "properties": {
    "addr:full":"293/295, Bd Saint Denis, 92400 Courbevoie Ile de France",
    "addr:housenumber":"293 / 295",
    "addr:postcode":"92400",
    "addr:street":"Bd Saint Denis",
    "iso:country":"FR",
    "sg:address":"293/295, Bd Saint Denis, 92400 Courbevoie",
    "sg:orig_category":"Unclassifiable Establishments",
    "sg:phone":"+33 1 41 88 92 57",
    "sg:province":"Ile de France",
    "wof:name":"Pahntos S.a.r.l.",
    "wof:placetype":"venue"
},
  "geometry": {"coordinates":[2.275071,48.902905],"type":"Point"}
}