{
  "type": "Feature",
  "properties": {
    "iso:country":"FR",
    "sg:address":"24, Rue Principale, 68520 Burnhaupt le Haut",
    "sg:city":"Burnhaupt-le-Bas",
    "sg:orig_category":"Non-Classified Establishments",
    "sg:phone":"+33 3 89 48 70 42",
    "sg:postcode":"68520",
    "sg:province":"Alsace",
    "wof:name":"Bauer Bernard Et Fils S.a.r.l.",
    "wof:placetype":"venue"
},
  "geometry": {"coordinates":[7.14782,47.735569],"type":"Point"}
}