{
  "type": "Feature",
  "properties": {
    "addr:full":"B.P. 25, 77370 Nangis^^24, Rue de la Boucherie, 77370 Nangis Ile de France 77370",
    "addr:postcode":"77370;77370;77370",
    "addr:street":"B.P. 25;Rue De La Boucherie;Ile De France",
    "iso:country":"FR",
    "sg:address":"B.P. 25, 77370 Nangis^^24, Rue de la Boucherie, 77370 Nangis",
    "sg:orig_category":"Non-Classified Establishments",
    "sg:phone":"+33 1 60 67 07 93",
    "sg:postcode":"77370",
    "sg:province":"Ile de France",
    "wof:name":"Com\u00e9na S.a.",
    "wof:placetype":"venue"
},
  "geometry": {"coordinates":[2.948903,48.507874],"type":"Point"}
}