{
  "type": "Feature",
  "properties": {
    "addr:full":"44, Av. Montmartin, 69960 Corbas Rhone-Alpes 69960",
    "addr:postcode":"69960;69960",
    "addr:street":"44 Av.",
    "iso:country":"FR",
    "sg:address":"44, Av. Montmartin, 69960 Corbas",
    "sg:orig_category":"Non-Classified Establishments",
    "sg:phone":"+33 4 78 21 40 90",
    "sg:postcode":"69960",
    "sg:province":"Rhone-Alpes",
    "wof:name":"U.b.l. S.a. - Union De La Boucherie Lyonnaise",
    "wof:placetype":"venue"
},
  "geometry": {"coordinates":[4.922284,45.676956],"type":"Point"}
}