{
  "type": "Feature",
  "properties": {
    "iso:country":"FR",
    "sg:address":"56bis, Rue des Plantes, 75014 Paris",
    "sg:orig_category":"Non-Classified Establishments",
    "sg:phone":"+33 1 45 43 50 40",
    "sg:postcode":"75014",
    "sg:province":"Ile de France",
    "wof:name":"Axciom Multim\u00e9dia S.a.r.l.",
    "wof:placetype":"venue"
},
  "geometry": {"coordinates":[2.32145,48.828228],"type":"Point"}
}