{
  "type": "Feature",
  "properties": {
    "addr:full":"Rte de Fontaine Simon - ZI La Loupe Centre 28240",
    "addr:housenumber":"loupe",
    "addr:postcode":"28240",
    "addr:street":"Rte De Fontaine Simon Zi La",
    "iso:country":"FR",
    "sg:address":"Rte de Fontaine Simon - ZI",
    "sg:city":"La Loupe",
    "sg:orig_category":"Non-Classified Establishments",
    "sg:phone":"+33 2 37 53 44 66",
    "sg:postcode":"28240",
    "sg:province":"Centre",
    "wof:name":"Oller S.a.",
    "wof:placetype":"venue"
},
  "geometry": {"coordinates":[1.1675,48.357948],"type":"Point"}
}