{
  "type": "Feature",
  "properties": {
    "iso:country":"FR",
    "sg:address":"3 rue de la Digue 59800 Lille",
    "sg:classifiers":[
        {
            "category":"Professional",
            "subcategory":"Research",
            "type":"Services"
        }
    ],
    "sg:phone":"+33 3 20 54 63 40",
    "sg:postcode":"59800",
    "sg:province":"Nord Pas-de-Calais",
    "sg:tags":[
        "opinion",
        "market"
    ],
    "wof:name":"Ieseg Conseil Association",
    "wof:placetype":"venue"
},
  "geometry": {"coordinates":[3.046096,50.635075],"type":"Point"}
}