{
  "type": "Feature",
  "properties": {
    "addr:full":"100, Rue Louis Blanc - Les Marches de l'Oise, 60160 Montataire Picardie",
    "addr:housenumber":"100",
    "addr:postcode":"60160",
    "addr:street":"Rue Louis Blanc Les;L'Oise",
    "iso:country":"FR",
    "sg:address":"100, Rue Louis Blanc - Les Marches de l'Oise, 60160 Montataire",
    "sg:orig_category":"Unclassifiable Establishments",
    "sg:phone":"+33 3 44 25 97 99",
    "sg:province":"Picardie",
    "wof:name":"Dj\u00e9py S.a.r.l.",
    "wof:placetype":"venue"
},
  "geometry": {"coordinates":[2.453671,49.259373],"type":"Point"}
}