{
  "type": "Feature",
  "properties": {
    "iso:country":"FR",
    "sg:address":"109 rue de la Ferme de Fatigue 40000 Mont de Marsan",
    "sg:city":"Mont-de-Marsan",
    "sg:classifiers":[
        {
            "category":"Food & Beverages",
            "subcategory":"Meat & Fish",
            "type":"Retail Goods"
        }
    ],
    "sg:phone":"+33 5 58 75 75 44",
    "sg:postcode":"40000",
    "sg:province":"Aquitaine",
    "sg:tags":[
        "product"
    ],
    "wof:name":"Bevimo Sa",
    "wof:placetype":"venue"
},
  "geometry": {"coordinates":[-0.482208,43.889709],"type":"Point"}
}