{
  "type": "Feature",
  "properties": {
    "iso:country":"FR",
    "sg:address":"106 rue Choletaise 49450 St Macaire En Mauges",
    "sg:classifiers":[
        {
            "category":"Professional",
            "subcategory":"Engineering",
            "type":"Services"
        }
    ],
    "sg:phone":"+33 2 41 49 11 99",
    "sg:province":"Pays de Loire",
    "sg:tags":[
        "textile",
        "technology",
        "machinery",
        "special"
    ],
    "wof:name":"Ste Nouvelle Suteau Anver S.a.",
    "wof:placetype":"venue"
},
  "geometry": {"coordinates":[-0.988629,47.12281],"type":"Point"}
}