{
  "type": "Feature",
  "properties": {
    "addr:full":"87, Rue Gabriel Peri, 59700 Marcq en Baroeul Nord Pas-de-Calais",
    "addr:housenumber":"87",
    "addr:postcode":"59700",
    "addr:street":"Rue Gabriel Peri;En Baroeul Nord",
    "iso:country":"FR",
    "sg:address":"87, Rue Gabriel Peri, 59700 Marcq en Baroeul",
    "sg:orig_category":"Non-Classified Establishments",
    "sg:phone":"+33 3 20 72 25 64",
    "sg:province":"Nord Pas-de-Calais",
    "wof:name":"Petit Delcleve S.a.r.l.",
    "wof:placetype":"venue"
},
  "geometry": {"coordinates":[3.085927,50.674614],"type":"Point"}
}