{
  "type": "Feature",
  "properties": {
    "addr:full":"ZAE les B\u00e8gues Fillinges Rhone-Alpes 74250",
    "addr:postcode":"74250",
    "addr:street":"Zae Les Be\u0300Gues;Rhone-Alpes",
    "iso:country":"FR",
    "sg:address":"ZAE les B\u00e8gues",
    "sg:city":"Fillinges",
    "sg:orig_category":"Non-Classified Establishments",
    "sg:phone":"+33 4 50 36 49 32",
    "sg:postcode":"74250",
    "sg:province":"Rhone-Alpes",
    "wof:name":"Epiphar S.a.r.l.",
    "wof:placetype":"venue"
},
  "geometry": {"coordinates":[6.398949,46.111687],"type":"Point"}
}