{
  "type": "Feature",
  "properties": {
    "iso:country":"FR",
    "sg:address":"La Bertholi\u00e8re 85700 La Flocelli\u00e8re",
    "sg:orig_category":"Non-Classified Establishments",
    "sg:phone":"+33 2 51 57 20 38",
    "sg:province":"Pays de Loire",
    "wof:name":"Le Panoramic G.a.e.c.",
    "wof:placetype":"venue"
},
  "geometry": {"coordinates":[-0.875403,46.812836],"type":"Point"}
}