{
  "type": "Feature",
  "properties": {
    "iso:country":"FR",
    "sg:address":"94 rue de Turenne; Paris; 75003",
    "sg:classifiers":[
        {
            "category":"Banks & Credit Unions",
            "subcategory":"Bank",
            "type":"Services"
        }
    ],
    "sg:phone":"+33 1 44 78 88 58",
    "sg:postcode":"75003",
    "sg:province":"Ile de France",
    "wof:name":"Soci\u00e9t\u00e9 G\u00e9n\u00e9rale",
    "wof:placetype":"venue"
},
  "geometry": {"coordinates":[2.36455,48.864704],"type":"Point"}
}