{
  "type": "Feature",
  "properties": {
    "iso:country":"FR",
    "sg:address":"B.P. 69, 70204 Lure C\u00e9dex^^17, Rue de la Forge, 70200 Magny Vernois",
    "sg:orig_category":"Non-Classified Establishments",
    "sg:phone":"+33 3 84 89 30 00",
    "sg:postcode":"70200",
    "sg:province":"Franche Comt\u00e9",
    "wof:name":"B.f.e. S.a. - Bertrand Faure Equipements",
    "wof:placetype":"venue"
},
  "geometry": {"coordinates":[6.497465,47.682686],"type":"Point"}
}