{
  "type": "Feature",
  "properties": {
    "addr:full":"B.P. 69, 70204 Lure C\u00e9dex^^17, Rue de la Forge, 70200 Magny Vernois Franche Comt\u00e9 70200",
    "addr:postcode":"70204;70200;70200",
    "addr:street":"B.P. 69;Rue De La Forge;Franche Comte\u0301",
    "iso:country":"FR",
    "sg:address":"B.P. 69, 70204 Lure C\u00e9dex^^17, Rue de la Forge, 70200 Magny Vernois",
    "sg:orig_category":"Non-Classified Establishments",
    "sg:phone":"+33 3 84 89 30 00",
    "sg:postcode":"70200",
    "sg:province":"Franche Comt\u00e9",
    "wof:name":"B.f.e. S.a. - Bertrand Faure Equipements",
    "wof:placetype":"venue"
},
  "geometry": {"coordinates":[6.497465,47.682686],"type":"Point"}
}