{
  "type": "Feature",
  "properties": {
    "addr:full":"92517 Boulogne Billancourt C\u00e9dex^^25 bis, Av. Pierre Grenier, 92100 Boulogne Billancourt Ile de France 92100",
    "addr:postcode":"92517;92100;92100",
    "addr:street":"Av. Pierre Grenier",
    "iso:country":"FR",
    "sg:address":"92517 Boulogne Billancourt C\u00e9dex^^25 bis, Av. Pierre Grenier, 92100 Boulogne Billancourt",
    "sg:orig_category":"Non-Classified Establishments",
    "sg:phone":"+33 1 46 10 34 00",
    "sg:postcode":"92100",
    "sg:province":"Ile de France",
    "wof:name":"Danel Electronic S.a.",
    "wof:placetype":"venue"
},
  "geometry": {"coordinates":[2.24102,48.835155],"type":"Point"}
}