{
  "type": "Feature",
  "properties": {
    "addr:full":"Camon 31800 Labarthe Riviere Midi Pyr\u00e9n\u00e9es 31800",
    "addr:postcode":"31800;31800",
    "iso:country":"FR",
    "sg:address":"Camon 31800 Labarthe Riviere",
    "sg:classifiers":[
        {
            "category":"Utilities",
            "subcategory":"Electric",
            "type":"Services"
        }
    ],
    "sg:phone":"+33 5 61 89 14 13",
    "sg:postcode":"31800",
    "sg:province":"Midi Pyr\u00e9n\u00e9es",
    "sg:tags":[
        "electricity",
        "raw",
        "energy",
        "material"
    ],
    "wof:name":"Electricite De France (edf)",
    "wof:placetype":"venue"
},
  "geometry": {"coordinates":[0.6529,43.103859],"type":"Point"}
}