{
  "type": "Feature",
  "properties": {
    "addr:full":"Chemin du Moulinet - Bastilde Milane Cabri\u00e8s Provence-Alpes-C\u00f4te d'Azur 13480",
    "addr:postcode":"13480",
    "addr:street":"Chemin Du Moulinet Bastilde Milane",
    "iso:country":"FR",
    "sg:address":"Chemin du Moulinet - Bastilde Milane",
    "sg:city":"Cabri\u00e8s",
    "sg:orig_category":"Unclassifiable Establishments",
    "sg:phone":"+33 4 42 22 47 95",
    "sg:postcode":"13480",
    "sg:province":"Provence-Alpes-C\u00f4te d'Azur",
    "wof:name":"Alsace Audio-visuel S.a.",
    "wof:placetype":"venue"
},
  "geometry": {"coordinates":[5.379897,43.441792],"type":"Point"}
}