{
  "type": "Feature",
  "properties": {
    "addr:full":"Rue de la Prairie Golbey Lorraine 88190",
    "addr:postcode":"88190",
    "addr:street":"Rue De La Prairie",
    "iso:country":"FR",
    "sg:address":"Rue de la Prairie",
    "sg:city":"Golbey",
    "sg:orig_category":"Unclassifiable Establishments",
    "sg:phone":"+33 3 29 34 01 32",
    "sg:postcode":"88190",
    "sg:province":"Lorraine",
    "wof:name":"Sagram S.a.",
    "wof:placetype":"venue"
},
  "geometry": {"coordinates":[6.442327,48.200119],"type":"Point"}
}