{
  "type": "Feature",
  "properties": {
    "iso:country":"FR",
    "sg:address":"33 Avenue Du Docteur Georges Levy Parc Club Moulin A Vent 69200 Venissieux",
    "sg:classifiers":[
        {
            "category":"Manufacturing",
            "subcategory":"Tools & Machinery",
            "type":"Manufacturing & Wholesale Goods"
        }
    ],
    "sg:phone":"+33 4 37 90 41 00",
    "sg:postcode":"69200",
    "sg:province":"Rhone-Alpes",
    "sg:tags":[
        "equipment",
        "measurement",
        "-",
        "precision",
        "instrument"
    ],
    "wof:name":"Landis Et Staefa",
    "wof:placetype":"venue"
},
  "geometry": {"coordinates":[4.860519,45.719555],"type":"Point"}
}