{
  "type": "Feature",
  "properties": {
    "iso:country":"FR",
    "sg:address":"Rue du Chemin Vert - ZI de Clermont",
    "sg:city":"Persan",
    "sg:orig_category":"Unclassifiable Establishments",
    "sg:phone":"+33 1 34 70 19 22",
    "sg:postcode":"95340",
    "sg:province":"Ile de France",
    "wof:name":"Fl\u00e9xaduc International S.a.r.l.",
    "wof:placetype":"venue"
},
  "geometry": {"coordinates":[2.276365,49.151005],"type":"Point"}
}