{
  "type": "Feature",
  "properties": {
    "iso:country":"FR",
    "sg:address":"1, Rue du Parc, 59320 Haubourdin",
    "sg:orig_category":"Non-Classified Establishments",
    "sg:phone":"+33 3 20 17 92 92",
    "sg:province":"Nord Pas-de-Calais",
    "wof:name":"Septra Plus S.a.",
    "wof:placetype":"venue"
},
  "geometry": {"coordinates":[2.983666,50.607311],"type":"Point"}
}