{
  "type": "Feature",
  "properties": {
    "iso:country":"FR",
    "sg:address":"15 rue des Jardins 85170 Le Poir\u00e9 sur Vie",
    "sg:classifiers":[
        {
            "category":"Manufacturing",
            "subcategory":"Wood Products",
            "type":"Manufacturing & Wholesale Goods"
        }
    ],
    "sg:phone":"+33 2 51 31 82 95",
    "sg:province":"Pays de Loire",
    "sg:tags":[
        "solid",
        "panel"
    ],
    "wof:name":"Charpentes Fournier Sa",
    "wof:placetype":"venue"
},
  "geometry": {"coordinates":[-1.50635,46.771549],"type":"Point"}
}