{
  "type": "Feature",
  "properties": {
    "addr:full":"560, Bd de Lery - ZA les Playes, 83140 Six Fours les Plages Provence-Alpes-C\u00f4te d'Azur",
    "addr:housenumber":"560",
    "addr:postcode":"83140",
    "addr:street":"Bd De Lery Za Les Playes;Fours Les Plages",
    "iso:country":"FR",
    "sg:address":"560, Bd de Lery - ZA les Playes, 83140 Six Fours les Plages",
    "sg:orig_category":"Non-Classified Establishments",
    "sg:phone":"+33 4 94 94 16 16",
    "sg:province":"Provence-Alpes-C\u00f4te d'Azur",
    "wof:name":"Protec S.a.r.l.",
    "wof:placetype":"venue"
},
  "geometry": {"coordinates":[5.842716,43.093311],"type":"Point"}
}