{
  "type": "Feature",
  "properties": {
    "iso:country":"FR",
    "sg:address":"471, Rue Victor Hugo, 26000 Valence",
    "sg:orig_category":"Non-Classified Establishments",
    "sg:phone":"+33 4 75 81 29 81",
    "sg:postcode":"26000",
    "sg:province":"Rhone-Alpes",
    "wof:name":"S.e.p. S.a.r.l. - S\u00e9curit\u00e9 Ecoute Permanente",
    "wof:placetype":"venue"
},
  "geometry": {"coordinates":[4.883908,44.908764],"type":"Point"}
}