{
  "type": "Feature",
  "properties": {
    "addr:full":"B.P. 202, 67506 Haguenau C\u00e9dex^^200, Grand'Rue, 67500 Haguenau Haguenau Alsace 67500",
    "addr:housenumber":"b.p. 202",
    "addr:postcode":"67506;67500;67500",
    "addr:street":"Grand'Rue",
    "iso:country":"FR",
    "sg:address":"B.P. 202, 67506 Haguenau C\u00e9dex^^200, Grand'Rue, 67500 Haguenau",
    "sg:city":"Haguenau",
    "sg:orig_category":"Non-Classified Establishments",
    "sg:phone":"+33 3 88 63 82 82",
    "sg:postcode":"67500",
    "sg:province":"Alsace",
    "wof:name":"Crit Int\u00e9rim S.a.",
    "wof:placetype":"venue"
},
  "geometry": {"coordinates":[7.82145,48.81979],"type":"Point"}
}