{
  "type": "Feature",
  "properties": {
    "addr:full":"46700 Montcabrier Midi Pyr\u00e9n\u00e9es",
    "addr:postcode":"46700",
    "iso:country":"FR",
    "sg:address":"46700 Montcabrier",
    "sg:orig_category":"Unclassifiable Establishments",
    "sg:phone":"+33 5 65 36 53 17",
    "sg:province":"Midi Pyr\u00e9n\u00e9es",
    "wof:name":"Bergon Delteil S.a.",
    "wof:placetype":"venue"
},
  "geometry": {"coordinates":[1.07494,44.541164],"type":"Point"}
}