{
  "type": "Feature",
  "properties": {
    "iso:country":"FR",
    "sg:address":"5 Rue De L Europe Zi Du Bois Rigault 62300 Lens",
    "sg:classifiers":[
        {
            "category":"Wholesale",
            "subcategory":"Medical Equipment & Supplies",
            "type":"Manufacturing & Wholesale Goods"
        }
    ],
    "sg:phone":"+33 3 21 28 26 30",
    "sg:postcode":"62300",
    "sg:province":"Nord Pas-de-Calais",
    "sg:tags":[
        "instrument",
        "health",
        "-",
        "precision"
    ],
    "wof:name":"Orthopedie Prothese Edupont",
    "wof:placetype":"venue"
},
  "geometry": {"coordinates":[2.83296,50.42934],"type":"Point"}
}