{
  "type": "Feature",
  "properties": {
    "addr:full":"21, Grande Rue, 60310 Thiescourt Picardie 60310",
    "addr:housenumber":"21",
    "addr:postcode":"60310;60310",
    "addr:street":"Grande Rue;Picardie",
    "iso:country":"FR",
    "sg:address":"21, Grande Rue, 60310 Thiescourt",
    "sg:orig_category":"Non-Classified Establishments",
    "sg:phone":"+33 3 44 43 64 53",
    "sg:postcode":"60310",
    "sg:province":"Picardie",
    "wof:name":"Deflandre Alain Et Elyasinski G\u00e9rard S.a.r.l. - M\u00e9canique G\u00e9n\u00e9rale",
    "wof:placetype":"venue"
},
  "geometry": {"coordinates":[2.884463,49.562416],"type":"Point"}
}