{
  "type": "Feature",
  "properties": {
    "addr:full":"1 Rue Des Champs 59290 Wasquehal Nord Pas-de-Calais 59290",
    "addr:housenumber":"1",
    "addr:postcode":"59290;59290",
    "addr:street":"Rue Des Champs",
    "iso:country":"FR",
    "sg:address":"1 Rue Des Champs 59290 Wasquehal",
    "sg:classifiers":[
        {
            "category":"Professional",
            "subcategory":"Computer Services",
            "type":"Services"
        }
    ],
    "sg:phone":"+33 3 20 65 93 10",
    "sg:postcode":"59290",
    "sg:province":"Nord Pas-de-Calais",
    "sg:tags":[
        "information",
        "technology",
        "software"
    ],
    "wof:name":"Ssin Sarl",
    "wof:placetype":"venue"
},
  "geometry": {"coordinates":[3.12235,50.653763],"type":"Point"}
}