{
  "type": "Feature",
  "properties": {
    "addr:full":"70 Rue Des Loges Fontenay Le Comte Pays de Loire 85200",
    "addr:housenumber":"70",
    "addr:postcode":"85200",
    "addr:street":"Rue Des Loges;Comte",
    "iso:country":"FR",
    "sg:address":"70 Rue Des Loges",
    "sg:city":"Fontenay Le Comte",
    "sg:classifiers":[
        {
            "category":"Banks & Credit Unions",
            "subcategory":"Financial Services",
            "type":"Services"
        }
    ],
    "sg:phone":"+33 2 51 50 12 80",
    "sg:postcode":"85200",
    "sg:province":"Pays de Loire",
    "sg:tags":[
        "banking",
        "finance",
        "insurance"
    ],
    "wof:name":"Societe De Revision D'expertise De Gestion Et D'organisation (soregor)",
    "wof:placetype":"venue"
},
  "geometry": {"coordinates":[-0.801478,46.466568],"type":"Point"}
}