{
  "type": "Feature",
  "properties": {
    "iso:country":"FR",
    "sg:address":"B.P. 26, 68160 Sainte Marie aux Mines^^52, Rue Jean Jaur\u00e8s, 68160 Sainte Marie aux Mines",
    "sg:city":"Sainte-Croix-aux-Mines",
    "sg:orig_category":"Non-Classified Establishments",
    "sg:phone":"+33 3 89 58 71 90",
    "sg:postcode":"68160",
    "sg:province":"Alsace",
    "wof:name":"Montalec S.a.r.l.",
    "wof:placetype":"venue"
},
  "geometry": {"coordinates":[7.195476,48.252544],"type":"Point"}
}