{
  "type": "Feature",
  "properties": {
    "iso:country":"FR",
    "sg:address":"Rte du R\u00e9cru",
    "sg:city":"Ampuis",
    "sg:orig_category":"Non-Classified Establishments",
    "sg:phone":"+33 4 74 56 10 19",
    "sg:postcode":"69420",
    "sg:province":"Rhone-Alpes",
    "wof:name":"Euberlay S.a.",
    "wof:placetype":"venue"
},
  "geometry": {"coordinates":[4.802155,45.501465],"type":"Point"}
}