{
  "type": "Feature",
  "properties": {
    "addr:full":"B.P. 8 Pierrefontaine les Varans^^La P\u00e9pini\u00e9re 25510 Pierrefontaine les Varans Franche Comt\u00e9 25510",
    "addr:postcode":"25510;25510",
    "addr:street":"B.P. 8 Pierrefontaine Les;Pe\u0301Pinie\u0301Re;Franche Comte\u0301",
    "iso:country":"FR",
    "sg:address":"B.P. 8",
    "sg:city":"Pierrefontaine les Varans^^La P\u00e9pini\u00e9re 25510 Pierrefontaine les Varans",
    "sg:orig_category":"Non-Classified Establishments",
    "sg:phone":"+33 3 81 56 10 77",
    "sg:postcode":"25510",
    "sg:province":"Franche Comt\u00e9",
    "wof:name":"Gaec Des P\u00e9pini\u00e8res - Haut Doubs Espaces Verts S.a.r.l.",
    "wof:placetype":"venue"
},
  "geometry": {"coordinates":[6.53993,47.215336],"type":"Point"}
}