{
  "type": "Feature",
  "properties": {
    "addr:full":"B.P. 80529, 57205 Sarreguemines C\u00e9dex^^Angle rue d'Or rue de la Paix, 57200 Sarreguemines Lorraine 57200",
    "addr:postcode":"57205;57200;57200",
    "addr:street":"Rue D'Or Rue De La Paix",
    "iso:country":"FR",
    "sg:address":"B.P. 80529, 57205 Sarreguemines C\u00e9dex^^Angle rue d'Or rue de la Paix, 57200 Sarreguemines",
    "sg:orig_category":"Non-Classified Establishments",
    "sg:phone":"+33 3 87 98 25 00",
    "sg:postcode":"57200",
    "sg:province":"Lorraine",
    "wof:name":"Editions Claude Vervin S.a.",
    "wof:placetype":"venue"
},
  "geometry": {"coordinates":[7.096985,49.089573],"type":"Point"}
}