{
  "type": "Feature",
  "properties": {
    "addr:full":"27 Bellevue 63309 THIERS CEDEX Auvergne",
    "addr:housenumber":"27",
    "addr:postcode":"63309;cedex",
    "addr:street":"Bellevue",
    "iso:country":"FR",
    "sg:address":"27 Bellevue 63309 THIERS CEDEX",
    "sg:classifiers":[
        {
            "category":"Shopping",
            "subcategory":"Hobbies, Toys, & Games",
            "type":"Retail Goods"
        }
    ],
    "sg:phone":"+33 4 73 80 01 04",
    "sg:province":"Auvergne",
    "sg:tags":[
        "hobby",
        "knife"
    ],
    "wof:name":"Etab A. Sarry Sabatier Sarl",
    "wof:placetype":"venue"
},
  "geometry": {"coordinates":[3.548272,45.855244],"type":"Point"}
}