{
  "type": "Feature",
  "properties": {
    "addr:full":"37, Rue du Nouveau B\u00e8le, 44477 Carquefou C\u00e9dex^^37, Rue du Nouveau B\u00e8le, 44470 Carquefou Pays de Loire",
    "addr:housenumber":"37",
    "addr:postcode":"44477;44470",
    "addr:street":"Rue Du Nouveau Be\u0300Le;Rue Du Nouveau Be\u0300Le",
    "iso:country":"FR",
    "sg:address":"37, Rue du Nouveau B\u00e8le, 44477 Carquefou C\u00e9dex^^37, Rue du Nouveau B\u00e8le, 44470 Carquefou",
    "sg:orig_category":"Non-Classified Establishments",
    "sg:phone":"+33 2 40 25 25 82",
    "sg:province":"Pays de Loire",
    "wof:name":"T.c.d.f. S.a. - Transport Course Distribution Fa\u00e7onnage",
    "wof:placetype":"venue"
},
  "geometry": {"coordinates":[-1.440899,47.266781],"type":"Point"}
}