{
  "type": "Feature",
  "properties": {
    "addr:full":"B.P. 214, 61306 L'Aigle C\u00e9dex^^ZI n\u00b01, 61300 L'Aigle Chandai Basse Normandie 61300",
    "addr:housenumber":"b.p. 214",
    "addr:postcode":"61306;n\u00b01 61300;61300",
    "iso:country":"FR",
    "sg:address":"B.P. 214, 61306 L'Aigle C\u00e9dex^^ZI n\u00b01, 61300 L'Aigle",
    "sg:city":"Chandai",
    "sg:orig_category":"Non-Classified Establishments",
    "sg:phone":"+33 2 33 84 34 99",
    "sg:postcode":"61300",
    "sg:province":"Basse Normandie",
    "wof:name":"Usine Plastohm S.a.",
    "wof:placetype":"venue"
},
  "geometry": {"coordinates":[0.634017,48.760406],"type":"Point"}
}