{
  "type": "Feature",
  "properties": {
    "addr:full":"Z.A. - Actip\u00f4le A2 Raillencourt Sainte Olle Nord Pas-de-Calais 59554",
    "addr:housenumber":"a2",
    "addr:postcode":"59554",
    "addr:street":"Z.A. Actipo\u0302Le;Pas-De-Calais",
    "iso:country":"FR",
    "sg:address":"Z.A. - Actip\u00f4le A2",
    "sg:city":"Raillencourt Sainte Olle",
    "sg:orig_category":"Unclassifiable Establishments",
    "sg:phone":"+33 3 27 72 97 29",
    "sg:postcode":"59554",
    "sg:province":"Nord Pas-de-Calais",
    "wof:name":"Soco System S.a.",
    "wof:placetype":"venue"
},
  "geometry": {"coordinates":[3.167315,50.190399],"type":"Point"}
}