{
  "type": "Feature",
  "properties": {
    "iso:country":"FR",
    "sg:address":"1, Av. Joseph Kessel, 78180 Montigny le Bretonneux",
    "sg:orig_category":"Non-Classified Establishments",
    "sg:phone":"+33 1 30 64 06 07",
    "sg:province":"Ile de France",
    "wof:name":"Ressorts Spec E.u.r.l.",
    "wof:placetype":"venue"
},
  "geometry": {"coordinates":[2.037266,48.773678],"type":"Point"}
}