{
  "type": "Feature",
  "properties": {
    "addr:full":"6, Rte de Blois, 41700 Cour Cheverny Cheverny Centre 41700",
    "addr:housenumber":"6",
    "addr:postcode":"41700;41700",
    "addr:street":"Rte De Blois",
    "iso:country":"FR",
    "sg:address":"6, Rte de Blois, 41700 Cour Cheverny",
    "sg:city":"Cheverny",
    "sg:orig_category":"Unclassifiable Establishments",
    "sg:phone":"+33 2 54 79 97 22",
    "sg:postcode":"41700",
    "sg:province":"Centre",
    "wof:name":"Alizon Et Fils S.a.r.l.",
    "wof:placetype":"venue"
},
  "geometry": {"coordinates":[1.433897,47.523064],"type":"Point"}
}