{
  "type": "Feature",
  "properties": {
    "iso:country":"FR",
    "sg:address":"44 A Rue Du Bois Bourgeois",
    "sg:city":"Montbeliard",
    "sg:classifiers":[
        {
            "category":"Banks & Credit Unions",
            "subcategory":"Financial Services",
            "type":"Services"
        }
    ],
    "sg:phone":"+33 3 81 96 76 14",
    "sg:postcode":"25200",
    "sg:province":"Franche Comt\u00e9",
    "sg:tags":[
        "banking",
        "finance",
        "insurance"
    ],
    "wof:name":"Fiduciaire Juridique Et Fiscale De France Fidal (fjff)",
    "wof:placetype":"venue"
},
  "geometry": {"coordinates":[6.788742,47.512924],"type":"Point"}
}