{
  "type": "Feature",
  "properties": {
    "addr:full":"11, Rue du Ch\u00e2teau d'Eau, 50210 Saint Martin de C\u00e9nilly Belval Basse Normandie 50210",
    "addr:housenumber":"11",
    "addr:postcode":"50210;50210",
    "addr:street":"Rue Du Cha\u0302Teau D'Eau",
    "iso:country":"FR",
    "sg:address":"11, Rue du Ch\u00e2teau d'Eau, 50210 Saint Martin de C\u00e9nilly",
    "sg:city":"Belval",
    "sg:orig_category":"Non-Classified Establishments",
    "sg:phone":"+33 2 33 46 91 05",
    "sg:postcode":"50210",
    "sg:province":"Basse Normandie",
    "wof:name":"Le Brun Henri",
    "wof:placetype":"venue"
},
  "geometry": {"coordinates":[-1.278484,48.987823],"type":"Point"}
}