{
  "type": "Feature",
  "properties": {
    "iso:country":"FR",
    "sg:address":"6 boulevard Jean Moulin 44100 Nantes",
    "sg:orig_category":"Punching Tools For Leather, Cardboard, Paper, Plastics",
    "sg:phone":"+33 2 40 58 18 00",
    "sg:province":"Pays de Loire",
    "wof:name":"Sa Atoutforme",
    "wof:placetype":"venue"
},
  "geometry": {"coordinates":[-1.604729,47.200649],"type":"Point"}
}