{
  "type": "Feature",
  "properties": {
    "iso:country":"FR",
    "sg:address":"37, Rte des Vall\u00e9es, 37510 Ballan Mir\u00e9",
    "sg:city":"Ballan-Mir\u00e9",
    "sg:orig_category":"Unclassifiable Establishments",
    "sg:phone":"+33 2 51 48 41 02",
    "sg:postcode":"37510",
    "sg:province":"Centre",
    "wof:name":"A.b. Technics S.a.r.l.",
    "wof:placetype":"venue"
},
  "geometry": {"coordinates":[0.612873,47.360275],"type":"Point"}
}