{
  "type": "Feature",
  "properties": {
    "addr:full":"B.P. 63, 38291 La Verpill\u00e8re C\u00e9dex^^51, Rue de la Malacombe - ZI de Chesnes, 38070 Saint Quentin Fal Rhone-Alpes 38070",
    "addr:postcode":"38291;38070;38070",
    "addr:street":"B.P. 63;Rue De La Malacombe Zi De Chesnes;Rhone-Alpes",
    "iso:country":"FR",
    "sg:address":"B.P. 63, 38291 La Verpill\u00e8re C\u00e9dex^^51, Rue de la Malacombe - ZI de Chesnes, 38070 Saint Quentin Fal",
    "sg:orig_category":"Non-Classified Establishments",
    "sg:phone":"+33 4 74 94 31 80",
    "sg:postcode":"38070",
    "sg:province":"Rhone-Alpes",
    "wof:name":"Phil Trans S.a.r.l.",
    "wof:placetype":"venue"
},
  "geometry": {"coordinates":[5.128534,45.645126],"type":"Point"}
}