{
  "type": "Feature",
  "properties": {
    "addr:full":"58, Rue Gambetta, 59273 Fretin Nord Pas-de-Calais",
    "addr:housenumber":"58",
    "addr:postcode":"59273",
    "addr:street":"Rue Gambetta",
    "iso:country":"FR",
    "sg:address":"58, Rue Gambetta, 59273 Fretin",
    "sg:orig_category":"Unclassifiable Establishments",
    "sg:phone":"+33 3 20 61 43 40",
    "sg:province":"Nord Pas-de-Calais",
    "wof:name":"A.v.e.c. Nord S.a.r.l. - Automatisme Vide Emballage Conditionnement",
    "wof:placetype":"venue"
},
  "geometry": {"coordinates":[3.124352,50.556633],"type":"Point"}
}