{
  "type": "Feature",
  "properties": {
    "iso:country":"FR",
    "sg:address":"ZI Convenant Uraz",
    "sg:city":"Tr\u00e9guier",
    "sg:orig_category":"Non-Classified Establishments",
    "sg:phone":"+33 2 96 92 29 49",
    "sg:postcode":"22220",
    "sg:province":"Bretagne",
    "wof:name":"Euro Process S.a.",
    "wof:placetype":"venue"
},
  "geometry": {"coordinates":[-3.228931,48.776031],"type":"Point"}
}