{
  "type": "Feature",
  "properties": {
    "addr:full":"7 R Flatters 75005 Paris Ile de France 75005",
    "addr:housenumber":"7 r",
    "addr:postcode":"75005;75005",
    "addr:street":"Flatters",
    "iso:country":"FR",
    "sg:address":"7 R Flatters 75005 Paris",
    "sg:classifiers":[
        {
            "category":"Wholesale",
            "subcategory":"Medical Equipment & Supplies",
            "type":"Manufacturing & Wholesale Goods"
        }
    ],
    "sg:phone":"+33 1 47 07 48 00",
    "sg:postcode":"75005",
    "sg:province":"Ile de France",
    "sg:tags":[
        "instrument",
        "health",
        "-",
        "precision"
    ],
    "wof:name":"M. Delaune Bruno",
    "wof:placetype":"venue"
},
  "geometry": {"coordinates":[2.346299,48.837868],"type":"Point"}
}