{
  "type": "Feature",
  "properties": {
    "addr:full":"4 Rue Kepler 44240 La Chapelle Sur Erdre Pays de Loire 44240",
    "addr:housenumber":"4",
    "addr:postcode":"44240;44240",
    "addr:street":"Rue Kepler;Chapelle;Erdre",
    "iso:country":"FR",
    "sg:address":"4 Rue Kepler 44240 La Chapelle Sur Erdre",
    "sg:orig_category":"Agriculture - machinery and equipment Mechanical Engineering - machines Miscellaneous Products",
    "sg:phone":"+33 2 40 93 53 53",
    "sg:postcode":"44240",
    "sg:province":"Pays de Loire",
    "wof:name":"Laboratoires Humeau Sa",
    "wof:placetype":"venue"
},
  "geometry": {"coordinates":[-1.553672,47.265305],"type":"Point"}
}