{
  "type": "Feature",
  "properties": {
    "addr:full":"40, Rue Louis Blanc, 75010 Paris Ile de France 75010",
    "addr:housenumber":"40",
    "addr:postcode":"75010;75010",
    "addr:street":"Rue Louis Blanc",
    "iso:country":"FR",
    "sg:address":"40, Rue Louis Blanc, 75010 Paris",
    "sg:orig_category":"Non-Classified Establishments",
    "sg:phone":"+33 1 40 36 57 29",
    "sg:postcode":"75010",
    "sg:province":"Ile de France",
    "wof:name":"A.c.h. S.a.r.l. - Haas Application Conseil",
    "wof:placetype":"venue"
},
  "geometry": {"coordinates":[2.36431,48.881737],"type":"Point"}
}