{
  "type": "Feature",
  "properties": {
    "iso:country":"FR",
    "sg:address":"Le Ch\u00e2teau de Faverges 38110 Faverges de la Tour",
    "sg:orig_category":"Unclassifiable Establishments",
    "sg:phone":"+33 4 74 97 42 52",
    "sg:postcode":"38110",
    "sg:province":"Rhone-Alpes",
    "wof:name":"Le Ch\u00e2teau De Faverges",
    "wof:placetype":"venue"
},
  "geometry": {"coordinates":[5.454585,45.52478],"type":"Point"}
}