{
  "type": "Feature",
  "properties": {
    "iso:country":"FR",
    "sg:address":"23 R De La Croix Renaudau 49120 Chemill\u00e9",
    "sg:classifiers":[
        {
            "category":"Professional",
            "type":"Services"
        }
    ],
    "sg:phone":"+33 2 41 30 52 65",
    "sg:province":"Pays de Loire",
    "sg:tags":[
        "transport",
        "road"
    ],
    "wof:name":"Eurl Morille Transport",
    "wof:placetype":"venue"
},
  "geometry": {"coordinates":[-0.717167,47.218773],"type":"Point"}
}