{
  "type": "Feature",
  "properties": {
    "addr:full":"375, Av. Saint Just, 83130 La Garde Provence-Alpes-C\u00f4te d'Azur",
    "addr:housenumber":"375",
    "addr:postcode":"83130",
    "addr:street":"Av. Saint Just;Garde",
    "iso:country":"FR",
    "sg:address":"375, Av. Saint Just, 83130 La Garde",
    "sg:orig_category":"Unclassifiable Establishments",
    "sg:phone":"+33 4 94 21 51 57",
    "sg:province":"Provence-Alpes-C\u00f4te d'Azur",
    "wof:name":"Iss Abilis France S.a.",
    "wof:placetype":"venue"
},
  "geometry": {"coordinates":[6.009775,43.124866],"type":"Point"}
}