{
  "type": "Feature",
  "properties": {
    "iso:country":"FR",
    "sg:address":"01430 Outriaz",
    "sg:orig_category":"Non-Classified Establishments",
    "sg:phone":"+33 4 74 76 33 99",
    "sg:postcode":"01430",
    "sg:province":"Rhone-Alpes",
    "wof:name":"Monnet S\u00e8ve S.a.",
    "wof:placetype":"venue"
},
  "geometry": {"coordinates":[5.547365,46.066837],"type":"Point"}
}