{
  "type": "Feature",
  "properties": {
    "addr:full":"67-69 Rte De Pommard 21200 Beaune Beaune Bourgogne 21200",
    "addr:housenumber":"67-69",
    "addr:postcode":"21200;21200",
    "addr:street":"Rte De Pommard",
    "iso:country":"FR",
    "sg:address":"67-69 Rte De Pommard 21200 Beaune",
    "sg:city":"Beaune",
    "sg:classifiers":[
        {
            "category":"Manufacturing",
            "subcategory":"Wood Products",
            "type":"Manufacturing & Wholesale Goods"
        }
    ],
    "sg:phone":"+33 3 80 22 62 57",
    "sg:postcode":"21200",
    "sg:province":"Bourgogne",
    "sg:tags":[
        "furniture"
    ],
    "wof:name":"Cuisines Et Meubles Lavaillotte (cml) Sarl",
    "wof:placetype":"venue"
},
  "geometry": {"coordinates":[4.823407,47.016796],"type":"Point"}
}