{
  "type": "Feature",
  "properties": {
    "iso:country":"FR",
    "sg:address":"16 rue de la Ferotterie 02310 Nogent L'Artaud",
    "sg:classifiers":[
        {
            "category":"Manufacturing",
            "subcategory":"Metals",
            "type":"Manufacturing & Wholesale Goods"
        }
    ],
    "sg:phone":"+33 3 23 70 02 03",
    "sg:province":"Picardie",
    "sg:tags":[
        "precious",
        "recovery"
    ],
    "wof:name":"Affinage Et R\u00e9cuperation Des Metaux S.a.",
    "wof:placetype":"venue"
},
  "geometry": {"coordinates":[3.301536,48.974861],"type":"Point"}
}