{
  "type": "Feature",
  "properties": {
    "addr:full":"126, Av. Gambetta, 17800 Pons Poitou-Charentes 17800",
    "addr:postcode":"17800;17800",
    "addr:street":"126 Av. Gambetta",
    "iso:country":"FR",
    "sg:address":"126, Av. Gambetta, 17800 Pons",
    "sg:orig_category":"Non-Classified Establishments",
    "sg:phone":"+33 5 46 91 24 59",
    "sg:postcode":"17800",
    "sg:province":"Poitou-Charentes",
    "wof:name":"Ashland France S.a.s.",
    "wof:placetype":"venue"
},
  "geometry": {"coordinates":[-0.548948,45.590462],"type":"Point"}
}