{
  "type": "Feature",
  "properties": {
    "addr:full":"225 rue Louis Armand 74300 Cluses Rhone-Alpes 74300",
    "addr:housenumber":"225",
    "addr:postcode":"74300;74300",
    "addr:street":"Rue Louis Armand",
    "iso:country":"FR",
    "sg:address":"225 rue Louis Armand 74300 Cluses",
    "sg:classifiers":[
        {
            "category":"Manufacturing",
            "subcategory":"Signs",
            "type":"Manufacturing & Wholesale Goods"
        }
    ],
    "sg:phone":"+33 4 50 89 26 50",
    "sg:postcode":"74300",
    "sg:province":"Rhone-Alpes",
    "sg:tags":[
        "identification",
        "card"
    ],
    "wof:name":"G. Cartier Technologies S.a.r.l.",
    "wof:placetype":"venue"
},
  "geometry": {"coordinates":[6.566086,46.077911],"type":"Point"}
}