{
  "type": "Feature",
  "properties": {
    "addr:full":"Rue Emile Souvestre Zac De Mivoie 35136 St Jacques De La Lande Saint-Jacques-de-la-Lande Bretagne 35136",
    "addr:postcode":"35136;35136",
    "addr:street":"Rue Emile Souvestre Zac De Mivoie;St Jacques De La Lande Saint-Jacques-De-La-Lande Bretagne",
    "iso:country":"FR",
    "sg:address":"Rue Emile Souvestre Zac De Mivoie 35136 St Jacques De La Lande",
    "sg:city":"Saint-Jacques-de-la-Lande",
    "sg:classifiers":[
        {
            "category":"Government",
            "subcategory":"Department Of Motor Vehicles",
            "type":"Public Place"
        }
    ],
    "sg:phone":"+33 2 99 31 08 43",
    "sg:postcode":"35136",
    "sg:province":"Bretagne",
    "sg:tags":[
        "equipment",
        "industrial",
        "transport",
        "motor-cars"
    ],
    "wof:name":"Etablissements Dilange",
    "wof:placetype":"venue"
},
  "geometry": {"coordinates":[-1.699254,48.068741],"type":"Point"}
}