{
  "type": "Feature",
  "properties": {
    "iso:country":"FR",
    "sg:address":"3 Rue De L'Amandier 78540 Vernouillet",
    "sg:classifiers":[
        {
            "category":"Professional",
            "subcategory":"Engineering",
            "type":"Services"
        }
    ],
    "sg:phone":"+33 1 30 06 56 56",
    "sg:postcode":"78540",
    "sg:province":"Ile de France",
    "sg:tags":[
        "electricity",
        "-",
        "machine",
        "equipment",
        "electrical",
        "mechanical",
        "electronic"
    ],
    "wof:name":"Apilog",
    "wof:placetype":"venue"
},
  "geometry": {"coordinates":[1.991938,48.972099],"type":"Point"}
}