{
  "type": "Feature",
  "properties": {
    "addr:full":"Les Champs Vie De Fesches Zi Technoland 25460 Etupes Franche Comt\u00e9",
    "addr:postcode":"25460",
    "addr:street":"Les;Vie;Technoland;Franche Comte\u0301",
    "iso:country":"FR",
    "sg:address":"Les Champs Vie De Fesches Zi Technoland 25460 Etupes",
    "sg:classifiers":[
        {
            "category":"Professional",
            "type":"Services"
        }
    ],
    "sg:phone":"+33 3 81 31 22 90",
    "sg:province":"Franche Comt\u00e9",
    "sg:tags":[
        "transport",
        "road"
    ],
    "wof:name":"Les Transports Lexoviens",
    "wof:placetype":"venue"
},
  "geometry": {"coordinates":[6.862814,47.506931],"type":"Point"}
}