{
  "type": "Feature",
  "properties": {
    "iso:country":"FR",
    "sg:address":"45, Av de Bale, 68330 Huningue",
    "sg:city":"Huningue",
    "sg:orig_category":"Unclassifiable Establishments",
    "sg:phone":"+33 3 89 89 60 00",
    "sg:postcode":"68330",
    "sg:province":"Alsace",
    "wof:name":"Clariant Huningue S.a.",
    "wof:placetype":"venue"
},
  "geometry": {"coordinates":[7.58169,47.57988],"type":"Point"}
}