{
  "type": "Feature",
  "properties": {
    "addr:full":"R Des Aulnes 67590 Wintershouse Wintershouse Alsace 67590",
    "addr:postcode":"67590;67590",
    "addr:street":"Wintershouse",
    "iso:country":"FR",
    "sg:address":"R Des Aulnes 67590 Wintershouse",
    "sg:city":"Wintershouse",
    "sg:classifiers":[
        {
            "category":"Manufacturing",
            "subcategory":"Food",
            "type":"Manufacturing & Wholesale Goods"
        }
    ],
    "sg:phone":"+33 3 88 73 80 33",
    "sg:postcode":"67590",
    "sg:province":"Alsace",
    "sg:tags":[
        "preserve",
        "product",
        "related"
    ],
    "wof:name":"Est Friture",
    "wof:placetype":"venue"
},
  "geometry": {"coordinates":[7.704885,48.791336],"type":"Point"}
}