{
  "type": "Feature",
  "properties": {
    "iso:country":"FR",
    "sg:address":"3 Av Du Parc 95011 Cergy Pontoise Cedex",
    "sg:classifiers":[
        {
            "category":"Travel",
            "subcategory":"Hotels & Motels",
            "type":"Entertainment"
        }
    ],
    "sg:phone":"+33 1 30 30 39 47",
    "sg:province":"Ile de France",
    "sg:tags":[
        "professional",
        "hotels",
        "fair",
        "business",
        "restaurant"
    ],
    "wof:name":"Novotel",
    "wof:placetype":"venue"
},
  "geometry": {"coordinates":[2.07243,49.033463],"type":"Point"}
}