{
  "type": "Feature",
  "properties": {
    "addr:full":"rue Gustave Eiffel 78120 Rambouillet Ile de France 78120",
    "addr:postcode":"78120;ile;78120",
    "addr:street":"Rue Gustave Eiffel;France",
    "iso:country":"FR",
    "sg:address":"rue Gustave Eiffel 78120 Rambouillet",
    "sg:classifiers":[
        {
            "category":"Home & Garden",
            "subcategory":"Mobile Homes",
            "type":"Retail Goods"
        }
    ],
    "sg:phone":"+33 1 30 46 55 55",
    "sg:postcode":"78120",
    "sg:province":"Ile de France",
    "sg:tags":[
        "tent",
        "marquee"
    ],
    "wof:name":"Dalo Fr\u00e8res Sa",
    "wof:placetype":"venue"
},
  "geometry": {"coordinates":[1.823611,48.625996],"type":"Point"}
}