{
  "type": "Feature",
  "properties": {
    "addr:full":"47, Rte de Mons, 59600 Bettignies Nord Pas-de-Calais",
    "addr:housenumber":"47",
    "addr:postcode":"59600",
    "addr:street":"Rte De Mons",
    "iso:country":"FR",
    "sg:address":"47, Rte de Mons, 59600 Bettignies",
    "sg:orig_category":"Non-Classified Establishments",
    "sg:phone":"+33 3 27 67 95 96",
    "sg:province":"Nord Pas-de-Calais",
    "wof:name":"Tapis Nord S.a.r.l.",
    "wof:placetype":"venue"
},
  "geometry": {"coordinates":[3.972799,50.336189],"type":"Point"}
}