{
  "type": "Feature",
  "properties": {
    "iso:country":"FR",
    "sg:address":"9, Rte de l'Epinette, 78113 La Hauteville",
    "sg:orig_category":"Unclassifiable Establishments",
    "sg:phone":"+33 1 30 46 14 50",
    "sg:province":"Ile de France",
    "wof:name":"Epinette Publicit\u00e9 S.a.r.l.",
    "wof:placetype":"venue"
},
  "geometry": {"coordinates":[1.619598,48.706779],"type":"Point"}
}