{
  "type": "Feature",
  "properties": {
    "iso:country":"FR",
    "sg:address":"82-84 Rue Grande 77390 Champdeuil",
    "sg:classifiers":[
        {
            "category":"Professional",
            "subcategory":"Engineering",
            "type":"Services"
        }
    ],
    "sg:phone":"+33 1 64 38 82 54",
    "sg:postcode":"77390",
    "sg:province":"Ile de France",
    "sg:tags":[
        "machine",
        "-",
        "mechanical"
    ],
    "wof:name":"Joncour Metral Sarl",
    "wof:placetype":"venue"
},
  "geometry": {"coordinates":[2.73386,48.619461],"type":"Point"}
}