{
  "type": "Feature",
  "properties": {
    "iso:country":"FR",
    "sg:address":"53 Grand Rue 57720 Waldhouse",
    "sg:classifiers":[
        {
            "category":"Manufacturing",
            "subcategory":"Metals",
            "type":"Manufacturing & Wholesale Goods"
        }
    ],
    "sg:phone":"+33 3 87 96 55 06",
    "sg:postcode":"57720",
    "sg:province":"Lorraine",
    "sg:tags":[
        "metallurgy",
        "metalworking",
        "processing"
    ],
    "wof:name":"Conrad Armand Sarl",
    "wof:placetype":"venue"
},
  "geometry": {"coordinates":[7.464825,49.141464],"type":"Point"}
}