{
  "type": "Feature",
  "properties": {
    "addr:full":"18, Rue Pr\u00eateur, 67500 Haguenau Haguenau Alsace 67500",
    "addr:housenumber":"18",
    "addr:postcode":"67500;67500",
    "addr:street":"Rue Pre\u0302Teur",
    "iso:country":"FR",
    "sg:address":"18, Rue Pr\u00eateur, 67500 Haguenau",
    "sg:city":"Haguenau",
    "sg:orig_category":"Unclassifiable Establishments",
    "sg:phone":"+33 3 82 33 58 15",
    "sg:postcode":"67500",
    "sg:province":"Alsace",
    "wof:name":"Technibel S.a.",
    "wof:placetype":"venue"
},
  "geometry": {"coordinates":[7.778377,48.806873],"type":"Point"}
}