{
  "type": "Feature",
  "properties": {
    "addr:full":"22, Rue Jean Jaur\u00e8s, 12700 Capdenac Gare Midi Pyr\u00e9n\u00e9es",
    "addr:housenumber":"22",
    "addr:postcode":"12700",
    "addr:street":"Rue Jean Jaure\u0300S",
    "iso:country":"FR",
    "sg:address":"22, Rue Jean Jaur\u00e8s, 12700 Capdenac Gare",
    "sg:orig_category":"Unclassifiable Establishments",
    "sg:phone":"+33 5 65 80 22 00",
    "sg:province":"Midi Pyr\u00e9n\u00e9es",
    "wof:name":"Entreprise Capraro Et Compagnie S.a.",
    "wof:placetype":"venue"
},
  "geometry": {"coordinates":[2.07679,44.57502],"type":"Point"}
}