{
  "type": "Feature",
  "properties": {
    "addr:full":"32, Rue Beaumont, 06300 Nice Franche Comt\u00e9",
    "addr:housenumber":"32",
    "addr:postcode":"06300",
    "addr:street":"Rue Beaumont;Franche Comte\u0301",
    "iso:country":"FR",
    "sg:address":"32, Rue Beaumont, 06300 Nice",
    "sg:orig_category":"Unclassifiable Establishments",
    "sg:phone":"+33 4 92 00 71 20",
    "sg:province":"Franche Comt\u00e9",
    "wof:name":"Eclairage 06 S.a.r.l.",
    "wof:placetype":"venue"
},
  "geometry": {"coordinates":[7.285369,43.703667],"type":"Point"}
}