{
  "type": "Feature",
  "properties": {
    "addr:full":"ZI la Vignasse La Voulte sur Rh\u00f4ne Rhone-Alpes 07800",
    "addr:postcode":"07800",
    "addr:street":"Zi La Vignasse La Voulte Sur",
    "iso:country":"FR",
    "sg:address":"ZI la Vignasse",
    "sg:city":"La Voulte sur Rh\u00f4ne",
    "sg:orig_category":"Non-Classified Establishments",
    "sg:phone":"+33 4 75 62 06 24",
    "sg:postcode":"07800",
    "sg:province":"Rhone-Alpes",
    "wof:name":"Reynaud Traitement Thermique",
    "wof:placetype":"venue"
},
  "geometry": {"coordinates":[4.78152,44.800594],"type":"Point"}
}