{
  "type": "Feature",
  "properties": {
    "iso:country":"FR",
    "sg:address":"149 av Louis Barthou; Bordeaux",
    "sg:classifiers":[
        {
            "category":"Banks & Credit Unions",
            "subcategory":"Bank",
            "type":"Services"
        }
    ],
    "sg:phone":"+33 3356084694",
    "sg:province":"Limousin",
    "wof:name":"Banque Nationale De Paris",
    "wof:placetype":"venue"
},
  "geometry": {"coordinates":[-0.614496,44.852333],"type":"Point"}
}