{
  "type": "Feature",
  "properties": {
    "iso:country":"FR",
    "sg:address":"103, Av. Mar\u00e9chal de Saxe, 69003 Lyon",
    "sg:orig_category":"Non-Classified Establishments",
    "sg:phone":"+33 4 78 95 60 09",
    "sg:postcode":"69003",
    "sg:province":"Rhone-Alpes",
    "wof:name":"Interflora France S.a.",
    "wof:placetype":"venue"
},
  "geometry": {"coordinates":[4.846012,45.759331],"type":"Point"}
}