{
  "type": "Feature",
  "properties": {
    "addr:full":"153 Rue De Buzenval 92380 Garches Ile de France 92380",
    "addr:housenumber":"153",
    "addr:postcode":"92380;ile;92380",
    "addr:street":"Rue De Buzenval;France",
    "iso:country":"FR",
    "sg:address":"153 Rue De Buzenval 92380 Garches",
    "sg:classifiers":[
        {
            "category":"Health Services",
            "subcategory":"Medical Lab",
            "type":"Services"
        }
    ],
    "sg:phone":"+33 1 47 10 88 00",
    "sg:postcode":"92380",
    "sg:province":"Ile de France",
    "sg:tags":[
        "chemical",
        "pharmaceutical",
        "pharmacy"
    ],
    "wof:name":"Fournier",
    "wof:placetype":"venue"
},
  "geometry": {"coordinates":[2.201251,48.853054],"type":"Point"}
}