{
  "type": "Feature",
  "properties": {
    "addr:full":"24, Av. Foch, 64200 Biarritz Biarritz Aquitaine 64200",
    "addr:postcode":"64200;64200",
    "addr:street":"24 Av. Foch",
    "iso:country":"FR",
    "sg:address":"24, Av. Foch, 64200 Biarritz",
    "sg:city":"Biarritz",
    "sg:orig_category":"Unclassifiable Establishments",
    "sg:phone":"+33 5 59 24 01 10",
    "sg:postcode":"64200",
    "sg:province":"Aquitaine",
    "wof:name":"Tourisme Basque S.a.r.l.",
    "wof:placetype":"venue"
},
  "geometry": {"coordinates":[-1.556129,43.47649],"type":"Point"}
}