{
  "type": "Feature",
  "properties": {
    "addr:full":"62 Quai Dr Jacquin 38340 Voreppe Rhone-Alpes 38340",
    "addr:housenumber":"62",
    "addr:postcode":"38340;38340",
    "addr:street":"Quai Dr Jacquin",
    "iso:country":"FR",
    "sg:address":"62 Quai Dr Jacquin 38340 Voreppe",
    "sg:classifiers":[
        {
            "category":"Professional",
            "subcategory":"Business Services",
            "type":"Services"
        }
    ],
    "sg:phone":"+33 4 76 50 47 00",
    "sg:postcode":"38340",
    "sg:province":"Rhone-Alpes",
    "sg:tags":[
        "body",
        "advice"
    ],
    "wof:name":"Mairie",
    "wof:placetype":"venue"
},
  "geometry": {"coordinates":[5.637144,45.298046],"type":"Point"}
}