{
  "type": "Feature",
  "properties": {
    "addr:full":"ZA le Bois Cholet Saint Aignan Grandlieu Pays de Loire 44860",
    "addr:postcode":"grandlieu;44860",
    "addr:street":"Za Le Bois",
    "iso:country":"FR",
    "sg:address":"ZA le Bois Cholet",
    "sg:city":"Saint Aignan Grandlieu",
    "sg:orig_category":"Non-Classified Establishments",
    "sg:phone":"+33 2 40 32 64 30",
    "sg:postcode":"44860",
    "sg:province":"Pays de Loire",
    "wof:name":"Ar\u00e9a S.a.r.l.",
    "wof:placetype":"venue"
},
  "geometry": {"coordinates":[-1.633484,47.12294],"type":"Point"}
}