{
  "type": "Feature",
  "properties": {
    "addr:full":"Rue de Bourgogne Saint Priest Rhone-Alpes 69800",
    "addr:postcode":"69800",
    "addr:street":"Rue De Bourgogne Saint;Rhone-Alpes",
    "iso:country":"FR",
    "sg:address":"Rue de Bourgogne",
    "sg:city":"Saint Priest",
    "sg:orig_category":"Non-Classified Establishments",
    "sg:phone":"+33 4 72 28 13 40",
    "sg:postcode":"69800",
    "sg:province":"Rhone-Alpes",
    "wof:name":"Promosol S.a.",
    "wof:placetype":"venue"
},
  "geometry": {"coordinates":[4.914015,45.694859],"type":"Point"}
}