{
  "type": "Feature",
  "properties": {
    "addr:full":"B.P. 89, 61203 Urou et Crennes C\u00e9dex^^1, Rue Michel Brilland, 61200 Urou et Crennes Argentan Basse Normandie 61200",
    "addr:postcode":"61203;61200;61200",
    "addr:street":"B.P. 89;Rue Michel Brilland;Basse",
    "iso:country":"FR",
    "sg:address":"B.P. 89, 61203 Urou et Crennes C\u00e9dex^^1, Rue Michel Brilland, 61200 Urou et Crennes",
    "sg:city":"Argentan",
    "sg:orig_category":"Non-Classified Establishments",
    "sg:phone":"+33 2 33 67 80 60",
    "sg:postcode":"61200",
    "sg:province":"Basse Normandie",
    "wof:name":"S.e.r.t.e.c. S.a.r.l. - Soci\u00e9t\u00e9 Etude R\u00e9alisation Technique Et Commerce",
    "wof:placetype":"venue"
},
  "geometry": {"coordinates":[-0.057034,48.691784],"type":"Point"}
}