{
  "type": "Feature",
  "properties": {
    "iso:country":"FR",
    "sg:address":"30 Rue Edouard Idoux 69700 Givors",
    "sg:classifiers":[
        {
            "category":"Shopping",
            "type":"Retail Goods"
        }
    ],
    "sg:phone":"+33 4 72 49 21 70",
    "sg:postcode":"69700",
    "sg:province":"Rhone-Alpes",
    "sg:tags":[
        "metallurgy",
        "finished",
        "-",
        "metalworking",
        "metallic"
    ],
    "wof:name":"Fabrique De Moules En Verrerie Sa",
    "wof:placetype":"venue"
},
  "geometry": {"coordinates":[4.763629,45.592495],"type":"Point"}
}