{
  "type": "Feature",
  "properties": {
    "addr:full":"65 Avenue De Fronton Toulouse Midi Pyr\u00e9n\u00e9es 31200",
    "addr:housenumber":"65",
    "addr:postcode":"31200",
    "addr:street":"Avenue De Fronton",
    "iso:country":"FR",
    "sg:address":"65 Avenue De Fronton",
    "sg:city":"Toulouse",
    "sg:classifiers":[
        {
            "category":"Banks & Credit Unions",
            "subcategory":"Financial Services",
            "type":"Services"
        }
    ],
    "sg:phone":"+33 5 61 47 92 73",
    "sg:postcode":"31200",
    "sg:province":"Midi Pyr\u00e9n\u00e9es",
    "sg:tags":[
        "banking",
        "finance",
        "insurance"
    ],
    "wof:name":"Cabinet Yves Lang Sarl",
    "wof:placetype":"venue"
},
  "geometry": {"coordinates":[1.433574,43.629883],"type":"Point"}
}