{
  "type": "Feature",
  "properties": {
    "iso:country":"FR",
    "sg:address":"43 ave Montaigne; Paris; 75008",
    "sg:classifiers":[
        {
            "category":"Banks & Credit Unions",
            "subcategory":"Bank",
            "type":"Services"
        }
    ],
    "sg:phone":"+33 1 47 23 78 57",
    "sg:postcode":"75008",
    "sg:province":"Ile de France",
    "wof:name":"Bank Melli Iran",
    "wof:placetype":"venue"
},
  "geometry": {"coordinates":[2.306504,48.86739],"type":"Point"}
}