{
  "type": "Feature",
  "properties": {
    "iso:country":"FR",
    "sg:address":"5 Av Du G\u00e9n\u00e9ral De Gaulle 77370 Nangis",
    "sg:classifiers":[
        {
            "category":"Professional",
            "subcategory":"Engineering",
            "type":"Services"
        }
    ],
    "sg:phone":"+33 1 60 58 54 00",
    "sg:postcode":"77370",
    "sg:province":"Ile de France",
    "sg:tags":[
        "good",
        "material",
        "-",
        "equipment",
        "handling",
        "machinery",
        "mechanical",
        "agriculture"
    ],
    "wof:name":"Etablissements Gibouin Sa",
    "wof:placetype":"venue"
},
  "geometry": {"coordinates":[3.014824,48.561382],"type":"Point"}
}