{
  "type": "Feature",
  "properties": {
    "iso:country":"FR",
    "sg:address":"27 Rue Edmond Nocard 77160 Provins",
    "sg:classifiers":[
        {
            "category":"Banks & Credit Unions",
            "subcategory":"Investment Brokerage",
            "type":"Services"
        }
    ],
    "sg:phone":"+33 1 64 01 41 74",
    "sg:province":"Ile de France",
    "sg:tags":[
        "-",
        "transport",
        "related"
    ],
    "wof:name":"Comareg Sa",
    "wof:placetype":"venue"
},
  "geometry": {"coordinates":[3.30209,48.560638],"type":"Point"}
}