{
  "type": "Feature",
  "properties": {
    "iso:country":"FR",
    "sg:address":"Rue de l'Industrie - ZA le Grand Lieu",
    "sg:city":"Saint Philbert de Grand Lieu",
    "sg:orig_category":"Unclassifiable Establishments",
    "sg:phone":"+33 2 40 78 08 08",
    "sg:postcode":"44310",
    "sg:province":"Pays de Loire",
    "wof:name":"Abri Plus Equipements S.a.",
    "wof:placetype":"venue"
},
  "geometry": {"coordinates":[-1.634477,47.050335],"type":"Point"}
}