{
  "type": "Feature",
  "properties": {
    "iso:country":"FR",
    "sg:address":"14 bis, Rue Barb\u00e8s, 92300 Levallois Perret",
    "sg:orig_category":"Non-Classified Establishments",
    "sg:phone":"+33 1 47 58 58 58",
    "sg:province":"Ile de France",
    "wof:name":"Soregraph S.a.",
    "wof:placetype":"venue"
},
  "geometry": {"coordinates":[2.282174,48.890343],"type":"Point"}
}