{
  "type": "Feature",
  "properties": {
    "iso:country":"FR",
    "sg:address":"B.P. 7, 77211 Avon C\u00e9dex^^92, Rue Gambetta, 77210 Avon",
    "sg:orig_category":"Non-Classified Establishments",
    "sg:phone":"+33 1 60 74 56 50",
    "sg:province":"Ile de France",
    "wof:name":"Goulard Travaux Publics S.a.r.l.",
    "wof:placetype":"venue"
},
  "geometry": {"coordinates":[2.72196,48.415936],"type":"Point"}
}