{
  "type": "Feature",
  "properties": {
    "iso:country":"FR",
    "sg:address":"Rue De Gare 62112 Corbehem",
    "sg:classifiers":[
        {
            "category":"Manufacturing",
            "subcategory":"Metals",
            "type":"Manufacturing & Wholesale Goods"
        }
    ],
    "sg:phone":"+33 3 27 99 22 00",
    "sg:postcode":"62112",
    "sg:province":"Nord Pas-de-Calais",
    "sg:tags":[
        "pharmaceutical",
        "-",
        "metallic",
        "metallurgy",
        "finished",
        "chemical",
        "chemistry",
        "by-product"
    ],
    "wof:name":"Premines Industries Sas",
    "wof:placetype":"venue"
},
  "geometry": {"coordinates":[3.046631,50.337727],"type":"Point"}
}