{
  "type": "Feature",
  "properties": {
    "addr:full":"1630, Av. de la Croix Rouge, 84046 Avignon C\u00e9dex 9 Franche Comt\u00e9",
    "addr:housenumber":"1630;9",
    "addr:postcode":"84046",
    "addr:street":"Av. De La Croix Rouge;Ce\u0301Dex;Franche Comte\u0301",
    "iso:country":"FR",
    "sg:address":"1630, Av. de la Croix Rouge, 84046 Avignon C\u00e9dex 9",
    "sg:orig_category":"Non-Classified Establishments",
    "sg:phone":"+33 4 90 13 27 00",
    "sg:province":"Franche Comt\u00e9",
    "wof:name":"E.d.f. G.d.f. Services Avignon",
    "wof:placetype":"venue"
},
  "geometry": {"coordinates":[4.837463,43.925282],"type":"Point"}
}