{
  "type": "Feature",
  "properties": {
    "iso:country":"FR",
    "sg:address":"230 R Des Fr\u00e8res Montgolfier 82000 Montauban",
    "sg:classifiers":[
        {
            "category":"Shopping",
            "type":"Retail Goods"
        }
    ],
    "sg:phone":"+33 5 63 23 04 04",
    "sg:postcode":"82000",
    "sg:province":"Midi Pyr\u00e9n\u00e9es",
    "sg:tags":[
        "metallurgy",
        "finished",
        "-",
        "metalworking",
        "metallic"
    ],
    "wof:name":"Comptec Sa",
    "wof:placetype":"venue"
},
  "geometry": {"coordinates":[1.333369,43.980423],"type":"Point"}
}