{
  "type": "Feature",
  "properties": {
    "addr:full":"69, Rue du Docteur Pontier, 62380 Lumbres Nord Pas-de-Calais",
    "addr:housenumber":"69",
    "addr:postcode":"62380",
    "addr:street":"Rue Du Docteur Pontier",
    "iso:country":"FR",
    "sg:address":"69, Rue du Docteur Pontier, 62380 Lumbres",
    "sg:orig_category":"Non-Classified Establishments",
    "sg:phone":"+33 3 21 38 60 00",
    "sg:province":"Nord Pas-de-Calais",
    "wof:name":"Sical S.a.",
    "wof:placetype":"venue"
},
  "geometry": {"coordinates":[2.12328,50.694103],"type":"Point"}
}