{
  "type": "Feature",
  "properties": {
    "addr:full":"10 Rue Hebert Grenoble Rhone-Alpes 38000",
    "addr:housenumber":"10",
    "addr:postcode":"38000",
    "addr:street":"Rue Hebert",
    "iso:country":"FR",
    "sg:address":"10 Rue Hebert",
    "sg:city":"Grenoble",
    "sg:classifiers":[
        {
            "category":"Banks & Credit Unions",
            "subcategory":"Financial Services",
            "type":"Services"
        }
    ],
    "sg:phone":"+33 4 76 28 39 11",
    "sg:postcode":"38000",
    "sg:province":"Rhone-Alpes",
    "sg:tags":[
        "banking",
        "finance",
        "insurance"
    ],
    "wof:name":"Caisse D'epargne Et De Prevoyance Des Alpesecureuil",
    "wof:placetype":"venue"
},
  "geometry": {"coordinates":[5.737363,45.190784],"type":"Point"}
}