{
  "type": "Feature",
  "properties": {
    "iso:country":"FR",
    "sg:address":"52/70, Av. du G\u00e9n\u00e9ral de Gaulle, 92230 Gennevilliers",
    "sg:orig_category":"Unclassifiable Establishments",
    "sg:phone":"+33 1 41 21 89 00",
    "sg:province":"Ile de France",
    "wof:name":"Intersoft-i.s.m. S.a.r.l.",
    "wof:placetype":"venue"
},
  "geometry": {"coordinates":[2.310775,48.933456],"type":"Point"}
}