{
  "type": "Feature",
  "properties": {
    "iso:country":"FR",
    "sg:address":"2, Rue des Francs Bourgeois, 75003 Paris",
    "sg:orig_category":"Non-Classified Establishments",
    "sg:phone":"+33 1 42 72 94 31",
    "sg:province":"Ile de France",
    "wof:name":"G\u00e9rard Bernardin Merchandai S.a.r.l.",
    "wof:placetype":"venue"
},
  "geometry": {"coordinates":[2.3647,48.856514],"type":"Point"}
}