{
  "type": "Feature",
  "properties": {
    "iso:country":"FR",
    "sg:address":"B.P. 9, 78373 Plaisir C\u00e9dex^^1, Rue des Fr\u00e8res Lumi\u00e8re, 78370 Plaisir",
    "sg:orig_category":"Non-Classified Establishments",
    "sg:phone":"+33 1 30 81 73 00",
    "sg:postcode":"78370",
    "sg:province":"Ile de France",
    "wof:name":"Elf Atochem Agri S.a.",
    "wof:placetype":"venue"
},
  "geometry": {"coordinates":[1.949255,48.816689],"type":"Point"}
}