{
  "type": "Feature",
  "properties": {
    "addr:full":"57 Mont\u00e9e De St Menet 13011 Marseille Poitou-Charentes",
    "addr:housenumber":"57",
    "addr:postcode":"13011",
    "addr:street":"Monte\u0301E De St",
    "iso:country":"FR",
    "sg:address":"57 Mont\u00e9e De St Menet 13011 Marseille",
    "sg:classifiers":[
        {
            "category":"Professional",
            "subcategory":"Engineering",
            "type":"Services"
        }
    ],
    "sg:phone":"+33 4 91 43 19 19",
    "sg:province":"Poitou-Charentes",
    "sg:tags":[
        "machine",
        "-",
        "mechanical"
    ],
    "wof:name":"Mongin Jauffret",
    "wof:placetype":"venue"
},
  "geometry": {"coordinates":[5.437165,43.289322],"type":"Point"}
}