{
  "type": "Feature",
  "properties": {
    "addr:full":"9 rue Porte Saumon; Le Loroux Bottereau Le Loroux Bretagne 35133",
    "addr:housenumber":"9",
    "addr:postcode":"35133",
    "addr:street":"Rue Porte Saumon;Le Loroux Bretagne",
    "iso:country":"FR",
    "sg:address":"9 rue Porte Saumon; Le Loroux Bottereau",
    "sg:city":"Le Loroux",
    "sg:classifiers":[
        {
            "category":"Banks & Credit Unions",
            "subcategory":"Bank",
            "type":"Services"
        }
    ],
    "sg:phone":"+33 3340338127",
    "sg:postcode":"35133",
    "sg:province":"Bretagne",
    "wof:name":"Caisse De Cr\u00e9dit Mutuel",
    "wof:placetype":"venue"
},
  "geometry": {"coordinates":[-1.348439,47.237965],"type":"Point"}
}