{
  "type": "Feature",
  "properties": {
    "iso:country":"FR",
    "sg:address":"18 Rue Cl\u00e9ment Vienot 94300 Vincennes",
    "sg:classifiers":[
        {
            "category":"Professional",
            "subcategory":"Engineering",
            "type":"Services"
        }
    ],
    "sg:phone":"+33 1 43 98 88 33",
    "sg:postcode":"94300",
    "sg:province":"Ile de France",
    "sg:tags":[
        "machine",
        "-",
        "mechanical"
    ],
    "wof:name":"Robot Coupe",
    "wof:placetype":"venue"
},
  "geometry": {"coordinates":[2.451209,48.847031],"type":"Point"}
}