{
  "type": "Feature",
  "properties": {
    "addr:full":"Plaine De L Habitarelle Pole Indust Alcatel Cable 30110 Les Salles Du Gardon Languedoc-Roussillon 30110",
    "addr:postcode":"30110;30110",
    "addr:street":"Plaine De L Habitarelle Pole;Gardon",
    "iso:country":"FR",
    "sg:address":"Plaine De L Habitarelle Pole Indust Alcatel Cable 30110 Les Salles Du Gardon",
    "sg:classifiers":[
        {
            "category":"Autos & Motor Vehicles",
            "subcategory":"Automobile Sales",
            "type":"Retail Goods"
        }
    ],
    "sg:phone":"+33 4 66 54 95 22",
    "sg:postcode":"30110",
    "sg:province":"Languedoc-Roussillon",
    "sg:tags":[
        "equipment",
        "motor-cars",
        "transport"
    ],
    "wof:name":"Sc Azurea",
    "wof:placetype":"venue"
},
  "geometry": {"coordinates":[4.012342,44.175049],"type":"Point"}
}