{
  "type": "Feature",
  "properties": {
    "addr:full":"9 Rue Magellan 75008 Paris Ile de France",
    "addr:housenumber":"9",
    "addr:postcode":"75008",
    "addr:street":"Rue Magellan",
    "iso:country":"FR",
    "sg:address":"9 Rue Magellan 75008 Paris",
    "sg:classifiers":[
        {
            "category":"Professional",
            "subcategory":"Printing & Photocopies",
            "type":"Services"
        }
    ],
    "sg:phone":"+33 1 40 73 80 00",
    "sg:province":"Ile de France",
    "sg:tags":[
        "publishing"
    ],
    "wof:name":"Revue Generale Des Routes Et Des Aerodromes",
    "wof:placetype":"venue"
},
  "geometry": {"coordinates":[2.299748,48.870338],"type":"Point"}
}