{
  "type": "Feature",
  "properties": {
    "iso:country":"FR",
    "sg:address":"11, Rue Amp\u00e8re, 01100 Oyonnax",
    "sg:orig_category":"Unclassifiable Establishments",
    "sg:phone":"+33 4 74 81 75 99",
    "sg:postcode":"01100",
    "sg:province":"Rhone-Alpes",
    "wof:name":"Plastic Omnium S.a.",
    "wof:placetype":"venue"
},
  "geometry": {"coordinates":[5.664568,46.266483],"type":"Point"}
}