{
  "type": "Feature",
  "properties": {
    "addr:full":"52 Rue De Lisbonne 75008 Paris Ile de France 75008",
    "addr:housenumber":"52",
    "addr:postcode":"75008;75008",
    "addr:street":"Rue De Lisbonne",
    "iso:country":"FR",
    "sg:address":"52 Rue De Lisbonne 75008 Paris",
    "sg:classifiers":[
        {
            "category":"Food Court",
            "type":"Food & Drink"
        }
    ],
    "sg:phone":"+33 1 42 99 75 00",
    "sg:postcode":"75008",
    "sg:province":"Ile de France",
    "sg:tags":[
        "product",
        "related"
    ],
    "wof:name":"Societe Jas Hennessy Et Compagnie (hennessy)",
    "wof:placetype":"venue"
},
  "geometry": {"coordinates":[2.309366,48.877621],"type":"Point"}
}