{
  "type": "Feature",
  "properties": {
    "iso:country":"FR",
    "sg:address":"B.P. 2, 44119 Treilli\u00e8res^^Rte de la P\u00e2quelais, 44119 Treilli\u00e8res",
    "sg:orig_category":"Non-Classified Establishments",
    "sg:phone":"+33 2 40 94 64 29",
    "sg:province":"Pays de Loire",
    "wof:name":"Imprimerie Et S\u00e9rigraphie De L'atlantique S.a.r.l.",
    "wof:placetype":"venue"
},
  "geometry": {"coordinates":[-1.622475,47.330029],"type":"Point"}
}