{
  "type": "Feature",
  "properties": {
    "addr:full":"Route Ch\u00e2teaufort 91190 Gif Sur Yvette Ile de France 91190",
    "addr:postcode":"91190;91190",
    "addr:street":"Route Cha\u0302Teaufort",
    "iso:country":"FR",
    "sg:address":"Route Ch\u00e2teaufort 91190 Gif Sur Yvette",
    "sg:classifiers":[
        {
            "category":"Wholesale",
            "subcategory":"Meat",
            "type":"Manufacturing & Wholesale Goods"
        }
    ],
    "sg:phone":"+33 1 69 07 79 24",
    "sg:postcode":"91190",
    "sg:province":"Ile de France",
    "sg:tags":[
        "food",
        "cooked",
        "product",
        "related"
    ],
    "wof:name":"Etablissements Lanier Sarl",
    "wof:placetype":"venue"
},
  "geometry": {"coordinates":[2.120161,48.709606],"type":"Point"}
}