{
  "type": "Feature",
  "properties": {
    "addr:full":"67, Rue Jules Siegfried, 76056 Le Havre C\u00e9dex Haute-Normandie",
    "addr:housenumber":"67",
    "addr:postcode":"76056",
    "addr:street":"Rue Jules Siegfried",
    "iso:country":"FR",
    "sg:address":"67, Rue Jules Siegfried, 76056 Le Havre C\u00e9dex",
    "sg:orig_category":"Unclassifiable Establishments",
    "sg:phone":"+33 2 32 74 01 00",
    "sg:province":"Haute-Normandie",
    "wof:name":"E.c.l. Informatique S.a.",
    "wof:placetype":"venue"
},
  "geometry": {"coordinates":[0.113889,49.492207],"type":"Point"}
}