{
  "type": "Feature",
  "properties": {
    "addr:full":"Za La Prade 33650 St Medard D Eyrans Cabanac-et-Villagrains Aquitaine 33650",
    "addr:housenumber":"cabanac-et-villagrains",
    "addr:postcode":"33650;33650",
    "addr:street":"Za La Prade",
    "iso:country":"FR",
    "sg:address":"Za La Prade 33650 St Medard D Eyrans",
    "sg:city":"Cabanac-et-Villagrains",
    "sg:classifiers":[
        {
            "category":"Food & Beverages",
            "subcategory":"Dairy",
            "type":"Retail Goods"
        }
    ],
    "sg:phone":"+33 5 57 97 02 60",
    "sg:postcode":"33650",
    "sg:province":"Aquitaine",
    "sg:tags":[
        "product",
        "related"
    ],
    "wof:name":"Le Petit Basque Sa",
    "wof:placetype":"venue"
},
  "geometry": {"coordinates":[-0.508946,44.717876],"type":"Point"}
}