{
  "type": "Feature",
  "properties": {
    "iso:country":"FR",
    "sg:address":"Rue De La Loire 42110 Feurs",
    "sg:classifiers":[
        {
            "category":"Professional",
            "subcategory":"Engineering",
            "type":"Services"
        }
    ],
    "sg:phone":"+33 4 77 26 03 07",
    "sg:postcode":"42110",
    "sg:province":"Rhone-Alpes",
    "sg:tags":[
        "machine",
        "-",
        "mechanical"
    ],
    "wof:name":"Societe Forezienne D'abattage",
    "wof:placetype":"venue"
},
  "geometry": {"coordinates":[4.214,45.74268],"type":"Point"}
}