{
  "type": "Feature",
  "properties": {
    "addr:full":"16, 3\u00e8me Avenue - ZI des Estroublancs, 13127 Vitrolles Midi Pyr\u00e9n\u00e9es",
    "addr:housenumber":"16",
    "addr:postcode":"13127",
    "addr:street":"3E\u0300Me Avenue Zi Des Estroublancs",
    "iso:country":"FR",
    "sg:address":"16, 3\u00e8me Avenue - ZI des Estroublancs, 13127 Vitrolles",
    "sg:orig_category":"Unclassifiable Establishments",
    "sg:phone":"+33 4 42 79 68 07",
    "sg:province":"Midi Pyr\u00e9n\u00e9es",
    "wof:name":"Iris L'int\u00e9rim D'action",
    "wof:placetype":"venue"
},
  "geometry": {"coordinates":[5.247865,43.432285],"type":"Point"}
}