{
  "type": "Feature",
  "properties": {
    "iso:country":"FR",
    "sg:address":"46 Bis Rue Henri Bordeaux 52101 St Dizier Cedex",
    "sg:city":"Bordeaux",
    "sg:classifiers":[
        {
            "category":"Manufacturing",
            "subcategory":"Metals",
            "type":"Manufacturing & Wholesale Goods"
        }
    ],
    "sg:phone":"+33 3 25 05 40 40",
    "sg:postcode":"33100",
    "sg:province":"Aquitaine",
    "sg:tags":[
        "metallurgy",
        "metalworking",
        "processing"
    ],
    "wof:name":"Sedacier Sa",
    "wof:placetype":"venue"
},
  "geometry": {"coordinates":[7.130767,47.578274],"type":"Point"}
}