{
  "type": "Feature",
  "properties": {
    "addr:full":"2 Rue Des Fr\u00e9res Bertrand 69200 Venissieux Rhone-Alpes",
    "addr:housenumber":"2",
    "addr:postcode":"69200",
    "addr:street":"Rue Des Fre\u0301Res Bertrand",
    "iso:country":"FR",
    "sg:address":"2 Rue Des Fr\u00e9res Bertrand 69200 Venissieux",
    "sg:classifiers":[
        {
            "category":"Government",
            "subcategory":"Department Of Motor Vehicles",
            "type":"Public Place"
        }
    ],
    "sg:phone":"+33 4 72 78 49 49",
    "sg:province":"Rhone-Alpes",
    "sg:tags":[
        "equipment",
        "industrial",
        "transport",
        "motor-cars"
    ],
    "wof:name":"Automobiles Peugeot",
    "wof:placetype":"venue"
},
  "geometry": {"coordinates":[4.861002,45.717026],"type":"Point"}
}