{
  "type": "Feature",
  "properties": {
    "addr:full":"11, Rue Haut de Veaux RETONFEY 57645",
    "addr:housenumber":"11",
    "addr:postcode":"57645",
    "addr:street":"Rue Haut De Veaux",
    "iso:country":"FR",
    "sg:address":"11, Rue Haut de Veaux",
    "sg:city":"RETONFEY",
    "sg:classifiers":[
        {
            "category":"Professional",
            "subcategory":"Advertising",
            "type":"Services"
        }
    ],
    "sg:postcode":"57645",
    "sg:tags":[
        "french",
        "media",
        "hyperlocal",
        "news",
        "network"
    ],
    "sg:website":"http://www.proxiti.com",
    "wof:name":"ProXiti",
    "wof:placetype":"venue"
},
  "geometry": {"coordinates":[6.30231,49.134798],"type":"Point"}
}