{
  "type": "Feature",
  "properties": {
    "iso:country":"FR",
    "sg:address":"38 Rue Des Thermes Romains 17100 Saintes",
    "sg:classifiers":[
        {
            "category":"Professional",
            "subcategory":"Engineering",
            "type":"Services"
        }
    ],
    "sg:phone":"+33 5 46 74 18 83",
    "sg:postcode":"17100",
    "sg:province":"Poitou-Charentes",
    "sg:tags":[
        "machine",
        "-",
        "mechanical"
    ],
    "wof:name":"Etablissements Gougnon Jacques",
    "wof:placetype":"venue"
},
  "geometry": {"coordinates":[-0.637973,45.750652],"type":"Point"}
}