{
  "type": "Feature",
  "properties": {
    "addr:full":"58bis, Rue de l'Abb\u00e9 Choquet, 59140 Dunkerque Nord Pas-de-Calais",
    "addr:housenumber":"58bis",
    "addr:postcode":"59140",
    "addr:street":"Rue De L'Abbe \u0301 Choquet",
    "iso:country":"FR",
    "sg:address":"58bis, Rue de l'Abb\u00e9 Choquet, 59140 Dunkerque",
    "sg:orig_category":"Unclassifiable Establishments",
    "sg:phone":"+33 3 28 25 93 93",
    "sg:province":"Nord Pas-de-Calais",
    "wof:name":"Sipiajoint E.u.r.l.",
    "wof:placetype":"venue"
},
  "geometry": {"coordinates":[2.37551,51.026829],"type":"Point"}
}