{
  "type": "Feature",
  "properties": {
    "iso:country":"FR",
    "sg:address":"ZA des Longs Pr\u00e9s",
    "sg:city":"Lumbin",
    "sg:orig_category":"Unclassifiable Establishments",
    "sg:phone":"+33 4 76 08 27 52",
    "sg:postcode":"38660",
    "sg:province":"Rhone-Alpes",
    "wof:name":"Alpes Confection S.a.r.l.",
    "wof:placetype":"venue"
},
  "geometry": {"coordinates":[5.913275,45.307453],"type":"Point"}
}