{
  "type": "Feature",
  "properties": {
    "iso:country":"FR",
    "sg:address":"343, Bd Romain Rolland - B\u00e2t B, 13000 Marseille",
    "sg:orig_category":"Unclassifiable Establishments",
    "sg:phone":"+33 4 42 24 38 00",
    "sg:province":"Provence-Alpes-C\u00f4te d'Azur",
    "wof:name":"Besnier Valmont Rodez",
    "wof:placetype":"venue"
},
  "geometry": {"coordinates":[5.409284,43.27129],"type":"Point"}
}