{
  "type": "Feature",
  "properties": {
    "addr:full":"9, Rue Amp\u00e8re, 67120 Duttlenheim Duttlenheim Alsace 67120",
    "addr:housenumber":"9",
    "addr:postcode":"67120;67120",
    "addr:street":"Rue Ampe\u0300Re;Duttlenheim",
    "iso:country":"FR",
    "sg:address":"9, Rue Amp\u00e8re, 67120 Duttlenheim",
    "sg:city":"Duttlenheim",
    "sg:orig_category":"Non-Classified Establishments",
    "sg:phone":"+33 3 88 47 95 95",
    "sg:postcode":"67120",
    "sg:province":"Alsace",
    "wof:name":"Core Products S.a.s.",
    "wof:placetype":"venue"
},
  "geometry": {"coordinates":[7.574529,48.539925],"type":"Point"}
}