{
  "type": "Feature",
  "properties": {
    "addr:full":"B.P. 16, 13771 Fos sur Mer C\u00e9dex^^450, Chemin du Guigonnet, 13770 Fos sur Mer Franche Comt\u00e9",
    "addr:postcode":"13771;13770",
    "addr:street":"B.P. 16;Chemin Du Guigonnet;Franche Comte\u0301",
    "iso:country":"FR",
    "sg:address":"B.P. 16, 13771 Fos sur Mer C\u00e9dex^^450, Chemin du Guigonnet, 13770 Fos sur Mer",
    "sg:orig_category":"Non-Classified Establishments",
    "sg:phone":"+33 4 42 11 35 00",
    "sg:province":"Franche Comt\u00e9",
    "wof:name":"S.p.m.r. - Soci\u00e9t\u00e9 Du Pipeline M\u00e9diterran\u00e9e Rh\u00f4ne",
    "wof:placetype":"venue"
},
  "geometry": {"coordinates":[5.485145,43.599094],"type":"Point"}
}