{
  "type": "Feature",
  "properties": {
    "addr:full":"23 Rue Orl\u00e9ans 60350 Trosly Breuil Picardie 60350",
    "addr:housenumber":"23",
    "addr:postcode":"60350;60350",
    "addr:street":"Rue Orle\u0301Ans",
    "iso:country":"FR",
    "sg:address":"23 Rue Orl\u00e9ans 60350 Trosly Breuil",
    "sg:classifiers":[
        {
            "category":"Professional",
            "subcategory":"Business Services",
            "type":"Services"
        }
    ],
    "sg:phone":"+33 3 44 85 56 16",
    "sg:postcode":"60350",
    "sg:province":"Picardie",
    "sg:tags":[
        "body",
        "advice"
    ],
    "wof:name":"Association L Arche",
    "wof:placetype":"venue"
},
  "geometry": {"coordinates":[2.966886,49.400642],"type":"Point"}
}