{
  "type": "Feature",
  "properties": {
    "addr:full":"18 Rue Marcel Paul 29000 Quimper Quimper Bretagne 29000",
    "addr:housenumber":"18",
    "addr:postcode":"29000;29000",
    "addr:street":"Rue Marcel Paul",
    "iso:country":"FR",
    "sg:address":"18 Rue Marcel Paul 29000 Quimper",
    "sg:city":"Quimper",
    "sg:classifiers":[
        {
            "category":"Bakery",
            "type":"Food & Drink"
        }
    ],
    "sg:phone":"+33 2 98 53 74 75",
    "sg:postcode":"29000",
    "sg:province":"Bretagne",
    "sg:tags":[
        "cake",
        "product",
        "related",
        "bread"
    ],
    "wof:name":"Millcrepes",
    "wof:placetype":"venue"
},
  "geometry": {"coordinates":[-4.026337,47.97691],"type":"Point"}
}