{
  "type": "Feature",
  "properties": {
    "addr:full":"Rue des Herbillaux Niort Poitou-Charentes 79000",
    "addr:postcode":"79000",
    "addr:street":"Rue Des Herbillaux Niort",
    "iso:country":"FR",
    "sg:address":"Rue des Herbillaux",
    "sg:city":"Niort",
    "sg:orig_category":"Non-Classified Establishments",
    "sg:phone":"+33 5 49 33 11 71",
    "sg:postcode":"79000",
    "sg:province":"Poitou-Charentes",
    "wof:name":"Niortaise De Mat\u00e9riaux S.n.c.",
    "wof:placetype":"venue"
},
  "geometry": {"coordinates":[-0.420444,46.333729],"type":"Point"}
}