{
  "type": "Feature",
  "properties": {
    "iso:country":"FR",
    "sg:address":"Rte de la Prairie",
    "sg:city":"Varennes sur Seine",
    "sg:orig_category":"Non-Classified Establishments",
    "sg:phone":"+33 1 60 96 19 75",
    "sg:postcode":"77130",
    "sg:province":"Ile de France",
    "wof:name":"Vulca Service S.a.r.l.",
    "wof:placetype":"venue"
},
  "geometry": {"coordinates":[2.934829,48.378586],"type":"Point"}
}