{
  "type": "Feature",
  "properties": {
    "iso:country":"FR",
    "sg:address":"Champ De La Gr\u00e8le 72320 St Jean Des \u00c9chelles",
    "sg:classifiers":[
        {
            "category":"Home & Garden",
            "subcategory":"Furniture",
            "type":"Retail Goods"
        }
    ],
    "sg:phone":"+33 2 43 71 08 52",
    "sg:postcode":"72320",
    "sg:province":"Pays de Loire",
    "sg:tags":[
        "household",
        "wood"
    ],
    "wof:name":"Meubles Saint Jean Sa",
    "wof:placetype":"venue"
},
  "geometry": {"coordinates":[0.71276,48.12899],"type":"Point"}
}