{
  "type": "Feature",
  "properties": {
    "iso:country":"FR",
    "sg:address":"94, Rue Fran\u00e7ois Perrin, 87000 Limoges",
    "sg:orig_category":"Unclassifiable Establishments",
    "sg:phone":"+33 5 55 01 16 58",
    "sg:province":"Limousin",
    "wof:name":"F.f.t. S.a.r.l. - France Fonderies Typographiques",
    "wof:placetype":"venue"
},
  "geometry": {"coordinates":[1.242598,45.828735],"type":"Point"}
}