{
  "type": "Feature",
  "properties": {
    "addr:full":"B.P. 40, 46101 Figeac C\u00e9dex^^ZI de l'Aiguille, 46101 Figeac Midi Pyr\u00e9n\u00e9es",
    "addr:postcode":"46101;46101",
    "addr:street":"B.P. 40;L'Aiguille",
    "iso:country":"FR",
    "sg:address":"B.P. 40, 46101 Figeac C\u00e9dex^^ZI de l'Aiguille, 46101 Figeac",
    "sg:orig_category":"Non-Classified Establishments",
    "sg:phone":"+33 5 65 34 20 82",
    "sg:province":"Midi Pyr\u00e9n\u00e9es",
    "wof:name":"Algans S.a.",
    "wof:placetype":"venue"
},
  "geometry": {"coordinates":[2.037327,44.596252],"type":"Point"}
}