{
  "type": "Feature",
  "properties": {
    "addr:full":"95, Av. du Vercors, 26600 Tain l'Hermitage Rhone-Alpes",
    "addr:postcode":"26600",
    "addr:street":"95 Av. Du Vercors",
    "iso:country":"FR",
    "sg:address":"95, Av. du Vercors, 26600 Tain l'Hermitage",
    "sg:orig_category":"Unclassifiable Establishments",
    "sg:phone":"+33 4 75 08 13 11",
    "sg:province":"Rhone-Alpes",
    "wof:name":"Hermitage Besse Is\u00e8re G.i.e.",
    "wof:placetype":"venue"
},
  "geometry": {"coordinates":[4.875049,45.010761],"type":"Point"}
}