{
  "type": "Feature",
  "properties": {
    "iso:country":"FR",
    "sg:address":"Zi De La Biscomtee 63760 Messeix",
    "sg:city":"Bourg-Lastic",
    "sg:classifiers":[
        {
            "category":"Wholesale",
            "subcategory":"Machinery & Supplies",
            "type":"Manufacturing & Wholesale Goods"
        }
    ],
    "sg:phone":"+33 4 73 21 49 02",
    "sg:postcode":"63760",
    "sg:province":"Auvergne",
    "sg:tags":[
        "handling",
        "material",
        "-",
        "machine",
        "equipment",
        "engineering",
        "mechanical"
    ],
    "wof:name":"Constructions Et Emballages Bois Massif",
    "wof:placetype":"venue"
},
  "geometry": {"coordinates":[-89.914146,37.2677],"type":"Point"}
}