{
  "type": "Feature",
  "properties": {
    "iso:country":"FR",
    "sg:address":"B.P. 636, 95196 Goussainville C\u00e9dex^^1, Rue Len\u00f4tre, 95190 Goussainville",
    "sg:orig_category":"Non-Classified Establishments",
    "sg:phone":"+33 1 39 88 63 00",
    "sg:province":"Ile de France",
    "wof:name":"Modulfroid Services S.a.r.l.",
    "wof:placetype":"venue"
},
  "geometry": {"coordinates":[2.47375,49.032452],"type":"Point"}
}