{
  "type": "Feature",
  "properties": {
    "iso:country":"FR",
    "sg:address":"124 Avenue Rubillard 72000 Le Mans",
    "sg:classifiers":[
        {
            "category":"Professional",
            "type":"Services"
        }
    ],
    "sg:phone":"+33 2 43 28 60 60",
    "sg:province":"Pays de Loire",
    "sg:tags":[
        "transport",
        "road"
    ],
    "wof:name":"Le Mans Ambulances Sarl",
    "wof:placetype":"venue"
},
  "geometry": {"coordinates":[0.181955,48.012375],"type":"Point"}
}