{
  "type": "Feature",
  "properties": {
    "addr:full":"54 Av Du Mar\u00e9chal De Saxe 69006 Lyon Rhone-Alpes",
    "addr:postcode":"69006",
    "addr:street":"54 Av Du Mare\u0301Chal De Saxe",
    "iso:country":"FR",
    "sg:address":"54 Av Du Mar\u00e9chal De Saxe 69006 Lyon",
    "sg:classifiers":[
        {
            "category":"Professional",
            "type":"Services"
        }
    ],
    "sg:phone":"+33 4 78 52 25 47",
    "sg:province":"Rhone-Alpes",
    "sg:tags":[
        "-",
        "related",
        "road",
        "transport"
    ],
    "wof:name":"Aux Professionnels Reunis De Lyon Sarl",
    "wof:placetype":"venue"
},
  "geometry": {"coordinates":[4.844692,45.763897],"type":"Point"}
}