{
  "type": "Feature",
  "properties": {
    "addr:full":"Rte de la Commanderie Tavel Languedoc-Roussillon 30126",
    "addr:postcode":"30126",
    "addr:street":"Rte De La Commanderie",
    "iso:country":"FR",
    "sg:address":"Rte de la Commanderie",
    "sg:city":"Tavel",
    "sg:orig_category":"Unclassifiable Establishments",
    "sg:phone":"+33 4 66 50 03 57",
    "sg:postcode":"30126",
    "sg:province":"Languedoc-Roussillon",
    "wof:name":"Caves Des Vignerons De Tavel S.c.a.",
    "wof:placetype":"venue"
},
  "geometry": {"coordinates":[4.702454,44.011173],"type":"Point"}
}