{
  "type": "Feature",
  "properties": {
    "addr:full":"4 rue du Bois Chaland 91090 Lisses Ile de France 91090",
    "addr:housenumber":"4",
    "addr:postcode":"91090;ile;91090",
    "addr:street":"Rue Du Bois Chaland;France",
    "iso:country":"FR",
    "sg:address":"4 rue du Bois Chaland 91090 Lisses",
    "sg:classifiers":[
        {
            "category":"Health Services",
            "subcategory":"Nursing And Care Facility",
            "type":"Services"
        }
    ],
    "sg:phone":"+33 1 69 89 70 00",
    "sg:postcode":"91090",
    "sg:province":"Ile de France",
    "sg:tags":[
        "industrial",
        "robot"
    ],
    "wof:name":"Fanuc Robotics France S.a.",
    "wof:placetype":"venue"
},
  "geometry": {"coordinates":[2.429175,48.606518],"type":"Point"}
}