{
  "type": "Feature",
  "properties": {
    "iso:country":"FR",
    "sg:address":"33 Av Georges L\u00e9vy 69200 V\u00e9nissieux",
    "sg:classifiers":[
        {
            "category":"Building & Trades",
            "subcategory":"Construction",
            "type":"Services"
        }
    ],
    "sg:phone":"+33 4 78 78 82 42",
    "sg:province":"Rhone-Alpes",
    "sg:tags":[
        "work",
        "public"
    ],
    "wof:name":"Sacer Sud-est Sa",
    "wof:placetype":"venue"
},
  "geometry": {"coordinates":[4.860519,45.719555],"type":"Point"}
}