{
  "type": "Feature",
  "properties": {
    "iso:country":"FR",
    "sg:address":"24-32 rue des Amandiers 75020 Paris",
    "sg:classifiers":[
        {
            "category":"Shopping",
            "subcategory":"Books",
            "type":"Retail Goods"
        }
    ],
    "sg:phone":"+33 1 40 33 84 00",
    "sg:postcode":"75020",
    "sg:province":"Ile de France",
    "wof:name":"Epa-lidis S.a.",
    "wof:placetype":"venue"
},
  "geometry": {"coordinates":[2.389635,48.864426],"type":"Point"}
}