{
  "type": "Feature",
  "properties": {
    "iso:country":"FR",
    "sg:address":"Immeuble Le Florestan 78054 Saint Quentin En Yvelines",
    "sg:classifiers":[
        {
            "category":"Banks & Credit Unions",
            "subcategory":"Financial Services",
            "type":"Services"
        }
    ],
    "sg:phone":"+33 1 30 12 96 00",
    "sg:province":"Haute Normandie",
    "sg:tags":[
        "banking",
        "insurance",
        "institution",
        "finance"
    ],
    "wof:name":"Societe Generale Sa",
    "wof:placetype":"venue"
},
  "geometry": {"coordinates":[2.04549,48.785019],"type":"Point"}
}