{
  "type": "Feature",
  "properties": {
    "addr:full":"7 Place Michel-de-l'Hospital, 63000 Clermont-Ferrand, Dept 63 Clermont-Ferrand Auvergne 63000",
    "addr:housenumber":"7;63",
    "addr:postcode":"63000;63000",
    "addr:street":"Place Michel-De-L'Hospital;Clermont-Ferrand",
    "iso:country":"FR",
    "sg:address":"7 Place Michel-de-l'Hospital, 63000 Clermont-Ferrand, Dept 63",
    "sg:city":"Clermont-Ferrand",
    "sg:classifiers":[
        {
            "category":"Banks & Credit Unions",
            "subcategory":"Bank",
            "type":"Services"
        }
    ],
    "sg:phone":"+33 4 73 42 73 42",
    "sg:postcode":"63000",
    "sg:province":"Auvergne",
    "wof:name":"Banque Nuger",
    "wof:placetype":"venue"
},
  "geometry": {"coordinates":[3.088802,45.776428],"type":"Point"}
}