{
  "type": "Feature",
  "properties": {
    "iso:country":"FR",
    "sg:address":"1, Rue Louis L\u00e9pine - ZAC Carr\u00e9 d'As, 13500 Martigues",
    "sg:orig_category":"Non-Classified Establishments",
    "sg:phone":"+33 4 42 07 00 25",
    "sg:province":"Languedoc-Roussillon",
    "wof:name":"Coraflex S.a.r.l.",
    "wof:placetype":"venue"
},
  "geometry": {"coordinates":[5.030942,43.395824],"type":"Point"}
}