{
  "type": "Feature",
  "properties": {
    "addr:full":"18, Rue Mondan, 26000 Valence Rhone-Alpes",
    "addr:housenumber":"18",
    "addr:postcode":"26000",
    "addr:street":"Rue Mondan",
    "iso:country":"FR",
    "sg:address":"18, Rue Mondan, 26000 Valence",
    "sg:orig_category":"Unclassifiable Establishments",
    "sg:phone":"+33 4 75 82 00 20",
    "sg:province":"Rhone-Alpes",
    "wof:name":"Rambaud S.a.",
    "wof:placetype":"venue"
},
  "geometry": {"coordinates":[4.9084,44.934479],"type":"Point"}
}