{
  "type": "Feature",
  "properties": {
    "addr:full":"55, Bd Hippolyte Faure, 51000 Ch\u00e2lons en Champagne Champagne",
    "addr:housenumber":"55",
    "addr:postcode":"51000",
    "addr:street":"Bd Hippolyte Faure",
    "iso:country":"FR",
    "sg:address":"55, Bd Hippolyte Faure, 51000 Ch\u00e2lons en Champagne",
    "sg:orig_category":"Unclassifiable Establishments",
    "sg:phone":"+33 3 26 68 37 11",
    "sg:province":"Champagne",
    "wof:name":"La Renaissance Immobili\u00e8re Ch\u00e2lonaise S.a.",
    "wof:placetype":"venue"
},
  "geometry": {"coordinates":[4.372877,48.954887],"type":"Point"}
}