{
  "type": "Feature",
  "properties": {
    "addr:full":"1 Rue Des Freres Farman Centre St Quentin En Yveli 78114 Magny Les Hameaux Ile de France 78114",
    "addr:housenumber":"1",
    "addr:postcode":"78114;78114",
    "addr:street":"Rue Des Freres Farman Centre St",
    "iso:country":"FR",
    "sg:address":"1 Rue Des Freres Farman Centre St Quentin En Yveli 78114 Magny Les Hameaux",
    "sg:classifiers":[
        {
            "category":"Manufacturing",
            "subcategory":"Aerospace",
            "type":"Manufacturing & Wholesale Goods"
        }
    ],
    "sg:phone":"+33 1 30 96 28 00",
    "sg:postcode":"78114",
    "sg:province":"Ile de France",
    "sg:tags":[
        "equipment",
        "aeronautic",
        "transport",
        "vehicle"
    ],
    "wof:name":"Snecma Services",
    "wof:placetype":"venue"
},
  "geometry": {"coordinates":[2.066322,48.753792],"type":"Point"}
}