{
  "type": "Feature",
  "properties": {
    "addr:full":"Usine Boisthorel 61270 Rai Rai Basse Normandie 61270",
    "addr:postcode":"61270;61270",
    "iso:country":"FR",
    "sg:address":"Usine Boisthorel 61270 Rai",
    "sg:city":"Rai",
    "sg:classifiers":[
        {
            "category":"Manufacturing",
            "subcategory":"Metals",
            "type":"Manufacturing & Wholesale Goods"
        }
    ],
    "sg:phone":"+33 2 33 24 94 06",
    "sg:postcode":"61270",
    "sg:province":"Basse Normandie",
    "sg:tags":[
        "metallurgy",
        "steel",
        "metalworking"
    ],
    "wof:name":"Trefimetaux",
    "wof:placetype":"venue"
},
  "geometry": {"coordinates":[0.572107,48.749886],"type":"Point"}
}