{
  "type": "Feature",
  "properties": {
    "addr:full":"15 rue Sainte-Gertrude 68920 Wettolsheim Wettolsheim Alsace 68920",
    "addr:housenumber":"15",
    "addr:postcode":"68920;68920",
    "addr:street":"Rue Sainte-Gertrude",
    "iso:country":"FR",
    "sg:address":"15 rue Sainte-Gertrude 68920 Wettolsheim",
    "sg:city":"Wettolsheim",
    "sg:classifiers":[
        {
            "category":"Wholesale",
            "subcategory":"Wine & Distilled Alcoholic Beverages",
            "type":"Manufacturing & Wholesale Goods"
        }
    ],
    "sg:phone":"+33 3 89 80 64 73",
    "sg:postcode":"68920",
    "sg:province":"Alsace",
    "sg:tags":[
        "french"
    ],
    "wof:name":"Buecher Paul Et Fils Sarl",
    "wof:placetype":"venue"
},
  "geometry": {"coordinates":[7.298272,48.059437],"type":"Point"}
}