{
  "type": "Feature",
  "properties": {
    "iso:country":"FR",
    "sg:address":"4, Place Jean Jaur\u00e8s, 91200 Athis Mons",
    "sg:orig_category":"Unclassifiable Establishments",
    "sg:phone":"+33 1 69 38 27 06",
    "sg:province":"Ile de France",
    "wof:name":"Seinet S.a.r.l.",
    "wof:placetype":"venue"
},
  "geometry": {"coordinates":[2.381793,48.692425],"type":"Point"}
}