{
  "type": "Feature",
  "properties": {
    "iso:country":"FR",
    "sg:address":"96",
    "sg:city":"Poincare; Paris; 75116",
    "sg:classifiers":[
        {
            "category":"Banks & Credit Unions",
            "subcategory":"Bank",
            "type":"Services"
        }
    ],
    "sg:phone":"+33 1 40 07 89 00",
    "sg:province":"Champagne",
    "wof:name":"Monte Paschi Banque",
    "wof:placetype":"venue"
},
  "geometry": {"coordinates":[2.285244,48.870701],"type":"Point"}
}