{
  "type": "Feature",
  "properties": {
    "iso:country":"FR",
    "sg:address":"B.P. 119, 90002 Belfort C\u00e9dex^^3, Av Trois ch\u00eanes, 90000 Belfort",
    "sg:orig_category":"Non-Classified Establishments",
    "sg:phone":"+33 3 84 55 61 61",
    "sg:postcode":"90000",
    "sg:province":"Franche Comt\u00e9",
    "wof:name":"Alstom Transport S.a.",
    "wof:placetype":"venue"
},
  "geometry": {"coordinates":[6.863753,47.639225],"type":"Point"}
}