{
  "type": "Feature",
  "properties": {
    "addr:full":"7 Rue Simone De Beauvoir 42270 St Priest En Jarez Rhone-Alpes 42270",
    "addr:housenumber":"7",
    "addr:postcode":"42270;42270",
    "addr:street":"Rue Simone De Beauvoir;Rhone-Alpes",
    "iso:country":"FR",
    "sg:address":"7 Rue Simone De Beauvoir 42270 St Priest En Jarez",
    "sg:classifiers":[
        {
            "category":"Utilities",
            "subcategory":"Telephone",
            "type":"Services"
        }
    ],
    "sg:phone":"+33 4 77 74 12 98",
    "sg:postcode":"42270",
    "sg:province":"Rhone-Alpes",
    "sg:tags":[
        "telecommunication"
    ],
    "wof:name":"Js Concept",
    "wof:placetype":"venue"
},
  "geometry": {"coordinates":[4.383844,45.478073],"type":"Point"}
}