{
  "type": "Feature",
  "properties": {
    "addr:full":"261, Rue de Paris - Immeuble le M\u00e9li\u00e8s, 93104 Montreuil C\u00e9dex Nord-Pas-de-Calais",
    "addr:housenumber":"261;immeuble",
    "addr:postcode":"93104",
    "addr:street":"Rue De Paris",
    "iso:country":"FR",
    "sg:address":"261, Rue de Paris - Immeuble le M\u00e9li\u00e8s, 93104 Montreuil C\u00e9dex",
    "sg:orig_category":"Non-Classified Establishments",
    "sg:phone":"+33 1 49 72 66 00",
    "sg:province":"Nord-Pas-de-Calais",
    "wof:name":"Postaxess S.a.",
    "wof:placetype":"venue"
},
  "geometry": {"coordinates":[1.757131,50.457104],"type":"Point"}
}