{
  "type": "Feature",
  "properties": {
    "addr:full":"RD 154 Medan Ile de France 78670",
    "addr:postcode":"78670",
    "addr:street":"Rd 154;Ile De France",
    "iso:country":"FR",
    "sg:address":"RD 154",
    "sg:city":"Medan",
    "sg:orig_category":"Unclassifiable Establishments",
    "sg:phone":"+33 1 39 08 04 45",
    "sg:postcode":"78670",
    "sg:province":"Ile de France",
    "wof:name":"Art Dimension S.a.r.l.",
    "wof:placetype":"venue"
},
  "geometry": {"coordinates":[1.998645,48.938606],"type":"Point"}
}