{
  "type": "Feature",
  "properties": {
    "addr:full":"20 Bis Rue Gay Lussac 94430 Chennevieres Sur Marne Ile de France 94430",
    "addr:housenumber":"20 bis",
    "addr:postcode":"94430;94430",
    "addr:street":"Rue Gay Lussac",
    "iso:country":"FR",
    "sg:address":"20 Bis Rue Gay Lussac 94430 Chennevieres Sur Marne",
    "sg:classifiers":[
        {
            "category":"Utilities",
            "subcategory":"Electric",
            "type":"Services"
        }
    ],
    "sg:phone":"+33 1 45 93 12 12",
    "sg:postcode":"94430",
    "sg:province":"Ile de France",
    "sg:tags":[
        "electricity",
        "electronic",
        "electrical",
        "equipment"
    ],
    "wof:name":"Ste Duval Messien",
    "wof:placetype":"venue"
},
  "geometry": {"coordinates":[2.54039,48.79636],"type":"Point"}
}