{
  "type": "Feature",
  "properties": {
    "addr:full":"33 Rue De La Haie Coq 93300 Aubervilliers Ile de France 93300",
    "addr:housenumber":"33",
    "addr:postcode":"93300;93300",
    "addr:street":"Rue De La Haie Coq",
    "iso:country":"FR",
    "sg:address":"33 Rue De La Haie Coq 93300 Aubervilliers",
    "sg:orig_category":"Miscellaneous Products",
    "sg:phone":"+33 1 43 52 37 88",
    "sg:postcode":"93300",
    "sg:province":"Ile de France",
    "wof:name":"Lingot Import Export Sarl",
    "wof:placetype":"venue"
},
  "geometry": {"coordinates":[2.373167,48.908669],"type":"Point"}
}