{
  "type": "Feature",
  "properties": {
    "addr:full":"Rue Gustave Eiffel - Parc des Chatelliers Orl\u00e9ans Centre 45000",
    "addr:postcode":"45000",
    "addr:street":"Rue Gustave Eiffel Parc Des Chatelliers",
    "iso:country":"FR",
    "sg:address":"Rue Gustave Eiffel - Parc des Chatelliers",
    "sg:city":"Orl\u00e9ans",
    "sg:orig_category":"Non-Classified Establishments",
    "sg:phone":"+33 2 38 22 12 12",
    "sg:postcode":"45000",
    "sg:province":"Centre",
    "wof:name":"Adem Etiquettes S.a.",
    "wof:placetype":"venue"
},
  "geometry": {"coordinates":[1.942975,47.922676],"type":"Point"}
}