{
  "type": "Feature",
  "properties": {
    "addr:full":"pl Cosnier; Bernay Champagne",
    "addr:street":"Pl Cosnier",
    "iso:country":"FR",
    "sg:address":"pl Cosnier; Bernay",
    "sg:classifiers":[
        {
            "category":"Banks & Credit Unions",
            "subcategory":"Bank",
            "type":"Services"
        }
    ],
    "sg:phone":"+33 32456025",
    "sg:province":"Champagne",
    "wof:name":"Cr\u00e9dit Agricole De L'eure",
    "wof:placetype":"venue"
},
  "geometry": {"coordinates":[0.591317,49.089123],"type":"Point"}
}