{
  "type": "Feature",
  "properties": {
    "addr:full":"1 Rue Charles Coulomb Zac De La Hazaie 22950 Tr\u00e9gueux Tr\u00e9gueux Bretagne 22950",
    "addr:housenumber":"1",
    "addr:postcode":"22950;22950",
    "addr:street":"Rue Charles Coulomb Zac De La Hazaie",
    "iso:country":"FR",
    "sg:address":"1 Rue Charles Coulomb Zac De La Hazaie 22950 Tr\u00e9gueux",
    "sg:city":"Tr\u00e9gueux",
    "sg:classifiers":[
        {
            "category":"Building & Trades",
            "subcategory":"Construction",
            "type":"Services"
        }
    ],
    "sg:phone":"+33 2 96 52 57 57",
    "sg:postcode":"22950",
    "sg:province":"Bretagne",
    "sg:tags":[
        "work",
        "public"
    ],
    "wof:name":"Scobat",
    "wof:placetype":"venue"
},
  "geometry": {"coordinates":[-2.736668,48.489059],"type":"Point"}
}