{
  "type": "Feature",
  "properties": {
    "addr:full":"B.P. 304, 26107 Romans sur Is\u00e8re C\u00e9dex^^All\u00e9e Pascal, 26100 Romans sur Is\u00e8re Rhone-Alpes",
    "addr:housenumber":"b.p. 304",
    "addr:postcode":"26107;26100",
    "addr:street":"Pascal",
    "iso:country":"FR",
    "sg:address":"B.P. 304, 26107 Romans sur Is\u00e8re C\u00e9dex^^All\u00e9e Pascal, 26100 Romans sur Is\u00e8re",
    "sg:orig_category":"Non-Classified Establishments",
    "sg:phone":"+33 4 75 72 38 00",
    "sg:province":"Rhone-Alpes",
    "wof:name":"Saunier Environnement S.a.",
    "wof:placetype":"venue"
},
  "geometry": {"coordinates":[5.049637,45.045036],"type":"Point"}
}