{
  "type": "Feature",
  "properties": {
    "iso:country":"FR",
    "sg:address":"3-5 rue Paul Dautier 78140 Velizy Villacoublay",
    "sg:classifiers":[
        {
            "category":"Banks & Credit Unions",
            "subcategory":"Investment Brokerage",
            "type":"Services"
        }
    ],
    "sg:phone":"+33 1 39 26 22 22",
    "sg:province":"Ile de France",
    "sg:tags":[
        "printing",
        "ink"
    ],
    "wof:name":"St\u00e9 Des Encres G Et P Brancher Fr\u00e8res Sa",
    "wof:placetype":"venue"
},
  "geometry": {"coordinates":[2.210288,48.780704],"type":"Point"}
}