{
  "type": "Feature",
  "properties": {
    "iso:country":"FR",
    "sg:address":"3, Rte de Besan\u00e7on - ZI la Louvi\u00e8re, 25480 Pirey",
    "sg:orig_category":"Unclassifiable Establishments",
    "sg:phone":"+33 3 81 53 65 10",
    "sg:province":"Franche Comt\u00e9",
    "wof:name":"E.t.i. Servicenter S.a.s.",
    "wof:placetype":"venue"
},
  "geometry": {"coordinates":[5.982078,47.27187],"type":"Point"}
}