{
  "type": "Feature",
  "properties": {
    "addr:full":"rue de Milan 44470 Thouare Sur Loire Pays de Loire 44470",
    "addr:postcode":"44470;44470",
    "addr:street":"Rue De Milan",
    "iso:country":"FR",
    "sg:address":"rue de Milan 44470 Thouare Sur Loire",
    "sg:classifiers":[
        {
            "category":"Banks & Credit Unions",
            "subcategory":"Investment Brokerage",
            "type":"Services"
        }
    ],
    "sg:phone":"+33 2 40 18 37 00",
    "sg:postcode":"44470",
    "sg:province":"Pays de Loire",
    "sg:tags":[
        "audio",
        "accessory"
    ],
    "wof:name":"Camac Sa",
    "wof:placetype":"venue"
},
  "geometry": {"coordinates":[-1.447783,47.283131],"type":"Point"}
}