{
  "type": "Feature",
  "properties": {
    "iso:country":"FR",
    "sg:address":"13 Avenue Du Cimetiere Parisien 93500 Pantin",
    "sg:orig_category":"Miscellaneous Products",
    "sg:phone":"+33 1 48 44 50 61",
    "sg:postcode":"93500",
    "sg:province":"Ile de France",
    "wof:name":"Etablissements Pierre",
    "wof:placetype":"venue"
},
  "geometry": {"coordinates":[2.399043,48.908516],"type":"Point"}
}