{
  "type": "Feature",
  "properties": {
    "addr:full":"1, Rte de Magny - ZI, 28120 Illiers Combray Magny Centre 28120",
    "addr:housenumber":"1",
    "addr:postcode":"28120;28120",
    "addr:street":"Rte De Magny Zi",
    "iso:country":"FR",
    "sg:address":"1, Rte de Magny - ZI, 28120 Illiers Combray",
    "sg:city":"Magny",
    "sg:orig_category":"Non-Classified Establishments",
    "sg:phone":"+33 2 37 91 65 70",
    "sg:postcode":"28120",
    "sg:province":"Centre",
    "wof:name":"Cabep S.c.a.",
    "wof:placetype":"venue"
},
  "geometry": {"coordinates":[1.215425,48.263744],"type":"Point"}
}