{
  "type": "Feature",
  "properties": {
    "addr:full":"1 Rue De L'Industrie 67118 Geispolsheim Alsace",
    "addr:housenumber":"1",
    "addr:postcode":"67118",
    "addr:street":"Rue De L'Industrie",
    "iso:country":"FR",
    "sg:address":"1 Rue De L'Industrie 67118 Geispolsheim",
    "sg:classifiers":[
        {
            "category":"Manufacturing",
            "subcategory":"Rubber & Plastics",
            "type":"Manufacturing & Wholesale Goods"
        }
    ],
    "sg:phone":"+33 3 88 66 03 12",
    "sg:province":"Alsace",
    "wof:name":"Tarifold",
    "wof:placetype":"venue"
},
  "geometry": {"coordinates":[7.685899,48.532497],"type":"Point"}
}