{
  "type": "Feature",
  "properties": {
    "addr:full":"Ramonde 09100 Pamiers Midi Pyr\u00e9n\u00e9es 09100",
    "addr:postcode":"09100;09100",
    "addr:street":"Ramonde",
    "iso:country":"FR",
    "sg:address":"Ramonde 09100 Pamiers",
    "sg:classifiers":[
        {
            "category":"Farming",
            "subcategory":"Livestock Farm",
            "type":"Manufacturing & Wholesale Goods"
        }
    ],
    "sg:phone":"+33 5 34 01 32 00",
    "sg:postcode":"09100",
    "sg:province":"Midi Pyr\u00e9n\u00e9es",
    "sg:tags":[
        "breeding",
        "agriculture",
        "animal"
    ],
    "wof:name":"Synergie",
    "wof:placetype":"venue"
},
  "geometry": {"coordinates":[1.6023,43.15234],"type":"Point"}
}