{
  "type": "Feature",
  "properties": {
    "iso:country":"FR",
    "sg:address":"55, Av. Louis Br\u00e9guet - B\u00e2t. Hermes, 31400 Toulouse",
    "sg:orig_category":"Non-Classified Establishments",
    "sg:phone":"+33 5 61 54 29 56",
    "sg:postcode":"31400",
    "sg:province":"Midi Pyr\u00e9n\u00e9es",
    "wof:name":"Cabinet Apports S.a.r.l.",
    "wof:placetype":"venue"
},
  "geometry": {"coordinates":[1.47942,43.57724],"type":"Point"}
}