{
  "type": "Feature",
  "properties": {
    "addr:full":"Rue de Montb\u00e9liard Bethoncourt Franche Comt\u00e9 25200",
    "addr:postcode":"25200",
    "addr:street":"Rue De Montbe\u0301Liard;Franche Comte\u0301",
    "iso:country":"FR",
    "sg:address":"Rue de Montb\u00e9liard",
    "sg:city":"Bethoncourt",
    "sg:orig_category":"Unclassifiable Establishments",
    "sg:phone":"+33 3 81 92 98 98",
    "sg:postcode":"25200",
    "sg:province":"Franche Comt\u00e9",
    "wof:name":"G.2.t. S.a.r.l. - G\u00e9n\u00e9rale Travaux Thermiques",
    "wof:placetype":"venue"
},
  "geometry": {"coordinates":[6.79767,47.521801],"type":"Point"}
}