{
  "type": "Feature",
  "properties": {
    "iso:country":"FR",
    "sg:address":"B.P. 126, 92124 Montrouge C\u00e9dex^^115, Av. Henri Ginioux, 92120 Montrouge",
    "sg:orig_category":"Non-Classified Establishments",
    "sg:phone":"+33 1 46 12 02 02",
    "sg:province":"Ile de France",
    "wof:name":"Multiphone S.a.",
    "wof:placetype":"venue"
},
  "geometry": {"coordinates":[2.320105,48.818424],"type":"Point"}
}