{
  "type": "Feature",
  "properties": {
    "addr:full":"170, Rue Etienne Lenoir, 30900 N\u00eemes Languedoc-Roussillon",
    "addr:housenumber":"170",
    "addr:postcode":"30900",
    "addr:street":"Rue Etienne Lenoir",
    "iso:country":"FR",
    "sg:address":"170, Rue Etienne Lenoir, 30900 N\u00eemes",
    "sg:orig_category":"Non-Classified Establishments",
    "sg:phone":"+33 4 66 29 70 10",
    "sg:province":"Languedoc-Roussillon",
    "wof:name":"Michel Vabre S.a.r.l.",
    "wof:placetype":"venue"
},
  "geometry": {"coordinates":[4.3386,43.810425],"type":"Point"}
}