{
  "type": "Feature",
  "properties": {
    "iso:country":"FR",
    "sg:address":"B.P. 10166, 95702 Roissy Charles de Gaulle C\u00e9dex^^Lomede Fr\u00eat 2 - B\u00e2timent 3702, 95700 Roissy en Fra",
    "sg:orig_category":"Non-Classified Establishments",
    "sg:phone":"+33 1 48 64 20 17",
    "sg:postcode":"95700",
    "sg:province":"Ile de France",
    "wof:name":"Adia",
    "wof:placetype":"venue"
},
  "geometry": {"coordinates":[2.517005,49.003883],"type":"Point"}
}