{
  "type": "Feature",
  "properties": {
    "addr:full":"23, Rue du Coeur Joyeux, 59160 Lomme Nord Pas-de-Calais",
    "addr:housenumber":"23",
    "addr:postcode":"59160",
    "addr:street":"Rue Du Coeur Joyeux",
    "iso:country":"FR",
    "sg:address":"23, Rue du Coeur Joyeux, 59160 Lomme",
    "sg:orig_category":"Unclassifiable Establishments",
    "sg:phone":"+33 3 20 92 09 93",
    "sg:province":"Nord Pas-de-Calais",
    "wof:name":"Nord Maintenance Industrie S.a.r.l.",
    "wof:placetype":"venue"
},
  "geometry": {"coordinates":[3.015732,50.641247],"type":"Point"}
}