{
  "type": "Feature",
  "properties": {
    "iso:country":"FR",
    "sg:address":"102, Rue Camille Desmoulins, 92136 Issy les Moulineaux C\u00e9dex",
    "sg:orig_category":"Non-Classified Establishments",
    "sg:phone":"+33 1 41 08 31 00",
    "sg:province":"\u00cele-de-France",
    "wof:name":"Sopac R\u00e9novation S.n.c.",
    "wof:placetype":"venue"
},
  "geometry": {"coordinates":[2.260867,48.827477],"type":"Point"}
}