{
  "type": "Feature",
  "properties": {
    "addr:full":"B.P. 17 Moirans^^Le Pommarin 38430 Moirans Rhone-Alpes 38430",
    "addr:postcode":"38430;38430",
    "addr:street":"B.P. 17 Moirans^^Le Pommarin",
    "iso:country":"FR",
    "sg:address":"B.P. 17",
    "sg:city":"Moirans^^Le Pommarin 38430 Moirans",
    "sg:orig_category":"Non-Classified Establishments",
    "sg:phone":"+33 4 76 35 79 00",
    "sg:postcode":"38430",
    "sg:province":"Rhone-Alpes",
    "wof:name":"Hutchinson - Dept Fit Profiles S.n.c.",
    "wof:placetype":"venue"
},
  "geometry": {"coordinates":[5.554805,45.327175],"type":"Point"}
}