{
  "type": "Feature",
  "properties": {
    "addr:full":"22 Rue De Montmorency 75003 Paris Ile de France 75003",
    "addr:housenumber":"22",
    "addr:postcode":"75003;75003",
    "addr:street":"Rue De Montmorency",
    "iso:country":"FR",
    "sg:address":"22 Rue De Montmorency 75003 Paris",
    "sg:classifiers":[
        {
            "category":"Health Services",
            "subcategory":"Optometrist",
            "type":"Services"
        }
    ],
    "sg:phone":"+33 1 44 78 31 00",
    "sg:postcode":"75003",
    "sg:province":"Ile de France",
    "sg:tags":[
        "instrument",
        "optical",
        "-",
        "precision",
        "equipment"
    ],
    "wof:name":"Bbgr Sa",
    "wof:placetype":"venue"
},
  "geometry": {"coordinates":[2.355633,48.863068],"type":"Point"}
}