{
  "type": "Feature",
  "properties": {
    "addr:full":"729, Rue de la Croix Verte - Parc Eurom\u00e9decine, 34000 Montpellier Languedoc-Roussillon",
    "addr:housenumber":"729",
    "addr:postcode":"34000",
    "addr:street":"Rue De La Croix Verte Parc Eurome\u0301Decine",
    "iso:country":"FR",
    "sg:address":"729, Rue de la Croix Verte - Parc Eurom\u00e9decine, 34000 Montpellier",
    "sg:orig_category":"Unclassifiable Establishments",
    "sg:phone":"+33 4 67 04 73 00",
    "sg:province":"Languedoc-Roussillon",
    "wof:name":"Caisse D'epargne Languedoc Roussillon",
    "wof:placetype":"venue"
},
  "geometry": {"coordinates":[3.841721,43.644878],"type":"Point"}
}