{
  "type": "Feature",
  "properties": {
    "addr:full":"52140 Sarrey Champagne",
    "addr:postcode":"52140",
    "iso:country":"FR",
    "sg:address":"52140 Sarrey",
    "sg:orig_category":"Non-Classified Establishments",
    "sg:phone":"+33 3 25 90 35 90",
    "sg:province":"Champagne",
    "wof:name":"Sanichro S.a.r.l.",
    "wof:placetype":"venue"
},
  "geometry": {"coordinates":[5.426577,48.003647],"type":"Point"}
}