{
  "type": "Feature",
  "properties": {
    "addr:full":"9, Rue du Mar\u00e9chal Leclerc, 28600 Luisant Luisant Centre 28600",
    "addr:housenumber":"9",
    "addr:postcode":"28600;28600",
    "addr:street":"Rue Du Mare\u0301Chal Leclerc",
    "iso:country":"FR",
    "sg:address":"9, Rue du Mar\u00e9chal Leclerc, 28600 Luisant",
    "sg:city":"Luisant",
    "sg:orig_category":"Unclassifiable Establishments",
    "sg:phone":"+33 2 37 24 48 03",
    "sg:postcode":"28600",
    "sg:province":"Centre",
    "wof:name":"Imprimerie Durand S.a.",
    "wof:placetype":"venue"
},
  "geometry": {"coordinates":[1.459504,48.42765],"type":"Point"}
}