{
  "type": "Feature",
  "properties": {
    "iso:country":"FR",
    "sg:address":"Rue Francisco Ferrer - ZI Nord",
    "sg:city":"Limoges",
    "sg:orig_category":"Unclassifiable Establishments",
    "sg:phone":"+33 5 55 11 31 90",
    "sg:postcode":"87280",
    "sg:province":"Limousin",
    "wof:name":"G.p. Gaz S.n.c.",
    "wof:placetype":"venue"
},
  "geometry": {"coordinates":[1.299435,45.914837],"type":"Point"}
}