{
  "type": "Feature",
  "properties": {
    "iso:country":"FR",
    "sg:address":"Rue Emile Zola - ZA de l'Agavon",
    "sg:city":"Les Pennes Mirabeau",
    "sg:orig_category":"Unclassifiable Establishments",
    "sg:phone":"+33 4 42 02 58 88",
    "sg:postcode":"13170",
    "sg:province":"Poitou-Charentes",
    "wof:name":"Forb\u00e9ton Sud S.a.",
    "wof:placetype":"venue"
},
  "geometry": {"coordinates":[5.282638,43.417511],"type":"Point"}
}