{
  "type": "Feature",
  "properties": {
    "iso:country":"FR",
    "sg:address":"B.P. 181",
    "sg:city":"Auch C\u00e9dex",
    "sg:orig_category":"Non-Classified Establishments",
    "sg:phone":"+33 5 62 61 62 61",
    "sg:postcode":"32004",
    "sg:province":"Midi Pyr\u00e9n\u00e9es",
    "wof:name":"C.c.i. D'auch Et Du Gers En Gascogne - Chambre De Commerce Et D'industrie Du Gers",
    "wof:placetype":"venue"
},
  "geometry": {"coordinates":[-96.824448,37.166721],"type":"Point"}
}