{
  "type": "Feature",
  "properties": {
    "iso:country":"FR",
    "sg:address":"B.P. 206, 22192 Pl\u00e9rin C\u00e9dex^^41, Rue du Vieux Moulin - Port du L\u00e9gu\u00e9 , 22190 Pl\u00e9rin",
    "sg:city":"Pl\u00e9rin",
    "sg:orig_category":"Non-Classified Establishments",
    "sg:phone":"+33 2 96 60 88 00",
    "sg:postcode":"22190",
    "sg:province":"Bretagne",
    "wof:name":"Cars Rouillard S.a.",
    "wof:placetype":"venue"
},
  "geometry": {"coordinates":[-2.746364,48.524429],"type":"Point"}
}