{
  "type": "Feature",
  "properties": {
    "iso:country":"FR",
    "sg:address":"168, Av. des Aur\u00e9ats, 26000 Valence",
    "sg:orig_category":"Non-Classified Establishments",
    "sg:phone":"+33 4 75 44 08 82",
    "sg:postcode":"26000",
    "sg:province":"Rhone-Alpes",
    "wof:name":"Bacou S.a.",
    "wof:placetype":"venue"
},
  "geometry": {"coordinates":[4.884321,44.892139],"type":"Point"}
}