{
  "type": "Feature",
  "properties": {
    "iso:country":"FR",
    "sg:address":"164 Bis, Rte Nationale - Kerjoly , 22530 M\u00fbr de Bretagne",
    "sg:city":"Caurel",
    "sg:orig_category":"Non-Classified Establishments",
    "sg:phone":"+33 2 96 28 54 87",
    "sg:postcode":"22530",
    "sg:province":"Bretagne",
    "wof:name":"Charcuterie Bretonne Senan S.a.",
    "wof:placetype":"venue"
},
  "geometry": {"coordinates":[-2.92285,48.178635],"type":"Point"}
}