{
  "type": "Feature",
  "properties": {
    "iso:country":"FR",
    "sg:address":"1572, Rte de Guise, 02100 Saint Quentin",
    "sg:orig_category":"Unclassifiable Establishments",
    "sg:phone":"+33 3 23 50 70 00",
    "sg:province":"Picardie",
    "wof:name":"Ge Power Controls France S.a.s.",
    "wof:placetype":"venue"
},
  "geometry": {"coordinates":[3.31678,49.84079],"type":"Point"}
}