{
  "type": "Feature",
  "properties": {
    "iso:country":"FR",
    "sg:address":"75, Rue Deleuvre, 69317 Lyon C\u00e9dex 04",
    "sg:orig_category":"Non-Classified Establishments",
    "sg:phone":"+33 4 72 10 94 94",
    "sg:province":"Haute Normandie",
    "wof:name":"Union R\u00e9gionale Coop\u00e9rative Vente De Lait",
    "wof:placetype":"venue"
},
  "geometry": {"coordinates":[4.825015,45.782192],"type":"Point"}
}