{
  "type": "Feature",
  "properties": {
    "addr:full":"rue Alain Colas 29200 Brest Brest Bretagne 29200",
    "addr:postcode":"29200;29200",
    "addr:street":"Rue Alain Colas",
    "iso:country":"FR",
    "sg:address":"rue Alain Colas 29200 Brest",
    "sg:city":"Brest",
    "sg:classifiers":[
        {
            "category":"Professional",
            "subcategory":"Detective & Security Services",
            "type":"Services"
        }
    ],
    "sg:phone":"+33 2 98 33 10 10",
    "sg:postcode":"29200",
    "sg:province":"Bretagne",
    "sg:tags":[
        "project",
        "environmental",
        "planning",
        "protection"
    ],
    "wof:name":"C.e.d.r.e. Ass Loi 1901",
    "wof:placetype":"venue"
},
  "geometry": {"coordinates":[-4.435931,48.391033],"type":"Point"}
}