{
  "type": "Feature",
  "properties": {
    "addr:full":"4 rue de la Marne; Moyeuvre Grande; 57250 Lorraine 57250",
    "addr:housenumber":"4",
    "addr:postcode":"57250;57250",
    "addr:street":"Rue De La Marne Moyeuvre Grande",
    "iso:country":"FR",
    "sg:address":"4 rue de la Marne; Moyeuvre Grande; 57250",
    "sg:classifiers":[
        {
            "category":"Banks & Credit Unions",
            "subcategory":"Bank",
            "type":"Services"
        }
    ],
    "sg:phone":"+33 3387671105",
    "sg:postcode":"57250",
    "sg:province":"Lorraine",
    "wof:name":"Soci\u00e9t\u00e9 G\u00e9n\u00e9rale",
    "wof:placetype":"venue"
},
  "geometry": {"coordinates":[6.044123,49.251686],"type":"Point"}
}