{
  "type": "Feature",
  "properties": {
    "iso:country":"FR",
    "sg:address":"65 Avenue D Orleans 45190 Beaugency",
    "sg:city":"Beaugency",
    "sg:classifiers":[
        {
            "category":"Wholesale",
            "subcategory":"Medical Equipment & Supplies",
            "type":"Manufacturing & Wholesale Goods"
        }
    ],
    "sg:phone":"+33 2 38 46 43 39",
    "sg:postcode":"45190",
    "sg:province":"Centre",
    "sg:tags":[
        "instrument",
        "health",
        "-",
        "precision"
    ],
    "wof:name":"Apphex",
    "wof:placetype":"venue"
},
  "geometry": {"coordinates":[1.638798,47.786285],"type":"Point"}
}