{
  "type": "Feature",
  "properties": {
    "addr:full":"100 Rue Mine 54970 Landres Lorraine",
    "addr:housenumber":"100",
    "addr:postcode":"54970",
    "addr:street":"Rue Mine",
    "iso:country":"FR",
    "sg:address":"100 Rue Mine 54970 Landres",
    "sg:classifiers":[
        {
            "category":"Professional",
            "type":"Services"
        }
    ],
    "sg:phone":"+33 3 82 21 71 79",
    "sg:province":"Lorraine",
    "sg:tags":[
        "transport",
        "road"
    ],
    "wof:name":"Lts Suk Sarl",
    "wof:placetype":"venue"
},
  "geometry": {"coordinates":[5.794724,49.312893],"type":"Point"}
}