{
  "type": "Feature",
  "properties": {
    "addr:full":"87, Bd Louis Botinelly, 13004 Marseille Poitou-Charentes",
    "addr:housenumber":"87",
    "addr:postcode":"13004",
    "addr:street":"Bd Louis Botinelly",
    "iso:country":"FR",
    "sg:address":"87, Bd Louis Botinelly, 13004 Marseille",
    "sg:orig_category":"Non-Classified Establishments",
    "sg:phone":"+33 4 91 49 13 33",
    "sg:province":"Poitou-Charentes",
    "wof:name":"C.t.s. S.a. - Cin\u00e9ma T\u00e9lec Service",
    "wof:placetype":"venue"
},
  "geometry": {"coordinates":[5.405716,43.298325],"type":"Point"}
}