{
  "type": "Feature",
  "properties": {
    "iso:country":"FR",
    "sg:address":"8 Avenue Charles De Gaulle 28190 Pontgouin",
    "sg:city":"Pontgouin",
    "sg:classifiers":[
        {
            "category":"Building & Trades",
            "subcategory":"Electrical",
            "type":"Services"
        }
    ],
    "sg:phone":"+33 2 37 37 40 93",
    "sg:postcode":"28190",
    "sg:province":"Centre",
    "sg:tags":[
        "electronic",
        "lighting",
        "equipment"
    ],
    "wof:name":"Lum'art",
    "wof:placetype":"venue"
},
  "geometry": {"coordinates":[1.173634,48.478901],"type":"Point"}
}