{
  "type": "Feature",
  "properties": {
    "addr:full":"Le Bourg 22250 Lanrelas Lanrelas Bretagne 22250",
    "addr:postcode":"22250;22250",
    "addr:street":"Le Bourg;Lanrelas",
    "iso:country":"FR",
    "sg:address":"Le Bourg 22250 Lanrelas",
    "sg:city":"Lanrelas",
    "sg:orig_category":"Miscellaneous Products",
    "sg:phone":"+33 2 96 86 63 12",
    "sg:postcode":"22250",
    "sg:province":"Bretagne",
    "wof:name":"Houel Sa",
    "wof:placetype":"venue"
},
  "geometry": {"coordinates":[-2.294449,48.249092],"type":"Point"}
}