{
  "type": "Feature",
  "properties": {
    "addr:full":"2 Rue Pascal Zi Sud 77100 Meaux Ile de France 77100",
    "addr:housenumber":"2",
    "addr:postcode":"77100;ile;77100",
    "addr:street":"Rue Pascal Zi Sud;France",
    "iso:country":"FR",
    "sg:address":"2 Rue Pascal Zi Sud 77100 Meaux",
    "sg:classifiers":[
        {
            "category":"Utilities",
            "subcategory":"Recycling",
            "type":"Services"
        }
    ],
    "sg:phone":"+33 1 64 34 31 09",
    "sg:postcode":"77100",
    "sg:province":"Ile de France",
    "sg:tags":[
        "product",
        "good",
        "-",
        "miscellaneous",
        "metallic",
        "metallurgy",
        "metalworking",
        "finished"
    ],
    "wof:name":"Usines Albert Bieth Et Fils",
    "wof:placetype":"venue"
},
  "geometry": {"coordinates":[2.883054,48.959351],"type":"Point"}
}