{
  "type": "Feature",
  "properties": {
    "iso:country":"FR",
    "sg:address":"B.P. 119, 62230 Outreau^^Rue Pierre Curie, 62230 Outreau",
    "sg:orig_category":"Non-Classified Establishments",
    "sg:phone":"+33 3 21 99 53 00",
    "sg:province":"Nord Pas-de-Calais",
    "wof:name":"Manoir Industries S.a.",
    "wof:placetype":"venue"
},
  "geometry": {"coordinates":[1.596139,50.703754],"type":"Point"}
}