{
  "type": "Feature",
  "properties": {
    "iso:country":"FR",
    "sg:address":"29, Rue Arago, 92800 Puteaux",
    "sg:orig_category":"Non-Classified Establishments",
    "sg:phone":"+33 1 47 73 93 63",
    "sg:postcode":"92800",
    "sg:province":"Ile de France",
    "wof:name":"Bathroom Graffiti S.a.",
    "wof:placetype":"venue"
},
  "geometry": {"coordinates":[2.245975,48.8848],"type":"Point"}
}