{
  "type": "Feature",
  "properties": {
    "addr:full":"19 Quartier Fabrique 59142 Villers Outr\u00e9aux Nord Pas-de-Calais 59142",
    "addr:housenumber":"19",
    "addr:postcode":"59142;59142",
    "addr:street":"Quartier Fabrique;Pas-De-Calais",
    "iso:country":"FR",
    "sg:address":"19 Quartier Fabrique 59142 Villers Outr\u00e9aux",
    "sg:classifiers":[
        {
            "category":"Shopping",
            "subcategory":"Crafts & Fabrics",
            "type":"Retail Goods"
        }
    ],
    "sg:phone":"+33 3 27 82 01 82",
    "sg:postcode":"59142",
    "sg:province":"Nord Pas-de-Calais",
    "sg:tags":[
        "textile",
        "linen",
        "clothing"
    ],
    "wof:name":"Lamouret Emile Sa",
    "wof:placetype":"venue"
},
  "geometry": {"coordinates":[3.298357,50.032337],"type":"Point"}
}