{
  "type": "Feature",
  "properties": {
    "iso:country":"FR",
    "sg:address":"91042 Evry C\u00e9dex^^98, All\u00e9e des Champs Elys\u00e9es, 91000 Evry",
    "sg:orig_category":"Non-Classified Establishments",
    "sg:phone":"+33 1 60 78 54 44",
    "sg:province":"Ile de France",
    "wof:name":"Ile De France Courses S.a.r.l.",
    "wof:placetype":"venue"
},
  "geometry": {"coordinates":[2.4293,48.624664],"type":"Point"}
}