{
  "type": "Feature",
  "properties": {
    "iso:country":"FR",
    "sg:address":"Route De Lieme Zi 39570 Perrigny",
    "sg:classifiers":[
        {
            "category":"Food Court",
            "type":"Food & Drink"
        }
    ],
    "sg:phone":"+33 3 84 47 20 91",
    "sg:postcode":"39570",
    "sg:province":"Franche Comt\u00e9",
    "sg:tags":[
        "product",
        "related"
    ],
    "wof:name":"Etablissements Yves Jacquier Anciens Etss Pianet Rousset",
    "wof:placetype":"venue"
},
  "geometry": {"coordinates":[5.516002,46.599735],"type":"Point"}
}