{
  "type": "Feature",
  "properties": {
    "addr:full":"28 Bd Gambetta 94130 Nogent Sur Marne Ile de France 94130",
    "addr:housenumber":"28",
    "addr:postcode":"94130;94130",
    "addr:street":"Bd Gambetta",
    "iso:country":"FR",
    "sg:address":"28 Bd Gambetta 94130 Nogent Sur Marne",
    "sg:classifiers":[
        {
            "category":"Professional",
            "subcategory":"Business Services",
            "type":"Services"
        }
    ],
    "sg:phone":"+33 1 48 73 76 46",
    "sg:postcode":"94130",
    "sg:province":"Ile de France",
    "sg:tags":[
        "training",
        "advice"
    ],
    "wof:name":"Ecole College Lycee Prives Montalembert",
    "wof:placetype":"venue"
},
  "geometry": {"coordinates":[2.47142,48.838165],"type":"Point"}
}