{
  "type": "Feature",
  "properties": {
    "iso:country":"FR",
    "sg:address":"30 Rue De Blois 45130 Meung Sur Loire",
    "sg:city":"Baule",
    "sg:classifiers":[
        {
            "category":"Manufacturing",
            "subcategory":"Tools & Machinery",
            "type":"Manufacturing & Wholesale Goods"
        }
    ],
    "sg:phone":"+33 2 38 46 93 30",
    "sg:postcode":"45130",
    "sg:province":"Centre",
    "sg:tags":[
        "metallurgy",
        "metalworking"
    ],
    "wof:name":"Vm Sa",
    "wof:placetype":"venue"
},
  "geometry": {"coordinates":[1.69272,47.828094],"type":"Point"}
}