{
  "type": "Feature",
  "properties": {
    "addr:full":"34 - 4, Rue Henri Regnault - Courbevoie , 92068 Paris la D\u00e9fense Picardie",
    "addr:housenumber":"4",
    "addr:postcode":"92068",
    "addr:street":"34;Rue Henri Regnault",
    "iso:country":"FR",
    "sg:address":"34 - 4, Rue Henri Regnault - Courbevoie , 92068 Paris la D\u00e9fense",
    "sg:orig_category":"Unclassifiable Establishments",
    "sg:phone":"+33 1 41 02 20 00",
    "sg:province":"Picardie",
    "wof:name":"E.d.f. Et Gaz De France",
    "wof:placetype":"venue"
},
  "geometry": {"coordinates":[2.24119,48.888939],"type":"Point"}
}