{
  "type": "Feature",
  "properties": {
    "iso:country":"FR",
    "sg:address":"B.P. 116, 91944 Coutaboeuf C\u00e9dex^^10, Av. du Qu\u00e9bec, 91140 Villebon sur Yvette",
    "sg:orig_category":"Non-Classified Establishments",
    "sg:phone":"+33 1 60 92 41 66",
    "sg:province":"Ile de France",
    "wof:name":"Mehrtech S.a.r.l.",
    "wof:placetype":"venue"
},
  "geometry": {"coordinates":[2.227225,48.700069],"type":"Point"}
}