{
  "type": "Feature",
  "properties": {
    "addr:full":"18, Rue Jean Errard, 55000 Bar le Duc Lorraine",
    "addr:housenumber":"18",
    "addr:postcode":"55000",
    "addr:street":"Rue Jean Errard;Le Duc",
    "iso:country":"FR",
    "sg:address":"18, Rue Jean Errard, 55000 Bar le Duc",
    "sg:orig_category":"Unclassifiable Establishments",
    "sg:phone":"+33 3 29 79 35 24",
    "sg:province":"Lorraine",
    "wof:name":"No.so.co.ba. S.a. - Nouvelle Soci\u00e9t\u00e9 De Confection Du Barrois",
    "wof:placetype":"venue"
},
  "geometry": {"coordinates":[5.157428,48.772724],"type":"Point"}
}