{
  "type": "Feature",
  "properties": {
    "addr:full":"14 Rue Des Jardins 70800 St Loup Sur Semouse Franche Comt\u00e9 70800",
    "addr:housenumber":"14",
    "addr:postcode":"70800;70800",
    "addr:street":"Rue Des Jardins;Franche Comte\u0301",
    "iso:country":"FR",
    "sg:address":"14 Rue Des Jardins 70800 St Loup Sur Semouse",
    "sg:classifiers":[
        {
            "category":"Home & Garden",
            "subcategory":"Furniture",
            "type":"Retail Goods"
        }
    ],
    "sg:phone":"+33 3 84 94 18 03",
    "sg:postcode":"70800",
    "sg:province":"Franche Comt\u00e9",
    "sg:tags":[
        "household",
        "wood"
    ],
    "wof:name":"Meubles D'art Lagrange",
    "wof:placetype":"venue"
},
  "geometry": {"coordinates":[6.271867,47.887222],"type":"Point"}
}