{
  "type": "Feature",
  "properties": {
    "iso:country":"FR",
    "sg:address":"3, Rue Barb\u00e8s, 71300 Montceau les Mines",
    "sg:city":"Saint-Berain-sous-Sanvignes",
    "sg:orig_category":"Unclassifiable Establishments",
    "sg:phone":"+33 3 85 57 23 23",
    "sg:postcode":"71300",
    "sg:province":"Bourgogne",
    "wof:name":"A.2c.i. S.a.r.l. - Assistance Et Conseil Conception Industriel",
    "wof:placetype":"venue"
},
  "geometry": {"coordinates":[4.36559,46.669109],"type":"Point"}
}