{
  "type": "Feature",
  "properties": {
    "addr:full":"2, All\u00e9e des Grandes Pi\u00e8ces, 91214 Draveil C\u00e9dex Haute Normandie",
    "addr:housenumber":"2",
    "addr:postcode":"91214",
    "addr:street":"Alle\u0301E Des Grandes Pie\u0300Ces;Haute Normandie",
    "iso:country":"FR",
    "sg:address":"2, All\u00e9e des Grandes Pi\u00e8ces, 91214 Draveil C\u00e9dex",
    "sg:orig_category":"Non-Classified Establishments",
    "sg:phone":"+33 1 69 42 42 03",
    "sg:province":"Haute Normandie",
    "wof:name":"Genetier S.a.",
    "wof:placetype":"venue"
},
  "geometry": {"coordinates":[-118.24550600000001,34.23122],"type":"Point"}
}