{
  "type": "Feature",
  "properties": {
    "addr:full":"Rte De Chateauroux 36230 Neuvy Saint Sepulchre Saint-Denis-de-Jouhet Centre 36230",
    "addr:housenumber":"saint-denis-de-jouhet",
    "addr:postcode":"36230;sepulchre;36230",
    "addr:street":"Rte De Chateauroux",
    "iso:country":"FR",
    "sg:address":"Rte De Chateauroux 36230 Neuvy Saint Sepulchre",
    "sg:city":"Saint-Denis-de-Jouhet",
    "sg:classifiers":[
        {
            "category":"Building & Trades",
            "subcategory":"Construction",
            "type":"Services"
        }
    ],
    "sg:phone":"+33 2 54 06 17 00",
    "sg:postcode":"36230",
    "sg:province":"Centre",
    "sg:tags":[
        "electric",
        "-",
        "component",
        "equipment",
        "engineering",
        "electrical",
        "mechanical",
        "electronic",
        "mach"
    ],
    "wof:name":"Neuvy Motors S.a.",
    "wof:placetype":"venue"
},
  "geometry": {"coordinates":[1.867975,46.530304],"type":"Point"}
}