{
  "type": "Feature",
  "properties": {
    "iso:country":"FR",
    "sg:address":"1, Rue de Gourville, 45140 Ormes",
    "sg:city":"Ingr\u00e9",
    "sg:orig_category":"Unclassifiable Establishments",
    "sg:phone":"+33 2 38 74 77 33",
    "sg:postcode":"45140",
    "sg:province":"Centre",
    "wof:name":"Quadrilaser S.a.",
    "wof:placetype":"venue"
},
  "geometry": {"coordinates":[1.8166,47.943138],"type":"Point"}
}