{
  "type": "Feature",
  "properties": {
    "iso:country":"FR",
    "sg:address":"1, Rue Paul Braux, 02290 Vic sur Aisne",
    "sg:orig_category":"Unclassifiable Establishments",
    "sg:phone":"+33 3 23 55 55 77",
    "sg:province":"Picardie",
    "wof:name":"Routi\u00e8re Morin S.a.",
    "wof:placetype":"venue"
},
  "geometry": {"coordinates":[3.110767,49.403008],"type":"Point"}
}