{
  "type": "Feature",
  "properties": {
    "addr:full":"33480 Avensan Avensan Aquitaine 33480",
    "addr:postcode":"33480;33480",
    "iso:country":"FR",
    "sg:address":"33480 Avensan",
    "sg:city":"Avensan",
    "sg:orig_category":"Unclassifiable Establishments",
    "sg:phone":"+33 5 56 58 21 01",
    "sg:postcode":"33480",
    "sg:province":"Aquitaine",
    "wof:name":"Ch\u00e2teau Citran M\u00e9doc S.a.",
    "wof:placetype":"venue"
},
  "geometry": {"coordinates":[-0.757418,45.034893],"type":"Point"}
}