{
  "type": "Feature",
  "properties": {
    "addr:full":"Rue C\u00e9sar Jeoffray 19100 Brive La Gaillarde Limousin 19100",
    "addr:postcode":"19100;19100",
    "addr:street":"Rue Ce\u0301Sar Jeoffray",
    "iso:country":"FR",
    "sg:address":"Rue C\u00e9sar Jeoffray 19100 Brive La Gaillarde",
    "sg:classifiers":[
        {
            "category":"Shopping",
            "type":"Retail Goods"
        }
    ],
    "sg:phone":"+33 5 55 87 50 51",
    "sg:postcode":"19100",
    "sg:province":"Limousin",
    "sg:tags":[
        "metallurgy",
        "finished",
        "-",
        "metalworking",
        "metallic"
    ],
    "wof:name":"Mecanique Generale Du Prieur",
    "wof:placetype":"venue"
},
  "geometry": {"coordinates":[1.507865,45.156158],"type":"Point"}
}