{
  "type": "Feature",
  "properties": {
    "addr:full":"Zi Du Vernay 73460 Ste H\u00e9l\u00e8ne Sr Is\u00e8re Rhone-Alpes 73460",
    "addr:postcode":"73460;73460",
    "addr:street":"Zi Du Vernay;He\u0301Le\u0300Ne Sr Ise\u0300Re Rhone-Alpes",
    "iso:country":"FR",
    "sg:address":"Zi Du Vernay 73460 Ste H\u00e9l\u00e8ne Sr Is\u00e8re",
    "sg:classifiers":[
        {
            "category":"Social Services",
            "subcategory":"Job Training",
            "type":"Services"
        }
    ],
    "sg:phone":"+33 4 79 38 44 42",
    "sg:postcode":"73460",
    "sg:province":"Rhone-Alpes",
    "sg:tags":[
        "good",
        "business",
        "advice",
        "-",
        "metalworking",
        "metallic",
        "metallurgy",
        "finished"
    ],
    "wof:name":"Bordas Ercem Industries",
    "wof:placetype":"venue"
},
  "geometry": {"coordinates":[6.317803,45.614742],"type":"Point"}
}