{
  "type": "Feature",
  "properties": {
    "addr:full":"2 Rue Jules Verne Zi St Cosme 37520 La Riche La Riche Centre 37520",
    "addr:housenumber":"2",
    "addr:postcode":"37520;37520",
    "addr:street":"Rue Jules Verne Zi St",
    "iso:country":"FR",
    "sg:address":"2 Rue Jules Verne Zi St Cosme 37520 La Riche",
    "sg:city":"La Riche",
    "sg:classifiers":[
        {
            "category":"Banks & Credit Unions",
            "subcategory":"Investment Brokerage",
            "type":"Services"
        }
    ],
    "sg:phone":"+33 2 47 37 21 21",
    "sg:postcode":"37520",
    "sg:province":"Centre",
    "sg:tags":[
        "-",
        "transport",
        "related"
    ],
    "wof:name":"Mory Logidis Touraine",
    "wof:placetype":"venue"
},
  "geometry": {"coordinates":[0.66471,47.390419],"type":"Point"}
}