{
  "type": "Feature",
  "properties": {
    "iso:country":"FR",
    "sg:address":"22 Avenue Stroh 59440 Avesnes Sur Helpe",
    "sg:classifiers":[
        {
            "category":"Manufacturing",
            "subcategory":"Rubber & Plastics",
            "type":"Manufacturing & Wholesale Goods"
        }
    ],
    "sg:phone":"+33 3 27 61 22 36",
    "sg:province":"Nord Pas-de-Calais",
    "wof:name":"Societe Industrielle Des Plastiques D'avesnes (sipa)",
    "wof:placetype":"venue"
},
  "geometry": {"coordinates":[3.936867,50.128696],"type":"Point"}
}