{
  "type": "Feature",
  "properties": {
    "iso:country":"FR",
    "sg:address":"B.P. 2, 06371 Mouans Sartoux C\u00e9dex^^Z.I. du Tiragon, 06370 Mouans Sartoux",
    "sg:orig_category":"Non-Classified Establishments",
    "sg:phone":"+33 4 92 92 59 25",
    "wof:name":"S\u00e9palumic",
    "wof:placetype":"venue"
},
  "geometry": {"coordinates":[6.96621,43.618511],"type":"Point"}
}