{
  "type": "Feature",
  "properties": {
    "iso:country":"FR",
    "sg:address":"16, All\u00e9e Claude Rouget de Lisle, 44800 Saint Herblain",
    "sg:orig_category":"Non-Classified Establishments",
    "sg:phone":"+33 2 40 46 31 32",
    "sg:province":"Pays de Loire",
    "wof:name":"Nord R\u00e9ducteurs S.a.r.l.",
    "wof:placetype":"venue"
},
  "geometry": {"coordinates":[-1.608967,47.231911],"type":"Point"}
}