{
  "type": "Feature",
  "properties": {
    "addr:full":"2, Rue de Limacon, 41190 Herbault Herbault Centre 41190",
    "addr:housenumber":"2;herbault",
    "addr:postcode":"41190;41190",
    "addr:street":"Rue De Limacon",
    "iso:country":"FR",
    "sg:address":"2, Rue de Limacon, 41190 Herbault",
    "sg:city":"Herbault",
    "sg:orig_category":"Unclassifiable Establishments",
    "sg:phone":"+33 2 54 46 11 84",
    "sg:postcode":"41190",
    "sg:province":"Centre",
    "wof:name":"Entreprise Lardillier Dabin S.a.r.l.",
    "wof:placetype":"venue"
},
  "geometry": {"coordinates":[1.14452,47.609791],"type":"Point"}
}