{
  "type": "Feature",
  "properties": {
    "addr:full":"66 rue de la Chauss\u00e9e d'Antin 75009 Paris Ile de France 75009",
    "addr:housenumber":"66",
    "addr:postcode":"75009;75009",
    "addr:street":"Rue De La Chausse\u0301E D'Antin",
    "iso:country":"FR",
    "sg:address":"66 rue de la Chauss\u00e9e d'Antin 75009 Paris",
    "sg:classifiers":[
        {
            "category":"Food & Beverages",
            "subcategory":"Dairy",
            "type":"Retail Goods"
        }
    ],
    "sg:phone":"+33 1 55 07 17 00",
    "sg:postcode":"75009",
    "sg:province":"Ile de France",
    "sg:tags":[
        "product",
        "milk"
    ],
    "wof:name":"Primordia Sas",
    "wof:placetype":"venue"
},
  "geometry": {"coordinates":[2.332278,48.874851],"type":"Point"}
}