{
  "type": "Feature",
  "properties": {
    "addr:full":"41/43, Rue Vouill\u00e9, 75015 Paris Ile de France",
    "addr:housenumber":"41 / 43",
    "addr:postcode":"75015",
    "addr:street":"Rue Vouille\u0301",
    "iso:country":"FR",
    "sg:address":"41/43, Rue Vouill\u00e9, 75015 Paris",
    "sg:orig_category":"Non-Classified Establishments",
    "sg:phone":"+33 1 48 28 07 52",
    "sg:province":"Ile de France",
    "wof:name":"Magot S.a.",
    "wof:placetype":"venue"
},
  "geometry": {"coordinates":[2.307758,48.834095],"type":"Point"}
}