{
  "type": "Feature",
  "properties": {
    "iso:country":"FR",
    "sg:address":"35, Rte Nationale le Raquet, 59552 Lambres lez Douai",
    "sg:orig_category":"Non-Classified Establishments",
    "sg:phone":"+33 3 27 88 72 69",
    "sg:province":"Nord Pas-de-Calais",
    "wof:name":"Maison Saint P\u00f4l S.a.r.l.",
    "wof:placetype":"venue"
},
  "geometry": {"coordinates":[3.064857,50.353138],"type":"Point"}
}