{
  "type": "Feature",
  "properties": {
    "addr:full":"Chemin des Bellons Istres Provence-Alpes-C\u00f4te d'Azur 13800",
    "addr:postcode":"13800",
    "addr:street":"Chemin Des Bellons",
    "iso:country":"FR",
    "sg:address":"Chemin des Bellons",
    "sg:city":"Istres",
    "sg:orig_category":"Unclassifiable Establishments",
    "sg:phone":"+33 4 42 35 90 35",
    "sg:postcode":"13800",
    "sg:province":"Provence-Alpes-C\u00f4te d'Azur",
    "wof:name":"Snecma",
    "wof:placetype":"venue"
},
  "geometry": {"coordinates":[4.974395,43.529854],"type":"Point"}
}