{
  "type": "Feature",
  "properties": {
    "iso:country":"FR",
    "sg:address":"89, Rue Gustave Vatonne, 91190 Gif sur Yvette",
    "sg:orig_category":"Unclassifiable Establishments",
    "sg:phone":"+33 1 69 28 03 03",
    "sg:province":"Ile de France",
    "wof:name":"Marc Oliva S.a.r.l.",
    "wof:placetype":"venue"
},
  "geometry": {"coordinates":[2.152482,48.70253],"type":"Point"}
}