{
  "type": "Feature",
  "properties": {
    "iso:country":"FR",
    "sg:address":"223, Av. de Denain, 59300 Valenciennes",
    "sg:orig_category":"Non-Classified Establishments",
    "sg:phone":"+33 3 27 46 16 11",
    "sg:province":"Nord Pas-de-Calais",
    "wof:name":"Riou S.a.r.l.",
    "wof:placetype":"venue"
},
  "geometry": {"coordinates":[3.491573,50.350658],"type":"Point"}
}