{
  "type": "Feature",
  "properties": {
    "addr:full":"La Sucrerie 60190 Laneuvilleroy Picardie 60190",
    "addr:postcode":"60190;60190",
    "addr:street":"Picardie",
    "iso:country":"FR",
    "sg:address":"La Sucrerie 60190 Laneuvilleroy",
    "sg:classifiers":[
        {
            "category":"Shopping",
            "subcategory":"Bicycles & Sporting Goods",
            "type":"Retail Goods"
        }
    ],
    "sg:phone":"+33 3 44 51 73 28",
    "sg:postcode":"60190",
    "sg:province":"Picardie",
    "sg:tags":[
        "product",
        "sport",
        "miscellaneous"
    ],
    "wof:name":"Ets Sampic Pere Et Fils",
    "wof:placetype":"venue"
},
  "geometry": {"coordinates":[2.570818,49.488388],"type":"Point"}
}