{
  "type": "Feature",
  "properties": {
    "addr:full":"12 Av Andr\u00e9 Margot 51885 Reims Cedex 3 Champagne",
    "addr:postcode":"51885",
    "addr:street":"12 Av Andre\u0301 Margot",
    "iso:country":"FR",
    "sg:address":"12 Av Andr\u00e9 Margot 51885 Reims Cedex 3",
    "sg:classifiers":[
        {
            "category":"Building & Trades",
            "subcategory":"Construction",
            "type":"Services"
        }
    ],
    "sg:phone":"+33 3 26 09 30 55",
    "sg:province":"Champagne",
    "sg:tags":[
        "work",
        "public"
    ],
    "wof:name":"Routiere Morin",
    "wof:placetype":"venue"
},
  "geometry": {"coordinates":[4.03384,49.25415],"type":"Point"}
}