{
  "type": "Feature",
  "properties": {
    "iso:country":"FR",
    "sg:address":"211, Rue de Picardie, 45160 Olivet",
    "sg:city":"Olivet",
    "sg:orig_category":"Unclassifiable Establishments",
    "sg:phone":"+33 2 38 69 38 55",
    "sg:postcode":"45160",
    "sg:province":"Centre",
    "wof:name":"G.a.m. Ing\u00e9nierie S.a.r.l.",
    "wof:placetype":"venue"
},
  "geometry": {"coordinates":[1.922233,47.841961],"type":"Point"}
}