{
  "type": "Feature",
  "properties": {
    "addr:full":"14 Av Georges Clemenceau 76460 St Valery En Caux Haute Normandie 76460",
    "addr:postcode":"76460;76460",
    "addr:street":"14 Av Georges Clemenceau;Haute Normandie",
    "iso:country":"FR",
    "sg:address":"14 Av Georges Clemenceau 76460 St Valery En Caux",
    "sg:classifiers":[
        {
            "category":"Travel",
            "subcategory":"Hotels & Motels",
            "type":"Entertainment"
        }
    ],
    "sg:phone":"+33 2 35 57 88 00",
    "sg:postcode":"76460",
    "sg:province":"Haute Normandie",
    "sg:tags":[
        "hotels",
        "business",
        "restaurant"
    ],
    "wof:name":"Hotel Mercure",
    "wof:placetype":"venue"
},
  "geometry": {"coordinates":[0.71176,49.868809],"type":"Point"}
}