{
  "type": "Feature",
  "properties": {
    "addr:full":"37 Fran\u00e7ois Mitterrand 44800 Saint Herblain Pays de Loire 44800",
    "addr:housenumber":"37",
    "addr:postcode":"44800;44800",
    "addr:street":"Franc\u0327Ois Mitterrand;Herblain",
    "iso:country":"FR",
    "sg:address":"37",
    "sg:city":"Fran\u00e7ois Mitterrand 44800 Saint Herblain",
    "sg:classifiers":[
        {
            "category":"Health Services",
            "subcategory":"Podiatrist",
            "type":"Services"
        }
    ],
    "sg:phone":"+33 2 40 92 07 09",
    "sg:postcode":"44800",
    "sg:province":"Pays de Loire",
    "sg:tags":[
        "instrument",
        "measurement",
        "-",
        "precision",
        "equipment"
    ],
    "wof:name":"Grosseron",
    "wof:placetype":"venue"
},
  "geometry": {"coordinates":[-1.648032,47.213352],"type":"Point"}
}