{
  "type": "Feature",
  "properties": {
    "iso:country":"FR",
    "sg:address":"47 cours Doct Long; Lyon",
    "sg:classifiers":[
        {
            "category":"Banks & Credit Unions",
            "subcategory":"Bank",
            "type":"Services"
        }
    ],
    "sg:phone":"+33 3378549149",
    "sg:province":"Midi Pyr\u00e9n\u00e9es",
    "wof:name":"Cr\u00e9dit Lyonnais Sa, Montchat",
    "wof:placetype":"venue"
},
  "geometry": {"coordinates":[-90.541031,34.219009],"type":"Point"}
}