{
  "type": "Feature",
  "properties": {
    "iso:country":"FR",
    "sg:address":"106, Av. de Richelieu, 86100 Chatellerault",
    "sg:orig_category":"Unclassifiable Establishments",
    "sg:phone":"+33 5 49 20 06 60",
    "sg:postcode":"86100",
    "sg:province":"Poitou-Charentes",
    "wof:name":"S.i.m. S.a. - Soci\u00e9t\u00e9 Industrielle De M\u00e9canique",
    "wof:placetype":"venue"
},
  "geometry": {"coordinates":[0.531745,46.824051],"type":"Point"}
}