{
  "type": "Feature",
  "properties": {
    "addr:full":"B.P. 3, 25490 Dampierre les Bois^^Rue de l'Eglise, 25490 Dampierre les Bois Franche Comt\u00e9 25490",
    "addr:housenumber":"3",
    "addr:postcode":"25490;25490;25490",
    "addr:street":"B.P.;L'Eglise;Franche Comte\u0301",
    "iso:country":"FR",
    "sg:address":"B.P. 3, 25490 Dampierre les Bois^^Rue de l'Eglise, 25490 Dampierre les Bois",
    "sg:orig_category":"Non-Classified Establishments",
    "sg:phone":"+33 3 81 93 01 15",
    "sg:postcode":"25490",
    "sg:province":"Franche Comt\u00e9",
    "wof:name":"Concastri S.a.r.l.",
    "wof:placetype":"venue"
},
  "geometry": {"coordinates":[6.937647,47.504898],"type":"Point"}
}