{
  "type": "Feature",
  "properties": {
    "iso:country":"FR",
    "sg:address":"ZI du Pr\u00e9 de la Dame 60128 PLAILLY",
    "sg:classifiers":[
        {
            "category":"Manufacturing",
            "subcategory":"Rubber & Plastics",
            "type":"Manufacturing & Wholesale Goods"
        }
    ],
    "sg:phone":"+33 3 44 54 19 90",
    "sg:province":"Picardie",
    "sg:tags":[
        "technical",
        "parts"
    ],
    "wof:name":"Filtertek Sa",
    "wof:placetype":"venue"
},
  "geometry": {"coordinates":[2.582529,49.104084],"type":"Point"}
}