{
  "type": "Feature",
  "properties": {
    "addr:full":"Manoir De Cokerel 50600 Milly Milly Basse Normandie 50600",
    "addr:postcode":"50600;50600",
    "iso:country":"FR",
    "sg:address":"Manoir De Cokerel 50600 Milly",
    "sg:city":"Milly",
    "sg:classifiers":[
        {
            "category":"Food Court",
            "type":"Food & Drink"
        }
    ],
    "sg:phone":"+33 2 33 79 02 20",
    "sg:postcode":"50600",
    "sg:province":"Basse Normandie",
    "sg:tags":[
        "product",
        "related"
    ],
    "wof:name":"Domaine Du Coquerel",
    "wof:placetype":"venue"
},
  "geometry": {"coordinates":[-1.091154,48.539909],"type":"Point"}
}