{
  "type": "Feature",
  "properties": {
    "addr:full":"213-21, Rue Galli\u00e9ni, 92100 Boulogne Billancourt Ile de France",
    "addr:housenumber":"213-21",
    "addr:postcode":"92100",
    "addr:street":"Rue Gallie\u0301Ni",
    "iso:country":"FR",
    "sg:address":"213-21, Rue Galli\u00e9ni, 92100 Boulogne Billancourt",
    "sg:orig_category":"Unclassifiable Establishments",
    "sg:phone":"+33 1 41 10 01 01",
    "sg:province":"Ile de France",
    "wof:name":"Avant Garde S.a.r.l.",
    "wof:placetype":"venue"
},
  "geometry": {"coordinates":[2.231246,48.835346],"type":"Point"}
}