{
  "type": "Feature",
  "properties": {
    "iso:country":"FR",
    "sg:address":"14 R Piliers Chauvini\u00e8re 44805 St Herblain",
    "sg:classifiers":[
        {
            "category":"Health Services",
            "subcategory":"Medical Lab",
            "type":"Services"
        }
    ],
    "sg:phone":"+33 2 28 09 12 12",
    "sg:province":"Pays de Loire",
    "sg:tags":[
        "chemical",
        "pharmaceutical",
        "pharmacy"
    ],
    "wof:name":"Cooperative D'exploitation Et De Repartition Pharmaceutique",
    "wof:placetype":"venue"
},
  "geometry": {"coordinates":[-1.63688,47.231201],"type":"Point"}
}