{
  "type": "Feature",
  "properties": {
    "iso:country":"FR",
    "sg:address":"89, Av. de la Libert\u00e9, 33440 Ambar\u00e8s et Lagrave",
    "sg:city":"Ambar\u00e8s-et-Lagrave",
    "sg:orig_category":"Unclassifiable Establishments",
    "sg:phone":"+33 5 56 38 81 28",
    "sg:postcode":"33440",
    "sg:province":"Aquitaine",
    "wof:name":"Atec S.a.r.l.",
    "wof:placetype":"venue"
},
  "geometry": {"coordinates":[-0.491747,44.940491],"type":"Point"}
}