{
  "type": "Feature",
  "properties": {
    "addr:full":"10, Rue Curie, 08000 Charleville M\u00e9zi\u00e8res Charleville-M\u00e9zi\u00e8res Champagne 08000",
    "addr:housenumber":"10",
    "addr:postcode":"08000;08000",
    "addr:street":"Rue Curie",
    "iso:country":"FR",
    "sg:address":"10, Rue Curie, 08000 Charleville M\u00e9zi\u00e8res",
    "sg:city":"Charleville-M\u00e9zi\u00e8res",
    "sg:orig_category":"Unclassifiable Establishments",
    "sg:phone":"+33 3 24 57 00 70",
    "sg:postcode":"08000",
    "sg:province":"Champagne",
    "wof:name":"Alstom S.a.",
    "wof:placetype":"venue"
},
  "geometry": {"coordinates":[4.72062,49.753708],"type":"Point"}
}