{
  "type": "Feature",
  "properties": {
    "addr:full":"B.P. 38, 71240 Sennecey le Grand^^ZA du Chemin Ferr\u00e9, 71240 Sennecey le Grand Marnay Bourgogne 71240",
    "addr:postcode":"71240;71240;71240",
    "addr:street":"B.P. 38;Chemin Ferre\u0301;Grand;Bourgogne",
    "iso:country":"FR",
    "sg:address":"B.P. 38, 71240 Sennecey le Grand^^ZA du Chemin Ferr\u00e9, 71240 Sennecey le Grand",
    "sg:city":"Marnay",
    "sg:orig_category":"Non-Classified Establishments",
    "sg:phone":"+33 3 85 44 79 64",
    "sg:postcode":"71240",
    "sg:province":"Bourgogne",
    "wof:name":"Berthoux Transports S.a.",
    "wof:placetype":"venue"
},
  "geometry": {"coordinates":[4.835139,46.575211],"type":"Point"}
}