{
  "type": "Feature",
  "properties": {
    "addr:full":"route de la Br\u00fblatte 53410 Port Brillet Pays de Loire 53410",
    "addr:postcode":"53410;53410",
    "addr:street":"Route De La Bru\u0302Latte;Brillet",
    "iso:country":"FR",
    "sg:address":"route de la Br\u00fblatte 53410 Port Brillet",
    "sg:orig_category":"Gyros Grills For Household Use",
    "sg:phone":"+33 2 43 26 10 10",
    "sg:postcode":"53410",
    "sg:province":"Pays de Loire",
    "wof:name":"Pebeco Sa",
    "wof:placetype":"venue"
},
  "geometry": {"coordinates":[-1.013198,48.072639],"type":"Point"}
}