{
  "type": "Feature",
  "properties": {
    "addr:full":"8 ter, Chemin de Lourmet, 31180 Castelmaurou Midi Pyr\u00e9n\u00e9es",
    "addr:housenumber":"8 ter",
    "addr:postcode":"31180",
    "addr:street":"Chemin De Lourmet",
    "iso:country":"FR",
    "sg:address":"8 ter, Chemin de Lourmet, 31180 Castelmaurou",
    "sg:orig_category":"Non-Classified Establishments",
    "sg:phone":"+33 5 61 09 15 36",
    "sg:province":"Midi Pyr\u00e9n\u00e9es",
    "wof:name":"Louis Cogo S.a.r.l.",
    "wof:placetype":"venue"
},
  "geometry": {"coordinates":[1.539246,43.687641],"type":"Point"}
}