{
  "type": "Feature",
  "properties": {
    "addr:full":"51 rue Montgolfier 69006 Lyon Rhone-Alpes",
    "addr:housenumber":"51",
    "addr:postcode":"69006",
    "addr:street":"Rue Montgolfier",
    "iso:country":"FR",
    "sg:address":"51 rue Montgolfier 69006 Lyon",
    "sg:classifiers":[
        {
            "category":"Professional",
            "subcategory":"Computer Services",
            "type":"Services"
        }
    ],
    "sg:phone":"+33 1 78 17 16 16",
    "sg:province":"Rhone-Alpes",
    "sg:tags":[
        "services",
        "consulting",
        "internet"
    ],
    "wof:name":"Jet Multimedia Sa",
    "wof:placetype":"venue"
},
  "geometry": {"coordinates":[4.849422,45.772079],"type":"Point"}
}