{
  "type": "Feature",
  "properties": {
    "addr:full":"Impasse de Lespinasse - ZI de la Plaine Aucamville Midi Pyr\u00e9n\u00e9es 31140",
    "addr:postcode":"31140",
    "addr:street":"Impasse De Lespinasse Zi De La Plaine",
    "iso:country":"FR",
    "sg:address":"Impasse de Lespinasse - ZI de la Plaine",
    "sg:city":"Aucamville",
    "sg:orig_category":"Non-Classified Establishments",
    "sg:phone":"+33 5 61 70 37 52",
    "sg:postcode":"31140",
    "sg:province":"Midi Pyr\u00e9n\u00e9es",
    "wof:name":"A.p.c. S.a.r.l.",
    "wof:placetype":"venue"
},
  "geometry": {"coordinates":[1.429025,43.668308],"type":"Point"}
}