{
  "type": "Feature",
  "properties": {
    "addr:full":"168, Rue de Grennelle, 75007 Paris Ile de France",
    "addr:housenumber":"168",
    "addr:postcode":"75007",
    "addr:street":"Rue De Grennelle",
    "iso:country":"FR",
    "sg:address":"168, Rue de Grennelle, 75007 Paris",
    "sg:orig_category":"Unclassifiable Establishments",
    "sg:phone":"+33 1 44 42 94 60",
    "sg:province":"Ile de France",
    "wof:name":"Masters Consultants S.a.s.",
    "wof:placetype":"venue"
},
  "geometry": {"coordinates":[2.30824,48.858025],"type":"Point"}
}