{
  "type": "Feature",
  "properties": {
    "addr:full":"Rue Entre Deux Rochers Donville les Bains Basse Normandie 50350",
    "addr:postcode":"50350",
    "addr:street":"Rue Entre Deux Rochers",
    "iso:country":"FR",
    "sg:address":"Rue Entre Deux Rochers",
    "sg:city":"Donville les Bains",
    "sg:orig_category":"Unclassifiable Establishments",
    "sg:phone":"+33 2 33 90 62 00",
    "sg:postcode":"50350",
    "sg:province":"Basse Normandie",
    "wof:name":"Etablissements Agrex S.a.",
    "wof:placetype":"venue"
},
  "geometry": {"coordinates":[-1.57093,48.849258],"type":"Point"}
}