{
  "type": "Feature",
  "properties": {
    "addr:full":"B.P. 415, 73104 Aix les Bains C\u00e9dex^^31, Chemin de Saint Pol, 73100 Aix les Bains Rhone-Alpes 73100",
    "addr:housenumber":"b.p. 415",
    "addr:postcode":"73104;73100;73100",
    "addr:street":"Chemin De Saint;Aix",
    "iso:country":"FR",
    "sg:address":"B.P. 415, 73104 Aix les Bains C\u00e9dex^^31, Chemin de Saint Pol, 73100 Aix les Bains",
    "sg:orig_category":"Non-Classified Establishments",
    "sg:phone":"+33 4 79 88 32 87",
    "sg:postcode":"73100",
    "sg:province":"Rhone-Alpes",
    "wof:name":"Satali Soci\u00e9t\u00e9 Assistance Technique Agro Aliment - Industriel S.a.r.l.",
    "wof:placetype":"venue"
},
  "geometry": {"coordinates":[5.922591,45.685276],"type":"Point"}
}