{
  "type": "Feature",
  "properties": {
    "addr:full":"ZAC de la Croix Camus Sainte Verge Poitou-Charentes 79100",
    "addr:postcode":"79100",
    "addr:street":"Zac De La Croix Camus Sainte Verge",
    "iso:country":"FR",
    "sg:address":"ZAC de la Croix Camus",
    "sg:city":"Sainte Verge",
    "sg:orig_category":"Non-Classified Establishments",
    "sg:phone":"+33 5 49 66 48 80",
    "sg:postcode":"79100",
    "sg:province":"Poitou-Charentes",
    "wof:name":"S\u00e9fop Service S.a.r.l.",
    "wof:placetype":"venue"
},
  "geometry": {"coordinates":[-0.210911,47.007378],"type":"Point"}
}