{
  "type": "Feature",
  "properties": {
    "addr:full":"122, Rue Edouard Vailland, 92593 Levallois Perret C\u00e9dex \u00cele-de-France",
    "addr:housenumber":"122",
    "addr:postcode":"92593",
    "addr:street":"Rue Edouard Vailland;Ce\u0301Dex",
    "iso:country":"FR",
    "sg:address":"122, Rue Edouard Vailland, 92593 Levallois Perret C\u00e9dex",
    "sg:orig_category":"Unclassifiable Establishments",
    "sg:phone":"+33 1 41 49 73 00",
    "sg:province":"\u00cele-de-France",
    "wof:name":"L\u00e9o Burnett S.a.",
    "wof:placetype":"venue"
},
  "geometry": {"coordinates":[2.2882,48.894329],"type":"Point"}
}