{
  "type": "Feature",
  "properties": {
    "iso:country":"FR",
    "sg:address":"Les Clos Tort's 61120 Vimoutiers",
    "sg:city":"Vimoutiers",
    "sg:orig_category":"Unclassifiable Establishments",
    "sg:phone":"+33 2 33 39 63 00",
    "sg:postcode":"61120",
    "sg:province":"Basse Normandie",
    "wof:name":"Solaipa S.a. -soci\u00e9t\u00e9 Laiti\u00e8re Du Pays D'auge",
    "wof:placetype":"venue"
},
  "geometry": {"coordinates":[0.19877,48.92786],"type":"Point"}
}