{
  "type": "Feature",
  "properties": {
    "iso:country":"FR",
    "sg:address":"Parc Confort Land Za Rte Du Meuble 35520 Melesse",
    "sg:city":"Melesse",
    "sg:classifiers":[
        {
            "category":"Professional",
            "subcategory":"Advertising",
            "type":"Services"
        }
    ],
    "sg:phone":"+33 2 99 66 57 11",
    "sg:postcode":"35520",
    "sg:province":"Bretagne",
    "sg:tags":[
        "marketing",
        "medium",
        "communication"
    ],
    "wof:name":"Lamifilm Routage",
    "wof:placetype":"venue"
},
  "geometry": {"coordinates":[-1.734432,48.178051],"type":"Point"}
}