{
  "type": "Feature",
  "properties": {
    "addr:full":"33360 C\u00e9nac C\u00e9nac Aquitaine 33360",
    "addr:postcode":"33360;33360",
    "iso:country":"FR",
    "sg:address":"33360 C\u00e9nac",
    "sg:city":"C\u00e9nac",
    "sg:orig_category":"Unclassifiable Establishments",
    "sg:phone":"+33 5 56 20 73 28",
    "sg:postcode":"33360",
    "sg:province":"Aquitaine",
    "wof:name":"Ch\u00e2teau Duplessy",
    "wof:placetype":"venue"
},
  "geometry": {"coordinates":[-0.462197,44.780354],"type":"Point"}
}