{
  "type": "Feature",
  "properties": {
    "addr:full":"Za Des Granges 42600 Montbrison Rhone-Alpes 42600",
    "addr:postcode":"42600;42600",
    "addr:street":"Za Des Granges",
    "iso:country":"FR",
    "sg:address":"Za Des Granges 42600 Montbrison",
    "sg:classifiers":[
        {
            "category":"Military Area",
            "subcategory":"Air Force Base",
            "type":"Public Place"
        }
    ],
    "sg:phone":"+33 4 77 96 89 00",
    "sg:postcode":"42600",
    "sg:province":"Rhone-Alpes",
    "sg:tags":[
        "equipment",
        "energy",
        "material",
        "-",
        "environment",
        "raw",
        "engineering",
        "machinery",
        "mechanical",
        "machi"
    ],
    "wof:name":"Saur France",
    "wof:placetype":"venue"
},
  "geometry": {"coordinates":[4.062125,45.607185],"type":"Point"}
}