{
  "type": "Feature",
  "properties": {
    "addr:full":"5 ave du Charles de Gaulle; Autun; 71400 Autun Bourgogne 71400",
    "addr:postcode":"71400;71400",
    "addr:street":"5 Ave Du Charles De Gaulle;Bourgogne",
    "iso:country":"FR",
    "sg:address":"5 ave du Charles de Gaulle; Autun; 71400",
    "sg:city":"Autun",
    "sg:classifiers":[
        {
            "category":"Banks & Credit Unions",
            "subcategory":"Bank",
            "type":"Services"
        }
    ],
    "sg:phone":"+33 3385522443",
    "sg:postcode":"71400",
    "sg:province":"Bourgogne",
    "wof:name":"Banque Nationale De Paris",
    "wof:placetype":"venue"
},
  "geometry": {"coordinates":[4.298225,46.950451],"type":"Point"}
}