{
  "type": "Feature",
  "properties": {
    "addr:full":"Rte de Melle Chef Boutonne Poitou-Charentes 79110",
    "addr:postcode":"79110",
    "addr:street":"Rte De;Boutonne",
    "iso:country":"FR",
    "sg:address":"Rte de Melle",
    "sg:city":"Chef Boutonne",
    "sg:orig_category":"Unclassifiable Establishments",
    "sg:phone":"+33 5 49 27 82 00",
    "sg:postcode":"79110",
    "sg:province":"Poitou-Charentes",
    "wof:name":"B.s.a.d. S.a. - Bourgoin S.a. Distribution",
    "wof:placetype":"venue"
},
  "geometry": {"coordinates":[-0.08101,45.99334],"type":"Point"}
}