{
  "type": "Feature",
  "properties": {
    "iso:country":"FR",
    "sg:address":"Rte de Chazeau - ZI de la Martini\u00e8re",
    "sg:city":"Firminy",
    "sg:orig_category":"Unclassifiable Establishments",
    "sg:phone":"+33 4 77 40 20 80",
    "sg:postcode":"42700",
    "sg:province":"Auvergne",
    "wof:name":"Cornillon S.a.r.l.",
    "wof:placetype":"venue"
},
  "geometry": {"coordinates":[4.28652,45.388603],"type":"Point"}
}