{
  "type": "Feature",
  "properties": {
    "iso:country":"FR",
    "sg:address":"11, Rue Monberdin, 77320 Meilleray",
    "sg:orig_category":"Non-Classified Establishments",
    "sg:phone":"+33 1 64 20 12 74",
    "sg:province":"Ile de France",
    "wof:name":"Imprimerie Dillenseger E.u.r.l.",
    "wof:placetype":"venue"
},
  "geometry": {"coordinates":[3.425457,48.786404],"type":"Point"}
}