{
  "type": "Feature",
  "properties": {
    "iso:country":"FR",
    "sg:address":"76, Rue Bonaparte, 75006 Paris",
    "sg:orig_category":"Non-Classified Establishments",
    "sg:phone":"+33 1 44 41 35 00",
    "sg:province":"Ile de France",
    "wof:name":"Plon-perrin S.a.",
    "wof:placetype":"venue"
},
  "geometry": {"coordinates":[2.332676,48.851055],"type":"Point"}
}