{
  "type": "Feature",
  "properties": {
    "addr:full":"2, All\u00e9e Martin Luther King, 76620 Le Havre Haute-Normandie",
    "addr:housenumber":"2",
    "addr:postcode":"76620",
    "addr:street":"Alle\u0301E Martin Luther King;Havre",
    "iso:country":"FR",
    "sg:address":"2, All\u00e9e Martin Luther King, 76620 Le Havre",
    "sg:orig_category":"Non-Classified Establishments",
    "sg:phone":"+33 2 35 89 39 66",
    "sg:province":"Haute-Normandie",
    "wof:name":"Jumo R\u00e9gulation S.a.",
    "wof:placetype":"venue"
},
  "geometry": {"coordinates":[0.08741,49.51548],"type":"Point"}
}