{
  "type": "Feature",
  "properties": {
    "addr:full":"15 Rue Alphonse Pluchet 92220 Bagneux Ile de France 92220",
    "addr:housenumber":"15",
    "addr:postcode":"92220;ile;92220",
    "addr:street":"Rue Alphonse Pluchet;France",
    "iso:country":"FR",
    "sg:address":"15 Rue Alphonse Pluchet 92220 Bagneux",
    "sg:classifiers":[
        {
            "category":"Home & Garden",
            "subcategory":"Furniture",
            "type":"Retail Goods"
        }
    ],
    "sg:phone":"+33 1 46 56 08 37",
    "sg:postcode":"92220",
    "sg:province":"Ile de France",
    "sg:tags":[
        "household",
        "wood"
    ],
    "wof:name":"Tolerie Chaudronnerie De Bagneux Sarl",
    "wof:placetype":"venue"
},
  "geometry": {"coordinates":[2.298205,48.797981],"type":"Point"}
}