{
  "type": "Feature",
  "properties": {
    "addr:full":"21, Rue Galil\u00e9e - Cit\u00e9 Descartes, 77420 Champs sur Marne Ile de France",
    "addr:housenumber":"21",
    "addr:postcode":"77420",
    "addr:street":"Rue Galile\u0301E Cite\u0301 Descartes",
    "iso:country":"FR",
    "sg:address":"21, Rue Galil\u00e9e - Cit\u00e9 Descartes, 77420 Champs sur Marne",
    "sg:orig_category":"Unclassifiable Establishments",
    "sg:phone":"+33 1 64 73 34 43",
    "sg:province":"Ile de France",
    "wof:name":"Cogicom S.a.r.l.",
    "wof:placetype":"venue"
},
  "geometry": {"coordinates":[2.592358,48.835842],"type":"Point"}
}