{
  "type": "Feature",
  "properties": {
    "addr:full":"28, Rue Carnot, 86000 Poitiers Poitou-Charentes",
    "addr:housenumber":"28",
    "addr:postcode":"86000",
    "addr:street":"Rue Carnot",
    "iso:country":"FR",
    "sg:address":"28, Rue Carnot, 86000 Poitiers",
    "sg:orig_category":"Unclassifiable Establishments",
    "sg:phone":"+33 5 49 41 09 09",
    "sg:province":"Poitou-Charentes",
    "wof:name":"Comareg",
    "wof:placetype":"venue"
},
  "geometry": {"coordinates":[0.338532,46.579067],"type":"Point"}
}