{
  "type": "Feature",
  "properties": {
    "iso:country":"FR",
    "sg:address":"2 Av Luan 31130 Balma",
    "sg:classifiers":[
        {
            "category":"Health Services",
            "subcategory":"Medical Lab",
            "type":"Services"
        }
    ],
    "sg:phone":"+33 5 61 24 77 77",
    "sg:postcode":"31130",
    "sg:province":"Midi Pyr\u00e9n\u00e9es",
    "sg:tags":[
        "chemical",
        "pharmaceutical",
        "pharmacy"
    ],
    "wof:name":"Cooperative D'exploitation Et De Repartition Pharmaceutiques (cerp Rouen) Cerp Rouen",
    "wof:placetype":"venue"
},
  "geometry": {"coordinates":[1.490978,43.627258],"type":"Point"}
}