{
  "type": "Feature",
  "properties": {
    "addr:full":"Zone Agricole Saint Romain en Gal Rhone-Alpes 69560",
    "addr:postcode":"69560",
    "addr:street":"Saint",
    "iso:country":"FR",
    "sg:address":"Zone Agricole",
    "sg:city":"Saint Romain en Gal",
    "sg:orig_category":"Non-Classified Establishments",
    "sg:phone":"+33 4 72 24 00 32",
    "sg:postcode":"69560",
    "sg:province":"Rhone-Alpes",
    "wof:name":"Trans-man S.a.",
    "wof:placetype":"venue"
},
  "geometry": {"coordinates":[4.858154,45.535912],"type":"Point"}
}