{
  "type": "Feature",
  "properties": {
    "iso:country":"FR",
    "sg:address":"51240 La Chaussee Sur Marne",
    "sg:classifiers":[
        {
            "category":"Farming",
            "subcategory":"Livestock Farm",
            "type":"Manufacturing & Wholesale Goods"
        }
    ],
    "sg:phone":"+33 3 26 66 36 78",
    "sg:postcode":"51240",
    "sg:province":"Champagne",
    "sg:tags":[
        "grain",
        "agriculture",
        "cereal"
    ],
    "wof:name":"Etablissements Hubert",
    "wof:placetype":"venue"
},
  "geometry": {"coordinates":[4.517429,48.836494],"type":"Point"}
}