{
  "type": "Feature",
  "properties": {
    "iso:country":"FR",
    "sg:address":"34, Rue Mozart, 92110 Clichy",
    "sg:orig_category":"Non-Classified Establishments",
    "sg:phone":"+33 1 55 46 50 50",
    "sg:province":"Ile de France",
    "wof:name":"Suptec S.a.",
    "wof:placetype":"venue"
},
  "geometry": {"coordinates":[2.316957,48.906235],"type":"Point"}
}