{
  "type": "Feature",
  "properties": {
    "addr:full":"94, Rue Lafayette, 75010 Paris Ile de France",
    "addr:housenumber":"94",
    "addr:postcode":"75010",
    "addr:street":"Rue Lafayette",
    "iso:country":"FR",
    "sg:address":"94, Rue Lafayette, 75010 Paris",
    "sg:orig_category":"Unclassifiable Establishments",
    "sg:phone":"+33 1 55 33 51 50",
    "sg:province":"Ile de France",
    "wof:name":"Odyssey S.a.r.l.",
    "wof:placetype":"venue"
},
  "geometry": {"coordinates":[2.358515,48.87352],"type":"Point"}
}