{
  "type": "Feature",
  "properties": {
    "addr:full":"B.P. 101, 78503 Sartrouville C\u00e9dex^^128, Rue L\u00e9on Jouhaux, 78500 Sartrouville Ile de France",
    "addr:housenumber":"b.p. 101",
    "addr:postcode":"78503;78500;ile",
    "addr:street":"Rue Le\u0301On Jouhaux",
    "iso:country":"FR",
    "sg:address":"B.P. 101, 78503 Sartrouville C\u00e9dex^^128, Rue L\u00e9on Jouhaux, 78500 Sartrouville",
    "sg:orig_category":"Non-Classified Establishments",
    "sg:phone":"+33 1 39 57 67 36",
    "sg:province":"Ile de France",
    "wof:name":"S.r.c.i. S.a. - Soci\u00e9t\u00e9 R\u00e9alisation Des Circuits Imprim\u00e9s",
    "wof:placetype":"venue"
},
  "geometry": {"coordinates":[2.16183,48.941525],"type":"Point"}
}