{
  "type": "Feature",
  "properties": {
    "addr:full":"1, Rue de la Mare Blanche - ZI, 77186 Noisiel Ile de France",
    "addr:housenumber":"1",
    "addr:postcode":"77186",
    "addr:street":"Rue De La Mare Blanche Zi",
    "iso:country":"FR",
    "sg:address":"1, Rue de la Mare Blanche - ZI, 77186 Noisiel",
    "sg:orig_category":"Unclassifiable Establishments",
    "sg:phone":"+33 1 60 37 48 77",
    "sg:province":"Ile de France",
    "wof:name":"Isogard",
    "wof:placetype":"venue"
},
  "geometry": {"coordinates":[2.628145,48.854988],"type":"Point"}
}