{
  "type": "Feature",
  "properties": {
    "iso:country":"FR",
    "sg:address":"Zi Du Mont Vaudois 70400 H\u00e9ricourt",
    "sg:classifiers":[
        {
            "category":"Professional",
            "subcategory":"Engineering",
            "type":"Services"
        }
    ],
    "sg:phone":"+33 3 84 46 88 37",
    "sg:postcode":"70400",
    "sg:province":"Franche Comt\u00e9",
    "sg:tags":[
        "machine",
        "-",
        "mechanical"
    ],
    "wof:name":"Jacques Thourot Sa",
    "wof:placetype":"venue"
},
  "geometry": {"coordinates":[6.754775,47.574718],"type":"Point"}
}