{
  "type": "Feature",
  "properties": {
    "iso:country":"FR",
    "sg:address":"16, Rue Colbert, 67390 Marckolsheim",
    "sg:city":"Marckolsheim",
    "sg:orig_category":"Unclassifiable Establishments",
    "sg:phone":"+33 3 88 58 31 00",
    "sg:postcode":"67390",
    "sg:province":"Alsace",
    "wof:name":"Sommer Industrie S.n.c.",
    "wof:placetype":"venue"
},
  "geometry": {"coordinates":[7.556894,48.156708],"type":"Point"}
}