{
  "type": "Feature",
  "properties": {
    "iso:country":"FR",
    "sg:address":"Rue d'Orval",
    "sg:city":"Margut",
    "sg:orig_category":"Unclassifiable Establishments",
    "sg:phone":"+33 3 24 22 60 11",
    "sg:postcode":"08370",
    "sg:province":"Champagne",
    "wof:name":"Soci\u00e9t\u00e9 Fromag\u00e8re S.n.c.",
    "wof:placetype":"venue"
},
  "geometry": {"coordinates":[5.268244,49.586533],"type":"Point"}
}