{
  "type": "Feature",
  "properties": {
    "addr:full":"B.P. 10313, 60618 La Croix Saint Ouen C\u00e9dex^^3, Rue du Tourteret - ZI, 60880 Le Meux Picardie",
    "addr:housenumber":"10313",
    "addr:postcode":"60618;60880",
    "addr:street":"Rue Du Tourteret Zi",
    "iso:country":"FR",
    "sg:address":"B.P. 10313, 60618 La Croix Saint Ouen C\u00e9dex^^3, Rue du Tourteret - ZI, 60880 Le Meux",
    "sg:orig_category":"Non-Classified Establishments",
    "sg:phone":"+33 3 44 41 70 71",
    "sg:province":"Picardie",
    "wof:name":"Placoplatre S.a.",
    "wof:placetype":"venue"
},
  "geometry": {"coordinates":[2.776811,49.389362],"type":"Point"}
}