{
  "type": "Feature",
  "properties": {
    "addr:full":"Rte de Mauron - ZA Mauron Bretagne 56430",
    "addr:postcode":"56430",
    "addr:street":"Rte De Mauron Za Mauron Bretagne",
    "iso:country":"FR",
    "sg:address":"Rte de Mauron - ZA",
    "sg:city":"Mauron",
    "sg:orig_category":"Non-Classified Establishments",
    "sg:phone":"+33 2 97 22 61 57",
    "sg:postcode":"56430",
    "sg:province":"Bretagne",
    "wof:name":"Sai Mauron S.a.",
    "wof:placetype":"venue"
},
  "geometry": {"coordinates":[-2.288254,48.008797],"type":"Point"}
}