{
  "type": "Feature",
  "properties": {
    "iso:country":"FR",
    "sg:address":"1 voie F\u00e9lix Ebou\u00e9 94000 Creteil",
    "sg:classifiers":[
        {
            "category":"Professional",
            "subcategory":"Business Services",
            "type":"Services"
        }
    ],
    "sg:phone":"+33 1 48 99 77 75",
    "sg:postcode":"94000",
    "sg:province":"Ile de France",
    "sg:tags":[
        "industrial",
        "export"
    ],
    "wof:name":"Orison Jack Sarl",
    "wof:placetype":"venue"
},
  "geometry": {"coordinates":[2.447792,48.797001],"type":"Point"}
}