{
  "type": "Feature",
  "properties": {
    "iso:country":"FR",
    "sg:address":"28 Rue Raymond Aron, Parc D Activites La Vatine, 76130 Mont St Aignan",
    "sg:classifiers":[
        {
            "category":"Banks & Credit Unions",
            "subcategory":"Financial Services",
            "type":"Services"
        }
    ],
    "sg:phone":"+33 2 35 60 40 19",
    "sg:postcode":"76130",
    "sg:province":"Haute Normandie",
    "sg:tags":[
        "banking",
        "finance",
        "insurance"
    ],
    "wof:name":"Cabinet Norman Expertis Comptabl Conseil",
    "wof:placetype":"venue"
},
  "geometry": {"coordinates":[1.094614,49.475529],"type":"Point"}
}