{
  "type": "Feature",
  "properties": {
    "iso:country":"FR",
    "sg:address":"Rue Marcel Luquet - ZI Engachies",
    "sg:city":"Auch",
    "sg:orig_category":"Non-Classified Establishments",
    "sg:phone":"+33 5 62 63 03 29",
    "sg:postcode":"32000",
    "sg:province":"Midi Pyr\u00e9n\u00e9es",
    "wof:name":"E.t.d.e. S.a. - Entreprise De Transport Et Distribution D'energies",
    "wof:placetype":"venue"
},
  "geometry": {"coordinates":[0.584605,43.647324],"type":"Point"}
}