{
  "type": "Feature",
  "properties": {
    "iso:country":"FR",
    "sg:address":"Rue de l'Ecole",
    "sg:city":"Plon\u00e9vez du Faou",
    "sg:orig_category":"Non-Classified Establishments",
    "sg:phone":"+33 5 46 91 19 17",
    "sg:postcode":"29530",
    "sg:province":"Bretagne",
    "wof:name":"Biscuiterie Cadiou S.a.s.",
    "wof:placetype":"venue"
},
  "geometry": {"coordinates":[-3.824364,48.252419],"type":"Point"}
}