{
  "type": "Feature",
  "properties": {
    "iso:country":"FR",
    "sg:address":"5, Place de l'Europe, 38070 Saint Quentin Fallavier",
    "sg:orig_category":"Unclassifiable Establishments",
    "sg:phone":"+33 4 74 99 00 99",
    "sg:postcode":"38070",
    "sg:province":"Rhone-Alpes",
    "wof:name":"Ex\u00e9quation Marketing",
    "wof:placetype":"venue"
},
  "geometry": {"coordinates":[5.11285,45.63916],"type":"Point"}
}