{
  "type": "Feature",
  "properties": {
    "addr:full":"66, Av Mar\u00e9chal Foch, 34500 B\u00e9ziers Languedoc-Roussillon",
    "addr:postcode":"34500",
    "addr:street":"66 Av Mare\u0301Chal Foch",
    "iso:country":"FR",
    "sg:address":"66, Av Mar\u00e9chal Foch, 34500 B\u00e9ziers",
    "sg:orig_category":"Unclassifiable Establishments",
    "sg:phone":"+33 4 67 31 04 32",
    "sg:province":"Languedoc-Roussillon",
    "wof:name":"Pizza Pizza S.a.r.l.",
    "wof:placetype":"venue"
},
  "geometry": {"coordinates":[3.216769,43.349537],"type":"Point"}
}