{
  "type": "Feature",
  "properties": {
    "addr:full":"route de Saint-Gilles 13200 Arles Centre",
    "addr:postcode":"13200",
    "addr:street":"Route De Saint-Gilles",
    "iso:country":"FR",
    "sg:address":"route de Saint-Gilles 13200 Arles",
    "sg:classifiers":[
        {
            "category":"Wholesale",
            "subcategory":"Wine & Distilled Alcoholic Beverages",
            "type":"Manufacturing & Wholesale Goods"
        }
    ],
    "sg:phone":"+33 4 90 96 11 84",
    "sg:province":"Centre",
    "sg:tags":[
        "french"
    ],
    "wof:name":"Ste Civile Du Mas De Rey Sca",
    "wof:placetype":"venue"
},
  "geometry": {"coordinates":[4.600143,43.681599],"type":"Point"}
}