{
  "type": "Feature",
  "properties": {
    "addr:full":"Av. de la Gare Y\u00e8bles Ile de France 77390",
    "addr:postcode":"77390",
    "addr:street":"Av. De La Gare",
    "iso:country":"FR",
    "sg:address":"Av. de la Gare",
    "sg:city":"Y\u00e8bles",
    "sg:orig_category":"Unclassifiable Establishments",
    "sg:phone":"+33 1 64 06 00 37",
    "sg:postcode":"77390",
    "sg:province":"Ile de France",
    "wof:name":"Les Ateliers De Y\u00e8bles S.a.",
    "wof:placetype":"venue"
},
  "geometry": {"coordinates":[2.772823,48.637539],"type":"Point"}
}