{
  "type": "Feature",
  "properties": {
    "addr:full":"1bis, Chauss\u00e9e Jules C\u00e9sar, 95480 Pierrelaye Ile de France",
    "addr:housenumber":"1bis",
    "addr:postcode":"95480;ile",
    "addr:street":"Chausse\u0301E Jules Ce\u0301Sar",
    "iso:country":"FR",
    "sg:address":"1bis, Chauss\u00e9e Jules C\u00e9sar, 95480 Pierrelaye",
    "sg:orig_category":"Unclassifiable Establishments",
    "sg:phone":"+33 1 30 40 24 24",
    "sg:province":"Ile de France",
    "wof:name":"Filpack S.a.",
    "wof:placetype":"venue"
},
  "geometry": {"coordinates":[2.167675,49.019276],"type":"Point"}
}