{
  "type": "Feature",
  "properties": {
    "addr:full":"225, Rue L\u00e9on Dupontreu\u00e9, 80080 Amiens Picardie",
    "addr:housenumber":"225",
    "addr:postcode":"80080",
    "addr:street":"Rue Le\u0301On Dupontreue\u0301",
    "iso:country":"FR",
    "sg:address":"225, Rue L\u00e9on Dupontreu\u00e9, 80080 Amiens",
    "sg:orig_category":"Non-Classified Establishments",
    "sg:phone":"+33 3 22 69 37 37",
    "sg:province":"Picardie",
    "wof:name":"Roger's S.a. - K. Rex",
    "wof:placetype":"venue"
},
  "geometry": {"coordinates":[2.316135,49.906361],"type":"Point"}
}