{
  "type": "Feature",
  "properties": {
    "iso:country":"FR",
    "sg:address":"59 av Francis; Cannes",
    "sg:classifiers":[
        {
            "category":"Banks & Credit Unions",
            "subcategory":"Bank",
            "type":"Services"
        }
    ],
    "sg:phone":"+33 3393471272",
    "wof:name":"Cr\u00e9dit Agricole Des Alpes Maritimes",
    "wof:placetype":"venue"
},
  "geometry": {"coordinates":[7.01325,43.553261],"type":"Point"}
}