{
  "type": "Feature",
  "properties": {
    "addr:full":"25, Rue de Mulhouse, 68170 Rixheim Rixheim Alsace 68170",
    "addr:housenumber":"25",
    "addr:postcode":"68170;68170",
    "addr:street":"Rue De Mulhouse;Rixheim",
    "iso:country":"FR",
    "sg:address":"25, Rue de Mulhouse, 68170 Rixheim",
    "sg:city":"Rixheim",
    "sg:orig_category":"Non-Classified Establishments",
    "sg:phone":"+33 3 89 65 97 50",
    "sg:postcode":"68170",
    "sg:province":"Alsace",
    "wof:name":"Catra S.a.",
    "wof:placetype":"venue"
},
  "geometry": {"coordinates":[7.401226,47.751717],"type":"Point"}
}