{
  "type": "Feature",
  "properties": {
    "addr:full":"Av. des Templiers - ZI Napollon - Local 1 Aubagne Languedoc-Roussillon 13400",
    "addr:housenumber":"local 1",
    "addr:postcode":"13400",
    "addr:street":"Av. Des Templiers Zi Napollon",
    "iso:country":"FR",
    "sg:address":"Av. des Templiers - ZI Napollon - Local 1",
    "sg:city":"Aubagne",
    "sg:orig_category":"Non-Classified Establishments",
    "sg:phone":"+33 4 42 03 42 00",
    "sg:postcode":"13400",
    "sg:province":"Languedoc-Roussillon",
    "wof:name":"Fondasol Etudes S.a.",
    "wof:placetype":"venue"
},
  "geometry": {"coordinates":[5.5687,43.292141],"type":"Point"}
}