{
  "type": "Feature",
  "properties": {
    "iso:country":"FR",
    "sg:address":"16, Av. de la Gineste, 12000 Rodez",
    "sg:orig_category":"Unclassifiable Establishments",
    "sg:phone":"+33 5 65 78 11 70",
    "sg:province":"Midi Pyr\u00e9n\u00e9es",
    "wof:name":"Geldoc S.a.",
    "wof:placetype":"venue"
},
  "geometry": {"coordinates":[2.567519,44.361767],"type":"Point"}
}