{
  "type": "Feature",
  "properties": {
    "addr:full":"832 rue des Pr\u00e9s Moulin 74190 Passy Rhone-Alpes",
    "addr:housenumber":"832",
    "addr:postcode":"74190",
    "addr:street":"Rue Des Pre\u0301S",
    "iso:country":"FR",
    "sg:address":"832 rue des Pr\u00e9s Moulin 74190 Passy",
    "sg:orig_category":"Recycling Of Automotive Coolants",
    "sg:phone":"+33 4 50 78 00 45",
    "sg:province":"Rhone-Alpes",
    "wof:name":"Produits Chimiques Du Mont-blanc S.a.r.l.",
    "wof:placetype":"venue"
},
  "geometry": {"coordinates":[6.713982,45.919102],"type":"Point"}
}