{
  "type": "Feature",
  "properties": {
    "addr:full":"2 rue St Petroni 33190 Gironde sur Dropt Barie Aquitaine 33190",
    "addr:housenumber":"2",
    "addr:postcode":"33190;33190",
    "addr:street":"Rue St Petroni",
    "iso:country":"FR",
    "sg:address":"2 rue St Petroni 33190 Gironde sur Dropt",
    "sg:city":"Barie",
    "sg:classifiers":[
        {
            "category":"Wholesale",
            "subcategory":"Wine & Distilled Alcoholic Beverages",
            "type":"Manufacturing & Wholesale Goods"
        }
    ],
    "sg:phone":"+33 5 56 61 54 54",
    "sg:postcode":"33190",
    "sg:province":"Aquitaine",
    "sg:tags":[
        "french"
    ],
    "wof:name":"Yvon Mau Sa",
    "wof:placetype":"venue"
},
  "geometry": {"coordinates":[-0.087504,44.58894],"type":"Point"}
}