{
  "type": "Feature",
  "properties": {
    "addr:full":"1 Rue Mafsidano 62950 NOYELLES GODAULT Nord Pas-de-Calais",
    "addr:housenumber":"1",
    "addr:postcode":"62950",
    "addr:street":"Rue Mafsidano",
    "iso:country":"FR",
    "sg:address":"1 Rue Mafsidano 62950 NOYELLES GODAULT",
    "sg:orig_category":"Non-Classified Establishments",
    "sg:phone":"+33 3 21 08 52 00",
    "sg:province":"Nord Pas-de-Calais",
    "wof:name":"Meteleurop Nord Sa",
    "wof:placetype":"venue"
},
  "geometry": {"coordinates":[2.99495,50.41996],"type":"Point"}
}