{
  "type": "Feature",
  "properties": {
    "iso:country":"FR",
    "sg:address":"4 rue Charles de Coulomb 81100 Castres",
    "sg:classifiers":[
        {
            "category":"Professional",
            "type":"Services"
        }
    ],
    "sg:phone":"+33 5 63 59 42 27",
    "sg:province":"Midi Pyr\u00e9n\u00e9es",
    "sg:tags":[
        "transport"
    ],
    "wof:name":"Eurl Riols",
    "wof:placetype":"venue"
},
  "geometry": {"coordinates":[2.239799,43.612167],"type":"Point"}
}