{
  "type": "Feature",
  "properties": {
    "addr:full":"57rue Charlot 75003 Paris Ile de France 75003",
    "addr:postcode":"75003;75003",
    "addr:street":"Charlot",
    "iso:country":"FR",
    "sg:address":"57rue Charlot 75003 Paris",
    "sg:classifiers":[
        {
            "category":"Health Services",
            "subcategory":"Medical Lab",
            "type":"Services"
        }
    ],
    "sg:phone":"+33 1 42 71 50 95",
    "sg:postcode":"75003",
    "sg:province":"Ile de France",
    "sg:tags":[
        "chemical",
        "pharmaceutical",
        "pharmacy"
    ],
    "wof:name":"Institut Jacques Waynberg",
    "wof:placetype":"venue"
},
  "geometry": {"coordinates":[2.363094,48.863495],"type":"Point"}
}