{
  "type": "Feature",
  "properties": {
    "addr:full":"11, Av. Lobbe, 19120 Beaulieu sur Dordogne Limousin",
    "addr:postcode":"19120",
    "addr:street":"11 Av. Lobbe",
    "iso:country":"FR",
    "sg:address":"11, Av. Lobbe, 19120 Beaulieu sur Dordogne",
    "sg:orig_category":"Unclassifiable Establishments",
    "sg:phone":"+33 5 55 91 05 56",
    "sg:province":"Limousin",
    "wof:name":"Etablissements Vigier S.a.",
    "wof:placetype":"venue"
},
  "geometry": {"coordinates":[1.83886,44.977505],"type":"Point"}
}