{
  "type": "Feature",
  "properties": {
    "iso:country":"FR",
    "sg:address":"11, Rue Denis Papin, 51100 Reims",
    "sg:orig_category":"Unclassifiable Establishments",
    "sg:phone":"+33 3 26 97 85 20",
    "sg:province":"Champagne",
    "wof:name":"S.r.e. S.a. - Soci\u00e9t\u00e9 R\u00e9moise D'equipement",
    "wof:placetype":"venue"
},
  "geometry": {"coordinates":[4.071336,49.271461],"type":"Point"}
}