{
  "type": "Feature",
  "properties": {
    "addr:full":"5, Rue Paul Langevin - ZI du Hellu, 59260 Hellemmes Lille Nord Pas-de-Calais",
    "addr:housenumber":"5",
    "addr:postcode":"59260",
    "addr:street":"Rue Paul Langevin Zi Du Hellu;Hellemmes Lille Nord",
    "iso:country":"FR",
    "sg:address":"5, Rue Paul Langevin - ZI du Hellu, 59260 Hellemmes Lille",
    "sg:orig_category":"Unclassifiable Establishments",
    "sg:phone":"+33 3 20 33 03 04",
    "sg:province":"Nord Pas-de-Calais",
    "wof:name":"Loxam S.a.",
    "wof:placetype":"venue"
},
  "geometry": {"coordinates":[3.11705,50.614567],"type":"Point"}
}