{
  "type": "Feature",
  "properties": {
    "iso:country":"FR",
    "sg:address":"63, Av. Tony Garnier, 69366 Lyon C\u00e9dex 07",
    "sg:orig_category":"Non-Classified Establishments",
    "sg:phone":"+33 4 72 72 42 42",
    "sg:province":"Rhone-Alpes",
    "wof:name":"Technip",
    "wof:placetype":"venue"
},
  "geometry": {"coordinates":[4.834225,45.7267],"type":"Point"}
}