{
  "type": "Feature",
  "properties": {
    "iso:country":"FR",
    "sg:address":"4 Rte De Caixon 65500 Vic En Bigorre",
    "sg:classifiers":[
        {
            "category":"Home & Garden",
            "subcategory":"Furniture",
            "type":"Retail Goods"
        }
    ],
    "sg:phone":"+33 5 62 96 74 14",
    "sg:province":"Midi Pyr\u00e9n\u00e9es",
    "sg:tags":[
        "wood"
    ],
    "wof:name":"M. Nougue Michel",
    "wof:placetype":"venue"
},
  "geometry": {"coordinates":[0.039158,43.388786],"type":"Point"}
}