{
  "type": "Feature",
  "properties": {
    "iso:country":"FR",
    "sg:address":"24 Avenue Marcel Dassault 86580 Biard",
    "sg:classifiers":[
        {
            "category":"Manufacturing",
            "subcategory":"Aerospace",
            "type":"Manufacturing & Wholesale Goods"
        }
    ],
    "sg:phone":"+33 5 49 37 62 00",
    "sg:postcode":"86580",
    "sg:province":"Poitou-Charentes",
    "sg:tags":[
        "equipment",
        "aeronautic",
        "transport",
        "vehicle"
    ],
    "wof:name":"Dassault Aviation",
    "wof:placetype":"venue"
},
  "geometry": {"coordinates":[0.311735,46.596939],"type":"Point"}
}