{
  "type": "Feature",
  "properties": {
    "addr:full":"B.P. 472, 50002 Saint L\u00f4 C\u00e9dex^^12, Rue du Belle, 50000 Saint L\u00f4 Saint-L\u00f4 Basse Normandie 50000",
    "addr:housenumber":"b.p. 472",
    "addr:postcode":"50002;50000;saint-lo\u0302;50000",
    "addr:street":"Rue Du Belle",
    "iso:country":"FR",
    "sg:address":"B.P. 472, 50002 Saint L\u00f4 C\u00e9dex^^12, Rue du Belle, 50000 Saint L\u00f4",
    "sg:city":"Saint-L\u00f4",
    "sg:orig_category":"Non-Classified Establishments",
    "sg:phone":"+33 2 33 57 14 23",
    "sg:postcode":"50000",
    "sg:province":"Basse Normandie",
    "wof:name":"Soci\u00e9t\u00e9 Des Constructions De L'ouest S.a.",
    "wof:placetype":"venue"
},
  "geometry": {"coordinates":[-1.073094,49.09045],"type":"Point"}
}