{
  "type": "Feature",
  "properties": {
    "iso:country":"FR",
    "sg:address":"96 Av Du Ch\u00e2teau 95310 Saint Ouen L'Aumone",
    "sg:classifiers":[
        {
            "category":"Food & Beverages",
            "subcategory":"Dairy",
            "type":"Retail Goods"
        }
    ],
    "sg:phone":"+33 1 30 37 80 04",
    "sg:postcode":"95310",
    "sg:province":"Ile de France",
    "sg:tags":[
        "cake",
        "product",
        "related",
        "bread"
    ],
    "wof:name":"L'art Du Sorbet",
    "wof:placetype":"venue"
},
  "geometry": {"coordinates":[1.195581,49.690762],"type":"Point"}
}