{
  "type": "Feature",
  "properties": {
    "iso:country":"FR",
    "sg:address":"14, Quatri\u00e8me Avenue - ZI, 13127 Vitrolles",
    "sg:orig_category":"Non-Classified Establishments",
    "sg:phone":"+33 4 42 89 09 33",
    "sg:province":"Provence-Alpes-C\u00f4te d'Azur",
    "wof:name":"Paindor Provence S.a.",
    "wof:placetype":"venue"
},
  "geometry": {"coordinates":[5.243537,43.425232],"type":"Point"}
}