{
  "type": "Feature",
  "properties": {
    "iso:country":"FR",
    "sg:address":"85 Bd De La R\u00e9publique 17076 La Rochelle Cedex 09",
    "sg:city":"La Rochelle",
    "sg:classifiers":[
        {
            "category":"Banks & Credit Unions",
            "subcategory":"Financial Services",
            "type":"Services"
        }
    ],
    "sg:phone":"+33 5 46 27 47 00",
    "sg:postcode":"17000",
    "sg:province":"Poitou-Charentes",
    "sg:tags":[
        "banking",
        "insurance",
        "institution",
        "finance"
    ],
    "wof:name":"Centre Departemental Gestion Fonction Publique",
    "wof:placetype":"venue"
},
  "geometry": {"coordinates":[-1.15283,46.161812],"type":"Point"}
}