{
  "type": "Feature",
  "properties": {
    "addr:full":"Bois De Chante Merle Centre Commercial Chante Merle 16400 La Couronne Poitou-Charentes 16400",
    "addr:housenumber":"16400",
    "addr:postcode":"couronne;16400",
    "addr:street":"Bois De Chante Merle Centre;Merle",
    "iso:country":"FR",
    "sg:address":"Bois De Chante Merle Centre Commercial Chante Merle 16400 La Couronne",
    "sg:classifiers":[
        {
            "category":"Farming",
            "subcategory":"Farm",
            "type":"Manufacturing & Wholesale Goods"
        }
    ],
    "sg:phone":"+33 5 45 67 17 77",
    "sg:postcode":"16400",
    "sg:province":"Poitou-Charentes",
    "sg:tags":[
        "horticulture",
        "agriculture",
        "livestock"
    ],
    "wof:name":"Plantes Et Loisirs",
    "wof:placetype":"venue"
},
  "geometry": {"coordinates":[0.102157,45.608215],"type":"Point"}
}