{
  "type": "Feature",
  "properties": {
    "iso:country":"FR",
    "sg:address":"70, Rue Ernest Sauvestre, 44400 Rez\u00e9",
    "sg:orig_category":"Unclassifiable Establishments",
    "sg:phone":"+33 2 51 70 27 14",
    "sg:province":"Pays de Loire",
    "wof:name":"Gilbert Guilbaud S.a.",
    "wof:placetype":"venue"
},
  "geometry": {"coordinates":[-1.542545,47.163593],"type":"Point"}
}