{
  "type": "Feature",
  "properties": {
    "addr:full":"Av. du Mirail - B\u00e2t. C Toulouse Midi Pyr\u00e9n\u00e9es 31100",
    "addr:housenumber":"ba\u0302t c",
    "addr:postcode":"31100",
    "addr:street":"Av. Du Mirail",
    "iso:country":"FR",
    "sg:address":"Av. du Mirail - B\u00e2t. C",
    "sg:city":"Toulouse",
    "sg:orig_category":"Non-Classified Establishments",
    "sg:phone":"+33 5 61 76 11 33",
    "sg:postcode":"31100",
    "sg:province":"Midi Pyr\u00e9n\u00e9es",
    "wof:name":"Franciaflex Industrie S.a.",
    "wof:placetype":"venue"
},
  "geometry": {"coordinates":[1.391091,43.569614],"type":"Point"}
}