{
  "type": "Feature",
  "properties": {
    "addr:full":"150, Quai de la Souys, 33270 Floirac Floirac Aquitaine 33270",
    "addr:housenumber":"150",
    "addr:postcode":"33270;33270",
    "addr:street":"Quai De La Souys",
    "iso:country":"FR",
    "sg:address":"150, Quai de la Souys, 33270 Floirac",
    "sg:city":"Floirac",
    "sg:orig_category":"Unclassifiable Establishments",
    "sg:phone":"+33 5 56 86 47 29",
    "sg:postcode":"33270",
    "sg:province":"Aquitaine",
    "wof:name":"Dimatrap S.a.",
    "wof:placetype":"venue"
},
  "geometry": {"coordinates":[-0.533845,44.823639],"type":"Point"}
}