{
  "type": "Feature",
  "properties": {
    "iso:country":"FR",
    "sg:address":"25 Rue Des Processions 93130 Noisy Le Sec",
    "sg:classifiers":[
        {
            "category":"Manufacturing",
            "subcategory":"Metals",
            "type":"Manufacturing & Wholesale Goods"
        }
    ],
    "sg:phone":"+33 1 48 59 82 80",
    "sg:postcode":"93130",
    "sg:province":"Ile de France",
    "sg:tags":[
        "metallurgy",
        "metalworking",
        "processing"
    ],
    "wof:name":"Repoussage Et Industries Sa",
    "wof:placetype":"venue"
},
  "geometry": {"coordinates":[2.456759,48.878674],"type":"Point"}
}