{
  "type": "Feature",
  "properties": {
    "addr:full":"89 Av Du Progr\u00e8s 69680 Chassieu Rhone-Alpes 69680",
    "addr:postcode":"69680;69680",
    "addr:street":"89 Av Du Progre\u0300S",
    "iso:country":"FR",
    "sg:address":"89 Av Du Progr\u00e8s 69680 Chassieu",
    "sg:classifiers":[
        {
            "category":"Shopping",
            "type":"Retail Goods"
        }
    ],
    "sg:phone":"+33 4 78 90 33 43",
    "sg:postcode":"69680",
    "sg:province":"Rhone-Alpes",
    "sg:tags":[
        "metallurgy",
        "finished",
        "-",
        "metalworking",
        "metallic"
    ],
    "wof:name":"Mvi",
    "wof:placetype":"venue"
},
  "geometry": {"coordinates":[4.963106,45.725864],"type":"Point"}
}