{
  "type": "Feature",
  "properties": {
    "addr:full":"2, Rue Louis Armand - Tour Objectif, 92600 Asni\u00e8res sur Seine Ile de France 92600",
    "addr:housenumber":"2",
    "addr:postcode":"92600;92600",
    "addr:street":"Rue Louis Armand Tour Objectif",
    "iso:country":"FR",
    "sg:address":"2, Rue Louis Armand - Tour Objectif, 92600 Asni\u00e8res sur Seine",
    "sg:orig_category":"Non-Classified Establishments",
    "sg:phone":"+33 1 41 32 91 11",
    "sg:postcode":"92600",
    "sg:province":"Ile de France",
    "wof:name":"E.d.f. G.d.f. Services Asni\u00e8res",
    "wof:placetype":"venue"
},
  "geometry": {"coordinates":[2.310119,48.916004],"type":"Point"}
}