{
  "type": "Feature",
  "properties": {
    "addr:full":"B.P. 222, 22602 Loud\u00e9ac C\u00e9dex^^47, Rue Notre Dame, 22600 Loud\u00e9ac Loud\u00e9ac Bretagne 22600",
    "addr:housenumber":"b.p. 222",
    "addr:postcode":"22602;22600;22600",
    "addr:street":"Rue Notre Dame",
    "iso:country":"FR",
    "sg:address":"B.P. 222, 22602 Loud\u00e9ac C\u00e9dex^^47, Rue Notre Dame, 22600 Loud\u00e9ac",
    "sg:city":"Loud\u00e9ac",
    "sg:orig_category":"Non-Classified Establishments",
    "sg:phone":"+33 2 96 28 37 50",
    "sg:postcode":"22600",
    "sg:province":"Bretagne",
    "wof:name":"C.c.i. - Chambre Du Commerce Et De L'industrie",
    "wof:placetype":"venue"
},
  "geometry": {"coordinates":[-2.773909,48.113571],"type":"Point"}
}