{
  "type": "Feature",
  "properties": {
    "addr:full":"11, Rue Auguste Mouni\u00e9, 92160 Antony Ile de France",
    "addr:housenumber":"11",
    "addr:postcode":"92160",
    "addr:street":"Rue Auguste Mounie\u0301",
    "iso:country":"FR",
    "sg:address":"11, Rue Auguste Mouni\u00e9, 92160 Antony",
    "sg:orig_category":"Unclassifiable Establishments",
    "sg:phone":"+33 1 40 96 91 21",
    "sg:province":"Ile de France",
    "wof:name":"Alcyr S.a.r.l.",
    "wof:placetype":"venue"
},
  "geometry": {"coordinates":[2.303638,48.753574],"type":"Point"}
}