{
  "type": "Feature",
  "properties": {
    "addr:full":"Chemin Rochelais 17290 AIGREFEUILLE D AUNIS Poitou-Charentes",
    "addr:postcode":"17290",
    "addr:street":"Chemin Rochelais",
    "iso:country":"FR",
    "sg:address":"Chemin Rochelais 17290 AIGREFEUILLE D AUNIS",
    "sg:classifiers":[
        {
            "category":"Structure",
            "subcategory":"Building",
            "type":"Public Place"
        }
    ],
    "sg:phone":"+33 5 46 27 56 56",
    "sg:province":"Poitou-Charentes",
    "sg:tags":[
        "attic",
        "addition",
        "finishing",
        "roof",
        "trusses"
    ],
    "wof:name":"Charpent Emballa Menuiserie Sarl",
    "wof:placetype":"venue"
},
  "geometry": {"coordinates":[-0.943369,46.110168],"type":"Point"}
}