{
  "type": "Feature",
  "properties": {
    "addr:full":"Place Fernand Pouillon Valence Midi Pyr\u00e9n\u00e9es 26000",
    "addr:postcode":"26000",
    "addr:street":"Place Fernand Pouillon",
    "iso:country":"FR",
    "sg:address":"Place Fernand Pouillon",
    "sg:city":"Valence",
    "sg:orig_category":"Unclassifiable Establishments",
    "sg:phone":"+33 4 75 43 32 07",
    "sg:postcode":"26000",
    "sg:province":"Midi Pyr\u00e9n\u00e9es",
    "wof:name":"S.a.i.p. S.a. - Soci\u00e9t\u00e9 D'application Industrielles Et Polyur\u00e9tha",
    "wof:placetype":"venue"
},
  "geometry": {"coordinates":[4.924913,44.949818],"type":"Point"}
}