{
  "type": "Feature",
  "properties": {
    "addr:full":"Chateau De Fesles 49380 Thouarce Pays de Loire 49380",
    "addr:postcode":"49380;49380",
    "addr:street":"Thouarce",
    "iso:country":"FR",
    "sg:address":"Chateau De Fesles 49380 Thouarce",
    "sg:classifiers":[
        {
            "category":"Food Court",
            "type":"Food & Drink"
        }
    ],
    "sg:phone":"+33 2 41 68 94 00",
    "sg:postcode":"49380",
    "sg:province":"Pays de Loire",
    "sg:tags":[
        "product",
        "related"
    ],
    "wof:name":"Sa De Fesles",
    "wof:placetype":"venue"
},
  "geometry": {"coordinates":[-0.504057,47.2673],"type":"Point"}
}