{
  "type": "Feature",
  "properties": {
    "iso:country":"FR",
    "sg:address":"21, Av. du Phare, 33700 M\u00e9rignac",
    "sg:city":"M\u00e9rignac",
    "sg:orig_category":"Unclassifiable Establishments",
    "sg:phone":"+33 5 56 34 19 55",
    "sg:postcode":"33700",
    "sg:province":"Aquitaine",
    "wof:name":"Sabi S.a.r.l.",
    "wof:placetype":"venue"
},
  "geometry": {"coordinates":[-0.693644,44.853409],"type":"Point"}
}