{
  "type": "Feature",
  "properties": {
    "addr:full":"530, Chemin du Riou - Quartier Bramafan, 06740 Ch\u00e2teauneuf Grasse Corse",
    "addr:housenumber":"530",
    "addr:postcode":"06740",
    "addr:street":"Chemin Du Riou",
    "iso:country":"FR",
    "sg:address":"530, Chemin du Riou - Quartier Bramafan, 06740 Ch\u00e2teauneuf Grasse",
    "sg:orig_category":"Non-Classified Establishments",
    "sg:phone":"+33 4 93 60 04 40",
    "sg:province":"Corse",
    "wof:name":"Cefira S.a.r.l.",
    "wof:placetype":"venue"
},
  "geometry": {"coordinates":[6.975437,43.667526],"type":"Point"}
}