{
  "type": "Feature",
  "properties": {
    "addr:full":"Zone Industrielle Pesmes Franche Comt\u00e9 70140",
    "addr:postcode":"70140",
    "addr:street":"Zone Industrielle;Franche Comte\u0301",
    "iso:country":"FR",
    "sg:address":"Zone Industrielle",
    "sg:city":"Pesmes",
    "sg:orig_category":"Unclassifiable Establishments",
    "sg:phone":"+33 3 80 46 56 32",
    "sg:postcode":"70140",
    "sg:province":"Franche Comt\u00e9",
    "wof:name":"Clarilac S.a.",
    "wof:placetype":"venue"
},
  "geometry": {"coordinates":[5.508498,47.313107],"type":"Point"}
}