{
  "type": "Feature",
  "properties": {
    "addr:full":"28 bis, Rue la Fontaine - ZI La Perri\u00e8re, 35340 Liffr\u00e9 Liffr\u00e9 Bretagne 35340",
    "addr:housenumber":"28 bis",
    "addr:postcode":"35340;35340",
    "addr:street":"Rue La Fontaine Zi",
    "iso:country":"FR",
    "sg:address":"28 bis, Rue la Fontaine - ZI La Perri\u00e8re, 35340 Liffr\u00e9",
    "sg:city":"Liffr\u00e9",
    "sg:orig_category":"Non-Classified Establishments",
    "sg:phone":"+33 2 99 68 64 43",
    "sg:postcode":"35340",
    "sg:province":"Bretagne",
    "wof:name":"Actisols S.a.r.l.",
    "wof:placetype":"venue"
},
  "geometry": {"coordinates":[-1.438089,48.183979],"type":"Point"}
}