{
  "type": "Feature",
  "properties": {
    "addr:full":"3, Rue des Vignes, 68027 Colmar C\u00e9dex Alsace",
    "addr:housenumber":"3",
    "addr:postcode":"68027",
    "addr:street":"Rue Des Vignes;Ce\u0301Dex",
    "iso:country":"FR",
    "sg:address":"3, Rue des Vignes, 68027 Colmar C\u00e9dex",
    "sg:orig_category":"Unclassifiable Establishments",
    "sg:phone":"+33 3 89 79 19 21",
    "sg:province":"Alsace",
    "wof:name":"Schoenenberger S.a.",
    "wof:placetype":"venue"
},
  "geometry": {"coordinates":[7.344918,48.085365],"type":"Point"}
}