{
  "type": "Feature",
  "properties": {
    "iso:country":"FR",
    "sg:address":"25, Av du Pr\u00e9sident Roosevelt, 01100 Oyonnax",
    "sg:orig_category":"Unclassifiable Establishments",
    "sg:phone":"+33 4 74 81 86 20",
    "sg:postcode":"01100",
    "sg:province":"Rhone-Alpes",
    "wof:name":"M.f.i. Cr\u00e9ations S.a.",
    "wof:placetype":"venue"
},
  "geometry": {"coordinates":[5.655028,46.262516],"type":"Point"}
}