{
  "type": "Feature",
  "properties": {
    "addr:full":"1 Rue Francois Arago 78190 Trappes Ile de France 78190",
    "addr:housenumber":"1",
    "addr:postcode":"78190;ile;78190",
    "addr:street":"Rue Francois Arago;France",
    "iso:country":"FR",
    "sg:address":"1 Rue Francois Arago 78190 Trappes",
    "sg:classifiers":[
        {
            "category":"Shopping",
            "type":"Retail Goods"
        }
    ],
    "sg:phone":"+33 1 34 82 84 00",
    "sg:postcode":"78190",
    "sg:province":"Ile de France",
    "sg:tags":[
        "metallurgy",
        "finished",
        "-",
        "metalworking",
        "metallic"
    ],
    "wof:name":"Le Petit Ressort De Precision",
    "wof:placetype":"venue"
},
  "geometry": {"coordinates":[1.97664,48.757671],"type":"Point"}
}