{
  "type": "Feature",
  "properties": {
    "iso:country":"FR",
    "sg:address":"4 Rue Jacques De Vaucanson 60200 Compi\u00e8gne",
    "sg:classifiers":[
        {
            "category":"Professional",
            "type":"Services"
        }
    ],
    "sg:phone":"+33 3 44 23 23 33",
    "sg:province":"Picardie",
    "sg:tags":[
        "transport",
        "road"
    ],
    "wof:name":"Van Der Graaf Sa",
    "wof:placetype":"venue"
},
  "geometry": {"coordinates":[2.787879,49.393848],"type":"Point"}
}