{
  "type": "Feature",
  "properties": {
    "addr:full":"St Lambert 33250 Pauillac Pauillac Aquitaine 33250",
    "addr:postcode":"33250;33250",
    "addr:street":"St",
    "iso:country":"FR",
    "sg:address":"St Lambert 33250 Pauillac",
    "sg:city":"Pauillac",
    "sg:classifiers":[
        {
            "category":"Food Court",
            "type":"Food & Drink"
        }
    ],
    "sg:phone":"+33 5 56 59 19 40",
    "sg:postcode":"33250",
    "sg:province":"Aquitaine",
    "sg:tags":[
        "product",
        "related"
    ],
    "wof:name":"Ch\u00c2teau Pichon Longueville Comtesse De Lalande",
    "wof:placetype":"venue"
},
  "geometry": {"coordinates":[-0.753279,45.179375],"type":"Point"}
}