{
  "type": "Feature",
  "properties": {
    "addr:full":"27, Rue Carnot, 92300 Levallois Perret Ile de France",
    "addr:housenumber":"27",
    "addr:postcode":"92300;ile",
    "addr:street":"Rue Carnot",
    "iso:country":"FR",
    "sg:address":"27, Rue Carnot, 92300 Levallois Perret",
    "sg:orig_category":"Non-Classified Establishments",
    "sg:phone":"+33 1 47 58 89 39",
    "sg:province":"Ile de France",
    "wof:name":"T\u00e9l\u00e9pizza France S.a.",
    "wof:placetype":"venue"
},
  "geometry": {"coordinates":[2.288046,48.889999],"type":"Point"}
}