{
  "type": "Feature",
  "properties": {
    "iso:country":"FR",
    "sg:address":"2, All\u00e9e Baltard, 87220 Feytiat",
    "sg:orig_category":"Unclassifiable Establishments",
    "sg:phone":"+33 5 55 31 02 00",
    "sg:province":"Limousin",
    "wof:name":"Galtier S.a.",
    "wof:placetype":"venue"
},
  "geometry": {"coordinates":[1.323045,45.736263],"type":"Point"}
}