{
  "type": "Feature",
  "properties": {
    "addr:full":"2, All\u00e9e Baltard, 87220 Feytiat Limousin",
    "addr:housenumber":"2",
    "addr:postcode":"87220",
    "addr:street":"Alle\u0301E Baltard",
    "iso:country":"FR",
    "sg:address":"2, All\u00e9e Baltard, 87220 Feytiat",
    "sg:orig_category":"Unclassifiable Establishments",
    "sg:phone":"+33 5 55 31 02 00",
    "sg:province":"Limousin",
    "wof:name":"Galtier S.a.",
    "wof:placetype":"venue"
},
  "geometry": {"coordinates":[1.323045,45.736263],"type":"Point"}
}