{
  "type": "Feature",
  "properties": {
    "addr:full":"77 R Gabriel P\u00e9ri 94120 Fontenay Sous Bois Ile de France 94120",
    "addr:housenumber":"77",
    "addr:postcode":"94120;94120",
    "addr:street":"R Gabriel Pe\u0301Ri;Bois Ile De France",
    "iso:country":"FR",
    "sg:address":"77 R Gabriel P\u00e9ri 94120 Fontenay Sous Bois",
    "sg:classifiers":[
        {
            "category":"Communications",
            "type":"Services"
        }
    ],
    "sg:phone":"+33 1 45 14 03 50",
    "sg:postcode":"94120",
    "sg:province":"Ile de France",
    "sg:tags":[
        "advice",
        "interpretation",
        "translation",
        "business"
    ],
    "wof:name":"A A T Sarl",
    "wof:placetype":"venue"
},
  "geometry": {"coordinates":[2.448422,48.846638],"type":"Point"}
}