{
  "type": "Feature",
  "properties": {
    "addr:full":"13, Rue Bonnet, 92110 Clichy Ile de France 92110",
    "addr:housenumber":"13",
    "addr:postcode":"92110;92110",
    "addr:street":"Rue Bonnet;Ile De France",
    "iso:country":"FR",
    "sg:address":"13, Rue Bonnet, 92110 Clichy",
    "sg:orig_category":"Non-Classified Establishments",
    "sg:phone":"+33 1 47 37 11 28",
    "sg:postcode":"92110",
    "sg:province":"Ile de France",
    "wof:name":"Burgunder Cie D\u00e9colletage S.a.",
    "wof:placetype":"venue"
},
  "geometry": {"coordinates":[2.309558,48.898136],"type":"Point"}
}