{
  "type": "Feature",
  "properties": {
    "addr:full":"Rue Orl\u00e9ans 51120 S\u00e9zanne Champagne",
    "addr:postcode":"51120",
    "addr:street":"Rue Orle\u0301Ans",
    "iso:country":"FR",
    "sg:address":"Rue Orl\u00e9ans 51120 S\u00e9zanne",
    "sg:classifiers":[
        {
            "category":"Professional",
            "type":"Services"
        }
    ],
    "sg:phone":"+33 3 26 80 66 68",
    "sg:province":"Champagne",
    "sg:tags":[
        "transport",
        "road"
    ],
    "wof:name":"Societe Des Transports Rosier Sa",
    "wof:placetype":"venue"
},
  "geometry": {"coordinates":[3.7288,48.709637],"type":"Point"}
}