{
  "type": "Feature",
  "properties": {
    "addr:full":"5 Rue Du Lieutenant Naucourt 01100 Oyonnax Rhone-Alpes 01100",
    "addr:housenumber":"5",
    "addr:postcode":"01100;01100",
    "addr:street":"Rue Du Lieutenant Naucourt",
    "iso:country":"FR",
    "sg:address":"5 Rue Du Lieutenant Naucourt 01100 Oyonnax",
    "sg:classifiers":[
        {
            "category":"Wholesale",
            "subcategory":"Medical Equipment & Supplies",
            "type":"Manufacturing & Wholesale Goods"
        }
    ],
    "sg:phone":"+33 4 74 81 22 00",
    "sg:postcode":"01100",
    "sg:province":"Rhone-Alpes",
    "sg:tags":[
        "instrument",
        "health",
        "-",
        "precision"
    ],
    "wof:name":"Alain Sartorio Sa",
    "wof:placetype":"venue"
},
  "geometry": {"coordinates":[5.662393,46.261066],"type":"Point"}
}