{
  "type": "Feature",
  "properties": {
    "iso:country":"FR",
    "sg:address":"10, Bd de l'Industrie, 41400 Montrichard",
    "sg:city":"Montrichard",
    "sg:orig_category":"Non-Classified Establishments",
    "sg:phone":"+33 2 54 32 47 48",
    "sg:postcode":"41400",
    "sg:province":"Centre",
    "wof:name":"Confinoble Tradition S.a.r.l.",
    "wof:placetype":"venue"
},
  "geometry": {"coordinates":[1.177948,47.357246],"type":"Point"}
}