{
  "type": "Feature",
  "properties": {
    "addr:full":"123 all\u00e9e Du B\u00e9n\u00e9lux 62118 MONCHY LE PREUX Nord Pas-de-Calais",
    "addr:housenumber":"123",
    "addr:postcode":"62118",
    "addr:street":"Alle\u0301E Du Be\u0301Ne\u0301Lux;Preux Nord",
    "iso:country":"FR",
    "sg:address":"123 all\u00e9e Du B\u00e9n\u00e9lux 62118 MONCHY LE PREUX",
    "sg:classifiers":[
        {
            "category":"Home & Garden",
            "subcategory":"Hardware",
            "type":"Retail Goods"
        }
    ],
    "sg:phone":"+33 3 21 50 48 49",
    "sg:province":"Nord Pas-de-Calais",
    "sg:tags":[
        "seed",
        "potato"
    ],
    "wof:name":"Desmazieres-artois Bapaume Sa",
    "wof:placetype":"venue"
},
  "geometry": {"coordinates":[2.86187,50.274788],"type":"Point"}
}