{
  "type": "Feature",
  "properties": {
    "iso:country":"FR",
    "sg:address":"90, Rue Cuvier, 83150 Bandol",
    "sg:orig_category":"Unclassifiable Establishments",
    "sg:phone":"+33 4 94 29 79 80",
    "sg:province":"Provence-Alpes-C\u00f4te d'Azur",
    "wof:name":"B\u00e9raud Michel",
    "wof:placetype":"venue"
},
  "geometry": {"coordinates":[5.758116,43.140881],"type":"Point"}
}