{
  "type": "Feature",
  "properties": {
    "iso:country":"FR",
    "sg:address":"Rue Des Zagots 58260 La Machine",
    "sg:city":"La Machine",
    "sg:classifiers":[
        {
            "category":"Building & Trades",
            "subcategory":"Pest Control",
            "type":"Services"
        }
    ],
    "sg:phone":"+33 3 86 50 81 64",
    "sg:postcode":"58260",
    "sg:province":"Bourgogne",
    "sg:tags":[
        "metallurgy",
        "sheet",
        "-",
        "metalworking",
        "pipe",
        "engineering",
        "machine",
        "mechanical"
    ],
    "wof:name":"Mecamachine Sa",
    "wof:placetype":"venue"
},
  "geometry": {"coordinates":[3.458923,46.89312],"type":"Point"}
}