{
  "type": "Feature",
  "properties": {
    "iso:country":"FR",
    "sg:address":"Les Tremelieres Communaute Urbaine Du Mans 72700 Allonnes",
    "sg:classifiers":[
        {
            "category":"Manufacturing",
            "subcategory":"Motor Vehicles & Parts",
            "type":"Manufacturing & Wholesale Goods"
        }
    ],
    "sg:phone":"+33 2 43 83 90 00",
    "sg:postcode":"72700",
    "sg:province":"Pays de Loire",
    "sg:tags":[
        "engine",
        "machine",
        "engineering",
        "-",
        "mechanical"
    ],
    "wof:name":"Ntn Transmissions Europe",
    "wof:placetype":"venue"
},
  "geometry": {"coordinates":[0.150345,47.923435],"type":"Point"}
}