{
  "type": "Feature",
  "properties": {
    "addr:full":"47, Rue des Juifs, 21500 Saint-R\u00e9my Saint-R\u00e9my Bourgogne 21500",
    "addr:housenumber":"47",
    "addr:postcode":"21500;21500",
    "addr:street":"Rue Des Juifs",
    "iso:country":"FR",
    "sg:address":"47, Rue des Juifs, 21500 Saint-R\u00e9my",
    "sg:city":"Saint-R\u00e9my",
    "sg:orig_category":"Non-Classified Establishments",
    "sg:phone":"+33 3 80 92 15 10",
    "sg:postcode":"21500",
    "sg:province":"Bourgogne",
    "wof:name":"E.m.i. Bourgogne S.a.r.l.",
    "wof:placetype":"venue"
},
  "geometry": {"coordinates":[4.300267,47.643871],"type":"Point"}
}