{
  "type": "Feature",
  "properties": {
    "addr:full":"71 Rue Des Tilleuls 92771 Boulogne Billancourt Cedex Ancourt Haute Normandie 76370",
    "addr:housenumber":"71",
    "addr:postcode":"92771;76370",
    "addr:street":"Rue Des Tilleuls;Haute Normandie",
    "iso:country":"FR",
    "sg:address":"71 Rue Des Tilleuls 92771 Boulogne Billancourt Cedex",
    "sg:city":"Ancourt",
    "sg:classifiers":[
        {
            "category":"Professional",
            "subcategory":"Business Services",
            "type":"Services"
        }
    ],
    "sg:phone":"+33 1 41 86 41 86",
    "sg:postcode":"76370",
    "sg:province":"Haute Normandie",
    "sg:tags":[
        "travel",
        "fair"
    ],
    "wof:name":"Adhesion Group",
    "wof:placetype":"venue"
},
  "geometry": {"coordinates":[2.236626,48.844971],"type":"Point"}
}