{
  "type": "Feature",
  "properties": {
    "addr:full":"16, Rue Marc Boillet, 71150 Chagny Chagny Bourgogne 71150",
    "addr:housenumber":"16",
    "addr:postcode":"71150;71150",
    "addr:street":"Rue Marc Boillet",
    "iso:country":"FR",
    "sg:address":"16, Rue Marc Boillet, 71150 Chagny",
    "sg:city":"Chagny",
    "sg:orig_category":"Non-Classified Establishments",
    "sg:phone":"+33 3 85 91 22 66",
    "sg:postcode":"71150",
    "sg:province":"Bourgogne",
    "wof:name":"C.g.c. Conseil S.a.r.l. - Communication Gestion Commercialisation Conseil",
    "wof:placetype":"venue"
},
  "geometry": {"coordinates":[4.75605,46.9086],"type":"Point"}
}