{
  "type": "Feature",
  "properties": {
    "addr:full":"55, Chemin des meules, 81100 Castres Midi Pyr\u00e9n\u00e9es",
    "addr:housenumber":"55",
    "addr:postcode":"81100",
    "addr:street":"Chemin Des Meules",
    "iso:country":"FR",
    "sg:address":"55, Chemin des meules, 81100 Castres",
    "sg:orig_category":"Unclassifiable Establishments",
    "sg:phone":"+33 5 63 62 57 00",
    "sg:province":"Midi Pyr\u00e9n\u00e9es",
    "wof:name":"Siminor Ascenceurs S.a.",
    "wof:placetype":"venue"
},
  "geometry": {"coordinates":[2.26771,43.61079],"type":"Point"}
}