{
  "type": "Feature",
  "properties": {
    "iso:country":"FR",
    "sg:address":"3 Av Du Canada 91958 Ulis Courtaboeuf Cedex",
    "sg:classifiers":[
        {
            "category":"Utilities",
            "subcategory":"Telephone",
            "type":"Services"
        }
    ],
    "sg:phone":"+33 1 64 86 64 00",
    "sg:province":"Aquitaine",
    "sg:tags":[
        "telecommunication"
    ],
    "wof:name":"Motorola Sa",
    "wof:placetype":"venue"
},
  "geometry": {"coordinates":[-96.582092,62.35873],"type":"Point"}
}