{
  "type": "Feature",
  "properties": {
    "addr:full":"15, Rue du Petit Fief, 91700 Sainte Genevi\u00e8ve des Bois Ile de France",
    "addr:housenumber":"15",
    "addr:postcode":"91700",
    "addr:street":"Rue Du Petit Fief;Des Bois Ile De France",
    "iso:country":"FR",
    "sg:address":"15, Rue du Petit Fief, 91700 Sainte Genevi\u00e8ve des Bois",
    "sg:orig_category":"Unclassifiable Establishments",
    "sg:phone":"+33 1 69 25 00 50",
    "sg:province":"Ile de France",
    "wof:name":"Thierry S.a.",
    "wof:placetype":"venue"
},
  "geometry": {"coordinates":[2.340615,48.622581],"type":"Point"}
}