{
  "type": "Feature",
  "properties": {
    "iso:country":"FR",
    "sg:address":"B.P. 29, 59450 Sin le Noble^^386, Rue des Fusill\u00e9s, 59450 Sin le Noble",
    "sg:orig_category":"Non-Classified Establishments",
    "sg:phone":"+33 3 27 94 40 00",
    "sg:postcode":"59450",
    "sg:province":"Nord Pas-de-Calais",
    "wof:name":"Daussy Fr\u00e8res S.a.",
    "wof:placetype":"venue"
},
  "geometry": {"coordinates":[3.11248,50.364014],"type":"Point"}
}