{
  "type": "Feature",
  "properties": {
    "iso:country":"FR",
    "sg:address":"44, Bd de Lorraine, 57500 Saint Avold",
    "sg:orig_category":"CAO, DAO-calculs Ing\u00e9nierie: Bureau d'\u00e9tudes, assistance technique, conception, \u00e9tudes de tuyauterie",
    "sg:phone":"+33 3 87 91 39 49",
    "sg:postcode":"57500",
    "sg:province":"Lorraine",
    "wof:name":"Auxitec Industrie",
    "wof:placetype":"venue"
},
  "geometry": {"coordinates":[6.709636,49.10651],"type":"Point"}
}