{
  "type": "Feature",
  "properties": {
    "iso:country":"FR",
    "sg:address":"B.P. 56, 67242 Bischwiller C\u00e9dex^^Chemin de la Chartreuse, 67240 Bischwiller",
    "sg:city":"Bischwiller",
    "sg:orig_category":"Non-Classified Establishments",
    "sg:phone":"+33 3 88 06 23 23",
    "sg:postcode":"67240",
    "sg:province":"Alsace",
    "wof:name":"Nt Normbau France S.a.",
    "wof:placetype":"venue"
},
  "geometry": {"coordinates":[7.85912,48.768261],"type":"Point"}
}