{
  "type": "Feature",
  "properties": {
    "iso:country":"FR",
    "sg:address":"51 rue Jacques Mugnier 68200 Mulhouse",
    "sg:city":"Mulhouse",
    "sg:classifiers":[
        {
            "category":"Structure",
            "subcategory":"Office Building",
            "type":"Public Place"
        }
    ],
    "sg:phone":"+33 3 89 59 10 56",
    "sg:postcode":"68200",
    "sg:province":"Alsace",
    "sg:tags":[
        "energy",
        "system",
        "analysis"
    ],
    "wof:name":"Stepper Energie France Sa",
    "wof:placetype":"venue"
},
  "geometry": {"coordinates":[7.289908,47.729671],"type":"Point"}
}