{
  "type": "Feature",
  "properties": {
    "addr:full":"48 av Francis Tonner; Cannes",
    "addr:street":"48 Av Francis Tonner",
    "iso:country":"FR",
    "sg:address":"48 av Francis Tonner; Cannes",
    "sg:classifiers":[
        {
            "category":"Banks & Credit Unions",
            "subcategory":"Bank",
            "type":"Services"
        }
    ],
    "sg:phone":"+33 3393472867",
    "wof:name":"Cr\u00e9dit Lyonnais",
    "wof:placetype":"venue"
},
  "geometry": {"coordinates":[6.980142,43.54953],"type":"Point"}
}