{
  "type": "Feature",
  "properties": {
    "addr:full":"67, Cours Emile Zola, 69100 Villeurbanne Rhone-Alpes 69100",
    "addr:housenumber":"67",
    "addr:postcode":"69100;69100",
    "addr:street":"Cours Emile Zola",
    "iso:country":"FR",
    "sg:address":"67, Cours Emile Zola, 69100 Villeurbanne",
    "sg:orig_category":"Unclassifiable Establishments",
    "sg:phone":"+33 4 72 69 50 50",
    "sg:postcode":"69100",
    "sg:province":"Rhone-Alpes",
    "wof:name":"G.t. S.a. - G\u00e9n\u00e9ral Transmission",
    "wof:placetype":"venue"
},
  "geometry": {"coordinates":[4.868491,45.771049],"type":"Point"}
}