{
  "type": "Feature",
  "properties": {
    "addr:full":"Chemin de la For\u00eat Montcy Notre Dame Champagne 08090",
    "addr:postcode":"08090",
    "addr:street":"Chemin De La Fore\u0302T",
    "iso:country":"FR",
    "sg:address":"Chemin de la For\u00eat",
    "sg:city":"Montcy Notre Dame",
    "sg:orig_category":"Non-Classified Establishments",
    "sg:phone":"+33 3 24 54 29 87",
    "sg:postcode":"08090",
    "sg:province":"Champagne",
    "wof:name":"Scierie L.p.c. S.a.r.l.",
    "wof:placetype":"venue"
},
  "geometry": {"coordinates":[4.744926,49.783871],"type":"Point"}
}