{
  "type": "Feature",
  "properties": {
    "addr:full":"2 Gambetta 51150 Bouzy Champagne 51150",
    "addr:housenumber":"2",
    "addr:postcode":"51150;51150",
    "addr:street":"Gambetta;Champagne",
    "iso:country":"FR",
    "sg:address":"2",
    "sg:city":"Gambetta 51150 Bouzy",
    "sg:classifiers":[
        {
            "category":"Food Court",
            "type":"Food & Drink"
        }
    ],
    "sg:phone":"+33 3 26 57 01 54",
    "sg:postcode":"51150",
    "sg:province":"Champagne",
    "sg:tags":[
        "product",
        "related"
    ],
    "wof:name":"Barnaut Edmond Champagne Et Seconde Philippe",
    "wof:placetype":"venue"
},
  "geometry": {"coordinates":[4.146201,49.078411],"type":"Point"}
}