{
  "type": "Feature",
  "properties": {
    "addr:full":"607, Rue Saint pierre, 13012 Marseille Poitou-Charentes",
    "addr:housenumber":"607",
    "addr:postcode":"13012",
    "addr:street":"Rue Saint Pierre",
    "iso:country":"FR",
    "sg:address":"607, Rue Saint pierre, 13012 Marseille",
    "sg:orig_category":"Non-Classified Establishments",
    "sg:phone":"+33 4 96 12 50 00",
    "sg:province":"Poitou-Charentes",
    "wof:name":"Les Peinture Jefco S.a.",
    "wof:placetype":"venue"
},
  "geometry": {"coordinates":[5.42582,43.29018],"type":"Point"}
}