{
  "type": "Feature",
  "properties": {
    "iso:country":"FR",
    "sg:address":"B.P. 20232, 57352 Stiring Wendel C\u00e9dex^^Rue Robert Schuman - ZI de la Heid, 57350 Stiring Wendel",
    "sg:orig_category":"Non-Classified Establishments",
    "sg:phone":"+33 3 87 84 68 10",
    "sg:province":"Lorraine",
    "wof:name":"Resa S.a.r.l.",
    "wof:placetype":"venue"
},
  "geometry": {"coordinates":[6.928195,49.200981],"type":"Point"}
}