{
  "type": "Feature",
  "properties": {
    "addr:full":"35, Av. Delaville, 50100 Cherbourg Cherbourg-Octeville Basse Normandie 50100",
    "addr:postcode":"50100;50100",
    "addr:street":"35 Av. Delaville",
    "iso:country":"FR",
    "sg:address":"35, Av. Delaville, 50100 Cherbourg",
    "sg:city":"Cherbourg-Octeville",
    "sg:orig_category":"Non-Classified Establishments",
    "sg:phone":"+33 2 33 94 00 66",
    "sg:postcode":"50100",
    "sg:province":"Basse Normandie",
    "wof:name":"C.r.i.t. Int\u00e9rim S.a.",
    "wof:placetype":"venue"
},
  "geometry": {"coordinates":[-1.625551,49.635693],"type":"Point"}
}