{
  "type": "Feature",
  "properties": {
    "addr:full":"B.P. 02 Neuvelle l\u00e8s la Ch\u00e2rit\u00e9^^70130 Neuvelle l\u00e8s la Ch\u00e2rit\u00e9 Franche Comt\u00e9 70130",
    "addr:postcode":"70130",
    "addr:street":"B.P. 02;Franche Comte\u0301",
    "iso:country":"FR",
    "sg:address":"B.P. 02",
    "sg:city":"Neuvelle l\u00e8s la Ch\u00e2rit\u00e9^^70130 Neuvelle l\u00e8s la Ch\u00e2rit\u00e9",
    "sg:orig_category":"Non-Classified Establishments",
    "sg:phone":"+33 3 84 78 80 55",
    "sg:postcode":"70130",
    "sg:province":"Franche Comt\u00e9",
    "wof:name":"Transports Maillot Louis Et Fils S.a.",
    "wof:placetype":"venue"
},
  "geometry": {"coordinates":[5.876931,47.582588],"type":"Point"}
}