{
  "type": "Feature",
  "properties": {
    "addr:full":"Immeuble internationale Bat A 78180 Montigny le Bretonneux Ile de France 78180",
    "addr:housenumber":"montigny",
    "addr:postcode":"78180;78180",
    "addr:street":"Le Bretonneux Ile De France",
    "iso:country":"FR",
    "sg:address":"Immeuble internationale Bat A 78180 Montigny le Bretonneux",
    "sg:classifiers":[
        {
            "category":"Building & Trades",
            "subcategory":"Cleaning & Sanitation",
            "type":"Services"
        }
    ],
    "sg:phone":"+33 1 39 30 84 84",
    "sg:postcode":"78180",
    "sg:province":"Ile de France",
    "sg:tags":[
        "axle"
    ],
    "wof:name":"Valdunes Sas",
    "wof:placetype":"venue"
},
  "geometry": {"coordinates":[2.04549,48.785019],"type":"Point"}
}