{
  "type": "Feature",
  "properties": {
    "addr:full":"7 B, Chemin du Saquin, 69130 Ecully Rhone-Alpes",
    "addr:housenumber":"7 b",
    "addr:postcode":"69130",
    "addr:street":"Chemin Du Saquin",
    "iso:country":"FR",
    "sg:address":"7 B, Chemin du Saquin, 69130 Ecully",
    "sg:orig_category":"Unclassifiable Establishments",
    "sg:phone":"+33 4 72 18 04 04",
    "sg:province":"Rhone-Alpes",
    "wof:name":"Access Commerce S.a.",
    "wof:placetype":"venue"
},
  "geometry": {"coordinates":[4.77391,45.78474],"type":"Point"}
}