{
  "type": "Feature",
  "properties": {
    "iso:country":"FR",
    "sg:address":"Rte de Mezangers - ZI de Bray",
    "sg:city":"Evron",
    "sg:orig_category":"Unclassifiable Establishments",
    "sg:phone":"+33 2 43 01 66 51",
    "sg:postcode":"53600",
    "sg:province":"Pays de Loire",
    "wof:name":"E.s. S.a.r.l. - Energie Services",
    "wof:placetype":"venue"
},
  "geometry": {"coordinates":[-0.432901,48.132961],"type":"Point"}
}