{
  "type": "Feature",
  "properties": {
    "iso:country":"FR",
    "sg:address":"171 Bd St Denis 92400 Courbevoie",
    "sg:classifiers":[
        {
            "category":"Shopping",
            "subcategory":"Computers & Home Electronics",
            "type":"Retail Goods"
        }
    ],
    "sg:phone":"+33 1 43 34 61 61",
    "sg:postcode":"92400",
    "sg:province":"Ile de France",
    "sg:tags":[
        "electronic",
        "electrical",
        "equipment"
    ],
    "wof:name":"Moteurs Leroy Somer",
    "wof:placetype":"venue"
},
  "geometry": {"coordinates":[2.267446,48.899639],"type":"Point"}
}