{
  "type": "Feature",
  "properties": {
    "addr:full":"B.P. 22, 74301 Cluses C\u00e9dex^^450, Av. du Mont Blanc, 74300 Cluses Rhone-Alpes",
    "addr:postcode":"74301;74300",
    "addr:street":"B.P. 22;Av. Du Mont Blanc",
    "iso:country":"FR",
    "sg:address":"B.P. 22, 74301 Cluses C\u00e9dex^^450, Av. du Mont Blanc, 74300 Cluses",
    "sg:orig_category":"Non-Classified Establishments",
    "sg:phone":"+33 4 50 96 41 63",
    "sg:province":"Rhone-Alpes",
    "wof:name":"Pellier-cuit S.a.r.l.",
    "wof:placetype":"venue"
},
  "geometry": {"coordinates":[6.633185,45.987919],"type":"Point"}
}