{
  "type": "Feature",
  "properties": {
    "iso:country":"FR",
    "sg:address":"2, Rue Jean Bonnardel, 33140 Villenave d'Ornon",
    "sg:city":"Cadaujac",
    "sg:orig_category":"Unclassifiable Establishments",
    "sg:phone":"+33 5 56 75 82 32",
    "sg:postcode":"33140",
    "sg:province":"Aquitaine",
    "wof:name":"Tixit S.a.",
    "wof:placetype":"venue"
},
  "geometry": {"coordinates":[-0.573186,44.76799],"type":"Point"}
}