{
  "type": "Feature",
  "properties": {
    "addr:full":"2, Rue Jean Bonnardel, 33140 Villenave d'Ornon Cadaujac Aquitaine 33140",
    "addr:housenumber":"2",
    "addr:postcode":"33140;33140",
    "addr:street":"Rue Jean Bonnardel",
    "iso:country":"FR",
    "sg:address":"2, Rue Jean Bonnardel, 33140 Villenave d'Ornon",
    "sg:city":"Cadaujac",
    "sg:orig_category":"Unclassifiable Establishments",
    "sg:phone":"+33 5 56 75 82 32",
    "sg:postcode":"33140",
    "sg:province":"Aquitaine",
    "wof:name":"Tixit S.a.",
    "wof:placetype":"venue"
},
  "geometry": {"coordinates":[-0.573186,44.76799],"type":"Point"}
}