{
  "type": "Feature",
  "properties": {
    "iso:country":"FR",
    "sg:address":"B.P. 341",
    "sg:city":"Amboise Cedex",
    "sg:orig_category":"Non-Classified Establishments",
    "sg:phone":"+33 2 47 57 68 68",
    "sg:postcode":"37403",
    "sg:province":"Centre",
    "wof:name":"Antoine Courtois S.a.",
    "wof:placetype":"venue"
},
  "geometry": {"coordinates":[0.98255,47.412853],"type":"Point"}
}