{
  "type": "Feature",
  "properties": {
    "iso:country":"FR",
    "sg:address":"3 Rue Gaston Ramon 57063 Metz Cedex 2",
    "sg:classifiers":[
        {
            "category":"Professional",
            "subcategory":"Engineering",
            "type":"Services"
        }
    ],
    "sg:phone":"+33 3 87 31 88 80",
    "sg:province":"Midi Pyr\u00e9n\u00e9es",
    "sg:tags":[
        "machine",
        "-",
        "mechanical"
    ],
    "wof:name":"Kuthe Sa",
    "wof:placetype":"venue"
},
  "geometry": {"coordinates":[6.174878,49.139946],"type":"Point"}
}