{
  "type": "Feature",
  "properties": {
    "iso:country":"FR",
    "sg:address":"11/15, Rue de Lyon, 75012 Paris",
    "sg:orig_category":"Non-Classified Establishments",
    "sg:phone":"+33 1 53 02 20 00",
    "sg:province":"Ile de France",
    "wof:name":"Holiday Inn Paris Bastille",
    "wof:placetype":"venue"
},
  "geometry": {"coordinates":[2.371704,48.846844],"type":"Point"}
}