{
  "type": "Feature",
  "properties": {
    "addr:full":"2 Rue Du Stade Zac 76140 Le Petit Quevilly Haute Normandie 76140",
    "addr:housenumber":"2",
    "addr:postcode":"76140;76140",
    "addr:street":"Rue Du Stade Zac;Le Petit Quevilly Haute Normandie",
    "iso:country":"FR",
    "sg:address":"2 Rue Du Stade Zac 76140 Le Petit Quevilly",
    "sg:classifiers":[
        {
            "category":"Transit Center",
            "subcategory":"Freight",
            "type":"Transportation"
        }
    ],
    "sg:phone":"+33 2 35 73 07 76",
    "sg:postcode":"76140",
    "sg:province":"Haute Normandie",
    "sg:tags":[
        "metallurgy",
        "pipe",
        "metalworking",
        "sheet"
    ],
    "wof:name":"Technal",
    "wof:placetype":"venue"
},
  "geometry": {"coordinates":[1.06335,49.41679],"type":"Point"}
}