{
  "type": "Feature",
  "properties": {
    "addr:full":"B.P. 7169, 30906 N\u00eemes C\u00e9dex 2^^65, Av. Jean Jaur\u00e8s, 30900 N\u00eemes Languedoc-Roussillon",
    "addr:housenumber":"7169;^ 65",
    "addr:postcode":"30906;30900",
    "addr:street":"B.P.;Av. Jean Jaure\u0300S",
    "iso:country":"FR",
    "sg:address":"B.P. 7169, 30906 N\u00eemes C\u00e9dex 2^^65, Av. Jean Jaur\u00e8s, 30900 N\u00eemes",
    "sg:orig_category":"Non-Classified Establishments",
    "sg:phone":"+33 4 66 29 50 50",
    "sg:province":"Languedoc-Roussillon",
    "wof:name":"Jacques Barth\u00e9l\u00e9my Associ\u00e9s",
    "wof:placetype":"venue"
},
  "geometry": {"coordinates":[4.356115,43.830025],"type":"Point"}
}