{
  "type": "Feature",
  "properties": {
    "addr:full":"110, Av. de la R\u00e9publique, 93170 Bagnolet Ile de France",
    "addr:housenumber":"110",
    "addr:postcode":"93170;ile",
    "addr:street":"Av. De La Re\u0301Publique",
    "iso:country":"FR",
    "sg:address":"110, Av. de la R\u00e9publique, 93170 Bagnolet",
    "sg:orig_category":"Non-Classified Establishments",
    "sg:phone":"+33 1 56 93 35 50",
    "sg:province":"Ile de France",
    "wof:name":"Marin's S.a.r.l.",
    "wof:placetype":"venue"
},
  "geometry": {"coordinates":[2.423244,48.859646],"type":"Point"}
}