{
  "type": "Feature",
  "properties": {
    "addr:full":"1 Avenue John F Kennedy 62000 Arras Nord Pas-de-Calais 62000",
    "addr:housenumber":"1",
    "addr:postcode":"62000;62000",
    "addr:street":"Avenue John F",
    "iso:country":"FR",
    "sg:address":"1 Avenue John F Kennedy 62000 Arras",
    "sg:classifiers":[
        {
            "category":"Manufacturing",
            "subcategory":"Glass & Minerals",
            "type":"Manufacturing & Wholesale Goods"
        }
    ],
    "sg:phone":"+33 3 21 71 19 91",
    "sg:postcode":"62000",
    "sg:province":"Nord Pas-de-Calais",
    "sg:tags":[
        "building",
        "machine",
        "metal",
        "material",
        "equipmen",
        "-",
        "engineering",
        "machinery",
        "mechanical"
    ],
    "wof:name":"Paralu Menuiserie",
    "wof:placetype":"venue"
},
  "geometry": {"coordinates":[2.7598,50.289341],"type":"Point"}
}