{
  "type": "Feature",
  "properties": {
    "addr:full":"42, Rue Berthelot, 59000 Lille Nord Pas-de-Calais 59000",
    "addr:housenumber":"42",
    "addr:postcode":"59000;59000",
    "addr:street":"Rue Berthelot",
    "iso:country":"FR",
    "sg:address":"42, Rue Berthelot, 59000 Lille",
    "sg:orig_category":"Non-Classified Establishments",
    "sg:phone":"+33 3 20 88 24 21",
    "sg:postcode":"59000",
    "sg:province":"Nord Pas-de-Calais",
    "wof:name":"E.r.i. S.a.r.l. - Etudes Et R\u00e9alisations Industrielles",
    "wof:placetype":"venue"
},
  "geometry": {"coordinates":[3.069905,50.611603],"type":"Point"}
}