{
  "type": "Feature",
  "properties": {
    "addr:full":"259 cours Somme; Bordeaux Bordeaux Aquitaine 33100",
    "addr:housenumber":"259",
    "addr:postcode":"33100",
    "addr:street":"Cours Somme",
    "iso:country":"FR",
    "sg:address":"259 cours Somme; Bordeaux",
    "sg:city":"Bordeaux",
    "sg:classifiers":[
        {
            "category":"Banks & Credit Unions",
            "subcategory":"Bank",
            "type":"Services"
        }
    ],
    "sg:phone":"+33 3356917125",
    "sg:postcode":"33100",
    "sg:province":"Aquitaine",
    "wof:name":"Cr\u00e9dit Agricole",
    "wof:placetype":"venue"
},
  "geometry": {"coordinates":[-0.572489,44.820473],"type":"Point"}
}