{
  "type": "Feature",
  "properties": {
    "iso:country":"FR",
    "sg:address":"Rue Georges Claude 19100 Brive La Gaillarde",
    "sg:classifiers":[
        {
            "category":"Manufacturing",
            "subcategory":"Paper Products",
            "type":"Manufacturing & Wholesale Goods"
        }
    ],
    "sg:phone":"+33 5 55 86 89 00",
    "sg:province":"Limousin",
    "sg:tags":[
        "packaging",
        "material",
        "-",
        "cardboard"
    ],
    "wof:name":"B.r.g Emballagesa",
    "wof:placetype":"venue"
},
  "geometry": {"coordinates":[1.478055,45.151749],"type":"Point"}
}