{
  "type": "Feature",
  "properties": {
    "addr:full":"51 Av Jean Jaur\u00e8s 69007 Lyon Rhone-Alpes",
    "addr:postcode":"69007",
    "addr:street":"51 Av Jean Jaure\u0300S",
    "iso:country":"FR",
    "sg:address":"51 Av Jean Jaur\u00e8s 69007 Lyon",
    "sg:classifiers":[
        {
            "category":"Professional",
            "subcategory":"Business Services",
            "type":"Services"
        }
    ],
    "sg:phone":"+33 4 72 73 04 70",
    "sg:province":"Rhone-Alpes",
    "sg:tags":[
        "advice",
        "clothes"
    ],
    "wof:name":"Mgm Design Sa",
    "wof:placetype":"venue"
},
  "geometry": {"coordinates":[4.844785,45.749752],"type":"Point"}
}