{
  "type": "Feature",
  "properties": {
    "iso:country":"FR",
    "sg:address":"443 Rue Georges Clemenceau 85170 Les Lucs Sur Boulogne",
    "sg:classifiers":[
        {
            "category":"Manufacturing",
            "subcategory":"Printing",
            "type":"Manufacturing & Wholesale Goods"
        }
    ],
    "sg:phone":"+33 2 51 46 59 10",
    "sg:province":"Pays de Loire",
    "sg:tags":[
        "publishing"
    ],
    "wof:name":"Imprimerie Du Bocage Sa",
    "wof:placetype":"venue"
},
  "geometry": {"coordinates":[-1.399664,46.72414],"type":"Point"}
}