{
  "type": "Feature",
  "properties": {
    "addr:full":"ZI Pougues les Eaux Bourgogne 58320",
    "addr:postcode":"58320",
    "iso:country":"FR",
    "sg:address":"ZI",
    "sg:city":"Pougues les Eaux",
    "sg:orig_category":"Unclassifiable Establishments",
    "sg:phone":"+33 3 86 90 96 10",
    "sg:postcode":"58320",
    "sg:province":"Bourgogne",
    "wof:name":"C.i.a. Bourgogne S.a.",
    "wof:placetype":"venue"
},
  "geometry": {"coordinates":[3.100895,47.075207],"type":"Point"}
}