{
  "type": "Feature",
  "properties": {
    "addr:full":"48 Rue Charles De Gaulle 88400 G\u00e9rardmer Lorraine",
    "addr:housenumber":"48",
    "addr:postcode":"88400",
    "addr:street":"Rue Charles De Gaulle",
    "iso:country":"FR",
    "sg:address":"48 Rue Charles De Gaulle 88400 G\u00e9rardmer",
    "sg:classifiers":[
        {
            "category":"Professional",
            "type":"Services"
        }
    ],
    "sg:phone":"+33 3 29 63 06 29",
    "sg:province":"Lorraine",
    "sg:tags":[
        "transport",
        "road"
    ],
    "wof:name":"Ste Geromoise De Transports Sarl",
    "wof:placetype":"venue"
},
  "geometry": {"coordinates":[6.878168,48.070469],"type":"Point"}
}