{
  "type": "Feature",
  "properties": {
    "addr:full":"129 boulevard de S\u00e9bastopol 75002 Paris Ile de France 75002",
    "addr:housenumber":"129",
    "addr:postcode":"75002;75002",
    "addr:street":"Boulevard De Se\u0301Bastopol",
    "iso:country":"FR",
    "sg:address":"129 boulevard de S\u00e9bastopol 75002 Paris",
    "sg:orig_category":"Ladies' Trousers Suits, Suits, Jackets, Skirts, And Trousers",
    "sg:phone":"+33 1 40 28 00 23",
    "sg:postcode":"75002",
    "sg:province":"Ile de France",
    "wof:name":"Pim S.a.",
    "wof:placetype":"venue"
},
  "geometry": {"coordinates":[2.353395,48.868019],"type":"Point"}
}