{
  "type": "Feature",
  "properties": {
    "iso:country":"FR",
    "sg:address":"26, Rue G\u00e9n\u00e9ral de Gaulle, 44600 Saint Nazaire",
    "sg:orig_category":"Unclassifiable Establishments",
    "sg:phone":"+33 2 40 17 22 00",
    "sg:province":"Pays de Loire",
    "wof:name":"C.i.o. S.a.- Cr\u00e9dit Industriel De L'ouest",
    "wof:placetype":"venue"
},
  "geometry": {"coordinates":[-2.209368,47.273872],"type":"Point"}
}