{
  "type": "Feature",
  "properties": {
    "iso:country":"FR",
    "sg:address":"28 Rue Alfred Kastler",
    "sg:city":"Mont St Aignan",
    "sg:classifiers":[
        {
            "category":"Banks & Credit Unions",
            "subcategory":"Financial Services",
            "type":"Services"
        }
    ],
    "sg:phone":"+33 2 35 59 76 76",
    "sg:postcode":"76130",
    "sg:province":"Haute Normandie",
    "sg:tags":[
        "banking",
        "finance",
        "insurance"
    ],
    "wof:name":"Societe Expertises Comptables Nord Ouest Parc De La Vatine",
    "wof:placetype":"venue"
},
  "geometry": {"coordinates":[1.097232,49.475754],"type":"Point"}
}