{
  "type": "Feature",
  "properties": {
    "iso:country":"FR",
    "sg:address":"71 Rte D'Orl\u00e9ans",
    "sg:city":"20 91310 Montlh\u00e9ry",
    "sg:classifiers":[
        {
            "category":"Autos & Motor Vehicles",
            "subcategory":"Automobile Sales",
            "type":"Retail Goods"
        }
    ],
    "sg:phone":"+33 1 69 01 63 20",
    "sg:province":"Ile de France",
    "sg:tags":[
        "equipment",
        "transport"
    ],
    "wof:name":"Cls France",
    "wof:placetype":"venue"
},
  "geometry": {"coordinates":[2.252039,48.608856],"type":"Point"}
}