{
  "type": "Feature",
  "properties": {
    "iso:country":"FR",
    "sg:address":"2 rue de Chastillon; B.P. 533; CHALONS-EN-CHAMPAGNE CEDEX; 51010",
    "sg:city":"Still",
    "sg:classifiers":[
        {
            "category":"Shopping",
            "subcategory":"Computers & Home Electronics",
            "type":"Retail Goods"
        }
    ],
    "sg:phone":"+33 3 26 21 11 33",
    "sg:postcode":"67190",
    "sg:province":"Alsace",
    "sg:tags":[
        "chamber",
        "commerce"
    ],
    "wof:name":"C.c.i De Chalons-en-champagne, Vitry-le-frangois, Ste Menehould",
    "wof:placetype":"venue"
},
  "geometry": {"coordinates":[4.36364,48.955219],"type":"Point"}
}