{
  "type": "Feature",
  "properties": {
    "iso:country":"FR",
    "sg:address":"Zi D'Arsac 12850 Ste Radegonde",
    "sg:classifiers":[
        {
            "category":"Farming",
            "subcategory":"Farm",
            "type":"Manufacturing & Wholesale Goods"
        }
    ],
    "sg:phone":"+33 5 65 67 00 88",
    "sg:postcode":"12850",
    "sg:province":"Midi Pyr\u00e9n\u00e9es",
    "sg:tags":[
        "horticulture",
        "agriculture",
        "livestock"
    ],
    "wof:name":"Scpa Rodez Sa",
    "wof:placetype":"venue"
},
  "geometry": {"coordinates":[2.636089,44.355843],"type":"Point"}
}