{
  "type": "Feature",
  "properties": {
    "iso:country":"FR",
    "sg:address":"B.P. 5, 95301 Cergy Pontoise C\u00e9dex^^21, Rue Gambetta, 95300 Pontoise",
    "sg:orig_category":"Non-Classified Establishments",
    "sg:phone":"+33 1 30 38 32 85",
    "sg:postcode":"95300",
    "sg:province":"Ile de France",
    "wof:name":"Electra Unic Industrie S.a.",
    "wof:placetype":"venue"
},
  "geometry": {"coordinates":[2.100678,49.050671],"type":"Point"}
}