{
  "type": "Feature",
  "properties": {
    "iso:country":"FR",
    "sg:address":"1140 Rue Ampere 13100 Aix En Provence",
    "sg:classifiers":[
        {
            "category":"Utilities",
            "subcategory":"Electric",
            "type":"Services"
        }
    ],
    "sg:phone":"+33 4 42 24 57 77",
    "sg:province":"Nord Pas-de-Calais",
    "sg:tags":[
        "electricity",
        "electronic",
        "electrical",
        "equipment"
    ],
    "wof:name":"2 H Energy",
    "wof:placetype":"venue"
},
  "geometry": {"coordinates":[5.49167,43.509033],"type":"Point"}
}