{
  "type": "Feature",
  "properties": {
    "addr:full":"Route De Jard Sur Mer 85440 Talmont St Hilaire Pays de Loire",
    "addr:postcode":"85440",
    "addr:street":"Route De Jard Sur Mer;Talmont St Hilaire",
    "iso:country":"FR",
    "sg:address":"Route De Jard Sur Mer 85440 Talmont St Hilaire",
    "sg:classifiers":[
        {
            "category":"Banks & Credit Unions",
            "subcategory":"Investment Brokerage",
            "type":"Services"
        }
    ],
    "sg:phone":"+33 2 51 90 61 14",
    "sg:province":"Pays de Loire",
    "sg:tags":[
        "-",
        "transport",
        "related"
    ],
    "wof:name":"Cavac",
    "wof:placetype":"venue"
},
  "geometry": {"coordinates":[-1.628771,46.443314],"type":"Point"}
}