{
  "type": "Feature",
  "properties": {
    "iso:country":"FR",
    "sg:address":"29, Rue du Faubourg, 67430 Diemeringen",
    "sg:city":"Diemeringen",
    "sg:orig_category":"Non-Classified Establishments",
    "sg:phone":"+33 3 88 00 40 20",
    "sg:postcode":"67430",
    "sg:province":"Alsace",
    "wof:name":"Primosa S.a.r.l.",
    "wof:placetype":"venue"
},
  "geometry": {"coordinates":[7.187264,48.939243],"type":"Point"}
}