{
  "type": "Feature",
  "properties": {
    "addr:full":"Pl Bernard; Bourg en Bresse Centre",
    "addr:street":"Pl Bernard Bourg",
    "iso:country":"FR",
    "sg:address":"Pl Bernard; Bourg en Bresse",
    "sg:classifiers":[
        {
            "category":"Banks & Credit Unions",
            "subcategory":"Bank",
            "type":"Services"
        }
    ],
    "sg:phone":"+33 3374232721",
    "sg:province":"Centre",
    "wof:name":"Soci\u00e9t\u00e9 G\u00e9n\u00e9rale",
    "wof:placetype":"venue"
},
  "geometry": {"coordinates":[5.228161,46.206429],"type":"Point"}
}