{
  "type": "Feature",
  "properties": {
    "addr:full":"8, Rue des Marronniers, 84420 Piolenc Corse",
    "addr:housenumber":"8",
    "addr:postcode":"84420",
    "addr:street":"Rue Des Marronniers",
    "iso:country":"FR",
    "sg:address":"8, Rue des Marronniers, 84420 Piolenc",
    "sg:orig_category":"Unclassifiable Establishments",
    "sg:phone":"+33 4 90 29 64 54",
    "sg:province":"Corse",
    "wof:name":"Mouvex",
    "wof:placetype":"venue"
},
  "geometry": {"coordinates":[4.762444,44.179024],"type":"Point"}
}