{
  "type": "Feature",
  "properties": {
    "iso:country":"FR",
    "sg:address":"rue Amelie, Paris, Dept 75",
    "sg:classifiers":[
        {
            "category":"Banks & Credit Unions",
            "subcategory":"Bank",
            "type":"Services"
        }
    ],
    "sg:province":"Ile de France",
    "wof:name":"Ing Lease France Sa",
    "wof:placetype":"venue"
},
  "geometry": {"coordinates":[2.307581,48.858803],"type":"Point"}
}