{
  "type": "Feature",
  "properties": {
    "addr:full":"15 rue Edouard Aynard 69100 Villeurbanne Rhone-Alpes 69100",
    "addr:housenumber":"15",
    "addr:postcode":"69100;69100",
    "addr:street":"Rue Edouard Aynard",
    "iso:country":"FR",
    "sg:address":"15 rue Edouard Aynard 69100 Villeurbanne",
    "sg:orig_category":"Light Rail, Industrial Railway And Mining Railway Supplies",
    "sg:phone":"+33 4 78 03 49 49",
    "sg:postcode":"69100",
    "sg:province":"Rhone-Alpes",
    "wof:name":"Scmr Fournitures Industrielles Sarl",
    "wof:placetype":"venue"
},
  "geometry": {"coordinates":[4.876604,45.761127],"type":"Point"}
}