{
  "type": "Feature",
  "properties": {
    "addr:full":"71 Rue Desnouettes Bt C 75015 Paris Ile de France",
    "addr:housenumber":"71",
    "addr:postcode":"75015",
    "addr:street":"Rue Desnouettes Bt C",
    "iso:country":"FR",
    "sg:address":"71 Rue Desnouettes Bt C 75015 Paris",
    "sg:classifiers":[
        {
            "category":"Professional",
            "subcategory":"Printing & Photocopies",
            "type":"Services"
        }
    ],
    "sg:phone":"+33 1 48 28 57 57",
    "sg:province":"Ile de France",
    "sg:tags":[
        "publishing"
    ],
    "wof:name":"Codes Rousseau",
    "wof:placetype":"venue"
},
  "geometry": {"coordinates":[2.299265,48.841057],"type":"Point"}
}