{
  "type": "Feature",
  "properties": {
    "iso:country":"FR",
    "sg:address":"2 Quai De Seine 93206 St Denis Cedex",
    "sg:classifiers":[
        {
            "category":"Professional",
            "subcategory":"Engineering",
            "type":"Services"
        }
    ],
    "sg:phone":"+33 1 48 13 10 80",
    "sg:tags":[
        "machine",
        "-",
        "mechanical"
    ],
    "wof:name":"Inductothermie Sa",
    "wof:placetype":"venue"
},
  "geometry": {"coordinates":[2.342826,48.936691],"type":"Point"}
}