{
  "type": "Feature",
  "properties": {
    "iso:country":"FR",
    "sg:address":"7, Rue de la Lib\u00e9ration, 69270 Fontaines sur Sa\u00f4ne",
    "sg:orig_category":"Unclassifiable Establishments",
    "sg:phone":"+33 4 72 42 99 42",
    "sg:province":"Rhone-Alpes",
    "wof:name":"Frico France S.a.",
    "wof:placetype":"venue"
},
  "geometry": {"coordinates":[4.858411,45.832199],"type":"Point"}
}