{
  "type": "Feature",
  "properties": {
    "addr:full":"42 Rue Gal Charette 44650 Touvois Pays de Loire 44650",
    "addr:housenumber":"42",
    "addr:postcode":"44650;44650",
    "addr:street":"Rue Gal Charette",
    "iso:country":"FR",
    "sg:address":"42 Rue Gal Charette 44650 Touvois",
    "sg:classifiers":[
        {
            "category":"Farming",
            "subcategory":"Farm",
            "type":"Manufacturing & Wholesale Goods"
        }
    ],
    "sg:phone":"+33 2 40 31 60 06",
    "sg:postcode":"44650",
    "sg:province":"Pays de Loire",
    "sg:tags":[
        "horticulture",
        "agriculture",
        "livestock"
    ],
    "wof:name":"Cavac",
    "wof:placetype":"venue"
},
  "geometry": {"coordinates":[-1.683493,46.902576],"type":"Point"}
}