{
  "type": "Feature",
  "properties": {
    "iso:country":"FR",
    "sg:address":"13, Rue Feuillat, 69003 Lyon",
    "sg:orig_category":"Non-Classified Establishments",
    "sg:phone":"+33 4 72 68 88 91",
    "sg:postcode":"69003",
    "sg:province":"Rhone-Alpes",
    "wof:name":"Data Foot",
    "wof:placetype":"venue"
},
  "geometry": {"coordinates":[4.877291,45.753994],"type":"Point"}
}