{
  "type": "Feature",
  "properties": {
    "iso:country":"FR",
    "sg:address":"5, Rue Jean Mermoz, 75008 Paris",
    "sg:orig_category":"Non-Classified Establishments",
    "sg:phone":"+33 1 49 04 72 35",
    "sg:province":"Ile de France",
    "wof:name":"France Teaser S.a.s.",
    "wof:placetype":"venue"
},
  "geometry": {"coordinates":[2.311083,48.870579],"type":"Point"}
}