{
  "type": "Feature",
  "properties": {
    "addr:full":"1805, Av. Andr\u00e9 Lasquin - ZI, 74700 Sallanches Rhone-Alpes",
    "addr:housenumber":"1805",
    "addr:postcode":"74700",
    "addr:street":"Av. Andre\u0301 Lasquin Zi",
    "iso:country":"FR",
    "sg:address":"1805, Av. Andr\u00e9 Lasquin - ZI, 74700 Sallanches",
    "sg:orig_category":"Unclassifiable Establishments",
    "sg:phone":"+33 4 50 58 30 50",
    "sg:province":"Rhone-Alpes",
    "wof:name":"Pavillet S.a.r.l.",
    "wof:placetype":"venue"
},
  "geometry": {"coordinates":[6.648797,45.913139],"type":"Point"}
}