{
  "type": "Feature",
  "properties": {
    "addr:full":"3, Rue Robespierre, 22000 Saint Brieuc Saint-Brieuc Bretagne 22000",
    "addr:housenumber":"3",
    "addr:postcode":"22000;22000",
    "addr:street":"Rue Robespierre;Brieuc;Bretagne",
    "iso:country":"FR",
    "sg:address":"3, Rue Robespierre, 22000 Saint Brieuc",
    "sg:city":"Saint-Brieuc",
    "sg:orig_category":"Non-Classified Establishments",
    "sg:phone":"+33 2 96 01 21 21",
    "sg:postcode":"22000",
    "sg:province":"Bretagne",
    "wof:name":"C.s.a. S.a. - Chauffage Sanitaire D' Armor",
    "wof:placetype":"venue"
},
  "geometry": {"coordinates":[-2.771124,48.50248],"type":"Point"}
}