{
  "type": "Feature",
  "properties": {
    "addr:full":"Le Bourg Montrottier Rhone-Alpes 69770",
    "addr:postcode":"69770",
    "addr:street":"Le Bourg Montrottier Rhone-Alpes",
    "iso:country":"FR",
    "sg:address":"Le Bourg",
    "sg:city":"Montrottier",
    "sg:orig_category":"Non-Classified Establishments",
    "sg:phone":"+33 4 74 70 18 38",
    "sg:postcode":"69770",
    "sg:province":"Rhone-Alpes",
    "wof:name":"Soci\u00e9t\u00e9 D'exploitation Des Etablissements Second Michel S.a.r.l.",
    "wof:placetype":"venue"
},
  "geometry": {"coordinates":[4.368751,45.77243],"type":"Point"}
}