{
  "type": "Feature",
  "properties": {
    "addr:full":"7 avenue de la D\u00e9couverte 21000 Dijon Dijon Bourgogne 21000",
    "addr:housenumber":"7",
    "addr:postcode":"21000;21000",
    "addr:street":"Avenue De La De\u0301Couverte",
    "iso:country":"FR",
    "sg:address":"7 avenue de la D\u00e9couverte 21000 Dijon",
    "sg:city":"Dijon",
    "sg:classifiers":[
        {
            "category":"Banks & Credit Unions",
            "subcategory":"Investment Brokerage",
            "type":"Services"
        }
    ],
    "sg:phone":"+33 3 80 60 09 20",
    "sg:postcode":"21000",
    "sg:province":"Bourgogne",
    "sg:tags":[
        "bearing",
        "ball"
    ],
    "wof:name":"Interroll S.a.",
    "wof:placetype":"venue"
},
  "geometry": {"coordinates":[5.043943,47.355389],"type":"Point"}
}