{
  "type": "Feature",
  "properties": {
    "addr:full":"B.P. 37, 59840 P\u00e9renchies^^Rue Pietralunga - Z.A. du Bois, 59840 P\u00e9renchies Nord Pas-de-Calais",
    "addr:postcode":"59840;59840",
    "addr:street":"B.P. 37;Du Bois",
    "iso:country":"FR",
    "sg:address":"B.P. 37, 59840 P\u00e9renchies^^Rue Pietralunga - Z.A. du Bois, 59840 P\u00e9renchies",
    "sg:orig_category":"Non-Classified Establishments",
    "sg:phone":"+33 3 20 22 45 85",
    "sg:province":"Nord Pas-de-Calais",
    "wof:name":"Rafale Technologie S.a.",
    "wof:placetype":"venue"
},
  "geometry": {"coordinates":[2.973282,50.668343],"type":"Point"}
}