{
  "type": "Feature",
  "properties": {
    "iso:country":"FR",
    "sg:address":"13, Rue de Buffon, 37000 Tours",
    "sg:city":"Tours",
    "sg:orig_category":"Unclassifiable Establishments",
    "sg:phone":"+33 2 47 05 44 15",
    "sg:postcode":"37000",
    "sg:province":"Centre",
    "wof:name":"B.s.t.c.o - Bourse De Sous Traitance Du Centre Ouest",
    "wof:placetype":"venue"
},
  "geometry": {"coordinates":[0.690853,47.3927],"type":"Point"}
}