{
  "type": "Feature",
  "properties": {
    "iso:country":"FR",
    "sg:address":"Rue de la Plaine",
    "sg:city":"Bourgoin Jallieu",
    "sg:orig_category":"Unclassifiable Establishments",
    "sg:phone":"+33 4 74 28 32 55",
    "sg:postcode":"38300",
    "sg:province":"Rhone-Alpes",
    "wof:name":"Venditelli Transports S.a.",
    "wof:placetype":"venue"
},
  "geometry": {"coordinates":[5.268291,45.599991],"type":"Point"}
}