{
  "type": "Feature",
  "properties": {
    "iso:country":"FR",
    "sg:address":"59 Rue De Ch\u00e2teaudun",
    "sg:city":"Paris",
    "sg:classifiers":[
        {
            "category":"Banks & Credit Unions",
            "subcategory":"Financial Services",
            "type":"Services"
        }
    ],
    "sg:phone":"+33 1 42 81 97 00",
    "sg:postcode":"75009",
    "sg:province":"Ile de France",
    "sg:tags":[
        "banking",
        "finance",
        "insurance"
    ],
    "wof:name":"European Benefits Administrators",
    "wof:placetype":"venue"
},
  "geometry": {"coordinates":[2.332224,48.876171],"type":"Point"}
}