{
  "type": "Feature",
  "properties": {
    "iso:country":"FR",
    "sg:address":"5 rue Descartes 95330 Domont",
    "sg:classifiers":[
        {
            "category":"Utilities",
            "subcategory":"Telephone",
            "type":"Services"
        }
    ],
    "sg:phone":"+33 1 39 35 48 88",
    "sg:province":"Ile de France",
    "wof:name":"Couleur Communication Ecriture Sarl",
    "wof:placetype":"venue"
},
  "geometry": {"coordinates":[2.344846,49.030018],"type":"Point"}
}