{
  "type": "Feature",
  "properties": {
    "iso:country":"FR",
    "sg:address":"B.P. Senia 547, 94577 Thiais C\u00e9dex^^18/28, Rue du Puits Dixmes, 94320 Thiais",
    "sg:orig_category":"Non-Classified Establishments",
    "sg:phone":"+33 1 41 80 33 33",
    "sg:postcode":"94320",
    "sg:province":"Ile de France",
    "wof:name":"A.z. France S.a.",
    "wof:placetype":"venue"
},
  "geometry": {"coordinates":[2.390409,48.765186],"type":"Point"}
}