{
  "type": "Feature",
  "properties": {
    "iso:country":"FR",
    "sg:address":"B.P. 60506, 44005 Nantes C\u00e9dex 01^^Rue Sourdeac, 44000 Nantes",
    "sg:orig_category":"Non-Classified Establishments",
    "sg:phone":"+33 2 40 89 57 10",
    "sg:postcode":"44000",
    "sg:province":"Pays de Loire",
    "wof:name":"Boisti\u00e8re Et Compagnie S.a.r.l.",
    "wof:placetype":"venue"
},
  "geometry": {"coordinates":[-1.553059,47.218117],"type":"Point"}
}