{
  "type": "Feature",
  "properties": {
    "addr:full":"14, Grande Rue, 45220 Melleroy Melleroy Centre 45220",
    "addr:housenumber":"14;melleroy",
    "addr:postcode":"45220;45220",
    "addr:street":"Grande Rue",
    "iso:country":"FR",
    "sg:address":"14, Grande Rue, 45220 Melleroy",
    "sg:city":"Melleroy",
    "sg:orig_category":"Non-Classified Establishments",
    "sg:phone":"+33 2 38 95 24 52",
    "sg:postcode":"45220",
    "sg:province":"Centre",
    "wof:name":"B.s.m. S.a. - Bois Et Scierie De Melleroy",
    "wof:placetype":"venue"
},
  "geometry": {"coordinates":[2.952895,47.895451],"type":"Point"}
}