{
  "type": "Feature",
  "properties": {
    "iso:country":"FR",
    "sg:address":"1 boulevard de la Madeleine 75001 Paris",
    "sg:classifiers":[
        {
            "category":"Banks & Credit Unions",
            "subcategory":"Atm",
            "type":"Services"
        }
    ],
    "sg:phone":"+33 1 55 04 90 00",
    "sg:postcode":"75001",
    "sg:province":"Ile de France",
    "sg:tags":[
        "carrier",
        "airlines",
        "air-freight"
    ],
    "wof:name":"Aeromexico Sa",
    "wof:placetype":"venue"
},
  "geometry": {"coordinates":[2.327736,48.869759],"type":"Point"}
}