{
  "type": "Feature",
  "properties": {
    "addr:full":"15 Rue Des Rosiers 93400 St Ouen Ile de France",
    "addr:housenumber":"15",
    "addr:postcode":"93400",
    "addr:street":"Rue Des Rosiers;St;Ile De France",
    "iso:country":"FR",
    "sg:address":"15 Rue Des Rosiers 93400 St Ouen",
    "sg:classifiers":[
        {
            "category":"Autos & Motor Vehicles",
            "subcategory":"Automobile Sales",
            "type":"Retail Goods"
        }
    ],
    "sg:phone":"+33 1 49 45 32 32",
    "sg:province":"Ile de France",
    "sg:tags":[
        "equipment",
        "transport"
    ],
    "wof:name":"Valeo",
    "wof:placetype":"venue"
},
  "geometry": {"coordinates":[2.334781,48.907169],"type":"Point"}
}