{
  "type": "Feature",
  "properties": {
    "addr:full":"13, Rue Roland Coffignot, 51100 Reims Champagne",
    "addr:housenumber":"13",
    "addr:postcode":"51100",
    "addr:street":"Rue Roland Coffignot",
    "iso:country":"FR",
    "sg:address":"13, Rue Roland Coffignot, 51100 Reims",
    "sg:orig_category":"Unclassifiable Establishments",
    "sg:phone":"+33 3 26 08 27 99",
    "sg:province":"Champagne",
    "wof:name":"Durando Bureau Concept S.a.r.l.",
    "wof:placetype":"venue"
},
  "geometry": {"coordinates":[4.079088,49.233177],"type":"Point"}
}