{
  "type": "Feature",
  "properties": {
    "addr:full":"19, Rte des Petits Coins, 78610 Saint L\u00e9ger en Yvelines Ile de France 78610",
    "addr:housenumber":"19",
    "addr:postcode":"78610;78610",
    "addr:street":"Rte Des Petits Coins;Le\u0301Ger En Yvelines Ile De France",
    "iso:country":"FR",
    "sg:address":"19, Rte des Petits Coins, 78610 Saint L\u00e9ger en Yvelines",
    "sg:orig_category":"Non-Classified Establishments",
    "sg:phone":"+33 1 34 86 38 50",
    "sg:postcode":"78610",
    "sg:province":"Ile de France",
    "wof:name":"E.t.s. Electronic - European Technologies Services Electroniques S.a.",
    "wof:placetype":"venue"
},
  "geometry": {"coordinates":[1.760821,48.712788],"type":"Point"}
}