{
  "type": "Feature",
  "properties": {
    "iso:country":"FR",
    "sg:address":"10, Rue Eug\u00e8ne H\u00e9naff - ZI les Vignes, 93000 Bobigny",
    "sg:orig_category":"Non-Classified Establishments",
    "sg:phone":"+33 1 41 83 76 50",
    "sg:province":"Ile de France",
    "wof:name":"Transport Demonceau S.a.r.l.",
    "wof:placetype":"venue"
},
  "geometry": {"coordinates":[2.445785,48.90477],"type":"Point"}
}