{
  "type": "Feature",
  "properties": {
    "addr:full":"Route De Surgy 58501 CLAMECY CEDEX Poitou-Charentes",
    "addr:postcode":"58501 clamecy cedex",
    "addr:street":"Route De Surgy",
    "iso:country":"FR",
    "sg:address":"Route De Surgy 58501 CLAMECY CEDEX",
    "sg:classifiers":[
        {
            "category":"Building & Trades",
            "subcategory":"Plumbing",
            "type":"Services"
        }
    ],
    "sg:phone":"+33 3 86 27 50 50",
    "sg:province":"Poitou-Charentes",
    "sg:tags":[
        "piping"
    ],
    "wof:name":"Cico-centre Sa",
    "wof:placetype":"venue"
},
  "geometry": {"coordinates":[3.520745,47.459946],"type":"Point"}
}