{
  "type": "Feature",
  "properties": {
    "iso:country":"FR",
    "sg:address":"2 bis, Rue de la Fosse aux Leux - Z.A.C. de la Croix Blanche, 91700 Sainte Genevi\u00e8ve des Bois",
    "sg:orig_category":"Unclassifiable Establishments",
    "sg:phone":"+33 1 69 46 17 77",
    "sg:province":"Ile de France",
    "wof:name":"E.t.u.b.a.t. - S.a.r.l. - Etude Pour Le B\u00e2timent Et Travaux",
    "wof:placetype":"venue"
},
  "geometry": {"coordinates":[2.326545,48.640656],"type":"Point"}
}