{
  "type": "Feature",
  "properties": {
    "addr:full":"Route Fades 63770 Les Ancizes Comps Ancizes-Comps Auvergne 63770",
    "addr:postcode":"63770;63770",
    "addr:street":"Route Fades",
    "iso:country":"FR",
    "sg:address":"Route Fades 63770 Les Ancizes Comps",
    "sg:city":"Ancizes-Comps",
    "sg:classifiers":[
        {
            "category":"Professional",
            "type":"Services"
        }
    ],
    "sg:phone":"+33 4 73 86 81 31",
    "sg:postcode":"63770",
    "sg:province":"Auvergne",
    "sg:tags":[
        "transport",
        "road"
    ],
    "wof:name":"Transport Meunier P\u00c8re & Fils Sarl",
    "wof:placetype":"venue"
},
  "geometry": {"coordinates":[2.803587,45.970676],"type":"Point"}
}