{
  "type": "Feature",
  "properties": {
    "addr:full":"12, Place du March\u00e9, 57200 Sarreguemines Lorraine 57200",
    "addr:housenumber":"12",
    "addr:postcode":"57200;57200",
    "addr:street":"Place Du Marche\u0301",
    "iso:country":"FR",
    "sg:address":"12, Place du March\u00e9, 57200 Sarreguemines",
    "sg:orig_category":"GROSSISTE: BUREAUTIQUE, FOURNITURES DE BUREAUX, ORDINATEURS, IMPRIMANTES ET PHOTOCOPIEURS. INSTALLAT",
    "sg:phone":"+33 3 87 95 05 85",
    "sg:postcode":"57200",
    "sg:province":"Lorraine",
    "wof:name":"T.p.i. Bureautique S.a.r.l.",
    "wof:placetype":"venue"
},
  "geometry": {"coordinates":[7.065332,49.111435],"type":"Point"}
}