{
  "type": "Feature",
  "properties": {
    "iso:country":"FR",
    "sg:address":"14 Av Berthelot 69007 Lyon",
    "sg:classifiers":[
        {
            "category":"Professional",
            "subcategory":"Business Services",
            "type":"Services"
        }
    ],
    "sg:phone":"+33 4 78 69 79 79",
    "sg:province":"Rhone-Alpes",
    "sg:tags":[
        "body",
        "advice"
    ],
    "wof:name":"Handicap International",
    "wof:placetype":"venue"
},
  "geometry": {"coordinates":[4.835468,45.747097],"type":"Point"}
}