{
  "type": "Feature",
  "properties": {
    "addr:full":"B.P. 1046, 68050 Mulhouse C\u00e9dex^^9, Av Foch, 68100 Mulhouse Mulhouse Alsace 68100",
    "addr:postcode":"68050;68100;68100",
    "addr:street":"B.P. 1046;Av Foch",
    "iso:country":"FR",
    "sg:address":"B.P. 1046, 68050 Mulhouse C\u00e9dex^^9, Av Foch, 68100 Mulhouse",
    "sg:city":"Mulhouse",
    "sg:orig_category":"Non-Classified Establishments",
    "sg:phone":"+33 3 89 36 26 00",
    "sg:postcode":"68100",
    "sg:province":"Alsace",
    "wof:name":"Voyages Lesage S.a.",
    "wof:placetype":"venue"
},
  "geometry": {"coordinates":[7.34365,47.751709],"type":"Point"}
}