{
  "type": "Feature",
  "properties": {
    "iso:country":"FR",
    "sg:address":"11, Av. de Norv\u00e8ge, 91978 Courtaboeuf",
    "sg:orig_category":"Non-Classified Establishments",
    "sg:phone":"+33 1 69 29 22 00",
    "sg:province":"Nord-Tr\u00f8ndelag",
    "wof:name":"Hoerbiger - Origa S.a.",
    "wof:placetype":"venue"
},
  "geometry": {"coordinates":[12.66538,64.556534],"type":"Point"}
}