{
  "type": "Feature",
  "properties": {
    "addr:full":"1 Rue Sous St Arnould 57000 Metz Lorraine 57000",
    "addr:housenumber":"1",
    "addr:postcode":"57000;57000",
    "addr:street":"Rue Sous St",
    "iso:country":"FR",
    "sg:address":"1 Rue Sous St Arnould 57000 Metz",
    "sg:classifiers":[
        {
            "category":"Professional",
            "subcategory":"Engineering",
            "type":"Services"
        }
    ],
    "sg:phone":"+33 3 87 75 30 45",
    "sg:postcode":"57000",
    "sg:province":"Lorraine",
    "sg:tags":[
        "machine",
        "-",
        "mechanical"
    ],
    "wof:name":"Ste R Spirk Et Fils Sarl",
    "wof:placetype":"venue"
},
  "geometry": {"coordinates":[6.171133,49.119133],"type":"Point"}
}