{
  "type": "Feature",
  "properties": {
    "iso:country":"FR",
    "sg:address":"B.P. 39, 53500 Ern\u00e9e^^Av. de Paris, 53500 Ern\u00e9e",
    "sg:orig_category":"Non-Classified Establishments",
    "sg:phone":"+33 2 43 05 14 31",
    "sg:province":"Pays de Loire",
    "wof:name":"Pannard Cr\u00e9ations S.a.r.l.",
    "wof:placetype":"venue"
},
  "geometry": {"coordinates":[-1.027721,48.273811],"type":"Point"}
}