{
  "type": "Feature",
  "properties": {
    "addr:full":"Av Des Pyr\u00e9n\u00e9es 09100 St Jean Du Falga Midi Pyr\u00e9n\u00e9es 09100",
    "addr:postcode":"09100;09100",
    "addr:street":"Av Des Pyre\u0301Ne\u0301Es;Du Falga Midi Pyre\u0301Ne\u0301Es",
    "iso:country":"FR",
    "sg:address":"Av Des Pyr\u00e9n\u00e9es 09100 St Jean Du Falga",
    "sg:classifiers":[
        {
            "category":"Autos & Motor Vehicles",
            "subcategory":"Automobile Sales",
            "type":"Retail Goods"
        }
    ],
    "sg:phone":"+33 5 61 68 01 41",
    "sg:postcode":"09100",
    "sg:province":"Midi Pyr\u00e9n\u00e9es",
    "sg:tags":[
        "equipment",
        "motor-cars",
        "transport"
    ],
    "wof:name":"Pamiers Automobiles",
    "wof:placetype":"venue"
},
  "geometry": {"coordinates":[1.629934,43.080723],"type":"Point"}
}