{
  "type": "Feature",
  "properties": {
    "iso:country":"FR",
    "sg:address":"voie d'Angleterre 13127 Vitrolles",
    "sg:city":"Anglet",
    "sg:classifiers":[
        {
            "category":"Professional",
            "subcategory":"Computer Services",
            "type":"Services"
        }
    ],
    "sg:phone":"+33 4 42 10 01 42",
    "sg:postcode":"64600",
    "sg:province":"Aquitaine",
    "sg:tags":[
        "development",
        "software"
    ],
    "wof:name":"Com 2 I Sarl",
    "wof:placetype":"venue"
},
  "geometry": {"coordinates":[5.260901,43.426197],"type":"Point"}
}