{
  "type": "Feature",
  "properties": {
    "iso:country":"FR",
    "sg:address":"2 Av De La For\u00eat Noire 67000 Strasbourg",
    "sg:city":"Strasbourg",
    "sg:classifiers":[
        {
            "category":"Banks & Credit Unions",
            "subcategory":"Financial Services",
            "type":"Services"
        }
    ],
    "sg:phone":"+33 3 88 45 55 50",
    "sg:postcode":"67000",
    "sg:province":"Alsace",
    "sg:tags":[
        "banking",
        "insurance",
        "institution",
        "finance"
    ],
    "wof:name":"Coopers Et Lybrand Audit",
    "wof:placetype":"venue"
},
  "geometry": {"coordinates":[7.76345,48.586082],"type":"Point"}
}