{
  "type": "Feature",
  "properties": {
    "iso:country":"FR",
    "sg:address":"La Rampinsolle Sud Route D Atur 24660 Coulounieix Chamiers",
    "sg:city":"Coulounieix-Chamiers",
    "sg:classifiers":[
        {
            "category":"Building & Trades",
            "subcategory":"Construction",
            "type":"Services"
        }
    ],
    "sg:phone":"+33 5 53 05 55 30",
    "sg:postcode":"24660",
    "sg:province":"Aquitaine",
    "sg:tags":[
        "work",
        "public"
    ],
    "wof:name":"Dordogne Enrobes",
    "wof:placetype":"venue"
},
  "geometry": {"coordinates":[0.714495,45.122566],"type":"Point"}
}