{
  "type": "Feature",
  "properties": {
    "addr:full":"B.P. 2154, 69603 Villeurbanne C\u00e9dex^^16, Rue d'Inkermann, 69600 Villeurbanne Rhone-Alpes 69600",
    "addr:postcode":"69603;69600;69600",
    "addr:street":"B.P. 2154;Rue D'Inkermann",
    "iso:country":"FR",
    "sg:address":"B.P. 2154, 69603 Villeurbanne C\u00e9dex^^16, Rue d'Inkermann, 69600 Villeurbanne",
    "sg:orig_category":"Non-Classified Establishments",
    "sg:phone":"+33 4 78 24 01 21",
    "sg:postcode":"69600",
    "sg:province":"Rhone-Alpes",
    "wof:name":"Art Publicitaire S.a.",
    "wof:placetype":"venue"
},
  "geometry": {"coordinates":[4.868352,45.777622],"type":"Point"}
}