{
  "type": "Feature",
  "properties": {
    "addr:full":"75, Rue des Etats Unis, 69800 Saint Priest Rhone-Alpes 69800",
    "addr:housenumber":"75",
    "addr:postcode":"69800;69800",
    "addr:street":"Rue Des Etats Unis;Priest Rhone-Alpes",
    "iso:country":"FR",
    "sg:address":"75, Rue des Etats Unis, 69800 Saint Priest",
    "sg:orig_category":"Non-Classified Establishments",
    "sg:phone":"+33 4 78 20 62 37",
    "sg:postcode":"69800",
    "sg:province":"Rhone-Alpes",
    "wof:name":"Film\u00e9tal S.a.r.l.",
    "wof:placetype":"venue"
},
  "geometry": {"coordinates":[4.91746,45.70359],"type":"Point"}
}