{
  "type": "Feature",
  "properties": {
    "addr:full":"77 Pl L'H\u00e9rillier 59500 Douai Nord Pas-de-Calais",
    "addr:housenumber":"77",
    "addr:postcode":"59500",
    "addr:street":"Pl L'He \u0301Rillier",
    "iso:country":"FR",
    "sg:address":"77 Pl L'H\u00e9rillier 59500 Douai",
    "sg:classifiers":[
        {
            "category":"Manufacturing",
            "subcategory":"Rubber & Plastics",
            "type":"Manufacturing & Wholesale Goods"
        }
    ],
    "sg:phone":"+33 3 27 87 91 91",
    "sg:province":"Nord Pas-de-Calais",
    "wof:name":"Fermoba Industrie",
    "wof:placetype":"venue"
},
  "geometry": {"coordinates":[3.078372,50.363148],"type":"Point"}
}