{
  "type": "Feature",
  "properties": {
    "addr:full":"65, Chauss\u00e9e Watt, 59200 Tourcoing Nord Pas-de-Calais",
    "addr:housenumber":"65",
    "addr:postcode":"59200",
    "addr:street":"Chausse\u0301E Watt",
    "iso:country":"FR",
    "sg:address":"65, Chauss\u00e9e Watt, 59200 Tourcoing",
    "sg:orig_category":"Unclassifiable Establishments",
    "sg:phone":"+33 3 20 03 11 11",
    "sg:province":"Nord Pas-de-Calais",
    "wof:name":"Nys Et Compagnie S.a.r.l.",
    "wof:placetype":"venue"
},
  "geometry": {"coordinates":[3.134753,50.726597],"type":"Point"}
}