{
  "type": "Feature",
  "properties": {
    "iso:country":"FR",
    "sg:address":"Mounet 17700 St Germain De Marencennes",
    "sg:classifiers":[
        {
            "category":"Food & Beverages",
            "subcategory":"Groceries & Convenience Stores",
            "type":"Retail Goods"
        }
    ],
    "sg:phone":"+33 5 46 07 38 38",
    "sg:postcode":"17700",
    "sg:province":"Poitou-Charentes",
    "sg:tags":[
        "product",
        "grain",
        "cereal",
        "related"
    ],
    "wof:name":"Les Meuniers Du Littoral",
    "wof:placetype":"venue"
},
  "geometry": {"coordinates":[-0.786879,46.07626],"type":"Point"}
}