{
  "type": "Feature",
  "properties": {
    "iso:country":"FR",
    "sg:address":"28 Avenue Valrose",
    "sg:city":"Valrose 06108 Nice Cedex 2",
    "sg:classifiers":[
        {
            "category":"Professional",
            "subcategory":"Business Services",
            "type":"Services"
        }
    ],
    "sg:phone":"+33 4 92 07 60 60",
    "sg:province":"Languedoc-Roussillon",
    "sg:tags":[
        "training",
        "advice"
    ],
    "wof:name":"Universite De Nice Sophia Antipolis",
    "wof:placetype":"venue"
},
  "geometry": {"coordinates":[7.26542,43.714989],"type":"Point"}
}