{
  "type": "Feature",
  "properties": {
    "addr:full":"2 Rue Philippe Gaudey 25400 Exincourt Franche Comt\u00e9 25400",
    "addr:housenumber":"2",
    "addr:postcode":"25400;25400",
    "addr:street":"Rue Philippe Gaudey;Franche Comte\u0301",
    "iso:country":"FR",
    "sg:address":"2 Rue Philippe Gaudey 25400 Exincourt",
    "sg:classifiers":[
        {
            "category":"Travel",
            "subcategory":"Hotels & Motels",
            "type":"Entertainment"
        }
    ],
    "sg:phone":"+33 3 81 95 57 53",
    "sg:postcode":"25400",
    "sg:province":"Franche Comt\u00e9",
    "sg:tags":[
        "hotels",
        "business",
        "restaurant"
    ],
    "wof:name":"D'exincourt",
    "wof:placetype":"venue"
},
  "geometry": {"coordinates":[6.83359,47.49865],"type":"Point"}
}