{
  "type": "Feature",
  "properties": {
    "addr:full":"6, Rue des Gli\u00e8res - ZI, 74150 Rumilly Rhone-Alpes",
    "addr:housenumber":"6",
    "addr:postcode":"74150",
    "addr:street":"Rue Des Glie\u0300Res Zi",
    "iso:country":"FR",
    "sg:address":"6, Rue des Gli\u00e8res - ZI, 74150 Rumilly",
    "sg:orig_category":"Unclassifiable Establishments",
    "sg:phone":"+33 4 50 01 31 95",
    "sg:province":"Rhone-Alpes",
    "wof:name":"S.o.c.c. S.a. - Soci\u00e9t\u00e9 D'outillage De Carbure Du Ch\u00e9ran",
    "wof:placetype":"venue"
},
  "geometry": {"coordinates":[5.943953,45.822372],"type":"Point"}
}