{
  "type": "Feature",
  "properties": {
    "addr:full":"11 Rue Gambetta 51500 Rilly La Montagne Champagne 51500",
    "addr:housenumber":"11",
    "addr:postcode":"51500;51500",
    "addr:street":"Rue Gambetta;Champagne",
    "iso:country":"FR",
    "sg:address":"11 Rue Gambetta 51500 Rilly La Montagne",
    "sg:classifiers":[
        {
            "category":"Food Court",
            "type":"Food & Drink"
        }
    ],
    "sg:phone":"+33 3 26 03 40 67",
    "sg:postcode":"51500",
    "sg:province":"Champagne",
    "sg:tags":[
        "product",
        "related"
    ],
    "wof:name":"Champagne Daniel Dumont",
    "wof:placetype":"venue"
},
  "geometry": {"coordinates":[4.042522,49.166897],"type":"Point"}
}