{
  "type": "Feature",
  "properties": {
    "iso:country":"FR",
    "sg:address":"2, Quai Aulagnier - Port de Plaisance Van Gogh, 92600 Asni\u00e8res sur Seine",
    "sg:orig_category":"Non-Classified Establishments",
    "sg:phone":"+33 1 41 32 13 13",
    "sg:postcode":"92600",
    "sg:province":"Ile de France",
    "wof:name":"Bw Marketing S.a.",
    "wof:placetype":"venue"
},
  "geometry": {"coordinates":[2.289035,48.910294],"type":"Point"}
}