{
  "type": "Feature",
  "properties": {
    "addr:full":"La Croix des Riaux 44530 Saint Gildas des Bois Pays de Loire",
    "addr:postcode":"44530;gildas",
    "addr:street":"La Croix Des Riaux;Des Bois Pays",
    "iso:country":"FR",
    "sg:address":"La Croix des Riaux 44530 Saint Gildas des Bois",
    "sg:orig_category":"Unclassifiable Establishments",
    "sg:phone":"+33 2 40 91 88 00",
    "sg:province":"Pays de Loire",
    "wof:name":"Etablissements Poupard S.a.r.l.",
    "wof:placetype":"venue"
},
  "geometry": {"coordinates":[-1.98347,47.57576],"type":"Point"}
}