{
  "type": "Feature",
  "properties": {
    "iso:country":"FR",
    "sg:address":"La Croix des Riaux 44530 Saint Gildas des Bois",
    "sg:orig_category":"Unclassifiable Establishments",
    "sg:phone":"+33 2 40 91 88 00",
    "sg:province":"Pays de Loire",
    "wof:name":"Etablissements Poupard S.a.r.l.",
    "wof:placetype":"venue"
},
  "geometry": {"coordinates":[-1.98347,47.57576],"type":"Point"}
}