{
  "type": "Feature",
  "properties": {
    "addr:full":"Hameau De Paterier 74410 St Eustache Rhone-Alpes 74410",
    "addr:postcode":"74410;74410",
    "addr:street":"Hameau De Paterier",
    "iso:country":"FR",
    "sg:address":"Hameau De Paterier 74410 St Eustache",
    "sg:classifiers":[
        {
            "category":"Farming",
            "subcategory":"Farm & Veterinary Services",
            "type":"Manufacturing & Wholesale Goods"
        }
    ],
    "sg:phone":"+33 4 50 32 00 12",
    "sg:postcode":"74410",
    "sg:province":"Rhone-Alpes",
    "sg:tags":[
        "advice",
        "agriculture",
        "livestock",
        "business"
    ],
    "wof:name":"Entreprise Mugnier Pollet Pere Et Fils",
    "wof:placetype":"venue"
},
  "geometry": {"coordinates":[6.160926,45.806999],"type":"Point"}
}