{
  "type": "Feature",
  "properties": {
    "addr:full":"route de Montargis 89300 Joigny Joigny Bourgogne 89300",
    "addr:postcode":"89300;89300",
    "addr:street":"Route De Montargis",
    "iso:country":"FR",
    "sg:address":"route de Montargis 89300 Joigny",
    "sg:city":"Joigny",
    "sg:classifiers":[
        {
            "category":"Autos & Motor Vehicles",
            "subcategory":"Auto Supplies",
            "type":"Retail Goods"
        }
    ],
    "sg:phone":"+33 3 86 92 82 00",
    "sg:postcode":"89300",
    "sg:province":"Bourgogne",
    "sg:tags":[
        "automobile",
        "accessory"
    ],
    "wof:name":"Arvin Exhaust Sa",
    "wof:placetype":"venue"
},
  "geometry": {"coordinates":[3.38553,47.9776],"type":"Point"}
}