{
  "type": "Feature",
  "properties": {
    "addr:full":"B.P. 333, 07003 Privas C\u00e9dex^^Chemin des Artisans - ZI, 07000 Privas Rhone-Alpes 07000",
    "addr:housenumber":"b.p. 333",
    "addr:postcode":"07003;07000;07000",
    "addr:street":"Zi",
    "iso:country":"FR",
    "sg:address":"B.P. 333, 07003 Privas C\u00e9dex^^Chemin des Artisans - ZI, 07000 Privas",
    "sg:orig_category":"Non-Classified Establishments",
    "sg:phone":"+33 4 75 64 29 11",
    "sg:postcode":"07000",
    "sg:province":"Rhone-Alpes",
    "wof:name":"Delta Pr\u00e9fabrication S.a.",
    "wof:placetype":"venue"
},
  "geometry": {"coordinates":[4.59695,44.738419],"type":"Point"}
}