{
  "type": "Feature",
  "properties": {
    "addr:full":"8 rue Bellini 75116 Paris Ile de France",
    "addr:housenumber":"8",
    "addr:postcode":"75116",
    "addr:street":"Rue Bellini",
    "iso:country":"FR",
    "sg:address":"8 rue Bellini 75116 Paris",
    "sg:classifiers":[
        {
            "category":"Professional",
            "subcategory":"Advertising",
            "type":"Services"
        }
    ],
    "sg:phone":"+33 1 53 65 63 33",
    "sg:province":"Ile de France",
    "sg:tags":[
        "newspaper",
        "journal"
    ],
    "wof:name":"Medicus 1 Team Sarl",
    "wof:placetype":"venue"
},
  "geometry": {"coordinates":[2.282304,48.860973],"type":"Point"}
}