{
  "type": "Feature",
  "properties": {
    "addr:full":"Nancelles 71960 La Roche Vineuse Berz\u00e9-le-Ch\u00e2tel Bourgogne 71960",
    "addr:postcode":"71960;71960",
    "addr:street":"Nancelles;Bourgogne",
    "iso:country":"FR",
    "sg:address":"Nancelles 71960 La Roche Vineuse",
    "sg:city":"Berz\u00e9-le-Ch\u00e2tel",
    "sg:orig_category":"Non-Classified Establishments",
    "sg:phone":"+33 3 85 34 53 56",
    "sg:postcode":"71960",
    "sg:province":"Bourgogne",
    "wof:name":"Grosne Terrassement S.a.r.l.",
    "wof:placetype":"venue"
},
  "geometry": {"coordinates":[4.765079,46.354641],"type":"Point"}
}