{
  "type": "Feature",
  "properties": {
    "iso:country":"FR",
    "sg:address":"B.P. 159, 84124 Pertuis C\u00e9dex^^Rte d' Aix en Provence, 84120 Pertuis",
    "sg:orig_category":"Non-Classified Establishments",
    "sg:phone":"+33 4 90 09 23 00",
    "sg:province":"Provence-Alpes-C\u00f4te d'Azur",
    "wof:name":"Salaison Pertuisienne S.a.",
    "wof:placetype":"venue"
},
  "geometry": {"coordinates":[5.501571,43.684769],"type":"Point"}
}