{
  "type": "Feature",
  "properties": {
    "addr:full":"38 Rue de la Resistance; Bergerac; 24100 Bergerac Aquitaine 24100",
    "addr:housenumber":"38",
    "addr:postcode":"24100;24100",
    "addr:street":"Rue De La Resistance",
    "iso:country":"FR",
    "sg:address":"38 Rue de la Resistance; Bergerac; 24100",
    "sg:city":"Bergerac",
    "sg:classifiers":[
        {
            "category":"Banks & Credit Unions",
            "subcategory":"Bank",
            "type":"Services"
        }
    ],
    "sg:phone":"+33 5 53 74 48 00",
    "sg:postcode":"24100",
    "sg:province":"Aquitaine",
    "wof:name":"Cr\u00e9dit Commercial, Du Sud Ouest",
    "wof:placetype":"venue"
},
  "geometry": {"coordinates":[0.485657,44.853058],"type":"Point"}
}