{
  "type": "Feature",
  "properties": {
    "addr:full":"1305 R Achille P\u00e9r\u00e8s 59640 Dunkerque Franche Comt\u00e9",
    "addr:housenumber":"1305",
    "addr:postcode":"59640",
    "addr:street":"R Achille Pe\u0301Re\u0300S;Franche Comte\u0301",
    "iso:country":"FR",
    "sg:address":"1305 R Achille P\u00e9r\u00e8s 59640 Dunkerque",
    "sg:classifiers":[
        {
            "category":"Professional",
            "subcategory":"Engineering",
            "type":"Services"
        }
    ],
    "sg:phone":"+33 3 28 64 50 60",
    "sg:province":"Franche Comt\u00e9",
    "sg:tags":[
        "machine",
        "-",
        "mechanical"
    ],
    "wof:name":"Gleser",
    "wof:placetype":"venue"
},
  "geometry": {"coordinates":[2.332552,51.007557],"type":"Point"}
}