{
  "type": "Feature",
  "properties": {
    "iso:country":"FR",
    "sg:address":"La Parroni\u00e8re 61100 Caligny",
    "sg:city":"Caligny",
    "sg:orig_category":"Unclassifiable Establishments",
    "sg:phone":"+33 2 33 96 41 75",
    "sg:postcode":"61100",
    "sg:province":"Basse Normandie",
    "wof:name":"Caligny Viandes Du Bocage S.a.r.l.",
    "wof:placetype":"venue"
},
  "geometry": {"coordinates":[-0.582924,48.708271],"type":"Point"}
}