{
  "type": "Feature",
  "properties": {
    "addr:full":"Rte de Choisy La Balme de Sillingy Rhone-Alpes 74330",
    "addr:postcode":"74330",
    "addr:street":"Rte De Choisy La Balme De Sillingy Rhone-Alpes",
    "iso:country":"FR",
    "sg:address":"Rte de Choisy",
    "sg:city":"La Balme de Sillingy",
    "sg:orig_category":"Non-Classified Establishments",
    "sg:phone":"+33 4 50 68 87 00",
    "sg:postcode":"74330",
    "sg:province":"Rhone-Alpes",
    "wof:name":"Maisons Giraud S.a.",
    "wof:placetype":"venue"
},
  "geometry": {"coordinates":[6.04104,45.960114],"type":"Point"}
}