{
  "type": "Feature",
  "properties": {
    "iso:country":"FR",
    "sg:address":"B.P. 106, 59542 Caudry C\u00e9dex^^46, Rue Jules Guesde, 59540 Caudry",
    "sg:orig_category":"Non-Classified Establishments",
    "sg:phone":"+33 3 27 85 30 41",
    "sg:province":"Nord Pas-de-Calais",
    "wof:name":"Tarsot Industrie Successeur S.a.r.l.",
    "wof:placetype":"venue"
},
  "geometry": {"coordinates":[3.41236,50.124474],"type":"Point"}
}