{
  "type": "Feature",
  "properties": {
    "addr:full":"3, Rue Largilli\u00e8re, 75016 Paris Ile de France 75016",
    "addr:housenumber":"3",
    "addr:postcode":"75016;75016",
    "addr:street":"Rue Largillie\u0300Re",
    "iso:country":"FR",
    "sg:address":"3, Rue Largilli\u00e8re, 75016 Paris",
    "sg:orig_category":"Non-Classified Establishments",
    "sg:phone":"+33 1 45 24 34 34",
    "sg:postcode":"75016",
    "sg:province":"Ile de France",
    "wof:name":"Alain Damay Consulting S.a.r.l.",
    "wof:placetype":"venue"
},
  "geometry": {"coordinates":[2.272588,48.857555],"type":"Point"}
}