{
  "type": "Feature",
  "properties": {
    "addr:full":"Rue Louis Neel - ZI des Blanchisseries Voiron C\u00e9dex Midi Pyr\u00e9n\u00e9es 38516",
    "addr:postcode":"38516",
    "addr:street":"Rue Louis Neel Zi Des Blanchisseries",
    "iso:country":"FR",
    "sg:address":"Rue Louis Neel - ZI des Blanchisseries",
    "sg:city":"Voiron C\u00e9dex",
    "sg:orig_category":"Non-Classified Establishments",
    "sg:phone":"+33 4 76 05 02 47",
    "sg:postcode":"38516",
    "sg:province":"Midi Pyr\u00e9n\u00e9es",
    "wof:name":"Neton Et Compagnie S.a.",
    "wof:placetype":"venue"
},
  "geometry": {"coordinates":[5.59166,45.367149],"type":"Point"}
}