{
  "type": "Feature",
  "properties": {
    "addr:full":"8 Rue Saint-Marc 75002 Paris Ile de France",
    "addr:housenumber":"8",
    "addr:postcode":"75002",
    "addr:street":"Rue Saint-Marc",
    "iso:country":"FR",
    "sg:address":"8 Rue Saint-Marc 75002 Paris",
    "sg:classifiers":[
        {
            "category":"Manufacturing",
            "subcategory":"Printing",
            "type":"Manufacturing & Wholesale Goods"
        }
    ],
    "sg:phone":"+33 1 42 36 08 15",
    "sg:province":"Ile de France",
    "sg:tags":[
        "publishing"
    ],
    "wof:name":"Simediat",
    "wof:placetype":"venue"
},
  "geometry": {"coordinates":[2.341696,48.870461],"type":"Point"}
}