{
  "type": "Feature",
  "properties": {
    "addr:full":"Rue Patrick Baudry Tarbes Midi Pyr\u00e9n\u00e9es 65000",
    "addr:postcode":"65000",
    "addr:street":"Rue Patrick Baudry",
    "iso:country":"FR",
    "sg:address":"Rue Patrick Baudry",
    "sg:city":"Tarbes",
    "sg:orig_category":"Non-Classified Establishments",
    "sg:phone":"+33 5 62 93 47 57",
    "sg:postcode":"65000",
    "sg:province":"Midi Pyr\u00e9n\u00e9es",
    "wof:name":"Asturienne Penamet S.a.",
    "wof:placetype":"venue"
},
  "geometry": {"coordinates":[0.089625,43.219311],"type":"Point"}
}