{
  "type": "Feature",
  "properties": {
    "iso:country":"FR",
    "sg:address":"ZI de la Croix Blanche",
    "sg:city":"Malville",
    "sg:orig_category":"Non-Classified Establishments",
    "sg:phone":"+33 2 40 56 42 58",
    "sg:postcode":"44260",
    "sg:province":"Pays de Loire",
    "wof:name":"Soci\u00e9t\u00e9 Dyonix S.a.r.l.",
    "wof:placetype":"venue"
},
  "geometry": {"coordinates":[-1.863199,47.359871],"type":"Point"}
}