{
  "type": "Feature",
  "properties": {
    "addr:full":"B.P. 411, 74013 Annecy C\u00e9dex^^24-26, Av. de Chamb\u00e9ry, 74000 Annecy Rhone-Alpes 74000",
    "addr:housenumber":"b.p. 411;-26",
    "addr:postcode":"74013;74000;74000",
    "addr:street":"Ce\u0301Dex^^24;Av. De Chambe\u0301Ry",
    "iso:country":"FR",
    "sg:address":"B.P. 411, 74013 Annecy C\u00e9dex^^24-26, Av. de Chamb\u00e9ry, 74000 Annecy",
    "sg:orig_category":"Non-Classified Establishments",
    "sg:phone":"+33 4 50 51 86 22",
    "sg:postcode":"74000",
    "sg:province":"Rhone-Alpes",
    "wof:name":"B.f.c.c.",
    "wof:placetype":"venue"
},
  "geometry": {"coordinates":[6.128832,45.898781],"type":"Point"}
}