{
  "type": "Feature",
  "properties": {
    "addr:full":"21 Rte Ay 51160 Mareuil Sur Ay Champagne 51160",
    "addr:housenumber":"21",
    "addr:postcode":"51160;51160",
    "addr:street":"Rte Ay;Mareuil",
    "iso:country":"FR",
    "sg:address":"21 Rte Ay 51160 Mareuil Sur Ay",
    "sg:classifiers":[
        {
            "category":"Professional",
            "subcategory":"Engineering",
            "type":"Services"
        }
    ],
    "sg:phone":"+33 3 26 59 54 00",
    "sg:postcode":"51160",
    "sg:province":"Champagne",
    "sg:tags":[
        "machine",
        "-",
        "mechanical"
    ],
    "wof:name":"Pechiney Capsules",
    "wof:placetype":"venue"
},
  "geometry": {"coordinates":[4.030412,49.046539],"type":"Point"}
}