{
  "type": "Feature",
  "properties": {
    "iso:country":"FR",
    "sg:address":". - Le Village",
    "sg:city":"Saint Sorlin de Morestel",
    "sg:orig_category":"Unclassifiable Establishments",
    "sg:phone":"+33 4 74 80 19 33",
    "sg:postcode":"38510",
    "sg:province":"Rhone-Alpes",
    "wof:name":"S.o.d.a.f.o.m. S.a. - Soci\u00e9t\u00e9 Dauphinoise De Fonderie Et De M\u00e9canique",
    "wof:placetype":"venue"
},
  "geometry": {"coordinates":[5.475785,45.635395],"type":"Point"}
}