{
  "type": "Feature",
  "properties": {
    "iso:country":"FR",
    "sg:address":"B.P. 391, 63011 Clermont Ferrand C\u00e9dex 1^^3, Rue d'Enfer, 63000 Clermont Ferrand",
    "sg:city":"Clermont-Ferrand",
    "sg:orig_category":"Non-Classified Establishments",
    "sg:phone":"+33 4 73 14 44 04",
    "sg:postcode":"63000",
    "sg:province":"Auvergne",
    "wof:name":"Queyriaux Design Et Communication S.a.",
    "wof:placetype":"venue"
},
  "geometry": {"coordinates":[3.12125,45.77145],"type":"Point"}
}