{
  "type": "Feature",
  "properties": {
    "addr:full":"chemin de Ch\u00e2teauvallon 83190 Ollioules Ch\u00e2teau Bourgogne 71250",
    "addr:postcode":"83190;71250",
    "addr:street":"Chemin De Cha\u0302Teauvallon",
    "iso:country":"FR",
    "sg:address":"chemin de Ch\u00e2teauvallon 83190 Ollioules",
    "sg:city":"Ch\u00e2teau",
    "sg:orig_category":"Broking Agencies For Electronics, Domestic And Foreign",
    "sg:phone":"+33 4 94 18 90 20",
    "sg:postcode":"71250",
    "sg:province":"Bourgogne",
    "wof:name":"Auxiliaire M\u00e9tallurgique Sa",
    "wof:placetype":"venue"
},
  "geometry": {"coordinates":[5.878309,43.147099],"type":"Point"}
}