{
  "type": "Feature",
  "properties": {
    "iso:country":"FR",
    "sg:address":"Chemin de l'Oratoire de Bouc - ZI Avon",
    "sg:city":"Gardanne",
    "sg:orig_category":"Unclassifiable Establishments",
    "sg:phone":"+33 4 42 65 85 77",
    "sg:postcode":"13120",
    "sg:province":"Poitou-Charentes",
    "wof:name":"Roumejon Pagano Soudure S.a.r.l.",
    "wof:placetype":"venue"
},
  "geometry": {"coordinates":[5.48555,43.458542],"type":"Point"}
}