{
  "type": "Feature",
  "properties": {
    "iso:country":"FR",
    "sg:address":"19, Rue Jules David, 93260 Les Lilas",
    "sg:orig_category":"Unclassifiable Establishments",
    "sg:phone":"+33 1 43 62 60 22",
    "sg:province":"Ile de France",
    "wof:name":"Aguirre Michel",
    "wof:placetype":"venue"
},
  "geometry": {"coordinates":[2.413944,48.875317],"type":"Point"}
}