{
  "type": "Feature",
  "properties": {
    "iso:country":"FR",
    "sg:address":"Le Grand Saint Mitre 83470 Saint Maximin la Sainte Baume",
    "sg:orig_category":"Unclassifiable Establishments",
    "sg:phone":"+33 4 94 59 73 15",
    "sg:province":"Provence-Alpes-C\u00f4te d'Azur",
    "wof:name":"P\u00e9pini\u00e8res Sainte-baume S.a.r.l.",
    "wof:placetype":"venue"
},
  "geometry": {"coordinates":[5.86024,43.452839],"type":"Point"}
}