{
  "type": "Feature",
  "properties": {
    "addr:full":"1 Rue Du Ch\u00e2teau D'Eau 28150 Voves Voves Centre 28150",
    "addr:housenumber":"1;voves",
    "addr:postcode":"28150;28150",
    "addr:street":"Rue Du Cha\u0302Teau D'Eau",
    "iso:country":"FR",
    "sg:address":"1 Rue Du Ch\u00e2teau D'Eau 28150 Voves",
    "sg:city":"Voves",
    "sg:classifiers":[
        {
            "category":"Professional",
            "type":"Services"
        }
    ],
    "sg:phone":"+33 2 37 99 08 82",
    "sg:postcode":"28150",
    "sg:province":"Centre",
    "sg:tags":[
        "transport",
        "road"
    ],
    "wof:name":"Transports Beauhaire Sarl",
    "wof:placetype":"venue"
},
  "geometry": {"coordinates":[1.565464,48.259747],"type":"Point"}
}