{
  "type": "Feature",
  "properties": {
    "iso:country":"FR",
    "sg:address":"5 R Des Cr\u00eats 01007 Bourg En Bresse Cedex",
    "sg:classifiers":[
        {
            "category":"Food & Beverages",
            "subcategory":"Dairy",
            "type":"Retail Goods"
        }
    ],
    "sg:phone":"+33 4 74 50 41 30",
    "sg:province":"Centre",
    "sg:tags":[
        "product",
        "related"
    ],
    "wof:name":"Laiterie De La Bresse Sa",
    "wof:placetype":"venue"
},
  "geometry": {"coordinates":[5.22361,46.214344],"type":"Point"}
}