{
  "type": "Feature",
  "properties": {
    "iso:country":"FR",
    "sg:address":"7 pl du Minage; Clisson; 44190",
    "sg:classifiers":[
        {
            "category":"Banks & Credit Unions",
            "subcategory":"Bank",
            "type":"Services"
        }
    ],
    "sg:phone":"+33 3340783533",
    "sg:postcode":"44190",
    "sg:province":"Pays de Loire",
    "wof:name":"Banque Nationale De Paris",
    "wof:placetype":"venue"
},
  "geometry": {"coordinates":[-1.28191,47.087029],"type":"Point"}
}