{
  "type": "Feature",
  "properties": {
    "addr:full":"8 rue de l'Azin 41000 Blois Blois Centre 41000",
    "addr:housenumber":"8",
    "addr:postcode":"41000;41000",
    "addr:street":"Rue De L'Azin",
    "iso:country":"FR",
    "sg:address":"8 rue de l'Azin 41000 Blois",
    "sg:city":"Blois",
    "sg:classifiers":[
        {
            "category":"Social Services",
            "subcategory":"Job Training",
            "type":"Services"
        }
    ],
    "sg:phone":"+33 2 54 74 65 15",
    "sg:postcode":"41000",
    "sg:province":"Centre",
    "sg:tags":[
        "consulting",
        "maintenance"
    ],
    "wof:name":"Cimi Association Ass",
    "wof:placetype":"venue"
},
  "geometry": {"coordinates":[1.329004,47.613453],"type":"Point"}
}