{
  "type": "Feature",
  "properties": {
    "addr:full":"ZAC de Carling - Espace Europort Saint Avold Lorraine 57500",
    "addr:postcode":"57500",
    "addr:street":"Zac De Carling Espace Europort Saint Avold Lorraine",
    "iso:country":"FR",
    "sg:address":"ZAC de Carling - Espace Europort",
    "sg:city":"Saint Avold",
    "sg:orig_category":"Unclassifiable Establishments",
    "sg:phone":"+33 3 87 93 98 20",
    "sg:postcode":"57500",
    "sg:province":"Lorraine",
    "wof:name":"Poliglas France Industrie S.a.",
    "wof:placetype":"venue"
},
  "geometry": {"coordinates":[6.705505,49.104275],"type":"Point"}
}