{
  "type": "Feature",
  "properties": {
    "addr:full":"19 Rue Du Mal Brune 19102 Brive La Gaillarde Lorraine",
    "addr:housenumber":"19",
    "addr:postcode":"19102",
    "addr:street":"Rue Du Mal Brune",
    "iso:country":"FR",
    "sg:address":"19 Rue Du Mal Brune 19102 Brive La Gaillarde",
    "sg:classifiers":[
        {
            "category":"Manufacturing",
            "subcategory":"Printing",
            "type":"Manufacturing & Wholesale Goods"
        }
    ],
    "sg:phone":"+33 5 55 92 84 84",
    "sg:province":"Lorraine",
    "sg:tags":[
        "publishing"
    ],
    "wof:name":"Sarl Georges Lachaise",
    "wof:placetype":"venue"
},
  "geometry": {"coordinates":[0.85753,49.836731],"type":"Point"}
}