{
  "type": "Feature",
  "properties": {
    "addr:full":"Rue Sarrault Zi 18200 St Amand Montrond Arpheuilles Centre 18200",
    "addr:postcode":"18200;18200",
    "addr:street":"Rue Sarrault Zi",
    "iso:country":"FR",
    "sg:address":"Rue Sarrault Zi 18200 St Amand Montrond",
    "sg:city":"Arpheuilles",
    "sg:classifiers":[
        {
            "category":"Manufacturing",
            "subcategory":"Jewelry",
            "type":"Manufacturing & Wholesale Goods"
        }
    ],
    "sg:phone":"+33 2 48 96 50 26",
    "sg:postcode":"18200",
    "sg:province":"Centre",
    "sg:tags":[
        "product",
        "miscellaneous",
        "jewellery"
    ],
    "wof:name":"Carmafix Ste Sa",
    "wof:placetype":"venue"
},
  "geometry": {"coordinates":[2.574637,46.64399],"type":"Point"}
}