{
  "type": "Feature",
  "properties": {
    "iso:country":"FR",
    "sg:address":"49170 St Georges Sur Loire",
    "sg:classifiers":[
        {
            "category":"Education",
            "subcategory":"Special Training",
            "type":"Public Place"
        }
    ],
    "sg:phone":"+33 2 41 39 14 57",
    "sg:postcode":"49170",
    "sg:province":"Pays de Loire",
    "sg:tags":[
        "pharmaceutical",
        "livestock",
        "animal",
        "chemical",
        "grain",
        "cereal",
        "breeding",
        "chem",
        "agriculture"
    ],
    "wof:name":"Caval",
    "wof:placetype":"venue"
},
  "geometry": {"coordinates":[-0.760769,47.40876],"type":"Point"}
}