{
  "type": "Feature",
  "properties": {
    "addr:full":"10 R Des Entrep\u00f4ts 27400 Louviers Haute Normandie",
    "addr:housenumber":"10 r",
    "addr:postcode":"27400",
    "addr:street":"Des Entrepo\u0302Ts;Haute Normandie",
    "iso:country":"FR",
    "sg:address":"10 R Des Entrep\u00f4ts 27400 Louviers",
    "sg:classifiers":[
        {
            "category":"Manufacturing",
            "subcategory":"Printing",
            "type":"Manufacturing & Wholesale Goods"
        }
    ],
    "sg:phone":"+33 2 32 40 01 33",
    "sg:province":"Haute Normandie",
    "sg:tags":[
        "publishing"
    ],
    "wof:name":"Budin Et Fils Sa",
    "wof:placetype":"venue"
},
  "geometry": {"coordinates":[1.170625,49.229721],"type":"Point"}
}