{
  "type": "Feature",
  "properties": {
    "addr:full":"B.P. 5, 21601 Longvic C\u00e9dex^^3, Bd de Beauregard, 21600 Longvic Longvic Bourgogne 21600",
    "addr:housenumber":"5",
    "addr:postcode":"21601;ce\u0301dex^^3;21600;21600",
    "addr:street":"B.P.;Bd De Beauregard",
    "iso:country":"FR",
    "sg:address":"B.P. 5, 21601 Longvic C\u00e9dex^^3, Bd de Beauregard, 21600 Longvic",
    "sg:city":"Longvic",
    "sg:orig_category":"Non-Classified Establishments",
    "sg:phone":"+33 3 80 73 78 78",
    "sg:postcode":"21600",
    "sg:province":"Bourgogne",
    "wof:name":"I.f.f. S.a.s. - International Flavors And Fragrances",
    "wof:placetype":"venue"
},
  "geometry": {"coordinates":[5.06327,47.286015],"type":"Point"}
}