{
  "type": "Feature",
  "properties": {
    "iso:country":"FR",
    "sg:address":"Rte de Monsau - ZI",
    "sg:city":"Steinbourg",
    "sg:orig_category":"Unclassifiable Establishments",
    "sg:phone":"+33 3 88 01 87 07",
    "sg:postcode":"67790",
    "sg:province":"Alsace",
    "wof:name":"Heinrich Bock S.a.",
    "wof:placetype":"venue"
},
  "geometry": {"coordinates":[7.413322,48.769691],"type":"Point"}
}