{
  "type": "Feature",
  "properties": {
    "addr:full":"La Grange Arthuis 89170 Lavau Lavau Bourgogne 89170",
    "addr:postcode":"89170;89170",
    "addr:street":"Arthuis",
    "iso:country":"FR",
    "sg:address":"La Grange Arthuis 89170 Lavau",
    "sg:city":"Lavau",
    "sg:classifiers":[
        {
            "category":"Food Court",
            "type":"Food & Drink"
        }
    ],
    "sg:phone":"+33 3 86 74 06 20",
    "sg:postcode":"89170",
    "sg:province":"Bourgogne",
    "sg:tags":[
        "product",
        "related"
    ],
    "wof:name":"Ste Agricole De La Grange Arthuis (saga)",
    "wof:placetype":"venue"
},
  "geometry": {"coordinates":[2.966435,47.603653],"type":"Point"}
}