{
  "type": "Feature",
  "properties": {
    "addr:full":"16, Rue Boussingault, 75013 Paris Ile de France",
    "addr:housenumber":"16",
    "addr:postcode":"75013",
    "addr:street":"Rue Boussingault",
    "iso:country":"FR",
    "sg:address":"16, Rue Boussingault, 75013 Paris",
    "sg:orig_category":"Unclassifiable Establishments",
    "sg:phone":"+33 1 45 88 33 34",
    "sg:province":"Ile de France",
    "wof:name":"M\u00e9dia Alarme S.a.",
    "wof:placetype":"venue"
},
  "geometry": {"coordinates":[2.345507,48.823448],"type":"Point"}
}