{
  "type": "Feature",
  "properties": {
    "iso:country":"FR",
    "sg:address":"B.P. 303, 56008 Vannes c\u00e9dex^^Parc d'Innovation Bretagne Sud, 56000 Vannes",
    "sg:city":"Vannes",
    "sg:orig_category":"Non-Classified Establishments",
    "sg:phone":"+33 2 97 47 83 06",
    "sg:postcode":"56000",
    "sg:province":"Bretagne",
    "wof:name":"Arca Editions S.a.r.l.",
    "wof:placetype":"venue"
},
  "geometry": {"coordinates":[-2.760302,47.660984],"type":"Point"}
}