{
  "type": "Feature",
  "properties": {
    "iso:country":"FR",
    "sg:address":"38 Chemin De La Noiviere 85270 St Hilaire De Riez",
    "sg:classifiers":[
        {
            "category":"Farming",
            "subcategory":"Livestock Farm",
            "type":"Manufacturing & Wholesale Goods"
        }
    ],
    "sg:phone":"+33 2 51 54 15 05",
    "sg:postcode":"85270",
    "sg:province":"Pays de Loire",
    "sg:tags":[
        "breeding",
        "agriculture",
        "animal"
    ],
    "wof:name":"Burgaud Karl",
    "wof:placetype":"venue"
},
  "geometry": {"coordinates":[-1.948649,46.738895],"type":"Point"}
}