{
  "type": "Feature",
  "properties": {
    "addr:full":"111 Av De Villarcher Zi Des Landiers Nord 73000 Chamb\u00e9ry Rhone-Alpes 73000",
    "addr:postcode":"73000;73000",
    "addr:street":"111 Av De Villarcher Zi Des Landiers Nord",
    "iso:country":"FR",
    "sg:address":"111 Av De Villarcher Zi Des Landiers Nord 73000 Chamb\u00e9ry",
    "sg:classifiers":[
        {
            "category":"Building & Trades",
            "subcategory":"Construction",
            "type":"Services"
        }
    ],
    "sg:phone":"+33 4 79 62 74 49",
    "sg:postcode":"73000",
    "sg:province":"Rhone-Alpes",
    "sg:tags":[
        "work",
        "public"
    ],
    "wof:name":"Ste Roui\u00c8re Dauphine Savoie",
    "wof:placetype":"venue"
},
  "geometry": {"coordinates":[5.90839,45.538151],"type":"Point"}
}