{
  "type": "Feature",
  "properties": {
    "iso:country":"FR",
    "sg:address":"2150 Rue Faidherbe 59134 Fournes En Weppes",
    "sg:classifiers":[
        {
            "category":"Wholesale",
            "subcategory":"Farm Supplies",
            "type":"Manufacturing & Wholesale Goods"
        }
    ],
    "sg:phone":"+33 3 20 50 69 69",
    "sg:postcode":"59134",
    "sg:province":"Nord Pas-de-Calais",
    "sg:tags":[
        "-",
        "machine",
        "equipment",
        "engineering",
        "machinery",
        "mechanical",
        "agriculture"
    ],
    "wof:name":"Coussin Motoculture Sarl",
    "wof:placetype":"venue"
},
  "geometry": {"coordinates":[2.89898,50.583759],"type":"Point"}
}