{
  "type": "Feature",
  "properties": {
    "iso:country":"FR",
    "sg:address":"Rue Avogadro - Zone Technologique Sud",
    "sg:city":"Forbach",
    "sg:orig_category":"Bureautique Bureaux-conseils en informatique C\u00e2blage informatique Imprimantes industrielles Informat",
    "sg:phone":"+33 3 87 84 75 00",
    "sg:postcode":"57600",
    "sg:province":"Lorraine",
    "wof:name":"Int\u00e9grasys S.a. - R\u00e9seaux Informatique Et T\u00e9l\u00e9communications",
    "wof:placetype":"venue"
},
  "geometry": {"coordinates":[6.895186,49.185646],"type":"Point"}
}