{
  "type": "Feature",
  "properties": {
    "addr:full":"B.P. 4, 84870 Loriol du Comtat^^Rte de Carpentras, 84870 Loriol du Comtat Picardie",
    "addr:housenumber":"4",
    "addr:postcode":"84870;84870",
    "addr:street":"B.P.;Comtat",
    "iso:country":"FR",
    "sg:address":"B.P. 4, 84870 Loriol du Comtat^^Rte de Carpentras, 84870 Loriol du Comtat",
    "sg:orig_category":"Non-Classified Establishments",
    "sg:phone":"+33 4 90 67 10 25",
    "sg:province":"Picardie",
    "wof:name":"Creps Bouix Espaces Verts S.a.",
    "wof:placetype":"venue"
},
  "geometry": {"coordinates":[5.000185,44.076481],"type":"Point"}
}