{
  "type": "Feature",
  "properties": {
    "addr:full":"40, Bd de Dunkerque, 13002 Marseille Poitou-Charentes",
    "addr:housenumber":"40",
    "addr:postcode":"13002",
    "addr:street":"Bd De Dunkerque",
    "iso:country":"FR",
    "sg:address":"40, Bd de Dunkerque, 13002 Marseille",
    "sg:orig_category":"Non-Classified Establishments",
    "sg:phone":"+33 4 91 13 29 29",
    "sg:province":"Poitou-Charentes",
    "wof:name":"I.s.s. S.a. - Inchcape Shipping Services",
    "wof:placetype":"venue"
},
  "geometry": {"coordinates":[5.368016,43.307137],"type":"Point"}
}