{
  "type": "Feature",
  "properties": {
    "addr:full":"B.P. 24, 27170 Beaumont le Roger^^4, Rue Aristide Briand, 27170 Beaumont le Roger Haute Normandie",
    "addr:postcode":"27170;27170",
    "addr:street":"B.P. 24;Rue Aristide Briand;Roger Haute Normandie",
    "iso:country":"FR",
    "sg:address":"B.P. 24, 27170 Beaumont le Roger^^4, Rue Aristide Briand, 27170 Beaumont le Roger",
    "sg:orig_category":"Non-Classified Establishments",
    "sg:phone":"+33 2 32 45 30 06",
    "sg:province":"Haute Normandie",
    "wof:name":"Maison Fils Et Compagnie S.a.",
    "wof:placetype":"venue"
},
  "geometry": {"coordinates":[0.89014,49.003105],"type":"Point"}
}