{
  "type": "Feature",
  "properties": {
    "iso:country":"FR",
    "sg:address":"B.P. 41, 91311 Ballainvilliers C\u00e9dex^^11, Rue du Perray, 91310 Ballainvilliers",
    "sg:orig_category":"Non-Classified Establishments",
    "sg:phone":"+33 1 69 80 76 16",
    "sg:postcode":"91310",
    "sg:province":"Ile de France",
    "wof:name":"E.r.i.m.o. S.a.r.l.",
    "wof:placetype":"venue"
},
  "geometry": {"coordinates":[-118.595879,34.286919],"type":"Point"}
}