{
  "type": "Feature",
  "properties": {
    "addr:full":"12/32, Rue Louis Bl\u00e9riot - Les Portiques de la Grande Ile, 78530 Buc Ile de France 78530",
    "addr:housenumber":"12 / 32",
    "addr:postcode":"78530;ile;78530",
    "addr:street":"Rue Louis Ble\u0301Riot Les Portiques De La Grande Ile;France",
    "iso:country":"FR",
    "sg:address":"12/32, Rue Louis Bl\u00e9riot - Les Portiques de la Grande Ile, 78530 Buc",
    "sg:orig_category":"Non-Classified Establishments",
    "sg:phone":"+33 1 30 84 89 89",
    "sg:postcode":"78530",
    "sg:province":"Ile de France",
    "wof:name":"Axodyn S.a.r.l.",
    "wof:placetype":"venue"
},
  "geometry": {"coordinates":[2.126343,48.774464],"type":"Point"}
}