{
  "type": "Feature",
  "properties": {
    "iso:country":"FR",
    "sg:address":"7 Rue Des Grands Augustins",
    "sg:city":"Paris",
    "sg:classifiers":[
        {
            "category":"Banks & Credit Unions",
            "subcategory":"Financial Services",
            "type":"Services"
        }
    ],
    "sg:phone":"+33 1 43 26 57 86",
    "sg:postcode":"75006",
    "sg:province":"Ile de France",
    "sg:tags":[
        "banking",
        "finance",
        "insurance"
    ],
    "wof:name":"Bureau De Signification De Paris",
    "wof:placetype":"venue"
},
  "geometry": {"coordinates":[2.340929,48.854565],"type":"Point"}
}