{
  "type": "Feature",
  "properties": {
    "iso:country":"FR",
    "sg:address":"50 Rue Vaillant Couturier 69200 V\u00e9nissieux",
    "sg:classifiers":[
        {
            "category":"Manufacturing",
            "subcategory":"Motor Vehicles & Parts",
            "type":"Manufacturing & Wholesale Goods"
        }
    ],
    "sg:phone":"+33 4 78 76 00 93",
    "sg:province":"Rhone-Alpes",
    "sg:tags":[
        "engine",
        "machine",
        "engineering",
        "-",
        "mechanical"
    ],
    "wof:name":"Corteco Milleur Sa",
    "wof:placetype":"venue"
},
  "geometry": {"coordinates":[4.8597,45.726589],"type":"Point"}
}