{
  "type": "Feature",
  "properties": {
    "addr:full":"17, Place des Reflets, 92400 Courbevoie Ile de France 92400",
    "addr:housenumber":"17",
    "addr:postcode":"92400;92400",
    "addr:street":"Place Des Reflets",
    "iso:country":"FR",
    "sg:address":"17, Place des Reflets, 92400 Courbevoie",
    "sg:orig_category":"Non-Classified Establishments",
    "sg:phone":"+33 1 49 02 51 07",
    "sg:postcode":"92400",
    "sg:province":"Ile de France",
    "wof:name":"E.d.f. - G.d.f. Services Centraux",
    "wof:placetype":"venue"
},
  "geometry": {"coordinates":[2.24583,48.890644],"type":"Point"}
}