{
  "type": "Feature",
  "properties": {
    "addr:full":"53, Rue Chaptal, 22000 Saint Brieuc Saint-Brieuc Bretagne 22000",
    "addr:housenumber":"53",
    "addr:postcode":"22000;22000",
    "addr:street":"Rue Chaptal;Brieuc;Bretagne",
    "iso:country":"FR",
    "sg:address":"53, Rue Chaptal, 22000 Saint Brieuc",
    "sg:city":"Saint-Brieuc",
    "sg:orig_category":"Unclassifiable Establishments",
    "sg:phone":"+33 2 96 33 07 08",
    "sg:postcode":"22000",
    "sg:province":"Bretagne",
    "wof:name":"Cyclelect S.a.r.l.",
    "wof:placetype":"venue"
},
  "geometry": {"coordinates":[-2.733653,48.50872],"type":"Point"}
}