{
  "type": "Feature",
  "properties": {
    "iso:country":"FR",
    "sg:address":"13292 Marseille C\u00e9dex 06^^55, Rue Paradis, 13006 Marseille",
    "sg:orig_category":"Non-Classified Establishments",
    "sg:phone":"+33 4 91 00 33 33",
    "sg:province":"Poitou-Charentes",
    "wof:name":"Cookson Clal S.a.",
    "wof:placetype":"venue"
},
  "geometry": {"coordinates":[5.38324,43.290806],"type":"Point"}
}