{
  "type": "Feature",
  "properties": {
    "addr:full":"3 rue Sem 14800 VAUVILLE Vauville Basse Normandie 14800",
    "addr:housenumber":"3",
    "addr:postcode":"14800;14800",
    "addr:street":"Rue Sem",
    "iso:country":"FR",
    "sg:address":"3 rue Sem 14800 VAUVILLE",
    "sg:city":"Vauville",
    "sg:classifiers":[
        {
            "category":"Shopping",
            "subcategory":"Beauty & Cosmetics",
            "type":"Retail Goods"
        }
    ],
    "sg:phone":"+33 2 31 06 16 25",
    "sg:postcode":"14800",
    "sg:province":"Basse Normandie",
    "sg:tags":[
        "herbal"
    ],
    "wof:name":"Algotherm-cosmopharm S.a.",
    "wof:placetype":"venue"
},
  "geometry": {"coordinates":[0.052675,49.312599],"type":"Point"}
}