{
  "type": "Feature",
  "properties": {
    "iso:country":"FR",
    "sg:address":"ZI Monterrat",
    "sg:city":"Le Chambon Feugerolles",
    "sg:orig_category":"Unclassifiable Establishments",
    "sg:phone":"+33 4 77 40 55 55",
    "sg:postcode":"42500",
    "sg:province":"Rhone-Alpes",
    "wof:name":"Loire Mat\u00e9riaux S.a.",
    "wof:placetype":"venue"
},
  "geometry": {"coordinates":[4.321885,45.396324],"type":"Point"}
}