{
  "type": "Feature",
  "properties": {
    "iso:country":"FR",
    "sg:address":"2000 Route De Lucioles Algorit",
    "sg:city":"Antipolis 06410 Biot",
    "sg:classifiers":[
        {
            "category":"Utilities",
            "subcategory":"Telephone",
            "type":"Services"
        }
    ],
    "sg:phone":"+33 4 92 96 53 00",
    "sg:province":"Midi Pyr\u00e9n\u00e9es",
    "sg:tags":[
        "telecommunication"
    ],
    "wof:name":"Bouygues Telecom",
    "wof:placetype":"venue"
},
  "geometry": {"coordinates":[7.08509,43.626709],"type":"Point"}
}