{
  "type": "Feature",
  "properties": {
    "addr:full":"249, Rue Mandron, 33000 Bordeaux Bordeaux Aquitaine 33000",
    "addr:housenumber":"249",
    "addr:postcode":"33000;33000",
    "addr:street":"Rue Mandron",
    "iso:country":"FR",
    "sg:address":"249, Rue Mandron, 33000 Bordeaux",
    "sg:city":"Bordeaux",
    "sg:orig_category":"Non-Classified Establishments",
    "sg:phone":"+33 5 57 19 17 60",
    "sg:postcode":"33000",
    "sg:province":"Aquitaine",
    "wof:name":"Groupe G\u00e9rer Comptabilit\u00e9 Information Pour La D\u00e9cision Et Le Contr\u00f4le S.a.",
    "wof:placetype":"venue"
},
  "geometry": {"coordinates":[-0.583829,44.855419],"type":"Point"}
}