{
  "type": "Feature",
  "properties": {
    "addr:full":"D 924 60500 Vineuil St Firmin Picardie 60500",
    "addr:housenumber":"924",
    "addr:postcode":"60500;60500",
    "addr:street":"St;Picardie",
    "iso:country":"FR",
    "sg:address":"D 924 60500 Vineuil St Firmin",
    "sg:classifiers":[
        {
            "category":"Manufacturing",
            "subcategory":"Chemicals & Compounds",
            "type":"Manufacturing & Wholesale Goods"
        }
    ],
    "sg:phone":"+33 3 44 57 11 86",
    "sg:postcode":"60500",
    "sg:province":"Picardie",
    "sg:tags":[
        "pharmaceutical",
        "chemistry"
    ],
    "wof:name":"Polytitan",
    "wof:placetype":"venue"
},
  "geometry": {"coordinates":[2.464945,49.192917],"type":"Point"}
}