{
  "type": "Feature",
  "properties": {
    "addr:full":"9, Av. du Braou, 64200 Biarritz Biarritz Aquitaine 64200",
    "addr:postcode":"64200;64200",
    "addr:street":"Av. Du Braou",
    "iso:country":"FR",
    "sg:address":"9, Av. du Braou, 64200 Biarritz",
    "sg:city":"Biarritz",
    "sg:orig_category":"Non-Classified Establishments",
    "sg:phone":"+33 5 59 41 22 22",
    "sg:postcode":"64200",
    "sg:province":"Aquitaine",
    "wof:name":"Proth Jet S.a.",
    "wof:placetype":"venue"
},
  "geometry": {"coordinates":[-1.535309,43.480007],"type":"Point"}
}