{
  "type": "Feature",
  "properties": {
    "iso:country":"FR",
    "sg:address":"5, Rue de Lille - B\u00e2t E4, 94610 Rungis",
    "sg:orig_category":"Unclassifiable Establishments",
    "sg:phone":"+33 1 46 87 13 99",
    "sg:province":"Nord Pas-de-Calais",
    "wof:name":"Hellot S.a.",
    "wof:placetype":"venue"
},
  "geometry": {"coordinates":[3.0628,50.63718],"type":"Point"}
}