{
  "type": "Feature",
  "properties": {
    "iso:country":"FR",
    "sg:address":"Chez Game",
    "sg:city":"Saint Martin d'Estr\u00e9aux",
    "sg:orig_category":"Unclassifiable Establishments",
    "sg:phone":"+33 4 77 64 03 12",
    "sg:postcode":"42620",
    "sg:province":"Rhone-Alpes",
    "wof:name":"Etablissements Valeyre Et Compagnie S.a.r.l.",
    "wof:placetype":"venue"
},
  "geometry": {"coordinates":[3.80078,46.207031],"type":"Point"}
}