{
  "type": "Feature",
  "properties": {
    "addr:full":"50, Rue de R\u00f4me, 13001 Marseille Poitou-Charentes",
    "addr:housenumber":"50",
    "addr:postcode":"13001",
    "addr:street":"Rue De Ro\u0302Me",
    "iso:country":"FR",
    "sg:address":"50, Rue de R\u00f4me, 13001 Marseille",
    "sg:orig_category":"Unclassifiable Establishments",
    "sg:phone":"+33 4 91 33 73 43",
    "sg:province":"Poitou-Charentes",
    "wof:name":"Nareg S.a.r.l.",
    "wof:placetype":"venue"
},
  "geometry": {"coordinates":[5.379416,43.293213],"type":"Point"}
}