{
  "type": "Feature",
  "properties": {
    "iso:country":"FR",
    "sg:address":"3 rue Edgar Quinet 59540 Caudry",
    "sg:classifiers":[
        {
            "category":"Wholesale",
            "subcategory":"Construction Materials",
            "type":"Manufacturing & Wholesale Goods"
        }
    ],
    "sg:phone":"+33 3 27 85 12 02",
    "sg:province":"Nord Pas-de-Calais",
    "sg:tags":[
        "sewing",
        "thread"
    ],
    "wof:name":"C.l.r. Sa",
    "wof:placetype":"venue"
},
  "geometry": {"coordinates":[3.406737,50.125919],"type":"Point"}
}