{
  "type": "Feature",
  "properties": {
    "addr:full":"ZI les Benoits Romenay Bourgogne 71470",
    "addr:postcode":"71470",
    "addr:street":"Zi Les;Bourgogne",
    "iso:country":"FR",
    "sg:address":"ZI les Benoits",
    "sg:city":"Romenay",
    "sg:orig_category":"Unclassifiable Establishments",
    "sg:phone":"+33 3 85 71 30 20",
    "sg:postcode":"71470",
    "sg:province":"Bourgogne",
    "wof:name":"Orama S.a.",
    "wof:placetype":"venue"
},
  "geometry": {"coordinates":[5.06668,46.502464],"type":"Point"}
}