{
  "type": "Feature",
  "properties": {
    "addr:full":"6, Rue de Berri, 75008 Paris Ile de France 75008",
    "addr:housenumber":"6",
    "addr:postcode":"75008;75008",
    "addr:street":"Rue De Berri",
    "iso:country":"FR",
    "sg:address":"6, Rue de Berri, 75008 Paris",
    "sg:orig_category":"Non-Classified Establishments",
    "sg:phone":"+33 1 53 93 46 00",
    "sg:postcode":"75008",
    "sg:province":"Ile de France",
    "wof:name":"Delta Airlines",
    "wof:placetype":"venue"
},
  "geometry": {"coordinates":[2.303547,48.871922],"type":"Point"}
}