{
  "type": "Feature",
  "properties": {
    "addr:full":"Rue de l'Europe - ZI des Petites Landes Thouar\u00e9 sur Loire Pays de Loire 44470",
    "addr:postcode":"44470",
    "addr:street":"Rue De L'Europe Zi Des Petites Landes",
    "iso:country":"FR",
    "sg:address":"Rue de l'Europe - ZI des Petites Landes",
    "sg:city":"Thouar\u00e9 sur Loire",
    "sg:orig_category":"Non-Classified Establishments",
    "sg:phone":"+33 2 40 68 01 81",
    "sg:postcode":"44470",
    "sg:province":"Pays de Loire",
    "wof:name":"Gam S.a.r.l.",
    "wof:placetype":"venue"
},
  "geometry": {"coordinates":[-1.388825,47.300938],"type":"Point"}
}