{
  "type": "Feature",
  "properties": {
    "addr:full":"206 Rte De St Martin D'Ordon 89330 Piffonds Piffonds Bourgogne 89330",
    "addr:housenumber":"206",
    "addr:postcode":"89330;89330",
    "addr:street":"Rte De;D'Ordon",
    "iso:country":"FR",
    "sg:address":"206 Rte De St Martin D'Ordon 89330 Piffonds",
    "sg:city":"Piffonds",
    "sg:classifiers":[
        {
            "category":"Professional",
            "subcategory":"Engineering",
            "type":"Services"
        }
    ],
    "sg:phone":"+33 3 86 86 48 48",
    "sg:postcode":"89330",
    "sg:province":"Bourgogne",
    "sg:tags":[
        "machine",
        "-",
        "mechanical"
    ],
    "wof:name":"Kaufel Sa",
    "wof:placetype":"venue"
},
  "geometry": {"coordinates":[5.09827,46.801403],"type":"Point"}
}