{
  "type": "Feature",
  "properties": {
    "iso:country":"FR",
    "sg:address":"17 R Du Mar\u00e9chal Joffre 67505 Haguenau Cedex",
    "sg:city":"Haguenau",
    "sg:classifiers":[
        {
            "category":"Banks & Credit Unions",
            "subcategory":"Financial Services",
            "type":"Services"
        }
    ],
    "sg:phone":"+33 3 88 63 45 00",
    "sg:postcode":"67500",
    "sg:province":"Alsace",
    "sg:tags":[
        "banking",
        "finance",
        "insurance"
    ],
    "wof:name":"Caisse Primaire D' Assurance Maladie",
    "wof:placetype":"venue"
},
  "geometry": {"coordinates":[7.785038,48.817612],"type":"Point"}
}