{
  "type": "Feature",
  "properties": {
    "iso:country":"FR",
    "sg:address":"167 Rue Des Foulons 59500 Douai",
    "sg:classifiers":[
        {
            "category":"Utilities",
            "type":"Services"
        }
    ],
    "sg:phone":"+33 3 27 99 26 68",
    "sg:postcode":"59500",
    "sg:province":"Nord Pas-de-Calais",
    "sg:tags":[
        "raw",
        "energy",
        "material"
    ],
    "wof:name":"Cokes De Drocourt Sa",
    "wof:placetype":"venue"
},
  "geometry": {"coordinates":[3.077952,50.366955],"type":"Point"}
}