{
  "type": "Feature",
  "properties": {
    "iso:country":"FR",
    "sg:address":"Chemin Basses Valli\u00e8res - ZI Nord",
    "sg:city":"Brignais",
    "sg:orig_category":"Unclassifiable Establishments",
    "sg:phone":"+33 4 78 05 08 20",
    "sg:postcode":"69530",
    "sg:province":"Rhone-Alpes",
    "wof:name":"Moutot S.a.",
    "wof:placetype":"venue"
},
  "geometry": {"coordinates":[4.753949,45.674034],"type":"Point"}
}