{
  "type": "Feature",
  "properties": {
    "addr:full":"Lieu-Dit Les Viviers 16260 Chasseneuil Sur Bonnieure Poitou-Charentes 16260",
    "addr:postcode":"16260;16260",
    "addr:street":"Lieu-Dit Les Viviers;Bonnieure",
    "iso:country":"FR",
    "sg:address":"Lieu-Dit Les Viviers 16260 Chasseneuil Sur Bonnieure",
    "sg:classifiers":[
        {
            "category":"Education",
            "subcategory":"School",
            "type":"Public Place"
        }
    ],
    "sg:phone":"+33 5 45 39 98 00",
    "sg:postcode":"16260",
    "sg:province":"Poitou-Charentes",
    "sg:tags":[
        "breeding",
        "livestock",
        "cattle"
    ],
    "wof:name":"Ste Cooperative Agric Regionale Atlant",
    "wof:placetype":"venue"
},
  "geometry": {"coordinates":[0.432511,45.804134],"type":"Point"}
}