{
  "type": "Feature",
  "properties": {
    "addr:full":"5, Rue Beno\u00eet Frachon - ZAET de Creil Saint Maximin Zone 5, 60740 Saint Maximin Picardie",
    "addr:housenumber":"5",
    "addr:postcode":"60740",
    "addr:street":"Rue Benoi\u0302T Frachon;De Creil Saint Maximin",
    "iso:country":"FR",
    "sg:address":"5, Rue Beno\u00eet Frachon - ZAET de Creil Saint Maximin Zone 5, 60740 Saint Maximin",
    "sg:orig_category":"Non-Classified Establishments",
    "sg:phone":"+33 3 44 64 62 62",
    "sg:province":"Picardie",
    "wof:name":"Sylvexfor S.a.s.",
    "wof:placetype":"venue"
},
  "geometry": {"coordinates":[2.461846,49.205025],"type":"Point"}
}