{
  "type": "Feature",
  "properties": {
    "iso:country":"FR",
    "sg:address":"79, Rue Claude Bernard, 59200 Tourcoing",
    "sg:orig_category":"Non-Classified Establishments",
    "sg:phone":"+33 3 20 24 59 33",
    "sg:province":"Nord Pas-de-Calais",
    "wof:name":"Eurod\u00e9cor S.a.",
    "wof:placetype":"venue"
},
  "geometry": {"coordinates":[3.15297,50.698929],"type":"Point"}
}