{
  "type": "Feature",
  "properties": {
    "addr:full":"All\u00e9e Industrie Corbie Picardie 80800",
    "addr:postcode":"80800",
    "addr:street":"Alle\u0301E Industrie;Picardie",
    "iso:country":"FR",
    "sg:address":"All\u00e9e Industrie",
    "sg:city":"Corbie",
    "sg:orig_category":"Non-Classified Establishments",
    "sg:phone":"+33 3 22 48 32 44",
    "sg:postcode":"80800",
    "sg:province":"Picardie",
    "wof:name":"Sopelec R\u00e9seaux E.u.r.l.",
    "wof:placetype":"venue"
},
  "geometry": {"coordinates":[2.489771,49.915062],"type":"Point"}
}