{
  "type": "Feature",
  "properties": {
    "addr:full":"2 All Des Tilleuls 04200 Sisteron Haute Normandie",
    "addr:housenumber":"2",
    "addr:postcode":"04200",
    "addr:street":"All Des Tilleuls;Haute Normandie",
    "iso:country":"FR",
    "sg:address":"2 All Des Tilleuls 04200 Sisteron",
    "sg:classifiers":[
        {
            "category":"Wholesale",
            "subcategory":"Meat",
            "type":"Manufacturing & Wholesale Goods"
        }
    ],
    "sg:phone":"+33 4 92 61 33 33",
    "sg:province":"Haute Normandie",
    "sg:tags":[
        "food",
        "cooked",
        "product",
        "related"
    ],
    "wof:name":"Sasu Provisud",
    "wof:placetype":"venue"
},
  "geometry": {"coordinates":[5.912887,44.227936],"type":"Point"}
}