{
  "type": "Feature",
  "properties": {
    "addr:full":"Centre Commercial du Moulin; Paris; 94430 Ile de France 94430",
    "addr:postcode":"94430;94430",
    "addr:street":"Ile De France",
    "iso:country":"FR",
    "sg:address":"Centre Commercial du Moulin; Paris; 94430",
    "sg:classifiers":[
        {
            "category":"Banks & Credit Unions",
            "subcategory":"Bank",
            "type":"Services"
        }
    ],
    "sg:phone":"+33 1 45 76 49 02",
    "sg:postcode":"94430",
    "sg:province":"Ile de France",
    "wof:name":"Bred, Banque Populaire",
    "wof:placetype":"venue"
},
  "geometry": {"coordinates":[2.53196,48.796413],"type":"Point"}
}