{
  "type": "Feature",
  "properties": {
    "addr:full":"A\u00e9roport de Dinard Pleurtuit Dinard Bretagne 35800",
    "addr:postcode":"35800",
    "addr:street":"Dinard",
    "iso:country":"FR",
    "sg:address":"A\u00e9roport de Dinard Pleurtuit",
    "sg:city":"Dinard",
    "sg:orig_category":"Unclassifiable Establishments",
    "sg:phone":"+33 2 99 82 72 72",
    "sg:postcode":"35800",
    "sg:province":"Bretagne",
    "wof:name":"Hydrep S.a.",
    "wof:placetype":"venue"
},
  "geometry": {"coordinates":[-2.136755,48.624207],"type":"Point"}
}