{
  "type": "Feature",
  "properties": {
    "addr:full":"8 Place De L Eglise 78360 Montesson Ile de France 78360",
    "addr:housenumber":"8",
    "addr:postcode":"78360;ile;78360",
    "addr:street":"Place De L Eglise;France",
    "iso:country":"FR",
    "sg:address":"8 Place De L Eglise 78360 Montesson",
    "sg:classifiers":[
        {
            "category":"Wholesale",
            "subcategory":"Medical Equipment & Supplies",
            "type":"Manufacturing & Wholesale Goods"
        }
    ],
    "sg:phone":"+33 1 39 52 80 09",
    "sg:postcode":"78360",
    "sg:province":"Ile de France",
    "sg:tags":[
        "instrument",
        "health",
        "-",
        "precision"
    ],
    "wof:name":"Stellaceram",
    "wof:placetype":"venue"
},
  "geometry": {"coordinates":[2.148951,48.907719],"type":"Point"}
}