{
  "type": "Feature",
  "properties": {
    "addr:full":"Rte de Courpi\u00e8re Peschadoires Auvergne 63920",
    "addr:postcode":"63920",
    "addr:street":"Rte De Courpie\u0300Re Peschadoires",
    "iso:country":"FR",
    "sg:address":"Rte de Courpi\u00e8re",
    "sg:city":"Peschadoires",
    "sg:orig_category":"Non-Classified Establishments",
    "sg:phone":"+33 4 73 80 10 93",
    "sg:postcode":"63920",
    "sg:province":"Auvergne",
    "wof:name":"A.m.t. S.a. - Atelier M\u00e9canique De Thiers",
    "wof:placetype":"venue"
},
  "geometry": {"coordinates":[3.501278,45.828983],"type":"Point"}
}