{
  "type": "Feature",
  "properties": {
    "addr:full":"All\u00e9e Roger Guillemet Fontenay le Comte Pays de Loire 85200",
    "addr:postcode":"85200",
    "addr:street":"Alle\u0301E Roger Guillemet;Comte",
    "iso:country":"FR",
    "sg:address":"All\u00e9e Roger Guillemet",
    "sg:city":"Fontenay le Comte",
    "sg:orig_category":"Unclassifiable Establishments",
    "sg:phone":"+33 2 51 69 27 83",
    "sg:postcode":"85200",
    "sg:province":"Pays de Loire",
    "wof:name":"B.s.v. S.a.r.l. - B\u00e9ton Du Sud Vend\u00e9e",
    "wof:placetype":"venue"
},
  "geometry": {"coordinates":[-0.782892,46.459232],"type":"Point"}
}