{
  "type": "Feature",
  "properties": {
    "iso:country":"FR",
    "sg:address":"14 Pl De France 95200 Sarcelles",
    "sg:classifiers":[
        {
            "category":"Shopping",
            "type":"Retail Goods"
        }
    ],
    "sg:phone":"+33 1 39 90 88 87",
    "sg:postcode":"95200",
    "sg:province":"Ile de France",
    "sg:tags":[
        "metallurgy",
        "finished",
        "-",
        "metalworking",
        "metallic"
    ],
    "wof:name":"Metafac",
    "wof:placetype":"venue"
},
  "geometry": {"coordinates":[2.37742,48.977871],"type":"Point"}
}