{
  "type": "Feature",
  "properties": {
    "iso:country":"FR",
    "sg:address":"6 Grand Rue 35400 St Malo",
    "sg:city":"Saint-Malo",
    "sg:classifiers":[
        {
            "category":"Travel",
            "subcategory":"Hotels & Motels",
            "type":"Entertainment"
        }
    ],
    "sg:phone":"+33 2 99 40 87 70",
    "sg:postcode":"35400",
    "sg:province":"Bretagne",
    "sg:tags":[
        "hotels",
        "business",
        "restaurant"
    ],
    "wof:name":"Hotel Central Sarl",
    "wof:placetype":"venue"
},
  "geometry": {"coordinates":[-2.024459,48.648968],"type":"Point"}
}