{
  "type": "Feature",
  "properties": {
    "addr:full":"5, Rue Ludovic Trarieux, 24000 Perigueux P\u00e9rigueux Aquitaine 24000",
    "addr:housenumber":"5",
    "addr:postcode":"24000;24000",
    "addr:street":"Rue Ludovic Trarieux",
    "iso:country":"FR",
    "sg:address":"5, Rue Ludovic Trarieux, 24000 Perigueux",
    "sg:city":"P\u00e9rigueux",
    "sg:orig_category":"Unclassifiable Establishments",
    "sg:phone":"+33 5 53 09 05 80",
    "sg:postcode":"24000",
    "sg:province":"Aquitaine",
    "wof:name":"S.y.r.i.c. S.a.r.l.",
    "wof:placetype":"venue"
},
  "geometry": {"coordinates":[0.712809,45.1912],"type":"Point"}
}