{
  "type": "Feature",
  "properties": {
    "addr:full":"B.P. 38 Equeurdreville Hainneville Basse Normandie 50120",
    "addr:postcode":"50120",
    "addr:street":"B.P. 38 Equeurdreville Hainneville Basse",
    "iso:country":"FR",
    "sg:address":"B.P. 38",
    "sg:city":"Equeurdreville Hainneville",
    "sg:orig_category":"Non-Classified Establishments",
    "sg:phone":"+33 2 33 02 30 00",
    "sg:postcode":"50120",
    "sg:province":"Basse Normandie",
    "wof:name":"S.g.n. S.a. - Soci\u00e9t\u00e9 G\u00e9n\u00e9rale Pour Les Techniques Nouvelles",
    "wof:placetype":"venue"
},
  "geometry": {"coordinates":[-1.674594,49.656322],"type":"Point"}
}