{
  "type": "Feature",
  "properties": {
    "addr:full":"5, Rue d'Aspach, 68520 Schweighouse pr\u00e8s Thann Burnhaupt-le-Bas Alsace 68520",
    "addr:housenumber":"5",
    "addr:postcode":"68520;68520",
    "addr:street":"Rue D'Aspach",
    "iso:country":"FR",
    "sg:address":"5, Rue d'Aspach, 68520 Schweighouse pr\u00e8s Thann",
    "sg:city":"Burnhaupt-le-Bas",
    "sg:orig_category":"Unclassifiable Establishments",
    "sg:phone":"+33 3 89 48 70 24",
    "sg:postcode":"68520",
    "sg:province":"Alsace",
    "wof:name":"Kuttler S.a.r.l.",
    "wof:placetype":"venue"
},
  "geometry": {"coordinates":[7.11798,47.800564],"type":"Point"}
}