{
  "type": "Feature",
  "properties": {
    "addr:full":"Bd Salvador Allend\u00e9 Soissons Picardie 02200",
    "addr:postcode":"02200",
    "addr:street":"Bd Salvador Allende\u0301;Picardie",
    "iso:country":"FR",
    "sg:address":"Bd Salvador Allend\u00e9",
    "sg:city":"Soissons",
    "sg:orig_category":"Unclassifiable Establishments",
    "sg:phone":"+33 3 23 73 84 20",
    "sg:postcode":"02200",
    "sg:province":"Picardie",
    "wof:name":"Cabinet Gevraux S.a.",
    "wof:placetype":"venue"
},
  "geometry": {"coordinates":[3.32355,49.364361],"type":"Point"}
}