{
  "type": "Feature",
  "properties": {
    "iso:country":"FR",
    "sg:address":"Chemin des Soupirs",
    "sg:city":"Belley",
    "sg:orig_category":"Non-Classified Establishments",
    "sg:phone":"+33 4 79 42 21 53",
    "sg:postcode":"01300",
    "sg:province":"Rhone-Alpes",
    "wof:name":"Entreprise Abdelkader Ghilas",
    "wof:placetype":"venue"
},
  "geometry": {"coordinates":[5.690992,45.764267],"type":"Point"}
}