{
  "type": "Feature",
  "properties": {
    "addr:full":"B.P. 6, 63171 Aubi\u00e8re C\u00e9dex^^Rue des Varennes, 63170 Aubi\u00e8re Aubi\u00e8re Auvergne 63170",
    "addr:housenumber":"6",
    "addr:postcode":"63171;63170;63170",
    "addr:street":"B.P.;Varennes",
    "iso:country":"FR",
    "sg:address":"B.P. 6, 63171 Aubi\u00e8re C\u00e9dex^^Rue des Varennes, 63170 Aubi\u00e8re",
    "sg:city":"Aubi\u00e8re",
    "sg:orig_category":"Non-Classified Establishments",
    "sg:phone":"+33 4 73 26 33 58",
    "sg:postcode":"63170",
    "sg:province":"Auvergne",
    "wof:name":"Clermont Mat\u00e9riel S.a.",
    "wof:placetype":"venue"
},
  "geometry": {"coordinates":[3.110975,45.7509],"type":"Point"}
}