{
  "type": "Feature",
  "properties": {
    "iso:country":"FR",
    "sg:address":"B.P. 7",
    "sg:city":"Mon\u00e9teau",
    "sg:orig_category":"Non-Classified Establishments",
    "sg:phone":"+33 3 86 53 49 00",
    "sg:postcode":"89470",
    "sg:province":"Bourgogne",
    "wof:name":"Hermes M\u00e9tal S.a.",
    "wof:placetype":"venue"
},
  "geometry": {"coordinates":[3.578575,47.85006],"type":"Point"}
}