{
  "type": "Feature",
  "properties": {
    "iso:country":"FR",
    "sg:address":"Route D Avranches 50370 BRECEY",
    "sg:city":"Br\u00e9cey",
    "sg:classifiers":[
        {
            "category":"Food & Beverages",
            "subcategory":"Meat & Fish",
            "type":"Retail Goods"
        }
    ],
    "sg:phone":"+33 2 33 48 12 77",
    "sg:postcode":"50370",
    "sg:province":"Basse Normandie",
    "sg:tags":[
        "sausage"
    ],
    "wof:name":"La Chaiseronne S.a.r.l.",
    "wof:placetype":"venue"
},
  "geometry": {"coordinates":[-1.148274,48.670448],"type":"Point"}
}