{
  "type": "Feature",
  "properties": {
    "addr:full":"9, Rue Pages, 92150 Suresnes Ile de France",
    "addr:housenumber":"9",
    "addr:postcode":"92150;ile",
    "addr:street":"Rue Pages",
    "iso:country":"FR",
    "sg:address":"9, Rue Pages, 92150 Suresnes",
    "sg:orig_category":"Non-Classified Establishments",
    "sg:phone":"+33 1 41 38 98 62",
    "sg:province":"Ile de France",
    "wof:name":"Kaba S.a.r.l.",
    "wof:placetype":"venue"
},
  "geometry": {"coordinates":[2.230151,48.8717],"type":"Point"}
}