{
  "type": "Feature",
  "properties": {
    "addr:full":"4 J Ferry BP 09 28190 Courville sur Eure Centre 28190",
    "addr:housenumber":"4;09",
    "addr:postcode":"28190;28190",
    "addr:street":"J Ferry Bp",
    "iso:country":"FR",
    "sg:address":"4",
    "sg:city":"J Ferry BP 09 28190 Courville sur Eure",
    "sg:classifiers":[
        {
            "category":"Professional",
            "subcategory":"Engineering",
            "type":"Services"
        }
    ],
    "sg:phone":"+33 2 37 23 21 15",
    "sg:postcode":"28190",
    "sg:province":"Centre",
    "sg:tags":[
        "machine",
        "-",
        "mechanical"
    ],
    "wof:name":"Nova Socimec",
    "wof:placetype":"venue"
},
  "geometry": {"coordinates":[1.241868,48.450146],"type":"Point"}
}