{
  "type": "Feature",
  "properties": {
    "iso:country":"FR",
    "sg:address":"11, Rue Jules Verne, 69500 Bron",
    "sg:orig_category":"Unclassifiable Establishments",
    "sg:phone":"+33 4 78 26 07 48",
    "sg:province":"Rhone-Alpes",
    "wof:name":"Novagraph",
    "wof:placetype":"venue"
},
  "geometry": {"coordinates":[4.910662,45.730099],"type":"Point"}
}