{
  "type": "Feature",
  "properties": {
    "iso:country":"FR",
    "sg:address":"29/31, Av. de Stalingrad, 92700 Colombes",
    "sg:orig_category":"Unclassifiable Establishments",
    "sg:phone":"+33 1 47 84 94 57",
    "sg:province":"Ile de France",
    "wof:name":"Alcaud S.a.",
    "wof:placetype":"venue"
},
  "geometry": {"coordinates":[2.270924,48.927895],"type":"Point"}
}