{
  "type": "Feature",
  "properties": {
    "iso:country":"FR",
    "sg:address":"B.P. 24, 77313 Marne la Vall\u00e9e C\u00e9dex 2^^Bd Olof Palme, 77184 Emerainville",
    "sg:orig_category":"Non-Classified Establishments",
    "sg:phone":"+33 1 60 37 41 36",
    "sg:postcode":"77184",
    "sg:province":"Ile de France",
    "wof:name":"C.f.a. Industrie",
    "wof:placetype":"venue"
},
  "geometry": {"coordinates":[2.622175,48.811619],"type":"Point"}
}