{
  "type": "Feature",
  "properties": {
    "addr:full":"21 Rue D Artois 75008 Paris Ile de France 75008",
    "addr:housenumber":"21",
    "addr:postcode":"75008;75008",
    "addr:street":"Rue D Artois",
    "iso:country":"FR",
    "sg:address":"21 Rue D Artois 75008 Paris",
    "sg:classifiers":[
        {
            "category":"Manufacturing",
            "subcategory":"Chemicals & Compounds",
            "type":"Manufacturing & Wholesale Goods"
        }
    ],
    "sg:phone":"+33 1 53 83 72 40",
    "sg:postcode":"75008",
    "sg:province":"Ile de France",
    "sg:tags":[
        "pharmaceutical",
        "chemistry",
        "-",
        "by-product"
    ],
    "wof:name":"Gaz Liquefies Industrie (gli)",
    "wof:placetype":"venue"
},
  "geometry": {"coordinates":[2.307073,48.873184],"type":"Point"}
}