{
  "type": "Feature",
  "properties": {
    "iso:country":"FR",
    "sg:address":"9, Rue Lavoisier, 80130 Friville Escarbotin",
    "sg:orig_category":"Unclassifiable Establishments",
    "sg:phone":"+33 3 22 60 22 11",
    "sg:province":"Picardie",
    "wof:name":"Vimeu D\u00e9cor S.a.r.l.",
    "wof:placetype":"venue"
},
  "geometry": {"coordinates":[1.542695,50.077801],"type":"Point"}
}