{
  "type": "Feature",
  "properties": {
    "addr:full":"109, Rue du Canteleu, 59500 Douai Nord Pas-de-Calais",
    "addr:postcode":"59500",
    "addr:street":"Rue Du Canteleu",
    "iso:country":"FR",
    "sg:address":"109, Rue du Canteleu, 59500 Douai",
    "sg:orig_category":"Unclassifiable Establishments",
    "sg:phone":"+33 3 27 71 33 90",
    "sg:province":"Nord Pas-de-Calais",
    "wof:name":"Prodys S.a.r.l.",
    "wof:placetype":"venue"
},
  "geometry": {"coordinates":[3.084046,50.369061],"type":"Point"}
}