{
  "type": "Feature",
  "properties": {
    "addr:full":"27, Rue Delemazure, 59260 Hellemmes Lille Nord Pas-de-Calais",
    "addr:housenumber":"27",
    "addr:postcode":"59260",
    "addr:street":"Rue Delemazure;Hellemmes Lille Nord",
    "iso:country":"FR",
    "sg:address":"27, Rue Delemazure, 59260 Hellemmes Lille",
    "sg:orig_category":"Unclassifiable Establishments",
    "sg:phone":"+33 3 20 61 78 84",
    "sg:province":"Nord Pas-de-Calais",
    "wof:name":"A.n.p.e.",
    "wof:placetype":"venue"
},
  "geometry": {"coordinates":[3.10851,50.628689],"type":"Point"}
}