{
  "type": "Feature",
  "properties": {
    "iso:country":"FR",
    "sg:address":"13 ave de la R\u00e9publique; Niort; 79000",
    "sg:classifiers":[
        {
            "category":"Banks & Credit Unions",
            "subcategory":"Bank",
            "type":"Services"
        }
    ],
    "sg:phone":"+33 3349240349",
    "sg:postcode":"79000",
    "sg:province":"Poitou-Charentes",
    "wof:name":"Cr\u00e9dit Foncier De France",
    "wof:placetype":"venue"
},
  "geometry": {"coordinates":[-0.460165,46.322845],"type":"Point"}
}