{
  "type": "Feature",
  "properties": {
    "addr:full":"51 Av De La R\u00e9publique 69200 V\u00e9nissieux Rhone-Alpes",
    "addr:postcode":"69200",
    "addr:street":"51 Av De La Re\u0301Publique",
    "iso:country":"FR",
    "sg:address":"51 Av De La R\u00e9publique 69200 V\u00e9nissieux",
    "sg:classifiers":[
        {
            "category":"Manufacturing",
            "subcategory":"Jewelry",
            "type":"Manufacturing & Wholesale Goods"
        }
    ],
    "sg:phone":"+33 4 72 21 54 00",
    "sg:province":"Rhone-Alpes",
    "sg:tags":[
        "product",
        "jewellery",
        "equipement",
        "miscellaneous",
        "timekeeping",
        "equipment",
        "precision"
    ],
    "wof:name":"Bijouterie Jean Delatour",
    "wof:placetype":"venue"
},
  "geometry": {"coordinates":[4.877919,45.705475],"type":"Point"}
}