{
  "type": "Feature",
  "properties": {
    "iso:country":"FR",
    "sg:address":"Av Joliot Curie 17180 Perigny",
    "sg:classifiers":[
        {
            "category":"Building & Trades",
            "subcategory":"Construction",
            "type":"Services"
        }
    ],
    "sg:phone":"+33 5 46 44 17 50",
    "sg:postcode":"17180",
    "sg:province":"Poitou-Charentes",
    "sg:tags":[
        "work",
        "public"
    ],
    "wof:name":"Entreprise M Robin",
    "wof:placetype":"venue"
},
  "geometry": {"coordinates":[-1.107134,46.157475],"type":"Point"}
}