{
  "type": "Feature",
  "properties": {
    "addr:full":"3 all\u00e9e Pierre de Coubertin 31700 Blagnac Midi Pyr\u00e9n\u00e9es 31700",
    "addr:housenumber":"3",
    "addr:postcode":"31700;31700",
    "addr:street":"Alle\u0301E Pierre De Coubertin",
    "iso:country":"FR",
    "sg:address":"3 all\u00e9e Pierre de Coubertin 31700 Blagnac",
    "sg:orig_category":"Hydraulic Aircraft Control",
    "sg:phone":"+33 5 34 60 70 00",
    "sg:postcode":"31700",
    "sg:province":"Midi Pyr\u00e9n\u00e9es",
    "wof:name":"Bae Systems Regional Aircraft S.a.",
    "wof:placetype":"venue"
},
  "geometry": {"coordinates":[1.371558,43.651863],"type":"Point"}
}