{
  "type": "Feature",
  "properties": {
    "addr:full":"B.P. 6, 10430 Rosi\u00e8res pr\u00e9s Troyes C\u00e9dex^^52, Rue Pasteur, 10430 Rosi\u00e8res pr\u00e8s Troyes Champagne 10430",
    "addr:housenumber":"6",
    "addr:postcode":"10430;pre\u0301s troyes;10430;10430",
    "addr:street":"B.P.;Rue Pasteur",
    "iso:country":"FR",
    "sg:address":"B.P. 6, 10430 Rosi\u00e8res pr\u00e9s Troyes C\u00e9dex^^52, Rue Pasteur, 10430 Rosi\u00e8res pr\u00e8s Troyes",
    "sg:orig_category":"Non-Classified Establishments",
    "sg:phone":"+33 3 25 82 91 33",
    "sg:postcode":"10430",
    "sg:province":"Champagne",
    "wof:name":"Dubix - Electrolux S.n.c. - Syst\u00e8mes De Blanchisserie",
    "wof:placetype":"venue"
},
  "geometry": {"coordinates":[4.064516,48.257263],"type":"Point"}
}