{
  "type": "Feature",
  "properties": {
    "iso:country":"FR",
    "sg:address":"3, Rue Gracchus Baboeuf, 93135 Noisy le Sec C\u00e9dex",
    "sg:city":"Baboeuf",
    "sg:orig_category":"Non-Classified Establishments",
    "sg:phone":"+33 1 48 44 55 67",
    "sg:postcode":"60400",
    "sg:province":"Picardie",
    "wof:name":"Erimo S.a.r.l.",
    "wof:placetype":"venue"
},
  "geometry": {"coordinates":[2.448338,48.895218],"type":"Point"}
}