{
  "type": "Feature",
  "properties": {
    "addr:full":"30, Rue Romaine, 24000 P\u00e9rigueux P\u00e9rigueux Aquitaine 24000",
    "addr:housenumber":"30",
    "addr:postcode":"24000;24000",
    "addr:street":"Rue Romaine",
    "iso:country":"FR",
    "sg:address":"30, Rue Romaine, 24000 P\u00e9rigueux",
    "sg:city":"P\u00e9rigueux",
    "sg:orig_category":"Non-Classified Establishments",
    "sg:phone":"+33 5 53 09 07 54",
    "sg:postcode":"24000",
    "sg:province":"Aquitaine",
    "wof:name":"Ikon Office Solutions S.a.",
    "wof:placetype":"venue"
},
  "geometry": {"coordinates":[0.714494,45.181259],"type":"Point"}
}