{
  "type": "Feature",
  "properties": {
    "iso:country":"FR",
    "sg:address":"19 Av Montaigne 75008 Paris",
    "sg:classifiers":[
        {
            "category":"Autos & Motor Vehicles",
            "subcategory":"Automobile Sales",
            "type":"Retail Goods"
        }
    ],
    "sg:phone":"+33 1 44 21 92 00",
    "sg:postcode":"75008",
    "sg:province":"Ile de France",
    "sg:tags":[
        "equipment",
        "motor-cars",
        "transport"
    ],
    "wof:name":"Fiat France Sa",
    "wof:placetype":"venue"
},
  "geometry": {"coordinates":[2.303442,48.865845],"type":"Point"}
}