{
  "type": "Feature",
  "properties": {
    "iso:country":"FR",
    "sg:address":"2, Rue Joseph Jacquard, 21800 Sennecey l\u00e8s Dijon",
    "sg:city":"Neuilly-l\u00e8s-Dijon",
    "sg:orig_category":"Unclassifiable Establishments",
    "sg:phone":"+33 3 80 47 31 31",
    "sg:postcode":"21800",
    "sg:province":"Bourgogne",
    "wof:name":"M.b.p. S.a. - Manufacture Bourguignonne De Plastique",
    "wof:placetype":"venue"
},
  "geometry": {"coordinates":[5.10386,47.29847],"type":"Point"}
}