{
  "type": "Feature",
  "properties": {
    "addr:full":"ZA de Troyalac'h Quimper Bretagne 29000",
    "addr:postcode":"29000",
    "addr:street":"Za De Troyalac'H;Bretagne",
    "iso:country":"FR",
    "sg:address":"ZA de Troyalac'h",
    "sg:city":"Quimper",
    "sg:orig_category":"Unclassifiable Establishments",
    "sg:phone":"+33 2 98 94 67 00",
    "sg:postcode":"29000",
    "sg:province":"Bretagne",
    "wof:name":"Tuffigo S.a.r.l.",
    "wof:placetype":"venue"
},
  "geometry": {"coordinates":[-4.0977,47.998119],"type":"Point"}
}