{
  "type": "Feature",
  "properties": {
    "addr:full":"B.P. 3, 42240 Unieux C\u00e9dex^^48, Rue Holtzer, 42240 Unieux Rhone-Alpes 42240",
    "addr:housenumber":"3",
    "addr:postcode":"42240;42240;42240",
    "addr:street":"B.P.;Rue Holtzer;Rhone-Alpes",
    "iso:country":"FR",
    "sg:address":"B.P. 3, 42240 Unieux C\u00e9dex^^48, Rue Holtzer, 42240 Unieux",
    "sg:orig_category":"Non-Classified Establishments",
    "sg:phone":"+33 4 77 40 57 00",
    "sg:postcode":"42240",
    "sg:province":"Rhone-Alpes",
    "wof:name":"Fonderie De La P\u00e9rivaure S.a.",
    "wof:placetype":"venue"
},
  "geometry": {"coordinates":[4.261915,45.399975],"type":"Point"}
}