{
  "type": "Feature",
  "properties": {
    "iso:country":"FR",
    "sg:address":"Rte D'Alen\u00e7on Za De Pr\u00e9vert 53140 Pr\u00e9 En Pail",
    "sg:classifiers":[
        {
            "category":"Manufacturing",
            "subcategory":"Wood Products",
            "type":"Manufacturing & Wholesale Goods"
        }
    ],
    "sg:phone":"+33 2 43 03 03 94",
    "sg:province":"Pays de Loire",
    "sg:tags":[
        "professional",
        "furniture"
    ],
    "wof:name":"Ste De Menuiserie Agencement Mobilier Sarl",
    "wof:placetype":"venue"
},
  "geometry": {"coordinates":[-0.19834,48.459789],"type":"Point"}
}