{
  "type": "Feature",
  "properties": {
    "addr:full":"144 rue Garibaldi 69006 Lyon Rhone-Alpes",
    "addr:housenumber":"144",
    "addr:postcode":"69006",
    "addr:street":"Rue Garibaldi",
    "iso:country":"FR",
    "sg:address":"144 rue Garibaldi 69006 Lyon",
    "sg:classifiers":[
        {
            "category":"Professional",
            "subcategory":"Advertising",
            "type":"Services"
        }
    ],
    "sg:phone":"+33 4 72 83 07 77",
    "sg:province":"Rhone-Alpes",
    "sg:tags":[
        "agency"
    ],
    "wof:name":"Additif Mc Cann Sa",
    "wof:placetype":"venue"
},
  "geometry": {"coordinates":[4.850684,45.765797],"type":"Point"}
}