{
  "type": "Feature",
  "properties": {
    "iso:country":"FR",
    "sg:address":"B.P. 215, 07205 Aubenas C\u00e9dex^^Quartier de la Temple, 07200 Aubenas",
    "sg:orig_category":"Non-Classified Establishments",
    "sg:phone":"+33 4 75 35 23 80",
    "sg:postcode":"07200",
    "sg:province":"Rhone-Alpes",
    "wof:name":"A\u00e9rodrome D'aubenas-vals",
    "wof:placetype":"venue"
},
  "geometry": {"coordinates":[4.39417,44.613239],"type":"Point"}
}