{
  "type": "Feature",
  "properties": {
    "iso:country":"FR",
    "sg:address":"Quartier Saint Cassien - ZI du B\u00e9al",
    "sg:city":"Cannes la Bocca",
    "sg:orig_category":"Unclassifiable Establishments",
    "sg:phone":"+33 4 93 47 23 84",
    "sg:postcode":"06150",
    "sg:province":"Provence-Alpes-C\u00f4te d'Azur",
    "wof:name":"Ghini",
    "wof:placetype":"venue"
},
  "geometry": {"coordinates":[6.96872,43.55698],"type":"Point"}
}