{
  "type": "Feature",
  "properties": {
    "iso:country":"FR",
    "sg:address":"B.P. 2717, 51055 Reims C\u00e9dex^^63, Rue Gosset, 51100 Reims",
    "sg:orig_category":"Non-Classified Establishments",
    "sg:phone":"+33 3 26 77 30 30",
    "sg:province":"Champagne",
    "wof:name":"Forbo-sarlino S.a.",
    "wof:placetype":"venue"
},
  "geometry": {"coordinates":[4.028445,49.26284],"type":"Point"}
}