{
  "type": "Feature",
  "properties": {
    "addr:full":"Rue des Fr\u00e8res Garnier - ZI de la Dame Huguenotte Chaumont Champagne 52000",
    "addr:postcode":"52000",
    "addr:street":"Rue Des Fre\u0300Res Garnier Zi De La Dame Huguenotte;Champagne",
    "iso:country":"FR",
    "sg:address":"Rue des Fr\u00e8res Garnier - ZI de la Dame Huguenotte",
    "sg:city":"Chaumont",
    "sg:orig_category":"Unclassifiable Establishments",
    "sg:phone":"+33 3 25 30 31 80",
    "sg:postcode":"52000",
    "sg:province":"Champagne",
    "wof:name":"Pr\u00e9vot Sm\u00e9ta S.a.",
    "wof:placetype":"venue"
},
  "geometry": {"coordinates":[5.135536,48.110767],"type":"Point"}
}