{
  "type": "Feature",
  "properties": {
    "iso:country":"FR",
    "sg:address":"24, Rue Berjon, 69009 Lyon",
    "sg:orig_category":"Unclassifiable Establishments",
    "sg:phone":"+33 4 78 83 58 17",
    "sg:province":"Rhone-Alpes",
    "wof:name":"C.i.s.c. S.a.r.l.",
    "wof:placetype":"venue"
},
  "geometry": {"coordinates":[4.798909,45.777287],"type":"Point"}
}