{
  "type": "Feature",
  "properties": {
    "iso:country":"FR",
    "sg:address":"5 rue Franklin 93310 Le Pre St Gervais",
    "sg:classifiers":[
        {
            "category":"Sports & Exercise",
            "subcategory":"Tennis Court",
            "type":"Entertainment"
        }
    ],
    "sg:phone":"+33 1 48 45 04 29",
    "sg:province":"Ile de France",
    "sg:tags":[
        "accessory"
    ],
    "wof:name":"Ste Etablissement Veuillote Willemain Sa",
    "wof:placetype":"venue"
},
  "geometry": {"coordinates":[2.403055,48.888302],"type":"Point"}
}