{
  "type": "Feature",
  "properties": {
    "iso:country":"FR",
    "sg:address":"B.P. 25, 78170 La Celle Saint Cloud^^6, Mail de l'Europe, 78170 La Celle Saint Cloud",
    "sg:orig_category":"Non-Classified Establishments",
    "sg:phone":"+33 1 30 82 50 00",
    "sg:postcode":"78170",
    "sg:province":"Ile de France",
    "wof:name":"E.m.c. Computer Systems France S.a.",
    "wof:placetype":"venue"
},
  "geometry": {"coordinates":[2.133577,48.849007],"type":"Point"}
}