{
  "type": "Feature",
  "properties": {
    "iso:country":"FR",
    "sg:address":"Place Bauzu 71200 Le Creusot",
    "sg:city":"Le Creusot",
    "sg:classifiers":[
        {
            "category":"Autos & Motor Vehicles",
            "subcategory":"Automobile Sales",
            "type":"Retail Goods"
        }
    ],
    "sg:phone":"+33 3 85 77 00 22",
    "sg:postcode":"71200",
    "sg:province":"Bourgogne",
    "sg:tags":[
        "equipment",
        "motor-cars",
        "transport"
    ],
    "wof:name":"Anc Automobiles",
    "wof:placetype":"venue"
},
  "geometry": {"coordinates":[4.416444,46.805855],"type":"Point"}
}