{
  "type": "Feature",
  "properties": {
    "addr:full":"8 Impasse Des Platanes 42500 Le Chambon Feugerolles Rhone-Alpes 42500",
    "addr:housenumber":"8",
    "addr:postcode":"42500;42500",
    "addr:street":"Impasse Des Platanes;Chambon Feugerolles Rhone-Alpes",
    "iso:country":"FR",
    "sg:address":"8 Impasse Des Platanes 42500 Le Chambon Feugerolles",
    "sg:classifiers":[
        {
            "category":"Shopping",
            "subcategory":"Clothing, Apparel, & Fashions",
            "type":"Retail Goods"
        }
    ],
    "sg:phone":"+33 4 77 56 50 31",
    "sg:postcode":"42500",
    "sg:province":"Rhone-Alpes",
    "sg:tags":[
        "textile",
        "clothing",
        "clothes"
    ],
    "wof:name":"Entreprise Chapelon",
    "wof:placetype":"venue"
},
  "geometry": {"coordinates":[4.316302,45.395027],"type":"Point"}
}