{
  "type": "Feature",
  "properties": {
    "iso:country":"FR",
    "sg:address":"43, Rue Jean-Jacques Rousseau, 01100 Oyonnax",
    "sg:orig_category":"Non-Classified Establishments",
    "sg:phone":"+33 4 74 77 09 25",
    "sg:province":"Rhone-Alpes",
    "wof:name":"O.m.m. S.a.r.l. - Outillage M\u00e9canique Mermet",
    "wof:placetype":"venue"
},
  "geometry": {"coordinates":[5.658379,46.25309],"type":"Point"}
}