{
  "type": "Feature",
  "properties": {
    "addr:full":"76 Rue Saint-Lazare Paris Ile de France 75009",
    "addr:housenumber":"76",
    "addr:postcode":"75009",
    "addr:street":"Rue Saint-Lazare",
    "iso:country":"FR",
    "sg:address":"76 Rue Saint-Lazare",
    "sg:city":"Paris",
    "sg:classifiers":[
        {
            "category":"Banks & Credit Unions",
            "subcategory":"Financial Services",
            "type":"Services"
        }
    ],
    "sg:phone":"+33 1 55 32 27 00",
    "sg:postcode":"75009",
    "sg:province":"Ile de France",
    "sg:tags":[
        "banking",
        "finance",
        "insurance"
    ],
    "wof:name":"Generali France Sa",
    "wof:placetype":"venue"
},
  "geometry": {"coordinates":[2.330097,48.876106],"type":"Point"}
}