{
  "type": "Feature",
  "properties": {
    "iso:country":"FR",
    "sg:address":"3, Rue Alexandre Fleming, 49066 Angers C\u00e9dex",
    "sg:orig_category":"Non-Classified Establishments",
    "sg:phone":"+33 2 41 73 18 18",
    "sg:province":"Rhone-Alpes",
    "wof:name":"Cr\u00e9ative Eur\u00e9com S.a.",
    "wof:placetype":"venue"
},
  "geometry": {"coordinates":[-0.605478,47.477455],"type":"Point"}
}