{
  "type": "Feature",
  "properties": {
    "iso:country":"FR",
    "sg:address":"1, Rue des Quatre Chapeaux, 69002 Lyon",
    "sg:orig_category":"Non-Classified Establishments",
    "sg:phone":"+33 4 72 41 98 23",
    "sg:postcode":"69002",
    "sg:province":"Rhone-Alpes",
    "wof:name":"Ipsos R\u00e9gions",
    "wof:placetype":"venue"
},
  "geometry": {"coordinates":[4.83464,45.762794],"type":"Point"}
}