{
  "type": "Feature",
  "properties": {
    "addr:full":"37 Rue Condorcet 59490 Somain Nord Pas-de-Calais 59490",
    "addr:housenumber":"37",
    "addr:postcode":"59490;59490",
    "addr:street":"Rue Condorcet",
    "iso:country":"FR",
    "sg:address":"37 Rue Condorcet 59490 Somain",
    "sg:classifiers":[
        {
            "category":"Professional",
            "subcategory":"Business Services",
            "type":"Services"
        }
    ],
    "sg:phone":"+33 3 27 86 51 57",
    "sg:postcode":"59490",
    "sg:province":"Nord Pas-de-Calais",
    "sg:tags":[
        "training",
        "advice"
    ],
    "wof:name":"Ecole Sainte Anne",
    "wof:placetype":"venue"
},
  "geometry": {"coordinates":[3.282683,50.359489],"type":"Point"}
}