{
  "type": "Feature",
  "properties": {
    "iso:country":"FR",
    "sg:address":"Chaudenay 18300 Verdigny",
    "sg:city":"Verdigny",
    "sg:orig_category":"Unclassifiable Establishments",
    "sg:phone":"+33 2 48 79 33 96",
    "sg:postcode":"18300",
    "sg:province":"Centre",
    "wof:name":"Daulny Etienne",
    "wof:placetype":"venue"
},
  "geometry": {"coordinates":[2.79394,47.353024],"type":"Point"}
}