{
  "type": "Feature",
  "properties": {
    "addr:full":"35, Av. Saint Just, 83130 La Garde Provence-Alpes-C\u00f4te d'Azur",
    "addr:postcode":"83130",
    "addr:street":"35 Av. Saint Just;Garde",
    "iso:country":"FR",
    "sg:address":"35, Av. Saint Just, 83130 La Garde",
    "sg:orig_category":"Unclassifiable Establishments",
    "sg:phone":"+33 4 94 21 51 57",
    "sg:province":"Provence-Alpes-C\u00f4te d'Azur",
    "wof:name":"Solnet = Iss Abilis France S.a.s.",
    "wof:placetype":"venue"
},
  "geometry": {"coordinates":[6.02332,43.143402],"type":"Point"}
}