{
  "type": "Feature",
  "properties": {
    "iso:country":"FR",
    "sg:address":"11, Rue Paulin Talabot, 31100 Toulouse",
    "sg:orig_category":"Non-Classified Establishments",
    "sg:phone":"+33 5 61 43 06 06",
    "sg:province":"Midi Pyr\u00e9n\u00e9es",
    "wof:name":"Multiware Informatique S.a.",
    "wof:placetype":"venue"
},
  "geometry": {"coordinates":[1.387794,43.564457],"type":"Point"}
}