{
  "type": "Feature",
  "properties": {
    "addr:full":"21 rue de la Vo\u00fbte 75012 Paris Ile de France 75012",
    "addr:housenumber":"21",
    "addr:postcode":"75012;75012",
    "addr:street":"Rue De La Vou\u0302Te",
    "iso:country":"FR",
    "sg:address":"21 rue de la Vo\u00fbte 75012 Paris",
    "sg:classifiers":[
        {
            "category":"Professional",
            "subcategory":"Testing Lab",
            "type":"Services"
        }
    ],
    "sg:phone":"+33 1 43 45 44 50",
    "sg:postcode":"75012",
    "sg:province":"Ile de France",
    "sg:tags":[
        "laboratory",
        "furniture"
    ],
    "wof:name":"Assistance Et Realisation De Flux Sarl",
    "wof:placetype":"venue"
},
  "geometry": {"coordinates":[2.40697,48.845673],"type":"Point"}
}