{
  "type": "Feature",
  "properties": {
    "addr:full":"16 Bis Rue Fontaine 75009 Paris Ile de France 75009",
    "addr:housenumber":"16 bis",
    "addr:postcode":"75009;75009",
    "addr:street":"Rue Fontaine",
    "iso:country":"FR",
    "sg:address":"16 Bis Rue Fontaine 75009 Paris",
    "sg:orig_category":"Audio-visual Games and entertainment Miscellaneous Products Telecommunications",
    "sg:phone":"+33 1 48 74 50 90",
    "sg:postcode":"75009",
    "sg:province":"Ile de France",
    "wof:name":"Piano Show Sa",
    "wof:placetype":"venue"
},
  "geometry": {"coordinates":[2.334432,48.881523],"type":"Point"}
}