{
  "type": "Feature",
  "properties": {
    "addr:full":"15 Rue Gare 78370 Plaisir Ile de France 78370",
    "addr:housenumber":"15",
    "addr:postcode":"78370;78370",
    "addr:street":"Rue Gare",
    "iso:country":"FR",
    "sg:address":"15 Rue Gare 78370 Plaisir",
    "sg:classifiers":[
        {
            "category":"Building & Trades",
            "subcategory":"Construction",
            "type":"Services"
        }
    ],
    "sg:phone":"+33 1 30 54 03 55",
    "sg:postcode":"78370",
    "sg:province":"Ile de France",
    "sg:tags":[
        "work",
        "public"
    ],
    "wof:name":"Sem De Plaisir Sa",
    "wof:placetype":"venue"
},
  "geometry": {"coordinates":[1.943226,48.829021],"type":"Point"}
}