{
  "type": "Feature",
  "properties": {
    "addr:full":"Zone Art Tannes Basses - Parc d'Actiivit\u00e9s Economique Clermont l'H\u00e9rault Languedoc-Roussillon 34800",
    "addr:postcode":"34800",
    "iso:country":"FR",
    "sg:address":"Zone Art Tannes Basses - Parc d'Actiivit\u00e9s Economique",
    "sg:city":"Clermont l'H\u00e9rault",
    "sg:orig_category":"Unclassifiable Establishments",
    "sg:phone":"+33 4 67 88 05 70",
    "sg:postcode":"34800",
    "sg:province":"Languedoc-Roussillon",
    "wof:name":"Hankor P.v.c. S.a.r.l.",
    "wof:placetype":"venue"
},
  "geometry": {"coordinates":[3.43383,43.626781],"type":"Point"}
}