{
  "type": "Feature",
  "properties": {
    "addr:full":"2 Rue Augustin Fresnel 57082 Metz Lorraine",
    "addr:housenumber":"2",
    "addr:postcode":"57082",
    "addr:street":"Rue Augustin Fresnel",
    "iso:country":"FR",
    "sg:address":"2 Rue Augustin Fresnel 57082 Metz",
    "sg:classifiers":[
        {
            "category":"Professional",
            "subcategory":"Business Services",
            "type":"Services"
        }
    ],
    "sg:phone":"+33 3 87 75 36 18",
    "sg:province":"Lorraine",
    "sg:tags":[
        "body",
        "advice"
    ],
    "wof:name":"Adielor",
    "wof:placetype":"venue"
},
  "geometry": {"coordinates":[6.226581,49.096245],"type":"Point"}
}