{
  "type": "Feature",
  "properties": {
    "iso:country":"FR",
    "sg:address":"2, Impasse Henri Pitot - Parc Technologique de la Plaine, 31500 Toulouse",
    "sg:orig_category":"Unclassifiable Establishments",
    "sg:phone":"+33 5 61 36 76 36",
    "sg:province":"Midi Pyr\u00e9n\u00e9es",
    "wof:name":"Allium S.a.",
    "wof:placetype":"venue"
},
  "geometry": {"coordinates":[1.494194,43.582806],"type":"Point"}
}