{
  "type": "Feature",
  "properties": {
    "addr:full":"134, Rue des Fr\u00e8res Lumi\u00e8re, 83000 Toulon Bourgogne",
    "addr:housenumber":"134",
    "addr:postcode":"83000",
    "addr:street":"Rue Des Fre\u0300Res Lumie\u0300Re",
    "iso:country":"FR",
    "sg:address":"134, Rue des Fr\u00e8res Lumi\u00e8re, 83000 Toulon",
    "sg:orig_category":"Unclassifiable Establishments",
    "sg:phone":"+33 4 94 75 26 42",
    "sg:province":"Bourgogne",
    "wof:name":"B.d.i. S.a.s. - B\u00e9daricienne Doras Industries",
    "wof:placetype":"venue"
},
  "geometry": {"coordinates":[5.930305,43.125324],"type":"Point"}
}