{
  "type": "Feature",
  "properties": {
    "addr:full":"18 rue des Pyramides 75001 Paris Ile de France 75001",
    "addr:housenumber":"18",
    "addr:postcode":"75001;75001",
    "addr:street":"Rue Des Pyramides",
    "iso:country":"FR",
    "sg:address":"18 rue des Pyramides 75001 Paris",
    "sg:classifiers":[
        {
            "category":"Wholesale",
            "subcategory":"Wine & Distilled Alcoholic Beverages",
            "type":"Manufacturing & Wholesale Goods"
        }
    ],
    "sg:phone":"+33 1 42 60 41 06",
    "sg:postcode":"75001",
    "sg:province":"Ile de France",
    "sg:tags":[
        "french"
    ],
    "wof:name":"Ste G\u00e9n\u00e9rale Representation Inspection Sa",
    "wof:placetype":"venue"
},
  "geometry": {"coordinates":[2.333618,48.86549],"type":"Point"}
}