{
  "type": "Feature",
  "properties": {
    "addr:full":"89, Place Saint L\u00e9ger, 73000 Chamb\u00e9ry Rhone-Alpes",
    "addr:housenumber":"89",
    "addr:postcode":"73000",
    "addr:street":"Place Saint",
    "iso:country":"FR",
    "sg:address":"89, Place Saint L\u00e9ger, 73000 Chamb\u00e9ry",
    "sg:orig_category":"Unclassifiable Establishments",
    "sg:phone":"+33 4 79 33 16 72",
    "sg:province":"Rhone-Alpes",
    "wof:name":"L.b.",
    "wof:placetype":"venue"
},
  "geometry": {"coordinates":[5.921086,45.564522],"type":"Point"}
}