{
  "type": "Feature",
  "properties": {
    "iso:country":"FR",
    "sg:address":"5, Av. Marcel Dassault, 31500 Toulouse",
    "sg:orig_category":"Unclassifiable Establishments",
    "sg:phone":"+33 5 62 71 66 55",
    "sg:province":"Midi Pyr\u00e9n\u00e9es",
    "wof:name":"G\u00e9nie T\u00e9l\u00e9com S.a.",
    "wof:placetype":"venue"
},
  "geometry": {"coordinates":[1.493356,43.573338],"type":"Point"}
}