{
  "type": "Feature",
  "properties": {
    "iso:country":"FR",
    "sg:address":"2 avenue Gustave Eiffel 28000 Chartres",
    "sg:city":"Chartres",
    "sg:classifiers":[
        {
            "category":"Train Station",
            "subcategory":"Light Rail",
            "type":"Transportation"
        }
    ],
    "sg:phone":"+33 2 37 30 42 00",
    "sg:postcode":"28000",
    "sg:province":"Centre",
    "sg:tags":[
        "air-conditioning",
        "unit",
        "vehicle"
    ],
    "wof:name":"Manuli Auto France S.a.r.l",
    "wof:placetype":"venue"
},
  "geometry": {"coordinates":[1.537394,48.444756],"type":"Point"}
}