{
  "type": "Feature",
  "properties": {
    "addr:full":"20 Rue De La Tuilerie St Avertin Centre 37550",
    "addr:housenumber":"20",
    "addr:postcode":"37550",
    "addr:street":"Rue De La Tuilerie St",
    "iso:country":"FR",
    "sg:address":"20 Rue De La Tuilerie",
    "sg:city":"St Avertin",
    "sg:classifiers":[
        {
            "category":"Banks & Credit Unions",
            "subcategory":"Financial Services",
            "type":"Services"
        }
    ],
    "sg:phone":"+33 2 47 71 23 71",
    "sg:postcode":"37550",
    "sg:province":"Centre",
    "sg:tags":[
        "banking",
        "finance",
        "insurance"
    ],
    "wof:name":"Galtier (expertises)",
    "wof:placetype":"venue"
},
  "geometry": {"coordinates":[0.717358,47.367702],"type":"Point"}
}