{
  "type": "Feature",
  "properties": {
    "addr:full":"15 Rue Des Fontaines 89100 Collemiers Collemiers Bourgogne 89100",
    "addr:housenumber":"15",
    "addr:postcode":"89100;89100",
    "addr:street":"Rue Des Fontaines",
    "iso:country":"FR",
    "sg:address":"15 Rue Des Fontaines 89100 Collemiers",
    "sg:city":"Collemiers",
    "sg:classifiers":[
        {
            "category":"Manufacturing",
            "subcategory":"Wood Products",
            "type":"Manufacturing & Wholesale Goods"
        }
    ],
    "sg:phone":"+33 3 86 65 93 22",
    "sg:postcode":"89100",
    "sg:province":"Bourgogne",
    "sg:tags":[
        "professional",
        "furniture"
    ],
    "wof:name":"L'agenceur",
    "wof:placetype":"venue"
},
  "geometry": {"coordinates":[3.207894,48.15379],"type":"Point"}
}