{
  "type": "Feature",
  "properties": {
    "addr:full":"10, Rue Ernest Sylvain Boll\u00e9e - ZAC de la Vivi\u00e8re, 72230 Arnage Pays de Loire",
    "addr:housenumber":"10",
    "addr:postcode":"72230",
    "addr:street":"Rue Ernest Sylvain Bolle\u0301E Zac De La Vivie\u0300Re",
    "iso:country":"FR",
    "sg:address":"10, Rue Ernest Sylvain Boll\u00e9e - ZAC de la Vivi\u00e8re, 72230 Arnage",
    "sg:orig_category":"Unclassifiable Establishments",
    "sg:phone":"+33 2 43 21 63 03",
    "sg:province":"Pays de Loire",
    "wof:name":"3 L S.a.r.l.",
    "wof:placetype":"venue"
},
  "geometry": {"coordinates":[0.12903,47.877361],"type":"Point"}
}