{
  "type": "Feature",
  "properties": {
    "addr:full":"Place de la Gare Cognac Poitou-Charentes 16100",
    "addr:postcode":"cognac;16100",
    "addr:street":"Place De La Gare",
    "iso:country":"FR",
    "sg:address":"Place de la Gare",
    "sg:city":"Cognac",
    "sg:orig_category":"Unclassifiable Establishments",
    "sg:phone":"+33 5 45 82 23 68",
    "sg:postcode":"16100",
    "sg:province":"Poitou-Charentes",
    "wof:name":"Agence C.n.c. - Compagnie Nouvelle De Conteneurs",
    "wof:placetype":"venue"
},
  "geometry": {"coordinates":[-0.326198,45.685043],"type":"Point"}
}