{
  "type": "Feature",
  "properties": {
    "iso:country":"FR",
    "sg:address":"410 Chemin De Chauvi\u00e8re 07400 Rochemaure",
    "sg:classifiers":[
        {
            "category":"Shopping",
            "type":"Retail Goods"
        }
    ],
    "sg:phone":"+33 4 75 49 63 00",
    "sg:postcode":"07400",
    "sg:province":"Rhone-Alpes",
    "sg:tags":[
        "metallurgy",
        "finished",
        "-",
        "metalworking",
        "metallic"
    ],
    "wof:name":"Ccm Durand Sa",
    "wof:placetype":"venue"
},
  "geometry": {"coordinates":[4.690045,44.565216],"type":"Point"}
}