{
  "type": "Feature",
  "properties": {
    "addr:full":"64 Rue De La Folie M\u00e9ricourt 75011 Paris Ile de France 75011",
    "addr:housenumber":"64",
    "addr:postcode":"75011;75011",
    "addr:street":"Rue De La Folie",
    "iso:country":"FR",
    "sg:address":"64 Rue De La Folie M\u00e9ricourt 75011 Paris",
    "sg:orig_category":"Miscellaneous Products",
    "sg:phone":"+33 1 49 29 27 38",
    "sg:postcode":"75011",
    "sg:province":"Ile de France",
    "wof:name":"Attica",
    "wof:placetype":"venue"
},
  "geometry": {"coordinates":[2.371236,48.864906],"type":"Point"}
}