{
  "type": "Feature",
  "properties": {
    "addr:full":"All\u00e9e de la gare - B\u00e2t Isba Bouff\u00e9mont Ile de France 95570",
    "addr:housenumber":"ba\u0302t",
    "addr:postcode":"95570",
    "addr:street":"Alle\u0301E De La Gare",
    "iso:country":"FR",
    "sg:address":"All\u00e9e de la gare - B\u00e2t Isba",
    "sg:city":"Bouff\u00e9mont",
    "sg:orig_category":"Unclassifiable Establishments",
    "sg:phone":"+33 1 39 35 04 33",
    "sg:postcode":"95570",
    "sg:province":"Ile de France",
    "wof:name":"Im\u00e9dia S.a.r.l.",
    "wof:placetype":"venue"
},
  "geometry": {"coordinates":[2.322205,49.045116],"type":"Point"}
}