{
  "type": "Feature",
  "properties": {
    "addr:full":"14, Rue des Arts, 31000 Toulouse Midi Pyr\u00e9n\u00e9es",
    "addr:housenumber":"14",
    "addr:postcode":"31000",
    "addr:street":"Rue Des Arts",
    "iso:country":"FR",
    "sg:address":"14, Rue des Arts, 31000 Toulouse",
    "sg:orig_category":"Unclassifiable Establishments",
    "sg:phone":"+33 5 61 11 03 20",
    "sg:province":"Midi Pyr\u00e9n\u00e9es",
    "wof:name":"Editions Privat S.a.",
    "wof:placetype":"venue"
},
  "geometry": {"coordinates":[1.447164,43.600712],"type":"Point"}
}