{
  "type": "Feature",
  "properties": {
    "iso:country":"FR",
    "sg:address":"La Boutonni\u00e8re 79300 Terves",
    "sg:orig_category":"Unclassifiable Establishments",
    "sg:phone":"+33 5 49 65 33 13",
    "sg:province":"Poitou-Charentes",
    "wof:name":"Proco S.a.",
    "wof:placetype":"venue"
},
  "geometry": {"coordinates":[-0.434544,46.774929],"type":"Point"}
}