{
  "type": "Feature",
  "properties": {
    "addr:full":"chemin de Sury 08000 Warcq Charleville-M\u00e9zi\u00e8res Champagne 08000",
    "addr:postcode":"08000;08000",
    "addr:street":"Chemin De Sury",
    "iso:country":"FR",
    "sg:address":"chemin de Sury 08000 Warcq",
    "sg:city":"Charleville-M\u00e9zi\u00e8res",
    "sg:classifiers":[
        {
            "category":"Autos & Motor Vehicles",
            "subcategory":"Auto Supplies",
            "type":"Retail Goods"
        }
    ],
    "sg:phone":"+33 3 24 59 23 45",
    "sg:postcode":"08000",
    "sg:province":"Champagne",
    "sg:tags":[
        "body",
        "car",
        "truck",
        "trailer",
        "superstructure"
    ],
    "wof:name":"Thiriet Sas",
    "wof:placetype":"venue"
},
  "geometry": {"coordinates":[4.663647,49.768665],"type":"Point"}
}