{
  "type": "Feature",
  "properties": {
    "iso:country":"FR",
    "sg:address":"3 Place Joseph Aletti; Vichy; 03200",
    "sg:city":"Vichy",
    "sg:classifiers":[
        {
            "category":"Travel",
            "subcategory":"Travel Agent",
            "type":"Entertainment"
        }
    ],
    "sg:phone":"+33 3347031787",
    "sg:postcode":"03200",
    "sg:province":"Auvergne",
    "wof:name":"Best Western Aletti Palace Hotel",
    "wof:placetype":"venue"
},
  "geometry": {"coordinates":[3.418941,46.123421],"type":"Point"}
}