{
  "type": "Feature",
  "properties": {
    "addr:full":"B.P. 36, 71380 Saint Marcel^^ZI Portuaire Sud, 71380 Saint Marcel Ch\u00e2tenoy-en-Bresse Bourgogne 71380",
    "addr:postcode":"71380;71380;71380",
    "addr:street":"B.P. 36;Portuaire Sud;Marcel",
    "iso:country":"FR",
    "sg:address":"B.P. 36, 71380 Saint Marcel^^ZI Portuaire Sud, 71380 Saint Marcel",
    "sg:city":"Ch\u00e2tenoy-en-Bresse",
    "sg:orig_category":"Non-Classified Establishments",
    "sg:phone":"+33 3 85 93 44 22",
    "sg:postcode":"71380",
    "sg:province":"Bourgogne",
    "wof:name":"C\u00e9ri Antirouille S.a.",
    "wof:placetype":"venue"
},
  "geometry": {"coordinates":[4.890325,46.775509],"type":"Point"}
}