{
  "type": "Feature",
  "properties": {
    "addr:full":"Rue Moulineau 33326 Eysines Cedex Eysines Aquitaine 33320",
    "addr:postcode":"33326;33320",
    "addr:street":"Rue Moulineau",
    "iso:country":"FR",
    "sg:address":"Rue Moulineau 33326 Eysines Cedex",
    "sg:city":"Eysines",
    "sg:classifiers":[
        {
            "category":"Building & Trades",
            "subcategory":"Construction",
            "type":"Services"
        }
    ],
    "sg:phone":"+33 5 56 28 17 67",
    "sg:postcode":"33320",
    "sg:province":"Aquitaine",
    "sg:tags":[
        "work",
        "public"
    ],
    "wof:name":"Sud Ouest Pavage (sop)",
    "wof:placetype":"venue"
},
  "geometry": {"coordinates":[-0.664554,44.876759],"type":"Point"}
}