{
  "type": "Feature",
  "properties": {
    "addr:full":"36, Bd de la Bastille, 75012 Paris Ile de France",
    "addr:housenumber":"36",
    "addr:postcode":"75012",
    "addr:street":"Bd De La Bastille",
    "iso:country":"FR",
    "sg:address":"36, Bd de la Bastille, 75012 Paris",
    "sg:orig_category":"Non-Classified Establishments",
    "sg:phone":"+33 1 43 43 98 16",
    "sg:province":"Ile de France",
    "wof:name":"Imprimerie Helde S.a.",
    "wof:placetype":"venue"
},
  "geometry": {"coordinates":[2.368925,48.850281],"type":"Point"}
}