{
  "type": "Feature",
  "properties": {
    "iso:country":"FR",
    "sg:address":"10, Avenue Hoche; 75381 Paris Cedex 08, France",
    "sg:classifiers":[
        {
            "category":"Industrial Area",
            "type":"Public Place"
        }
    ],
    "sg:phone":"+33 1 45 64 61 00",
    "sg:province":"Aquitaine",
    "sg:tags":[
        "large",
        "private"
    ],
    "wof:name":"Pinault-printemps-redoute S.a.",
    "wof:placetype":"venue"
},
  "geometry": {"coordinates":[2.30288,48.877277],"type":"Point"}
}