{
  "type": "Feature",
  "properties": {
    "addr:full":"Mas Blumenthal 06130 Grasse Rhone-Alpes",
    "addr:postcode":"06130",
    "iso:country":"FR",
    "sg:address":"Mas",
    "sg:city":"Blumenthal 06130 Grasse",
    "sg:classifiers":[
        {
            "category":"Home & Garden",
            "subcategory":"Furniture",
            "type":"Retail Goods"
        }
    ],
    "sg:phone":"+33 4 93 70 08 98",
    "sg:province":"Rhone-Alpes",
    "sg:tags":[
        "household",
        "wood"
    ],
    "wof:name":"La Halle Au Sommeil",
    "wof:placetype":"venue"
},
  "geometry": {"coordinates":[6.931647,43.649738],"type":"Point"}
}