{
  "type": "Feature",
  "properties": {
    "addr:full":"Les Sardons Route De Cassis 13830 Roquefort La Bedoule Franche Comt\u00e9",
    "addr:postcode":"13830",
    "addr:street":"Route De Cassis;Franche Comte\u0301",
    "iso:country":"FR",
    "sg:address":"Les Sardons Route De Cassis 13830 Roquefort La Bedoule",
    "sg:classifiers":[
        {
            "category":"Park",
            "type":"Public Place"
        }
    ],
    "sg:phone":"+33 4 42 73 07 49",
    "sg:province":"Franche Comt\u00e9",
    "sg:tags":[
        "work",
        "construction",
        "sport"
    ],
    "wof:name":"Alliance Piscine Polyester",
    "wof:placetype":"venue"
},
  "geometry": {"coordinates":[5.589952,43.247658],"type":"Point"}
}