{
  "type": "Feature",
  "properties": {
    "addr:full":"515, Av. Roland Garros, 78531 Buc C\u00e9dex Corse",
    "addr:housenumber":"515",
    "addr:postcode":"78531",
    "addr:street":"Av. Roland Garros",
    "iso:country":"FR",
    "sg:address":"515, Av. Roland Garros, 78531 Buc C\u00e9dex",
    "sg:orig_category":"Non-Classified Establishments",
    "sg:phone":"+33 1 39 56 63 00",
    "sg:province":"Corse",
    "wof:name":"Equinox S.a.r.l.",
    "wof:placetype":"venue"
},
  "geometry": {"coordinates":[2.121094,48.762154],"type":"Point"}
}