{
  "type": "Feature",
  "properties": {
    "addr:full":"BP 540, Immeuble Atlantique Montparnasse - Nord Pont, 7 Place des 5 Martyrs du Lyc\u00e9e Buffon, 75725 P Rhone-Alpes",
    "addr:housenumber":"540;7",
    "addr:postcode":"75725",
    "addr:street":"Immeuble;Pont;Place Des 5 Martyrs Du Lyce\u0301E Buffon",
    "iso:country":"FR",
    "sg:address":"BP 540, Immeuble Atlantique Montparnasse - Nord Pont, 7 Place des 5 Martyrs du Lyc\u00e9e Buffon, 75725 P",
    "sg:classifiers":[
        {
            "category":"Banks & Credit Unions",
            "subcategory":"Bank",
            "type":"Services"
        }
    ],
    "sg:province":"Rhone-Alpes",
    "wof:name":"Caisse Centrale Des Caisses D'epargne Et De Pr\u00e9voyance",
    "wof:placetype":"venue"
},
  "geometry": {"coordinates":[3.84692,50.221619],"type":"Point"}
}