{
  "type": "Feature",
  "properties": {
    "addr:full":"Rte de Bale P\u00e9rouse Franche Comt\u00e9 90160",
    "addr:postcode":"90160",
    "addr:street":"Rte De Bale;Franche Comte\u0301",
    "iso:country":"FR",
    "sg:address":"Rte de Bale",
    "sg:city":"P\u00e9rouse",
    "sg:orig_category":"Non-Classified Establishments",
    "sg:phone":"+33 3 84 21 71 53",
    "sg:postcode":"90160",
    "sg:province":"Franche Comt\u00e9",
    "wof:name":"Couroux S.a.",
    "wof:placetype":"venue"
},
  "geometry": {"coordinates":[6.892687,47.63689],"type":"Point"}
}