{
  "type": "Feature",
  "properties": {
    "addr:full":"7 Grand Rue 62159 Vaulx Vraucourt Nord Pas-de-Calais 62159",
    "addr:housenumber":"7",
    "addr:postcode":"62159;62159",
    "addr:street":"Grand Rue;Pas-De-Calais",
    "iso:country":"FR",
    "sg:address":"7 Grand Rue 62159 Vaulx Vraucourt",
    "sg:classifiers":[
        {
            "category":"Manufacturing",
            "subcategory":"Metals",
            "type":"Manufacturing & Wholesale Goods"
        }
    ],
    "sg:phone":"+33 3 21 07 48 19",
    "sg:postcode":"62159",
    "sg:province":"Nord Pas-de-Calais",
    "sg:tags":[
        "metallurgy",
        "metalworking",
        "processing"
    ],
    "wof:name":"Entreprise Coppin",
    "wof:placetype":"venue"
},
  "geometry": {"coordinates":[2.90737,50.149212],"type":"Point"}
}