{
  "type": "Feature",
  "properties": {
    "addr:full":"11 Av Du Mal Joffre 51200 Epernay Champagne",
    "addr:postcode":"51200",
    "addr:street":"11 Av Du Mal Joffre",
    "iso:country":"FR",
    "sg:address":"11 Av Du Mal Joffre 51200 Epernay",
    "sg:classifiers":[
        {
            "category":"Professional",
            "type":"Services"
        }
    ],
    "sg:phone":"+33 3 26 51 19 20",
    "sg:province":"Champagne",
    "sg:tags":[
        "transport",
        "road"
    ],
    "wof:name":"Walbaum",
    "wof:placetype":"venue"
},
  "geometry": {"coordinates":[3.953991,49.050251],"type":"Point"}
}