{
  "type": "Feature",
  "properties": {
    "iso:country":"FR",
    "sg:address":"11 Cour De Verdun 33000 Bordeaux",
    "sg:city":"Bordeaux",
    "sg:classifiers":[
        {
            "category":"Professional",
            "subcategory":"Computer Services",
            "type":"Services"
        }
    ],
    "sg:phone":"+33 5 56 52 08 37",
    "sg:postcode":"33000",
    "sg:province":"Aquitaine",
    "sg:tags":[
        "information",
        "technology",
        "software"
    ],
    "wof:name":"Encod Sa",
    "wof:placetype":"venue"
},
  "geometry": {"coordinates":[-0.577683,44.845882],"type":"Point"}
}