{
  "type": "Feature",
  "properties": {
    "addr:full":"195 Rue De Bercy 75012 Paris Ile de France 75012",
    "addr:housenumber":"195",
    "addr:postcode":"75012;75012",
    "addr:street":"Rue De Bercy",
    "iso:country":"FR",
    "sg:address":"195 Rue De Bercy 75012 Paris",
    "sg:classifiers":[
        {
            "category":"Professional",
            "subcategory":"Computer Services",
            "type":"Services"
        }
    ],
    "sg:phone":"+33 1 53 46 61 91",
    "sg:postcode":"75012",
    "sg:province":"Ile de France",
    "sg:tags":[
        "information",
        "technology",
        "software"
    ],
    "wof:name":"Hotline Sa",
    "wof:placetype":"venue"
},
  "geometry": {"coordinates":[2.373042,48.843758],"type":"Point"}
}