{
  "type": "Feature",
  "properties": {
    "iso:country":"FR",
    "sg:address":"15 rue de la Grande-Bretagne 44470 Carquefou",
    "sg:orig_category":"Aluminium Tubes, Seamless Extruded And Drawn",
    "sg:phone":"+33 2 40 18 47 00",
    "sg:postcode":"44470",
    "sg:province":"Pays de Loire",
    "wof:name":"Pechiney Aviatube Sa",
    "wof:placetype":"venue"
},
  "geometry": {"coordinates":[-1.505422,47.25943],"type":"Point"}
}