{
  "type": "Feature",
  "properties": {
    "addr:full":"Pont Vieux 81440 Montdragon Midi Pyr\u00e9n\u00e9es",
    "addr:postcode":"81440",
    "addr:street":"Pont Vieux",
    "iso:country":"FR",
    "sg:address":"Pont Vieux 81440 Montdragon",
    "sg:orig_category":"Unclassifiable Establishments",
    "sg:phone":"+33 5 63 42 02 81",
    "sg:province":"Midi Pyr\u00e9n\u00e9es",
    "wof:name":"Soci\u00e9t\u00e9 M\u00e9gisserie Du Pont Vieux S.a.r.l.",
    "wof:placetype":"venue"
},
  "geometry": {"coordinates":[2.095308,43.7799],"type":"Point"}
}