{
  "type": "Feature",
  "properties": {
    "addr:full":"11 rue de Foucharupt 88100 ST DIE DES VOSGES Lorraine 88100",
    "addr:housenumber":"11",
    "addr:postcode":"88100 st;88100",
    "addr:street":"Rue De Foucharupt;Des Vosges",
    "iso:country":"FR",
    "sg:address":"11 rue de Foucharupt 88100 ST DIE DES VOSGES",
    "sg:classifiers":[
        {
            "category":"Manufacturing",
            "subcategory":"Printing",
            "type":"Manufacturing & Wholesale Goods"
        }
    ],
    "sg:phone":"+33 3 29 55 21 15",
    "sg:postcode":"88100",
    "sg:province":"Lorraine",
    "sg:tags":[
        "house",
        "book"
    ],
    "wof:name":"Les Imprimeries Loos Hvi Humblot Sarl",
    "wof:placetype":"venue"
},
  "geometry": {"coordinates":[6.95193,48.280407],"type":"Point"}
}