{
  "type": "Feature",
  "properties": {
    "iso:country":"FR",
    "sg:address":"6 bis, Av. de la Boudini\u00e8re, 13013 Marseille",
    "sg:orig_category":"Non-Classified Establishments",
    "sg:phone":"+33 4 91 66 17 18",
    "sg:province":"Poitou-Charentes",
    "wof:name":"Atelier Gay",
    "wof:placetype":"venue"
},
  "geometry": {"coordinates":[5.416757,43.323654],"type":"Point"}
}