{
  "type": "Feature",
  "properties": {
    "addr:full":"B.P. 19 Perrex^^L'All\u00e9e 01540 Perrex Rhone-Alpes 01540",
    "addr:postcode":"01540;01540",
    "addr:street":"B.P. 19 Perrex^^L ' Alle\u0301E",
    "iso:country":"FR",
    "sg:address":"B.P. 19",
    "sg:city":"Perrex^^L'All\u00e9e 01540 Perrex",
    "sg:orig_category":"Non-Classified Establishments",
    "sg:phone":"+33 4 74 50 01 45",
    "sg:postcode":"01540",
    "sg:province":"Rhone-Alpes",
    "wof:name":"Etablissements Jean Four S.a.",
    "wof:placetype":"venue"
},
  "geometry": {"coordinates":[4.97954,46.244999],"type":"Point"}
}