{
  "type": "Feature",
  "properties": {
    "addr:full":"B.P. 5, 08330 Vrigne aux Bois^^6, Rue Jean-Jacques Rousseau, 08330 Vrigne aux Bois Champagne",
    "addr:housenumber":"5",
    "addr:postcode":"08330;08330",
    "addr:street":"B.P.;Rue Jean-Jacques Rousseau;Aux Bois Champagne",
    "iso:country":"FR",
    "sg:address":"B.P. 5, 08330 Vrigne aux Bois^^6, Rue Jean-Jacques Rousseau, 08330 Vrigne aux Bois",
    "sg:orig_category":"Non-Classified Establishments",
    "sg:phone":"+33 3 24 52 22 47",
    "sg:province":"Champagne",
    "wof:name":"Thermic Ardennes S.a.r.l.",
    "wof:placetype":"venue"
},
  "geometry": {"coordinates":[4.855204,49.739227],"type":"Point"}
}