{
  "type": "Feature",
  "properties": {
    "iso:country":"FR",
    "sg:address":"3, Rue Damozanne, 14000 Caen",
    "sg:city":"Caen",
    "sg:orig_category":"Non-Classified Establishments",
    "sg:phone":"+33 2 31 86 46 22",
    "sg:postcode":"14000",
    "sg:province":"Basse Normandie",
    "wof:name":"Sopregi S.a.r.l.",
    "wof:placetype":"venue"
},
  "geometry": {"coordinates":[-0.380457,49.178719],"type":"Point"}
}