{
  "type": "Feature",
  "properties": {
    "iso:country":"FR",
    "sg:address":"87 Rue Pt Ed Herriot 69002 Lyon",
    "sg:classifiers":[
        {
            "category":"Manufacturing",
            "subcategory":"Leather Goods",
            "type":"Manufacturing & Wholesale Goods"
        }
    ],
    "sg:phone":"+33 4 72 41 78 53",
    "sg:postcode":"69002",
    "sg:province":"Rhone-Alpes",
    "sg:tags":[
        "shoe"
    ],
    "wof:name":"Christian Dior Couture",
    "wof:placetype":"venue"
},
  "geometry": {"coordinates":[4.828975,45.759399],"type":"Point"}
}