{
  "type": "Feature",
  "properties": {
    "iso:country":"FR",
    "sg:address":"180 rue du Moulin Routhion 45270 LADON",
    "sg:city":"Ladon",
    "sg:classifiers":[
        {
            "category":"Arena",
            "subcategory":"Horse Racetrack",
            "type":"Entertainment"
        }
    ],
    "sg:phone":"+33 2 38 95 50 14",
    "sg:postcode":"45270",
    "sg:province":"Centre",
    "sg:tags":[
        "fodder"
    ],
    "wof:name":"Thoreau Sa",
    "wof:placetype":"venue"
},
  "geometry": {"coordinates":[2.54352,48.002716],"type":"Point"}
}