{
  "type": "Feature",
  "properties": {
    "iso:country":"FR",
    "sg:address":"37, Quai de Grenelle, 75738 Paris Cedex 15",
    "sg:orig_category":"Non-Classified Establishments",
    "sg:phone":"+33 1 40 59 31 67",
    "sg:province":"Ile de France",
    "wof:name":"I.f.g. S.a.s. - Institut Fran\u00e7ais De Gestion",
    "wof:placetype":"venue"
},
  "geometry": {"coordinates":[2.286078,48.852051],"type":"Point"}
}