{
  "type": "Feature",
  "properties": {
    "addr:full":"Av Des Abb\u00e9s Dupont 64800 Nay Nay Aquitaine 64800",
    "addr:postcode":"64800;64800",
    "addr:street":"Av Des Abbe\u0301S Dupont",
    "iso:country":"FR",
    "sg:address":"Av Des Abb\u00e9s Dupont 64800 Nay",
    "sg:city":"Nay",
    "sg:classifiers":[
        {
            "category":"Professional",
            "subcategory":"Business Services",
            "type":"Services"
        }
    ],
    "sg:phone":"+33 5 59 61 18 32",
    "sg:postcode":"64800",
    "sg:province":"Aquitaine",
    "sg:tags":[
        "training",
        "advice"
    ],
    "wof:name":"Ogec St Joseph",
    "wof:placetype":"venue"
},
  "geometry": {"coordinates":[-0.262924,43.173504],"type":"Point"}
}