{
  "type": "Feature",
  "properties": {
    "addr:full":"Les Hauts Banquets 84300 Cavaillon Languedoc-Roussillon",
    "addr:postcode":"84300",
    "addr:street":"Les Hauts Banquets",
    "iso:country":"FR",
    "sg:address":"Les Hauts Banquets 84300 Cavaillon",
    "sg:classifiers":[
        {
            "category":"Manufacturing",
            "subcategory":"Wood Products",
            "type":"Manufacturing & Wholesale Goods"
        }
    ],
    "sg:phone":"+33 4 90 06 05 77",
    "sg:province":"Languedoc-Roussillon",
    "sg:tags":[
        "furniture"
    ],
    "wof:name":"Decor Et Tradition Sarl",
    "wof:placetype":"venue"
},
  "geometry": {"coordinates":[5.060953,43.826355],"type":"Point"}
}