{
  "type": "Feature",
  "properties": {
    "iso:country":"FR",
    "sg:address":"Rte De Cazaubon 32800 Eauze",
    "sg:classifiers":[
        {
            "category":"Food Court",
            "type":"Food & Drink"
        }
    ],
    "sg:phone":"+33 5 62 09 94 22",
    "sg:postcode":"32800",
    "sg:province":"Midi Pyr\u00e9n\u00e9es",
    "sg:tags":[
        "product",
        "related"
    ],
    "wof:name":"Marquis De Caussade Sa",
    "wof:placetype":"venue"
},
  "geometry": {"coordinates":[0.16501,43.809696],"type":"Point"}
}