{
  "type": "Feature",
  "properties": {
    "addr:full":"Le Moulin Nantay 51480 OEUILLY Champagne 51480",
    "addr:postcode":"51480;51480",
    "addr:street":"Champagne",
    "iso:country":"FR",
    "sg:address":"Le Moulin Nantay 51480 OEUILLY",
    "sg:classifiers":[
        {
            "category":"Communications",
            "subcategory":"Film & Video Production",
            "type":"Services"
        }
    ],
    "sg:phone":"+33 3 26 58 33 73",
    "sg:postcode":"51480",
    "sg:province":"Champagne",
    "sg:tags":[
        "adhesive",
        "labels",
        "reel"
    ],
    "wof:name":"Agipa Sa",
    "wof:placetype":"venue"
},
  "geometry": {"coordinates":[3.878572,49.072487],"type":"Point"}
}