{
  "type": "Feature",
  "properties": {
    "iso:country":"FR",
    "sg:address":"ZA",
    "sg:city":"Brioude",
    "sg:orig_category":"Unclassifiable Establishments",
    "sg:phone":"+33 4 71 50 31 83",
    "sg:postcode":"43100",
    "sg:province":"Auvergne",
    "wof:name":"Delmas Germain",
    "wof:placetype":"venue"
},
  "geometry": {"coordinates":[3.29335,45.191734],"type":"Point"}
}