{
  "type": "Feature",
  "properties": {
    "addr:full":"Rue des Tuileries - ZA Souffelweyersheim Alsace 67460",
    "addr:postcode":"67460",
    "addr:street":"Rue Des Tuileries Za Souffelweyersheim",
    "iso:country":"FR",
    "sg:address":"Rue des Tuileries - ZA",
    "sg:city":"Souffelweyersheim",
    "sg:orig_category":"Unclassifiable Establishments",
    "sg:phone":"+33 3 88 33 96 66",
    "sg:postcode":"67460",
    "sg:province":"Alsace",
    "wof:name":"Intexalu Syst\u00e8mes S.n.c.",
    "wof:placetype":"venue"
},
  "geometry": {"coordinates":[7.74147,48.635509],"type":"Point"}
}