{
  "type": "Feature",
  "properties": {
    "addr:full":"Pontanevaux 71570 La Chapelle De Guinchay Chaintr\u00e9 Bourgogne 71570",
    "addr:postcode":"71570;71570",
    "addr:street":"Pontanevaux",
    "iso:country":"FR",
    "sg:address":"Pontanevaux 71570 La Chapelle De Guinchay",
    "sg:city":"Chaintr\u00e9",
    "sg:classifiers":[
        {
            "category":"Food Court",
            "type":"Food & Drink"
        }
    ],
    "sg:phone":"+33 3 85 36 72 32",
    "sg:postcode":"71570",
    "sg:province":"Bourgogne",
    "sg:tags":[
        "product",
        "related"
    ],
    "wof:name":"Sarl Desvignes Aine Et Fils",
    "wof:placetype":"venue"
},
  "geometry": {"coordinates":[4.772,46.209129],"type":"Point"}
}