{
  "type": "Feature",
  "properties": {
    "addr:full":"Les Clos Tords 61120 Vimoutiers Vimoutiers Basse Normandie 61120",
    "addr:postcode":"61120;61120",
    "addr:street":"Tords",
    "iso:country":"FR",
    "sg:address":"Les Clos Tords 61120 Vimoutiers",
    "sg:city":"Vimoutiers",
    "sg:classifiers":[
        {
            "category":"Food & Beverages",
            "subcategory":"Dairy",
            "type":"Retail Goods"
        }
    ],
    "sg:phone":"+33 2 33 39 63 00",
    "sg:postcode":"61120",
    "sg:province":"Basse Normandie",
    "sg:tags":[
        "product",
        "related"
    ],
    "wof:name":"Solaipa",
    "wof:placetype":"venue"
},
  "geometry": {"coordinates":[0.232705,48.851215],"type":"Point"}
}