{
  "type": "Feature",
  "properties": {
    "addr:full":"Gostang 29430 Plouescat Plouescat Bretagne 29430",
    "addr:postcode":"29430;plouescat;29430",
    "addr:street":"Gostang",
    "iso:country":"FR",
    "sg:address":"Gostang 29430 Plouescat",
    "sg:city":"Plouescat",
    "sg:classifiers":[
        {
            "category":"Professional",
            "type":"Services"
        }
    ],
    "sg:phone":"+33 2 98 69 84 94",
    "sg:postcode":"29430",
    "sg:province":"Bretagne",
    "sg:tags":[
        "transport",
        "road"
    ],
    "wof:name":"Transports Du Leon",
    "wof:placetype":"venue"
},
  "geometry": {"coordinates":[-4.172129,48.649288],"type":"Point"}
}