{
  "type": "Feature",
  "properties": {
    "addr:full":"37, Bd Bernard Palissy, 42312 Roanne C\u00e9dex Ile de France",
    "addr:housenumber":"37",
    "addr:postcode":"42312",
    "addr:street":"Bd Bernard Palissy",
    "iso:country":"FR",
    "sg:address":"37, Bd Bernard Palissy, 42312 Roanne C\u00e9dex",
    "sg:orig_category":"Non-Classified Establishments",
    "sg:phone":"+33 4 77 71 96 14",
    "sg:province":"Ile de France",
    "wof:name":"Etablissement Bonnard S.a.",
    "wof:placetype":"venue"
},
  "geometry": {"coordinates":[4.08187,46.041637],"type":"Point"}
}