{
  "type": "Feature",
  "properties": {
    "iso:country":"FR",
    "sg:address":"ZAC de Voitrelle",
    "sg:city":"Saint Memmie",
    "sg:orig_category":"Non-Classified Establishments",
    "sg:phone":"+33 3 26 68 28 39",
    "sg:postcode":"51470",
    "sg:province":"Champagne",
    "wof:name":"Charlet Piscines S.a.r.l.",
    "wof:placetype":"venue"
},
  "geometry": {"coordinates":[4.384128,48.954563],"type":"Point"}
}