{
  "type": "Feature",
  "properties": {
    "iso:country":"FR",
    "sg:address":"chemin du Charbonnier 69800 St Priest",
    "sg:classifiers":[
        {
            "category":"Utilities",
            "subcategory":"Fuel Oil & Lpg",
            "type":"Services"
        }
    ],
    "sg:phone":"+33 4 72 90 12 12",
    "sg:postcode":"69800",
    "sg:province":"Rhone-Alpes",
    "sg:tags":[
        "truck",
        "vehicle"
    ],
    "wof:name":"Jonas International S.a.",
    "wof:placetype":"venue"
},
  "geometry": {"coordinates":[4.907195,45.691875],"type":"Point"}
}