{
  "type": "Feature",
  "properties": {
    "addr:full":"13 Rue Du Port 89400 Epineau Les Voves Bussy-en-Othe Bourgogne 89400",
    "addr:housenumber":"13",
    "addr:postcode":"89400;89400",
    "addr:street":"Rue Du Port",
    "iso:country":"FR",
    "sg:address":"13 Rue Du Port 89400 Epineau Les Voves",
    "sg:city":"Bussy-en-Othe",
    "sg:classifiers":[
        {
            "category":"Manufacturing",
            "subcategory":"Food",
            "type":"Manufacturing & Wholesale Goods"
        }
    ],
    "sg:phone":"+33 3 86 80 10 51",
    "sg:postcode":"89400",
    "sg:province":"Bourgogne",
    "sg:tags":[
        "preserve",
        "product",
        "related"
    ],
    "wof:name":"Prince St-fran\u00c7ois Frangile",
    "wof:placetype":"venue"
},
  "geometry": {"coordinates":[3.483955,47.960121],"type":"Point"}
}