{
  "type": "Feature",
  "properties": {
    "addr:full":"March\u00e9 Gare Murisserie - Bat L2 84033 Avignon Cedex Champagne",
    "addr:postcode":"84033",
    "addr:street":"L2",
    "iso:country":"FR",
    "sg:address":"March\u00e9 Gare Murisserie - Bat L2 84033 Avignon Cedex",
    "sg:classifiers":[
        {
            "category":"Farming",
            "subcategory":"Crops",
            "type":"Manufacturing & Wholesale Goods"
        }
    ],
    "sg:phone":"+33 4 90 88 13 02",
    "sg:province":"Champagne",
    "sg:tags":[
        "vegetable",
        "fruit",
        "agriculture",
        "livestock"
    ],
    "wof:name":"Dole France",
    "wof:placetype":"venue"
},
  "geometry": {"coordinates":[4.80597,43.948608],"type":"Point"}
}