{
  "type": "Feature",
  "properties": {
    "iso:country":"FR",
    "sg:address":"12, Rue du 11 Novembre 1918, 94460 Valenton",
    "sg:orig_category":"Non-Classified Establishments",
    "sg:phone":"+33 1 43 89 04 04",
    "sg:province":"Ile de France",
    "wof:name":"Euro-vert S.a.",
    "wof:placetype":"venue"
},
  "geometry": {"coordinates":[2.467909,48.750362],"type":"Point"}
}