{
  "type": "Feature",
  "properties": {
    "addr:full":"Les Fontaines 74300 Ch\u00e2tillon sur Cluses Rhone-Alpes 74300",
    "addr:postcode":"74300;74300",
    "iso:country":"FR",
    "sg:address":"Les Fontaines 74300 Ch\u00e2tillon sur Cluses",
    "sg:orig_category":"Unclassifiable Establishments",
    "sg:phone":"+33 4 50 98 06 82",
    "sg:postcode":"74300",
    "sg:province":"Rhone-Alpes",
    "wof:name":"Moret G\u00e9rard S.a.r.l.",
    "wof:placetype":"venue"
},
  "geometry": {"coordinates":[6.56786,46.083775],"type":"Point"}
}