{
  "type": "Feature",
  "properties": {
    "addr:full":"26, Rue Pierre Curie, 78130 Les Mureaux Ile de France",
    "addr:housenumber":"26",
    "addr:postcode":"78130",
    "addr:street":"Rue Pierre Curie",
    "iso:country":"FR",
    "sg:address":"26, Rue Pierre Curie, 78130 Les Mureaux",
    "sg:orig_category":"Unclassifiable Establishments",
    "sg:phone":"+33 1 34 74 04 34",
    "sg:province":"Ile de France",
    "wof:name":"Entreprise Coutin S.a.",
    "wof:placetype":"venue"
},
  "geometry": {"coordinates":[1.921217,48.994427],"type":"Point"}
}