{
  "type": "Feature",
  "properties": {
    "addr:full":"14 Avenue Du Lion Za La Poulasse 83210 Sollies Pont Aquitaine",
    "addr:housenumber":"14",
    "addr:postcode":"83210",
    "addr:street":"Avenue Du Lion Za La Poulasse",
    "iso:country":"FR",
    "sg:address":"14 Avenue Du Lion Za La Poulasse 83210 Sollies Pont",
    "sg:classifiers":[
        {
            "category":"Utilities",
            "subcategory":"Telephone",
            "type":"Services"
        }
    ],
    "sg:phone":"+33 4 94 13 50 50",
    "sg:province":"Aquitaine",
    "sg:tags":[
        "telecommunication"
    ],
    "wof:name":"Groupe Sircet Sa",
    "wof:placetype":"venue"
},
  "geometry": {"coordinates":[6.042811,43.166992],"type":"Point"}
}