{
  "type": "Feature",
  "properties": {
    "addr:full":"16, Cit\u00e9 Joly, 75011 Paris Ile de France",
    "addr:housenumber":"16",
    "addr:postcode":"75011",
    "addr:street":"Cite\u0301 Joly",
    "iso:country":"FR",
    "sg:address":"16, Cit\u00e9 Joly, 75011 Paris",
    "sg:orig_category":"Unclassifiable Establishments",
    "sg:phone":"+33 1 43 57 51 17",
    "sg:province":"Ile de France",
    "wof:name":"Actua Color S.a.r.l.",
    "wof:placetype":"venue"
},
  "geometry": {"coordinates":[2.383002,48.862671],"type":"Point"}
}