{
  "type": "Feature",
  "properties": {
    "addr:full":"La Rouge 24200 Sarlat la Can\u00e9da Aquitaine 24200",
    "addr:postcode":"24200;24200",
    "addr:street":"La Rouge",
    "iso:country":"FR",
    "sg:address":"La",
    "sg:city":"Rouge 24200 Sarlat la Can\u00e9da",
    "sg:classifiers":[
        {
            "category":"Food Court",
            "type":"Food & Drink"
        }
    ],
    "sg:phone":"+33 5 53 29 97 55",
    "sg:postcode":"24200",
    "sg:province":"Aquitaine",
    "sg:tags":[
        "product",
        "related"
    ],
    "wof:name":"La Cave Du Gouyat",
    "wof:placetype":"venue"
},
  "geometry": {"coordinates":[1.234939,44.852894],"type":"Point"}
}