{
  "type": "Feature",
  "properties": {
    "addr:full":"27, Bd du 11 Novembre 1918 - B\u00e2t CEI, 69100 Villeurbanne Rhone-Alpes",
    "addr:housenumber":"27;ba\u0302t",
    "addr:postcode":"69100",
    "addr:street":"Bd Du 11 Novembre 1918",
    "iso:country":"FR",
    "sg:address":"27, Bd du 11 Novembre 1918 - B\u00e2t CEI, 69100 Villeurbanne",
    "sg:orig_category":"Unclassifiable Establishments",
    "sg:phone":"+33 4 72 44 02 03",
    "sg:province":"Rhone-Alpes",
    "wof:name":"Trioptics France S.a.r.l.",
    "wof:placetype":"venue"
},
  "geometry": {"coordinates":[4.861573,45.77951],"type":"Point"}
}