{
  "type": "Feature",
  "properties": {
    "addr:full":"Rue Augustin Fresnel 35300 Foug\u00e8res Foug\u00e8res Bretagne 35300",
    "addr:postcode":"35300;35300",
    "addr:street":"Rue Augustin Fresnel",
    "iso:country":"FR",
    "sg:address":"Rue Augustin Fresnel 35300 Foug\u00e8res",
    "sg:city":"Foug\u00e8res",
    "sg:classifiers":[
        {
            "category":"Health Services",
            "subcategory":"Optometrist",
            "type":"Services"
        }
    ],
    "sg:phone":"+33 2 99 94 84 84",
    "sg:postcode":"35300",
    "sg:province":"Bretagne",
    "sg:tags":[
        "instrument",
        "optical",
        "-",
        "precision",
        "equipment"
    ],
    "wof:name":"Ao Ouest Optique",
    "wof:placetype":"venue"
},
  "geometry": {"coordinates":[-1.181408,48.349121],"type":"Point"}
}