{
  "type": "Feature",
  "properties": {
    "iso:country":"FR",
    "sg:address":"40, Av. Paul Doumer, 92502 Rueil Malmaison C\u00e9dex",
    "sg:orig_category":"Non-Classified Establishments",
    "sg:phone":"+33 1 47 32 11 22",
    "sg:province":"Centre",
    "wof:name":"Delcommune S.a.",
    "wof:placetype":"venue"
},
  "geometry": {"coordinates":[2.188896,48.883076],"type":"Point"}
}