{
  "type": "Feature",
  "properties": {
    "iso:country":"FR",
    "sg:address":"5 Rue De La Romillais Le Ch\u00eane Vert 35650 Le Rheu",
    "sg:city":"Le Rheu",
    "sg:classifiers":[
        {
            "category":"Professional",
            "type":"Services"
        }
    ],
    "sg:phone":"+33 2 99 14 80 80",
    "sg:postcode":"35650",
    "sg:province":"Bretagne",
    "sg:tags":[
        "-",
        "related",
        "road",
        "transport"
    ],
    "wof:name":"Nexia Transport",
    "wof:placetype":"venue"
},
  "geometry": {"coordinates":[-1.775371,48.080837],"type":"Point"}
}