{
  "type": "Feature",
  "properties": {
    "addr:full":"BP 31 62126 Wimille Nord Pas-de-Calais 62126",
    "addr:housenumber":"bp 31",
    "addr:postcode":"62126;62126",
    "iso:country":"FR",
    "sg:address":"BP 31 62126 Wimille",
    "sg:classifiers":[
        {
            "category":"Shopping",
            "type":"Retail Goods"
        }
    ],
    "sg:phone":"+33 3 21 33 17 17",
    "sg:postcode":"62126",
    "sg:province":"Nord Pas-de-Calais",
    "sg:tags":[
        "metallurgy",
        "finished",
        "-",
        "metalworking",
        "metallic"
    ],
    "wof:name":"Socofri Sa",
    "wof:placetype":"venue"
},
  "geometry": {"coordinates":[1.631271,50.764091],"type":"Point"}
}