{
  "type": "Feature",
  "properties": {
    "iso:country":"FR",
    "sg:address":"110 R G\u00e9o Lufbery 02300 Chauny",
    "sg:classifiers":[
        {
            "category":"Banks & Credit Unions",
            "subcategory":"Investment Brokerage",
            "type":"Services"
        }
    ],
    "sg:phone":"+33 3 23 39 11 11",
    "sg:province":"Picardie",
    "sg:tags":[
        "-",
        "transport",
        "related"
    ],
    "wof:name":"C D S Equipement Sarl",
    "wof:placetype":"venue"
},
  "geometry": {"coordinates":[3.239908,49.620258],"type":"Point"}
}