{
  "type": "Feature",
  "properties": {
    "iso:country":"FR",
    "sg:address":"8 Rue Malmedonne 78310 Maurepas",
    "sg:classifiers":[
        {
            "category":"Professional",
            "subcategory":"Engineering",
            "type":"Services"
        }
    ],
    "sg:phone":"+33 1 30 13 90 50",
    "sg:postcode":"78310",
    "sg:province":"Ile de France",
    "sg:tags":[
        "machine",
        "-",
        "mechanical"
    ],
    "wof:name":"Maurepas Techniques Sa",
    "wof:placetype":"venue"
},
  "geometry": {"coordinates":[1.935039,48.759636],"type":"Point"}
}