{
  "type": "Feature",
  "properties": {
    "addr:full":"2, All\u00e9e des Tullistes, 69130 Ecully Rhone-Alpes",
    "addr:housenumber":"2",
    "addr:postcode":"69130",
    "addr:street":"Alle\u0301E Des Tullistes",
    "iso:country":"FR",
    "sg:address":"2, All\u00e9e des Tullistes, 69130 Ecully",
    "sg:orig_category":"Non-Classified Establishments",
    "sg:phone":"+33 4 78 33 01 94",
    "sg:province":"Rhone-Alpes",
    "wof:name":"Scp Auberger Et Favre",
    "wof:placetype":"venue"
},
  "geometry": {"coordinates":[4.78027,45.775398],"type":"Point"}
}