{
  "type": "Feature",
  "properties": {
    "addr:full":"82 Avenue De Tivoli Le Bouscat Aquitaine 33110",
    "addr:housenumber":"82",
    "addr:postcode":"33110",
    "addr:street":"Avenue De Tivoli",
    "iso:country":"FR",
    "sg:address":"82 Avenue De Tivoli",
    "sg:city":"Le Bouscat",
    "sg:classifiers":[
        {
            "category":"Banks & Credit Unions",
            "subcategory":"Financial Services",
            "type":"Services"
        }
    ],
    "sg:phone":"+33 5 56 02 08 18",
    "sg:postcode":"33110",
    "sg:province":"Aquitaine",
    "sg:tags":[
        "banking",
        "finance",
        "insurance"
    ],
    "wof:name":"Lassus Georges Bernard",
    "wof:placetype":"venue"
},
  "geometry": {"coordinates":[-0.592892,44.860985],"type":"Point"}
}