{
  "type": "Feature",
  "properties": {
    "iso:country":"FR",
    "sg:address":"130, Av de Marseille, 26000 Valence",
    "sg:orig_category":"Non-Classified Establishments",
    "sg:phone":"+33 4 75 57 67 00",
    "sg:postcode":"26000",
    "sg:province":"Rhone-Alpes",
    "wof:name":"S.t.v. S.a. - Soci\u00e9t\u00e9 Thermique De Valence",
    "wof:placetype":"venue"
},
  "geometry": {"coordinates":[4.881903,44.900871],"type":"Point"}
}