{
  "type": "Feature",
  "properties": {
    "addr:full":"118, Bd Haussmann, 75008 Paris Ile de France",
    "addr:housenumber":"118",
    "addr:postcode":"75008",
    "addr:street":"Bd Haussmann",
    "iso:country":"FR",
    "sg:address":"118, Bd Haussmann, 75008 Paris",
    "sg:orig_category":"Unclassifiable Establishments",
    "sg:phone":"+33 1 43 12 37 80",
    "sg:province":"Ile de France",
    "wof:name":"Datops S.a.",
    "wof:placetype":"venue"
},
  "geometry": {"coordinates":[2.318798,48.875053],"type":"Point"}
}