{
  "type": "Feature",
  "properties": {
    "iso:country":"FR",
    "sg:address":"7, Av. Mar\u00e9chal de Lattre de Tassigny, 21200 Beaune",
    "sg:city":"Beaune",
    "sg:orig_category":"Unclassifiable Establishments",
    "sg:phone":"+33 3 80 24 83 24",
    "sg:postcode":"21200",
    "sg:province":"Bourgogne",
    "wof:name":"Greta",
    "wof:placetype":"venue"
},
  "geometry": {"coordinates":[4.851014,47.030453],"type":"Point"}
}