{
  "type": "Feature",
  "properties": {
    "addr:full":"42 Rue Ferdinand De Lesseps 59130 Lambersart Nord Pas-de-Calais 59130",
    "addr:housenumber":"42",
    "addr:postcode":"59130;59130",
    "addr:street":"Rue Ferdinand De Lesseps",
    "iso:country":"FR",
    "sg:address":"42 Rue Ferdinand De Lesseps 59130 Lambersart",
    "sg:classifiers":[
        {
            "category":"Manufacturing",
            "subcategory":"Tools & Machinery",
            "type":"Manufacturing & Wholesale Goods"
        }
    ],
    "sg:phone":"+33 3 20 00 12 50",
    "sg:postcode":"59130",
    "sg:province":"Nord Pas-de-Calais",
    "sg:tags":[
        "environment",
        "equipment",
        "-"
    ],
    "wof:name":"Technico",
    "wof:placetype":"venue"
},
  "geometry": {"coordinates":[3.01477,50.660244],"type":"Point"}
}