{
  "type": "Feature",
  "properties": {
    "addr:full":"13, Rue de la Grassinais, 35400 Saint Malo Saint-Malo Bretagne 35400",
    "addr:housenumber":"13",
    "addr:postcode":"35400;35400",
    "addr:street":"Rue De La Grassinais;Saint-Malo",
    "iso:country":"FR",
    "sg:address":"13, Rue de la Grassinais, 35400 Saint Malo",
    "sg:city":"Saint-Malo",
    "sg:orig_category":"Unclassifiable Establishments",
    "sg:phone":"+33 2 99 82 23 55",
    "sg:postcode":"35400",
    "sg:province":"Bretagne",
    "wof:name":"Bretagne Manutention",
    "wof:placetype":"venue"
},
  "geometry": {"coordinates":[-1.985916,48.620415],"type":"Point"}
}