{
  "type": "Feature",
  "properties": {
    "iso:country":"FR",
    "sg:address":"zi",
    "sg:city":"4 Termes 13400 Aubagne",
    "sg:classifiers":[
        {
            "category":"Shopping",
            "subcategory":"Crafts & Fabrics",
            "type":"Retail Goods"
        }
    ],
    "sg:phone":"+33 4 42 72 66 17",
    "sg:province":"Languedoc-Roussillon",
    "sg:tags":[
        "textile",
        "linen",
        "clothing"
    ],
    "wof:name":"Les Senteurs Du Midi",
    "wof:placetype":"venue"
},
  "geometry": {"coordinates":[5.5687,43.292141],"type":"Point"}
}