{
  "type": "Feature",
  "properties": {
    "iso:country":"FR",
    "sg:address":"6, Rue des Vignes, 28130 Bouglainval",
    "sg:city":"Bouglainval",
    "sg:orig_category":"Unclassifiable Establishments",
    "sg:phone":"+33 2 37 22 83 25",
    "sg:postcode":"28130",
    "sg:province":"Centre",
    "wof:name":"Biocade S.a.r.l.",
    "wof:placetype":"venue"
},
  "geometry": {"coordinates":[1.50463,48.568195],"type":"Point"}
}