{
  "type": "Feature",
  "properties": {
    "addr:full":"49, Rue de Ponthieu, 75008 Paris Ile de France 75008",
    "addr:housenumber":"49",
    "addr:postcode":"75008;75008",
    "addr:street":"Rue De Ponthieu",
    "iso:country":"FR",
    "sg:address":"49, Rue de Ponthieu, 75008 Paris",
    "sg:orig_category":"Non-Classified Establishments",
    "sg:phone":"+33 1 42 89 04 58",
    "sg:postcode":"75008",
    "sg:province":"Ile de France",
    "wof:name":"Coopsette S.a.r.l.",
    "wof:placetype":"venue"
},
  "geometry": {"coordinates":[2.306645,48.871529],"type":"Point"}
}