{
  "type": "Feature",
  "properties": {
    "iso:country":"FR",
    "sg:address":"20, Rue de la Tour, 67200 Strasbourg",
    "sg:city":"Strasbourg",
    "sg:orig_category":"Non-Classified Establishments",
    "sg:phone":"+33 3 88 30 13 88",
    "sg:postcode":"67200",
    "sg:province":"Alsace",
    "wof:name":"Munsch P\u00e8re Et Fils S.a.",
    "wof:placetype":"venue"
},
  "geometry": {"coordinates":[7.717591,48.578587],"type":"Point"}
}