{
  "type": "Feature",
  "properties": {
    "iso:country":"FR",
    "sg:address":"3 Rue Arago 91520 \u00c9gly",
    "sg:classifiers":[
        {
            "category":"Manufacturing",
            "subcategory":"Wood Products",
            "type":"Manufacturing & Wholesale Goods"
        }
    ],
    "sg:phone":"+33 1 60 83 07 90",
    "sg:province":"Ile de France",
    "sg:tags":[
        "furniture"
    ],
    "wof:name":"Petit-chanon & Associes",
    "wof:placetype":"venue"
},
  "geometry": {"coordinates":[2.205792,48.574482],"type":"Point"}
}