{
  "type": "Feature",
  "properties": {
    "addr:full":"Rue de la Fontaine Saint Christophe Cr\u00e9teil Ile de France 94000",
    "addr:postcode":"94000",
    "addr:street":"Rue De La Fontaine Saint Christophe",
    "iso:country":"FR",
    "sg:address":"Rue de la Fontaine Saint Christophe",
    "sg:city":"Cr\u00e9teil",
    "sg:orig_category":"Unclassifiable Establishments",
    "sg:phone":"+33 1 48 99 89 99",
    "sg:postcode":"94000",
    "sg:province":"Ile de France",
    "wof:name":"Kiloutou S.a.",
    "wof:placetype":"venue"
},
  "geometry": {"coordinates":[2.438575,48.780289],"type":"Point"}
}