{
  "type": "Feature",
  "properties": {
    "addr:full":"1, Rue Auguste Rolland, 57580 R\u00e9milly Lorraine",
    "addr:housenumber":"1",
    "addr:postcode":"57580",
    "addr:street":"Rue Auguste Rolland",
    "iso:country":"FR",
    "sg:address":"1, Rue Auguste Rolland, 57580 R\u00e9milly",
    "sg:orig_category":"Unclassifiable Establishments",
    "sg:phone":"+33 3 87 64 60 14",
    "sg:province":"Lorraine",
    "wof:name":"Reinert Daniel",
    "wof:placetype":"venue"
},
  "geometry": {"coordinates":[6.395111,49.013241],"type":"Point"}
}