{
  "type": "Feature",
  "properties": {
    "iso:country":"FR",
    "sg:address":"22, Av. des Vieux Moulins - ZI de Vovray, 74020 Annecy",
    "sg:city":"Annecy",
    "sg:orig_category":"Unclassifiable Establishments",
    "sg:phone":"+33 4 50 45 24 61",
    "sg:postcode":"74000",
    "sg:province":"Rhone-Alpes",
    "wof:name":"Rectifil Modular S.a.",
    "wof:placetype":"venue"
},
  "geometry": {"coordinates":[6.12845,45.89962],"type":"Point"}
}