{
  "type": "Feature",
  "properties": {
    "addr:full":"431, Av. Ambroise Croizat - ZI, 38920 Crolles Rhone-Alpes",
    "addr:postcode":"38920",
    "addr:street":"431 Av. Ambroise Croizat Zi",
    "iso:country":"FR",
    "sg:address":"431, Av. Ambroise Croizat - ZI, 38920 Crolles",
    "sg:orig_category":"Unclassifiable Establishments",
    "sg:phone":"+33 4 76 08 00 11",
    "sg:province":"Rhone-Alpes",
    "wof:name":"Aquazur S.a.",
    "wof:placetype":"venue"
},
  "geometry": {"coordinates":[5.884878,45.2854],"type":"Point"}
}