{
  "type": "Feature",
  "properties": {
    "iso:country":"FR",
    "sg:address":"155 Rue Henri V\u00e9niard 61100 St Georges Des Groseillers",
    "sg:city":"Br\u00e9el",
    "sg:classifiers":[
        {
            "category":"Shopping",
            "subcategory":"Clothing, Apparel, & Fashions",
            "type":"Retail Goods"
        }
    ],
    "sg:phone":"+33 2 33 65 00 22",
    "sg:postcode":"61100",
    "sg:province":"Basse Normandie",
    "sg:tags":[
        "textile",
        "clothing",
        "clothes"
    ],
    "wof:name":"Ets Desmonts Sarl",
    "wof:placetype":"venue"
},
  "geometry": {"coordinates":[-0.566138,48.758572],"type":"Point"}
}