{
  "type": "Feature",
  "properties": {
    "iso:country":"FR",
    "sg:address":"19 rue du G\u00e9n\u00e9ral Leclerc; Nangis; 77370",
    "sg:classifiers":[
        {
            "category":"Banks & Credit Unions",
            "subcategory":"Bank",
            "type":"Services"
        }
    ],
    "sg:phone":"+33 3364080261",
    "sg:postcode":"77370",
    "sg:province":"Ile de France",
    "wof:name":"Soci\u00e9t\u00e9 G\u00e9n\u00e9rale",
    "wof:placetype":"venue"
},
  "geometry": {"coordinates":[3.01231,48.556213],"type":"Point"}
}