{
  "type": "Feature",
  "properties": {
    "iso:country":"FR",
    "sg:address":"B.P. 28, 62113 Verquigneul^^Rte Nationale, 62113 Verquigneul",
    "sg:orig_category":"Non-Classified Establishments",
    "sg:phone":"+33 3 21 65 88 90",
    "sg:postcode":"62113",
    "sg:province":"Nord Pas-de-Calais",
    "wof:name":"Compal S.a.",
    "wof:placetype":"venue"
},
  "geometry": {"coordinates":[2.696664,50.500561],"type":"Point"}
}