{
  "type": "Feature",
  "properties": {
    "addr:full":"26, Rue Daubenton, 75005 Paris Ile de France 75005",
    "addr:housenumber":"26",
    "addr:postcode":"75005;75005",
    "addr:street":"Rue Daubenton",
    "iso:country":"FR",
    "sg:address":"26, Rue Daubenton, 75005 Paris",
    "sg:orig_category":"Non-Classified Establishments",
    "sg:phone":"+33 1 43 37 99 22",
    "sg:postcode":"75005",
    "sg:province":"Ile de France",
    "wof:name":"C.i.s. S.a.r.l. - Compagnie Internationale De Services",
    "wof:placetype":"venue"
},
  "geometry": {"coordinates":[2.353179,48.841354],"type":"Point"}
}