{
  "type": "Feature",
  "properties": {
    "iso:country":"FR",
    "sg:address":"B.P. 8, 70320 Aillevillers et Lyaumont^^19, Rue de la Gare, 70320 Aillevillers et Lyaumont",
    "sg:orig_category":"Non-Classified Establishments",
    "sg:phone":"+33 3 84 49 20 44",
    "sg:postcode":"70320",
    "sg:province":"Franche Comt\u00e9",
    "wof:name":"A.m.c.a. S.a. - Atelier De M\u00e9canique Et De Construction D'aillevillers",
    "wof:placetype":"venue"
},
  "geometry": {"coordinates":[6.336723,47.919704],"type":"Point"}
}