{
  "type": "Feature",
  "properties": {
    "addr:full":"15, Av. des Sabli\u00e8res, 33114 Le Barp Le Barp Aquitaine 33114",
    "addr:housenumber":"barp;barp",
    "addr:postcode":"33114;33114",
    "addr:street":"15 Av. Des Sablie\u0300Res",
    "iso:country":"FR",
    "sg:address":"15, Av. des Sabli\u00e8res, 33114 Le Barp",
    "sg:city":"Le Barp",
    "sg:orig_category":"Unclassifiable Establishments",
    "sg:phone":"+33 5 57 04 40 00",
    "sg:postcode":"33114",
    "sg:province":"Aquitaine",
    "wof:name":"C.e.a. / C.e.s.t.a. - Centre D'etudes Scientifiques Et Techniques D'aquitaine",
    "wof:placetype":"venue"
},
  "geometry": {"coordinates":[-0.779572,44.662842],"type":"Point"}
}