{
  "type": "Feature",
  "properties": {
    "addr:full":"rue Jean Foucault 81100 Castres Midi Pyr\u00e9n\u00e9es 81100",
    "addr:postcode":"81100;81100",
    "addr:street":"Rue Jean Foucault",
    "iso:country":"FR",
    "sg:address":"rue Jean Foucault 81100 Castres",
    "sg:classifiers":[
        {
            "category":"Building & Trades",
            "subcategory":"Electrical",
            "type":"Services"
        }
    ],
    "sg:phone":"+33 5 63 59 79 32",
    "sg:postcode":"81100",
    "sg:province":"Midi Pyr\u00e9n\u00e9es",
    "sg:tags":[
        "plants",
        "plant",
        "industrial",
        "buildings",
        "construction"
    ],
    "wof:name":"Benne Sa",
    "wof:placetype":"venue"
},
  "geometry": {"coordinates":[2.21056,43.587753],"type":"Point"}
}