{
  "type": "Feature",
  "properties": {
    "addr:full":"3 Rue Pierre Salmon 51500 Bezannes Champagne",
    "addr:housenumber":"3",
    "addr:postcode":"51500",
    "addr:street":"Rue Pierre Salmon",
    "iso:country":"FR",
    "sg:address":"3 Rue Pierre Salmon 51500 Bezannes",
    "sg:classifiers":[
        {
            "category":"Manufacturing",
            "subcategory":"Wood Products",
            "type":"Manufacturing & Wholesale Goods"
        }
    ],
    "sg:phone":"+33 3 26 36 55 88",
    "sg:province":"Champagne",
    "sg:tags":[
        "furniture"
    ],
    "wof:name":"Clignet Et Compagnie Sa",
    "wof:placetype":"venue"
},
  "geometry": {"coordinates":[3.989293,49.219234],"type":"Point"}
}