{
  "type": "Feature",
  "properties": {
    "addr:full":"Av. des B\u00e9thunes - ZI des B\u00e9thunes Saint Ouen l'Aum\u00f4ne Ile de France 95310",
    "addr:postcode":"95310",
    "addr:street":"Av. Des Be\u0301Thunes Zi Des Be\u0301Thunes Saint",
    "iso:country":"FR",
    "sg:address":"Av. des B\u00e9thunes - ZI des B\u00e9thunes",
    "sg:city":"Saint Ouen l'Aum\u00f4ne",
    "sg:orig_category":"Unclassifiable Establishments",
    "sg:phone":"+33 1 34 21 83 50",
    "sg:postcode":"95310",
    "sg:province":"Ile de France",
    "wof:name":"D.e.c. - Diffusion Electronique Aux Collectivit\u00e9s",
    "wof:placetype":"venue"
},
  "geometry": {"coordinates":[1.151225,47.715446],"type":"Point"}
}