{
  "type": "Feature",
  "properties": {
    "iso:country":"FR",
    "sg:address":"B.P. 287, 68005 Colmar C\u00e9dex^^2, Av Joseph Rey, 68000 Colmar",
    "sg:city":"Colmar",
    "sg:orig_category":"Non-Classified Establishments",
    "sg:phone":"+33 3 89 21 30 30",
    "sg:postcode":"68000",
    "sg:province":"Alsace",
    "wof:name":"Liebherr France S.a.",
    "wof:placetype":"venue"
},
  "geometry": {"coordinates":[7.363583,48.081985],"type":"Point"}
}