{
  "type": "Feature",
  "properties": {
    "addr:full":"5, Rue Gambetta, 93697 Pantin C\u00e9dex Midi Pyr\u00e9n\u00e9es",
    "addr:housenumber":"5",
    "addr:postcode":"93697",
    "addr:street":"Rue Gambetta",
    "iso:country":"FR",
    "sg:address":"5, Rue Gambetta, 93697 Pantin C\u00e9dex",
    "sg:orig_category":"Non-Classified Establishments",
    "sg:phone":"+33 1 48 43 91 52",
    "sg:province":"Midi Pyr\u00e9n\u00e9es",
    "wof:name":"R.m.t. Setar S.a.",
    "wof:placetype":"venue"
},
  "geometry": {"coordinates":[2.410797,48.888729],"type":"Point"}
}