{
  "type": "Feature",
  "properties": {
    "iso:country":"FR",
    "sg:address":"16 rue de la Ville; Paris; 75402",
    "sg:city":"Vill\u00e9",
    "sg:classifiers":[
        {
            "category":"Banks & Credit Unions",
            "subcategory":"Bank",
            "type":"Services"
        }
    ],
    "sg:phone":"+33 1 44 51 20 20",
    "sg:postcode":"67220",
    "sg:province":"Alsace",
    "wof:name":"Banque La Henin",
    "wof:placetype":"venue"
},
  "geometry": {"coordinates":[2.3111,48.873241],"type":"Point"}
}