{
  "type": "Feature",
  "properties": {
    "addr:full":"166 rue Saint-Fran\u00e7ois Xavier 33170 Gradignan Gradignan Aquitaine 33170",
    "addr:housenumber":"166",
    "addr:postcode":"33170;33170",
    "addr:street":"Rue Saint-Franc\u0327Ois Xavier",
    "iso:country":"FR",
    "sg:address":"166 rue Saint-Fran\u00e7ois Xavier 33170 Gradignan",
    "sg:city":"Gradignan",
    "sg:classifiers":[
        {
            "category":"Manufacturing",
            "subcategory":"Textiles",
            "type":"Manufacturing & Wholesale Goods"
        }
    ],
    "sg:phone":"+33 5 56 89 89 90",
    "sg:postcode":"33170",
    "sg:province":"Aquitaine",
    "sg:tags":[
        "natural"
    ],
    "wof:name":"Arsenal Sarl",
    "wof:placetype":"venue"
},
  "geometry": {"coordinates":[-0.593189,44.777119],"type":"Point"}
}