{
  "type": "Feature",
  "properties": {
    "iso:country":"FR",
    "sg:address":"ZI de Feline",
    "sg:city":"Carcassonne",
    "sg:orig_category":"Unclassifiable Establishments",
    "sg:phone":"+33 4 68 72 67 89",
    "sg:postcode":"11000",
    "sg:province":"Languedoc-Roussillon",
    "wof:name":"Caroline De Beaulieu C.i.r.a. S.a.r.l. - Consultant International Pour Les R\u00e9gions D'appelation",
    "wof:placetype":"venue"
},
  "geometry": {"coordinates":[2.358405,43.21183],"type":"Point"}
}