{
  "type": "Feature",
  "properties": {
    "addr:full":"261 Rue Victor Hugo 59116 Houplines Nord Pas-de-Calais 59116",
    "addr:housenumber":"261",
    "addr:postcode":"59116;59116",
    "addr:street":"Rue Victor Hugo",
    "iso:country":"FR",
    "sg:address":"261 Rue Victor Hugo 59116 Houplines",
    "sg:classifiers":[
        {
            "category":"Shopping",
            "subcategory":"Crafts & Fabrics",
            "type":"Retail Goods"
        }
    ],
    "sg:phone":"+33 3 20 77 01 74",
    "sg:postcode":"59116",
    "sg:province":"Nord Pas-de-Calais",
    "sg:tags":[
        "textile",
        "linen",
        "clothing"
    ],
    "wof:name":"Acquart Confection Sarl",
    "wof:placetype":"venue"
},
  "geometry": {"coordinates":[2.89838,50.687328],"type":"Point"}
}