{
  "type": "Feature",
  "properties": {
    "addr:full":"2 All Henri Laborde 79200 Parthenay Poitou-Charentes",
    "addr:housenumber":"2",
    "addr:postcode":"79200",
    "addr:street":"All Henri Laborde",
    "iso:country":"FR",
    "sg:address":"2 All Henri Laborde 79200 Parthenay",
    "sg:classifiers":[
        {
            "category":"Professional",
            "subcategory":"Business Services",
            "type":"Services"
        }
    ],
    "sg:phone":"+33 5 49 94 64 82",
    "sg:province":"Poitou-Charentes",
    "sg:tags":[
        "training",
        "advice"
    ],
    "wof:name":"Ass Formation De Conseil Et Orientation",
    "wof:placetype":"venue"
},
  "geometry": {"coordinates":[-0.249279,46.643002],"type":"Point"}
}