{
  "type": "Feature",
  "properties": {
    "iso:country":"FR",
    "sg:address":"5, Rue Notre Dame, 84100 Orange",
    "sg:orig_category":"Non-Classified Establishments",
    "sg:phone":"+33 4 90 34 27 56",
    "sg:province":"Centre",
    "wof:name":"Comareg S.a.",
    "wof:placetype":"venue"
},
  "geometry": {"coordinates":[4.807179,44.137875],"type":"Point"}
}