{
  "type": "Feature",
  "properties": {
    "addr:full":"269 Fbg Croncels 10080 Troyes Cedex Auvergne",
    "addr:housenumber":"269",
    "addr:postcode":"10080;cedex",
    "addr:street":"Fbg Croncels",
    "iso:country":"FR",
    "sg:address":"269 Fbg Croncels 10080 Troyes Cedex",
    "sg:classifiers":[
        {
            "category":"Banks & Credit Unions",
            "subcategory":"Financial Services",
            "type":"Services"
        }
    ],
    "sg:phone":"+33 3 25 71 40 00",
    "sg:province":"Auvergne",
    "sg:tags":[
        "banking",
        "insurance",
        "institution",
        "finance"
    ],
    "wof:name":"Credit Agricole",
    "wof:placetype":"venue"
},
  "geometry": {"coordinates":[4.07529,48.301182],"type":"Point"}
}