{
  "type": "Feature",
  "properties": {
    "iso:country":"FR",
    "sg:address":"6, Av du Mal Joffre, 57000 Metz",
    "sg:orig_category":"Non-Classified Establishments",
    "sg:phone":"+33 3 87 63 16 16",
    "sg:postcode":"57000",
    "sg:province":"Lorraine",
    "wof:name":"Adia Travail Temporaire",
    "wof:placetype":"venue"
},
  "geometry": {"coordinates":[6.171841,49.111935],"type":"Point"}
}