{
  "type": "Feature",
  "properties": {
    "addr:full":"62 ave de la R\u00e9publique; Montchanin; 71210 Montchanin Bourgogne 71210",
    "addr:postcode":"71210;71210",
    "addr:street":"62 Ave De La Re\u0301Publique;Bourgogne",
    "iso:country":"FR",
    "sg:address":"62 ave de la R\u00e9publique; Montchanin; 71210",
    "sg:city":"Montchanin",
    "sg:classifiers":[
        {
            "category":"Banks & Credit Unions",
            "subcategory":"Bank",
            "type":"Services"
        }
    ],
    "sg:phone":"+33 3385781154",
    "sg:postcode":"71210",
    "sg:province":"Bourgogne",
    "wof:name":"Soci\u00e9t\u00e9 G\u00e9n\u00e9rale",
    "wof:placetype":"venue"
},
  "geometry": {"coordinates":[4.472079,46.743038],"type":"Point"}
}