{
  "type": "Feature",
  "properties": {
    "iso:country":"FR",
    "sg:address":"11, Place de la Paix, 41200 Romorantin Lanthenay",
    "sg:city":"Villefranche-sur-Cher",
    "sg:orig_category":"Unclassifiable Establishments",
    "sg:phone":"+33 2 54 76 01 66",
    "sg:postcode":"41200",
    "sg:province":"Centre",
    "wof:name":"D\u00e9m\u00e9nagements Maurice Cr\u00e9pau S.a.r.l.",
    "wof:placetype":"venue"
},
  "geometry": {"coordinates":[1.742839,47.359138],"type":"Point"}
}