{
  "type": "Feature",
  "properties": {
    "addr:full":"15 Chem De La Glaci\u00e8re 31200 Toulouse Midi Pyr\u00e9n\u00e9es",
    "addr:housenumber":"15",
    "addr:postcode":"31200",
    "addr:street":"Chem De La Glacie\u0300Re",
    "iso:country":"FR",
    "sg:address":"15 Chem De La Glaci\u00e8re 31200 Toulouse",
    "sg:classifiers":[
        {
            "category":"Home & Garden",
            "subcategory":"Furniture",
            "type":"Retail Goods"
        }
    ],
    "sg:phone":"+33 5 61 47 93 96",
    "sg:province":"Midi Pyr\u00e9n\u00e9es",
    "sg:tags":[
        "wood"
    ],
    "wof:name":"Ste Panofrance",
    "wof:placetype":"venue"
},
  "geometry": {"coordinates":[1.418924,43.644829],"type":"Point"}
}