{
  "type": "Feature",
  "properties": {
    "iso:country":"FR",
    "sg:address":"32 Av Albert 1er 92500 Rueil Malmaison",
    "sg:classifiers":[
        {
            "category":"Manufacturing",
            "subcategory":"Rubber & Plastics",
            "type":"Manufacturing & Wholesale Goods"
        }
    ],
    "sg:phone":"+33 1 47 14 32 00",
    "sg:postcode":"92500",
    "sg:province":"Ile de France",
    "sg:tags":[
        "metallurgy",
        "finished",
        "-",
        "metalworking",
        "metallic"
    ],
    "wof:name":"Asco Joucomatic Sa",
    "wof:placetype":"venue"
},
  "geometry": {"coordinates":[2.177544,48.882202],"type":"Point"}
}