{
  "type": "Feature",
  "properties": {
    "iso:country":"FR",
    "sg:address":"2, Av. de Bourgogne - Zone Agricole les B\u00e9thunes, 95310 Saint Ouen l'Aum\u00f4ne",
    "sg:orig_category":"Unclassifiable Establishments",
    "sg:phone":"+33 1 34 32 34 00",
    "sg:province":"Ile de France",
    "wof:name":"P.d.i. S.a. - Produit Diffusion Des Imprimeries",
    "wof:placetype":"venue"
},
  "geometry": {"coordinates":[0.490902,48.605492],"type":"Point"}
}