{
  "type": "Feature",
  "properties": {
    "addr:full":"B.P. 201, 78702 Conflans Sainte Honorine C\u00e9dex^^3, Rue L\u00e9onard de Vinci - ZA des Boutries, 78700 Con Ile de France",
    "addr:housenumber":"b.p. 201",
    "addr:postcode":"78702;78700",
    "addr:street":"Rue Le\u0301Onard De Vinci Za Des Boutries;De",
    "iso:country":"FR",
    "sg:address":"B.P. 201, 78702 Conflans Sainte Honorine C\u00e9dex^^3, Rue L\u00e9onard de Vinci - ZA des Boutries, 78700 Con",
    "sg:orig_category":"Non-Classified Establishments",
    "sg:phone":"+33 1 30 37 63 75",
    "sg:province":"Ile de France",
    "wof:name":"M\u00e9caprob Engineering S.a.r.l.",
    "wof:placetype":"venue"
},
  "geometry": {"coordinates":[2.093755,48.99337],"type":"Point"}
}