{
  "type": "Feature",
  "properties": {
    "addr:full":"16 rue Velouterie; Avignon; 84000 Basse Normandie",
    "addr:housenumber":"16",
    "addr:postcode":"84000",
    "addr:street":"Rue Velouterie",
    "iso:country":"FR",
    "sg:address":"16 rue Velouterie; Avignon; 84000",
    "sg:classifiers":[
        {
            "category":"Banks & Credit Unions",
            "subcategory":"Bank",
            "type":"Services"
        }
    ],
    "sg:phone":"+33 3390826606",
    "sg:province":"Basse Normandie",
    "wof:name":"Sovac",
    "wof:placetype":"venue"
},
  "geometry": {"coordinates":[4.799199,43.945213],"type":"Point"}
}