{
  "type": "Feature",
  "properties": {
    "iso:country":"FR",
    "sg:address":"B.P. 6, 69470 Cours la Ville C\u00e9dex^^La Rivi\u00e8re, 69470 Cours la Ville",
    "sg:orig_category":"Non-Classified Establishments",
    "sg:phone":"+33 4 74 89 74 14",
    "sg:postcode":"69470",
    "sg:province":"Rhone-Alpes",
    "wof:name":"Etablissement Henri Moncorg\u00e9 S.a.",
    "wof:placetype":"venue"
},
  "geometry": {"coordinates":[4.321375,46.100021],"type":"Point"}
}