{
  "type": "Feature",
  "properties": {
    "addr:full":"6, Rue Curnonsky, 75017 Paris Ile de France",
    "addr:housenumber":"6",
    "addr:postcode":"75017",
    "addr:street":"Rue Curnonsky",
    "iso:country":"FR",
    "sg:address":"6, Rue Curnonsky, 75017 Paris",
    "sg:orig_category":"Non-Classified Establishments",
    "sg:phone":"+33 1 47 54 28 97",
    "sg:province":"Ile de France",
    "wof:name":"G.d.f. International S.a. -gaz De France International",
    "wof:placetype":"venue"
},
  "geometry": {"coordinates":[2.318885,48.883629],"type":"Point"}
}