{
  "type": "Feature",
  "properties": {
    "addr:full":"689 avenue de Chamb\u00e9ry 73230 St Alban Leysse Rhone-Alpes 73230",
    "addr:housenumber":"689",
    "addr:postcode":"73230;73230",
    "addr:street":"Avenue De Chambe\u0301Ry;Rhone-Alpes",
    "iso:country":"FR",
    "sg:address":"689 avenue de Chamb\u00e9ry 73230 St Alban Leysse",
    "sg:classifiers":[
        {
            "category":"Government",
            "subcategory":"Fire Station",
            "type":"Public Place"
        }
    ],
    "sg:phone":"+33 4 79 75 66 92",
    "sg:postcode":"73230",
    "sg:province":"Rhone-Alpes",
    "sg:tags":[
        "extinguishing",
        "accessory"
    ],
    "wof:name":"Ste Indust Materiels Incendie Securite Sa",
    "wof:placetype":"venue"
},
  "geometry": {"coordinates":[5.95805,45.573181],"type":"Point"}
}