{
  "type": "Feature",
  "properties": {
    "addr:full":"chemin de Noyarey 38700 La Tronche Rhone-Alpes 38700",
    "addr:postcode":"38700;38700",
    "addr:street":"Chemin De Noyarey",
    "iso:country":"FR",
    "sg:address":"chemin de Noyarey 38700 La Tronche",
    "sg:classifiers":[
        {
            "category":"Banks & Credit Unions",
            "subcategory":"Investment Brokerage",
            "type":"Services"
        }
    ],
    "sg:phone":"+33 4 38 37 21 21",
    "sg:postcode":"38700",
    "sg:province":"Rhone-Alpes",
    "sg:tags":[
        "processing",
        "data",
        "system"
    ],
    "wof:name":"Ordinateurs Peripheriques Services Sa",
    "wof:placetype":"venue"
},
  "geometry": {"coordinates":[5.738707,45.209969],"type":"Point"}
}