{
  "type": "Feature",
  "properties": {
    "iso:country":"FR",
    "sg:address":"6, Rue Yves Farge, 78210 Saint Cyr l'Ecole",
    "sg:orig_category":"Non-Classified Establishments",
    "sg:phone":"+33 1 30 45 05 53",
    "sg:province":"Ile de France",
    "wof:name":"Fusibet Jean-pierre",
    "wof:placetype":"venue"
},
  "geometry": {"coordinates":[-98.461052,29.39657],"type":"Point"}
}