{
  "type": "Feature",
  "properties": {
    "iso:country":"FR",
    "sg:address":"Chemin du Gu\u00e9 de la Comtesse",
    "sg:city":"Rethel",
    "sg:orig_category":"Unclassifiable Establishments",
    "sg:phone":"+33 3 24 39 50 10",
    "sg:postcode":"08300",
    "sg:province":"Champagne",
    "wof:name":"Vigalarden S.a.",
    "wof:placetype":"venue"
},
  "geometry": {"coordinates":[4.378369,49.504581],"type":"Point"}
}