{
  "type": "Feature",
  "properties": {
    "addr:full":"102 Rue Du Cherche Midi 75006 Paris Ile de France 75006",
    "addr:housenumber":"102",
    "addr:postcode":"75006;75006",
    "addr:street":"Rue Du Cherche Midi",
    "iso:country":"FR",
    "sg:address":"102 Rue Du Cherche Midi 75006 Paris",
    "sg:orig_category":"Miscellaneous Products",
    "sg:phone":"+33 1 34 62 80 81",
    "sg:postcode":"75006",
    "sg:province":"Ile de France",
    "wof:name":"Unlimited Trading International",
    "wof:placetype":"venue"
},
  "geometry": {"coordinates":[2.321543,48.847103],"type":"Point"}
}