{
  "type": "Feature",
  "properties": {
    "addr:full":"25, Av. du G\u00e9n\u00e9ral de Castelnau, 33140 Villenave d'Ornon Cadaujac Aquitaine 33140",
    "addr:postcode":"33140;33140",
    "addr:street":"25 Av. Du Ge\u0301Ne\u0301Ral De Castelnau",
    "iso:country":"FR",
    "sg:address":"25, Av. du G\u00e9n\u00e9ral de Castelnau, 33140 Villenave d'Ornon",
    "sg:city":"Cadaujac",
    "sg:orig_category":"Unclassifiable Establishments",
    "sg:phone":"+33 5 57 99 01 70",
    "sg:postcode":"33140",
    "sg:province":"Aquitaine",
    "wof:name":"Web Report S.a.r.l.",
    "wof:placetype":"venue"
},
  "geometry": {"coordinates":[-0.545677,44.77047],"type":"Point"}
}