{
  "type": "Feature",
  "properties": {
    "addr:full":"9, Rue Saint Exup\u00e9ry, 67500 Haguenau Haguenau Alsace 67500",
    "addr:housenumber":"9",
    "addr:postcode":"67500;67500",
    "addr:street":"Rue Saint Exupe\u0301Ry",
    "iso:country":"FR",
    "sg:address":"9, Rue Saint Exup\u00e9ry, 67500 Haguenau",
    "sg:city":"Haguenau",
    "sg:orig_category":"Unclassifiable Establishments",
    "sg:phone":"+33 3 88 05 43 00",
    "sg:postcode":"67500",
    "sg:province":"Alsace",
    "wof:name":"Distria Schoettl\u00e9 S.a.",
    "wof:placetype":"venue"
},
  "geometry": {"coordinates":[7.807757,48.799423],"type":"Point"}
}