{
  "type": "Feature",
  "properties": {
    "addr:full":"4, Rue de l'Arsenal - ZAC des Gravanches, 63100 Clermont Ferrand Clermont-Ferrand Auvergne 63100",
    "addr:housenumber":"4",
    "addr:postcode":"63100;63100",
    "addr:street":"Rue De L'Arsenal Zac Des Gravanches",
    "iso:country":"FR",
    "sg:address":"4, Rue de l'Arsenal - ZAC des Gravanches, 63100 Clermont Ferrand",
    "sg:city":"Clermont-Ferrand",
    "sg:orig_category":"Unclassifiable Establishments",
    "sg:phone":"+33 4 73 14 14 14",
    "sg:postcode":"63100",
    "sg:province":"Auvergne",
    "wof:name":"J.l.b. Technologies S.a.",
    "wof:placetype":"venue"
},
  "geometry": {"coordinates":[3.10785,45.796341],"type":"Point"}
}