{
  "type": "Feature",
  "properties": {
    "addr:full":"ZI de Laiz Pont de Veyle Rhone-Alpes 01290",
    "addr:postcode":"01290",
    "addr:street":"Zi De Laiz Pont De Veyle Rhone-Alpes",
    "iso:country":"FR",
    "sg:address":"ZI de Laiz",
    "sg:city":"Pont de Veyle",
    "sg:orig_category":"Unclassifiable Establishments",
    "sg:phone":"+33 3 85 23 94 20",
    "sg:postcode":"01290",
    "sg:province":"Rhone-Alpes",
    "wof:name":"C.i.p.a.b. S.a.r.l. -constructions Inoxydables Pascal Badet",
    "wof:placetype":"venue"
},
  "geometry": {"coordinates":[4.88894,46.265121],"type":"Point"}
}