{
  "type": "Feature",
  "properties": {
    "iso:country":"FR",
    "sg:address":"11, Av. Joliot Curie - Z.I. Bois de l'Epine, 91130 Ris Orangis",
    "sg:orig_category":"Unclassifiable Establishments",
    "sg:phone":"+33 1 69 77 89 89",
    "sg:province":"Ile de France",
    "wof:name":"Cibox Distribution S.a.",
    "wof:placetype":"venue"
},
  "geometry": {"coordinates":[2.41432,48.656807],"type":"Point"}
}