{
  "type": "Feature",
  "properties": {
    "iso:country":"FR",
    "sg:address":"19, Rue du Fort, 92120 Montrouge",
    "sg:orig_category":"Non-Classified Establishments",
    "sg:phone":"+33 1 42 31 05 50",
    "sg:postcode":"92120",
    "sg:province":"Ile de France",
    "wof:name":"C.g.e. Distribution S.a.",
    "wof:placetype":"venue"
},
  "geometry": {"coordinates":[2.323419,48.811153],"type":"Point"}
}