{
  "type": "Feature",
  "properties": {
    "iso:country":"FR",
    "sg:address":"37 Boulevard Jeanne D Arc 93100 Montreuil",
    "sg:classifiers":[
        {
            "category":"Manufacturing",
            "subcategory":"Textiles",
            "type":"Manufacturing & Wholesale Goods"
        }
    ],
    "sg:phone":"+33 1 48 18 14 04",
    "sg:postcode":"93100",
    "sg:province":"Ile de France",
    "sg:tags":[
        "clothing",
        "accessory"
    ],
    "wof:name":"Societe Nationale D'extrusion Et D'injection Des Plastiques (sneip)",
    "wof:placetype":"venue"
},
  "geometry": {"coordinates":[2.445126,48.853905],"type":"Point"}
}