{
  "type": "Feature",
  "properties": {
    "iso:country":"FR",
    "sg:address":"La Haie Gautrais",
    "sg:city":"Bruz",
    "sg:orig_category":"Unclassifiable Establishments",
    "sg:phone":"+33 2 99 05 08 08",
    "sg:postcode":"35170",
    "sg:province":"Bretagne",
    "wof:name":"Dubois Pierson S.a.",
    "wof:placetype":"venue"
},
  "geometry": {"coordinates":[-1.732339,48.054527],"type":"Point"}
}