{
  "type": "Feature",
  "properties": {
    "addr:full":"2, Rue Louis Aragon, 91130 Ris Orangis Ile de France 91130",
    "addr:housenumber":"2",
    "addr:postcode":"91130;91130",
    "addr:street":"Rue Louis Aragon",
    "iso:country":"FR",
    "sg:address":"2, Rue Louis Aragon, 91130 Ris Orangis",
    "sg:orig_category":"Non-Classified Establishments",
    "sg:phone":"+33 1 69 02 58 00",
    "sg:postcode":"91130",
    "sg:province":"Ile de France",
    "wof:name":"A.f.p.a. - Association National Formation Professionnel Adultes",
    "wof:placetype":"venue"
},
  "geometry": {"coordinates":[2.409515,48.64957],"type":"Point"}
}