{
  "type": "Feature",
  "properties": {
    "addr:full":"B.P. 104, 29411 Landerneau C\u00e9dex^^ZI de Lanrinou, 29800 Landerneau Landerneau Bretagne 29800",
    "addr:housenumber":"b.p. 104",
    "addr:postcode":"29411;29800;29800",
    "iso:country":"FR",
    "sg:address":"B.P. 104, 29411 Landerneau C\u00e9dex^^ZI de Lanrinou, 29800 Landerneau",
    "sg:city":"Landerneau",
    "sg:orig_category":"Non-Classified Establishments",
    "sg:phone":"+33 2 98 85 46 46",
    "sg:postcode":"29800",
    "sg:province":"Bretagne",
    "wof:name":"Gel Ouest S.a.",
    "wof:placetype":"venue"
},
  "geometry": {"coordinates":[-4.228497,48.400295],"type":"Point"}
}