{
  "type": "Feature",
  "properties": {
    "iso:country":"FR",
    "sg:address":"61250 Hauterive",
    "sg:city":"Hauterive",
    "sg:orig_category":"Non-Classified Establishments",
    "sg:phone":"+33 2 33 27 10 67",
    "sg:postcode":"61250",
    "sg:province":"Basse Normandie",
    "wof:name":"Eurovia Normandie S.n.c.",
    "wof:placetype":"venue"
},
  "geometry": {"coordinates":[0.200532,48.477402],"type":"Point"}
}