{
  "type": "Feature",
  "properties": {
    "addr:full":"36 Route Du Bassin Numero 6 92230 Gennevilliers Ile de France 92230",
    "addr:housenumber":"36;6",
    "addr:postcode":"92230;ile;92230",
    "addr:street":"Route Du Bassin Numero;France",
    "iso:country":"FR",
    "sg:address":"36 Route Du Bassin Numero 6 92230 Gennevilliers",
    "sg:classifiers":[
        {
            "category":"Utilities",
            "type":"Services"
        }
    ],
    "sg:phone":"+33 1 47 98 85 49",
    "sg:postcode":"92230",
    "sg:province":"Ile de France",
    "sg:tags":[
        "raw",
        "energy",
        "material"
    ],
    "wof:name":"France Charbons",
    "wof:placetype":"venue"
},
  "geometry": {"coordinates":[2.285391,48.94899],"type":"Point"}
}