{
  "type": "Feature",
  "properties": {
    "iso:country":"FR",
    "sg:address":"7, Rue El\u00e9onore Daubr\u00e9e, 50200 Coutances",
    "sg:city":"Coutances",
    "sg:orig_category":"Non-Classified Establishments",
    "sg:phone":"+33 2 33 19 11 20",
    "sg:postcode":"50200",
    "sg:province":"Basse Normandie",
    "wof:name":"Jade S.a.r.l.",
    "wof:placetype":"venue"
},
  "geometry": {"coordinates":[-1.433329,49.00985],"type":"Point"}
}