{
  "type": "Feature",
  "properties": {
    "addr:full":"10, Rue du Comte Bernadotte, 56100 Lorient Lorient Bretagne 56100",
    "addr:housenumber":"10",
    "addr:postcode":"56100;56100",
    "addr:street":"Rue Du Comte Bernadotte",
    "iso:country":"FR",
    "sg:address":"10, Rue du Comte Bernadotte, 56100 Lorient",
    "sg:city":"Lorient",
    "sg:orig_category":"Non-Classified Establishments",
    "sg:phone":"+33 2 97 37 15 55",
    "sg:postcode":"56100",
    "sg:province":"Bretagne",
    "wof:name":"Kolorian S.a.",
    "wof:placetype":"venue"
},
  "geometry": {"coordinates":[-3.360754,47.732925],"type":"Point"}
}