{
  "type": "Feature",
  "properties": {
    "addr:full":"14, Rue du Plessis, 44600 Saint Nazaire Pays de Loire",
    "addr:housenumber":"14",
    "addr:postcode":"44600",
    "addr:street":"Rue Du Plessis;Nazaire",
    "iso:country":"FR",
    "sg:address":"14, Rue du Plessis, 44600 Saint Nazaire",
    "sg:orig_category":"Unclassifiable Establishments",
    "sg:phone":"+33 2 40 01 96 56",
    "sg:province":"Pays de Loire",
    "wof:name":"Rineau",
    "wof:placetype":"venue"
},
  "geometry": {"coordinates":[-2.224525,47.284184],"type":"Point"}
}