{
  "type": "Feature",
  "properties": {
    "addr:full":"31 Rue Du Colonel Pierre Avia 75725 Paris Cedex 15 Languedoc-Roussillon",
    "addr:housenumber":"31",
    "addr:postcode":"75725;15",
    "addr:street":"Rue Du Colonel Pierre Avia",
    "iso:country":"FR",
    "sg:address":"31 Rue Du Colonel Pierre Avia 75725 Paris Cedex 15",
    "sg:classifiers":[
        {
            "category":"Travel",
            "subcategory":"Hotels & Motels",
            "type":"Entertainment"
        }
    ],
    "sg:phone":"+33 1 41 33 70 10",
    "sg:province":"Languedoc-Roussillon",
    "sg:tags":[
        "hotels",
        "business",
        "restaurant"
    ],
    "wof:name":"Groupe Accor",
    "wof:placetype":"venue"
},
  "geometry": {"coordinates":[2.29386,48.841679],"type":"Point"}
}