{
  "type": "Feature",
  "properties": {
    "iso:country":"FR",
    "sg:address":"1044, Rue de Bresse, 01330 Villars les Dombes",
    "sg:orig_category":"Unclassifiable Establishments",
    "sg:phone":"+33 4 74 98 03 44",
    "sg:postcode":"01330",
    "sg:province":"Rhone-Alpes",
    "wof:name":"Entreprise Geoffray Patrick",
    "wof:placetype":"venue"
},
  "geometry": {"coordinates":[5.028107,46.004658],"type":"Point"}
}