{
  "type": "Feature",
  "properties": {
    "addr:full":"Av des Lions Sainte Marie des Champs Haute Normandie 76190",
    "addr:postcode":"76190",
    "addr:street":"Av Des Lions",
    "iso:country":"FR",
    "sg:address":"Av des Lions",
    "sg:city":"Sainte Marie des Champs",
    "sg:orig_category":"Unclassifiable Establishments",
    "sg:phone":"+33 2 35 95 72 72",
    "sg:postcode":"76190",
    "sg:province":"Haute Normandie",
    "wof:name":"Finordis Vatine S.a.",
    "wof:placetype":"venue"
},
  "geometry": {"coordinates":[0.781966,49.622719],"type":"Point"}
}