{
  "type": "Feature",
  "properties": {
    "addr:full":"B.P. 435, 53104 Mayenne C\u00e9dex^^Impasse Edouard Branly - Z.I. de la Peyennerie, 53100 Mayenne Pays de Loire",
    "addr:housenumber":"b.p. 435",
    "addr:postcode":"53104;53100 mayenne",
    "addr:street":"Edouard Branly Z.I. De La Peyennerie",
    "iso:country":"FR",
    "sg:address":"B.P. 435, 53104 Mayenne C\u00e9dex^^Impasse Edouard Branly - Z.I. de la Peyennerie, 53100 Mayenne",
    "sg:orig_category":"Non-Classified Establishments",
    "sg:phone":"+33 2 43 04 04 04",
    "sg:province":"Pays de Loire",
    "wof:name":"T.p.a.m. S.n.c.",
    "wof:placetype":"venue"
},
  "geometry": {"coordinates":[-0.655999,48.262119],"type":"Point"}
}