{
  "type": "Feature",
  "properties": {
    "addr:full":"ZAL du petit Sailly Sailly Labourse Nord Pas-de-Calais 62113",
    "addr:postcode":"62113",
    "addr:street":"Du Petit Sailly",
    "iso:country":"FR",
    "sg:address":"ZAL du petit Sailly",
    "sg:city":"Sailly Labourse",
    "sg:orig_category":"Unclassifiable Establishments",
    "sg:phone":"+33 3 21 65 45 22",
    "sg:postcode":"62113",
    "sg:province":"Nord Pas-de-Calais",
    "wof:name":"S.t.a.p.i. S.a.r.l.",
    "wof:placetype":"venue"
},
  "geometry": {"coordinates":[2.723517,50.512684],"type":"Point"}
}