{
  "type": "Feature",
  "properties": {
    "iso:country":"FR",
    "sg:address":"119 Av Louis Roche 92231 Gennevilliers Cedex",
    "sg:city":"Gennevilliers",
    "sg:classifiers":[
        {
            "category":"Manufacturing",
            "subcategory":"Metals",
            "type":"Manufacturing & Wholesale Goods"
        }
    ],
    "sg:phone":"+33 1 46 88 15 00",
    "sg:postcode":"92230",
    "sg:province":"Ile de France",
    "sg:tags":[
        "metallurgy",
        "steel",
        "metalworking"
    ],
    "wof:name":"Delachaux Sa",
    "wof:placetype":"venue"
},
  "geometry": {"coordinates":[2.315154,48.926403],"type":"Point"}
}