{
  "type": "Feature",
  "properties": {
    "iso:country":"FR",
    "sg:address":"1, Rue de la Mare Blanche - Z.I. de Noisiel, 77186 Noisiel",
    "sg:orig_category":"Unclassifiable Establishments",
    "sg:phone":"+33 1 60 05 92 12",
    "sg:province":"Ile de France",
    "wof:name":"Norgren H\u00e9rion S.a.",
    "wof:placetype":"venue"
},
  "geometry": {"coordinates":[2.628145,48.854988],"type":"Point"}
}