{
  "type": "Feature",
  "properties": {
    "addr:full":"Lieu dit Regat Long 47300 STE COLOMBE DE VILLENEUVE Villeneuve-sur-Lot Aquitaine 47300",
    "addr:postcode":"47300;47300",
    "addr:street":"Lieu Dit Regat Long",
    "iso:country":"FR",
    "sg:address":"Lieu dit Regat Long 47300 STE COLOMBE DE VILLENEUVE",
    "sg:city":"Villeneuve-sur-Lot",
    "sg:classifiers":[
        {
            "category":"Shopping",
            "subcategory":"Pets & Pet Supplies",
            "type":"Retail Goods"
        }
    ],
    "sg:phone":"+33 5 53 36 36 36",
    "sg:postcode":"47300",
    "sg:province":"Aquitaine",
    "sg:tags":[
        "food",
        "dog",
        "cat"
    ],
    "wof:name":"V.p.f.sa",
    "wof:placetype":"venue"
},
  "geometry": {"coordinates":[0.65937,44.359684],"type":"Point"}
}