{
  "type": "Feature",
  "properties": {
    "addr:full":"10, Av. de Contades, 49000 Angers Pays de Loire",
    "addr:postcode":"49000",
    "addr:street":"10 Av. De Contades",
    "iso:country":"FR",
    "sg:address":"10, Av. de Contades, 49000 Angers",
    "sg:orig_category":"Unclassifiable Establishments",
    "sg:phone":"+33 2 41 88 99 07",
    "sg:province":"Pays de Loire",
    "wof:name":"Strat\u00e9gic S.a.",
    "wof:placetype":"venue"
},
  "geometry": {"coordinates":[-0.554184,47.463871],"type":"Point"}
}