{
  "type": "Feature",
  "properties": {
    "addr:full":"25, Rue Centrale, 73000 Bassens Rhone-Alpes",
    "addr:housenumber":"25",
    "addr:postcode":"73000",
    "addr:street":"Rue Centrale",
    "iso:country":"FR",
    "sg:address":"25, Rue Centrale, 73000 Bassens",
    "sg:orig_category":"Unclassifiable Establishments",
    "sg:phone":"+33 4 79 33 33 34",
    "sg:province":"Rhone-Alpes",
    "wof:name":"Etablissements Horticoles Vuillermet E.a.r.l.",
    "wof:placetype":"venue"
},
  "geometry": {"coordinates":[5.944609,45.57497],"type":"Point"}
}