{
  "type": "Feature",
  "properties": {
    "addr:full":"La Brindossi\u00e8re 61600 Magny le D\u00e9sert Beauvain Basse Normandie 61600",
    "addr:postcode":"61600;le;61600",
    "addr:street":"Magny;Basse",
    "iso:country":"FR",
    "sg:address":"La Brindossi\u00e8re 61600 Magny le D\u00e9sert",
    "sg:city":"Beauvain",
    "sg:orig_category":"Unclassifiable Establishments",
    "sg:phone":"+33 2 33 30 65 50",
    "sg:postcode":"61600",
    "sg:province":"Basse Normandie",
    "wof:name":"Laboratoire Du Dermophil Indien S.a.",
    "wof:placetype":"venue"
},
  "geometry": {"coordinates":[-0.329754,48.588291],"type":"Point"}
}