{
  "type": "Feature",
  "properties": {
    "iso:country":"FR",
    "sg:address":"15 rue de la Ligne de l'Est 69100 Villeurbanne",
    "sg:classifiers":[
        {
            "category":"Manufacturing",
            "subcategory":"Tools & Machinery",
            "type":"Manufacturing & Wholesale Goods"
        }
    ],
    "sg:phone":"+33 4 72 68 95 05",
    "sg:postcode":"69100",
    "sg:province":"Rhone-Alpes",
    "sg:tags":[
        "machine"
    ],
    "wof:name":"Yamada Dobby Japan Co Ltd Sa",
    "wof:placetype":"venue"
},
  "geometry": {"coordinates":[4.9069,45.757668],"type":"Point"}
}