{
  "type": "Feature",
  "properties": {
    "iso:country":"FR",
    "sg:address":"Palluat 07110 Largenti\u00e8re",
    "sg:orig_category":"Unclassifiable Establishments",
    "sg:phone":"+33 4 75 39 17 27",
    "sg:province":"Rhone-Alpes",
    "wof:name":"Chefaro-ardeval S.a.",
    "wof:placetype":"venue"
},
  "geometry": {"coordinates":[4.25501,44.550549],"type":"Point"}
}