{
  "type": "Feature",
  "properties": {
    "addr:full":"603 Rue George Sand Zi Molina La Chazotte 42350 La Talaudiere Rhone-Alpes 42350",
    "addr:housenumber":"603",
    "addr:postcode":"42350;42350",
    "addr:street":"Rue George Sand Zi Molina La Chazotte;Rhone-Alpes",
    "iso:country":"FR",
    "sg:address":"603 Rue George Sand Zi Molina La Chazotte 42350 La Talaudiere",
    "sg:classifiers":[
        {
            "category":"Transit Center",
            "subcategory":"Freight",
            "type":"Transportation"
        }
    ],
    "sg:phone":"+33 4 77 48 11 63",
    "sg:postcode":"42350",
    "sg:province":"Rhone-Alpes",
    "sg:tags":[
        "metallurgy",
        "pipe",
        "metalworking",
        "sheet"
    ],
    "wof:name":"Proferal",
    "wof:placetype":"venue"
},
  "geometry": {"coordinates":[4.434398,45.481918],"type":"Point"}
}