{
  "type": "Feature",
  "properties": {
    "addr:full":"47 Rue De Longvic 21301 Chenove Chen\u00f4ve Bourgogne 21300",
    "addr:housenumber":"47",
    "addr:postcode":"21301;21300",
    "addr:street":"Rue De Longvic",
    "iso:country":"FR",
    "sg:address":"47 Rue De Longvic 21301 Chenove",
    "sg:city":"Chen\u00f4ve",
    "sg:classifiers":[
        {
            "category":"Health Services",
            "subcategory":"Medical Lab",
            "type":"Services"
        }
    ],
    "sg:phone":"+33 3 80 44 72 72",
    "sg:postcode":"21300",
    "sg:province":"Bourgogne",
    "sg:tags":[
        "chemical",
        "pharmaceutical",
        "pharmacy"
    ],
    "wof:name":"Synkem",
    "wof:placetype":"venue"
},
  "geometry": {"coordinates":[5.017955,47.286476],"type":"Point"}
}