{
  "type": "Feature",
  "properties": {
    "iso:country":"FR",
    "sg:address":"Rte Paris",
    "sg:city":"Artenay",
    "sg:orig_category":"Unclassifiable Establishments",
    "sg:phone":"+33 2 38 78 78 78",
    "sg:postcode":"45410",
    "sg:province":"Centre",
    "wof:name":"U.s.d.a. S.c.a. - Union Sucreries Distilleries Agricoles",
    "wof:placetype":"venue"
},
  "geometry": {"coordinates":[1.880494,48.082932],"type":"Point"}
}