{
  "type": "Feature",
  "properties": {
    "addr:full":"248, Rte de Grenoble - Espace Nikaia, 06200 Nice Grenoble Rhone-Alpes 38100",
    "addr:housenumber":"248",
    "addr:postcode":"06200;38100",
    "addr:street":"Rte De Grenoble Espace Nikaia",
    "iso:country":"FR",
    "sg:address":"248, Rte de Grenoble - Espace Nikaia, 06200 Nice",
    "sg:city":"Grenoble",
    "sg:orig_category":"Unclassifiable Establishments",
    "sg:phone":"+33 4 92 29 36 36",
    "sg:postcode":"38100",
    "sg:province":"Rhone-Alpes",
    "wof:name":"L'espace Graphic S.a.",
    "wof:placetype":"venue"
},
  "geometry": {"coordinates":[7.215093,43.745003],"type":"Point"}
}