{
  "type": "Feature",
  "properties": {
    "addr:full":"chemin de la Meurthe 88580 Saulcy sur Meurthe Lorraine 88580",
    "addr:postcode":"88580;88580",
    "addr:street":"Chemin De La Meurthe",
    "iso:country":"FR",
    "sg:address":"chemin de la Meurthe 88580 Saulcy sur Meurthe",
    "sg:classifiers":[
        {
            "category":"Real Estate",
            "subcategory":"Surveying",
            "type":"Services"
        }
    ],
    "sg:phone":"+33 3 29 52 30 80",
    "sg:postcode":"88580",
    "sg:province":"Lorraine",
    "sg:tags":[
        "stationery",
        "writing",
        "material",
        "creative"
    ],
    "wof:name":"Emey Sa",
    "wof:placetype":"venue"
},
  "geometry": {"coordinates":[6.9572,48.24284],"type":"Point"}
}