{
  "type": "Feature",
  "properties": {
    "addr:full":"ZI de la Croix Rouge Vern sur Seiche Bretagne 35770",
    "addr:postcode":"35770",
    "addr:street":"Zi De La Croix Rouge Vern Sur Seiche Bretagne",
    "iso:country":"FR",
    "sg:address":"ZI de la Croix Rouge",
    "sg:city":"Vern sur Seiche",
    "sg:orig_category":"Unclassifiable Establishments",
    "sg:phone":"+33 2 99 62 87 78",
    "sg:postcode":"35770",
    "sg:province":"Bretagne",
    "wof:name":"Giffard Manutention S.a.",
    "wof:placetype":"venue"
},
  "geometry": {"coordinates":[-1.604871,48.050728],"type":"Point"}
}