{
  "type": "Feature",
  "properties": {
    "iso:country":"FR",
    "sg:address":"B.P. 21, 51470 Saint Memmie^^77, av. Roosevelt, 51470 Saint Memmie",
    "sg:orig_category":"Non-Classified Establishments",
    "sg:phone":"+33 3 26 68 37 37",
    "sg:province":"Champagne",
    "wof:name":"Vacher Transports S.a.",
    "wof:placetype":"venue"
},
  "geometry": {"coordinates":[4.384128,48.954563],"type":"Point"}
}