{
  "type": "Feature",
  "properties": {
    "iso:country":"FR",
    "sg:address":"132, Av. du Pr\u00e9sident Wilson, 93210 La Plaine Saint Denis",
    "sg:city":"Plaine",
    "sg:orig_category":"Non-Classified Establishments",
    "sg:phone":"+33 1 49 22 20 01",
    "sg:postcode":"67420",
    "sg:province":"Alsace",
    "wof:name":"Ab Disques Vid\u00e9o S.a.",
    "wof:placetype":"venue"
},
  "geometry": {"coordinates":[2.358803,48.908916],"type":"Point"}
}