{
  "type": "Feature",
  "properties": {
    "iso:country":"FR",
    "sg:address":"2, Rue Charles Cros, 95320 Saint Leu la For\u00eat",
    "sg:orig_category":"Non-Classified Establishments",
    "sg:phone":"+33 1 39 32 10 27",
    "sg:province":"Ile de France",
    "wof:name":"Extrum\u00e9ca S.a.r.l.",
    "wof:placetype":"venue"
},
  "geometry": {"coordinates":[2.249357,49.002468],"type":"Point"}
}