{
  "type": "Feature",
  "properties": {
    "addr:full":"Boulevard des Loges 53220 ST BERTHEVIN LA TANNIERE Pays de Loire",
    "addr:postcode":"53220",
    "addr:street":"Boulevard Des Loges;Tanniere",
    "iso:country":"FR",
    "sg:address":"Boulevard des Loges 53220 ST BERTHEVIN LA TANNIERE",
    "sg:classifiers":[
        {
            "category":"Building & Trades",
            "subcategory":"Plumbing",
            "type":"Services"
        }
    ],
    "sg:phone":"+33 2 43 64 16 41",
    "sg:province":"Pays de Loire",
    "sg:tags":[
        "tank"
    ],
    "wof:name":"Etablissement Mauguin Sa",
    "wof:placetype":"venue"
},
  "geometry": {"coordinates":[-1.051274,48.407269],"type":"Point"}
}