{
  "type": "Feature",
  "properties": {
    "addr:full":"B.P. 119, 54183 Heillecourt C\u00e9dex^^6, Rue du Coteau, 54183 Heillecourt Lorraine",
    "addr:housenumber":"b.p. 119",
    "addr:postcode":"54183;54183",
    "addr:street":"Rue Du Coteau",
    "iso:country":"FR",
    "sg:address":"B.P. 119, 54183 Heillecourt C\u00e9dex^^6, Rue du Coteau, 54183 Heillecourt",
    "sg:orig_category":"Non-Classified Establishments",
    "sg:phone":"+33 3 83 55 06 70",
    "sg:province":"Lorraine",
    "wof:name":"F.l.b. S.a. - France-lanord Et Bichaton",
    "wof:placetype":"venue"
},
  "geometry": {"coordinates":[6.194192,48.653137],"type":"Point"}
}