{
  "type": "Feature",
  "properties": {
    "addr:full":"9 impasse Isaac Newton 14200 HEROUVILLE ST CLAIR H\u00e9rouville-Saint-Clair Basse Normandie 14200",
    "addr:housenumber":"9",
    "addr:postcode":"14200;14200",
    "addr:street":"Impasse Isaac Newton",
    "iso:country":"FR",
    "sg:address":"9 impasse Isaac Newton 14200 HEROUVILLE ST CLAIR",
    "sg:city":"H\u00e9rouville-Saint-Clair",
    "sg:orig_category":"Soap Extrudate",
    "sg:phone":"+33 2 31 95 52 56",
    "sg:postcode":"14200",
    "sg:province":"Basse Normandie",
    "wof:name":"Hygena International S.a.",
    "wof:placetype":"venue"
},
  "geometry": {"coordinates":[-0.338319,49.207806],"type":"Point"}
}