{
  "type": "Feature",
  "properties": {
    "addr:full":"497, Rue Jean Moulin, 50110 Tourlaville Tourlaville Basse Normandie 50110",
    "addr:housenumber":"497",
    "addr:postcode":"50110;50110",
    "addr:street":"Rue Jean Moulin",
    "iso:country":"FR",
    "sg:address":"497, Rue Jean Moulin, 50110 Tourlaville",
    "sg:city":"Tourlaville",
    "sg:orig_category":"Unclassifiable Establishments",
    "sg:phone":"+33 2 33 20 42 78",
    "sg:postcode":"50110",
    "sg:province":"Basse Normandie",
    "wof:name":"R.l.d. Cherbourg S.a.s. - R\u00e9gie Linge D\u00e9veloppement",
    "wof:placetype":"venue"
},
  "geometry": {"coordinates":[-1.592388,49.634979],"type":"Point"}
}