{
  "type": "Feature",
  "properties": {
    "addr:full":"V.E. de Montifaut Pouzauges Pays de Loire 85700",
    "addr:postcode":"85700",
    "addr:street":"V.E.",
    "iso:country":"FR",
    "sg:address":"V.E. de Montifaut",
    "sg:city":"Pouzauges",
    "sg:orig_category":"Unclassifiable Establishments",
    "sg:phone":"+33 2 51 91 33 82",
    "sg:postcode":"85700",
    "sg:province":"Pays de Loire",
    "wof:name":"V\u00e9dia Vend\u00e9e Diamant S.a.",
    "wof:placetype":"venue"
},
  "geometry": {"coordinates":[-0.80288,46.721252],"type":"Point"}
}