{
  "type": "Feature",
  "properties": {
    "iso:country":"FR",
    "sg:address":"Za De Ruisset Parc D'Activit\u00e9s 38360 Noyarey",
    "sg:classifiers":[
        {
            "category":"Banks & Credit Unions",
            "subcategory":"Investment Brokerage",
            "type":"Services"
        }
    ],
    "sg:phone":"+33 4 76 53 73 00",
    "sg:province":"Rhone-Alpes",
    "sg:tags":[
        "-",
        "transport",
        "related"
    ],
    "wof:name":"Ducros Services Rapides Sa",
    "wof:placetype":"venue"
},
  "geometry": {"coordinates":[5.63225,45.243542],"type":"Point"}
}