{
  "type": "Feature",
  "properties": {
    "iso:country":"FR",
    "sg:address":"10 Rue Du Marechal Joffre 06000 Nice",
    "sg:classifiers":[
        {
            "category":"Manufacturing",
            "subcategory":"Jewelry",
            "type":"Manufacturing & Wholesale Goods"
        }
    ],
    "sg:phone":"+33 4 93 16 05 45",
    "sg:province":"Outre-Mer",
    "sg:tags":[
        "product",
        "miscellaneous",
        "jewellery"
    ],
    "wof:name":"Sa Albert A",
    "wof:placetype":"venue"
},
  "geometry": {"coordinates":[7.266966,43.699345],"type":"Point"}
}