{
  "type": "Feature",
  "properties": {
    "iso:country":"FR",
    "sg:address":"RN 92 - ZA Les Chasses",
    "sg:city":"Saint Paul l\u00e8s Romans",
    "sg:orig_category":"Unclassifiable Establishments",
    "sg:phone":"+33 4 75 02 36 20",
    "sg:postcode":"26750",
    "sg:province":"Rhone-Alpes",
    "wof:name":"L'europ\u00e9enne De Pneumatique S.a.",
    "wof:placetype":"venue"
},
  "geometry": {"coordinates":[5.091878,45.068378],"type":"Point"}
}