{
  "type": "Feature",
  "properties": {
    "addr:full":"5 Rue Jardins 88150 Chavelot Lorraine",
    "addr:housenumber":"5",
    "addr:postcode":"88150",
    "addr:street":"Rue Jardins",
    "iso:country":"FR",
    "sg:address":"5 Rue Jardins 88150 Chavelot",
    "sg:classifiers":[
        {
            "category":"Home & Garden",
            "subcategory":"Furniture",
            "type":"Retail Goods"
        }
    ],
    "sg:phone":"+33 3 29 39 20 57",
    "sg:province":"Lorraine",
    "sg:tags":[
        "wood"
    ],
    "wof:name":"Scierie Vosgienne Schell Sa",
    "wof:placetype":"venue"
},
  "geometry": {"coordinates":[6.436222,48.235752],"type":"Point"}
}