{
  "type": "Feature",
  "properties": {
    "addr:full":"3 rue Fernand Pelloutier 69200 Venissieux Rhone-Alpes",
    "addr:housenumber":"3",
    "addr:postcode":"69200",
    "addr:street":"Rue Fernand Pelloutier",
    "iso:country":"FR",
    "sg:address":"3 rue Fernand Pelloutier 69200 Venissieux",
    "sg:classifiers":[
        {
            "category":"Structure",
            "subcategory":"Warehouse",
            "type":"Public Place"
        }
    ],
    "sg:phone":"+33 4 72 90 81 00",
    "sg:province":"Rhone-Alpes",
    "sg:tags":[
        "high-voltage",
        "system"
    ],
    "wof:name":"Gtm Electric Reseaux Haute Tension",
    "wof:placetype":"venue"
},
  "geometry": {"coordinates":[4.900838,45.691624],"type":"Point"}
}