{
  "type": "Feature",
  "properties": {
    "iso:country":"FR",
    "sg:address":"10, Rue Edouard Vaillant, 93170 Bagnolet",
    "sg:orig_category":"Non-Classified Establishments",
    "sg:phone":"+33 1 48 59 81 02",
    "sg:postcode":"93170",
    "sg:province":"Ile de France",
    "wof:name":"Carteau & Ots S.a.",
    "wof:placetype":"venue"
},
  "geometry": {"coordinates":[2.416739,48.856323],"type":"Point"}
}