{
  "type": "Feature",
  "properties": {
    "iso:country":"FR",
    "sg:address":"7 rue Nationale; Villefranche sur Sa\u00f4ne",
    "sg:city":"Vill\u00e9",
    "sg:classifiers":[
        {
            "category":"Banks & Credit Unions",
            "subcategory":"Bank",
            "type":"Services"
        }
    ],
    "sg:phone":"+33 3374652047",
    "sg:postcode":"67220",
    "sg:province":"Alsace",
    "wof:name":"Cr\u00e9dit Agricole Du Sud Est",
    "wof:placetype":"venue"
},
  "geometry": {"coordinates":[4.719203,45.995331],"type":"Point"}
}