{
  "type": "Feature",
  "properties": {
    "iso:country":"FR",
    "sg:address":"la Forie 63600 Ambert",
    "sg:city":"La Forie",
    "sg:orig_category":"Unclassifiable Establishments",
    "sg:phone":"+33 4 73 82 03 72",
    "sg:postcode":"63600",
    "sg:province":"Auvergne",
    "wof:name":"Etablissements Bernard",
    "wof:placetype":"venue"
},
  "geometry": {"coordinates":[3.750097,45.541386],"type":"Point"}
}