{
  "type": "Feature",
  "properties": {
    "iso:country":"FR",
    "sg:address":"20 Rue Georges Cl\u00e9menceau 44840 Les Sorinis\u00e8res",
    "sg:classifiers":[
        {
            "category":"Farming",
            "subcategory":"Fish & Marine Products",
            "type":"Manufacturing & Wholesale Goods"
        }
    ],
    "sg:phone":"+33 2 40 13 40 40",
    "sg:postcode":"44840",
    "sg:province":"Pays de Loire",
    "sg:tags":[
        "livestock",
        "food",
        "related",
        "fruit",
        "vegetable",
        "agriculture"
    ],
    "wof:name":"Marais Gustave Sa",
    "wof:placetype":"venue"
},
  "geometry": {"coordinates":[-95.655869,37.653156],"type":"Point"}
}