{
  "type": "Feature",
  "properties": {
    "addr:full":"Centre Commercial la Motte Mayenne Pays de Loire 53100",
    "addr:postcode":"53100",
    "addr:street":"Mayenne",
    "iso:country":"FR",
    "sg:address":"Centre Commercial la Motte",
    "sg:city":"Mayenne",
    "sg:orig_category":"Non-Classified Establishments",
    "sg:phone":"+33 2 43 00 29 84",
    "sg:postcode":"53100",
    "sg:province":"Pays de Loire",
    "wof:name":"Letourneux S.a.r.l.",
    "wof:placetype":"venue"
},
  "geometry": {"coordinates":[-0.617214,48.305771],"type":"Point"}
}