{
  "type": "Feature",
  "properties": {
    "iso:country":"FR",
    "sg:address":"Ccal Les 4 Temps 92092 Paris La D\u00e9fense",
    "sg:classifiers":[
        {
            "category":"Communications",
            "type":"Services"
        }
    ],
    "sg:phone":"+33 1 47 73 08 53",
    "sg:province":"Midi Pyr\u00e9n\u00e9es",
    "sg:tags":[
        "translation",
        "training",
        "interpretation",
        "advice",
        "business"
    ],
    "wof:name":"Mac Donalds De La Defense",
    "wof:placetype":"venue"
},
  "geometry": {"coordinates":[2.24119,48.888939],"type":"Point"}
}