{
  "type": "Feature",
  "properties": {
    "addr:full":"41 R Andr\u00e9 Marie Amp\u00e8re 17200 Royan Poitou-Charentes 17200",
    "addr:housenumber":"41",
    "addr:postcode":"17200;17200",
    "addr:street":"R Andre\u0301 Marie Ampe\u0300Re",
    "iso:country":"FR",
    "sg:address":"41 R Andr\u00e9 Marie Amp\u00e8re 17200 Royan",
    "sg:classifiers":[
        {
            "category":"Building & Trades",
            "subcategory":"Construction",
            "type":"Services"
        }
    ],
    "sg:phone":"+33 5 46 05 15 24",
    "sg:postcode":"17200",
    "sg:province":"Poitou-Charentes",
    "sg:tags":[
        "work",
        "public"
    ],
    "wof:name":"Eurovia Poitou Charentes Limousin",
    "wof:placetype":"venue"
},
  "geometry": {"coordinates":[-1.000724,45.631222],"type":"Point"}
}