{
  "type": "Feature",
  "properties": {
    "addr:full":"9, Av. Guy de Maupassant - ZA de l'Agavon, 13170 Les Pennes Mirabeau Poitou-Charentes",
    "addr:postcode":"13170",
    "addr:street":"Av. Guy De Maupassant Za De L'Agavon;Pennes Mirabeau",
    "iso:country":"FR",
    "sg:address":"9, Av. Guy de Maupassant - ZA de l'Agavon, 13170 Les Pennes Mirabeau",
    "sg:orig_category":"Non-Classified Establishments",
    "sg:phone":"+33 4 42 02 58 00",
    "sg:province":"Poitou-Charentes",
    "wof:name":"Sorop S.a.r.l.",
    "wof:placetype":"venue"
},
  "geometry": {"coordinates":[5.282038,43.420105],"type":"Point"}
}