{
  "type": "Feature",
  "properties": {
    "addr:full":"12, Rue Parmentier, 08090 Aiglemont Aiglemont Champagne 08090",
    "addr:housenumber":"12",
    "addr:postcode":"08090;08090",
    "addr:street":"Rue Parmentier;Champagne",
    "iso:country":"FR",
    "sg:address":"12, Rue Parmentier, 08090 Aiglemont",
    "sg:city":"Aiglemont",
    "sg:orig_category":"Non-Classified Establishments",
    "sg:phone":"+33 3 24 56 12 66",
    "sg:postcode":"08090",
    "sg:province":"Champagne",
    "wof:name":"Jean Magot S.a.",
    "wof:placetype":"venue"
},
  "geometry": {"coordinates":[4.765955,49.779461],"type":"Point"}
}