{
  "type": "Feature",
  "properties": {
    "iso:country":"FR",
    "sg:address":"Rte de Charnay",
    "sg:city":"Marcy",
    "sg:orig_category":"Unclassifiable Establishments",
    "sg:phone":"+33 4 74 09 92 92",
    "sg:postcode":"69480",
    "sg:province":"Bourgogne",
    "wof:name":"Eurotrading S.a.r.l.",
    "wof:placetype":"venue"
},
  "geometry": {"coordinates":[4.6808,45.914394],"type":"Point"}
}