{
  "type": "Feature",
  "properties": {
    "addr:full":"Plateau de Lonnaz 74200 Armoy Rhone-Alpes",
    "addr:postcode":"74200",
    "addr:street":"Plateau De Lonnaz",
    "iso:country":"FR",
    "sg:address":"Plateau de Lonnaz 74200 Armoy",
    "sg:orig_category":"Unclassifiable Establishments",
    "sg:phone":"+33 4 50 71 17 89",
    "sg:province":"Rhone-Alpes",
    "wof:name":"Sols Nett S.a.",
    "wof:placetype":"venue"
},
  "geometry": {"coordinates":[6.499286,46.34903],"type":"Point"}
}