{
  "type": "Feature",
  "properties": {
    "iso:country":"FR",
    "sg:address":"4, Rue du Canal, 68126 Bennwihr",
    "sg:city":"Bennwihr",
    "sg:orig_category":"Unclassifiable Establishments",
    "sg:phone":"+33 3 89 41 73 53",
    "sg:postcode":"68630",
    "sg:province":"Alsace",
    "wof:name":"Kwo France S.a.r.l.",
    "wof:placetype":"venue"
},
  "geometry": {"coordinates":[7.353206,48.13118],"type":"Point"}
}