{
  "type": "Feature",
  "properties": {
    "iso:country":"FR",
    "sg:address":"66 Rue Jean Baptiste Defernez 62800 Li\u00e9vin",
    "sg:classifiers":[
        {
            "category":"Government",
            "subcategory":"Department Of Motor Vehicles",
            "type":"Public Place"
        }
    ],
    "sg:phone":"+33 3 21 44 20 50",
    "sg:postcode":"62800",
    "sg:province":"Nord Pas-de-Calais",
    "sg:tags":[
        "equipment",
        "industrial",
        "transport",
        "motor-cars"
    ],
    "wof:name":"Sa Etablissements Lagny",
    "wof:placetype":"venue"
},
  "geometry": {"coordinates":[2.775995,50.420582],"type":"Point"}
}