{
  "type": "Feature",
  "properties": {
    "iso:country":"FR",
    "sg:address":"490, Av. Gaston Lecouz\u00e8res, 40120 Roquefort",
    "sg:city":"Roquefort",
    "sg:orig_category":"Unclassifiable Establishments",
    "sg:phone":"+33 5 58 45 78 03",
    "sg:postcode":"40120",
    "sg:province":"Aquitaine",
    "wof:name":"Comilev Sodamel S.a.",
    "wof:placetype":"venue"
},
  "geometry": {"coordinates":[-0.322026,44.042252],"type":"Point"}
}