{
  "type": "Feature",
  "properties": {
    "addr:full":"72, Rue Mal Ney, 54140 Jarville la Malgrange Lorraine",
    "addr:housenumber":"72",
    "addr:postcode":"54140",
    "addr:street":"Rue Mal Ney",
    "iso:country":"FR",
    "sg:address":"72, Rue Mal Ney, 54140 Jarville la Malgrange",
    "sg:orig_category":"Non-Classified Establishments",
    "sg:phone":"+33 3 83 54 84 60",
    "sg:province":"Lorraine",
    "wof:name":"Expertis Conseil S.a.r.l.",
    "wof:placetype":"venue"
},
  "geometry": {"coordinates":[6.198826,48.666557],"type":"Point"}
}