{
  "type": "Feature",
  "properties": {
    "addr:full":"13, Rue Montalibet, 64100 Bayonne Bayonne Aquitaine 64100",
    "addr:housenumber":"13",
    "addr:postcode":"64100 bayonne;64100",
    "addr:street":"Rue Montalibet",
    "iso:country":"FR",
    "sg:address":"13, Rue Montalibet, 64100 Bayonne",
    "sg:city":"Bayonne",
    "sg:orig_category":"Non-Classified Establishments",
    "sg:phone":"+33 5 59 52 39 03",
    "sg:postcode":"64100",
    "sg:province":"Aquitaine",
    "wof:name":"Agorila S.a.r.l.",
    "wof:placetype":"venue"
},
  "geometry": {"coordinates":[-1.482482,43.485516],"type":"Point"}
}