{
  "type": "Feature",
  "properties": {
    "iso:country":"FR",
    "sg:address":"4",
    "sg:city":"Jeanne d'Arc; Villerupt; 54190",
    "sg:classifiers":[
        {
            "category":"Banks & Credit Unions",
            "subcategory":"Bank",
            "type":"Services"
        }
    ],
    "sg:phone":"+33 3382891603",
    "sg:postcode":"54190",
    "sg:province":"Lorraine",
    "wof:name":"Soci\u00e9t\u00e9 G\u00e9n\u00e9rale",
    "wof:placetype":"venue"
},
  "geometry": {"coordinates":[5.930412,49.469997],"type":"Point"}
}