{
  "type": "Feature",
  "properties": {
    "addr:full":"59, Rte de Besan\u00e7on, 25220 Thise Franche Comt\u00e9",
    "addr:housenumber":"59",
    "addr:postcode":"25220",
    "addr:street":"Rte De Besanc\u0327On;Franche Comte\u0301",
    "iso:country":"FR",
    "sg:address":"59, Rte de Besan\u00e7on, 25220 Thise",
    "sg:orig_category":"Non-Classified Establishments",
    "sg:phone":"+33 3 81 80 31 66",
    "sg:province":"Franche Comt\u00e9",
    "wof:name":"Franche-comt\u00e9 C\u00e2blage S.a.r.l.",
    "wof:placetype":"venue"
},
  "geometry": {"coordinates":[6.07082,47.278606],"type":"Point"}
}