{
  "type": "Feature",
  "properties": {
    "addr:full":"Rte de Compi\u00e8gne - Zone Industrielle Mercin et Vaux Picardie 02200",
    "addr:postcode":"02200",
    "addr:street":"Rte De Compie\u0300Gne;Industrielle Mercin Et Vaux Picardie",
    "iso:country":"FR",
    "sg:address":"Rte de Compi\u00e8gne - Zone Industrielle",
    "sg:city":"Mercin et Vaux",
    "sg:orig_category":"Non-Classified Establishments",
    "sg:phone":"+33 3 23 73 69 59",
    "sg:postcode":"02200",
    "sg:province":"Picardie",
    "wof:name":"Socam Equipements S.a.r.l.",
    "wof:placetype":"venue"
},
  "geometry": {"coordinates":[3.32451,49.366711],"type":"Point"}
}