{
  "type": "Feature",
  "properties": {
    "addr:full":"B.P. 27, 17800 Pons^^10, Rue Paulin Charron, 17800 Pons Poitou-Charentes",
    "addr:postcode":"17800;17800",
    "addr:street":"B.P. 27;Rue Paulin Charron",
    "iso:country":"FR",
    "sg:address":"B.P. 27, 17800 Pons^^10, Rue Paulin Charron, 17800 Pons",
    "sg:orig_category":"Non-Classified Establishments",
    "sg:phone":"+33 5 46 91 47 47",
    "sg:province":"Poitou-Charentes",
    "wof:name":"S.e.d.i.s. S.a. - Service Et Distribution",
    "wof:placetype":"venue"
},
  "geometry": {"coordinates":[-0.59809,45.51733],"type":"Point"}
}