{
  "type": "Feature",
  "properties": {
    "iso:country":"FR",
    "sg:address":"7 bis, Rue du Pont de l'Aveugle, 64600 Anglet",
    "sg:city":"Anglet",
    "sg:orig_category":"Non-Classified Establishments",
    "sg:phone":"+33 5 59 52 33 44",
    "sg:postcode":"64600",
    "sg:province":"Aquitaine",
    "wof:name":"Onet Propret\u00e9 S.a.",
    "wof:placetype":"venue"
},
  "geometry": {"coordinates":[-1.49388,43.498966],"type":"Point"}
}