{
  "type": "Feature",
  "properties": {
    "addr:full":"145, Rue Saint Roch, 84120 Pertuis Picardie",
    "addr:housenumber":"145",
    "addr:postcode":"84120",
    "addr:street":"Rue Saint Roch",
    "iso:country":"FR",
    "sg:address":"145, Rue Saint Roch, 84120 Pertuis",
    "sg:orig_category":"Non-Classified Establishments",
    "sg:phone":"+33 4 90 79 42 90",
    "sg:province":"Picardie",
    "wof:name":"D\u00e9bim\u00e9trie A Et T S.a.r.l.",
    "wof:placetype":"venue"
},
  "geometry": {"coordinates":[5.503819,43.691257],"type":"Point"}
}