{
  "type": "Feature",
  "properties": {
    "iso:country":"FR",
    "sg:address":"18 bis, Rue Pierre Bonnard, 92260 Fontenay aux Roses",
    "sg:orig_category":"Unclassifiable Establishments",
    "sg:phone":"+33 1 47 02 22 18",
    "sg:province":"Ile de France",
    "wof:name":"Meta S.a.r.l.",
    "wof:placetype":"venue"
},
  "geometry": {"coordinates":[2.282956,48.784527],"type":"Point"}
}