{
  "type": "Feature",
  "properties": {
    "iso:country":"FR",
    "sg:address":"22 Rue Des Forges 36100 Les Bordes",
    "sg:city":"Les Bordes",
    "sg:classifiers":[
        {
            "category":"Utilities",
            "subcategory":"Electric",
            "type":"Services"
        }
    ],
    "sg:phone":"+33 2 54 21 39 79",
    "sg:postcode":"36100",
    "sg:province":"Centre",
    "sg:tags":[
        "electricity",
        "electronic",
        "electrical",
        "equipment"
    ],
    "wof:name":"Sarl Etablissements Sainson",
    "wof:placetype":"venue"
},
  "geometry": {"coordinates":[1.970208,46.982719],"type":"Point"}
}