{
  "type": "Feature",
  "properties": {
    "addr:full":"Le Mesnil Roux 76360 Barentin Haute Normandie 76360",
    "addr:postcode":"76360;76360",
    "addr:street":"Le Mesnil Roux;Haute Normandie",
    "iso:country":"FR",
    "sg:address":"Le Mesnil Roux 76360 Barentin",
    "sg:classifiers":[
        {
            "category":"Utilities",
            "subcategory":"Electric",
            "type":"Services"
        }
    ],
    "sg:phone":"+33 810 07 60 76",
    "sg:postcode":"76360",
    "sg:province":"Haute Normandie",
    "sg:tags":[
        "electricity",
        "raw",
        "energy",
        "material"
    ],
    "wof:name":"Electricite De France (edf)",
    "wof:placetype":"venue"
},
  "geometry": {"coordinates":[0.966315,49.535774],"type":"Point"}
}