{
  "type": "Feature",
  "properties": {
    "iso:country":"FR",
    "sg:address":"48 blvd de Strasbourg; Toulon; 83041",
    "sg:city":"Strasbourg",
    "sg:classifiers":[
        {
            "category":"Banks & Credit Unions",
            "subcategory":"Bank",
            "type":"Services"
        }
    ],
    "sg:phone":"+33 4 94 09 83 29",
    "sg:postcode":"67000",
    "sg:province":"Alsace",
    "wof:name":"Lyonnaise De Banque Sa",
    "wof:placetype":"venue"
},
  "geometry": {"coordinates":[5.9052,43.13773],"type":"Point"}
}