{
  "type": "Feature",
  "properties": {
    "addr:full":"Rue des B\u00e9gonias Reherrey Lorraine 54120",
    "addr:postcode":"54120",
    "addr:street":"Rue Des Be\u0301Gonias",
    "iso:country":"FR",
    "sg:address":"Rue des B\u00e9gonias",
    "sg:city":"Reherrey",
    "sg:orig_category":"Non-Classified Establishments",
    "sg:phone":"+33 3 83 72 23 76",
    "sg:postcode":"54120",
    "sg:province":"Lorraine",
    "wof:name":"Treffe Et Vantillard S.a.r.l.",
    "wof:placetype":"venue"
},
  "geometry": {"coordinates":[6.772245,48.50824],"type":"Point"}
}