{
  "type": "Feature",
  "properties": {
    "iso:country":"FR",
    "sg:address":"2 route de Villers le Lac 25500 Les Fins",
    "sg:classifiers":[
        {
            "category":"Shopping Center",
            "type":"Public Place"
        }
    ],
    "sg:phone":"+33 3 81 68 51 51",
    "sg:postcode":"25500",
    "sg:province":"Franche Comt\u00e9",
    "sg:tags":[
        "case",
        "clock"
    ],
    "wof:name":"Habillage Garde Temps Petit Jean S.a.",
    "wof:placetype":"venue"
},
  "geometry": {"coordinates":[6.639686,47.082199],"type":"Point"}
}