{
  "type": "Feature",
  "properties": {
    "addr:full":"21/23, Rue Emile Zola, 69150 D\u00e9cines Charpieu Rhone-Alpes",
    "addr:housenumber":"21 / 23",
    "addr:postcode":"69150",
    "addr:street":"Rue Emile Zola",
    "iso:country":"FR",
    "sg:address":"21/23, Rue Emile Zola, 69150 D\u00e9cines Charpieu",
    "sg:orig_category":"Unclassifiable Establishments",
    "sg:phone":"+33 4 72 05 47 47",
    "sg:province":"Rhone-Alpes",
    "wof:name":"Codima S.a.",
    "wof:placetype":"venue"
},
  "geometry": {"coordinates":[4.939539,45.763474],"type":"Point"}
}