{
  "type": "Feature",
  "properties": {
    "iso:country":"FR",
    "sg:address":"253, Rue du Rond d'Eau - ZI de la Saussaye, 45075 Orl\u00e9ans C\u00e9dex 2",
    "sg:orig_category":"Non-Classified Establishments",
    "sg:phone":"+33 2 38 25 12 19",
    "sg:province":"Champagne",
    "wof:name":"Entreprise Cochez S.a.",
    "wof:placetype":"venue"
},
  "geometry": {"coordinates":[1.859897,47.9147],"type":"Point"}
}