{
  "type": "Feature",
  "properties": {
    "iso:country":"FR",
    "sg:address":"Zi Sassevil 76450 Cany Barville",
    "sg:classifiers":[
        {
            "category":"Shopping",
            "type":"Retail Goods"
        }
    ],
    "sg:phone":"+33 2 35 97 73 33",
    "sg:postcode":"76450",
    "sg:province":"Haute Normandie",
    "sg:tags":[
        "metallurgy",
        "finished",
        "-",
        "metalworking",
        "metallic"
    ],
    "wof:name":"Ets Baumert Mauler Sa",
    "wof:placetype":"venue"
},
  "geometry": {"coordinates":[0.638909,49.788616],"type":"Point"}
}