{
  "type": "Feature",
  "properties": {
    "addr:full":"23 Rue Voltaire BP 2 80531 Friville Cedex Vill\u00e9 Alsace 67220",
    "addr:housenumber":"23;2",
    "addr:postcode":"80531;67220",
    "addr:street":"Rue Voltaire Bp",
    "iso:country":"FR",
    "sg:address":"23 Rue Voltaire BP 2 80531 Friville Cedex",
    "sg:city":"Vill\u00e9",
    "sg:classifiers":[
        {
            "category":"Manufacturing",
            "subcategory":"Metals",
            "type":"Manufacturing & Wholesale Goods"
        }
    ],
    "sg:phone":"+33 3 22 30 20 01",
    "sg:postcode":"67220",
    "sg:province":"Alsace",
    "sg:tags":[
        "metallurgy",
        "steel",
        "metalworking"
    ],
    "wof:name":"Boutte Fonderie Sa",
    "wof:placetype":"venue"
},
  "geometry": {"coordinates":[1.54353,50.090778],"type":"Point"}
}