{
  "type": "Feature",
  "properties": {
    "addr:full":"2000, rue Horizon, 62117 Br\u00e8bi\u00e8res Nord Pas-de-Calais 62117",
    "addr:housenumber":"2000",
    "addr:postcode":"62117;62117",
    "addr:street":"Rue Horizon;Bre\u0300Bie\u0300Res Nord",
    "iso:country":"FR",
    "sg:address":"2000, rue Horizon, 62117 Br\u00e8bi\u00e8res",
    "sg:orig_category":"Non-Classified Establishments",
    "sg:phone":"+33 3 21 50 92 92",
    "sg:postcode":"62117",
    "sg:province":"Nord Pas-de-Calais",
    "wof:name":"D.b.t. S.a. - Douaisienne De Basse Tension",
    "wof:placetype":"venue"
},
  "geometry": {"coordinates":[3.02308,50.337639],"type":"Point"}
}