{
  "type": "Feature",
  "properties": {
    "iso:country":"FR",
    "sg:address":"Lapouyade 33230 Saint M\u00e9dard de Guizi\u00e8res",
    "sg:city":"Abzac",
    "sg:orig_category":"Non-Classified Establishments",
    "sg:phone":"+33 5 57 69 62 31",
    "sg:postcode":"33230",
    "sg:province":"Aquitaine",
    "wof:name":"Huileries Gid S.a.r.l.",
    "wof:placetype":"venue"
},
  "geometry": {"coordinates":[-0.073849,45.017826],"type":"Point"}
}