{
  "type": "Feature",
  "properties": {
    "addr:full":"4, Rue Samuel Morse - ZI, 77100 Meaux Ile de France",
    "addr:housenumber":"4",
    "addr:postcode":"77100;ile",
    "addr:street":"Rue Samuel Morse Zi",
    "iso:country":"FR",
    "sg:address":"4, Rue Samuel Morse - ZI, 77100 Meaux",
    "sg:orig_category":"Unclassifiable Establishments",
    "sg:phone":"+33 1 60 44 00 22",
    "sg:province":"Ile de France",
    "wof:name":"Pum Plastiques",
    "wof:placetype":"venue"
},
  "geometry": {"coordinates":[2.883054,48.959351],"type":"Point"}
}