{
  "type": "Feature",
  "properties": {
    "addr:full":"rue de la Douane 10600 LA CHAPELLE ST LUC Champagne 10600",
    "addr:postcode":"10600;10600",
    "addr:street":"Rue De La Douane;La Chapelle St Luc Champagne",
    "iso:country":"FR",
    "sg:address":"rue de la Douane 10600 LA CHAPELLE ST LUC",
    "sg:classifiers":[
        {
            "category":"Utilities",
            "subcategory":"Recycling",
            "type":"Services"
        }
    ],
    "sg:phone":"+33 3 25 82 46 67",
    "sg:postcode":"10600",
    "sg:province":"Champagne",
    "sg:tags":[
        "polystyrene",
        "expanded",
        "eps"
    ],
    "wof:name":"Etab A. Chazelle Sa",
    "wof:placetype":"venue"
},
  "geometry": {"coordinates":[4.035315,48.320999],"type":"Point"}
}