{
  "type": "Feature",
  "properties": {
    "addr:full":"1 Rue Des Oliviers 94537 Thiais Picardie",
    "addr:housenumber":"1",
    "addr:postcode":"94537",
    "addr:street":"Rue Des Oliviers",
    "iso:country":"FR",
    "sg:address":"1 Rue Des Oliviers 94537 Thiais",
    "sg:classifiers":[
        {
            "category":"Food Court",
            "type":"Food & Drink"
        }
    ],
    "sg:phone":"+33 1 45 12 42 00",
    "sg:province":"Picardie",
    "sg:tags":[
        "product",
        "related"
    ],
    "wof:name":"Castel Freres",
    "wof:placetype":"venue"
},
  "geometry": {"coordinates":[-121.98214,37.550961],"type":"Point"}
}