{
  "type": "Feature",
  "properties": {
    "addr:full":"18 Rue D'Avoux 21000 Dijon Dijon Bourgogne 21000",
    "addr:housenumber":"18",
    "addr:postcode":"21000;21000",
    "addr:street":"Rue D'Avoux",
    "iso:country":"FR",
    "sg:address":"18 Rue D'Avoux 21000 Dijon",
    "sg:city":"Dijon",
    "sg:classifiers":[
        {
            "category":"Banks & Credit Unions",
            "subcategory":"Financial Services",
            "type":"Services"
        }
    ],
    "sg:phone":"+33 3 80 63 56 35",
    "sg:postcode":"21000",
    "sg:province":"Bourgogne",
    "sg:tags":[
        "banking",
        "insurance",
        "institution",
        "finance"
    ],
    "wof:name":"Credit Agricole De La Cote D'or - Caisse Regionale",
    "wof:placetype":"venue"
},
  "geometry": {"coordinates":[5.020306,47.346718],"type":"Point"}
}