{
  "type": "Feature",
  "properties": {
    "addr:full":"Rte de Courtonne Glos Basse Normandie 14100",
    "addr:postcode":"14100",
    "addr:street":"Rte De Courtonne",
    "iso:country":"FR",
    "sg:address":"Rte de Courtonne",
    "sg:city":"Glos",
    "sg:orig_category":"Non-Classified Establishments",
    "sg:phone":"+33 2 31 48 31 48",
    "sg:postcode":"14100",
    "sg:province":"Basse Normandie",
    "wof:name":"Atos S.a.",
    "wof:placetype":"venue"
},
  "geometry": {"coordinates":[0.28721,49.125866],"type":"Point"}
}