{
  "type": "Feature",
  "properties": {
    "addr:full":"16, Rue de la Mairie, 77167 Poligny Ile de France 77167",
    "addr:housenumber":"16",
    "addr:postcode":"77167;ile;77167",
    "addr:street":"Rue De La Mairie;France",
    "iso:country":"FR",
    "sg:address":"16, Rue de la Mairie, 77167 Poligny",
    "sg:orig_category":"Non-Classified Establishments",
    "sg:phone":"+33 1 64 78 57 00",
    "sg:postcode":"77167",
    "sg:province":"Ile de France",
    "wof:name":"Entreprise Boyer S.a.",
    "wof:placetype":"venue"
},
  "geometry": {"coordinates":[2.746002,48.224728],"type":"Point"}
}