{
  "type": "Feature",
  "properties": {
    "iso:country":"FR",
    "sg:address":"Lieu Dit la Thebaudi\u00e8re 50150 Sourdeval",
    "sg:city":"Sourdeval",
    "sg:classifiers":[
        {
            "category":"Train Station",
            "subcategory":"Rail",
            "type":"Transportation"
        }
    ],
    "sg:phone":"+33 2 33 59 60 18",
    "sg:postcode":"50150",
    "sg:province":"Basse Normandie",
    "sg:tags":[
        "steel",
        "cutlery",
        "rust-proof"
    ],
    "wof:name":"Lebrun Sa",
    "wof:placetype":"venue"
},
  "geometry": {"coordinates":[-0.92453,48.731758],"type":"Point"}
}