{
  "type": "Feature",
  "properties": {
    "addr:full":"120 Rue Nationale 57351 Stiring Wendel Cedex Basse Normandie",
    "addr:housenumber":"120",
    "addr:postcode":"57351;wendel cedex",
    "addr:street":"Rue Nationale",
    "iso:country":"FR",
    "sg:address":"120 Rue Nationale 57351 Stiring Wendel Cedex",
    "sg:classifiers":[
        {
            "category":"Home & Garden",
            "subcategory":"Furniture",
            "type":"Retail Goods"
        }
    ],
    "sg:phone":"+33 3 87 87 41 85",
    "sg:province":"Basse Normandie",
    "sg:tags":[
        "household",
        "wood"
    ],
    "wof:name":"Moderncuisine Meubles Scherer Sarl",
    "wof:placetype":"venue"
},
  "geometry": {"coordinates":[6.920937,49.194836],"type":"Point"}
}