{
  "type": "Feature",
  "properties": {
    "iso:country":"FR",
    "sg:address":"52 Avenue Vaucanson 93370 Montfermeil",
    "sg:classifiers":[
        {
            "category":"Shopping",
            "subcategory":"Computers & Home Electronics",
            "type":"Retail Goods"
        }
    ],
    "sg:phone":"+33 1 45 09 58 44",
    "sg:postcode":"93370",
    "sg:province":"Ile de France",
    "sg:tags":[
        "equipment",
        "electrical",
        "component",
        "electric",
        "electronic"
    ],
    "wof:name":"Societe De Produits Applications Specifiques (pas)",
    "wof:placetype":"venue"
},
  "geometry": {"coordinates":[2.58362,48.902328],"type":"Point"}
}