{
  "type": "Feature",
  "properties": {
    "addr:full":"23 rue de la Pr\u00e9 02370 VAILLY SUR AISNE Picardie",
    "addr:housenumber":"23",
    "addr:postcode":"02370",
    "addr:street":"Rue De La Pre\u0301",
    "iso:country":"FR",
    "sg:address":"23 rue de la Pr\u00e9 02370 VAILLY SUR AISNE",
    "sg:classifiers":[
        {
            "category":"Professional",
            "type":"Services"
        }
    ],
    "sg:phone":"+33 3 23 54 72 24",
    "sg:province":"Picardie",
    "sg:tags":[
        "transport"
    ],
    "wof:name":"Scher Sa",
    "wof:placetype":"venue"
},
  "geometry": {"coordinates":[3.518145,49.405678],"type":"Point"}
}