{
  "type": "Feature",
  "properties": {
    "addr:full":"3, Rue de la Motte, 71380 Epervans \u00c9pervans Bourgogne 71380",
    "addr:housenumber":"3",
    "addr:postcode":"71380;71380",
    "addr:street":"Rue De La Motte",
    "iso:country":"FR",
    "sg:address":"3, Rue de la Motte, 71380 Epervans",
    "sg:city":"\u00c9pervans",
    "sg:orig_category":"Unclassifiable Establishments",
    "sg:phone":"+33 3 85 96 72 32",
    "sg:postcode":"71380",
    "sg:province":"Bourgogne",
    "wof:name":"B.s.t. Electronique S.a.r.l.",
    "wof:placetype":"venue"
},
  "geometry": {"coordinates":[4.914506,46.756786],"type":"Point"}
}