{
  "type": "Feature",
  "properties": {
    "addr:full":"680, Rte du Guigonnet, 13270 Fos sur Mer Midi Pyr\u00e9n\u00e9es",
    "addr:housenumber":"680",
    "addr:postcode":"13270",
    "addr:street":"Rte Du Guigonnet",
    "iso:country":"FR",
    "sg:address":"680, Rte du Guigonnet, 13270 Fos sur Mer",
    "sg:orig_category":"Non-Classified Establishments",
    "sg:phone":"+33 4 42 05 34 95",
    "sg:province":"Midi Pyr\u00e9n\u00e9es",
    "wof:name":"Phocomex S.a.r.l.",
    "wof:placetype":"venue"
},
  "geometry": {"coordinates":[4.928239,43.449085],"type":"Point"}
}