{
  "type": "Feature",
  "properties": {
    "iso:country":"FR",
    "sg:address":"ZA du Guimand",
    "sg:city":"Malissard",
    "sg:orig_category":"Unclassifiable Establishments",
    "sg:phone":"+33 4 75 85 44 20",
    "sg:postcode":"26120",
    "sg:province":"Rhone-Alpes",
    "wof:name":"Etablissements Hubert Chapon",
    "wof:placetype":"venue"
},
  "geometry": {"coordinates":[4.95581,44.90102],"type":"Point"}
}