{
  "type": "Feature",
  "properties": {
    "iso:country":"FR",
    "sg:address":"5 rue du Centre; Digoin; 71160",
    "sg:city":"Digoin",
    "sg:classifiers":[
        {
            "category":"Banks & Credit Unions",
            "subcategory":"Bank",
            "type":"Services"
        }
    ],
    "sg:phone":"+33 3385531015",
    "sg:postcode":"71160",
    "sg:province":"Bourgogne",
    "wof:name":"Banque Nationale De Paris",
    "wof:placetype":"venue"
},
  "geometry": {"coordinates":[3.978493,46.480488],"type":"Point"}
}