{
  "type": "Feature",
  "properties": {
    "addr:full":"1/3, Rue du 19 Janvier, 92380 Garches Ile de France",
    "addr:housenumber":"1 / 3",
    "addr:postcode":"92380;ile",
    "addr:street":"Rue Du 19 Janvier",
    "iso:country":"FR",
    "sg:address":"1/3, Rue du 19 Janvier, 92380 Garches",
    "sg:orig_category":"Non-Classified Establishments",
    "sg:phone":"+33 1 47 10 95 00",
    "sg:province":"Ile de France",
    "wof:name":"Omnicontact S.a.s.",
    "wof:placetype":"venue"
},
  "geometry": {"coordinates":[2.200707,48.848946],"type":"Point"}
}