{
  "type": "Feature",
  "properties": {
    "iso:country":"FR",
    "sg:address":"Av De L'Europe 71210 Ecuisses",
    "sg:city":"\u00c9cuisses",
    "sg:classifiers":[
        {
            "category":"Professional",
            "subcategory":"Engineering",
            "type":"Services"
        }
    ],
    "sg:phone":"+33 3 85 73 90 09",
    "sg:postcode":"71210",
    "sg:province":"Bourgogne",
    "sg:tags":[
        "machine",
        "-",
        "mechanical"
    ],
    "wof:name":"Gel Kit Sa",
    "wof:placetype":"venue"
},
  "geometry": {"coordinates":[4.502737,46.761242],"type":"Point"}
}