{
  "type": "Feature",
  "properties": {
    "addr:full":"6 Rue De La Banque 71100 Chalon Sur Sa\u00f4ne Chalon-sur-Sa\u00f4ne Bourgogne 71100",
    "addr:housenumber":"6",
    "addr:postcode":"71100;71100",
    "addr:street":"Rue De La Banque",
    "iso:country":"FR",
    "sg:address":"6 Rue De La Banque 71100 Chalon Sur Sa\u00f4ne",
    "sg:city":"Chalon-sur-Sa\u00f4ne",
    "sg:classifiers":[
        {
            "category":"Professional",
            "subcategory":"Advertising",
            "type":"Services"
        }
    ],
    "sg:phone":"+33 3 85 93 06 69",
    "sg:postcode":"71100",
    "sg:province":"Bourgogne",
    "sg:tags":[
        "information",
        "medium",
        "communication"
    ],
    "wof:name":"Regie Networks",
    "wof:placetype":"venue"
},
  "geometry": {"coordinates":[4.852227,46.783813],"type":"Point"}
}