{
  "type": "Feature",
  "properties": {
    "addr:full":"42 Rue Des Mathurins 75008 Paris Ile de France 75008",
    "addr:housenumber":"42",
    "addr:postcode":"75008;75008",
    "addr:street":"Rue Des Mathurins",
    "iso:country":"FR",
    "sg:address":"42 Rue Des Mathurins 75008 Paris",
    "sg:classifiers":[
        {
            "category":"Banks & Credit Unions",
            "subcategory":"Financial Services",
            "type":"Services"
        }
    ],
    "sg:phone":"+33 1 44 71 52 00",
    "sg:postcode":"75008",
    "sg:province":"Ile de France",
    "sg:tags":[
        "banking",
        "finance",
        "insurance"
    ],
    "wof:name":"Socapi Sa",
    "wof:placetype":"venue"
},
  "geometry": {"coordinates":[2.324882,48.873394],"type":"Point"}
}