{
  "type": "Feature",
  "properties": {
    "addr:full":"359 route De Chez Diossaz 74570 GROISY Rhone-Alpes 74570",
    "addr:housenumber":"359",
    "addr:postcode":"74570;74570",
    "addr:street":"Route De Chez Diossaz;Rhone-Alpes",
    "iso:country":"FR",
    "sg:address":"359 route De Chez Diossaz 74570 GROISY",
    "sg:classifiers":[
        {
            "category":"Manufacturing",
            "subcategory":"Lumber",
            "type":"Manufacturing & Wholesale Goods"
        }
    ],
    "sg:phone":"+33 4 50 68 01 29",
    "sg:postcode":"74570",
    "sg:province":"Rhone-Alpes",
    "sg:tags":[
        "hardwood",
        "sawmill"
    ],
    "wof:name":"Ets Chaumontet S.a.r.l.",
    "wof:placetype":"venue"
},
  "geometry": {"coordinates":[6.221405,45.977425],"type":"Point"}
}