{
  "type": "Feature",
  "properties": {
    "addr:full":"Za Echarmasses 01200 Ch\u00e2tillon En Michaille Rhone-Alpes 01200",
    "addr:postcode":"01200;01200",
    "addr:street":"Za Echarmasses;Rhone-Alpes",
    "iso:country":"FR",
    "sg:address":"Za Echarmasses 01200 Ch\u00e2tillon En Michaille",
    "sg:classifiers":[
        {
            "category":"Shopping",
            "type":"Retail Goods"
        }
    ],
    "sg:phone":"+33 4 50 48 06 61",
    "sg:postcode":"01200",
    "sg:province":"Rhone-Alpes",
    "sg:tags":[
        "metallurgy",
        "finished",
        "-",
        "metalworking",
        "metallic"
    ],
    "wof:name":"Ste Exploitation Ets Jean Carraz Sa",
    "wof:placetype":"venue"
},
  "geometry": {"coordinates":[5.79882,46.144123],"type":"Point"}
}