{
  "type": "Feature",
  "properties": {
    "addr:full":"B.P. 4, 02590 Etreillers^^Rue Andr\u00e9 Dietrich, 02590 Etreillers Picardie 02590",
    "addr:housenumber":"4",
    "addr:postcode":"02590;02590;02590",
    "addr:street":"B.P.;Picardie",
    "iso:country":"FR",
    "sg:address":"B.P. 4, 02590 Etreillers^^Rue Andr\u00e9 Dietrich, 02590 Etreillers",
    "sg:orig_category":"Non-Classified Establishments",
    "sg:phone":"+33 3 23 68 82 23",
    "sg:postcode":"02590",
    "sg:province":"Picardie",
    "wof:name":"Ercim Engineering S.a.r.l.",
    "wof:placetype":"venue"
},
  "geometry": {"coordinates":[3.136976,49.820503],"type":"Point"}
}