{
  "type": "Feature",
  "properties": {
    "addr:full":"Za Le Bois Du Breuil 35190 St Domineuc B\u00e9cherel Bretagne 35190",
    "addr:postcode":"35190;35190",
    "addr:street":"Za Le Bois Du Breuil;Be\u0301Cherel",
    "iso:country":"FR",
    "sg:address":"Za Le Bois Du Breuil 35190 St Domineuc",
    "sg:city":"B\u00e9cherel",
    "sg:classifiers":[
        {
            "category":"Home & Garden",
            "subcategory":"Furniture",
            "type":"Retail Goods"
        }
    ],
    "sg:phone":"+33 2 99 45 31 90",
    "sg:postcode":"35190",
    "sg:province":"Bretagne",
    "sg:tags":[
        "wood"
    ],
    "wof:name":"Pinault Bretagne Et Compagnie",
    "wof:placetype":"venue"
},
  "geometry": {"coordinates":[-1.875689,48.372566],"type":"Point"}
}