{
  "type": "Feature",
  "properties": {
    "addr:full":"5, Rue d'Ariane, 31240 L'Union Midi Pyr\u00e9n\u00e9es",
    "addr:housenumber":"5",
    "addr:postcode":"31240",
    "addr:street":"Rue D'Ariane",
    "iso:country":"FR",
    "sg:address":"5, Rue d'Ariane, 31240 L'Union",
    "sg:orig_category":"Unclassifiable Establishments",
    "sg:phone":"+33 5 61 58 48 48",
    "sg:province":"Midi Pyr\u00e9n\u00e9es",
    "wof:name":"Sereib S.a.r.l. - Soci\u00e9t\u00e9 Etude Informatique Reproduction",
    "wof:placetype":"venue"
},
  "geometry": {"coordinates":[-87.905098,32.996254],"type":"Point"}
}