{
  "type": "Feature",
  "properties": {
    "iso:country":"FR",
    "sg:address":"Parc De Montigni Maxilly 74500 Evian Les Bains",
    "sg:classifiers":[
        {
            "category":"Professional",
            "subcategory":"Engineering",
            "type":"Services"
        }
    ],
    "sg:phone":"+33 4 50 70 74 74",
    "sg:postcode":"74500",
    "sg:province":"Rhone-Alpes",
    "sg:tags":[
        "machine",
        "-",
        "mechanical"
    ],
    "wof:name":"Actini Sa",
    "wof:placetype":"venue"
},
  "geometry": {"coordinates":[6.64146,46.330173],"type":"Point"}
}