{
  "type": "Feature",
  "properties": {
    "addr:full":"4 Rue De L Europe Zone Industrielle 60530 Neuilly En Thelle Picardie 60530",
    "addr:housenumber":"4",
    "addr:postcode":"60530;60530",
    "addr:street":"Rue De L Europe Zone Industrielle;En Thelle Picardie",
    "iso:country":"FR",
    "sg:address":"4 Rue De L Europe Zone Industrielle 60530 Neuilly En Thelle",
    "sg:classifiers":[
        {
            "category":"Wholesale",
            "subcategory":"Medical Equipment & Supplies",
            "type":"Manufacturing & Wholesale Goods"
        }
    ],
    "sg:phone":"+33 3 44 26 63 46",
    "sg:postcode":"60530",
    "sg:province":"Picardie",
    "sg:tags":[
        "instrument",
        "health",
        "-",
        "precision"
    ],
    "wof:name":"Prodimed",
    "wof:placetype":"venue"
},
  "geometry": {"coordinates":[2.28527,49.224705],"type":"Point"}
}