{
  "type": "Feature",
  "properties": {
    "addr:full":"Rue des Oliviers - ZA du Pouvelel La Garde Provence-Alpes-C\u00f4te d'Azur 83130",
    "addr:postcode":"83130",
    "addr:street":"Rue Des Oliviers Za Du Pouvelel La Garde",
    "iso:country":"FR",
    "sg:address":"Rue des Oliviers - ZA du Pouvelel",
    "sg:city":"La Garde",
    "sg:orig_category":"Unclassifiable Establishments",
    "sg:phone":"+33 4 94 08 67 20",
    "sg:postcode":"83130",
    "sg:province":"Provence-Alpes-C\u00f4te d'Azur",
    "wof:name":"Prot\u00e9lec S.a.r.l.",
    "wof:placetype":"venue"
},
  "geometry": {"coordinates":[6.009775,43.124866],"type":"Point"}
}