{
  "type": "Feature",
  "properties": {
    "iso:country":"FR",
    "sg:address":"2, Rue des Bourets - Tour Ventose, 92150 Suresnes",
    "sg:orig_category":"Non-Classified Establishments",
    "sg:phone":"+33 1 41 44 92 20",
    "sg:postcode":"92150",
    "sg:province":"Ile de France",
    "wof:name":"Elsa France S.a.s",
    "wof:placetype":"venue"
},
  "geometry": {"coordinates":[2.226566,48.867844],"type":"Point"}
}