{
  "type": "Feature",
  "properties": {
    "iso:country":"FR",
    "sg:address":"28, Rue Basfroi, 75011 Paris",
    "sg:orig_category":"Unclassifiable Establishments",
    "sg:phone":"+33 1 43 70 88 17",
    "sg:province":"Ile de France",
    "wof:name":"Eosi S.a.r.l. - Electronique Online Systems International",
    "wof:placetype":"venue"
},
  "geometry": {"coordinates":[2.37941,48.855118],"type":"Point"}
}