{
  "type": "Feature",
  "properties": {
    "iso:country":"FR",
    "sg:address":"113, All\u00e9e des Chataigniers, 01600 Reyrieux",
    "sg:orig_category":"Unclassifiable Establishments",
    "sg:phone":"+33 4 74 00 09 24",
    "sg:province":"Rhone-Alpes",
    "wof:name":"B.e.c.i.r. S.a.r.l. - Bureau D'etudes Cirenei",
    "wof:placetype":"venue"
},
  "geometry": {"coordinates":[4.797516,45.940449],"type":"Point"}
}