{
  "type": "Feature",
  "properties": {
    "iso:country":"FR",
    "sg:address":"61 rue Lavoisier 14200 Herouville St Clair",
    "sg:city":"H\u00e9rouville-Saint-Clair",
    "sg:classifiers":[
        {
            "category":"Shopping",
            "subcategory":"Beauty & Cosmetics",
            "type":"Retail Goods"
        }
    ],
    "sg:phone":"+33 2 31 06 16 06",
    "sg:postcode":"14200",
    "sg:province":"Basse Normandie",
    "sg:tags":[
        "product",
        "special"
    ],
    "wof:name":"Sabiluc Sa",
    "wof:placetype":"venue"
},
  "geometry": {"coordinates":[-0.328299,49.203964],"type":"Point"}
}