{
  "type": "Feature",
  "properties": {
    "iso:country":"FR",
    "sg:address":"B.P. 10, 69591 L'Arbresle C\u00e9dex^^Les Bruy\u00e8res, 69210 Nuelles",
    "sg:orig_category":"Non-Classified Establishments",
    "sg:phone":"+33 4 74 01 00 44",
    "sg:postcode":"69210",
    "sg:province":"Rhone-Alpes",
    "wof:name":"Crouzet Fils S.a.",
    "wof:placetype":"venue"
},
  "geometry": {"coordinates":[4.621827,45.848305],"type":"Point"}
}