{
  "type": "Feature",
  "properties": {
    "iso:country":"FR",
    "sg:address":"3 Rue Du Maine La Noir\u00e9e 38070 St Quentin Fallavier",
    "sg:classifiers":[
        {
            "category":"Wholesale",
            "subcategory":"Meat",
            "type":"Manufacturing & Wholesale Goods"
        }
    ],
    "sg:phone":"+33 4 74 94 23 53",
    "sg:postcode":"38070",
    "sg:province":"Rhone-Alpes",
    "sg:tags":[
        "food",
        "cooked",
        "product",
        "related"
    ],
    "wof:name":"Popy Sa",
    "wof:placetype":"venue"
},
  "geometry": {"coordinates":[5.11081,45.632595],"type":"Point"}
}