{
  "type": "Feature",
  "properties": {
    "iso:country":"FR",
    "sg:address":"La Gare 71800 Gibles",
    "sg:city":"Gibles",
    "sg:orig_category":"Unclassifiable Establishments",
    "sg:phone":"+33 3 85 84 50 90",
    "sg:postcode":"71800",
    "sg:province":"Bourgogne",
    "wof:name":"Comep - Holding Mario Pizzone S.a.",
    "wof:placetype":"venue"
},
  "geometry": {"coordinates":[4.222603,46.261425],"type":"Point"}
}