{
  "type": "Feature",
  "properties": {
    "addr:full":"B.P. 519, 59059 Roubaix C\u00e9dex 1^^7, Rue de S\u00e9vign\u00e9, 59100 Roubaix Nord Pas-de-Calais 59100",
    "addr:housenumber":"b.p. 519;1;^ 7",
    "addr:postcode":"59059;59100;59100",
    "addr:street":"^;Rue De Se\u0301Vigne\u0301",
    "iso:country":"FR",
    "sg:address":"B.P. 519, 59059 Roubaix C\u00e9dex 1^^7, Rue de S\u00e9vign\u00e9, 59100 Roubaix",
    "sg:orig_category":"Non-Classified Establishments",
    "sg:phone":"+33 3 20 45 35 55",
    "sg:postcode":"59100",
    "sg:province":"Nord Pas-de-Calais",
    "wof:name":"Bossu Cuvelier S.a.",
    "wof:placetype":"venue"
},
  "geometry": {"coordinates":[3.1752,50.691704],"type":"Point"}
}