{
  "type": "Feature",
  "properties": {
    "iso:country":"FR",
    "sg:address":"57 Rue Bersot 25004 Besan\u00e7on Cedex",
    "sg:city":"Besan\u00e7on",
    "sg:classifiers":[
        {
            "category":"Utilities",
            "subcategory":"Electric",
            "type":"Services"
        }
    ],
    "sg:phone":"+33 3 81 83 84 85",
    "sg:postcode":"25000",
    "sg:province":"Franche Comt\u00e9",
    "sg:tags":[
        "electricity",
        "raw",
        "energy",
        "material"
    ],
    "wof:name":"Edf-gdf",
    "wof:placetype":"venue"
},
  "geometry": {"coordinates":[6.02996,47.239223],"type":"Point"}
}