{
  "type": "Feature",
  "properties": {
    "iso:country":"FR",
    "sg:address":"3, Rue Gutenberg - ZA de la Butte, 91620 Nozay",
    "sg:orig_category":"Non-Classified Establishments",
    "sg:phone":"+33 1 64 49 33 78",
    "sg:province":"Ile de France",
    "wof:name":"Meyer S.a.r.l.",
    "wof:placetype":"venue"
},
  "geometry": {"coordinates":[2.242235,48.66037],"type":"Point"}
}