{
  "type": "Feature",
  "properties": {
    "addr:full":"Plateau Signargues Rte D'Avignon 30390 Domazan Languedoc-Roussillon",
    "addr:postcode":"30390",
    "addr:street":"Rte D'Avignon",
    "iso:country":"FR",
    "sg:address":"Plateau Signargues Rte D'Avignon 30390 Domazan",
    "sg:classifiers":[
        {
            "category":"Manufacturing",
            "subcategory":"Paper Products",
            "type":"Manufacturing & Wholesale Goods"
        }
    ],
    "sg:phone":"+33 4 66 57 49 99",
    "sg:province":"Languedoc-Roussillon",
    "sg:tags":[
        "finished",
        "cardboard",
        "-"
    ],
    "wof:name":"Cgmp Sud Sa",
    "wof:placetype":"venue"
},
  "geometry": {"coordinates":[4.689469,43.895676],"type":"Point"}
}