{
  "type": "Feature",
  "properties": {
    "iso:country":"FR",
    "sg:address":"B.P. 323, 69154 D\u00e9cines Charpieu C\u00e9dex^^65, Av. Franklin Roosevelt, 69150 D\u00e9cines Charpieu",
    "sg:orig_category":"Non-Classified Establishments",
    "sg:phone":"+33 4 78 49 19 35",
    "sg:postcode":"69150",
    "sg:province":"Rhone-Alpes",
    "wof:name":"Elec-industrie S.a.",
    "wof:placetype":"venue"
},
  "geometry": {"coordinates":[4.95911,45.770794],"type":"Point"}
}