{
  "type": "Feature",
  "properties": {
    "iso:country":"FR",
    "sg:address":"12 all\u00e9e Luye 01150 St Vulbas",
    "sg:classifiers":[
        {
            "category":"Shopping",
            "subcategory":"Pharmacy",
            "type":"Retail Goods"
        }
    ],
    "sg:phone":"+33 4 74 46 21 90",
    "sg:province":"Rhone-Alpes",
    "sg:tags":[
        "preparation",
        "pharmaceutical"
    ],
    "wof:name":"Orgamol France S.a.",
    "wof:placetype":"venue"
},
  "geometry": {"coordinates":[5.265008,45.833897],"type":"Point"}
}