{
  "type": "Feature",
  "properties": {
    "addr:full":"30, Grande Rue, 77580 Pierre L\u00e9v\u00e9e Ile de France 77580",
    "addr:housenumber":"30",
    "addr:postcode":"77580;77580",
    "addr:street":"Grande Rue;Pierre Le\u0301Ve\u0301E Ile De France",
    "iso:country":"FR",
    "sg:address":"30, Grande Rue, 77580 Pierre L\u00e9v\u00e9e",
    "sg:orig_category":"Non-Classified Establishments",
    "sg:phone":"+33 1 60 22 21 20",
    "sg:postcode":"77580",
    "sg:province":"Ile de France",
    "wof:name":"Alpha Print / D. Technologies S.a.r.l.",
    "wof:placetype":"venue"
},
  "geometry": {"coordinates":[3.036921,48.899887],"type":"Point"}
}