{
  "type": "Feature",
  "properties": {
    "addr:full":"1, Place du Granier - Immeubles les Marelles, 35135 Chantepie Chantepie Bretagne 35135",
    "addr:housenumber":"1",
    "addr:postcode":"35135;35135",
    "addr:street":"Place Du Granier Immeubles Les Marelles",
    "iso:country":"FR",
    "sg:address":"1, Place du Granier - Immeubles les Marelles, 35135 Chantepie",
    "sg:city":"Chantepie",
    "sg:orig_category":"Unclassifiable Establishments",
    "sg:phone":"+33 2 99 41 64 30",
    "sg:postcode":"35135",
    "sg:province":"Bretagne",
    "wof:name":"Formavenir Performances",
    "wof:placetype":"venue"
},
  "geometry": {"coordinates":[-1.618863,48.08836],"type":"Point"}
}