{
  "type": "Feature",
  "properties": {
    "iso:country":"FR",
    "sg:address":"2 Route Chateauneuf 06650 Opio",
    "sg:city":"Ch\u00e2teau",
    "sg:classifiers":[
        {
            "category":"Food & Beverages",
            "subcategory":"Groceries & Convenience Stores",
            "type":"Retail Goods"
        }
    ],
    "sg:phone":"+33 4 93 77 23 03",
    "sg:postcode":"71250",
    "sg:province":"Bourgogne",
    "sg:tags":[
        "product",
        "related"
    ],
    "wof:name":"Sarl Les Moulins De La Brague",
    "wof:placetype":"venue"
},
  "geometry": {"coordinates":[6.984451,43.669598],"type":"Point"}
}