{
  "type": "Feature",
  "properties": {
    "addr:full":"16 R De Bouchain BP 55 59124 Escaudain Nord Pas-de-Calais 59124",
    "addr:housenumber":"16;55",
    "addr:postcode":"59124;59124",
    "addr:street":"R De Bouchain Bp",
    "iso:country":"FR",
    "sg:address":"16 R De Bouchain BP 55 59124 Escaudain",
    "sg:classifiers":[
        {
            "category":"Shopping",
            "type":"Retail Goods"
        }
    ],
    "sg:phone":"+33 3 27 30 20 42",
    "sg:postcode":"59124",
    "sg:province":"Nord Pas-de-Calais",
    "sg:tags":[
        "metallurgy",
        "finished",
        "-",
        "metalworking",
        "metallic"
    ],
    "wof:name":"Dessenis Sa",
    "wof:placetype":"venue"
},
  "geometry": {"coordinates":[3.363715,50.317501],"type":"Point"}
}