{
  "type": "Feature",
  "properties": {
    "addr:full":"B.P. 61, 21121 Fontaine l\u00e8s Dijon^^3, Rue de la Petite Fin - ZA, 21121 Fontaine l\u00e8s Dijon Ahuy Bourgogne 21121",
    "addr:postcode":"21121;21121;21121",
    "addr:street":"B.P. 61;Rue De La Petite Fin Za;Bourgogne",
    "iso:country":"FR",
    "sg:address":"B.P. 61, 21121 Fontaine l\u00e8s Dijon^^3, Rue de la Petite Fin - ZA, 21121 Fontaine l\u00e8s Dijon",
    "sg:city":"Ahuy",
    "sg:orig_category":"Non-Classified Establishments",
    "sg:phone":"+33 3 80 58 59 00",
    "sg:postcode":"21121",
    "sg:province":"Bourgogne",
    "wof:name":"Sicli S.a.",
    "wof:placetype":"venue"
},
  "geometry": {"coordinates":[5.028963,47.349144],"type":"Point"}
}