{
  "type": "Feature",
  "properties": {
    "iso:country":"FR",
    "sg:address":"Lieu Dit Les Freinets 74390 Chatel",
    "sg:classifiers":[
        {
            "category":"Home & Garden",
            "subcategory":"Furniture",
            "type":"Retail Goods"
        }
    ],
    "sg:phone":"+33 4 50 73 30 86",
    "sg:postcode":"74390",
    "sg:province":"Rhone-Alpes",
    "sg:tags":[
        "household",
        "wood"
    ],
    "wof:name":"L'atelier De Theo",
    "wof:placetype":"venue"
},
  "geometry": {"coordinates":[6.840885,46.268005],"type":"Point"}
}