{
  "type": "Feature",
  "properties": {
    "addr:full":"B.P. 11, 80570 Dargnies^^8, Rue Ambroise Croizat, 80570 Dargnies Picardie",
    "addr:postcode":"80570;80570",
    "addr:street":"B.P. 11;Rue Ambroise Croizat",
    "iso:country":"FR",
    "sg:address":"B.P. 11, 80570 Dargnies^^8, Rue Ambroise Croizat, 80570 Dargnies",
    "sg:orig_category":"Non-Classified Establishments",
    "sg:phone":"+33 3 22 30 73 25",
    "sg:province":"Picardie",
    "wof:name":"G.l. Usinage Marcel Lenne S.a.r.l.",
    "wof:placetype":"venue"
},
  "geometry": {"coordinates":[1.530662,50.03994],"type":"Point"}
}