{
  "type": "Feature",
  "properties": {
    "addr:full":"B.P. 43, 42161 Andr\u00e9zieux Bouth\u00e9on C\u00e9dex^^Av Beaunier - ZI Sud, 42160 Andr\u00e9zieux Bouth\u00e9on Rhone-Alpes 42160",
    "addr:postcode":"42161;beaunier zi;42160;42160",
    "addr:street":"B.P. 43;Rhone-Alpes",
    "iso:country":"FR",
    "sg:address":"B.P. 43, 42161 Andr\u00e9zieux Bouth\u00e9on C\u00e9dex^^Av Beaunier - ZI Sud, 42160 Andr\u00e9zieux Bouth\u00e9on",
    "sg:orig_category":"Non-Classified Establishments",
    "sg:phone":"+33 4 77 36 25 25",
    "sg:postcode":"42160",
    "sg:province":"Rhone-Alpes",
    "wof:name":"C.c.m.a. S.a.s. - Chaudronnerie Constructions M\u00e9caniques D'andr\u00e9zieux",
    "wof:placetype":"venue"
},
  "geometry": {"coordinates":[4.25674,45.52943],"type":"Point"}
}