{
  "type": "Feature",
  "properties": {
    "addr:full":"Rue du Moulin Le Peyrat Midi Pyr\u00e9n\u00e9es 09600",
    "addr:postcode":"09600",
    "addr:street":"Rue Du Moulin",
    "iso:country":"FR",
    "sg:address":"Rue du Moulin",
    "sg:city":"Le Peyrat",
    "sg:orig_category":"Unclassifiable Establishments",
    "sg:phone":"+33 5 61 01 11 26",
    "sg:postcode":"09600",
    "sg:province":"Midi Pyr\u00e9n\u00e9es",
    "wof:name":"Etablissements Arielux S.a.",
    "wof:placetype":"venue"
},
  "geometry": {"coordinates":[1.919055,42.955318],"type":"Point"}
}