{
  "type": "Feature",
  "properties": {
    "addr:full":"36 Rue Duquesne Lyon Rhone-Alpes 69006",
    "addr:housenumber":"36",
    "addr:postcode":"69006",
    "addr:street":"Rue Duquesne;Rhone-Alpes",
    "iso:country":"FR",
    "sg:address":"36 Rue Duquesne",
    "sg:city":"Lyon",
    "sg:classifiers":[
        {
            "category":"Banks & Credit Unions",
            "subcategory":"Financial Services",
            "type":"Services"
        }
    ],
    "sg:phone":"+33 4 72 44 27 78",
    "sg:postcode":"69006",
    "sg:province":"Rhone-Alpes",
    "sg:tags":[
        "banking",
        "finance",
        "insurance"
    ],
    "wof:name":"Fortis Assurances",
    "wof:placetype":"venue"
},
  "geometry": {"coordinates":[4.847024,45.77272],"type":"Point"}
}