{
  "type": "Feature",
  "properties": {
    "addr:full":"13 bis, Rue des Marais - Ors , 17480 Le Ch\u00e2teau d'Ol\u00e9ron Poitou-Charentes",
    "addr:housenumber":"13 bis",
    "addr:postcode":"17480",
    "addr:street":"Rue Des Marais Ors;\u0301Ron",
    "iso:country":"FR",
    "sg:address":"13 bis, Rue des Marais - Ors , 17480 Le Ch\u00e2teau d'Ol\u00e9ron",
    "sg:orig_category":"Unclassifiable Establishments",
    "sg:phone":"+33 5 46 47 72 19",
    "sg:province":"Poitou-Charentes",
    "wof:name":"Parcs & Jardins Androin S.a.r.l.",
    "wof:placetype":"venue"
},
  "geometry": {"coordinates":[-1.207101,45.873436],"type":"Point"}
}