{
  "type": "Feature",
  "properties": {
    "addr:full":"86, Rue Neuve, 29660 Carantec Carantec Bretagne 29660",
    "addr:housenumber":"86",
    "addr:postcode":"29660;29660",
    "addr:street":"Rue Neuve",
    "iso:country":"FR",
    "sg:address":"86, Rue Neuve, 29660 Carantec",
    "sg:city":"Carantec",
    "sg:orig_category":"Non-Classified Establishments",
    "sg:phone":"+33 2 98 67 00 06",
    "sg:postcode":"29660",
    "sg:province":"Bretagne",
    "wof:name":"J\u00e9z\u00e9quel Alain",
    "wof:placetype":"venue"
},
  "geometry": {"coordinates":[-3.922316,48.671494],"type":"Point"}
}