{
  "type": "Feature",
  "properties": {
    "iso:country":"FR",
    "sg:address":"8, Rue d'Amboise, 37530 Nazelles N\u00e9gron",
    "sg:city":"Cangey",
    "sg:orig_category":"Unclassifiable Establishments",
    "sg:phone":"+33 2 47 57 30 49",
    "sg:postcode":"37530",
    "sg:province":"Centre",
    "wof:name":"Huard S.a.r.l.",
    "wof:placetype":"venue"
},
  "geometry": {"coordinates":[0.98254,47.412849],"type":"Point"}
}