{
  "type": "Feature",
  "properties": {
    "iso:country":"FR",
    "sg:address":"8bis, Rue Edouard Branly, 25000 Besan\u00e7on",
    "sg:orig_category":"Non-Classified Establishments",
    "sg:phone":"+33 3 81 41 29 90",
    "sg:province":"Franche Comt\u00e9",
    "wof:name":"S.p.i.c. S.a.r.l. - Soci\u00e9t\u00e9 De Peinture Industrielle Comtoise",
    "wof:placetype":"venue"
},
  "geometry": {"coordinates":[5.968639,47.228043],"type":"Point"}
}