{
  "type": "Feature",
  "properties": {
    "addr:full":"B.P. 146, 54184 Heillecourt C\u00e9dex^^2, All\u00e9e des Paquis, 54180 Houdemont Lorraine 54180",
    "addr:housenumber":"b.p. 146",
    "addr:postcode":"54184;54180;54180",
    "addr:street":"Alle\u0301E Des Paquis",
    "iso:country":"FR",
    "sg:address":"B.P. 146, 54184 Heillecourt C\u00e9dex^^2, All\u00e9e des Paquis, 54180 Houdemont",
    "sg:orig_category":"Non-Classified Establishments",
    "sg:phone":"+33 3 83 54 04 35",
    "sg:postcode":"54180",
    "sg:province":"Lorraine",
    "wof:name":"Entreprise Walter S.a.r.l.",
    "wof:placetype":"venue"
},
  "geometry": {"coordinates":[6.194192,48.653137],"type":"Point"}
}