{
  "type": "Feature",
  "properties": {
    "addr:full":"12, Rue du Mar\u00e9chal Montgomery, 14480 Creully Creully Basse Normandie 14480",
    "addr:housenumber":"12",
    "addr:postcode":"14480;14480",
    "addr:street":"Rue Du Mare\u0301Chal Montgomery",
    "iso:country":"FR",
    "sg:address":"12, Rue du Mar\u00e9chal Montgomery, 14480 Creully",
    "sg:city":"Creully",
    "sg:orig_category":"Non-Classified Establishments",
    "sg:phone":"+33 2 31 29 46 00",
    "sg:postcode":"14480",
    "sg:province":"Basse Normandie",
    "wof:name":"Nestl\u00e9 Clinical Nutrition France",
    "wof:placetype":"venue"
},
  "geometry": {"coordinates":[-0.540198,49.286255],"type":"Point"}
}