{
  "type": "Feature",
  "properties": {
    "iso:country":"FR",
    "sg:address":"Rue Robert Estienne Zi 60400 Noyon",
    "sg:classifiers":[
        {
            "category":"Professional",
            "type":"Services"
        }
    ],
    "sg:phone":"+33 3 44 44 28 60",
    "sg:province":"Picardie",
    "sg:tags":[
        "transport",
        "road"
    ],
    "wof:name":"Transports Coppens Marcel Sa",
    "wof:placetype":"venue"
},
  "geometry": {"coordinates":[3.032583,49.575211],"type":"Point"}
}