{
  "type": "Feature",
  "properties": {
    "iso:country":"FR",
    "sg:address":"ZI les Milles - Le Tertial 1, 13851 Aix en Provence C\u00e9dex 03^^ZI les Milles - Le Tertial 1, 13850 Ai",
    "sg:orig_category":"Non-Classified Establishments",
    "sg:phone":"+33 4 42 24 42 05",
    "sg:province":"Provence-Alpes-C\u00f4te d'Azur",
    "wof:name":"Faure Herman S.a.",
    "wof:placetype":"venue"
},
  "geometry": {"coordinates":[5.541299,43.434277],"type":"Point"}
}