{
  "type": "Feature",
  "properties": {
    "addr:full":"112 Rue De General Leclerc 02600 Villers Cotter\u00eats Picardie",
    "addr:housenumber":"112",
    "addr:postcode":"02600",
    "addr:street":"Rue De General Leclerc",
    "iso:country":"FR",
    "sg:address":"112 Rue De General Leclerc 02600 Villers Cotter\u00eats",
    "sg:classifiers":[
        {
            "category":"Professional",
            "type":"Services"
        }
    ],
    "sg:phone":"+33 3 23 96 12 54",
    "sg:province":"Picardie",
    "sg:tags":[
        "transport",
        "road"
    ],
    "wof:name":"Mascitti Et Cie Sa",
    "wof:placetype":"venue"
},
  "geometry": {"coordinates":[3.079859,49.255215],"type":"Point"}
}