{
  "type": "Feature",
  "properties": {
    "iso:country":"FR",
    "sg:address":"20, Rue Troyon, 92316 S\u00e8vres C\u00e9dex",
    "sg:orig_category":"Non-Classified Establishments",
    "sg:phone":"+33 1 55 64 01 38",
    "sg:province":"California",
    "wof:name":"M.s. Relais S.a.",
    "wof:placetype":"venue"
},
  "geometry": {"coordinates":[-117.394142,34.063],"type":"Point"}
}