{
  "type": "Feature",
  "properties": {
    "iso:country":"FR",
    "sg:address":"56 Rue De La Boule D Or 45340 Nibelle",
    "sg:city":"Nibelle",
    "sg:classifiers":[
        {
            "category":"Farming",
            "subcategory":"Livestock Farm",
            "type":"Manufacturing & Wholesale Goods"
        }
    ],
    "sg:phone":"+33 2 38 32 23 67",
    "sg:postcode":"45340",
    "sg:province":"Centre",
    "sg:tags":[
        "breeding",
        "agriculture",
        "animal"
    ],
    "wof:name":"Elevage Avicole De Nibelle",
    "wof:placetype":"venue"
},
  "geometry": {"coordinates":[2.312455,48.030457],"type":"Point"}
}