{
  "type": "Feature",
  "properties": {
    "addr:full":"6 Rue Jean Pierre Timbaud 78180 Montigny Le Bretonneux Ile de France",
    "addr:housenumber":"6",
    "addr:postcode":"78180",
    "addr:street":"Rue Jean Pierre Timbaud",
    "iso:country":"FR",
    "sg:address":"6 Rue Jean Pierre Timbaud 78180 Montigny Le Bretonneux",
    "sg:classifiers":[
        {
            "category":"Utilities",
            "subcategory":"Telephone",
            "type":"Services"
        }
    ],
    "sg:phone":"+33 1 30 14 01 00",
    "sg:province":"Ile de France",
    "sg:tags":[
        "telecommunication"
    ],
    "wof:name":"Cmc Sa",
    "wof:placetype":"venue"
},
  "geometry": {"coordinates":[2.03644,48.792824],"type":"Point"}
}