{
  "type": "Feature",
  "properties": {
    "iso:country":"FR",
    "sg:address":"6 Rue Du General Lebocq 67270 Hochfelden",
    "sg:city":"Hochfelden",
    "sg:classifiers":[
        {
            "category":"Food Court",
            "type":"Food & Drink"
        }
    ],
    "sg:phone":"+33 3 88 02 22 89",
    "sg:postcode":"67270",
    "sg:province":"Alsace",
    "sg:tags":[
        "product",
        "related"
    ],
    "wof:name":"Brasserie Meteor",
    "wof:placetype":"venue"
},
  "geometry": {"coordinates":[7.56923,48.75732],"type":"Point"}
}