{
  "type": "Feature",
  "properties": {
    "iso:country":"FR",
    "sg:address":"B.P. 385, 36008 Ch\u00e2teauroux C\u00e9dex^^36, All\u00e9e des Maisons Rouges, 36330 Le Poin\u00e7onnet",
    "sg:city":"Poin\u00e7onnet",
    "sg:orig_category":"Non-Classified Establishments",
    "sg:phone":"+33 2 54 08 16 16",
    "sg:postcode":"36330",
    "sg:province":"Centre",
    "wof:name":"Indre Express S.a.",
    "wof:placetype":"venue"
},
  "geometry": {"coordinates":[1.648135,46.688477],"type":"Point"}
}