{
  "type": "Feature",
  "properties": {
    "addr:full":"B.P. 518, 76807 Saint Etienne du Rouvray C\u00e9dex^^Bd Industriel, 76800 Saint Etienne du Rouvray Haute Normandie",
    "addr:housenumber":"b.p. 518",
    "addr:postcode":"76807;76800",
    "addr:street":"Industriel;Haute Normandie",
    "iso:country":"FR",
    "sg:address":"B.P. 518, 76807 Saint Etienne du Rouvray C\u00e9dex^^Bd Industriel, 76800 Saint Etienne du Rouvray",
    "sg:orig_category":"Non-Classified Establishments",
    "sg:phone":"+33 2 35 64 39 39",
    "sg:province":"Haute Normandie",
    "wof:name":"Sodipan Transformation S.a.",
    "wof:placetype":"venue"
},
  "geometry": {"coordinates":[1.064498,49.390778],"type":"Point"}
}