{
  "type": "Feature",
  "properties": {
    "addr:full":"Rue De L'Abattoir 40700 Hagetmau Hagetmau Aquitaine 40700",
    "addr:postcode":"40700;40700",
    "addr:street":"Rue De L'Abattoir",
    "iso:country":"FR",
    "sg:address":"Rue De L'Abattoir 40700 Hagetmau",
    "sg:city":"Hagetmau",
    "sg:classifiers":[
        {
            "category":"Wholesale",
            "subcategory":"Meat",
            "type":"Manufacturing & Wholesale Goods"
        }
    ],
    "sg:phone":"+33 5 58 79 84 84",
    "sg:postcode":"40700",
    "sg:province":"Aquitaine",
    "sg:tags":[
        "food",
        "cooked",
        "product",
        "related"
    ],
    "wof:name":"Ets Baillet Sa",
    "wof:placetype":"venue"
},
  "geometry": {"coordinates":[-0.59036,43.627151],"type":"Point"}
}