{
  "type": "Feature",
  "properties": {
    "addr:full":"21, Rue Chemin Vert, 59770 Marly Nord Pas-de-Calais",
    "addr:housenumber":"21",
    "addr:postcode":"59770",
    "addr:street":"Rue Chemin Vert",
    "iso:country":"FR",
    "sg:address":"21, Rue Chemin Vert, 59770 Marly",
    "sg:orig_category":"Unclassifiable Establishments",
    "sg:phone":"+33 3 27 33 53 34",
    "sg:province":"Nord Pas-de-Calais",
    "wof:name":"Imprimerie Gantier S.a.r.l.",
    "wof:placetype":"venue"
},
  "geometry": {"coordinates":[3.538587,50.355282],"type":"Point"}
}