{
  "type": "Feature",
  "properties": {
    "addr:full":"44 Rue Des Carri\u00e8res BP 9 67350 Pfaffenhoffen Pfaffenhoffen Alsace 67350",
    "addr:housenumber":"44;9",
    "addr:postcode":"67350;67350",
    "addr:street":"Rue Des Carrie\u0300Res Bp",
    "iso:country":"FR",
    "sg:address":"44 Rue Des Carri\u00e8res BP 9 67350 Pfaffenhoffen",
    "sg:city":"Pfaffenhoffen",
    "sg:classifiers":[
        {
            "category":"Professional",
            "type":"Services"
        }
    ],
    "sg:phone":"+33 3 88 07 74 40",
    "sg:postcode":"67350",
    "sg:province":"Alsace",
    "sg:tags":[
        "transport",
        "road"
    ],
    "wof:name":"Trtp Bergantz Josephe Et Fils",
    "wof:placetype":"venue"
},
  "geometry": {"coordinates":[7.611261,48.843704],"type":"Point"}
}