{
  "type": "Feature",
  "properties": {
    "addr:full":"21, Av du G\u00e9n\u00e9ral Sarrail, 90000 Belfort Franche Comt\u00e9",
    "addr:postcode":"90000",
    "addr:street":"21 Av Du Ge\u0301Ne\u0301Ral Sarrail;Franche Comte\u0301",
    "iso:country":"FR",
    "sg:address":"21, Av du G\u00e9n\u00e9ral Sarrail, 90000 Belfort",
    "sg:orig_category":"Non-Classified Establishments",
    "sg:phone":"+33 3 84 21 75 91",
    "sg:province":"Franche Comt\u00e9",
    "wof:name":"S\u00e9rigraphie Monami S.a.",
    "wof:placetype":"venue"
},
  "geometry": {"coordinates":[6.861931,47.634884],"type":"Point"}
}