{
  "type": "Feature",
  "properties": {
    "addr:full":"B.P. 5, 16101 Cognac C\u00e9dex^^1, Rue Samuel de Champlain, 16100 Ch\u00e2teaubernard Poitou-Charentes",
    "addr:housenumber":"5",
    "addr:postcode":"16101;16100",
    "addr:street":"B.P.;Rue Samuel De Champlain",
    "iso:country":"FR",
    "sg:address":"B.P. 5, 16101 Cognac C\u00e9dex^^1, Rue Samuel de Champlain, 16100 Ch\u00e2teaubernard",
    "sg:orig_category":"Non-Classified Establishments",
    "sg:phone":"+33 5 45 36 31 32",
    "sg:province":"Poitou-Charentes",
    "wof:name":"Jean-fran\u00e7ois Hillebrand France S.a.",
    "wof:placetype":"venue"
},
  "geometry": {"coordinates":[-0.313384,45.67149],"type":"Point"}
}