{
  "type": "Feature",
  "properties": {
    "addr:full":"41 Rue D'Elbeuf 76100 Rouen Haute Normandie 76100",
    "addr:housenumber":"41",
    "addr:postcode":"76100;76100",
    "addr:street":"Rue D'Elbeuf;Haute Normandie",
    "iso:country":"FR",
    "sg:address":"41 Rue D'Elbeuf 76100 Rouen",
    "sg:classifiers":[
        {
            "category":"Professional",
            "subcategory":"Computer Services",
            "type":"Services"
        }
    ],
    "sg:phone":"+33 2 32 81 65 81",
    "sg:postcode":"76100",
    "sg:province":"Haute Normandie",
    "sg:tags":[
        "information",
        "technology",
        "software"
    ],
    "wof:name":"Axilog",
    "wof:placetype":"venue"
},
  "geometry": {"coordinates":[1.084794,49.428581],"type":"Point"}
}