{
  "type": "Feature",
  "properties": {
    "addr:full":"Av. Jean jaur\u00e8s Montm\u00e9lian Rhone-Alpes 73800",
    "addr:postcode":"73800",
    "addr:street":"Av. Jean Jaure\u0300S;Rhone-Alpes",
    "iso:country":"FR",
    "sg:address":"Av. Jean jaur\u00e8s",
    "sg:city":"Montm\u00e9lian",
    "sg:orig_category":"Non-Classified Establishments",
    "sg:phone":"+33 4 79 84 34 50",
    "sg:postcode":"73800",
    "sg:province":"Rhone-Alpes",
    "wof:name":"Philibert Braillon Groupe S.a.",
    "wof:placetype":"venue"
},
  "geometry": {"coordinates":[6.06713,45.502804],"type":"Point"}
}