{
  "type": "Feature",
  "properties": {
    "addr:full":"Malmaison Champagne",
    "iso:country":"FR",
    "sg:address":"Malmaison",
    "sg:classifiers":[
        {
            "category":"Banks & Credit Unions",
            "subcategory":"Bank",
            "type":"Services"
        }
    ],
    "sg:province":"Champagne",
    "wof:name":"Storagetek Location Sarl",
    "wof:placetype":"venue"
},
  "geometry": {"coordinates":[-90.01226800000001,33.50132],"type":"Point"}
}