{
  "type": "Feature",
  "properties": {
    "addr:full":"2 Rue Des Canadiens Airaines Picardie 80270",
    "addr:housenumber":"2",
    "addr:postcode":"80270",
    "addr:street":"Rue Des Canadiens;Picardie",
    "iso:country":"FR",
    "sg:address":"2 Rue Des Canadiens",
    "sg:city":"Airaines",
    "sg:classifiers":[
        {
            "category":"Banks & Credit Unions",
            "subcategory":"Financial Services",
            "type":"Services"
        }
    ],
    "sg:phone":"+33 3 22 29 40 49",
    "sg:postcode":"80270",
    "sg:province":"Picardie",
    "sg:tags":[
        "banking",
        "finance",
        "insurance"
    ],
    "wof:name":"Caisse Regional E De Credit Agricole Mutuel De La Somme",
    "wof:placetype":"venue"
},
  "geometry": {"coordinates":[1.940587,49.956776],"type":"Point"}
}