{
  "type": "Feature",
  "properties": {
    "iso:country":"FR",
    "sg:address":"20, Rue des Parisiens, 92600 Asni\u00e8res sur Seine",
    "sg:orig_category":"Unclassifiable Establishments",
    "sg:phone":"+33 1 47 33 23 15",
    "sg:province":"Ile de France",
    "wof:name":"Entreprise Legrand S.a.",
    "wof:placetype":"venue"
},
  "geometry": {"coordinates":[2.283458,48.916168],"type":"Point"}
}