{
  "type": "Feature",
  "properties": {
    "addr:full":"Zi Le Pavillon 87200 St Junien Limousin 87200",
    "addr:postcode":"87200;87200",
    "addr:street":"Zi Le",
    "iso:country":"FR",
    "sg:address":"Zi Le Pavillon 87200 St Junien",
    "sg:classifiers":[
        {
            "category":"Shopping",
            "subcategory":"Clothing, Apparel, & Fashions",
            "type":"Retail Goods"
        }
    ],
    "sg:phone":"+33 5 55 02 14 81",
    "sg:postcode":"87200",
    "sg:province":"Limousin",
    "sg:tags":[
        "textile",
        "clothing",
        "clothes"
    ],
    "wof:name":"Pelleterie Fourrures Du Grand Nord",
    "wof:placetype":"venue"
},
  "geometry": {"coordinates":[0.939449,45.904026],"type":"Point"}
}