{
  "type": "Feature",
  "properties": {
    "addr:full":"9 RUE DOCTEUR PAUL MICHELON 42100 ST ETIENNE Rhone-Alpes 42100",
    "addr:housenumber":"9",
    "addr:postcode":"42100;42100",
    "addr:street":"Rue Docteur Paul Michelon",
    "iso:country":"FR",
    "sg:address":"9 RUE DOCTEUR PAUL MICHELON 42100 ST ETIENNE",
    "sg:classifiers":[
        {
            "category":"Shopping",
            "subcategory":"Clothing, Apparel, & Fashions",
            "type":"Retail Goods"
        }
    ],
    "sg:phone":"+33 4 77 25 26 92",
    "sg:postcode":"42100",
    "sg:province":"Rhone-Alpes",
    "sg:tags":[
        "blouse",
        "ladies'",
        "dress"
    ],
    "wof:name":"Chrismas S Sa",
    "wof:placetype":"venue"
},
  "geometry": {"coordinates":[4.423589,45.424438],"type":"Point"}
}