{
  "type": "Feature",
  "properties": {
    "addr:full":"B.P. 68, 54320 Max\u00e9ville^^33, Rue Andr\u00e9 Fruchard, 54320 Max\u00e9ville Lorraine 54320",
    "addr:postcode":"54320;54320;54320",
    "addr:street":"B.P. 68;Rue Andre\u0301 Fruchard",
    "iso:country":"FR",
    "sg:address":"B.P. 68, 54320 Max\u00e9ville^^33, Rue Andr\u00e9 Fruchard, 54320 Max\u00e9ville",
    "sg:orig_category":"Non-Classified Establishments",
    "sg:phone":"+33 3 83 37 92 63",
    "sg:postcode":"54320",
    "sg:province":"Lorraine",
    "wof:name":"E.i.m. - Electricit\u00e9 Industrielle Maxevilloise",
    "wof:placetype":"venue"
},
  "geometry": {"coordinates":[6.16249,48.712032],"type":"Point"}
}