{
  "type": "Feature",
  "properties": {
    "addr:full":"105, Rue du G\u00e9n\u00e9ral Leclerc, 67440 Marmoutier Marmoutier Alsace 67440",
    "addr:housenumber":"105",
    "addr:postcode":"67440;67440",
    "addr:street":"Rue Du Ge\u0301Ne\u0301Ral Leclerc",
    "iso:country":"FR",
    "sg:address":"105, Rue du G\u00e9n\u00e9ral Leclerc, 67440 Marmoutier",
    "sg:city":"Marmoutier",
    "sg:orig_category":"Unclassifiable Establishments",
    "sg:phone":"+33 3 88 70 62 00",
    "sg:postcode":"67440",
    "sg:province":"Alsace",
    "wof:name":"Eurofarad S.a.",
    "wof:placetype":"venue"
},
  "geometry": {"coordinates":[7.382639,48.689083],"type":"Point"}
}