{
  "type": "Feature",
  "properties": {
    "addr:full":"42, Rue de la Lib\u00e9ration, 88460 Docelles Lorraine",
    "addr:housenumber":"42",
    "addr:postcode":"88460",
    "addr:street":"Rue De La Libe\u0301Ration",
    "iso:country":"FR",
    "sg:address":"42, Rue de la Lib\u00e9ration, 88460 Docelles",
    "sg:orig_category":"Unclassifiable Establishments",
    "sg:phone":"+33 3 29 42 11 03",
    "sg:province":"Lorraine",
    "wof:name":"Cartonnerie Paul Jacquemin S.a.",
    "wof:placetype":"venue"
},
  "geometry": {"coordinates":[6.617412,48.144684],"type":"Point"}
}