{
  "type": "Feature",
  "properties": {
    "addr:full":"RD 13 Carnoules 83660",
    "addr:postcode":"83660",
    "addr:street":"Rd 13",
    "iso:country":"FR",
    "sg:address":"RD 13",
    "sg:city":"Carnoules",
    "sg:orig_category":"Unclassifiable Establishments",
    "sg:phone":"+33 4 98 01 80 08",
    "sg:postcode":"83660",
    "wof:name":"Domaine Du Grand Cros E.u.r.l.",
    "wof:placetype":"venue"
},
  "geometry": {"coordinates":[6.18908,43.30241],"type":"Point"}
}