{
  "type": "Feature",
  "properties": {
    "iso:country":"FR",
    "sg:address":"5, Rue du Pont de Fer, 12100 Millau",
    "sg:orig_category":"Non-Classified Establishments",
    "sg:phone":"+33 5 65 60 52 44",
    "sg:province":"Midi Pyr\u00e9n\u00e9es",
    "wof:name":"S.e.g.a.p. S.a.",
    "wof:placetype":"venue"
},
  "geometry": {"coordinates":[3.081089,44.095909],"type":"Point"}
}