{
  "type": "Feature",
  "properties": {
    "addr:full":"3, Rue Saint Joseph, 75002 Paris Ile de France",
    "addr:housenumber":"3",
    "addr:postcode":"75002",
    "addr:street":"Rue Saint Joseph",
    "iso:country":"FR",
    "sg:address":"3, Rue Saint Joseph, 75002 Paris",
    "sg:orig_category":"Unclassifiable Establishments",
    "sg:phone":"+33 1 40 26 46 42",
    "sg:province":"Ile de France",
    "wof:name":"Mille Et Une S.a.r.l.",
    "wof:placetype":"venue"
},
  "geometry": {"coordinates":[2.345082,48.868267],"type":"Point"}
}