{
  "type": "Feature",
  "properties": {
    "addr:full":"99, Rue Nationale, 59012 Lille Nord-Pas-de-Calais",
    "addr:housenumber":"99",
    "addr:postcode":"59012",
    "addr:street":"Rue Nationale",
    "iso:country":"FR",
    "sg:address":"99, Rue Nationale, 59012 Lille",
    "sg:orig_category":"Unclassifiable Establishments",
    "sg:phone":"+33 3 20 12 56 00",
    "sg:province":"Nord-Pas-de-Calais",
    "wof:name":"S.c.p. Delpierre Delattre Et Associ\u00e9s",
    "wof:placetype":"venue"
},
  "geometry": {"coordinates":[3.057487,50.634747],"type":"Point"}
}