{
  "type": "Feature",
  "properties": {
    "iso:country":"FR",
    "sg:address":"93 Pl Pierre Duhem Immeuble Les Centuries Le Mill\u00e9naire 2 34000 Montpellier",
    "sg:classifiers":[
        {
            "category":"Banks & Credit Unions",
            "subcategory":"Financial Services",
            "type":"Services"
        }
    ],
    "sg:phone":"+33 4 67 20 31 00",
    "sg:postcode":"34000",
    "sg:province":"Languedoc-Roussillon",
    "sg:tags":[
        "banking",
        "insurance",
        "institution",
        "finance"
    ],
    "wof:name":"Credit Lyonnais",
    "wof:placetype":"venue"
},
  "geometry": {"coordinates":[3.914571,43.60688],"type":"Point"}
}