{
  "type": "Feature",
  "properties": {
    "addr:full":"335, Av. du Ch\u00e2teau, 34093 Montpellier C\u00e9dex 5 Languedoc-Roussillon",
    "addr:housenumber":"5",
    "addr:postcode":"34093",
    "addr:street":"335 Av. Du Cha\u0302Teau;Ce\u0301Dex",
    "iso:country":"FR",
    "sg:address":"335, Av. du Ch\u00e2teau, 34093 Montpellier C\u00e9dex 5",
    "sg:orig_category":"Non-Classified Establishments",
    "sg:phone":"+33 4 67 41 65 41",
    "sg:province":"Languedoc-Roussillon",
    "wof:name":"S.i.e.e. S.a.r.l. - Soci\u00e9t\u00e9 D'ing\u00e9nierie Pour L'eau Et L'environnemen",
    "wof:placetype":"venue"
},
  "geometry": {"coordinates":[3.84122,43.62748],"type":"Point"}
}