{
  "type": "Feature",
  "properties": {
    "addr:full":"8 Bis Rue Dieu 75010 Paris Ile de France 75010",
    "addr:housenumber":"8 bis",
    "addr:postcode":"75010;75010",
    "addr:street":"Rue Dieu",
    "iso:country":"FR",
    "sg:address":"8 Bis Rue Dieu 75010 Paris",
    "sg:classifiers":[
        {
            "category":"Shopping",
            "subcategory":"Clothing, Apparel, & Fashions",
            "type":"Retail Goods"
        }
    ],
    "sg:phone":"+33 1 53 38 48 20",
    "sg:postcode":"75010",
    "sg:province":"Ile de France",
    "sg:tags":[
        "textile",
        "clothing",
        "clothes"
    ],
    "wof:name":"Uniform",
    "wof:placetype":"venue"
},
  "geometry": {"coordinates":[2.364616,48.870182],"type":"Point"}
}