{
  "type": "Feature",
  "properties": {
    "addr:full":"4, Rue Edouard Mignot, 51000 Reims Champagne",
    "addr:housenumber":"4",
    "addr:postcode":"51000",
    "addr:street":"Rue Edouard Mignot",
    "iso:country":"FR",
    "sg:address":"4, Rue Edouard Mignot, 51000 Reims",
    "sg:orig_category":"Unclassifiable Establishments",
    "sg:phone":"+33 3 26 79 82 70",
    "sg:province":"Champagne",
    "wof:name":"A.p.e.c. - Association Pour L'emploi Des Cadres",
    "wof:placetype":"venue"
},
  "geometry": {"coordinates":[4.021272,49.259926],"type":"Point"}
}