{
  "type": "Feature",
  "properties": {
    "addr:full":"18, Bd de Belgique, 42300 Roanne Rhone-Alpes 42300",
    "addr:housenumber":"18",
    "addr:postcode":"42300;42300",
    "addr:street":"Bd De Belgique;Rhone-Alpes",
    "iso:country":"FR",
    "sg:address":"18, Bd de Belgique, 42300 Roanne",
    "sg:orig_category":"Non-Classified Establishments",
    "sg:phone":"+33 4 77 71 67 02",
    "sg:postcode":"42300",
    "sg:province":"Rhone-Alpes",
    "wof:name":"Cabinet Guy Meyrieux S.a.",
    "wof:placetype":"venue"
},
  "geometry": {"coordinates":[4.078134,46.045261],"type":"Point"}
}