{
  "type": "Feature",
  "properties": {
    "addr:full":"2 Pl Ren\u00e9 Cassin 56408 Auray Cedex Bretagne",
    "addr:housenumber":"2",
    "addr:postcode":"56408;cedex",
    "addr:street":"Pl Rene\u0301 Cassin",
    "iso:country":"FR",
    "sg:address":"2 Pl Ren\u00e9 Cassin 56408 Auray Cedex",
    "sg:classifiers":[
        {
            "category":"Wholesale",
            "subcategory":"Chemicals & Plastics",
            "type":"Manufacturing & Wholesale Goods"
        }
    ],
    "sg:phone":"+33 2 97 24 42 00",
    "sg:province":"Bretagne",
    "sg:tags":[
        "pharmaceutical",
        "energy",
        "material",
        "-",
        "raw",
        "chemistry",
        "by-product"
    ],
    "wof:name":"Saur",
    "wof:placetype":"venue"
},
  "geometry": {"coordinates":[-2.982301,47.665485],"type":"Point"}
}