{
  "type": "Feature",
  "properties": {
    "iso:country":"FR",
    "sg:address":"55, Bd Bineau, 92200 Neuilly sur Seine",
    "sg:orig_category":"Non-Classified Establishments",
    "sg:phone":"+33 1 47 57 83 65",
    "sg:province":"Ile de France",
    "wof:name":"Pierson Et Compagnie S.a.r.l.",
    "wof:placetype":"venue"
},
  "geometry": {"coordinates":[2.282033,48.886799],"type":"Point"}
}