{
  "type": "Feature",
  "properties": {
    "addr:full":"55 boulevard Richard-Lenoir 75011 Paris Ile de France 75011",
    "addr:housenumber":"55",
    "addr:postcode":"75011;75011",
    "addr:street":"Boulevard Richard-Lenoir",
    "iso:country":"FR",
    "sg:address":"55 boulevard Richard-Lenoir 75011 Paris",
    "sg:classifiers":[
        {
            "category":"Building & Trades",
            "subcategory":"Equipment Rental",
            "type":"Services"
        }
    ],
    "sg:phone":"+33 1 53 36 36 36",
    "sg:postcode":"75011",
    "sg:province":"Ile de France",
    "sg:tags":[
        "first-aid"
    ],
    "wof:name":"Etab Edouard Rousseau Sa",
    "wof:placetype":"venue"
},
  "geometry": {"coordinates":[2.371765,48.859879],"type":"Point"}
}