{
  "type": "Feature",
  "properties": {
    "iso:country":"FR",
    "sg:address":"Route Beauvoir 85300 Challans",
    "sg:classifiers":[
        {
            "category":"Building & Trades",
            "subcategory":"Construction",
            "type":"Services"
        }
    ],
    "sg:phone":"+33 2 51 93 05 87",
    "sg:postcode":"85300",
    "sg:province":"Pays de Loire",
    "sg:tags":[
        "work",
        "public"
    ],
    "wof:name":"Henri Merceron Sa",
    "wof:placetype":"venue"
},
  "geometry": {"coordinates":[-1.879324,46.845879],"type":"Point"}
}