{
  "type": "Feature",
  "properties": {
    "addr:full":"Beg Rohu 56510 St. Pierre Quiberon Saint-Pierre-Quiberon Bretagne 56510",
    "addr:postcode":"56510;saint-pierre-quiberon;56510",
    "addr:street":"Rohu",
    "iso:country":"FR",
    "sg:address":"Beg Rohu 56510 St. Pierre Quiberon",
    "sg:city":"Saint-Pierre-Quiberon",
    "sg:classifiers":[
        {
            "category":"Professional",
            "subcategory":"Business Services",
            "type":"Services"
        }
    ],
    "sg:phone":"+33 2 97 30 30 30",
    "sg:postcode":"56510",
    "sg:province":"Bretagne",
    "sg:tags":[
        "training",
        "advice"
    ],
    "wof:name":"Ecole Nationale De Voile",
    "wof:placetype":"venue"
},
  "geometry": {"coordinates":[-3.120978,47.508278],"type":"Point"}
}