{
  "type": "Feature",
  "properties": {
    "addr:full":"14, Rue Moreau, 75012 Paris Ile de France 75012",
    "addr:housenumber":"14",
    "addr:postcode":"75012;75012",
    "addr:street":"Rue Moreau",
    "iso:country":"FR",
    "sg:address":"14, Rue Moreau, 75012 Paris",
    "sg:orig_category":"Non-Classified Establishments",
    "sg:phone":"+33 1 43 43 30 52",
    "sg:postcode":"75012",
    "sg:province":"Ile de France",
    "wof:name":"Arte Fact - Diane Diffusion S.a.",
    "wof:placetype":"venue"
},
  "geometry": {"coordinates":[2.372793,48.849716],"type":"Point"}
}