{
  "type": "Feature",
  "properties": {
    "iso:country":"FR",
    "sg:address":"15, Rue des Drapiers - ZI Metz Borny, 57070 Metz",
    "sg:orig_category":"Unclassifiable Establishments",
    "sg:phone":"+33 3 87 75 25 33",
    "sg:province":"Lorraine",
    "wof:name":"Callith\u00e9a S.a.",
    "wof:placetype":"venue"
},
  "geometry": {"coordinates":[6.202294,49.133659],"type":"Point"}
}