{
  "type": "Feature",
  "properties": {
    "addr:full":"Rte de Baume les Dames - ZA de la Gr\u00e2ce Dieu Vercel Villedieu le Camp Franche Comt\u00e9 25530",
    "addr:postcode":"25530",
    "addr:street":"Rte De Baume;Za De La Gra\u0302Ce;Franche Comte\u0301",
    "iso:country":"FR",
    "sg:address":"Rte de Baume les Dames - ZA de la Gr\u00e2ce Dieu",
    "sg:city":"Vercel Villedieu le Camp",
    "sg:orig_category":"Unclassifiable Establishments",
    "sg:phone":"+33 3 81 56 39 00",
    "sg:postcode":"25530",
    "sg:province":"Franche Comt\u00e9",
    "wof:name":"M.h.t. S.a. - M\u00e9canique De Haute Technologie",
    "wof:placetype":"venue"
},
  "geometry": {"coordinates":[6.396401,47.185013],"type":"Point"}
}