{
  "type": "Feature",
  "properties": {
    "addr:full":"10, Rue de la Chancellerie - Place du Ch\u00e2teau, 78000 Versailles Ile de France",
    "addr:housenumber":"10",
    "addr:postcode":"78000",
    "addr:street":"Rue De La Chancellerie Place Du Cha\u0302Teau",
    "iso:country":"FR",
    "sg:address":"10, Rue de la Chancellerie - Place du Ch\u00e2teau, 78000 Versailles",
    "sg:orig_category":"Non-Classified Establishments",
    "sg:phone":"+33 1 30 97 89 00",
    "sg:province":"Ile de France",
    "wof:name":"Palais Des Congr\u00e9s De Versailles",
    "wof:placetype":"venue"
},
  "geometry": {"coordinates":[2.13112,48.801933],"type":"Point"}
}