{
  "type": "Feature",
  "properties": {
    "addr:full":"Av de Fr\u00e9jus - RN 7 Mandelieu la Napoule Haute Normandie 06210",
    "addr:postcode":"06210",
    "addr:street":"Av De Fre\u0301Jus Rn 7;Haute Normandie",
    "iso:country":"FR",
    "sg:address":"Av de Fr\u00e9jus - RN 7",
    "sg:city":"Mandelieu la Napoule",
    "sg:orig_category":"Unclassifiable Establishments",
    "sg:phone":"+33 4 92 97 48 00",
    "sg:postcode":"06210",
    "sg:province":"Haute Normandie",
    "wof:name":"S.n.p. S.a.r.l. - Soci\u00e9t\u00e9 Nouvelle Parachini",
    "wof:placetype":"venue"
},
  "geometry": {"coordinates":[6.93623,43.542488],"type":"Point"}
}