{
  "type": "Feature",
  "properties": {
    "iso:country":"FR",
    "sg:address":"B.P. 14, 60570 Andeville^^Zone Industrielle d'Angleterre, 60570 Andeville",
    "sg:orig_category":"Non-Classified Establishments",
    "sg:phone":"+33 3 44 52 14 82",
    "sg:province":"Picardie",
    "wof:name":"Victor S.a.",
    "wof:placetype":"venue"
},
  "geometry": {"coordinates":[2.16133,49.26907],"type":"Point"}
}