{
  "type": "Feature",
  "properties": {
    "iso:country":"FR",
    "sg:address":"59 Rue Leclerc Neustadtmuhle 57850 Dabo",
    "sg:classifiers":[
        {
            "category":"Manufacturing",
            "subcategory":"Glass & Minerals",
            "type":"Manufacturing & Wholesale Goods"
        }
    ],
    "sg:phone":"+33 3 87 07 45 96",
    "sg:postcode":"57850",
    "sg:province":"Lorraine",
    "sg:tags":[
        "building",
        "material"
    ],
    "wof:name":"Cristal Lehrer Bruno Eurl",
    "wof:placetype":"venue"
},
  "geometry": {"coordinates":[7.23636,48.653488],"type":"Point"}
}