{
  "type": "Feature",
  "properties": {
    "addr:full":"Z I Les Eaux Blanches 34200 Sete Languedoc-Roussillon 34200",
    "addr:postcode":"34200;34200",
    "addr:street":"Z I Les;Blanches",
    "iso:country":"FR",
    "sg:address":"Z I Les Eaux Blanches 34200 Sete",
    "sg:classifiers":[
        {
            "category":"Home & Garden",
            "subcategory":"Household Appliances",
            "type":"Retail Goods"
        }
    ],
    "sg:phone":"+33 4 67 51 68 78",
    "sg:postcode":"34200",
    "sg:province":"Languedoc-Roussillon",
    "sg:tags":[
        "electric"
    ],
    "wof:name":"Service Radio Menager Sa",
    "wof:placetype":"venue"
},
  "geometry": {"coordinates":[3.69633,43.399052],"type":"Point"}
}