{
  "type": "Feature",
  "properties": {
    "iso:country":"FR",
    "sg:address":"94, Av. Cyrnos, 06100 Nice",
    "sg:orig_category":"Unclassifiable Establishments",
    "sg:phone":"+33 4 93 52 70 51",
    "sg:province":"Picardie",
    "wof:name":"A.c. Cr\u00e9ation S.a.r.l.",
    "wof:placetype":"venue"
},
  "geometry": {"coordinates":[7.25046,43.716717],"type":"Point"}
}