{
  "type": "Feature",
  "properties": {
    "addr:full":"12 Rue Andre Citroen 31130 Balma Midi Pyr\u00e9n\u00e9es",
    "addr:housenumber":"12",
    "addr:postcode":"31130",
    "addr:street":"Rue Andre Citroen",
    "iso:country":"FR",
    "sg:address":"12 Rue Andre Citroen 31130 Balma",
    "sg:classifiers":[
        {
            "category":"Manufacturing",
            "subcategory":"Wood Products",
            "type":"Manufacturing & Wholesale Goods"
        }
    ],
    "sg:phone":"+33 5 62 57 01 40",
    "sg:province":"Midi Pyr\u00e9n\u00e9es",
    "sg:tags":[
        "professional",
        "furniture"
    ],
    "wof:name":"Deco Design",
    "wof:placetype":"venue"
},
  "geometry": {"coordinates":[1.486319,43.627998],"type":"Point"}
}