{
  "type": "Feature",
  "properties": {
    "addr:full":"Impasse de l'Ecureuil 25048 BESANCON Besan\u00e7on Franche Comt\u00e9 25000",
    "addr:postcode":"25048;25000",
    "addr:street":"Impasse De L'Ecureuil;Franche Comte\u0301",
    "iso:country":"FR",
    "sg:address":"Impasse de l'Ecureuil 25048 BESANCON",
    "sg:city":"Besan\u00e7on",
    "sg:classifiers":[
        {
            "category":"Manufacturing",
            "subcategory":"Motor Vehicles & Parts",
            "type":"Manufacturing & Wholesale Goods"
        }
    ],
    "sg:phone":"+33 3 81 88 52 66",
    "sg:postcode":"25000",
    "sg:province":"Franche Comt\u00e9",
    "sg:tags":[
        "precision",
        "mechanic"
    ],
    "wof:name":"Safitec Sa",
    "wof:placetype":"venue"
},
  "geometry": {"coordinates":[6.000309,47.313362],"type":"Point"}
}