{
  "type": "Feature",
  "properties": {
    "addr:full":"48 Rue Decomberousse 69100 Villeurbanne Rhone-Alpes 69100",
    "addr:housenumber":"48",
    "addr:postcode":"69100;69100",
    "addr:street":"Rue Decomberousse",
    "iso:country":"FR",
    "sg:address":"48 Rue Decomberousse 69100 Villeurbanne",
    "sg:classifiers":[
        {
            "category":"Manufacturing",
            "subcategory":"Rubber & Plastics",
            "type":"Manufacturing & Wholesale Goods"
        }
    ],
    "sg:phone":"+33 4 78 41 00 41",
    "sg:postcode":"69100",
    "sg:province":"Rhone-Alpes",
    "sg:tags":[
        "metallurgy",
        "finished",
        "-",
        "metalworking",
        "metallic"
    ],
    "wof:name":"Soremo Societe De Realisation De Moules",
    "wof:placetype":"venue"
},
  "geometry": {"coordinates":[4.91685,45.761665],"type":"Point"}
}