{
  "type": "Feature",
  "properties": {
    "addr:full":"184, Mont\u00e9e de la Velette, 69140 Rillieux la Pape Rhone-Alpes 69140",
    "addr:housenumber":"184",
    "addr:postcode":"69140;69140",
    "addr:street":"Monte\u0301E De La Velette",
    "iso:country":"FR",
    "sg:address":"184, Mont\u00e9e de la Velette, 69140 Rillieux la Pape",
    "sg:orig_category":"Non-Classified Establishments",
    "sg:phone":"+33 4 78 88 85 64",
    "sg:postcode":"69140",
    "sg:province":"Rhone-Alpes",
    "wof:name":"Demeter Plastiques S.a.r.l.",
    "wof:placetype":"venue"
},
  "geometry": {"coordinates":[4.90548,45.813179],"type":"Point"}
}