{
  "type": "Feature",
  "properties": {
    "iso:country":"FR",
    "sg:address":"203, Av. de l'Argonne, 33700 M\u00e9rignac",
    "sg:city":"M\u00e9rignac",
    "sg:orig_category":"Unclassifiable Establishments",
    "sg:phone":"+33 5 56 55 53 37",
    "sg:postcode":"33700",
    "sg:province":"Aquitaine",
    "wof:name":"Coger S.a. - Compagnie De Gestion De Rechanges A\u00e9ronautiques",
    "wof:placetype":"venue"
},
  "geometry": {"coordinates":[-0.678885,44.826828],"type":"Point"}
}