{
  "type": "Feature",
  "properties": {
    "iso:country":"FR",
    "sg:address":"Pech d'Ang\u00e9ly Sud 46001 CAHORS CEDEX 9",
    "sg:classifiers":[
        {
            "category":"Wholesale",
            "subcategory":"Wine & Distilled Alcoholic Beverages",
            "type":"Manufacturing & Wholesale Goods"
        }
    ],
    "sg:phone":"+33 5 65 35 26 47",
    "sg:province":"Centre",
    "sg:tags":[
        "french"
    ],
    "wof:name":"Ets L.e. Reutenauer Sarl",
    "wof:placetype":"venue"
},
  "geometry": {"coordinates":[1.44299,44.445499],"type":"Point"}
}