{
  "type": "Feature",
  "properties": {
    "iso:country":"FR",
    "sg:address":"Route D'Ormes 45770 Saran",
    "sg:city":"Saran",
    "sg:classifiers":[
        {
            "category":"Professional",
            "type":"Services"
        }
    ],
    "sg:phone":"+33 2 38 78 70 25",
    "sg:postcode":"45770",
    "sg:province":"Centre",
    "sg:tags":[
        "transport",
        "road"
    ],
    "wof:name":"Transports Lucien Robinet",
    "wof:placetype":"venue"
},
  "geometry": {"coordinates":[1.88065,47.94767],"type":"Point"}
}