{
  "type": "Feature",
  "properties": {
    "iso:country":"FR",
    "sg:address":"Rue de la Taille",
    "sg:city":"Vaucouleurs",
    "sg:orig_category":"Unclassifiable Establishments",
    "sg:phone":"+33 3 29 89 46 91",
    "sg:postcode":"55140",
    "sg:province":"Lorraine",
    "wof:name":"France Emballages S.a.",
    "wof:placetype":"venue"
},
  "geometry": {"coordinates":[5.665625,48.605946],"type":"Point"}
}