{
  "type": "Feature",
  "properties": {
    "iso:country":"FR",
    "sg:address":"B.P. 205, 22002 Saint Brieuc C\u00e9dex 1^^3, Rue Auguste Lumi\u00e8re, 22000 Saint Brieuc",
    "sg:city":"Saint-Brieuc",
    "sg:orig_category":"Non-Classified Establishments",
    "sg:phone":"+33 2 96 68 29 29",
    "sg:postcode":"22000",
    "sg:province":"Bretagne",
    "wof:name":"Comptoir Des Lumi\u00e8res S.a.",
    "wof:placetype":"venue"
},
  "geometry": {"coordinates":[-2.733237,48.508881],"type":"Point"}
}