{
  "type": "Feature",
  "properties": {
    "iso:country":"FR",
    "sg:address":"B.P. 12",
    "sg:city":"Custines^^Pr\u00e9 \u00e0 Varois 54670 Custines",
    "sg:orig_category":"Non-Classified Establishments",
    "sg:phone":"+33 3 83 92 60 00",
    "sg:postcode":"54670",
    "sg:province":"Lorraine",
    "wof:name":"Ascom\u00e9tal S.a.",
    "wof:placetype":"venue"
},
  "geometry": {"coordinates":[6.142335,48.791302],"type":"Point"}
}