{
  "type": "Feature",
  "properties": {
    "iso:country":"FR",
    "sg:address":"32 Avenue Vauban 89100 Sens",
    "sg:city":"Sens",
    "sg:classifiers":[
        {
            "category":"Professional",
            "subcategory":"Engineering",
            "type":"Services"
        }
    ],
    "sg:phone":"+33 3 86 95 03 43",
    "sg:postcode":"89100",
    "sg:province":"Bourgogne",
    "sg:tags":[
        "machine",
        "-",
        "mechanical"
    ],
    "wof:name":"Froid Henriot",
    "wof:placetype":"venue"
},
  "geometry": {"coordinates":[3.27302,48.1978],"type":"Point"}
}