{
  "type": "Feature",
  "properties": {
    "addr:full":"394 Rue Louis L\u00e9pine BP 7 34935 Montpellier Cedex 9 L\u00e9pine Nord Pas-de-Calais 62170",
    "addr:housenumber":"394;7",
    "addr:postcode":"34935;cedex 9 le\u0301pine nord;62170",
    "addr:street":"Rue Louis Le\u0301Pine Bp",
    "iso:country":"FR",
    "sg:address":"394 Rue Louis L\u00e9pine BP 7 34935 Montpellier Cedex 9",
    "sg:city":"L\u00e9pine",
    "sg:classifiers":[
        {
            "category":"Shopping",
            "subcategory":"Computers & Home Electronics",
            "type":"Retail Goods"
        }
    ],
    "sg:phone":"+33 4 67 99 47 47",
    "sg:postcode":"62170",
    "sg:province":"Nord Pas-de-Calais",
    "sg:tags":[
        "equipment",
        "electrical",
        "component",
        "electric",
        "electronic"
    ],
    "wof:name":"Qualiflow Sa",
    "wof:placetype":"venue"
},
  "geometry": {"coordinates":[3.87927,43.608528],"type":"Point"}
}