{
  "type": "Feature",
  "properties": {
    "addr:full":"Rue Du Parc Des Sports 91160 Champlan Ile de France 91160",
    "addr:postcode":"91160;ile;91160",
    "addr:street":"Rue Du Parc Des Sports;France",
    "iso:country":"FR",
    "sg:address":"Rue Du Parc Des Sports 91160 Champlan",
    "sg:classifiers":[
        {
            "category":"Manufacturing",
            "subcategory":"Motor Vehicles & Parts",
            "type":"Manufacturing & Wholesale Goods"
        }
    ],
    "sg:phone":"+33 1 69 34 41 24",
    "sg:postcode":"91160",
    "sg:province":"Ile de France",
    "sg:tags":[
        "engine",
        "industrial",
        "tran",
        "-",
        "machine",
        "engineering",
        "mechanical",
        "motor-cars"
    ],
    "wof:name":"Sreid Division Chaines",
    "wof:placetype":"venue"
},
  "geometry": {"coordinates":[2.272723,48.712257],"type":"Point"}
}