{
  "type": "Feature",
  "properties": {
    "iso:country":"FR",
    "sg:address":"RN 20",
    "sg:city":"Foix",
    "sg:orig_category":"Non-Classified Establishments",
    "sg:phone":"+33 5 61 02 92 22",
    "sg:postcode":"09000",
    "sg:province":"Midi Pyr\u00e9n\u00e9es",
    "wof:name":"C.s.o.",
    "wof:placetype":"venue"
},
  "geometry": {"coordinates":[1.59651,42.95871],"type":"Point"}
}