{
  "type": "Feature",
  "properties": {
    "addr:full":"B.P. 11, 10320 Bouilly^^16, Rue de la Paix, 10320 Bouilly Champagne",
    "addr:postcode":"10320;10320",
    "addr:street":"B.P. 11;Rue De La Paix",
    "iso:country":"FR",
    "sg:address":"B.P. 11, 10320 Bouilly^^16, Rue de la Paix, 10320 Bouilly",
    "sg:orig_category":"Non-Classified Establishments",
    "sg:phone":"+33 3 25 40 28 48",
    "sg:province":"Champagne",
    "wof:name":"L'union Des Electriciens S.a.",
    "wof:placetype":"venue"
},
  "geometry": {"coordinates":[4.00008,48.196186],"type":"Point"}
}