{
  "type": "Feature",
  "properties": {
    "addr:full":"15, Rue Jacques Monod - Zone Industrielle Eurochannel, 76378 Dieppe C\u00e9dex Nord Pas-de-Calais",
    "addr:housenumber":"15",
    "addr:postcode":"76378",
    "addr:street":"Rue Jacques Monod Zone Industrielle Eurochannel;Ce\u0301Dex Nord",
    "iso:country":"FR",
    "sg:address":"15, Rue Jacques Monod - Zone Industrielle Eurochannel, 76378 Dieppe C\u00e9dex",
    "sg:orig_category":"Non-Classified Establishments",
    "sg:phone":"+33 2 32 90 58 50",
    "sg:province":"Nord Pas-de-Calais",
    "wof:name":"Euromaster S.n.c.",
    "wof:placetype":"venue"
},
  "geometry": {"coordinates":[1.08787,49.92749],"type":"Point"}
}