{
  "type": "Feature",
  "properties": {
    "addr:full":"6, Rue No\u00ebl, 08000 Charleville M\u00e9zi\u00e8res Charleville-M\u00e9zi\u00e8res Champagne 08000",
    "addr:housenumber":"6",
    "addr:postcode":"08000;08000",
    "addr:street":"Rue Noe\u0308L",
    "iso:country":"FR",
    "sg:address":"6, Rue No\u00ebl, 08000 Charleville M\u00e9zi\u00e8res",
    "sg:city":"Charleville-M\u00e9zi\u00e8res",
    "sg:orig_category":"Non-Classified Establishments",
    "sg:phone":"+33 3 24 33 38 96",
    "sg:postcode":"08000",
    "sg:province":"Champagne",
    "wof:name":"Caf\u00e9s O.c.e. S.a.",
    "wof:placetype":"venue"
},
  "geometry": {"coordinates":[4.719403,49.774815],"type":"Point"}
}