{
  "type": "Feature",
  "properties": {
    "addr:full":"17 rue de Gerland 69007 Lyon Rhone-Alpes",
    "addr:housenumber":"17",
    "addr:postcode":"69007",
    "addr:street":"Rue De Gerland",
    "iso:country":"FR",
    "sg:address":"17 rue de Gerland 69007 Lyon",
    "sg:classifiers":[
        {
            "category":"Home & Garden",
            "subcategory":"Home Furnishings",
            "type":"Retail Goods"
        }
    ],
    "sg:phone":"+33 4 78 72 98 78",
    "sg:province":"Rhone-Alpes",
    "sg:tags":[
        "curtain",
        "trimming"
    ],
    "wof:name":"Reymondon Sa",
    "wof:placetype":"venue"
},
  "geometry": {"coordinates":[4.840945,45.741104],"type":"Point"}
}