{
  "type": "Feature",
  "properties": {
    "iso:country":"FR",
    "sg:address":"2, Av de la D\u00e9couverte, 21000 Dijon",
    "sg:city":"Dijon",
    "sg:orig_category":"Unclassifiable Establishments",
    "sg:phone":"+33 3 80 70 73 30",
    "sg:postcode":"21000",
    "sg:province":"Bourgogne",
    "wof:name":"S.o.d.i.c.o.b. S.a. - Soci\u00e9t\u00e9 De Didtribution Pour La Communication Et L'organisation De Bureau",
    "wof:placetype":"venue"
},
  "geometry": {"coordinates":[5.045165,47.354576],"type":"Point"}
}