{
  "type": "Feature",
  "properties": {
    "addr:full":"47, Rue du Val de Saire, 50100 Cherbourg Cherbourg-Octeville Basse Normandie 50100",
    "addr:housenumber":"47",
    "addr:postcode":"50100;50100",
    "addr:street":"Rue Du Val De Saire",
    "iso:country":"FR",
    "sg:address":"47, Rue du Val de Saire, 50100 Cherbourg",
    "sg:city":"Cherbourg-Octeville",
    "sg:orig_category":"Unclassifiable Establishments",
    "sg:phone":"+33 2 33 43 50 25",
    "sg:postcode":"50100",
    "sg:province":"Basse Normandie",
    "wof:name":"Mabille S.a.",
    "wof:placetype":"venue"
},
  "geometry": {"coordinates":[-1.616521,49.638939],"type":"Point"}
}