{
  "type": "Feature",
  "properties": {
    "addr:full":"60 Faubourg De Belfort 90100 Delle Franche Comt\u00e9 90100",
    "addr:housenumber":"60",
    "addr:postcode":"90100;90100",
    "addr:street":"Faubourg De Belfort;Franche Comte\u0301",
    "iso:country":"FR",
    "sg:address":"60 Faubourg De Belfort 90100 Delle",
    "sg:classifiers":[
        {
            "category":"Manufacturing",
            "subcategory":"Chemicals & Compounds",
            "type":"Manufacturing & Wholesale Goods"
        }
    ],
    "sg:phone":"+33 3 22 47 79 47",
    "sg:postcode":"90100",
    "sg:province":"Franche Comt\u00e9",
    "sg:tags":[
        "pharmaceutical",
        "energy",
        "chemistry",
        "-",
        "by-product"
    ],
    "wof:name":"Igol Nord Est Sa",
    "wof:placetype":"venue"
},
  "geometry": {"coordinates":[7.001381,47.518642],"type":"Point"}
}