{
  "type": "Feature",
  "properties": {
    "iso:country":"FR",
    "sg:address":"9 rue Bataille 57600 Forbach",
    "sg:classifiers":[
        {
            "category":"Food & Beverages",
            "subcategory":"Meat & Fish",
            "type":"Retail Goods"
        }
    ],
    "sg:phone":"+33 3 87 87 65 10",
    "sg:postcode":"57600",
    "sg:province":"Lorraine",
    "wof:name":"Jeca Sa",
    "wof:placetype":"venue"
},
  "geometry": {"coordinates":[6.894739,49.19532],"type":"Point"}
}