{
  "type": "Feature",
  "properties": {
    "addr:full":"11 Route De Villebois Lavalette 16250 Blanzac Porcheresse Poitou-Charentes 16250",
    "addr:housenumber":"11",
    "addr:postcode":"16250;16250",
    "addr:street":"Route De Villebois Lavalette;Porcheresse",
    "iso:country":"FR",
    "sg:address":"11 Route De Villebois Lavalette 16250 Blanzac Porcheresse",
    "sg:classifiers":[
        {
            "category":"Bakery",
            "type":"Food & Drink"
        }
    ],
    "sg:phone":"+33 5 45 64 10 22",
    "sg:postcode":"16250",
    "sg:province":"Poitou-Charentes",
    "sg:tags":[
        "cake",
        "product",
        "related",
        "bread"
    ],
    "wof:name":"Art Pat Gel",
    "wof:placetype":"venue"
},
  "geometry": {"coordinates":[0.030907,45.455208],"type":"Point"}
}