{
  "type": "Feature",
  "properties": {
    "addr:full":"6 Tavers Centre 45190",
    "addr:housenumber":"6",
    "addr:postcode":"45190",
    "addr:street":"Tavers Centre",
    "iso:country":"FR",
    "sg:address":"6",
    "sg:city":"Tavers",
    "sg:classifiers":[
        {
            "category":"Building & Trades",
            "subcategory":"Electrical",
            "type":"Services"
        }
    ],
    "sg:phone":"+33 2 38 46 93 93",
    "sg:postcode":"45190",
    "sg:province":"Centre",
    "sg:tags":[
        "electronic",
        "lighting",
        "equipment"
    ],
    "wof:name":"Claude Lefebvre",
    "wof:placetype":"venue"
},
  "geometry": {"coordinates":[1.630985,47.779282],"type":"Point"}
}