{
  "type": "Feature",
  "properties": {
    "addr:full":"1 Bd De La Chantourn 38700 La Tronche Rhone-Alpes 38700",
    "addr:housenumber":"1",
    "addr:postcode":"38700;38700",
    "addr:street":"Bd De La Chantourn",
    "iso:country":"FR",
    "sg:address":"1 Bd De La Chantourn 38700 La Tronche",
    "sg:classifiers":[
        {
            "category":"Manufacturing",
            "subcategory":"Chemicals & Compounds",
            "type":"Manufacturing & Wholesale Goods"
        }
    ],
    "sg:phone":"+33 4 76 44 62 88",
    "sg:postcode":"38700",
    "sg:province":"Rhone-Alpes",
    "sg:tags":[
        "pharmaceutical",
        "chemistry",
        "-",
        "by-product"
    ],
    "wof:name":"Sibellas Nobel Sa",
    "wof:placetype":"venue"
},
  "geometry": {"coordinates":[5.746145,45.196823],"type":"Point"}
}