{
  "type": "Feature",
  "properties": {
    "addr:full":"55 av du Corps Franc Pommi\u00e8s 64110 JURANCON Juran\u00e7on Aquitaine 64110",
    "addr:postcode":"64110;64110",
    "addr:street":"55 Av Du Corps Franc Pommie\u0300S",
    "iso:country":"FR",
    "sg:address":"55 av du Corps Franc Pommi\u00e8s 64110 JURANCON",
    "sg:city":"Juran\u00e7on",
    "sg:classifiers":[
        {
            "category":"Manufacturing",
            "subcategory":"Textiles",
            "type":"Manufacturing & Wholesale Goods"
        }
    ],
    "sg:phone":"+33 5 59 06 36 88",
    "sg:postcode":"64110",
    "sg:province":"Aquitaine",
    "sg:tags":[
        "knitted"
    ],
    "wof:name":"Mtp Manufacture De Tissu Des Pyren\u00e9es S.a.",
    "wof:placetype":"venue"
},
  "geometry": {"coordinates":[-0.398634,43.292305],"type":"Point"}
}