{
  "type": "Feature",
  "properties": {
    "addr:full":"26, Rue Copernic - ZA des Hauts de France, 62970 Courcelles l\u00e8s Lens Nord Pas-de-Calais",
    "addr:housenumber":"26",
    "addr:postcode":"62970",
    "addr:street":"Rue Copernic Za Des Hauts De France",
    "iso:country":"FR",
    "sg:address":"26, Rue Copernic - ZA des Hauts de France, 62970 Courcelles l\u00e8s Lens",
    "sg:orig_category":"Unclassifiable Establishments",
    "sg:phone":"+33 3 21 77 92 92",
    "sg:province":"Nord Pas-de-Calais",
    "wof:name":"Lepinard Profilage S.a.",
    "wof:placetype":"venue"
},
  "geometry": {"coordinates":[3.016587,50.410511],"type":"Point"}
}