{
  "type": "Feature",
  "properties": {
    "addr:full":"42 Quai Gustave Lamarle 62100 Calais Nord Pas-de-Calais",
    "addr:housenumber":"42",
    "addr:postcode":"62100",
    "addr:street":"Quai Gustave Lamarle;Calais;Pas-De-Calais",
    "iso:country":"FR",
    "sg:address":"42 Quai Gustave Lamarle 62100 Calais",
    "sg:classifiers":[
        {
            "category":"Home & Garden",
            "subcategory":"Furniture",
            "type":"Retail Goods"
        }
    ],
    "sg:phone":"+33 3 21 85 21 20",
    "sg:province":"Nord Pas-de-Calais",
    "sg:tags":[
        "wood"
    ],
    "wof:name":"Plastirama",
    "wof:placetype":"venue"
},
  "geometry": {"coordinates":[1.866052,50.944576],"type":"Point"}
}