{
  "type": "Feature",
  "properties": {
    "iso:country":"FR",
    "sg:address":"7, Rue de l'Oc\u00e9an, 85170 Belleville sur Vie",
    "sg:orig_category":"Non-Classified Establishments",
    "sg:phone":"+33 2 51 41 11 69",
    "sg:postcode":"85170",
    "sg:province":"Pays de Loire",
    "wof:name":"Belleville Confection S.a.r.l.",
    "wof:placetype":"venue"
},
  "geometry": {"coordinates":[-6.33135,53.371677],"type":"Point"}
}