{
  "type": "Feature",
  "properties": {
    "addr:full":"7, Rue Galil\u00e9e, 75116 Paris \u00cele-de-France",
    "addr:housenumber":"7",
    "addr:postcode":"75116",
    "addr:street":"Rue Galile\u0301E",
    "iso:country":"FR",
    "sg:address":"7, Rue Galil\u00e9e, 75116 Paris",
    "sg:orig_category":"Non-Classified Establishments",
    "sg:phone":"+33 1 49 52 43 00",
    "sg:province":"\u00cele-de-France",
    "wof:name":"J.p.a. S.a. - Jacques Potdevin Associ\u00e9s",
    "wof:placetype":"venue"
},
  "geometry": {"coordinates":[2.291192,48.867706],"type":"Point"}
}