{
  "type": "Feature",
  "properties": {
    "addr:full":"B.P. 2, 59163 Cond\u00e9 sur l'Escaut^^91, Rue Gambetta, 59163 Cond\u00e9 sur l'Escaut Nord Pas-de-Calais",
    "addr:housenumber":"2;^ 91",
    "addr:postcode":"59163;59163",
    "addr:street":"B.P.;Rue Gambetta;L'Escaut Nord",
    "iso:country":"FR",
    "sg:address":"B.P. 2, 59163 Cond\u00e9 sur l'Escaut^^91, Rue Gambetta, 59163 Cond\u00e9 sur l'Escaut",
    "sg:orig_category":"Non-Classified Establishments",
    "sg:phone":"+33 3 27 34 27 13",
    "sg:province":"Nord Pas-de-Calais",
    "wof:name":"R.a.s. S.a.r.l. - Rassurer - Assister - S\u00e9curiser",
    "wof:placetype":"venue"
},
  "geometry": {"coordinates":[3.593694,50.450409],"type":"Point"}
}