{
  "type": "Feature",
  "properties": {
    "iso:country":"FR",
    "sg:address":"79, Chemin de Payssat, 31400 Toulouse",
    "sg:orig_category":"Unclassifiable Establishments",
    "sg:phone":"+33 5 62 16 63 07",
    "sg:province":"Midi Pyr\u00e9n\u00e9es",
    "wof:name":"S.m.e. - Soci\u00e9t\u00e9 M\u00e9ridonale Des Eaux",
    "wof:placetype":"venue"
},
  "geometry": {"coordinates":[1.487727,43.572182],"type":"Point"}
}