{
  "type": "Feature",
  "properties": {
    "iso:country":"FR",
    "sg:address":"Parcs d'Affaires d'Archamps",
    "sg:city":"Archamps",
    "sg:orig_category":"Unclassifiable Establishments",
    "sg:phone":"+33 4 50 95 92 92",
    "sg:postcode":"74160",
    "sg:province":"Rhone-Alpes",
    "wof:name":"Laiterie D'ambilly S.a.",
    "wof:placetype":"venue"
},
  "geometry": {"coordinates":[6.13239,46.135201],"type":"Point"}
}