{
  "type": "Feature",
  "properties": {
    "iso:country":"FR",
    "sg:address":"Rte de Chemir\u00e9 le Gaudin",
    "sg:city":"La Suze sur Sarthe",
    "sg:orig_category":"Unclassifiable Establishments",
    "sg:phone":"+33 2 43 77 63 00",
    "sg:postcode":"72210",
    "sg:province":"Pays de Loire",
    "wof:name":"Val\u00e9o Climatisation S.a.",
    "wof:placetype":"venue"
},
  "geometry": {"coordinates":[0.02721,47.889709],"type":"Point"}
}