{
  "type": "Feature",
  "properties": {
    "iso:country":"FR",
    "sg:address":"6, Place des All\u00e9es, 64120 Saint Palais",
    "sg:city":"M\u00e9harin",
    "sg:orig_category":"Unclassifiable Establishments",
    "sg:phone":"+33 5 59 65 69 70",
    "sg:postcode":"64120",
    "sg:province":"Aquitaine",
    "wof:name":"Banque Populaire Du Sud-ouest",
    "wof:placetype":"venue"
},
  "geometry": {"coordinates":[-1.0318,43.327126],"type":"Point"}
}