{
  "type": "Feature",
  "properties": {
    "addr:full":"9, Rue des Campanules, 77185 Lognes Ile de France 77185",
    "addr:housenumber":"9",
    "addr:postcode":"77185;ile;77185",
    "addr:street":"Rue Des Campanules;France",
    "iso:country":"FR",
    "sg:address":"9, Rue des Campanules, 77185 Lognes",
    "sg:orig_category":"Non-Classified Establishments",
    "sg:phone":"+33 1 60 05 55 53",
    "sg:postcode":"77185",
    "sg:province":"Ile de France",
    "wof:name":"E. T. P. M. S.a.r.l. - Engeenering Transport Pneumatique Et M\u00e9canique",
    "wof:placetype":"venue"
},
  "geometry": {"coordinates":[2.636211,48.832706],"type":"Point"}
}