{
  "type": "Feature",
  "properties": {
    "addr:full":"59 ave Albert Thomas; Carmaux; 81400 Midi Pyr\u00e9n\u00e9es 81400",
    "addr:postcode":"81400;81400",
    "addr:street":"59 Ave Albert Thomas",
    "iso:country":"FR",
    "sg:address":"59 ave Albert Thomas; Carmaux; 81400",
    "sg:classifiers":[
        {
            "category":"Banks & Credit Unions",
            "subcategory":"Bank",
            "type":"Services"
        }
    ],
    "sg:phone":"+33 3363755005",
    "sg:postcode":"81400",
    "sg:province":"Midi Pyr\u00e9n\u00e9es",
    "wof:name":"Soci\u00e9t\u00e9 G\u00e9n\u00e9rale",
    "wof:placetype":"venue"
},
  "geometry": {"coordinates":[2.158238,44.049301],"type":"Point"}
}