{
  "type": "Feature",
  "properties": {
    "iso:country":"FR",
    "sg:address":"Z.I.",
    "sg:city":"Orgelet",
    "sg:orig_category":"Unclassifiable Establishments",
    "sg:phone":"+33 3 84 25 44 44",
    "sg:postcode":"39270",
    "sg:province":"Franche Comt\u00e9",
    "wof:name":"Perrier Transports S.a.",
    "wof:placetype":"venue"
},
  "geometry": {"coordinates":[5.610467,46.52206],"type":"Point"}
}