{
  "type": "Feature",
  "properties": {
    "iso:country":"FR",
    "sg:address":"56, Petit Chemin des Bruy\u00e8res, 69150 D\u00e9cines Charpieu",
    "sg:orig_category":"Unclassifiable Establishments",
    "sg:phone":"+33 4 72 02 06 56",
    "sg:postcode":"69150",
    "sg:province":"Rhone-Alpes",
    "wof:name":"Guinet Derriaz",
    "wof:placetype":"venue"
},
  "geometry": {"coordinates":[4.939051,45.756393],"type":"Point"}
}