{
  "type": "Feature",
  "properties": {
    "addr:full":"2, Rue Sainte Barbe, 67600 S\u00e9lestat S\u00e9lestat Alsace 67600",
    "addr:housenumber":"2",
    "addr:postcode":"67600;67600",
    "addr:street":"Rue Sainte Barbe",
    "iso:country":"FR",
    "sg:address":"2, Rue Sainte Barbe, 67600 S\u00e9lestat",
    "sg:city":"S\u00e9lestat",
    "sg:orig_category":"Unclassifiable Establishments",
    "sg:phone":"+33 3 88 92 98 66",
    "sg:postcode":"67600",
    "sg:province":"Alsace",
    "wof:name":"Marquette Papeterie S.a.r.l.",
    "wof:placetype":"venue"
},
  "geometry": {"coordinates":[7.453694,48.25843],"type":"Point"}
}