{
  "type": "Feature",
  "properties": {
    "iso:country":"FR",
    "sg:address":"Lafargue 24380 St Michel De Villadeix",
    "sg:city":"Breuilh",
    "sg:classifiers":[
        {
            "category":"Farming",
            "subcategory":"Farm & Veterinary Services",
            "type":"Manufacturing & Wholesale Goods"
        }
    ],
    "sg:phone":"+33 5 53 54 91 62",
    "sg:postcode":"24380",
    "sg:province":"Aquitaine",
    "sg:tags":[
        "livestock",
        "business",
        "advice",
        "wood",
        "agriculture",
        "furniture"
    ],
    "wof:name":"Dupont Et Fils",
    "wof:placetype":"venue"
},
  "geometry": {"coordinates":[0.72181,44.972164],"type":"Point"}
}