{
  "type": "Feature",
  "properties": {
    "addr:full":"B\u00e2t. 8 U - Garonor Aulnay sous Bois Ile de France 93600",
    "addr:postcode":"93600",
    "iso:country":"FR",
    "sg:address":"B\u00e2t. 8 U - Garonor",
    "sg:city":"Aulnay sous Bois",
    "sg:orig_category":"Unclassifiable Establishments",
    "sg:phone":"+33 1 55 81 50 50",
    "sg:postcode":"93600",
    "sg:province":"Ile de France",
    "wof:name":"Gama International S.a.",
    "wof:placetype":"venue"
},
  "geometry": {"coordinates":[2.472009,48.962227],"type":"Point"}
}