{
  "type": "Feature",
  "properties": {
    "iso:country":"FR",
    "sg:address":"3, Rue de la Corderie, 94550 Chevilly Larue",
    "sg:orig_category":"Unclassifiable Establishments",
    "sg:phone":"+33 1 46 87 30 00",
    "sg:province":"Ile de France",
    "wof:name":"Commercial Fruits S.a.",
    "wof:placetype":"venue"
},
  "geometry": {"coordinates":[2.36214,48.760387],"type":"Point"}
}