{
  "type": "Feature",
  "properties": {
    "iso:country":"FR",
    "sg:address":"12 Rue Sadi Carnot 93170 Bagnolet",
    "sg:classifiers":[
        {
            "category":"Shopping",
            "subcategory":"Computers & Home Electronics",
            "type":"Retail Goods"
        }
    ],
    "sg:phone":"+33 1 49 93 19 18",
    "sg:postcode":"93170",
    "sg:province":"Ile de France",
    "sg:tags":[
        "electronic",
        "electrical",
        "equipment"
    ],
    "wof:name":"Saft",
    "wof:placetype":"venue"
},
  "geometry": {"coordinates":[2.418124,48.866528],"type":"Point"}
}