{
  "type": "Feature",
  "properties": {
    "addr:full":"B.P. 144, 59811 Lesquin C\u00e9dex^^Rue de Berzin, 59273 Fretin Nord Pas-de-Calais",
    "addr:housenumber":"b.p. 144",
    "addr:postcode":"59811;59273",
    "addr:street":"Berzin",
    "iso:country":"FR",
    "sg:address":"B.P. 144, 59811 Lesquin C\u00e9dex^^Rue de Berzin, 59273 Fretin",
    "sg:orig_category":"Non-Classified Establishments",
    "sg:phone":"+33 3 20 97 60 91",
    "sg:province":"Nord Pas-de-Calais",
    "wof:name":"H\u00e4nsel Textil France S.a.r.l.",
    "wof:placetype":"venue"
},
  "geometry": {"coordinates":[3.133035,50.557724],"type":"Point"}
}