{
  "type": "Feature",
  "properties": {
    "addr:full":"30 Av De La Lib\u00e9ration 59270 Bailleul Nord Pas-de-Calais 59270",
    "addr:postcode":"59270;59270",
    "addr:street":"30 Av De La Libe\u0301Ration",
    "iso:country":"FR",
    "sg:address":"30 Av De La Lib\u00e9ration 59270 Bailleul",
    "sg:classifiers":[
        {
            "category":"Building & Trades",
            "subcategory":"Construction",
            "type":"Services"
        }
    ],
    "sg:phone":"+33 3 28 49 25 06",
    "sg:postcode":"59270",
    "sg:province":"Nord Pas-de-Calais",
    "sg:tags":[
        "work",
        "public"
    ],
    "wof:name":"Euro Flandres Tp",
    "wof:placetype":"venue"
},
  "geometry": {"coordinates":[2.741734,50.731312],"type":"Point"}
}