{
  "type": "Feature",
  "properties": {
    "addr:full":"40 rue du Docteur Roux 75015 Paris Ile de France",
    "addr:housenumber":"40",
    "addr:postcode":"75015",
    "addr:street":"Rue Du Docteur Roux",
    "iso:country":"FR",
    "sg:address":"40 rue du Docteur Roux 75015 Paris",
    "sg:classifiers":[
        {
            "category":"Wholesale",
            "subcategory":"Books, Periodicals, & Newspapers",
            "type":"Manufacturing & Wholesale Goods"
        }
    ],
    "sg:phone":"+33 1 40 56 33 33",
    "sg:province":"Ile de France",
    "sg:tags":[
        "town",
        "city",
        "magazine"
    ],
    "wof:name":"Editions Neressis S.a.",
    "wof:placetype":"venue"
},
  "geometry": {"coordinates":[2.309686,48.839809],"type":"Point"}
}