{
  "type": "Feature",
  "properties": {
    "addr:full":"RN 75 - La Botte V\u00e9z\u00e9ronce Curtin Rhone-Alpes 38510",
    "addr:postcode":"38510",
    "addr:street":"Rn 75 La;Curtin Rhone-Alpes",
    "iso:country":"FR",
    "sg:address":"RN 75 - La Botte",
    "sg:city":"V\u00e9z\u00e9ronce Curtin",
    "sg:orig_category":"Unclassifiable Establishments",
    "sg:phone":"+33 4 74 80 58 58",
    "sg:postcode":"38510",
    "sg:province":"Rhone-Alpes",
    "wof:name":"Soropa S.a.r.l.",
    "wof:placetype":"venue"
},
  "geometry": {"coordinates":[5.475785,45.635395],"type":"Point"}
}