{
  "type": "Feature",
  "properties": {
    "iso:country":"FR",
    "sg:address":"18, Rue Auguste Lamey, 67000 Strasbourg",
    "sg:city":"Strasbourg",
    "sg:orig_category":"Unclassifiable Establishments",
    "sg:phone":"+33 3 88 35 99 00",
    "sg:postcode":"67000",
    "sg:province":"Alsace",
    "wof:name":"Andromaque S.a",
    "wof:placetype":"venue"
},
  "geometry": {"coordinates":[7.756641,48.589111],"type":"Point"}
}