{
  "type": "Feature",
  "properties": {
    "addr:full":"21, Rue Edgar Guinet, 93360 Neuilly Plaisance Ile de France 93360",
    "addr:housenumber":"21",
    "addr:postcode":"93360;93360",
    "addr:street":"Rue Edgar Guinet;Ile De France",
    "iso:country":"FR",
    "sg:address":"21, Rue Edgar Guinet, 93360 Neuilly Plaisance",
    "sg:orig_category":"Non-Classified Establishments",
    "sg:phone":"+33 1 43 08 14 62",
    "sg:postcode":"93360",
    "sg:province":"Ile de France",
    "wof:name":"Etablissements M.k.m. S.a.r.l",
    "wof:placetype":"venue"
},
  "geometry": {"coordinates":[2.511762,48.854481],"type":"Point"}
}