{
  "type": "Feature",
  "properties": {
    "iso:country":"FR",
    "sg:address":"383, Av. du G\u00e9n\u00e9ral De Gaulle, 92140 Clamart",
    "sg:orig_category":"Unclassifiable Establishments",
    "sg:phone":"+33 1 46 30 59 00",
    "sg:province":"Ile de France",
    "wof:name":"Mat\u00e9riaux Service S.a.",
    "wof:placetype":"venue"
},
  "geometry": {"coordinates":[2.245468,48.782829],"type":"Point"}
}