{
  "type": "Feature",
  "properties": {
    "iso:country":"FR",
    "sg:address":"6 Rue De La For\u00eat 57550 Merten",
    "sg:classifiers":[
        {
            "category":"Manufacturing",
            "subcategory":"Metals",
            "type":"Manufacturing & Wholesale Goods"
        }
    ],
    "sg:phone":"+33 3 87 29 75 10",
    "sg:postcode":"57550",
    "sg:province":"Lorraine",
    "sg:tags":[
        "metallurgy",
        "metalworking",
        "processing"
    ],
    "wof:name":"Mim",
    "wof:placetype":"venue"
},
  "geometry": {"coordinates":[6.661877,49.244793],"type":"Point"}
}