{
  "type": "Feature",
  "properties": {
    "addr:full":"61 Avenue De Paris 86130 Jaunay Clan Poitou-Charentes 86130",
    "addr:housenumber":"61",
    "addr:postcode":"86130;86130",
    "addr:street":"Avenue De Paris;Clan",
    "iso:country":"FR",
    "sg:address":"61 Avenue De Paris 86130 Jaunay Clan",
    "sg:classifiers":[
        {
            "category":"Manufacturing",
            "subcategory":"Rubber & Plastics",
            "type":"Manufacturing & Wholesale Goods"
        }
    ],
    "sg:phone":"+33 5 49 30 08 00",
    "sg:postcode":"86130",
    "sg:province":"Poitou-Charentes",
    "wof:name":"Sunclear Diffusion",
    "wof:placetype":"venue"
},
  "geometry": {"coordinates":[0.3888,46.69099],"type":"Point"}
}