{
  "type": "Feature",
  "properties": {
    "addr:full":"21 Quai Riondet Vienne Rhone-Alpes 38200",
    "addr:housenumber":"21",
    "addr:postcode":"38200",
    "addr:street":"Quai Riondet;Rhone-Alpes",
    "iso:country":"FR",
    "sg:address":"21 Quai Riondet",
    "sg:city":"Vienne",
    "sg:classifiers":[
        {
            "category":"Banks & Credit Unions",
            "subcategory":"Financial Services",
            "type":"Services"
        }
    ],
    "sg:phone":"+33 4 74 78 82 82",
    "sg:postcode":"38200",
    "sg:province":"Rhone-Alpes",
    "sg:tags":[
        "banking",
        "finance",
        "insurance"
    ],
    "wof:name":"Fiducial Sa",
    "wof:placetype":"venue"
},
  "geometry": {"coordinates":[4.867108,45.519871],"type":"Point"}
}