{
  "type": "Feature",
  "properties": {
    "iso:country":"FR",
    "sg:address":"14/16, Rue de Moronval, 28100 Dreux",
    "sg:city":"Dreux",
    "sg:orig_category":"Non-Classified Establishments",
    "sg:phone":"+33 2 37 38 92 03",
    "sg:postcode":"28100",
    "sg:province":"Centre",
    "wof:name":"Watson - Marlow S.a.",
    "wof:placetype":"venue"
},
  "geometry": {"coordinates":[1.376543,48.73328],"type":"Point"}
}