{
  "type": "Feature",
  "properties": {
    "addr:full":"18 Rue Du Jour Batiment Vim Min 94550 Chevilly Larue Ile de France 94550",
    "addr:housenumber":"18",
    "addr:postcode":"94550;94550",
    "addr:street":"Rue Du Jour;Min",
    "iso:country":"FR",
    "sg:address":"18 Rue Du Jour Batiment Vim Min 94550 Chevilly Larue",
    "sg:classifiers":[
        {
            "category":"Food & Beverages",
            "subcategory":"Groceries & Convenience Stores",
            "type":"Retail Goods"
        }
    ],
    "sg:phone":"+33 1 45 60 91 95",
    "sg:postcode":"94550",
    "sg:province":"Ile de France",
    "sg:tags":[
        "product",
        "related"
    ],
    "wof:name":"A La Fine Barde",
    "wof:placetype":"venue"
},
  "geometry": {"coordinates":[2.363493,48.758678],"type":"Point"}
}