{
  "type": "Feature",
  "properties": {
    "addr:full":"Hameau De Laperriere 21450 POISEUL ET LAPERRIERE Ampilly-les-Bordes Bourgogne 21450",
    "addr:postcode":"21450;21450",
    "addr:street":"Hameau De Laperriere;Bourgogne",
    "iso:country":"FR",
    "sg:address":"Hameau De Laperriere 21450 POISEUL ET LAPERRIERE",
    "sg:city":"Ampilly-les-Bordes",
    "sg:classifiers":[
        {
            "category":"Manufacturing",
            "subcategory":"Lumber",
            "type":"Manufacturing & Wholesale Goods"
        }
    ],
    "sg:phone":"+33 3 80 96 53 73",
    "sg:postcode":"21450",
    "sg:province":"Bourgogne",
    "sg:tags":[
        "hardwood",
        "sawmill"
    ],
    "wof:name":"Ste Exploitation Ets Paturat S.a.r.l.",
    "wof:placetype":"venue"
},
  "geometry": {"coordinates":[4.525675,47.681274],"type":"Point"}
}