{
  "type": "Feature",
  "properties": {
    "addr:full":"Quai Flora Tristan - ZAC du Val de Croze Montpellier Languedoc-Roussillon 34070",
    "addr:postcode":"34070",
    "addr:street":"Quai Flora Tristan Zac Du Val De Croze",
    "iso:country":"FR",
    "sg:address":"Quai Flora Tristan - ZAC du Val de Croze",
    "sg:city":"Montpellier",
    "sg:orig_category":"Unclassifiable Establishments",
    "sg:phone":"+33 4 67 07 60 60",
    "sg:postcode":"34070",
    "sg:province":"Languedoc-Roussillon",
    "wof:name":"Canon France",
    "wof:placetype":"venue"
},
  "geometry": {"coordinates":[3.84676,43.591499],"type":"Point"}
}