{
  "type": "Feature",
  "properties": {
    "addr:full":"2, Av. G\u00e9n\u00e9ral Balfourier, 75016 Paris Ile de France 75016",
    "addr:postcode":"75016;75016",
    "addr:street":"Av. Ge\u0301Ne\u0301Ral Balfourier",
    "iso:country":"FR",
    "sg:address":"2, Av. G\u00e9n\u00e9ral Balfourier, 75016 Paris",
    "sg:orig_category":"Non-Classified Establishments",
    "sg:phone":"+33 1 46 51 56 00",
    "sg:postcode":"75016",
    "sg:province":"Ile de France",
    "wof:name":"Etablissements Filiatre Et Fils S.a.",
    "wof:placetype":"venue"
},
  "geometry": {"coordinates":[2.259966,48.845074],"type":"Point"}
}