{
  "type": "Feature",
  "properties": {
    "iso:country":"FR",
    "sg:address":"Logis Neuf 01310 Confrancon",
    "sg:classifiers":[
        {
            "category":"Manufacturing",
            "subcategory":"Rubber & Plastics",
            "type":"Manufacturing & Wholesale Goods"
        }
    ],
    "sg:phone":"+33 4 74 25 24 54",
    "sg:postcode":"01310",
    "sg:province":"Rhone-Alpes",
    "sg:tags":[
        "metallurgy",
        "metalworking",
        "processing",
        "metal"
    ],
    "wof:name":"Gravo Marque Trophees Coupes Gmtc",
    "wof:placetype":"venue"
},
  "geometry": {"coordinates":[5.058695,46.255932],"type":"Point"}
}