{
  "type": "Feature",
  "properties": {
    "iso:country":"FR",
    "sg:address":"B.P. 317, 38203 Vienne C\u00e9dex^^44, Rue du 11 Novembre, 38200 Vienne",
    "sg:orig_category":"Non-Classified Establishments",
    "sg:phone":"+33 4 74 78 83 20",
    "sg:postcode":"38200",
    "sg:province":"Rhone-Alpes",
    "wof:name":"Agri Sud Est S.a.",
    "wof:placetype":"venue"
},
  "geometry": {"coordinates":[4.942395,45.467644],"type":"Point"}
}