{
  "type": "Feature",
  "properties": {
    "addr:full":"B.P. 1, 54530 Arnaville^^61, Rue du Mad, 54530 Arnaville Lorraine 54530",
    "addr:housenumber":"1",
    "addr:postcode":"54530;54530;54530",
    "addr:street":"B.P.;Rue Du Mad",
    "iso:country":"FR",
    "sg:address":"B.P. 1, 54530 Arnaville^^61, Rue du Mad, 54530 Arnaville",
    "sg:orig_category":"Non-Classified Establishments",
    "sg:phone":"+33 3 83 80 02 02",
    "sg:postcode":"54530",
    "sg:province":"Lorraine",
    "wof:name":"Arnatronic Plus S.a.r.l.",
    "wof:placetype":"venue"
},
  "geometry": {"coordinates":[6.022943,48.982639],"type":"Point"}
}