{
  "type": "Feature",
  "properties": {
    "iso:country":"FR",
    "sg:address":"ZI la Plaine",
    "sg:city":"Izernore",
    "sg:orig_category":"Non-Classified Establishments",
    "sg:phone":"+33 4 74 76 99 31",
    "sg:postcode":"01580",
    "sg:province":"Rhone-Alpes",
    "wof:name":"Arburg S.a.s.",
    "wof:placetype":"venue"
},
  "geometry": {"coordinates":[5.55378,46.218575],"type":"Point"}
}