{
  "type": "Feature",
  "properties": {
    "addr:full":"1, Av. de l'Europe - ZAC du Campus - B\u00e2t. D, 31400 Toulouse Midi Pyr\u00e9n\u00e9es",
    "addr:housenumber":"ba\u0302t d",
    "addr:postcode":"31400",
    "addr:street":"Av. De L'Europe Zac Du Campus",
    "iso:country":"FR",
    "sg:address":"1, Av. de l'Europe - ZAC du Campus - B\u00e2t. D, 31400 Toulouse",
    "sg:orig_category":"Non-Classified Establishments",
    "sg:phone":"+33 5 61 00 31 61",
    "sg:province":"Midi Pyr\u00e9n\u00e9es",
    "wof:name":"Synstar S.a.",
    "wof:placetype":"venue"
},
  "geometry": {"coordinates":[1.408258,43.558113],"type":"Point"}
}