{
  "type": "Feature",
  "properties": {
    "addr:full":"88, Rue du G\u00e9n\u00e9ral de Gaulle, 44600 St Nazaire Pays de Loire",
    "addr:housenumber":"88",
    "addr:postcode":"44600 st nazaire",
    "addr:street":"Rue Du Ge\u0301Ne\u0301Ral De Gaulle",
    "iso:country":"FR",
    "sg:address":"88, Rue du G\u00e9n\u00e9ral de Gaulle, 44600 St Nazaire",
    "sg:orig_category":"Unclassifiable Establishments",
    "sg:phone":"+33 2 40 22 14 51",
    "sg:province":"Pays de Loire",
    "wof:name":"Bouedo Organisation S.a.",
    "wof:placetype":"venue"
},
  "geometry": {"coordinates":[-2.215837,47.2747],"type":"Point"}
}