{
  "type": "Feature",
  "properties": {
    "addr:full":"63 B Avenue Jean Henri Dunant Meaux Ile de France 77100",
    "addr:housenumber":"63",
    "addr:postcode":"77100",
    "addr:street":"B Avenue Jean Henri Dunant;Ile De France",
    "iso:country":"FR",
    "sg:address":"63 B Avenue Jean Henri Dunant",
    "sg:city":"Meaux",
    "sg:classifiers":[
        {
            "category":"Banks & Credit Unions",
            "subcategory":"Financial Services",
            "type":"Services"
        }
    ],
    "sg:phone":"+33 1 60 23 37 37",
    "sg:postcode":"77100",
    "sg:province":"Ile de France",
    "sg:tags":[
        "banking",
        "finance",
        "insurance"
    ],
    "wof:name":"Office Public D'amenagement Et De Construction (opac)",
    "wof:placetype":"venue"
},
  "geometry": {"coordinates":[2.895207,48.947849],"type":"Point"}
}