{
  "type": "Feature",
  "properties": {
    "iso:country":"FR",
    "sg:address":"35",
    "sg:city":"Jules Rein; Sartrouville; 78500",
    "sg:classifiers":[
        {
            "category":"Banks & Credit Unions",
            "subcategory":"Bank",
            "type":"Services"
        }
    ],
    "sg:phone":"+33 3339140394",
    "sg:postcode":"78500",
    "sg:province":"Ile de France",
    "wof:name":"Banque Nationale De Paris",
    "wof:placetype":"venue"
},
  "geometry": {"coordinates":[2.158649,48.938213],"type":"Point"}
}