{
  "type": "Feature",
  "properties": {
    "addr:full":"7 rue de Ch\u00e2teaudun 75009 Paris Ile de France 75009",
    "addr:housenumber":"7",
    "addr:postcode":"75009;75009",
    "addr:street":"Rue De Cha\u0302Teaudun",
    "iso:country":"FR",
    "sg:address":"7 rue de Ch\u00e2teaudun 75009 Paris",
    "sg:classifiers":[
        {
            "category":"Shopping",
            "subcategory":"Jewelry",
            "type":"Retail Goods"
        }
    ],
    "sg:phone":"+33 1 48 78 53 92",
    "sg:postcode":"75009",
    "sg:province":"Ile de France",
    "sg:tags":[
        "gemstone",
        "jewellery"
    ],
    "wof:name":"Lestret Et Fils Sa",
    "wof:placetype":"venue"
},
  "geometry": {"coordinates":[2.341246,48.875679],"type":"Point"}
}