{
  "type": "Feature",
  "properties": {
    "addr:full":"12-14 Rue Du Placieux 54000 Nancy Lorraine 54000",
    "addr:housenumber":"12-14",
    "addr:postcode":"54000;54000",
    "addr:street":"Rue Du Placieux",
    "iso:country":"FR",
    "sg:address":"12-14 Rue Du Placieux 54000 Nancy",
    "sg:classifiers":[
        {
            "category":"Shopping",
            "subcategory":"Hobbies, Toys, & Games",
            "type":"Retail Goods"
        }
    ],
    "sg:phone":"+33 3 83 28 13 31",
    "sg:postcode":"54000",
    "sg:province":"Lorraine",
    "sg:tags":[
        "product",
        "miscellaneous",
        "entertainment"
    ],
    "wof:name":"Commissaire Priseur Sylvie Teitgen",
    "wof:placetype":"venue"
},
  "geometry": {"coordinates":[6.167564,48.677841],"type":"Point"}
}