{
  "type": "Feature",
  "properties": {
    "addr:full":"RUE NICOLAS COPERNIC 13200 Arles Midi Pyr\u00e9n\u00e9es",
    "addr:postcode":"13200",
    "addr:street":"Rue Nicolas Copernic",
    "iso:country":"FR",
    "sg:address":"RUE NICOLAS COPERNIC 13200 Arles",
    "sg:classifiers":[
        {
            "category":"Home & Garden",
            "subcategory":"Furniture",
            "type":"Retail Goods"
        }
    ],
    "sg:phone":"+33 4 90 96 71 25",
    "sg:province":"Midi Pyr\u00e9n\u00e9es",
    "wof:name":"St\u00e9 Exploitation Meubles Fa\u00efsse Et Plata S.a.r.l.",
    "wof:placetype":"venue"
},
  "geometry": {"coordinates":[4.634037,43.69981],"type":"Point"}
}