{
  "type": "Feature",
  "properties": {
    "addr:full":"1, Square du Ch\u00eane Germain - Immeuble Lutetium Les Lanthanides, 35510 Cesson S\u00e9vign\u00e9 Cesson-S\u00e9vign\u00e9 Bretagne 35510",
    "addr:housenumber":"1",
    "addr:postcode":"35510 cesson se\u0301vigne\u0301 cesson-se\u0301vigne\u0301;35510",
    "addr:street":"Square Du Che\u0302Ne Germain Immeuble Lutetium Les Lanthanides",
    "iso:country":"FR",
    "sg:address":"1, Square du Ch\u00eane Germain - Immeuble Lutetium Les Lanthanides, 35510 Cesson S\u00e9vign\u00e9",
    "sg:city":"Cesson-S\u00e9vign\u00e9",
    "sg:orig_category":"Unclassifiable Establishments",
    "sg:phone":"+33 2 99 63 85 30",
    "sg:postcode":"35510",
    "sg:province":"Bretagne",
    "wof:name":"Elios Informatique",
    "wof:placetype":"venue"
},
  "geometry": {"coordinates":[-1.624309,48.132069],"type":"Point"}
}