{
  "type": "Feature",
  "properties": {
    "iso:country":"FR",
    "sg:address":"B.P. 35, 34701 Lod\u00e8ve C\u00e9dex^^Quai M\u00e9gisserie, 34700 Lod\u00e8ve",
    "sg:orig_category":"Non-Classified Establishments",
    "sg:phone":"+33 4 67 44 14 60",
    "sg:province":"Languedoc-Roussillon",
    "wof:name":"Les Serres Du Lod\u00e9vois S.a.r.l.",
    "wof:placetype":"venue"
},
  "geometry": {"coordinates":[3.323017,43.731468],"type":"Point"}
}