{
  "type": "Feature",
  "properties": {
    "addr:full":"Rue De L'Industrie BP 196 Zi De Fontenailles 69823 Belleville Cedex Vill\u00e9 Alsace 67220",
    "addr:housenumber":"196",
    "addr:postcode":"69823;67220",
    "addr:street":"Rue De L'Industrie Bp",
    "iso:country":"FR",
    "sg:address":"Rue De L'Industrie BP 196 Zi De Fontenailles 69823 Belleville Cedex",
    "sg:city":"Vill\u00e9",
    "sg:classifiers":[
        {
            "category":"Utilities",
            "subcategory":"Electric",
            "type":"Services"
        }
    ],
    "sg:phone":"+33 4 74 67 63 82",
    "sg:postcode":"67220",
    "sg:province":"Alsace",
    "sg:tags":[
        "electricity",
        "electronic",
        "electrical",
        "equipment"
    ],
    "wof:name":"Ste Electrique Du Rhone Sa",
    "wof:placetype":"venue"
},
  "geometry": {"coordinates":[4.735849,46.103062],"type":"Point"}
}