{
  "type": "Feature",
  "properties": {
    "iso:country":"FR",
    "sg:address":"170 rue de la Pompe 75116 Paris",
    "sg:classifiers":[
        {
            "category":"Communications",
            "type":"Services"
        }
    ],
    "sg:phone":"+33 1 45 05 15 82",
    "sg:province":"\u00cele-de-France",
    "sg:tags":[
        "translation"
    ],
    "wof:name":"Lexitech France Sarl",
    "wof:placetype":"venue"
},
  "geometry": {"coordinates":[2.283213,48.870514],"type":"Point"}
}