{
  "type": "Feature",
  "properties": {
    "addr:full":"73200 Venthon Rhone-Alpes 73200",
    "addr:postcode":"73200;73200",
    "addr:street":"Rhone-Alpes",
    "iso:country":"FR",
    "sg:address":"73200 Venthon",
    "sg:orig_category":"Non-Classified Establishments",
    "sg:phone":"+33 4 79 31 11 50",
    "sg:postcode":"73200",
    "sg:province":"Rhone-Alpes",
    "wof:name":"Aluminium Pechiney S.a.",
    "wof:placetype":"venue"
},
  "geometry": {"coordinates":[6.412449,45.688084],"type":"Point"}
}