{
  "type": "Feature",
  "properties": {
    "addr:full":"40 Groignard 83200 Toulon Bourgogne",
    "addr:housenumber":"40",
    "addr:postcode":"83200",
    "addr:street":"Groignard",
    "iso:country":"FR",
    "sg:address":"40",
    "sg:city":"Groignard 83200 Toulon",
    "sg:classifiers":[
        {
            "category":"Manufacturing",
            "subcategory":"Building Materials",
            "type":"Manufacturing & Wholesale Goods"
        }
    ],
    "sg:phone":"+33 4 94 24 47 32",
    "sg:province":"Bourgogne",
    "sg:tags":[
        "glass",
        "ceramic"
    ],
    "wof:name":"Sarl Pierre Richard",
    "wof:placetype":"venue"
},
  "geometry": {"coordinates":[5.903918,43.140045],"type":"Point"}
}