{
  "type": "Feature",
  "properties": {
    "iso:country":"FR",
    "sg:address":"ZAC Coudoulet",
    "sg:city":"Orange",
    "sg:orig_category":"Non-Classified Establishments",
    "sg:phone":"+33 4 90 51 10 00",
    "sg:postcode":"84100",
    "sg:province":"Provence-Alpes-C\u00f4te d'Azur",
    "wof:name":"Richardson S.a.",
    "wof:placetype":"venue"
},
  "geometry": {"coordinates":[4.80867,44.136169],"type":"Point"}
}