{
  "type": "Feature",
  "properties": {
    "addr:full":"rue Antoine Bourdelle 13009 Marseille Poitou-Charentes",
    "addr:postcode":"13009",
    "addr:street":"Rue Antoine Bourdelle",
    "iso:country":"FR",
    "sg:address":"rue Antoine Bourdelle 13009 Marseille",
    "sg:classifiers":[
        {
            "category":"Professional",
            "subcategory":"Business Services",
            "type":"Services"
        }
    ],
    "sg:phone":"+33 4 91 82 78 60",
    "sg:province":"Poitou-Charentes",
    "sg:tags":[
        "observation",
        "market"
    ],
    "wof:name":"Esc Chambre De Commerce",
    "wof:placetype":"venue"
},
  "geometry": {"coordinates":[5.432687,43.237007],"type":"Point"}
}