{
  "type": "Feature",
  "properties": {
    "addr:full":"41 Avenue Thiers 77000 Melun Ile de France 77000",
    "addr:housenumber":"41",
    "addr:postcode":"77000;ile;77000",
    "addr:street":"Avenue Thiers;France",
    "iso:country":"FR",
    "sg:address":"41 Avenue Thiers 77000 Melun",
    "sg:classifiers":[
        {
            "category":"Travel",
            "subcategory":"Hotels & Motels",
            "type":"Entertainment"
        }
    ],
    "sg:phone":"+33 1 64 39 40 10",
    "sg:postcode":"77000",
    "sg:province":"Ile de France",
    "sg:tags":[
        "hotels",
        "business",
        "restaurant"
    ],
    "wof:name":"Telepizza Sa",
    "wof:placetype":"venue"
},
  "geometry": {"coordinates":[2.655057,48.530022],"type":"Point"}
}