{
  "type": "Feature",
  "properties": {
    "addr:full":"Zi De La M\u00e9tairie 49160 Longue Pays de Loire 49160",
    "addr:postcode":"49160;pays;49160",
    "addr:street":"Zi De La Me\u0301Tairie;Longue",
    "iso:country":"FR",
    "sg:address":"Zi De La M\u00e9tairie 49160 Longue",
    "sg:classifiers":[
        {
            "category":"Shopping",
            "subcategory":"Computers & Home Electronics",
            "type":"Retail Goods"
        }
    ],
    "sg:phone":"+33 2 41 53 04 78",
    "sg:postcode":"49160",
    "sg:province":"Pays de Loire",
    "sg:tags":[
        "equipment",
        "electrical",
        "component",
        "electric",
        "electronic"
    ],
    "wof:name":"Ere Etudes Et Realisations Electroniques",
    "wof:placetype":"venue"
},
  "geometry": {"coordinates":[-0.106544,47.376423],"type":"Point"}
}