{
  "type": "Feature",
  "properties": {
    "iso:country":"FR",
    "sg:address":"ZA de Lanveur",
    "sg:city":"Languidic",
    "sg:orig_category":"Unclassifiable Establishments",
    "sg:phone":"+33 2 97 65 18 65",
    "sg:postcode":"56440",
    "sg:province":"Bretagne",
    "wof:name":"Soci\u00e9t\u00e9 Nouvelle Jab S.a.",
    "wof:placetype":"venue"
},
  "geometry": {"coordinates":[-3.158574,47.832745],"type":"Point"}
}