{
  "type": "Feature",
  "properties": {
    "addr:full":"69 rue des Jacobins, 80001 Amiens C\u00e9dex 1, Dept 80 Amiens Picardie 80000",
    "addr:housenumber":"69;1 dept 80",
    "addr:postcode":"80001;80000",
    "addr:street":"Rue Des Jacobins;Ce\u0301Dex",
    "iso:country":"FR",
    "sg:address":"69 rue des Jacobins, 80001 Amiens C\u00e9dex 1, Dept 80",
    "sg:city":"Amiens",
    "sg:classifiers":[
        {
            "category":"Banks & Credit Unions",
            "subcategory":"Bank",
            "type":"Services"
        }
    ],
    "sg:phone":"+33 3 22 97 58 00",
    "sg:postcode":"80000",
    "sg:province":"Picardie",
    "wof:name":"Banque Lenoir Et Bernard",
    "wof:placetype":"venue"
},
  "geometry": {"coordinates":[2.301342,49.890923],"type":"Point"}
}