{
  "type": "Feature",
  "properties": {
    "addr:full":"18, Rue Yves Toudic, 75010 Paris Ile de France 75010",
    "addr:housenumber":"18",
    "addr:postcode":"75010;75010",
    "addr:street":"Rue Yves Toudic",
    "iso:country":"FR",
    "sg:address":"18, Rue Yves Toudic, 75010 Paris",
    "sg:orig_category":"Non-Classified Establishments",
    "sg:phone":"+33 1 42 08 54 30",
    "sg:postcode":"75010",
    "sg:province":"Ile de France",
    "wof:name":"C.n.a.-tapis S.a.",
    "wof:placetype":"venue"
},
  "geometry": {"coordinates":[2.364069,48.869823],"type":"Point"}
}