{
  "type": "Feature",
  "properties": {
    "iso:country":"FR",
    "sg:address":"210, Chauss\u00e9e Jules C\u00e9sar, 95250 Beauchamp",
    "sg:orig_category":"Unclassifiable Establishments",
    "sg:phone":"+33 1 34 13 28 16",
    "sg:province":"Ile de France",
    "wof:name":"T\u00f4lerie G\u00e9n\u00e9rale S.a.",
    "wof:placetype":"venue"
},
  "geometry": {"coordinates":[2.179154,49.015499],"type":"Point"}
}