{
  "type": "Feature",
  "properties": {
    "addr:full":"6, Rue Giotto - Parc Technologique du Canal, 31520 Ramonville Saint Agne Midi Pyr\u00e9n\u00e9es",
    "addr:housenumber":"6",
    "addr:postcode":"31520",
    "addr:street":"Rue Giotto",
    "iso:country":"FR",
    "sg:address":"6, Rue Giotto - Parc Technologique du Canal, 31520 Ramonville Saint Agne",
    "sg:orig_category":"Unclassifiable Establishments",
    "sg:phone":"+33 5 61 73 15 29",
    "sg:province":"Midi Pyr\u00e9n\u00e9es",
    "wof:name":"Shiva Technologies Europe S.a.r.l.",
    "wof:placetype":"venue"
},
  "geometry": {"coordinates":[1.484365,43.552273],"type":"Point"}
}