{
  "type": "Feature",
  "properties": {
    "iso:country":"FR",
    "sg:address":"Rte de Mamers",
    "sg:city":"Saint Paterne",
    "sg:orig_category":"Non-Classified Establishments",
    "sg:phone":"+33 2 33 81 17 50",
    "sg:postcode":"72610",
    "sg:province":"Pays de Loire",
    "wof:name":"Garnier Gedimat S.a.",
    "wof:placetype":"venue"
},
  "geometry": {"coordinates":[0.182135,48.304836],"type":"Point"}
}