{
  "type": "Feature",
  "properties": {
    "iso:country":"FR",
    "sg:address":"Les Petits Moulins 24360 St Est\u00e8phe",
    "sg:city":"Busserolles",
    "sg:classifiers":[
        {
            "category":"Sports & Exercise",
            "subcategory":"Sports Center",
            "type":"Entertainment"
        }
    ],
    "sg:phone":"+33 5 53 56 29 76",
    "sg:postcode":"24360",
    "sg:province":"Aquitaine",
    "sg:tags":[
        "product",
        "game",
        "miscellaneous"
    ],
    "wof:name":"Desyris Productions",
    "wof:placetype":"venue"
},
  "geometry": {"coordinates":[0.66562,45.590218],"type":"Point"}
}