{
  "type": "Feature",
  "properties": {
    "addr:full":"B.P. 19, 84840 Lapalud^^ZI les Plani\u00e8res, 84840 Lapalud Rhone-Alpes",
    "addr:postcode":"84840;84840",
    "addr:street":"B.P. 19",
    "iso:country":"FR",
    "sg:address":"B.P. 19, 84840 Lapalud^^ZI les Plani\u00e8res, 84840 Lapalud",
    "sg:orig_category":"Non-Classified Establishments",
    "sg:phone":"+33 4 90 40 20 51",
    "sg:province":"Rhone-Alpes",
    "wof:name":"Eftic Nucl\u00e9aire S.a.",
    "wof:placetype":"venue"
},
  "geometry": {"coordinates":[4.690797,44.310493],"type":"Point"}
}