{
  "type": "Feature",
  "properties": {
    "iso:country":"FR",
    "sg:address":"Rue Edouard Branly - ZI de la Maladi\u00e8re",
    "sg:city":"Bourgoin Jallieu",
    "sg:orig_category":"Unclassifiable Establishments",
    "sg:phone":"+33 4 74 28 08 52",
    "sg:postcode":"38300",
    "sg:province":"Rhone-Alpes",
    "wof:name":"F.i.r.e.m. S.a. - Fournitures Industrielles R\u00e9paration Electro M\u00e9ca",
    "wof:placetype":"venue"
},
  "geometry": {"coordinates":[5.30075,45.4981],"type":"Point"}
}