{
  "type": "Feature",
  "properties": {
    "iso:country":"FR",
    "sg:address":"7 Rue Des Charrons 31702 Blagnac Cedex",
    "sg:classifiers":[
        {
            "category":"Building & Trades",
            "subcategory":"Electrical",
            "type":"Services"
        }
    ],
    "sg:phone":"+33 5 61 71 46 32",
    "sg:province":"Aquitaine",
    "sg:tags":[
        "electronic",
        "lighting",
        "equipment"
    ],
    "wof:name":"Enseignes Lumineuses Fluoneon (soc Nouvelle) Sarl",
    "wof:placetype":"venue"
},
  "geometry": {"coordinates":[1.381888,43.646393],"type":"Point"}
}