{
  "type": "Feature",
  "properties": {
    "addr:full":"Zone Expo Sud 2 Bis Rue Tabart 45081 Orl\u00e9ans Cedex 2 Limousin",
    "addr:housenumber":"2 bis",
    "addr:postcode":"45081",
    "addr:street":"Rue Tabart",
    "iso:country":"FR",
    "sg:address":"Zone Expo Sud 2 Bis Rue Tabart 45081 Orl\u00e9ans Cedex 2",
    "sg:classifiers":[
        {
            "category":"Autos & Motor Vehicles",
            "subcategory":"Automobile Sales",
            "type":"Retail Goods"
        }
    ],
    "sg:phone":"+33 2 38 22 74 74",
    "sg:province":"Limousin",
    "sg:tags":[
        "equipment",
        "motor-cars",
        "transport"
    ],
    "wof:name":"Prestige Automobile Sa",
    "wof:placetype":"venue"
},
  "geometry": {"coordinates":[1.913916,47.875568],"type":"Point"}
}