{
  "type": "Feature",
  "properties": {
    "iso:country":"FR",
    "sg:address":"46 bis, Av. Michelet, 93400 Saint Ouen",
    "sg:orig_category":"Non-Classified Establishments",
    "sg:phone":"+33 1 41 66 30 60",
    "sg:province":"Ile de France",
    "wof:name":"Lesb\u00e2ches De France S.a.",
    "wof:placetype":"venue"
},
  "geometry": {"coordinates":[2.344024,48.909397],"type":"Point"}
}