{
  "type": "Feature",
  "properties": {
    "addr:full":"19, Rue Carnot, 54150 Briey Lorraine",
    "addr:housenumber":"19",
    "addr:postcode":"54150",
    "addr:street":"Rue Carnot",
    "iso:country":"FR",
    "sg:address":"19, Rue Carnot, 54150 Briey",
    "sg:orig_category":"Non-Classified Establishments",
    "sg:phone":"+33 3 82 20 28 99",
    "sg:province":"Lorraine",
    "wof:name":"Netcomposant.com",
    "wof:placetype":"venue"
},
  "geometry": {"coordinates":[5.940261,49.247837],"type":"Point"}
}