{
  "type": "Feature",
  "properties": {
    "iso:country":"FR",
    "sg:address":"21, Rue Ad\u00e8le Bourdon, 42420 Lorette",
    "sg:orig_category":"Unclassifiable Establishments",
    "sg:phone":"+33 4 77 73 24 24",
    "sg:postcode":"42420",
    "sg:province":"Rhone-Alpes",
    "wof:name":"Lorette Plastique S.a.r.l.",
    "wof:placetype":"venue"
},
  "geometry": {"coordinates":[4.57998,45.515079],"type":"Point"}
}