{
  "type": "Feature",
  "properties": {
    "addr:full":"Rte de Saint Nicolas du Port Ville en Vermois Lorraine 54210",
    "addr:postcode":"54210",
    "addr:street":"Rte De Saint Nicolas Du Port Ville En Vermois Lorraine",
    "iso:country":"FR",
    "sg:address":"Rte de Saint Nicolas du Port",
    "sg:city":"Ville en Vermois",
    "sg:orig_category":"Non-Classified Establishments",
    "sg:phone":"+33 3 83 46 93 66",
    "sg:postcode":"54210",
    "sg:province":"Lorraine",
    "wof:name":"For.sci.ca",
    "wof:placetype":"venue"
},
  "geometry": {"coordinates":[6.272675,48.618706],"type":"Point"}
}