{
  "type": "Feature",
  "properties": {
    "iso:country":"FR",
    "sg:address":"11, Rue Poissonni\u00e8re, 75002 Paris",
    "sg:orig_category":"Unclassifiable Establishments",
    "sg:phone":"+33 1 43 11 42 50",
    "sg:province":"Ile de France",
    "wof:name":"Philippe S.a.",
    "wof:placetype":"venue"
},
  "geometry": {"coordinates":[2.347598,48.869049],"type":"Point"}
}