{
  "type": "Feature",
  "properties": {
    "addr:full":"Technopole Rennes Atalante Site d'Apigne - Les Landes d'Apign\u00e9 Le Rheu Bretagne 35650",
    "addr:postcode":"35650",
    "addr:street":"Le Rheu Bretagne",
    "iso:country":"FR",
    "sg:address":"Technopole Rennes Atalante Site d'Apigne - Les Landes d'Apign\u00e9",
    "sg:city":"Le Rheu",
    "sg:orig_category":"Non-Classified Establishments",
    "sg:phone":"+33 2 99 14 62 33",
    "sg:postcode":"35650",
    "sg:province":"Bretagne",
    "wof:name":"Apia - Transitube S.a.",
    "wof:placetype":"venue"
},
  "geometry": {"coordinates":[-1.78809,48.096958],"type":"Point"}
}