{
  "type": "Feature",
  "properties": {
    "addr:full":"4, Rue Marc Seguin - ZI Ouest, 69740 Genas Rhone-Alpes",
    "addr:housenumber":"4",
    "addr:postcode":"69740",
    "addr:street":"Rue Marc Seguin Zi Ouest",
    "iso:country":"FR",
    "sg:address":"4, Rue Marc Seguin - ZI Ouest, 69740 Genas",
    "sg:orig_category":"Unclassifiable Establishments",
    "sg:phone":"+33 4 72 47 76 80",
    "sg:province":"Rhone-Alpes",
    "wof:name":"Airmig Locasoud S.a.",
    "wof:placetype":"venue"
},
  "geometry": {"coordinates":[5.000308,45.731804],"type":"Point"}
}