{
  "type": "Feature",
  "properties": {
    "iso:country":"FR",
    "sg:address":"1, Rue de Courtonne, 14000 Caen",
    "sg:city":"Caen",
    "sg:orig_category":"Unclassifiable Establishments",
    "sg:phone":"+33 2 31 47 24 50",
    "sg:postcode":"14000",
    "sg:province":"Basse Normandie",
    "wof:name":"Centre Affaires Mercure S.n.c.",
    "wof:placetype":"venue"
},
  "geometry": {"coordinates":[-0.355448,49.184303],"type":"Point"}
}