{
  "type": "Feature",
  "properties": {
    "iso:country":"FR",
    "sg:address":"19, Rue de la gare de Revilly, 75012 Paris",
    "sg:orig_category":"Unclassifiable Establishments",
    "sg:phone":"+33 1 43 43 22 22",
    "sg:province":"Ile de France",
    "wof:name":"Soci\u00e9t\u00e9 Dipam S.a.r.l.",
    "wof:placetype":"venue"
},
  "geometry": {"coordinates":[2.395103,48.841717],"type":"Point"}
}