{
  "type": "Feature",
  "properties": {
    "addr:full":"ZI - Parc Horizon 2000 Br\u00e9bi\u00e8res Nord Pas-de-Calais 62117",
    "addr:housenumber":"2000",
    "addr:postcode":"62117",
    "addr:street":"Bre\u0301Bie\u0300Res Nord",
    "iso:country":"FR",
    "sg:address":"ZI - Parc Horizon 2000",
    "sg:city":"Br\u00e9bi\u00e8res",
    "sg:orig_category":"Non-Classified Establishments",
    "sg:phone":"+33 3 21 50 76 50",
    "sg:postcode":"62117",
    "sg:province":"Nord Pas-de-Calais",
    "wof:name":"Speedwich S.a.r.l.",
    "wof:placetype":"venue"
},
  "geometry": {"coordinates":[3.02308,50.337639],"type":"Point"}
}