{
  "type": "Feature",
  "properties": {
    "addr:full":"ZI les Martini\u00e8res Saint Val\u00e9rien Bourgogne 89150",
    "addr:postcode":"89150",
    "addr:street":"Zi Les Martinie\u0300Res Saint Vale\u0301Rien Bourgogne",
    "iso:country":"FR",
    "sg:address":"ZI les Martini\u00e8res",
    "sg:city":"Saint Val\u00e9rien",
    "sg:orig_category":"Unclassifiable Establishments",
    "sg:phone":"+33 3 86 88 61 85",
    "sg:postcode":"89150",
    "sg:province":"Bourgogne",
    "wof:name":"Ulmann Et Compagnie S.a.",
    "wof:placetype":"venue"
},
  "geometry": {"coordinates":[3.094495,48.179066],"type":"Point"}
}