{
  "type": "Feature",
  "properties": {
    "iso:country":"FR",
    "sg:address":"Rue Ambroise Pare Zone Industrielle 59932 Chapelle Armentieres Cedex",
    "sg:city":"Armenti\u00e8res",
    "sg:classifiers":[
        {
            "category":"Wholesale",
            "subcategory":"Machinery & Supplies",
            "type":"Manufacturing & Wholesale Goods"
        }
    ],
    "sg:phone":"+33 3 20 35 30 42",
    "sg:postcode":"59280",
    "sg:province":"Nord Pas-de-Calais",
    "sg:tags":[
        "handling",
        "material",
        "-",
        "machine",
        "equipment",
        "engineering",
        "mechanical"
    ],
    "wof:name":"Savime",
    "wof:placetype":"venue"
},
  "geometry": {"coordinates":[2.87789,50.689949],"type":"Point"}
}