{
  "type": "Feature",
  "properties": {
    "addr:full":"B.P. 206, 92142 Clamart^^8, Av. R\u00e9aumur, 92140 Clamart Ile de France",
    "addr:housenumber":"b.p. 206",
    "addr:postcode":"92142;92140;ile",
    "addr:street":"Av. Re\u0301Aumur",
    "iso:country":"FR",
    "sg:address":"B.P. 206, 92142 Clamart^^8, Av. R\u00e9aumur, 92140 Clamart",
    "sg:orig_category":"Non-Classified Establishments",
    "sg:phone":"+33 1 30 12 73 00",
    "sg:province":"Ile de France",
    "wof:name":"S.k.f. France S.a.",
    "wof:placetype":"venue"
},
  "geometry": {"coordinates":[2.262025,48.80027],"type":"Point"}
}