{
  "type": "Feature",
  "properties": {
    "addr:full":"4 bis, Rue Emile Zola, 37000 Tours Tours Centre 37000",
    "addr:housenumber":"4 bis",
    "addr:postcode":"37000;37000",
    "addr:street":"Rue Emile Zola",
    "iso:country":"FR",
    "sg:address":"4 bis, Rue Emile Zola, 37000 Tours",
    "sg:city":"Tours",
    "sg:orig_category":"Non-Classified Establishments",
    "sg:phone":"+33 2 47 60 67 60",
    "sg:postcode":"37000",
    "sg:province":"Centre",
    "wof:name":"Cap G\u00e9mini France S.a.",
    "wof:placetype":"venue"
},
  "geometry": {"coordinates":[0.687919,47.393139],"type":"Point"}
}