{
  "type": "Feature",
  "properties": {
    "addr:full":"B.P. SENIA 712 Thiais C\u00e9dex \u00cele-de-France 94657",
    "addr:housenumber":"712",
    "addr:postcode":"94657",
    "addr:street":"B.P. Senia;Ce\u0301Dex",
    "iso:country":"FR",
    "sg:address":"B.P. SENIA 712",
    "sg:city":"Thiais C\u00e9dex",
    "sg:orig_category":"Non-Classified Establishments",
    "sg:phone":"+33 1 45 12 88 88",
    "sg:postcode":"94657",
    "sg:province":"\u00cele-de-France",
    "wof:name":"Paris Store Distribution S.a.",
    "wof:placetype":"venue"
},
  "geometry": {"coordinates":[2.39276,48.765701],"type":"Point"}
}