{
  "type": "Feature",
  "properties": {
    "addr:full":"Rue Du Bois De La Gourdine 59127 Malincourt Nord Pas-de-Calais 59127",
    "addr:postcode":"59127;59127",
    "addr:street":"Rue Du Bois De La Gourdine",
    "iso:country":"FR",
    "sg:address":"Rue Du Bois De La Gourdine 59127 Malincourt",
    "sg:classifiers":[
        {
            "category":"Shopping",
            "subcategory":"Crafts & Fabrics",
            "type":"Retail Goods"
        }
    ],
    "sg:phone":"+33 3 27 82 08 14",
    "sg:postcode":"59127",
    "sg:province":"Nord Pas-de-Calais",
    "sg:tags":[
        "textile",
        "clothing"
    ],
    "wof:name":"Leignel Broderies",
    "wof:placetype":"venue"
},
  "geometry": {"coordinates":[3.30436,50.03854],"type":"Point"}
}