{
  "type": "Feature",
  "properties": {
    "addr:full":"B.P. 80 Marsat Auvergne 63200",
    "addr:postcode":"63200",
    "addr:street":"B.P. 80 Marsat",
    "iso:country":"FR",
    "sg:address":"B.P. 80",
    "sg:city":"Marsat",
    "sg:orig_category":"Non-Classified Establishments",
    "sg:phone":"+33 4 73 33 70 50",
    "sg:postcode":"63200",
    "sg:province":"Auvergne",
    "wof:name":"Editions La Source D'or S.a.",
    "wof:placetype":"venue"
},
  "geometry": {"coordinates":[3.052114,45.84782],"type":"Point"}
}