{
  "type": "Feature",
  "properties": {
    "iso:country":"FR",
    "sg:address":"41, Rue du Mesnil Saint Denis, 78310 Coigni\u00e8res",
    "sg:orig_category":"Non-Classified Establishments",
    "sg:phone":"+33 1 34 61 95 10",
    "sg:postcode":"78310",
    "sg:province":"Ile de France",
    "wof:name":"Bocquet Paysage S.a.r.l.",
    "wof:placetype":"venue"
},
  "geometry": {"coordinates":[1.932587,48.747433],"type":"Point"}
}