{
  "type": "Feature",
  "properties": {
    "addr:full":"Av. du 8 Mai 1945 - ZI N\u00b0 1 Ch\u00e2teau Renault Centre 37110",
    "addr:housenumber":"zi n\u00b0 1 cha\u0302teau",
    "addr:postcode":"37110",
    "addr:street":"Av. Du 8 Mai 1945",
    "iso:country":"FR",
    "sg:address":"Av. du 8 Mai 1945 - ZI N\u00b0 1",
    "sg:city":"Ch\u00e2teau Renault",
    "sg:orig_category":"Non-Classified Establishments",
    "sg:phone":"+33 2 47 44 54 32",
    "sg:postcode":"37110",
    "sg:province":"Centre",
    "wof:name":"Fisons S.c.a.c.",
    "wof:placetype":"venue"
},
  "geometry": {"coordinates":[0.91899,47.597984],"type":"Point"}
}