{
  "type": "Feature",
  "properties": {
    "iso:country":"FR",
    "sg:address":"2, Rue Jean Rostand - Parc Club Universit\u00e9, 91400 Orsay",
    "sg:orig_category":"Unclassifiable Establishments",
    "sg:phone":"+33 1 69 85 24 13",
    "sg:province":"Ile de France",
    "wof:name":"Atrid Syst\u00e8mes S.a.s.",
    "wof:placetype":"venue"
},
  "geometry": {"coordinates":[2.17625,48.7103],"type":"Point"}
}