{
  "type": "Feature",
  "properties": {
    "iso:country":"FR",
    "sg:address":"B.P. 8, 73540 La B\u00e2thie C\u00e9dex^^ZI les Vernays, 73540 La B\u00e2thie",
    "sg:orig_category":"Non-Classified Establishments",
    "sg:phone":"+33 4 79 31 09 00",
    "sg:province":"Rhone-Alpes",
    "wof:name":"Sotrabas S.a.",
    "wof:placetype":"venue"
},
  "geometry": {"coordinates":[6.449745,45.626606],"type":"Point"}
}