{
  "type": "Feature",
  "properties": {
    "iso:country":"FR",
    "sg:address":"44150 Ancenis",
    "sg:orig_category":"Unclassifiable Establishments",
    "sg:phone":"+33 2 40 98 92 72",
    "sg:province":"Pays de Loire",
    "wof:name":"C.a.n.a. S.c.a. - Coop\u00e9rative Agricole La Noelle Ancenis",
    "wof:placetype":"venue"
},
  "geometry": {"coordinates":[-1.14098,47.393372],"type":"Point"}
}