{
  "type": "Feature",
  "properties": {
    "addr:full":"9 Rue Barbette 75003 Paris Ile de France",
    "addr:housenumber":"9",
    "addr:postcode":"75003",
    "addr:street":"Rue Barbette",
    "iso:country":"FR",
    "sg:address":"9 Rue Barbette 75003 Paris",
    "sg:classifiers":[
        {
            "category":"Manufacturing",
            "subcategory":"Paper Products",
            "type":"Manufacturing & Wholesale Goods"
        }
    ],
    "sg:phone":"+33 1 48 87 83 39",
    "sg:province":"Ile de France",
    "sg:tags":[
        "finished",
        "cardboard",
        "-"
    ],
    "wof:name":"Corbeaux Les Fils De A Sa",
    "wof:placetype":"venue"
},
  "geometry": {"coordinates":[2.36057,48.858757],"type":"Point"}
}