{
  "type": "Feature",
  "properties": {
    "addr:full":"23 chemin des Pr\u00e9s 38240 Meylan Rhone-Alpes 38240",
    "addr:housenumber":"23",
    "addr:postcode":"38240;38240",
    "addr:street":"Chemin Des Pre\u0301S",
    "iso:country":"FR",
    "sg:address":"23 chemin des Pr\u00e9s 38240 Meylan",
    "sg:orig_category":"Signal Analysers",
    "sg:phone":"+33 4 76 90 62 36",
    "sg:postcode":"38240",
    "sg:province":"Rhone-Alpes",
    "wof:name":"Oros Sarl",
    "wof:placetype":"venue"
},
  "geometry": {"coordinates":[5.79102,45.211521],"type":"Point"}
}