{
  "type": "Feature",
  "properties": {
    "iso:country":"FR",
    "sg:address":"Rte Maringues",
    "sg:city":"Peschadoires",
    "sg:orig_category":"Unclassifiable Establishments",
    "sg:phone":"+33 4 73 51 32 90",
    "sg:postcode":"63920",
    "sg:province":"Auvergne",
    "wof:name":"Sup & Pub S.a.",
    "wof:placetype":"venue"
},
  "geometry": {"coordinates":[3.490885,45.844131],"type":"Point"}
}