{
  "type": "Feature",
  "properties": {
    "addr:full":"1180 Avenue Jean Perrin Zi Zi Les Milles 13090 Aix En Provence Nord Pas-de-Calais",
    "addr:housenumber":"1180",
    "addr:postcode":"13090",
    "addr:street":"Avenue Jean Perrin Zi Zi;Milles;En Provence Nord",
    "iso:country":"FR",
    "sg:address":"1180 Avenue Jean Perrin Zi Zi Les Milles 13090 Aix En Provence",
    "sg:classifiers":[
        {
            "category":"Shopping",
            "subcategory":"Gifts & Souvenirs",
            "type":"Retail Goods"
        }
    ],
    "sg:phone":"+33 4 42 39 82 54",
    "sg:province":"Nord Pas-de-Calais",
    "sg:tags":[
        "product",
        "miscellaneous"
    ],
    "wof:name":"Fontana Patrice",
    "wof:placetype":"venue"
},
  "geometry": {"coordinates":[5.41946,43.55584],"type":"Point"}
}