{
  "type": "Feature",
  "properties": {
    "addr:full":"37, Rue Pierre et Marie Curie, 41000 Blois Blois Centre 41000",
    "addr:housenumber":"37",
    "addr:postcode":"41000;41000",
    "addr:street":"Rue Pierre Et Marie Curie",
    "iso:country":"FR",
    "sg:address":"37, Rue Pierre et Marie Curie, 41000 Blois",
    "sg:city":"Blois",
    "sg:orig_category":"Non-Classified Establishments",
    "sg:phone":"+33 2 54 43 51 22",
    "sg:postcode":"41000",
    "sg:province":"Centre",
    "wof:name":"Mission Locale Du Bl\u00e9sois",
    "wof:placetype":"venue"
},
  "geometry": {"coordinates":[1.339455,47.579044],"type":"Point"}
}