{
  "type": "Feature",
  "properties": {
    "iso:country":"FR",
    "sg:address":"ZI Les Troques",
    "sg:city":"Chaponost",
    "sg:orig_category":"Unclassifiable Establishments",
    "sg:phone":"+33 4 78 56 72 80",
    "sg:postcode":"69630",
    "sg:province":"Rhone-Alpes",
    "wof:name":"L.p.i. S.a. - Laboratoire P\u00e9rouse Implan",
    "wof:placetype":"venue"
},
  "geometry": {"coordinates":[4.74319,45.710232],"type":"Point"}
}