{
  "type": "Feature",
  "properties": {
    "addr:full":"B.P. 82, 02203 Soissons C\u00e9dex^^Rue des Moines - ZI, 02200 Villeneuve Saint Germain Picardie",
    "addr:postcode":"02203;02200",
    "addr:street":"B.P. 82",
    "iso:country":"FR",
    "sg:address":"B.P. 82, 02203 Soissons C\u00e9dex^^Rue des Moines - ZI, 02200 Villeneuve Saint Germain",
    "sg:orig_category":"Non-Classified Establishments",
    "sg:phone":"+33 3 23 75 63 00",
    "sg:province":"Picardie",
    "wof:name":"Norbert Dentressangle S.a.",
    "wof:placetype":"venue"
},
  "geometry": {"coordinates":[3.352301,49.372929],"type":"Point"}
}