{
  "type": "Feature",
  "properties": {
    "addr:full":"2, Rue Bois Bouquin, 37110 Ch\u00e2teau Renault Autr\u00e8che Centre 37110",
    "addr:housenumber":"2;autre\u0300che",
    "addr:postcode":"37110;37110",
    "addr:street":"Rue Bois Bouquin",
    "iso:country":"FR",
    "sg:address":"2, Rue Bois Bouquin, 37110 Ch\u00e2teau Renault",
    "sg:city":"Autr\u00e8che",
    "sg:orig_category":"Non-Classified Establishments",
    "sg:phone":"+33 2 47 29 53 73",
    "sg:postcode":"37110",
    "sg:province":"Centre",
    "wof:name":"A.i. Plastics S.a.r.l.",
    "wof:placetype":"venue"
},
  "geometry": {"coordinates":[0.895955,47.592129],"type":"Point"}
}