{
  "type": "Feature",
  "properties": {
    "addr:full":"B.P. 8, 42420 Lorette^^Passage Gandin, 42420 Lorette Rhone-Alpes 42420",
    "addr:housenumber":"8",
    "addr:postcode":"42420;42420;42420",
    "addr:street":"B.P.;Gandin",
    "iso:country":"FR",
    "sg:address":"B.P. 8, 42420 Lorette^^Passage Gandin, 42420 Lorette",
    "sg:orig_category":"Non-Classified Establishments",
    "sg:phone":"+33 4 77 73 53 86",
    "sg:postcode":"42420",
    "sg:province":"Rhone-Alpes",
    "wof:name":"Mavinox S.a.",
    "wof:placetype":"venue"
},
  "geometry": {"coordinates":[4.58077,45.512573],"type":"Point"}
}