{
  "type": "Feature",
  "properties": {
    "addr:full":"97 Cours Gambetta Le Capitole Lyon Rhone-Alpes 69003",
    "addr:housenumber":"97",
    "addr:postcode":"69003",
    "addr:street":"Cours Gambetta",
    "iso:country":"FR",
    "sg:address":"97 Cours Gambetta Le Capitole",
    "sg:city":"Lyon",
    "sg:classifiers":[
        {
            "category":"Banks & Credit Unions",
            "subcategory":"Financial Services",
            "type":"Services"
        }
    ],
    "sg:phone":"+33 4 72 84 12 12",
    "sg:postcode":"69003",
    "sg:province":"Rhone-Alpes",
    "sg:tags":[
        "banking",
        "finance",
        "insurance"
    ],
    "wof:name":"Jacques Barthelemy Et Associes",
    "wof:placetype":"venue"
},
  "geometry": {"coordinates":[4.84978,45.760479],"type":"Point"}
}