{
  "type": "Feature",
  "properties": {
    "addr:full":"Clos du Grand Chemin Prin Deyran\u00e7on Poitou-Charentes 79210",
    "addr:postcode":"79210",
    "addr:street":"Clos Du Grand Chemin Prin Deyranc\u0327On",
    "iso:country":"FR",
    "sg:address":"Clos du Grand Chemin",
    "sg:city":"Prin Deyran\u00e7on",
    "sg:orig_category":"Unclassifiable Establishments",
    "sg:phone":"+33 5 49 26 33 22",
    "sg:postcode":"79210",
    "sg:province":"Poitou-Charentes",
    "wof:name":"Chamaleau S.a.s.",
    "wof:placetype":"venue"
},
  "geometry": {"coordinates":[-0.606155,46.143532],"type":"Point"}
}