{
  "type": "Feature",
  "properties": {
    "addr:full":"B.P. 1017, 26010 Valence C\u00e9dex^^2, Place de la R\u00e9publique, 26000 Valence Rhone-Alpes 26000",
    "addr:postcode":"26010;26000;26000",
    "addr:street":"B.P. 1017;Place De La Re\u0301Publique",
    "iso:country":"FR",
    "sg:address":"B.P. 1017, 26010 Valence C\u00e9dex^^2, Place de la R\u00e9publique, 26000 Valence",
    "sg:orig_category":"Non-Classified Establishments",
    "sg:phone":"+33 4 75 75 86 86",
    "sg:postcode":"26000",
    "sg:province":"Rhone-Alpes",
    "wof:name":"S.m.c.",
    "wof:placetype":"venue"
},
  "geometry": {"coordinates":[4.889246,44.930458],"type":"Point"}
}