{
  "type": "Feature",
  "properties": {
    "iso:country":"FR",
    "sg:address":"100, Av. du G\u00e9n\u00e9ral Leclerc, 93500 Pantin",
    "sg:orig_category":"Unclassifiable Establishments",
    "sg:phone":"+33 1 48 10 36 30",
    "sg:province":"Ile de France",
    "wof:name":"Sercotex S.a.",
    "wof:placetype":"venue"
},
  "geometry": {"coordinates":[2.40312,48.896889],"type":"Point"}
}