{
  "type": "Feature",
  "properties": {
    "addr:full":"Rte de Bollwiller Soultz Haut Rhin Alsace 68360",
    "addr:postcode":"68360",
    "addr:street":"Rte De Bollwiller;Haut Rhin",
    "iso:country":"FR",
    "sg:address":"Rte de Bollwiller",
    "sg:city":"Soultz Haut Rhin",
    "sg:orig_category":"Unclassifiable Establishments",
    "sg:phone":"+33 3 89 74 45 00",
    "sg:postcode":"68360",
    "sg:province":"Alsace",
    "wof:name":"Sharp S.a.",
    "wof:placetype":"venue"
},
  "geometry": {"coordinates":[7.235465,47.880997],"type":"Point"}
}