{
  "type": "Feature",
  "properties": {
    "iso:country":"FR",
    "sg:address":"91, Bd Ir\u00e9ne Joliot Curie, 69200 V\u00e9nissieux",
    "sg:orig_category":"Unclassifiable Establishments",
    "sg:phone":"+33 4 78 78 52 52",
    "sg:postcode":"69200",
    "sg:province":"Rhone-Alpes",
    "wof:name":"Rexroth S.a.",
    "wof:placetype":"venue"
},
  "geometry": {"coordinates":[4.880507,45.713177],"type":"Point"}
}