{
  "type": "Feature",
  "properties": {
    "addr:full":"Les Quatre Ch\u00eanes 35760 Saint Gr\u00e9goire Montgermont Bretagne 35760",
    "addr:postcode":"35760;montgermont;35760",
    "addr:street":"Che\u0302Nes",
    "iso:country":"FR",
    "sg:address":"Les Quatre Ch\u00eanes 35760 Saint Gr\u00e9goire",
    "sg:city":"Montgermont",
    "sg:orig_category":"Non-Classified Establishments",
    "sg:phone":"+33 2 99 33 28 20",
    "sg:postcode":"35760",
    "sg:province":"Bretagne",
    "wof:name":"Kevrenn International S.a.r.l.",
    "wof:placetype":"venue"
},
  "geometry": {"coordinates":[-1.701529,48.142117],"type":"Point"}
}