{
  "type": "Feature",
  "properties": {
    "addr:full":"Ferme de la Houssaye - Garnetot L'Oudon Basse Normandie 14170",
    "addr:postcode":"14170",
    "addr:street":"Houssaye;L'Oudon Basse",
    "iso:country":"FR",
    "sg:address":"Ferme de la Houssaye - Garnetot",
    "sg:city":"L'Oudon",
    "sg:orig_category":"Unclassifiable Establishments",
    "sg:phone":"+33 2 31 20 70 07",
    "sg:postcode":"14170",
    "sg:province":"Basse Normandie",
    "wof:name":"Au Frisson Normand",
    "wof:placetype":"venue"
},
  "geometry": {"coordinates":[0.047738,48.927753],"type":"Point"}
}