{
  "type": "Feature",
  "properties": {
    "iso:country":"FR",
    "sg:address":"B.P. 548, 13682 Aubagne C\u00e9dex^^Z.I. Saint Mitre, 13400 Aubagne",
    "sg:orig_category":"Non-Classified Establishments",
    "sg:phone":"+33 4 42 84 51 00",
    "sg:province":"Basse Normandie",
    "wof:name":"Socado S.a.",
    "wof:placetype":"venue"
},
  "geometry": {"coordinates":[5.5687,43.292141],"type":"Point"}
}