{
  "type": "Feature",
  "properties": {
    "addr:full":"Chem De Gimeaux 13200 Arles Gimeaux Auvergne 63200",
    "addr:postcode":"13200;63200",
    "addr:street":"Chem;Gimeaux",
    "iso:country":"FR",
    "sg:address":"Chem De Gimeaux 13200 Arles",
    "sg:city":"Gimeaux",
    "sg:classifiers":[
        {
            "category":"Bars & Pubs",
            "subcategory":"Hookah Bar",
            "type":"Food & Drink"
        }
    ],
    "sg:phone":"+33 4 90 93 60 51",
    "sg:postcode":"63200",
    "sg:province":"Auvergne",
    "sg:tags":[
        "product",
        "livestock",
        "related",
        "grain",
        "cereal",
        "agriculture"
    ],
    "wof:name":"Riz (sica France)",
    "wof:placetype":"venue"
},
  "geometry": {"coordinates":[4.604977,43.673557],"type":"Point"}
}