{
  "type": "Feature",
  "properties": {
    "iso:country":"FR",
    "sg:address":"ZA",
    "sg:city":"Saint Laurent M\u00e9doc",
    "sg:orig_category":"Non-Classified Establishments",
    "sg:phone":"+33 5 56 59 46 43",
    "sg:postcode":"33112",
    "sg:province":"Aquitaine",
    "wof:name":"Etablissements Arnold Lechevin S.a.r.l.",
    "wof:placetype":"venue"
},
  "geometry": {"coordinates":[-0.821959,45.150249],"type":"Point"}
}