{
  "type": "Feature",
  "properties": {
    "iso:country":"FR",
    "sg:address":"B.P. 43, 92170 Vanves C\u00e9dex^^3, Rue Ernest Laval, 92170 Vanves",
    "sg:orig_category":"Non-Classified Establishments",
    "sg:phone":"+33 1 47 36 10 31",
    "sg:postcode":"92170",
    "sg:province":"Ile de France",
    "wof:name":"Assu 200 S.a.",
    "wof:placetype":"venue"
},
  "geometry": {"coordinates":[2.291016,48.820904],"type":"Point"}
}