{
  "type": "Feature",
  "properties": {
    "iso:country":"FR",
    "sg:address":"32, Rue Fran\u00e7ois Arago - P\u00f4le des Vaindes, 01000 Bourg en Bresse",
    "sg:orig_category":"Non-Classified Establishments",
    "sg:phone":"+33 4 74 22 30 66",
    "sg:postcode":"01000",
    "sg:province":"Rhone-Alpes",
    "wof:name":"C.a.b. S.a. - Coop\u00e9rative Abattage Bourg",
    "wof:placetype":"venue"
},
  "geometry": {"coordinates":[5.18957,46.199814],"type":"Point"}
}