{
  "type": "Feature",
  "properties": {
    "addr:full":"17 Rue Lanvignec 22500 Paimpol Paimpol Bretagne 22500",
    "addr:housenumber":"17",
    "addr:postcode":"22500;22500",
    "addr:street":"Rue Lanvignec",
    "iso:country":"FR",
    "sg:address":"17 Rue Lanvignec 22500 Paimpol",
    "sg:city":"Paimpol",
    "sg:classifiers":[
        {
            "category":"Professional",
            "subcategory":"Business Services",
            "type":"Services"
        }
    ],
    "sg:phone":"+33 2 96 55 35 40",
    "sg:postcode":"22500",
    "sg:province":"Bretagne",
    "sg:tags":[
        "training",
        "advice"
    ],
    "wof:name":"College Lanvignec",
    "wof:placetype":"venue"
},
  "geometry": {"coordinates":[-3.054553,48.78286],"type":"Point"}
}