{
  "type": "Feature",
  "properties": {
    "addr:full":"Rte de la Marolle - La Platine La Fert\u00e9 Saint Cyr Centre 41220",
    "addr:postcode":"41220",
    "addr:street":"Rte De La Marolle La Platine;Ferte\u0301 Saint",
    "iso:country":"FR",
    "sg:address":"Rte de la Marolle - La Platine",
    "sg:city":"La Fert\u00e9 Saint Cyr",
    "sg:orig_category":"Non-Classified Establishments",
    "sg:phone":"+33 2 54 87 66 65",
    "sg:postcode":"41220",
    "sg:province":"Centre",
    "wof:name":"Ciform S.a.r.l.",
    "wof:placetype":"venue"
},
  "geometry": {"coordinates":[1.657628,47.58931],"type":"Point"}
}