{
  "type": "Feature",
  "properties": {
    "iso:country":"FR",
    "sg:address":"449, Chemin des Plantades, 83130 La Garde",
    "sg:orig_category":"Non-Classified Establishments",
    "sg:phone":"+33 4 94 14 89 49",
    "sg:province":"Provence-Alpes-C\u00f4te d'Azur",
    "wof:name":"Laho Equipements S.a.",
    "wof:placetype":"venue"
},
  "geometry": {"coordinates":[6.026651,43.143383],"type":"Point"}
}