{
  "type": "Feature",
  "properties": {
    "iso:country":"FR",
    "sg:address":"104/106, Rue Jean Jaur\u00e8s, 79200 Parthenay",
    "sg:orig_category":"Non-Classified Establishments",
    "sg:phone":"+33 5 49 94 34 11",
    "sg:province":"Poitou-Charentes",
    "wof:name":"Microgat Informatique S.a.r.l.",
    "wof:placetype":"venue"
},
  "geometry": {"coordinates":[-0.252208,46.646397],"type":"Point"}
}