{
  "type": "Feature",
  "properties": {
    "addr:full":"3, Rue Garance - Immeuble Actys, 31670 Lab\u00e8ge Midi Pyr\u00e9n\u00e9es",
    "addr:housenumber":"3",
    "addr:postcode":"31670",
    "addr:street":"Rue Garance",
    "iso:country":"FR",
    "sg:address":"3, Rue Garance - Immeuble Actys, 31670 Lab\u00e8ge",
    "sg:orig_category":"Unclassifiable Establishments",
    "sg:phone":"+33 5 61 00 84 95",
    "sg:province":"Midi Pyr\u00e9n\u00e9es",
    "wof:name":"Demorum Logiciels S.a.r.l.",
    "wof:placetype":"venue"
},
  "geometry": {"coordinates":[1.500995,43.549866],"type":"Point"}
}