{
  "type": "Feature",
  "properties": {
    "iso:country":"FR",
    "sg:address":"B.P. 4, 33650 Cabanac et Villagrains^^10, Rte de la Gemmeyre - Le Boury , 33650 Cabanac et Villagrai",
    "sg:city":"Cabanac-et-Villagrains",
    "sg:orig_category":"Non-Classified Establishments",
    "sg:phone":"+33 5 57 97 02 50",
    "sg:postcode":"33650",
    "sg:province":"Aquitaine",
    "wof:name":"Ets Cluzant Et D\u00e9molin S.a.",
    "wof:placetype":"venue"
},
  "geometry": {"coordinates":[-0.594689,44.569355],"type":"Point"}
}