{
  "type": "Feature",
  "properties": {
    "addr:full":"B.P. 106, 12200 Villefranche de Rouergue C\u00e9dex^^Les Carri\u00e8res, 12200 Villefranche de Rouergue Midi Pyr\u00e9n\u00e9es 12200",
    "addr:housenumber":"b.p. 106",
    "addr:postcode":"12200;12200;12200",
    "iso:country":"FR",
    "sg:address":"B.P. 106, 12200 Villefranche de Rouergue C\u00e9dex^^Les Carri\u00e8res, 12200 Villefranche de Rouergue",
    "sg:orig_category":"Non-Classified Establishments",
    "sg:phone":"+33 5 65 45 05 20",
    "sg:postcode":"12200",
    "sg:province":"Midi Pyr\u00e9n\u00e9es",
    "wof:name":"Castres Industrie S.a.",
    "wof:placetype":"venue"
},
  "geometry": {"coordinates":[1.996273,44.265919],"type":"Point"}
}