{
  "type": "Feature",
  "properties": {
    "addr:full":"Rte de Brou - ZI Arrou Centre 28290",
    "addr:housenumber":"arrou",
    "addr:postcode":"28290",
    "addr:street":"Rte De Brou Zi",
    "iso:country":"FR",
    "sg:address":"Rte de Brou - ZI",
    "sg:city":"Arrou",
    "sg:orig_category":"Non-Classified Establishments",
    "sg:phone":"+33 2 37 97 08 99",
    "sg:postcode":"28290",
    "sg:province":"Centre",
    "wof:name":"O.g.c.t. Plastique S.a.r.l.",
    "wof:placetype":"venue"
},
  "geometry": {"coordinates":[1.142689,48.072193],"type":"Point"}
}