{
  "type": "Feature",
  "properties": {
    "addr:full":"ZI les Aulnes Condren Picardie 02700",
    "addr:postcode":"02700",
    "addr:street":"Zi Les;Picardie",
    "iso:country":"FR",
    "sg:address":"ZI les Aulnes",
    "sg:city":"Condren",
    "sg:orig_category":"Non-Classified Establishments",
    "sg:phone":"+33 3 23 57 54 50",
    "sg:postcode":"02700",
    "sg:province":"Picardie",
    "wof:name":"Rotoplast S.a.",
    "wof:placetype":"venue"
},
  "geometry": {"coordinates":[3.280905,49.628567],"type":"Point"}
}