{
  "type": "Feature",
  "properties": {
    "addr:full":"B.P. 14, 67880 Krautergersheim^^1, Rue du Mal Foch, 67880 Krautergersheim Krautergersheim Alsace 67880",
    "addr:postcode":"67880;67880;67880",
    "addr:street":"B.P. 14;Rue Du Mal Foch",
    "iso:country":"FR",
    "sg:address":"B.P. 14, 67880 Krautergersheim^^1, Rue du Mal Foch, 67880 Krautergersheim",
    "sg:city":"Krautergersheim",
    "sg:orig_category":"Non-Classified Establishments",
    "sg:phone":"+33 3 88 95 75 10",
    "sg:postcode":"67880",
    "sg:province":"Alsace",
    "wof:name":"Weber R. Et Fils Fabrication De Choucroute S.a.r.l.",
    "wof:placetype":"venue"
},
  "geometry": {"coordinates":[7.565579,48.476131],"type":"Point"}
}