{
  "type": "Feature",
  "properties": {
    "addr:full":"Rue Amp\u00e8re Laon Picardie 02000",
    "addr:postcode":"02000",
    "addr:street":"Rue Ampe\u0300Re;Picardie",
    "iso:country":"FR",
    "sg:address":"Rue Amp\u00e8re",
    "sg:city":"Laon",
    "sg:orig_category":"Unclassifiable Establishments",
    "sg:phone":"+33 3 23 23 10 58",
    "sg:postcode":"02000",
    "sg:province":"Picardie",
    "wof:name":"Meunier Transports S.a.r.l.",
    "wof:placetype":"venue"
},
  "geometry": {"coordinates":[3.645885,49.578499],"type":"Point"}
}