{
  "type": "Feature",
  "properties": {
    "iso:country":"FR",
    "sg:address":"13 route de Limonest 69380 LISSIEU",
    "sg:orig_category":"Surface Marking Systems",
    "sg:phone":"+33 4 72 54 80 00",
    "sg:province":"Rhone-Alpes",
    "wof:name":"Sic Marking Sas",
    "wof:placetype":"venue"
},
  "geometry": {"coordinates":[4.748696,45.872143],"type":"Point"}
}