{
  "type": "Feature",
  "properties": {
    "addr:full":"11 Rue Des Treize Langues 28200 Ch\u00e2teaudun Ch\u00e2teaudun Centre 28200",
    "addr:housenumber":"11",
    "addr:postcode":"28200;28200",
    "addr:street":"Rue Des Treize Langues",
    "iso:country":"FR",
    "sg:address":"11 Rue Des Treize Langues 28200 Ch\u00e2teaudun",
    "sg:city":"Ch\u00e2teaudun",
    "sg:classifiers":[
        {
            "category":"Utilities",
            "type":"Services"
        }
    ],
    "sg:phone":"+33 2 37 45 04 21",
    "sg:postcode":"28200",
    "sg:province":"Centre",
    "sg:tags":[
        "raw",
        "energy",
        "material"
    ],
    "wof:name":"Societe D'amenagement Urbain Et Rural (saur)",
    "wof:placetype":"venue"
},
  "geometry": {"coordinates":[1.34807,48.08675],"type":"Point"}
}