{
  "type": "Feature",
  "properties": {
    "addr:full":"Les Vergers 35120 Cherrueix Cherrueix Bretagne 35120",
    "addr:postcode":"35120;35120",
    "addr:street":"Les Vergers;Cherrueix",
    "iso:country":"FR",
    "sg:address":"Les Vergers 35120 Cherrueix",
    "sg:city":"Cherrueix",
    "sg:orig_category":"Non-Classified Establishments",
    "sg:phone":"+33 2 99 48 92 82",
    "sg:postcode":"35120",
    "sg:province":"Bretagne",
    "wof:name":"Maheu Dutertre S.a.r.l.",
    "wof:placetype":"venue"
},
  "geometry": {"coordinates":[-1.715704,48.58329],"type":"Point"}
}