{
  "type": "Feature",
  "properties": {
    "addr:full":"3 Rue De Stockholm 13127 Vitrolles Centre",
    "addr:housenumber":"3",
    "addr:postcode":"13127",
    "addr:street":"Rue De Stockholm",
    "iso:country":"FR",
    "sg:address":"3 Rue De Stockholm 13127 Vitrolles",
    "sg:classifiers":[
        {
            "category":"Autos & Motor Vehicles",
            "subcategory":"Automobile Sales",
            "type":"Retail Goods"
        }
    ],
    "sg:phone":"+33 4 42 15 01 50",
    "sg:province":"Centre",
    "sg:tags":[
        "equipment",
        "industrial",
        "transport"
    ],
    "wof:name":"Unicea France Sa",
    "wof:placetype":"venue"
},
  "geometry": {"coordinates":[5.24112,43.434132],"type":"Point"}
}