{
  "type": "Feature",
  "properties": {
    "addr:full":"8, Rue Vernier, 75017 Paris Ile de France 75017",
    "addr:housenumber":"8",
    "addr:postcode":"75017;75017",
    "addr:street":"Rue Vernier",
    "iso:country":"FR",
    "sg:address":"8, Rue Vernier, 75017 Paris",
    "sg:orig_category":"Non-Classified Establishments",
    "sg:phone":"+33 1 34 34 15 15",
    "sg:postcode":"75017",
    "sg:province":"Ile de France",
    "wof:name":"Butard Enescot",
    "wof:placetype":"venue"
},
  "geometry": {"coordinates":[2.290986,48.883266],"type":"Point"}
}