{
  "type": "Feature",
  "properties": {
    "iso:country":"FR",
    "sg:address":"40 avenue Georges Pompidou 15000 Aurillac",
    "sg:city":"Aurillac",
    "sg:classifiers":[
        {
            "category":"Home & Garden",
            "subcategory":"Home Furnishings",
            "type":"Retail Goods"
        }
    ],
    "sg:phone":"+33 4 71 45 52 52",
    "sg:postcode":"15000",
    "sg:province":"Auvergne",
    "sg:tags":[
        "desk"
    ],
    "wof:name":"Lafa Mobilier Sa",
    "wof:placetype":"venue"
},
  "geometry": {"coordinates":[2.453655,44.911785],"type":"Point"}
}