{
  "type": "Feature",
  "properties": {
    "addr:full":"Les Chatelets BP 4529 22045 St Brieuc Bretagne",
    "addr:housenumber":"bp 4529",
    "addr:postcode":"22045",
    "addr:street":"St Brieuc",
    "iso:country":"FR",
    "sg:address":"Les Chatelets",
    "sg:city":"BP 4529 22045 St Brieuc",
    "sg:classifiers":[
        {
            "category":"Manufacturing",
            "subcategory":"Printing",
            "type":"Manufacturing & Wholesale Goods"
        }
    ],
    "sg:phone":"+33 2 96 76 62 10",
    "sg:province":"Bretagne",
    "sg:tags":[
        "publishing"
    ],
    "wof:name":"Les Presses Bretonnes",
    "wof:placetype":"venue"
},
  "geometry": {"coordinates":[-2.763814,48.515701],"type":"Point"}
}