{
  "type": "Feature",
  "properties": {
    "iso:country":"FR",
    "sg:address":"B.P. 40567",
    "sg:city":"Metz C\u00e9dex 01",
    "sg:orig_category":"Non-Classified Establishments",
    "sg:phone":"+33 3 87 30 82 31",
    "sg:postcode":"57010",
    "sg:province":"Lorraine",
    "wof:name":"C.a.p.e.m. - Comit\u00e9 D'am\u00e9nagement De Promotion Et D'expansion De La Moselle",
    "wof:placetype":"venue"
},
  "geometry": {"coordinates":[6.17572,49.119331],"type":"Point"}
}