{
  "type": "Feature",
  "properties": {
    "addr:full":"21 Rue De Provence 69800 St Priest Rhone-Alpes 69800",
    "addr:housenumber":"21",
    "addr:postcode":"69800;69800",
    "addr:street":"Rue De Provence",
    "iso:country":"FR",
    "sg:address":"21 Rue De Provence 69800 St Priest",
    "sg:classifiers":[
        {
            "category":"Professional",
            "subcategory":"Engineering",
            "type":"Services"
        }
    ],
    "sg:phone":"+33 4 78 20 68 42",
    "sg:postcode":"69800",
    "sg:province":"Rhone-Alpes",
    "sg:tags":[
        "machine",
        "-",
        "environment",
        "equipment",
        "machinery",
        "mechanical"
    ],
    "wof:name":"Gr",
    "wof:placetype":"venue"
},
  "geometry": {"coordinates":[4.923395,45.693871],"type":"Point"}
}