{
  "type": "Feature",
  "properties": {
    "addr:full":"427, Rte du Hazay - Zone Portuaire, 78520 Limay Ile de France",
    "addr:housenumber":"427",
    "addr:postcode":"78520",
    "addr:street":"Rte Du Hazay;Portuaire;Ile De France",
    "iso:country":"FR",
    "sg:address":"427, Rte du Hazay - Zone Portuaire, 78520 Limay",
    "sg:orig_category":"Non-Classified Establishments",
    "sg:phone":"+33 1 34 97 25 25",
    "sg:province":"Ile de France",
    "wof:name":"Groupe Sarp Industries S.a.",
    "wof:placetype":"venue"
},
  "geometry": {"coordinates":[1.73261,48.994545],"type":"Point"}
}