{
  "type": "Feature",
  "properties": {
    "iso:country":"FR",
    "sg:address":"B.P. 60, 53420 Chaillant^^Rte Ern\u00e9 Laval, 53500 Ern\u00e9e",
    "sg:orig_category":"Non-Classified Establishments",
    "sg:phone":"+33 2 43 02 77 77",
    "sg:postcode":"53420",
    "sg:province":"Pays de Loire",
    "wof:name":"Boy\u00e8re S.a.",
    "wof:placetype":"venue"
},
  "geometry": {"coordinates":[-1.027721,48.273811],"type":"Point"}
}