{
  "type": "Feature",
  "properties": {
    "iso:country":"FR",
    "sg:address":"Moulin De Grenet 17400 Courcelles",
    "sg:classifiers":[
        {
            "category":"Food & Beverages",
            "subcategory":"Groceries & Convenience Stores",
            "type":"Retail Goods"
        }
    ],
    "sg:phone":"+33 5 46 32 12 01",
    "sg:postcode":"17400",
    "sg:province":"Poitou-Charentes",
    "sg:tags":[
        "product",
        "grain",
        "cereal",
        "related"
    ],
    "wof:name":"Minoterie Mechain",
    "wof:placetype":"venue"
},
  "geometry": {"coordinates":[-0.521604,45.890095],"type":"Point"}
}