{
  "type": "Feature",
  "properties": {
    "iso:country":"FR",
    "sg:address":"B.P. 755, 84035 Avignon C\u00e9dex^^115, Rte de Montfavet, 84000 Avignon",
    "sg:orig_category":"Non-Classified Establishments",
    "sg:phone":"+33 4 90 13 13 00",
    "sg:province":"Languedoc-Roussillon",
    "wof:name":"Bordet S.a.",
    "wof:placetype":"venue"
},
  "geometry": {"coordinates":[4.806015,43.948753],"type":"Point"}
}