{
  "type": "Feature",
  "properties": {
    "addr:full":"26 Rue Anatole France 92300 Levallois Perret Ile de France 92300",
    "addr:housenumber":"26",
    "addr:postcode":"92300;ile;92300",
    "addr:street":"Rue Anatole France;France",
    "iso:country":"FR",
    "sg:address":"26 Rue Anatole France 92300 Levallois Perret",
    "sg:orig_category":"Chemicals and Pharmaceuticals Chemistry - by-products Energy Environment - machinery and equipment M",
    "sg:phone":"+33 1 41 34 05 80",
    "sg:postcode":"92300",
    "sg:province":"Ile de France",
    "wof:name":"Sopac",
    "wof:placetype":"venue"
},
  "geometry": {"coordinates":[2.287747,48.889374],"type":"Point"}
}