{
  "type": "Feature",
  "properties": {
    "addr:full":"19, Rue Honor\u00e9 de Balzac, 69330 Meyzieu Rhone-Alpes",
    "addr:housenumber":"19",
    "addr:postcode":"69330",
    "addr:street":"Rue Honore\u0301 De Balzac",
    "iso:country":"FR",
    "sg:address":"19, Rue Honor\u00e9 de Balzac, 69330 Meyzieu",
    "sg:orig_category":"Unclassifiable Establishments",
    "sg:phone":"+33 4 78 31 02 70",
    "sg:province":"Rhone-Alpes",
    "wof:name":"Sorotec S.a.r.l.",
    "wof:placetype":"venue"
},
  "geometry": {"coordinates":[4.994054,45.78598],"type":"Point"}
}