{
  "type": "Feature",
  "properties": {
    "addr:full":"2 Avenue Robert Schuman 68100 Mulhouse Mulhouse Alsace 68100",
    "addr:housenumber":"2",
    "addr:postcode":"68100;68100",
    "addr:street":"Avenue Robert Schuman",
    "iso:country":"FR",
    "sg:address":"2 Avenue Robert Schuman 68100 Mulhouse",
    "sg:city":"Mulhouse",
    "sg:classifiers":[
        {
            "category":"Professional",
            "subcategory":"Advertising",
            "type":"Services"
        }
    ],
    "sg:phone":"+33 3 89 66 85 66",
    "sg:postcode":"68100",
    "sg:province":"Alsace",
    "sg:tags":[
        "information",
        "medium",
        "communication"
    ],
    "wof:name":"Les Dernieres Nouvelles D'alsace",
    "wof:placetype":"venue"
},
  "geometry": {"coordinates":[7.338939,47.750427],"type":"Point"}
}