{
  "type": "Feature",
  "properties": {
    "addr:full":"B.P. 470, 69659 Villefranche sur Sa\u00f4ne C\u00e9dex^^Av. de Beaujeu, 69650 Villefranche sur Sa\u00f4ne Rhone-Alpes 69650",
    "addr:housenumber":"b.p. 470",
    "addr:postcode":"69659;69650;69650",
    "addr:street":"Beaujeu;Rhone-Alpes",
    "iso:country":"FR",
    "sg:address":"B.P. 470, 69659 Villefranche sur Sa\u00f4ne C\u00e9dex^^Av. de Beaujeu, 69650 Villefranche sur Sa\u00f4ne",
    "sg:orig_category":"Non-Classified Establishments",
    "sg:phone":"+33 4 74 68 45 49",
    "sg:postcode":"69650",
    "sg:province":"Rhone-Alpes",
    "wof:name":"Giraud Rh\u00f4ne Alpes S.a.",
    "wof:placetype":"venue"
},
  "geometry": {"coordinates":[4.77716,45.913994],"type":"Point"}
}