{
  "type": "Feature",
  "properties": {
    "addr:full":"5 Rue De Bitche 57620 Goetzenbruck Lorraine 57620",
    "addr:housenumber":"5",
    "addr:postcode":"57620;57620",
    "addr:street":"Rue De Bitche",
    "iso:country":"FR",
    "sg:address":"5 Rue De Bitche 57620 Goetzenbruck",
    "sg:classifiers":[
        {
            "category":"Health Services",
            "subcategory":"Optometrist",
            "type":"Services"
        }
    ],
    "sg:phone":"+33 3 87 06 60 60",
    "sg:postcode":"57620",
    "sg:province":"Lorraine",
    "sg:tags":[
        "instrument",
        "optical",
        "-",
        "precision",
        "equipment"
    ],
    "wof:name":"Industrie Optique Sola S A",
    "wof:placetype":"venue"
},
  "geometry": {"coordinates":[7.38192,48.98621],"type":"Point"}
}