{
  "type": "Feature",
  "properties": {
    "addr:full":"5A250, PA Savipol, 10300 Sainte Savine Champagne",
    "addr:housenumber":"5a250",
    "addr:postcode":"10300",
    "iso:country":"FR",
    "sg:address":"5A250, PA Savipol, 10300 Sainte Savine",
    "sg:orig_category":"Unclassifiable Establishments",
    "sg:phone":"+33 3 25 74 94 29",
    "sg:province":"Champagne",
    "wof:name":"Rib S.a.r.l.",
    "wof:placetype":"venue"
},
  "geometry": {"coordinates":[4.014694,48.290302],"type":"Point"}
}