{
  "type": "Feature",
  "properties": {
    "addr:full":"1, Rue des Promenades - Immeuble Le Tertial, 59110 La Madeleine Nord Pas-de-Calais 59110",
    "addr:housenumber":"1",
    "addr:postcode":"59110;59110",
    "addr:street":"Rue Des Promenades Immeuble Le Tertial",
    "iso:country":"FR",
    "sg:address":"1, Rue des Promenades - Immeuble Le Tertial, 59110 La Madeleine",
    "sg:orig_category":"Non-Classified Establishments",
    "sg:phone":"+33 3 20 55 58 03",
    "sg:postcode":"59110",
    "sg:province":"Nord Pas-de-Calais",
    "wof:name":"Direct S.a.",
    "wof:placetype":"venue"
},
  "geometry": {"coordinates":[3.060945,50.653069],"type":"Point"}
}