{
  "type": "Feature",
  "properties": {
    "addr:full":"1 Rue De Montlu\u00e7on 60150 Thourotte Picardie 60150",
    "addr:housenumber":"1",
    "addr:postcode":"60150;60150",
    "addr:street":"Rue De Montluc\u0327On;Picardie",
    "iso:country":"FR",
    "sg:address":"1 Rue De Montlu\u00e7on 60150 Thourotte",
    "sg:classifiers":[
        {
            "category":"Travel",
            "subcategory":"Hotels & Motels",
            "type":"Entertainment"
        }
    ],
    "sg:phone":"+33 3 44 76 03 27",
    "sg:postcode":"60150",
    "sg:province":"Picardie",
    "sg:tags":[
        "hotels",
        "business",
        "restaurant"
    ],
    "wof:name":"St Gobain Chantereine",
    "wof:placetype":"venue"
},
  "geometry": {"coordinates":[2.89471,49.485199],"type":"Point"}
}