{
  "type": "Feature",
  "properties": {
    "iso:country":"FR",
    "sg:address":"B.P. 12, 73492 La Ravoire Cedex^^ZI de l'Albanne, 73490 La Ravoire",
    "sg:orig_category":"Non-Classified Establishments",
    "sg:phone":"+33 4 79 28 28 50",
    "sg:province":"Rhone-Alpes",
    "wof:name":"Interco S.a.",
    "wof:placetype":"venue"
},
  "geometry": {"coordinates":[5.958541,45.546753],"type":"Point"}
}