{
  "type": "Feature",
  "properties": {
    "iso:country":"FR",
    "sg:address":"Le Bignon 35137 Bed\u00e9e",
    "sg:city":"B\u00e9d\u00e9e",
    "sg:orig_category":"Unclassifiable Establishments",
    "sg:phone":"+33 2 99 09 86 09",
    "sg:postcode":"35137",
    "sg:province":"Bretagne",
    "wof:name":"Au Grand Saloir Saint-nicolas S.a.",
    "wof:placetype":"venue"
},
  "geometry": {"coordinates":[-86.782593,33.208271],"type":"Point"}
}