{
  "type": "Feature",
  "properties": {
    "addr:full":"24 Rue De La Vaserie 44340 Bouguenais Pays de Loire 44340",
    "addr:housenumber":"24",
    "addr:postcode":"44340;44340",
    "addr:street":"Rue De La Vaserie",
    "iso:country":"FR",
    "sg:address":"24 Rue De La Vaserie 44340 Bouguenais",
    "sg:classifiers":[
        {
            "category":"Building & Trades",
            "subcategory":"Construction",
            "type":"Services"
        }
    ],
    "sg:phone":"+33 2 40 26 92 92",
    "sg:postcode":"44340",
    "sg:province":"Pays de Loire",
    "sg:tags":[
        "work",
        "public"
    ],
    "wof:name":"Freyssinet France",
    "wof:placetype":"venue"
},
  "geometry": {"coordinates":[-1.587457,47.187157],"type":"Point"}
}