{
  "type": "Feature",
  "properties": {
    "addr:full":"29 Rue Charles De Gaulle 60800 Crepy En Valois Picardie 60800",
    "addr:housenumber":"29",
    "addr:postcode":"60800;60800",
    "addr:street":"Rue Charles De Gaulle",
    "iso:country":"FR",
    "sg:address":"29 Rue Charles De Gaulle 60800 Crepy En Valois",
    "sg:classifiers":[
        {
            "category":"Retail",
            "subcategory":"Event Space",
            "type":"Services"
        }
    ],
    "sg:phone":"+33 3 44 59 12 06",
    "sg:postcode":"60800",
    "sg:province":"Picardie",
    "sg:tags":[
        "product",
        "transport",
        "road",
        "miscellaneous"
    ],
    "wof:name":"Ogf",
    "wof:placetype":"venue"
},
  "geometry": {"coordinates":[2.887301,49.233173],"type":"Point"}
}