{
  "type": "Feature",
  "properties": {
    "iso:country":"FR",
    "sg:address":"Chem Vert",
    "sg:city":"Clermont 95340 Persan",
    "sg:classifiers":[
        {
            "category":"Government",
            "subcategory":"Department Of Motor Vehicles",
            "type":"Public Place"
        }
    ],
    "sg:phone":"+33 1 39 37 50 00",
    "sg:postcode":"95340",
    "sg:province":"Ile de France",
    "sg:tags":[
        "equipment",
        "industrial",
        "transport",
        "motor-cars"
    ],
    "wof:name":"Mahle Filtersysteme",
    "wof:placetype":"venue"
},
  "geometry": {"coordinates":[2.276365,49.151005],"type":"Point"}
}