{
  "type": "Feature",
  "properties": {
    "addr:full":"B.P. 137 Lure C\u00e9dex Franche Comt\u00e9 70203",
    "addr:housenumber":"b.p. 137",
    "addr:postcode":"70203",
    "addr:street":"Franche Comte\u0301",
    "iso:country":"FR",
    "sg:address":"B.P. 137",
    "sg:city":"Lure C\u00e9dex",
    "sg:orig_category":"Non-Classified Establishments",
    "sg:phone":"+33 3 84 89 02 00",
    "sg:postcode":"70203",
    "sg:province":"Franche Comt\u00e9",
    "wof:name":"Tissage De La C\u00f4te S.a.",
    "wof:placetype":"venue"
},
  "geometry": {"coordinates":[6.497465,47.682686],"type":"Point"}
}