{
  "type": "Feature",
  "properties": {
    "iso:country":"FR",
    "sg:address":"37, Rue de Ponthieu, 75008 Paris",
    "sg:orig_category":"Non-Classified Establishments",
    "sg:phone":"+33 1 42 56 36 65",
    "sg:province":"Ile de France",
    "wof:name":"Intercontinental Triad Sarl",
    "wof:placetype":"venue"
},
  "geometry": {"coordinates":[2.307657,48.871147],"type":"Point"}
}