{
  "type": "Feature",
  "properties": {
    "addr:full":"Zac De La Goulagatire 35221 Ch\u00e2teaubourg Centre",
    "addr:postcode":"35221",
    "addr:street":"Zac De La Goulagatire",
    "iso:country":"FR",
    "sg:address":"Zac De La Goulagatire 35221 Ch\u00e2teaubourg",
    "sg:classifiers":[
        {
            "category":"Shopping",
            "subcategory":"Computers & Home Electronics",
            "type":"Retail Goods"
        }
    ],
    "sg:phone":"+33 2 99 62 33 80",
    "sg:province":"Centre",
    "sg:tags":[
        "equipment",
        "electrical",
        "component",
        "electric",
        "electronic"
    ],
    "wof:name":"Transfo Services Sarl",
    "wof:placetype":"venue"
},
  "geometry": {"coordinates":[-86.900673,33.455589],"type":"Point"}
}