{
  "type": "Feature",
  "properties": {
    "iso:country":"FR",
    "sg:address":"B.P. 275, 62204 Boulogne sur Mer C\u00e9dex^^ZI de la Tr\u00e9sorerie, 62200 Boulogne sur Mer",
    "sg:orig_category":"Non-Classified Establishments",
    "sg:phone":"+33 3 21 32 27 27",
    "sg:province":"Nord Pas-de-Calais",
    "wof:name":"Soprop\u00eache S.a.s.",
    "wof:placetype":"venue"
},
  "geometry": {"coordinates":[1.615514,50.727444],"type":"Point"}
}