{
  "type": "Feature",
  "properties": {
    "iso:country":"FR",
    "sg:address":"31, Place Jules Grandcl\u00e9ment - Immeuble de Saint Nicolas, 69100 Villeurbanne",
    "sg:orig_category":"Non-Classified Establishments",
    "sg:phone":"+33 4 72 91 26 26",
    "sg:province":"Rhone-Alpes",
    "wof:name":"Isor S.a.",
    "wof:placetype":"venue"
},
  "geometry": {"coordinates":[4.887207,45.758892],"type":"Point"}
}