{
  "type": "Feature",
  "properties": {
    "iso:country":"FR",
    "sg:address":"13, Rue Jules Jeanneney, 70300 Luxeuil les Bains",
    "sg:orig_category":"Non-Classified Establishments",
    "sg:phone":"+33 3 84 40 05 21",
    "sg:province":"Franche Comt\u00e9",
    "wof:name":"Romain Passard S.a.r.l.",
    "wof:placetype":"venue"
},
  "geometry": {"coordinates":[6.380761,47.815067],"type":"Point"}
}