{
  "type": "Feature",
  "properties": {
    "addr:full":"1 Avenue Aristide Briand 77410 Claye Souilly Ile de France 77410",
    "addr:housenumber":"1",
    "addr:postcode":"77410;77410",
    "addr:street":"Avenue Aristide Briand",
    "iso:country":"FR",
    "sg:address":"1 Avenue Aristide Briand 77410 Claye Souilly",
    "sg:classifiers":[
        {
            "category":"Manufacturing",
            "subcategory":"Metals",
            "type":"Manufacturing & Wholesale Goods"
        }
    ],
    "sg:phone":"+33 1 60 26 00 09",
    "sg:postcode":"77410",
    "sg:province":"Ile de France",
    "sg:tags":[
        "-",
        "machine",
        "equipment",
        "engineering",
        "machinery",
        "mechanical"
    ],
    "wof:name":"Entreprise Macquet",
    "wof:placetype":"venue"
},
  "geometry": {"coordinates":[2.696,48.944519],"type":"Point"}
}