{
  "type": "Feature",
  "properties": {
    "addr:full":"20 Av P\u00e9rigord 33370 Artigues Pr\u00e8s Bordeaux Artigues-pr\u00e8s-Bordeaux Aquitaine 33370",
    "addr:postcode":"33370;33370",
    "addr:street":"20 Av",
    "iso:country":"FR",
    "sg:address":"20 Av P\u00e9rigord 33370 Artigues Pr\u00e8s Bordeaux",
    "sg:city":"Artigues-pr\u00e8s-Bordeaux",
    "sg:classifiers":[
        {
            "category":"Banks & Credit Unions",
            "subcategory":"Investment Brokerage",
            "type":"Services"
        }
    ],
    "sg:phone":"+33 5 57 34 04 60",
    "sg:postcode":"33370",
    "sg:province":"Aquitaine",
    "sg:tags":[
        "-",
        "transport",
        "related"
    ],
    "wof:name":"Atms Sarl",
    "wof:placetype":"venue"
},
  "geometry": {"coordinates":[-0.474379,44.86544],"type":"Point"}
}