{
  "type": "Feature",
  "properties": {
    "addr:full":"Rte de Bergerac Eymet Aquitaine 24500",
    "addr:postcode":"24500",
    "addr:street":"Rte De Bergerac",
    "iso:country":"FR",
    "sg:address":"Rte de Bergerac",
    "sg:city":"Eymet",
    "sg:orig_category":"Unclassifiable Establishments",
    "sg:phone":"+33 5 53 23 81 92",
    "sg:postcode":"24500",
    "sg:province":"Aquitaine",
    "wof:name":"Les Cars Bleus S.a.r.l.",
    "wof:placetype":"venue"
},
  "geometry": {"coordinates":[0.408171,44.677948],"type":"Point"}
}