{
  "type": "Feature",
  "properties": {
    "addr:full":"218, Rue de Rosny, 93106 Montreuil C\u00e9dex Haute Normandie",
    "addr:housenumber":"218",
    "addr:postcode":"93106",
    "addr:street":"Rue De Rosny;Haute Normandie",
    "iso:country":"FR",
    "sg:address":"218, Rue de Rosny, 93106 Montreuil C\u00e9dex",
    "sg:orig_category":"Non-Classified Establishments",
    "sg:phone":"+33 1 40 70 42 42",
    "sg:province":"Haute Normandie",
    "wof:name":"E.p.l.s. S.a.",
    "wof:placetype":"venue"
},
  "geometry": {"coordinates":[2.442661,48.864525],"type":"Point"}
}