{
  "type": "Feature",
  "properties": {
    "addr:full":"18, Rue des Majots, 80000 Amiens Picardie 80000",
    "addr:housenumber":"18",
    "addr:postcode":"80000;80000",
    "addr:street":"Rue Des Majots",
    "iso:country":"FR",
    "sg:address":"18, Rue des Majots, 80000 Amiens",
    "sg:orig_category":"Non-Classified Establishments",
    "sg:phone":"+33 3 22 92 28 13",
    "sg:postcode":"80000",
    "sg:province":"Picardie",
    "wof:name":"Ceres Conseil S.a.r.l.",
    "wof:placetype":"venue"
},
  "geometry": {"coordinates":[2.302042,49.896961],"type":"Point"}
}