{
  "type": "Feature",
  "properties": {
    "addr:full":"Pi De L'Erdre 44540 St Mars La Jaille Pays de Loire 44540",
    "addr:postcode":"44540;44540",
    "addr:street":"Pi;Jaille",
    "iso:country":"FR",
    "sg:address":"Pi De L'Erdre 44540 St Mars La Jaille",
    "sg:classifiers":[
        {
            "category":"Manufacturing",
            "subcategory":"Metals",
            "type":"Manufacturing & Wholesale Goods"
        }
    ],
    "sg:phone":"+33 2 40 97 60 90",
    "sg:postcode":"44540",
    "sg:province":"Pays de Loire",
    "sg:tags":[
        "metallurgy",
        "metalworking",
        "processing"
    ],
    "wof:name":"Metal 44",
    "wof:placetype":"venue"
},
  "geometry": {"coordinates":[-1.178767,47.525688],"type":"Point"}
}