{
  "type": "Feature",
  "properties": {
    "addr:full":"86, Rte de Montpellier, 34200 S\u00e8te Languedoc-Roussillon",
    "addr:housenumber":"86",
    "addr:postcode":"34200",
    "addr:street":"Rte De Montpellier",
    "iso:country":"FR",
    "sg:address":"86, Rte de Montpellier, 34200 S\u00e8te",
    "sg:orig_category":"Non-Classified Establishments",
    "sg:phone":"+33 4 67 51 89 00",
    "sg:province":"Languedoc-Roussillon",
    "wof:name":"Touat S.a.",
    "wof:placetype":"venue"
},
  "geometry": {"coordinates":[3.69633,43.399052],"type":"Point"}
}