{
  "type": "Feature",
  "properties": {
    "addr:full":"92 avenue Fran\u00e7ois Mitterrand 36000 CHATEAUROUX Ch\u00e2teauroux Centre 36000",
    "addr:housenumber":"92",
    "addr:postcode":"36000;36000",
    "addr:street":"Avenue Franc\u0327Ois Mitterrand;Cha\u0302Teauroux",
    "iso:country":"FR",
    "sg:address":"92 avenue Fran\u00e7ois Mitterrand 36000 CHATEAUROUX",
    "sg:city":"Ch\u00e2teauroux",
    "sg:classifiers":[
        {
            "category":"Manufacturing",
            "subcategory":"Textiles",
            "type":"Manufacturing & Wholesale Goods"
        }
    ],
    "sg:phone":"+33 2 54 53 48 48",
    "sg:postcode":"36000",
    "sg:province":"Centre",
    "sg:tags":[
        "finishing",
        "auxiliary"
    ],
    "wof:name":"Le Flockage Sa",
    "wof:placetype":"venue"
},
  "geometry": {"coordinates":[1.675693,46.811047],"type":"Point"}
}