{
  "type": "Feature",
  "properties": {
    "addr:full":"35 rue du Docteur Oursel; B.P. 187; EVREUX CEDEX; 27001 Haute Normandie",
    "addr:housenumber":"35;187",
    "addr:postcode":"27001",
    "addr:street":"Rue Du Docteur Oursel B.P.",
    "iso:country":"FR",
    "sg:address":"35 rue du Docteur Oursel; B.P. 187; EVREUX CEDEX; 27001",
    "sg:classifiers":[
        {
            "category":"Shopping",
            "subcategory":"Computers & Home Electronics",
            "type":"Retail Goods"
        }
    ],
    "sg:phone":"+33 3232388100",
    "sg:province":"Haute Normandie",
    "sg:tags":[
        "chamber",
        "commerce"
    ],
    "wof:name":"C.c.i De L'eure",
    "wof:placetype":"venue"
},
  "geometry": {"coordinates":[1.13663,49.023628],"type":"Point"}
}