{
  "type": "Feature",
  "properties": {
    "iso:country":"FR",
    "sg:address":"17 Rue De L' Erbonni\u00e8re Zi Sud Est Chantepie 35510 Cesson Sevigne",
    "sg:city":"Cesson-S\u00e9vign\u00e9",
    "sg:classifiers":[
        {
            "category":"Professional",
            "type":"Services"
        }
    ],
    "sg:phone":"+33 2 99 86 87 88",
    "sg:postcode":"35510",
    "sg:province":"Bretagne",
    "sg:tags":[
        "transport",
        "road"
    ],
    "wof:name":"Ducros Euro Express Sa",
    "wof:placetype":"venue"
},
  "geometry": {"coordinates":[-1.604202,48.102985],"type":"Point"}
}