{
  "type": "Feature",
  "properties": {
    "iso:country":"FR",
    "sg:address":"B.P. 17, 11000 Carcassonne C\u00e9dex^^11, Av. du G\u00e9n\u00e9ral Leclerc, 11000 Carcassonne",
    "sg:orig_category":"Non-Classified Establishments",
    "sg:phone":"+33 4 68 10 54 54",
    "sg:postcode":"11000",
    "sg:province":"Languedoc-Roussillon",
    "wof:name":"Chipie International S.a.s.",
    "wof:placetype":"venue"
},
  "geometry": {"coordinates":[2.306378,43.188465],"type":"Point"}
}