{
  "type": "Feature",
  "properties": {
    "iso:country":"FR",
    "sg:address":"8, Rue Vaucausson, 63300 Thiers",
    "sg:city":"Thiers",
    "sg:orig_category":"Unclassifiable Establishments",
    "sg:phone":"+33 4 73 80 03 20",
    "sg:postcode":"63300",
    "sg:province":"Auvergne",
    "wof:name":"Laviale Guy",
    "wof:placetype":"venue"
},
  "geometry": {"coordinates":[3.563396,45.82058],"type":"Point"}
}