{
  "type": "Feature",
  "properties": {
    "addr:full":"4, Rue du Saering, 68500 Guebwiller Guebwiller Alsace 68500",
    "addr:housenumber":"4",
    "addr:postcode":"68500;68500",
    "addr:street":"Rue Du Saering",
    "iso:country":"FR",
    "sg:address":"4, Rue du Saering, 68500 Guebwiller",
    "sg:city":"Guebwiller",
    "sg:orig_category":"Unclassifiable Establishments",
    "sg:phone":"+33 3 89 74 11 12",
    "sg:postcode":"68500",
    "sg:province":"Alsace",
    "wof:name":"Unfer-zusslin S.a.",
    "wof:placetype":"venue"
},
  "geometry": {"coordinates":[7.225236,47.903866],"type":"Point"}
}