{
  "type": "Feature",
  "properties": {
    "addr:full":"A\u00e9roport de Morlaix Morlaix Bretagne 29600",
    "addr:postcode":"29600",
    "iso:country":"FR",
    "sg:address":"A\u00e9roport de Morlaix",
    "sg:city":"Morlaix",
    "sg:orig_category":"Unclassifiable Establishments",
    "sg:phone":"+33 2 98 62 39 39",
    "sg:postcode":"29600",
    "sg:province":"Bretagne",
    "wof:name":"C.c.i. De Morlaix - Chambre De Commerce Et D'industrie De Morlaix",
    "wof:placetype":"venue"
},
  "geometry": {"coordinates":[-3.826259,48.577026],"type":"Point"}
}