{
  "type": "Feature",
  "properties": {
    "addr:full":"62 bis, Av. Andr\u00e9 Morizet, 92643 Boulogne Billancourt C\u00e9dex \u00cele-de-France",
    "addr:housenumber":"62 bis",
    "addr:postcode":"92643",
    "addr:street":"Av. Andre\u0301 Morizet;Ce\u0301Dex",
    "iso:country":"FR",
    "sg:address":"62 bis, Av. Andr\u00e9 Morizet, 92643 Boulogne Billancourt C\u00e9dex",
    "sg:orig_category":"Non-Classified Establishments",
    "sg:phone":"+33 1 41 86 10 00",
    "sg:province":"\u00cele-de-France",
    "wof:name":"S\u00e9agat Technology S.a.",
    "wof:placetype":"venue"
},
  "geometry": {"coordinates":[2.235655,48.837479],"type":"Point"}
}