{
  "type": "Feature",
  "properties": {
    "iso:country":"FR",
    "sg:address":"R Du Cuivre 77176 Savigny Le Temple",
    "sg:classifiers":[
        {
            "category":"Manufacturing",
            "subcategory":"Metals",
            "type":"Manufacturing & Wholesale Goods"
        }
    ],
    "sg:phone":"+33 1 64 41 44 44",
    "sg:postcode":"77176",
    "sg:province":"Ile de France",
    "sg:tags":[
        "metallurgy",
        "steel",
        "metalworking"
    ],
    "wof:name":"Hueck France Sarl",
    "wof:placetype":"venue"
},
  "geometry": {"coordinates":[2.591132,48.588181],"type":"Point"}
}