{
  "type": "Feature",
  "properties": {
    "addr:full":"Zi La Garnasse 43240 St Just Malmont Saint-Just-Malmont Auvergne 43240",
    "addr:postcode":"43240;43240",
    "addr:street":"Zi La Garnasse",
    "iso:country":"FR",
    "sg:address":"Zi La Garnasse 43240 St Just Malmont",
    "sg:city":"Saint-Just-Malmont",
    "sg:classifiers":[
        {
            "category":"Professional",
            "type":"Services"
        }
    ],
    "sg:phone":"+33 4 77 35 68 43",
    "sg:postcode":"43240",
    "sg:province":"Auvergne",
    "sg:tags":[
        "transport",
        "road"
    ],
    "wof:name":"Transports Pierre Rousson Sarl",
    "wof:placetype":"venue"
},
  "geometry": {"coordinates":[4.313666,45.339558],"type":"Point"}
}