{
  "type": "Feature",
  "properties": {
    "iso:country":"FR",
    "sg:address":"Z IRue Henri Fabre 47400 TONNEINS",
    "sg:city":"Tonneins",
    "sg:orig_category":"Powdered Yoghurt",
    "sg:phone":"+33 5 53 79 04 36",
    "sg:postcode":"47400",
    "sg:province":"Aquitaine",
    "wof:name":"Ste Industrielle De Fabrication De Poudres Alimentaires Sa",
    "wof:placetype":"venue"
},
  "geometry": {"coordinates":[0.299815,44.402039],"type":"Point"}
}