{
  "type": "Feature",
  "properties": {
    "addr:full":"49 Rue R\u00e9aumur 75003 Paris Ile de France",
    "addr:housenumber":"49",
    "addr:postcode":"75003",
    "addr:street":"Rue Re\u0301Aumur",
    "iso:country":"FR",
    "sg:address":"49 Rue R\u00e9aumur 75003 Paris",
    "sg:classifiers":[
        {
            "category":"Professional",
            "type":"Services"
        }
    ],
    "sg:phone":"+33 1 42 71 39 79",
    "sg:province":"Ile de France",
    "sg:tags":[
        "transport",
        "road"
    ],
    "wof:name":"Brinks Evolution",
    "wof:placetype":"venue"
},
  "geometry": {"coordinates":[2.352676,48.866066],"type":"Point"}
}