{
  "type": "Feature",
  "properties": {
    "iso:country":"FR",
    "sg:address":"155, Rue du Docteur Bauer, 93400 Saint Ouen",
    "sg:orig_category":"Unclassifiable Establishments",
    "sg:phone":"+33 1 49 48 93 00",
    "sg:province":"Ile de France",
    "wof:name":"Pilote Distribution S.a.",
    "wof:placetype":"venue"
},
  "geometry": {"coordinates":[2.346922,48.903778],"type":"Point"}
}