{
  "type": "Feature",
  "properties": {
    "iso:country":"FR",
    "sg:address":"12 bis, Bd Saint Ruf, 84000 Avignon",
    "sg:orig_category":"Non-Classified Establishments",
    "sg:phone":"+33 4 90 80 60 50",
    "sg:province":"Provence-Alpes-C\u00f4te d'Azur",
    "wof:name":"Randstad Int\u00e9rim",
    "wof:placetype":"venue"
},
  "geometry": {"coordinates":[4.80827,43.930214],"type":"Point"}
}