{
  "type": "Feature",
  "properties": {
    "iso:country":"FR",
    "sg:address":"Z ARTISANALE CHARABOUTIE 42160 ST CYPRIEN",
    "sg:orig_category":"Infants' Clothing",
    "sg:phone":"+33 4 77 36 42 68",
    "sg:postcode":"42160",
    "sg:province":"Rhone-Alpes",
    "wof:name":"Oxaro Sarl",
    "wof:placetype":"venue"
},
  "geometry": {"coordinates":[4.25674,45.52943],"type":"Point"}
}