{
  "type": "Feature",
  "properties": {
    "addr:full":"B.P. 190, 01105 Oyonnax C\u00e9dex^^11, Rue Pascal, 01100 Oyonnax Rhone-Alpes",
    "addr:housenumber":"b.p. 190",
    "addr:postcode":"01105;01100",
    "addr:street":"Rue Pascal",
    "iso:country":"FR",
    "sg:address":"B.P. 190, 01105 Oyonnax C\u00e9dex^^11, Rue Pascal, 01100 Oyonnax",
    "sg:orig_category":"Non-Classified Establishments",
    "sg:phone":"+33 4 74 77 28 31",
    "sg:province":"Rhone-Alpes",
    "wof:name":"Guignot S.a.r.l.",
    "wof:placetype":"venue"
},
  "geometry": {"coordinates":[5.64405,46.24968],"type":"Point"}
}