{
  "type": "Feature",
  "properties": {
    "addr:full":"Cr\u00e9dit Mutuel de Bretagne, Direction G\u00e9n\u00e9rale et Services Centraux, 29808 Brest Cedex 09, Dept 29, F Bretagne",
    "addr:housenumber":"29",
    "addr:postcode":"29808",
    "addr:street":"F",
    "iso:country":"FR",
    "sg:address":"Cr\u00e9dit Mutuel de Bretagne, Direction G\u00e9n\u00e9rale et Services Centraux, 29808 Brest Cedex 09, Dept 29, F",
    "sg:classifiers":[
        {
            "category":"Banks & Credit Unions",
            "subcategory":"Bank",
            "type":"Services"
        }
    ],
    "sg:phone":"+33 2 98 00 22 22",
    "sg:province":"Bretagne",
    "wof:name":"Compagnie Financi\u00e8re Du Cr\u00e9dit Mutuel",
    "wof:placetype":"venue"
},
  "geometry": {"coordinates":[-4.48622,48.390228],"type":"Point"}
}