{
  "type": "Feature",
  "properties": {
    "addr:full":"Rue Henri Striet 14126 Mondeville Vill\u00e9 Alsace 67220",
    "addr:postcode":"14126;67220",
    "addr:street":"Rue Henri Striet;Ville\u0301",
    "iso:country":"FR",
    "sg:address":"Rue Henri Striet 14126 Mondeville",
    "sg:city":"Vill\u00e9",
    "sg:classifiers":[
        {
            "category":"Wholesale",
            "subcategory":"Metals & Minerals",
            "type":"Manufacturing & Wholesale Goods"
        }
    ],
    "sg:phone":"+33 2 31 82 54 40",
    "sg:postcode":"67220",
    "sg:province":"Alsace",
    "sg:tags":[
        "steel",
        "metallurgy",
        "metalworking",
        "processing"
    ],
    "wof:name":"Rencast",
    "wof:placetype":"venue"
},
  "geometry": {"coordinates":[-0.318344,49.178711],"type":"Point"}
}