{
  "type": "Feature",
  "properties": {
    "iso:country":"FR",
    "sg:address":"2, Rue de Trac\u00e9, 72100 Le Mans",
    "sg:orig_category":"Unclassifiable Establishments",
    "sg:phone":"+33 2 43 41 40 79",
    "sg:province":"Pays de Loire",
    "wof:name":"Le Mans Usinage S.a.r.l.",
    "wof:placetype":"venue"
},
  "geometry": {"coordinates":[0.19767,47.989391],"type":"Point"}
}