{
  "type": "Feature",
  "properties": {
    "addr:full":"Route De Lisieux 27260 Cormeilles Haute Normandie 27260",
    "addr:postcode":"27260;27260",
    "addr:street":"Route De Lisieux",
    "iso:country":"FR",
    "sg:address":"Route De Lisieux 27260 Cormeilles",
    "sg:classifiers":[
        {
            "category":"Food Court",
            "type":"Food & Drink"
        }
    ],
    "sg:phone":"+33 2 32 57 80 08",
    "sg:postcode":"27260",
    "sg:province":"Haute Normandie",
    "sg:tags":[
        "product",
        "related"
    ],
    "wof:name":"Distillerie Busnel",
    "wof:placetype":"venue"
},
  "geometry": {"coordinates":[0.380015,49.244934],"type":"Point"}
}