{
  "type": "Feature",
  "properties": {
    "iso:country":"FR",
    "sg:address":"1 Bis R De Plaisance 94130 Nogent Sur Marne",
    "sg:classifiers":[
        {
            "category":"Health Services",
            "subcategory":"Medical Lab",
            "type":"Services"
        }
    ],
    "sg:phone":"+33 1 43 24 70 70",
    "sg:postcode":"94130",
    "sg:province":"Ile de France",
    "sg:tags":[
        "chemical",
        "pharmaceutical",
        "pharmacy"
    ],
    "wof:name":"Laboratoire Fuca Sa",
    "wof:placetype":"venue"
},
  "geometry": {"coordinates":[2.489667,48.838451],"type":"Point"}
}