{
  "type": "Feature",
  "properties": {
    "iso:country":"FR",
    "sg:address":"2, Rue du Canal, 21470 Brazey en Plaine",
    "sg:city":"Brazey-en-Plaine",
    "sg:orig_category":"Non-Classified Establishments",
    "sg:phone":"+33 3 80 29 90 05",
    "sg:postcode":"21470",
    "sg:province":"Bourgogne",
    "wof:name":"S.r.e.i. S.a.r.l. - Soci\u00e9t\u00e9 De Recherche En Electronique Industrielle",
    "wof:placetype":"venue"
},
  "geometry": {"coordinates":[5.21818,47.138485],"type":"Point"}
}