{
  "type": "Feature",
  "properties": {
    "iso:country":"FR",
    "sg:address":"Rte Charasses",
    "sg:city":"Colroy la Roche",
    "sg:orig_category":"Unclassifiable Establishments",
    "sg:phone":"+33 3 88 97 60 45",
    "sg:postcode":"67420",
    "sg:province":"Alsace",
    "wof:name":"Seriag S.a.r.l.",
    "wof:placetype":"venue"
},
  "geometry": {"coordinates":[7.176476,48.38921],"type":"Point"}
}