{
  "type": "Feature",
  "properties": {
    "iso:country":"FR",
    "sg:address":"B.P. 107, 01601 Tr\u00e9voux C\u00e9dex^^ZI les Communaux, 01600 Reyrieux",
    "sg:orig_category":"Non-Classified Establishments",
    "sg:phone":"+33 4 74 00 44 99",
    "sg:postcode":"01600",
    "sg:province":"Rhone-Alpes",
    "wof:name":"Etablissements Gabriel Et Compagnie S.a.",
    "wof:placetype":"venue"
},
  "geometry": {"coordinates":[4.79649,45.94265],"type":"Point"}
}