{
  "type": "Feature",
  "properties": {
    "iso:country":"FR",
    "sg:address":"1 Allee Des Tilleuls Ecoparc 27400 Louviers",
    "sg:classifiers":[
        {
            "category":"Food & Beverages",
            "subcategory":"Groceries & Convenience Stores",
            "type":"Retail Goods"
        }
    ],
    "sg:phone":"+33 2 32 25 04 04",
    "sg:postcode":"27400",
    "sg:province":"Haute Normandie",
    "sg:tags":[
        "product",
        "related"
    ],
    "wof:name":"Cuisine Solutions",
    "wof:placetype":"venue"
},
  "geometry": {"coordinates":[1.134962,49.107613],"type":"Point"}
}