{
  "type": "Feature",
  "properties": {
    "iso:country":"FR",
    "sg:address":"Place Jean Monnet",
    "sg:city":"Ploemeur",
    "sg:orig_category":"Unclassifiable Establishments",
    "sg:phone":"+33 2 97 86 46 46",
    "sg:postcode":"56270",
    "sg:province":"Bretagne",
    "wof:name":"A.a.c. S.a. - Associ\u00e9s Audit Et Conseil",
    "wof:placetype":"venue"
},
  "geometry": {"coordinates":[-3.424849,47.733833],"type":"Point"}
}