{
  "type": "Feature",
  "properties": {
    "iso:country":"FR",
    "sg:address":"368, Fbg de Lyon - ZI, 01120 Montluel",
    "sg:orig_category":"Unclassifiable Establishments",
    "sg:phone":"+33 4 78 06 52 32",
    "sg:postcode":"01120",
    "sg:province":"Rhone-Alpes",
    "wof:name":"Aries S.a.",
    "wof:placetype":"venue"
},
  "geometry": {"coordinates":[5.051237,45.858295],"type":"Point"}
}