{
  "type": "Feature",
  "properties": {
    "addr:full":"2 rue Paul Rohmer 67200 Strasbourg Strasbourg Alsace 67200",
    "addr:housenumber":"2",
    "addr:postcode":"67200;67200",
    "addr:street":"Rue Paul Rohmer",
    "iso:country":"FR",
    "sg:address":"2 rue Paul Rohmer 67200 Strasbourg",
    "sg:city":"Strasbourg",
    "sg:classifiers":[
        {
            "category":"Manufacturing",
            "subcategory":"Metals",
            "type":"Manufacturing & Wholesale Goods"
        }
    ],
    "sg:phone":"+33 3 90 20 46 70",
    "sg:postcode":"67200",
    "sg:province":"Alsace",
    "sg:tags":[
        "ironmongery"
    ],
    "wof:name":"Ferrures Et Patines Sarl",
    "wof:placetype":"venue"
},
  "geometry": {"coordinates":[7.689885,48.586319],"type":"Point"}
}