{
  "type": "Feature",
  "properties": {
    "addr:full":"9 Rue Du Port 37520 La Riche La Riche Centre 37520",
    "addr:housenumber":"9",
    "addr:postcode":"37520;37520",
    "addr:street":"Rue Du Port",
    "iso:country":"FR",
    "sg:address":"9 Rue Du Port 37520 La Riche",
    "sg:city":"La Riche",
    "sg:classifiers":[
        {
            "category":"Utilities",
            "subcategory":"Telephone",
            "type":"Services"
        }
    ],
    "sg:phone":"+33 2 47 37 37 77",
    "sg:postcode":"37520",
    "sg:province":"Centre",
    "sg:tags":[
        "telecommunication"
    ],
    "wof:name":"Applications Artistiques Electro Plastique De Touraine Aa Elpat (elpat)",
    "wof:placetype":"venue"
},
  "geometry": {"coordinates":[0.666144,47.391697],"type":"Point"}
}