{
  "type": "Feature",
  "properties": {
    "iso:country":"FR",
    "sg:address":"B.P. 26, 80480 Saleux^^2, Rue Ernest Cauvin, 80480 Saleux",
    "sg:orig_category":"Non-Classified Establishments",
    "sg:phone":"+33 3 22 45 00 03",
    "sg:province":"Picardie",
    "wof:name":"Picardie Staff S.a.r.l.",
    "wof:placetype":"venue"
},
  "geometry": {"coordinates":[2.243165,49.870926],"type":"Point"}
}