{
  "type": "Feature",
  "properties": {
    "addr:full":"29 Boulevard D Anvaux 36000 Chateauroux Ch\u00e2teauroux Centre 36000",
    "addr:housenumber":"29",
    "addr:postcode":"36000;36000",
    "addr:street":"Boulevard D Anvaux;Cha\u0302Teauroux",
    "iso:country":"FR",
    "sg:address":"29 Boulevard D Anvaux 36000 Chateauroux",
    "sg:city":"Ch\u00e2teauroux",
    "sg:classifiers":[
        {
            "category":"Manufacturing",
            "subcategory":"Metals",
            "type":"Manufacturing & Wholesale Goods"
        }
    ],
    "sg:phone":"+33 2 54 07 70 01",
    "sg:postcode":"36000",
    "sg:province":"Centre",
    "sg:tags":[
        "-",
        "machine",
        "equipment",
        "engineering",
        "machinery",
        "mechanical"
    ],
    "wof:name":"Megtec Systems Sa (meg)",
    "wof:placetype":"venue"
},
  "geometry": {"coordinates":[1.73841,46.80125],"type":"Point"}
}