{
  "type": "Feature",
  "properties": {
    "iso:country":"FR",
    "sg:address":"154 Hameau Quenonville 77570 Bougligny",
    "sg:classifiers":[
        {
            "category":"Professional",
            "subcategory":"Engineering",
            "type":"Services"
        }
    ],
    "sg:phone":"+33 1 64 28 75 85",
    "sg:postcode":"77570",
    "sg:province":"Ile de France",
    "sg:tags":[
        "machine",
        "-",
        "mechanical"
    ],
    "wof:name":"Remoiville Sa",
    "wof:placetype":"venue"
},
  "geometry": {"coordinates":[2.70282,48.149406],"type":"Point"}
}