{
  "type": "Feature",
  "properties": {
    "iso:country":"FR",
    "sg:address":"B.P. 32",
    "sg:city":"Neufch\u00e2tel en Bray^^Le Four Rouge 76270 Neufchatel en Bray",
    "sg:orig_category":"Non-Classified Establishments",
    "sg:phone":"+33 2 35 94 95 95",
    "sg:postcode":"76270",
    "sg:province":"Haute Normandie",
    "wof:name":"Cordonnier S.a.r.l.",
    "wof:placetype":"venue"
},
  "geometry": {"coordinates":[1.399665,49.690815],"type":"Point"}
}