{
  "type": "Feature",
  "properties": {
    "addr:full":"Rue du 19 Mars 1962 Beaurepaire Haute Normandie 38270",
    "addr:postcode":"38270",
    "addr:street":"Rue Du 19 Mars 1962;Haute Normandie",
    "iso:country":"FR",
    "sg:address":"Rue du 19 Mars 1962",
    "sg:city":"Beaurepaire",
    "sg:orig_category":"Unclassifiable Establishments",
    "sg:phone":"+33 4 74 79 07 00",
    "sg:postcode":"38270",
    "sg:province":"Haute Normandie",
    "wof:name":"C.a.t. Et Foyer Henri Robin",
    "wof:placetype":"venue"
},
  "geometry": {"coordinates":[5.054485,45.336479],"type":"Point"}
}