{
  "type": "Feature",
  "properties": {
    "addr:full":"5, Rue de la Montagne, 89340 Chaumont Saint-Agnan Bourgogne 89340",
    "addr:housenumber":"5",
    "addr:postcode":"89340;89340",
    "addr:street":"Rue De La Montagne",
    "iso:country":"FR",
    "sg:address":"5, Rue de la Montagne, 89340 Chaumont",
    "sg:city":"Saint-Agnan",
    "sg:orig_category":"Non-Classified Establishments",
    "sg:phone":"+33 3 86 96 61 69",
    "sg:postcode":"89340",
    "sg:province":"Bourgogne",
    "wof:name":"Le Ch\u00e2teau De Chaumont",
    "wof:placetype":"venue"
},
  "geometry": {"coordinates":[3.104696,48.324398],"type":"Point"}
}