{
  "type": "Feature",
  "properties": {
    "iso:country":"FR",
    "sg:address":"33, Fbg des Vosges, 68800 Thann",
    "sg:city":"Thann",
    "sg:orig_category":"Unclassifiable Establishments",
    "sg:phone":"+33 3 89 37 11 18",
    "sg:postcode":"68800",
    "sg:province":"Alsace",
    "wof:name":"Lutringer Sillon S.a.",
    "wof:placetype":"venue"
},
  "geometry": {"coordinates":[7.089066,47.815678],"type":"Point"}
}