{
  "type": "Feature",
  "properties": {
    "iso:country":"FR",
    "sg:address":"36 Rue Des Carmes 01100 Oyonnax Cedex",
    "sg:classifiers":[
        {
            "category":"Manufacturing",
            "subcategory":"Rubber & Plastics",
            "type":"Manufacturing & Wholesale Goods"
        }
    ],
    "sg:phone":"+33 4 74 77 80 44",
    "sg:province":"Rhone-Alpes",
    "wof:name":"Ets Georges David Sa",
    "wof:placetype":"venue"
},
  "geometry": {"coordinates":[5.666011,46.261269],"type":"Point"}
}