{
  "type": "Feature",
  "properties": {
    "addr:full":"113 Cs Berriat 38000 Grenoble Rhone-Alpes 38000",
    "addr:housenumber":"113",
    "addr:postcode":"38000;38000",
    "addr:street":"Cs Berriat",
    "iso:country":"FR",
    "sg:address":"113 Cs Berriat 38000 Grenoble",
    "sg:classifiers":[
        {
            "category":"Manufacturing",
            "subcategory":"Tools & Machinery",
            "type":"Manufacturing & Wholesale Goods"
        }
    ],
    "sg:phone":"+33 4 76 33 49 49",
    "sg:postcode":"38000",
    "sg:province":"Rhone-Alpes",
    "sg:tags":[
        "metallurgy",
        "metalworking"
    ],
    "wof:name":"A Raymond Sarl",
    "wof:placetype":"venue"
},
  "geometry": {"coordinates":[5.70961,45.18848],"type":"Point"}
}