{
  "type": "Feature",
  "properties": {
    "iso:country":"FR",
    "sg:address":"6 Rue Du Pont De L'Arche 37550 St Avertin",
    "sg:city":"Saint-Avertin",
    "sg:classifiers":[
        {
            "category":"Manufacturing",
            "subcategory":"Tools & Machinery",
            "type":"Manufacturing & Wholesale Goods"
        }
    ],
    "sg:phone":"+33 2 47 27 20 15",
    "sg:postcode":"37550",
    "sg:province":"Centre",
    "sg:tags":[
        "equipment",
        "measurement",
        "-",
        "precision",
        "instrument"
    ],
    "wof:name":"Manumesure",
    "wof:placetype":"venue"
},
  "geometry": {"coordinates":[0.73428,47.354641],"type":"Point"}
}