{
  "type": "Feature",
  "properties": {
    "addr:full":"20 Avenue Charles De Gaulle 01330 Villars Les Dombes Rhone-Alpes 01330",
    "addr:housenumber":"20",
    "addr:postcode":"01330;01330",
    "addr:street":"Avenue Charles De Gaulle;Rhone-Alpes",
    "iso:country":"FR",
    "sg:address":"20 Avenue Charles De Gaulle 01330 Villars Les Dombes",
    "sg:classifiers":[
        {
            "category":"Home & Garden",
            "subcategory":"Furniture",
            "type":"Retail Goods"
        }
    ],
    "sg:phone":"+33 4 74 98 24 93",
    "sg:postcode":"01330",
    "sg:province":"Rhone-Alpes",
    "sg:tags":[
        "household",
        "wood"
    ],
    "wof:name":"Jsm Productions",
    "wof:placetype":"venue"
},
  "geometry": {"coordinates":[5.029725,45.999836],"type":"Point"}
}