{
  "type": "Feature",
  "properties": {
    "addr:full":"Parc d'Activit\u00e9s du Ponteix Feytiat Limousin 87220",
    "addr:postcode":"87220",
    "iso:country":"FR",
    "sg:address":"Parc d'Activit\u00e9s du Ponteix",
    "sg:city":"Feytiat",
    "sg:orig_category":"Unclassifiable Establishments",
    "sg:phone":"+33 5 55 30 52 30",
    "sg:postcode":"87220",
    "sg:province":"Limousin",
    "wof:name":"Inov'd\u00e9cor S.a.r.l.",
    "wof:placetype":"venue"
},
  "geometry": {"coordinates":[1.298609,45.807583],"type":"Point"}
}