{
  "type": "Feature",
  "properties": {
    "addr:full":"14, Rue du Patronnage La\u00efque, 52000 Chaumont Champagne",
    "addr:housenumber":"14",
    "addr:postcode":"52000",
    "addr:street":"Rue Du Patronnage Lai\u0308Que",
    "iso:country":"FR",
    "sg:address":"14, Rue du Patronnage La\u00efque, 52000 Chaumont",
    "sg:orig_category":"Unclassifiable Establishments",
    "sg:phone":"+33 3 25 87 08 34",
    "sg:province":"Champagne",
    "wof:name":"Imprimerie De Champagne S.a.",
    "wof:placetype":"venue"
},
  "geometry": {"coordinates":[5.143485,48.106682],"type":"Point"}
}