{
  "type": "Feature",
  "properties": {
    "iso:country":"FR",
    "sg:address":"3, Villa Poirier, 75015 Paris",
    "sg:orig_category":"Non-Classified Establishments",
    "sg:phone":"+33 1 53 69 55 55",
    "sg:postcode":"75015",
    "sg:province":"Ile de France",
    "wof:name":"Cantoriel S.a.",
    "wof:placetype":"venue"
},
  "geometry": {"coordinates":[2.30418,48.843445],"type":"Point"}
}