{
  "type": "Feature",
  "properties": {
    "addr:full":"Soumagne 87400 St L\u00e9onard De Noblat Limousin 87400",
    "addr:postcode":"87400;87400",
    "iso:country":"FR",
    "sg:address":"Soumagne 87400 St L\u00e9onard De Noblat",
    "sg:classifiers":[
        {
            "category":"Professional",
            "subcategory":"Engineering",
            "type":"Services"
        }
    ],
    "sg:phone":"+33 5 55 56 04 64",
    "sg:postcode":"87400",
    "sg:province":"Limousin",
    "sg:tags":[
        "machine",
        "-",
        "mechanical"
    ],
    "wof:name":"Galalitum Sa",
    "wof:placetype":"venue"
},
  "geometry": {"coordinates":[1.50009,45.822769],"type":"Point"}
}