{
  "type": "Feature",
  "properties": {
    "addr:full":"Rue Guynemer 33290 Blanquefort Blanquefort Aquitaine 33290",
    "addr:postcode":"33290;33290",
    "addr:street":"Rue Guynemer",
    "iso:country":"FR",
    "sg:address":"Rue Guynemer 33290 Blanquefort",
    "sg:city":"Blanquefort",
    "sg:classifiers":[
        {
            "category":"Manufacturing",
            "subcategory":"Metals",
            "type":"Manufacturing & Wholesale Goods"
        }
    ],
    "sg:phone":"+33 5 56 35 11 35",
    "sg:postcode":"33290",
    "sg:province":"Aquitaine",
    "sg:tags":[
        "metallurgy",
        "steel",
        "metalworking"
    ],
    "wof:name":"Abaque Industrie Sa",
    "wof:placetype":"venue"
},
  "geometry": {"coordinates":[-0.622979,44.923946],"type":"Point"}
}