{
  "type": "Feature",
  "properties": {
    "iso:country":"FR",
    "sg:address":"7 Route Loyettes 38230 Chavanoz",
    "sg:classifiers":[
        {
            "category":"Manufacturing",
            "subcategory":"Metals",
            "type":"Manufacturing & Wholesale Goods"
        }
    ],
    "sg:phone":"+33 4 72 46 19 60",
    "sg:postcode":"38230",
    "sg:province":"Rhone-Alpes",
    "sg:tags":[
        "metallurgy",
        "steel",
        "metalworking"
    ],
    "wof:name":"Gindre Composants Sa",
    "wof:placetype":"venue"
},
  "geometry": {"coordinates":[5.194933,45.765343],"type":"Point"}
}