{
  "type": "Feature",
  "properties": {
    "addr:full":"7 Rue Gounod 75017 Paris Ile de France 75017",
    "addr:housenumber":"7",
    "addr:postcode":"75017;75017",
    "addr:street":"Rue Gounod",
    "iso:country":"FR",
    "sg:address":"7 Rue Gounod 75017 Paris",
    "sg:classifiers":[
        {
            "category":"Professional",
            "subcategory":"Advertising",
            "type":"Services"
        }
    ],
    "sg:phone":"+33 1 42 67 05 05",
    "sg:postcode":"75017",
    "sg:province":"Ile de France",
    "sg:tags":[
        "communication",
        "medium"
    ],
    "wof:name":"Quad Productions",
    "wof:placetype":"venue"
},
  "geometry": {"coordinates":[2.3004,48.883083],"type":"Point"}
}