{
  "type": "Feature",
  "properties": {
    "iso:country":"FR",
    "sg:address":"15, Rue du 1er Mai, 92000 Nanterre",
    "sg:orig_category":"Non-Classified Establishments",
    "sg:phone":"+33 1 47 85 52 20",
    "sg:postcode":"92000",
    "sg:province":"Ile de France",
    "wof:name":"Automax Control S.a.r.l.",
    "wof:placetype":"venue"
},
  "geometry": {"coordinates":[2.213536,48.908756],"type":"Point"}
}