{
  "type": "Feature",
  "properties": {
    "iso:country":"FR",
    "sg:address":"B.P. 53, 59142 Villers Outr\u00e9aux^^48, Rue Cl\u00e9menceau, 59142 Villers Outr\u00e9aux",
    "sg:orig_category":"Non-Classified Establishments",
    "sg:phone":"+33 3 27 82 01 21",
    "sg:postcode":"59142",
    "sg:province":"Nord Pas-de-Calais",
    "wof:name":"Bourgeois Leclercq S.a.",
    "wof:placetype":"venue"
},
  "geometry": {"coordinates":[3.298357,50.032337],"type":"Point"}
}