{
  "type": "Feature",
  "properties": {
    "iso:country":"FR",
    "sg:address":"Rue De La Gare 71150 Rully",
    "sg:city":"Rully",
    "sg:classifiers":[
        {
            "category":"Shopping",
            "type":"Retail Goods"
        }
    ],
    "sg:phone":"+33 3 85 87 62 70",
    "sg:postcode":"71150",
    "sg:province":"Bourgogne",
    "sg:tags":[
        "metallurgy",
        "finished",
        "-",
        "metalworking",
        "metallic"
    ],
    "wof:name":"Tolerie Jannin Carnet",
    "wof:placetype":"venue"
},
  "geometry": {"coordinates":[4.75268,46.879173],"type":"Point"}
}