{
  "type": "Feature",
  "properties": {
    "addr:full":"140, All\u00e9e des R\u00e9sidences du Sal\u00e8ve, 74160 Collonges sous Sal\u00e8ve Rhone-Alpes",
    "addr:housenumber":"140",
    "addr:postcode":"74160",
    "addr:street":"Alle\u0301E Des Re\u0301Sidences Du Sale\u0300Ve;Sale\u0300Ve",
    "iso:country":"FR",
    "sg:address":"140, All\u00e9e des R\u00e9sidences du Sal\u00e8ve, 74160 Collonges sous Sal\u00e8ve",
    "sg:orig_category":"Unclassifiable Establishments",
    "sg:phone":"+33 4 50 95 32 84",
    "sg:province":"Rhone-Alpes",
    "wof:name":"Ecosys S.a.r.l.",
    "wof:placetype":"venue"
},
  "geometry": {"coordinates":[6.139875,46.140663],"type":"Point"}
}