{
  "type": "Feature",
  "properties": {
    "addr:full":"Chemin D\u00e9partemental 54 Avelin Nord Pas-de-Calais 59710",
    "addr:housenumber":"54",
    "addr:postcode":"59710",
    "addr:street":"Chemin De\u0301Partemental;Nord",
    "iso:country":"FR",
    "sg:address":"Chemin D\u00e9partemental 54",
    "sg:city":"Avelin",
    "sg:orig_category":"Unclassifiable Establishments",
    "sg:phone":"+33 3 20 62 01 22",
    "sg:postcode":"59710",
    "sg:province":"Nord Pas-de-Calais",
    "wof:name":"Avery International Syst\u00e8me D'etiquetage France S.a.s.",
    "wof:placetype":"venue"
},
  "geometry": {"coordinates":[3.080295,50.53793],"type":"Point"}
}