{
  "type": "Feature",
  "properties": {
    "addr:full":"Zi Nord 26300 Bourg De P\u00e8age Rhone-Alpes 26300",
    "addr:postcode":"26300;26300",
    "addr:street":"Zi;Rhone-Alpes",
    "iso:country":"FR",
    "sg:address":"Zi Nord 26300 Bourg De P\u00e8age",
    "sg:classifiers":[
        {
            "category":"Professional",
            "type":"Services"
        }
    ],
    "sg:phone":"+33 4 75 72 52 53",
    "sg:postcode":"26300",
    "sg:province":"Rhone-Alpes",
    "sg:tags":[
        "transport",
        "road"
    ],
    "wof:name":"Gondrand Freres Sarl",
    "wof:placetype":"venue"
},
  "geometry": {"coordinates":[5.04852,45.04092],"type":"Point"}
}