{
  "type": "Feature",
  "properties": {
    "addr:full":"Chem Ste Marguerite 66400 C\u00e9ret Languedoc-Roussillon",
    "addr:postcode":"66400",
    "addr:street":"Chem Ste Marguerite",
    "iso:country":"FR",
    "sg:address":"Chem Ste Marguerite 66400 C\u00e9ret",
    "sg:classifiers":[
        {
            "category":"Manufacturing",
            "subcategory":"Wood Products",
            "type":"Manufacturing & Wholesale Goods"
        }
    ],
    "sg:phone":"+33 4 68 83 11 91",
    "sg:province":"Languedoc-Roussillon",
    "sg:tags":[
        "furniture"
    ],
    "wof:name":"Pairot (maison)",
    "wof:placetype":"venue"
},
  "geometry": {"coordinates":[2.748129,42.49873],"type":"Point"}
}