{
  "type": "Feature",
  "properties": {
    "iso:country":"FR",
    "sg:address":"Peronne 80200 Peronne",
    "sg:classifiers":[
        {
            "category":"Shopping",
            "subcategory":"Clothing, Apparel, & Fashions",
            "type":"Retail Goods"
        }
    ],
    "sg:phone":"+33 3 22 83 83 83",
    "sg:postcode":"80200",
    "sg:province":"Picardie",
    "sg:tags":[
        "interlinings"
    ],
    "wof:name":"Laini\u00e8re De Picardie Sa",
    "wof:placetype":"venue"
},
  "geometry": {"coordinates":[2.93084,49.923698],"type":"Point"}
}