{
  "type": "Feature",
  "properties": {
    "addr:full":"B.P. 4, 72310 Bess\u00e9 sur Braye C\u00e9dex^^Rue Elie Savatier, 72310 Bess\u00e9 sur Braye Bess\u00e9 sur Braye Pays de Loire 72310",
    "addr:housenumber":"4",
    "addr:postcode":"72310;72310;braye;72310",
    "addr:street":"B.P.",
    "iso:country":"FR",
    "sg:address":"B.P. 4, 72310 Bess\u00e9 sur Braye C\u00e9dex^^Rue Elie Savatier, 72310 Bess\u00e9 sur Braye",
    "sg:city":"Bess\u00e9 sur Braye",
    "sg:orig_category":"Non-Classified Establishments",
    "sg:phone":"+33 2 43 63 12 34",
    "sg:postcode":"72310",
    "sg:province":"Pays de Loire",
    "wof:name":"F.t.b. S.a. - Fabrication Textile De La Braye",
    "wof:placetype":"venue"
},
  "geometry": {"coordinates":[0.690845,47.77095],"type":"Point"}
}