{
  "type": "Feature",
  "properties": {
    "addr:full":"19 des Italiens; Paris; 75002 Ile de France",
    "addr:housenumber":"19",
    "addr:postcode":"75002 ile",
    "addr:street":"Des Italiens",
    "iso:country":"FR",
    "sg:address":"19",
    "sg:city":"des Italiens; Paris; 75002",
    "sg:classifiers":[
        {
            "category":"Industrial Area",
            "type":"Public Place"
        }
    ],
    "sg:phone":"+33 1 49 53 15 15",
    "sg:province":"Ile de France",
    "sg:tags":[
        "large",
        "private"
    ],
    "wof:name":"Cr\u00e9dit Lyonnais",
    "wof:placetype":"venue"
},
  "geometry": {"coordinates":[2.336604,48.871296],"type":"Point"}
}