{
  "type": "Feature",
  "properties": {
    "addr:full":"Bat Alexandre 92230 Gennevilliers Ile de France 92230",
    "addr:postcode":"92230;ile;92230",
    "addr:street":"France",
    "iso:country":"FR",
    "sg:address":"Bat",
    "sg:city":"Alexandre 92230 Gennevilliers",
    "sg:classifiers":[
        {
            "category":"Manufacturing",
            "subcategory":"Tools & Machinery",
            "type":"Manufacturing & Wholesale Goods"
        }
    ],
    "sg:phone":"+33 1 46 88 99 00",
    "sg:postcode":"92230",
    "sg:province":"Ile de France",
    "sg:tags":[
        "environment",
        "equipment",
        "-"
    ],
    "wof:name":"Icf Environnement",
    "wof:placetype":"venue"
},
  "geometry": {"coordinates":[2.32228,48.921619],"type":"Point"}
}