{
  "type": "Feature",
  "properties": {
    "iso:country":"FR",
    "sg:address":"11, Av Henri Barbusse, 45700 Villemandeur",
    "sg:city":"Villemandeur",
    "sg:orig_category":"Non-Classified Establishments",
    "sg:phone":"+33 2 38 85 43 19",
    "sg:postcode":"45700",
    "sg:province":"Centre",
    "wof:name":"Transports Boffin S.a.r.l.",
    "wof:placetype":"venue"
},
  "geometry": {"coordinates":[2.712664,47.991215],"type":"Point"}
}