{
  "type": "Feature",
  "properties": {
    "iso:country":"FR",
    "sg:address":"460 Parc D Activite L Argile Avenue La Quiera 06370 Mouans Sartoux",
    "sg:classifiers":[
        {
            "category":"Manufacturing",
            "subcategory":"Chemicals & Compounds",
            "type":"Manufacturing & Wholesale Goods"
        }
    ],
    "sg:phone":"+33 4 92 28 38 10",
    "sg:province":"Midi Pyr\u00e9n\u00e9es",
    "sg:tags":[
        "pharmaceutical",
        "chemistry",
        "-",
        "by-product"
    ],
    "wof:name":"Fragrances Essentielles (frages)",
    "wof:placetype":"venue"
},
  "geometry": {"coordinates":[6.96621,43.618511],"type":"Point"}
}