{
  "type": "Feature",
  "properties": {
    "addr:full":"52 Rue Garennes 57155 Marly Aquitaine",
    "addr:housenumber":"52",
    "addr:postcode":"57155",
    "addr:street":"Rue Garennes",
    "iso:country":"FR",
    "sg:address":"52 Rue Garennes 57155 Marly",
    "sg:classifiers":[
        {
            "category":"Utilities",
            "subcategory":"Telephone",
            "type":"Services"
        }
    ],
    "sg:phone":"+33 3 87 38 90 90",
    "sg:province":"Aquitaine",
    "sg:tags":[
        "telecommunication"
    ],
    "wof:name":"Sefie Societe Nouvelle Sa",
    "wof:placetype":"venue"
},
  "geometry": {"coordinates":[6.144372,49.073757],"type":"Point"}
}