{
  "type": "Feature",
  "properties": {
    "addr:full":"2 Rue De La D\u00e9couverte 31676 Labege Cedex Lab\u00e8ge Midi Pyr\u00e9n\u00e9es 31670",
    "addr:housenumber":"2",
    "addr:postcode":"31676;31670",
    "addr:street":"Rue De La De\u0301Couverte",
    "iso:country":"FR",
    "sg:address":"2 Rue De La D\u00e9couverte 31676 Labege Cedex",
    "sg:city":"Lab\u00e8ge",
    "sg:classifiers":[
        {
            "category":"Professional",
            "subcategory":"Computer Services",
            "type":"Services"
        }
    ],
    "sg:phone":"+33 5 61 39 23 24",
    "sg:postcode":"31670",
    "sg:province":"Midi Pyr\u00e9n\u00e9es",
    "sg:tags":[
        "information",
        "technology",
        "software"
    ],
    "wof:name":"Magnus France",
    "wof:placetype":"venue"
},
  "geometry": {"coordinates":[1.504438,43.546341],"type":"Point"}
}