{
  "type": "Feature",
  "properties": {
    "addr:full":"B.P. 549, 77006 Melun C\u00e9dex^^938, Rue Saint Just - ZI de Vaux le P\u00e9nil, 77000 Melun Ile de France",
    "addr:housenumber":"b.p. 549",
    "addr:postcode":"77006;77000;ile",
    "addr:street":"Rue Saint Just Zi De Vaux Le Pe\u0301Nil",
    "iso:country":"FR",
    "sg:address":"B.P. 549, 77006 Melun C\u00e9dex^^938, Rue Saint Just - ZI de Vaux le P\u00e9nil, 77000 Melun",
    "sg:orig_category":"Non-Classified Establishments",
    "sg:phone":"+33 1 60 56 43 03",
    "sg:province":"Ile de France",
    "wof:name":"Etablissements Savigny S.a.",
    "wof:placetype":"venue"
},
  "geometry": {"coordinates":[2.664085,48.539577],"type":"Point"}
}