{
  "type": "Feature",
  "properties": {
    "addr:full":"La Vernelle 24510 St F\u00e9lix De Villadeix Saint-F\u00e9lix-de-Villadeix Aquitaine 24510",
    "addr:postcode":"24510;24510",
    "iso:country":"FR",
    "sg:address":"La Vernelle 24510 St F\u00e9lix De Villadeix",
    "sg:city":"Saint-F\u00e9lix-de-Villadeix",
    "sg:classifiers":[
        {
            "category":"Manufacturing",
            "subcategory":"Chemicals & Compounds",
            "type":"Manufacturing & Wholesale Goods"
        }
    ],
    "sg:phone":"+33 5 53 82 91 44",
    "sg:postcode":"24510",
    "sg:province":"Aquitaine",
    "sg:tags":[
        "pharmaceutical",
        "chemistry",
        "-",
        "by-product"
    ],
    "wof:name":"Eurl De Bonfils",
    "wof:placetype":"venue"
},
  "geometry": {"coordinates":[0.6491,44.937527],"type":"Point"}
}