{
  "type": "Feature",
  "properties": {
    "addr:full":"Kervriou 29370 Elliant Elliant Bretagne 29370",
    "addr:postcode":"29370;29370",
    "addr:street":"Kervriou;Elliant",
    "iso:country":"FR",
    "sg:address":"Kervriou 29370 Elliant",
    "sg:city":"Elliant",
    "sg:orig_category":"Agriculture - machinery and equipment Mechanical Engineering - machines Metallurgy and Metalworking ",
    "sg:phone":"+33 2 98 59 12 08",
    "sg:postcode":"29370",
    "sg:province":"Bretagne",
    "wof:name":"Armo Distribution",
    "wof:placetype":"venue"
},
  "geometry": {"coordinates":[-3.926819,48.033424],"type":"Point"}
}