{
  "type": "Feature",
  "properties": {
    "addr:full":"Ch\u00e2teau de Calissanne 13680 Lan\u00e7on Provence Ch\u00e2teau Bourgogne 71250",
    "addr:postcode":"13680;71250",
    "iso:country":"FR",
    "sg:address":"Ch\u00e2teau de Calissanne 13680 Lan\u00e7on Provence",
    "sg:city":"Ch\u00e2teau",
    "sg:orig_category":"Non-Classified Establishments",
    "sg:phone":"+33 4 90 42 63 03",
    "sg:postcode":"71250",
    "sg:province":"Bourgogne",
    "wof:name":"Duran\u00e7ole S.c.a.",
    "wof:placetype":"venue"
},
  "geometry": {"coordinates":[5.137655,43.545246],"type":"Point"}
}