{
  "type": "Feature",
  "properties": {
    "iso:country":"FR",
    "sg:address":"Travers De La Montre Centre Etoile Valentine 13011 Marseille",
    "sg:classifiers":[
        {
            "category":"Wholesale",
            "subcategory":"Medical Equipment & Supplies",
            "type":"Manufacturing & Wholesale Goods"
        }
    ],
    "sg:phone":"+33 4 91 44 07 58",
    "sg:province":"Poitou-Charentes",
    "sg:tags":[
        "instrument",
        "health",
        "-",
        "precision"
    ],
    "wof:name":"Ets Proteor",
    "wof:placetype":"venue"
},
  "geometry": {"coordinates":[5.437165,43.289322],"type":"Point"}
}