{
  "type": "Feature",
  "properties": {
    "iso:country":"FR",
    "sg:address":"Rue Jules Vernes",
    "sg:city":"Ronchin",
    "sg:orig_category":"Unclassifiable Establishments",
    "sg:phone":"+33 3 28 80 03 28",
    "sg:postcode":"59790",
    "sg:province":"Nord Pas-de-Calais",
    "wof:name":"Siemens Landis Et Staefa S.a.",
    "wof:placetype":"venue"
},
  "geometry": {"coordinates":[3.108038,50.60965],"type":"Point"}
}