{
  "type": "Feature",
  "properties": {
    "addr:full":"93, Rue du Hocquet, 80000 Amiens Picardie",
    "addr:housenumber":"93",
    "addr:postcode":"80000",
    "addr:street":"Rue Du Hocquet",
    "iso:country":"FR",
    "sg:address":"93, Rue du Hocquet, 80000 Amiens",
    "sg:orig_category":"Non-Classified Establishments",
    "sg:phone":"+33 3 22 82 23 21",
    "sg:province":"Picardie",
    "wof:name":"Supm\u00e9diacom",
    "wof:placetype":"venue"
},
  "geometry": {"coordinates":[2.304651,49.895134],"type":"Point"}
}