{
  "type": "Feature",
  "properties": {
    "addr:full":"12, Rue Albert Einstein - Espace Descartes, 77420 Champs sur Marne Ile de France",
    "addr:housenumber":"12",
    "addr:postcode":"77420",
    "addr:street":"Rue Albert Einstein Espace Descartes",
    "iso:country":"FR",
    "sg:address":"12, Rue Albert Einstein - Espace Descartes, 77420 Champs sur Marne",
    "sg:orig_category":"Non-Classified Establishments",
    "sg:phone":"+33 1 64 73 00 61",
    "sg:province":"Ile de France",
    "wof:name":"Sensopart France S.a.r.l.",
    "wof:placetype":"venue"
},
  "geometry": {"coordinates":[2.602945,48.852322],"type":"Point"}
}