{
  "type": "Feature",
  "properties": {
    "iso:country":"FR",
    "sg:address":"Z.A. du Noret",
    "sg:city":"Mamirolle",
    "sg:orig_category":"Electro-\u00e9rosion Electro-\u00e9rosion par enfon\u00e7age Electro-\u00e9rosion \u00e0 fil Per\u00e7age par \u00e9lectro-\u00e9rosion",
    "sg:phone":"+33 3 81 55 81 81",
    "sg:postcode":"25620",
    "sg:province":"Franche Comt\u00e9",
    "wof:name":"Fila Production S.a.",
    "wof:placetype":"venue"
},
  "geometry": {"coordinates":[6.114195,47.157475],"type":"Point"}
}