{
  "type": "Feature",
  "properties": {
    "iso:country":"FR",
    "sg:address":"Zi 4 68520 Burnhaupt Le Haut",
    "sg:city":"Burnhaupt-le-Bas",
    "sg:classifiers":[
        {
            "category":"Professional",
            "type":"Services"
        }
    ],
    "sg:phone":"+33 3 89 48 90 00",
    "sg:postcode":"68520",
    "sg:province":"Alsace",
    "sg:tags":[
        "transport",
        "road"
    ],
    "wof:name":"Transports Wolfersperger Sa",
    "wof:placetype":"venue"
},
  "geometry": {"coordinates":[7.14988,47.728867],"type":"Point"}
}