{
  "type": "Feature",
  "properties": {
    "addr:full":"44 Rue De Mazy 21160 Marsannay La Cote Marsannay-la-C\u00f4te Bourgogne 21160",
    "addr:housenumber":"44",
    "addr:postcode":"21160;21160",
    "addr:street":"Rue De Mazy;Cote",
    "iso:country":"FR",
    "sg:address":"44 Rue De Mazy 21160 Marsannay La Cote",
    "sg:city":"Marsannay-la-C\u00f4te",
    "sg:classifiers":[
        {
            "category":"Food Court",
            "type":"Food & Drink"
        }
    ],
    "sg:phone":"+33 3 80 51 25 75",
    "sg:postcode":"21160",
    "sg:province":"Bourgogne",
    "sg:tags":[
        "product",
        "related"
    ],
    "wof:name":"Domaine Fougeray De Beauclair",
    "wof:placetype":"venue"
},
  "geometry": {"coordinates":[4.987559,47.26918],"type":"Point"}
}