{
  "type": "Feature",
  "properties": {
    "addr:full":"6 Rue Du Pre 39200 St Claude Franche Comt\u00e9 39200",
    "addr:housenumber":"6",
    "addr:postcode":"39200;39200",
    "addr:street":"Rue Du Pre;St Claude Franche Comte\u0301",
    "iso:country":"FR",
    "sg:address":"6 Rue Du Pre 39200 St Claude",
    "sg:classifiers":[
        {
            "category":"Manufacturing",
            "subcategory":"Jewelry",
            "type":"Manufacturing & Wholesale Goods"
        }
    ],
    "sg:phone":"+33 3 84 45 10 96",
    "sg:postcode":"39200",
    "sg:province":"Franche Comt\u00e9",
    "sg:tags":[
        "product",
        "miscellaneous",
        "jewellery"
    ],
    "wof:name":"Pesenti",
    "wof:placetype":"venue"
},
  "geometry": {"coordinates":[5.864374,46.388039],"type":"Point"}
}