{
  "type": "Feature",
  "properties": {
    "addr:full":"16, Chemin de Malacher - ZAC Virst 4402, 38240 Meylan Rhone-Alpes",
    "addr:housenumber":"16;4402",
    "addr:postcode":"38240",
    "addr:street":"Chemin De Malacher Zac Virst",
    "iso:country":"FR",
    "sg:address":"16, Chemin de Malacher - ZAC Virst 4402, 38240 Meylan",
    "sg:orig_category":"Unclassifiable Establishments",
    "sg:phone":"+33 4 76 04 97 57",
    "sg:province":"Rhone-Alpes",
    "wof:name":"Synergies Projets D\u00e9veloppement",
    "wof:placetype":"venue"
},
  "geometry": {"coordinates":[5.77846,45.209316],"type":"Point"}
}