{
  "type": "Feature",
  "properties": {
    "iso:country":"FR",
    "sg:address":"Ornans 25290 ORNANS",
    "sg:classifiers":[
        {
            "category":"Wholesale",
            "subcategory":"Metals & Minerals",
            "type":"Manufacturing & Wholesale Goods"
        }
    ],
    "sg:phone":"+33 3 81 62 25 87",
    "sg:postcode":"25290",
    "sg:province":"Franche Comt\u00e9",
    "sg:tags":[
        "machine",
        "forming"
    ],
    "wof:name":"Sosolic Sarl",
    "wof:placetype":"venue"
},
  "geometry": {"coordinates":[6.14574,47.106831],"type":"Point"}
}