{
  "type": "Feature",
  "properties": {
    "addr:full":"1 Place Max Barel Nice Provence-Alpes-C\u00f4te d'Azur 06300",
    "addr:housenumber":"1",
    "addr:postcode":"06300",
    "addr:street":"Place Max Barel Nice",
    "iso:country":"FR",
    "sg:address":"1 Place Max Barel",
    "sg:city":"Nice",
    "sg:classifiers":[
        {
            "category":"Banks & Credit Unions",
            "subcategory":"Financial Services",
            "type":"Services"
        }
    ],
    "sg:phone":"+33 4 92 00 29 40",
    "sg:postcode":"06300",
    "sg:province":"Provence-Alpes-C\u00f4te d'Azur",
    "sg:tags":[
        "banking",
        "finance",
        "insurance"
    ],
    "wof:name":"Credit Commercial De France (ccf)",
    "wof:placetype":"venue"
},
  "geometry": {"coordinates":[7.287223,43.700565],"type":"Point"}
}