{
  "type": "Feature",
  "properties": {
    "addr:full":"71 rue Liandier 13008 Marseille Provence-Alpes-C\u00f4te d'Azur",
    "addr:housenumber":"71",
    "addr:postcode":"13008",
    "addr:street":"Rue Liandier",
    "iso:country":"FR",
    "sg:address":"71 rue Liandier 13008 Marseille",
    "sg:classifiers":[
        {
            "category":"Home & Garden",
            "subcategory":"Carpets & Floor Coverings",
            "type":"Retail Goods"
        }
    ],
    "sg:phone":"+33 4 91 79 45 72",
    "sg:province":"Provence-Alpes-C\u00f4te d'Azur",
    "sg:tags":[
        "oriental"
    ],
    "wof:name":"Irriplass S.a.r.l.",
    "wof:placetype":"venue"
},
  "geometry": {"coordinates":[5.393159,43.278889],"type":"Point"}
}