{
  "type": "Feature",
  "properties": {
    "addr:full":"14 rue de la Blanchisserie 02151 SISSONNE CEDEX Massachusetts",
    "addr:housenumber":"14",
    "addr:postcode":"02151",
    "addr:street":"Rue De La Blanchisserie",
    "iso:country":"FR",
    "sg:address":"14 rue de la Blanchisserie 02151 SISSONNE CEDEX",
    "sg:classifiers":[
        {
            "category":"Park",
            "subcategory":"Provincial",
            "type":"Public Place"
        }
    ],
    "sg:phone":"+33 3 23 80 40 51",
    "sg:province":"Massachusetts",
    "sg:tags":[
        "dyer",
        "piece"
    ],
    "wof:name":"B.i.m. Sa",
    "wof:placetype":"venue"
},
  "geometry": {"coordinates":[-70.99597900000001,42.419022],"type":"Point"}
}