{
  "type": "Feature",
  "properties": {
    "addr:full":"Zi La Massane 13210 St R\u00e9my De Provence Nord Pas-de-Calais",
    "addr:postcode":"13210",
    "addr:street":"Zi La Massane;Provence;Pas-De-Calais",
    "iso:country":"FR",
    "sg:address":"Zi La Massane 13210 St R\u00e9my De Provence",
    "sg:classifiers":[
        {
            "category":"Professional",
            "type":"Services"
        }
    ],
    "sg:phone":"+33 4 90 92 17 94",
    "sg:province":"Nord Pas-de-Calais",
    "sg:tags":[
        "transport",
        "road"
    ],
    "wof:name":"Gondrand Bellagambi Annie",
    "wof:placetype":"venue"
},
  "geometry": {"coordinates":[4.829515,43.788704],"type":"Point"}
}