{
  "type": "Feature",
  "properties": {
    "addr:full":"34, Place Martel Guaimard, 73700 Bourg Saint Maurice Rhone-Alpes 73700",
    "addr:housenumber":"34",
    "addr:postcode":"73700;73700",
    "addr:street":"Place Martel Guaimard;Rhone-Alpes",
    "iso:country":"FR",
    "sg:address":"34, Place Martel Guaimard, 73700 Bourg Saint Maurice",
    "sg:orig_category":"Unclassifiable Establishments",
    "sg:phone":"+33 4 79 07 23 70",
    "sg:postcode":"73700",
    "sg:province":"Rhone-Alpes",
    "wof:name":"Aux D\u00e9lices De Tarentaise S.a.r.l.",
    "wof:placetype":"venue"
},
  "geometry": {"coordinates":[6.76931,45.618439],"type":"Point"}
}