{
  "type": "Feature",
  "properties": {
    "addr:full":"Vaugarny 35560 Bazouges la P\u00e9rouse Antrain Bretagne 35560",
    "addr:postcode":"35560;35560",
    "addr:street":"Vaugarny;Antrain Bretagne",
    "iso:country":"FR",
    "sg:address":"Vaugarny 35560 Bazouges la P\u00e9rouse",
    "sg:city":"Antrain",
    "sg:orig_category":"Non-Classified Establishments",
    "sg:phone":"+33 2 99 97 45 40",
    "sg:postcode":"35560",
    "sg:province":"Bretagne",
    "wof:name":"Riaux Escaliers S.a.",
    "wof:placetype":"venue"
},
  "geometry": {"coordinates":[-1.563309,48.425526],"type":"Point"}
}