{
  "type": "Feature",
  "properties": {
    "addr:full":"BP 63, 10 Ave Bujault, 79000 Niort, Dept 79 Poitou-Charentes 79000",
    "addr:housenumber":"bp;79",
    "addr:postcode":"79000;79000",
    "addr:street":"63 10 Ave Bujault",
    "iso:country":"FR",
    "sg:address":"BP 63, 10 Ave Bujault, 79000 Niort, Dept 79",
    "sg:classifiers":[
        {
            "category":"Banks & Credit Unions",
            "subcategory":"Bank",
            "type":"Services"
        }
    ],
    "sg:phone":"+33 5 49 08 50 50",
    "sg:postcode":"79000",
    "sg:province":"Poitou-Charentes",
    "wof:name":"Banque Populaire Centre-atlantique",
    "wof:placetype":"venue"
},
  "geometry": {"coordinates":[-0.459038,46.322105],"type":"Point"}
}