{
  "type": "Feature",
  "properties": {
    "iso:country":"FR",
    "sg:address":"Betheneins 01090 Montceaux",
    "sg:orig_category":"Unclassifiable Establishments",
    "sg:phone":"+33 4 74 66 19 41",
    "sg:province":"Rhone-Alpes",
    "wof:name":"P.a.d.i.c.s. S.a.r.l. - Plomberie Assistance D\u00e9pannage Installation Chauffage Sanitaire",
    "wof:placetype":"venue"
},
  "geometry": {"coordinates":[4.797027,46.092564],"type":"Point"}
}