{
  "type": "Feature",
  "properties": {
    "iso:country":"FR",
    "sg:address":"5 Rue Des Grands Pr\u00e9s 92000 Nanterre",
    "sg:orig_category":"Agriculture - machinery and equipment Animals and breeding Computers Information Technology Mechanic",
    "sg:phone":"+33 1 47 86 63 00",
    "sg:postcode":"92000",
    "sg:province":"Ile de France",
    "wof:name":"Metro Libre Service De Gros Sarl",
    "wof:placetype":"venue"
},
  "geometry": {"coordinates":[2.214158,48.910313],"type":"Point"}
}