{
  "type": "Feature",
  "properties": {
    "addr:full":"325 R Joseph L\u00e9on Jacquemaire 69400 Villefranche Sur Sa\u00f4ne Rhone-Alpes 69400",
    "addr:housenumber":"325",
    "addr:postcode":"69400;69400",
    "addr:street":"R Joseph Le\u0301On Jacquemaire;Rhone-Alpes",
    "iso:country":"FR",
    "sg:address":"325 R Joseph L\u00e9on Jacquemaire 69400 Villefranche Sur Sa\u00f4ne",
    "sg:classifiers":[
        {
            "category":"Home & Garden",
            "subcategory":"Furniture",
            "type":"Retail Goods"
        }
    ],
    "sg:phone":"+33 4 74 02 98 20",
    "sg:postcode":"69400",
    "sg:province":"Rhone-Alpes",
    "sg:tags":[
        "wood"
    ],
    "wof:name":"Etablissements Ollier Sa",
    "wof:placetype":"venue"
},
  "geometry": {"coordinates":[4.743254,45.99234],"type":"Point"}
}