{
  "type": "Feature",
  "properties": {
    "iso:country":"FR",
    "sg:address":"B.P. 64, 59732 Saint Amand les Eaux C\u00e9dex^^Z.A. du Marillon, 59230 Saint Amand les Eaux",
    "sg:orig_category":"Non-Classified Establishments",
    "sg:phone":"+33 3 27 48 20 22",
    "sg:postcode":"59230",
    "sg:province":"Nord Pas-de-Calais",
    "wof:name":"Descamps Jacques S.a.",
    "wof:placetype":"venue"
},
  "geometry": {"coordinates":[3.40956,50.454521],"type":"Point"}
}