{
  "type": "Feature",
  "properties": {
    "iso:country":"FR",
    "sg:address":"1 avenue Joseph Cugnot 94420 LE PLESSIS TREVISE",
    "sg:classifiers":[
        {
            "category":"Wholesale",
            "subcategory":"Construction Materials",
            "type":"Manufacturing & Wholesale Goods"
        }
    ],
    "sg:phone":"+33 1 45 94 95 77",
    "sg:postcode":"94420",
    "sg:province":"Ile de France",
    "sg:tags":[
        "mould",
        "injection"
    ],
    "wof:name":"Plastique Forme Outillage S.a.r.l.",
    "wof:placetype":"venue"
},
  "geometry": {"coordinates":[2.56134,48.80463],"type":"Point"}
}