{
  "type": "Feature",
  "properties": {
    "addr:full":"10, Rue de la Biome - La Motte Sainte Euverte , 45800 Saint Jean de Braye Combleux Centre 45800",
    "addr:housenumber":"10;combleux",
    "addr:postcode":"45800;45800",
    "addr:street":"Rue De La Biome",
    "iso:country":"FR",
    "sg:address":"10, Rue de la Biome - La Motte Sainte Euverte , 45800 Saint Jean de Braye",
    "sg:city":"Combleux",
    "sg:orig_category":"Unclassifiable Establishments",
    "sg:phone":"+33 2 38 75 29 00",
    "sg:postcode":"45800",
    "sg:province":"Centre",
    "wof:name":"S.or.ele.c. S.a. - Soci\u00e9t\u00e9 Orl\u00e9anaise D'electricit\u00e9 Et De Chauffage",
    "wof:placetype":"venue"
},
  "geometry": {"coordinates":[2.001924,47.91853],"type":"Point"}
}