{
  "type": "Feature",
  "properties": {
    "iso:country":"FR",
    "sg:address":"Halberderie 49320 VAUCHRETIEN",
    "sg:classifiers":[
        {
            "category":"Manufacturing",
            "subcategory":"Rubber & Plastics",
            "type":"Manufacturing & Wholesale Goods"
        }
    ],
    "sg:phone":"+33 2 41 66 00 66",
    "sg:province":"Pays de Loire",
    "sg:tags":[
        "technical",
        "parts"
    ],
    "wof:name":"Delahousse Et Fils Sa",
    "wof:placetype":"venue"
},
  "geometry": {"coordinates":[-0.506754,47.337925],"type":"Point"}
}