{
  "type": "Feature",
  "properties": {
    "addr:full":"366, Chauss\u00e9e Marcelin Berthelot, 59200 Tourcoing Nord Pas-de-Calais",
    "addr:housenumber":"366",
    "addr:postcode":"59200",
    "addr:street":"Chausse\u0301E Marcelin Berthelot",
    "iso:country":"FR",
    "sg:address":"366, Chauss\u00e9e Marcelin Berthelot, 59200 Tourcoing",
    "sg:orig_category":"Unclassifiable Establishments",
    "sg:phone":"+33 3 20 11 37 51",
    "sg:province":"Nord Pas-de-Calais",
    "wof:name":"Mayafil S.a.",
    "wof:placetype":"venue"
},
  "geometry": {"coordinates":[3.184029,50.731041],"type":"Point"}
}