{
  "type": "Feature",
  "properties": {
    "iso:country":"FR",
    "sg:address":"1\u00e8re Avenue - 5191 m\u00e8tres - ZI",
    "sg:city":"Carros",
    "sg:orig_category":"Non-Classified Establishments",
    "sg:phone":"+33 4 92 08 06 08",
    "sg:postcode":"06510",
    "sg:province":"Provence-Alpes-C\u00f4te d'Azur",
    "wof:name":"Direct 1000 S.a.",
    "wof:placetype":"venue"
},
  "geometry": {"coordinates":[7.17573,43.785782],"type":"Point"}
}