{
  "type": "Feature",
  "properties": {
    "addr:full":"45 Rue Croix Des Petits Champs 75001 Paris Ile de France 75001",
    "addr:housenumber":"45",
    "addr:postcode":"75001;75001",
    "addr:street":"Rue Croix Des Petits Champs",
    "iso:country":"FR",
    "sg:address":"45 Rue Croix Des Petits Champs 75001 Paris",
    "sg:classifiers":[
        {
            "category":"Shopping",
            "subcategory":"Clothing, Apparel, & Fashions",
            "type":"Retail Goods"
        }
    ],
    "sg:phone":"+33 1 40 41 07 69",
    "sg:postcode":"75001",
    "sg:province":"Ile de France",
    "sg:tags":[
        "textile",
        "clothing",
        "clothes"
    ],
    "wof:name":"Mulberry Company France Sarl",
    "wof:placetype":"venue"
},
  "geometry": {"coordinates":[2.340548,48.864944],"type":"Point"}
}