{
  "type": "Feature",
  "properties": {
    "addr:full":"Rte de Grasse Saint Cezaire sur Siagne Provence-Alpes-C\u00f4te d'Azur 06530",
    "addr:postcode":"06530",
    "addr:street":"Rte De Grasse Saint Cezaire Sur Siagne",
    "iso:country":"FR",
    "sg:address":"Rte de Grasse",
    "sg:city":"Saint Cezaire sur Siagne",
    "sg:orig_category":"Unclassifiable Establishments",
    "sg:phone":"+33 4 93 60 22 22",
    "sg:postcode":"06530",
    "sg:province":"Provence-Alpes-C\u00f4te d'Azur",
    "wof:name":"Cr\u00e9ation Et Parfums S.a.r.l.",
    "wof:placetype":"venue"
},
  "geometry": {"coordinates":[6.85967,43.644451],"type":"Point"}
}