{
  "type": "Feature",
  "properties": {
    "addr:full":"20 plage Estaque 16e; Marseille Poitou-Charentes",
    "addr:housenumber":"20;16e",
    "addr:street":"Plage Estaque",
    "iso:country":"FR",
    "sg:address":"20 plage Estaque 16e; Marseille",
    "sg:classifiers":[
        {
            "category":"Banks & Credit Unions",
            "subcategory":"Bank",
            "type":"Services"
        }
    ],
    "sg:phone":"+33 3391460801",
    "sg:province":"Poitou-Charentes",
    "wof:name":"Cr\u00e9dit Lyonnais",
    "wof:placetype":"venue"
},
  "geometry": {"coordinates":[5.37249,43.293686],"type":"Point"}
}