{
  "type": "Feature",
  "properties": {
    "iso:country":"FR",
    "sg:address":"B.P. 409, 01704 Beynost C\u00e9dex^^ZAC des Baterses ZI Nord, 01700 Beynost",
    "sg:orig_category":"Non-Classified Establishments",
    "sg:phone":"+33 4 78 55 22 10",
    "sg:postcode":"01700",
    "sg:province":"Rhone-Alpes",
    "wof:name":"S.i.e.r.o.m. S.a. - Soci\u00e9t\u00e9 Industrielle D'etudes Et R\u00e9alisations D'o",
    "wof:placetype":"venue"
},
  "geometry": {"coordinates":[4.96153,45.828629],"type":"Point"}
}