{
  "type": "Feature",
  "properties": {
    "iso:country":"FR",
    "sg:address":"B.P. 162, 59400 Cambrai^^74, Rue Saint Georges, 59400 Cambrai",
    "sg:orig_category":"Non-Classified Establishments",
    "sg:phone":"+33 3 27 83 49 49",
    "sg:province":"Nord Pas-de-Calais",
    "wof:name":"V\u00e9dior Bis",
    "wof:placetype":"venue"
},
  "geometry": {"coordinates":[3.23419,50.175018],"type":"Point"}
}