{
  "type": "Feature",
  "properties": {
    "addr:full":"2, Rue Gilets, 11400 Lasbordes Languedoc-Roussillon",
    "addr:housenumber":"2",
    "addr:postcode":"11400",
    "addr:street":"Rue Gilets",
    "iso:country":"FR",
    "sg:address":"2, Rue Gilets, 11400 Lasbordes",
    "sg:orig_category":"Unclassifiable Establishments",
    "sg:phone":"+33 4 68 94 90 27",
    "sg:province":"Languedoc-Roussillon",
    "wof:name":"Cassignol Et Imart S.a.r.l.",
    "wof:placetype":"venue"
},
  "geometry": {"coordinates":[2.044285,43.295242],"type":"Point"}
}