{
  "type": "Feature",
  "properties": {
    "addr:full":"Quartier Ladev\u00e8ze Soumoulou Aquitaine 64420",
    "addr:postcode":"64420",
    "iso:country":"FR",
    "sg:address":"Quartier Ladev\u00e8ze",
    "sg:city":"Soumoulou",
    "sg:orig_category":"Unclassifiable Establishments",
    "sg:phone":"+33 5 59 04 60 42",
    "sg:postcode":"64420",
    "sg:province":"Aquitaine",
    "wof:name":"Toujas Et Coll S.a.",
    "wof:placetype":"venue"
},
  "geometry": {"coordinates":[-0.169847,43.230305],"type":"Point"}
}