{
  "type": "Feature",
  "properties": {
    "addr:full":"B.P. 31, 68131 Altkirch^^76, Rue du 3\u00e8me Zouave, 68130 Altkirch Altkirch Alsace 68130",
    "addr:postcode":"68131;68130;68130",
    "addr:street":"B.P. 31;Rue Du 3E\u0300Me",
    "iso:country":"FR",
    "sg:address":"B.P. 31, 68131 Altkirch^^76, Rue du 3\u00e8me Zouave, 68130 Altkirch",
    "sg:city":"Altkirch",
    "sg:orig_category":"Non-Classified Establishments",
    "sg:phone":"+33 3 89 08 31 31",
    "sg:postcode":"68130",
    "sg:province":"Alsace",
    "wof:name":"M.g.i. Coutier S.a.",
    "wof:placetype":"venue"
},
  "geometry": {"coordinates":[7.24009,47.625919],"type":"Point"}
}