{
  "type": "Feature",
  "properties": {
    "addr:full":"B.P. 15, 08800 Montherm\u00e9^^1, Rue Andr\u00e9 Compain, 08800 Montherm\u00e9 Deville Champagne 08800",
    "addr:postcode":"08800;08800;08800",
    "addr:street":"B.P. 15;Rue Andre\u0301 Compain;Champagne",
    "iso:country":"FR",
    "sg:address":"B.P. 15, 08800 Montherm\u00e9^^1, Rue Andr\u00e9 Compain, 08800 Montherm\u00e9",
    "sg:city":"Deville",
    "sg:orig_category":"Estampage de m\u00e9taux Traitement thermique des m\u00e9taux",
    "sg:phone":"+33 3 24 59 62 59",
    "sg:postcode":"08800",
    "sg:province":"Champagne",
    "wof:name":"Forge Sefac S.a.s.",
    "wof:placetype":"venue"
},
  "geometry": {"coordinates":[4.76741,49.882038],"type":"Point"}
}