{
  "type": "Feature",
  "properties": {
    "iso:country":"FR",
    "sg:address":"2 Pl De La Bourse Palais Du Commerce 69002 Lyon",
    "sg:classifiers":[
        {
            "category":"Banks & Credit Unions",
            "subcategory":"Financial Services",
            "type":"Services"
        }
    ],
    "sg:phone":"+33 4 72 56 26 26",
    "sg:postcode":"69002",
    "sg:province":"Rhone-Alpes",
    "sg:tags":[
        "banking",
        "insurance",
        "institution",
        "finance"
    ],
    "wof:name":"Euronext Delegation De Lyon",
    "wof:placetype":"venue"
},
  "geometry": {"coordinates":[4.828975,45.759399],"type":"Point"}
}