{
  "type": "Feature",
  "properties": {
    "iso:country":"FR",
    "sg:address":"50 Arpents 91290 Arpajon",
    "sg:classifiers":[
        {
            "category":"Industrial Area",
            "type":"Public Place"
        }
    ],
    "sg:phone":"+33 1 60 85 52 00",
    "sg:postcode":"91290",
    "sg:province":"Ile de France",
    "sg:tags":[
        "adhesive",
        "glue"
    ],
    "wof:name":"Labord Sa",
    "wof:placetype":"venue"
},
  "geometry": {"coordinates":[2.249095,48.590462],"type":"Point"}
}