{
  "type": "Feature",
  "properties": {
    "iso:country":"FR",
    "sg:address":"4 Place Hoche, 78002 Versailles, Dept 78",
    "sg:classifiers":[
        {
            "category":"Banks & Credit Unions",
            "subcategory":"Bank",
            "type":"Services"
        }
    ],
    "sg:phone":"+33 1 34 60 61 00",
    "sg:province":"Corse",
    "wof:name":"Banque Populaire De La Region Ouest De Paris Bp Rop",
    "wof:placetype":"venue"
},
  "geometry": {"coordinates":[2.127285,48.805851],"type":"Point"}
}