{
  "type": "Feature",
  "properties": {
    "addr:full":"14 Bd Du Gal Leclerc 92572 Neuilly Sur Seine Cedex Haute Normandie",
    "addr:housenumber":"14",
    "addr:postcode":"92572;seine cedex",
    "addr:street":"Bd Du Gal Leclerc",
    "iso:country":"FR",
    "sg:address":"14 Bd Du Gal Leclerc 92572 Neuilly Sur Seine Cedex",
    "sg:classifiers":[
        {
            "category":"Manufacturing",
            "subcategory":"Chemicals & Compounds",
            "type":"Manufacturing & Wholesale Goods"
        }
    ],
    "sg:phone":"+33 1 41 43 17 81",
    "sg:province":"Haute Normandie",
    "sg:tags":[
        "pharmaceutical",
        "energy",
        "chemistry",
        "-",
        "by-product"
    ],
    "wof:name":"Novaol France",
    "wof:placetype":"venue"
},
  "geometry": {"coordinates":[2.27224,48.883621],"type":"Point"}
}