{
  "type": "Feature",
  "properties": {
    "iso:country":"FR",
    "sg:address":"Chemin Du Couvent 44340 Bouguenais",
    "sg:classifiers":[
        {
            "category":"Professional",
            "subcategory":"Business Services",
            "type":"Services"
        }
    ],
    "sg:phone":"+33 2 40 65 29 90",
    "sg:postcode":"44340",
    "sg:province":"Pays de Loire",
    "sg:tags":[
        "training",
        "advice"
    ],
    "wof:name":"Maison Daniel Brottier Orphelins Apprentis Auteuils Sarl",
    "wof:placetype":"venue"
},
  "geometry": {"coordinates":[-1.585021,47.187939],"type":"Point"}
}