{
  "type": "Feature",
  "properties": {
    "addr:full":"1, Rue Montespan, 91000 Evry Ile de France",
    "addr:housenumber":"1",
    "addr:postcode":"91000",
    "addr:street":"Rue Montespan",
    "iso:country":"FR",
    "sg:address":"1, Rue Montespan, 91000 Evry",
    "sg:orig_category":"Unclassifiable Establishments",
    "sg:phone":"+33 1 60 77 60 89",
    "sg:province":"Ile de France",
    "wof:name":"A.m. G.r.h. S.a.r.l.",
    "wof:placetype":"venue"
},
  "geometry": {"coordinates":[2.437354,48.633766],"type":"Point"}
}