{
  "type": "Feature",
  "properties": {
    "addr:full":"23, Place Dilo, 89600 Saint Florentin Ch\u00e9u Bourgogne 89600",
    "addr:housenumber":"23",
    "addr:postcode":"89600;89600",
    "addr:street":"Place Dilo",
    "iso:country":"FR",
    "sg:address":"23, Place Dilo, 89600 Saint Florentin",
    "sg:city":"Ch\u00e9u",
    "sg:orig_category":"Non-Classified Establishments",
    "sg:phone":"+33 3 86 43 53 00",
    "sg:postcode":"89600",
    "sg:province":"Bourgogne",
    "wof:name":"Humbert S.a.",
    "wof:placetype":"venue"
},
  "geometry": {"coordinates":[3.729076,48.002571],"type":"Point"}
}