{
  "type": "Feature",
  "properties": {
    "addr:full":"57, Rue de la R\u00e9publique, 01200 Bellegarde sur Valserine Rhone-Alpes 01200",
    "addr:housenumber":"57",
    "addr:postcode":"01200;01200",
    "addr:street":"Rue De La Re\u0301Publique;Rhone-Alpes",
    "iso:country":"FR",
    "sg:address":"57, Rue de la R\u00e9publique, 01200 Bellegarde sur Valserine",
    "sg:orig_category":"Non-Classified Establishments",
    "sg:phone":"+33 4 50 49 81 48",
    "sg:postcode":"01200",
    "sg:province":"Rhone-Alpes",
    "wof:name":"B.p.s. - Banque Populaire Savoisienne",
    "wof:placetype":"venue"
},
  "geometry": {"coordinates":[5.824413,46.106731],"type":"Point"}
}