{
  "type": "Feature",
  "properties": {
    "addr:full":"17, Av. Didier Daurat - Immeuble Thal\u00e8s, 31700 Blagnac Midi Pyr\u00e9n\u00e9es",
    "addr:postcode":"31700",
    "addr:street":"17 Av. Didier Daurat",
    "iso:country":"FR",
    "sg:address":"17, Av. Didier Daurat - Immeuble Thal\u00e8s, 31700 Blagnac",
    "sg:orig_category":"Non-Classified Establishments",
    "sg:phone":"+33 5 61 71 06 50",
    "sg:province":"Midi Pyr\u00e9n\u00e9es",
    "wof:name":"Eurespace S.a.",
    "wof:placetype":"venue"
},
  "geometry": {"coordinates":[1.379176,43.6301],"type":"Point"}
}