{
  "type": "Feature",
  "properties": {
    "addr:full":"Plaine de Lachotaut - ZA de Ch\u00e2teau Vieux Gap Provence-Alpes-C\u00f4te d'Azur 05000",
    "addr:postcode":"05000",
    "addr:street":"Plaine;Za De Cha\u0302Teau Vieux Gap",
    "iso:country":"FR",
    "sg:address":"Plaine de Lachotaut - ZA de Ch\u00e2teau Vieux",
    "sg:city":"Gap",
    "sg:orig_category":"Unclassifiable Establishments",
    "sg:phone":"+33 4 92 53 51 61",
    "sg:postcode":"05000",
    "sg:province":"Provence-Alpes-C\u00f4te d'Azur",
    "wof:name":"Cotfer France S.a.r.l.",
    "wof:placetype":"venue"
},
  "geometry": {"coordinates":[6.07483,44.554939],"type":"Point"}
}