{
  "type": "Feature",
  "properties": {
    "iso:country":"FR",
    "sg:address":"Lieu Dit Les Mazieres 12270 Lunac",
    "sg:classifiers":[
        {
            "category":"Bakery",
            "type":"Food & Drink"
        }
    ],
    "sg:phone":"+33 5 65 65 70 24",
    "sg:postcode":"12270",
    "sg:province":"Midi Pyr\u00e9n\u00e9es",
    "sg:tags":[
        "cake",
        "product",
        "related",
        "bread"
    ],
    "wof:name":"Sarl Le Pivert",
    "wof:placetype":"venue"
},
  "geometry": {"coordinates":[2.08104,44.261459],"type":"Point"}
}