{
  "type": "Feature",
  "properties": {
    "addr:full":"2715 Av Etienne M\u00e9hul 34070 Montpellier Languedoc-Roussillon 34070",
    "addr:housenumber":"2715",
    "addr:postcode":"34070;34070",
    "addr:street":"Av Etienne Me\u0301Hul",
    "iso:country":"FR",
    "sg:address":"2715 Av Etienne M\u00e9hul 34070 Montpellier",
    "sg:classifiers":[
        {
            "category":"Professional",
            "subcategory":"Engineering",
            "type":"Services"
        }
    ],
    "sg:phone":"+33 4 67 27 52 77",
    "sg:postcode":"34070",
    "sg:province":"Languedoc-Roussillon",
    "sg:tags":[
        "machine",
        "-",
        "mechanical"
    ],
    "wof:name":"Emafu",
    "wof:placetype":"venue"
},
  "geometry": {"coordinates":[3.860004,43.578995],"type":"Point"}
}