{
  "type": "Feature",
  "properties": {
    "iso:country":"FR",
    "sg:address":"La Gueriniere 35370 Argentre Du Plessis",
    "sg:city":"Argentr\u00e9-du-Plessis",
    "sg:classifiers":[
        {
            "category":"Farming",
            "subcategory":"Livestock Farm",
            "type":"Manufacturing & Wholesale Goods"
        }
    ],
    "sg:phone":"+33 2 99 96 76 98",
    "sg:postcode":"35370",
    "sg:province":"Bretagne",
    "sg:tags":[
        "breeding",
        "agriculture",
        "animal"
    ],
    "wof:name":"Sarl Fadier Elevage",
    "wof:placetype":"venue"
},
  "geometry": {"coordinates":[-1.126664,48.051666],"type":"Point"}
}