{
  "type": "Feature",
  "properties": {
    "addr:full":"Bd de la Croisette Cannes Provence-Alpes-C\u00f4te d'Azur 06400",
    "addr:postcode":"06400",
    "addr:street":"Bd De La Croisette Cannes",
    "iso:country":"FR",
    "sg:address":"Bd de la Croisette",
    "sg:city":"Cannes",
    "sg:orig_category":"Unclassifiable Establishments",
    "sg:phone":"+33 4 93 39 01 01",
    "sg:postcode":"06400",
    "sg:province":"Provence-Alpes-C\u00f4te d'Azur",
    "wof:name":"Palais Des Festivals Et Des Congr\u00e8s",
    "wof:placetype":"venue"
},
  "geometry": {"coordinates":[7.018105,43.551327],"type":"Point"}
}