{
  "type": "Feature",
  "properties": {
    "addr:full":"Z.I. du Bois Franois Franche Comt\u00e9 25770",
    "addr:postcode":"25770",
    "addr:street":"Z.I. Du Bois;Franche Comte\u0301",
    "iso:country":"FR",
    "sg:address":"Z.I. du Bois",
    "sg:city":"Franois",
    "sg:orig_category":"Unclassifiable Establishments",
    "sg:phone":"+33 3 81 48 22 58",
    "sg:postcode":"25770",
    "sg:province":"Franche Comt\u00e9",
    "wof:name":"S.a.m.i. S.a.r.l. - Soci\u00e9t\u00e9 D'assemblage Et Montage Industriel",
    "wof:placetype":"venue"
},
  "geometry": {"coordinates":[5.93433,47.228195],"type":"Point"}
}