{
  "type": "Feature",
  "properties": {
    "addr:full":"209 rue de la Belle Etoile 95700 Roissy En France Ile de France 95700",
    "addr:housenumber":"209",
    "addr:postcode":"95700;95700",
    "addr:street":"Rue De La Belle Etoile",
    "iso:country":"FR",
    "sg:address":"209 rue de la Belle Etoile 95700 Roissy En France",
    "sg:classifiers":[
        {
            "category":"Building & Trades",
            "subcategory":"Electrical",
            "type":"Services"
        }
    ],
    "sg:phone":"+33 1 49 90 14 14",
    "sg:postcode":"95700",
    "sg:province":"Ile de France",
    "sg:tags":[
        "tool",
        "high-quality"
    ],
    "wof:name":"Ryobi Europe S.a.",
    "wof:placetype":"venue"
},
  "geometry": {"coordinates":[2.510147,48.98481],"type":"Point"}
}