{
  "type": "Feature",
  "properties": {
    "addr:full":"389, Rue de Tarare, 69400 Villefranche sur Sa\u00f4ne Rhone-Alpes",
    "addr:housenumber":"389",
    "addr:postcode":"69400",
    "addr:street":"Rue De Tarare",
    "iso:country":"FR",
    "sg:address":"389, Rue de Tarare, 69400 Villefranche sur Sa\u00f4ne",
    "sg:orig_category":"Unclassifiable Establishments",
    "sg:phone":"+33 4 74 65 26 26",
    "sg:province":"Rhone-Alpes",
    "wof:name":"Comesa S.a.",
    "wof:placetype":"venue"
},
  "geometry": {"coordinates":[4.70265,45.985298],"type":"Point"}
}