{
  "type": "Feature",
  "properties": {
    "addr:full":"18, Rue Boileau - Parc d'Activit\u00e9s de Versailles, 78000 Versailles Ile de France",
    "addr:housenumber":"18",
    "addr:postcode":"78000",
    "addr:street":"Rue Boileau Parc D'Activite \u0301S De Versailles",
    "iso:country":"FR",
    "sg:address":"18, Rue Boileau - Parc d'Activit\u00e9s de Versailles, 78000 Versailles",
    "sg:orig_category":"Unclassifiable Establishments",
    "sg:phone":"+33 1 39 50 09 09",
    "sg:province":"Ile de France",
    "wof:name":"Bureau Service 2 S.a.r.l.",
    "wof:placetype":"venue"
},
  "geometry": {"coordinates":[2.146729,48.795052],"type":"Point"}
}