{
  "type": "Feature",
  "properties": {
    "addr:full":"Tournebride 44115 Haute Goulaine Pays de Loire 44115",
    "addr:postcode":"44115;44115",
    "addr:street":"Tournebride;Goulaine",
    "iso:country":"FR",
    "sg:address":"Tournebride 44115 Haute Goulaine",
    "sg:classifiers":[
        {
            "category":"Professional",
            "subcategory":"Engineering",
            "type":"Services"
        }
    ],
    "sg:phone":"+33 2 40 36 74 74",
    "sg:postcode":"44115",
    "sg:province":"Pays de Loire",
    "sg:tags":[
        "machine",
        "-",
        "mechanical"
    ],
    "wof:name":"Atauce",
    "wof:placetype":"venue"
},
  "geometry": {"coordinates":[-1.407954,47.179443],"type":"Point"}
}