{
  "type": "Feature",
  "properties": {
    "addr:full":"P\u00f4le Technique Agropac Maison De L'Agriculture Avignon Franche Comt\u00e9 84000",
    "addr:postcode":"84000",
    "addr:street":"Franche Comte\u0301",
    "iso:country":"FR",
    "sg:address":"P\u00f4le Technique Agropac Maison De L'Agriculture",
    "sg:city":"Avignon",
    "sg:classifiers":[
        {
            "category":"Banks & Credit Unions",
            "subcategory":"Financial Services",
            "type":"Services"
        }
    ],
    "sg:phone":"+33 4 90 78 31 60",
    "sg:postcode":"84000",
    "sg:province":"Franche Comt\u00e9",
    "sg:tags":[
        "banking",
        "finance",
        "insurance"
    ],
    "wof:name":"Assoc Fiscalite Gestion Agricole",
    "wof:placetype":"venue"
},
  "geometry": {"coordinates":[4.770859,43.962543],"type":"Point"}
}