{
  "type": "Feature",
  "properties": {
    "addr:full":"26, Rue des Magasins G\u00e9n\u00e9raux, 76600 Le Havre Haute Normandie 76600",
    "addr:housenumber":"26",
    "addr:postcode":"76600;76600",
    "addr:street":"Rue Des Magasins Ge\u0301Ne\u0301Raux",
    "iso:country":"FR",
    "sg:address":"26, Rue des Magasins G\u00e9n\u00e9raux, 76600 Le Havre",
    "sg:orig_category":"Non-Classified Establishments",
    "sg:phone":"+33 2 35 25 83 25",
    "sg:postcode":"76600",
    "sg:province":"Haute Normandie",
    "wof:name":"E.t.n. S.a.r.l. - Electrotechnique De Normandie",
    "wof:placetype":"venue"
},
  "geometry": {"coordinates":[0.136094,49.492023],"type":"Point"}
}