{
  "type": "Feature",
  "properties": {
    "iso:country":"FR",
    "sg:address":"B.P. 8, 87700 Aixe sur Vienne^^9, Rue Saboterie, 87700 Aixe sur Vienne",
    "sg:orig_category":"Non-Classified Establishments",
    "sg:phone":"+33 5 55 30 90 50",
    "sg:postcode":"87700",
    "sg:province":"Limousin",
    "wof:name":"B.p.c. - Banque Populaire Du Centre",
    "wof:placetype":"venue"
},
  "geometry": {"coordinates":[1.119023,45.744747],"type":"Point"}
}