{
  "type": "Feature",
  "properties": {
    "iso:country":"FR",
    "sg:address":"Rue de la Jouardais; Le Pellerin; 44640",
    "sg:classifiers":[
        {
            "category":"Banks & Credit Unions",
            "subcategory":"Bank",
            "type":"Services"
        }
    ],
    "sg:phone":"+33 3340045625",
    "sg:postcode":"44640",
    "sg:province":"Pays de Loire",
    "wof:name":"Caisse Regionale, De Credit Argicole",
    "wof:placetype":"venue"
},
  "geometry": {"coordinates":[-1.758754,47.196274],"type":"Point"}
}