{
  "type": "Feature",
  "properties": {
    "addr:full":"13 Bis Rue Condorcet 94430 Chennevi\u00e8res Sur Marne Ile de France 94430",
    "addr:housenumber":"13 bis",
    "addr:postcode":"94430;94430",
    "addr:street":"Rue Condorcet",
    "iso:country":"FR",
    "sg:address":"13 Bis Rue Condorcet 94430 Chennevi\u00e8res Sur Marne",
    "sg:classifiers":[
        {
            "category":"Professional",
            "subcategory":"Engineering",
            "type":"Services"
        }
    ],
    "sg:phone":"+33 1 49 62 72 58",
    "sg:postcode":"94430",
    "sg:province":"Ile de France",
    "sg:tags":[
        "machine",
        "-",
        "mechanical"
    ],
    "wof:name":"Eloy Sa",
    "wof:placetype":"venue"
},
  "geometry": {"coordinates":[2.544592,48.79657],"type":"Point"}
}