{
  "type": "Feature",
  "properties": {
    "addr:full":"71 R\u00e9s. Elys\u00e9e 2 78170 La Celle St Cloud Ile de France 78170",
    "addr:housenumber":"71;2",
    "addr:postcode":"78170;78170",
    "addr:street":"Re\u0301S Elyse\u0301E",
    "iso:country":"FR",
    "sg:address":"71 R\u00e9s. Elys\u00e9e 2 78170 La Celle St Cloud",
    "sg:classifiers":[
        {
            "category":"Professional",
            "subcategory":"Business Services",
            "type":"Services"
        }
    ],
    "sg:phone":"+33 1 39 18 48 52",
    "sg:postcode":"78170",
    "sg:province":"Ile de France",
    "sg:tags":[
        "training",
        "advice"
    ],
    "wof:name":"Gx Technology France Sarl",
    "wof:placetype":"venue"
},
  "geometry": {"coordinates":[2.14853,48.860409],"type":"Point"}
}