{
  "type": "Feature",
  "properties": {
    "addr:full":"32 rue Robert Thomas 91400 Saclay Ile de France 91400",
    "addr:housenumber":"32",
    "addr:postcode":"91400;ile;91400",
    "addr:street":"Rue Robert Thomas;France",
    "iso:country":"FR",
    "sg:address":"32 rue Robert Thomas 91400 Saclay",
    "sg:orig_category":"Carbon Fibre Components",
    "sg:phone":"+33 1 69 33 62 00",
    "sg:postcode":"91400",
    "sg:province":"Ile de France",
    "wof:name":"Etandex Sa",
    "wof:placetype":"venue"
},
  "geometry": {"coordinates":[2.168191,48.730354],"type":"Point"}
}