{
  "type": "Feature",
  "properties": {
    "addr:full":"B.P. 27, 57690 Cr\u00e9hange C\u00e9dex^^14, Rue Pierre Curie, 57690 Cr\u00e9hange Lorraine",
    "addr:postcode":"57690;57690",
    "addr:street":"B.P. 27;Rue Pierre Curie",
    "iso:country":"FR",
    "sg:address":"B.P. 27, 57690 Cr\u00e9hange C\u00e9dex^^14, Rue Pierre Curie, 57690 Cr\u00e9hange",
    "sg:orig_category":"Non-Classified Establishments",
    "sg:phone":"+33 3 87 29 86 40",
    "sg:province":"Lorraine",
    "wof:name":"S.e.f. S.a.r.l. - Soci\u00e9t\u00e9 Europ\u00e9enne De Formation",
    "wof:placetype":"venue"
},
  "geometry": {"coordinates":[6.58013,49.062054],"type":"Point"}
}