{
  "type": "Feature",
  "properties": {
    "addr:full":"B.P. 3 Marne la Vall\u00e9e C\u00e9dex 1 Midi Pyr\u00e9n\u00e9es 77201",
    "addr:housenumber":"1",
    "addr:postcode":"77201",
    "addr:street":"B.P. 3;Ce\u0301Dex",
    "iso:country":"FR",
    "sg:address":"B.P. 3",
    "sg:city":"Marne la Vall\u00e9e C\u00e9dex 1",
    "sg:orig_category":"Non-Classified Establishments",
    "sg:phone":"+33 1 60 05 85 27",
    "sg:postcode":"77201",
    "sg:province":"Midi Pyr\u00e9n\u00e9es",
    "wof:name":"Degr\u00e9mont S.a.",
    "wof:placetype":"venue"
},
  "geometry": {"coordinates":[-95.36982,29.760469],"type":"Point"}
}