{
  "type": "Feature",
  "properties": {
    "addr:full":"555, Rue Saint Pierre, 13012 Marseille Provence-Alpes-C\u00f4te d'Azur",
    "addr:housenumber":"555",
    "addr:postcode":"13012",
    "addr:street":"Rue Saint Pierre",
    "iso:country":"FR",
    "sg:address":"555, Rue Saint Pierre, 13012 Marseille",
    "sg:orig_category":"Non-Classified Establishments",
    "sg:phone":"+33 4 91 48 22 63",
    "sg:province":"Provence-Alpes-C\u00f4te d'Azur",
    "wof:name":"Fa\u00e7onnage Th\u00e9venon S.a.r.l.",
    "wof:placetype":"venue"
},
  "geometry": {"coordinates":[5.42582,43.29018],"type":"Point"}
}