{
  "type": "Feature",
  "properties": {
    "addr:full":"10 Rue Henri Cartier Moulin 73200 Albertville Rhone-Alpes 73200",
    "addr:housenumber":"10",
    "addr:postcode":"73200;73200",
    "addr:street":"Rue Henri Cartier Moulin",
    "iso:country":"FR",
    "sg:address":"10 Rue Henri Cartier Moulin 73200 Albertville",
    "sg:classifiers":[
        {
            "category":"Professional",
            "subcategory":"Advertising",
            "type":"Services"
        }
    ],
    "sg:phone":"+33 4 79 32 05 77",
    "sg:postcode":"73200",
    "sg:province":"Rhone-Alpes",
    "sg:tags":[
        "marketing",
        "medium",
        "communication"
    ],
    "wof:name":"Delta Diffusion Sa",
    "wof:placetype":"venue"
},
  "geometry": {"coordinates":[6.398814,45.665073],"type":"Point"}
}