{
  "type": "Feature",
  "properties": {
    "iso:country":"FR",
    "sg:address":"Lieu Dit Clermoy 41300 Theillay",
    "sg:city":"Theillay",
    "sg:classifiers":[
        {
            "category":"Building & Trades",
            "subcategory":"Construction",
            "type":"Services"
        }
    ],
    "sg:phone":"+33 2 54 83 38 18",
    "sg:postcode":"41300",
    "sg:province":"Centre",
    "sg:tags":[
        "livestock",
        "business",
        "advice",
        "animal",
        "breeding",
        "agriculture"
    ],
    "wof:name":"Madiot Jacques",
    "wof:placetype":"venue"
},
  "geometry": {"coordinates":[2.05406,47.304386],"type":"Point"}
}