{
  "type": "Feature",
  "properties": {
    "iso:country":"FR",
    "sg:address":"Champ Rond 07340 St D\u00e9sirat",
    "sg:classifiers":[
        {
            "category":"Food Court",
            "type":"Food & Drink"
        }
    ],
    "sg:phone":"+33 4 75 34 23 11",
    "sg:postcode":"07340",
    "sg:province":"Rhone-Alpes",
    "sg:tags":[
        "product",
        "related"
    ],
    "wof:name":"Distillerie Jean Gauthier Sa",
    "wof:placetype":"venue"
},
  "geometry": {"coordinates":[4.75202,45.29179],"type":"Point"}
}