{
  "type": "Feature",
  "properties": {
    "addr:full":"ZI Nord Lu\u00e7on Pays de Loire 85400",
    "addr:postcode":"85400",
    "addr:street":"Zi Nord Luc\u0327On Pays",
    "iso:country":"FR",
    "sg:address":"ZI Nord",
    "sg:city":"Lu\u00e7on",
    "sg:orig_category":"Unclassifiable Establishments",
    "sg:phone":"+33 2 51 29 10 05",
    "sg:postcode":"85400",
    "sg:province":"Pays de Loire",
    "wof:name":"Lovineau Lionel S.a.r.l.",
    "wof:placetype":"venue"
},
  "geometry": {"coordinates":[-1.166538,46.454948],"type":"Point"}
}