{
  "type": "Feature",
  "properties": {
    "addr:full":"les Barons 37260 Villeperdue Villeperdue Centre 37260",
    "addr:postcode":"37260;37260",
    "addr:street":"Barons",
    "iso:country":"FR",
    "sg:address":"les Barons 37260 Villeperdue",
    "sg:city":"Villeperdue",
    "sg:orig_category":"Unclassifiable Establishments",
    "sg:phone":"+33 2 47 26 08 12",
    "sg:postcode":"37260",
    "sg:province":"Centre",
    "wof:name":"Dufresne S.a.r.l.",
    "wof:placetype":"venue"
},
  "geometry": {"coordinates":[0.619915,47.184216],"type":"Point"}
}