{
  "type": "Feature",
  "properties": {
    "iso:country":"FR",
    "sg:address":"310, Bd Charles de Gaulle, 92390 Villeneuve la Garenne",
    "sg:orig_category":"Unclassifiable Establishments",
    "sg:phone":"+33 1 41 47 71 71",
    "sg:province":"Ile de France",
    "wof:name":"Teddington S.a.",
    "wof:placetype":"venue"
},
  "geometry": {"coordinates":[2.312897,48.94434],"type":"Point"}
}