{
  "type": "Feature",
  "properties": {
    "addr:full":"4 Rue Des Aviots 55300 St Mihiel Lorraine 55300",
    "addr:housenumber":"4",
    "addr:postcode":"55300;55300",
    "addr:street":"Rue Des Aviots",
    "iso:country":"FR",
    "sg:address":"4 Rue Des Aviots 55300 St Mihiel",
    "sg:classifiers":[
        {
            "category":"Wholesale",
            "subcategory":"Meat",
            "type":"Manufacturing & Wholesale Goods"
        }
    ],
    "sg:phone":"+33 3 29 90 94 49",
    "sg:postcode":"55300",
    "sg:province":"Lorraine",
    "sg:tags":[
        "food",
        "cooked",
        "product",
        "related"
    ],
    "wof:name":"Gourmelor Sarl",
    "wof:placetype":"venue"
},
  "geometry": {"coordinates":[5.538335,48.896191],"type":"Point"}
}