{
  "type": "Feature",
  "properties": {
    "addr:full":"11, Rue Marius Franay, 92210 Saint Cloud Ile de France",
    "addr:housenumber":"11",
    "addr:postcode":"92210",
    "addr:street":"Rue Marius Franay",
    "iso:country":"FR",
    "sg:address":"11, Rue Marius Franay, 92210 Saint Cloud",
    "sg:orig_category":"Unclassifiable Establishments",
    "sg:phone":"+33 1 46 02 35 00",
    "sg:province":"Ile de France",
    "wof:name":"Dujardin International S.a.r.l.",
    "wof:placetype":"venue"
},
  "geometry": {"coordinates":[2.222136,48.850811],"type":"Point"}
}