{
  "type": "Feature",
  "properties": {
    "iso:country":"FR",
    "sg:address":"47, Rue du Professeur Perrin, 59170 Croix",
    "sg:orig_category":"Non-Classified Establishments",
    "sg:phone":"+33 3 20 45 88 64",
    "sg:province":"Nord Pas-de-Calais",
    "wof:name":"Pix'l S.a.r.l.",
    "wof:placetype":"venue"
},
  "geometry": {"coordinates":[3.145383,50.672474],"type":"Point"}
}