{
  "type": "Feature",
  "properties": {
    "addr:full":"Route Departementale 42 69230 St Genis Laval Cedex Rhone-Alpes 69230",
    "addr:housenumber":"42",
    "addr:postcode":"69230;cedex rhone-alpes 69230",
    "addr:street":"Route Departementale;Genis",
    "iso:country":"FR",
    "sg:address":"Route Departementale 42 69230 St Genis Laval Cedex",
    "sg:classifiers":[
        {
            "category":"Manufacturing",
            "subcategory":"Metals",
            "type":"Manufacturing & Wholesale Goods"
        }
    ],
    "sg:phone":"+33 4 78 56 12 58",
    "sg:postcode":"69230",
    "sg:province":"Rhone-Alpes",
    "sg:tags":[
        "-",
        "machine",
        "equipment",
        "engineering",
        "machinery",
        "mechanical"
    ],
    "wof:name":"Eral",
    "wof:placetype":"venue"
},
  "geometry": {"coordinates":[4.79296,45.694736],"type":"Point"}
}