{
  "type": "Feature",
  "properties": {
    "addr:full":"148, Rue de Chevilly, 94240 L'Ha\u00ff les Roses Ile de France",
    "addr:housenumber":"148",
    "addr:postcode":"94240",
    "addr:street":"Rue De Chevilly;\u0308",
    "iso:country":"FR",
    "sg:address":"148, Rue de Chevilly, 94240 L'Ha\u00ff les Roses",
    "sg:orig_category":"Non-Classified Establishments",
    "sg:phone":"+33 1 56 30 16 00",
    "sg:province":"Ile de France",
    "wof:name":"M\u00e9dia Talk S.a.r.l.",
    "wof:placetype":"venue"
},
  "geometry": {"coordinates":[2.350953,48.773918],"type":"Point"}
}