{
  "type": "Feature",
  "properties": {
    "iso:country":"FR",
    "sg:address":"226 Rue Loeze 01570 Feillens",
    "sg:classifiers":[
        {
            "category":"Wholesale",
            "subcategory":"Meat",
            "type":"Manufacturing & Wholesale Goods"
        }
    ],
    "sg:phone":"+33 3 85 36 13 23",
    "sg:postcode":"01570",
    "sg:province":"Rhone-Alpes",
    "sg:tags":[
        "food",
        "cooked",
        "product",
        "related"
    ],
    "wof:name":"Monterrat (sa Roland)",
    "wof:placetype":"venue"
},
  "geometry": {"coordinates":[4.888295,46.325809],"type":"Point"}
}