{
  "type": "Feature",
  "properties": {
    "iso:country":"FR",
    "sg:address":"B.P. 20160, 86360 Futuroscope C\u00e9dex^^Av. Thomas Edison, 86360 Chasseneuil du Poitou",
    "sg:orig_category":"Non-Classified Establishments",
    "sg:phone":"+33 5 49 49 49 30",
    "sg:province":"Corse",
    "wof:name":"Serli Informatique S.a.r.l.",
    "wof:placetype":"venue"
},
  "geometry": {"coordinates":[0.37477,46.650494],"type":"Point"}
}