{
  "type": "Feature",
  "properties": {
    "addr:full":"B.P. 2, 18500 Mehun sur Y\u00e8vre^^120, Av. Raoul Aladenize, 18500 Mehun sur Y\u00e8vre Marmagne Centre 18500",
    "addr:housenumber":"2",
    "addr:postcode":"18500;18500;18500",
    "addr:street":"B.P.;Av. Raoul Aladenize",
    "iso:country":"FR",
    "sg:address":"B.P. 2, 18500 Mehun sur Y\u00e8vre^^120, Av. Raoul Aladenize, 18500 Mehun sur Y\u00e8vre",
    "sg:city":"Marmagne",
    "sg:orig_category":"Non-Classified Establishments",
    "sg:phone":"+33 2 48 57 31 05",
    "sg:postcode":"18500",
    "sg:province":"Centre",
    "wof:name":"Etablissements R Melin S.a.",
    "wof:placetype":"venue"
},
  "geometry": {"coordinates":[2.318975,47.076126],"type":"Point"}
}