{
  "type": "Feature",
  "properties": {
    "iso:country":"FR",
    "sg:address":"ZA le Bourgeat",
    "sg:city":"Villars",
    "sg:orig_category":"Unclassifiable Establishments",
    "sg:phone":"+33 4 77 93 28 36",
    "sg:postcode":"42390",
    "sg:province":"Rhone-Alpes",
    "wof:name":"I.v.f. S.a.r.l. - Inter Velay Forez",
    "wof:placetype":"venue"
},
  "geometry": {"coordinates":[4.353038,45.467468],"type":"Point"}
}