{
  "type": "Feature",
  "properties": {
    "iso:country":"FR",
    "sg:address":"48 R Maurice Thorez 92000 Nanterre",
    "sg:classifiers":[
        {
            "category":"Banks & Credit Unions",
            "subcategory":"Financial Services",
            "type":"Services"
        }
    ],
    "sg:phone":"+33 1 41 20 98 30",
    "sg:postcode":"92000",
    "sg:province":"Ile de France",
    "sg:tags":[
        "banking",
        "insurance",
        "institution",
        "finance"
    ],
    "wof:name":"Ste Generale Sa",
    "wof:placetype":"venue"
},
  "geometry": {"coordinates":[2.195921,48.893337],"type":"Point"}
}