{
  "type": "Feature",
  "properties": {
    "iso:country":"FR",
    "sg:address":"15 Rn 76210 Lanquetot",
    "sg:classifiers":[
        {
            "category":"Building & Trades",
            "subcategory":"Construction",
            "type":"Services"
        }
    ],
    "sg:phone":"+33 2 35 39 95 38",
    "sg:postcode":"76210",
    "sg:province":"Haute Normandie",
    "sg:tags":[
        "work",
        "public"
    ],
    "wof:name":"Lheureux Charles Henri Paul Pressing Carnot",
    "wof:placetype":"venue"
},
  "geometry": {"coordinates":[0.451852,49.553249],"type":"Point"}
}