{
  "type": "Feature",
  "properties": {
    "iso:country":"FR",
    "sg:address":"Bd Maxime Gorki",
    "sg:city":"Stains",
    "sg:orig_category":"Unclassifiable Establishments",
    "sg:phone":"+33 1 49 40 13 31",
    "sg:postcode":"93240",
    "sg:province":"Ile de France",
    "wof:name":"A.f.p.a.",
    "wof:placetype":"venue"
},
  "geometry": {"coordinates":[2.383285,48.95528],"type":"Point"}
}