{
  "type": "Feature",
  "properties": {
    "addr:full":"387 R Des Vall\u00e9es 53100 Mayenne Pays de Loire 53100",
    "addr:housenumber":"387",
    "addr:postcode":"53100 mayenne;53100",
    "addr:street":"R Des Valle\u0301Es",
    "iso:country":"FR",
    "sg:address":"387 R Des Vall\u00e9es 53100 Mayenne",
    "sg:classifiers":[
        {
            "category":"Professional",
            "subcategory":"Business Services",
            "type":"Services"
        }
    ],
    "sg:phone":"+33 2 43 30 47 48",
    "sg:postcode":"53100",
    "sg:province":"Pays de Loire",
    "sg:tags":[
        "training",
        "advice"
    ],
    "wof:name":"L'ecole Primaire De La Vallee Don Bosco",
    "wof:placetype":"venue"
},
  "geometry": {"coordinates":[-0.619482,48.296165],"type":"Point"}
}