{
  "type": "Feature",
  "properties": {
    "iso:country":"FR",
    "sg:address":"75, Cours Balguerie Stuttenberg, 33300 Bordeaux",
    "sg:city":"Bordeaux",
    "sg:orig_category":"Non-Classified Establishments",
    "sg:phone":"+33 5 56 50 51 51",
    "sg:postcode":"33300",
    "sg:province":"Aquitaine",
    "wof:name":"Interservice Bordeaux S.a.r.l.",
    "wof:placetype":"venue"
},
  "geometry": {"coordinates":[-0.56813,44.857349],"type":"Point"}
}