{
  "type": "Feature",
  "properties": {
    "addr:full":"21, Rue de la Fontaine au Roi, 75011 Paris Ile de France",
    "addr:housenumber":"21",
    "addr:postcode":"75011",
    "addr:street":"Rue De La Fontaine Au Roi",
    "iso:country":"FR",
    "sg:address":"21, Rue de la Fontaine au Roi, 75011 Paris",
    "sg:orig_category":"Non-Classified Establishments",
    "sg:phone":"+33 1 43 38 10 24",
    "sg:province":"Ile de France",
    "wof:name":"Imaginet S.a.",
    "wof:placetype":"venue"
},
  "geometry": {"coordinates":[2.370359,48.868542],"type":"Point"}
}