{
  "type": "Feature",
  "properties": {
    "iso:country":"FR",
    "sg:address":"52, Av. de Cournon, 63170 Aubi\u00e8re",
    "sg:city":"Aubi\u00e8re",
    "sg:orig_category":"Unclassifiable Establishments",
    "sg:phone":"+33 4 73 26 34 29",
    "sg:postcode":"63170",
    "sg:province":"Auvergne",
    "wof:name":"Pouderoux",
    "wof:placetype":"venue"
},
  "geometry": {"coordinates":[3.137632,45.753433],"type":"Point"}
}