{
  "type": "Feature",
  "properties": {
    "addr:full":"52, Av. de Cournon, 63170 Aubi\u00e8re Aubi\u00e8re Auvergne 63170",
    "addr:postcode":"63170;63170",
    "addr:street":"52 Av. De Cournon",
    "iso:country":"FR",
    "sg:address":"52, Av. de Cournon, 63170 Aubi\u00e8re",
    "sg:city":"Aubi\u00e8re",
    "sg:orig_category":"Unclassifiable Establishments",
    "sg:phone":"+33 4 73 26 34 29",
    "sg:postcode":"63170",
    "sg:province":"Auvergne",
    "wof:name":"Pouderoux",
    "wof:placetype":"venue"
},
  "geometry": {"coordinates":[3.137632,45.753433],"type":"Point"}
}