{
  "type": "Feature",
  "properties": {
    "addr:full":"15, Rue Loustau, 64200 Biarritz Biarritz Aquitaine 64200",
    "addr:housenumber":"15",
    "addr:postcode":"64200;64200",
    "addr:street":"Rue Loustau",
    "iso:country":"FR",
    "sg:address":"15, Rue Loustau, 64200 Biarritz",
    "sg:city":"Biarritz",
    "sg:orig_category":"Non-Classified Establishments",
    "sg:phone":"+33 5 59 24 94 33",
    "sg:postcode":"64200",
    "sg:province":"Aquitaine",
    "wof:name":"S.f.i. S.a.r.l. - Soci\u00e9t\u00e9 De Fa\u00e7onnage Industriel",
    "wof:placetype":"venue"
},
  "geometry": {"coordinates":[-1.564323,43.477566],"type":"Point"}
}