{
  "type": "Feature",
  "properties": {
    "iso:country":"FR",
    "sg:address":"24, Rue Ozenne, 31000 Toulouse",
    "sg:orig_category":"Unclassifiable Establishments",
    "sg:phone":"+33 5 61 52 01 02",
    "sg:province":"Midi Pyr\u00e9n\u00e9es",
    "wof:name":"Louis Foug\u00e8re Et Fils S.a.r.l.",
    "wof:placetype":"venue"
},
  "geometry": {"coordinates":[1.448239,43.595146],"type":"Point"}
}