{
  "type": "Feature",
  "properties": {
    "addr:full":"23 Rue Du Saule Trapu 91300 Massy Ile de France",
    "addr:housenumber":"23",
    "addr:postcode":"91300",
    "addr:street":"Rue Du Saule Trapu;Ile De France",
    "iso:country":"FR",
    "sg:address":"23 Rue Du Saule Trapu 91300 Massy",
    "sg:classifiers":[
        {
            "category":"Utilities",
            "subcategory":"Telephone",
            "type":"Services"
        }
    ],
    "sg:phone":"+33 1 69 93 14 00",
    "sg:province":"Ile de France",
    "sg:tags":[
        "telecommunication"
    ],
    "wof:name":"Etde",
    "wof:placetype":"venue"
},
  "geometry": {"coordinates":[2.30347,48.730751],"type":"Point"}
}