{
  "type": "Feature",
  "properties": {
    "iso:country":"FR",
    "sg:address":"B.P. 217, 95523 Cergy Pontoise C\u00e9dex^^9, Chauss\u00e9e Jules C\u00e9sar, 95520 Osny",
    "sg:orig_category":"Non-Classified Establishments",
    "sg:phone":"+33 1 34 35 35 10",
    "sg:postcode":"95520",
    "sg:province":"Ile de France",
    "wof:name":"Apitec S.a.r.l.",
    "wof:placetype":"venue"
},
  "geometry": {"coordinates":[2.064945,49.064018],"type":"Point"}
}