{
  "type": "Feature",
  "properties": {
    "addr:full":"B.P. 1, 37270 Montlouis sur Loire Cedex^^ZI de Thuisseau, 37270 Montlouis sur Loire Ath\u00e9e-sur-Cher Centre 37270",
    "addr:housenumber":"1;athe\u0301e-sur-cher",
    "addr:postcode":"37270;37270;37270",
    "addr:street":"B.P.",
    "iso:country":"FR",
    "sg:address":"B.P. 1, 37270 Montlouis sur Loire Cedex^^ZI de Thuisseau, 37270 Montlouis sur Loire",
    "sg:city":"Ath\u00e9e-sur-Cher",
    "sg:orig_category":"Non-Classified Establishments",
    "sg:phone":"+33 2 47 45 05 84",
    "sg:postcode":"37270",
    "sg:province":"Centre",
    "wof:name":"Philocolor-prochinor S.a.",
    "wof:placetype":"venue"
},
  "geometry": {"coordinates":[0.918022,47.31168],"type":"Point"}
}