{
  "type": "Feature",
  "properties": {
    "addr:full":"4 Rue Saint-Vincent 40100 Dax Dax Aquitaine 40100",
    "addr:housenumber":"4",
    "addr:postcode":"40100;40100",
    "addr:street":"Rue Saint-Vincent",
    "iso:country":"FR",
    "sg:address":"4 Rue Saint-Vincent 40100 Dax",
    "sg:city":"Dax",
    "sg:classifiers":[
        {
            "category":"Health Services",
            "subcategory":"Optometrist",
            "type":"Services"
        }
    ],
    "sg:phone":"+33 5 58 74 22 13",
    "sg:postcode":"40100",
    "sg:province":"Aquitaine",
    "sg:tags":[
        "instrument",
        "optical",
        "-",
        "precision",
        "equipment"
    ],
    "wof:name":"Optique Malfroy Sarl",
    "wof:placetype":"venue"
},
  "geometry": {"coordinates":[-1.054918,43.708866],"type":"Point"}
}