{
  "type": "Feature",
  "properties": {
    "addr:full":"308, Rue des Fontaines - ZI la Praz, 74130 Vougy Rhone-Alpes 74130",
    "addr:housenumber":"308",
    "addr:postcode":"74130;74130",
    "addr:street":"Rue Des Fontaines Zi La;Rhone-Alpes",
    "iso:country":"FR",
    "sg:address":"308, Rue des Fontaines - ZI la Praz, 74130 Vougy",
    "sg:orig_category":"Unclassifiable Establishments",
    "sg:phone":"+33 4 50 34 57 15",
    "sg:postcode":"74130",
    "sg:province":"Rhone-Alpes",
    "wof:name":"Prapack Cartonnages S.a.r.l.",
    "wof:placetype":"venue"
},
  "geometry": {"coordinates":[6.388322,45.95652],"type":"Point"}
}