{
  "type": "Feature",
  "properties": {
    "iso:country":"FR",
    "sg:address":"Za Maison Dieu 21220 Fixin",
    "sg:city":"Fixin",
    "sg:classifiers":[
        {
            "category":"Shopping",
            "type":"Retail Goods"
        }
    ],
    "sg:phone":"+33 3 80 52 45 30",
    "sg:postcode":"21220",
    "sg:province":"Bourgogne",
    "sg:tags":[
        "metallurgy",
        "finished",
        "-",
        "metalworking",
        "metallic"
    ],
    "wof:name":"Sarl Bourgogne Enseignes",
    "wof:placetype":"venue"
},
  "geometry": {"coordinates":[4.97305,47.244911],"type":"Point"}
}