{
  "type": "Feature",
  "properties": {
    "addr:full":"55 avenue du Loup 64000 Pau Pau Aquitaine 64000",
    "addr:housenumber":"55",
    "addr:postcode":"64000;64000",
    "addr:street":"Avenue Du Loup",
    "iso:country":"FR",
    "sg:address":"55 avenue du Loup 64000 Pau",
    "sg:city":"Pau",
    "sg:classifiers":[
        {
            "category":"Wholesale",
            "subcategory":"Wine & Distilled Alcoholic Beverages",
            "type":"Manufacturing & Wholesale Goods"
        }
    ],
    "sg:phone":"+33 5 59 30 56 12",
    "sg:postcode":"64000",
    "sg:province":"Aquitaine",
    "sg:tags":[
        "french"
    ],
    "wof:name":"Giraud Et Hallot Sas",
    "wof:placetype":"venue"
},
  "geometry": {"coordinates":[-0.356242,43.312359],"type":"Point"}
}