{
  "type": "Feature",
  "properties": {
    "addr:full":"B.P. 26, 34201 S\u00e8te C\u00e9dex^^15, Rue Jules Valles - R\u00e9sidence Saint Marc, 34200 S\u00e8te Languedoc-Roussillon",
    "addr:postcode":"34201;34200",
    "addr:street":"B.P. 26;Rue Jules Valles Re\u0301Sidence Saint Marc",
    "iso:country":"FR",
    "sg:address":"B.P. 26, 34201 S\u00e8te C\u00e9dex^^15, Rue Jules Valles - R\u00e9sidence Saint Marc, 34200 S\u00e8te",
    "sg:orig_category":"Non-Classified Establishments",
    "sg:phone":"+33 4 67 74 93 39",
    "sg:province":"Languedoc-Roussillon",
    "wof:name":"S\u00e8te Informatique S.a.r.l.",
    "wof:placetype":"venue"
},
  "geometry": {"coordinates":[3.69633,43.399052],"type":"Point"}
}