{
  "type": "Feature",
  "properties": {
    "addr:full":"45 Grand Rue 68500 Orschwihr Orschwihr Alsace 68500",
    "addr:housenumber":"45",
    "addr:postcode":"68500;68500",
    "addr:street":"Grand Rue;Orschwihr",
    "iso:country":"FR",
    "sg:address":"45 Grand Rue 68500 Orschwihr",
    "sg:city":"Orschwihr",
    "sg:classifiers":[
        {
            "category":"Food Court",
            "type":"Food & Drink"
        }
    ],
    "sg:phone":"+33 3 89 76 95 17",
    "sg:postcode":"68500",
    "sg:province":"Alsace",
    "sg:tags":[
        "product",
        "related"
    ],
    "wof:name":"Haegelin Materne Sa",
    "wof:placetype":"venue"
},
  "geometry": {"coordinates":[7.232226,47.933853],"type":"Point"}
}