{
  "type": "Feature",
  "properties": {
    "iso:country":"FR",
    "sg:address":"Zi De L\u00e9z\u00e9on Plou\u00e9dern 29419 Landerneau",
    "sg:classifiers":[
        {
            "category":"Food Court",
            "type":"Food & Drink"
        }
    ],
    "sg:phone":"+33 2 98 37 57 00",
    "sg:province":"Haute Normandie",
    "sg:tags":[
        "product",
        "related"
    ],
    "wof:name":"France Boisson Brest Sa",
    "wof:placetype":"venue"
},
  "geometry": {"coordinates":[-4.25207,48.453659],"type":"Point"}
}