{
  "type": "Feature",
  "properties": {
    "addr:full":"5 Boulevard Victor Hugo 83150 Bandol Provence-Alpes-C\u00f4te d'Azur",
    "addr:housenumber":"5",
    "addr:postcode":"83150",
    "addr:street":"Boulevard Victor Hugo;Bandol",
    "iso:country":"FR",
    "sg:address":"5 Boulevard Victor Hugo 83150 Bandol",
    "sg:classifiers":[
        {
            "category":"Professional",
            "subcategory":"Printing & Photocopies",
            "type":"Services"
        }
    ],
    "sg:phone":"+33 4 94 29 52 98",
    "sg:province":"Provence-Alpes-C\u00f4te d'Azur",
    "sg:tags":[
        "publishing"
    ],
    "wof:name":"Les Editions Aris",
    "wof:placetype":"venue"
},
  "geometry": {"coordinates":[5.753157,43.135284],"type":"Point"}
}