{
  "type": "Feature",
  "properties": {
    "addr:full":"279, Rue des Gentianes, 74800 La Roche sur Foron Rhone-Alpes 74800",
    "addr:housenumber":"279",
    "addr:postcode":"74800;74800",
    "addr:street":"Rue Des Gentianes",
    "iso:country":"FR",
    "sg:address":"279, Rue des Gentianes, 74800 La Roche sur Foron",
    "sg:orig_category":"Non-Classified Establishments",
    "sg:phone":"+33 4 50 25 88 90",
    "sg:postcode":"74800",
    "sg:province":"Rhone-Alpes",
    "wof:name":"Vall\u00e9e Verte Voyages S.a.r.l.",
    "wof:placetype":"venue"
},
  "geometry": {"coordinates":[6.295083,46.076466],"type":"Point"}
}