{
  "type": "Feature",
  "properties": {
    "iso:country":"FR",
    "sg:address":"13 Rue Du 8 Mai 54520 Laxou",
    "sg:classifiers":[
        {
            "category":"Professional",
            "subcategory":"Business Services",
            "type":"Services"
        }
    ],
    "sg:phone":"+33 3 83 28 69 27",
    "sg:postcode":"54520",
    "sg:province":"Lorraine",
    "sg:tags":[
        "training",
        "advice"
    ],
    "wof:name":"Ecole De Musique De Laxou",
    "wof:placetype":"venue"
},
  "geometry": {"coordinates":[6.153412,48.681122],"type":"Point"}
}