{
  "type": "Feature",
  "properties": {
    "iso:country":"FR",
    "sg:address":"Zone Industrielle",
    "sg:city":"Chevigny Saint Sauveur",
    "sg:orig_category":"Non-Classified Establishments",
    "sg:phone":"+33 3 80 46 32 31",
    "sg:postcode":"21800",
    "sg:province":"Bourgogne",
    "wof:name":"S.n.c.i. S.a. - Soci\u00e9t\u00e9 Nouvelle De Construction Pour L'industrie",
    "wof:placetype":"venue"
},
  "geometry": {"coordinates":[5.135262,47.301807],"type":"Point"}
}