{
  "type": "Feature",
  "properties": {
    "addr:full":"B.P. 16, 90100 Delle^^60, Fbg de Belfort, 90100 Delle Franche Comt\u00e9",
    "addr:postcode":"90100;90100",
    "addr:street":"B.P. 16;Belfort;Franche Comte\u0301",
    "iso:country":"FR",
    "sg:address":"B.P. 16, 90100 Delle^^60, Fbg de Belfort, 90100 Delle",
    "sg:orig_category":"Non-Classified Establishments",
    "sg:phone":"+33 3 84 58 48 48",
    "sg:province":"Franche Comt\u00e9",
    "wof:name":"Igol Nord Est S.a.",
    "wof:placetype":"venue"
},
  "geometry": {"coordinates":[7.00309,47.508034],"type":"Point"}
}