{
  "type": "Feature",
  "properties": {
    "iso:country":"FR",
    "sg:address":"58 rue Alain Gerbault 56000 Vannes",
    "sg:city":"Vannes",
    "sg:classifiers":[
        {
            "category":"Shopping",
            "subcategory":"Bicycles & Sporting Goods",
            "type":"Retail Goods"
        }
    ],
    "sg:phone":"+33 2 97 43 75 00",
    "sg:postcode":"56000",
    "sg:province":"Bretagne",
    "sg:tags":[
        "surfboard"
    ],
    "wof:name":"Bic Sport S.a.",
    "wof:placetype":"venue"
},
  "geometry": {"coordinates":[-2.727109,47.66383],"type":"Point"}
}