{
  "type": "Feature",
  "properties": {
    "iso:country":"FR",
    "sg:address":"41-43, Rue P\u00e9rier, 92120 Montrouge",
    "sg:orig_category":"Unclassifiable Establishments",
    "sg:phone":"+33 1 46 12 52 52",
    "sg:province":"Ile de France",
    "wof:name":"Ar\u00e9s S.a.",
    "wof:placetype":"venue"
},
  "geometry": {"coordinates":[2.316036,48.813999],"type":"Point"}
}