{
  "type": "Feature",
  "properties": {
    "addr:full":"Av Charles De Foucault 62114 Sains En Gohelle Nord Pas-de-Calais 62114",
    "addr:postcode":"62114;62114",
    "addr:street":"Av Charles De Foucault;Pas-De-Calais",
    "iso:country":"FR",
    "sg:address":"Av Charles De Foucault 62114 Sains En Gohelle",
    "sg:classifiers":[
        {
            "category":"Manufacturing",
            "subcategory":"Glass & Minerals",
            "type":"Manufacturing & Wholesale Goods"
        }
    ],
    "sg:phone":"+33 3 21 29 10 55",
    "sg:postcode":"62114",
    "sg:province":"Nord Pas-de-Calais",
    "sg:tags":[
        "building",
        "material"
    ],
    "wof:name":"Beton De France Nord Alsace",
    "wof:placetype":"venue"
},
  "geometry": {"coordinates":[2.69254,50.444832],"type":"Point"}
}