{
  "type": "Feature",
  "properties": {
    "addr:full":"Zi De Buray 41500 Mer Mer Centre 41500",
    "addr:postcode":"41500;41500",
    "addr:street":"Zi De Buray",
    "iso:country":"FR",
    "sg:address":"Zi De Buray 41500 Mer",
    "sg:city":"Mer",
    "sg:classifiers":[
        {
            "category":"Wholesale",
            "subcategory":"Farm Supplies",
            "type":"Manufacturing & Wholesale Goods"
        }
    ],
    "sg:phone":"+33 2 54 81 01 77",
    "sg:postcode":"41500",
    "sg:province":"Centre",
    "sg:tags":[
        "-",
        "machine",
        "equipment",
        "engineering",
        "machinery",
        "mechanical",
        "agriculture"
    ],
    "wof:name":"Ets Thelliez Sa",
    "wof:placetype":"venue"
},
  "geometry": {"coordinates":[1.50857,47.703461],"type":"Point"}
}