{
  "type": "Feature",
  "properties": {
    "iso:country":"FR",
    "sg:address":"22, Av. des Nations - ZAC Paris Nord II - Immeuble Rapha\u00ebl, 93420 Villepinte",
    "sg:orig_category":"Unclassifiable Establishments",
    "sg:phone":"+33 1 48 63 13 92",
    "sg:province":"Ile de France",
    "wof:name":"Zwick France S.a.r.l.",
    "wof:placetype":"venue"
},
  "geometry": {"coordinates":[2.53979,48.955807],"type":"Point"}
}