{
  "type": "Feature",
  "properties": {
    "addr:full":"B.P. 7, 95141 Garges l\u00e8s Gonesse C\u00e9dex^^21/23, Bd de la Muette, 95140 Garges l\u00e8s Gonesse Ile de France 95140",
    "addr:housenumber":"7",
    "addr:postcode":"95141;23;95140;le\u0300s;ile;95140",
    "addr:street":"B.P.;Bd De La Muette;France",
    "iso:country":"FR",
    "sg:address":"B.P. 7, 95141 Garges l\u00e8s Gonesse C\u00e9dex^^21/23, Bd de la Muette, 95140 Garges l\u00e8s Gonesse",
    "sg:orig_category":"Non-Classified Establishments",
    "sg:phone":"+33 1 34 45 08 00",
    "sg:postcode":"95140",
    "sg:province":"Ile de France",
    "wof:name":"De Ruysscher Papyrus S.a.",
    "wof:placetype":"venue"
},
  "geometry": {"coordinates":[2.39924,48.970955],"type":"Point"}
}