{
  "type": "Feature",
  "properties": {
    "addr:full":"B.P. 7, 82400 Valence d'Agen C\u00e9dex^^Place Sylvain Dumon, 82400 Valence d'Agen Midi Pyr\u00e9n\u00e9es 82400",
    "addr:housenumber":"7",
    "addr:postcode":"82400;82400;82400",
    "addr:street":"B.P.;Dumon",
    "iso:country":"FR",
    "sg:address":"B.P. 7, 82400 Valence d'Agen C\u00e9dex^^Place Sylvain Dumon, 82400 Valence d'Agen",
    "sg:orig_category":"Non-Classified Establishments",
    "sg:phone":"+33 5 63 29 04 44",
    "sg:postcode":"82400",
    "sg:province":"Midi Pyr\u00e9n\u00e9es",
    "wof:name":"Auto-distribution Syldos Toulouse S.a.",
    "wof:placetype":"venue"
},
  "geometry": {"coordinates":[0.889021,44.107674],"type":"Point"}
}