{
  "type": "Feature",
  "properties": {
    "addr:full":"20, Rue de la Girine, 38460 Saint Romain de Jalionas Rhone-Alpes",
    "addr:housenumber":"20",
    "addr:postcode":"38460",
    "addr:street":"Rue De La Girine",
    "iso:country":"FR",
    "sg:address":"20, Rue de la Girine, 38460 Saint Romain de Jalionas",
    "sg:orig_category":"Unclassifiable Establishments",
    "sg:phone":"+33 4 74 90 76 33",
    "sg:province":"Rhone-Alpes",
    "wof:name":"D.e.2.m. S.a.r.l.",
    "wof:placetype":"venue"
},
  "geometry": {"coordinates":[5.21171,45.755524],"type":"Point"}
}