{
  "type": "Feature",
  "properties": {
    "addr:full":"39, Av. de Vizille, 38000 Grenoble Rhone-Alpes",
    "addr:postcode":"38000",
    "addr:street":"39 Av. De Vizille",
    "iso:country":"FR",
    "sg:address":"39, Av. de Vizille, 38000 Grenoble",
    "sg:orig_category":"Unclassifiable Establishments",
    "sg:phone":"+33 4 76 48 22 17",
    "sg:province":"Rhone-Alpes",
    "wof:name":"Saro S.a.r.l.",
    "wof:placetype":"venue"
},
  "geometry": {"coordinates":[5.71573,45.187344],"type":"Point"}
}