{
  "type": "Feature",
  "properties": {
    "addr:full":"1, Rue Amp\u00e8re - ZA du Patis, 78120 Rambouillet Ile de France 78120",
    "addr:housenumber":"1",
    "addr:postcode":"78120;ile;78120",
    "addr:street":"Rue Ampe\u0300Re Za Du Patis;France",
    "iso:country":"FR",
    "sg:address":"1, Rue Amp\u00e8re - ZA du Patis, 78120 Rambouillet",
    "sg:orig_category":"Non-Classified Establishments",
    "sg:phone":"+33 1 34 85 78 51",
    "sg:postcode":"78120",
    "sg:province":"Ile de France",
    "wof:name":"D.p. S.a. - D\u00e9sign Performance",
    "wof:placetype":"venue"
},
  "geometry": {"coordinates":[1.826199,48.643406],"type":"Point"}
}