{
  "type": "Feature",
  "properties": {
    "iso:country":"FR",
    "sg:address":"Zac De Novialle 63670 La Roche Blanche",
    "sg:city":"Le Cendre",
    "sg:classifiers":[
        {
            "category":"Professional",
            "subcategory":"Engineering",
            "type":"Services"
        }
    ],
    "sg:phone":"+33 4 73 79 14 90",
    "sg:postcode":"63670",
    "sg:province":"Auvergne",
    "sg:tags":[
        "machine",
        "-",
        "mechanical"
    ],
    "wof:name":"Froid Climat Auvergne",
    "wof:placetype":"venue"
},
  "geometry": {"coordinates":[3.129955,45.704155],"type":"Point"}
}