{
  "type": "Feature",
  "properties": {
    "addr:full":"5 rue des Italiens 74200 Thonon les Bains Rhone-Alpes 74200",
    "addr:housenumber":"5",
    "addr:postcode":"74200;74200",
    "addr:street":"Rue Des Italiens",
    "iso:country":"FR",
    "sg:address":"5 rue des Italiens 74200 Thonon les Bains",
    "sg:classifiers":[
        {
            "category":"Manufacturing",
            "subcategory":"Soap",
            "type":"Manufacturing & Wholesale Goods"
        }
    ],
    "sg:phone":"+33 4 50 36 37 56",
    "sg:postcode":"74200",
    "sg:province":"Rhone-Alpes",
    "sg:tags":[
        "curd"
    ],
    "wof:name":"Laboratoire Provendi S.a.r.l.",
    "wof:placetype":"venue"
},
  "geometry": {"coordinates":[6.476475,46.368492],"type":"Point"}
}