{
  "type": "Feature",
  "properties": {
    "addr:full":"161, Bd de la Croix Rousse, 69004 Lyon Rhone-Alpes 69004",
    "addr:housenumber":"161",
    "addr:postcode":"69004;69004",
    "addr:street":"Bd De La Croix Rousse",
    "iso:country":"FR",
    "sg:address":"161, Bd de la Croix Rousse, 69004 Lyon",
    "sg:orig_category":"Non-Classified Establishments",
    "sg:phone":"+33 4 72 10 97 60",
    "sg:postcode":"69004",
    "sg:province":"Rhone-Alpes",
    "wof:name":"Banque Sanpaolo S.a.",
    "wof:placetype":"venue"
},
  "geometry": {"coordinates":[4.83107,45.774624],"type":"Point"}
}