{
  "type": "Feature",
  "properties": {
    "iso:country":"FR",
    "sg:address":"B.P. 06, 63014 Clermont Ferrand C\u00e9dex^^8, Rue Chappe, 63000 Clermont Ferrand",
    "sg:city":"Clermont-Ferrand",
    "sg:orig_category":"Non-Classified Establishments",
    "sg:phone":"+33 4 73 90 84 79",
    "sg:postcode":"63000",
    "sg:province":"Auvergne",
    "wof:name":"Limoujoux Surgel\u00e9s S.a.r.l.",
    "wof:placetype":"venue"
},
  "geometry": {"coordinates":[3.08183,45.777618],"type":"Point"}
}