{
  "type": "Feature",
  "properties": {
    "addr:full":"B.P. 59, 91072 Bondoufle Cedex^^8, Rue Pierre Josse - ZA des Bordes, 91070 Bondoufle Ile de France 91070",
    "addr:postcode":"91072;91070;ile;91070",
    "addr:street":"B.P. 59;Rue Pierre Josse Za Des Bordes;France",
    "iso:country":"FR",
    "sg:address":"B.P. 59, 91072 Bondoufle Cedex^^8, Rue Pierre Josse - ZA des Bordes, 91070 Bondoufle",
    "sg:orig_category":"Non-Classified Establishments",
    "sg:phone":"+33 1 69 11 83 00",
    "sg:postcode":"91070",
    "sg:province":"Ile de France",
    "wof:name":"A.c.f.r.i. S.a. - Atelier De Construction Frigorifique",
    "wof:placetype":"venue"
},
  "geometry": {"coordinates":[2.379516,48.615681],"type":"Point"}
}