{
  "type": "Feature",
  "properties": {
    "addr:full":"11 route Industrielle 68320 Kunheim Kunheim Alsace 68320",
    "addr:housenumber":"11",
    "addr:postcode":"68320;68320",
    "addr:street":"Route Industrielle",
    "iso:country":"FR",
    "sg:address":"11 route Industrielle 68320 Kunheim",
    "sg:city":"Kunheim",
    "sg:orig_category":"Cardboard, General",
    "sg:phone":"+33 3 89 72 22 00",
    "sg:postcode":"68320",
    "sg:province":"Alsace",
    "wof:name":"Kaysersberg Packaging Sa",
    "wof:placetype":"venue"
},
  "geometry": {"coordinates":[7.42541,48.110287],"type":"Point"}
}