{
  "type": "Feature",
  "properties": {
    "addr:full":"Chemin du Collet Rouge Les Pennes Mirabeau Provence-Alpes-C\u00f4te d'Azur 13170",
    "addr:postcode":"13170",
    "addr:street":"Chemin Du Collet Rouge Les Pennes Mirabeau",
    "iso:country":"FR",
    "sg:address":"Chemin du Collet Rouge",
    "sg:city":"Les Pennes Mirabeau",
    "sg:orig_category":"Unclassifiable Establishments",
    "sg:phone":"+33 4 42 02 06 00",
    "sg:postcode":"13170",
    "sg:province":"Provence-Alpes-C\u00f4te d'Azur",
    "wof:name":"B.h. S.a. - Boulogne Et Huard",
    "wof:placetype":"venue"
},
  "geometry": {"coordinates":[5.358138,43.412373],"type":"Point"}
}