{
  "type": "Feature",
  "properties": {
    "addr:full":"Rue Augustin l'Hermitte 59139 Wattignies Nord Pas-de-Calais 59139",
    "addr:postcode":"59139;59139",
    "addr:street":"Rue Augustin L'Hermitte",
    "iso:country":"FR",
    "sg:address":"Rue Augustin l'Hermitte 59139 Wattignies",
    "sg:orig_category":"Joinery Supraregional",
    "sg:phone":"+33 3 20 62 04 60",
    "sg:postcode":"59139",
    "sg:province":"Nord Pas-de-Calais",
    "wof:name":"Flip Sa",
    "wof:placetype":"venue"
},
  "geometry": {"coordinates":[3.032819,50.574734],"type":"Point"}
}