{
  "type": "Feature",
  "properties": {
    "iso:country":"FR",
    "sg:address":"54, Rue des Dou\u00e9s, 37000 Tours",
    "sg:city":"Tours",
    "sg:orig_category":"Non-Classified Establishments",
    "sg:phone":"+33 2 47 85 55 44",
    "sg:postcode":"37000",
    "sg:province":"Centre",
    "wof:name":"A.t.a.i.s.",
    "wof:placetype":"venue"
},
  "geometry": {"coordinates":[0.689715,47.390385],"type":"Point"}
}