{
  "type": "Feature",
  "properties": {
    "addr:full":"2B, Rue Aristide Briand, 27530 Ezy sur Eure Haute Normandie",
    "addr:housenumber":"2b",
    "addr:postcode":"27530",
    "addr:street":"Rue Aristide Briand;Ezy;Haute Normandie",
    "iso:country":"FR",
    "sg:address":"2B, Rue Aristide Briand, 27530 Ezy sur Eure",
    "sg:orig_category":"Unclassifiable Establishments",
    "sg:phone":"+33 2 37 62 87 00",
    "sg:province":"Haute Normandie",
    "wof:name":"Revicompta S.a.",
    "wof:placetype":"venue"
},
  "geometry": {"coordinates":[1.418151,48.863014],"type":"Point"}
}