{
  "type": "Feature",
  "properties": {
    "addr:full":"38, Rue Andr\u00e9 Boulle, 41000 Blois Blois Centre 41000",
    "addr:housenumber":"38",
    "addr:postcode":"41000;41000",
    "addr:street":"Rue Andre\u0301 Boulle",
    "iso:country":"FR",
    "sg:address":"38, Rue Andr\u00e9 Boulle, 41000 Blois",
    "sg:city":"Blois",
    "sg:orig_category":"Non-Classified Establishments",
    "sg:phone":"+33 2 54 78 76 75",
    "sg:postcode":"41000",
    "sg:province":"Centre",
    "wof:name":"P.e.b. S.a.",
    "wof:placetype":"venue"
},
  "geometry": {"coordinates":[1.318878,47.607815],"type":"Point"}
}