{
  "type": "Feature",
  "properties": {
    "addr:full":"93 Bis Rue Du Billemont 59223 Roncq Nord Pas-de-Calais 59223",
    "addr:housenumber":"93 bis",
    "addr:postcode":"59223;59223",
    "addr:street":"Rue Du Billemont",
    "iso:country":"FR",
    "sg:address":"93 Bis Rue Du Billemont 59223 Roncq",
    "sg:classifiers":[
        {
            "category":"Shopping",
            "type":"Retail Goods"
        }
    ],
    "sg:phone":"+33 3 20 03 61 95",
    "sg:postcode":"59223",
    "sg:province":"Nord Pas-de-Calais",
    "sg:tags":[
        "metallurgy",
        "finished",
        "-",
        "metalworking",
        "metallic"
    ],
    "wof:name":"Ferronnerie Roncquoise Sarl",
    "wof:placetype":"venue"
},
  "geometry": {"coordinates":[3.12884,50.757683],"type":"Point"}
}