{
  "type": "Feature",
  "properties": {
    "addr:full":"70, Rue de la Briderie - Le Clos de la Briderie , 41150 Monteaux Monteaux Centre 41150",
    "addr:housenumber":"70;monteaux",
    "addr:postcode":"41150;41150",
    "addr:street":"Rue De La Briderie Le;De;Briderie",
    "iso:country":"FR",
    "sg:address":"70, Rue de la Briderie - Le Clos de la Briderie , 41150 Monteaux",
    "sg:city":"Monteaux",
    "sg:orig_category":"Unclassifiable Establishments",
    "sg:phone":"+33 2 54 70 28 89",
    "sg:postcode":"41150",
    "sg:province":"Centre",
    "wof:name":"Scea Clos De La Briderie",
    "wof:placetype":"venue"
},
  "geometry": {"coordinates":[1.132808,47.455837],"type":"Point"}
}