{
  "type": "Feature",
  "properties": {
    "addr:full":"4, Rue du Parc - Oberhausbergen , 67088 Strasbourg Alsace",
    "addr:housenumber":"4",
    "addr:postcode":"67088",
    "addr:street":"Rue Du Parc",
    "iso:country":"FR",
    "sg:address":"4, Rue du Parc - Oberhausbergen , 67088 Strasbourg",
    "sg:orig_category":"Unclassifiable Establishments",
    "sg:phone":"+33 3 88 56 84 84",
    "sg:province":"Alsace",
    "wof:name":"Bureau Veritas C.e.p. S.a. - Contr\u00f4le Et Pr\u00e9vention",
    "wof:placetype":"venue"
},
  "geometry": {"coordinates":[7.74983,48.58176],"type":"Point"}
}