{
  "type": "Feature",
  "properties": {
    "iso:country":"FR",
    "sg:address":"4, Rue de Courtalain, 28290 Ch\u00e2tillon en Dunois",
    "sg:city":"Courtalain",
    "sg:orig_category":"Unclassifiable Establishments",
    "sg:phone":"+33 2 37 97 50 50",
    "sg:postcode":"28290",
    "sg:province":"Centre",
    "wof:name":"H\u00e9lios Marketing S.a.r.l.",
    "wof:placetype":"venue"
},
  "geometry": {"coordinates":[1.183225,48.114021],"type":"Point"}
}