{
  "type": "Feature",
  "properties": {
    "addr:full":"B.P. 61, 56120 Gu\u00e9gon^^ZI Croix Blanche, 56120 Gu\u00e9gon Gu\u00e9gon Bretagne 56120",
    "addr:postcode":"56120;56120;56120",
    "addr:street":"B.P. 61;Gue\u0301Gon",
    "iso:country":"FR",
    "sg:address":"B.P. 61, 56120 Gu\u00e9gon^^ZI Croix Blanche, 56120 Gu\u00e9gon",
    "sg:city":"Gu\u00e9gon",
    "sg:orig_category":"Non-Classified Establishments",
    "sg:phone":"+33 2 97 22 24 52",
    "sg:postcode":"56120",
    "sg:province":"Bretagne",
    "wof:name":"Polarcup Containers S.a.",
    "wof:placetype":"venue"
},
  "geometry": {"coordinates":[-2.545152,47.900028],"type":"Point"}
}