{
  "type": "Feature",
  "properties": {
    "addr:full":"Ld Champ Grillet 69650 Quincieux Rhone-Alpes 69650",
    "addr:postcode":"69650;69650",
    "addr:street":"Ld Champ Grillet;Rhone-Alpes",
    "iso:country":"FR",
    "sg:address":"Ld Champ Grillet 69650 Quincieux",
    "sg:classifiers":[
        {
            "category":"Manufacturing",
            "subcategory":"Motor Vehicles & Parts",
            "type":"Manufacturing & Wholesale Goods"
        }
    ],
    "sg:phone":"+33 4 78 91 10 10",
    "sg:postcode":"69650",
    "sg:province":"Rhone-Alpes",
    "sg:tags":[
        "engine",
        "machine",
        "engineering",
        "-",
        "mechanical"
    ],
    "wof:name":"Sapaic Industrie Sa",
    "wof:placetype":"venue"
},
  "geometry": {"coordinates":[4.779843,45.904675],"type":"Point"}
}