{
  "type": "Feature",
  "properties": {
    "addr:full":"85, Impasse de l'Enclume - Le Biollay , 74400 Chamonix Mont Blanc Rhone-Alpes 74400",
    "addr:housenumber":"85",
    "addr:postcode":"74400;74400",
    "addr:street":"Impasse De L'Enclume Le Biollay;Mont;Rhone-Alpes",
    "iso:country":"FR",
    "sg:address":"85, Impasse de l'Enclume - Le Biollay , 74400 Chamonix Mont Blanc",
    "sg:orig_category":"Unclassifiable Establishments",
    "sg:phone":"+33 4 50 53 13 56",
    "sg:postcode":"74400",
    "sg:province":"Rhone-Alpes",
    "wof:name":"Pianfetti A. Et Fils",
    "wof:placetype":"venue"
},
  "geometry": {"coordinates":[6.876555,45.923561],"type":"Point"}
}