{
  "type": "Feature",
  "properties": {
    "iso:country":"FR",
    "sg:address":"Chem Monument 70230 Larians Et Munans",
    "sg:classifiers":[
        {
            "category":"Manufacturing",
            "subcategory":"Metals",
            "type":"Manufacturing & Wholesale Goods"
        }
    ],
    "sg:phone":"+33 3 81 86 18 79",
    "sg:postcode":"70230",
    "sg:province":"Franche Comt\u00e9",
    "sg:tags":[
        "metallurgy",
        "steel",
        "metalworking"
    ],
    "wof:name":"Fonderie De Treveray Sa",
    "wof:placetype":"venue"
},
  "geometry": {"coordinates":[6.230515,47.509766],"type":"Point"}
}