{
  "type": "Feature",
  "properties": {
    "addr:full":"122 Avenue Michel Baroin 10800 St Julien Les Villas Champagne 10800",
    "addr:housenumber":"122",
    "addr:postcode":"10800 st julien;10800",
    "addr:street":"Avenue Michel Baroin;Les Villas",
    "iso:country":"FR",
    "sg:address":"122 Avenue Michel Baroin 10800 St Julien Les Villas",
    "sg:classifiers":[
        {
            "category":"Professional",
            "subcategory":"Engineering",
            "type":"Services"
        }
    ],
    "sg:phone":"+33 3 25 75 19 66",
    "sg:postcode":"10800",
    "sg:province":"Champagne",
    "sg:tags":[
        "machine",
        "-",
        "mechanical"
    ],
    "wof:name":"Albaret Froid Climatisation",
    "wof:placetype":"venue"
},
  "geometry": {"coordinates":[4.094681,48.28091],"type":"Point"}
}