{
  "type": "Feature",
  "properties": {
    "iso:country":"FR",
    "sg:address":"53, Rue de F\u00e8re, 02400 Ch\u00e2teau Thierry",
    "sg:orig_category":"Non-Classified Establishments",
    "sg:phone":"+33 3 23 69 09 38",
    "sg:province":"Picardie",
    "wof:name":"Plantin Et Fils S.a.r.l.",
    "wof:placetype":"venue"
},
  "geometry": {"coordinates":[3.404796,49.048862],"type":"Point"}
}