{
  "type": "Feature",
  "properties": {
    "addr:full":"44 Rue Du Jura 94150 Rungis Ile de France 94150",
    "addr:housenumber":"44",
    "addr:postcode":"94150;94150",
    "addr:street":"Rue Du Jura",
    "iso:country":"FR",
    "sg:address":"44 Rue Du Jura 94150 Rungis",
    "sg:classifiers":[
        {
            "category":"Professional",
            "subcategory":"Engineering",
            "type":"Services"
        }
    ],
    "sg:phone":"+33 1 46 87 36 96",
    "sg:postcode":"94150",
    "sg:province":"Ile de France",
    "sg:tags":[
        "machine",
        "-",
        "mechanical"
    ],
    "wof:name":"Service De Maintenance Et D'inst En Froid Coml Et Indl (smi Fci)",
    "wof:placetype":"venue"
},
  "geometry": {"coordinates":[2.34974,48.743351],"type":"Point"}
}