{
  "type": "Feature",
  "properties": {
    "iso:country":"FR",
    "sg:address":"3, Rue Silo, 02420 Vendhuile",
    "sg:orig_category":"Non-Classified Establishments",
    "sg:phone":"+33 3 23 66 26 65",
    "sg:province":"Picardie",
    "wof:name":"Furcot S.a.r.l.",
    "wof:placetype":"venue"
},
  "geometry": {"coordinates":[3.210995,50.012466],"type":"Point"}
}