{
  "type": "Feature",
  "properties": {
    "iso:country":"FR",
    "sg:address":"ZAC des Peyrades",
    "sg:city":"Saint Just Saint Rambert",
    "sg:orig_category":"Unclassifiable Establishments",
    "sg:phone":"+33 4 77 02 12 12",
    "sg:postcode":"42170",
    "sg:province":"Rhone-Alpes",
    "wof:name":"Etablissements Linossier S.a.",
    "wof:placetype":"venue"
},
  "geometry": {"coordinates":[4.24036,45.49968],"type":"Point"}
}