{
  "type": "Feature",
  "properties": {
    "addr:full":"Canteloup Est 33340 Blaignan Blaignan Aquitaine 33340",
    "addr:postcode":"33340;33340",
    "addr:street":"Canteloup",
    "iso:country":"FR",
    "sg:address":"Canteloup Est 33340 Blaignan",
    "sg:city":"Blaignan",
    "sg:classifiers":[
        {
            "category":"Food Court",
            "type":"Food & Drink"
        }
    ],
    "sg:phone":"+33 5 56 09 01 22",
    "sg:postcode":"33340",
    "sg:province":"Aquitaine",
    "sg:tags":[
        "product",
        "related"
    ],
    "wof:name":"Ch\u00c2teau La Gorce Scea",
    "wof:placetype":"venue"
},
  "geometry": {"coordinates":[-0.886212,45.2724],"type":"Point"}
}