{
  "type": "Feature",
  "properties": {
    "addr:full":"route de Lavaur 81300 Graulhet Midi Pyr\u00e9n\u00e9es 81300",
    "addr:postcode":"81300;81300",
    "addr:street":"Route De Lavaur",
    "iso:country":"FR",
    "sg:address":"route de Lavaur 81300 Graulhet",
    "sg:classifiers":[
        {
            "category":"Banks & Credit Unions",
            "subcategory":"Investment Brokerage",
            "type":"Services"
        }
    ],
    "sg:phone":"+33 5 63 42 81 81",
    "sg:postcode":"81300",
    "sg:province":"Midi Pyr\u00e9n\u00e9es",
    "sg:tags":[
        "garment",
        "industry",
        "finisher",
        "form"
    ],
    "wof:name":"Saric Sa",
    "wof:placetype":"venue"
},
  "geometry": {"coordinates":[1.948225,43.754921],"type":"Point"}
}