{
  "type": "Feature",
  "properties": {
    "addr:full":"8 Rue Ad\u00e9le Riton 67000 Strasbourg Strasbourg Alsace 67000",
    "addr:housenumber":"8",
    "addr:postcode":"67000;67000",
    "addr:street":"Rue Ade\u0301Le Riton",
    "iso:country":"FR",
    "sg:address":"8 Rue Ad\u00e9le Riton 67000 Strasbourg",
    "sg:city":"Strasbourg",
    "sg:classifiers":[
        {
            "category":"Wholesale",
            "subcategory":"Machinery & Supplies",
            "type":"Manufacturing & Wholesale Goods"
        }
    ],
    "sg:phone":"+33 3 88 15 21 50",
    "sg:postcode":"67000",
    "sg:province":"Alsace",
    "sg:tags":[
        "handling",
        "material",
        "-",
        "machine",
        "equipment",
        "engineering",
        "mechanical"
    ],
    "wof:name":"Ascenseurs Kone",
    "wof:placetype":"venue"
},
  "geometry": {"coordinates":[7.740172,48.590965],"type":"Point"}
}