{
  "type": "Feature",
  "properties": {
    "addr:full":"Route Paisson 89740 Cruzy Le Ch\u00e2tel Arthonnay Bourgogne 89740",
    "addr:postcode":"89740;89740",
    "addr:street":"Route Paisson",
    "iso:country":"FR",
    "sg:address":"Route Paisson 89740 Cruzy Le Ch\u00e2tel",
    "sg:city":"Arthonnay",
    "sg:classifiers":[
        {
            "category":"Wholesale",
            "subcategory":"Farm Supplies",
            "type":"Manufacturing & Wholesale Goods"
        }
    ],
    "sg:phone":"+33 3 86 75 20 98",
    "sg:postcode":"89740",
    "sg:province":"Bourgogne",
    "sg:tags":[
        "-",
        "machine",
        "equipment",
        "engineering",
        "machinery",
        "mechanical",
        "agriculture"
    ],
    "wof:name":"Lucas Et Fils Sarl",
    "wof:placetype":"venue"
},
  "geometry": {"coordinates":[4.2176,47.856541],"type":"Point"}
}