{
  "type": "Feature",
  "properties": {
    "addr:full":"ZI des No\u00ebs Montoir de Bretagne Pays de Loire 44550",
    "addr:postcode":"44550",
    "addr:street":"Des Noe\u0308S;De Bretagne",
    "iso:country":"FR",
    "sg:address":"ZI des No\u00ebs",
    "sg:city":"Montoir de Bretagne",
    "sg:orig_category":"Unclassifiable Establishments",
    "sg:phone":"+33 2 40 45 11 47",
    "sg:postcode":"44550",
    "sg:province":"Pays de Loire",
    "wof:name":"Entreprise Philippe Lassarat S.a.",
    "wof:placetype":"venue"
},
  "geometry": {"coordinates":[-2.153179,47.327759],"type":"Point"}
}