{
  "type": "Feature",
  "properties": {
    "iso:country":"FR",
    "sg:address":"59 rue de l'Ill 67390 OHNENHEIM",
    "sg:city":"Ohnenheim",
    "sg:classifiers":[
        {
            "category":"Retail",
            "subcategory":"Car Wash",
            "type":"Services"
        }
    ],
    "sg:phone":"+33 3 88 92 50 75",
    "sg:postcode":"67390",
    "sg:province":"Alsace",
    "sg:tags":[
        "transportation",
        "special"
    ],
    "wof:name":"Flecher Voyages Sarl",
    "wof:placetype":"venue"
},
  "geometry": {"coordinates":[7.507288,48.183781],"type":"Point"}
}