{
  "type": "Feature",
  "properties": {
    "iso:country":"FR",
    "sg:address":"Zi De Kervidanou 1 29300 Quimperle",
    "sg:city":"Quimperl\u00e9",
    "sg:classifiers":[
        {
            "category":"Shopping",
            "subcategory":"Computers & Home Electronics",
            "type":"Retail Goods"
        }
    ],
    "sg:phone":"+33 2 98 39 00 71",
    "sg:postcode":"29300",
    "sg:province":"Bretagne",
    "sg:tags":[
        "electric",
        "electricity",
        "component",
        "equipment",
        "electrical",
        "electronic"
    ],
    "wof:name":"Societe Bellion",
    "wof:placetype":"venue"
},
  "geometry": {"coordinates":[-3.548564,47.883514],"type":"Point"}
}