{
  "type": "Feature",
  "properties": {
    "addr:full":"9 R Du Bois Sauvage BP 234 Les Rives De Seine C 91007 Evry Cedex Poitou-Charentes",
    "addr:housenumber":"9;234;c",
    "addr:postcode":"91007;cedex",
    "addr:street":"R Du Bois Sauvage Bp;Les Rives De Seine",
    "iso:country":"FR",
    "sg:address":"9 R Du Bois Sauvage BP 234 Les Rives De Seine",
    "sg:city":"C 91007 Evry Cedex",
    "sg:classifiers":[
        {
            "category":"Utilities",
            "subcategory":"Electric",
            "type":"Services"
        }
    ],
    "sg:phone":"+33 1 60 87 40 30",
    "sg:province":"Poitou-Charentes",
    "sg:tags":[
        "electricity",
        "electronic",
        "electrical",
        "equipment"
    ],
    "wof:name":"Sdel Iris",
    "wof:placetype":"venue"
},
  "geometry": {"coordinates":[2.4293,48.624664],"type":"Point"}
}