{
  "type": "Feature",
  "properties": {
    "addr:full":"B.P. 10532, 95702 Roissy Charles de Gaulle C\u00e9dex^^4, Derri\u00e8re la Dime, 95700 Roissy en France Ile de France",
    "addr:housenumber":"10532",
    "addr:postcode":"95702;95700",
    "addr:street":"Derrie\u0300Re La Dime",
    "iso:country":"FR",
    "sg:address":"B.P. 10532, 95702 Roissy Charles de Gaulle C\u00e9dex^^4, Derri\u00e8re la Dime, 95700 Roissy en France",
    "sg:orig_category":"Non-Classified Establishments",
    "sg:phone":"+33 1 48 62 43 22",
    "sg:province":"Ile de France",
    "wof:name":"S.w. Air Freight S.a.",
    "wof:placetype":"venue"
},
  "geometry": {"coordinates":[2.517005,49.003883],"type":"Point"}
}