{
  "type": "Feature",
  "properties": {
    "addr:full":"5, Rue Nungesser, 94120 Fontenay sous Bois Ile de France",
    "addr:housenumber":"5",
    "addr:postcode":"94120",
    "addr:street":"Rue Nungesser;Bois Ile De France",
    "iso:country":"FR",
    "sg:address":"5, Rue Nungesser, 94120 Fontenay sous Bois",
    "sg:orig_category":"Non-Classified Establishments",
    "sg:phone":"+33 1 48 75 62 00",
    "sg:province":"Ile de France",
    "wof:name":"La Renaissance S.a.",
    "wof:placetype":"venue"
},
  "geometry": {"coordinates":[2.448584,48.851723],"type":"Point"}
}