{
  "type": "Feature",
  "properties": {
    "addr:full":"1, Place du March\u00e9, 87500 Saint Yrieix la Perche Limousin",
    "addr:housenumber":"1",
    "addr:postcode":"87500",
    "addr:street":"Place Du Marche\u0301",
    "iso:country":"FR",
    "sg:address":"1, Place du March\u00e9, 87500 Saint Yrieix la Perche",
    "sg:orig_category":"Unclassifiable Establishments",
    "sg:phone":"+33 5 55 75 91 25",
    "sg:province":"Limousin",
    "wof:name":"Aredius-net Informatique",
    "wof:placetype":"venue"
},
  "geometry": {"coordinates":[1.200962,45.514477],"type":"Point"}
}