{
  "type": "Feature",
  "properties": {
    "addr:full":"Gu\u00e9rin 35370 Argentr\u00e9 du Plessis Argentr\u00e9-du-Plessis Bretagne 35370",
    "addr:postcode":"35370;35370",
    "addr:street":"Gue\u0301Rin;Argentre\u0301-Du-Plessis Bretagne",
    "iso:country":"FR",
    "sg:address":"Gu\u00e9rin 35370 Argentr\u00e9 du Plessis",
    "sg:city":"Argentr\u00e9-du-Plessis",
    "sg:orig_category":"Non-Classified Establishments",
    "sg:phone":"+33 2 99 96 72 54",
    "sg:postcode":"35370",
    "sg:province":"Bretagne",
    "wof:name":"Frigelait S.a.",
    "wof:placetype":"venue"
},
  "geometry": {"coordinates":[-1.168524,48.032394],"type":"Point"}
}