{
  "type": "Feature",
  "properties": {
    "addr:full":"113, Bd Stalingrad, 69100 Villeurbanne Rhone-Alpes 69100",
    "addr:housenumber":"113",
    "addr:postcode":"69100;69100",
    "addr:street":"Bd Stalingrad",
    "iso:country":"FR",
    "sg:address":"113, Bd Stalingrad, 69100 Villeurbanne",
    "sg:orig_category":"Unclassifiable Establishments",
    "sg:phone":"+33 4 72 82 02 00",
    "sg:postcode":"69100",
    "sg:province":"Rhone-Alpes",
    "wof:name":"Pereire Conseil Rh\u00f4ne Alpes S.a.r.l.",
    "wof:placetype":"venue"
},
  "geometry": {"coordinates":[4.858967,45.772579],"type":"Point"}
}