{
  "type": "Feature",
  "properties": {
    "iso:country":"FR",
    "sg:address":"9 B Rue Augustin Fresnel 37170 Chambray Les Tours",
    "sg:city":"Chambray-l\u00e8s-Tours",
    "sg:classifiers":[
        {
            "category":"Professional",
            "subcategory":"Business Services",
            "type":"Services"
        }
    ],
    "sg:phone":"+33 2 47 28 30 02",
    "sg:postcode":"37170",
    "sg:province":"Centre",
    "sg:tags":[
        "body",
        "advice"
    ],
    "wof:name":"Ste D Editions Et De Publications Agricoles De (sepat)",
    "wof:placetype":"venue"
},
  "geometry": {"coordinates":[0.728726,47.342983],"type":"Point"}
}