{
  "type": "Feature",
  "properties": {
    "addr:full":"71, Av. de la R\u00e9publique, 44600 Saint Nazaire Pays de Loire 44600",
    "addr:postcode":"44600;44600",
    "addr:street":"71 Av. De La Re\u0301Publique;Nazaire",
    "iso:country":"FR",
    "sg:address":"71, Av. de la R\u00e9publique, 44600 Saint Nazaire",
    "sg:orig_category":"Non-Classified Establishments",
    "sg:phone":"+33 2 40 00 71 71",
    "sg:postcode":"44600",
    "sg:province":"Pays de Loire",
    "wof:name":"Caisse D'epargne Pr\u00e9voyance De La Loire",
    "wof:placetype":"venue"
},
  "geometry": {"coordinates":[-2.212562,47.279591],"type":"Point"}
}