{
  "type": "Feature",
  "properties": {
    "addr:full":"Z I 28290 ARROU Arrou Centre 28290",
    "addr:housenumber":"arrou",
    "addr:postcode":"28290;28290",
    "addr:street":"Z",
    "iso:country":"FR",
    "sg:address":"Z I 28290 ARROU",
    "sg:city":"Arrou",
    "sg:classifiers":[
        {
            "category":"Manufacturing",
            "subcategory":"Motor Vehicles & Parts",
            "type":"Manufacturing & Wholesale Goods"
        }
    ],
    "sg:phone":"+33 2 37 44 65 60",
    "sg:postcode":"28290",
    "sg:province":"Centre",
    "sg:tags":[
        "precision",
        "mechanic"
    ],
    "wof:name":"Gavard Et Cie S.a.",
    "wof:placetype":"venue"
},
  "geometry": {"coordinates":[1.142689,48.072193],"type":"Point"}
}