{
  "type": "Feature",
  "properties": {
    "addr:full":"15, Av. du Pr\u00e9 de Challes - P.A.E. des Glaisins, 74940 Annecy le Vieux Rhone-Alpes",
    "addr:postcode":"74940",
    "addr:street":"15 Av. Du Pre\u0301 De Challes P.A.E. Des Glaisins",
    "iso:country":"FR",
    "sg:address":"15, Av. du Pr\u00e9 de Challes - P.A.E. des Glaisins, 74940 Annecy le Vieux",
    "sg:orig_category":"Unclassifiable Establishments",
    "sg:phone":"+33 4 50 64 00 57",
    "sg:province":"Rhone-Alpes",
    "wof:name":"Oleodyne S.a.",
    "wof:placetype":"venue"
},
  "geometry": {"coordinates":[6.142605,45.919136],"type":"Point"}
}