{
  "type": "Feature",
  "properties": {
    "addr:full":"05300 Le Po\u00ebt",
    "addr:postcode":"05300",
    "iso:country":"FR",
    "sg:address":"05300 Le Po\u00ebt",
    "sg:orig_category":"Unclassifiable Establishments",
    "sg:phone":"+33 4 92 65 72 08",
    "wof:name":"Welco Industries S.a.r.l.",
    "wof:placetype":"venue"
},
  "geometry": {"coordinates":[5.897192,44.292019],"type":"Point"}
}