{
  "type": "Feature",
  "properties": {
    "addr:full":"92, Rue Jean-Baptiste Dumas, 59160 Lomme Nord Pas-de-Calais",
    "addr:housenumber":"92",
    "addr:postcode":"59160",
    "addr:street":"Rue Jean-Baptiste Dumas",
    "iso:country":"FR",
    "sg:address":"92, Rue Jean-Baptiste Dumas, 59160 Lomme",
    "sg:orig_category":"Unclassifiable Establishments",
    "sg:phone":"+33 3 20 22 89 40",
    "sg:province":"Nord Pas-de-Calais",
    "wof:name":"S.p.i. S.a.r.l. - Soci\u00e9t\u00e9 De Peintures Industrielles",
    "wof:placetype":"venue"
},
  "geometry": {"coordinates":[3.006891,50.627857],"type":"Point"}
}