{
  "type": "Feature",
  "properties": {
    "iso:country":"FR",
    "sg:address":"ZI de Naudon",
    "sg:city":"Carbonne",
    "sg:orig_category":"Non-Classified Establishments",
    "sg:phone":"+33 5 61 87 62 25",
    "sg:postcode":"31390",
    "sg:province":"Midi Pyr\u00e9n\u00e9es",
    "wof:name":"Transports Pedussaud S.a.",
    "wof:placetype":"venue"
},
  "geometry": {"coordinates":[1.22642,43.293919],"type":"Point"}
}