{
  "type": "Feature",
  "properties": {
    "iso:country":"FR",
    "sg:address":"RN 7 - La Petite Calade",
    "sg:city":"Puyricard",
    "sg:orig_category":"Unclassifiable Establishments",
    "sg:phone":"+33 4 42 96 64 88",
    "sg:postcode":"13540",
    "sg:province":"Provence-Alpes-C\u00f4te d'Azur",
    "wof:name":"Confit De Provence S.a.s.",
    "wof:placetype":"venue"
},
  "geometry": {"coordinates":[5.421925,43.582729],"type":"Point"}
}