{
  "type": "Feature",
  "properties": {
    "addr:full":"1, Rtedu Somport, 64400 Gurmen\u00e7on Gurmen\u00e7on Aquitaine 64400",
    "addr:housenumber":"1",
    "addr:postcode":"64400;64400",
    "addr:street":"Rtedu Somport",
    "iso:country":"FR",
    "sg:address":"1, Rtedu Somport, 64400 Gurmen\u00e7on",
    "sg:city":"Gurmen\u00e7on",
    "sg:orig_category":"Unclassifiable Establishments",
    "sg:phone":"+33 5 59 36 36 36",
    "sg:postcode":"64400",
    "sg:province":"Aquitaine",
    "wof:name":"M.m.p. S.a. - Micro M\u00e9canique Pyr\u00e9n\u00e9ennes",
    "wof:placetype":"venue"
},
  "geometry": {"coordinates":[-0.60187,43.167892],"type":"Point"}
}