{
  "type": "Feature",
  "properties": {
    "addr:full":"Zone Commerciale des Arcades Chavagnes en Paillers Pays de Loire 85250",
    "addr:postcode":"85250",
    "addr:street":"Zone Commerciale Des Arcades Chavagnes",
    "iso:country":"FR",
    "sg:address":"Zone Commerciale des Arcades",
    "sg:city":"Chavagnes en Paillers",
    "sg:orig_category":"Unclassifiable Establishments",
    "sg:phone":"+33 2 51 42 25 13",
    "sg:postcode":"85250",
    "sg:province":"Pays de Loire",
    "wof:name":"D\u00e9fiweb S.a.r.l.",
    "wof:placetype":"venue"
},
  "geometry": {"coordinates":[-1.250884,46.893082],"type":"Point"}
}