{
  "type": "Feature",
  "properties": {
    "iso:country":"FR",
    "sg:address":"30 rue Paul Bert 93370 Montfermeil",
    "sg:classifiers":[
        {
            "category":"Shopping",
            "subcategory":"Computers & Home Electronics",
            "type":"Retail Goods"
        }
    ],
    "sg:phone":"+33 1 43 30 43 39",
    "sg:postcode":"93370",
    "sg:province":"Ile de France",
    "sg:tags":[
        "digital"
    ],
    "wof:name":"M.e.m. S.a.",
    "wof:placetype":"venue"
},
  "geometry": {"coordinates":[2.565442,48.901974],"type":"Point"}
}