{
  "type": "Feature",
  "properties": {
    "iso:country":"FR",
    "sg:address":"16, Rue de Hohengoeft, 67310 Wasselonne",
    "sg:city":"Hohengoeft",
    "sg:orig_category":"Non-Classified Establishments",
    "sg:phone":"+33 3 88 87 04 36",
    "sg:postcode":"67310",
    "sg:province":"Alsace",
    "wof:name":"Roenfanz Martzolff S.a.r.l.",
    "wof:placetype":"venue"
},
  "geometry": {"coordinates":[7.450017,48.638985],"type":"Point"}
}