{
  "type": "Feature",
  "properties": {
    "addr:full":"Av Robert Schuman; Reims; 51100 Champagne 51100",
    "addr:postcode":"51100;51100",
    "addr:street":"Av Robert Schuman",
    "iso:country":"FR",
    "sg:address":"Av Robert Schuman; Reims; 51100",
    "sg:classifiers":[
        {
            "category":"Banks & Credit Unions",
            "subcategory":"Bank",
            "type":"Services"
        }
    ],
    "sg:phone":"+33 26483680",
    "sg:postcode":"51100",
    "sg:province":"Champagne",
    "wof:name":"Cr\u00e9dit Commercial De France (ccf)",
    "wof:placetype":"venue"
},
  "geometry": {"coordinates":[4.01268,49.231846],"type":"Point"}
}