{
  "type": "Feature",
  "properties": {
    "addr:full":"Rue Pierre Martin - ZI de l'Inqu\u00e9trie Saint Martin Boulogne Nord Pas-de-Calais 62280",
    "addr:postcode":"62280",
    "addr:street":"Rue Pierre Martin Zi De L'Inque \u0301Trie",
    "iso:country":"FR",
    "sg:address":"Rue Pierre Martin - ZI de l'Inqu\u00e9trie",
    "sg:city":"Saint Martin Boulogne",
    "sg:orig_category":"Unclassifiable Establishments",
    "sg:phone":"+33 3 21 87 78 78",
    "sg:postcode":"62280",
    "sg:province":"Nord Pas-de-Calais",
    "wof:name":"Soci\u00e9t\u00e9 D'exploitation Pg S.a.",
    "wof:placetype":"venue"
},
  "geometry": {"coordinates":[1.662667,50.730118],"type":"Point"}
}