{
  "type": "Feature",
  "properties": {
    "addr:full":"48 blvd de Strasbourg; Aulnay sous Bois; 93600 Ile de France 93600",
    "addr:postcode":"93600 ile;france 93600",
    "addr:street":"48 Blvd De Strasbourg",
    "iso:country":"FR",
    "sg:address":"48 blvd de Strasbourg; Aulnay sous Bois; 93600",
    "sg:classifiers":[
        {
            "category":"Banks & Credit Unions",
            "subcategory":"Bank",
            "type":"Services"
        }
    ],
    "sg:phone":"+33 3348699397",
    "sg:postcode":"93600",
    "sg:province":"Ile de France",
    "wof:name":"Caixa G\u00e9ral, De Depositos Sa",
    "wof:placetype":"venue"
},
  "geometry": {"coordinates":[2.489879,48.927406],"type":"Point"}
}