{
  "type": "Feature",
  "properties": {
    "addr:full":"Domaine du Bourrian 83580 Gassin Centre",
    "addr:postcode":"83580",
    "addr:street":"Domaine;Gassin",
    "iso:country":"FR",
    "sg:address":"Domaine du Bourrian 83580 Gassin",
    "sg:orig_category":"Non-Classified Establishments",
    "sg:phone":"+33 4 94 56 16 28",
    "sg:province":"Centre",
    "wof:name":"Domaine Du Bourrian S.a.r.l.",
    "wof:placetype":"venue"
},
  "geometry": {"coordinates":[6.58701,43.254913],"type":"Point"}
}