{
  "type": "Feature",
  "properties": {
    "addr:full":"36 Avenue De Bobigny 93135 Noisy Le Sec Bobigny Ile de France 93000",
    "addr:housenumber":"36",
    "addr:postcode":"93135;93000",
    "addr:street":"Avenue De Bobigny",
    "iso:country":"FR",
    "sg:address":"36 Avenue De Bobigny 93135 Noisy Le Sec",
    "sg:city":"Bobigny",
    "sg:classifiers":[
        {
            "category":"Manufacturing",
            "subcategory":"Metals",
            "type":"Manufacturing & Wholesale Goods"
        }
    ],
    "sg:phone":"+33 1 48 10 32 40",
    "sg:postcode":"93000",
    "sg:province":"Ile de France",
    "sg:tags":[
        "-",
        "machine",
        "equipment",
        "engineering",
        "machinery",
        "mechanical"
    ],
    "wof:name":"Chaland Et Fils",
    "wof:placetype":"venue"
},
  "geometry": {"coordinates":[1.99499,46.045448],"type":"Point"}
}