{
  "type": "Feature",
  "properties": {
    "iso:country":"FR",
    "sg:address":"4, Rte de Paray, 91320 Wissous",
    "sg:orig_category":"Unclassifiable Establishments",
    "sg:phone":"+33 1 60 11 16 69",
    "sg:province":"Ile de France",
    "wof:name":"Eris Technique S.a.r.l.",
    "wof:placetype":"venue"
},
  "geometry": {"coordinates":[2.332674,48.727962],"type":"Point"}
}