{
  "type": "Feature",
  "properties": {
    "iso:country":"FR",
    "sg:address":"6, Rue du Rh\u00f4ne, 90000 Belfort",
    "sg:orig_category":"Non-Classified Establishments",
    "sg:phone":"+33 3 84 46 60 40",
    "sg:province":"Franche Comt\u00e9",
    "wof:name":"Klinos",
    "wof:placetype":"venue"
},
  "geometry": {"coordinates":[6.85846,47.629223],"type":"Point"}
}