{
  "type": "Feature",
  "properties": {
    "iso:country":"FR",
    "sg:address":"8, Av. du Qu\u00e9bec - Les Ulis , 91951 Courtaboeuf C\u00e9dex",
    "sg:orig_category":"Non-Classified Establishments",
    "sg:phone":"+33 1 69 18 93 93",
    "sg:province":"Quebec",
    "wof:name":"S.f.s.c. S.a. - Soci\u00e9t\u00e9 Fran\u00e7aise S\u00e9curit\u00e9 Et De Conseil",
    "wof:placetype":"venue"
},
  "geometry": {"coordinates":[-68.42929100000001,53.890121],"type":"Point"}
}