{
  "type": "Feature",
  "properties": {
    "iso:country":"FR",
    "sg:address":"18bis, Av Jean Jaur\u00e8s, 51100 Reims",
    "sg:orig_category":"Non-Classified Establishments",
    "sg:phone":"+33 3 26 40 61 68",
    "sg:province":"Champagne",
    "wof:name":"Jourdan Fr\u00e8res S.a.r.l.",
    "wof:placetype":"venue"
},
  "geometry": {"coordinates":[4.041036,49.257992],"type":"Point"}
}