{
  "type": "Feature",
  "properties": {
    "iso:country":"FR",
    "sg:address":"13, Cours Valmy - Immeuble Pacific, 92070 Paris La D\u00e9fense",
    "sg:orig_category":"Unclassifiable Establishments",
    "sg:phone":"+33 1 41 25 60 20",
    "sg:province":"\u00cele-de-France",
    "wof:name":"Ugine S.a.",
    "wof:placetype":"venue"
},
  "geometry": {"coordinates":[2.23153,48.892799],"type":"Point"}
}