{
  "type": "Feature",
  "properties": {
    "iso:country":"FR",
    "sg:address":"539 Rue Du Fbg Bannier 45770 Saran",
    "sg:city":"Saran",
    "sg:classifiers":[
        {
            "category":"Autos & Motor Vehicles",
            "subcategory":"Automobile Sales",
            "type":"Retail Goods"
        }
    ],
    "sg:phone":"+33 2 38 43 36 42",
    "sg:postcode":"45770",
    "sg:province":"Centre",
    "sg:tags":[
        "equipment",
        "motor-cars",
        "transport"
    ],
    "wof:name":"Renault France Automobiles (rfa)",
    "wof:placetype":"venue"
},
  "geometry": {"coordinates":[1.89393,47.937786],"type":"Point"}
}