{
  "type": "Feature",
  "properties": {
    "iso:country":"FR",
    "sg:address":"B.P. 74033, 25071 Besan\u00e7on C\u00e9dex 9^^17, Rue Auguste Jouchoux - ZI, 25000 Besan\u00e7on",
    "sg:orig_category":"Non-Classified Establishments",
    "sg:phone":"+33 3 81 53 81 14",
    "sg:province":"Franche Comt\u00e9",
    "wof:name":"Lu S.a.",
    "wof:placetype":"venue"
},
  "geometry": {"coordinates":[6.025686,47.242317],"type":"Point"}
}