{
  "type": "Feature",
  "properties": {
    "addr:full":"21 Rue Gutenberg 57207 Sarreguemines Cedex Berg Alsace 67320",
    "addr:housenumber":"21",
    "addr:postcode":"57207;cedex;67320",
    "addr:street":"Rue Gutenberg;Berg",
    "iso:country":"FR",
    "sg:address":"21 Rue Gutenberg 57207 Sarreguemines Cedex",
    "sg:city":"Berg",
    "sg:classifiers":[
        {
            "category":"Government",
            "subcategory":"Department Of Motor Vehicles",
            "type":"Public Place"
        }
    ],
    "sg:phone":"+33 3 87 95 02 55",
    "sg:postcode":"67320",
    "sg:province":"Alsace",
    "sg:tags":[
        "equipment",
        "industrial",
        "transport",
        "motor-cars"
    ],
    "wof:name":"Ghibaudi France Sarl",
    "wof:placetype":"venue"
},
  "geometry": {"coordinates":[7.094862,49.110191],"type":"Point"}
}