{
  "type": "Feature",
  "properties": {
    "addr:full":"6 R Du Buiron 59970 Odomez Nord Pas-de-Calais 59970",
    "addr:housenumber":"6",
    "addr:postcode":"59970;59970",
    "addr:street":"R Du Buiron",
    "iso:country":"FR",
    "sg:address":"6 R Du Buiron 59970 Odomez",
    "sg:classifiers":[
        {
            "category":"Farming",
            "subcategory":"Farm",
            "type":"Manufacturing & Wholesale Goods"
        }
    ],
    "sg:phone":"+33 3 27 34 18 18",
    "sg:postcode":"59970",
    "sg:province":"Nord Pas-de-Calais",
    "sg:tags":[
        "horticulture",
        "agriculture",
        "livestock"
    ],
    "wof:name":"Pepinieres Wannyn Sarl",
    "wof:placetype":"venue"
},
  "geometry": {"coordinates":[3.529364,50.452278],"type":"Point"}
}