{
  "type": "Feature",
  "properties": {
    "addr:full":"315, Square des Champs Elys\u00e9es, 91026 Evry C\u00e9dex Auvergne",
    "addr:housenumber":"315",
    "addr:postcode":"91026;ce\u0301dex",
    "addr:street":"Square Des Champs Elyse\u0301Es",
    "iso:country":"FR",
    "sg:address":"315, Square des Champs Elys\u00e9es, 91026 Evry C\u00e9dex",
    "sg:orig_category":"Non-Classified Establishments",
    "sg:phone":"+33 1 60 91 34 00",
    "sg:province":"Auvergne",
    "wof:name":"Albe S.a.r.l.",
    "wof:placetype":"venue"
},
  "geometry": {"coordinates":[2.43072,48.626919],"type":"Point"}
}