{
  "type": "Feature",
  "properties": {
    "iso:country":"FR",
    "sg:address":"Rue de Port Gentil - ZA Schweitzer",
    "sg:city":"Illkirch Graffenstaden",
    "sg:orig_category":"Unclassifiable Establishments",
    "sg:phone":"+33 3 88 55 38 38",
    "sg:postcode":"67400",
    "sg:province":"Alsace",
    "wof:name":"Ethywag S.a.",
    "wof:placetype":"venue"
},
  "geometry": {"coordinates":[7.711838,48.528809],"type":"Point"}
}