{
  "type": "Feature",
  "properties": {
    "addr:full":"52/54, Chemin des Bruy\u00e8res, 69150 D\u00e9cines Charpieu Rhone-Alpes 69150",
    "addr:housenumber":"52 / 54",
    "addr:postcode":"69150;69150",
    "addr:street":"Chemin Des Bruye\u0300Res;Rhone-Alpes",
    "iso:country":"FR",
    "sg:address":"52/54, Chemin des Bruy\u00e8res, 69150 D\u00e9cines Charpieu",
    "sg:orig_category":"Non-Classified Establishments",
    "sg:phone":"+33 4 78 49 79 84",
    "sg:postcode":"69150",
    "sg:province":"Rhone-Alpes",
    "wof:name":"R.m.d S.a.r.l. - Rh\u00f4ne M\u00e9tal Diffusion",
    "wof:placetype":"venue"
},
  "geometry": {"coordinates":[4.939132,45.756821],"type":"Point"}
}