{
  "type": "Feature",
  "properties": {
    "addr:full":"896, Rte des Belledonnes, 73490 La Ravoire Rhone-Alpes 73490",
    "addr:housenumber":"896",
    "addr:postcode":"73490;73490",
    "addr:street":"Rte Des Belledonnes",
    "iso:country":"FR",
    "sg:address":"896, Rte des Belledonnes, 73490 La Ravoire",
    "sg:orig_category":"Non-Classified Establishments",
    "sg:phone":"+33 4 79 33 28 16",
    "sg:postcode":"73490",
    "sg:province":"Rhone-Alpes",
    "wof:name":"Chabert S.a.r.l.",
    "wof:placetype":"venue"
},
  "geometry": {"coordinates":[5.960221,45.557373],"type":"Point"}
}