{
  "type": "Feature",
  "properties": {
    "iso:country":"FR",
    "sg:address":"Quartier de la Montre Saint Marcel",
    "sg:city":"Marseille",
    "sg:orig_category":"Unclassifiable Establishments",
    "sg:phone":"+33 4 91 87 61 90",
    "sg:postcode":"13011",
    "sg:province":"Poitou-Charentes",
    "wof:name":"Panzani S.a.",
    "wof:placetype":"venue"
},
  "geometry": {"coordinates":[5.437165,43.289322],"type":"Point"}
}