{
  "type": "Feature",
  "properties": {
    "iso:country":"FR",
    "sg:address":"Rte d'Humberville",
    "sg:city":"Manois",
    "sg:orig_category":"Unclassifiable Establishments",
    "sg:phone":"+33 3 25 02 80 11",
    "sg:postcode":"52700",
    "sg:province":"Champagne",
    "wof:name":"Tr\u00e9filac S.n.c.",
    "wof:placetype":"venue"
},
  "geometry": {"coordinates":[5.37838,48.286079],"type":"Point"}
}