{
  "type": "Feature",
  "properties": {
    "iso:country":"FR",
    "sg:address":"Les Bois Olives 50730 Hamelin",
    "sg:city":"Hamelin",
    "sg:orig_category":"Unclassifiable Establishments",
    "sg:phone":"+33 2 33 49 18 41",
    "sg:postcode":"50730",
    "sg:province":"Basse Normandie",
    "wof:name":"Minoterie Des Bois Olives S.a.s.",
    "wof:placetype":"venue"
},
  "geometry": {"coordinates":[-1.208679,48.541866],"type":"Point"}
}