{
  "type": "Feature",
  "properties": {
    "addr:full":"ZA Illange 57971 YUTZ Centre",
    "addr:postcode":"57971",
    "addr:street":"Za Illange",
    "iso:country":"FR",
    "sg:address":"ZA Illange 57971 YUTZ",
    "sg:classifiers":[
        {
            "category":"Home & Garden",
            "subcategory":"Building Materials",
            "type":"Retail Goods"
        }
    ],
    "sg:phone":"+33 3 82 56 45 29",
    "sg:province":"Centre",
    "sg:tags":[
        "double",
        "end",
        "stud"
    ],
    "wof:name":"Trevis Sa",
    "wof:placetype":"venue"
},
  "geometry": {"coordinates":[6.1873,49.35741],"type":"Point"}
}