{
  "type": "Feature",
  "properties": {
    "addr:full":"B.P. 33, 62250 Marquise^^18, Rue de la Motte, 62250 Marquise Nord Pas-de-Calais 62250",
    "addr:postcode":"62250;62250;62250",
    "addr:street":"B.P. 33;Rue De La Motte",
    "iso:country":"FR",
    "sg:address":"B.P. 33, 62250 Marquise^^18, Rue de la Motte, 62250 Marquise",
    "sg:orig_category":"Non-Classified Establishments",
    "sg:phone":"+33 3 21 92 90 42",
    "sg:postcode":"62250",
    "sg:province":"Nord Pas-de-Calais",
    "wof:name":"A.n.p.e.",
    "wof:placetype":"venue"
},
  "geometry": {"coordinates":[1.6679,50.768139],"type":"Point"}
}