{
  "type": "Feature",
  "properties": {
    "iso:country":"FR",
    "sg:address":"10, Rue des Acacias - Campus d'Activit\u00e9s, 57140 La Maxe",
    "sg:orig_category":"Non-Classified Establishments",
    "sg:phone":"+33 3 87 34 09 09",
    "sg:province":"Lorraine",
    "wof:name":"Michaud Chailly S.a.",
    "wof:placetype":"venue"
},
  "geometry": {"coordinates":[6.186117,49.154316],"type":"Point"}
}