{
  "type": "Feature",
  "properties": {
    "addr:full":"ZAC Puits d'Ordet Challes les Eaux Rhone-Alpes 73190",
    "addr:postcode":"73190",
    "addr:street":"Zac Puits D'Ordet",
    "iso:country":"FR",
    "sg:address":"ZAC Puits d'Ordet",
    "sg:city":"Challes les Eaux",
    "sg:orig_category":"Non-Classified Establishments",
    "sg:phone":"+33 4 79 72 70 98",
    "sg:postcode":"73190",
    "sg:province":"Rhone-Alpes",
    "wof:name":"Quad Photogravure S.a.",
    "wof:placetype":"venue"
},
  "geometry": {"coordinates":[5.974675,45.555035],"type":"Point"}
}