{
  "type": "Feature",
  "properties": {
    "iso:country":"FR",
    "sg:address":"33, Rue des Vanesses - ZI Paris Nord 2, 93200 Tremblay en France",
    "sg:orig_category":"Unclassifiable Establishments",
    "sg:phone":"+33 1 41 84 57 00",
    "sg:province":"Ile de France",
    "wof:name":"Marquette Hellige S.a.s.",
    "wof:placetype":"venue"
},
  "geometry": {"coordinates":[2.35497,48.938454],"type":"Point"}
}