{
  "type": "Feature",
  "properties": {
    "addr:full":"57, Quai Jacoutot, 67000 Strasbourg Strasbourg Alsace 67000",
    "addr:housenumber":"57",
    "addr:postcode":"67000;67000",
    "addr:street":"Quai Jacoutot",
    "iso:country":"FR",
    "sg:address":"57, Quai Jacoutot, 67000 Strasbourg",
    "sg:city":"Strasbourg",
    "sg:orig_category":"Unclassifiable Establishments",
    "sg:phone":"+33 3 90 41 04 50",
    "sg:postcode":"67000",
    "sg:province":"Alsace",
    "wof:name":"Algeco S.a.",
    "wof:placetype":"venue"
},
  "geometry": {"coordinates":[7.793886,48.590302],"type":"Point"}
}