{
  "type": "Feature",
  "properties": {
    "addr:full":"avenue Gross Umstadt 07130 ST PERAY Rhone-Alpes",
    "addr:postcode":"07130",
    "addr:street":"Avenue Gross Umstadt",
    "iso:country":"FR",
    "sg:address":"avenue Gross Umstadt 07130 ST PERAY",
    "sg:classifiers":[
        {
            "category":"Manufacturing",
            "subcategory":"Metals",
            "type":"Manufacturing & Wholesale Goods"
        }
    ],
    "sg:phone":"+33 4 75 81 82 70",
    "sg:province":"Rhone-Alpes",
    "sg:tags":[
        "sheet",
        "thin",
        "working"
    ],
    "wof:name":"Cegem S.a.r.l.",
    "wof:placetype":"venue"
},
  "geometry": {"coordinates":[4.85536,44.945068],"type":"Point"}
}