{
  "type": "Feature",
  "properties": {
    "addr:full":"4 rue Jean Bart; Douarnenez Midi Pyr\u00e9n\u00e9es",
    "addr:housenumber":"4",
    "addr:street":"Rue Jean Bart",
    "iso:country":"FR",
    "sg:address":"4 rue Jean Bart; Douarnenez",
    "sg:classifiers":[
        {
            "category":"Banks & Credit Unions",
            "subcategory":"Bank",
            "type":"Services"
        }
    ],
    "sg:phone":"+33 3398920735",
    "sg:province":"Midi Pyr\u00e9n\u00e9es",
    "wof:name":"Cr\u00e9dit Mutuel De Bretagne",
    "wof:placetype":"venue"
},
  "geometry": {"coordinates":[-4.329267,48.093327],"type":"Point"}
}