{
  "type": "Feature",
  "properties": {
    "addr:full":"31, Chauss\u00e9e Jules C\u00e9sar, 95300 Pontoise Ile de France",
    "addr:housenumber":"31",
    "addr:postcode":"95300;ile",
    "addr:street":"Chausse\u0301E Jules Ce\u0301Sar",
    "iso:country":"FR",
    "sg:address":"31, Chauss\u00e9e Jules C\u00e9sar, 95300 Pontoise",
    "sg:orig_category":"Unclassifiable Establishments",
    "sg:phone":"+33 1 34 35 15 15",
    "sg:province":"Ile de France",
    "wof:name":"Clarins S.a.",
    "wof:placetype":"venue"
},
  "geometry": {"coordinates":[2.07669,49.048672],"type":"Point"}
}