{
  "type": "Feature",
  "properties": {
    "iso:country":"FR",
    "sg:address":"12 Rue De La Seille 54320 Max\u00e9ville",
    "sg:classifiers":[
        {
            "category":"Travel",
            "subcategory":"Hotels & Motels",
            "type":"Entertainment"
        }
    ],
    "sg:phone":"+33 3 83 96 32 61",
    "sg:postcode":"54320",
    "sg:province":"Lorraine",
    "sg:tags":[
        "hotels",
        "business",
        "restaurant"
    ],
    "wof:name":"Sa3r",
    "wof:placetype":"venue"
},
  "geometry": {"coordinates":[6.13364,48.702042],"type":"Point"}
}