{
  "type": "Feature",
  "properties": {
    "iso:country":"FR",
    "sg:address":"lieu dit Petite Condemine 71700 Tournus",
    "sg:city":"Tournus",
    "sg:classifiers":[
        {
            "category":"Wholesale",
            "subcategory":"Home Furnishings",
            "type":"Manufacturing & Wholesale Goods"
        }
    ],
    "sg:phone":"+33 3 85 51 15 27",
    "sg:postcode":"71700",
    "sg:province":"Bourgogne",
    "sg:tags":[
        "chair"
    ],
    "wof:name":"Ste D Exploitation Des Ets Grebert Sarl",
    "wof:placetype":"venue"
},
  "geometry": {"coordinates":[4.903947,46.572906],"type":"Point"}
}