{
  "type": "Feature",
  "properties": {
    "addr:full":"Le Caillaouo 32300 St Michel Midi Pyr\u00e9n\u00e9es 32300",
    "addr:postcode":"32300;32300",
    "iso:country":"FR",
    "sg:address":"Le Caillaouo 32300 St Michel",
    "sg:classifiers":[
        {
            "category":"Shopping Center",
            "type":"Public Place"
        }
    ],
    "sg:phone":"+33 5 62 67 01 34",
    "sg:postcode":"32300",
    "sg:province":"Midi Pyr\u00e9n\u00e9es",
    "sg:tags":[
        "product",
        "meat",
        "cooked",
        "frozen",
        "related",
        "food"
    ],
    "wof:name":"Lahille Foies Gras",
    "wof:placetype":"venue"
},
  "geometry": {"coordinates":[0.41853,43.4398],"type":"Point"}
}