{
  "type": "Feature",
  "properties": {
    "iso:country":"FR",
    "sg:address":"RN 7 - ZI la Mon\u00e8de",
    "sg:city":"Verqui\u00e8res",
    "sg:orig_category":"Unclassifiable Establishments",
    "sg:phone":"+33 4 90 90 21 01",
    "sg:postcode":"13670",
    "sg:province":"Midi Pyr\u00e9n\u00e9es",
    "wof:name":"Assidoman Agripack S.a.r.l.",
    "wof:placetype":"venue"
},
  "geometry": {"coordinates":[4.94301,43.836479],"type":"Point"}
}