{
  "type": "Feature",
  "properties": {
    "addr:full":"Rte de Montlou\u00e9 Soize Picardie 02340",
    "addr:postcode":"02340",
    "addr:street":"Rte De Montloue\u0301;Picardie",
    "iso:country":"FR",
    "sg:address":"Rte de Montlou\u00e9",
    "sg:city":"Soize",
    "sg:orig_category":"Non-Classified Establishments",
    "sg:phone":"+33 3 23 98 53 94",
    "sg:postcode":"02340",
    "sg:province":"Picardie",
    "wof:name":"Transports Papin S.a.r.l.",
    "wof:placetype":"venue"
},
  "geometry": {"coordinates":[4.081759,49.698681],"type":"Point"}
}