{
  "type": "Feature",
  "properties": {
    "addr:full":"B.P. 7, 55300 Chauvoncourt^^Rte de Bar le Duc, 55300 Chauvoncourt Lorraine",
    "addr:housenumber":"7",
    "addr:postcode":"55300;55300",
    "addr:street":"B.P.;Le Duc",
    "iso:country":"FR",
    "sg:address":"B.P. 7, 55300 Chauvoncourt^^Rte de Bar le Duc, 55300 Chauvoncourt",
    "sg:orig_category":"Non-Classified Establishments",
    "sg:phone":"+33 3 29 90 22 22",
    "sg:province":"Lorraine",
    "wof:name":"Gente Meubles S.a.",
    "wof:placetype":"venue"
},
  "geometry": {"coordinates":[5.541056,48.891834],"type":"Point"}
}