{
  "type": "Feature",
  "properties": {
    "addr:full":"8 Rue Emile Verhaeren 92210 St Cloud Ile de France 92210",
    "addr:housenumber":"8",
    "addr:postcode":"92210;92210",
    "addr:street":"Rue Emile Verhaeren",
    "iso:country":"FR",
    "sg:address":"8 Rue Emile Verhaeren 92210 St Cloud",
    "sg:classifiers":[
        {
            "category":"Professional",
            "subcategory":"Business Services",
            "type":"Services"
        }
    ],
    "sg:phone":"+33 1 46 02 49 82",
    "sg:postcode":"92210",
    "sg:province":"Ile de France",
    "sg:tags":[
        "training",
        "advice"
    ],
    "wof:name":"Ecole & College St Joseph",
    "wof:placetype":"venue"
},
  "geometry": {"coordinates":[2.213429,48.84499],"type":"Point"}
}