{
  "type": "Feature",
  "properties": {
    "addr:full":"9 Rue Du Bois 39600 Cramans Franche Comt\u00e9 39600",
    "addr:housenumber":"9",
    "addr:postcode":"39600;39600",
    "addr:street":"Rue Du Bois;Franche Comte\u0301",
    "iso:country":"FR",
    "sg:address":"9 Rue Du Bois 39600 Cramans",
    "sg:classifiers":[
        {
            "category":"Wholesale",
            "subcategory":"Machinery & Supplies",
            "type":"Manufacturing & Wholesale Goods"
        }
    ],
    "sg:phone":"+33 3 84 37 60 65",
    "sg:postcode":"39600",
    "sg:province":"Franche Comt\u00e9",
    "sg:tags":[
        "handling",
        "material",
        "-",
        "machine",
        "equipment",
        "engineering",
        "mechanical"
    ],
    "wof:name":"Jacquot Baudier Sarl",
    "wof:placetype":"venue"
},
  "geometry": {"coordinates":[5.78051,47.012718],"type":"Point"}
}