{
  "type": "Feature",
  "properties": {
    "addr:full":"Av. du G\u00e9n\u00e9ral de Gaulle - Tour de Bureaux Rosny sous Bois Ile de France 93110",
    "addr:postcode":"93110",
    "addr:street":"Av. Du Ge\u0301Ne\u0301Ral De Gaulle Tour De Bureaux",
    "iso:country":"FR",
    "sg:address":"Av. du G\u00e9n\u00e9ral de Gaulle - Tour de Bureaux",
    "sg:city":"Rosny sous Bois",
    "sg:orig_category":"Unclassifiable Establishments",
    "sg:phone":"+33 1 48 94 32 52",
    "sg:postcode":"93110",
    "sg:province":"Ile de France",
    "wof:name":"Forum Sant\u00e9 S.a.",
    "wof:placetype":"venue"
},
  "geometry": {"coordinates":[2.47911,48.878315],"type":"Point"}
}