{
  "type": "Feature",
  "properties": {
    "addr:full":"140 Rte Des Moulins 38490 Chimilin Rhone-Alpes 38490",
    "addr:housenumber":"140",
    "addr:postcode":"38490;38490",
    "addr:street":"Rte Des Moulins;Rhone-Alpes",
    "iso:country":"FR",
    "sg:address":"140 Rte Des Moulins 38490 Chimilin",
    "sg:classifiers":[
        {
            "category":"Government",
            "subcategory":"Department Of Motor Vehicles",
            "type":"Public Place"
        }
    ],
    "sg:phone":"+33 4 76 32 69 69",
    "sg:postcode":"38490",
    "sg:province":"Rhone-Alpes",
    "sg:tags":[
        "equipment",
        "industrial",
        "transport",
        "motor-cars"
    ],
    "wof:name":"Impex Sa",
    "wof:placetype":"venue"
},
  "geometry": {"coordinates":[5.604036,45.576962],"type":"Point"}
}