{
  "type": "Feature",
  "properties": {
    "iso:country":"FR",
    "sg:address":"136, Grande Rue, 01660 M\u00e9z\u00e9riat",
    "sg:orig_category":"Non-Classified Establishments",
    "sg:phone":"+33 4 74 30 26 35",
    "sg:postcode":"01660",
    "sg:province":"Rhone-Alpes",
    "wof:name":"Fort P\u00e8re Et Fils S.a.r.l.",
    "wof:placetype":"venue"
},
  "geometry": {"coordinates":[5.047902,46.234337],"type":"Point"}
}