{
  "type": "Feature",
  "properties": {
    "addr:full":"ZI le Coin Saint Chamond Picardie 42402",
    "addr:postcode":"42402",
    "addr:street":"Zi Le Coin Saint;Picardie",
    "iso:country":"FR",
    "sg:address":"ZI le Coin",
    "sg:city":"Saint Chamond",
    "sg:orig_category":"Non-Classified Establishments",
    "sg:phone":"+33 4 77 31 06 92",
    "sg:postcode":"42402",
    "sg:province":"Picardie",
    "wof:name":"Spear & Jackson France S.a.",
    "wof:placetype":"venue"
},
  "geometry": {"coordinates":[4.518753,45.471889],"type":"Point"}
}