{
  "type": "Feature",
  "properties": {
    "addr:full":"63 rue Emile Salaun; L'Hopital Camfrout Picardie",
    "addr:housenumber":"63",
    "addr:street":"Rue Emile Salaun L'Hopital Camfrout",
    "iso:country":"FR",
    "sg:address":"63 rue Emile Salaun; L'Hopital Camfrout",
    "sg:classifiers":[
        {
            "category":"Banks & Credit Unions",
            "subcategory":"Bank",
            "type":"Services"
        }
    ],
    "sg:phone":"+33 3398200280",
    "sg:province":"Picardie",
    "wof:name":"Cr\u00e9dit Agricole Mutuel",
    "wof:placetype":"venue"
},
  "geometry": {"coordinates":[-4.241399,48.327969],"type":"Point"}
}