{
  "type": "Feature",
  "properties": {
    "iso:country":"FR",
    "sg:address":"Rue Saint Roch",
    "sg:city":"Montbard",
    "sg:orig_category":"Unclassifiable Establishments",
    "sg:phone":"+33 3 80 92 14 28",
    "sg:postcode":"21500",
    "sg:province":"Bourgogne",
    "wof:name":"F.i.c.a. S.a. - Fourniture Industrielle Comfort Ameublement Et Automobile",
    "wof:placetype":"venue"
},
  "geometry": {"coordinates":[4.342869,47.620686],"type":"Point"}
}