{
  "type": "Feature",
  "properties": {
    "iso:country":"FR",
    "sg:address":"2 bis, Av. d'Aubi\u00e8re, 63800 Cournon d'Auvergne",
    "sg:city":"P\u00e9rignat-sur-Allier",
    "sg:orig_category":"Unclassifiable Establishments",
    "sg:phone":"+33 4 73 84 20 30",
    "sg:postcode":"63800",
    "sg:province":"Auvergne",
    "wof:name":"Mic Signaloc S.a.r.l.",
    "wof:placetype":"venue"
},
  "geometry": {"coordinates":[3.159597,45.749783],"type":"Point"}
}