{
  "type": "Feature",
  "properties": {
    "addr:full":"Centre Commercial Les; Plaisir; 78370 Ile de France 78370",
    "addr:postcode":"78370;78370",
    "addr:street":"Commercial Les Plaisir;France",
    "iso:country":"FR",
    "sg:address":"Centre Commercial Les; Plaisir; 78370",
    "sg:classifiers":[
        {
            "category":"Banks & Credit Unions",
            "subcategory":"Bank",
            "type":"Services"
        }
    ],
    "sg:phone":"+33 30553341",
    "sg:postcode":"78370",
    "sg:province":"Ile de France",
    "wof:name":"Soci\u00e9t\u00e9 G\u00e9n\u00e9rale",
    "wof:placetype":"venue"
},
  "geometry": {"coordinates":[1.949255,48.816689],"type":"Point"}
}