{
  "type": "Feature",
  "properties": {
    "iso:country":"FR",
    "sg:address":"29, Rte de Carcassonne, 11300 Limoux",
    "sg:orig_category":"Unclassifiable Establishments",
    "sg:phone":"+33 4 68 74 73 30",
    "sg:province":"Languedoc-Roussillon",
    "wof:name":"Sapie S.a.r.l.",
    "wof:placetype":"venue"
},
  "geometry": {"coordinates":[2.213352,43.056618],"type":"Point"}
}