{
  "type": "Feature",
  "properties": {
    "iso:country":"FR",
    "sg:address":"Za 85610 Cugand",
    "sg:classifiers":[
        {
            "category":"Shopping",
            "subcategory":"Clothing, Apparel, & Fashions",
            "type":"Retail Goods"
        }
    ],
    "sg:phone":"+33 2 51 43 67 07",
    "sg:postcode":"85610",
    "sg:province":"Pays de Loire",
    "sg:tags":[
        "textile",
        "clothing",
        "clothes"
    ],
    "wof:name":"Filmad Sarl",
    "wof:placetype":"venue"
},
  "geometry": {"coordinates":[-1.253818,47.065861],"type":"Point"}
}