{
  "type": "Feature",
  "properties": {
    "addr:full":"78, Rue de Turbigo, 75003 Paris Ile de France",
    "addr:housenumber":"78",
    "addr:postcode":"75003",
    "addr:street":"Rue De Turbigo",
    "iso:country":"FR",
    "sg:address":"78, Rue de Turbigo, 75003 Paris",
    "sg:orig_category":"Unclassifiable Establishments",
    "sg:phone":"+33 1 44 54 15 50",
    "sg:province":"Ile de France",
    "wof:name":"Pro.mo.ref. S.a. - Produits Monolithiques R\u00e9fractaires",
    "wof:placetype":"venue"
},
  "geometry": {"coordinates":[2.361344,48.866524],"type":"Point"}
}