{
  "type": "Feature",
  "properties": {
    "iso:country":"FR",
    "sg:address":"Rue Saint Christophe",
    "sg:city":"Rodez",
    "sg:orig_category":"Non-Classified Establishments",
    "sg:phone":"+33 5 65 77 36 36",
    "sg:postcode":"12000",
    "sg:province":"Midi Pyr\u00e9n\u00e9es",
    "wof:name":"Sc Tout\u00e9lectric S.a.",
    "wof:placetype":"venue"
},
  "geometry": {"coordinates":[2.545595,44.372292],"type":"Point"}
}