{
  "type": "Feature",
  "properties": {
    "addr:full":"5 Rue D'Altkirch 68000 Colmar Colmar Alsace 68000",
    "addr:housenumber":"5",
    "addr:postcode":"68000;68000",
    "addr:street":"Rue D'Altkirch",
    "iso:country":"FR",
    "sg:address":"5 Rue D'Altkirch 68000 Colmar",
    "sg:city":"Colmar",
    "sg:classifiers":[
        {
            "category":"Autos & Motor Vehicles",
            "subcategory":"Automobile Sales",
            "type":"Retail Goods"
        }
    ],
    "sg:phone":"+33 3 89 80 22 11",
    "sg:postcode":"68000",
    "sg:province":"Alsace",
    "sg:tags":[
        "equipment",
        "transport"
    ],
    "wof:name":"Societe Des Anciens Etablissements L. Geismar",
    "wof:placetype":"venue"
},
  "geometry": {"coordinates":[7.343834,48.069714],"type":"Point"}
}