{
  "type": "Feature",
  "properties": {
    "addr:full":"851 Rue De Bernau De Plateau 94500 Champigny Sur Marne Ile de France 94500",
    "addr:housenumber":"851",
    "addr:postcode":"94500;94500",
    "addr:street":"Rue De Bernau De Plateau",
    "iso:country":"FR",
    "sg:address":"851 Rue De Bernau",
    "sg:city":"De Plateau 94500 Champigny Sur Marne",
    "sg:classifiers":[
        {
            "category":"Manufacturing",
            "subcategory":"Textiles",
            "type":"Manufacturing & Wholesale Goods"
        }
    ],
    "sg:phone":"+33 1 45 16 37 72",
    "sg:postcode":"94500",
    "sg:province":"Ile de France",
    "sg:tags":[
        "printing",
        "clothing",
        "fabric"
    ],
    "wof:name":"Trans Laser Tlb",
    "wof:placetype":"venue"
},
  "geometry": {"coordinates":[2.51158,48.813404],"type":"Point"}
}