{
  "type": "Feature",
  "properties": {
    "iso:country":"FR",
    "sg:address":"B.P. 88, 07302 Tournon sur Rh\u00f4ne C\u00e9dex^^Rue des Condamines, 07300 Mauves",
    "sg:orig_category":"Non-Classified Establishments",
    "sg:phone":"+33 4 75 07 87 07",
    "sg:province":"Rhone-Alpes",
    "wof:name":"Mecelec Industrie S.a.",
    "wof:placetype":"venue"
},
  "geometry": {"coordinates":[4.80233,45.06245],"type":"Point"}
}