{
  "type": "Feature",
  "properties": {
    "iso:country":"FR",
    "sg:address":"RN 82 - Les Embreux",
    "sg:city":"Saint Laurent la Conche",
    "sg:orig_category":"Non-Classified Establishments",
    "sg:phone":"+33 4 77 27 47 50",
    "sg:postcode":"42210",
    "sg:province":"Rhone-Alpes",
    "wof:name":"Eyraud Plants G.a.e.c.",
    "wof:placetype":"venue"
},
  "geometry": {"coordinates":[4.230482,45.584427],"type":"Point"}
}