{
  "type": "Feature",
  "properties": {
    "iso:country":"FR",
    "sg:address":"ZI des Eaux Blanches",
    "sg:city":"S\u00e8te",
    "sg:orig_category":"Non-Classified Establishments",
    "sg:phone":"+33 4 67 80 00 70",
    "sg:postcode":"34200",
    "sg:province":"Languedoc-Roussillon",
    "wof:name":"C.i.r. S.a.r.l. - Compagnie Industrielle Du Roulement",
    "wof:placetype":"venue"
},
  "geometry": {"coordinates":[3.69633,43.399052],"type":"Point"}
}