{
  "type": "Feature",
  "properties": {
    "iso:country":"FR",
    "sg:address":"Rte de Nanfray - ZA Levray - Immeuble First",
    "sg:city":"Cran Gevrier",
    "sg:orig_category":"Unclassifiable Establishments",
    "sg:phone":"+33 4 50 10 94 95",
    "sg:postcode":"74960",
    "sg:province":"Rhone-Alpes",
    "wof:name":"Axel Savoies Technologies S.a.",
    "wof:placetype":"venue"
},
  "geometry": {"coordinates":[6.10647,45.907654],"type":"Point"}
}