{
  "type": "Feature",
  "properties": {
    "iso:country":"FR",
    "sg:address":"9 bis, Rue Jean Jaur\u00e8s, 95130 Le Plessis Bouchard",
    "sg:orig_category":"Unclassifiable Establishments",
    "sg:phone":"+33 1 34 15 23 09",
    "sg:province":"Ile de France",
    "wof:name":"Seam S.a.",
    "wof:placetype":"venue"
},
  "geometry": {"coordinates":[2.239537,48.99651],"type":"Point"}
}