{
  "type": "Feature",
  "properties": {
    "addr:full":"ZI Bernard Palissy Parthenay Poitou-Charentes 79200",
    "addr:postcode":"79200",
    "iso:country":"FR",
    "sg:address":"ZI Bernard Palissy",
    "sg:city":"Parthenay",
    "sg:orig_category":"Unclassifiable Establishments",
    "sg:phone":"+33 5 49 64 58 46",
    "sg:postcode":"79200",
    "sg:province":"Poitou-Charentes",
    "wof:name":"S.i.c. S.a.r.l. - Soci\u00e9t\u00e9 Industrielle De Chaudronnerie",
    "wof:placetype":"venue"
},
  "geometry": {"coordinates":[-0.247062,46.647381],"type":"Point"}
}