{
  "type": "Feature",
  "properties": {
    "addr:full":"139, Rue Vend\u00f4me, 69477 Lyon C\u00e9dex 06 Rhone-Alpes",
    "addr:housenumber":"139;06",
    "addr:postcode":"69477",
    "addr:street":"Rue Vendo\u0302Me;Ce\u0301Dex",
    "iso:country":"FR",
    "sg:address":"139, Rue Vend\u00f4me, 69477 Lyon C\u00e9dex 06",
    "sg:orig_category":"Non-Classified Establishments",
    "sg:phone":"+33 4 72 75 75 75",
    "sg:province":"Rhone-Alpes",
    "wof:name":"N.s.m.d. S.a.",
    "wof:placetype":"venue"
},
  "geometry": {"coordinates":[4.846094,45.764931],"type":"Point"}
}