{
  "type": "Feature",
  "properties": {
    "addr:full":"B.P. 75, 74150 Rumilly C\u00e9dex^^ZI des Perouses, 74150 Rumilly Rhone-Alpes",
    "addr:postcode":"74150;74150",
    "addr:street":"B.P. 75",
    "iso:country":"FR",
    "sg:address":"B.P. 75, 74150 Rumilly C\u00e9dex^^ZI des Perouses, 74150 Rumilly",
    "sg:orig_category":"Non-Classified Establishments",
    "sg:phone":"+33 4 50 01 40 36",
    "sg:province":"Rhone-Alpes",
    "wof:name":"Olpg Industries S.a.",
    "wof:placetype":"venue"
},
  "geometry": {"coordinates":[5.943953,45.822372],"type":"Point"}
}