{
  "type": "Feature",
  "properties": {
    "iso:country":"FR",
    "sg:address":"32, Quai Marcel Boyer, 94200 Ivry sur Seine",
    "sg:orig_category":"Unclassifiable Establishments",
    "sg:phone":"+33 1 45 15 54 54",
    "sg:province":"Ile de France",
    "wof:name":"Schmitt Wey Sanitaire Chauffage S.a.",
    "wof:placetype":"venue"
},
  "geometry": {"coordinates":[2.393183,48.821842],"type":"Point"}
}