{
  "type": "Feature",
  "properties": {
    "addr:full":"Base A\u00e9rienne 120 33260 La Teste De Buch Teste-de-Buch Aquitaine 33260",
    "addr:housenumber":"120",
    "addr:postcode":"33260;33260",
    "iso:country":"FR",
    "sg:address":"Base A\u00e9rienne 120 33260 La Teste De Buch",
    "sg:city":"Teste-de-Buch",
    "sg:classifiers":[
        {
            "category":"Manufacturing",
            "subcategory":"Aerospace",
            "type":"Manufacturing & Wholesale Goods"
        }
    ],
    "sg:phone":"+33 5 56 22 44 00",
    "sg:postcode":"33260",
    "sg:province":"Aquitaine",
    "sg:tags":[
        "equipment",
        "aeronautic",
        "transport",
        "vehicle"
    ],
    "wof:name":"Dassault Aviation",
    "wof:placetype":"venue"
},
  "geometry": {"coordinates":[-1.145227,44.632915],"type":"Point"}
}