{
  "type": "Feature",
  "properties": {
    "addr:full":"Rue Pierre De Coubertin 71000 M\u00e2con Sanc\u00e9 Bourgogne 71000",
    "addr:postcode":"71000;71000",
    "addr:street":"Rue Pierre De Coubertin",
    "iso:country":"FR",
    "sg:address":"Rue Pierre De Coubertin 71000 M\u00e2con",
    "sg:city":"Sanc\u00e9",
    "sg:classifiers":[
        {
            "category":"Professional",
            "subcategory":"Business Services",
            "type":"Services"
        }
    ],
    "sg:phone":"+33 3 85 39 95 55",
    "sg:postcode":"71000",
    "sg:province":"Bourgogne",
    "sg:tags":[
        "training",
        "advice"
    ],
    "wof:name":"Ctre Education Populaire Et De Sport",
    "wof:placetype":"venue"
},
  "geometry": {"coordinates":[4.84127,46.318375],"type":"Point"}
}