{
  "type": "Feature",
  "properties": {
    "addr:full":"Zone Industrielle 25340 ANTEUIL Franche Comt\u00e9 25340",
    "addr:postcode":"25340;25340",
    "addr:street":"Zone Industrielle;Franche Comte\u0301",
    "iso:country":"FR",
    "sg:address":"Zone Industrielle 25340 ANTEUIL",
    "sg:classifiers":[
        {
            "category":"Manufacturing",
            "subcategory":"Rubber & Plastics",
            "type":"Manufacturing & Wholesale Goods"
        }
    ],
    "sg:phone":"+33 3 81 90 73 00",
    "sg:postcode":"25340",
    "sg:province":"Franche Comt\u00e9",
    "sg:tags":[
        "conduit",
        "cap",
        "made",
        "cable",
        "protection"
    ],
    "wof:name":"Sofanou S.a.",
    "wof:placetype":"venue"
},
  "geometry": {"coordinates":[6.560065,47.388084],"type":"Point"}
}