{
  "type": "Feature",
  "properties": {
    "addr:full":"164, Rue Foch, 57200 Sarreguemines Lorraine",
    "addr:housenumber":"164",
    "addr:postcode":"57200",
    "addr:street":"Rue Foch",
    "iso:country":"FR",
    "sg:address":"164, Rue Foch, 57200 Sarreguemines",
    "sg:orig_category":"Unclassifiable Establishments",
    "sg:phone":"+33 3 87 95 00 59",
    "sg:province":"Lorraine",
    "wof:name":"B.l.s. S.a.r.l. - Berger Learn System",
    "wof:placetype":"venue"
},
  "geometry": {"coordinates":[7.087097,49.11924],"type":"Point"}
}