{
  "type": "Feature",
  "properties": {
    "iso:country":"FR",
    "sg:address":"251 Boulevard Pereire 75017 Paris",
    "sg:classifiers":[
        {
            "category":"Professional",
            "subcategory":"Computer Services",
            "type":"Services"
        }
    ],
    "sg:phone":"+33 1 44 09 55 00",
    "sg:postcode":"75017",
    "sg:province":"Ile de France",
    "sg:tags":[
        "information",
        "technology",
        "software"
    ],
    "wof:name":"Viveo",
    "wof:placetype":"venue"
},
  "geometry": {"coordinates":[2.286443,48.87878],"type":"Point"}
}