{
  "type": "Feature",
  "properties": {
    "addr:full":"14 Rue Pierre Josse 91070 Bondoufle Ile de France",
    "addr:housenumber":"14",
    "addr:postcode":"91070;ile",
    "addr:street":"Rue Pierre Josse",
    "iso:country":"FR",
    "sg:address":"14 Rue Pierre Josse 91070 Bondoufle",
    "sg:classifiers":[
        {
            "category":"Manufacturing",
            "subcategory":"Paper Products",
            "type":"Manufacturing & Wholesale Goods"
        }
    ],
    "sg:phone":"+33 1 60 86 41 32",
    "sg:province":"Ile de France",
    "sg:tags":[
        "finished",
        "cardboard",
        "-"
    ],
    "wof:name":"Coltrege Sa",
    "wof:placetype":"venue"
},
  "geometry": {"coordinates":[2.36229,48.605167],"type":"Point"}
}