{
  "type": "Feature",
  "properties": {
    "iso:country":"FR",
    "sg:address":"Zac De La Solane 19000 TULLE",
    "sg:classifiers":[
        {
            "category":"Bars & Pubs",
            "type":"Food & Drink"
        }
    ],
    "sg:phone":"+33 5 55 26 00 44",
    "sg:postcode":"19000",
    "sg:province":"Limousin",
    "sg:tags":[
        "knife",
        "bread"
    ],
    "wof:name":"Manufacture De Couteaux Regionaux S.a.",
    "wof:placetype":"venue"
},
  "geometry": {"coordinates":[1.756695,45.259048],"type":"Point"}
}