{
  "type": "Feature",
  "properties": {
    "addr:full":"4 Allee Paul Sabatier Toulouse Midi Pyr\u00e9n\u00e9es 31000",
    "addr:housenumber":"4",
    "addr:postcode":"31000",
    "addr:street":"Allee Paul Sabatier",
    "iso:country":"FR",
    "sg:address":"4 Allee Paul Sabatier",
    "sg:city":"Toulouse",
    "sg:classifiers":[
        {
            "category":"Banks & Credit Unions",
            "subcategory":"Financial Services",
            "type":"Services"
        }
    ],
    "sg:phone":"+33 5 61 53 90 16",
    "sg:postcode":"31000",
    "sg:province":"Midi Pyr\u00e9n\u00e9es",
    "sg:tags":[
        "banking",
        "finance",
        "insurance"
    ],
    "wof:name":"Bnp Lease",
    "wof:placetype":"venue"
},
  "geometry": {"coordinates":[1.454277,43.595955],"type":"Point"}
}