{
  "type": "Feature",
  "properties": {
    "addr:full":"17 rue de Surene 75008 Paris Ile de France 75008",
    "addr:housenumber":"17",
    "addr:postcode":"75008;75008",
    "addr:street":"Rue De Surene",
    "iso:country":"FR",
    "sg:address":"17 rue de Surene 75008 Paris",
    "sg:classifiers":[
        {
            "category":"Professional",
            "subcategory":"Advertising",
            "type":"Services"
        }
    ],
    "sg:phone":"+33 1 40 17 17 01",
    "sg:postcode":"75008",
    "sg:province":"Ile de France",
    "sg:tags":[
        "bank"
    ],
    "wof:name":"Dow Jones International Sa",
    "wof:placetype":"venue"
},
  "geometry": {"coordinates":[2.320611,48.870838],"type":"Point"}
}