{
  "type": "Feature",
  "properties": {
    "iso:country":"FR",
    "sg:address":"12 rue Joseph B\u00e9ghin 59239 Thumeries",
    "sg:classifiers":[
        {
            "category":"Ice Cream",
            "type":"Food & Drink"
        }
    ],
    "sg:phone":"+33 3 20 62 44 00",
    "sg:province":"Nord Pas-de-Calais",
    "sg:tags":[
        "sugar"
    ],
    "wof:name":"Eridania B\u00e9ghin-say Sa",
    "wof:placetype":"venue"
},
  "geometry": {"coordinates":[3.065997,50.470516],"type":"Point"}
}