{
  "type": "Feature",
  "properties": {
    "iso:country":"FR",
    "sg:address":"63",
    "sg:city":"Henri Dunant BP 49 77103 MEAUX",
    "sg:classifiers":[
        {
            "category":"Professional",
            "subcategory":"Engineering",
            "type":"Services"
        }
    ],
    "sg:phone":"+33 1 64 33 30 01",
    "sg:province":"Midi Pyr\u00e9n\u00e9es",
    "sg:tags":[
        "machine",
        "-",
        "environment",
        "equipment",
        "machinery",
        "mechanical"
    ],
    "wof:name":"S.e.t.r.e",
    "wof:placetype":"venue"
},
  "geometry": {"coordinates":[2.895207,48.947849],"type":"Point"}
}