{
  "type": "Feature",
  "properties": {
    "iso:country":"FR",
    "sg:address":"31 Rue Des Bosquets 25480 Ecole Valentin",
    "sg:classifiers":[
        {
            "category":"Wholesale",
            "subcategory":"Medical Equipment & Supplies",
            "type":"Manufacturing & Wholesale Goods"
        }
    ],
    "sg:phone":"+33 3 81 53 43 44",
    "sg:postcode":"25480",
    "sg:province":"Franche Comt\u00e9",
    "sg:tags":[
        "instrument",
        "health",
        "-",
        "precision"
    ],
    "wof:name":"Alain Decaudin Orthopedie (ado)",
    "wof:placetype":"venue"
},
  "geometry": {"coordinates":[5.99,47.271336],"type":"Point"}
}