{
  "type": "Feature",
  "properties": {
    "iso:country":"FR",
    "sg:address":"85 Rue Ferdinand West 49800 Trelaze",
    "sg:classifiers":[
        {
            "category":"Manufacturing",
            "subcategory":"Tools & Machinery",
            "type":"Manufacturing & Wholesale Goods"
        }
    ],
    "sg:phone":"+33 2 41 33 19 00",
    "sg:postcode":"49800",
    "sg:province":"Pays de Loire",
    "sg:tags":[
        "equipment",
        "measurement",
        "-",
        "precision",
        "instrument"
    ],
    "wof:name":"Activite Productique Mecanique Angevine (apma)",
    "wof:placetype":"venue"
},
  "geometry": {"coordinates":[-0.477109,47.443653],"type":"Point"}
}