{
  "type": "Feature",
  "properties": {
    "iso:country":"FR",
    "sg:address":"7, Av. Charras, 63000 Clermont Ferrand",
    "sg:city":"Clermont-Ferrand",
    "sg:orig_category":"Non-Classified Establishments",
    "sg:phone":"+33 4 73 90 14 14",
    "sg:postcode":"63000",
    "sg:province":"Auvergne",
    "wof:name":"Egexpo S.a.r.l.",
    "wof:placetype":"venue"
},
  "geometry": {"coordinates":[3.09368,45.779835],"type":"Point"}
}