{
  "type": "Feature",
  "properties": {
    "addr:full":"1, Rue du lac - ZAC du Val des Pr\u00e9s, 38120 Saint Egr\u00e8ve Rhone-Alpes",
    "addr:housenumber":"1",
    "addr:postcode":"38120",
    "addr:street":"Rue Du Lac Zac Du Val Des Pre\u0301S",
    "iso:country":"FR",
    "sg:address":"1, Rue du lac - ZAC du Val des Pr\u00e9s, 38120 Saint Egr\u00e8ve",
    "sg:orig_category":"Unclassifiable Establishments",
    "sg:phone":"+33 4 76 56 04 47",
    "sg:province":"Rhone-Alpes",
    "wof:name":"Manuli Sonatra S.a.",
    "wof:placetype":"venue"
},
  "geometry": {"coordinates":[5.68088,45.232937],"type":"Point"}
}