{
  "type": "Feature",
  "properties": {
    "addr:full":"4, Rue des Sources, 44350 Gu\u00e9rande Pays de Loire 44350",
    "addr:housenumber":"4",
    "addr:postcode":"44350;44350",
    "addr:street":"Rue Des Sources",
    "iso:country":"FR",
    "sg:address":"4, Rue des Sources, 44350 Gu\u00e9rande",
    "sg:orig_category":"Non-Classified Establishments",
    "sg:phone":"+33 2 40 15 60 60",
    "sg:postcode":"44350",
    "sg:province":"Pays de Loire",
    "wof:name":"Andr\u00e9 Mah\u00e9 S.a.",
    "wof:placetype":"venue"
},
  "geometry": {"coordinates":[-2.406244,47.323551],"type":"Point"}
}