{
  "type": "Feature",
  "properties": {
    "addr:full":"6, Rue des Templiers, 69002 Lyon Rhone-Alpes 69002",
    "addr:housenumber":"6",
    "addr:postcode":"69002;69002",
    "addr:street":"Rue Des Templiers",
    "iso:country":"FR",
    "sg:address":"6, Rue des Templiers, 69002 Lyon",
    "sg:orig_category":"Unclassifiable Establishments",
    "sg:phone":"+33 4 78 37 71 01",
    "sg:postcode":"69002",
    "sg:province":"Rhone-Alpes",
    "wof:name":"Etablissement Trompier Et Compagnie S.a.r.l.",
    "wof:placetype":"venue"
},
  "geometry": {"coordinates":[4.831129,45.759403],"type":"Point"}
}