{
  "type": "Feature",
  "properties": {
    "iso:country":"FR",
    "sg:address":"14 Rue De H\u00e9singue 68220 H\u00e9genheim",
    "sg:city":"H\u00e9singue",
    "sg:classifiers":[
        {
            "category":"Wholesale",
            "subcategory":"Meat",
            "type":"Manufacturing & Wholesale Goods"
        }
    ],
    "sg:phone":"+33 3 89 69 18 51",
    "sg:postcode":"68220",
    "sg:province":"Alsace",
    "sg:tags":[
        "food",
        "cooked",
        "product",
        "related"
    ],
    "wof:name":"Boucheries-charcuteries Eckert Sa",
    "wof:placetype":"venue"
},
  "geometry": {"coordinates":[7.526663,47.562584],"type":"Point"}
}