{
  "type": "Feature",
  "properties": {
    "iso:country":"FR",
    "sg:address":"1, Rue de Provence, 75009 Paris",
    "sg:orig_category":"Unclassifiable Establishments",
    "sg:phone":"+33 1 53 24 64 65",
    "sg:province":"Ile de France",
    "wof:name":"Editec S.a.r.l.",
    "wof:placetype":"venue"
},
  "geometry": {"coordinates":[2.342026,48.873924],"type":"Point"}
}