{
  "type": "Feature",
  "properties": {
    "addr:full":"B.P. 422, 66334 Cabestany C\u00e9dex^^10, Av. Amp\u00e8re, 66330 Cabestany Languedoc-Roussillon 66330",
    "addr:housenumber":"b.p. 422",
    "addr:postcode":"66334;66330;66330",
    "addr:street":"Av. Ampe\u0300Re",
    "iso:country":"FR",
    "sg:address":"B.P. 422, 66334 Cabestany C\u00e9dex^^10, Av. Amp\u00e8re, 66330 Cabestany",
    "sg:orig_category":"Non-Classified Establishments",
    "sg:phone":"+33 4 68 67 29 66",
    "sg:postcode":"66330",
    "sg:province":"Languedoc-Roussillon",
    "wof:name":"Atout K Ro S.a.r.l.",
    "wof:placetype":"venue"
},
  "geometry": {"coordinates":[2.937813,42.681599],"type":"Point"}
}