{
  "type": "Feature",
  "properties": {
    "addr:full":"100, Rue Principale, 68120 Richwiller Richwiller Alsace 68120",
    "addr:housenumber":"100",
    "addr:postcode":"68120;68120",
    "addr:street":"Rue Principale",
    "iso:country":"FR",
    "sg:address":"100, Rue Principale, 68120 Richwiller",
    "sg:city":"Richwiller",
    "sg:orig_category":"Unclassifiable Establishments",
    "sg:phone":"+33 3 89 52 14 00",
    "sg:postcode":"68120",
    "sg:province":"Alsace",
    "wof:name":"Abt S.a.r.l.",
    "wof:placetype":"venue"
},
  "geometry": {"coordinates":[7.277932,47.780308],"type":"Point"}
}