{
  "type": "Feature",
  "properties": {
    "addr:full":"12, Rue de la Minoterie, 67000 Strasbourg Strasbourg Alsace 67000",
    "addr:housenumber":"12",
    "addr:postcode":"67000;67000",
    "addr:street":"Rue De La Minoterie",
    "iso:country":"FR",
    "sg:address":"12, Rue de la Minoterie, 67000 Strasbourg",
    "sg:city":"Strasbourg",
    "sg:orig_category":"Non-Classified Establishments",
    "sg:phone":"+33 3 88 41 10 15",
    "sg:postcode":"67000",
    "sg:province":"Alsace",
    "wof:name":"France Packaging France S.a.r.l.",
    "wof:placetype":"venue"
},
  "geometry": {"coordinates":[7.792214,48.581421],"type":"Point"}
}