{
  "type": "Feature",
  "properties": {
    "addr:full":"146 Avenue Cyrille Besset 06100 Nice Auvergne",
    "addr:housenumber":"146",
    "addr:postcode":"06100",
    "addr:street":"Avenue Cyrille",
    "iso:country":"FR",
    "sg:address":"146 Avenue Cyrille Besset 06100 Nice",
    "sg:classifiers":[
        {
            "category":"Professional",
            "subcategory":"Engineering",
            "type":"Services"
        }
    ],
    "sg:phone":"+33 4 93 51 13 50",
    "sg:province":"Auvergne",
    "sg:tags":[
        "machine",
        "-",
        "mechanical"
    ],
    "wof:name":"Ims Azur Ingenierie Maintenance Systemes (ims Azur)",
    "wof:placetype":"venue"
},
  "geometry": {"coordinates":[7.248193,43.723206],"type":"Point"}
}