{
  "type": "Feature",
  "properties": {
    "addr:full":"Z.I. 26130 ST PAUL TROIS CHATEAUX Rhone-Alpes 26130",
    "addr:postcode":"26130;26130",
    "addr:street":"Z.I.;Rhone-Alpes",
    "iso:country":"FR",
    "sg:address":"Z.I. 26130 ST PAUL TROIS CHATEAUX",
    "sg:classifiers":[
        {
            "category":"Wholesale",
            "subcategory":"Machinery & Supplies",
            "type":"Manufacturing & Wholesale Goods"
        }
    ],
    "sg:phone":"+33 4 75 04 70 38",
    "sg:postcode":"26130",
    "sg:province":"Rhone-Alpes",
    "sg:tags":[
        "agricultural",
        "equipment"
    ],
    "wof:name":"Ets Arnaud Fr\u00e8res S.a.",
    "wof:placetype":"venue"
},
  "geometry": {"coordinates":[4.76946,44.348251],"type":"Point"}
}