{
  "type": "Feature",
  "properties": {
    "iso:country":"FR",
    "sg:address":"17 Rue Aristide Briand 60110 Meru",
    "sg:classifiers":[
        {
            "category":"Farming",
            "subcategory":"Livestock Farm",
            "type":"Manufacturing & Wholesale Goods"
        }
    ],
    "sg:phone":"+33 3 44 52 37 37",
    "sg:postcode":"60110",
    "sg:province":"Picardie",
    "sg:tags":[
        "grain",
        "agriculture",
        "cereal"
    ],
    "wof:name":"Cooperative Agricole Force 5 Sa",
    "wof:placetype":"venue"
},
  "geometry": {"coordinates":[2.13162,49.226921],"type":"Point"}
}