{
  "type": "Feature",
  "properties": {
    "iso:country":"FR",
    "sg:address":"93, Rte de Monnaie, 37210 Vouvray",
    "sg:city":"Vouvray",
    "sg:orig_category":"Unclassifiable Establishments",
    "sg:phone":"+33 2 47 52 70 30",
    "sg:postcode":"37210",
    "sg:province":"Centre",
    "wof:name":"Laboratoires Chemineau S.a.",
    "wof:placetype":"venue"
},
  "geometry": {"coordinates":[0.796563,47.425156],"type":"Point"}
}