{
  "type": "Feature",
  "properties": {
    "addr:full":"36, rue du Commerce, 51350 Cormontreuil Champagne",
    "addr:housenumber":"36",
    "addr:postcode":"51350",
    "addr:street":"Rue Du Commerce",
    "iso:country":"FR",
    "sg:address":"36, rue du Commerce, 51350 Cormontreuil",
    "sg:orig_category":"Unclassifiable Establishments",
    "sg:phone":"+33 3 26 82 23 21",
    "sg:province":"Champagne",
    "wof:name":"Soseloc S.a.",
    "wof:placetype":"venue"
},
  "geometry": {"coordinates":[4.066117,49.214748],"type":"Point"}
}