{
  "type": "Feature",
  "properties": {
    "addr:full":"Rue Aristide Briand 70300 Luxeuil Les Bains Franche Comt\u00e9 70300",
    "addr:postcode":"70300;70300",
    "addr:street":"Rue Aristide Briand;Franche Comte\u0301",
    "iso:country":"FR",
    "sg:address":"Rue Aristide Briand 70300 Luxeuil Les Bains",
    "sg:classifiers":[
        {
            "category":"Manufacturing",
            "subcategory":"Tools & Machinery",
            "type":"Manufacturing & Wholesale Goods"
        }
    ],
    "sg:phone":"+33 3 84 93 69 70",
    "sg:postcode":"70300",
    "sg:province":"Franche Comt\u00e9",
    "sg:tags":[
        "metallurgy",
        "metalworking"
    ],
    "wof:name":"Quincaillerie Veissiere Sarl",
    "wof:placetype":"venue"
},
  "geometry": {"coordinates":[6.38904,47.816109],"type":"Point"}
}