{
  "type": "Feature",
  "properties": {
    "addr:full":"Chemin De L Usine Utard 55000 Longeville En Barrois Lorraine",
    "addr:postcode":"55000",
    "addr:street":"Chemin De L Usine Utard",
    "iso:country":"FR",
    "sg:address":"Chemin De L Usine Utard 55000 Longeville En Barrois",
    "sg:classifiers":[
        {
            "category":"Professional",
            "type":"Services"
        }
    ],
    "sg:phone":"+33 3 29 77 38 38",
    "sg:province":"Lorraine",
    "sg:tags":[
        "transport",
        "road"
    ],
    "wof:name":"Jige International",
    "wof:placetype":"venue"
},
  "geometry": {"coordinates":[5.084741,48.685223],"type":"Point"}
}