{
  "type": "Feature",
  "properties": {
    "iso:country":"FR",
    "sg:address":"8, Rte de Cabernet - Ch\u00e2teau Tour Bicheau , 33640 Portets",
    "sg:city":"Portets",
    "sg:orig_category":"Non-Classified Establishments",
    "sg:phone":"+33 5 56 67 37 75",
    "sg:postcode":"33640",
    "sg:province":"Aquitaine",
    "wof:name":"Vignobles Daubas Et Fils S.c.e.a.",
    "wof:placetype":"venue"
},
  "geometry": {"coordinates":[-0.402069,44.679958],"type":"Point"}
}