{
  "type": "Feature",
  "properties": {
    "iso:country":"FR",
    "sg:address":"Zone Portuaire de Segonnaux",
    "sg:city":"Arles",
    "sg:orig_category":"Unclassifiable Establishments",
    "sg:phone":"+33 4 90 96 98 08",
    "sg:postcode":"13200",
    "sg:province":"Provence-Alpes-C\u00f4te d'Azur",
    "wof:name":"S.e.d. S.a. - Sud Engrais Distribution",
    "wof:placetype":"venue"
},
  "geometry": {"coordinates":[4.62833,43.675301],"type":"Point"}
}