{
  "type": "Feature",
  "properties": {
    "iso:country":"FR",
    "sg:address":"4, Rue Victor Basch, 91300 Massy",
    "sg:orig_category":"Non-Classified Establishments",
    "sg:phone":"+33 1 69 30 20 50",
    "sg:province":"Ile de France",
    "wof:name":"Les Cars Lecaplain S.a.",
    "wof:placetype":"venue"
},
  "geometry": {"coordinates":[2.270773,48.727394],"type":"Point"}
}