{
  "type": "Feature",
  "properties": {
    "addr:full":"5, Rue des Famards - Centre de Gros Lesquin, 59273 Fretin Nord Pas-de-Calais",
    "addr:housenumber":"5",
    "addr:postcode":"59273",
    "addr:street":"Rue Des Famards",
    "iso:country":"FR",
    "sg:address":"5, Rue des Famards - Centre de Gros Lesquin, 59273 Fretin",
    "sg:orig_category":"Unclassifiable Establishments",
    "sg:phone":"+33 3 20 87 54 02",
    "sg:province":"Nord Pas-de-Calais",
    "wof:name":"Fraikin Location S.a.",
    "wof:placetype":"venue"
},
  "geometry": {"coordinates":[3.133035,50.557724],"type":"Point"}
}