{
  "type": "Feature",
  "properties": {
    "iso:country":"FR",
    "sg:address":"140 Boulevard Haussmann",
    "sg:city":"Paris",
    "sg:classifiers":[
        {
            "category":"Banks & Credit Unions",
            "subcategory":"Financial Services",
            "type":"Services"
        }
    ],
    "sg:phone":"+33 1 45 63 75 09",
    "sg:postcode":"75008",
    "sg:province":"Ile de France",
    "sg:tags":[
        "banking",
        "finance",
        "insurance"
    ],
    "wof:name":"Prorevise Societe D Expertise Comptable Sa",
    "wof:placetype":"venue"
},
  "geometry": {"coordinates":[2.313363,48.875336],"type":"Point"}
}