{
  "type": "Feature",
  "properties": {
    "addr:full":"Route De Nerac Zone Industrielle 32100 Condom Midi Pyr\u00e9n\u00e9es 32100",
    "addr:postcode":"32100;32100",
    "addr:street":"Route De Nerac Zone Industrielle",
    "iso:country":"FR",
    "sg:address":"Route De Nerac Zone Industrielle 32100 Condom",
    "sg:classifiers":[
        {
            "category":"Food Court",
            "type":"Food & Drink"
        }
    ],
    "sg:phone":"+33 5 62 28 04 61",
    "sg:postcode":"32100",
    "sg:province":"Midi Pyr\u00e9n\u00e9es",
    "sg:tags":[
        "product",
        "related"
    ],
    "wof:name":"Compagnie Armagnac Ducastaing St Vivant",
    "wof:placetype":"venue"
},
  "geometry": {"coordinates":[0.334099,43.908184],"type":"Point"}
}