{
  "type": "Feature",
  "properties": {
    "addr:full":"29, Rue Danielle Casanova, 75001 Paris Ile de France",
    "addr:housenumber":"29",
    "addr:postcode":"75001",
    "addr:street":"Rue Danielle Casanova",
    "iso:country":"FR",
    "sg:address":"29, Rue Danielle Casanova, 75001 Paris",
    "sg:orig_category":"Unclassifiable Establishments",
    "sg:phone":"+33 1 42 60 52 22",
    "sg:province":"Ile de France",
    "wof:name":"Tissages Boselli S.a.r.l.",
    "wof:placetype":"venue"
},
  "geometry": {"coordinates":[2.33094,48.868004],"type":"Point"}
}