{
  "type": "Feature",
  "properties": {
    "addr:full":"12 RUE DES LONGUES RAIES 78440 GARGENVILLE Ile de France",
    "addr:housenumber":"12",
    "addr:postcode":"78440",
    "addr:street":"Rue Des Longues Raies;Ile De France",
    "iso:country":"FR",
    "sg:address":"12 RUE DES LONGUES RAIES 78440 GARGENVILLE",
    "sg:classifiers":[
        {
            "category":"Professional",
            "subcategory":"Engineering",
            "type":"Services"
        }
    ],
    "sg:phone":"+33 1 30 93 56 90",
    "sg:province":"Ile de France",
    "sg:tags":[
        "surface"
    ],
    "wof:name":"Revet Service Sarl",
    "wof:placetype":"venue"
},
  "geometry": {"coordinates":[1.802827,48.977589],"type":"Point"}
}