{
  "type": "Feature",
  "properties": {
    "addr:full":"67, Rue des Peseignes, 81300 Graulhet Midi Pyr\u00e9n\u00e9es",
    "addr:housenumber":"67",
    "addr:postcode":"81300",
    "addr:street":"Rue Des Peseignes",
    "iso:country":"FR",
    "sg:address":"67, Rue des Peseignes, 81300 Graulhet",
    "sg:orig_category":"Unclassifiable Establishments",
    "sg:phone":"+33 5 63 34 44 13",
    "sg:province":"Midi Pyr\u00e9n\u00e9es",
    "wof:name":"Bascom France S.n.c.",
    "wof:placetype":"venue"
},
  "geometry": {"coordinates":[1.994018,43.760395],"type":"Point"}
}