{
  "type": "Feature",
  "properties": {
    "addr:full":"Route de Castetner 64300 Biron Castetner Aquitaine 64300",
    "addr:postcode":"64300;64300",
    "addr:street":"Route De Castetner",
    "iso:country":"FR",
    "sg:address":"Route de Castetner 64300 Biron",
    "sg:city":"Castetner",
    "sg:orig_category":"Tin Items, Tinwork, Artisans'",
    "sg:phone":"+33 5 59 69 90 22",
    "sg:postcode":"64300",
    "sg:province":"Aquitaine",
    "wof:name":"Goard\u00e8re Sa",
    "wof:placetype":"venue"
},
  "geometry": {"coordinates":[-0.742425,43.465401],"type":"Point"}
}