{
  "type": "Feature",
  "properties": {
    "iso:country":"FR",
    "sg:address":"102, Rue Anjou, 49540 Martign\u00e9 Briand",
    "sg:orig_category":"Non-Classified Establishments",
    "sg:phone":"+33 2 41 59 42 78",
    "sg:province":"Pays de Loire",
    "wof:name":"Motheron Chantal",
    "wof:placetype":"venue"
},
  "geometry": {"coordinates":[-0.429935,47.233601],"type":"Point"}
}