{
  "type": "Feature",
  "properties": {
    "iso:country":"FR",
    "sg:address":"18, Bd de la Petite Vitesse, 72200 La Fl\u00e8che",
    "sg:orig_category":"Unclassifiable Establishments",
    "sg:phone":"+33 2 43 94 09 24",
    "sg:province":"Pays de Loire",
    "wof:name":"Elidis Boissons Services S.a.",
    "wof:placetype":"venue"
},
  "geometry": {"coordinates":[-0.074029,47.688908],"type":"Point"}
}