{
  "type": "Feature",
  "properties": {
    "addr:full":"2, Rue Alfred Kastler, 44300 Nantes Pays de Loire",
    "addr:housenumber":"2",
    "addr:postcode":"44300",
    "addr:street":"Rue Alfred Kastler",
    "iso:country":"FR",
    "sg:address":"2, Rue Alfred Kastler, 44300 Nantes",
    "sg:orig_category":"Unclassifiable Establishments",
    "sg:phone":"+33 2 40 18 04 05",
    "sg:province":"Pays de Loire",
    "wof:name":"Adepa",
    "wof:placetype":"venue"
},
  "geometry": {"coordinates":[-1.520547,47.281116],"type":"Point"}
}