{
  "type": "Feature",
  "properties": {
    "iso:country":"FR",
    "sg:address":"B.P. 188, 02205 Soissons C\u00e9dex^^Rue Jean-Baptiste Godin - ZI de Villeneuve Saint Germain, 02200 Vill",
    "sg:orig_category":"Non-Classified Establishments",
    "sg:phone":"+33 3 23 53 23 33",
    "sg:province":"Picardie",
    "wof:name":"Olisys S.a.",
    "wof:placetype":"venue"
},
  "geometry": {"coordinates":[3.36555,49.370384],"type":"Point"}
}