{
  "type": "Feature",
  "properties": {
    "iso:country":"FR",
    "sg:address":"92, Rue des Fr\u00e8res Lumi\u00e8re, 93330 Neuilly sur Marne",
    "sg:orig_category":"Unclassifiable Establishments",
    "sg:phone":"+33 1 43 00 26 18",
    "sg:province":"Ile de France",
    "wof:name":"Transports Sitges S.a.r.l.",
    "wof:placetype":"venue"
},
  "geometry": {"coordinates":[2.519702,48.86702],"type":"Point"}
}