{
  "type": "Feature",
  "properties": {
    "iso:country":"FR",
    "sg:address":"Le Gueret 35460 Saint Brice en Cogl\u00e8s",
    "sg:city":"Cogl\u00e8s",
    "sg:orig_category":"Unclassifiable Establishments",
    "sg:phone":"+33 2 99 95 04 05",
    "sg:postcode":"35460",
    "sg:province":"Bretagne",
    "wof:name":"Les Granits Polis S.a.",
    "wof:placetype":"venue"
},
  "geometry": {"coordinates":[-1.340914,48.403534],"type":"Point"}
}