{
  "type": "Feature",
  "properties": {
    "addr:full":"143, Rue L\u00e9on Faucher, 51100 Reims Champagne",
    "addr:housenumber":"143",
    "addr:postcode":"51100",
    "addr:street":"Rue Le\u0301On Faucher",
    "iso:country":"FR",
    "sg:address":"143, Rue L\u00e9on Faucher, 51100 Reims",
    "sg:orig_category":"Unclassifiable Establishments",
    "sg:phone":"+33 3 26 07 38 28",
    "sg:province":"Champagne",
    "wof:name":"Thouvenin Daniel",
    "wof:placetype":"venue"
},
  "geometry": {"coordinates":[4.04359,49.270908],"type":"Point"}
}