{
  "type": "Feature",
  "properties": {
    "addr:full":"8, Rue Mal de Lattre de Tassigny, 59800 Lille Nord Pas-de-Calais 59800",
    "addr:housenumber":"8",
    "addr:postcode":"59800;59800",
    "addr:street":"Rue Mal De Lattre De Tassigny",
    "iso:country":"FR",
    "sg:address":"8, Rue Mal de Lattre de Tassigny, 59800 Lille",
    "sg:orig_category":"Emballage automatiques, Machines d' Emballage final, Machines d' Emballage sous blister et/ou skinpa",
    "sg:phone":"+33 3 20 57 27 16",
    "sg:postcode":"59800",
    "sg:province":"Nord Pas-de-Calais",
    "wof:name":"Coeman Packaging S.a.",
    "wof:placetype":"venue"
},
  "geometry": {"coordinates":[3.055095,50.634968],"type":"Point"}
}