{
  "type": "Feature",
  "properties": {
    "addr:full":"71 Avenue Du Gen De Gaulle Colmar Alsace 68000",
    "addr:housenumber":"71",
    "addr:postcode":"68000",
    "addr:street":"Avenue Du Gen De Gaulle",
    "iso:country":"FR",
    "sg:address":"71 Avenue Du Gen De Gaulle",
    "sg:city":"Colmar",
    "sg:classifiers":[
        {
            "category":"Banks & Credit Unions",
            "subcategory":"Financial Services",
            "type":"Services"
        }
    ],
    "sg:phone":"+33 3 89 22 95 33",
    "sg:postcode":"68000",
    "sg:province":"Alsace",
    "sg:tags":[
        "banking",
        "finance",
        "insurance"
    ],
    "wof:name":"Credit Industriel D'alsace Et De Lorraine (cial)",
    "wof:placetype":"venue"
},
  "geometry": {"coordinates":[7.3403,48.073036],"type":"Point"}
}