{
  "type": "Feature",
  "properties": {
    "iso:country":"FR",
    "sg:address":"B.P. 152, 82001 Montauban C\u00e9dex^^139, Quai Adolphe Poult, 82000 Montauban",
    "sg:orig_category":"Non-Classified Establishments",
    "sg:phone":"+33 5 63 66 13 11",
    "sg:postcode":"82000",
    "sg:province":"Midi Pyr\u00e9n\u00e9es",
    "wof:name":"Eiffage Constructions Midi-pyr\u00e9n\u00e9es S.n.c.",
    "wof:placetype":"venue"
},
  "geometry": {"coordinates":[1.352205,44.016762],"type":"Point"}
}