{
  "type": "Feature",
  "properties": {
    "addr:full":"30 Rue Du Commerce 49600 Le Puiset Dor\u00e9 Pays de Loire",
    "addr:housenumber":"30",
    "addr:postcode":"49600",
    "addr:street":"Rue Du Commerce;Dore\u0301",
    "iso:country":"FR",
    "sg:address":"30 Rue Du Commerce 49600 Le Puiset Dor\u00e9",
    "sg:classifiers":[
        {
            "category":"Home & Garden",
            "subcategory":"Furniture",
            "type":"Retail Goods"
        }
    ],
    "sg:phone":"+33 2 41 56 70 13",
    "sg:province":"Pays de Loire",
    "sg:tags":[
        "wood"
    ],
    "wof:name":"Gaudin Rene Marie Georges Eurl",
    "wof:placetype":"venue"
},
  "geometry": {"coordinates":[-1.119894,47.232735],"type":"Point"}
}