{
  "type": "Feature",
  "properties": {
    "addr:full":"Les Challonges 49270 Le Fuilet Pays de Loire",
    "addr:postcode":"49270",
    "addr:street":"Le Fuilet",
    "iso:country":"FR",
    "sg:address":"Les Challonges 49270 Le Fuilet",
    "sg:orig_category":"Non-Classified Establishments",
    "sg:phone":"+33 2 41 70 53 76",
    "sg:province":"Pays de Loire",
    "wof:name":"Poterie Des Challonges S.a.r.l.",
    "wof:placetype":"venue"
},
  "geometry": {"coordinates":[-1.131737,47.269623],"type":"Point"}
}