{
  "type": "Feature",
  "properties": {
    "addr:full":"11 Rue Jean Jaur\u00e8s Zi De Moimont 95670 Marly La Ville Ile de France",
    "addr:housenumber":"11",
    "addr:postcode":"95670",
    "addr:street":"Rue Jean Jaure\u0300S Zi De Moimont",
    "iso:country":"FR",
    "sg:address":"11 Rue Jean Jaur\u00e8s Zi De Moimont 95670 Marly La Ville",
    "sg:classifiers":[
        {
            "category":"Professional",
            "type":"Services"
        }
    ],
    "sg:phone":"+33 1 34 47 12 47",
    "sg:province":"Ile de France",
    "sg:tags":[
        "transport",
        "road"
    ],
    "wof:name":"Gefco",
    "wof:placetype":"venue"
},
  "geometry": {"coordinates":[2.499715,49.079617],"type":"Point"}
}