{
  "type": "Feature",
  "properties": {
    "addr:full":"151 Av Jean Jaur\u00e8s 47200 Marmande Marmande Aquitaine 47200",
    "addr:postcode":"47200;47200",
    "addr:street":"151 Av Jean Jaure\u0300S",
    "iso:country":"FR",
    "sg:address":"151 Av Jean Jaur\u00e8s 47200 Marmande",
    "sg:city":"Marmande",
    "sg:classifiers":[
        {
            "category":"Shopping",
            "subcategory":"Computers & Home Electronics",
            "type":"Retail Goods"
        }
    ],
    "sg:phone":"+33 5 53 64 24 54",
    "sg:postcode":"47200",
    "sg:province":"Aquitaine",
    "sg:tags":[
        "electric",
        "electricity",
        "component",
        "equipment",
        "electrical",
        "electronic"
    ],
    "wof:name":"Comptoir Du Sud Ouest",
    "wof:placetype":"venue"
},
  "geometry": {"coordinates":[0.146311,44.506882],"type":"Point"}
}