{
  "type": "Feature",
  "properties": {
    "iso:country":"FR",
    "sg:address":"3",
    "sg:city":"Redon",
    "sg:classifiers":[
        {
            "category":"Banks & Credit Unions",
            "subcategory":"Bank",
            "type":"Services"
        }
    ],
    "sg:phone":"+33 3399710021",
    "sg:postcode":"35600",
    "sg:province":"Bretagne",
    "wof:name":"Soci\u00e9t\u00e9 G\u00e9n\u00e9rale",
    "wof:placetype":"venue"
},
  "geometry": {"coordinates":[-2.084673,47.65184],"type":"Point"}
}