{
  "type": "Feature",
  "properties": {
    "addr:full":"12 R Louis Bl\u00e9riot 63017 Clermont Ferrand Cedex 2 Clermont Rhone-Alpes 74270",
    "addr:housenumber":"12",
    "addr:postcode":"63017;74270",
    "addr:street":"R Louis Ble\u0301Riot",
    "iso:country":"FR",
    "sg:address":"12 R Louis Bl\u00e9riot 63017 Clermont Ferrand Cedex 2",
    "sg:city":"Clermont",
    "sg:classifiers":[
        {
            "category":"Health Services",
            "subcategory":"Medical Lab",
            "type":"Services"
        }
    ],
    "sg:phone":"+33 4 73 98 14 36",
    "sg:postcode":"74270",
    "sg:province":"Rhone-Alpes",
    "sg:tags":[
        "chemical",
        "pharmaceutical",
        "pharmacy"
    ],
    "wof:name":"Laboratoires Thea Sa",
    "wof:placetype":"venue"
},
  "geometry": {"coordinates":[3.149455,45.805447],"type":"Point"}
}