{
  "type": "Feature",
  "properties": {
    "iso:country":"FR",
    "sg:address":"9/11, Rue de l' Aubetin, 77120 Coulommiers",
    "sg:orig_category":"Non-Classified Establishments",
    "sg:phone":"+33 1 64 75 82 82",
    "sg:province":"Ile de France",
    "wof:name":"Verre Plus S.a.r.l.",
    "wof:placetype":"venue"
},
  "geometry": {"coordinates":[3.093886,48.803429],"type":"Point"}
}