{
  "type": "Feature",
  "properties": {
    "iso:country":"FR",
    "sg:address":"4 Rue Saint-Jacques 13006 Marseille",
    "sg:classifiers":[
        {
            "category":"Shopping",
            "subcategory":"Clothing, Apparel, & Fashions",
            "type":"Retail Goods"
        }
    ],
    "sg:phone":"+33 4 91 37 45 50",
    "sg:province":"Nord Pas-de-Calais",
    "sg:tags":[
        "textile",
        "clothing",
        "clothes"
    ],
    "wof:name":"Belissa (sarl)",
    "wof:placetype":"venue"
},
  "geometry": {"coordinates":[5.38138,43.289436],"type":"Point"}
}