{
  "type": "Feature",
  "properties": {
    "addr:full":"50, Chemin de l'Etoile, 38330 Montbonnot Saint Martin Rhone-Alpes 38330",
    "addr:housenumber":"50",
    "addr:postcode":"38330;38330",
    "addr:street":"Chemin De L'Etoile;Rhone-Alpes",
    "iso:country":"FR",
    "sg:address":"50, Chemin de l'Etoile, 38330 Montbonnot Saint Martin",
    "sg:orig_category":"Non-Classified Establishments",
    "sg:phone":"+33 4 76 41 28 27",
    "sg:postcode":"38330",
    "sg:province":"Rhone-Alpes",
    "wof:name":"Cabinet Bigallet-miard S.a.r.l.",
    "wof:placetype":"venue"
},
  "geometry": {"coordinates":[5.810732,45.219276],"type":"Point"}
}