{
  "type": "Feature",
  "properties": {
    "iso:country":"FR",
    "sg:address":"12 rue Paul Langevin 49240 Avrille",
    "sg:classifiers":[
        {
            "category":"Autos & Motor Vehicles",
            "subcategory":"Automobile Sales",
            "type":"Retail Goods"
        }
    ],
    "sg:phone":"+33 2 41 21 13 59",
    "sg:province":"Pays de Loire",
    "sg:tags":[
        "passenger",
        "car"
    ],
    "wof:name":"Simpa Sa",
    "wof:placetype":"venue"
},
  "geometry": {"coordinates":[-0.609207,47.518288],"type":"Point"}
}