{
  "type": "Feature",
  "properties": {
    "iso:country":"FR",
    "sg:address":"B.P. 1618, 27016 Evreux C\u00e9dex^^Rue Alfred Nobel - ZI 1, 27000 Evreux",
    "sg:orig_category":"Non-Classified Establishments",
    "sg:phone":"+33 2 32 29 66 66",
    "sg:province":"Haute Normandie",
    "wof:name":"Soci\u00e9t\u00e9 Varillon S.a.",
    "wof:placetype":"venue"
},
  "geometry": {"coordinates":[1.150283,49.027546],"type":"Point"}
}