{
  "type": "Feature",
  "properties": {
    "iso:country":"FR",
    "sg:address":"B.P. 11, 13274 Marseille C\u00e9dex 09^^ZAC de la Jarre - ., 13009 Marseille",
    "sg:orig_category":"Non-Classified Establishments",
    "sg:phone":"+33 4 91 17 63 00",
    "sg:province":"Provence-Alpes-C\u00f4te d'Azur",
    "wof:name":"M.a.s. S.a.s.",
    "wof:placetype":"venue"
},
  "geometry": {"coordinates":[5.401315,43.248466],"type":"Point"}
}