{
  "type": "Feature",
  "properties": {
    "addr:full":"B.P. 5529, 44354 Gu\u00e9rande C\u00e9dex^^Site de Kerquessaud, 44350 Gu\u00e9rande Pays de Loire",
    "addr:postcode":"44354;44350",
    "addr:street":"B.P. 5529;Kerquessaud",
    "iso:country":"FR",
    "sg:address":"B.P. 5529, 44354 Gu\u00e9rande C\u00e9dex^^Site de Kerquessaud, 44350 Gu\u00e9rande",
    "sg:orig_category":"Non-Classified Establishments",
    "sg:phone":"+33 2 40 11 21 00",
    "sg:province":"Pays de Loire",
    "wof:name":"M.s.l. France Op\u00e9rations S.a.s.",
    "wof:placetype":"venue"
},
  "geometry": {"coordinates":[-2.39309,47.292137],"type":"Point"}
}