{
  "type": "Feature",
  "properties": {
    "addr:full":"19, Av. de Cigogne, 13012 Marseille Provence-Alpes-C\u00f4te d'Azur",
    "addr:postcode":"13012",
    "addr:street":"19 Av. De Cigogne",
    "iso:country":"FR",
    "sg:address":"19, Av. de Cigogne, 13012 Marseille",
    "sg:orig_category":"Non-Classified Establishments",
    "sg:phone":"+33 4 91 88 05 83",
    "sg:province":"Provence-Alpes-C\u00f4te d'Azur",
    "wof:name":"Soci\u00e9t\u00e9 D'henri Et Fils Informatique S.a.r.l.",
    "wof:placetype":"venue"
},
  "geometry": {"coordinates":[5.416456,43.305122],"type":"Point"}
}