{
  "type": "Feature",
  "properties": {
    "addr:full":"49 Rue Pierre Corneille 69006 Lyon Rhone-Alpes",
    "addr:housenumber":"49",
    "addr:postcode":"69006",
    "addr:street":"Rue Pierre Corneille",
    "iso:country":"FR",
    "sg:address":"49 Rue Pierre Corneille 69006 Lyon",
    "sg:classifiers":[
        {
            "category":"Shopping",
            "subcategory":"Clothing, Apparel, & Fashions",
            "type":"Retail Goods"
        }
    ],
    "sg:phone":"+33 4 78 24 33 74",
    "sg:province":"Rhone-Alpes",
    "sg:tags":[
        "textile",
        "clothing",
        "clothes"
    ],
    "wof:name":"Nouvelle Industrie Du Vetement Sa",
    "wof:placetype":"venue"
},
  "geometry": {"coordinates":[4.849785,45.769245],"type":"Point"}
}