{
  "type": "Feature",
  "properties": {
    "iso:country":"FR",
    "sg:address":"31, Rue Cl\u00e9menceau, 57430 Sarralbe",
    "sg:orig_category":"Unclassifiable Establishments",
    "sg:phone":"+33 3 87 97 81 23",
    "sg:province":"Lorraine",
    "wof:name":"Wollenschneider S.a.r.l.",
    "wof:placetype":"venue"
},
  "geometry": {"coordinates":[7.030859,48.999828],"type":"Point"}
}