{
  "type": "Feature",
  "properties": {
    "iso:country":"FR",
    "sg:address":"B.P. 2, 54720 Lexy^^84, Rue du Mal Foch, 54720 Lexy",
    "sg:orig_category":"Non-Classified Establishments",
    "sg:phone":"+33 3 82 23 26 33",
    "sg:postcode":"54720",
    "sg:province":"Lorraine",
    "wof:name":"Colle Fr\u00e8res S.a.",
    "wof:placetype":"venue"
},
  "geometry": {"coordinates":[5.731524,49.500458],"type":"Point"}
}