{
  "type": "Feature",
  "properties": {
    "iso:country":"FR",
    "sg:address":"Dampierre 52360 Neuilly L Eveque",
    "sg:classifiers":[
        {
            "category":"Home & Garden",
            "subcategory":"Furniture",
            "type":"Retail Goods"
        }
    ],
    "sg:phone":"+33 3 25 84 02 41",
    "sg:postcode":"52360",
    "sg:province":"Champagne",
    "sg:tags":[
        "household",
        "wood"
    ],
    "wof:name":"Drapt Gilles",
    "wof:placetype":"venue"
},
  "geometry": {"coordinates":[5.442607,47.916428],"type":"Point"}
}