{
  "type": "Feature",
  "properties": {
    "iso:country":"FR",
    "sg:address":"8, Av. d'Orl\u00e9ans, 41300 Salbris",
    "sg:city":"Salbris",
    "sg:orig_category":"Non-Classified Establishments",
    "sg:phone":"+33 2 54 97 18 53",
    "sg:postcode":"41300",
    "sg:province":"Centre",
    "wof:name":"Le Parc",
    "wof:placetype":"venue"
},
  "geometry": {"coordinates":[2.05198,47.426991],"type":"Point"}
}