{
  "type": "Feature",
  "properties": {
    "iso:country":"FR",
    "sg:address":"Immeuble Le Cid",
    "sg:city":"Sanary; 83110",
    "sg:classifiers":[
        {
            "category":"Banks & Credit Unions",
            "subcategory":"Bank",
            "type":"Services"
        }
    ],
    "sg:phone":"+33 3394740872",
    "sg:province":"Haute Normandie",
    "wof:name":"Banque Nationale De Paris",
    "wof:placetype":"venue"
},
  "geometry": {"coordinates":[5.80096,43.117786],"type":"Point"}
}