{
  "type": "Feature",
  "properties": {
    "iso:country":"FR",
    "sg:address":"B.P. 32",
    "sg:city":"Juran\u00e7on",
    "sg:orig_category":"Non-Classified Establishments",
    "sg:phone":"+33 5 59 06 36 88",
    "sg:postcode":"64110",
    "sg:province":"Aquitaine",
    "wof:name":"M.t.p. S.a. - Manufactures Des Tissus Du Pyr\u00e9n\u00e9es",
    "wof:placetype":"venue"
},
  "geometry": {"coordinates":[-0.390229,43.287868],"type":"Point"}
}