{
  "type": "Feature",
  "properties": {
    "addr:full":"58, Av. Henri Barbusse, 92140 Clamart Ile de France",
    "addr:postcode":"92140;ile",
    "addr:street":"58 Av. Henri Barbusse",
    "iso:country":"FR",
    "sg:address":"58, Av. Henri Barbusse, 92140 Clamart",
    "sg:orig_category":"Unclassifiable Establishments",
    "sg:phone":"+33 1 46 42 00 34",
    "sg:province":"Ile de France",
    "wof:name":"Imprim' Union S.a.",
    "wof:placetype":"venue"
},
  "geometry": {"coordinates":[2.258694,48.809494],"type":"Point"}
}