{
  "type": "Feature",
  "properties": {
    "addr:full":"Z ArtisanaleRoute De Blaye 17210 BUSSAC FORET Poitou-Charentes 17210",
    "addr:postcode":"17210;17210",
    "addr:street":"Foret",
    "iso:country":"FR",
    "sg:address":"Z ArtisanaleRoute De Blaye 17210 BUSSAC FORET",
    "sg:classifiers":[
        {
            "category":"Education",
            "subcategory":"Special Training",
            "type":"Public Place"
        }
    ],
    "sg:phone":"+33 5 46 04 31 01",
    "sg:postcode":"17210",
    "sg:province":"Poitou-Charentes",
    "sg:tags":[
        "bread"
    ],
    "wof:name":"Pin Decor Sa",
    "wof:placetype":"venue"
},
  "geometry": {"coordinates":[-0.300861,45.166016],"type":"Point"}
}