{
  "type": "Feature",
  "properties": {
    "addr:full":"B.P. 7, 74580 Viry^^1176, Rue de la Gare - Les Grands Champs Sud , 74580 Viry Rhone-Alpes 74580",
    "addr:housenumber":"7",
    "addr:postcode":"74580;74580;74580",
    "addr:street":"B.P.;Rue De La Gare Les Grands Champs Sud",
    "iso:country":"FR",
    "sg:address":"B.P. 7, 74580 Viry^^1176, Rue de la Gare - Les Grands Champs Sud , 74580 Viry",
    "sg:orig_category":"Non-Classified Establishments",
    "sg:phone":"+33 4 50 04 76 87",
    "sg:postcode":"74580",
    "sg:province":"Rhone-Alpes",
    "wof:name":"Coop\u00e9rative Jura Mont Blanc",
    "wof:placetype":"venue"
},
  "geometry": {"coordinates":[6.037754,46.117142],"type":"Point"}
}