{
  "type": "Feature",
  "properties": {
    "addr:full":"29 Rue De Turbigo Paris Ile de France 75002",
    "addr:housenumber":"29",
    "addr:postcode":"75002",
    "addr:street":"Rue De Turbigo",
    "iso:country":"FR",
    "sg:address":"29 Rue De Turbigo",
    "sg:city":"Paris",
    "sg:classifiers":[
        {
            "category":"Banks & Credit Unions",
            "subcategory":"Financial Services",
            "type":"Services"
        }
    ],
    "sg:phone":"+33 1 40 39 75 63",
    "sg:postcode":"75002",
    "sg:province":"Ile de France",
    "sg:tags":[
        "banking",
        "finance",
        "insurance"
    ],
    "wof:name":"Mutuelle Nationale De La Presse Du Livre Et De La Communication",
    "wof:placetype":"venue"
},
  "geometry": {"coordinates":[2.35082,48.864319],"type":"Point"}
}