{
  "type": "Feature",
  "properties": {
    "iso:country":"FR",
    "sg:address":"12, Rue Soddy, 94044 Cr\u00e9teil C\u00e9dex",
    "sg:orig_category":"Non-Classified Establishments",
    "sg:phone":"+33 1 41 94 11 50",
    "sg:province":"\u00cele-de-France",
    "wof:name":"Sollas France S.a.",
    "wof:placetype":"venue"
},
  "geometry": {"coordinates":[2.475278,48.767838],"type":"Point"}
}