{
  "type": "Feature",
  "properties": {
    "addr:full":"32 bis, Rue Gutenberg - ZA de la Marini\u00e8re, 91919 Bondoufle C\u00e9dex Berg Alsace 67320",
    "addr:housenumber":"32 bis",
    "addr:postcode":"91919;ce\u0301dex;67320",
    "addr:street":"Rue Gutenberg Za De La Marinie\u0300Re;Berg",
    "iso:country":"FR",
    "sg:address":"32 bis, Rue Gutenberg - ZA de la Marini\u00e8re, 91919 Bondoufle C\u00e9dex",
    "sg:city":"Berg",
    "sg:orig_category":"Non-Classified Establishments",
    "sg:phone":"+33 1 69 91 49 00",
    "sg:postcode":"67320",
    "sg:province":"Alsace",
    "wof:name":"Composite Industrie S.a.",
    "wof:placetype":"venue"
},
  "geometry": {"coordinates":[2.37735,48.615971],"type":"Point"}
}