{
  "type": "Feature",
  "properties": {
    "iso:country":"FR",
    "sg:address":"7 Rue Alfred Mongy 59700 Marcq En Baroeul",
    "sg:classifiers":[
        {
            "category":"Shopping",
            "subcategory":"Clothing, Apparel, & Fashions",
            "type":"Retail Goods"
        }
    ],
    "sg:phone":"+33 3 20 72 57 72",
    "sg:postcode":"59700",
    "sg:province":"Nord Pas-de-Calais",
    "sg:tags":[
        "textile",
        "clothing",
        "clothes"
    ],
    "wof:name":"Regionale De Location Et Services Textiles (rlst) Elis Nord Localinge",
    "wof:placetype":"venue"
},
  "geometry": {"coordinates":[3.102736,50.65419],"type":"Point"}
}