{
  "type": "Feature",
  "properties": {
    "addr:full":"B.P. 80118, 29401 Landivisiau C\u00e9dex^^1, Rue des Ch\u00e2taigniers, 29400 Landivisiau Landivisiau Bretagne 29400",
    "addr:postcode":"29401;29400;29400",
    "addr:street":"Rue Des Cha\u0302Taigniers",
    "iso:country":"FR",
    "sg:address":"B.P. 80118, 29401 Landivisiau C\u00e9dex^^1, Rue des Ch\u00e2taigniers, 29400 Landivisiau",
    "sg:city":"Landivisiau",
    "sg:orig_category":"Non-Classified Establishments",
    "sg:phone":"+33 2 98 68 00 20",
    "sg:postcode":"29400",
    "sg:province":"Bretagne",
    "wof:name":"Aldouest S.a.",
    "wof:placetype":"venue"
},
  "geometry": {"coordinates":[-4.004424,48.445419],"type":"Point"}
}