{
  "type": "Feature",
  "properties": {
    "addr:full":"2 Rue Gabriel Vicaire 75003 Paris Ile de France 75003",
    "addr:housenumber":"2",
    "addr:postcode":"75003;75003",
    "addr:street":"Rue Gabriel Vicaire",
    "iso:country":"FR",
    "sg:address":"2 Rue Gabriel Vicaire 75003 Paris",
    "sg:classifiers":[
        {
            "category":"Communications",
            "type":"Services"
        }
    ],
    "sg:phone":"+33 1 48 87 62 26",
    "sg:postcode":"75003",
    "sg:province":"Ile de France",
    "sg:tags":[
        "translation",
        "training",
        "interpretation",
        "advice",
        "business"
    ],
    "wof:name":"Asples",
    "wof:placetype":"venue"
},
  "geometry": {"coordinates":[2.361817,48.864872],"type":"Point"}
}