{
  "type": "Feature",
  "properties": {
    "addr:full":"B.P. 109, 44406 Rez\u00e9 C\u00e9dex^^Rue du Seil, 44400 Rez\u00e9 Pays de Loire",
    "addr:housenumber":"b.p. 109",
    "addr:postcode":"44406;44400",
    "addr:street":"Seil",
    "iso:country":"FR",
    "sg:address":"B.P. 109, 44406 Rez\u00e9 C\u00e9dex^^Rue du Seil, 44400 Rez\u00e9",
    "sg:orig_category":"Non-Classified Establishments",
    "sg:phone":"+33 2 40 75 52 02",
    "sg:province":"Pays de Loire",
    "wof:name":"Lemasson Marcel S.a.",
    "wof:placetype":"venue"
},
  "geometry": {"coordinates":[-1.569829,47.191238],"type":"Point"}
}