{
  "type": "Feature",
  "properties": {
    "iso:country":"FR",
    "sg:address":"76170 St Nicolas De La Taille",
    "sg:classifiers":[
        {
            "category":"Autos & Motor Vehicles",
            "subcategory":"Boat Sales",
            "type":"Retail Goods"
        }
    ],
    "sg:phone":"+33 2 35 39 80 37",
    "sg:postcode":"76170",
    "sg:province":"Haute Normandie",
    "sg:tags":[
        "equipment",
        "transport"
    ],
    "wof:name":"Chantiers Pierre Hauchard",
    "wof:placetype":"venue"
},
  "geometry": {"coordinates":[0.473374,49.51202],"type":"Point"}
}