{
  "type": "Feature",
  "properties": {
    "addr:full":"Rte De St-Louet 14280 Authie Authie Basse Normandie 14280",
    "addr:postcode":"14280;14280",
    "addr:street":"Rte De St-Louet",
    "iso:country":"FR",
    "sg:address":"Rte De St-Louet 14280 Authie",
    "sg:city":"Authie",
    "sg:classifiers":[
        {
            "category":"Manufacturing",
            "subcategory":"Paper Products",
            "type":"Manufacturing & Wholesale Goods"
        }
    ],
    "sg:phone":"+33 2 31 71 20 00",
    "sg:postcode":"14280",
    "sg:province":"Basse Normandie",
    "sg:tags":[
        "pharmaceutical",
        "cardboard",
        "fabric",
        "-",
        "chemical",
        "linen",
        "chemistry",
        "by-product"
    ],
    "wof:name":"Cyjoco Sarl",
    "wof:placetype":"venue"
},
  "geometry": {"coordinates":[-0.432333,49.207088],"type":"Point"}
}