{
  "type": "Feature",
  "properties": {
    "iso:country":"FR",
    "sg:address":"5 R Du Chauffour 60271 Gouvieux Cedex",
    "sg:classifiers":[
        {
            "category":"Professional",
            "subcategory":"Business Services",
            "type":"Services"
        }
    ],
    "sg:phone":"+33 3 44 57 07 02",
    "sg:province":"Haute Normandie",
    "sg:tags":[
        "training",
        "advice"
    ],
    "wof:name":"Afasec",
    "wof:placetype":"venue"
},
  "geometry": {"coordinates":[2.443191,49.189903],"type":"Point"}
}