{
  "type": "Feature",
  "properties": {
    "iso:country":"FR",
    "sg:address":"9",
    "sg:city":"Quimper",
    "sg:classifiers":[
        {
            "category":"Professional",
            "subcategory":"Engineering",
            "type":"Services"
        }
    ],
    "sg:phone":"+33 2 98 94 66 00",
    "sg:postcode":"29000",
    "sg:province":"Bretagne",
    "sg:tags":[
        "machine",
        "pharmacy",
        "-",
        "mechanical"
    ],
    "wof:name":"C.m.a (construction Mecanique D'armorique)",
    "wof:placetype":"venue"
},
  "geometry": {"coordinates":[-4.107947,47.99469],"type":"Point"}
}