{
  "type": "Feature",
  "properties": {
    "iso:country":"FR",
    "sg:address":"Place Jean Jaur\u00e9s",
    "sg:city":"Romans sur Is\u00e8re",
    "sg:orig_category":"Non-Classified Establishments",
    "sg:phone":"+33 4 75 02 95 35",
    "sg:postcode":"26100",
    "sg:province":"Rhone-Alpes",
    "wof:name":"Cit\u00e9bus Des Deux Rives S.a.r.l.",
    "wof:placetype":"venue"
},
  "geometry": {"coordinates":[5.052835,45.04599],"type":"Point"}
}