{
  "type": "Feature",
  "properties": {
    "addr:full":"45, All\u00e9e du Mans - Parc d'Activit\u00e9s du Mans, 69100 Villeurbanne Rhone-Alpes 69100",
    "addr:housenumber":"45",
    "addr:postcode":"69100;69100",
    "addr:street":"Alle\u0301E Du Mans Parc D'Activite \u0301S Du Mans",
    "iso:country":"FR",
    "sg:address":"45, All\u00e9e du Mans - Parc d'Activit\u00e9s du Mans, 69100 Villeurbanne",
    "sg:orig_category":"Non-Classified Establishments",
    "sg:phone":"+33 4 72 04 68 73",
    "sg:postcode":"69100",
    "sg:province":"Rhone-Alpes",
    "wof:name":"I.t.i. S.a. - Innovation Et Techniques Industrielles",
    "wof:placetype":"venue"
},
  "geometry": {"coordinates":[4.88982,45.771992],"type":"Point"}
}