{
  "type": "Feature",
  "properties": {
    "iso:country":"FR",
    "sg:address":"5 Rue Des Petites Maulevries",
    "sg:city":"Angers",
    "sg:classifiers":[
        {
            "category":"Banks & Credit Unions",
            "subcategory":"Financial Services",
            "type":"Services"
        }
    ],
    "sg:phone":"+33 2 41 44 33 88",
    "sg:postcode":"49000",
    "sg:province":"Pays de Loire",
    "sg:tags":[
        "banking",
        "finance",
        "insurance"
    ],
    "wof:name":"Societe Fiduciaire D'expertise Comptable De Gestion Et De Re (socogere)",
    "wof:placetype":"venue"
},
  "geometry": {"coordinates":[-0.545864,47.450577],"type":"Point"}
}