{
  "type": "Feature",
  "properties": {
    "iso:country":"FR",
    "sg:address":"9, rue Emile Zola, 80390 Fressenneville",
    "sg:orig_category":"Non-Classified Establishments",
    "sg:phone":"+33 3 22 30 38 45",
    "sg:province":"Picardie",
    "wof:name":"Malbranche Et Fils S.a.r.l.",
    "wof:placetype":"venue"
},
  "geometry": {"coordinates":[1.576948,50.063789],"type":"Point"}
}