{
  "type": "Feature",
  "properties": {
    "iso:country":"FR",
    "sg:address":"9 Chaussee Jules Cesar Zac Beaux Soleils Batiment 3 333 95520 Osny",
    "sg:classifiers":[
        {
            "category":"Professional",
            "subcategory":"Printing & Photocopies",
            "type":"Services"
        }
    ],
    "sg:phone":"+33 1 30 73 08 31",
    "sg:province":"Ile de France",
    "sg:tags":[
        "publishing"
    ],
    "wof:name":"Integral Plus",
    "wof:placetype":"venue"
},
  "geometry": {"coordinates":[2.064945,49.064018],"type":"Point"}
}