{
  "type": "Feature",
  "properties": {
    "addr:full":"La Petite Gare 56800 Ploermel Plo\u00ebrmel Bretagne 56800",
    "addr:postcode":"56800;56800",
    "addr:street":"Ploe\u0308Rmel",
    "iso:country":"FR",
    "sg:address":"La Petite Gare 56800 Ploermel",
    "sg:city":"Plo\u00ebrmel",
    "sg:classifiers":[
        {
            "category":"Farming",
            "subcategory":"Farm",
            "type":"Manufacturing & Wholesale Goods"
        }
    ],
    "sg:phone":"+33 2 97 74 00 69",
    "sg:postcode":"56800",
    "sg:province":"Bretagne",
    "sg:tags":[
        "horticulture",
        "agriculture",
        "livestock"
    ],
    "wof:name":"Centrale Cooperative Agricole Bretonne (cecab)",
    "wof:placetype":"venue"
},
  "geometry": {"coordinates":[-2.357955,47.879848],"type":"Point"}
}