{
  "type": "Feature",
  "properties": {
    "iso:country":"FR",
    "sg:address":"69 Avenue Du Prado",
    "sg:city":"Marseille",
    "sg:classifiers":[
        {
            "category":"Banks & Credit Unions",
            "subcategory":"Financial Services",
            "type":"Services"
        }
    ],
    "sg:phone":"+33 4 91 83 40 00",
    "sg:postcode":"13006",
    "sg:province":"Provence-Alpes-C\u00f4te d'Azur",
    "sg:tags":[
        "banking",
        "finance",
        "insurance"
    ],
    "wof:name":"Axa Collectives",
    "wof:placetype":"venue"
},
  "geometry": {"coordinates":[5.386304,43.282368],"type":"Point"}
}