{
  "type": "Feature",
  "properties": {
    "addr:full":"Rue Edouard Lavoine Dieppe C\u00e9dex Basse Normandie 76376",
    "addr:postcode":"76376",
    "addr:street":"Rue Edouard Lavoine",
    "iso:country":"FR",
    "sg:address":"Rue Edouard Lavoine",
    "sg:city":"Dieppe C\u00e9dex",
    "sg:orig_category":"Non-Classified Establishments",
    "sg:phone":"+33 2 35 82 51 40",
    "sg:postcode":"76376",
    "sg:province":"Basse Normandie",
    "wof:name":"Arno Normandie S.a.",
    "wof:placetype":"venue"
},
  "geometry": {"coordinates":[1.08326,49.924866],"type":"Point"}
}