{
  "type": "Feature",
  "properties": {
    "addr:full":"183 Pl Fran\u00e7ois Tourel 84300 Cavaillon Fran\u00e7ois Poitou-Charentes 79260",
    "addr:housenumber":"183",
    "addr:postcode":"84300;79260",
    "addr:street":"Pl Franc\u0327Ois Tourel;Franc\u0327Ois",
    "iso:country":"FR",
    "sg:address":"183 Pl Fran\u00e7ois Tourel 84300 Cavaillon",
    "sg:city":"Fran\u00e7ois",
    "sg:classifiers":[
        {
            "category":"Travel",
            "subcategory":"Hotels & Motels",
            "type":"Entertainment"
        }
    ],
    "sg:phone":"+33 4 90 71 57 78",
    "sg:postcode":"79260",
    "sg:province":"Poitou-Charentes",
    "sg:tags":[
        "hotels",
        "business",
        "restaurant"
    ],
    "wof:name":"Hotel Du Parc ** Nn",
    "wof:placetype":"venue"
},
  "geometry": {"coordinates":[5.034652,43.833961],"type":"Point"}
}