{
  "type": "Feature",
  "properties": {
    "addr:full":"Ch\u00e2teau Corbin Saint Emilion Aquitaine 33330",
    "addr:postcode":"33330",
    "addr:street":"Saint",
    "iso:country":"FR",
    "sg:address":"Ch\u00e2teau Corbin",
    "sg:city":"Saint Emilion",
    "sg:orig_category":"Unclassifiable Establishments",
    "sg:phone":"+33 5 57 25 20 30",
    "sg:postcode":"33330",
    "sg:province":"Aquitaine",
    "wof:name":"Ch\u00e2teau Corbin S.c.a.",
    "wof:placetype":"venue"
},
  "geometry": {"coordinates":[-0.156634,44.892399],"type":"Point"}
}