{
  "type": "Feature",
  "properties": {
    "addr:full":"3, Quai Til Sitt, 69002 Lyon Rhone-Alpes 69002",
    "addr:housenumber":"3",
    "addr:postcode":"69002;69002",
    "addr:street":"Quai Til Sitt",
    "iso:country":"FR",
    "sg:address":"3, Quai Til Sitt, 69002 Lyon",
    "sg:orig_category":"Non-Classified Establishments",
    "sg:phone":"+33 4 78 42 89 71",
    "sg:postcode":"69002",
    "sg:province":"Rhone-Alpes",
    "wof:name":"Tech Style S.a.r.l.",
    "wof:placetype":"venue"
},
  "geometry": {"coordinates":[4.829577,45.759125],"type":"Point"}
}