{
  "type": "Feature",
  "properties": {
    "addr:full":"24 Rue Leinster 44240 La Chapelle Sur Erdre Pays de Loire 44240",
    "addr:housenumber":"24",
    "addr:postcode":"44240;44240",
    "addr:street":"Rue Leinster;Chapelle;Erdre",
    "iso:country":"FR",
    "sg:address":"24 Rue Leinster 44240 La Chapelle Sur Erdre",
    "sg:classifiers":[
        {
            "category":"Professional",
            "subcategory":"Engineering",
            "type":"Services"
        }
    ],
    "sg:phone":"+33 2 40 72 87 12",
    "sg:postcode":"44240",
    "sg:province":"Pays de Loire",
    "sg:tags":[
        "machine",
        "-",
        "mechanical"
    ],
    "wof:name":"Atlantic Climat Sas",
    "wof:placetype":"venue"
},
  "geometry": {"coordinates":[-1.552079,47.282059],"type":"Point"}
}