{
  "type": "Feature",
  "properties": {
    "iso:country":"FR",
    "sg:address":"181 Rue Lucien Larnicol 29760 Penmarch",
    "sg:city":"Penmarch",
    "sg:classifiers":[
        {
            "category":"Autos & Motor Vehicles",
            "subcategory":"Boat Sales",
            "type":"Retail Goods"
        }
    ],
    "sg:phone":"+33 2 98 58 62 72",
    "sg:postcode":"29760",
    "sg:province":"Bretagne",
    "sg:tags":[
        "equipment",
        "transport"
    ],
    "wof:name":"Diougoant Sa",
    "wof:placetype":"venue"
},
  "geometry": {"coordinates":[-4.377327,47.818882],"type":"Point"}
}