{
  "type": "Feature",
  "properties": {
    "addr:full":"4, Rue de la Croix Faubin, 75011 Paris Ile de France",
    "addr:housenumber":"4",
    "addr:postcode":"75011",
    "addr:street":"Rue De La Croix Faubin",
    "iso:country":"FR",
    "sg:address":"4, Rue de la Croix Faubin, 75011 Paris",
    "sg:orig_category":"Unclassifiable Establishments",
    "sg:phone":"+33 1 43 98 76 90",
    "sg:province":"Ile de France",
    "wof:name":"Dehon Service S.a.",
    "wof:placetype":"venue"
},
  "geometry": {"coordinates":[2.386221,48.857761],"type":"Point"}
}