{
  "type": "Feature",
  "properties": {
    "iso:country":"FR",
    "sg:address":"La For\u00eat Du Ch\u00e2teau 61550 La Fert\u00e9 Fr\u00e9nel",
    "sg:city":"Anceins",
    "sg:classifiers":[
        {
            "category":"Manufacturing",
            "subcategory":"Tools & Machinery",
            "type":"Manufacturing & Wholesale Goods"
        }
    ],
    "sg:phone":"+33 2 33 34 66 29",
    "sg:postcode":"61550",
    "sg:province":"Basse Normandie",
    "sg:tags":[
        "metallurgy",
        "metalworking",
        "processing",
        "metal"
    ],
    "wof:name":"Nomel Sas",
    "wof:placetype":"venue"
},
  "geometry": {"coordinates":[-85.478325,37.016586],"type":"Point"}
}