{
  "type": "Feature",
  "properties": {
    "addr:full":"Rte de Lyon - ZA des Cerisiers Lozanne Rhone-Alpes 69380",
    "addr:postcode":"69380",
    "addr:street":"Rte De Lyon Za Des Cerisiers;Rhone-Alpes",
    "iso:country":"FR",
    "sg:address":"Rte de Lyon - ZA des Cerisiers",
    "sg:city":"Lozanne",
    "sg:orig_category":"Non-Classified Establishments",
    "sg:phone":"+33 4 78 43 70 17",
    "sg:postcode":"69380",
    "sg:province":"Rhone-Alpes",
    "wof:name":"Sotrager S.a.",
    "wof:placetype":"venue"
},
  "geometry": {"coordinates":[4.71535,45.835541],"type":"Point"}
}