{
  "type": "Feature",
  "properties": {
    "addr:full":"La Reclaine 69240 Thizy Rhone-Alpes 69240",
    "addr:postcode":"69240;69240",
    "iso:country":"FR",
    "sg:address":"La Reclaine 69240 Thizy",
    "sg:classifiers":[
        {
            "category":"Shopping",
            "subcategory":"Crafts & Fabrics",
            "type":"Retail Goods"
        }
    ],
    "sg:phone":"+33 4 74 64 58 50",
    "sg:postcode":"69240",
    "sg:province":"Rhone-Alpes",
    "sg:tags":[
        "textile",
        "clothing"
    ],
    "wof:name":"Societe Stet Sas",
    "wof:placetype":"venue"
},
  "geometry": {"coordinates":[4.314613,46.036469],"type":"Point"}
}