{
  "type": "Feature",
  "properties": {
    "iso:country":"FR",
    "sg:address":"Zi Sud",
    "sg:city":"Rue Louis Amp\u00e8re 67400 Illkirch Graffenstaden",
    "sg:classifiers":[
        {
            "category":"Manufacturing",
            "subcategory":"Printing",
            "type":"Manufacturing & Wholesale Goods"
        }
    ],
    "sg:phone":"+33 3 88 65 44 20",
    "sg:province":"Alsace",
    "sg:tags":[
        "publishing"
    ],
    "wof:name":"Siac",
    "wof:placetype":"venue"
},
  "geometry": {"coordinates":[7.711343,48.510059],"type":"Point"}
}