{
  "type": "Feature",
  "properties": {
    "iso:country":"FR",
    "sg:address":"380, Rue Claude Nicolas Ledoux - P\u00f4le d'Activit\u00e9s, 13103 Aix en Provence",
    "sg:orig_category":"Unclassifiable Establishments",
    "sg:phone":"+33 4 42 97 24 91",
    "sg:province":"Provence-Alpes-C\u00f4te d'Azur",
    "wof:name":"E.h.s. Aurea S.a.r.l.",
    "wof:placetype":"venue"
},
  "geometry": {"coordinates":[5.385739,43.481834],"type":"Point"}
}