{
  "type": "Feature",
  "properties": {
    "addr:full":"47 Bd De La Madeleine 06000 Nice Midi Pyr\u00e9n\u00e9es",
    "addr:housenumber":"47",
    "addr:postcode":"06000",
    "addr:street":"Bd De La Madeleine",
    "iso:country":"FR",
    "sg:address":"47 Bd De La Madeleine 06000 Nice",
    "sg:classifiers":[
        {
            "category":"Home & Garden",
            "subcategory":"Furniture",
            "type":"Retail Goods"
        }
    ],
    "sg:phone":"+33 4 93 97 63 70",
    "sg:province":"Midi Pyr\u00e9n\u00e9es",
    "sg:tags":[
        "professional",
        "household",
        "wood"
    ],
    "wof:name":"M. Arnaut Rosin Roger",
    "wof:placetype":"venue"
},
  "geometry": {"coordinates":[7.240857,43.697109],"type":"Point"}
}