{
  "type": "Feature",
  "properties": {
    "addr:full":"19, Rue de la Petite Suttree, 79600 Airvault Poitou-Charentes 79600",
    "addr:housenumber":"19",
    "addr:postcode":"79600;79600",
    "addr:street":"Rue De La Petite Suttree",
    "iso:country":"FR",
    "sg:address":"19, Rue de la Petite Suttree, 79600 Airvault",
    "sg:orig_category":"Unclassifiable Establishments",
    "sg:phone":"+33 5 49 69 70 55",
    "sg:postcode":"79600",
    "sg:province":"Poitou-Charentes",
    "wof:name":"S.t.v. S.a. - Soci\u00e9t\u00e8 De Transport Valen\u00e7on",
    "wof:placetype":"venue"
},
  "geometry": {"coordinates":[-0.204094,46.847904],"type":"Point"}
}