{
  "type": "Feature",
  "properties": {
    "iso:country":"FR",
    "sg:address":"RN 144",
    "sg:city":"Saint Eloy les Mines",
    "sg:orig_category":"Non-Classified Establishments",
    "sg:phone":"+33 4 73 85 01 69",
    "sg:postcode":"63700",
    "sg:province":"Auvergne",
    "wof:name":"Soci\u00e9t\u00e9 Ren\u00e9 Monteil S.a.r.l.",
    "wof:placetype":"venue"
},
  "geometry": {"coordinates":[2.842339,46.124016],"type":"Point"}
}