{
  "type": "Feature",
  "properties": {
    "addr:full":"6 Rue Chastel 1 Rue Manuel 13100 Aix En Provence Nord Pas-de-Calais",
    "addr:housenumber":"6;1",
    "addr:postcode":"13100",
    "addr:street":"Rue Chastel;Rue Manuel;En Provence Nord",
    "iso:country":"FR",
    "sg:address":"6 Rue Chastel 1 Rue Manuel 13100 Aix En Provence",
    "sg:classifiers":[
        {
            "category":"Professional",
            "subcategory":"Business Services",
            "type":"Services"
        }
    ],
    "sg:phone":"+33 4 42 26 87 84",
    "sg:province":"Nord Pas-de-Calais",
    "sg:tags":[
        "advice",
        "clothes"
    ],
    "wof:name":"Boissel Marie Helene",
    "wof:placetype":"venue"
},
  "geometry": {"coordinates":[5.49167,43.509033],"type":"Point"}
}