{
  "type": "Feature",
  "properties": {
    "addr:full":"5 Rue Du Lantissargues 34070 Montpellier Languedoc-Roussillon",
    "addr:housenumber":"5",
    "addr:postcode":"34070",
    "addr:street":"Rue Du Lantissargues",
    "iso:country":"FR",
    "sg:address":"5 Rue Du Lantissargues 34070 Montpellier",
    "sg:classifiers":[
        {
            "category":"Manufacturing",
            "subcategory":"Wood Products",
            "type":"Manufacturing & Wholesale Goods"
        }
    ],
    "sg:phone":"+33 4 67 58 17 17",
    "sg:province":"Languedoc-Roussillon",
    "sg:tags":[
        "professional",
        "furniture"
    ],
    "wof:name":"Audio Decipro Sarl",
    "wof:placetype":"venue"
},
  "geometry": {"coordinates":[3.88578,43.587906],"type":"Point"}
}