{
  "type": "Feature",
  "properties": {
    "addr:full":"11, Rue Marsoulas, 31800 Saint Gaudens Midi Pyr\u00e9n\u00e9es",
    "addr:housenumber":"11",
    "addr:postcode":"31800",
    "addr:street":"Rue Marsoulas",
    "iso:country":"FR",
    "sg:address":"11, Rue Marsoulas, 31800 Saint Gaudens",
    "sg:orig_category":"Unclassifiable Establishments",
    "sg:phone":"+33 5 62 00 94 20",
    "sg:province":"Midi Pyr\u00e9n\u00e9es",
    "wof:name":"E.d.f. Et Gaz De France",
    "wof:placetype":"venue"
},
  "geometry": {"coordinates":[0.730193,43.11047],"type":"Point"}
}