{
  "type": "Feature",
  "properties": {
    "addr:full":"40, Chemin des Loisirs - District Bassin d'Aigueblanche - Morel , 73260 Aigueblanche Rhone-Alpes",
    "addr:housenumber":"40",
    "addr:postcode":"73260",
    "addr:street":"Chemin Des Loisirs",
    "iso:country":"FR",
    "sg:address":"40, Chemin des Loisirs - District Bassin d'Aigueblanche - Morel , 73260 Aigueblanche",
    "sg:orig_category":"Unclassifiable Establishments",
    "sg:phone":"+33 4 79 09 85 55",
    "sg:province":"Rhone-Alpes",
    "wof:name":"Office De Tourisme Maison De Valmorel",
    "wof:placetype":"venue"
},
  "geometry": {"coordinates":[6.493422,45.507744],"type":"Point"}
}