{
  "type": "Feature",
  "properties": {
    "addr:full":"8, Rue de la Raini\u00e8re - Parc Club du Perray, 44300 Nantes Pays de Loire",
    "addr:housenumber":"8",
    "addr:postcode":"44300",
    "addr:street":"Rue De La Rainie\u0300Re Parc Club Du Perray",
    "iso:country":"FR",
    "sg:address":"8, Rue de la Raini\u00e8re - Parc Club du Perray, 44300 Nantes",
    "sg:orig_category":"Unclassifiable Establishments",
    "sg:phone":"+33 2 40 52 54 70",
    "sg:province":"Pays de Loire",
    "wof:name":"A.d.t. S.a.",
    "wof:placetype":"venue"
},
  "geometry": {"coordinates":[-1.50688,47.248466],"type":"Point"}
}