{
  "type": "Feature",
  "properties": {
    "iso:country":"FR",
    "sg:address":"8, Rue de la Raini\u00e8re - Parc Club du Perray, 44300 Nantes",
    "sg:orig_category":"Unclassifiable Establishments",
    "sg:phone":"+33 2 40 52 54 70",
    "sg:province":"Pays de Loire",
    "wof:name":"A.d.t. S.a.",
    "wof:placetype":"venue"
},
  "geometry": {"coordinates":[-1.50688,47.248466],"type":"Point"}
}