{
  "type": "Feature",
  "properties": {
    "addr:full":"M\u00e9ret 82100 Labastide Du Temple Midi Pyr\u00e9n\u00e9es 82100",
    "addr:postcode":"82100;82100",
    "addr:street":"Me\u0301Ret;Du Temple",
    "iso:country":"FR",
    "sg:address":"M\u00e9ret 82100 Labastide Du Temple",
    "sg:classifiers":[
        {
            "category":"Manufacturing",
            "subcategory":"Metals",
            "type":"Manufacturing & Wholesale Goods"
        }
    ],
    "sg:phone":"+33 5 63 31 64 57",
    "sg:postcode":"82100",
    "sg:province":"Midi Pyr\u00e9n\u00e9es",
    "sg:tags":[
        "metallurgy",
        "metalworking",
        "processing"
    ],
    "wof:name":"Almeca Sa",
    "wof:placetype":"venue"
},
  "geometry": {"coordinates":[1.109529,43.941746],"type":"Point"}
}