{
  "type": "Feature",
  "properties": {
    "addr:full":"3, Rue Notre Dame de Bon Secours, 60200 Compi\u00e8gne Picardie",
    "addr:housenumber":"3",
    "addr:postcode":"60200",
    "addr:street":"Rue Notre Dame De Bon Secours",
    "iso:country":"FR",
    "sg:address":"3, Rue Notre Dame de Bon Secours, 60200 Compi\u00e8gne",
    "sg:orig_category":"Unclassifiable Establishments",
    "sg:phone":"+33 3 44 36 41 60",
    "sg:province":"Picardie",
    "wof:name":"Centaure S\u00e9curit\u00e9 S.a.r.l.",
    "wof:placetype":"venue"
},
  "geometry": {"coordinates":[2.821723,49.415375],"type":"Point"}
}