{
  "type": "Feature",
  "properties": {
    "iso:country":"FR",
    "sg:address":"43 rue Saint-Andr\u00e9 93000 Bobigny",
    "sg:classifiers":[
        {
            "category":"Building & Trades",
            "subcategory":"Landscaping Services",
            "type":"Services"
        }
    ],
    "sg:phone":"+33 1 41 83 33 75",
    "sg:province":"Ile de France",
    "sg:tags":[
        "textile"
    ],
    "wof:name":"Jennyfer",
    "wof:placetype":"venue"
},
  "geometry": {"coordinates":[2.424293,48.903194],"type":"Point"}
}