{
  "type": "Feature",
  "properties": {
    "iso:country":"FR",
    "sg:address":"5, Rue Champs de Tir - ZI de la Mission, 17810 Saint Georges des Coteaux",
    "sg:orig_category":"Unclassifiable Establishments",
    "sg:phone":"+33 5 46 92 13 10",
    "sg:province":"Poitou-Charentes",
    "wof:name":"Orkyn",
    "wof:placetype":"venue"
},
  "geometry": {"coordinates":[-0.675246,45.751797],"type":"Point"}
}