{
  "type": "Feature",
  "properties": {
    "iso:country":"FR",
    "sg:address":"ZI Bel Air - La Petite M\u00e9tairie",
    "sg:city":"Esvres",
    "sg:orig_category":"Unclassifiable Establishments",
    "sg:phone":"+33 2 47 26 53 52",
    "sg:postcode":"37320",
    "sg:province":"Centre",
    "wof:name":"C.m.a. Bigmat S.a. - Soci\u00e9t\u00e9 Des Chaux Et Mat\u00e9riaux D'ambroise",
    "wof:placetype":"venue"
},
  "geometry": {"coordinates":[0.788785,47.289276],"type":"Point"}
}