{
  "type": "Feature",
  "properties": {
    "addr:full":"129B, Rte de Lorry, 57000 Metz Lorraine",
    "addr:housenumber":"129b",
    "addr:postcode":"57000",
    "addr:street":"Rte De Lorry",
    "iso:country":"FR",
    "sg:address":"129B, Rte de Lorry, 57000 Metz",
    "sg:orig_category":"Unclassifiable Establishments",
    "sg:phone":"+33 3 87 31 83 60",
    "sg:province":"Lorraine",
    "wof:name":"Mestrole S.a.r.l.",
    "wof:placetype":"venue"
},
  "geometry": {"coordinates":[6.148003,49.136162],"type":"Point"}
}