{
  "type": "Feature",
  "properties": {
    "addr:full":"Le Grand Marais 62140 Marconnelle Nord Pas-de-Calais 62140",
    "addr:postcode":"62140;62140",
    "iso:country":"FR",
    "sg:address":"Le Grand Marais 62140 Marconnelle",
    "sg:classifiers":[
        {
            "category":"Farming",
            "subcategory":"Farm & Veterinary Services",
            "type":"Manufacturing & Wholesale Goods"
        }
    ],
    "sg:phone":"+33 3 21 90 04 44",
    "sg:postcode":"62140",
    "sg:province":"Nord Pas-de-Calais",
    "sg:tags":[
        "food",
        "product",
        "breeding",
        "animal",
        "related"
    ],
    "wof:name":"Friskies France",
    "wof:placetype":"venue"
},
  "geometry": {"coordinates":[2.009226,50.375629],"type":"Point"}
}