{
  "type": "Feature",
  "properties": {
    "addr:full":"31, Rue Fr\u00e9d\u00e9ric Chopin, 29200 Brest Brest Bretagne 29200",
    "addr:housenumber":"31",
    "addr:postcode":"29200;29200",
    "addr:street":"Rue Fre\u0301De\u0301Ric Chopin",
    "iso:country":"FR",
    "sg:address":"31, Rue Fr\u00e9d\u00e9ric Chopin, 29200 Brest",
    "sg:city":"Brest",
    "sg:orig_category":"Unclassifiable Establishments",
    "sg:phone":"+33 2 98 47 07 70",
    "sg:postcode":"29200",
    "sg:province":"Bretagne",
    "wof:name":"C\u00e9rid S.a.",
    "wof:placetype":"venue"
},
  "geometry": {"coordinates":[-4.494487,48.411568],"type":"Point"}
}