{
  "type": "Feature",
  "properties": {
    "iso:country":"FR",
    "sg:address":"5 Av De La R\u00e9publique 75011 Paris",
    "sg:classifiers":[
        {
            "category":"Autos & Motor Vehicles",
            "subcategory":"Automobile Sales",
            "type":"Retail Goods"
        }
    ],
    "sg:phone":"+33 1 49 23 70 00",
    "sg:province":"Ile de France",
    "sg:tags":[
        "equipment",
        "transport"
    ],
    "wof:name":"Ste Nouvelle Du Garage Alhambra Sa",
    "wof:placetype":"venue"
},
  "geometry": {"coordinates":[2.367536,48.866722],"type":"Point"}
}