{
  "type": "Feature",
  "properties": {
    "iso:country":"FR",
    "sg:address":"1, Terrasse Bellini, 92800 Puteaux",
    "sg:orig_category":"Unclassifiable Establishments",
    "sg:phone":"+33 1 49 39 55 55",
    "sg:province":"Ile de France",
    "wof:name":"Distriphar S.a.",
    "wof:placetype":"venue"
},
  "geometry": {"coordinates":[2.249804,48.887184],"type":"Point"}
}