{
  "type": "Feature",
  "properties": {
    "iso:country":"FR",
    "sg:address":"Tour Kvaerner la D\u00e9fense Trois 92040 Puteaux",
    "sg:classifiers":[
        {
            "category":"Juice Bar",
            "subcategory":"None",
            "type":"Food & Drink"
        }
    ],
    "sg:phone":"+33 1 46 96 70 00",
    "sg:province":"Midi Pyr\u00e9n\u00e9es",
    "sg:tags":[
        "liquid",
        "paraffin"
    ],
    "wof:name":"Groupe Sofresid Sa",
    "wof:placetype":"venue"
},
  "geometry": {"coordinates":[2.24119,48.888939],"type":"Point"}
}