{
  "type": "Feature",
  "properties": {
    "addr:full":"42 Rue Du Bois Pouty 77120 Mouroux Ile de France",
    "addr:housenumber":"42",
    "addr:postcode":"77120",
    "addr:street":"Rue Du Bois Pouty;Ile De France",
    "iso:country":"FR",
    "sg:address":"42 Rue Du Bois Pouty 77120 Mouroux",
    "sg:classifiers":[
        {
            "category":"Home & Garden",
            "subcategory":"Furniture",
            "type":"Retail Goods"
        }
    ],
    "sg:phone":"+33 1 64 75 05 64",
    "sg:province":"Ile de France",
    "sg:tags":[
        "wood"
    ],
    "wof:name":"Krasniqi",
    "wof:placetype":"venue"
},
  "geometry": {"coordinates":[3.06073,48.820099],"type":"Point"}
}