{
  "type": "Feature",
  "properties": {
    "addr:full":"23, Rue de Metz, 57800 Freyming Merlebach Lorraine",
    "addr:housenumber":"23",
    "addr:postcode":"57800",
    "addr:street":"Rue De Metz",
    "iso:country":"FR",
    "sg:address":"23, Rue de Metz, 57800 Freyming Merlebach",
    "sg:orig_category":"Non-Classified Establishments",
    "sg:phone":"+33 3 87 04 41 21",
    "sg:province":"Lorraine",
    "wof:name":"Voyages Diss S.a.r.l.",
    "wof:placetype":"venue"
},
  "geometry": {"coordinates":[6.811202,49.141838],"type":"Point"}
}