{
  "type": "Feature",
  "properties": {
    "addr:full":"49 rue de la Lib\u00e9ration 87570 Rilhac Rancon Limousin",
    "addr:housenumber":"49",
    "addr:postcode":"87570",
    "addr:street":"Rue De La Libe\u0301Ration",
    "iso:country":"FR",
    "sg:address":"49 rue de la Lib\u00e9ration 87570 Rilhac Rancon",
    "sg:classifiers":[
        {
            "category":"Shopping",
            "subcategory":"Computers & Home Electronics",
            "type":"Retail Goods"
        }
    ],
    "sg:phone":"+33 5 55 36 76 95",
    "sg:province":"Limousin",
    "sg:tags":[
        "industrial",
        "power"
    ],
    "wof:name":"Cedepe Sa",
    "wof:placetype":"venue"
},
  "geometry": {"coordinates":[1.317891,45.901958],"type":"Point"}
}