{
  "type": "Feature",
  "properties": {
    "addr:full":"Lieu dit Les Nazins 69220 Saint Lager Rhone-Alpes 69220",
    "addr:postcode":"69220;69220",
    "addr:street":"Lieu Dit Les Nazins;Rhone-Alpes",
    "iso:country":"FR",
    "sg:address":"Lieu dit Les Nazins 69220 Saint Lager",
    "sg:orig_category":"Non-Classified Establishments",
    "sg:phone":"+33 4 74 66 80 48",
    "sg:postcode":"69220",
    "sg:province":"Rhone-Alpes",
    "wof:name":"Trichard",
    "wof:placetype":"venue"
},
  "geometry": {"coordinates":[4.680845,46.109165],"type":"Point"}
}