{
  "type": "Feature",
  "properties": {
    "addr:full":"Rue de la Bigorre Odos Midi Pyr\u00e9n\u00e9es 65310",
    "addr:postcode":"65310",
    "addr:street":"Rue De La Bigorre Odos",
    "iso:country":"FR",
    "sg:address":"Rue de la Bigorre",
    "sg:city":"Odos",
    "sg:orig_category":"Unclassifiable Establishments",
    "sg:phone":"+33 5 62 32 62 33",
    "sg:postcode":"65310",
    "sg:province":"Midi Pyr\u00e9n\u00e9es",
    "wof:name":"Multimessages Communication S.a.r.l.",
    "wof:placetype":"venue"
},
  "geometry": {"coordinates":[0.062457,43.202744],"type":"Point"}
}