{
  "type": "Feature",
  "properties": {
    "addr:full":"Route D Anduze 30380 St Christol Les Ales Languedoc-Roussillon",
    "addr:postcode":"30380 st christol",
    "addr:street":"Route D",
    "iso:country":"FR",
    "sg:address":"Route D Anduze 30380 St Christol Les Ales",
    "sg:classifiers":[
        {
            "category":"Manufacturing",
            "subcategory":"Wood Products",
            "type":"Manufacturing & Wholesale Goods"
        }
    ],
    "sg:phone":"+33 4 66 60 77 42",
    "sg:province":"Languedoc-Roussillon",
    "sg:tags":[
        "professional",
        "furniture"
    ],
    "wof:name":"Etablissements Soulier Pere Et Fils",
    "wof:placetype":"venue"
},
  "geometry": {"coordinates":[4.064041,44.089695],"type":"Point"}
}