{
  "type": "Feature",
  "properties": {
    "addr:full":"34120 Lezignan La Cebe Languedoc-Roussillon 34120",
    "addr:postcode":"34120;34120",
    "addr:street":"Cebe",
    "iso:country":"FR",
    "sg:address":"34120 Lezignan La Cebe",
    "sg:classifiers":[
        {
            "category":"Building & Trades",
            "subcategory":"Construction",
            "type":"Services"
        }
    ],
    "sg:phone":"+33 4 67 90 40 00",
    "sg:postcode":"34120",
    "sg:province":"Languedoc-Roussillon",
    "sg:tags":[
        "work",
        "public"
    ],
    "wof:name":"Tpso",
    "wof:placetype":"venue"
},
  "geometry": {"coordinates":[3.438614,43.494274],"type":"Point"}
}