{
  "type": "Feature",
  "properties": {
    "addr:full":"14 Rue De L'Atome 67800 Bischheim Bischheim Alsace 67800",
    "addr:housenumber":"14",
    "addr:postcode":"67800;67800",
    "addr:street":"Rue De L'Atome",
    "iso:country":"FR",
    "sg:address":"14 Rue De L'Atome 67800 Bischheim",
    "sg:city":"Bischheim",
    "sg:classifiers":[
        {
            "category":"Professional",
            "type":"Services"
        }
    ],
    "sg:phone":"+33 3 88 83 22 62",
    "sg:postcode":"67800",
    "sg:province":"Alsace",
    "sg:tags":[
        "transport",
        "road"
    ],
    "wof:name":"Transports Marcel Dupuy",
    "wof:placetype":"venue"
},
  "geometry": {"coordinates":[7.769752,48.628761],"type":"Point"}
}