{
  "type": "Feature",
  "properties": {
    "addr:full":"8, Rue Proudhon, 93210 La Plaine saint Denis Ile-de-France",
    "addr:housenumber":"8",
    "addr:postcode":"93210",
    "addr:street":"Rue Proudhon",
    "iso:country":"FR",
    "sg:address":"8, Rue Proudhon, 93210 La Plaine saint Denis",
    "sg:orig_category":"Unclassifiable Establishments",
    "sg:phone":"+33 1 49 46 22 50",
    "sg:province":"Ile-de-France",
    "wof:name":"Servomex S.a.",
    "wof:placetype":"venue"
},
  "geometry": {"coordinates":[2.359111,48.906391],"type":"Point"}
}