{
  "type": "Feature",
  "properties": {
    "addr:full":"9 Gilberte Desnoyer 93600 Aulnay sous Bois Ile de France",
    "addr:housenumber":"9",
    "addr:postcode":"93600",
    "addr:street":"Gilberte Desnoyer",
    "iso:country":"FR",
    "sg:address":"9",
    "sg:city":"Gilberte Desnoyer 93600 Aulnay sous Bois",
    "sg:classifiers":[
        {
            "category":"Professional",
            "type":"Services"
        }
    ],
    "sg:phone":"+33 1 45 91 96 16",
    "sg:province":"Ile de France",
    "sg:tags":[
        "transport",
        "road"
    ],
    "wof:name":"Transforce",
    "wof:placetype":"venue"
},
  "geometry": {"coordinates":[2.479172,48.952663],"type":"Point"}
}