{
  "type": "Feature",
  "properties": {
    "addr:full":"1 Rue Honore Euzet 34200 Sete Languedoc-Roussillon",
    "addr:housenumber":"1",
    "addr:postcode":"34200",
    "addr:street":"Rue Honore",
    "iso:country":"FR",
    "sg:address":"1 Rue Honore Euzet 34200 Sete",
    "sg:classifiers":[
        {
            "category":"Professional",
            "subcategory":"Printing & Photocopies",
            "type":"Services"
        }
    ],
    "sg:phone":"+33 4 67 74 84 30",
    "sg:province":"Languedoc-Roussillon",
    "sg:tags":[
        "publishing"
    ],
    "wof:name":"Societe Du Journal Midi Libre",
    "wof:placetype":"venue"
},
  "geometry": {"coordinates":[3.69777,43.404598],"type":"Point"}
}