{
  "type": "Feature",
  "properties": {
    "addr:full":"B.P. 43, 14101 Lisieux C\u00e9dex^^ZI Nord, 14100 Lisieux Lisieux Basse Normandie 14100",
    "addr:postcode":"14101;14100;14100",
    "addr:street":"B.P. 43",
    "iso:country":"FR",
    "sg:address":"B.P. 43, 14101 Lisieux C\u00e9dex^^ZI Nord, 14100 Lisieux",
    "sg:city":"Lisieux",
    "sg:orig_category":"Non-Classified Establishments",
    "sg:phone":"+33 2 31 31 44 36",
    "sg:postcode":"14100",
    "sg:province":"Basse Normandie",
    "wof:name":"Scanormande S.a.",
    "wof:placetype":"venue"
},
  "geometry": {"coordinates":[0.189525,49.074329],"type":"Point"}
}