{
  "type": "Feature",
  "properties": {
    "addr:full":"B.P. 53, 51470 Saint Memmie^^3, av. du Maquis des Gli\u00e8res, 51470 Saint Memmie Champagne",
    "addr:postcode":"51470;51470",
    "addr:street":"B.P. 53;Av. Du Maquis Des Glie\u0300Res",
    "iso:country":"FR",
    "sg:address":"B.P. 53, 51470 Saint Memmie^^3, av. du Maquis des Gli\u00e8res, 51470 Saint Memmie",
    "sg:orig_category":"Non-Classified Establishments",
    "sg:phone":"+33 3 26 69 50 60",
    "sg:province":"Champagne",
    "wof:name":"M.c.a. S.a. - Messageries Cossenet Associ\u00e9s",
    "wof:placetype":"venue"
},
  "geometry": {"coordinates":[4.384128,48.954563],"type":"Point"}
}