{
  "type": "Feature",
  "properties": {
    "addr:full":"B.P. 73 Saint Vallier C\u00e9dex^^26240 Saint Vallier Rhone-Alpes 26240",
    "addr:housenumber":"73",
    "addr:postcode":"26240",
    "addr:street":"B.P.;Saint Vallier Ce\u0301Dex^^26240 Saint Vallier Rhone-Alpes",
    "iso:country":"FR",
    "sg:address":"B.P. 73",
    "sg:city":"Saint Vallier C\u00e9dex^^26240 Saint Vallier",
    "sg:orig_category":"Non-Classified Establishments",
    "sg:phone":"+33 4 75 23 88 88",
    "sg:postcode":"26240",
    "sg:province":"Rhone-Alpes",
    "wof:name":"C\u00e9ralep S.a.",
    "wof:placetype":"venue"
},
  "geometry": {"coordinates":[4.836268,45.159122],"type":"Point"}
}