{
  "type": "Feature",
  "properties": {
    "addr:full":"Rte de Gelacourt Baccarat Lorraine 54120",
    "addr:postcode":"54120",
    "addr:street":"Rte De Gelacourt Baccarat Lorraine",
    "iso:country":"FR",
    "sg:address":"Rte de Gelacourt",
    "sg:city":"Baccarat",
    "sg:orig_category":"Unclassifiable Establishments",
    "sg:phone":"+33 3 83 75 12 11",
    "sg:postcode":"54120",
    "sg:province":"Lorraine",
    "wof:name":"Antonini S.n.c.",
    "wof:placetype":"venue"
},
  "geometry": {"coordinates":[6.738444,48.464428],"type":"Point"}
}