{
  "type": "Feature",
  "properties": {
    "addr:full":"Marignieu 38118 HIERES SUR AMBY Rhone-Alpes 38118",
    "addr:postcode":"38118;38118",
    "addr:street":"Rhone-Alpes",
    "iso:country":"FR",
    "sg:address":"Marignieu 38118 HIERES SUR AMBY",
    "sg:classifiers":[
        {
            "category":"Food & Beverages",
            "subcategory":"Meat & Fish",
            "type":"Retail Goods"
        }
    ],
    "sg:phone":"+33 4 74 95 15 55",
    "sg:postcode":"38118",
    "sg:province":"Rhone-Alpes",
    "sg:tags":[
        "product"
    ],
    "wof:name":"Carrel S.a.",
    "wof:placetype":"venue"
},
  "geometry": {"coordinates":[5.304195,45.813236],"type":"Point"}
}