{
  "type": "Feature",
  "properties": {
    "iso:country":"FR",
    "sg:address":"535 Chemin De La Cassine 73000 Chambery",
    "sg:classifiers":[
        {
            "category":"Manufacturing",
            "subcategory":"Metals",
            "type":"Manufacturing & Wholesale Goods"
        }
    ],
    "sg:phone":"+33 4 79 60 71 00",
    "sg:postcode":"73000",
    "sg:province":"Rhone-Alpes",
    "sg:tags":[
        "metallurgy",
        "metalworking"
    ],
    "wof:name":"Accel",
    "wof:placetype":"venue"
},
  "geometry": {"coordinates":[5.921531,45.57452],"type":"Point"}
}