{
  "type": "Feature",
  "properties": {
    "addr:full":"90 Av De Flandre 75019 Paris Ile de France 75019",
    "addr:postcode":"75019;75019",
    "addr:street":"90 Av De Flandre",
    "iso:country":"FR",
    "sg:address":"90 Av De Flandre 75019 Paris",
    "sg:classifiers":[
        {
            "category":"Shopping",
            "subcategory":"Luggage & Leather Goods",
            "type":"Retail Goods"
        }
    ],
    "sg:phone":"+33 1 40 37 12 51",
    "sg:postcode":"75019",
    "sg:province":"Ile de France",
    "sg:tags":[
        "shoe"
    ],
    "wof:name":"Comite D Etablissement Andre Sa Succursale",
    "wof:placetype":"venue"
},
  "geometry": {"coordinates":[2.376565,48.890125],"type":"Point"}
}