{
  "type": "Feature",
  "properties": {
    "addr:full":"9 Berlioz 34500 B\u00e9ziers Languedoc-Roussillon",
    "addr:housenumber":"9",
    "addr:postcode":"34500",
    "addr:street":"Berlioz",
    "iso:country":"FR",
    "sg:address":"9",
    "sg:city":"Berlioz 34500 B\u00e9ziers",
    "sg:classifiers":[
        {
            "category":"Professional",
            "subcategory":"Printing & Photocopies",
            "type":"Services"
        }
    ],
    "sg:phone":"+33 4 67 49 18 18",
    "sg:province":"Languedoc-Roussillon",
    "sg:tags":[
        "publishing"
    ],
    "wof:name":"Isoc",
    "wof:placetype":"venue"
},
  "geometry": {"coordinates":[3.218307,43.343803],"type":"Point"}
}