{
  "type": "Feature",
  "properties": {
    "addr:full":"B.P. 6219, 14066 Caen C\u00e9dex 4^^18, Rue de la Girafe, 14000 Caen Caen Basse Normandie 14000",
    "addr:housenumber":"6219;^ 18",
    "addr:postcode":"14066;14000;14000",
    "addr:street":"B.P.;Rue De La Girafe",
    "iso:country":"FR",
    "sg:address":"B.P. 6219, 14066 Caen C\u00e9dex 4^^18, Rue de la Girafe, 14000 Caen",
    "sg:city":"Caen",
    "sg:orig_category":"Non-Classified Establishments",
    "sg:phone":"+33 2 31 53 15 01",
    "sg:postcode":"14000",
    "sg:province":"Basse Normandie",
    "wof:name":"Sfpn Bruno Hebert S.a.r.l.",
    "wof:placetype":"venue"
},
  "geometry": {"coordinates":[-0.36111,49.184361],"type":"Point"}
}