{
  "type": "Feature",
  "properties": {
    "iso:country":"FR",
    "sg:address":"7 R Vaucanson 69150 D\u00e9cines Charpieu",
    "sg:classifiers":[
        {
            "category":"Utilities",
            "subcategory":"Electric",
            "type":"Services"
        }
    ],
    "sg:phone":"+33 4 74 99 94 60",
    "sg:postcode":"69150",
    "sg:province":"Rhone-Alpes",
    "sg:tags":[
        "electricity",
        "electronic",
        "electrical",
        "equipment"
    ],
    "wof:name":"Apl Sa",
    "wof:placetype":"venue"
},
  "geometry": {"coordinates":[4.936211,45.753521],"type":"Point"}
}