{
  "type": "Feature",
  "properties": {
    "addr:full":"4 Rue De Madrid 75008 Paris Ile de France 75008",
    "addr:housenumber":"4",
    "addr:postcode":"75008;75008",
    "addr:street":"Rue De Madrid",
    "iso:country":"FR",
    "sg:address":"4 Rue De Madrid 75008 Paris",
    "sg:classifiers":[
        {
            "category":"Shopping",
            "subcategory":"Hobbies, Toys, & Games",
            "type":"Retail Goods"
        }
    ],
    "sg:phone":"+33 1 45 22 89 81",
    "sg:postcode":"75008",
    "sg:province":"Ile de France",
    "sg:tags":[
        "product",
        "miscellaneous",
        "entertainment"
    ],
    "wof:name":"Alienor",
    "wof:placetype":"venue"
},
  "geometry": {"coordinates":[2.321813,48.878811],"type":"Point"}
}