{
  "type": "Feature",
  "properties": {
    "addr:full":"Cd 12 69360 Solaize Rhone-Alpes 69360",
    "addr:postcode":"69360;69360",
    "addr:street":"Cd 12",
    "iso:country":"FR",
    "sg:address":"Cd 12 69360 Solaize",
    "sg:classifiers":[
        {
            "category":"Professional",
            "subcategory":"Engineering",
            "type":"Services"
        }
    ],
    "sg:phone":"+33 4 78 02 77 44",
    "sg:postcode":"69360",
    "sg:province":"Rhone-Alpes",
    "sg:tags":[
        "machine",
        "-",
        "mechanical"
    ],
    "wof:name":"Sogequip Sa",
    "wof:placetype":"venue"
},
  "geometry": {"coordinates":[4.856095,45.634987],"type":"Point"}
}