{
  "type": "Feature",
  "properties": {
    "iso:country":"FR",
    "sg:address":"Route Nationale Bellevue 27 63309 THIERS CEDEX",
    "sg:classifiers":[
        {
            "category":"Shopping",
            "subcategory":"Crafts & Fabrics",
            "type":"Retail Goods"
        }
    ],
    "sg:phone":"+33 4 73 80 23 51",
    "sg:province":"Auvergne",
    "sg:tags":[
        "use",
        "industrial",
        "knife"
    ],
    "wof:name":"Sauzedde Roddier Et Cie Sarl",
    "wof:placetype":"venue"
},
  "geometry": {"coordinates":[3.548272,45.855244],"type":"Point"}
}