{
  "type": "Feature",
  "properties": {
    "addr:full":"11 des Pins 69570 Dardilly Rhone-Alpes 69570",
    "addr:housenumber":"11",
    "addr:postcode":"69570;69570",
    "addr:street":"Des Pins",
    "iso:country":"FR",
    "sg:address":"11",
    "sg:city":"des Pins 69570 Dardilly",
    "sg:classifiers":[
        {
            "category":"Manufacturing",
            "subcategory":"Rubber & Plastics",
            "type":"Manufacturing & Wholesale Goods"
        }
    ],
    "sg:phone":"+33 4 37 22 60 98",
    "sg:postcode":"69570",
    "sg:province":"Rhone-Alpes",
    "wof:name":"Hifi Film Industriels",
    "wof:placetype":"venue"
},
  "geometry": {"coordinates":[4.737389,45.792999],"type":"Point"}
}