{
  "type": "Feature",
  "properties": {
    "iso:country":"FR",
    "sg:address":"408, Bd de la Madeleine, 06000 Nice",
    "sg:orig_category":"Non-Classified Establishments",
    "sg:phone":"+33 4 93 97 93 00",
    "sg:province":"Midi Pyr\u00e9n\u00e9es",
    "wof:name":"Pi\u00e9rotti S.a.",
    "wof:placetype":"venue"
},
  "geometry": {"coordinates":[7.224229,43.716114],"type":"Point"}
}