{
  "type": "Feature",
  "properties": {
    "addr:full":"Zi De Sistrieres 2 15000 Aurillac Aurillac Auvergne 15000",
    "addr:housenumber":"2",
    "addr:postcode":"15000;15000",
    "addr:street":"Zi De Sistrieres",
    "iso:country":"FR",
    "sg:address":"Zi De Sistrieres 2 15000 Aurillac",
    "sg:city":"Aurillac",
    "sg:classifiers":[
        {
            "category":"Home & Garden",
            "subcategory":"Furniture",
            "type":"Retail Goods"
        }
    ],
    "sg:phone":"+33 4 71 64 10 48",
    "sg:postcode":"15000",
    "sg:province":"Auvergne",
    "sg:tags":[
        "household",
        "wood"
    ],
    "wof:name":"Gmv Ameublement Sas",
    "wof:placetype":"venue"
},
  "geometry": {"coordinates":[2.445745,44.91386],"type":"Point"}
}