{
  "type": "Feature",
  "properties": {
    "iso:country":"FR",
    "sg:address":"122 R Marcel Hartmann 94200 Ivry Sur Seine",
    "sg:classifiers":[
        {
            "category":"Home & Garden",
            "subcategory":"Furniture",
            "type":"Retail Goods"
        }
    ],
    "sg:phone":"+33 1 46 71 70 71",
    "sg:postcode":"94200",
    "sg:province":"Ile de France",
    "sg:tags":[
        "household",
        "wood"
    ],
    "wof:name":"Fournitures Sarl",
    "wof:placetype":"venue"
},
  "geometry": {"coordinates":[2.381001,48.808643],"type":"Point"}
}