{
  "type": "Feature",
  "properties": {
    "addr:full":"119 rue R\u00e9aumur 75002 Paris Ile de France 75002",
    "addr:housenumber":"119",
    "addr:postcode":"75002;75002",
    "addr:street":"Rue Re\u0301Aumur",
    "iso:country":"FR",
    "sg:address":"119 rue R\u00e9aumur 75002 Paris",
    "sg:classifiers":[
        {
            "category":"Government",
            "subcategory":"Post Office",
            "type":"Public Place"
        }
    ],
    "sg:phone":"+33 1 44 82 86 86",
    "sg:postcode":"75002",
    "sg:province":"Ile de France",
    "sg:tags":[
        "consulting",
        "investment",
        "capital"
    ],
    "wof:name":"Carr Futures Sa",
    "wof:placetype":"venue"
},
  "geometry": {"coordinates":[2.342342,48.868294],"type":"Point"}
}