{
  "type": "Feature",
  "properties": {
    "iso:country":"FR",
    "sg:address":"Bataill\u00e8res 49112 Pellouailles Les Vignes",
    "sg:classifiers":[
        {
            "category":"Manufacturing",
            "subcategory":"Tools & Machinery",
            "type":"Manufacturing & Wholesale Goods"
        }
    ],
    "sg:phone":"+33 2 41 76 57 40",
    "sg:postcode":"49112",
    "sg:province":"Pays de Loire",
    "sg:tags":[
        "metallurgy",
        "metalworking"
    ],
    "wof:name":"Moule Anjou Plastique",
    "wof:placetype":"venue"
},
  "geometry": {"coordinates":[-0.437397,47.519657],"type":"Point"}
}