{
  "type": "Feature",
  "properties": {
    "iso:country":"FR",
    "sg:address":"1140, Av. Amp\u00e8re - P\u00f4le d'Activit\u00e9s les Milles - Actimart Lot. 13, 13851 Aix en Provence C\u00e9dex 3",
    "sg:orig_category":"Non-Classified Establishments",
    "sg:phone":"+33 4 42 97 55 75",
    "sg:province":"Nord Pas-de-Calais",
    "wof:name":"Cris R\u00e9seaux S.a.r.l.",
    "wof:placetype":"venue"
},
  "geometry": {"coordinates":[5.4542,43.52494],"type":"Point"}
}