{
  "type": "Feature",
  "properties": {
    "addr:full":"197 Rue L\u00e9on Jouhaux 78500 Sartrouville Ile de France",
    "addr:housenumber":"197",
    "addr:postcode":"78500;ile",
    "addr:street":"Rue Le\u0301On Jouhaux",
    "iso:country":"FR",
    "sg:address":"197 Rue L\u00e9on Jouhaux 78500 Sartrouville",
    "sg:classifiers":[
        {
            "category":"Communications",
            "subcategory":"Newspaper",
            "type":"Services"
        }
    ],
    "sg:phone":"+33 1 39 15 30 27",
    "sg:province":"Ile de France",
    "sg:tags":[
        "printing",
        "publishing"
    ],
    "wof:name":"Imprimerie B M Sa",
    "wof:placetype":"venue"
},
  "geometry": {"coordinates":[2.19157,48.947914],"type":"Point"}
}