{
  "type": "Feature",
  "properties": {
    "iso:country":"FR",
    "sg:address":"7, Rue Charles Piot, 38320 Eybens",
    "sg:orig_category":"Unclassifiable Establishments",
    "sg:phone":"+33 4 76 62 67 00",
    "sg:province":"Rhone-Alpes",
    "wof:name":"Brun Investissement S.a.",
    "wof:placetype":"venue"
},
  "geometry": {"coordinates":[5.749599,45.155415],"type":"Point"}
}