{
  "type": "Feature",
  "properties": {
    "addr:full":"Les Aynans 70200 Lure Franche Comt\u00e9",
    "addr:postcode":"70200",
    "addr:street":"Franche Comte\u0301",
    "iso:country":"FR",
    "sg:address":"Les Aynans 70200 Lure",
    "sg:orig_category":"Unclassifiable Establishments",
    "sg:phone":"+33 3 84 63 90 00",
    "sg:province":"Franche Comt\u00e9",
    "wof:name":"Galvanoplast S.a.",
    "wof:placetype":"venue"
},
  "geometry": {"coordinates":[6.45129,47.62146],"type":"Point"}
}