{
  "type": "Feature",
  "properties": {
    "addr:full":"97 rue de Lille; Paris; 75007 Ile de France",
    "addr:housenumber":"97",
    "addr:postcode":"75007",
    "addr:street":"Rue De Lille Paris",
    "iso:country":"FR",
    "sg:address":"97 rue de Lille; Paris; 75007",
    "sg:classifiers":[
        {
            "category":"Industrial Area",
            "type":"Public Place"
        }
    ],
    "sg:phone":"+33 1 47 53 61 50",
    "sg:province":"Ile de France",
    "sg:tags":[
        "large",
        "private"
    ],
    "wof:name":"Fimalac S.a.",
    "wof:placetype":"venue"
},
  "geometry": {"coordinates":[2.32228,48.860554],"type":"Point"}
}