{
  "type": "Feature",
  "properties": {
    "addr:full":"82 Hablot 08110 Carignan Champagne 08110",
    "addr:housenumber":"82",
    "addr:postcode":"08110;08110",
    "addr:street":"Hablot;Champagne",
    "iso:country":"FR",
    "sg:address":"82 Hablot 08110 Carignan",
    "sg:classifiers":[
        {
            "category":"Utilities",
            "subcategory":"Electric",
            "type":"Services"
        }
    ],
    "sg:phone":"+33 3 24 22 27 66",
    "sg:postcode":"08110",
    "sg:province":"Champagne",
    "sg:tags":[
        "electricity",
        "raw",
        "energy",
        "material"
    ],
    "wof:name":"Sarl Teca",
    "wof:placetype":"venue"
},
  "geometry": {"coordinates":[5.16695,49.631287],"type":"Point"}
}