{
  "type": "Feature",
  "properties": {
    "iso:country":"FR",
    "sg:address":"B.P. 02, 86240 Ligug\u00e9 C\u00e9dex^^Chemin des deux Croix, 86240 Ligug\u00e9",
    "sg:orig_category":"Non-Classified Establishments",
    "sg:phone":"+33 5 49 55 20 13",
    "sg:postcode":"86240",
    "sg:province":"Poitou-Charentes",
    "wof:name":"Aubin Imprimeur S.a.",
    "wof:placetype":"venue"
},
  "geometry": {"coordinates":[0.287413,46.459652],"type":"Point"}
}