{
  "type": "Feature",
  "properties": {
    "addr:full":"Bargilet 17210 BUSSAC FORET Poitou-Charentes 17210",
    "addr:postcode":"17210;17210",
    "addr:street":"Bargilet;Foret",
    "iso:country":"FR",
    "sg:address":"Bargilet 17210 BUSSAC FORET",
    "sg:classifiers":[
        {
            "category":"Utilities",
            "subcategory":"Cable",
            "type":"Services"
        }
    ],
    "sg:phone":"+33 5 46 04 37 19",
    "sg:postcode":"17210",
    "sg:province":"Poitou-Charentes",
    "sg:tags":[
        "forestry"
    ],
    "wof:name":"Gravouil Michel Sa",
    "wof:placetype":"venue"
},
  "geometry": {"coordinates":[-0.377598,45.214386],"type":"Point"}
}