{
  "type": "Feature",
  "properties": {
    "addr:full":"51 Rue Docteur Mouflier 02600 Haramont Picardie",
    "addr:housenumber":"51",
    "addr:postcode":"02600",
    "addr:street":"Rue Docteur Mouflier",
    "iso:country":"FR",
    "sg:address":"51 Rue Docteur Mouflier 02600 Haramont",
    "sg:classifiers":[
        {
            "category":"Home & Garden",
            "subcategory":"Furniture",
            "type":"Retail Goods"
        }
    ],
    "sg:phone":"+33 3 23 96 17 88",
    "sg:province":"Picardie",
    "sg:tags":[
        "wood"
    ],
    "wof:name":"Pigoni Jc Et M",
    "wof:placetype":"venue"
},
  "geometry": {"coordinates":[3.061355,49.277645],"type":"Point"}
}