{
  "type": "Feature",
  "properties": {
    "addr:full":"2, Rue des Champs Corneille - ZI Nord, 28100 Dreux Dreux Centre 28100",
    "addr:housenumber":"2;dreux",
    "addr:postcode":"28100;28100",
    "addr:street":"Rue Des Champs Corneille Zi Nord",
    "iso:country":"FR",
    "sg:address":"2, Rue des Champs Corneille - ZI Nord, 28100 Dreux",
    "sg:city":"Dreux",
    "sg:orig_category":"Unclassifiable Establishments",
    "sg:phone":"+33 2 37 46 90 90",
    "sg:postcode":"28100",
    "sg:province":"Centre",
    "wof:name":"Or\u00e9fi - T.s.",
    "wof:placetype":"venue"
},
  "geometry": {"coordinates":[1.362293,48.736141],"type":"Point"}
}