{
  "type": "Feature",
  "properties": {
    "addr:full":"B.P. 14, 76191 Yvetot C\u00e9dex^^24, Rue Ha\u00ebmers, 76190 Yvetot Haute Normandie",
    "addr:postcode":"76191;76190",
    "addr:street":"B.P. 14;Rue Hae\u0308Mers;Haute Normandie",
    "iso:country":"FR",
    "sg:address":"B.P. 14, 76191 Yvetot C\u00e9dex^^24, Rue Ha\u00ebmers, 76190 Yvetot",
    "sg:orig_category":"Non-Classified Establishments",
    "sg:phone":"+33 2 35 95 16 22",
    "sg:province":"Haute Normandie",
    "wof:name":"Imprimerie Nouvelle S.a.",
    "wof:placetype":"venue"
},
  "geometry": {"coordinates":[0.795155,49.553596],"type":"Point"}
}