{
  "type": "Feature",
  "properties": {
    "addr:full":"27, Cours de Verdun, 01100 Oyonnax Rhone-Alpes",
    "addr:housenumber":"27",
    "addr:postcode":"01100",
    "addr:street":"Cours De Verdun",
    "iso:country":"FR",
    "sg:address":"27, Cours de Verdun, 01100 Oyonnax",
    "sg:orig_category":"Unclassifiable Establishments",
    "sg:phone":"+33 4 74 77 06 49",
    "sg:province":"Rhone-Alpes",
    "wof:name":"Martinand Auguste Et Fils S.a.",
    "wof:placetype":"venue"
},
  "geometry": {"coordinates":[5.65701,46.268559],"type":"Point"}
}