{
  "type": "Feature",
  "properties": {
    "addr:full":"70 Chem Couvertaire 33450 St Loub\u00e8s Saint-Loub\u00e8s Aquitaine 33450",
    "addr:housenumber":"70",
    "addr:postcode":"33450;33450",
    "addr:street":"Chem Couvertaire",
    "iso:country":"FR",
    "sg:address":"70 Chem Couvertaire 33450 St Loub\u00e8s",
    "sg:city":"Saint-Loub\u00e8s",
    "sg:classifiers":[
        {
            "category":"Food Court",
            "type":"Food & Drink"
        }
    ],
    "sg:phone":"+33 5 56 77 53 19",
    "sg:postcode":"33450",
    "sg:province":"Aquitaine",
    "sg:tags":[
        "product",
        "related"
    ],
    "wof:name":"Chateau Lescart",
    "wof:placetype":"venue"
},
  "geometry": {"coordinates":[-0.445825,44.916073],"type":"Point"}
}