{
  "type": "Feature",
  "properties": {
    "addr:full":"2, Rue Fr\u00e9d\u00e9ric Joliot Curie, 93270 Sevran Ile de France",
    "addr:housenumber":"2",
    "addr:postcode":"93270",
    "addr:street":"Rue Fre\u0301De\u0301Ric Joliot Curie",
    "iso:country":"FR",
    "sg:address":"2, Rue Fr\u00e9d\u00e9ric Joliot Curie, 93270 Sevran",
    "sg:orig_category":"Unclassifiable Establishments",
    "sg:phone":"+33 1 43 85 59 10",
    "sg:province":"Ile de France",
    "wof:name":"C.g.s.t. Save S.a.s. - Compagnie Gazi\u00e8re Service Technique Save",
    "wof:placetype":"venue"
},
  "geometry": {"coordinates":[2.527004,48.947163],"type":"Point"}
}