{
  "type": "Feature",
  "properties": {
    "iso:country":"FR",
    "sg:address":"Rue De Lunel 82170 Grisolles",
    "sg:classifiers":[
        {
            "category":"Utilities",
            "type":"Services"
        }
    ],
    "sg:phone":"+33 5 61 34 77 77",
    "sg:postcode":"82170",
    "sg:province":"Midi Pyr\u00e9n\u00e9es",
    "sg:tags":[
        "raw",
        "energy",
        "material"
    ],
    "wof:name":"Compagnie Generale Des Eaux",
    "wof:placetype":"venue"
},
  "geometry": {"coordinates":[1.296185,43.825314],"type":"Point"}
}