{
  "type": "Feature",
  "properties": {
    "addr:full":"34 Place De La R\u00e9publique Le Mans Cedex 2 Pays de Loire 72045",
    "addr:housenumber":"34",
    "addr:postcode":"2 pays;72045",
    "addr:street":"Place De La Re\u0301Publique",
    "iso:country":"FR",
    "sg:address":"34 Place De La R\u00e9publique",
    "sg:city":"Le Mans Cedex 2",
    "sg:classifiers":[
        {
            "category":"Banks & Credit Unions",
            "subcategory":"Financial Services",
            "type":"Services"
        }
    ],
    "sg:phone":"+33 2 43 47 54 00",
    "sg:postcode":"72045",
    "sg:province":"Pays de Loire",
    "sg:tags":[
        "banking",
        "finance",
        "insurance"
    ],
    "wof:name":"Defense Automobile Et Sportive (la)",
    "wof:placetype":"venue"
},
  "geometry": {"coordinates":[0.19611,48.003769],"type":"Point"}
}