{
  "type": "Feature",
  "properties": {
    "addr:full":"24, Rue Pierre et Marie Curie, 49300 Cholet Pays de Loire 49300",
    "addr:housenumber":"24",
    "addr:postcode":"49300;49300",
    "addr:street":"Rue Pierre Et Marie Curie",
    "iso:country":"FR",
    "sg:address":"24, Rue Pierre et Marie Curie, 49300 Cholet",
    "sg:orig_category":"Non-Classified Establishments",
    "sg:phone":"+33 2 41 65 14 80",
    "sg:postcode":"49300",
    "sg:province":"Pays de Loire",
    "wof:name":"Etablissements Georges Brongniart S.a.r.l.",
    "wof:placetype":"venue"
},
  "geometry": {"coordinates":[-0.861571,47.070122],"type":"Point"}
}