{
  "type": "Feature",
  "properties": {
    "addr:full":"78 Rue Santos Dumont 87000 Limoges Limousin 87000",
    "addr:housenumber":"78",
    "addr:postcode":"87000;87000",
    "addr:street":"Rue Santos Dumont",
    "iso:country":"FR",
    "sg:address":"78 Rue Santos Dumont 87000 Limoges",
    "sg:classifiers":[
        {
            "category":"Professional",
            "subcategory":"Engineering",
            "type":"Services"
        }
    ],
    "sg:phone":"+33 5 55 06 19 19",
    "sg:postcode":"87000",
    "sg:province":"Limousin",
    "sg:tags":[
        "machine",
        "-",
        "mechanical"
    ],
    "wof:name":"Hall Ceramique Sa",
    "wof:placetype":"venue"
},
  "geometry": {"coordinates":[1.28025,45.812241],"type":"Point"}
}