{
  "type": "Feature",
  "properties": {
    "addr:full":"Avenue Des Indes Za Courtaboeuf Le Karina 91940 Les Ulis Ile de France 91940",
    "addr:postcode":"91940;91940",
    "addr:street":"Avenue Des Indes Za Courtaboeuf Le Karina",
    "iso:country":"FR",
    "sg:address":"Avenue Des Indes Za Courtaboeuf Le Karina 91940 Les Ulis",
    "sg:classifiers":[
        {
            "category":"Wholesale",
            "subcategory":"Machinery & Supplies",
            "type":"Manufacturing & Wholesale Goods"
        }
    ],
    "sg:phone":"+33 1 69 86 95 00",
    "sg:postcode":"91940",
    "sg:province":"Ile de France",
    "sg:tags":[
        "handling",
        "material",
        "-",
        "machine",
        "equipment",
        "engineering",
        "mechanical"
    ],
    "wof:name":"Mistral Societe Anonyme",
    "wof:placetype":"venue"
},
  "geometry": {"coordinates":[2.169475,48.68161],"type":"Point"}
}