{
  "type": "Feature",
  "properties": {
    "iso:country":"FR",
    "sg:address":"16, Rue Barb\u00e8s, 92126 Montrouge C\u00e9dex",
    "sg:orig_category":"Non-Classified Establishments",
    "sg:phone":"+33 1 40 92 40 92",
    "sg:province":"\u00cele-de-France",
    "wof:name":"Sema Group S.a.",
    "wof:placetype":"venue"
},
  "geometry": {"coordinates":[2.327478,48.817196],"type":"Point"}
}