{
  "type": "Feature",
  "properties": {
    "iso:country":"FR",
    "sg:address":"B.P. 1255, 31047 Toulouse C\u00e9dex 01^^11, Rue Michel Labrousse, 31100 Toulouse",
    "sg:orig_category":"Non-Classified Establishments",
    "sg:phone":"+33 5 62 14 80 00",
    "sg:province":"Midi Pyr\u00e9n\u00e9es",
    "wof:name":"Schneider Electric S.a.",
    "wof:placetype":"venue"
},
  "geometry": {"coordinates":[1.39859,43.56786],"type":"Point"}
}