{
  "type": "Feature",
  "properties": {
    "addr:full":"Rue Gaston de Flotte - ZI des Fa\u00efenciers Marseille Poitou-Charentes 13012",
    "addr:postcode":"13012",
    "addr:street":"Rue Gaston De Flotte Zi Des Fai\u0308Enciers",
    "iso:country":"FR",
    "sg:address":"Rue Gaston de Flotte - ZI des Fa\u00efenciers",
    "sg:city":"Marseille",
    "sg:orig_category":"Unclassifiable Establishments",
    "sg:phone":"+33 4 91 93 02 33",
    "sg:postcode":"13012",
    "sg:province":"Poitou-Charentes",
    "wof:name":"L.v.s. S.a.s.",
    "wof:placetype":"venue"
},
  "geometry": {"coordinates":[5.416456,43.305122],"type":"Point"}
}