{
  "type": "Feature",
  "properties": {
    "iso:country":"FR",
    "sg:address":"Av Europe 62720 Rinxent",
    "sg:classifiers":[
        {
            "category":"Professional",
            "subcategory":"Printing & Photocopies",
            "type":"Services"
        }
    ],
    "sg:phone":"+33 3 21 33 34 35",
    "sg:province":"Nord Pas-de-Calais",
    "sg:tags":[
        "publishing"
    ],
    "wof:name":"Imprimerie Du Detroit",
    "wof:placetype":"venue"
},
  "geometry": {"coordinates":[1.734932,50.807476],"type":"Point"}
}