{
  "type": "Feature",
  "properties": {
    "addr:full":"1 Impasse Des Forts Zac Des Forts 2 28500 Cherisy Cherisy Centre 28500",
    "addr:housenumber":"1;2;cherisy",
    "addr:postcode":"28500;28500",
    "addr:street":"Impasse Des Forts Zac Des Forts",
    "iso:country":"FR",
    "sg:address":"1 Impasse Des Forts Zac Des Forts 2 28500 Cherisy",
    "sg:city":"Cherisy",
    "sg:classifiers":[
        {
            "category":"Manufacturing",
            "subcategory":"Rubber & Plastics",
            "type":"Manufacturing & Wholesale Goods"
        }
    ],
    "sg:phone":"+33 2 37 62 54 00",
    "sg:postcode":"28500",
    "sg:province":"Centre",
    "wof:name":"Societe A Responsabilite Limitee Smpc Fabrication",
    "wof:placetype":"venue"
},
  "geometry": {"coordinates":[1.369635,48.652908],"type":"Point"}
}