{
  "type": "Feature",
  "properties": {
    "iso:country":"FR",
    "sg:address":"B.P. 38, 10102 Romilly sur Seine C\u00e9dex^^35, Rue de Paris, 10100 Saint Hilaire sous Romilly",
    "sg:orig_category":"Non-Classified Establishments",
    "sg:phone":"+33 3 25 21 07 00",
    "sg:province":"Champagne",
    "wof:name":"Tractel S.a.",
    "wof:placetype":"venue"
},
  "geometry": {"coordinates":[3.657043,48.515602],"type":"Point"}
}