{
  "type": "Feature",
  "properties": {
    "iso:country":"FR",
    "sg:address":"B.P. 46, 91322 Wissous C\u00e9dex^^23, Av. Amp\u00e8re - ZI de Villemilan, 91320 Wissous",
    "sg:orig_category":"Non-Classified Establishments",
    "sg:phone":"+33 1 69 53 93 93",
    "sg:province":"Ile de France",
    "wof:name":"G.r.m. S.a.",
    "wof:placetype":"venue"
},
  "geometry": {"coordinates":[2.32612,48.731461],"type":"Point"}
}