{
  "type": "Feature",
  "properties": {
    "addr:full":"8 Rue De La Gare 62380 Nielles Les Bl\u00e9quin Nord Pas-de-Calais",
    "addr:housenumber":"8",
    "addr:postcode":"62380",
    "addr:street":"Rue De La Gare",
    "iso:country":"FR",
    "sg:address":"8 Rue De La Gare 62380 Nielles Les Bl\u00e9quin",
    "sg:classifiers":[
        {
            "category":"Professional",
            "type":"Services"
        }
    ],
    "sg:phone":"+33 3 21 39 64 05",
    "sg:province":"Nord Pas-de-Calais",
    "sg:tags":[
        "transport",
        "road"
    ],
    "wof:name":"Sae Transports Michel Cleton Sa",
    "wof:placetype":"venue"
},
  "geometry": {"coordinates":[2.03384,50.676071],"type":"Point"}
}