{
  "type": "Feature",
  "properties": {
    "addr:full":"28/30, Rue Fran\u00e7ois Garcin, 69003 Lyon Rhone-Alpes 69003",
    "addr:housenumber":"28 / 30",
    "addr:postcode":"69003;69003",
    "addr:street":"Rue Franc\u0327Ois Garcin",
    "iso:country":"FR",
    "sg:address":"28/30, Rue Fran\u00e7ois Garcin, 69003 Lyon",
    "sg:orig_category":"Non-Classified Establishments",
    "sg:phone":"+33 4 78 60 18 17",
    "sg:postcode":"69003",
    "sg:province":"Rhone-Alpes",
    "wof:name":"Etablissement Reygils S.a.",
    "wof:placetype":"venue"
},
  "geometry": {"coordinates":[4.849656,45.7593],"type":"Point"}
}