{
  "type": "Feature",
  "properties": {
    "iso:country":"FR",
    "sg:address":"188 avenue de Fronton 31200 Toulouse",
    "sg:classifiers":[
        {
            "category":"Coffee & Tea",
            "type":"Food & Drink"
        }
    ],
    "sg:phone":"+33 5 34 40 77 66",
    "sg:postcode":"31200",
    "sg:province":"Midi Pyr\u00e9n\u00e9es",
    "sg:tags":[
        "gardening",
        "seedling"
    ],
    "wof:name":"Castaing Jacques Sarl",
    "wof:placetype":"venue"
},
  "geometry": {"coordinates":[1.433545,43.642574],"type":"Point"}
}