{
  "type": "Feature",
  "properties": {
    "addr:full":"ZI les Planes Lapanouse Midi Pyr\u00e9n\u00e9es 12150",
    "addr:postcode":"12150",
    "addr:street":"Zi",
    "iso:country":"FR",
    "sg:address":"ZI les Planes",
    "sg:city":"Lapanouse",
    "sg:orig_category":"Unclassifiable Establishments",
    "sg:phone":"+33 5 65 71 65 24",
    "sg:postcode":"12150",
    "sg:province":"Midi Pyr\u00e9n\u00e9es",
    "wof:name":"Point P S.a.",
    "wof:placetype":"venue"
},
  "geometry": {"coordinates":[3.031976,44.334599],"type":"Point"}
}