{
  "type": "Feature",
  "properties": {
    "iso:country":"FR",
    "sg:address":"52 Imp Des Acacias Zi Les Valignons 74460 Marnaz",
    "sg:classifiers":[
        {
            "category":"Manufacturing",
            "subcategory":"Metals",
            "type":"Manufacturing & Wholesale Goods"
        }
    ],
    "sg:phone":"+33 4 50 98 04 22",
    "sg:postcode":"74460",
    "sg:province":"Rhone-Alpes",
    "sg:tags":[
        "metallurgy",
        "metalworking",
        "processing"
    ],
    "wof:name":"Carme Marcel Et Cie Sa",
    "wof:placetype":"venue"
},
  "geometry": {"coordinates":[6.52688,46.06094],"type":"Point"}
}