{
  "type": "Feature",
  "properties": {
    "iso:country":"FR",
    "sg:address":"41 rue Principale 57450 Theding",
    "sg:classifiers":[
        {
            "category":"Organizations",
            "subcategory":"Professional Association",
            "type":"Services"
        }
    ],
    "sg:phone":"+33 3 87 29 13 10",
    "sg:province":"Lorraine",
    "sg:tags":[
        "logistics",
        "planning",
        "software"
    ],
    "wof:name":"Areal S.a.r.l.",
    "wof:placetype":"venue"
},
  "geometry": {"coordinates":[6.894056,49.124008],"type":"Point"}
}