{
  "type": "Feature",
  "properties": {
    "iso:country":"FR",
    "sg:address":"Le Village 07290 Ardoix",
    "sg:classifiers":[
        {
            "category":"Travel",
            "subcategory":"Hotels & Motels",
            "type":"Entertainment"
        }
    ],
    "sg:phone":"+33 4 75 34 57 34",
    "sg:postcode":"07290",
    "sg:province":"Rhone-Alpes",
    "sg:tags":[
        "hotels",
        "business",
        "restaurant"
    ],
    "wof:name":"Sarl L'atria",
    "wof:placetype":"venue"
},
  "geometry": {"coordinates":[4.65085,45.160042],"type":"Point"}
}