{
  "type": "Feature",
  "properties": {
    "addr:full":"27/29, Rue Huret Lagache, 62200 Boulogne sur Mer Nord Pas-de-Calais",
    "addr:housenumber":"27 / 29",
    "addr:postcode":"62200",
    "addr:street":"Rue Huret Lagache;Sur Mer Nord",
    "iso:country":"FR",
    "sg:address":"27/29, Rue Huret Lagache, 62200 Boulogne sur Mer",
    "sg:orig_category":"Unclassifiable Establishments",
    "sg:phone":"+33 3 21 30 88 00",
    "sg:province":"Nord Pas-de-Calais",
    "wof:name":"Faroe France S.a.",
    "wof:placetype":"venue"
},
  "geometry": {"coordinates":[1.591549,50.724255],"type":"Point"}
}