{
  "type": "Feature",
  "properties": {
    "iso:country":"FR",
    "sg:address":"799 avenue de Tournamy 06250 Mougins",
    "sg:classifiers":[
        {
            "category":"Food & Beverages",
            "subcategory":"Chocolate",
            "type":"Retail Goods"
        }
    ],
    "sg:phone":"+33 4 93 75 20 08",
    "sg:province":"Picardie",
    "sg:tags":[
        "export"
    ],
    "wof:name":"Societe Francaise D' Importation Et D' Exportation Sarl",
    "wof:placetype":"venue"
},
  "geometry": {"coordinates":[6.98646,43.602322],"type":"Point"}
}