{
  "type": "Feature",
  "properties": {
    "addr:full":"10, Rue Marcel Cachin, 30100 Al\u00e8s Languedoc-Roussillon",
    "addr:housenumber":"10",
    "addr:postcode":"30100",
    "addr:street":"Rue Marcel Cachin",
    "iso:country":"FR",
    "sg:address":"10, Rue Marcel Cachin, 30100 Al\u00e8s",
    "sg:orig_category":"Unclassifiable Establishments",
    "sg:phone":"+33 4 66 52 02 05",
    "sg:province":"Languedoc-Roussillon",
    "wof:name":"A.f.p.a.",
    "wof:placetype":"venue"
},
  "geometry": {"coordinates":[4.098076,44.132549],"type":"Point"}
}