{
  "type": "Feature",
  "properties": {
    "addr:full":"12, Av. Mouyssagu\u00e8se, 31280 Dr\u00e9mil Lafage Midi Pyr\u00e9n\u00e9es",
    "addr:postcode":"31280",
    "addr:street":"12 Av. Mouyssague\u0300Se",
    "iso:country":"FR",
    "sg:address":"12, Av. Mouyssagu\u00e8se, 31280 Dr\u00e9mil Lafage",
    "sg:orig_category":"Unclassifiable Establishments",
    "sg:phone":"+33 5 61 83 95 07",
    "sg:province":"Midi Pyr\u00e9n\u00e9es",
    "wof:name":"Soci\u00e9t\u00e9 Vignes Jean-paul",
    "wof:placetype":"venue"
},
  "geometry": {"coordinates":[1.585666,43.597198],"type":"Point"}
}