{
  "type": "Feature",
  "properties": {
    "iso:country":"FR",
    "sg:address":"46, Rue Louis Blanc, 59260 Hellemmes Lille",
    "sg:orig_category":"Unclassifiable Establishments",
    "sg:phone":"+33 3 20 33 20 30",
    "sg:province":"Nord Pas-de-Calais",
    "wof:name":"Jeantils Gillet S.a.",
    "wof:placetype":"venue"
},
  "geometry": {"coordinates":[3.11705,50.614567],"type":"Point"}
}