{
  "type": "Feature",
  "properties": {
    "iso:country":"FR",
    "sg:address":"34 rue Paulin Pecqueux 02110 Bohain en Vermandois",
    "sg:classifiers":[
        {
            "category":"Manufacturing",
            "subcategory":"Textiles",
            "type":"Manufacturing & Wholesale Goods"
        }
    ],
    "sg:phone":"+33 3 23 07 12 96",
    "sg:postcode":"02110",
    "sg:province":"Picardie",
    "sg:tags":[
        "towel",
        "bath"
    ],
    "wof:name":"Manufacture De Bohain Picardie Sa",
    "wof:placetype":"venue"
},
  "geometry": {"coordinates":[3.451599,49.988823],"type":"Point"}
}