{
  "type": "Feature",
  "properties": {
    "addr:full":"Av. Ren\u00e9 Cassin - ZI Trets Pays de Loire 13530",
    "addr:postcode":"13530",
    "addr:street":"Av. Rene\u0301 Cassin",
    "iso:country":"FR",
    "sg:address":"Av. Ren\u00e9 Cassin - ZI",
    "sg:city":"Trets",
    "sg:orig_category":"Unclassifiable Establishments",
    "sg:phone":"+33 4 42 29 45 20",
    "sg:postcode":"13530",
    "sg:province":"Pays de Loire",
    "wof:name":"Etablissement Gouiran S.a.",
    "wof:placetype":"venue"
},
  "geometry": {"coordinates":[5.68379,43.447651],"type":"Point"}
}