{
  "type": "Feature",
  "properties": {
    "addr:full":"Zi Sud Du Mans 53960 Bonchamp Les Laval Pays de Loire",
    "addr:postcode":"53960",
    "addr:street":"Du Mans;Les Laval",
    "iso:country":"FR",
    "sg:address":"Zi Sud",
    "sg:city":"Du Mans 53960 Bonchamp Les Laval",
    "sg:classifiers":[
        {
            "category":"Professional",
            "type":"Services"
        }
    ],
    "sg:phone":"+33 2 43 49 29 55",
    "sg:province":"Pays de Loire",
    "sg:tags":[
        "transport",
        "road"
    ],
    "wof:name":"Laval Bureautique Sarl",
    "wof:placetype":"venue"
},
  "geometry": {"coordinates":[-0.698759,48.070309],"type":"Point"}
}