{
  "type": "Feature",
  "properties": {
    "addr:full":"4, Rte de Branchy, 74600 Seynod Rhone-Alpes",
    "addr:housenumber":"4",
    "addr:postcode":"74600",
    "addr:street":"Rte De Branchy",
    "iso:country":"FR",
    "sg:address":"4, Rte de Branchy, 74600 Seynod",
    "sg:orig_category":"Unclassifiable Establishments",
    "sg:phone":"+33 4 50 69 33 73",
    "sg:province":"Rhone-Alpes",
    "wof:name":"Initial S.a.",
    "wof:placetype":"venue"
},
  "geometry": {"coordinates":[6.08347,45.881699],"type":"Point"}
}