{
  "type": "Feature",
  "properties": {
    "addr:full":"ZA de la For\u00eat Champagn\u00e9 Pays de Loire 72470",
    "addr:postcode":"72470",
    "addr:street":"Za De La Fore\u0302T",
    "iso:country":"FR",
    "sg:address":"ZA de la For\u00eat",
    "sg:city":"Champagn\u00e9",
    "sg:orig_category":"Non-Classified Establishments",
    "sg:phone":"+33 2 43 54 05 20",
    "sg:postcode":"72470",
    "sg:province":"Pays de Loire",
    "wof:name":"E.t.d.e. S.a. - Entreprise De Transport Et Distribution D'energies",
    "wof:placetype":"venue"
},
  "geometry": {"coordinates":[0.330306,48.024048],"type":"Point"}
}