{
  "type": "Feature",
  "properties": {
    "addr:full":"160, Av de Strasbourg, 54000 Nancy Lorraine",
    "addr:housenumber":"160",
    "addr:postcode":"54000",
    "addr:street":"Av De Strasbourg",
    "iso:country":"FR",
    "sg:address":"160, Av de Strasbourg, 54000 Nancy",
    "sg:orig_category":"Unclassifiable Establishments",
    "sg:phone":"+33 3 83 85 58 55",
    "sg:province":"Lorraine",
    "wof:name":"Cabinet Blique Actimum S.a.r.l.",
    "wof:placetype":"venue"
},
  "geometry": {"coordinates":[6.194952,48.680149],"type":"Point"}
}