{
  "type": "Feature",
  "properties": {
    "addr:full":"269, Rte des 3 Lucs, 13011 Marseille Poitou-Charentes",
    "addr:housenumber":"269",
    "addr:postcode":"13011",
    "addr:street":"Rte Des 3 Lucs",
    "iso:country":"FR",
    "sg:address":"269, Rte des 3 Lucs, 13011 Marseille",
    "sg:orig_category":"Unclassifiable Establishments",
    "sg:phone":"+33 4 91 36 40 20",
    "sg:province":"Poitou-Charentes",
    "wof:name":"Laboratoires D'herboristerie G\u00e9n\u00e9rale S.a.",
    "wof:placetype":"venue"
},
  "geometry": {"coordinates":[5.482335,43.29821],"type":"Point"}
}