{
  "type": "Feature",
  "properties": {
    "iso:country":"FR",
    "sg:address":"9, Av. Saint Fiacre, 78100 Saint Germain en Laye",
    "sg:orig_category":"Non-Classified Establishments",
    "sg:phone":"+33 1 39 73 48 91",
    "sg:province":"Ile de France",
    "wof:name":"Gesop S.a.r.l.",
    "wof:placetype":"venue"
},
  "geometry": {"coordinates":[2.072586,48.895321],"type":"Point"}
}