{
  "type": "Feature",
  "properties": {
    "iso:country":"FR",
    "sg:address":"zone d'Activit\u00e9 35390 Grand Fougeray",
    "sg:city":"Grand-Fougeray",
    "sg:classifiers":[
        {
            "category":"Manufacturing",
            "subcategory":"Motor Vehicles & Parts",
            "type":"Manufacturing & Wholesale Goods"
        }
    ],
    "sg:phone":"+33 2 99 08 32 34",
    "sg:postcode":"35390",
    "sg:province":"Bretagne",
    "sg:tags":[
        "precision",
        "mechanic"
    ],
    "wof:name":"Ferotec France Sa",
    "wof:placetype":"venue"
},
  "geometry": {"coordinates":[-1.73254,47.723339],"type":"Point"}
}