{
  "type": "Feature",
  "properties": {
    "addr:full":"R De Sabanel 81160 Saint Ju\u00e9ry Midi Pyr\u00e9n\u00e9es 81160",
    "addr:postcode":"81160 saint jue\u0301ry;pyre\u0301ne\u0301es 81160",
    "iso:country":"FR",
    "sg:address":"R De Sabanel 81160 Saint Ju\u00e9ry",
    "sg:classifiers":[
        {
            "category":"Shopping",
            "type":"Retail Goods"
        }
    ],
    "sg:phone":"+33 5 63 78 12 00",
    "sg:postcode":"81160",
    "sg:province":"Midi Pyr\u00e9n\u00e9es",
    "sg:tags":[
        "metallurgy",
        "finished",
        "-",
        "metalworking",
        "metallic"
    ],
    "wof:name":"Fct",
    "wof:placetype":"venue"
},
  "geometry": {"coordinates":[2.20681,43.949619],"type":"Point"}
}