{
  "type": "Feature",
  "properties": {
    "addr:full":"Zi Chanteloiseau 33140 Villenave D'Ornon Cadaujac Aquitaine 33140",
    "addr:postcode":"33140;33140",
    "iso:country":"FR",
    "sg:address":"Zi Chanteloiseau 33140 Villenave D'Ornon",
    "sg:city":"Cadaujac",
    "sg:classifiers":[
        {
            "category":"Manufacturing",
            "subcategory":"Rubber & Plastics",
            "type":"Manufacturing & Wholesale Goods"
        }
    ],
    "sg:phone":"+33 5 56 89 62 38",
    "sg:postcode":"33140",
    "sg:province":"Aquitaine",
    "wof:name":"Prduits Metalliques Du Sud Ouest (pum Sa)",
    "wof:placetype":"venue"
},
  "geometry": {"coordinates":[-0.568254,44.759846],"type":"Point"}
}