{
  "type": "Feature",
  "properties": {
    "iso:country":"FR",
    "sg:address":"255 R Du Pont De Pierre 59600 Maubeuge",
    "sg:classifiers":[
        {
            "category":"Manufacturing",
            "subcategory":"Tools & Machinery",
            "type":"Manufacturing & Wholesale Goods"
        }
    ],
    "sg:phone":"+33 3 27 64 55 77",
    "sg:postcode":"59600",
    "sg:province":"Nord Pas-de-Calais",
    "sg:tags":[
        "equipment",
        "measurement",
        "-",
        "precision",
        "instrument"
    ],
    "wof:name":"Sambronic Sarl",
    "wof:placetype":"venue"
},
  "geometry": {"coordinates":[3.944281,50.28474],"type":"Point"}
}