{
  "type": "Feature",
  "properties": {
    "iso:country":"FR",
    "sg:address":"43, Rue Raspail, 92594 Levallois Perret C\u00e9dex",
    "sg:orig_category":"Non-Classified Establishments",
    "sg:phone":"+33 1 41 06 18 21",
    "sg:province":"Languedoc-Roussillon",
    "wof:name":"Axicom Communication S.a.r.l.",
    "wof:placetype":"venue"
},
  "geometry": {"coordinates":[2.291584,48.897919],"type":"Point"}
}