{
  "type": "Feature",
  "properties": {
    "addr:full":"Chemin des Merci\u00e8res - ZI Rillieux La Pape Rhone-Alpes 69140",
    "addr:postcode":"69140",
    "addr:street":"Chemin Des Mercie\u0300Res Zi Rillieux La Pape Rhone-Alpes",
    "iso:country":"FR",
    "sg:address":"Chemin des Merci\u00e8res - ZI",
    "sg:city":"Rillieux La Pape",
    "sg:orig_category":"Unclassifiable Establishments",
    "sg:phone":"+33 4 78 35 00 80",
    "sg:postcode":"69140",
    "sg:province":"Rhone-Alpes",
    "wof:name":"Soci\u00e9t\u00e9 Nouvelle Eltra S.a.",
    "wof:placetype":"venue"
},
  "geometry": {"coordinates":[4.897105,45.820801],"type":"Point"}
}