{
  "type": "Feature",
  "properties": {
    "addr:full":"160, Rue Amp\u00e8re - ZI, 36000 Ch\u00e2teauroux Ch\u00e2teauroux Centre 36000",
    "addr:housenumber":"160",
    "addr:postcode":"36000;36000",
    "addr:street":"Rue Ampe\u0300Re Zi;Cha\u0302Teauroux",
    "iso:country":"FR",
    "sg:address":"160, Rue Amp\u00e8re - ZI, 36000 Ch\u00e2teauroux",
    "sg:city":"Ch\u00e2teauroux",
    "sg:orig_category":"Non-Classified Establishments",
    "sg:phone":"+33 2 54 34 44 48",
    "sg:postcode":"36000",
    "sg:province":"Centre",
    "wof:name":"Aff\u00fbtage Industriel Du Centre S.a.r.l.",
    "wof:placetype":"venue"
},
  "geometry": {"coordinates":[1.696558,46.812469],"type":"Point"}
}