{
  "type": "Feature",
  "properties": {
    "iso:country":"FR",
    "sg:address":"ZA - La Servaz",
    "sg:city":"Chamoux sur Gelon",
    "sg:orig_category":"Unclassifiable Establishments",
    "sg:phone":"+33 4 79 36 41 72",
    "sg:postcode":"73390",
    "sg:province":"Rhone-Alpes",
    "wof:name":"S.m.e.a. S.a.r.l. - Soci\u00e9t\u00e9 De Maintenance Electrique Des Alpes",
    "wof:placetype":"venue"
},
  "geometry": {"coordinates":[6.215175,45.53289],"type":"Point"}
}