{
  "type": "Feature",
  "properties": {
    "iso:country":"FR",
    "sg:address":"14 Rue Denis Papin 95870 Bezons",
    "sg:classifiers":[
        {
            "category":"Wholesale",
            "subcategory":"Machinery & Supplies",
            "type":"Manufacturing & Wholesale Goods"
        }
    ],
    "sg:phone":"+33 1 39 82 25 55",
    "sg:province":"Ile de France",
    "sg:tags":[
        "equipment",
        "precision"
    ],
    "wof:name":"Precis Mecanique (ste) Sa",
    "wof:placetype":"venue"
},
  "geometry": {"coordinates":[2.206607,48.939182],"type":"Point"}
}