{
  "type": "Feature",
  "properties": {
    "addr:full":"rue Principale 01300 St Benoit Rhone-Alpes",
    "addr:postcode":"01300",
    "addr:street":"Rue Principale",
    "iso:country":"FR",
    "sg:address":"rue Principale 01300 St Benoit",
    "sg:classifiers":[
        {
            "category":"Manufacturing",
            "subcategory":"Electronics",
            "type":"Manufacturing & Wholesale Goods"
        }
    ],
    "sg:phone":"+33 4 74 39 71 42",
    "sg:province":"Rhone-Alpes",
    "sg:tags":[
        "pcb",
        "printed",
        "circuit",
        "board"
    ],
    "wof:name":"Plantin S.a.",
    "wof:placetype":"venue"
},
  "geometry": {"coordinates":[5.67735,45.734741],"type":"Point"}
}