{
  "type": "Feature",
  "properties": {
    "addr:full":"22, Passage Saint Bernard, 75011 Paris Ile de France",
    "addr:housenumber":"22",
    "addr:postcode":"75011",
    "addr:street":"Passage Saint",
    "iso:country":"FR",
    "sg:address":"22, Passage Saint Bernard, 75011 Paris",
    "sg:orig_category":"Unclassifiable Establishments",
    "sg:phone":"+33 1 49 23 06 00",
    "sg:province":"Ile de France",
    "wof:name":"Synergiss S.a.",
    "wof:placetype":"venue"
},
  "geometry": {"coordinates":[2.38022,48.852207],"type":"Point"}
}