{
  "type": "Feature",
  "properties": {
    "addr:full":"2, Rue de Crucy - L'Acropole, 44000 Nantes Pays de Loire 44000",
    "addr:housenumber":"2",
    "addr:postcode":"44000;44000",
    "addr:street":"Rue De Crucy L'Acropole",
    "iso:country":"FR",
    "sg:address":"2, Rue de Crucy - L'Acropole, 44000 Nantes",
    "sg:orig_category":"Non-Classified Establishments",
    "sg:phone":"+33 2 51 72 74 80",
    "sg:postcode":"44000",
    "sg:province":"Pays de Loire",
    "wof:name":"Coheris S.a. - Direction R\u00e9gionale Ouest",
    "wof:placetype":"venue"
},
  "geometry": {"coordinates":[-1.585654,47.19791],"type":"Point"}
}