{
  "type": "Feature",
  "properties": {
    "iso:country":"FR",
    "sg:address":"30 quai Rambaud 69002 Lyon",
    "sg:orig_category":"Food, Vegetarian",
    "sg:phone":"+33 4 78 37 57 03",
    "sg:postcode":"69002",
    "sg:province":"Rhone-Alpes",
    "wof:name":"Dubanchet Et Lay Reunis Sa",
    "wof:placetype":"venue"
},
  "geometry": {"coordinates":[4.815756,45.743992],"type":"Point"}
}