{
  "type": "Feature",
  "properties": {
    "addr:full":"63 Rue Montlosier 63961 Clermont Ferrand Clermont Rhone-Alpes 74270",
    "addr:housenumber":"63",
    "addr:postcode":"63961;74270",
    "addr:street":"Rue Montlosier",
    "iso:country":"FR",
    "sg:address":"63 Rue Montlosier 63961 Clermont Ferrand",
    "sg:city":"Clermont",
    "sg:classifiers":[
        {
            "category":"Banks & Credit Unions",
            "subcategory":"Financial Services",
            "type":"Services"
        }
    ],
    "sg:phone":"+33 4 73 98 58 58",
    "sg:postcode":"74270",
    "sg:province":"Rhone-Alpes",
    "sg:tags":[
        "banking",
        "insurance",
        "institution",
        "finance"
    ],
    "wof:name":"Caisse D'epargne D'auvergne",
    "wof:placetype":"venue"
},
  "geometry": {"coordinates":[2.09017,43.151814],"type":"Point"}
}