{
  "type": "Feature",
  "properties": {
    "iso:country":"FR",
    "sg:address":"RN 8",
    "sg:city":"G\u00e9menos C\u00e9dex",
    "sg:orig_category":"Non-Classified Establishments",
    "sg:phone":"+33 4 42 32 54 54",
    "sg:postcode":"13042",
    "wof:name":"Procopi S.a.",
    "wof:placetype":"venue"
},
  "geometry": {"coordinates":[-69.317047,45.035198],"type":"Point"}
}