{
  "type": "Feature",
  "properties": {
    "iso:country":"FR",
    "sg:address":"B.P. 9, 51130 Vertus^^Av du G\u00e9n\u00e9ral de Gaulle, 51130 Vertus",
    "sg:orig_category":"Non-Classified Establishments",
    "sg:phone":"+33 3 26 52 17 11",
    "sg:province":"Champagne",
    "wof:name":"Les Transports Vertusiens S.a.",
    "wof:placetype":"venue"
},
  "geometry": {"coordinates":[4.007176,48.905682],"type":"Point"}
}