{
  "type": "Feature",
  "properties": {
    "addr:full":"Rue Br\u00e8che 32160 Beaumarch\u00e9s Midi Pyr\u00e9n\u00e9es",
    "addr:postcode":"32160",
    "addr:street":"Rue Bre\u0300Che",
    "iso:country":"FR",
    "sg:address":"Rue Br\u00e8che 32160 Beaumarch\u00e9s",
    "sg:classifiers":[
        {
            "category":"Manufacturing",
            "subcategory":"Rubber & Plastics",
            "type":"Manufacturing & Wholesale Goods"
        }
    ],
    "sg:phone":"+33 5 62 69 48 29",
    "sg:province":"Midi Pyr\u00e9n\u00e9es",
    "wof:name":"Beaumarches Plastiques Sarl",
    "wof:placetype":"venue"
},
  "geometry": {"coordinates":[0.033657,43.551064],"type":"Point"}
}