{
  "type": "Feature",
  "properties": {
    "iso:country":"FR",
    "sg:address":"43, Av. Thiers, 77000 Melun",
    "sg:orig_category":"Unclassifiable Establishments",
    "sg:phone":"+33 1 64 10 29 10",
    "sg:province":"Ile de France",
    "wof:name":"Randstad Int\u00e9rim",
    "wof:placetype":"venue"
},
  "geometry": {"coordinates":[2.654789,48.529644],"type":"Point"}
}