{
  "type": "Feature",
  "properties": {
    "addr:full":"ZI Perrignier Rhone-Alpes 74550",
    "addr:postcode":"74550",
    "addr:street":"Rhone-Alpes",
    "iso:country":"FR",
    "sg:address":"ZI",
    "sg:city":"Perrignier",
    "sg:orig_category":"Unclassifiable Establishments",
    "sg:phone":"+33 4 50 72 03 91",
    "sg:postcode":"74550",
    "sg:province":"Rhone-Alpes",
    "wof:name":"Cnc Production S.a.r.l.",
    "wof:placetype":"venue"
},
  "geometry": {"coordinates":[6.442996,46.30439],"type":"Point"}
}