{
  "type": "Feature",
  "properties": {
    "iso:country":"FR",
    "sg:address":"1 Rue Du Billemont 59223 Roncq",
    "sg:classifiers":[
        {
            "category":"Shopping",
            "subcategory":"Crafts & Fabrics",
            "type":"Retail Goods"
        }
    ],
    "sg:phone":"+33 3 20 94 67 02",
    "sg:postcode":"59223",
    "sg:province":"Nord Pas-de-Calais",
    "sg:tags":[
        "textile",
        "clothing"
    ],
    "wof:name":"Location Autos Dalle",
    "wof:placetype":"venue"
},
  "geometry": {"coordinates":[3.120836,50.754177],"type":"Point"}
}