{
  "type": "Feature",
  "properties": {
    "addr:full":"B.P. 6, 08310 Pauvres^^Rte D\u00e9partementale 946, 08310 Pauvres Alincourt Champagne 08310",
    "addr:housenumber":"6",
    "addr:postcode":"08310;08310;08310",
    "addr:street":"B.P.;De\u0301Partementale 946;Champagne",
    "iso:country":"FR",
    "sg:address":"B.P. 6, 08310 Pauvres^^Rte D\u00e9partementale 946, 08310 Pauvres",
    "sg:city":"Alincourt",
    "sg:orig_category":"Non-Classified Establishments",
    "sg:phone":"+33 3 24 30 31 22",
    "sg:postcode":"08310",
    "sg:province":"Champagne",
    "wof:name":"Euroluz - Coop\u00e9rative Agricole De D\u00e9shydratation Et D'elevage S.c.a.",
    "wof:placetype":"venue"
},
  "geometry": {"coordinates":[4.455163,49.354828],"type":"Point"}
}