{
  "type": "Feature",
  "properties": {
    "addr:full":"Rue Haysettes 59145 Berlaimont Nord Pas-de-Calais 59145",
    "addr:postcode":"59145;59145",
    "addr:street":"Rue Haysettes",
    "iso:country":"FR",
    "sg:address":"Rue Haysettes 59145 Berlaimont",
    "sg:classifiers":[
        {
            "category":"Manufacturing",
            "subcategory":"Metals",
            "type":"Manufacturing & Wholesale Goods"
        }
    ],
    "sg:phone":"+33 3 27 53 66 00",
    "sg:postcode":"59145",
    "sg:province":"Nord Pas-de-Calais",
    "sg:tags":[
        "-",
        "machine",
        "equipment",
        "engineering",
        "machinery",
        "mechanical"
    ],
    "wof:name":"Akers",
    "wof:placetype":"venue"
},
  "geometry": {"coordinates":[3.8099,50.199615],"type":"Point"}
}