{
  "type": "Feature",
  "properties": {
    "iso:country":"FR",
    "sg:address":"14, Bd Marcel Cristol, 13012 Marseille",
    "sg:orig_category":"Non-Classified Establishments",
    "sg:phone":"+33 4 91 12 22 90",
    "sg:province":"Poitou-Charentes",
    "wof:name":"Technal S.a.",
    "wof:placetype":"venue"
},
  "geometry": {"coordinates":[5.416456,43.305122],"type":"Point"}
}