{
  "type": "Feature",
  "properties": {
    "addr:full":"26 Rue Du 11 Novembre 63000 Clermont Ferrand Clermont-Ferrand Auvergne 63000",
    "addr:housenumber":"26",
    "addr:postcode":"63000;63000",
    "addr:street":"Rue Du 11 Novembre",
    "iso:country":"FR",
    "sg:address":"26 Rue Du 11 Novembre 63000 Clermont Ferrand",
    "sg:city":"Clermont-Ferrand",
    "sg:classifiers":[
        {
            "category":"Food & Beverages",
            "subcategory":"Dairy",
            "type":"Retail Goods"
        }
    ],
    "sg:phone":"+33 4 73 37 38 26",
    "sg:postcode":"63000",
    "sg:province":"Auvergne",
    "sg:tags":[
        "cake",
        "product",
        "related",
        "bread"
    ],
    "wof:name":"La Ruche Trianon Sa",
    "wof:placetype":"venue"
},
  "geometry": {"coordinates":[3.082068,45.778442],"type":"Point"}
}