{
  "type": "Feature",
  "properties": {
    "iso:country":"FR",
    "sg:address":"2, Rue Crucy, 44000 Nantes",
    "sg:orig_category":"Unclassifiable Establishments",
    "sg:phone":"+33 2 51 95 48 16",
    "sg:province":"Pays de Loire",
    "wof:name":"Philippe Comte S.a.",
    "wof:placetype":"venue"
},
  "geometry": {"coordinates":[-1.546696,47.214828],"type":"Point"}
}