{
  "type": "Feature",
  "properties": {
    "addr:full":"10, Rue de l'Ile Napol\u00e9on, 68390 Sausheim Sausheim Alsace 68390",
    "addr:housenumber":"10",
    "addr:postcode":"68390;68390",
    "addr:street":"Rue De L'Ile Napole\u0301On;Sausheim",
    "iso:country":"FR",
    "sg:address":"10, Rue de l'Ile Napol\u00e9on, 68390 Sausheim",
    "sg:city":"Sausheim",
    "sg:orig_category":"Non-Classified Establishments",
    "sg:phone":"+33 3 89 45 23 33",
    "sg:postcode":"68390",
    "sg:province":"Alsace",
    "wof:name":"Ets D. Gostovic S.a.r.l.",
    "wof:placetype":"venue"
},
  "geometry": {"coordinates":[7.385881,47.80027],"type":"Point"}
}