{
  "type": "Feature",
  "properties": {
    "iso:country":"FR",
    "sg:address":"11/12, Rue Eug\u00e8ne H\u00e9naff, 78190 Trappes",
    "sg:orig_category":"Unclassifiable Establishments",
    "sg:phone":"+33 1 30 62 01 01",
    "sg:province":"Ile de France",
    "wof:name":"A.2.v. S.a. - Applications Vitesse Variable",
    "wof:placetype":"venue"
},
  "geometry": {"coordinates":[2.006522,48.770546],"type":"Point"}
}