{
  "type": "Feature",
  "properties": {
    "addr:full":"161, Rue Gabriel P\u00e9ri, 94400 Vitry sur Seine Ile de France 94400",
    "addr:housenumber":"161",
    "addr:postcode":"94400;94400",
    "addr:street":"Rue Gabriel Pe\u0301Ri;France",
    "iso:country":"FR",
    "sg:address":"161, Rue Gabriel P\u00e9ri, 94400 Vitry sur Seine",
    "sg:orig_category":"Non-Classified Establishments",
    "sg:phone":"+33 1 47 18 01 01",
    "sg:postcode":"94400",
    "sg:province":"Ile de France",
    "wof:name":"Couvertec France S.a.r.l.",
    "wof:placetype":"venue"
},
  "geometry": {"coordinates":[2.400546,48.793545],"type":"Point"}
}