{
  "type": "Feature",
  "properties": {
    "addr:full":"2 Rue De L'Artisanat 68500 Guebwiller Guebwiller Alsace 68500",
    "addr:housenumber":"2",
    "addr:postcode":"68500;68500",
    "addr:street":"Rue De L'Artisanat",
    "iso:country":"FR",
    "sg:address":"2 Rue De L'Artisanat 68500 Guebwiller",
    "sg:city":"Guebwiller",
    "sg:classifiers":[
        {
            "category":"Shopping",
            "type":"Retail Goods"
        }
    ],
    "sg:phone":"+33 3 89 76 27 30",
    "sg:postcode":"68500",
    "sg:province":"Alsace",
    "sg:tags":[
        "metallurgy",
        "finished",
        "-",
        "metalworking",
        "metallic"
    ],
    "wof:name":"Schmitt Constructions Metalliques Sa",
    "wof:placetype":"venue"
},
  "geometry": {"coordinates":[7.228833,47.8974],"type":"Point"}
}