{
  "type": "Feature",
  "properties": {
    "addr:full":"Le Marais Zone Industrielle 38510 Morestel Rhone-Alpes 38510",
    "addr:postcode":"38510;38510",
    "addr:street":"Zone Industrielle",
    "iso:country":"FR",
    "sg:address":"Le Marais Zone Industrielle 38510 Morestel",
    "sg:classifiers":[
        {
            "category":"Farming",
            "subcategory":"Livestock Farm",
            "type":"Manufacturing & Wholesale Goods"
        }
    ],
    "sg:phone":"+33 4 74 80 11 46",
    "sg:postcode":"38510",
    "sg:province":"Rhone-Alpes",
    "sg:tags":[
        "breeding",
        "agriculture",
        "animal"
    ],
    "wof:name":"Societe Desgal",
    "wof:placetype":"venue"
},
  "geometry": {"coordinates":[5.420305,45.650581],"type":"Point"}
}