{
  "type": "Feature",
  "properties": {
    "addr:full":"27, Rue des Vignes, 87510 Nieul Limousin 87510",
    "addr:housenumber":"27",
    "addr:postcode":"87510;87510",
    "addr:street":"Rue Des Vignes",
    "iso:country":"FR",
    "sg:address":"27, Rue des Vignes, 87510 Nieul",
    "sg:orig_category":"Non-Classified Establishments",
    "sg:phone":"+33 5 55 08 01 55",
    "sg:postcode":"87510",
    "sg:province":"Limousin",
    "wof:name":"Chausse Ren\u00e9",
    "wof:placetype":"venue"
},
  "geometry": {"coordinates":[1.175921,45.927113],"type":"Point"}
}