{
  "type": "Feature",
  "properties": {
    "iso:country":"FR",
    "sg:address":"16 Route Obernai 67530 Boersch",
    "sg:city":"Boersch",
    "sg:classifiers":[
        {
            "category":"Professional",
            "subcategory":"Engineering",
            "type":"Services"
        }
    ],
    "sg:phone":"+33 3 88 95 81 38",
    "sg:postcode":"67530",
    "sg:province":"Alsace",
    "sg:tags":[
        "-",
        "household",
        "appliance",
        "machine",
        "equipment",
        "electrical",
        "mechanical",
        "electronic"
    ],
    "wof:name":"Est Menager Sa",
    "wof:placetype":"venue"
},
  "geometry": {"coordinates":[7.450806,48.476711],"type":"Point"}
}