{
  "type": "Feature",
  "properties": {
    "addr:full":"Terre Plein Du Port 29750 Loctudy Loctudy Bretagne 29750",
    "addr:postcode":"29750;29750",
    "addr:street":"Terre Plein Du Port",
    "iso:country":"FR",
    "sg:address":"Terre Plein Du Port 29750 Loctudy",
    "sg:city":"Loctudy",
    "sg:classifiers":[
        {
            "category":"Autos & Motor Vehicles",
            "subcategory":"Boat Sales",
            "type":"Retail Goods"
        }
    ],
    "sg:phone":"+33 2 98 87 41 69",
    "sg:postcode":"29750",
    "sg:province":"Bretagne",
    "sg:tags":[
        "equipment",
        "transport"
    ],
    "wof:name":"Societe Mecanique Ateliers Bretons (smab)",
    "wof:placetype":"venue"
},
  "geometry": {"coordinates":[-4.168839,47.833488],"type":"Point"}
}