{
  "type": "Feature",
  "properties": {
    "addr:full":"5, Rue Magenta, 59200 Tourcoing Nord Pas-de-Calais",
    "addr:housenumber":"5",
    "addr:postcode":"59200",
    "addr:street":"Rue Magenta",
    "iso:country":"FR",
    "sg:address":"5, Rue Magenta, 59200 Tourcoing",
    "sg:orig_category":"Unclassifiable Establishments",
    "sg:phone":"+33 3 20 69 18 40",
    "sg:province":"Nord Pas-de-Calais",
    "wof:name":"L'affiche Du Nord S.a.",
    "wof:placetype":"venue"
},
  "geometry": {"coordinates":[3.162287,50.709305],"type":"Point"}
}