{
  "type": "Feature",
  "properties": {
    "addr:full":"B.P. 15, 59221 Bauvin^^Cour de la Gare, 59221 Bauvin Nord Pas-de-Calais",
    "addr:postcode":"59221;59221",
    "addr:street":"B.P. 15;La Gare",
    "iso:country":"FR",
    "sg:address":"B.P. 15, 59221 Bauvin^^Cour de la Gare, 59221 Bauvin",
    "sg:orig_category":"Non-Classified Establishments",
    "sg:phone":"+33 3 20 86 44 83",
    "sg:province":"Nord Pas-de-Calais",
    "wof:name":"Pom'ter S.c.a.",
    "wof:placetype":"venue"
},
  "geometry": {"coordinates":[2.897904,50.514332],"type":"Point"}
}