{
  "type": "Feature",
  "properties": {
    "addr:full":"361, Rue du Moulin Roul, 30920 Codognan Languedoc-Roussillon 30920",
    "addr:housenumber":"361",
    "addr:postcode":"30920;30920",
    "addr:street":"Rue Du Moulin Roul",
    "iso:country":"FR",
    "sg:address":"361, Rue du Moulin Roul, 30920 Codognan",
    "sg:orig_category":"Non-Classified Establishments",
    "sg:phone":"+33 4 66 35 10 96",
    "sg:postcode":"30920",
    "sg:province":"Languedoc-Roussillon",
    "wof:name":"Bouvier Robert",
    "wof:placetype":"venue"
},
  "geometry": {"coordinates":[4.214745,43.728195],"type":"Point"}
}