{
  "type": "Feature",
  "properties": {
    "addr:full":"74 Rue Docteur Lemoine 51100 Reims Champagne 51100",
    "addr:housenumber":"74",
    "addr:postcode":"51100;51100",
    "addr:street":"Rue Docteur Lemoine",
    "iso:country":"FR",
    "sg:address":"74 Rue Docteur Lemoine 51100 Reims",
    "sg:classifiers":[
        {
            "category":"Shopping",
            "subcategory":"Clothing, Apparel, & Fashions",
            "type":"Retail Goods"
        }
    ],
    "sg:phone":"+33 3 26 02 24 28",
    "sg:postcode":"51100",
    "sg:province":"Champagne",
    "sg:tags":[
        "textile",
        "clothing",
        "clothes"
    ],
    "wof:name":"Fiprotec Sa",
    "wof:placetype":"venue"
},
  "geometry": {"coordinates":[4.038213,49.266827],"type":"Point"}
}