{
  "type": "Feature",
  "properties": {
    "iso:country":"FR",
    "sg:address":"B.P. 10, 57480 R\u00e9meling^^6, Rte de Thionville, 57480 R\u00e9meling",
    "sg:orig_category":"Non-Classified Establishments",
    "sg:phone":"+33 3 82 83 37 30",
    "sg:postcode":"57480",
    "sg:province":"Lorraine",
    "wof:name":"Difac S.a.",
    "wof:placetype":"venue"
},
  "geometry": {"coordinates":[6.362756,49.443501],"type":"Point"}
}