{
  "type": "Feature",
  "properties": {
    "addr:full":"ZA de l'Olivet Servon sur Vilaine Bretagne 35530",
    "addr:postcode":"35530",
    "addr:street":"Za De L'Olivet Servon Sur Vilaine Bretagne",
    "iso:country":"FR",
    "sg:address":"ZA de l'Olivet",
    "sg:city":"Servon sur Vilaine",
    "sg:orig_category":"Unclassifiable Establishments",
    "sg:phone":"+33 2 99 00 28 00",
    "sg:postcode":"35530",
    "sg:province":"Bretagne",
    "wof:name":"C.i.f.a. S.a. - Construction Industrielle Frigorifique Armoricain",
    "wof:placetype":"venue"
},
  "geometry": {"coordinates":[-1.4593,48.123089],"type":"Point"}
}