{
  "type": "Feature",
  "properties": {
    "iso:country":"FR",
    "sg:address":"85, Av. Victor Hugo, 92563 Rueil Malmaison C\u00e9dex",
    "sg:orig_category":"Non-Classified Establishments",
    "sg:phone":"+33 1 47 52 39 55",
    "sg:province":"Picardie",
    "wof:name":"C.d.f. Ing\u00e9nierie S.a.",
    "wof:placetype":"venue"
},
  "geometry": {"coordinates":[2.17561,48.88596],"type":"Point"}
}