{
  "type": "Feature",
  "properties": {
    "iso:country":"FR",
    "sg:address":"B.P. CE 1511, 91015 Evry C\u00e9dex^^21, Rue des Cerisiers - ZI l'Eglantier, 91090 Lisses",
    "sg:orig_category":"Non-Classified Establishments",
    "sg:phone":"+33 1 60 86 19 21",
    "sg:postcode":"91090",
    "sg:province":"Ile de France",
    "wof:name":"Alpha Electronics S.a.r.l.",
    "wof:placetype":"venue"
},
  "geometry": {"coordinates":[2.432799,48.593472],"type":"Point"}
}