{
  "type": "Feature",
  "properties": {
    "addr:full":"Rte Du Lude 49490 Genneteil Pays de Loire 49490",
    "addr:postcode":"49490;49490",
    "addr:street":"Rte Du Lude",
    "iso:country":"FR",
    "sg:address":"Rte Du Lude 49490 Genneteil",
    "sg:classifiers":[
        {
            "category":"Farming",
            "subcategory":"Crops",
            "type":"Manufacturing & Wholesale Goods"
        }
    ],
    "sg:phone":"+33 2 41 82 10 79",
    "sg:postcode":"49490",
    "sg:province":"Pays de Loire",
    "sg:tags":[
        "horticulture",
        "agriculture",
        "grain",
        "livestock",
        "cereal"
    ],
    "wof:name":"Caval",
    "wof:placetype":"venue"
},
  "geometry": {"coordinates":[0.07725,47.45985],"type":"Point"}
}