{
  "type": "Feature",
  "properties": {
    "addr:full":"8, Av. de Bourranville - Immeuble le Saphir, 33700 M\u00e9rignac M\u00e9rignac Aquitaine 33700",
    "addr:postcode":"33700;33700",
    "addr:street":"Av. De Bourranville Immeuble Le Saphir",
    "iso:country":"FR",
    "sg:address":"8, Av. de Bourranville - Immeuble le Saphir, 33700 M\u00e9rignac",
    "sg:city":"M\u00e9rignac",
    "sg:orig_category":"Unclassifiable Establishments",
    "sg:phone":"+33 5 56 97 41 61",
    "sg:postcode":"33700",
    "sg:province":"Aquitaine",
    "wof:name":"Mannesmann Rexroth S.a.",
    "wof:placetype":"venue"
},
  "geometry": {"coordinates":[-0.630159,44.840649],"type":"Point"}
}