{
  "type": "Feature",
  "properties": {
    "iso:country":"FR",
    "sg:address":"ZA sous la Colombe",
    "sg:city":"Lavancia Epercy",
    "sg:orig_category":"Unclassifiable Establishments",
    "sg:phone":"+33 4 74 75 89 44",
    "sg:postcode":"01590",
    "sg:province":"Franche-Comt\u00e9",
    "wof:name":"Chavet S.a.",
    "wof:placetype":"venue"
},
  "geometry": {"coordinates":[5.678934,46.331543],"type":"Point"}
}