{
  "type": "Feature",
  "properties": {
    "addr:full":"275 Rue Roger Duquenois 60170 CAMBRONNE LES RIBECOURT Picardie",
    "addr:housenumber":"275",
    "addr:postcode":"60170",
    "addr:street":"Rue Roger Duquenois",
    "iso:country":"FR",
    "sg:address":"275 Rue Roger Duquenois 60170 CAMBRONNE LES RIBECOURT",
    "sg:classifiers":[
        {
            "category":"Building & Trades",
            "subcategory":"Plumbing",
            "type":"Services"
        }
    ],
    "sg:phone":"+33 3 44 75 73 00",
    "sg:province":"Picardie",
    "sg:tags":[
        "piping"
    ],
    "wof:name":"C.i.c.r. Sa",
    "wof:placetype":"venue"
},
  "geometry": {"coordinates":[2.898125,49.498348],"type":"Point"}
}