{
  "type": "Feature",
  "properties": {
    "addr:full":"2, Rue du Commerce - Zone du Plouich, 59590 Raismes Nord Pas-de-Calais",
    "addr:housenumber":"2",
    "addr:postcode":"59590",
    "addr:street":"Rue Du Commerce Zone Du Plouich",
    "iso:country":"FR",
    "sg:address":"2, Rue du Commerce - Zone du Plouich, 59590 Raismes",
    "sg:orig_category":"Non-Classified Establishments",
    "sg:phone":"+33 3 27 45 82 00",
    "sg:province":"Nord Pas-de-Calais",
    "wof:name":"Europ Usinage S.a.",
    "wof:placetype":"venue"
},
  "geometry": {"coordinates":[3.483329,50.392513],"type":"Point"}
}