{
  "type": "Feature",
  "properties": {
    "addr:full":"12 rue Roulot 51160 Ay Champagne 51160",
    "addr:housenumber":"12",
    "addr:postcode":"51160;51160",
    "addr:street":"Rue Roulot;Champagne",
    "iso:country":"FR",
    "sg:address":"12 rue Roulot 51160 Ay",
    "sg:classifiers":[
        {
            "category":"Food & Beverages",
            "subcategory":"Liquor & Beverages",
            "type":"Retail Goods"
        }
    ],
    "sg:phone":"+33 3 26 55 14 97",
    "sg:postcode":"51160",
    "sg:province":"Champagne",
    "sg:tags":[
        "champagne"
    ],
    "wof:name":"Champagne Richard Fliniaux Nad\u00e8ge Eurl",
    "wof:placetype":"venue"
},
  "geometry": {"coordinates":[4.008884,49.052975],"type":"Point"}
}