{
  "type": "Feature",
  "properties": {
    "addr:full":"rue Costes et Bellonte 49000 Angers Pays de Loire 49000",
    "addr:postcode":"49000;49000",
    "addr:street":"Rue Costes Et Bellonte",
    "iso:country":"FR",
    "sg:address":"rue Costes et Bellonte 49000 Angers",
    "sg:classifiers":[
        {
            "category":"Food & Beverages",
            "subcategory":"Fruits & Vegetables",
            "type":"Retail Goods"
        }
    ],
    "sg:phone":"+33 2 41 37 70 00",
    "sg:postcode":"49000",
    "sg:province":"Pays de Loire",
    "wof:name":"Pomanjou Sica Sa",
    "wof:placetype":"venue"
},
  "geometry": {"coordinates":[-0.521599,47.455284],"type":"Point"}
}