{
  "type": "Feature",
  "properties": {
    "iso:country":"FR",
    "sg:address":"Av L\u00e9on Blum Za Du Baroeul 59370 Mons En Baroeul",
    "sg:classifiers":[
        {
            "category":"Utilities",
            "subcategory":"Telephone",
            "type":"Services"
        }
    ],
    "sg:phone":"+33 3 28 80 50 80",
    "sg:province":"Nord Pas-de-Calais",
    "sg:tags":[
        "telecommunication"
    ],
    "wof:name":"Worldcom Sa",
    "wof:placetype":"venue"
},
  "geometry": {"coordinates":[3.11015,50.643887],"type":"Point"}
}