{
  "type": "Feature",
  "properties": {
    "addr:full":"B.P. 43 Livron sur Dr\u00f4me C\u00e9dex Rhone-Alpes 26250",
    "addr:postcode":"26250",
    "addr:street":"B.P. 43;Rhone-Alpes",
    "iso:country":"FR",
    "sg:address":"B.P. 43",
    "sg:city":"Livron sur Dr\u00f4me C\u00e9dex",
    "sg:orig_category":"Non-Classified Establishments",
    "sg:phone":"+33 4 75 61 22 11",
    "sg:postcode":"26250",
    "sg:province":"Rhone-Alpes",
    "wof:name":"Skipper Logistique S.a.s.",
    "wof:placetype":"venue"
},
  "geometry": {"coordinates":[4.84206,44.771477],"type":"Point"}
}