{
  "type": "Feature",
  "properties": {
    "iso:country":"FR",
    "sg:address":"S.C Lafont 16130 St Preuil",
    "sg:classifiers":[
        {
            "category":"Food Court",
            "type":"Food & Drink"
        }
    ],
    "sg:phone":"+33 5 45 83 41 27",
    "sg:postcode":"16130",
    "sg:province":"Poitou-Charentes",
    "sg:tags":[
        "product",
        "related"
    ],
    "wof:name":"Cognac Daniel Bouju Sarl",
    "wof:placetype":"venue"
},
  "geometry": {"coordinates":[-0.155144,45.605518],"type":"Point"}
}