{
  "type": "Feature",
  "properties": {
    "addr:full":"B.P. 30036, 14601 Honfleur C\u00e9dex^^Quai Bassin Carnot, 14600 Honfleur Honfleur Basse Normandie 14600",
    "addr:housenumber":"14601",
    "addr:postcode":"14600;14600",
    "addr:street":"Bassin Carnot",
    "iso:country":"FR",
    "sg:address":"B.P. 30036, 14601 Honfleur C\u00e9dex^^Quai Bassin Carnot, 14600 Honfleur",
    "sg:city":"Honfleur",
    "sg:orig_category":"Panneaux Panneaux en fibres de bois",
    "sg:phone":"+33 2 31 81 63 63",
    "sg:postcode":"14600",
    "sg:province":"Basse Normandie",
    "wof:name":"Isoroy Honfleur S.a.",
    "wof:placetype":"venue"
},
  "geometry": {"coordinates":[0.234295,49.356091],"type":"Point"}
}