{
  "type": "Feature",
  "properties": {
    "addr:full":"20, Av. du March\u00e9 Commun, 44300 Nantes Pays de Loire",
    "addr:postcode":"44300",
    "addr:street":"20 Av. Du Marche\u0301 Commun",
    "iso:country":"FR",
    "sg:address":"20, Av. du March\u00e9 Commun, 44300 Nantes",
    "sg:orig_category":"Unclassifiable Establishments",
    "sg:phone":"+33 2 51 89 70 70",
    "sg:province":"Pays de Loire",
    "wof:name":"Tessier Electricit\u00e9 S.a.",
    "wof:placetype":"venue"
},
  "geometry": {"coordinates":[-1.499372,47.255943],"type":"Point"}
}