{
  "type": "Feature",
  "properties": {
    "iso:country":"FR",
    "sg:address":"17, Av. de Paris, 86700 Couh\u00e9",
    "sg:orig_category":"Unclassifiable Establishments",
    "sg:phone":"+33 4 49 37 04 98",
    "sg:postcode":"86700",
    "sg:province":"Poitou-Charentes",
    "wof:name":"Sesaer S.a.r.l.",
    "wof:placetype":"venue"
},
  "geometry": {"coordinates":[0.18294,46.307159],"type":"Point"}
}