{
  "type": "Feature",
  "properties": {
    "iso:country":"FR",
    "sg:address":"20, Av Marcellin Berthelot, 92390 Villeneuve la Garenne",
    "sg:orig_category":"Non-Classified Establishments",
    "sg:phone":"+33 1 41 47 50 80",
    "sg:postcode":"92390",
    "sg:province":"Ile de France",
    "wof:name":"Chopin S.a.",
    "wof:placetype":"venue"
},
  "geometry": {"coordinates":[2.312887,48.945694],"type":"Point"}
}