{
  "type": "Feature",
  "properties": {
    "addr:full":"rue Paul Langevin 49240 Avrille Pays de Loire 49240",
    "addr:postcode":"49240;49240",
    "addr:street":"Rue Paul Langevin;Avrille",
    "iso:country":"FR",
    "sg:address":"rue Paul Langevin 49240 Avrille",
    "sg:classifiers":[
        {
            "category":"Manufacturing",
            "subcategory":"Leather Goods",
            "type":"Manufacturing & Wholesale Goods"
        }
    ],
    "sg:phone":"+33 2 41 42 46 42",
    "sg:postcode":"49240",
    "sg:province":"Pays de Loire",
    "sg:tags":[
        "ready",
        "use",
        "straps",
        "finished",
        "belt"
    ],
    "wof:name":"L'aiglon Sa",
    "wof:placetype":"venue"
},
  "geometry": {"coordinates":[-0.610705,47.518162],"type":"Point"}
}