{
  "type": "Feature",
  "properties": {
    "addr:full":"ZAE la Touffi\u00e8re Saint Martin Bellevue Rhone-Alpes 74370",
    "addr:postcode":"74370",
    "addr:street":"Zae;Rhone-Alpes",
    "iso:country":"FR",
    "sg:address":"ZAE la Touffi\u00e8re",
    "sg:city":"Saint Martin Bellevue",
    "sg:orig_category":"Unclassifiable Establishments",
    "sg:phone":"+33 4 50 60 36 50",
    "sg:postcode":"74370",
    "sg:province":"Rhone-Alpes",
    "wof:name":"Sademo S.a.r.l.",
    "wof:placetype":"venue"
},
  "geometry": {"coordinates":[6.109395,45.934166],"type":"Point"}
}