{
  "type": "Feature",
  "properties": {
    "iso:country":"FR",
    "sg:address":"Place Sylvain Dumon",
    "sg:city":"Valence d'Agen",
    "sg:orig_category":"Unclassifiable Establishments",
    "sg:phone":"+33 5 63 29 04 44",
    "sg:postcode":"82400",
    "sg:province":"Midi Pyr\u00e9n\u00e9es",
    "wof:name":"Auto-distribution Syldos Toulouse S.a.",
    "wof:placetype":"venue"
},
  "geometry": {"coordinates":[0.889021,44.107674],"type":"Point"}
}