{
  "type": "Feature",
  "properties": {
    "addr:full":"Acti Sud Saint-Jean Jouy aux Arches Lorraine 57130",
    "addr:postcode":"57130",
    "addr:street":"Aux Arches Lorraine",
    "iso:country":"FR",
    "sg:address":"Acti Sud Saint-Jean",
    "sg:city":"Jouy aux Arches",
    "sg:orig_category":"Unclassifiable Establishments",
    "sg:phone":"+33 3 87 38 46 70",
    "sg:postcode":"57130",
    "sg:province":"Lorraine",
    "wof:name":"Sercomat S.a.",
    "wof:placetype":"venue"
},
  "geometry": {"coordinates":[6.09949,49.079956],"type":"Point"}
}