{
  "type": "Feature",
  "properties": {
    "addr:full":"15, Av. de la R\u00e9publique, 69200 V\u00e9nissieux Rhone-Alpes",
    "addr:postcode":"69200",
    "addr:street":"15 Av. De La Re\u0301Publique",
    "iso:country":"FR",
    "sg:address":"15, Av. de la R\u00e9publique, 69200 V\u00e9nissieux",
    "sg:orig_category":"Non-Classified Establishments",
    "sg:phone":"+33 4 72 89 38 93",
    "sg:province":"Rhone-Alpes",
    "wof:name":"L.l.m. S.a. - Logistique Location Multiservices",
    "wof:placetype":"venue"
},
  "geometry": {"coordinates":[4.866756,45.707638],"type":"Point"}
}