{
  "type": "Feature",
  "properties": {
    "addr:full":"Place de l'Eglise Val d'Is\u00e8re Rhone-Alpes 73150",
    "addr:postcode":"73150",
    "addr:street":"Place De L'Eglise Val;Rhone-Alpes",
    "iso:country":"FR",
    "sg:address":"Place de l'Eglise",
    "sg:city":"Val d'Is\u00e8re",
    "sg:orig_category":"Non-Classified Establishments",
    "sg:phone":"+33 4 79 06 18 88",
    "sg:postcode":"73150",
    "sg:province":"Rhone-Alpes",
    "wof:name":"Maeva S.n.c.",
    "wof:placetype":"venue"
},
  "geometry": {"coordinates":[6.981215,45.447582],"type":"Point"}
}