{
  "type": "Feature",
  "properties": {
    "addr:full":"118, Av. Paul Doumer, 92500 Rueil Malmaison Ile de France",
    "addr:postcode":"92500",
    "addr:street":"118 Av. Paul Doumer",
    "iso:country":"FR",
    "sg:address":"118, Av. Paul Doumer, 92500 Rueil Malmaison",
    "sg:orig_category":"Unclassifiable Establishments",
    "sg:phone":"+33 1 47 32 36 36",
    "sg:province":"Ile de France",
    "wof:name":"Gika France S.a.s.",
    "wof:placetype":"venue"
},
  "geometry": {"coordinates":[2.183952,48.881325],"type":"Point"}
}