{
  "type": "Feature",
  "properties": {
    "iso:country":"FR",
    "sg:address":"7, Rue Ancienne Ligne, 36600 Vicq sur Nahon",
    "sg:city":"Fontguenand",
    "sg:orig_category":"Unclassifiable Establishments",
    "sg:phone":"+33 2 54 40 30 85",
    "sg:postcode":"36600",
    "sg:province":"Centre",
    "wof:name":"Rioland Maroquiniers S.a.",
    "wof:placetype":"venue"
},
  "geometry": {"coordinates":[1.53112,47.10553],"type":"Point"}
}