{
  "type": "Feature",
  "properties": {
    "iso:country":"FR",
    "sg:address":"141 chemin de Fenouillet 31200 Toulouse",
    "sg:classifiers":[
        {
            "category":"Autos & Motor Vehicles",
            "subcategory":"Fuel & Gas Station",
            "type":"Retail Goods"
        }
    ],
    "sg:phone":"+33 5 61 70 14 81",
    "sg:province":"Midi Pyr\u00e9n\u00e9es",
    "sg:tags":[
        "aluminium",
        "superstructure"
    ],
    "wof:name":"Carrosserie Industrielle Serignac Sa",
    "wof:placetype":"venue"
},
  "geometry": {"coordinates":[1.411467,43.655113],"type":"Point"}
}