{
  "type": "Feature",
  "properties": {
    "addr:full":"170 Pl Henri Regnault 92973 Paris La D\u00e9fense Cedex Picardie",
    "addr:housenumber":"170",
    "addr:postcode":"92973;de\u0301fense cedex",
    "addr:street":"Pl Henri Regnault",
    "iso:country":"FR",
    "sg:address":"170 Pl Henri Regnault 92973 Paris La D\u00e9fense Cedex",
    "sg:classifiers":[
        {
            "category":"Food & Beverages",
            "subcategory":"Groceries & Convenience Stores",
            "type":"Retail Goods"
        }
    ],
    "sg:phone":"+33 1 47 78 21 21",
    "sg:province":"Picardie",
    "sg:tags":[
        "product",
        "related"
    ],
    "wof:name":"Technip Sa",
    "wof:placetype":"venue"
},
  "geometry": {"coordinates":[2.24119,48.888939],"type":"Point"}
}