{
  "type": "Feature",
  "properties": {
    "addr:full":"23, Bd Gay Lussac, 13014 Marseille Poitou-Charentes",
    "addr:housenumber":"23",
    "addr:postcode":"13014",
    "addr:street":"Bd Gay Lussac",
    "iso:country":"FR",
    "sg:address":"23, Bd Gay Lussac, 13014 Marseille",
    "sg:orig_category":"Non-Classified Establishments",
    "sg:phone":"+33 4 91 98 30 33",
    "sg:province":"Poitou-Charentes",
    "wof:name":"Le Globe S.a.r.l.",
    "wof:placetype":"venue"
},
  "geometry": {"coordinates":[5.374405,43.333649],"type":"Point"}
}