{
  "type": "Feature",
  "properties": {
    "addr:full":"4/6, Place de la Halle, 41500 Mer Mer Centre 41500",
    "addr:housenumber":"4 / 6",
    "addr:postcode":"41500;41500",
    "addr:street":"Place De La Halle",
    "iso:country":"FR",
    "sg:address":"4/6, Place de la Halle, 41500 Mer",
    "sg:city":"Mer",
    "sg:orig_category":"Non-Classified Establishments",
    "sg:phone":"+33 2 54 81 03 56",
    "sg:postcode":"41500",
    "sg:province":"Centre",
    "wof:name":"Entreprise Bauer S.a.r.l.",
    "wof:placetype":"venue"
},
  "geometry": {"coordinates":[1.506232,47.703644],"type":"Point"}
}