{
  "type": "Feature",
  "properties": {
    "iso:country":"FR",
    "sg:address":"Rte de Dijon",
    "sg:city":"Bressey sur Tille",
    "sg:orig_category":"Unclassifiable Establishments",
    "sg:phone":"+33 3 80 37 22 91",
    "sg:postcode":"21560",
    "sg:province":"Bourgogne",
    "wof:name":"Maggioni",
    "wof:placetype":"venue"
},
  "geometry": {"coordinates":[5.179138,47.308144],"type":"Point"}
}