{
  "type": "Feature",
  "properties": {
    "addr:full":"Rte De St Laurent Du Pont 38380 Entre Deux Guiers Rhone-Alpes 38380",
    "addr:postcode":"38380;38380",
    "addr:street":"Rte De St Laurent Du Pont;Rhone-Alpes",
    "iso:country":"FR",
    "sg:address":"Rte De St Laurent Du Pont 38380 Entre Deux Guiers",
    "sg:classifiers":[
        {
            "category":"Home & Garden",
            "subcategory":"Furniture",
            "type":"Retail Goods"
        }
    ],
    "sg:phone":"+33 4 76 66 06 48",
    "sg:postcode":"38380",
    "sg:province":"Rhone-Alpes",
    "sg:tags":[
        "household",
        "wood"
    ],
    "wof:name":"Meubles Georges Vial Sarl",
    "wof:placetype":"venue"
},
  "geometry": {"coordinates":[5.790159,45.314697],"type":"Point"}
}