{
  "type": "Feature",
  "properties": {
    "addr:full":"B.P. 77, 77437 Marne la Vall\u00e9e C\u00e9dex^^6, Rue L\u00e9on Jouhaux, 77183 Croissy Beaubourg Ile de France 77183",
    "addr:postcode":"77437;77183;77183",
    "addr:street":"B.P. 77;Rue Le\u0301On Jouhaux",
    "iso:country":"FR",
    "sg:address":"B.P. 77, 77437 Marne la Vall\u00e9e C\u00e9dex^^6, Rue L\u00e9on Jouhaux, 77183 Croissy Beaubourg",
    "sg:orig_category":"Non-Classified Establishments",
    "sg:phone":"+33 4 64 11 62 62",
    "sg:postcode":"77183",
    "sg:province":"Ile de France",
    "wof:name":"A.d.d.x. S.a.",
    "wof:placetype":"venue"
},
  "geometry": {"coordinates":[2.659334,48.828526],"type":"Point"}
}