{
  "type": "Feature",
  "properties": {
    "addr:full":"Rue de l'Industrie - ZI le Fontanil Saint Egr\u00e8ve Rhone-Alpes 38120",
    "addr:postcode":"38120",
    "addr:street":"Rue De L'Industrie Zi Le Fontanil Saint;Rhone-Alpes",
    "iso:country":"FR",
    "sg:address":"Rue de l'Industrie - ZI le Fontanil",
    "sg:city":"Saint Egr\u00e8ve",
    "sg:orig_category":"Unclassifiable Establishments",
    "sg:phone":"+33 4 76 75 81 82",
    "sg:postcode":"38120",
    "sg:province":"Rhone-Alpes",
    "wof:name":"Davigel S.a.",
    "wof:placetype":"venue"
},
  "geometry": {"coordinates":[5.681469,45.221218],"type":"Point"}
}