{
  "type": "Feature",
  "properties": {
    "addr:full":"Route Maumusson 44540 ST MARS LA JAILLE Pays de Loire 44540",
    "addr:postcode":"44540;44540",
    "addr:street":"Route Maumusson;Jaille",
    "iso:country":"FR",
    "sg:address":"Route Maumusson 44540 ST MARS LA JAILLE",
    "sg:orig_category":"Non-Classified Establishments",
    "sg:phone":"+33 2 40 97 44 44",
    "sg:postcode":"44540",
    "sg:province":"Pays de Loire",
    "wof:name":"Aubret Sa",
    "wof:placetype":"venue"
},
  "geometry": {"coordinates":[-1.104094,47.482689],"type":"Point"}
}