{
  "type": "Feature",
  "properties": {
    "iso:country":"FR",
    "sg:address":"23 avenue des Morillons 95140 Garges les Gonesse",
    "sg:classifiers":[
        {
            "category":"Banks & Credit Unions",
            "subcategory":"Investment Brokerage",
            "type":"Services"
        }
    ],
    "sg:phone":"+33 1 39 93 70 11",
    "sg:postcode":"95140",
    "sg:province":"Ile de France",
    "sg:tags":[
        "aeronautics",
        "accessory"
    ],
    "wof:name":"Cmp Sa",
    "wof:placetype":"venue"
},
  "geometry": {"coordinates":[2.40153,48.96413],"type":"Point"}
}