{
  "type": "Feature",
  "properties": {
    "addr:full":"10, Av. 1\u00e8re Arm\u00e9e Fran\u00e7aise Rhin Danube, 01450 Poncin Rhone-Alpes 01450",
    "addr:postcode":"01450;01450",
    "addr:street":"10 Av. 1E\u0300Re Arme\u0301E Franc\u0327Aise Rhin;Rhone-Alpes",
    "iso:country":"FR",
    "sg:address":"10, Av. 1\u00e8re Arm\u00e9e Fran\u00e7aise Rhin Danube, 01450 Poncin",
    "sg:orig_category":"Non-Classified Establishments",
    "sg:phone":"+33 4 74 37 23 52",
    "sg:postcode":"01450",
    "sg:province":"Rhone-Alpes",
    "wof:name":"Ciamtec S.a.",
    "wof:placetype":"venue"
},
  "geometry": {"coordinates":[5.40609,46.082851],"type":"Point"}
}