{
  "type": "Feature",
  "properties": {
    "addr:full":"46, Av. des Fenots, 28100 Dreux Dreux Centre 28100",
    "addr:housenumber":"dreux",
    "addr:postcode":"28100;28100",
    "addr:street":"46 Av. Des Fenots",
    "iso:country":"FR",
    "sg:address":"46, Av. des Fenots, 28100 Dreux",
    "sg:city":"Dreux",
    "sg:orig_category":"Non-Classified Establishments",
    "sg:phone":"+33 2 37 38 07 40",
    "sg:postcode":"28100",
    "sg:province":"Centre",
    "wof:name":"Staim Ouest S.a.",
    "wof:placetype":"venue"
},
  "geometry": {"coordinates":[1.346696,48.740829],"type":"Point"}
}