{
  "type": "Feature",
  "properties": {
    "addr:full":"92084 Paris la D\u00e9fense C\u00e9dex^^1, Place de la Coupole, 92200 Neuilly sur Seine Ile de France",
    "addr:postcode":"92084;92200",
    "addr:street":"Place De La Coupole",
    "iso:country":"FR",
    "sg:address":"92084 Paris la D\u00e9fense C\u00e9dex^^1, Place de la Coupole, 92200 Neuilly sur Seine",
    "sg:orig_category":"Non-Classified Establishments",
    "sg:phone":"+33 1 34 22 41 20",
    "sg:province":"Ile de France",
    "wof:name":"S.m.r.g. S.a. - Soci\u00e9t\u00e9 Mobil Raffinage Notre Dame Gravenchon",
    "wof:placetype":"venue"
},
  "geometry": {"coordinates":[2.26934,48.884377],"type":"Point"}
}