{
  "type": "Feature",
  "properties": {
    "addr:full":"13, Rue Luyot - ZI B, 59113 Seclin Nord Pas-de-Calais 59113",
    "addr:housenumber":"13;b",
    "addr:postcode":"59113;59113",
    "addr:street":"Rue Luyot Zi",
    "iso:country":"FR",
    "sg:address":"13, Rue Luyot - ZI B, 59113 Seclin",
    "sg:orig_category":"Non-Classified Establishments",
    "sg:phone":"+33 3 20 32 91 46",
    "sg:postcode":"59113",
    "sg:province":"Nord Pas-de-Calais",
    "wof:name":"Biotys Ing\u00e9nierie S.a.",
    "wof:placetype":"venue"
},
  "geometry": {"coordinates":[3.026865,50.54681],"type":"Point"}
}