{
  "type": "Feature",
  "properties": {
    "iso:country":"FR",
    "sg:address":"B.P. 4, 56130 La Roche Bernard^^ZI des M\u00e9tairies, 56130 Nivillac",
    "sg:city":"Nivillac",
    "sg:orig_category":"Non-Classified Establishments",
    "sg:phone":"+33 2 99 90 83 14",
    "sg:postcode":"56130",
    "sg:province":"Bretagne",
    "wof:name":"A.m.p. Herblin S.a.r.l.",
    "wof:placetype":"venue"
},
  "geometry": {"coordinates":[-2.353767,47.478352],"type":"Point"}
}