{
  "type": "Feature",
  "properties": {
    "addr:full":"; Belleneuve Belleneuve Bourgogne 21310",
    "addr:postcode":"21310",
    "iso:country":"FR",
    "sg:address":"; Belleneuve",
    "sg:city":"Belleneuve",
    "sg:classifiers":[
        {
            "category":"Banks & Credit Unions",
            "subcategory":"Bank",
            "type":"Services"
        }
    ],
    "sg:phone":"+33 3380319547",
    "sg:postcode":"21310",
    "sg:province":"Bourgogne",
    "wof:name":"Cr\u00e9dit Agricole",
    "wof:placetype":"venue"
},
  "geometry": {"coordinates":[5.26688,47.357655],"type":"Point"}
}