{
  "type": "Feature",
  "properties": {
    "addr:full":"69, Rue du Chevaleret, 75013 Paris Ile de France 75013",
    "addr:housenumber":"69",
    "addr:postcode":"75013;75013",
    "addr:street":"Rue Du Chevaleret",
    "iso:country":"FR",
    "sg:address":"69, Rue du Chevaleret, 75013 Paris",
    "sg:orig_category":"Non-Classified Establishments",
    "sg:phone":"+33 1 56 61 92 80",
    "sg:postcode":"75013",
    "sg:province":"Ile de France",
    "wof:name":"Deltamatic S.a.",
    "wof:placetype":"venue"
},
  "geometry": {"coordinates":[2.37623,48.828541],"type":"Point"}
}