{
  "type": "Feature",
  "properties": {
    "addr:full":"1, Rue des Fauvettes, 85290 Mortagne sur S\u00e8vre Pays de Loire",
    "addr:housenumber":"1",
    "addr:postcode":"85290",
    "addr:street":"Rue Des Fauvettes;Se\u0300Vre",
    "iso:country":"FR",
    "sg:address":"1, Rue des Fauvettes, 85290 Mortagne sur S\u00e8vre",
    "sg:orig_category":"Unclassifiable Establishments",
    "sg:phone":"+33 2 51 65 09 06",
    "sg:province":"Pays de Loire",
    "wof:name":"Freydberg S.a.",
    "wof:placetype":"venue"
},
  "geometry": {"coordinates":[-0.945704,46.99654],"type":"Point"}
}