{
  "type": "Feature",
  "properties": {
    "iso:country":"FR",
    "sg:address":"Rue Marcelin Berthelot 83130 La Garde",
    "sg:classifiers":[
        {
            "category":"Health Services",
            "subcategory":"Medical Lab",
            "type":"Services"
        }
    ],
    "sg:phone":"+33 4 94 75 75 83",
    "sg:province":"Auvergne",
    "sg:tags":[
        "chemical",
        "pharmaceutical",
        "pharmacy"
    ],
    "wof:name":"Ocp Repartition",
    "wof:placetype":"venue"
},
  "geometry": {"coordinates":[6.040949,43.149574],"type":"Point"}
}