{
  "type": "Feature",
  "properties": {
    "addr:full":"Z.A.de Kervendras Sulniac Bretagne 56250",
    "addr:postcode":"56250",
    "addr:street":"Sulniac Bretagne",
    "iso:country":"FR",
    "sg:address":"Z.A.de Kervendras",
    "sg:city":"Sulniac",
    "sg:orig_category":"Unclassifiable Establishments",
    "sg:phone":"+33 2 97 53 28 64",
    "sg:postcode":"56250",
    "sg:province":"Bretagne",
    "wof:name":"A.b. Technologies Alimentaires S.a.r.l.",
    "wof:placetype":"venue"
},
  "geometry": {"coordinates":[-2.567049,47.666672],"type":"Point"}
}