{
  "type": "Feature",
  "properties": {
    "addr:full":"4, Rue du Commandant Dubois, 69003 Lyon Rhone-Alpes",
    "addr:housenumber":"4",
    "addr:postcode":"69003",
    "addr:street":"Rue Du Commandant Dubois",
    "iso:country":"FR",
    "sg:address":"4, Rue du Commandant Dubois, 69003 Lyon",
    "sg:orig_category":"Unclassifiable Establishments",
    "sg:phone":"+33 4 72 60 39 20",
    "sg:province":"Rhone-Alpes",
    "wof:name":"B.i.m.p. S.a.",
    "wof:placetype":"venue"
},
  "geometry": {"coordinates":[4.842881,45.759693],"type":"Point"}
}