{
  "type": "Feature",
  "properties": {
    "iso:country":"FR",
    "sg:address":"B.P. 101",
    "sg:city":"Levallois Perret C\u00e9dex",
    "sg:orig_category":"Non-Classified Establishments",
    "sg:phone":"+33 1 41 05 95 50",
    "sg:postcode":"92303",
    "sg:province":"Languedoc-Roussillon",
    "wof:name":"Grappin Annat Industries S.a.",
    "wof:placetype":"venue"
},
  "geometry": {"coordinates":[2.28505,48.890995],"type":"Point"}
}