{
  "type": "Feature",
  "properties": {
    "iso:country":"FR",
    "sg:address":"ZAC Puits d'Ordet",
    "sg:city":"Challes les Eaux",
    "sg:orig_category":"Non-Classified Establishments",
    "sg:phone":"+33 4 79 72 69 53",
    "sg:postcode":"73190",
    "sg:province":"Rhone-Alpes",
    "wof:name":"Savoie Automatisme",
    "wof:placetype":"venue"
},
  "geometry": {"coordinates":[5.974675,45.555035],"type":"Point"}
}