{
  "type": "Feature",
  "properties": {
    "iso:country":"FR",
    "sg:address":"9, Grand Rue, 68230 Turckheim",
    "sg:city":"Turckheim",
    "sg:orig_category":"Non-Classified Establishments",
    "sg:phone":"+33 3 89 27 14 58",
    "sg:postcode":"68230",
    "sg:province":"Alsace",
    "wof:name":"Marchand Menuiserie S.a.r.l.",
    "wof:placetype":"venue"
},
  "geometry": {"coordinates":[7.277647,48.086525],"type":"Point"}
}