{
  "type": "Feature",
  "properties": {
    "addr:full":"Landes Des Roches 35550 Sixt Sur Aff Bruc-sur-Aff Bretagne 35550",
    "addr:postcode":"35550;35550",
    "addr:street":"Roches;Bruc-Sur-Aff",
    "iso:country":"FR",
    "sg:address":"Landes Des Roches 35550 Sixt Sur Aff",
    "sg:city":"Bruc-sur-Aff",
    "sg:classifiers":[
        {
            "category":"Farming",
            "subcategory":"Crops",
            "type":"Manufacturing & Wholesale Goods"
        }
    ],
    "sg:phone":"+33 2 99 70 02 22",
    "sg:postcode":"35550",
    "sg:province":"Bretagne",
    "sg:tags":[
        "horticulture",
        "agriculture",
        "grain",
        "livestock",
        "cereal"
    ],
    "wof:name":"Cana",
    "wof:placetype":"venue"
},
  "geometry": {"coordinates":[-2.078434,47.770973],"type":"Point"}
}