{
  "type": "Feature",
  "properties": {
    "iso:country":"FR",
    "sg:address":"150 route de la Reine 92100 Boulogne Billancourt",
    "sg:classifiers":[
        {
            "category":"Real Estate",
            "subcategory":"Real Estate Services",
            "type":"Services"
        }
    ],
    "sg:phone":"+33 1 55 38 25 25",
    "sg:province":"Ile de France",
    "sg:tags":[
        "estates",
        "private"
    ],
    "wof:name":"Stim Batir S.a.",
    "wof:placetype":"venue"
},
  "geometry": {"coordinates":[2.231979,48.84058],"type":"Point"}
}