{
  "type": "Feature",
  "properties": {
    "iso:country":"FR",
    "sg:address":"L'Echalotte 16130 Juillac le Coq",
    "sg:orig_category":"Unclassifiable Establishments",
    "sg:phone":"+33 5 45 83 67 06",
    "sg:province":"Poitou-Charentes",
    "wof:name":"Cognac Guerb\u00e9 S.a.r.l.",
    "wof:placetype":"venue"
},
  "geometry": {"coordinates":[-0.284995,45.59687],"type":"Point"}
}