{
  "type": "Feature",
  "properties": {
    "addr:full":"ZI de l'Industrie Saint Laurent Nouan Centre 41220",
    "addr:postcode":"41220",
    "addr:street":"Zi De L'Industrie",
    "iso:country":"FR",
    "sg:address":"ZI de l'Industrie",
    "sg:city":"Saint Laurent Nouan",
    "sg:orig_category":"Non-Classified Establishments",
    "sg:phone":"+33 2 54 87 70 14",
    "sg:postcode":"41220",
    "sg:province":"Centre",
    "wof:name":"Soci\u00e9t\u00e9 Nouvelle D'exploitation Des Bois S.a.",
    "wof:placetype":"venue"
},
  "geometry": {"coordinates":[1.607789,47.710247],"type":"Point"}
}