{
  "type": "Feature",
  "properties": {
    "iso:country":"FR",
    "sg:address":"1 Rue Meyerbeer 75009 Paris",
    "sg:classifiers":[
        {
            "category":"Sports & Exercise",
            "subcategory":"Sports Center",
            "type":"Entertainment"
        }
    ],
    "sg:phone":"+33 1 47 42 35 00",
    "sg:province":"Ile de France",
    "wof:name":"Films Paramount Sa",
    "wof:placetype":"venue"
},
  "geometry": {"coordinates":[2.33361,48.871624],"type":"Point"}
}