{
  "type": "Feature",
  "properties": {
    "addr:full":"142 Avenue De La Viste 13015 Marseille Poitou-Charentes",
    "addr:housenumber":"142",
    "addr:postcode":"13015",
    "addr:street":"Avenue De La Viste",
    "iso:country":"FR",
    "sg:address":"142 Avenue De La Viste 13015 Marseille",
    "sg:classifiers":[
        {
            "category":"Autos & Motor Vehicles",
            "subcategory":"Automobile Sales",
            "type":"Retail Goods"
        }
    ],
    "sg:phone":"+33 4 91 51 93 16",
    "sg:province":"Poitou-Charentes",
    "sg:tags":[
        "equipment",
        "motor-cars",
        "transport"
    ],
    "wof:name":"La Viste Automobile Sa",
    "wof:placetype":"venue"
},
  "geometry": {"coordinates":[5.357444,43.362423],"type":"Point"}
}