{
  "type": "Feature",
  "properties": {
    "addr:full":"39, Rue Lafayette - Zone Industrielle, 58200 Cosne Cours sur Loire Cosne-Cours-sur-Loire Bourgogne 58200",
    "addr:housenumber":"39",
    "addr:postcode":"58200;58200",
    "addr:street":"Rue Lafayette Zone",
    "iso:country":"FR",
    "sg:address":"39, Rue Lafayette - Zone Industrielle, 58200 Cosne Cours sur Loire",
    "sg:city":"Cosne-Cours-sur-Loire",
    "sg:orig_category":"Non-Classified Establishments",
    "sg:phone":"+33 3 86 28 53 88",
    "sg:postcode":"58200",
    "sg:province":"Bourgogne",
    "wof:name":"Autodistribution Vast S.a.",
    "wof:placetype":"venue"
},
  "geometry": {"coordinates":[2.901115,47.369862],"type":"Point"}
}