{
  "type": "Feature",
  "properties": {
    "iso:country":"FR",
    "sg:address":"Ld Champs De Tracy 14500 Vir\u00e9",
    "sg:city":"Vire",
    "sg:classifiers":[
        {
            "category":"Professional",
            "subcategory":"Business Services",
            "type":"Services"
        }
    ],
    "sg:phone":"+33 2 31 66 18 10",
    "sg:postcode":"14500",
    "sg:province":"Basse Normandie",
    "sg:tags":[
        "training",
        "advice"
    ],
    "wof:name":"Lycee Professionnel Agricole",
    "wof:placetype":"venue"
},
  "geometry": {"coordinates":[-77.531914,40.651821],"type":"Point"}
}