{
  "type": "Feature",
  "properties": {
    "iso:country":"FR",
    "sg:address":"Gare Routi\u00e8re Sogaris",
    "sg:city":"Rungis",
    "sg:orig_category":"Unclassifiable Establishments",
    "sg:phone":"+33 1 45 60 81 81",
    "sg:postcode":"94150",
    "sg:province":"Ile de France",
    "wof:name":"Moiroud S.a.",
    "wof:placetype":"venue"
},
  "geometry": {"coordinates":[2.35142,48.74918],"type":"Point"}
}