{
  "type": "Feature",
  "properties": {
    "iso:country":"FR",
    "sg:address":"Larrouquere 40000 Mont De Marsan",
    "sg:city":"Mont-de-Marsan",
    "sg:classifiers":[
        {
            "category":"Food Court",
            "type":"Food & Drink"
        }
    ],
    "sg:phone":"+33 5 58 75 07 02",
    "sg:postcode":"40000",
    "sg:province":"Aquitaine",
    "sg:tags":[
        "product",
        "related"
    ],
    "wof:name":"Elidis Aquitaine",
    "wof:placetype":"venue"
},
  "geometry": {"coordinates":[-0.458266,43.908649],"type":"Point"}
}