{
  "type": "Feature",
  "properties": {
    "addr:full":"2, Rte du Wahlweg, 68310 Wittelsheim Wittelsheim Alsace 68310",
    "addr:housenumber":"2",
    "addr:postcode":"68310;68310",
    "addr:street":"Rte Du Wahlweg",
    "iso:country":"FR",
    "sg:address":"2, Rte du Wahlweg, 68310 Wittelsheim",
    "sg:city":"Wittelsheim",
    "sg:orig_category":"Unclassifiable Establishments",
    "sg:phone":"+33 3 89 55 12 66",
    "sg:postcode":"68310",
    "sg:province":"Alsace",
    "wof:name":"Entreprise Philippe Lassarat S.a.",
    "wof:placetype":"venue"
},
  "geometry": {"coordinates":[7.242588,47.790188],"type":"Point"}
}