{
  "type": "Feature",
  "properties": {
    "addr:full":"B.P. 30, 37110 Ch\u00e2teau Renault C\u00e9dex^^Z.I. N 1, 37110 Ch\u00e2teau Renault Autr\u00e8che Centre 37110",
    "addr:housenumber":"1;autre\u0300che",
    "addr:postcode":"37110;37110;37110",
    "addr:street":"B.P. 30;N",
    "iso:country":"FR",
    "sg:address":"B.P. 30, 37110 Ch\u00e2teau Renault C\u00e9dex^^Z.I. N 1, 37110 Ch\u00e2teau Renault",
    "sg:city":"Autr\u00e8che",
    "sg:orig_category":"Non-Classified Establishments",
    "sg:phone":"+33 2 47 29 84 84",
    "sg:postcode":"37110",
    "sg:province":"Centre",
    "wof:name":"Radiall",
    "wof:placetype":"venue"
},
  "geometry": {"coordinates":[0.99705,47.524975],"type":"Point"}
}