{
  "type": "Feature",
  "properties": {
    "addr:full":"39 Quai D'Embarquement 65000 Tarbes Midi Pyr\u00e9n\u00e9es 65000",
    "addr:housenumber":"39",
    "addr:postcode":"65000;65000",
    "addr:street":"Quai D'Embarquement",
    "iso:country":"FR",
    "sg:address":"39 Quai D'Embarquement 65000 Tarbes",
    "sg:classifiers":[
        {
            "category":"Utilities",
            "subcategory":"Electric",
            "type":"Services"
        }
    ],
    "sg:phone":"+33 5 62 38 93 30",
    "sg:postcode":"65000",
    "sg:province":"Midi Pyr\u00e9n\u00e9es",
    "sg:tags":[
        "electricity",
        "electronic",
        "electrical",
        "equipment"
    ],
    "wof:name":"Latelec",
    "wof:placetype":"venue"
},
  "geometry": {"coordinates":[0.065049,43.241596],"type":"Point"}
}