{
  "type": "Feature",
  "properties": {
    "addr:full":"13 Voiela Cardon Parc Gutemberg 91120 Palaiseau Ile de France",
    "addr:housenumber":"13",
    "addr:postcode":"91120;ile",
    "addr:street":"Voiela Cardon Parc Gutemberg",
    "iso:country":"FR",
    "sg:address":"13 Voiela Cardon Parc Gutemberg 91120 Palaiseau",
    "sg:classifiers":[
        {
            "category":"Wholesale",
            "subcategory":"Machinery & Supplies",
            "type":"Manufacturing & Wholesale Goods"
        }
    ],
    "sg:phone":"+33 1 69 32 10 90",
    "sg:province":"Ile de France",
    "sg:tags":[
        "equipment",
        "precision"
    ],
    "wof:name":"Ademco France",
    "wof:placetype":"venue"
},
  "geometry": {"coordinates":[2.256385,48.707489],"type":"Point"}
}