{
  "type": "Feature",
  "properties": {
    "iso:country":"FR",
    "sg:address":"24, Chemin de la Litte, 92390 Villeneuve la Garenne",
    "sg:orig_category":"Unclassifiable Establishments",
    "sg:phone":"+33 1 47 99 99 00",
    "sg:province":"Ile de France",
    "wof:name":"Clark Mat\u00e9rial Handling France S.a.",
    "wof:placetype":"venue"
},
  "geometry": {"coordinates":[2.325346,48.927422],"type":"Point"}
}