{
  "type": "Feature",
  "properties": {
    "addr:full":"1 \u00e8re Avenue 11\u00e8me Rue 06516 CARROS CEDEX Corse",
    "addr:housenumber":"1",
    "addr:postcode":"06516",
    "addr:street":"E\u0300Re Avenue 11E\u0300Me Rue",
    "iso:country":"FR",
    "sg:address":"1 \u00e8re Avenue 11\u00e8me Rue 06516 CARROS CEDEX",
    "sg:classifiers":[
        {
            "category":"Communications",
            "subcategory":"Radio Station",
            "type":"Services"
        }
    ],
    "sg:phone":"+33 4 92 08 43 00",
    "sg:province":"Corse",
    "sg:tags":[
        "control",
        "changing",
        "signal",
        "traffic"
    ],
    "wof:name":"Sofrel Sa",
    "wof:placetype":"venue"
},
  "geometry": {"coordinates":[7.191765,43.766804],"type":"Point"}
}