{
  "type": "Feature",
  "properties": {
    "iso:country":"FR",
    "sg:address":"81, Rue de Chaussas, 31200 Toulouse",
    "sg:orig_category":"Non-Classified Establishments",
    "sg:phone":"+33 5 61 57 95 96",
    "sg:province":"Midi Pyr\u00e9n\u00e9es",
    "wof:name":"S\u00e9curisol S.a.r.l.",
    "wof:placetype":"venue"
},
  "geometry": {"coordinates":[1.429573,43.618538],"type":"Point"}
}