{
  "type": "Feature",
  "properties": {
    "addr:full":"69 Rue Koechlin 68200 Mulhouse Mulhouse Alsace 68200",
    "addr:housenumber":"69",
    "addr:postcode":"68200;68200",
    "addr:street":"Rue Koechlin",
    "iso:country":"FR",
    "sg:address":"69 Rue Koechlin 68200 Mulhouse",
    "sg:city":"Mulhouse",
    "sg:classifiers":[
        {
            "category":"Professional",
            "subcategory":"Business Services",
            "type":"Services"
        }
    ],
    "sg:phone":"+33 3 89 32 74 40",
    "sg:postcode":"68200",
    "sg:province":"Alsace",
    "sg:tags":[
        "body",
        "advice"
    ],
    "wof:name":"Les Papillons Blancs",
    "wof:placetype":"venue"
},
  "geometry": {"coordinates":[7.332772,47.754368],"type":"Point"}
}