{
  "type": "Feature",
  "properties": {
    "addr:full":"Le Douhet 17100 Le Douhet Poitou-Charentes 17100",
    "addr:postcode":"17100;17100",
    "addr:street":"Douhet",
    "iso:country":"FR",
    "sg:address":"Le Douhet 17100 Le Douhet",
    "sg:orig_category":"Non-Classified Establishments",
    "sg:phone":"+33 5 46 97 78 99",
    "sg:postcode":"17100",
    "sg:province":"Poitou-Charentes",
    "wof:name":"Butagaz S.n.c.",
    "wof:placetype":"venue"
},
  "geometry": {"coordinates":[-0.56593,45.822498],"type":"Point"}
}