{
  "type": "Feature",
  "properties": {
    "addr:full":"2, Rue des Batailles, 63260 Aubiat Aubiat Auvergne 63260",
    "addr:housenumber":"2",
    "addr:postcode":"63260;aubiat;63260",
    "addr:street":"Rue Des Batailles",
    "iso:country":"FR",
    "sg:address":"2, Rue des Batailles, 63260 Aubiat",
    "sg:city":"Aubiat",
    "sg:orig_category":"Non-Classified Establishments",
    "sg:phone":"+33 4 73 97 60 46",
    "sg:postcode":"63260",
    "sg:province":"Auvergne",
    "wof:name":"C\u00e2blage B\u00e2timent Installations Industrielles S.a.r.l.",
    "wof:placetype":"venue"
},
  "geometry": {"coordinates":[3.16723,45.977863],"type":"Point"}
}