{
  "type": "Feature",
  "properties": {
    "iso:country":"FR",
    "sg:address":"40 Rue Amp\u00e8re 85000 La Roche Sur Yon",
    "sg:classifiers":[
        {
            "category":"Shopping",
            "subcategory":"Clothing, Apparel, & Fashions",
            "type":"Retail Goods"
        }
    ],
    "sg:phone":"+33 2 51 37 14 15",
    "sg:postcode":"85000",
    "sg:province":"Pays de Loire",
    "sg:tags":[
        "textile",
        "clothing",
        "clothes"
    ],
    "wof:name":"Ferry Jp Sarl",
    "wof:placetype":"venue"
},
  "geometry": {"coordinates":[-1.438179,46.66222],"type":"Point"}
}