{
  "type": "Feature",
  "properties": {
    "iso:country":"FR",
    "sg:address":"Les Granges De Montagnieu 01470 Montagnieu",
    "sg:classifiers":[
        {
            "category":"Home & Garden",
            "subcategory":"Furniture",
            "type":"Retail Goods"
        }
    ],
    "sg:phone":"+33 4 74 36 73 24",
    "sg:postcode":"01470",
    "sg:province":"Rhone-Alpes",
    "sg:tags":[
        "wood"
    ],
    "wof:name":"Romeggio Et Fils Bmb Sarl",
    "wof:placetype":"venue"
},
  "geometry": {"coordinates":[5.46698,45.797981],"type":"Point"}
}