{
  "type": "Feature",
  "properties": {
    "iso:country":"FR",
    "sg:address":"B.P. 42, 31321 Castanet Tolosan C\u00e9dex^^ZI de Vic, 31320 Castanet Tolosan",
    "sg:orig_category":"Non-Classified Establishments",
    "sg:phone":"+33 5 62 71 78 78",
    "sg:postcode":"31320",
    "sg:province":"Midi Pyr\u00e9n\u00e9es",
    "wof:name":"E.j.l. Midi-pyr\u00e9n\u00e9es S.n.c. - Entreprise Jean Lefebvre",
    "wof:placetype":"venue"
},
  "geometry": {"coordinates":[1.452547,43.482239],"type":"Point"}
}