{
  "type": "Feature",
  "properties": {
    "addr:full":"B.P. 171, 67726 Hoerdt C\u00e9dex^^6, Rue de l'Energie, 67720 Hoerdt Hoerdt Alsace 67720",
    "addr:housenumber":"b.p. 171",
    "addr:postcode":"67726;67720;67720",
    "addr:street":"Rue De L'Energie",
    "iso:country":"FR",
    "sg:address":"B.P. 171, 67726 Hoerdt C\u00e9dex^^6, Rue de l'Energie, 67720 Hoerdt",
    "sg:city":"Hoerdt",
    "sg:orig_category":"Non-Classified Establishments",
    "sg:phone":"+33 3 88 68 20 60",
    "sg:postcode":"67720",
    "sg:province":"Alsace",
    "wof:name":"Home Pro S.a.r.l.",
    "wof:placetype":"venue"
},
  "geometry": {"coordinates":[7.791481,48.67453],"type":"Point"}
}