{
  "type": "Feature",
  "properties": {
    "iso:country":"FR",
    "sg:address":"6 Rn 39 62170 Attin La Paix Faite",
    "sg:classifiers":[
        {
            "category":"Professional",
            "type":"Services"
        }
    ],
    "sg:phone":"+33 3 21 06 08 76",
    "sg:province":"Nord Pas-de-Calais",
    "sg:tags":[
        "transport",
        "road"
    ],
    "wof:name":"Martel Transports Sarl",
    "wof:placetype":"venue"
},
  "geometry": {"coordinates":[1.73439,50.384281],"type":"Point"}
}