{
  "type": "Feature",
  "properties": {
    "addr:full":"40, Place du G\u00e9n\u00e9ral de gaulle, 62310 Fruges Nord Pas-de-Calais",
    "addr:housenumber":"40",
    "addr:postcode":"62310",
    "addr:street":"Place Du Ge\u0301Ne\u0301Ral De Gaulle",
    "iso:country":"FR",
    "sg:address":"40, Place du G\u00e9n\u00e9ral de gaulle, 62310 Fruges",
    "sg:orig_category":"Non-Classified Establishments",
    "sg:phone":"+33 3 21 04 43 52",
    "sg:province":"Nord Pas-de-Calais",
    "wof:name":"Imprimerie Librairie Boulanger S.a.r.l.",
    "wof:placetype":"venue"
},
  "geometry": {"coordinates":[2.1345,50.513699],"type":"Point"}
}