{
  "type": "Feature",
  "properties": {
    "addr:full":"Bruillec 22780 Plounerin Ploun\u00e9rin Bretagne 22780",
    "addr:postcode":"22780;22780",
    "addr:street":"Bruillec;Ploune\u0301Rin",
    "iso:country":"FR",
    "sg:address":"Bruillec 22780 Plounerin",
    "sg:city":"Ploun\u00e9rin",
    "sg:orig_category":"Non-Classified Establishments",
    "sg:phone":"+33 2 96 38 63 97",
    "sg:postcode":"22780",
    "sg:province":"Bretagne",
    "wof:name":"Les Granits De Guerlesquin S.a.",
    "wof:placetype":"venue"
},
  "geometry": {"coordinates":[-3.567949,48.574245],"type":"Point"}
}