{
  "type": "Feature",
  "properties": {
    "iso:country":"FR",
    "sg:address":"6",
    "sg:city":"Vallet 49270 Landemont",
    "sg:classifiers":[
        {
            "category":"Food Court",
            "type":"Food & Drink"
        }
    ],
    "sg:phone":"+33 2 40 98 72 14",
    "sg:postcode":"49270",
    "sg:province":"Pays de Loire",
    "sg:tags":[
        "product",
        "related"
    ],
    "wof:name":"Bochereau Sa",
    "wof:placetype":"venue"
},
  "geometry": {"coordinates":[-1.184474,47.253479],"type":"Point"}
}