{
  "type": "Feature",
  "properties": {
    "addr:full":"26, Place Saint Marc, 76000 Rouen Haute Normandie",
    "addr:housenumber":"26",
    "addr:postcode":"76000",
    "addr:street":"Place Saint Marc;Haute Normandie",
    "iso:country":"FR",
    "sg:address":"26, Place Saint Marc, 76000 Rouen",
    "sg:orig_category":"Unclassifiable Establishments",
    "sg:phone":"+33 2 35 70 98 04",
    "sg:province":"Haute Normandie",
    "wof:name":"G.s.f. Neptune S.a. - Groupe Service France",
    "wof:placetype":"venue"
},
  "geometry": {"coordinates":[1.101826,49.43848],"type":"Point"}
}