{
  "type": "Feature",
  "properties": {
    "addr:full":"rue Lorival 59113 Seclin Nord Pas-de-Calais 59113",
    "addr:postcode":"59113;59113",
    "addr:street":"Rue Lorival",
    "iso:country":"FR",
    "sg:address":"rue Lorival 59113 Seclin",
    "sg:classifiers":[
        {
            "category":"Airport",
            "type":"Transportation"
        }
    ],
    "sg:phone":"+33 3 20 90 95 95",
    "sg:postcode":"59113",
    "sg:province":"Nord Pas-de-Calais",
    "sg:tags":[
        "air-freight",
        "forwarders"
    ],
    "wof:name":"Mazet Lille Sa",
    "wof:placetype":"venue"
},
  "geometry": {"coordinates":[3.03307,50.563847],"type":"Point"}
}