{
  "type": "Feature",
  "properties": {
    "iso:country":"FR",
    "sg:address":"38 rue Narcisse Lanchy 25000 BESANCON",
    "sg:classifiers":[
        {
            "category":"Communications",
            "type":"Services"
        }
    ],
    "sg:phone":"+33 3 81 80 86 45",
    "sg:province":"Franche Comt\u00e9",
    "sg:tags":[
        "translation"
    ],
    "wof:name":"Traje Sarl",
    "wof:placetype":"venue"
},
  "geometry": {"coordinates":[6.028854,47.258053],"type":"Point"}
}