{
  "type": "Feature",
  "properties": {
    "addr:full":"479, Rte de l'Oratoir - Chaumontet , 74330 Sillingy Rhone-Alpes",
    "addr:housenumber":"479",
    "addr:postcode":"74330",
    "addr:street":"Rte De L'Oratoir Chaumontet",
    "iso:country":"FR",
    "sg:address":"479, Rte de l'Oratoir - Chaumontet , 74330 Sillingy",
    "sg:orig_category":"Non-Classified Establishments",
    "sg:phone":"+33 4 50 22 34 50",
    "sg:province":"Rhone-Alpes",
    "wof:name":"S.a.e.v. S.a. - Soci\u00e9t\u00e9 D'am\u00e9nagement D'espaces Verts",
    "wof:placetype":"venue"
},
  "geometry": {"coordinates":[6.061498,45.94009],"type":"Point"}
}