{
  "type": "Feature",
  "properties": {
    "iso:country":"FR",
    "sg:address":"B.P. 53, 84134 Le Pontet C\u00e9dex^^RN 7, 84130 Le Pontet",
    "sg:orig_category":"Non-Classified Establishments",
    "sg:phone":"+33 4 90 31 45 14",
    "sg:province":"Provence-Alpes-C\u00f4te d'Azur",
    "wof:name":"Filtralfa",
    "wof:placetype":"venue"
},
  "geometry": {"coordinates":[4.859935,43.96188],"type":"Point"}
}