{
  "type": "Feature",
  "properties": {
    "addr:full":"288, Bd Teophile Sueur, 93100 Montreuil Ile de France",
    "addr:housenumber":"288",
    "addr:postcode":"93100",
    "addr:street":"Bd Teophile Sueur",
    "iso:country":"FR",
    "sg:address":"288, Bd Teophile Sueur, 93100 Montreuil",
    "sg:orig_category":"Unclassifiable Establishments",
    "sg:phone":"+33 1 48 70 00 80",
    "sg:province":"Ile de France",
    "wof:name":"Longuet Roger",
    "wof:placetype":"venue"
},
  "geometry": {"coordinates":[2.466829,48.858086],"type":"Point"}
}