{
  "type": "Feature",
  "properties": {
    "iso:country":"FR",
    "sg:address":"Blaise 08400 Vouziers",
    "sg:orig_category":"Non-Classified Establishments",
    "sg:phone":"+33 3 24 71 89 95",
    "sg:province":"Champagne",
    "wof:name":"Rouy Et Compagnie S.a.r.l.",
    "wof:placetype":"venue"
},
  "geometry": {"coordinates":[4.65469,49.391979],"type":"Point"}
}