{
  "type": "Feature",
  "properties": {
    "iso:country":"FR",
    "sg:address":"48, Rue Achard, 33000 Bordeaux",
    "sg:city":"Bordeaux",
    "sg:orig_category":"Unclassifiable Establishments",
    "sg:phone":"+33 5 56 50 60 11",
    "sg:postcode":"33000",
    "sg:province":"Aquitaine",
    "wof:name":"Schars S.a.",
    "wof:placetype":"venue"
},
  "geometry": {"coordinates":[-0.581039,44.836636],"type":"Point"}
}