{
  "type": "Feature",
  "properties": {
    "addr:full":"135, Rue Castagnary, 75015 Paris Ile de France",
    "addr:housenumber":"135",
    "addr:postcode":"75015",
    "addr:street":"Rue Castagnary",
    "iso:country":"FR",
    "sg:address":"135, Rue Castagnary, 75015 Paris",
    "sg:orig_category":"Unclassifiable Establishments",
    "sg:phone":"+33 1 48 28 25 81",
    "sg:province":"Ile de France",
    "wof:name":"Etablissement Barbaud S.a.",
    "wof:placetype":"venue"
},
  "geometry": {"coordinates":[2.302657,48.829933],"type":"Point"}
}