{
  "type": "Feature",
  "properties": {
    "addr:full":"180, Rue du Mar\u00e9chal Leclerc, 33130 B\u00e8gles B\u00e8gles Aquitaine 33130",
    "addr:housenumber":"180",
    "addr:postcode":"33130;33130",
    "addr:street":"Rue Du Mare\u0301Chal Leclerc",
    "iso:country":"FR",
    "sg:address":"180, Rue du Mar\u00e9chal Leclerc, 33130 B\u00e8gles",
    "sg:city":"B\u00e8gles",
    "sg:orig_category":"Non-Classified Establishments",
    "sg:phone":"+33 5 56 85 68 20",
    "sg:postcode":"33130",
    "sg:province":"Aquitaine",
    "wof:name":"Composition D'aquitaine S.a.r.l.",
    "wof:placetype":"venue"
},
  "geometry": {"coordinates":[-0.540046,44.814339],"type":"Point"}
}