{
  "type": "Feature",
  "properties": {
    "addr:full":"Impasse Emile Combres 95560 Montsoult Ile de France 95560",
    "addr:postcode":"95560;ile;95560",
    "addr:street":"Impasse Emile Combres;France",
    "iso:country":"FR",
    "sg:address":"Impasse Emile Combres 95560 Montsoult",
    "sg:classifiers":[
        {
            "category":"Shopping",
            "type":"Retail Goods"
        }
    ],
    "sg:phone":"+33 1 34 69 94 81",
    "sg:postcode":"95560",
    "sg:province":"Ile de France",
    "sg:tags":[
        "metallurgy",
        "finished",
        "-",
        "metalworking",
        "metallic"
    ],
    "wof:name":"Tmpa",
    "wof:placetype":"venue"
},
  "geometry": {"coordinates":[2.328112,49.069481],"type":"Point"}
}