{
  "type": "Feature",
  "properties": {
    "iso:country":"FR",
    "sg:address":"80, Rue du Dessous des Berges, 75013 Paris",
    "sg:orig_category":"Unclassifiable Establishments",
    "sg:phone":"+33 1 45 86 10 11",
    "sg:province":"Ile de France",
    "wof:name":"Mouve A Tech S.a.r.l.",
    "wof:placetype":"venue"
},
  "geometry": {"coordinates":[2.372781,48.828857],"type":"Point"}
}