{
  "type": "Feature",
  "properties": {
    "addr:full":"83 rue St Michel 59122 Killem Nord Pas-de-Calais",
    "addr:housenumber":"83",
    "addr:postcode":"59122",
    "addr:street":"Rue St Michel",
    "iso:country":"FR",
    "sg:address":"83 rue St Michel 59122 Killem",
    "sg:orig_category":"Non-Classified Establishments",
    "sg:phone":"+33 3 28 68 30 88",
    "sg:province":"Nord Pas-de-Calais",
    "wof:name":"Van Robaeys Fr\u00e8res Sa",
    "wof:placetype":"venue"
},
  "geometry": {"coordinates":[2.566979,50.958374],"type":"Point"}
}