{
  "type": "Feature",
  "properties": {
    "iso:country":"FR",
    "sg:address":"Rte d'Ocquerre",
    "sg:city":"Lizy sur Ourcq",
    "sg:orig_category":"Unclassifiable Establishments",
    "sg:phone":"+33 1 60 01 70 08",
    "sg:postcode":"77440",
    "sg:province":"Ile de France",
    "wof:name":"Sprint M\u00e9tal S.a.",
    "wof:placetype":"venue"
},
  "geometry": {"coordinates":[3.05762,49.038029],"type":"Point"}
}