{
  "type": "Feature",
  "properties": {
    "iso:country":"FR",
    "sg:address":"4 avenue Razel 91400 Saclay",
    "sg:classifiers":[
        {
            "category":"Wholesale",
            "subcategory":"Medical Equipment & Supplies",
            "type":"Manufacturing & Wholesale Goods"
        }
    ],
    "sg:phone":"+33 1 69 41 10 00",
    "sg:postcode":"91400",
    "sg:province":"Ile de France",
    "wof:name":"Medi Test Sa",
    "wof:placetype":"venue"
},
  "geometry": {"coordinates":[2.187755,48.698891],"type":"Point"}
}