{
  "type": "Feature",
  "properties": {
    "iso:country":"FR",
    "sg:address":"B.P. 69, 78960 Voisins le Bretonneux^^25/27, Rue des Tilleuls - Espace des Vergers, 78960 Voisins le",
    "sg:orig_category":"Non-Classified Establishments",
    "sg:phone":"+33 1 39 30 46 40",
    "sg:province":"Ile de France",
    "wof:name":"S.e.e.m. S.a.r.l. - Soci\u00e9t\u00e9 D'etudes Et D'exportations De Mat\u00e9riels",
    "wof:placetype":"venue"
},
  "geometry": {"coordinates":[2.04704,48.759998],"type":"Point"}
}