{
  "type": "Feature",
  "properties": {
    "iso:country":"FR",
    "sg:address":"Lieu Dit Creux De Boule 07700 St Just D Ardeche",
    "sg:classifiers":[
        {
            "category":"Wholesale",
            "subcategory":"Meat",
            "type":"Manufacturing & Wholesale Goods"
        }
    ],
    "sg:phone":"+33 4 75 97 26 00",
    "sg:postcode":"07700",
    "sg:province":"Rhone-Alpes",
    "sg:tags":[
        "food",
        "cooked",
        "product",
        "related"
    ],
    "wof:name":"Chazel",
    "wof:placetype":"venue"
},
  "geometry": {"coordinates":[4.602432,44.362293],"type":"Point"}
}