{
  "type": "Feature",
  "properties": {
    "addr:full":"6 Rte Boissy Le Girard 45480 Autruy Sur Juine Andonville Centre 45480",
    "addr:housenumber":"6",
    "addr:postcode":"45480;45480",
    "addr:street":"Rte Boissy Le Girard",
    "iso:country":"FR",
    "sg:address":"6 Rte Boissy Le Girard 45480 Autruy Sur Juine",
    "sg:city":"Andonville",
    "sg:classifiers":[
        {
            "category":"Professional",
            "subcategory":"Engineering",
            "type":"Services"
        }
    ],
    "sg:phone":"+33 2 38 32 50 00",
    "sg:postcode":"45480",
    "sg:province":"Centre",
    "sg:tags":[
        "machine",
        "-",
        "mechanical"
    ],
    "wof:name":"Gainair Sa",
    "wof:placetype":"venue"
},
  "geometry": {"coordinates":[2.14171,48.276096],"type":"Point"}
}