{
  "type": "Feature",
  "properties": {
    "iso:country":"FR",
    "sg:address":"8 Rue Roger Salengro Za De St Ouen 41100 Vend\u00f4me",
    "sg:city":"Vend\u00f4me",
    "sg:classifiers":[
        {
            "category":"Shopping",
            "subcategory":"Computers & Home Electronics",
            "type":"Retail Goods"
        }
    ],
    "sg:phone":"+33 2 54 67 50 50",
    "sg:postcode":"41100",
    "sg:province":"Centre",
    "sg:tags":[
        "equipment",
        "electrical",
        "component",
        "electric",
        "electronic"
    ],
    "wof:name":"Srt Microceramique Sarl",
    "wof:placetype":"venue"
},
  "geometry": {"coordinates":[1.17829,47.712414],"type":"Point"}
}