{
  "type": "Feature",
  "properties": {
    "addr:full":"146, Rue Paradis - Le Noilly Paradis, 13006 Marseille Provence-Alpes-C\u00f4te d'Azur",
    "addr:housenumber":"146",
    "addr:postcode":"13006",
    "addr:street":"Rue Paradis Le Noilly Paradis",
    "iso:country":"FR",
    "sg:address":"146, Rue Paradis - Le Noilly Paradis, 13006 Marseille",
    "sg:orig_category":"Unclassifiable Establishments",
    "sg:phone":"+33 4 91 37 19 05",
    "sg:province":"Provence-Alpes-C\u00f4te d'Azur",
    "wof:name":"Conti Service S.a.r.l.",
    "wof:placetype":"venue"
},
  "geometry": {"coordinates":[5.38324,43.290806],"type":"Point"}
}