{
  "type": "Feature",
  "properties": {
    "addr:full":"40, Rue des Mathurins, 75008 Paris Ile de France",
    "addr:housenumber":"40",
    "addr:postcode":"75008",
    "addr:street":"Rue Des Mathurins",
    "iso:country":"FR",
    "sg:address":"40, Rue des Mathurins, 75008 Paris",
    "sg:orig_category":"Non-Classified Establishments",
    "sg:phone":"+33 1 47 42 92 02",
    "sg:province":"Ile de France",
    "wof:name":"Sanger Paris S.a.",
    "wof:placetype":"venue"
},
  "geometry": {"coordinates":[2.325063,48.873379],"type":"Point"}
}