{
  "type": "Feature",
  "properties": {
    "addr:full":"60 Rue Des Fr\u00e8res Flavien 75020 Paris Ile de France 75020",
    "addr:housenumber":"60",
    "addr:postcode":"75020;75020",
    "addr:street":"Rue Des Fre\u0300Res Flavien",
    "iso:country":"FR",
    "sg:address":"60 Rue Des Fr\u00e8res Flavien 75020 Paris",
    "sg:orig_category":"Miscellaneous Products",
    "sg:phone":"+33 1 43 62 25 00",
    "sg:postcode":"75020",
    "sg:province":"Ile de France",
    "wof:name":"Fondation De L'arm\u00c9e Du Salut",
    "wof:placetype":"venue"
},
  "geometry": {"coordinates":[2.399365,48.864849],"type":"Point"}
}