{
  "type": "Feature",
  "properties": {
    "addr:full":"60, Av. Jean Jaur\u00e8s, 94200 Ivry sur Seine Ile de France 94200",
    "addr:postcode":"94200;94200",
    "addr:street":"60 Av. Jean Jaure\u0300S;France",
    "iso:country":"FR",
    "sg:address":"60, Av. Jean Jaur\u00e8s, 94200 Ivry sur Seine",
    "sg:orig_category":"Non-Classified Establishments",
    "sg:phone":"+33 1 49 60 02 02",
    "sg:postcode":"94200",
    "sg:province":"Ile de France",
    "wof:name":"C\u00e9dap S.a.",
    "wof:placetype":"venue"
},
  "geometry": {"coordinates":[2.403424,48.810215],"type":"Point"}
}