{
  "type": "Feature",
  "properties": {
    "addr:full":"B.P. 30611, 57010 Metz C\u00e9dex 01^^6, Place du Roi George, 57000 Metz Lorraine 57000",
    "addr:housenumber":"01 ^ ^ 6",
    "addr:postcode":"57010;57000;57000",
    "addr:street":"Ce\u0301Dex;Place Du Roi George",
    "iso:country":"FR",
    "sg:address":"B.P. 30611, 57010 Metz C\u00e9dex 01^^6, Place du Roi George, 57000 Metz",
    "sg:orig_category":"Non-Classified Establishments",
    "sg:phone":"+33 3 87 56 01 01",
    "sg:postcode":"57000",
    "sg:province":"Lorraine",
    "wof:name":"A.p.e.c.",
    "wof:placetype":"venue"
},
  "geometry": {"coordinates":[6.183995,49.07645],"type":"Point"}
}