{
  "type": "Feature",
  "properties": {
    "addr:full":"La M\u00e9rini\u00e8re 85340 Olonne Sur Mer Pays de Loire 85340",
    "addr:postcode":"85340;85340",
    "iso:country":"FR",
    "sg:address":"La M\u00e9rini\u00e8re 85340 Olonne Sur Mer",
    "sg:classifiers":[
        {
            "category":"Professional",
            "subcategory":"Business Services",
            "type":"Services"
        }
    ],
    "sg:phone":"+33 2 51 95 12 40",
    "sg:postcode":"85340",
    "sg:province":"Pays de Loire",
    "sg:tags":[
        "training",
        "advice"
    ],
    "wof:name":"I S E C",
    "wof:placetype":"venue"
},
  "geometry": {"coordinates":[-1.765599,46.510277],"type":"Point"}
}