{
  "type": "Feature",
  "properties": {
    "addr:full":"Pr\u00e9 De La Grange 07570 D\u00e9saignes Rhone-Alpes 07570",
    "addr:postcode":"07570;07570",
    "addr:street":"Pre\u0301 De La Grange;Rhone-Alpes",
    "iso:country":"FR",
    "sg:address":"Pr\u00e9 De La Grange 07570 D\u00e9saignes",
    "sg:classifiers":[
        {
            "category":"Wholesale",
            "subcategory":"Machinery & Supplies",
            "type":"Manufacturing & Wholesale Goods"
        }
    ],
    "sg:phone":"+33 4 75 06 61 43",
    "sg:postcode":"07570",
    "sg:province":"Rhone-Alpes",
    "sg:tags":[
        "handling",
        "material",
        "-",
        "machine",
        "equipment",
        "engineering",
        "mechanical"
    ],
    "wof:name":"Cros Pere Et Fils Sarl",
    "wof:placetype":"venue"
},
  "geometry": {"coordinates":[4.507347,44.99995],"type":"Point"}
}