{
  "type": "Feature",
  "properties": {
    "addr:full":"20 Rue Du Petit Chantilly 60510 Bresles Picardie 60510",
    "addr:housenumber":"20",
    "addr:postcode":"60510;60510",
    "addr:street":"Rue Du Petit Chantilly",
    "iso:country":"FR",
    "sg:address":"20 Rue Du Petit Chantilly 60510 Bresles",
    "sg:classifiers":[
        {
            "category":"Shopping",
            "subcategory":"Computers & Home Electronics",
            "type":"Retail Goods"
        }
    ],
    "sg:phone":"+33 3 44 07 90 89",
    "sg:postcode":"60510",
    "sg:province":"Picardie",
    "sg:tags":[
        "electric",
        "appliance",
        "household",
        "component",
        "equipment",
        "electrical",
        "electronic"
    ],
    "wof:name":"Societe De Techniques Electriques Electromecas Et Elec Sotelic",
    "wof:placetype":"venue"
},
  "geometry": {"coordinates":[2.23957,49.411163],"type":"Point"}
}