{
  "type": "Feature",
  "properties": {
    "addr:full":"Rue des Faines - Zone Industrielle Noidans Vesoul Franche Comt\u00e9 70000",
    "addr:postcode":"70000",
    "addr:street":"Rue Des Faines Zone Industrielle Noidans;Franche Comte\u0301",
    "iso:country":"FR",
    "sg:address":"Rue des Faines - Zone Industrielle Noidans",
    "sg:city":"Vesoul",
    "sg:orig_category":"Unclassifiable Establishments",
    "sg:phone":"+33 3 84 76 59 80",
    "sg:postcode":"70000",
    "sg:province":"Franche Comt\u00e9",
    "wof:name":"Jardival S.a.r.l.",
    "wof:placetype":"venue"
},
  "geometry": {"coordinates":[6.034054,47.524078],"type":"Point"}
}