{
  "type": "Feature",
  "properties": {
    "addr:full":"route de Mamers 72400 La Ferte Bernard Pays de Loire 72400",
    "addr:postcode":"72400;72400",
    "addr:street":"Route De Mamers;Bernard",
    "iso:country":"FR",
    "sg:address":"route de Mamers 72400 La Ferte Bernard",
    "sg:classifiers":[
        {
            "category":"Building & Trades",
            "subcategory":"Pest Control",
            "type":"Services"
        }
    ],
    "sg:phone":"+33 2 43 60 12 30",
    "sg:postcode":"72400",
    "sg:province":"Pays de Loire",
    "sg:tags":[
        "development",
        "automobile",
        "construction"
    ],
    "wof:name":"Protoline S.a.",
    "wof:placetype":"venue"
},
  "geometry": {"coordinates":[0.637544,48.193333],"type":"Point"}
}