{
  "type": "Feature",
  "properties": {
    "iso:country":"FR",
    "sg:address":"5, Rue Saarinen, 94150 Rungis",
    "sg:orig_category":"Unclassifiable Establishments",
    "sg:phone":"+33 1 45 60 36 50",
    "sg:province":"Ile de France",
    "wof:name":"Elyo Ile De France S.a.",
    "wof:placetype":"venue"
},
  "geometry": {"coordinates":[2.353318,48.747585],"type":"Point"}
}