{
  "type": "Feature",
  "properties": {
    "addr:full":"11, Rue Mar\u00e9chal Foch, 57700 Hayange Lorraine",
    "addr:housenumber":"11",
    "addr:postcode":"57700",
    "addr:street":"Rue Mare\u0301Chal Foch",
    "iso:country":"FR",
    "sg:address":"11, Rue Mar\u00e9chal Foch, 57700 Hayange",
    "sg:orig_category":"Non-Classified Establishments",
    "sg:phone":"+33 3 82 84 34 14",
    "sg:province":"Lorraine",
    "wof:name":"Rehabeco",
    "wof:placetype":"venue"
},
  "geometry": {"coordinates":[6.064768,49.329334],"type":"Point"}
}