{
  "type": "Feature",
  "properties": {
    "iso:country":"FR",
    "sg:address":"6, Rue des Mineurs - L'Orme Saint Pantal\u00e9on , 71400 Autun",
    "sg:city":"Autun",
    "sg:orig_category":"Unclassifiable Establishments",
    "sg:phone":"+33 3 85 86 20 02",
    "sg:postcode":"71400",
    "sg:province":"Bourgogne",
    "wof:name":"G.t.l.b. S.a.r.l. - Georgelin Transports Logistique Bourgogne",
    "wof:placetype":"venue"
},
  "geometry": {"coordinates":[4.3102,46.985867],"type":"Point"}
}