{
  "type": "Feature",
  "properties": {
    "iso:country":"FR",
    "sg:address":"B.P. 1058, 76172 Rouen C\u00e9dex^^5, Quai de France, 76000 Rouen",
    "sg:orig_category":"Non-Classified Establishments",
    "sg:phone":"+33 2 35 63 55 55",
    "sg:province":"Haute Normandie",
    "wof:name":"S.n.m.i. S.a. - Soci\u00e9t\u00e9 Normande De Mat\u00e9riel Industriel",
    "wof:placetype":"venue"
},
  "geometry": {"coordinates":[1.08933,49.44038],"type":"Point"}
}