{
  "type": "Feature",
  "properties": {
    "addr:full":"101 bd du Dr Camille Gu\u00e9rin 02100 ST QUENTIN Picardie",
    "addr:housenumber":"101",
    "addr:postcode":"02100",
    "addr:street":"Bd Du Dr Camille Gue\u0301Rin",
    "iso:country":"FR",
    "sg:address":"101 bd du Dr Camille Gu\u00e9rin 02100 ST QUENTIN",
    "sg:orig_category":"Slaughter-Houses, Abattoirs",
    "sg:phone":"+33 3 23 65 66 20",
    "sg:province":"Picardie",
    "wof:name":"Ste Expl Abattoir St Quentin Sarl",
    "wof:placetype":"venue"
},
  "geometry": {"coordinates":[3.291399,49.850842],"type":"Point"}
}