{
  "type": "Feature",
  "properties": {
    "addr:full":"Rue Charles Marie Ravel 51520 St Martin Sur Le Pr\u00e9 Champagne",
    "addr:postcode":"51520",
    "addr:street":"Rue Charles Marie Ravel;Sur Le Pre\u0301 Champagne",
    "iso:country":"FR",
    "sg:address":"Rue Charles Marie Ravel 51520 St Martin Sur Le Pr\u00e9",
    "sg:classifiers":[
        {
            "category":"Manufacturing",
            "subcategory":"Printing",
            "type":"Manufacturing & Wholesale Goods"
        }
    ],
    "sg:phone":"+33 3 26 68 09 77",
    "sg:province":"Champagne",
    "sg:tags":[
        "publishing"
    ],
    "wof:name":"Groupe Des Imprimeries Champenoises Sa",
    "wof:placetype":"venue"
},
  "geometry": {"coordinates":[4.344173,48.984692],"type":"Point"}
}