{
  "type": "Feature",
  "properties": {
    "addr:full":"15, Rue Tr\u00e9bois, 92300 Levallois Perret Ile de France",
    "addr:housenumber":"15",
    "addr:postcode":"92300;ile",
    "addr:street":"Rue Tre\u0301Bois",
    "iso:country":"FR",
    "sg:address":"15, Rue Tr\u00e9bois, 92300 Levallois Perret",
    "sg:orig_category":"Unclassifiable Establishments",
    "sg:phone":"+33 1 41 05 05 05",
    "sg:province":"Ile de France",
    "wof:name":"Pivotal",
    "wof:placetype":"venue"
},
  "geometry": {"coordinates":[2.290237,48.890472],"type":"Point"}
}