{
  "type": "Feature",
  "properties": {
    "addr:full":"4b Imp De Commandant Marzac BP 420 Cazaux 33260 Cazaux Teste-de-Buch Aquitaine 33260",
    "addr:housenumber":"4b;420",
    "addr:postcode":"33260;33260",
    "addr:street":"Imp De Commandant Marzac Bp",
    "iso:country":"FR",
    "sg:address":"4b Imp De Commandant Marzac BP 420 Cazaux 33260 Cazaux",
    "sg:city":"Teste-de-Buch",
    "sg:orig_category":"Miscellaneous Products",
    "sg:phone":"+33 5 56 22 21 19",
    "sg:postcode":"33260",
    "sg:province":"Aquitaine",
    "wof:name":"Cryolight Techniques Modernes",
    "wof:placetype":"venue"
},
  "geometry": {"coordinates":[-1.145227,44.632915],"type":"Point"}
}