{
  "type": "Feature",
  "properties": {
    "addr:full":"24, Rue Notre Dame, 69006 Lyon Rhone-Alpes 69006",
    "addr:housenumber":"24",
    "addr:postcode":"69006;69006",
    "addr:street":"Rue Notre Dame",
    "iso:country":"FR",
    "sg:address":"24, Rue Notre Dame, 69006 Lyon",
    "sg:orig_category":"Unclassifiable Establishments",
    "sg:phone":"+33 4 78 52 07 39",
    "sg:postcode":"69006",
    "sg:province":"Rhone-Alpes",
    "wof:name":"Etablissements Lebayle S.a.r.l.",
    "wof:placetype":"venue"
},
  "geometry": {"coordinates":[4.867659,45.764759],"type":"Point"}
}