{
  "type": "Feature",
  "properties": {
    "iso:country":"FR",
    "sg:address":"10, Rue des R\u00e9sistants, 65300 Lannemezan",
    "sg:orig_category":"Non-Classified Establishments",
    "sg:phone":"+33 5 62 98 00 46",
    "sg:province":"Midi Pyr\u00e9n\u00e9es",
    "wof:name":"Point P La M\u00e9ridionale S.a.",
    "wof:placetype":"venue"
},
  "geometry": {"coordinates":[0.384745,43.112911],"type":"Point"}
}