{
  "type": "Feature",
  "properties": {
    "iso:country":"FR",
    "sg:address":"401 avenue de la Fleuride 13400 Aubagne",
    "sg:classifiers":[
        {
            "category":"Train Station",
            "subcategory":"Light Rail",
            "type":"Transportation"
        }
    ],
    "sg:phone":"+33 4 42 84 68 00",
    "sg:province":"Provence-Alpes-C\u00f4te d'Azur",
    "sg:tags":[
        "sensor"
    ],
    "wof:name":"Scm Pons S.a.",
    "wof:placetype":"venue"
},
  "geometry": {"coordinates":[5.599459,43.28447],"type":"Point"}
}