{
  "type": "Feature",
  "properties": {
    "addr:full":"40 R De Bourgogne 69800 St Priest Rhone-Alpes 69800",
    "addr:housenumber":"40",
    "addr:postcode":"69800;69800",
    "addr:street":"R De Bourgogne",
    "iso:country":"FR",
    "sg:address":"40 R De Bourgogne 69800 St Priest",
    "sg:classifiers":[
        {
            "category":"Professional",
            "subcategory":"Engineering",
            "type":"Services"
        }
    ],
    "sg:phone":"+33 4 78 21 25 21",
    "sg:postcode":"69800",
    "sg:province":"Rhone-Alpes",
    "sg:tags":[
        "machine",
        "-",
        "mechanical"
    ],
    "wof:name":"Aeraulique Thermique Hydraulique (ath) Sas",
    "wof:placetype":"venue"
},
  "geometry": {"coordinates":[4.913041,45.695415],"type":"Point"}
}