{
  "type": "Feature",
  "properties": {
    "iso:country":"FR",
    "sg:address":"La Gravi\u00e8re 01480 Fareins",
    "sg:orig_category":"Unclassifiable Establishments",
    "sg:phone":"+33 4 74 60 99 83",
    "sg:postcode":"01480",
    "sg:province":"Rhone-Alpes",
    "wof:name":"Bresson Montage Couverture Barbage Isolation S.a.r.l.",
    "wof:placetype":"venue"
},
  "geometry": {"coordinates":[4.75974,46.005814],"type":"Point"}
}