{
  "type": "Feature",
  "properties": {
    "addr:full":"B.P. 1, 60870 Rieux^^Quai de l'Oise, 60870 Rieux Picardie",
    "addr:housenumber":"1",
    "addr:postcode":"60870;60870",
    "addr:street":"B.P.;L'Oise",
    "iso:country":"FR",
    "sg:address":"B.P. 1, 60870 Rieux^^Quai de l'Oise, 60870 Rieux",
    "sg:orig_category":"Non-Classified Establishments",
    "sg:phone":"+33 3 44 72 90 00",
    "sg:province":"Picardie",
    "wof:name":"Penarroya Oxide S.a.",
    "wof:placetype":"venue"
},
  "geometry": {"coordinates":[2.51787,49.29895],"type":"Point"}
}