{
  "type": "Feature",
  "properties": {
    "iso:country":"FR",
    "sg:address":"B.P. 90, 63240 Le Mont Dor\u00e9 C\u00e9dex^^33, Av. des Belges, 63240 Le Mont Dor\u00e9",
    "sg:city":"Mont-Dore",
    "sg:orig_category":"Non-Classified Establishments",
    "sg:phone":"+33 4 73 65 20 22",
    "sg:postcode":"63240",
    "sg:province":"Auvergne",
    "wof:name":"Taillandier",
    "wof:placetype":"venue"
},
  "geometry": {"coordinates":[-87.089005,33.730293],"type":"Point"}
}