{
  "type": "Feature",
  "properties": {
    "addr:full":"2, Rue de l'Aigue, 69780 Saint Pierre de Chandieu Rhone-Alpes",
    "addr:housenumber":"2",
    "addr:postcode":"69780",
    "addr:street":"Rue De L'Aigue",
    "iso:country":"FR",
    "sg:address":"2, Rue de l'Aigue, 69780 Saint Pierre de Chandieu",
    "sg:orig_category":"Unclassifiable Establishments",
    "sg:phone":"+33 4 72 48 29 67",
    "sg:province":"Rhone-Alpes",
    "wof:name":"Soci\u00e9t\u00e9 Adeska S.a.r.l.",
    "wof:placetype":"venue"
},
  "geometry": {"coordinates":[5.0234,45.646759],"type":"Point"}
}