{
  "type": "Feature",
  "properties": {
    "iso:country":"FR",
    "sg:address":"35 rue Louveau 92320 Chatillon",
    "sg:classifiers":[
        {
            "category":"Government",
            "subcategory":"Fire Station",
            "type":"Public Place"
        }
    ],
    "sg:phone":"+33 1 49 65 62 62",
    "sg:postcode":"92320",
    "sg:province":"Ile de France",
    "sg:tags":[
        "medium",
        "blast"
    ],
    "wof:name":"Sercap S.a.",
    "wof:placetype":"venue"
},
  "geometry": {"coordinates":[2.29465,48.802879],"type":"Point"}
}