{
  "type": "Feature",
  "properties": {
    "addr:full":"11, Av. Compagnonnage - ZI Fontcouverte, 84000 Avignon Provence-Alpes-C\u00f4te d'Azur",
    "addr:postcode":"84000",
    "addr:street":"11 Av. Compagnonnage Zi",
    "iso:country":"FR",
    "sg:address":"11, Av. Compagnonnage - ZI Fontcouverte, 84000 Avignon",
    "sg:orig_category":"Unclassifiable Establishments",
    "sg:phone":"+33 4 90 87 06 48",
    "sg:province":"Provence-Alpes-C\u00f4te d'Azur",
    "wof:name":"Appro 5 Sud",
    "wof:placetype":"venue"
},
  "geometry": {"coordinates":[4.806015,43.948753],"type":"Point"}
}