{
  "type": "Feature",
  "properties": {
    "iso:country":"FR",
    "sg:address":"Z.I. De la craye 25110 AUTECHAUX",
    "sg:classifiers":[
        {
            "category":"Manufacturing",
            "subcategory":"Motor Vehicles & Parts",
            "type":"Manufacturing & Wholesale Goods"
        }
    ],
    "sg:phone":"+33 3 81 84 39 20",
    "sg:province":"Franche Comt\u00e9",
    "sg:tags":[
        "precision",
        "mechanic"
    ],
    "wof:name":"M.b.p. S.a.",
    "wof:placetype":"venue"
},
  "geometry": {"coordinates":[6.35857,47.35133],"type":"Point"}
}