{
  "type": "Feature",
  "properties": {
    "iso:country":"FR",
    "sg:address":"B.P. 30, 30311 Al\u00e8s C\u00e9dex^^Rue Pressence, 30100 Al\u00e8s",
    "sg:orig_category":"Non-Classified Establishments",
    "sg:phone":"+33 4 66 78 96 58",
    "sg:postcode":"30100",
    "sg:province":"Languedoc-Roussillon",
    "wof:name":"E.g.t.s. S.a.r.l. - Entreprise G\u00e9n\u00e9rale Traitement Des Surfaces",
    "wof:placetype":"venue"
},
  "geometry": {"coordinates":[4.082515,44.121254],"type":"Point"}
}