{
  "type": "Feature",
  "properties": {
    "iso:country":"FR",
    "sg:address":"Rue De Kerdisson Upc Pontivy Le Tallen 56300 Pontivy",
    "sg:city":"Pontivy",
    "sg:classifiers":[
        {
            "category":"Travel",
            "subcategory":"Hotels & Motels",
            "type":"Entertainment"
        }
    ],
    "sg:phone":"+33 2 97 25 28 88",
    "sg:postcode":"56300",
    "sg:province":"Bretagne",
    "sg:tags":[
        "hotels",
        "business",
        "restaurant"
    ],
    "wof:name":"Etablissements Bontemps",
    "wof:placetype":"venue"
},
  "geometry": {"coordinates":[-2.951319,48.018394],"type":"Point"}
}