{
  "type": "Feature",
  "properties": {
    "iso:country":"FR",
    "sg:address":"Parc d'Activit\u00e9 Bois de Tellay",
    "sg:city":"Brie",
    "sg:orig_category":"Non-Classified Establishments",
    "sg:phone":"+33 2 99 47 21 21",
    "sg:postcode":"35150",
    "sg:province":"Bretagne",
    "wof:name":"Sor\u00e9al S.a.",
    "wof:placetype":"venue"
},
  "geometry": {"coordinates":[-1.53793,47.951012],"type":"Point"}
}