{
  "type": "Feature",
  "properties": {
    "iso:country":"FR",
    "sg:address":"Rue De Praley 70000 Vesoul",
    "sg:classifiers":[
        {
            "category":"Professional",
            "subcategory":"Advertising",
            "type":"Services"
        }
    ],
    "sg:phone":"+33 3 84 75 73 24",
    "sg:postcode":"70000",
    "sg:province":"Franche Comt\u00e9",
    "sg:tags":[
        "information",
        "medium",
        "communication"
    ],
    "wof:name":"Delta Diffusion Sa",
    "wof:placetype":"venue"
},
  "geometry": {"coordinates":[6.15497,47.63549],"type":"Point"}
}