{
  "type": "Feature",
  "properties": {
    "iso:country":"FR",
    "sg:address":"254, Rue Francis de Pr\u00e9ssens\u00e9, 69100 Villeurbanne",
    "sg:orig_category":"Unclassifiable Establishments",
    "sg:phone":"+33 4 72 65 31 00",
    "sg:province":"Rhone-Alpes",
    "wof:name":"S.e.c.r. S.a. - Soci\u00e9t\u00e9 Eaux Du Centre Et Du Bassin Du Rh\u00f4ne",
    "wof:placetype":"venue"
},
  "geometry": {"coordinates":[4.892495,45.76981],"type":"Point"}
}