{
  "type": "Feature",
  "properties": {
    "addr:full":"100, Rue Claude Bernard, 59200 Tourcoing Nord Pas-de-Calais 59200",
    "addr:housenumber":"100",
    "addr:postcode":"59200;59200",
    "addr:street":"Rue Claude Bernard",
    "iso:country":"FR",
    "sg:address":"100, Rue Claude Bernard, 59200 Tourcoing",
    "sg:orig_category":"Non-Classified Establishments",
    "sg:phone":"+33 3 20 26 97 37",
    "sg:postcode":"59200",
    "sg:province":"Nord Pas-de-Calais",
    "wof:name":"Delcour Paul S.a.",
    "wof:placetype":"venue"
},
  "geometry": {"coordinates":[3.15022,50.695194],"type":"Point"}
}