{
  "type": "Feature",
  "properties": {
    "addr:full":"310 Chem De L' Arm\u00e9e D'Afrique 13010 Marseille Poitou-Charentes",
    "addr:housenumber":"310",
    "addr:postcode":"13010",
    "addr:street":"Chem De L ' Arme\u0301E D'Afrique",
    "iso:country":"FR",
    "sg:address":"310 Chem De L' Arm\u00e9e D'Afrique 13010 Marseille",
    "sg:classifiers":[
        {
            "category":"Utilities",
            "subcategory":"Electric",
            "type":"Services"
        }
    ],
    "sg:phone":"+33 4 91 43 42 40",
    "sg:province":"Poitou-Charentes",
    "sg:tags":[
        "electricity",
        "electronic",
        "electrical",
        "equipment"
    ],
    "wof:name":"Ets Cabus Et Raulot",
    "wof:placetype":"venue"
},
  "geometry": {"coordinates":[5.42479,43.274269],"type":"Point"}
}