{
  "type": "Feature",
  "properties": {
    "addr:full":"33, Av. du Docteur G\u00e9rard L\u00e9vy - Parc Club du Moulin \u00e0 Vent, 69693 V\u00e9nissieux C\u00e9dex Rhone-Alpes",
    "addr:postcode":"69693",
    "addr:street":"33 Av. Du Docteur Ge\u0301Rard Le\u0301Vy Parc Club Du Moulin A\u0300 Vent",
    "iso:country":"FR",
    "sg:address":"33, Av. du Docteur G\u00e9rard L\u00e9vy - Parc Club du Moulin \u00e0 Vent, 69693 V\u00e9nissieux C\u00e9dex",
    "sg:orig_category":"Non-Classified Establishments",
    "sg:phone":"+33 4 72 78 34 56",
    "sg:province":"Rhone-Alpes",
    "wof:name":"I.n.h.n.i. - C.f.a. De La Propret\u00e9 Rh\u00f4ne Alpes",
    "wof:placetype":"venue"
},
  "geometry": {"coordinates":[4.860519,45.719555],"type":"Point"}
}