{
  "type": "Feature",
  "properties": {
    "addr:full":"B.P. 10, 28500 Cherisy^^14, Rue de Paris, 28500 Cherisy Cherisy Centre 28500",
    "addr:housenumber":"cherisy",
    "addr:postcode":"28500;28500;28500",
    "addr:street":"B.P. 10;Rue De Paris",
    "iso:country":"FR",
    "sg:address":"B.P. 10, 28500 Cherisy^^14, Rue de Paris, 28500 Cherisy",
    "sg:city":"Cherisy",
    "sg:orig_category":"Non-Classified Establishments",
    "sg:phone":"+33 2 37 62 77 77",
    "sg:postcode":"28500",
    "sg:province":"Centre",
    "wof:name":"Moulin De Cherisy - Lethuillier S.a.",
    "wof:placetype":"venue"
},
  "geometry": {"coordinates":[1.369635,48.652908],"type":"Point"}
}