{
  "type": "Feature",
  "properties": {
    "addr:full":"86 Imp Du Forestier 33127 St Jean D'Illac Martignas-sur-Jalle Aquitaine 33127",
    "addr:housenumber":"86;martignas-sur-jalle",
    "addr:postcode":"33127;33127",
    "addr:street":"Imp Du Forestier",
    "iso:country":"FR",
    "sg:address":"86 Imp Du Forestier 33127 St Jean D'Illac",
    "sg:city":"Martignas-sur-Jalle",
    "sg:classifiers":[
        {
            "category":"Autos & Motor Vehicles",
            "subcategory":"Boat Sales",
            "type":"Retail Goods"
        }
    ],
    "sg:phone":"+33 5 56 21 88 08",
    "sg:postcode":"33127",
    "sg:province":"Aquitaine",
    "sg:tags":[
        "equipment",
        "transport"
    ],
    "wof:name":"Zodiac International Sa",
    "wof:placetype":"venue"
},
  "geometry": {"coordinates":[-0.727869,44.814362],"type":"Point"}
}