{
  "type": "Feature",
  "properties": {
    "addr:full":"246 Rue Du Fbg St Martin 75010 Paris Ile de France 75010",
    "addr:housenumber":"246",
    "addr:postcode":"75010;75010",
    "addr:street":"Rue Du Fbg St Martin",
    "iso:country":"FR",
    "sg:address":"246 Rue Du Fbg St Martin 75010 Paris",
    "sg:classifiers":[
        {
            "category":"Shopping",
            "subcategory":"Clothing, Apparel, & Fashions",
            "type":"Retail Goods"
        }
    ],
    "sg:phone":"+33 1 46 07 04 93",
    "sg:postcode":"75010",
    "sg:province":"Ile de France",
    "sg:tags":[
        "textile",
        "clothing",
        "clothes"
    ],
    "wof:name":"Garpel",
    "wof:placetype":"venue"
},
  "geometry": {"coordinates":[2.365951,48.881622],"type":"Point"}
}