{
  "type": "Feature",
  "properties": {
    "iso:country":"FR",
    "sg:address":"B.P. 183, 07204 Aubenas C\u00e9dex^^Quartier Saint Pierre, 07200 Aubenas",
    "sg:orig_category":"Non-Classified Establishments",
    "sg:phone":"+33 4 75 93 55 33",
    "sg:postcode":"07200",
    "sg:province":"Rhone-Alpes",
    "wof:name":"A.c.i. S.a. - Atelier De Constructions Et D'innovations",
    "wof:placetype":"venue"
},
  "geometry": {"coordinates":[4.39417,44.613239],"type":"Point"}
}