{
  "type": "Feature",
  "properties": {
    "addr:full":"738 Route De Carpentras 84210 Pernes Les Fontaines Basse Normandie",
    "addr:housenumber":"738",
    "addr:postcode":"84210",
    "addr:street":"Route De Carpentras",
    "iso:country":"FR",
    "sg:address":"738 Route De Carpentras 84210 Pernes Les Fontaines",
    "sg:classifiers":[
        {
            "category":"Home & Garden",
            "subcategory":"Furniture",
            "type":"Retail Goods"
        }
    ],
    "sg:phone":"+33 4 90 61 42 00",
    "sg:province":"Basse Normandie",
    "sg:tags":[
        "household",
        "wood"
    ],
    "wof:name":"Ateliers D'encadrement Et Decoration (aed)",
    "wof:placetype":"venue"
},
  "geometry": {"coordinates":[5.055157,44.01078],"type":"Point"}
}