{
  "type": "Feature",
  "properties": {
    "iso:country":"FR",
    "sg:address":"5, Rue du Casino, 03200 Vichy",
    "sg:city":"Vichy",
    "sg:orig_category":"Unclassifiable Establishments",
    "sg:phone":"+33 4 70 30 50 50",
    "sg:postcode":"03200",
    "sg:province":"Auvergne",
    "wof:name":"Palais Des Congr\u00e8s Op\u00e9ra Vichy",
    "wof:placetype":"venue"
},
  "geometry": {"coordinates":[3.420669,46.123177],"type":"Point"}
}