{
  "type": "Feature",
  "properties": {
    "iso:country":"FR",
    "sg:address":"166 Rue Docteur Vanheeckoet 62480 Le Portel",
    "sg:classifiers":[
        {
            "category":"Farming",
            "subcategory":"Livestock Farm",
            "type":"Manufacturing & Wholesale Goods"
        }
    ],
    "sg:phone":"+33 3 21 10 05 10",
    "sg:postcode":"62480",
    "sg:province":"Nord Pas-de-Calais",
    "sg:tags":[
        "breeding",
        "agriculture",
        "animal"
    ],
    "wof:name":"Fournier Varlet Guillaume Sa",
    "wof:placetype":"venue"
},
  "geometry": {"coordinates":[1.574208,50.706753],"type":"Point"}
}