{
  "type": "Feature",
  "properties": {
    "iso:country":"FR",
    "sg:address":"8 Esplanade Du Champ De Mars 76000 Rouen",
    "sg:classifiers":[
        {
            "category":"Shopping",
            "subcategory":"Computers & Home Electronics",
            "type":"Retail Goods"
        }
    ],
    "sg:phone":"+33 2 35 88 25 10",
    "sg:postcode":"76000",
    "sg:province":"Haute Normandie",
    "sg:tags":[
        "information",
        "peripheral",
        "-",
        "technology"
    ],
    "wof:name":"Compagnie Ibm France",
    "wof:placetype":"venue"
},
  "geometry": {"coordinates":[1.104816,49.436203],"type":"Point"}
}