{
  "type": "Feature",
  "properties": {
    "iso:country":"FR",
    "sg:address":"15, Rue Vauban - Zone Industrielle, 67450 Mundolsheim",
    "sg:city":"Mundolsheim",
    "sg:orig_category":"Unclassifiable Establishments",
    "sg:phone":"+33 3 88 20 26 16",
    "sg:postcode":"67450",
    "sg:province":"Alsace",
    "wof:name":"Protibat S.a.",
    "wof:placetype":"venue"
},
  "geometry": {"coordinates":[7.715445,48.641788],"type":"Point"}
}