{
  "type": "Feature",
  "properties": {
    "iso:country":"FR",
    "sg:address":"1 Bd Mal De Lattre De Tassig",
    "sg:city":"Evry",
    "sg:classifiers":[
        {
            "category":"Banks & Credit Unions",
            "subcategory":"Financial Services",
            "type":"Services"
        }
    ],
    "sg:phone":"+33 1 60 87 26 50",
    "sg:postcode":"91000",
    "sg:province":"Ile de France",
    "sg:tags":[
        "banking",
        "finance",
        "insurance"
    ],
    "wof:name":"Caisse D'epargne Et De Prevoyance Ile De France Paris",
    "wof:placetype":"venue"
},
  "geometry": {"coordinates":[2.44915,48.626526],"type":"Point"}
}