{
  "type": "Feature",
  "properties": {
    "iso:country":"FR",
    "sg:address":"B.P. 1307, 44082 Nantes C\u00e9dex 03^^11, Rue de Bruxelles, 44000 Nantes",
    "sg:orig_category":"Non-Classified Establishments",
    "sg:phone":"+33 2 40 50 23 63",
    "sg:province":"Pays de Loire",
    "wof:name":"Systal",
    "wof:placetype":"venue"
},
  "geometry": {"coordinates":[-1.553059,47.218117],"type":"Point"}
}