{
  "type": "Feature",
  "properties": {
    "addr:full":"29, Av Charles Voisin - ZAC de Migalon, 42160 Andr\u00e9zieux Bouth\u00e9on Rhone-Alpes",
    "addr:postcode":"42160",
    "addr:street":"29 Av Charles Voisin Zac De Migalon",
    "iso:country":"FR",
    "sg:address":"29, Av Charles Voisin - ZAC de Migalon, 42160 Andr\u00e9zieux Bouth\u00e9on",
    "sg:orig_category":"Unclassifiable Establishments",
    "sg:phone":"+33 4 77 55 27 71",
    "sg:province":"Rhone-Alpes",
    "wof:name":"Aprolis",
    "wof:placetype":"venue"
},
  "geometry": {"coordinates":[4.25674,45.52943],"type":"Point"}
}