{
  "type": "Feature",
  "properties": {
    "addr:full":"B.P. 8, 08110 Carignan C\u00e9dex^^Rte d'Osne, 08110 Carignan Champagne",
    "addr:housenumber":"8",
    "addr:postcode":"08110;08110",
    "addr:street":"B.P.;Ce\u0301Dex^^Rte D'Osne",
    "iso:country":"FR",
    "sg:address":"B.P. 8, 08110 Carignan C\u00e9dex^^Rte d'Osne, 08110 Carignan",
    "sg:orig_category":"Non-Classified Establishments",
    "sg:phone":"+33 3 24 27 74 74",
    "sg:province":"Champagne",
    "wof:name":"Syval Ventes S.a.r.l.",
    "wof:placetype":"venue"
},
  "geometry": {"coordinates":[5.16856,49.63179],"type":"Point"}
}