{
  "type": "Feature",
  "properties": {
    "addr:full":"Chemin de Messines Saint Andr\u00e9 lez Lille Nord Pas-de-Calais 59350",
    "addr:postcode":"59350",
    "addr:street":"Chemin De Messines Saint;Pas-De-Calais",
    "iso:country":"FR",
    "sg:address":"Chemin de Messines",
    "sg:city":"Saint Andr\u00e9 lez Lille",
    "sg:orig_category":"Non-Classified Establishments",
    "sg:phone":"+33 3 28 04 06 10",
    "sg:postcode":"59350",
    "sg:province":"Nord Pas-de-Calais",
    "wof:name":"Abaco S.a.r.l.",
    "wof:placetype":"venue"
},
  "geometry": {"coordinates":[3.050507,50.661091],"type":"Point"}
}