{
  "type": "Feature",
  "properties": {
    "iso:country":"FR",
    "sg:address":"05500 St Laurent Du Cros",
    "sg:classifiers":[
        {
            "category":"Wholesale",
            "subcategory":"Meat",
            "type":"Manufacturing & Wholesale Goods"
        }
    ],
    "sg:phone":"+33 4 92 50 48 92",
    "sg:province":"Champagne",
    "sg:tags":[
        "food",
        "cooked",
        "product",
        "related"
    ],
    "wof:name":"Sarl Salaisons Du Champ Faur",
    "wof:placetype":"venue"
},
  "geometry": {"coordinates":[6.111215,44.642967],"type":"Point"}
}