{
  "type": "Feature",
  "properties": {
    "addr:full":"5 Rue Charles Edouard Jeanneret Poissy Cedex Poitou-Charentes 78306",
    "addr:housenumber":"5",
    "addr:postcode":"cedex;78306",
    "addr:street":"Rue Charles Edouard Jeanneret",
    "iso:country":"FR",
    "sg:address":"5 Rue Charles Edouard Jeanneret",
    "sg:city":"Poissy Cedex",
    "sg:classifiers":[
        {
            "category":"Banks & Credit Unions",
            "subcategory":"Financial Services",
            "type":"Services"
        }
    ],
    "sg:phone":"+33 1 39 11 76 00",
    "sg:postcode":"78306",
    "sg:province":"Poitou-Charentes",
    "sg:tags":[
        "banking",
        "finance",
        "insurance"
    ],
    "wof:name":"Ecrin Sa",
    "wof:placetype":"venue"
},
  "geometry": {"coordinates":[2.064862,48.948284],"type":"Point"}
}