{
  "type": "Feature",
  "properties": {
    "iso:country":"FR",
    "sg:address":"123, Rue Jules Guesde, 92300 Levallois Perret",
    "sg:orig_category":"Non-Classified Establishments",
    "sg:phone":"+33 1 47 15 64 00",
    "sg:postcode":"92300",
    "sg:province":"Ile de France",
    "wof:name":"Caci Import S.a.r.l.",
    "wof:placetype":"venue"
},
  "geometry": {"coordinates":[2.288036,48.898281],"type":"Point"}
}