{
  "type": "Feature",
  "properties": {
    "addr:full":"17, Rue Albert Sarraut, 78000 Versailles Ile de France",
    "addr:housenumber":"17",
    "addr:postcode":"78000",
    "addr:street":"Rue Albert Sarraut",
    "iso:country":"FR",
    "sg:address":"17, Rue Albert Sarraut, 78000 Versailles",
    "sg:orig_category":"Unclassifiable Establishments",
    "sg:phone":"+33 1 39 50 77 67",
    "sg:province":"Ile de France",
    "wof:name":"M.c.o. S.a. - Menuiserie Charpente De L'ouest",
    "wof:placetype":"venue"
},
  "geometry": {"coordinates":[2.15313,48.795712],"type":"Point"}
}