{
  "type": "Feature",
  "properties": {
    "addr:full":"21, Rue Maupertuis - Parc d'Activit\u00e9 des Ruires, 38320 Eybens Rhone-Alpes 38320",
    "addr:housenumber":"21",
    "addr:postcode":"38320;38320",
    "addr:street":"Rue Maupertuis Parc D'Activite",
    "iso:country":"FR",
    "sg:address":"21, Rue Maupertuis - Parc d'Activit\u00e9 des Ruires, 38320 Eybens",
    "sg:orig_category":"Non-Classified Establishments",
    "sg:phone":"+33 4 76 14 75 10",
    "sg:postcode":"38320",
    "sg:province":"Rhone-Alpes",
    "wof:name":"Alep Syst\u00e8mes S.a.r.l.",
    "wof:placetype":"venue"
},
  "geometry": {"coordinates":[5.7745,45.131962],"type":"Point"}
}