{
  "type": "Feature",
  "properties": {
    "iso:country":"FR",
    "sg:address":"34, Av. de Grande Bretagne, 63000 Clermont Ferrand",
    "sg:city":"Clermont-Ferrand",
    "sg:orig_category":"Unclassifiable Establishments",
    "sg:phone":"+33 4 73 91 13 59",
    "sg:postcode":"63000",
    "sg:province":"Auvergne",
    "wof:name":"Clermont Bobinage S.a.r.l.",
    "wof:placetype":"venue"
},
  "geometry": {"coordinates":[3.094716,45.777748],"type":"Point"}
}