{
  "type": "Feature",
  "properties": {
    "iso:country":"FR",
    "sg:address":"B.P. 214, 76304 Sotteville l\u00e8s Rouen C\u00e9dex^^Rue Nic\u00e9phore Niepce - Zone Industrielle, 76300 Sottevil",
    "sg:orig_category":"Non-Classified Establishments",
    "sg:phone":"+33 2 35 65 14 87",
    "sg:postcode":"76300",
    "sg:province":"Haute Normandie",
    "wof:name":"Erem - Etudes R\u00e9alisations Electro-m\u00e9caniques S.a.",
    "wof:placetype":"venue"
},
  "geometry": {"coordinates":[1.09469,49.411541],"type":"Point"}
}