{
  "type": "Feature",
  "properties": {
    "iso:country":"FR",
    "sg:address":"14 rue de la Procession 95100 Argenteuil",
    "sg:orig_category":"Ampoules",
    "sg:phone":"+33 1 39 81 22 99",
    "sg:postcode":"95100",
    "sg:province":"Ile de France",
    "wof:name":"Planetec Sas",
    "wof:placetype":"venue"
},
  "geometry": {"coordinates":[2.222977,48.933624],"type":"Point"}
}