{
  "type": "Feature",
  "properties": {
    "addr:full":"114, Traverse de la Serviane - La Valentine , 13012 Marseille Poitou-Charentes",
    "addr:housenumber":"114",
    "addr:postcode":"13012",
    "addr:street":"Traverse De La Serviane La Valentine",
    "iso:country":"FR",
    "sg:address":"114, Traverse de la Serviane - La Valentine , 13012 Marseille",
    "sg:orig_category":"Non-Classified Establishments",
    "sg:phone":"+33 4 91 93 92 00",
    "sg:province":"Poitou-Charentes",
    "wof:name":"Secafi Alpha S.a.",
    "wof:placetype":"venue"
},
  "geometry": {"coordinates":[5.416456,43.305122],"type":"Point"}
}