{
  "type": "Feature",
  "properties": {
    "addr:full":"128, Av. Fran\u00e7ois Mitterand, 65600 S\u00e9m\u00e9ac Midi Pyr\u00e9n\u00e9es",
    "addr:postcode":"65600",
    "addr:street":"128 Av. Franc\u0327Ois Mitterand",
    "iso:country":"FR",
    "sg:address":"128, Av. Fran\u00e7ois Mitterand, 65600 S\u00e9m\u00e9ac",
    "sg:orig_category":"Unclassifiable Establishments",
    "sg:phone":"+33 5 62 36 65 39",
    "sg:province":"Midi Pyr\u00e9n\u00e9es",
    "wof:name":"Cima S.a.r.l.",
    "wof:placetype":"venue"
},
  "geometry": {"coordinates":[0.104531,43.221813],"type":"Point"}
}