{
  "type": "Feature",
  "properties": {
    "iso:country":"FR",
    "sg:address":"B.P. 3917, 35039 Rennes C\u00e9dex^^16, Rue de la Roberdi\u00e8re, 35000 Rennes",
    "sg:city":"Rennes",
    "sg:orig_category":"Non-Classified Establishments",
    "sg:phone":"+33 2 99 59 26 08",
    "sg:postcode":"35000",
    "sg:province":"Bretagne",
    "wof:name":"Etablissement Besnard Et G\u00e9rard S.a.",
    "wof:placetype":"venue"
},
  "geometry": {"coordinates":[-1.684477,48.107521],"type":"Point"}
}