{
  "type": "Feature",
  "properties": {
    "addr:full":"ZA des Grands Champs Hillion Bretagne 22120",
    "addr:postcode":"22120",
    "addr:street":"Za Des Grands Champs Hillion Bretagne",
    "iso:country":"FR",
    "sg:address":"ZA des Grands Champs",
    "sg:city":"Hillion",
    "sg:orig_category":"Non-Classified Establishments",
    "sg:phone":"+33 2 96 63 83 10",
    "sg:postcode":"22120",
    "sg:province":"Bretagne",
    "wof:name":"Max Sauer S.a.",
    "wof:placetype":"venue"
},
  "geometry": {"coordinates":[-2.668589,48.513828],"type":"Point"}
}