{
  "type": "Feature",
  "properties": {
    "addr:full":"22 avenue de la Gare 67560 Rosheim Rosheim Alsace 67560",
    "addr:housenumber":"22",
    "addr:postcode":"67560;67560",
    "addr:street":"Avenue De La Gare",
    "iso:country":"FR",
    "sg:address":"22 avenue de la Gare 67560 Rosheim",
    "sg:city":"Rosheim",
    "sg:classifiers":[
        {
            "category":"Coffee & Tea",
            "type":"Food & Drink"
        }
    ],
    "sg:phone":"+33 3 88 50 42 25",
    "sg:postcode":"67560",
    "sg:province":"Alsace",
    "sg:tags":[
        "gardening",
        "seedling"
    ],
    "wof:name":"Ren\u00e9 Badda Sa",
    "wof:placetype":"venue"
},
  "geometry": {"coordinates":[7.488764,48.503159],"type":"Point"}
}