{
  "type": "Feature",
  "properties": {
    "addr:full":"69 Rue De Chateaurenard 94150 Rungis Ile de France 94150",
    "addr:housenumber":"69",
    "addr:postcode":"94150;94150",
    "addr:street":"Rue De Chateaurenard",
    "iso:country":"FR",
    "sg:address":"69 Rue De Chateaurenard 94150 Rungis",
    "sg:classifiers":[
        {
            "category":"Farming",
            "subcategory":"Crops",
            "type":"Manufacturing & Wholesale Goods"
        }
    ],
    "sg:phone":"+33 1 45 12 29 60",
    "sg:postcode":"94150",
    "sg:province":"Ile de France",
    "sg:tags":[
        "vegetable",
        "fruit",
        "agriculture",
        "livestock"
    ],
    "wof:name":"Lachiaille Bratigny Sa",
    "wof:placetype":"venue"
},
  "geometry": {"coordinates":[2.35142,48.74918],"type":"Point"}
}