{
  "type": "Feature",
  "properties": {
    "addr:full":"B.P. 13, 22360 Langueux C\u00e9dex^^29, Rue des Madi\u00e8res, 22360 Langueux Langueux Bretagne 22360",
    "addr:postcode":"22360;22360;22360",
    "addr:street":"B.P. 13;Rue Des Madie\u0300Res",
    "iso:country":"FR",
    "sg:address":"B.P. 13, 22360 Langueux C\u00e9dex^^29, Rue des Madi\u00e8res, 22360 Langueux",
    "sg:city":"Langueux",
    "sg:orig_category":"Non-Classified Establishments",
    "sg:phone":"+33 2 96 52 42 42",
    "sg:postcode":"22360",
    "sg:province":"Bretagne",
    "wof:name":"A.f.p.a.",
    "wof:placetype":"venue"
},
  "geometry": {"coordinates":[-2.715357,48.494778],"type":"Point"}
}