{
  "type": "Feature",
  "properties": {
    "addr:full":"14 Rue des Roquemeonts Folie Couvrechef; Caen; 14050 Basse-Normandie",
    "addr:housenumber":"14",
    "addr:postcode":"14050",
    "addr:street":"Rue Des Roquemeonts Folie",
    "iso:country":"FR",
    "sg:address":"14 Rue des Roquemeonts",
    "sg:city":"Folie Couvrechef; Caen; 14050",
    "sg:classifiers":[
        {
            "category":"Industrial Area",
            "type":"Public Place"
        }
    ],
    "sg:phone":"+33 2 33 76 15 15",
    "sg:province":"Basse-Normandie",
    "sg:tags":[
        "large",
        "private"
    ],
    "wof:name":"Soci\u00e9t\u00e9 Cooperative Agricole Et Agro-alimentaire",
    "wof:placetype":"venue"
},
  "geometry": {"coordinates":[-0.36014,49.184689],"type":"Point"}
}