{
  "type": "Feature",
  "properties": {
    "addr:full":"B.P. 5243, 20502 Ajaccio C\u00e9dex 5^^RN 194 - Bal\u00e9one , 20500 Mezzavia Languedoc-Roussillon",
    "addr:housenumber":"194",
    "addr:postcode":"20502;20500",
    "addr:street":"B.P. 5243;Bale\u0301One;Mezzavia",
    "iso:country":"FR",
    "sg:address":"B.P. 5243, 20502 Ajaccio C\u00e9dex 5^^RN 194 - Bal\u00e9one , 20500 Mezzavia",
    "sg:orig_category":"Non-Classified Establishments",
    "sg:phone":"+33 4 95 22 37 70",
    "sg:province":"Languedoc-Roussillon",
    "wof:name":"Mufraggi S.a.r.l.",
    "wof:placetype":"venue"
},
  "geometry": {"coordinates":[8.73908,41.917889],"type":"Point"}
}