{
  "type": "Feature",
  "properties": {
    "addr:full":"27, Bd de l'Industrie - ZI de Collonges, 42176 Saint Just Saint Rambert C\u00e9dex Ambert Auvergne 63600",
    "addr:housenumber":"27",
    "addr:postcode":"42176;63600",
    "addr:street":"Bd De L'Industrie Zi De Collonges",
    "iso:country":"FR",
    "sg:address":"27, Bd de l'Industrie - ZI de Collonges, 42176 Saint Just Saint Rambert C\u00e9dex",
    "sg:city":"Ambert",
    "sg:orig_category":"Non-Classified Establishments",
    "sg:phone":"+33 4 77 36 10 00",
    "sg:postcode":"63600",
    "sg:province":"Auvergne",
    "wof:name":"Faure Julien S.a.",
    "wof:placetype":"venue"
},
  "geometry": {"coordinates":[4.257258,45.518093],"type":"Point"}
}