{
  "type": "Feature",
  "properties": {
    "addr:full":"BP 21 42130 St Sixte Rhone-Alpes 42130",
    "addr:housenumber":"bp 21",
    "addr:postcode":"42130;42130",
    "addr:street":"Rhone-Alpes",
    "iso:country":"FR",
    "sg:address":"BP 21 42130 St Sixte",
    "sg:classifiers":[
        {
            "category":"Wholesale",
            "subcategory":"Medical Equipment & Supplies",
            "type":"Manufacturing & Wholesale Goods"
        }
    ],
    "sg:phone":"+33 4 77 97 70 70",
    "sg:postcode":"42130",
    "sg:province":"Rhone-Alpes",
    "sg:tags":[
        "instrument",
        "health",
        "-",
        "precision"
    ],
    "wof:name":"Poyet Et Fils (leon)",
    "wof:placetype":"venue"
},
  "geometry": {"coordinates":[3.981219,45.775761],"type":"Point"}
}