{
  "type": "Feature",
  "properties": {
    "addr:full":"20 rue du Mail 75002 Paris Ile de France 75002",
    "addr:housenumber":"20",
    "addr:postcode":"75002;75002",
    "addr:street":"Rue Du Mail",
    "iso:country":"FR",
    "sg:address":"20 rue du Mail 75002 Paris",
    "sg:classifiers":[
        {
            "category":"Shopping",
            "subcategory":"Crafts & Fabrics",
            "type":"Retail Goods"
        }
    ],
    "sg:phone":"+33 1 42 36 97 00",
    "sg:postcode":"75002",
    "sg:province":"Ile de France",
    "sg:tags":[
        "decorative"
    ],
    "wof:name":"Christian Fischbacher Sa",
    "wof:placetype":"venue"
},
  "geometry": {"coordinates":[2.342749,48.866699],"type":"Point"}
}