{
  "type": "Feature",
  "properties": {
    "iso:country":"FR",
    "sg:address":"106 rue Georges Lemaitre 76210 Bolbec",
    "sg:orig_category":"Slaughter-Houses, Abattoirs",
    "sg:phone":"+33 2 35 31 00 93",
    "sg:province":"Haute Normandie",
    "wof:name":"Mutuelle Cooperative Abattage Coop.",
    "wof:placetype":"venue"
},
  "geometry": {"coordinates":[0.461211,49.574921],"type":"Point"}
}