{
  "type": "Feature",
  "properties": {
    "addr:full":"Bd Desaix - ZI le Desaix Toulon Nord Pas-de-Calais 83000",
    "addr:postcode":"83000",
    "addr:street":"Bd Desaix Zi Le Desaix Toulon Nord",
    "iso:country":"FR",
    "sg:address":"Bd Desaix - ZI le Desaix",
    "sg:city":"Toulon",
    "sg:orig_category":"Non-Classified Establishments",
    "sg:phone":"+33 4 94 41 60 76",
    "sg:postcode":"83000",
    "sg:province":"Nord Pas-de-Calais",
    "wof:name":"Autos Pi\u00e8ces Et Accessoires Toulonnais S.a.",
    "wof:placetype":"venue"
},
  "geometry": {"coordinates":[5.930305,43.125324],"type":"Point"}
}