{
  "type": "Feature",
  "properties": {
    "addr:full":"Place de la R\u00e9publique Angoulins Poitou-Charentes 17690",
    "addr:postcode":"17690",
    "addr:street":"Place De La Re\u0301Publique",
    "iso:country":"FR",
    "sg:address":"Place de la R\u00e9publique",
    "sg:city":"Angoulins",
    "sg:orig_category":"Unclassifiable Establishments",
    "sg:phone":"+33 5 46 56 80 11",
    "sg:postcode":"17690",
    "sg:province":"Poitou-Charentes",
    "wof:name":"Entreprise Pianazza Et Fils S.a.r.l.",
    "wof:placetype":"venue"
},
  "geometry": {"coordinates":[-1.109509,46.104523],"type":"Point"}
}