{
  "type": "Feature",
  "properties": {
    "addr:full":"165, Rue de la Belle Etoile - ZI Paris Nord 2, 95700 Roissy en France Ile de France",
    "addr:housenumber":"165;2",
    "addr:postcode":"95700",
    "addr:street":"Rue De La Belle Etoile Zi;Nord",
    "iso:country":"FR",
    "sg:address":"165, Rue de la Belle Etoile - ZI Paris Nord 2, 95700 Roissy en France",
    "sg:orig_category":"Unclassifiable Establishments",
    "sg:phone":"+33 1 49 38 94 30",
    "sg:province":"Ile de France",
    "wof:name":"N.s.2. S.a. - Nord S\u00e9curit\u00e9 Services",
    "wof:placetype":"venue"
},
  "geometry": {"coordinates":[2.517005,49.003883],"type":"Point"}
}