{
  "type": "Feature",
  "properties": {
    "addr:full":"106 R Petit Leroy 94550 Chevilly Larue Ile de France",
    "addr:housenumber":"106",
    "addr:postcode":"94550",
    "addr:street":"R Petit Leroy",
    "iso:country":"FR",
    "sg:address":"106 R Petit Leroy 94550 Chevilly Larue",
    "sg:classifiers":[
        {
            "category":"Professional",
            "subcategory":"Printing & Photocopies",
            "type":"Services"
        }
    ],
    "sg:phone":"+33 1 41 80 20 20",
    "sg:province":"Ile de France",
    "sg:tags":[
        "publishing"
    ],
    "wof:name":"Union Distribution Sa",
    "wof:placetype":"venue"
},
  "geometry": {"coordinates":[2.359471,48.767467],"type":"Point"}
}