{
  "type": "Feature",
  "properties": {
    "iso:country":"FR",
    "sg:address":"Rue de Dublin - ZI La Poudrette",
    "sg:city":"Les Pavillons Sous Bois",
    "sg:orig_category":"Non-Classified Establishments",
    "sg:phone":"+33 1 48 02 47 27",
    "sg:postcode":"93320",
    "sg:province":"Ile de France",
    "wof:name":"Plastimat Injection S.a.r.l.",
    "wof:placetype":"venue"
},
  "geometry": {"coordinates":[2.515585,48.909222],"type":"Point"}
}