{
  "type": "Feature",
  "properties": {
    "addr:full":"1, Rue de l'Industrie - Zone Industrielle, 68360 Soultz Haut Rhin Soultz-Haut-Rhin Alsace 68360",
    "addr:housenumber":"1",
    "addr:postcode":"68360;68360",
    "addr:street":"Rue De L'Industrie Zone Industrielle;Soultz-Haut-Rhin",
    "iso:country":"FR",
    "sg:address":"1, Rue de l'Industrie - Zone Industrielle, 68360 Soultz Haut Rhin",
    "sg:city":"Soultz-Haut-Rhin",
    "sg:orig_category":"Unclassifiable Establishments",
    "sg:phone":"+33 3 89 74 53 10",
    "sg:postcode":"68360",
    "sg:province":"Alsace",
    "wof:name":"Oris France S.a.r.l.",
    "wof:placetype":"venue"
},
  "geometry": {"coordinates":[7.231627,47.896626],"type":"Point"}
}