{
  "type": "Feature",
  "properties": {
    "iso:country":"FR",
    "sg:address":"Zi",
    "sg:city":"Rue Gutenberg 57200 Sarreguemines",
    "sg:classifiers":[
        {
            "category":"Autos & Motor Vehicles",
            "subcategory":"Automobile Sales",
            "type":"Retail Goods"
        }
    ],
    "sg:phone":"+33 3 87 95 11 89",
    "sg:postcode":"57200",
    "sg:province":"Lorraine",
    "sg:tags":[
        "equipment",
        "motor-cars",
        "transport"
    ],
    "wof:name":"Lamberet-isomet Sa",
    "wof:placetype":"venue"
},
  "geometry": {"coordinates":[7.070569,49.108246],"type":"Point"}
}