{
  "type": "Feature",
  "properties": {
    "addr:full":"67 69 Victor Hugo Paris Ile de France 75116",
    "addr:housenumber":"69",
    "addr:postcode":"75116",
    "addr:street":"Victor Hugo",
    "iso:country":"FR",
    "sg:address":"67 69 Victor Hugo",
    "sg:city":"Paris",
    "sg:classifiers":[
        {
            "category":"Banks & Credit Unions",
            "subcategory":"Financial Services",
            "type":"Services"
        }
    ],
    "sg:phone":"+33 1 45 01 57 50",
    "sg:postcode":"75116",
    "sg:province":"Ile de France",
    "sg:tags":[
        "banking",
        "finance",
        "insurance"
    ],
    "wof:name":"Coutard & Associ\u00c9s",
    "wof:placetype":"venue"
},
  "geometry": {"coordinates":[2.28759,48.870415],"type":"Point"}
}