{
  "type": "Feature",
  "properties": {
    "addr:full":"3 Place Andr\u00e9 Malraux 75001 Paris Ile de France 75001",
    "addr:housenumber":"3",
    "addr:postcode":"75001;75001",
    "addr:street":"Place Andre\u0301 Malraux",
    "iso:country":"FR",
    "sg:address":"3 Place Andr\u00e9 Malraux 75001 Paris",
    "sg:classifiers":[
        {
            "category":"Banks & Credit Unions",
            "subcategory":"Financial Services",
            "type":"Services"
        }
    ],
    "sg:phone":"+33 1 44 50 51 00",
    "sg:postcode":"75001",
    "sg:province":"Ile de France",
    "sg:tags":[
        "banking",
        "insurance",
        "institution",
        "finance"
    ],
    "wof:name":"Credit Commercial De France (ccf) Agence Palais Royal",
    "wof:placetype":"venue"
},
  "geometry": {"coordinates":[2.334715,48.86388],"type":"Point"}
}