{
  "type": "Feature",
  "properties": {
    "iso:country":"FR",
    "sg:address":"13342 Marseille C\u00e9dex 15^^26, Av. Paul Heroult - Arnavant Activit\u00e9s Secteur de la Delorme, 13015 Mar",
    "sg:orig_category":"Non-Classified Establishments",
    "sg:phone":"+33 4 91 65 92 20",
    "sg:province":"Poitou-Charentes",
    "wof:name":"C.s.a. S.a. - C\u00e2blerie Saint Antoine",
    "wof:placetype":"venue"
},
  "geometry": {"coordinates":[5.37249,43.293678],"type":"Point"}
}