{
  "type": "Feature",
  "properties": {
    "iso:country":"FR",
    "sg:address":"R Du Manoir 95380 \u00c9piais L\u00e8s Louvres",
    "sg:classifiers":[
        {
            "category":"Manufacturing",
            "subcategory":"Printing",
            "type":"Manufacturing & Wholesale Goods"
        }
    ],
    "sg:phone":"+33 1 34 47 48 80",
    "sg:province":"Ile de France",
    "sg:tags":[
        "publishing"
    ],
    "wof:name":"Scip Label",
    "wof:placetype":"venue"
},
  "geometry": {"coordinates":[2.558325,49.031845],"type":"Point"}
}