{
  "type": "Feature",
  "properties": {
    "iso:country":"FR",
    "sg:address":"Impasse du Charmois",
    "sg:city":"Vagney",
    "sg:orig_category":"Unclassifiable Establishments",
    "sg:phone":"+33 3 29 24 72 78",
    "sg:postcode":"88120",
    "sg:province":"Lorraine",
    "wof:name":"La Nouvelle Graniterie Du Bouchot S.a.r.l.",
    "wof:placetype":"venue"
},
  "geometry": {"coordinates":[6.764836,47.98867],"type":"Point"}
}