{
  "type": "Feature",
  "properties": {
    "iso:country":"FR",
    "sg:address":"192 Rue De La Vall\u00e9e 76600 Le Havre",
    "sg:classifiers":[
        {
            "category":"Manufacturing",
            "subcategory":"Wood Products",
            "type":"Manufacturing & Wholesale Goods"
        }
    ],
    "sg:phone":"+33 2 35 11 33 50",
    "sg:province":"Haute Normandie",
    "sg:tags":[
        "furniture"
    ],
    "wof:name":"Touya Et Cie Sas",
    "wof:placetype":"venue"
},
  "geometry": {"coordinates":[0.159338,49.497318],"type":"Point"}
}