{
  "type": "Feature",
  "properties": {
    "iso:country":"FR",
    "sg:address":"8, Rue de la Dalle, 57680 Nov\u00e9ant sur Moselle",
    "sg:orig_category":"Unclassifiable Establishments",
    "sg:phone":"+33 3 87 52 80 07",
    "sg:province":"Lorraine",
    "wof:name":"Smurfit Lembacel S.a.",
    "wof:placetype":"venue"
},
  "geometry": {"coordinates":[6.049845,49.024681],"type":"Point"}
}