{
  "type": "Feature",
  "properties": {
    "addr:full":"255 Av Carnot 08000 Charleville M\u00e9zi\u00e8res Charleville-M\u00e9zi\u00e8res Champagne 08000",
    "addr:postcode":"08000;08000",
    "addr:street":"255 Av Carnot",
    "iso:country":"FR",
    "sg:address":"255 Av Carnot 08000 Charleville M\u00e9zi\u00e8res",
    "sg:city":"Charleville-M\u00e9zi\u00e8res",
    "sg:classifiers":[
        {
            "category":"Food Court",
            "type":"Food & Drink"
        }
    ],
    "sg:phone":"+33 3 24 52 68 52",
    "sg:postcode":"08000",
    "sg:province":"Champagne",
    "sg:tags":[
        "product",
        "related"
    ],
    "wof:name":"Grande Brasserie Ardial Sa",
    "wof:placetype":"venue"
},
  "geometry": {"coordinates":[4.72653,49.742081],"type":"Point"}
}