{
  "type": "Feature",
  "properties": {
    "iso:country":"FR",
    "sg:address":"141 Rue De Normandie 92400 Courbevoie",
    "sg:classifiers":[
        {
            "category":"Manufacturing",
            "subcategory":"Tools & Machinery",
            "type":"Manufacturing & Wholesale Goods"
        }
    ],
    "sg:phone":"+33 1 47 88 79 60",
    "sg:postcode":"92400",
    "sg:province":"Ile de France",
    "sg:tags":[
        "metallurgy",
        "metalworking"
    ],
    "wof:name":"Filetage Service Sarl",
    "wof:placetype":"venue"
},
  "geometry": {"coordinates":[2.240845,48.901985],"type":"Point"}
}