{
  "type": "Feature",
  "properties": {
    "iso:country":"FR",
    "sg:address":"Chemin Robert Brun - ZI Camp Laurent",
    "sg:city":"La Seyne sur Mer",
    "sg:orig_category":"Unclassifiable Establishments",
    "sg:phone":"+33 4 94 10 99 77",
    "sg:postcode":"83500",
    "sg:province":"Provence-Alpes-C\u00f4te d'Azur",
    "wof:name":"C.r.m.e. S.a.r.l. - Conception R\u00e9alisation M\u00e9canique Electronique Appliqu\u00e9e",
    "wof:placetype":"venue"
},
  "geometry": {"coordinates":[5.881685,43.101559],"type":"Point"}
}