{
  "type": "Feature",
  "properties": {
    "iso:country":"FR",
    "sg:address":"19 RUE ROGER FREMEAUX 68420 Voegtlinshoffen",
    "sg:city":"Voegtlinshoffen",
    "sg:classifiers":[
        {
            "category":"Wholesale",
            "subcategory":"Wine & Distilled Alcoholic Beverages",
            "type":"Manufacturing & Wholesale Goods"
        }
    ],
    "sg:phone":"+33 3 89 49 30 21",
    "sg:postcode":"68420",
    "sg:province":"Alsace",
    "sg:tags":[
        "french"
    ],
    "wof:name":"Cattin Fr\u00e8res Sarl",
    "wof:placetype":"venue"
},
  "geometry": {"coordinates":[7.284477,48.022057],"type":"Point"}
}