{
  "type": "Feature",
  "properties": {
    "addr:full":"2 ave Edouard VII; Biarritz; 64200 Biarritz Aquitaine 64200",
    "addr:postcode":"64200;64200",
    "addr:street":"2 Ave Edouard Vii",
    "iso:country":"FR",
    "sg:address":"2 ave Edouard VII; Biarritz; 64200",
    "sg:city":"Biarritz",
    "sg:classifiers":[
        {
            "category":"Banks & Credit Unions",
            "subcategory":"Bank",
            "type":"Services"
        }
    ],
    "sg:phone":"+33 3359241496",
    "sg:postcode":"64200",
    "sg:province":"Aquitaine",
    "wof:name":"Banque Nationale De Paris",
    "wof:placetype":"venue"
},
  "geometry": {"coordinates":[-1.558792,43.4823],"type":"Point"}
}