{
  "type": "Feature",
  "properties": {
    "addr:full":"130, Rue Mer Rouge, 68200 Mulhouse Mulhouse Alsace 68200",
    "addr:housenumber":"130",
    "addr:postcode":"68200;68200",
    "addr:street":"Rue Mer Rouge",
    "iso:country":"FR",
    "sg:address":"130, Rue Mer Rouge, 68200 Mulhouse",
    "sg:city":"Mulhouse",
    "sg:orig_category":"Non-Classified Establishments",
    "sg:phone":"+33 3 89 50 79 50",
    "sg:postcode":"68200",
    "sg:province":"Alsace",
    "wof:name":"Coop\u00e9rative Des Ma\u00eetres Boulangers Et P\u00e2tissiers De Mulhouse",
    "wof:placetype":"venue"
},
  "geometry": {"coordinates":[7.295103,47.743435],"type":"Point"}
}