{
  "type": "Feature",
  "properties": {
    "addr:full":"B.P. 16, 69571 Dardilly C\u00e9dex^^35, Chemin des Aulnes, 69570 Dardilly Rhone-Alpes",
    "addr:postcode":"69571;69570",
    "addr:street":"B.P. 16;Chemin Des Aulnes",
    "iso:country":"FR",
    "sg:address":"B.P. 16, 69571 Dardilly C\u00e9dex^^35, Chemin des Aulnes, 69570 Dardilly",
    "sg:orig_category":"Non-Classified Establishments",
    "sg:phone":"+33 4 72 52 10 00",
    "sg:province":"Rhone-Alpes",
    "wof:name":"Thor S.a.",
    "wof:placetype":"venue"
},
  "geometry": {"coordinates":[4.753535,45.805908],"type":"Point"}
}