{
  "type": "Feature",
  "properties": {
    "addr:full":"153, Rte de Lod\u00e8ve, 34990 Juvignac Languedoc-Roussillon",
    "addr:housenumber":"153",
    "addr:postcode":"34990",
    "addr:street":"Rte De Lode\u0300Ve",
    "iso:country":"FR",
    "sg:address":"153, Rte de Lod\u00e8ve, 34990 Juvignac",
    "sg:orig_category":"Unclassifiable Establishments",
    "sg:phone":"+33 4 67 75 37 24",
    "sg:province":"Languedoc-Roussillon",
    "wof:name":"B.c.l. S.a.s. - B\u00e9ton Chantiers Languedoc",
    "wof:placetype":"venue"
},
  "geometry": {"coordinates":[3.81286,43.614044],"type":"Point"}
}