{
  "type": "Feature",
  "properties": {
    "addr:full":"32400 St Germe Midi Pyr\u00e9n\u00e9es 32400",
    "addr:housenumber":"32400",
    "addr:postcode":"32400",
    "addr:street":"St",
    "iso:country":"FR",
    "sg:address":"32400 St Germe",
    "sg:classifiers":[
        {
            "category":"Farming",
            "subcategory":"Farm & Veterinary Services",
            "type":"Manufacturing & Wholesale Goods"
        }
    ],
    "sg:phone":"+33 5 62 69 66 00",
    "sg:postcode":"32400",
    "sg:province":"Midi Pyr\u00e9n\u00e9es",
    "sg:tags":[
        "food",
        "product",
        "breeding",
        "animal",
        "related"
    ],
    "wof:name":"Couvoirs De Gascogne Sa",
    "wof:placetype":"venue"
},
  "geometry": {"coordinates":[-0.149444,43.680607],"type":"Point"}
}