{
  "type": "Feature",
  "properties": {
    "addr:full":"5 Rue De La Lucque Zae Garrigue 34725 St Andre De Sangonis Languedoc-Roussillon 34725",
    "addr:housenumber":"5",
    "addr:postcode":"34725;34725",
    "addr:street":"Rue De La Lucque Zae Garrigue;Sangonis",
    "iso:country":"FR",
    "sg:address":"5 Rue De La Lucque Zae Garrigue 34725 St Andre De Sangonis",
    "sg:classifiers":[
        {
            "category":"Professional",
            "subcategory":"Engineering",
            "type":"Services"
        }
    ],
    "sg:phone":"+33 4 67 57 03 57",
    "sg:postcode":"34725",
    "sg:province":"Languedoc-Roussillon",
    "sg:tags":[
        "ma",
        "business",
        "advice",
        "-",
        "environment",
        "equipment",
        "machinery",
        "mechanical"
    ],
    "wof:name":"Action Prevention Incendie (api)",
    "wof:placetype":"venue"
},
  "geometry": {"coordinates":[3.503939,43.650146],"type":"Point"}
}