{
  "type": "Feature",
  "properties": {
    "addr:full":"Chem La Fosse 78550 Bazainville Ile de France 78550",
    "addr:postcode":"78550;78550",
    "addr:street":"Chem La Fosse;Ile De France",
    "iso:country":"FR",
    "sg:address":"Chem La Fosse 78550 Bazainville",
    "sg:classifiers":[
        {
            "category":"Banks & Credit Unions",
            "subcategory":"Financial Services",
            "type":"Services"
        }
    ],
    "sg:phone":"+33 1 30 88 19 19",
    "sg:postcode":"78550",
    "sg:province":"Ile de France",
    "sg:tags":[
        "banking",
        "insurance",
        "institution",
        "finance"
    ],
    "wof:name":"Guilde Des Lunetiers De France",
    "wof:placetype":"venue"
},
  "geometry": {"coordinates":[1.6701,48.799477],"type":"Point"}
}