{
  "type": "Feature",
  "properties": {
    "addr:full":"21, Rue du Petit Albi - Parc Silic - B\u00e2t. C, 95000 Cergy Ile de France",
    "addr:housenumber":"21;ba\u0302t c",
    "addr:postcode":"95000;ile",
    "addr:street":"Rue Du Petit Albi Parc Silic",
    "iso:country":"FR",
    "sg:address":"21, Rue du Petit Albi - Parc Silic - B\u00e2t. C, 95000 Cergy",
    "sg:orig_category":"Unclassifiable Establishments",
    "sg:phone":"+33 1 34 41 53 00",
    "sg:province":"Ile de France",
    "wof:name":"Matthews France S.a.",
    "wof:placetype":"venue"
},
  "geometry": {"coordinates":[2.04088,49.054691],"type":"Point"}
}