{
  "type": "Feature",
  "properties": {
    "addr:full":"B.P. 17, 22700 Perros Guirec C\u00e9dex^^ZA Kergadic, 22700 Perros Guirec Louannec Bretagne 22700",
    "addr:postcode":"22700;22700;22700",
    "addr:street":"B.P. 17;Kergadic",
    "iso:country":"FR",
    "sg:address":"B.P. 17, 22700 Perros Guirec C\u00e9dex^^ZA Kergadic, 22700 Perros Guirec",
    "sg:city":"Louannec",
    "sg:orig_category":"Non-Classified Establishments",
    "sg:phone":"+33 2 96 49 80 20",
    "sg:postcode":"22700",
    "sg:province":"Bretagne",
    "wof:name":"P.e.c.i. S.a. - Perros Express Circuits Imprim\u00e9s",
    "wof:placetype":"venue"
},
  "geometry": {"coordinates":[-3.446654,48.792221],"type":"Point"}
}