{
  "type": "Feature",
  "properties": {
    "iso:country":"FR",
    "sg:address":"43 Av De La Gare 36000 Chateauroux",
    "sg:city":"Ch\u00e2teauroux",
    "sg:classifiers":[
        {
            "category":"Professional",
            "subcategory":"Advertising",
            "type":"Services"
        }
    ],
    "sg:phone":"+33 2 54 53 12 01",
    "sg:postcode":"36000",
    "sg:province":"Centre",
    "sg:tags":[
        "information",
        "medium",
        "communication"
    ],
    "wof:name":"Nr Communication",
    "wof:placetype":"venue"
},
  "geometry": {"coordinates":[1.69738,46.810814],"type":"Point"}
}