{
  "type": "Feature",
  "properties": {
    "addr:full":"Av. L\u00e9on Heid Pau Aquitaine 64000",
    "addr:postcode":"64000",
    "addr:street":"Av. Le\u0301On Heid",
    "iso:country":"FR",
    "sg:address":"Av. L\u00e9on Heid",
    "sg:city":"Pau",
    "sg:orig_category":"Unclassifiable Establishments",
    "sg:phone":"+33 5 59 27 86 12",
    "sg:postcode":"64000",
    "sg:province":"Aquitaine",
    "wof:name":"C.n.c. S.a. - Compagnie Nouvelle De Containers",
    "wof:placetype":"venue"
},
  "geometry": {"coordinates":[-0.363599,43.292213],"type":"Point"}
}