{
  "type": "Feature",
  "properties": {
    "iso:country":"FR",
    "sg:address":"B.P. 3, 83390 Cuers^^Av. de la Promenade, 83210 Solli\u00e8s Toucas",
    "sg:orig_category":"Non-Classified Establishments",
    "sg:phone":"+33 4 94 28 93 28",
    "sg:province":"Midi Pyr\u00e9n\u00e9es",
    "wof:name":"Transvar S.a.",
    "wof:placetype":"venue"
},
  "geometry": {"coordinates":[6.042811,43.166992],"type":"Point"}
}