{
  "type": "Feature",
  "properties": {
    "iso:country":"FR",
    "sg:address":"Av Virecourt 33370 Artigues Pr\u00e8s Bordeaux",
    "sg:city":"Artigues-pr\u00e8s-Bordeaux",
    "sg:classifiers":[
        {
            "category":"Shopping",
            "type":"Retail Goods"
        }
    ],
    "sg:phone":"+33 5 56 38 51 38",
    "sg:postcode":"33370",
    "sg:province":"Aquitaine",
    "sg:tags":[
        "metallurgy",
        "finished",
        "-",
        "metalworking",
        "metallic"
    ],
    "wof:name":"Signalisations (ste Des) Sa",
    "wof:placetype":"venue"
},
  "geometry": {"coordinates":[-0.496149,44.856274],"type":"Point"}
}