{
  "type": "Feature",
  "properties": {
    "addr:full":"4 Impasse Milord 75018 Paris Ile de France",
    "addr:housenumber":"4",
    "addr:postcode":"75018",
    "addr:street":"Impasse Milord",
    "iso:country":"FR",
    "sg:address":"4 Impasse Milord 75018 Paris",
    "sg:classifiers":[
        {
            "category":"Manufacturing",
            "subcategory":"Printing",
            "type":"Manufacturing & Wholesale Goods"
        }
    ],
    "sg:phone":"+33 1 42 67 72 50",
    "sg:province":"Ile de France",
    "sg:tags":[
        "publishing"
    ],
    "wof:name":"Savoye Impression",
    "wof:placetype":"venue"
},
  "geometry": {"coordinates":[2.328823,48.8964],"type":"Point"}
}