{
  "type": "Feature",
  "properties": {
    "addr:full":"B.P. 16, 54810 Longlaville^^P\u00f4le Europ\u00e9en de D\u00e9veloppement, 54810 Longlaville Lorraine 54810",
    "addr:postcode":"54810;54810;54810",
    "addr:street":"B.P. 16;Europe\u0301En;De\u0301Veloppement",
    "iso:country":"FR",
    "sg:address":"B.P. 16, 54810 Longlaville^^P\u00f4le Europ\u00e9en de D\u00e9veloppement, 54810 Longlaville",
    "sg:orig_category":"Non-Classified Establishments",
    "sg:phone":"+33 3 82 44 80 00",
    "sg:postcode":"54810",
    "sg:province":"Lorraine",
    "wof:name":"Alliedsignal Industrial Fibers S.a.",
    "wof:placetype":"venue"
},
  "geometry": {"coordinates":[5.79868,49.534355],"type":"Point"}
}