{
  "type": "Feature",
  "properties": {
    "addr:full":"33380 Biganos Biganos Aquitaine 33380",
    "addr:postcode":"33380;33380",
    "iso:country":"FR",
    "sg:address":"33380 Biganos",
    "sg:city":"Biganos",
    "sg:orig_category":"Non-Classified Establishments",
    "sg:phone":"+33 5 56 82 60 75",
    "sg:postcode":"33380",
    "sg:province":"Aquitaine",
    "wof:name":"Cartonnerie Du Val De Leyre S.a.",
    "wof:placetype":"venue"
},
  "geometry": {"coordinates":[-0.976537,44.641827],"type":"Point"}
}