{
  "type": "Feature",
  "properties": {
    "iso:country":"FR",
    "sg:address":"B.P. 106, 76330 Notre Dame de Gravenchon^^Rue Bertin - Zone Industrielle, 76330 Notre Dame de Graven",
    "sg:orig_category":"Non-Classified Establishments",
    "sg:phone":"+33 2 35 38 71 82",
    "sg:postcode":"76330",
    "sg:province":"Haute Normandie",
    "wof:name":"C.s.t. S.a. - Chaudronnerie Soudure Tuyauterie",
    "wof:placetype":"venue"
},
  "geometry": {"coordinates":[0.5674,49.489555],"type":"Point"}
}