{
  "type": "Feature",
  "properties": {
    "iso:country":"FR",
    "sg:address":"Chemin du Cracaud",
    "sg:city":"Pornic",
    "sg:orig_category":"Unclassifiable Establishments",
    "sg:phone":"+33 2 40 82 01 73",
    "sg:postcode":"44210",
    "sg:province":"Pays de Loire",
    "wof:name":"Faiencerie De Pornic S.a.r.l.",
    "wof:placetype":"venue"
},
  "geometry": {"coordinates":[-2.111803,47.118759],"type":"Point"}
}