{
  "type": "Feature",
  "properties": {
    "addr:full":"31 Rue Dumont D'Urville 76600 Le Havre Haute Normandie",
    "addr:housenumber":"31",
    "addr:postcode":"76600",
    "addr:street":"Rue Dumont D'Urville",
    "iso:country":"FR",
    "sg:address":"31 Rue Dumont D'Urville 76600 Le Havre",
    "sg:classifiers":[
        {
            "category":"Banks & Credit Unions",
            "subcategory":"Investment Brokerage",
            "type":"Services"
        }
    ],
    "sg:phone":"+33 2 35 25 15 78",
    "sg:province":"Haute Normandie",
    "sg:tags":[
        "-",
        "transport",
        "related"
    ],
    "wof:name":"Manuport Sarl",
    "wof:placetype":"venue"
},
  "geometry": {"coordinates":[0.136117,49.48455],"type":"Point"}
}