{
  "type": "Feature",
  "properties": {
    "iso:country":"FR",
    "sg:address":"6, Rue des Aliz\u00e9es - ZI, 14790 Verson",
    "sg:city":"Verson",
    "sg:orig_category":"Non-Classified Establishments",
    "sg:phone":"+33 2 31 71 23 00",
    "sg:postcode":"14790",
    "sg:province":"Basse Normandie",
    "wof:name":"Les Studio Schuller S.a.",
    "wof:placetype":"venue"
},
  "geometry": {"coordinates":[-0.449964,49.15596],"type":"Point"}
}