{
  "type": "Feature",
  "properties": {
    "addr:full":"Rue Jacquart - Le Bert Les Aveni\u00e8res Rhone-Alpes 38630",
    "addr:postcode":"38630",
    "addr:street":"Rue Jacquart Le Bert Les;Rhone-Alpes",
    "iso:country":"FR",
    "sg:address":"Rue Jacquart - Le Bert",
    "sg:city":"Les Aveni\u00e8res",
    "sg:orig_category":"Non-Classified Establishments",
    "sg:phone":"+33 4 74 33 61 41",
    "sg:postcode":"38630",
    "sg:province":"Rhone-Alpes",
    "wof:name":"Imprimerie Max Perrin S.a.",
    "wof:placetype":"venue"
},
  "geometry": {"coordinates":[5.562497,45.635681],"type":"Point"}
}