{
  "type": "Feature",
  "properties": {
    "addr:full":"1 avenue Saint-Eloi 87000 Limoges Limousin 87000",
    "addr:housenumber":"1",
    "addr:postcode":"87000;87000",
    "addr:street":"Avenue Saint-Eloi",
    "iso:country":"FR",
    "sg:address":"1 avenue Saint-Eloi 87000 Limoges",
    "sg:classifiers":[
        {
            "category":"Professional",
            "subcategory":"Business Services",
            "type":"Services"
        }
    ],
    "sg:phone":"+33 5 55 12 17 60",
    "sg:postcode":"87000",
    "sg:province":"Limousin",
    "sg:tags":[
        "agency",
        "export"
    ],
    "wof:name":"Cerlim S.a.",
    "wof:placetype":"venue"
},
  "geometry": {"coordinates":[1.248968,45.827896],"type":"Point"}
}