{
  "type": "Feature",
  "properties": {
    "addr:full":"B.P. 6 Pamproux Poitou-Charentes 79800",
    "addr:postcode":"79800",
    "addr:street":"B.P. 6 Pamproux",
    "iso:country":"FR",
    "sg:address":"B.P. 6",
    "sg:city":"Pamproux",
    "sg:orig_category":"Non-Classified Establishments",
    "sg:phone":"+33 5 49 76 38 10",
    "sg:postcode":"79800",
    "sg:province":"Poitou-Charentes",
    "wof:name":"Pampr'oeuf Distribution S.a.",
    "wof:placetype":"venue"
},
  "geometry": {"coordinates":[-0.054749,46.396015],"type":"Point"}
}