{
  "type": "Feature",
  "properties": {
    "addr:full":"B.P. 13, 63360 Gerzat C\u00e9dex^^Rue de l'Etincelle, 63360 Gerzat Gerzat Auvergne 63360",
    "addr:postcode":"63360;63360;63360",
    "addr:street":"B.P. 13",
    "iso:country":"FR",
    "sg:address":"B.P. 13, 63360 Gerzat C\u00e9dex^^Rue de l'Etincelle, 63360 Gerzat",
    "sg:city":"Gerzat",
    "sg:orig_category":"Non-Classified Establishments",
    "sg:phone":"+33 4 73 23 48 20",
    "sg:postcode":"63360",
    "sg:province":"Auvergne",
    "wof:name":"S.m.c. S.a. - Soci\u00e9t\u00e9 Meuni\u00e8re Du Centre",
    "wof:placetype":"venue"
},
  "geometry": {"coordinates":[3.139361,45.82579],"type":"Point"}
}