{
  "type": "Feature",
  "properties": {
    "iso:country":"FR",
    "sg:address":"3 bis, Rue du Moulin, 89100 Saligny",
    "sg:city":"Saligny",
    "sg:orig_category":"Unclassifiable Establishments",
    "sg:phone":"+33 3 86 97 87 79",
    "sg:postcode":"89100",
    "sg:province":"Bourgogne",
    "wof:name":"Etablissements Allard S.a.",
    "wof:placetype":"venue"
},
  "geometry": {"coordinates":[3.359768,48.214787],"type":"Point"}
}