{
  "type": "Feature",
  "properties": {
    "addr:full":"6 Pl De La Sorbonne 75005 Paris Ile de France",
    "addr:housenumber":"6",
    "addr:postcode":"75005",
    "addr:street":"Pl De La Sorbonne",
    "iso:country":"FR",
    "sg:address":"6 Pl De La Sorbonne 75005 Paris",
    "sg:classifiers":[
        {
            "category":"Professional",
            "subcategory":"Printing & Photocopies",
            "type":"Services"
        }
    ],
    "sg:phone":"+33 1 43 54 03 47",
    "sg:province":"Ile de France",
    "sg:tags":[
        "publishing"
    ],
    "wof:name":"Librairie Philisophique Vrin Sarl",
    "wof:placetype":"venue"
},
  "geometry": {"coordinates":[2.342418,48.848682],"type":"Point"}
}