{
  "type": "Feature",
  "properties": {
    "iso:country":"FR",
    "sg:address":"31, Rue au Pain, 78100 Saint Germain en Laye",
    "sg:orig_category":"Non-Classified Establishments",
    "sg:phone":"+33 1 30 61 78 78",
    "sg:postcode":"78100",
    "sg:province":"Ile de France",
    "wof:name":"Caodao S.a.r.l.",
    "wof:placetype":"venue"
},
  "geometry": {"coordinates":[2.092283,48.896904],"type":"Point"}
}