{
  "type": "Feature",
  "properties": {
    "iso:country":"FR",
    "sg:address":"19 Rue Du Ratrait 92150 Suresnes",
    "sg:classifiers":[
        {
            "category":"Professional",
            "subcategory":"Printing & Photocopies",
            "type":"Services"
        }
    ],
    "sg:phone":"+33 1 46 25 07 20",
    "sg:postcode":"92150",
    "sg:province":"Ile de France",
    "sg:tags":[
        "machine",
        "engineering",
        "-",
        "mechanical"
    ],
    "wof:name":"Corneleup",
    "wof:placetype":"venue"
},
  "geometry": {"coordinates":[2.23011,48.876667],"type":"Point"}
}