{
  "type": "Feature",
  "properties": {
    "addr:full":"B.P. FRU 651 Rungis C\u00e9dex Ile de France 94621",
    "addr:housenumber":"651",
    "addr:postcode":"94621",
    "iso:country":"FR",
    "sg:address":"B.P. FRU 651",
    "sg:city":"Rungis C\u00e9dex",
    "sg:orig_category":"Non-Classified Establishments",
    "sg:phone":"+33 1 41 73 25 10",
    "sg:postcode":"94621",
    "sg:province":"Ile de France",
    "wof:name":"Pi\u00e9dor S.a.",
    "wof:placetype":"venue"
},
  "geometry": {"coordinates":[2.35325,48.751419],"type":"Point"}
}