{
  "type": "Feature",
  "properties": {
    "iso:country":"FR",
    "sg:address":"50 Blvd du G\u00e9n\u00e9ral; Roubaix; 59100",
    "sg:classifiers":[
        {
            "category":"Banks & Credit Unions",
            "subcategory":"Bank",
            "type":"Services"
        }
    ],
    "sg:phone":"+33 3 20 81 98 68",
    "sg:postcode":"59100",
    "sg:province":"Nord Pas-de-Calais",
    "wof:name":"Banque Regionale, Du Nord Sa",
    "wof:placetype":"venue"
},
  "geometry": {"coordinates":[3.171504,50.685066],"type":"Point"}
}