{
  "type": "Feature",
  "properties": {
    "iso:country":"FR",
    "sg:address":"17 Rue Eugene Varlin 75010 Paris",
    "sg:classifiers":[
        {
            "category":"Shopping",
            "subcategory":"Clothing, Apparel, & Fashions",
            "type":"Retail Goods"
        }
    ],
    "sg:phone":"+33 1 42 05 43 09",
    "sg:postcode":"75010",
    "sg:province":"Ile de France",
    "sg:tags":[
        "textile",
        "clothing",
        "clothes"
    ],
    "wof:name":"Claverie Style",
    "wof:placetype":"venue"
},
  "geometry": {"coordinates":[2.363579,48.878716],"type":"Point"}
}