{
  "type": "Feature",
  "properties": {
    "addr:full":"B.P. 11, 41913 Blois C\u00e9dex 9^^1, Rue de l'Erigny, 41000 Blois Blois Centre 41000",
    "addr:housenumber":"9 ^ ^ 1",
    "addr:postcode":"41913;41000;41000",
    "addr:street":"B.P. 11;Ce\u0301Dex;Rue De L'Erigny",
    "iso:country":"FR",
    "sg:address":"B.P. 11, 41913 Blois C\u00e9dex 9^^1, Rue de l'Erigny, 41000 Blois",
    "sg:city":"Blois",
    "sg:orig_category":"Non-Classified Establishments",
    "sg:phone":"+33 2 54 90 29 90",
    "sg:postcode":"41000",
    "sg:province":"Centre",
    "wof:name":"A.f.p.a.",
    "wof:placetype":"venue"
},
  "geometry": {"coordinates":[1.330772,47.608902],"type":"Point"}
}