{
  "type": "Feature",
  "properties": {
    "iso:country":"FR",
    "sg:address":"B.P. 14, 33451 Saint Loub\u00e8s C\u00e9dex^^9, Av. du G\u00e9n\u00e9ral de Castelnau, 33140 Villenave d'Ornon",
    "sg:city":"Cadaujac",
    "sg:orig_category":"Non-Classified Establishments",
    "sg:phone":"+33 5 56 87 11 92",
    "sg:postcode":"33140",
    "sg:province":"Aquitaine",
    "wof:name":"Bordeaux Viandes S.a.",
    "wof:placetype":"venue"
},
  "geometry": {"coordinates":[-0.543771,44.771378],"type":"Point"}
}