{
  "type": "Feature",
  "properties": {
    "addr:full":"12, Rue de la Cornillatte, 89500 Villeneuve sur Yonne Cornant Bourgogne 89500",
    "addr:housenumber":"12",
    "addr:postcode":"89500;89500",
    "addr:street":"Rue De La Cornillatte;Bourgogne",
    "iso:country":"FR",
    "sg:address":"12, Rue de la Cornillatte, 89500 Villeneuve sur Yonne",
    "sg:city":"Cornant",
    "sg:orig_category":"Unclassifiable Establishments",
    "sg:phone":"+33 3 86 87 34 61",
    "sg:postcode":"89500",
    "sg:province":"Bourgogne",
    "wof:name":"Guernet S.a.r.l.",
    "wof:placetype":"venue"
},
  "geometry": {"coordinates":[3.299767,48.085114],"type":"Point"}
}