{
  "type": "Feature",
  "properties": {
    "iso:country":"FR",
    "sg:address":"40 Av Eisenhower 50290 Br\u00e9hal",
    "sg:city":"Br\u00e9hal",
    "sg:classifiers":[
        {
            "category":"Professional",
            "type":"Services"
        }
    ],
    "sg:phone":"+33 2 33 51 72 40",
    "sg:postcode":"50290",
    "sg:province":"Basse Normandie",
    "sg:tags":[
        "transport",
        "road"
    ],
    "wof:name":"Societe Brehalaise De Transports Sarl",
    "wof:placetype":"venue"
},
  "geometry": {"coordinates":[-1.51141,48.902328],"type":"Point"}
}