{
  "type": "Feature",
  "properties": {
    "iso:country":"FR",
    "sg:address":"Impasse de l'Ecureuil - Espace Valentin",
    "sg:city":"Besan\u00e7on",
    "sg:orig_category":"Unclassifiable Establishments",
    "sg:phone":"+33 3 81 80 88 44",
    "sg:postcode":"25000",
    "sg:province":"Franche Comt\u00e9",
    "wof:name":"Yale France Manutention S.a.r.l.",
    "wof:placetype":"venue"
},
  "geometry": {"coordinates":[6.012065,47.266285],"type":"Point"}
}