{
  "type": "Feature",
  "properties": {
    "addr:full":"B.P. 453, 22108 Dinan C\u00e9dex^^Parc d'Activit\u00e9s des Alleux, 22100 Taden Taden Bretagne 22100",
    "addr:housenumber":"b.p. 453",
    "addr:postcode":"22108;22100;22100",
    "addr:street":"Taden",
    "iso:country":"FR",
    "sg:address":"B.P. 453, 22108 Dinan C\u00e9dex^^Parc d'Activit\u00e9s des Alleux, 22100 Taden",
    "sg:city":"Taden",
    "sg:orig_category":"Non-Classified Establishments",
    "sg:phone":"+33 2 96 87 13 13",
    "sg:postcode":"22100",
    "sg:province":"Bretagne",
    "wof:name":"S.m.o. International S.a. - Service Maintenance Organisation International",
    "wof:placetype":"venue"
},
  "geometry": {"coordinates":[-2.01664,48.475521],"type":"Point"}
}