{
  "type": "Feature",
  "properties": {
    "addr:full":"61, Rte de Cr\u00e9cy, 28500 Vernouillet Vernouillet Centre 28500",
    "addr:housenumber":"61",
    "addr:postcode":"28500;28500",
    "addr:street":"Rte De Cre\u0301Cy;Vernouillet",
    "iso:country":"FR",
    "sg:address":"61, Rte de Cr\u00e9cy, 28500 Vernouillet",
    "sg:city":"Vernouillet",
    "sg:orig_category":"Non-Classified Establishments",
    "sg:phone":"+33 2 37 42 42 81",
    "sg:postcode":"28500",
    "sg:province":"Centre",
    "wof:name":"L.s.b.h. S.a. - Laboratoires Saint Beno\u00eet Heuprophax",
    "wof:placetype":"venue"
},
  "geometry": {"coordinates":[1.331934,48.726574],"type":"Point"}
}