{
  "type": "Feature",
  "properties": {
    "addr:full":"B.P. 50, 37230 Fondettes Cedex^^ZI La Haute Limoug\u00e8re, 37230 Fondettes Fondettes Centre 37230",
    "addr:postcode":"37230;37230;37230",
    "addr:street":"B.P. 50;Limouge\u0300Re",
    "iso:country":"FR",
    "sg:address":"B.P. 50, 37230 Fondettes Cedex^^ZI La Haute Limoug\u00e8re, 37230 Fondettes",
    "sg:city":"Fondettes",
    "sg:orig_category":"Non-Classified Establishments",
    "sg:phone":"+33 2 47 42 23 46",
    "sg:postcode":"37230",
    "sg:province":"Centre",
    "wof:name":"Breugnon Daniel",
    "wof:placetype":"venue"
},
  "geometry": {"coordinates":[0.516665,47.370476],"type":"Point"}
}