{
  "type": "Feature",
  "properties": {
    "addr:full":"B.P. 85221, 57076 Metz C\u00e9dex 03^^8, Rue de la petite boucherie, 57000 Metz Lorraine 57000",
    "addr:housenumber":"03 ^ ^ 8",
    "addr:postcode":"57076;57000;57000",
    "addr:street":"Ce\u0301Dex;Rue De La Petite Boucherie",
    "iso:country":"FR",
    "sg:address":"B.P. 85221, 57076 Metz C\u00e9dex 03^^8, Rue de la petite boucherie, 57000 Metz",
    "sg:orig_category":"Non-Classified Establishments",
    "sg:phone":"+33 3 87 18 42 84",
    "sg:postcode":"57000",
    "sg:province":"Lorraine",
    "wof:name":"Axos S.a.r.l.",
    "wof:placetype":"venue"
},
  "geometry": {"coordinates":[6.183995,49.07645],"type":"Point"}
}