{
  "type": "Feature",
  "properties": {
    "addr:full":"22250 Lanrelas Lanrelas Bretagne 22250",
    "addr:housenumber":"22250",
    "addr:postcode":"22250",
    "addr:street":"Lanrelas Lanrelas Bretagne",
    "iso:country":"FR",
    "sg:address":"22250 Lanrelas",
    "sg:city":"Lanrelas",
    "sg:orig_category":"Unclassifiable Establishments",
    "sg:phone":"+33 2 96 84 70 63",
    "sg:postcode":"22250",
    "sg:province":"Bretagne",
    "wof:name":"Etablissement Houel S.a.",
    "wof:placetype":"venue"
},
  "geometry": {"coordinates":[-2.293149,48.251541],"type":"Point"}
}