{
  "type": "Feature",
  "properties": {
    "addr:full":"4 avenue Laurent Cely 92600 Asnieres sur Seine Ile de France 92600",
    "addr:housenumber":"4",
    "addr:postcode":"92600;92600",
    "addr:street":"Avenue Laurent Cely;France",
    "iso:country":"FR",
    "sg:address":"4 avenue Laurent Cely 92600 Asnieres sur Seine",
    "sg:classifiers":[
        {
            "category":"Wholesale",
            "subcategory":"Medical Equipment & Supplies",
            "type":"Manufacturing & Wholesale Goods"
        }
    ],
    "sg:phone":"+33 1 46 13 43 60",
    "sg:postcode":"92600",
    "sg:province":"Ile de France",
    "wof:name":"Europ Continents Sa",
    "wof:placetype":"venue"
},
  "geometry": {"coordinates":[2.31074,48.914474],"type":"Point"}
}