{
  "type": "Feature",
  "properties": {
    "iso:country":"FR",
    "sg:address":"34 avenue Karl Marx 69120 Vaulx en Velin",
    "sg:classifiers":[
        {
            "category":"Manufacturing",
            "subcategory":"Motor Vehicles & Parts",
            "type":"Manufacturing & Wholesale Goods"
        }
    ],
    "sg:phone":"+33 4 78 79 55 40",
    "sg:province":"Rhone-Alpes",
    "sg:tags":[
        "precision",
        "mechanic"
    ],
    "wof:name":"Someb Sa",
    "wof:placetype":"venue"
},
  "geometry": {"coordinates":[4.939672,45.778347],"type":"Point"}
}