{
  "type": "Feature",
  "properties": {
    "addr:full":"B.P. 659, 59506 Douai C\u00e9dex^^120, Rue Morel, 59500 Douai Nord Pas-de-Calais 59500",
    "addr:housenumber":"b.p. 659",
    "addr:postcode":"59506;59500;59500",
    "addr:street":"Rue Morel",
    "iso:country":"FR",
    "sg:address":"B.P. 659, 59506 Douai C\u00e9dex^^120, Rue Morel, 59500 Douai",
    "sg:orig_category":"Non-Classified Establishments",
    "sg:phone":"+33 3 27 93 74 77",
    "sg:postcode":"59500",
    "sg:province":"Nord Pas-de-Calais",
    "wof:name":"Douaisis D\u00e9veloppement - Cci Douai",
    "wof:placetype":"venue"
},
  "geometry": {"coordinates":[3.07836,50.368759],"type":"Point"}
}