{
  "type": "Feature",
  "properties": {
    "iso:country":"FR",
    "sg:address":"35 Rue Du Gal Metman 57070 Metz",
    "sg:classifiers":[
        {
            "category":"Farming",
            "subcategory":"Farm & Veterinary Services",
            "type":"Manufacturing & Wholesale Goods"
        }
    ],
    "sg:phone":"+33 3 87 74 29 34",
    "sg:postcode":"57070",
    "sg:province":"Lorraine",
    "sg:tags":[
        "advice",
        "agriculture",
        "livestock",
        "business"
    ],
    "wof:name":"Nature Est",
    "wof:placetype":"venue"
},
  "geometry": {"coordinates":[6.208374,49.119869],"type":"Point"}
}