{
  "type": "Feature",
  "properties": {
    "addr:full":"40 Rue Durmeyer 61100 Flers Flers Basse Normandie 61100",
    "addr:housenumber":"40",
    "addr:postcode":"61100;61100",
    "addr:street":"Rue Durmeyer",
    "iso:country":"FR",
    "sg:address":"40 Rue Durmeyer 61100 Flers",
    "sg:city":"Flers",
    "sg:classifiers":[
        {
            "category":"Shopping",
            "subcategory":"Crafts & Fabrics",
            "type":"Retail Goods"
        }
    ],
    "sg:phone":"+33 2 33 65 24 76",
    "sg:postcode":"61100",
    "sg:province":"Basse Normandie",
    "sg:tags":[
        "textile",
        "clothing"
    ],
    "wof:name":"Ets Jean Sabine",
    "wof:placetype":"venue"
},
  "geometry": {"coordinates":[-0.570834,48.74197],"type":"Point"}
}