{
  "type": "Feature",
  "properties": {
    "iso:country":"FR",
    "sg:address":"29, Rue Saint Lazare, 41260 La Chauss\u00e9e Saint Victor",
    "sg:city":"La Chauss\u00e9e-Saint-Victor",
    "sg:orig_category":"Unclassifiable Establishments",
    "sg:phone":"+33 2 54 74 69 55",
    "sg:postcode":"41260",
    "sg:province":"Centre",
    "wof:name":"Brousse Camille",
    "wof:placetype":"venue"
},
  "geometry": {"coordinates":[1.35488,47.610371],"type":"Point"}
}