{
  "type": "Feature",
  "properties": {
    "addr:full":"29, Rue Saint Lazare, 41260 La Chauss\u00e9e Saint Victor La Chauss\u00e9e-Saint-Victor Centre 41260",
    "addr:housenumber":"29;chausse\u0301e-saint-victor",
    "addr:postcode":"41260;41260",
    "addr:street":"Rue Saint Lazare;Chausse\u0301E Saint Victor La",
    "iso:country":"FR",
    "sg:address":"29, Rue Saint Lazare, 41260 La Chauss\u00e9e Saint Victor",
    "sg:city":"La Chauss\u00e9e-Saint-Victor",
    "sg:orig_category":"Unclassifiable Establishments",
    "sg:phone":"+33 2 54 74 69 55",
    "sg:postcode":"41260",
    "sg:province":"Centre",
    "wof:name":"Brousse Camille",
    "wof:placetype":"venue"
},
  "geometry": {"coordinates":[1.35488,47.610371],"type":"Point"}
}