{
  "type": "Feature",
  "properties": {
    "addr:full":"8, Rue du Mouzon, 54520 Laxou Lorraine",
    "addr:housenumber":"8",
    "addr:postcode":"54520",
    "addr:street":"Rue Du Mouzon",
    "iso:country":"FR",
    "sg:address":"8, Rue du Mouzon, 54520 Laxou",
    "sg:orig_category":"T\u00d4LERIE DE PR\u00c9CISION, CHAUDRONNERIE FINE d\u00e9coupage et soudage au laser r\u00e9alisation d'ensembles et de",
    "sg:phone":"+33 3 83 97 20 10",
    "sg:province":"Lorraine",
    "wof:name":"Collot Technologies - Groupe Kep S.a.",
    "wof:placetype":"venue"
},
  "geometry": {"coordinates":[6.121873,48.696186],"type":"Point"}
}