{
  "type": "Feature",
  "properties": {
    "addr:full":"Les Lacs 35500 Saint Aubin des Landes Vitr\u00e9 Bretagne 35500",
    "addr:postcode":"35500;35500",
    "addr:street":"Lacs;Landes;Bretagne",
    "iso:country":"FR",
    "sg:address":"Les Lacs 35500 Saint Aubin des Landes",
    "sg:city":"Vitr\u00e9",
    "sg:orig_category":"Unclassifiable Establishments",
    "sg:phone":"+33 2 99 49 51 09",
    "sg:postcode":"35500",
    "sg:province":"Bretagne",
    "wof:name":"Cari\u00e8res Des Lacs S.a.",
    "wof:placetype":"venue"
},
  "geometry": {"coordinates":[-1.316784,48.10799],"type":"Point"}
}