{
  "type": "Feature",
  "properties": {
    "iso:country":"FR",
    "sg:address":"R Fl\u00e9teau 37110 Ch\u00e2teau Renault",
    "sg:city":"Autr\u00e8che",
    "sg:classifiers":[
        {
            "category":"Manufacturing",
            "subcategory":"Metals",
            "type":"Manufacturing & Wholesale Goods"
        }
    ],
    "sg:phone":"+33 2 47 29 52 42",
    "sg:postcode":"37110",
    "sg:province":"Centre",
    "sg:tags":[
        "-",
        "machine",
        "equipment",
        "engineering",
        "machinery",
        "mechanical"
    ],
    "wof:name":"Tauzin Sa",
    "wof:placetype":"venue"
},
  "geometry": {"coordinates":[0.891764,47.590523],"type":"Point"}
}