{
  "type": "Feature",
  "properties": {
    "addr:full":"Rue Du Senarmont 55300 St Mihiel Lorraine",
    "addr:postcode":"55300",
    "addr:street":"Rue Du Senarmont",
    "iso:country":"FR",
    "sg:address":"Rue Du Senarmont 55300 St Mihiel",
    "sg:classifiers":[
        {
            "category":"Manufacturing",
            "subcategory":"Rubber & Plastics",
            "type":"Manufacturing & Wholesale Goods"
        }
    ],
    "sg:phone":"+33 3 29 90 20 55",
    "sg:province":"Lorraine",
    "wof:name":"Ste Etudes Realis Garnit Etanc",
    "wof:placetype":"venue"
},
  "geometry": {"coordinates":[5.541056,48.891834],"type":"Point"}
}