{
  "type": "Feature",
  "properties": {
    "addr:full":"B.P. 3 Saint Laurent en Royans^^Le Village 26190 Saint Laurent en Royans Rhone-Alpes 26190",
    "addr:housenumber":"3;26190",
    "addr:postcode":"26190",
    "addr:street":"B.P.;Rhone-Alpes",
    "iso:country":"FR",
    "sg:address":"B.P. 3",
    "sg:city":"Saint Laurent en Royans^^Le Village 26190 Saint Laurent en Royans",
    "sg:orig_category":"Non-Classified Establishments",
    "sg:phone":"+33 4 75 47 70 48",
    "sg:postcode":"26190",
    "sg:province":"Rhone-Alpes",
    "wof:name":"B\u00e9rard International S.a.",
    "wof:placetype":"venue"
},
  "geometry": {"coordinates":[5.293644,45.02449],"type":"Point"}
}