{
  "type": "Feature",
  "properties": {
    "addr:full":"chemin de la Pouranque 13170 Les Pennes Mirabeau Franche Comt\u00e9",
    "addr:postcode":"13170",
    "addr:street":"Chemin De La Pouranque;Franche Comte\u0301",
    "iso:country":"FR",
    "sg:address":"chemin de la Pouranque 13170 Les Pennes Mirabeau",
    "sg:classifiers":[
        {
            "category":"Manufacturing",
            "subcategory":"Food",
            "type":"Manufacturing & Wholesale Goods"
        }
    ],
    "sg:phone":"+33 4 42 02 70 86",
    "sg:province":"Franche Comt\u00e9",
    "sg:tags":[
        "frozen"
    ],
    "wof:name":"Ste Meridionale Des Produits De La Mer Sa",
    "wof:placetype":"venue"
},
  "geometry": {"coordinates":[5.297958,43.41497],"type":"Point"}
}