{
  "type": "Feature",
  "properties": {
    "addr:full":"Impasse de la Carri\u00e8re - ZAE les Trois Ponts Fabr\u00e8gues Languedoc-Roussillon 34690",
    "addr:postcode":"34690",
    "addr:street":"Impasse De La Carrie\u0300Re Zae Les",
    "iso:country":"FR",
    "sg:address":"Impasse de la Carri\u00e8re - ZAE les Trois Ponts",
    "sg:city":"Fabr\u00e8gues",
    "sg:orig_category":"Unclassifiable Establishments",
    "sg:phone":"+33 4 67 85 61 65",
    "sg:postcode":"34690",
    "sg:province":"Languedoc-Roussillon",
    "wof:name":"Cyndi Process S.a.r.l.",
    "wof:placetype":"venue"
},
  "geometry": {"coordinates":[3.786776,43.554996],"type":"Point"}
}