{
  "type": "Feature",
  "properties": {
    "iso:country":"FR",
    "sg:address":"12 avenue de Kergroise 56100 Lorient",
    "sg:city":"Lorient",
    "sg:classifiers":[
        {
            "category":"Utilities",
            "subcategory":"Natural Gas",
            "type":"Services"
        }
    ],
    "sg:phone":"+33 2 97 37 15 99",
    "sg:postcode":"56100",
    "sg:province":"Bretagne",
    "sg:tags":[
        "plant"
    ],
    "wof:name":"Mte Le Bras Manutent Trans Ent Sa",
    "wof:placetype":"venue"
},
  "geometry": {"coordinates":[-3.361182,47.735607],"type":"Point"}
}