{
  "type": "Feature",
  "properties": {
    "iso:country":"FR",
    "sg:address":"2 Rte De Bray En Val 45460 St Aignan Des Gu\u00e9s",
    "sg:city":"Bouzy-la-For\u00eat",
    "sg:classifiers":[
        {
            "category":"Food & Beverages",
            "subcategory":"Fruits & Vegetables",
            "type":"Retail Goods"
        }
    ],
    "sg:phone":"+33 2 38 58 26 67",
    "sg:postcode":"45460",
    "sg:province":"Centre",
    "sg:tags":[
        "preserve",
        "product",
        "related"
    ],
    "wof:name":"Daniel Allaire Sa",
    "wof:placetype":"venue"
},
  "geometry": {"coordinates":[2.335187,47.833092],"type":"Point"}
}