{
  "type": "Feature",
  "properties": {
    "iso:country":"FR",
    "sg:address":"B.P. 44816",
    "sg:city":"Paris C\u00e9dex 16",
    "sg:orig_category":"Non-Classified Establishments",
    "sg:phone":"+33 1 40 69 37 00",
    "sg:postcode":"75769",
    "sg:province":"Ile de France",
    "wof:name":"A.c.f.c.i. - Assembl\u00e9e Des Chambres Fran\u00e7aises De Commerce Et D'industrie",
    "wof:placetype":"venue"
},
  "geometry": {"coordinates":[2.26286,48.857079],"type":"Point"}
}