{
  "type": "Feature",
  "properties": {
    "addr:full":"Rte de Grasse Antibes Rhone-Alpes 06600",
    "addr:postcode":"06600",
    "addr:street":"Rte De Grasse;Rhone-Alpes",
    "iso:country":"FR",
    "sg:address":"Rte de Grasse",
    "sg:city":"Antibes",
    "sg:orig_category":"Unclassifiable Establishments",
    "sg:phone":"+33 4 93 65 40 09",
    "sg:postcode":"06600",
    "sg:province":"Rhone-Alpes",
    "wof:name":"C.n.i.m. S.a. - Constructions Industrielles M\u00e9diterran\u00e9e",
    "wof:placetype":"venue"
},
  "geometry": {"coordinates":[7.085145,43.600399],"type":"Point"}
}