{
  "type": "Feature",
  "properties": {
    "iso:country":"FR",
    "sg:address":"Bd Du Mal Foch 79303 Bressuire Cedex",
    "sg:city":"Bressuire",
    "sg:classifiers":[
        {
            "category":"Food & Beverages",
            "subcategory":"Meat & Fish",
            "type":"Retail Goods"
        }
    ],
    "sg:phone":"+33 5 49 74 03 77",
    "sg:postcode":"79300",
    "sg:province":"Poitou-Charentes",
    "sg:tags":[
        "preserve",
        "cooked",
        "product",
        "related"
    ],
    "wof:name":"Union Pca",
    "wof:placetype":"venue"
},
  "geometry": {"coordinates":[-0.492539,46.840065],"type":"Point"}
}