{
  "type": "Feature",
  "properties": {
    "iso:country":"FR",
    "sg:address":"12 Boulevard Carnot",
    "sg:city":"Dijon",
    "sg:classifiers":[
        {
            "category":"Banks & Credit Unions",
            "subcategory":"Financial Services",
            "type":"Services"
        }
    ],
    "sg:phone":"+33 3 80 77 52 00",
    "sg:postcode":"21000",
    "sg:province":"Bourgogne",
    "sg:tags":[
        "banking",
        "finance",
        "insurance"
    ],
    "wof:name":"Neuilly Contentieux",
    "wof:placetype":"venue"
},
  "geometry": {"coordinates":[5.046788,47.318165],"type":"Point"}
}