{
  "type": "Feature",
  "properties": {
    "iso:country":"FR",
    "sg:address":"65, Rte de Grenoble, 38690 Ch\u00e2bons",
    "sg:orig_category":"Unclassifiable Establishments",
    "sg:phone":"+33 4 76 65 00 92",
    "sg:province":"Rhone-Alpes",
    "wof:name":"Mondial Elite France S.a.",
    "wof:placetype":"venue"
},
  "geometry": {"coordinates":[5.390744,45.395943],"type":"Point"}
}