{
  "type": "Feature",
  "properties": {
    "addr:full":"8, Rue d'Ohlungen, 67590 Schweighouse sur Moder Ohlungen Alsace 67590",
    "addr:housenumber":"8",
    "addr:postcode":"67590;67590",
    "addr:street":"Rue D'Ohlungen",
    "iso:country":"FR",
    "sg:address":"8, Rue d'Ohlungen, 67590 Schweighouse sur Moder",
    "sg:city":"Ohlungen",
    "sg:orig_category":"Non-Classified Establishments",
    "sg:phone":"+33 3 88 72 76 62",
    "sg:postcode":"67590",
    "sg:province":"Alsace",
    "wof:name":"Koell Et Compagnie S.a.r.l.",
    "wof:placetype":"venue"
},
  "geometry": {"coordinates":[7.736732,48.819611],"type":"Point"}
}