{
  "type": "Feature",
  "properties": {
    "addr:full":"949, Rue Denis Papin, 73290 La Motte Servolex Rhone-Alpes",
    "addr:housenumber":"949",
    "addr:postcode":"73290",
    "addr:street":"Rue Denis Papin",
    "iso:country":"FR",
    "sg:address":"949, Rue Denis Papin, 73290 La Motte Servolex",
    "sg:orig_category":"Unclassifiable Establishments",
    "sg:phone":"+33 4 79 25 10 23",
    "sg:province":"Rhone-Alpes",
    "wof:name":"Graphique Productions S.a.r.l.",
    "wof:placetype":"venue"
},
  "geometry": {"coordinates":[5.878773,45.602402],"type":"Point"}
}