{
  "type": "Feature",
  "properties": {
    "addr:full":"145 Rue Yves Le Coz 78000 Versailles Ile de France 78000",
    "addr:housenumber":"145",
    "addr:postcode":"78000;78000",
    "addr:street":"Rue Yves Le Coz",
    "iso:country":"FR",
    "sg:address":"145 Rue Yves Le Coz 78000 Versailles",
    "sg:classifiers":[
        {
            "category":"Utilities",
            "type":"Services"
        }
    ],
    "sg:phone":"+33 1 39 24 39 00",
    "sg:postcode":"78000",
    "sg:province":"Ile de France",
    "sg:tags":[
        "raw",
        "energy",
        "material"
    ],
    "wof:name":"Ste Eaux Versailles-st Cloud",
    "wof:placetype":"venue"
},
  "geometry": {"coordinates":[2.150475,48.791668],"type":"Point"}
}