{
  "type": "Feature",
  "properties": {
    "addr:full":"Zi St Eloi 58000 Nevers Nevers Bourgogne 58000",
    "addr:postcode":"58000;58000",
    "addr:street":"Zi St",
    "iso:country":"FR",
    "sg:address":"Zi St Eloi 58000 Nevers",
    "sg:city":"Nevers",
    "sg:classifiers":[
        {
            "category":"Manufacturing",
            "subcategory":"Rubber & Plastics",
            "type":"Manufacturing & Wholesale Goods"
        }
    ],
    "sg:phone":"+33 3 86 59 20 60",
    "sg:postcode":"58000",
    "sg:province":"Bourgogne",
    "wof:name":"Frans Bonhomme",
    "wof:placetype":"venue"
},
  "geometry": {"coordinates":[3.15725,46.988964],"type":"Point"}
}