{
  "type": "Feature",
  "properties": {
    "iso:country":"FR",
    "sg:address":"B.P. 8, 08200 Balan^^7, Rue Hanrat, 08200 Balan",
    "sg:orig_category":"Gaines textiles d'emballage Tapis",
    "sg:phone":"+33 3 24 27 40 06",
    "sg:postcode":"08200",
    "sg:province":"Champagne",
    "wof:name":"Carpet' Syst\u00e8me S.a.r.l.",
    "wof:placetype":"venue"
},
  "geometry": {"coordinates":[4.93936,49.709202],"type":"Point"}
}