{
  "type": "Feature",
  "properties": {
    "addr:full":"958 Chem Pierre Drevet 69140 Rillieux La Pape Rhone-Alpes 69140",
    "addr:housenumber":"958",
    "addr:postcode":"69140;69140",
    "addr:street":"Chem Pierre Drevet",
    "iso:country":"FR",
    "sg:address":"958 Chem Pierre Drevet 69140 Rillieux La Pape",
    "sg:classifiers":[
        {
            "category":"Utilities",
            "type":"Services"
        }
    ],
    "sg:phone":"+33 4 78 98 77 77",
    "sg:postcode":"69140",
    "sg:province":"Rhone-Alpes",
    "sg:tags":[
        "raw",
        "energy",
        "material"
    ],
    "wof:name":"Suez Lyonnaise Des Eaux",
    "wof:placetype":"venue"
},
  "geometry": {"coordinates":[4.872375,45.807144],"type":"Point"}
}