{
  "type": "Feature",
  "properties": {
    "addr:full":"31 Rue Cam\u00e9linat 59129 Avesnes Les Aubert Nord Pas-de-Calais",
    "addr:housenumber":"31",
    "addr:postcode":"59129",
    "addr:street":"Rue Came\u0301Linat",
    "iso:country":"FR",
    "sg:address":"31 Rue Cam\u00e9linat 59129 Avesnes Les Aubert",
    "sg:classifiers":[
        {
            "category":"Autos & Motor Vehicles",
            "subcategory":"Automobile Sales",
            "type":"Retail Goods"
        }
    ],
    "sg:phone":"+33 3 27 37 14 39",
    "sg:province":"Nord Pas-de-Calais",
    "sg:tags":[
        "equipment",
        "transport"
    ],
    "wof:name":"Coupez Joel Sarl",
    "wof:placetype":"venue"
},
  "geometry": {"coordinates":[3.380755,50.196636],"type":"Point"}
}