{
  "type": "Feature",
  "properties": {
    "addr:full":"ZA Saint Manvieu Bocage Basse Normandie 14380",
    "addr:postcode":"14380",
    "addr:street":"Za Saint Manvieu Bocage Basse",
    "iso:country":"FR",
    "sg:address":"ZA",
    "sg:city":"Saint Manvieu Bocage",
    "sg:orig_category":"Non-Classified Establishments",
    "sg:phone":"+33 2 31 66 23 66",
    "sg:postcode":"14380",
    "sg:province":"Basse Normandie",
    "wof:name":"B.s.b. S.a.r.l.",
    "wof:placetype":"venue"
},
  "geometry": {"coordinates":[-1.005444,48.79351],"type":"Point"}
}