{
  "type": "Feature",
  "properties": {
    "iso:country":"FR",
    "sg:address":"42, Bd Charles de Gaulle - ZI, 42120 Le Coteau",
    "sg:orig_category":"Unclassifiable Establishments",
    "sg:phone":"+33 4 77 68 13 77",
    "sg:province":"Rhone-Alpes",
    "wof:name":"Maubero Brod 2000 S.a.r.l.",
    "wof:placetype":"venue"
},
  "geometry": {"coordinates":[4.096484,46.012802],"type":"Point"}
}