{
  "type": "Feature",
  "properties": {
    "addr:full":"34, Bd de l'Europe - ZI des Estroublans, 13127 Vitrolles Midi Pyr\u00e9n\u00e9es",
    "addr:housenumber":"34",
    "addr:postcode":"13127",
    "addr:street":"Bd De L'Europe Zi Des Estroublans",
    "iso:country":"FR",
    "sg:address":"34, Bd de l'Europe - ZI des Estroublans, 13127 Vitrolles",
    "sg:orig_category":"Non-Classified Establishments",
    "sg:phone":"+33 4 42 79 44 00",
    "sg:province":"Midi Pyr\u00e9n\u00e9es",
    "wof:name":"Cabus Et Raulot S.a.",
    "wof:placetype":"venue"
},
  "geometry": {"coordinates":[5.292057,43.422314],"type":"Point"}
}