{
  "type": "Feature",
  "properties": {
    "iso:country":"FR",
    "sg:address":"ZA le Ridor",
    "sg:city":"Pl\u00e9met",
    "sg:orig_category":"Unclassifiable Establishments",
    "sg:phone":"+33 2 96 66 32 00",
    "sg:postcode":"22210",
    "sg:province":"Bretagne",
    "wof:name":"Vapran S.a. - Valorisation Prot\u00e9ines Animales",
    "wof:placetype":"venue"
},
  "geometry": {"coordinates":[-2.594211,48.177696],"type":"Point"}
}