{
  "type": "Feature",
  "properties": {
    "iso:country":"FR",
    "sg:address":"Zi La Chamaree Zi La Chamaree 79300 St Aubin Du Plain",
    "sg:classifiers":[
        {
            "category":"Farming",
            "subcategory":"Livestock Farm",
            "type":"Manufacturing & Wholesale Goods"
        }
    ],
    "sg:phone":"+33 5 49 80 29 50",
    "sg:postcode":"79300",
    "sg:province":"Poitou-Charentes",
    "sg:tags":[
        "breeding",
        "agriculture",
        "animal"
    ],
    "wof:name":"Sarl Equip'home",
    "wof:placetype":"venue"
},
  "geometry": {"coordinates":[-0.4767,46.923706],"type":"Point"}
}