{
  "type": "Feature",
  "properties": {
    "iso:country":"FR",
    "sg:address":"6 All Du Val Du Moulin 93240 Stains",
    "sg:classifiers":[
        {
            "category":"Manufacturing",
            "subcategory":"Metals",
            "type":"Manufacturing & Wholesale Goods"
        }
    ],
    "sg:phone":"+33 1 48 26 62 12",
    "sg:postcode":"93240",
    "sg:province":"Ile de France",
    "sg:tags":[
        "metallurgy",
        "steel",
        "metalworking"
    ],
    "wof:name":"Pouget Sarl",
    "wof:placetype":"venue"
},
  "geometry": {"coordinates":[2.391109,48.95422],"type":"Point"}
}