{
  "type": "Feature",
  "properties": {
    "iso:country":"FR",
    "sg:address":"51 boulevard Voltaire 92600 Asni\u00e8res sur Seine",
    "sg:classifiers":[
        {
            "category":"Military Area",
            "subcategory":"Air Force Base",
            "type":"Public Place"
        }
    ],
    "sg:phone":"+33 1 46 88 03 40",
    "sg:province":"Ile de France",
    "sg:tags":[
        "system",
        "integration"
    ],
    "wof:name":"Ilex S.a.r.l.",
    "wof:placetype":"venue"
},
  "geometry": {"coordinates":[2.294649,48.914082],"type":"Point"}
}