{
  "type": "Feature",
  "properties": {
    "addr:full":"945, Av. Pic de Bertagne - Zone de la Plaine de Jouques - 3, 13420 G\u00e9menos Provence-Alpes-C\u00f4te d'Azur",
    "addr:housenumber":"3",
    "addr:postcode":"13420",
    "addr:street":"945 Av. Pic De Bertagne Zone De La Plaine De Jouques",
    "iso:country":"FR",
    "sg:address":"945, Av. Pic de Bertagne - Zone de la Plaine de Jouques - 3, 13420 G\u00e9menos",
    "sg:orig_category":"Unclassifiable Establishments",
    "sg:phone":"+33 4 42 32 05 21",
    "sg:province":"Provence-Alpes-C\u00f4te d'Azur",
    "wof:name":"Cejip Entretien E.u.r.l.",
    "wof:placetype":"venue"
},
  "geometry": {"coordinates":[5.627487,43.294132],"type":"Point"}
}