{
  "type": "Feature",
  "properties": {
    "iso:country":"FR",
    "sg:address":"18 Av Des Jardins 66240 St Est\u00e8ve",
    "sg:classifiers":[
        {
            "category":"Farming",
            "subcategory":"Crops",
            "type":"Manufacturing & Wholesale Goods"
        }
    ],
    "sg:phone":"+33 4 68 92 06 12",
    "sg:postcode":"66240",
    "sg:province":"Languedoc-Roussillon",
    "sg:tags":[
        "vegetable",
        "fruit",
        "agriculture",
        "livestock"
    ],
    "wof:name":"Rodriguez Sa",
    "wof:placetype":"venue"
},
  "geometry": {"coordinates":[2.846085,42.706486],"type":"Point"}
}