{
  "type": "Feature",
  "properties": {
    "addr:full":"8, Place Th\u00e9odore Paqu\u00e9, 57500 Saint Avold Lorraine",
    "addr:housenumber":"8",
    "addr:postcode":"57500",
    "addr:street":"Place The\u0301Odore Paque\u0301;Avold",
    "iso:country":"FR",
    "sg:address":"8, Place Th\u00e9odore Paqu\u00e9, 57500 Saint Avold",
    "sg:orig_category":"Unclassifiable Establishments",
    "sg:phone":"+33 3 87 29 93 93",
    "sg:province":"Lorraine",
    "wof:name":"Lorraine Int\u00e9rim S.a.r.l.",
    "wof:placetype":"venue"
},
  "geometry": {"coordinates":[6.701294,49.1036],"type":"Point"}
}