{
  "type": "Feature",
  "properties": {
    "addr:full":"40 Rue Verlyck 59190 Hazebrouck Nord Pas-de-Calais 59190",
    "addr:housenumber":"40",
    "addr:postcode":"59190;59190",
    "addr:street":"Rue Verlyck",
    "iso:country":"FR",
    "sg:address":"40 Rue Verlyck 59190 Hazebrouck",
    "sg:classifiers":[
        {
            "category":"Shopping",
            "subcategory":"Clothing, Apparel, & Fashions",
            "type":"Retail Goods"
        }
    ],
    "sg:phone":"+33 3 28 43 13 41",
    "sg:postcode":"59190",
    "sg:province":"Nord Pas-de-Calais",
    "sg:tags":[
        "textile",
        "clothing",
        "clothes"
    ],
    "wof:name":"Sogefac Sarl",
    "wof:placetype":"venue"
},
  "geometry": {"coordinates":[2.537987,50.731289],"type":"Point"}
}