{
  "type": "Feature",
  "properties": {
    "addr:full":"78 Rue Du Temple 75003 Paris Ile de France 75003",
    "addr:housenumber":"78",
    "addr:postcode":"75003;75003",
    "addr:street":"Rue Du Temple",
    "iso:country":"FR",
    "sg:address":"78 Rue Du Temple 75003 Paris",
    "sg:classifiers":[
        {
            "category":"Manufacturing",
            "subcategory":"Textiles",
            "type":"Manufacturing & Wholesale Goods"
        }
    ],
    "sg:phone":"+33 1 42 78 01 00",
    "sg:postcode":"75003",
    "sg:province":"Ile de France",
    "sg:tags":[
        "clothing",
        "accessory"
    ],
    "wof:name":"Paris Boutons",
    "wof:placetype":"venue"
},
  "geometry": {"coordinates":[2.356929,48.861824],"type":"Point"}
}