{
  "type": "Feature",
  "properties": {
    "addr:full":"B.P. 12, 70300 Froideconche^^ZA, 70300 Froideconche Franche Comt\u00e9",
    "addr:postcode":"70300;70300",
    "addr:street":"B.P. 12;Franche Comte\u0301",
    "iso:country":"FR",
    "sg:address":"B.P. 12, 70300 Froideconche^^ZA, 70300 Froideconche",
    "sg:orig_category":"Non-Classified Establishments",
    "sg:phone":"+33 3 84 40 12 04",
    "sg:province":"Franche Comt\u00e9",
    "wof:name":"Poupinet S.a.",
    "wof:placetype":"venue"
},
  "geometry": {"coordinates":[6.3795,47.819172],"type":"Point"}
}