{
  "type": "Feature",
  "properties": {
    "addr:full":"Chem Du Pas De La Paille 66000 Perpignan Languedoc-Roussillon 66000",
    "addr:postcode":"66000;66000",
    "addr:street":"Chem;La Paille",
    "iso:country":"FR",
    "sg:address":"Chem Du Pas De La Paille 66000 Perpignan",
    "sg:classifiers":[
        {
            "category":"Farming",
            "subcategory":"Crops",
            "type":"Manufacturing & Wholesale Goods"
        }
    ],
    "sg:phone":"+33 4 68 85 55 55",
    "sg:postcode":"66000",
    "sg:province":"Languedoc-Roussillon",
    "sg:tags":[
        "vegetable",
        "fruit",
        "agriculture",
        "livestock"
    ],
    "wof:name":"Etablissements Galup Sa",
    "wof:placetype":"venue"
},
  "geometry": {"coordinates":[2.865522,42.68631],"type":"Point"}
}