{
  "type": "Feature",
  "properties": {
    "iso:country":"FR",
    "sg:address":"40 rue Victor Hugo; Lyon",
    "sg:classifiers":[
        {
            "category":"Banks & Credit Unions",
            "subcategory":"Bank",
            "type":"Services"
        }
    ],
    "sg:phone":"+33 3378378827",
    "sg:province":"Rhone-Alpes",
    "wof:name":"Cr\u00e9dit Agricole Du Sud Est",
    "wof:placetype":"venue"
},
  "geometry": {"coordinates":[-90.541031,34.219009],"type":"Point"}
}