{
  "type": "Feature",
  "properties": {
    "addr:full":"366 Rue Chauverie 53100 Mayenne Pays de Loire 53100",
    "addr:housenumber":"366",
    "addr:postcode":"53100 mayenne;53100",
    "addr:street":"Rue Chauverie",
    "iso:country":"FR",
    "sg:address":"366 Rue Chauverie 53100 Mayenne",
    "sg:classifiers":[
        {
            "category":"Professional",
            "subcategory":"Engineering",
            "type":"Services"
        }
    ],
    "sg:phone":"+33 2 43 04 18 34",
    "sg:postcode":"53100",
    "sg:province":"Pays de Loire",
    "sg:tags":[
        "machine",
        "-",
        "mechanical"
    ],
    "wof:name":"Jean Sarl",
    "wof:placetype":"venue"
},
  "geometry": {"coordinates":[-0.6066,48.288189],"type":"Point"}
}