{
  "type": "Feature",
  "properties": {
    "addr:full":"Z.I. les Pr\u00e9s d'en Bas Chailley Bourgogne 89770",
    "addr:postcode":"89770",
    "addr:street":"Z.I. Les Pre\u0301S D'En Bas",
    "iso:country":"FR",
    "sg:address":"Z.I. les Pr\u00e9s d'en Bas",
    "sg:city":"Chailley",
    "sg:orig_category":"Unclassifiable Establishments",
    "sg:phone":"+33 3 86 56 23 52",
    "sg:postcode":"89770",
    "sg:province":"Bourgogne",
    "wof:name":"T\u00f4lerie D'hothe S.a.r.l.",
    "wof:placetype":"venue"
},
  "geometry": {"coordinates":[3.70176,48.083469],"type":"Point"}
}