{
  "type": "Feature",
  "properties": {
    "addr:full":"175, Av. de Vichy, 03200 Abrest Vichy Auvergne 03200",
    "addr:housenumber":"175",
    "addr:postcode":"03200;03200",
    "addr:street":"Av. De Vichy",
    "iso:country":"FR",
    "sg:address":"175, Av. de Vichy, 03200 Abrest",
    "sg:city":"Vichy",
    "sg:orig_category":"Unclassifiable Establishments",
    "sg:phone":"+33 4 70 98 49 41",
    "sg:postcode":"03200",
    "sg:province":"Auvergne",
    "wof:name":"Vernay Vichy S.a.",
    "wof:placetype":"venue"
},
  "geometry": {"coordinates":[3.442599,46.110733],"type":"Point"}
}