{
  "type": "Feature",
  "properties": {
    "addr:full":"34 Avenue Pdt Salvador Allende 93100 Montreuil Ile de France 93100",
    "addr:housenumber":"34",
    "addr:postcode":"93100;93100",
    "addr:street":"Avenue Pdt Salvador Allende",
    "iso:country":"FR",
    "sg:address":"34 Avenue Pdt Salvador Allende 93100 Montreuil",
    "sg:classifiers":[
        {
            "category":"Shopping",
            "subcategory":"Clothing, Apparel, & Fashions",
            "type":"Retail Goods"
        }
    ],
    "sg:phone":"+33 1 48 51 34 35",
    "sg:postcode":"93100",
    "sg:province":"Ile de France",
    "sg:tags":[
        "textile",
        "clothing",
        "clothes"
    ],
    "wof:name":"Diana Mode",
    "wof:placetype":"venue"
},
  "geometry": {"coordinates":[2.457522,48.869957],"type":"Point"}
}