{
  "type": "Feature",
  "properties": {
    "iso:country":"FR",
    "sg:address":"198 Av Joliot Curie BP N_MBOX 83087 Toulon",
    "sg:classifiers":[
        {
            "category":"Manufacturing",
            "subcategory":"Aerospace",
            "type":"Manufacturing & Wholesale Goods"
        }
    ],
    "sg:phone":"+33 4 94 08 61 59",
    "sg:province":"Bourgogne",
    "sg:tags":[
        "equipment",
        "aeronautic",
        "transport",
        "vehicle"
    ],
    "wof:name":"Ect Industries Sa",
    "wof:placetype":"venue"
},
  "geometry": {"coordinates":[5.9052,43.13773],"type":"Point"}
}