{
  "type": "Feature",
  "properties": {
    "addr:full":"4 R Dieudonn\u00e9 Costes 31700 Blagnac Midi Pyr\u00e9n\u00e9es 31700",
    "addr:housenumber":"4",
    "addr:postcode":"31700;31700",
    "addr:street":"R Dieudonne\u0301 Costes",
    "iso:country":"FR",
    "sg:address":"4 R Dieudonn\u00e9 Costes 31700 Blagnac",
    "sg:classifiers":[
        {
            "category":"Professional",
            "subcategory":"Engineering",
            "type":"Services"
        }
    ],
    "sg:phone":"+33 5 61 71 93 93",
    "sg:postcode":"31700",
    "sg:province":"Midi Pyr\u00e9n\u00e9es",
    "sg:tags":[
        "machine",
        "-",
        "mechanical"
    ],
    "wof:name":"Relais Blagnac",
    "wof:placetype":"venue"
},
  "geometry": {"coordinates":[1.379896,43.631298],"type":"Point"}
}