{
  "type": "Feature",
  "properties": {
    "iso:country":"FR",
    "sg:address":"B.P. 5, 07250 Le Pouzin^^16, Rue des 14 Martyrs, 07250 Le Pouzin",
    "sg:orig_category":"Non-Classified Establishments",
    "sg:phone":"+33 4 75 85 90 54",
    "sg:province":"Rhone-Alpes",
    "wof:name":"Les Jardins De Provence S.a.r.l.",
    "wof:placetype":"venue"
},
  "geometry": {"coordinates":[4.74692,44.757591],"type":"Point"}
}