{
  "type": "Feature",
  "properties": {
    "iso:country":"FR",
    "sg:address":"place Bernard Moitessier 17000 La Rochelle",
    "sg:classifiers":[
        {
            "category":"Wholesale",
            "subcategory":"Durable Goods & Equipment",
            "type":"Manufacturing & Wholesale Goods"
        }
    ],
    "sg:phone":"+33 5 46 50 50 46",
    "sg:province":"Poitou-Charentes",
    "sg:tags":[
        "ship"
    ],
    "wof:name":"Lewmar Ltd Sarl",
    "wof:placetype":"venue"
},
  "geometry": {"coordinates":[-1.151337,46.150059],"type":"Point"}
}