{
  "type": "Feature",
  "properties": {
    "iso:country":"FR",
    "sg:address":"B.P. 142",
    "sg:city":"Valence C\u00e9dex 09",
    "sg:orig_category":"Non-Classified Establishments",
    "sg:phone":"+33 4 75 82 64 00",
    "sg:postcode":"26905",
    "sg:province":"Rhone-Alpes",
    "wof:name":"Eurovia Rh\u00f4ne Alpes Auvergne S.n.c.",
    "wof:placetype":"venue"
},
  "geometry": {"coordinates":[4.89139,44.93045],"type":"Point"}
}