{
  "type": "Feature",
  "properties": {
    "addr:full":"Bd Pasteur Mauriac Auvergne 15200",
    "addr:postcode":"15200",
    "addr:street":"Bd Pasteur Mauriac",
    "iso:country":"FR",
    "sg:address":"Bd Pasteur",
    "sg:city":"Mauriac",
    "sg:orig_category":"Unclassifiable Establishments",
    "sg:phone":"+33 4 71 67 30 20",
    "sg:postcode":"15200",
    "sg:province":"Auvergne",
    "wof:name":"Laiterie De Mauriac S.a.",
    "wof:placetype":"venue"
},
  "geometry": {"coordinates":[2.34629,45.221806],"type":"Point"}
}