{
  "type": "Feature",
  "properties": {
    "iso:country":"FR",
    "sg:address":"B.P. 29, 54181 Heillecourt C\u00e9dex^^5, Av. des Erables - ZI Ouest, 54180 Heillecourt",
    "sg:orig_category":"Non-Classified Establishments",
    "sg:phone":"+33 3 83 15 14 18",
    "sg:province":"Lorraine",
    "wof:name":"Gu\u00e9rineau S.n.c.",
    "wof:placetype":"venue"
},
  "geometry": {"coordinates":[6.194192,48.653137],"type":"Point"}
}