{
  "type": "Feature",
  "properties": {
    "addr:full":"Av Du G\u00e9n\u00e9ral De Gaulle 34700 Lod\u00e8ve Languedoc-Roussillon 34700",
    "addr:postcode":"34700;34700",
    "addr:street":"Av Du Ge\u0301Ne\u0301Ral De Gaulle",
    "iso:country":"FR",
    "sg:address":"Av Du G\u00e9n\u00e9ral De Gaulle 34700 Lod\u00e8ve",
    "sg:classifiers":[
        {
            "category":"Shopping",
            "subcategory":"Computers & Home Electronics",
            "type":"Retail Goods"
        }
    ],
    "sg:phone":"+33 4 67 44 32 85",
    "sg:postcode":"34700",
    "sg:province":"Languedoc-Roussillon",
    "sg:tags":[
        "equipment",
        "electrical",
        "component",
        "electric",
        "electronic"
    ],
    "wof:name":"Gicep",
    "wof:placetype":"venue"
},
  "geometry": {"coordinates":[3.323037,43.725086],"type":"Point"}
}