{
  "type": "Feature",
  "properties": {
    "addr:full":"96 ave du Mar\u00e9chal Gallieni; Bondy; 93140 Ile de France 93140",
    "addr:postcode":"93140 ile;france 93140",
    "addr:street":"96 Ave Du Mare\u0301Chal Gallieni",
    "iso:country":"FR",
    "sg:address":"96 ave du Mar\u00e9chal Gallieni; Bondy; 93140",
    "sg:classifiers":[
        {
            "category":"Banks & Credit Unions",
            "subcategory":"Bank",
            "type":"Services"
        }
    ],
    "sg:phone":"+33 18470129",
    "sg:postcode":"93140",
    "sg:province":"Ile de France",
    "wof:name":"Banque Nationale De Paris",
    "wof:placetype":"venue"
},
  "geometry": {"coordinates":[2.479933,48.905556],"type":"Point"}
}