{
  "type": "Feature",
  "properties": {
    "addr:full":"1 pl des Degres; Paris; 92059 Pays de Loire",
    "addr:housenumber":"1",
    "addr:postcode":"92059",
    "addr:street":"Pl Des Degres Paris",
    "iso:country":"FR",
    "sg:address":"1 pl des Degres; Paris; 92059",
    "sg:classifiers":[
        {
            "category":"Banks & Credit Unions",
            "subcategory":"Bank",
            "type":"Services"
        }
    ],
    "sg:phone":"+33 1 49 07 50 50",
    "sg:province":"Pays de Loire",
    "wof:name":"Banque Worms Sa",
    "wof:placetype":"venue"
},
  "geometry": {"coordinates":[2.350761,48.869419],"type":"Point"}
}