{
  "type": "Feature",
  "properties": {
    "iso:country":"FR",
    "sg:address":"B.P. 4, 01100 Arbent C\u00e9dex^^2, Rue de l' Industrie - ZI La Tuilerie, 01100 Arbent",
    "sg:orig_category":"Non-Classified Establishments",
    "sg:phone":"+33 4 74 77 35 32",
    "sg:postcode":"01100",
    "sg:province":"Rhone-Alpes",
    "wof:name":"Electricit\u00e9 G\u00e9n\u00e9rale Duraffourg S.a.",
    "wof:placetype":"venue"
},
  "geometry": {"coordinates":[5.666596,46.273159],"type":"Point"}
}