{
  "type": "Feature",
  "properties": {
    "addr:full":"16 Corv\u00e9e Du Moulin 57420 Cuvry Lorraine 57420",
    "addr:housenumber":"16",
    "addr:postcode":"57420;57420",
    "addr:street":"Corve\u0301E Du Moulin",
    "iso:country":"FR",
    "sg:address":"16 Corv\u00e9e Du Moulin 57420 Cuvry",
    "sg:classifiers":[
        {
            "category":"Building & Trades",
            "subcategory":"Construction",
            "type":"Services"
        }
    ],
    "sg:phone":"+33 3 87 65 85 00",
    "sg:postcode":"57420",
    "sg:province":"Lorraine",
    "sg:tags":[
        "work",
        "public"
    ],
    "wof:name":"Les Travaux Publics De L'est-ltpe",
    "wof:placetype":"venue"
},
  "geometry": {"coordinates":[6.162705,49.045609],"type":"Point"}
}