{
  "type": "Feature",
  "properties": {
    "addr:full":"4 Parc Royal 75003 Paris Ile de France 75003",
    "addr:housenumber":"4",
    "addr:postcode":"75003;75003",
    "addr:street":"Parc Royal",
    "iso:country":"FR",
    "sg:address":"4",
    "sg:city":"Parc Royal 75003 Paris",
    "sg:classifiers":[
        {
            "category":"Building & Trades",
            "subcategory":"Electrical",
            "type":"Services"
        }
    ],
    "sg:phone":"+33 1 42 72 21 34",
    "sg:postcode":"75003",
    "sg:province":"Ile de France",
    "sg:tags":[
        "electronic",
        "lighting",
        "equipment"
    ],
    "wof:name":"Delisle Luminaires",
    "wof:placetype":"venue"
},
  "geometry": {"coordinates":[2.364079,48.858379],"type":"Point"}
}