{
  "type": "Feature",
  "properties": {
    "addr:full":"1, Av de l'Atlantique - ZAC de Courtaboeuf - Les Conqu\u00e9rants, 91940 Les Ulis Ile de France",
    "addr:postcode":"91940",
    "addr:street":"Av De L'Atlantique Zac De Courtaboeuf Les Conque\u0301Rants",
    "iso:country":"FR",
    "sg:address":"1, Av de l'Atlantique - ZAC de Courtaboeuf - Les Conqu\u00e9rants, 91940 Les Ulis",
    "sg:orig_category":"Unclassifiable Establishments",
    "sg:phone":"+33 1 60 92 36 70",
    "sg:province":"Ile de France",
    "wof:name":"Microware Systems France S.a.r.l.",
    "wof:placetype":"venue"
},
  "geometry": {"coordinates":[2.19902,48.680809],"type":"Point"}
}