{
  "type": "Feature",
  "properties": {
    "addr:full":"4, Rue Joseph Serlin, 69282 Lyon C\u00e9dex 1 Rhone-Alpes",
    "addr:housenumber":"4;1",
    "addr:postcode":"69282",
    "addr:street":"Rue Joseph Serlin;Ce\u0301Dex",
    "iso:country":"FR",
    "sg:address":"4, Rue Joseph Serlin, 69282 Lyon C\u00e9dex 1",
    "sg:orig_category":"Non-Classified Establishments",
    "sg:phone":"+33 4 72 98 04 04",
    "sg:province":"Rhone-Alpes",
    "wof:name":"Coindre Steiner S.a.",
    "wof:placetype":"venue"
},
  "geometry": {"coordinates":[4.83625,45.767433],"type":"Point"}
}