{
  "type": "Feature",
  "properties": {
    "addr:full":"12, Rue Rossignol Dubost, 92230 Gennevilliers Ile de France",
    "addr:housenumber":"12",
    "addr:postcode":"92230;ile",
    "addr:street":"Rue Rossignol Dubost",
    "iso:country":"FR",
    "sg:address":"12, Rue Rossignol Dubost, 92230 Gennevilliers",
    "sg:orig_category":"Unclassifiable Establishments",
    "sg:phone":"+33 1 40 80 03 59",
    "sg:province":"Ile de France",
    "wof:name":"Zaphir S.a.",
    "wof:placetype":"venue"
},
  "geometry": {"coordinates":[2.308247,48.918999],"type":"Point"}
}