{
  "type": "Feature",
  "properties": {
    "addr:full":"B.P. 70537, 57205 Sarreguemines C\u00e9dex^^1, Rue Ren\u00e9 Fran\u00e7ois Jolly - Parc Industriel Sud - Z.I. Neuwa Languedoc-Roussillon",
    "addr:postcode":"57205",
    "addr:street":"Rue Rene\u0301 Franc\u0327Ois Jolly;Neuwa",
    "iso:country":"FR",
    "sg:address":"B.P. 70537, 57205 Sarreguemines C\u00e9dex^^1, Rue Ren\u00e9 Fran\u00e7ois Jolly - Parc Industriel Sud - Z.I. Neuwa",
    "sg:orig_category":"Broyage, Installations de Broyeurs Concasseurs Cribles D\u00e9poussi\u00e9rage, Installations de Filtres de d\u00e9",
    "sg:phone":"+33 3 87 98 73 73",
    "sg:province":"Languedoc-Roussillon",
    "wof:name":"Krupp Hazemag S.a.",
    "wof:placetype":"venue"
},
  "geometry": {"coordinates":[7.07192,49.113911],"type":"Point"}
}