{
  "type": "Feature",
  "properties": {
    "addr:full":"57, Rue de Verdun, 51200 Epernay Champagne",
    "addr:housenumber":"57",
    "addr:postcode":"51200",
    "addr:street":"Rue De Verdun",
    "iso:country":"FR",
    "sg:address":"57, Rue de Verdun, 51200 Epernay",
    "sg:orig_category":"VINS DE CHAMPAGNE",
    "sg:phone":"+33 3 26 51 19 19",
    "sg:province":"Champagne",
    "wof:name":"Champagne De Castellane S.a.",
    "wof:placetype":"venue"
},
  "geometry": {"coordinates":[3.969409,49.042236],"type":"Point"}
}