{
  "type": "Feature",
  "properties": {
    "iso:country":"FR",
    "sg:address":"B.P. 138, 69125 Lyon C\u00e9dex^^A\u00e9roport Saint Exup\u00e9ry, 69124 Colombier Saugnieu",
    "sg:orig_category":"Non-Classified Establishments",
    "sg:phone":"+33 4 72 23 77 77",
    "sg:province":"Rhone-Alpes",
    "wof:name":"A\u00e9rolyon S.a.",
    "wof:placetype":"venue"
},
  "geometry": {"coordinates":[5.111505,45.712326],"type":"Point"}
}