{
  "type": "Feature",
  "properties": {
    "iso:country":"FR",
    "sg:address":"B.P. 117, 61004 Alen\u00e7on C\u00e9dex^^107, Av. de Basingstoke, 61000 Alen\u00e7on",
    "sg:city":"Alen\u00e7on",
    "sg:orig_category":"Non-Classified Establishments",
    "sg:phone":"+33 2 32 95 89 10",
    "sg:postcode":"61000",
    "sg:province":"Basse Normandie",
    "wof:name":"Loxam S.a.",
    "wof:placetype":"venue"
},
  "geometry": {"coordinates":[0.083175,48.430626],"type":"Point"}
}