{
  "type": "Feature",
  "properties": {
    "addr:full":"Chem Du Closot 52115 St Dizier Cedex Nord Pas-de-Calais",
    "addr:housenumber":"52115",
    "addr:postcode":"dizier cedex nord",
    "addr:street":"Chem",
    "iso:country":"FR",
    "sg:address":"Chem Du Closot 52115 St Dizier Cedex",
    "sg:classifiers":[
        {
            "category":"Manufacturing",
            "subcategory":"Motor Vehicles & Parts",
            "type":"Manufacturing & Wholesale Goods"
        }
    ],
    "sg:phone":"+33 3 25 06 38 00",
    "sg:province":"Nord Pas-de-Calais",
    "sg:tags":[
        "engine",
        "machine",
        "engineering",
        "-",
        "mechanical"
    ],
    "wof:name":"Valfont",
    "wof:placetype":"venue"
},
  "geometry": {"coordinates":[4.930992,48.6427],"type":"Point"}
}