{
  "type": "Feature",
  "properties": {
    "addr:full":"Rue Monjaret de Kerjegu - ZI Portuaire Brest C\u00e9dex Brittany 29601",
    "addr:postcode":"29601",
    "addr:street":"Rue Monjaret De Kerjegu Zi Portuaire;Ce\u0301Dex",
    "iso:country":"FR",
    "sg:address":"Rue Monjaret de Kerjegu - ZI Portuaire",
    "sg:city":"Brest C\u00e9dex",
    "sg:orig_category":"Non-Classified Establishments",
    "sg:phone":"+33 2 98 33 25 14",
    "sg:postcode":"29601",
    "sg:province":"Brittany",
    "wof:name":"M\u00fbrisserie D'armor S.a.r.l.",
    "wof:placetype":"venue"
},
  "geometry": {"coordinates":[-4.4869,48.390598],"type":"Point"}
}