{
  "type": "Feature",
  "properties": {
    "addr:full":"avenue de Sarlat 46200 Souillac Midi Pyr\u00e9n\u00e9es 46200",
    "addr:postcode":"46200;46200",
    "addr:street":"Avenue De Sarlat",
    "iso:country":"FR",
    "sg:address":"avenue de Sarlat 46200 Souillac",
    "sg:classifiers":[
        {
            "category":"Banks & Credit Unions",
            "subcategory":"Investment Brokerage",
            "type":"Services"
        }
    ],
    "sg:phone":"+33 5 65 32 22 20",
    "sg:postcode":"46200",
    "sg:province":"Midi Pyr\u00e9n\u00e9es",
    "sg:tags":[
        "case",
        "spectacle"
    ],
    "wof:name":"Ste Nouvelle C.e.l. Sarl",
    "wof:placetype":"venue"
},
  "geometry": {"coordinates":[1.47925,44.894131],"type":"Point"}
}