{
  "type": "Feature",
  "properties": {
    "addr:full":"7, Bd Pacatianus, 38200 Vienne Rhone-Alpes 38200",
    "addr:housenumber":"7",
    "addr:postcode":"38200;38200",
    "addr:street":"Bd Pacatianus",
    "iso:country":"FR",
    "sg:address":"7, Bd Pacatianus, 38200 Vienne",
    "sg:orig_category":"Unclassifiable Establishments",
    "sg:phone":"+33 4 74 31 36 00",
    "sg:postcode":"38200",
    "sg:province":"Rhone-Alpes",
    "wof:name":"E.d.f. Et Gaz De France",
    "wof:placetype":"venue"
},
  "geometry": {"coordinates":[4.84989,45.501549],"type":"Point"}
}