{
  "type": "Feature",
  "properties": {
    "iso:country":"FR",
    "sg:address":"Le Malcourlet Rn9 03800 Gannat",
    "sg:city":"Gannat",
    "sg:classifiers":[
        {
            "category":"Farming",
            "subcategory":"Livestock Farm",
            "type":"Manufacturing & Wholesale Goods"
        }
    ],
    "sg:phone":"+33 4 70 90 02 20",
    "sg:postcode":"03800",
    "sg:province":"Auvergne",
    "sg:tags":[
        "breeding",
        "agriculture",
        "animal"
    ],
    "wof:name":"Harlan France Sarl",
    "wof:placetype":"venue"
},
  "geometry": {"coordinates":[3.201044,46.112354],"type":"Point"}
}