{
  "type": "Feature",
  "properties": {
    "addr:full":"65, Av. Jean Mermoz, 93126 La Courneuve C\u00e9dex \u00cele-de-France",
    "addr:postcode":"93126",
    "addr:street":"65 Av. Jean Mermoz",
    "iso:country":"FR",
    "sg:address":"65, Av. Jean Mermoz, 93126 La Courneuve C\u00e9dex",
    "sg:orig_category":"Non-Classified Establishments",
    "sg:phone":"+33 1 48 38 71 71",
    "sg:province":"\u00cele-de-France",
    "wof:name":"Safety Kleen France S.a.",
    "wof:placetype":"venue"
},
  "geometry": {"coordinates":[2.40415,48.932419],"type":"Point"}
}