{
  "type": "Feature",
  "properties": {
    "iso:country":"FR",
    "sg:address":"Zi Du Marmagou 65706 Maubourguet Cedex",
    "sg:classifiers":[
        {
            "category":"Food & Beverages",
            "subcategory":"Meat & Fish",
            "type":"Retail Goods"
        }
    ],
    "sg:phone":"+33 5 62 96 92 00",
    "sg:province":"Centre",
    "sg:tags":[
        "preserve",
        "cooked",
        "product",
        "related"
    ],
    "wof:name":"Gmd",
    "wof:placetype":"venue"
},
  "geometry": {"coordinates":[0.03478,43.467564],"type":"Point"}
}