{
  "type": "Feature",
  "properties": {
    "addr:full":"Chemin Pont Rouge 38110 Cessieu Rhone-Alpes 38110",
    "addr:postcode":"38110;38110",
    "addr:street":"Chemin Pont Rouge;Rhone-Alpes",
    "iso:country":"FR",
    "sg:address":"Chemin Pont Rouge 38110 Cessieu",
    "sg:classifiers":[
        {
            "category":"Government",
            "subcategory":"Department Of Motor Vehicles",
            "type":"Public Place"
        }
    ],
    "sg:phone":"+33 4 74 97 25 34",
    "sg:postcode":"38110",
    "sg:province":"Rhone-Alpes",
    "sg:tags":[
        "equipment",
        "industrial",
        "transport",
        "motor-cars"
    ],
    "wof:name":"Autocasse Bouvier Sarl",
    "wof:placetype":"venue"
},
  "geometry": {"coordinates":[5.406555,45.564205],"type":"Point"}
}