{
  "type": "Feature",
  "properties": {
    "addr:full":"36 rue des Fillettes 93300 Aubervilliers Ile de France 93300",
    "addr:housenumber":"36",
    "addr:postcode":"93300;93300",
    "addr:street":"Rue Des Fillettes",
    "iso:country":"FR",
    "sg:address":"36 rue des Fillettes 93300 Aubervilliers",
    "sg:classifiers":[
        {
            "category":"Professional",
            "subcategory":"Business Services",
            "type":"Services"
        }
    ],
    "sg:phone":"+33 1 48 33 82 34",
    "sg:postcode":"93300",
    "sg:province":"Ile de France",
    "sg:tags":[
        "agency",
        "export"
    ],
    "wof:name":"Victor Import S.a.",
    "wof:placetype":"venue"
},
  "geometry": {"coordinates":[2.366389,48.911991],"type":"Point"}
}