{
  "type": "Feature",
  "properties": {
    "iso:country":"FR",
    "sg:address":"B.P. 87, 62502 Saint Omer C\u00e9dex^^23, Av. Cl\u00e9menceau, 62219 Longuenesse",
    "sg:orig_category":"Non-Classified Establishments",
    "sg:phone":"+33 3 21 12 22 21",
    "sg:province":"Nord Pas-de-Calais",
    "wof:name":"L'ind\u00e9pendant Du Pas De Calais S.a.",
    "wof:placetype":"venue"
},
  "geometry": {"coordinates":[2.245115,50.738091],"type":"Point"}
}