{
  "type": "Feature",
  "properties": {
    "addr:full":"Parc d'Activit\u00e9s de Forbach Ouest Forbach Lorraine 57600",
    "addr:postcode":"57600",
    "addr:street":"Lorraine",
    "iso:country":"FR",
    "sg:address":"Parc d'Activit\u00e9s de Forbach Ouest",
    "sg:city":"Forbach",
    "sg:orig_category":"Unclassifiable Establishments",
    "sg:phone":"+33 3 87 84 86 44",
    "sg:postcode":"57600",
    "sg:province":"Lorraine",
    "wof:name":"Egerland France S.a.r.l.",
    "wof:placetype":"venue"
},
  "geometry": {"coordinates":[6.90704,49.175175],"type":"Point"}
}