{
  "type": "Feature",
  "properties": {
    "addr:full":"8 all\u00e9e Moulin Berger 69130 Ecully Rhone-Alpes 69130",
    "addr:housenumber":"8",
    "addr:postcode":"69130;69130",
    "addr:street":"Alle\u0301E Moulin Berger;Rhone-Alpes",
    "iso:country":"FR",
    "sg:address":"8 all\u00e9e Moulin Berger 69130 Ecully",
    "sg:classifiers":[
        {
            "category":"Banks & Credit Unions",
            "subcategory":"Investment Brokerage",
            "type":"Services"
        }
    ],
    "sg:phone":"+33 4 78 66 85 70",
    "sg:postcode":"69130",
    "sg:province":"Rhone-Alpes",
    "sg:tags":[
        "compressor",
        "refrigeration"
    ],
    "wof:name":"Copeland France Sarl",
    "wof:placetype":"venue"
},
  "geometry": {"coordinates":[4.768235,45.798489],"type":"Point"}
}