{
  "type": "Feature",
  "properties": {
    "iso:country":"FR",
    "sg:address":"10, Rue Cl\u00e9ment Ader - ZI du Beau Marais, 62100 Calais",
    "sg:orig_category":"Unclassifiable Establishments",
    "sg:phone":"+33 3 21 96 32 76",
    "sg:province":"Nord Pas-de-Calais",
    "wof:name":"C.g.f. Charcuterie S.a.r.l.",
    "wof:placetype":"venue"
},
  "geometry": {"coordinates":[1.85305,50.953079],"type":"Point"}
}