{
  "type": "Feature",
  "properties": {
    "iso:country":"FR",
    "sg:address":"34-36 Rue Du Mal Lyautey 93200 St Denis",
    "sg:classifiers":[
        {
            "category":"Building & Trades",
            "subcategory":"Construction",
            "type":"Services"
        }
    ],
    "sg:phone":"+33 1 49 71 10 90",
    "sg:postcode":"93200",
    "sg:province":"Ile de France",
    "sg:tags":[
        "work",
        "public"
    ],
    "wof:name":"Dubrac Freres Sa",
    "wof:placetype":"venue"
},
  "geometry": {"coordinates":[2.374332,48.927731],"type":"Point"}
}