{
  "type": "Feature",
  "properties": {
    "addr:full":"102 Bd Voltaire 75011 Paris Ile de France 75011",
    "addr:housenumber":"102",
    "addr:postcode":"75011;75011",
    "addr:street":"Bd Voltaire",
    "iso:country":"FR",
    "sg:address":"102 Bd Voltaire 75011 Paris",
    "sg:classifiers":[
        {
            "category":"Shopping",
            "subcategory":"Clothing, Apparel, & Fashions",
            "type":"Retail Goods"
        }
    ],
    "sg:phone":"+33 1 47 00 53 54",
    "sg:postcode":"75011",
    "sg:province":"Ile de France",
    "sg:tags":[
        "textile",
        "clothing",
        "clothes"
    ],
    "wof:name":"Home Stock Sarl",
    "wof:placetype":"venue"
},
  "geometry": {"coordinates":[2.376938,48.859501],"type":"Point"}
}