{
  "type": "Feature",
  "properties": {
    "addr:full":"Les Vignobles 24640 Le Change Le Change Aquitaine 24640",
    "addr:housenumber":"le change le change",
    "addr:postcode":"24640;24640",
    "iso:country":"FR",
    "sg:address":"Les Vignobles 24640 Le Change",
    "sg:city":"Le Change",
    "sg:classifiers":[
        {
            "category":"Food & Beverages",
            "subcategory":"Meat & Fish",
            "type":"Retail Goods"
        }
    ],
    "sg:phone":"+33 5 53 06 07 84",
    "sg:postcode":"24640",
    "sg:province":"Aquitaine",
    "sg:tags":[
        "preserve",
        "cooked",
        "product",
        "related"
    ],
    "wof:name":"Conserves Perigourdines",
    "wof:placetype":"venue"
},
  "geometry": {"coordinates":[0.892617,45.195126],"type":"Point"}
}