{
  "type": "Feature",
  "properties": {
    "iso:country":"FR",
    "sg:address":"Quai Eug\u00e8ne Souchon",
    "sg:city":"Givors",
    "sg:orig_category":"Unclassifiable Establishments",
    "sg:phone":"+33 4 78 07 39 78",
    "sg:postcode":"69700",
    "sg:province":"Rhone-Alpes",
    "wof:name":"V.m.c. - Verreries M\u00e9caniques Champenoises",
    "wof:placetype":"venue"
},
  "geometry": {"coordinates":[4.767844,45.587414],"type":"Point"}
}