{
  "type": "Feature",
  "properties": {
    "addr:full":"Rue de la Ruette aux Loups Saint Malo Bretagne 35400",
    "addr:postcode":"35400",
    "addr:street":"Rue De La Ruette Aux Loups Saint Malo Bretagne",
    "iso:country":"FR",
    "sg:address":"Rue de la Ruette aux Loups",
    "sg:city":"Saint Malo",
    "sg:orig_category":"Unclassifiable Establishments",
    "sg:phone":"+33 2 99 82 85 85",
    "sg:postcode":"35400",
    "sg:province":"Bretagne",
    "wof:name":"Servich\u00e8que S.a.",
    "wof:placetype":"venue"
},
  "geometry": {"coordinates":[-1.981449,48.636623],"type":"Point"}
}