{
  "type": "Feature",
  "properties": {
    "addr:full":"122, Rue de l'Industrie - ZAE, 59264 Onnaing Nord Pas-de-Calais",
    "addr:housenumber":"122",
    "addr:postcode":"59264",
    "addr:street":"Rue De L'Industrie Zae",
    "iso:country":"FR",
    "sg:address":"122, Rue de l'Industrie - ZAE, 59264 Onnaing",
    "sg:orig_category":"Unclassifiable Establishments",
    "sg:phone":"+33 3 27 46 45 30",
    "sg:province":"Nord Pas-de-Calais",
    "wof:name":"Sofembal - Soflog S.a.s.",
    "wof:placetype":"venue"
},
  "geometry": {"coordinates":[3.602918,50.390537],"type":"Point"}
}