{
  "type": "Feature",
  "properties": {
    "addr:full":"B.P. 10017, 57160 Scy Chazelles^^8, Rue de l'Etang, 57160 Scy Chazelles Lorraine",
    "addr:housenumber":"10017",
    "addr:postcode":"57160;57160",
    "addr:street":"Rue De L'Etang",
    "iso:country":"FR",
    "sg:address":"B.P. 10017, 57160 Scy Chazelles^^8, Rue de l'Etang, 57160 Scy Chazelles",
    "sg:orig_category":"Non-Classified Establishments",
    "sg:phone":"+33 3 87 60 28 80",
    "sg:province":"Lorraine",
    "wof:name":"Europ\u00e9enne D'etanch\u00e9it\u00e9 S.a.r.l.",
    "wof:placetype":"venue"
},
  "geometry": {"coordinates":[6.119897,49.106422],"type":"Point"}
}