{
  "type": "Feature",
  "properties": {
    "addr:full":"Route Teinte 58300 Sougy Sur Loire Charrin Bourgogne 58300",
    "addr:postcode":"58300;58300",
    "addr:street":"Route Teinte;Bourgogne",
    "iso:country":"FR",
    "sg:address":"Route Teinte 58300 Sougy Sur Loire",
    "sg:city":"Charrin",
    "sg:classifiers":[
        {
            "category":"Social Services",
            "subcategory":"Job Training",
            "type":"Services"
        }
    ],
    "sg:phone":"+33 3 86 50 12 88",
    "sg:postcode":"58300",
    "sg:province":"Bourgogne",
    "sg:tags":[
        "good",
        "business",
        "advice",
        "-",
        "metalworking",
        "metallic",
        "metallurgy",
        "finished"
    ],
    "wof:name":"7 M Sarl",
    "wof:placetype":"venue"
},
  "geometry": {"coordinates":[3.390376,46.832748],"type":"Point"}
}