{
  "type": "Feature",
  "properties": {
    "addr:full":"B.P. 90 Cognac Cedex^^16100 Merpins Poitou-Charentes 16103",
    "addr:postcode":"16103",
    "addr:street":"B.P. 90;Merpins",
    "iso:country":"FR",
    "sg:address":"B.P. 90",
    "sg:city":"Cognac Cedex^^16100 Merpins",
    "sg:orig_category":"Non-Classified Establishments",
    "sg:phone":"+33 5 45 82 03 74",
    "sg:postcode":"16103",
    "sg:province":"Poitou-Charentes",
    "wof:name":"Maison Ren\u00e9 Pecner Fils S.a.r.l.",
    "wof:placetype":"venue"
},
  "geometry": {"coordinates":[-0.313384,45.67149],"type":"Point"}
}