{
  "type": "Feature",
  "properties": {
    "addr:full":"Zi D'Alba Sud Avenue D'Allemagne Montauban Midi Pyr\u00e9n\u00e9es 82000",
    "addr:postcode":"82000",
    "addr:street":"Avenue D'Allemagne",
    "iso:country":"FR",
    "sg:address":"Zi D'Alba Sud Avenue D'Allemagne",
    "sg:city":"Montauban",
    "sg:classifiers":[
        {
            "category":"Banks & Credit Unions",
            "subcategory":"Financial Services",
            "type":"Services"
        }
    ],
    "sg:phone":"+33 5 63 21 74 00",
    "sg:postcode":"82000",
    "sg:province":"Midi Pyr\u00e9n\u00e9es",
    "sg:tags":[
        "banking",
        "finance",
        "insurance"
    ],
    "wof:name":"Cabinet Durrieu Et Cie Sa",
    "wof:placetype":"venue"
},
  "geometry": {"coordinates":[1.329954,43.989723],"type":"Point"}
}