{
  "type": "Feature",
  "properties": {
    "iso:country":"FR",
    "sg:address":"2, Av. du G\u00e9n\u00e9ral Leclerc, 32110 Nogaro",
    "sg:orig_category":"Non-Classified Establishments",
    "sg:phone":"+33 5 62 09 03 61",
    "sg:province":"Midi Pyr\u00e9n\u00e9es",
    "wof:name":"Imprimerie Dauba Fr\u00e8res S.a.r.l.",
    "wof:placetype":"venue"
},
  "geometry": {"coordinates":[-0.030907,43.758659],"type":"Point"}
}