{
  "type": "Feature",
  "properties": {
    "addr:full":"30, Rue de l'Industrie, 76120 Le Grand Quevilly Haute Normandie",
    "addr:housenumber":"30",
    "addr:postcode":"76120",
    "addr:street":"Rue De L'Industrie;Haute Normandie",
    "iso:country":"FR",
    "sg:address":"30, Rue de l'Industrie, 76120 Le Grand Quevilly",
    "sg:orig_category":"Unclassifiable Establishments",
    "sg:phone":"+33 2 35 67 41 41",
    "sg:province":"Haute Normandie",
    "wof:name":"Grande Paroisse S.a.",
    "wof:placetype":"venue"
},
  "geometry": {"coordinates":[1.046985,49.423759],"type":"Point"}
}