{
  "type": "Feature",
  "properties": {
    "iso:country":"FR",
    "sg:address":"834 Lot Industriel Du Ventillo Secteur 83 Coussoul 13270 Fos Sur Mer",
    "sg:classifiers":[
        {
            "category":"Banks & Credit Unions",
            "subcategory":"Bank",
            "type":"Services"
        }
    ],
    "sg:phone":"+33 4 42 05 20 17",
    "sg:province":"Haute Normandie",
    "sg:tags":[
        "sea",
        "transport",
        "road"
    ],
    "wof:name":"Sdv",
    "wof:placetype":"venue"
},
  "geometry": {"coordinates":[4.946065,43.436958],"type":"Point"}
}