{
  "type": "Feature",
  "properties": {
    "iso:country":"FR",
    "sg:address":"Rue Mangine",
    "sg:city":"Dordives",
    "sg:orig_category":"Non-Classified Establishments",
    "sg:phone":"+33 2 38 30 77 00",
    "sg:postcode":"45680",
    "sg:province":"Centre",
    "wof:name":"S.t.j. S.a.r.l.",
    "wof:placetype":"venue"
},
  "geometry": {"coordinates":[2.760295,48.161442],"type":"Point"}
}