{
  "type": "Feature",
  "properties": {
    "iso:country":"FR",
    "sg:address":"Rte De Brindas Parc D Activite D'Abora BP 69510 69510 Soucieu En Jarrest",
    "sg:classifiers":[
        {
            "category":"Manufacturing",
            "subcategory":"Tools & Machinery",
            "type":"Manufacturing & Wholesale Goods"
        }
    ],
    "sg:phone":"+33 4 78 16 04 04",
    "sg:province":"Rhone-Alpes",
    "sg:tags":[
        "equipment",
        "measurement",
        "-",
        "precision",
        "instrument"
    ],
    "wof:name":"Sfere Sarl",
    "wof:placetype":"venue"
},
  "geometry": {"coordinates":[4.703539,45.684258],"type":"Point"}
}