{
  "type": "Feature",
  "properties": {
    "addr:full":"4 Rue Sainte Eulalie 64220 ST JEAN PIED DE PORT Anhaux Aquitaine 64220",
    "addr:housenumber":"4",
    "addr:postcode":"64220;64220",
    "addr:street":"Rue Sainte Eulalie",
    "iso:country":"FR",
    "sg:address":"4 Rue Sainte Eulalie 64220 ST JEAN PIED DE PORT",
    "sg:city":"Anhaux",
    "sg:classifiers":[
        {
            "category":"Retail",
            "subcategory":"Animal Services",
            "type":"Services"
        }
    ],
    "sg:phone":"+33 5 59 37 01 85",
    "sg:postcode":"64220",
    "sg:province":"Aquitaine",
    "sg:tags":[
        "transportation"
    ],
    "wof:name":"Lucien Harinordoquy- Import- Export Sarl",
    "wof:placetype":"venue"
},
  "geometry": {"coordinates":[-1.236189,43.164948],"type":"Point"}
}