{
  "type": "Feature",
  "properties": {
    "iso:country":"FR",
    "sg:address":"La Graverie 14350 La Graverie",
    "sg:city":"La Graverie",
    "sg:classifiers":[
        {
            "category":"Manufacturing",
            "subcategory":"Tools & Machinery",
            "type":"Manufacturing & Wholesale Goods"
        }
    ],
    "sg:phone":"+33 2 31 68 38 90",
    "sg:postcode":"14350",
    "sg:province":"Basse Normandie",
    "sg:tags":[
        "metallurgy",
        "metalworking"
    ],
    "wof:name":"Leitz Sarl",
    "wof:placetype":"venue"
},
  "geometry": {"coordinates":[-0.88017,48.894901],"type":"Point"}
}