{
  "type": "Feature",
  "properties": {
    "iso:country":"FR",
    "sg:address":"15 Rue Etienne Dolet 76140 Le Petit Quevilly",
    "sg:classifiers":[
        {
            "category":"Professional",
            "type":"Services"
        }
    ],
    "sg:phone":"+33 2 32 18 00 00",
    "sg:province":"Haute Normandie",
    "sg:tags":[
        "transport",
        "road"
    ],
    "wof:name":"Compagnie D'affretement Et De Transport (cat)",
    "wof:placetype":"venue"
},
  "geometry": {"coordinates":[1.046492,49.431934],"type":"Point"}
}