{
  "type": "Feature",
  "properties": {
    "addr:full":"188 Rue Jean Jaures Bobigny Ile de France 93000",
    "addr:housenumber":"188",
    "addr:postcode":"93000",
    "addr:street":"Rue Jean Jaures;Ile De France",
    "iso:country":"FR",
    "sg:address":"188 Rue Jean Jaures",
    "sg:city":"Bobigny",
    "sg:classifiers":[
        {
            "category":"Banks & Credit Unions",
            "subcategory":"Financial Services",
            "type":"Services"
        }
    ],
    "sg:phone":"+33 1 48 30 22 74",
    "sg:postcode":"93000",
    "sg:province":"Ile de France",
    "sg:tags":[
        "banking",
        "finance",
        "insurance"
    ],
    "wof:name":"Caisse Regionale De Credit Agricole Mutuel De Paris Et D Il",
    "wof:placetype":"venue"
},
  "geometry": {"coordinates":[2.437824,48.909473],"type":"Point"}
}