{
  "type": "Feature",
  "properties": {
    "iso:country":"FR",
    "sg:address":"Rte de la Massane - ZI",
    "sg:city":"Saint R\u00e9my de Provence",
    "sg:orig_category":"Unclassifiable Establishments",
    "sg:phone":"+33 4 90 92 17 79",
    "sg:postcode":"13210",
    "sg:province":"Nord Pas-de-Calais",
    "wof:name":"Sexmoor S.a.r.l.",
    "wof:placetype":"venue"
},
  "geometry": {"coordinates":[4.829515,43.788704],"type":"Point"}
}