{
  "type": "Feature",
  "properties": {
    "iso:country":"FR",
    "sg:address":"Lacanche 21230 Arnay le Duc",
    "sg:city":"Lacanche",
    "sg:orig_category":"Non-Classified Establishments",
    "sg:phone":"+33 3 80 90 35 00",
    "sg:postcode":"21230",
    "sg:province":"Bourgogne",
    "wof:name":"A.s.c. S.a.",
    "wof:placetype":"venue"
},
  "geometry": {"coordinates":[4.56037,47.076752],"type":"Point"}
}