{
  "type": "Feature",
  "properties": {
    "iso:country":"FR",
    "sg:address":"Rue Maurice Willot 59600 Assevent",
    "sg:classifiers":[
        {
            "category":"Manufacturing",
            "subcategory":"Rubber & Plastics",
            "type":"Manufacturing & Wholesale Goods"
        }
    ],
    "sg:phone":"+33 3 27 69 82 82",
    "sg:province":"Nord Pas-de-Calais",
    "sg:tags":[
        "packaging",
        "material",
        "-"
    ],
    "wof:name":"Graham Packaging France",
    "wof:placetype":"venue"
},
  "geometry": {"coordinates":[4.02055,50.2854],"type":"Point"}
}