{
  "type": "Feature",
  "properties": {
    "iso:country":"FR",
    "sg:address":"8 R Des Pyr\u00e9nn\u00e9es 94643 Rungis",
    "sg:classifiers":[
        {
            "category":"Health Services",
            "subcategory":"Podiatrist",
            "type":"Services"
        }
    ],
    "sg:phone":"+33 1 45 12 20 60",
    "sg:province":"Languedoc-Roussillon",
    "sg:tags":[
        "instrument",
        "measurement",
        "-",
        "precision",
        "equipment"
    ],
    "wof:name":"Efcie",
    "wof:placetype":"venue"
},
  "geometry": {"coordinates":[2.35325,48.751419],"type":"Point"}
}