{
  "type": "Feature",
  "properties": {
    "addr:full":"ZI La Nau Saint Viance Limousin 19240",
    "addr:postcode":"19240",
    "addr:street":"Zi La Nau Saint Viance Limousin",
    "iso:country":"FR",
    "sg:address":"ZI La Nau",
    "sg:city":"Saint Viance",
    "sg:orig_category":"Unclassifiable Establishments",
    "sg:phone":"+33 5 55 84 58 40",
    "sg:postcode":"19240",
    "sg:province":"Limousin",
    "wof:name":"S.i.l.a.b. S.a. - Soci\u00e9t\u00e9 Industrielle Limousine D'application Biologique",
    "wof:placetype":"venue"
},
  "geometry": {"coordinates":[1.452784,45.217667],"type":"Point"}
}