{
  "type": "Feature",
  "properties": {
    "addr:full":"71 Rue Porte De Chinon 86200 Loudun Poitou-Charentes 86200",
    "addr:housenumber":"71",
    "addr:postcode":"86200;86200",
    "addr:street":"Rue Porte De Chinon",
    "iso:country":"FR",
    "sg:address":"71 Rue Porte De Chinon 86200 Loudun",
    "sg:classifiers":[
        {
            "category":"Manufacturing",
            "subcategory":"Tools & Machinery",
            "type":"Manufacturing & Wholesale Goods"
        }
    ],
    "sg:phone":"+33 5 49 98 00 08",
    "sg:postcode":"86200",
    "sg:province":"Poitou-Charentes",
    "sg:tags":[
        "metallurgy",
        "metalworking"
    ],
    "wof:name":"Audran Sa",
    "wof:placetype":"venue"
},
  "geometry": {"coordinates":[0.08693,47.009125],"type":"Point"}
}