{
  "type": "Feature",
  "properties": {
    "iso:country":"FR",
    "sg:address":"Zi De La Prade 43110 Aurec Sur Loire",
    "sg:city":"Aurec-sur-Loire",
    "sg:classifiers":[
        {
            "category":"Banks & Credit Unions",
            "subcategory":"Investment Brokerage",
            "type":"Services"
        }
    ],
    "sg:phone":"+33 4 77 35 40 30",
    "sg:postcode":"43110",
    "sg:province":"Auvergne",
    "sg:tags":[
        "business",
        "electricity",
        "advice",
        "equipment",
        "electrical",
        "electronic"
    ],
    "wof:name":"Lst Groupe Sa",
    "wof:placetype":"venue"
},
  "geometry": {"coordinates":[4.202371,45.369537],"type":"Point"}
}