{
  "type": "Feature",
  "properties": {
    "addr:full":"71, Av. Louis Roche, 92230 Gennevilliers Ile de France",
    "addr:postcode":"92230;ile",
    "addr:street":"71 Av. Louis Roche",
    "iso:country":"FR",
    "sg:address":"71, Av. Louis Roche, 92230 Gennevilliers",
    "sg:orig_category":"Non-Classified Establishments",
    "sg:phone":"+33 1 40 86 26 27",
    "sg:province":"Ile de France",
    "wof:name":"Koksa\u00ef International S.a.r.l.",
    "wof:placetype":"venue"
},
  "geometry": {"coordinates":[2.318447,48.92469],"type":"Point"}
}