{
  "type": "Feature",
  "properties": {
    "iso:country":"FR",
    "sg:address":"Place Olivier de Serres 26110 Nyons",
    "sg:classifiers":[
        {
            "category":"Wholesale",
            "subcategory":"Wine & Distilled Alcoholic Beverages",
            "type":"Manufacturing & Wholesale Goods"
        }
    ],
    "sg:phone":"+33 4 75 26 95 00",
    "sg:postcode":"26110",
    "sg:province":"Rhone-Alpes",
    "sg:tags":[
        "french"
    ],
    "wof:name":"Coop\u00e9rative Du Nyonsais Coop",
    "wof:placetype":"venue"
},
  "geometry": {"coordinates":[5.13252,44.360134],"type":"Point"}
}