{
  "type": "Feature",
  "properties": {
    "addr:full":"Chemin des Madeleines Pont du Ch\u00e2teau Auvergne 63430",
    "addr:postcode":"63430",
    "addr:street":"Chemin Des Madeleines Pont Du Cha\u0302Teau",
    "iso:country":"FR",
    "sg:address":"Chemin des Madeleines",
    "sg:city":"Pont du Ch\u00e2teau",
    "sg:orig_category":"Unclassifiable Establishments",
    "sg:phone":"+33 4 73 83 38 00",
    "sg:postcode":"63430",
    "sg:province":"Auvergne",
    "wof:name":"S.b.a. - Syndicat Bois L'aumone",
    "wof:placetype":"venue"
},
  "geometry": {"coordinates":[3.264103,45.806419],"type":"Point"}
}