{
  "type": "Feature",
  "properties": {
    "addr:full":"1 r Louis Juttet; Champagne au Mont d'Or Champagn\u00e9 Pays de Loire 72470",
    "addr:housenumber":"1",
    "addr:postcode":"72470",
    "addr:street":"R Louis Juttet Champagne Au Mont",
    "iso:country":"FR",
    "sg:address":"1 r Louis Juttet; Champagne au Mont d'Or",
    "sg:city":"Champagn\u00e9",
    "sg:classifiers":[
        {
            "category":"Banks & Credit Unions",
            "subcategory":"Bank",
            "type":"Services"
        }
    ],
    "sg:phone":"+33 3378350883",
    "sg:postcode":"72470",
    "sg:province":"Pays de Loire",
    "wof:name":"Lyonnaise De Banque",
    "wof:placetype":"venue"
},
  "geometry": {"coordinates":[-0.100754,47.869232],"type":"Point"}
}