{
  "type": "Feature",
  "properties": {
    "addr:full":"B.P. 9155, 95310 Cergy C\u00e9dex^^13, Cit\u00e9 Artisanale de la Mare - ZI Les B\u00e9thunes, 95310 Saint Ouen l'A Ile de France",
    "addr:postcode":"95310;95310;l'a ile",
    "addr:street":"B.P. 9155;Cite\u0301 Artisanale De La Mare Zi Les Be\u0301Thunes",
    "iso:country":"FR",
    "sg:address":"B.P. 9155, 95310 Cergy C\u00e9dex^^13, Cit\u00e9 Artisanale de la Mare - ZI Les B\u00e9thunes, 95310 Saint Ouen l'A",
    "sg:orig_category":"Non-Classified Establishments",
    "sg:phone":"+33 1 34 64 01 70",
    "sg:province":"Ile de France",
    "wof:name":"Rambaudi S.a.r.l.",
    "wof:placetype":"venue"
},
  "geometry": {"coordinates":[2.134146,49.041138],"type":"Point"}
}