{
  "type": "Feature",
  "properties": {
    "iso:country":"FR",
    "sg:address":"9 Rue De La Gare 25690 Avoudrey",
    "sg:classifiers":[
        {
            "category":"Wholesale",
            "subcategory":"Meat",
            "type":"Manufacturing & Wholesale Goods"
        }
    ],
    "sg:phone":"+33 3 81 67 67 20",
    "sg:postcode":"25690",
    "sg:province":"Franche Comt\u00e9",
    "sg:tags":[
        "food",
        "cooked",
        "product",
        "related"
    ],
    "wof:name":"Jean-louis Amiotte Sa",
    "wof:placetype":"venue"
},
  "geometry": {"coordinates":[6.435077,47.13028],"type":"Point"}
}