{
  "type": "Feature",
  "properties": {
    "addr:full":"10, Chemin du Regina - ZA, 34110 Vic la Gardiole Languedoc-Roussillon 34110",
    "addr:housenumber":"10",
    "addr:postcode":"34110;34110",
    "addr:street":"Chemin Du Regina Za",
    "iso:country":"FR",
    "sg:address":"10, Chemin du Regina - ZA, 34110 Vic la Gardiole",
    "sg:orig_category":"Non-Classified Establishments",
    "sg:phone":"+33 4 67 78 17 80",
    "sg:postcode":"34110",
    "sg:province":"Languedoc-Roussillon",
    "wof:name":"C.m.a. - Construction M\u00e9tallique Artisanale",
    "wof:placetype":"venue"
},
  "geometry": {"coordinates":[3.75841,43.444561],"type":"Point"}
}