{
  "type": "Feature",
  "properties": {
    "addr:full":"B.P. 43, 69490 Sarcey C\u00e9dex^^ZA la Noyeraie, 69490 Sarcey Rhone-Alpes 69490",
    "addr:postcode":"69490;69490;69490",
    "addr:street":"B.P. 43",
    "iso:country":"FR",
    "sg:address":"B.P. 43, 69490 Sarcey C\u00e9dex^^ZA la Noyeraie, 69490 Sarcey",
    "sg:orig_category":"Non-Classified Establishments",
    "sg:phone":"+33 4 74 26 86 04",
    "sg:postcode":"69490",
    "sg:province":"Rhone-Alpes",
    "wof:name":"Les Cartonnages De La Turdine S.a.",
    "wof:placetype":"venue"
},
  "geometry": {"coordinates":[4.507927,45.837818],"type":"Point"}
}