{
  "type": "Feature",
  "properties": {
    "iso:country":"FR",
    "sg:address":"Rte de Strasbourg - ZA",
    "sg:city":"Sarralbe",
    "sg:orig_category":"Unclassifiable Establishments",
    "sg:phone":"+33 3 87 97 01 01",
    "sg:postcode":"57430",
    "sg:province":"Lorraine",
    "wof:name":"J.l.b. Communication S.a.r.l.",
    "wof:placetype":"venue"
},
  "geometry": {"coordinates":[7.03013,49.000999],"type":"Point"}
}