{
  "type": "Feature",
  "properties": {
    "addr:full":"43, All\u00e9e M\u00e9gevie, 33174 Gradignan C\u00e9dex Aquitaine",
    "addr:housenumber":"43",
    "addr:postcode":"33174",
    "addr:street":"Alle\u0301E Me\u0301Gevie",
    "iso:country":"FR",
    "sg:address":"43, All\u00e9e M\u00e9gevie, 33174 Gradignan C\u00e9dex",
    "sg:orig_category":"Non-Classified Establishments",
    "sg:phone":"+33 5 56 75 71 56",
    "sg:province":"Aquitaine",
    "wof:name":"Texaa S.a.",
    "wof:placetype":"venue"
},
  "geometry": {"coordinates":[-0.614138,44.773132],"type":"Point"}
}