{
  "type": "Feature",
  "properties": {
    "iso:country":"FR",
    "sg:address":"B.P. 12, 35150 Janz\u00e9 C\u00e9dex^^34 bis, Rue Nantaise, 35150 Janz\u00e9",
    "sg:city":"Janz\u00e9",
    "sg:orig_category":"Non-Classified Establishments",
    "sg:phone":"+33 2 99 47 03 72",
    "sg:postcode":"35150",
    "sg:province":"Bretagne",
    "wof:name":"Edou Breizh S.a.r.l.",
    "wof:placetype":"venue"
},
  "geometry": {"coordinates":[-1.495007,47.958996],"type":"Point"}
}