{
  "type": "Feature",
  "properties": {
    "iso:country":"FR",
    "sg:address":"54 Route Des Vorziers 74700 Sallanches",
    "sg:classifiers":[
        {
            "category":"Wholesale",
            "subcategory":"Machinery & Supplies",
            "type":"Manufacturing & Wholesale Goods"
        }
    ],
    "sg:phone":"+33 4 50 58 15 16",
    "sg:postcode":"74700",
    "sg:province":"Rhone-Alpes",
    "sg:tags":[
        "equipment",
        "equipement",
        "precision",
        "timekeeping"
    ],
    "wof:name":"Etablissements Maurice Gavard Sarl",
    "wof:placetype":"venue"
},
  "geometry": {"coordinates":[6.629361,45.973213],"type":"Point"}
}