{
  "type": "Feature",
  "properties": {
    "iso:country":"FR",
    "sg:address":"77, Av. Gustave Ferri\u00e9, 49300 Cholet",
    "sg:orig_category":"Unclassifiable Establishments",
    "sg:phone":"+33 2 41 49 03 60",
    "sg:province":"Pays de Loire",
    "wof:name":"Cir\u00e9a S.a.",
    "wof:placetype":"venue"
},
  "geometry": {"coordinates":[-0.858259,47.06226],"type":"Point"}
}