{
  "type": "Feature",
  "properties": {
    "iso:country":"FR",
    "sg:address":"300, Bureaux de la Colline, 92213 Saint Cloud C\u00e9dex",
    "sg:orig_category":"Non-Classified Establishments",
    "sg:phone":"+33 1 55 57 16 10",
    "sg:province":"\u00cele-de-France",
    "wof:name":"S\u00e9curit\u00e9 Sans Fronti\u00e8res S.a.s.",
    "wof:placetype":"venue"
},
  "geometry": {"coordinates":[2.22036,48.84441],"type":"Point"}
}