{
  "type": "Feature",
  "properties": {
    "iso:country":"FR",
    "sg:address":"Rue des Biches - B\u00e2t. les Lerracs - Village d'Entreprise",
    "sg:city":"Ville la Grand",
    "sg:orig_category":"Unclassifiable Establishments",
    "sg:phone":"+33 4 50 95 56 53",
    "sg:postcode":"74100",
    "sg:province":"Rhone-Alpes",
    "wof:name":"Reltronix",
    "wof:placetype":"venue"
},
  "geometry": {"coordinates":[6.266748,46.203903],"type":"Point"}
}