{
  "type": "Feature",
  "properties": {
    "addr:full":"77, Rue Bannier, 45000 Orl\u00e9ans Orl\u00e9ans Centre 45000",
    "addr:housenumber":"77",
    "addr:postcode":"45000;45000",
    "addr:street":"Rue Bannier",
    "iso:country":"FR",
    "sg:address":"77, Rue Bannier, 45000 Orl\u00e9ans",
    "sg:city":"Orl\u00e9ans",
    "sg:orig_category":"Non-Classified Establishments",
    "sg:phone":"+33 2 38 62 11 22",
    "sg:postcode":"45000",
    "sg:province":"Centre",
    "wof:name":"C.r.i.t. Int\u00e9rim S.a.",
    "wof:placetype":"venue"
},
  "geometry": {"coordinates":[1.902354,47.904972],"type":"Point"}
}