{
  "type": "Feature",
  "properties": {
    "addr:full":"127, Rte Cols, 65710 Beaudean Midi Pyr\u00e9n\u00e9es",
    "addr:housenumber":"127",
    "addr:postcode":"65710",
    "addr:street":"Rte Cols",
    "iso:country":"FR",
    "sg:address":"127, Rte Cols, 65710 Beaudean",
    "sg:orig_category":"Unclassifiable Establishments",
    "sg:phone":"+33 5 62 91 73 59",
    "sg:province":"Midi Pyr\u00e9n\u00e9es",
    "wof:name":"Etablissements Marcel Cheval S.a.r.l.",
    "wof:placetype":"venue"
},
  "geometry": {"coordinates":[0.164599,43.034393],"type":"Point"}
}