{
  "type": "Feature",
  "properties": {
    "addr:full":"39C, Rue des Buissonn\u00e9es, 38600 Fontaine Rhone-Alpes",
    "addr:housenumber":"39c",
    "addr:postcode":"38600",
    "addr:street":"Rue Des Buissonne\u0301Es",
    "iso:country":"FR",
    "sg:address":"39C, Rue des Buissonn\u00e9es, 38600 Fontaine",
    "sg:orig_category":"Unclassifiable Establishments",
    "sg:phone":"+33 4 76 26 47 88",
    "sg:province":"Rhone-Alpes",
    "wof:name":"E.2.c. S.a.r.l. - Entretien Chauffage Et Climatisation",
    "wof:placetype":"venue"
},
  "geometry": {"coordinates":[5.68858,45.200233],"type":"Point"}
}