{
  "type": "Feature",
  "properties": {
    "addr:full":"01990 Chaneins Rhone-Alpes 01990",
    "addr:postcode":"01990;01990",
    "addr:street":"Rhone-Alpes",
    "iso:country":"FR",
    "sg:address":"01990 Chaneins",
    "sg:orig_category":"Non-Classified Establishments",
    "sg:phone":"+33 4 74 55 87 52",
    "sg:postcode":"01990",
    "sg:province":"Rhone-Alpes",
    "wof:name":"Sablage De Chaneins S.a.r.l.",
    "wof:placetype":"venue"
},
  "geometry": {"coordinates":[4.85112,46.097111],"type":"Point"}
}