{
  "type": "Feature",
  "properties": {
    "iso:country":"FR",
    "sg:address":"Za L'Epaud 85700 St Michel Mont Mercure",
    "sg:classifiers":[
        {
            "category":"Autos & Motor Vehicles",
            "subcategory":"Automobile Sales",
            "type":"Retail Goods"
        }
    ],
    "sg:phone":"+33 2 51 57 24 93",
    "sg:province":"Pays de Loire",
    "sg:tags":[
        "equipment",
        "transport"
    ],
    "wof:name":"Glg",
    "wof:placetype":"venue"
},
  "geometry": {"coordinates":[-0.90579,46.83638],"type":"Point"}
}