{
  "type": "Feature",
  "properties": {
    "addr:full":"19, Rue Jean Perrin, 37170 Chambray l\u00e8s Tours Chambray-l\u00e8s-Tours Centre 37170",
    "addr:housenumber":"19",
    "addr:postcode":"37170;37170",
    "addr:street":"Rue Jean Perrin",
    "iso:country":"FR",
    "sg:address":"19, Rue Jean Perrin, 37170 Chambray l\u00e8s Tours",
    "sg:city":"Chambray-l\u00e8s-Tours",
    "sg:orig_category":"Unclassifiable Establishments",
    "sg:phone":"+33 2 47 28 77 29",
    "sg:postcode":"37170",
    "sg:province":"Centre",
    "wof:name":"Omeca S.a.r.l.",
    "wof:placetype":"venue"
},
  "geometry": {"coordinates":[0.728335,47.345222],"type":"Point"}
}