{
  "type": "Feature",
  "properties": {
    "addr:full":"1 Rue Du Vair Laxou Lorraine 54520",
    "addr:housenumber":"1",
    "addr:postcode":"54520",
    "addr:street":"Rue Du Vair",
    "iso:country":"FR",
    "sg:address":"1 Rue Du Vair",
    "sg:city":"Laxou",
    "sg:classifiers":[
        {
            "category":"Banks & Credit Unions",
            "subcategory":"Financial Services",
            "type":"Services"
        }
    ],
    "sg:phone":"+33 3 83 96 44 55",
    "sg:postcode":"54520",
    "sg:province":"Lorraine",
    "sg:tags":[
        "banking",
        "finance",
        "insurance"
    ],
    "wof:name":"Juxta Sa",
    "wof:placetype":"venue"
},
  "geometry": {"coordinates":[6.124111,48.695415],"type":"Point"}
}