{
  "type": "Feature",
  "properties": {
    "iso:country":"FR",
    "sg:address":"17, Rue Neuilly, 92110 Clichy",
    "sg:orig_category":"Non-Classified Establishments",
    "sg:phone":"+33 1 42 70 30 39",
    "sg:postcode":"92110",
    "sg:province":"Ile de France",
    "wof:name":"3.l. Informatique S.a.r.l.",
    "wof:placetype":"venue"
},
  "geometry": {"coordinates":[2.297332,48.899738],"type":"Point"}
}