{
  "type": "Feature",
  "properties": {
    "addr:full":"ZA de Saint Rambert Saint Genest Malifaux Rhone-Alpes 42660",
    "addr:postcode":"42660",
    "addr:street":"Za De Saint Rambert Saint Genest Malifaux Rhone-Alpes",
    "iso:country":"FR",
    "sg:address":"ZA de Saint Rambert",
    "sg:city":"Saint Genest Malifaux",
    "sg:orig_category":"Unclassifiable Establishments",
    "sg:phone":"+33 4 77 39 03 68",
    "sg:postcode":"42660",
    "sg:province":"Rhone-Alpes",
    "wof:name":"Genest Textile S.a.",
    "wof:placetype":"venue"
},
  "geometry": {"coordinates":[4.42102,45.347435],"type":"Point"}
}