{
  "type": "Feature",
  "properties": {
    "addr:full":"B.P. 619, 85306 Challans C\u00e9dex^^13, Rte de Cholet, 85300 Challans Pays de Loire",
    "addr:housenumber":"b.p. 619",
    "addr:postcode":"85306;85300",
    "addr:street":"Rte De Cholet",
    "iso:country":"FR",
    "sg:address":"B.P. 619, 85306 Challans C\u00e9dex^^13, Rte de Cholet, 85300 Challans",
    "sg:orig_category":"Non-Classified Establishments",
    "sg:phone":"+33 2 51 93 40 40",
    "sg:province":"Pays de Loire",
    "wof:name":"Motoculture Challandaise S.a.",
    "wof:placetype":"venue"
},
  "geometry": {"coordinates":[-1.879324,46.845879],"type":"Point"}
}