{
  "type": "Feature",
  "properties": {
    "addr:full":"Ld St Martin 17600 Le Gua Poitou-Charentes",
    "addr:postcode":"17600",
    "addr:street":"Ld St;Le Gua",
    "iso:country":"FR",
    "sg:address":"Ld St Martin 17600 Le Gua",
    "sg:classifiers":[
        {
            "category":"Home & Garden",
            "subcategory":"Furniture",
            "type":"Retail Goods"
        }
    ],
    "sg:phone":"+33 5 46 22 82 21",
    "sg:province":"Poitou-Charentes",
    "sg:tags":[
        "wood"
    ],
    "wof:name":"Charpent Menuiser Charentaise Le Dannois",
    "wof:placetype":"venue"
},
  "geometry": {"coordinates":[-0.975427,45.736481],"type":"Point"}
}