{
  "type": "Feature",
  "properties": {
    "addr:full":"B.P. 26, 74190 Le Fayet^^99, Av. de Warens, 74190 Passy Rhone-Alpes 74190",
    "addr:postcode":"74190;74190;74190",
    "addr:street":"B.P. 26;Av. De Warens",
    "iso:country":"FR",
    "sg:address":"B.P. 26, 74190 Le Fayet^^99, Av. de Warens, 74190 Passy",
    "sg:orig_category":"Non-Classified Establishments",
    "sg:phone":"+33 4 50 78 06 21",
    "sg:postcode":"74190",
    "sg:province":"Rhone-Alpes",
    "wof:name":"Besson S.a.",
    "wof:placetype":"venue"
},
  "geometry": {"coordinates":[6.685855,45.923489],"type":"Point"}
}