{
  "type": "Feature",
  "properties": {
    "iso:country":"FR",
    "sg:address":"28, Rue de Courtine, 41100 Vend\u00f4me",
    "sg:city":"Vend\u00f4me",
    "sg:orig_category":"Unclassifiable Establishments",
    "sg:phone":"+33 2 54 77 07 09",
    "sg:postcode":"41100",
    "sg:province":"Centre",
    "wof:name":"Emonet Raymond",
    "wof:placetype":"venue"
},
  "geometry": {"coordinates":[1.17829,47.712414],"type":"Point"}
}