{
  "type": "Feature",
  "properties": {
    "iso:country":"FR",
    "sg:address":"Chem Des Oliviers 30130 Pont St Esprit",
    "sg:classifiers":[
        {
            "category":"Food & Beverages",
            "subcategory":"Groceries & Convenience Stores",
            "type":"Retail Goods"
        }
    ],
    "sg:phone":"+33 4 66 90 54 54",
    "sg:postcode":"30130",
    "sg:province":"Languedoc-Roussillon",
    "sg:tags":[
        "product",
        "related"
    ],
    "wof:name":"Huilerie Emile Noel Sas",
    "wof:placetype":"venue"
},
  "geometry": {"coordinates":[4.64125,44.249477],"type":"Point"}
}