{
  "type": "Feature",
  "properties": {
    "addr:full":"Za Le P\u00e9tit Champ Chem Picou 63430 Pont Du Ch\u00e2teau Pont-du-Ch\u00e2teau Auvergne 63430",
    "addr:postcode":"63430;pont-du-cha\u0302teau;63430",
    "addr:street":"Za Le Pe\u0301Tit Champ Chem Picou",
    "iso:country":"FR",
    "sg:address":"Za Le P\u00e9tit Champ Chem Picou 63430 Pont Du Ch\u00e2teau",
    "sg:city":"Pont-du-Ch\u00e2teau",
    "sg:classifiers":[
        {
            "category":"Transit Center",
            "subcategory":"Freight",
            "type":"Transportation"
        }
    ],
    "sg:phone":"+33 4 73 83 71 71",
    "sg:postcode":"63430",
    "sg:province":"Auvergne",
    "sg:tags":[
        "metallurgy",
        "pipe",
        "metalworking",
        "sheet"
    ],
    "wof:name":"Auvergne Alu Sa",
    "wof:placetype":"venue"
},
  "geometry": {"coordinates":[3.22716,45.796024],"type":"Point"}
}