{
  "type": "Feature",
  "properties": {
    "addr:full":"75, Rue Paul Langevin - ZAC de la Robole, 13856 Aix-en-Provence C\u00e9dex Provence-Alpes-C\u00f4te d'Azur",
    "addr:housenumber":"75",
    "addr:postcode":"13856",
    "addr:street":"Rue Paul Langevin Zac De La Robole;Ce\u0301Dex",
    "iso:country":"FR",
    "sg:address":"75, Rue Paul Langevin - ZAC de la Robole, 13856 Aix-en-Provence C\u00e9dex",
    "sg:orig_category":"Non-Classified Establishments",
    "sg:phone":"+33 4 42 97 52 25",
    "sg:province":"Provence-Alpes-C\u00f4te d'Azur",
    "wof:name":"Sadimato Les Ma\u00eetres D'eau S.a.",
    "wof:placetype":"venue"
},
  "geometry": {"coordinates":[5.4542,43.52494],"type":"Point"}
}