{
  "type": "Feature",
  "properties": {
    "iso:country":"FR",
    "sg:address":"B.P. 15, 80520 Woincourt^^28, Rue de la R\u00e9publique - Ysengremer , 80520 Yzengremer",
    "sg:orig_category":"Non-Classified Establishments",
    "sg:phone":"+33 3 22 30 03 51",
    "sg:province":"Picardie",
    "wof:name":"Holleville Jean-claude S.a.r.l.",
    "wof:placetype":"venue"
},
  "geometry": {"coordinates":[1.53884,50.06715],"type":"Point"}
}