{
  "type": "Feature",
  "properties": {
    "iso:country":"FR",
    "sg:address":"CD 412 - Zone Industrielle Nord",
    "sg:city":"Amiens",
    "sg:orig_category":"Unclassifiable Establishments",
    "sg:phone":"+33 3 22 43 11 11",
    "sg:postcode":"80000",
    "sg:province":"Picardie",
    "wof:name":"Den Hartogh S.a.",
    "wof:placetype":"venue"
},
  "geometry": {"coordinates":[2.293165,49.894733],"type":"Point"}
}