{
  "type": "Feature",
  "properties": {
    "addr:full":"12 Rue Du Port De La Celle 77670 St Mammet Ile de France 77670",
    "addr:housenumber":"12",
    "addr:postcode":"77670;77670",
    "addr:street":"Rue Du Port De La Celle",
    "iso:country":"FR",
    "sg:address":"12 Rue Du Port De La Celle 77670 St Mammet",
    "sg:classifiers":[
        {
            "category":"Professional",
            "subcategory":"Engineering",
            "type":"Services"
        }
    ],
    "sg:phone":"+33 1 64 70 71 00",
    "sg:postcode":"77670",
    "sg:province":"Ile de France",
    "sg:tags":[
        "machine",
        "-",
        "mechanical"
    ],
    "wof:name":"Airsec Sa",
    "wof:placetype":"venue"
},
  "geometry": {"coordinates":[2.812944,48.383083],"type":"Point"}
}