{
  "type": "Feature",
  "properties": {
    "addr:full":"Za de Coulmer les Roussiers 61230 Coulmer Coulmer Basse Normandie 61230",
    "addr:postcode":"61230;61230",
    "addr:street":"Za De Coulmer Les Roussiers",
    "iso:country":"FR",
    "sg:address":"Za de Coulmer les Roussiers 61230 Coulmer",
    "sg:city":"Coulmer",
    "sg:classifiers":[
        {
            "category":"Manufacturing",
            "subcategory":"Rubber & Plastics",
            "type":"Manufacturing & Wholesale Goods"
        }
    ],
    "sg:phone":"+33 2 33 12 42 42",
    "sg:postcode":"61230",
    "sg:province":"Basse Normandie",
    "sg:tags":[
        "processing"
    ],
    "wof:name":"C.d.p. Laboratoires S.a.",
    "wof:placetype":"venue"
},
  "geometry": {"coordinates":[0.29757,48.774845],"type":"Point"}
}