{
  "type": "Feature",
  "properties": {
    "addr:full":"3, Rue Marise Basti\u00e9, 64600 Anglet Anglet Aquitaine 64600",
    "addr:housenumber":"3",
    "addr:postcode":"64600;64600",
    "addr:street":"Rue Marise Bastie\u0301",
    "iso:country":"FR",
    "sg:address":"3, Rue Marise Basti\u00e9, 64600 Anglet",
    "sg:city":"Anglet",
    "sg:orig_category":"Unclassifiable Establishments",
    "sg:phone":"+33 5 59 42 56 56",
    "sg:postcode":"64600",
    "sg:province":"Aquitaine",
    "wof:name":"B.a.b. Assainissement S.a.",
    "wof:placetype":"venue"
},
  "geometry": {"coordinates":[-1.514707,43.481705],"type":"Point"}
}