{
  "type": "Feature",
  "properties": {
    "iso:country":"FR",
    "sg:address":"4, Rue du Bignon - B\u00e2t. 2, 35044 Rennes C\u00e9dex",
    "sg:orig_category":"Unclassifiable Establishments",
    "sg:phone":"+33 2 99 22 76 22",
    "sg:province":"Bretagne",
    "wof:name":"G.t.b. Bouyer-duchemin S.a. - Grands Travaux De Bretagne",
    "wof:placetype":"venue"
},
  "geometry": {"coordinates":[-1.636896,48.096161],"type":"Point"}
}