{
  "type": "Feature",
  "properties": {
    "addr:full":"Chemin de Verdet Libourne Aquitaine 33500",
    "addr:postcode":"33500",
    "addr:street":"Chemin De Verdet",
    "iso:country":"FR",
    "sg:address":"Chemin de Verdet",
    "sg:city":"Libourne",
    "sg:orig_category":"Unclassifiable Establishments",
    "sg:phone":"+33 5 57 55 50 00",
    "sg:postcode":"33500",
    "sg:province":"Aquitaine",
    "wof:name":"Etablissements Jean Chambon S.a.",
    "wof:placetype":"venue"
},
  "geometry": {"coordinates":[-0.210851,44.903996],"type":"Point"}
}