{
  "type": "Feature",
  "properties": {
    "iso:country":"FR",
    "sg:address":"101/103, Rue Marius Berliet, 69008 Lyon",
    "sg:orig_category":"Unclassifiable Establishments",
    "sg:phone":"+33 4 72 78 80 20",
    "sg:postcode":"69008",
    "sg:province":"Rhone-Alpes",
    "wof:name":"Fico Industrie S.a.",
    "wof:placetype":"venue"
},
  "geometry": {"coordinates":[4.867347,45.738503],"type":"Point"}
}