{
  "type": "Feature",
  "properties": {
    "addr:full":"16 ter, Rue Albert R\u00e9my, 28250 Senonches Senonches Centre 28250",
    "addr:housenumber":"16 ter;senonches",
    "addr:postcode":"28250;28250",
    "addr:street":"Rue Albert Re\u0301My",
    "iso:country":"FR",
    "sg:address":"16 ter, Rue Albert R\u00e9my, 28250 Senonches",
    "sg:city":"Senonches",
    "sg:orig_category":"Non-Classified Establishments",
    "sg:phone":"+33 2 37 37 74 41",
    "sg:postcode":"28250",
    "sg:province":"Centre",
    "wof:name":"S.i.e.c. S.a.r.l. - Soci\u00e9t\u00e9 Industrielle Des Etablissements Colovrey",
    "wof:placetype":"venue"
},
  "geometry": {"coordinates":[1.031437,48.554581],"type":"Point"}
}