{
  "type": "Feature",
  "properties": {
    "addr:full":"B.P. 165, 79104 Thouars^^7, Rue Jean Devaux - ZI le Grand Ros\u00e9, 79100 Thouars Poitou-Charentes",
    "addr:housenumber":"b.p. 165",
    "addr:postcode":"79104;79100",
    "addr:street":"Rue Jean Devaux Zi",
    "iso:country":"FR",
    "sg:address":"B.P. 165, 79104 Thouars^^7, Rue Jean Devaux - ZI le Grand Ros\u00e9, 79100 Thouars",
    "sg:orig_category":"Non-Classified Establishments",
    "sg:phone":"+33 5 49 66 38 34",
    "sg:province":"Poitou-Charentes",
    "wof:name":"La Charpente Thouarsaise S.a.",
    "wof:placetype":"venue"
},
  "geometry": {"coordinates":[-0.099814,46.907261],"type":"Point"}
}