{
  "type": "Feature",
  "properties": {
    "iso:country":"FR",
    "sg:address":"B.P. 15, 56320 Le Faou\u00ebt^^20, Rue de Portz en Haie, 56320 Le Faou\u00ebt",
    "sg:city":"Le Faou\u00ebt",
    "sg:orig_category":"Non-Classified Establishments",
    "sg:phone":"+33 2 97 23 10 89",
    "sg:postcode":"56320",
    "sg:province":"Bretagne",
    "wof:name":"Liv'editions S.a.r.l.",
    "wof:placetype":"venue"
},
  "geometry": {"coordinates":[-3.432314,47.994316],"type":"Point"}
}