{
  "type": "Feature",
  "properties": {
    "iso:country":"FR",
    "sg:address":"74 Av Du Gal De Gaulle 18200 St Amand Montrond",
    "sg:city":"Arpheuilles",
    "sg:classifiers":[
        {
            "category":"Shopping",
            "subcategory":"Clothing, Apparel, & Fashions",
            "type":"Retail Goods"
        }
    ],
    "sg:phone":"+33 2 48 62 01 40",
    "sg:postcode":"18200",
    "sg:province":"Centre",
    "sg:tags":[
        "textile",
        "clothing",
        "clothes"
    ],
    "wof:name":"Rousseau",
    "wof:placetype":"venue"
},
  "geometry": {"coordinates":[2.494069,46.731846],"type":"Point"}
}