{
  "type": "Feature",
  "properties": {
    "iso:country":"FR",
    "sg:address":"15 Rue Du Sagittaire Silic 146 94523 Rungis Cedex",
    "sg:classifiers":[
        {
            "category":"Manufacturing",
            "subcategory":"Printing",
            "type":"Manufacturing & Wholesale Goods"
        }
    ],
    "sg:phone":"+33 1 56 30 99 30",
    "sg:province":"\u00cele-de-France",
    "sg:tags":[
        "publishing"
    ],
    "wof:name":"Photo Polymeres Services (p.p.s.)",
    "wof:placetype":"venue"
},
  "geometry": {"coordinates":[2.35325,48.751419],"type":"Point"}
}