{
  "type": "Feature",
  "properties": {
    "addr:full":"Rte de Cravant - Centre Artisanal 1 Chinon Centre 37500",
    "addr:housenumber":"1",
    "addr:postcode":"37500",
    "addr:street":"Rte De Cravant;Artisanal;Chinon Centre",
    "iso:country":"FR",
    "sg:address":"Rte de Cravant - Centre Artisanal 1",
    "sg:city":"Chinon",
    "sg:orig_category":"Non-Classified Establishments",
    "sg:phone":"+33 2 47 93 18 20",
    "sg:postcode":"37500",
    "sg:province":"Centre",
    "wof:name":"Moron S.a.r.l.",
    "wof:placetype":"venue"
},
  "geometry": {"coordinates":[0.29501,47.17437],"type":"Point"}
}