{
  "type": "Feature",
  "properties": {
    "addr:full":"1 T Rue Mal De Lattre Tassigny Roubaix Nord Pas-de-Calais 59100",
    "addr:housenumber":"1 t",
    "addr:postcode":"59100",
    "addr:street":"Rue Mal De Lattre Tassigny",
    "iso:country":"FR",
    "sg:address":"1 T Rue Mal De Lattre Tassigny",
    "sg:city":"Roubaix",
    "sg:classifiers":[
        {
            "category":"Banks & Credit Unions",
            "subcategory":"Financial Services",
            "type":"Services"
        }
    ],
    "sg:phone":"+33 3 20 45 72 00",
    "sg:postcode":"59100",
    "sg:province":"Nord Pas-de-Calais",
    "sg:tags":[
        "banking",
        "finance",
        "insurance"
    ],
    "wof:name":"Lloyd Continental",
    "wof:placetype":"venue"
},
  "geometry": {"coordinates":[3.17014,50.683201],"type":"Point"}
}