{
  "type": "Feature",
  "properties": {
    "addr:full":"B.P. 44, 62131 Verquin^^Rue Blaise Pascal, 62800 Li\u00e9vin Nord Pas-de-Calais",
    "addr:postcode":"62131;62800",
    "addr:street":"B.P. 44;Blaise Pascal",
    "iso:country":"FR",
    "sg:address":"B.P. 44, 62131 Verquin^^Rue Blaise Pascal, 62800 Li\u00e9vin",
    "sg:orig_category":"Non-Classified Establishments",
    "sg:phone":"+33 3 21 64 68 80",
    "sg:province":"Nord Pas-de-Calais",
    "wof:name":"Norelec Artois Picardie S.a.",
    "wof:placetype":"venue"
},
  "geometry": {"coordinates":[2.779565,50.4216],"type":"Point"}
}