{
  "type": "Feature",
  "properties": {
    "iso:country":"FR",
    "sg:address":"place ancienne gare 28290 CHAPELLE ROYALE",
    "sg:city":"Arrou",
    "sg:classifiers":[
        {
            "category":"Manufacturing",
            "subcategory":"Rubber & Plastics",
            "type":"Manufacturing & Wholesale Goods"
        }
    ],
    "sg:phone":"+33 2 37 53 50 50",
    "sg:postcode":"28290",
    "sg:province":"Centre",
    "sg:tags":[
        "technical",
        "parts"
    ],
    "wof:name":"A.t.p. S.a.",
    "wof:placetype":"venue"
},
  "geometry": {"coordinates":[1.142689,48.072193],"type":"Point"}
}