{
  "type": "Feature",
  "properties": {
    "addr:full":"ZI de Berret Bagnols sur C\u00e8ze Languedoc-Roussillon 30200",
    "addr:postcode":"30200",
    "addr:street":"Zi De Berret Bagnols Sur Ce\u0300Ze",
    "iso:country":"FR",
    "sg:address":"ZI de Berret",
    "sg:city":"Bagnols sur C\u00e8ze",
    "sg:orig_category":"Non-Classified Establishments",
    "sg:phone":"+33 4 66 90 10 55",
    "sg:postcode":"30200",
    "sg:province":"Languedoc-Roussillon",
    "wof:name":"Sogei S.a.r.l. - Soci\u00e9t\u00e9 Gardoise Etudes Industrielles",
    "wof:placetype":"venue"
},
  "geometry": {"coordinates":[4.62388,44.161461],"type":"Point"}
}