{
  "type": "Feature",
  "properties": {
    "addr:full":"La Croix Blanche Zone Industrielle 44260 Malville Pays de Loire",
    "addr:postcode":"44260",
    "addr:street":"Industrielle",
    "iso:country":"FR",
    "sg:address":"La Croix Blanche Zone Industrielle 44260 Malville",
    "sg:classifiers":[
        {
            "category":"Manufacturing",
            "subcategory":"Wood Products",
            "type":"Manufacturing & Wholesale Goods"
        }
    ],
    "sg:phone":"+33 2 40 56 43 21",
    "sg:province":"Pays de Loire",
    "sg:tags":[
        "professional",
        "furniture"
    ],
    "wof:name":"Savinox",
    "wof:placetype":"venue"
},
  "geometry": {"coordinates":[-1.965349,47.30954],"type":"Point"}
}