{
  "type": "Feature",
  "properties": {
    "iso:country":"FR",
    "sg:address":"Rue Mong\u00e9 - ZI",
    "sg:city":"Saint Brieuc",
    "sg:orig_category":"Unclassifiable Establishments",
    "sg:phone":"+33 2 96 33 42 77",
    "sg:postcode":"22000",
    "sg:province":"Bretagne",
    "wof:name":"S.e.m.a. S.a. - Soci\u00e9t\u00e9 Entreprise M\u00e9tallurgique Amor",
    "wof:placetype":"venue"
},
  "geometry": {"coordinates":[-2.763814,48.515701],"type":"Point"}
}