{
  "type": "Feature",
  "properties": {
    "iso:country":"FR",
    "sg:address":"12 F Rue Franz Heller",
    "sg:city":"Rennes",
    "sg:classifiers":[
        {
            "category":"Banks & Credit Unions",
            "subcategory":"Financial Services",
            "type":"Services"
        }
    ],
    "sg:phone":"+33 2 23 20 92 92",
    "sg:postcode":"35000",
    "sg:province":"Bretagne",
    "sg:tags":[
        "banking",
        "finance",
        "insurance"
    ],
    "wof:name":"La Mondiale",
    "wof:placetype":"venue"
},
  "geometry": {"coordinates":[-1.684477,48.107521],"type":"Point"}
}