{
  "type": "Feature",
  "properties": {
    "addr:full":"37 Place Martyrs; Reze Pays de Loire",
    "addr:housenumber":"37",
    "addr:street":"Place Martyrs Reze",
    "iso:country":"FR",
    "sg:address":"37 Place Martyrs; Reze",
    "sg:classifiers":[
        {
            "category":"Banks & Credit Unions",
            "subcategory":"Bank",
            "type":"Services"
        }
    ],
    "sg:phone":"+33 3340756364",
    "sg:province":"Pays de Loire",
    "wof:name":"Banque Cio",
    "wof:placetype":"venue"
},
  "geometry": {"coordinates":[-1.569829,47.191238],"type":"Point"}
}