{
  "type": "Feature",
  "properties": {
    "iso:country":"FR",
    "sg:address":"110 Chem De Bagatelle 38380 St Laurent Du Pont",
    "sg:classifiers":[
        {
            "category":"Shopping",
            "subcategory":"Bicycles & Sporting Goods",
            "type":"Retail Goods"
        }
    ],
    "sg:phone":"+33 4 76 06 20 24",
    "sg:postcode":"38380",
    "sg:province":"Rhone-Alpes",
    "sg:tags":[
        "product",
        "sport",
        "miscellaneous"
    ],
    "wof:name":"Rossignol Sa",
    "wof:placetype":"venue"
},
  "geometry": {"coordinates":[5.72358,45.391155],"type":"Point"}
}