{
  "type": "Feature",
  "properties": {
    "addr:full":"19, Rue de la Villeneuve, 29200 Brest Brest Bretagne 29200",
    "addr:housenumber":"19",
    "addr:postcode":"29200;29200",
    "addr:street":"Rue De La Villeneuve",
    "iso:country":"FR",
    "sg:address":"19, Rue de la Villeneuve, 29200 Brest",
    "sg:city":"Brest",
    "sg:orig_category":"Unclassifiable Establishments",
    "sg:phone":"+33 2 98 02 04 06",
    "sg:postcode":"29200",
    "sg:province":"Bretagne",
    "wof:name":"Grenat Gestion S.a.r.l.",
    "wof:placetype":"venue"
},
  "geometry": {"coordinates":[-4.463198,48.410278],"type":"Point"}
}