{
  "type": "Feature",
  "properties": {
    "addr:full":"Route De St Georges De Rex 79270 Le Vanneau Irleau Poitou-Charentes 79270",
    "addr:postcode":"79270;79270",
    "addr:street":"Route De St Georges De Rex;Vanneau Irleau",
    "iso:country":"FR",
    "sg:address":"Route De St Georges De Rex 79270 Le Vanneau Irleau",
    "sg:classifiers":[
        {
            "category":"Shopping",
            "subcategory":"Gifts & Souvenirs",
            "type":"Retail Goods"
        }
    ],
    "sg:phone":"+33 5 49 35 00 28",
    "sg:postcode":"79270",
    "sg:province":"Poitou-Charentes",
    "sg:tags":[
        "product",
        "miscellaneous"
    ],
    "wof:name":"Aaz Lievre",
    "wof:placetype":"venue"
},
  "geometry": {"coordinates":[-0.586446,46.205681],"type":"Point"}
}