{
  "type": "Feature",
  "properties": {
    "iso:country":"FR",
    "sg:address":"B.P. 39, 77220 Gretz Armainvilliers^^Rue Amp\u00e8re - ZI, 77220 Gretz Armainvilliers",
    "sg:orig_category":"Non-Classified Establishments",
    "sg:phone":"+33 1 64 25 44 00",
    "sg:province":"Ile de France",
    "wof:name":"Rot S.a.",
    "wof:placetype":"venue"
},
  "geometry": {"coordinates":[2.76256,48.739803],"type":"Point"}
}