{
  "type": "Feature",
  "properties": {
    "addr:full":"Zi Les Paluds BP 1113 Zi Les Paluds 13782 Aubagne Cedex",
    "addr:postcode":"1113;13782",
    "addr:street":"Zi Les Paluds Bp;Zi Les Paluds",
    "iso:country":"FR",
    "sg:address":"Zi Les Paluds BP 1113 Zi Les Paluds 13782 Aubagne Cedex",
    "sg:orig_category":"Mechanical Engineering - machines Paper and cardboard - raw materials Printing and Publishing",
    "sg:phone":"+33 4 42 84 21 01",
    "wof:name":"Serimag Creation",
    "wof:placetype":"venue"
},
  "geometry": {"coordinates":[5.57028,43.293251],"type":"Point"}
}