{
  "type": "Feature",
  "properties": {
    "iso:country":"FR",
    "sg:address":"99 avenue de la Ch\u00e2taigneraie 92500 Rueil Malmaison",
    "sg:classifiers":[
        {
            "category":"Government",
            "subcategory":"Fire Station",
            "type":"Public Place"
        }
    ],
    "sg:phone":"+33 1 47 16 64 00",
    "sg:postcode":"92500",
    "sg:province":"Ile de France",
    "sg:tags":[
        "coal",
        "grilling",
        "charcoal"
    ],
    "wof:name":"S.f.c.c. Sa",
    "wof:placetype":"venue"
},
  "geometry": {"coordinates":[2.178346,48.860359],"type":"Point"}
}