{
  "type": "Feature",
  "properties": {
    "addr:full":"Zi 49270 Saint Christophe La Couperie Pays de Loire 49270",
    "addr:postcode":"49270;49270",
    "addr:street":"Zi;Christophe;Couperie",
    "iso:country":"FR",
    "sg:address":"Zi 49270 Saint Christophe La Couperie",
    "sg:classifiers":[
        {
            "category":"Home & Garden",
            "subcategory":"Furniture",
            "type":"Retail Goods"
        }
    ],
    "sg:phone":"+33 2 40 83 72 78",
    "sg:postcode":"49270",
    "sg:province":"Pays de Loire",
    "sg:tags":[
        "household",
        "wood"
    ],
    "wof:name":"Coiffard Sa",
    "wof:placetype":"venue"
},
  "geometry": {"coordinates":[-1.184474,47.253479],"type":"Point"}
}