{
  "type": "Feature",
  "properties": {
    "addr:full":"All\u00e9e les Miroitiers - ZI Secteur A 4 Saint Laurent du Var Provence-Alpes-C\u00f4te d'Azur 06700",
    "addr:housenumber":"4",
    "addr:postcode":"06700",
    "addr:street":"Alle\u0301E Les Miroitiers Zi;A;Var",
    "iso:country":"FR",
    "sg:address":"All\u00e9e les Miroitiers - ZI Secteur A 4",
    "sg:city":"Saint Laurent du Var",
    "sg:orig_category":"Non-Classified Establishments",
    "sg:phone":"+33 4 93 19 03 03",
    "sg:postcode":"06700",
    "sg:province":"Provence-Alpes-C\u00f4te d'Azur",
    "wof:name":"L.m.r. S.a. - Les M\u00e9caniciens R\u00e9unis",
    "wof:placetype":"venue"
},
  "geometry": {"coordinates":[7.18804,43.678242],"type":"Point"}
}