{
  "type": "Feature",
  "properties": {
    "addr:full":"Av De La R\u00e9sistance 09200 St Girons Midi Pyr\u00e9n\u00e9es 09200",
    "addr:postcode":"09200;09200",
    "addr:street":"Av De La Re\u0301Sistance",
    "iso:country":"FR",
    "sg:address":"Av De La R\u00e9sistance 09200 St Girons",
    "sg:classifiers":[
        {
            "category":"Manufacturing",
            "subcategory":"Glass & Minerals",
            "type":"Manufacturing & Wholesale Goods"
        }
    ],
    "sg:phone":"+33 5 61 66 62 30",
    "sg:postcode":"09200",
    "sg:province":"Midi Pyr\u00e9n\u00e9es",
    "sg:tags":[
        "building",
        "material"
    ],
    "wof:name":"Lafforgue Materiaux Sa",
    "wof:placetype":"venue"
},
  "geometry": {"coordinates":[1.144268,42.979652],"type":"Point"}
}