{
  "type": "Feature",
  "properties": {
    "addr:full":"24, Rue Bartoli, 71160 Digoin Digoin Bourgogne 71160",
    "addr:housenumber":"24",
    "addr:postcode":"71160;71160",
    "addr:street":"Rue Bartoli",
    "iso:country":"FR",
    "sg:address":"24, Rue Bartoli, 71160 Digoin",
    "sg:city":"Digoin",
    "sg:orig_category":"Non-Classified Establishments",
    "sg:phone":"+33 3 85 53 01 81",
    "sg:postcode":"71160",
    "sg:province":"Bourgogne",
    "wof:name":"C.g.s.t. Save S.a.s. - Compagnie Gazi\u00e8re Service Technique Save",
    "wof:placetype":"venue"
},
  "geometry": {"coordinates":[3.980523,46.480072],"type":"Point"}
}