{
  "type": "Feature",
  "properties": {
    "iso:country":"FR",
    "sg:address":"Bourg 53190 Landivy",
    "sg:classifiers":[
        {
            "category":"Farming",
            "subcategory":"Fish & Marine Products",
            "type":"Manufacturing & Wholesale Goods"
        }
    ],
    "sg:phone":"+33 2 43 05 41 35",
    "sg:postcode":"53190",
    "sg:province":"Pays de Loire",
    "sg:tags":[
        "household",
        "miscellaneous",
        "gift"
    ],
    "wof:name":"Etablissements Gontier",
    "wof:placetype":"venue"
},
  "geometry": {"coordinates":[-0.964924,48.448681],"type":"Point"}
}