{
  "type": "Feature",
  "properties": {
    "addr:full":"Rue Pablo Picasso - ZI Nord 2 de Pouvry Rouvignies - Batterie 100 Valenciennes C\u00e9dex Nord-Pas-de-Calais 59328",
    "addr:housenumber":"2;100",
    "addr:postcode":"59328",
    "addr:street":"Rue Pablo Picasso Zi Nord;Batterie;Ce\u0301Dex",
    "iso:country":"FR",
    "sg:address":"Rue Pablo Picasso - ZI Nord 2 de Pouvry Rouvignies - Batterie 100",
    "sg:city":"Valenciennes C\u00e9dex",
    "sg:orig_category":"Non-Classified Establishments",
    "sg:phone":"+33 3 27 21 17 77",
    "sg:postcode":"59328",
    "sg:province":"Nord-Pas-de-Calais",
    "wof:name":"S.o.f.i.p. S.a.r.l. - Soci\u00e9t\u00e9 De Formation Industrielle En Productique",
    "wof:placetype":"venue"
},
  "geometry": {"coordinates":[3.52349,50.357632],"type":"Point"}
}