{
  "type": "Feature",
  "properties": {
    "iso:country":"FR",
    "sg:address":"62720 Rinxent",
    "sg:orig_category":"Unclassifiable Establishments",
    "sg:phone":"+33 3 21 99 53 99",
    "sg:province":"Nord Pas-de-Calais",
    "wof:name":"Carri\u00e8res De La Vall\u00e9e Heureuse S.a.",
    "wof:placetype":"venue"
},
  "geometry": {"coordinates":[1.734544,50.806122],"type":"Point"}
}