{
  "type": "Feature",
  "properties": {
    "iso:country":"FR",
    "sg:address":"Rue Des Galets 02460 La Ferte Milon",
    "sg:classifiers":[
        {
            "category":"Manufacturing",
            "subcategory":"Rubber & Plastics",
            "type":"Manufacturing & Wholesale Goods"
        }
    ],
    "sg:phone":"+33 3 23 96 51 30",
    "sg:province":"Picardie",
    "wof:name":"Vista",
    "wof:placetype":"venue"
},
  "geometry": {"coordinates":[3.12134,49.186131],"type":"Point"}
}