{
  "type": "Feature",
  "properties": {
    "addr:full":"ZA du Wameau Belleville sur Meuse Lorraine 55430",
    "addr:postcode":"55430",
    "addr:street":"Za Du Wameau;Meuse",
    "iso:country":"FR",
    "sg:address":"ZA du Wameau",
    "sg:city":"Belleville sur Meuse",
    "sg:orig_category":"Unclassifiable Establishments",
    "sg:phone":"+33 3 29 84 30 51",
    "sg:postcode":"55430",
    "sg:province":"Lorraine",
    "wof:name":"Geliviandes S.a.",
    "wof:placetype":"venue"
},
  "geometry": {"coordinates":[5.381125,49.174049],"type":"Point"}
}