{
  "type": "Feature",
  "properties": {
    "iso:country":"FR",
    "sg:address":"18, Rue la Cav\u00e9e, 80500 Guerbigny",
    "sg:orig_category":"Unclassifiable Establishments",
    "sg:phone":"+33 3 22 79 72 72",
    "sg:province":"Picardie",
    "wof:name":"Picardie B\u00e9ton - Etablissements Villain S.a.r.l.",
    "wof:placetype":"venue"
},
  "geometry": {"coordinates":[2.66106,49.700119],"type":"Point"}
}