{
  "type": "Feature",
  "properties": {
    "iso:country":"FR",
    "sg:address":"Horizon 2000 Mach 6 Av Des Hauts Grigneux 76420 Bihorel",
    "sg:classifiers":[
        {
            "category":"Professional",
            "subcategory":"Engineering",
            "type":"Services"
        }
    ],
    "sg:phone":"+33 2 35 60 33 60",
    "sg:postcode":"76420",
    "sg:province":"Haute Normandie",
    "sg:tags":[
        "machine",
        "-",
        "mechanical"
    ],
    "wof:name":"Delta Neu Sa",
    "wof:placetype":"venue"
},
  "geometry": {"coordinates":[1.143002,49.46619],"type":"Point"}
}