{
  "type": "Feature",
  "properties": {
    "addr:full":"40, Rue des Entrepreneurs, 75015 Paris Ile de France",
    "addr:housenumber":"40",
    "addr:postcode":"75015",
    "addr:street":"Rue Des Entrepreneurs",
    "iso:country":"FR",
    "sg:address":"40, Rue des Entrepreneurs, 75015 Paris",
    "sg:orig_category":"Unclassifiable Establishments",
    "sg:phone":"+33 1 45 78 25 10",
    "sg:province":"Ile de France",
    "wof:name":"Imprimerie Beaugrenelle Claerhout S.a.r.l.",
    "wof:placetype":"venue"
},
  "geometry": {"coordinates":[2.286331,48.846256],"type":"Point"}
}