{
  "type": "Feature",
  "properties": {
    "iso:country":"FR",
    "sg:address":"B.P. 44, 69540 Irigny^^42, Rue de la Mouche, 69540 Irigny",
    "sg:orig_category":"Non-Classified Establishments",
    "sg:phone":"+33 4 72 66 62 00",
    "sg:postcode":"69540",
    "sg:province":"Rhone-Alpes",
    "wof:name":"Richardson Plastiques S.a.",
    "wof:placetype":"venue"
},
  "geometry": {"coordinates":[4.82194,45.672909],"type":"Point"}
}