{
  "type": "Feature",
  "properties": {
    "iso:country":"FR",
    "sg:address":"14 Av Jean Jaur\u00e8s 13170 Les Pennes Mirabeau",
    "sg:orig_category":"Miscellaneous Products",
    "sg:phone":"+33 4 42 02 80 78",
    "sg:province":"Champagne",
    "wof:name":"Techno-sciences Sarl",
    "wof:placetype":"venue"
},
  "geometry": {"coordinates":[5.291407,43.418938],"type":"Point"}
}