{
  "type": "Feature",
  "properties": {
    "addr:full":"B.P. 72, 59435 Roncq C\u00e9dex^^Rue Norbert S\u00e9gard - ZA les Champs, 59435 Roncq Auvergne",
    "addr:postcode":"59435;59435",
    "addr:street":"B.P. 72;Za Les Champs",
    "iso:country":"FR",
    "sg:address":"B.P. 72, 59435 Roncq C\u00e9dex^^Rue Norbert S\u00e9gard - ZA les Champs, 59435 Roncq",
    "sg:orig_category":"Non-Classified Establishments",
    "sg:phone":"+33 3 20 46 59 88",
    "sg:province":"Auvergne",
    "wof:name":"A.d.j.i. S.a.r.l. - Atelier De D\u00e9coupe De Joints Industriels",
    "wof:placetype":"venue"
},
  "geometry": {"coordinates":[3.1207,50.754189],"type":"Point"}
}