{
  "type": "Feature",
  "properties": {
    "addr:full":"RN 193 Furiani Corse 20600",
    "addr:postcode":"20600",
    "addr:street":"Rn 193;Corse",
    "iso:country":"FR",
    "sg:address":"RN 193",
    "sg:city":"Furiani",
    "sg:orig_category":"Non-Classified Establishments",
    "sg:phone":"+33 4 95 59 20 00",
    "sg:postcode":"20600",
    "sg:province":"Corse",
    "wof:name":"Bianchi S.a.",
    "wof:placetype":"venue"
},
  "geometry": {"coordinates":[9.415856,42.658413],"type":"Point"}
}