{
  "type": "Feature",
  "properties": {
    "addr:full":"Za De L Ecotais 35410 Nouvoitou Nouvoitou Bretagne 35410",
    "addr:postcode":"35410;35410",
    "addr:street":"Za De L Ecotais;Nouvoitou",
    "iso:country":"FR",
    "sg:address":"Za De L Ecotais 35410 Nouvoitou",
    "sg:city":"Nouvoitou",
    "sg:classifiers":[
        {
            "category":"Manufacturing",
            "subcategory":"Paper Products",
            "type":"Manufacturing & Wholesale Goods"
        }
    ],
    "sg:phone":"+33 2 99 37 59 94",
    "sg:postcode":"35410",
    "sg:province":"Bretagne",
    "sg:tags":[
        "finished",
        "cardboard",
        "-"
    ],
    "wof:name":"Bs Synergie",
    "wof:placetype":"venue"
},
  "geometry": {"coordinates":[-1.545554,48.0415],"type":"Point"}
}