{
  "type": "Feature",
  "properties": {
    "iso:country":"FR",
    "sg:address":"171 Rue De Paris 16000 Angoul\u00eame",
    "sg:classifiers":[
        {
            "category":"Professional",
            "subcategory":"Business Services",
            "type":"Services"
        }
    ],
    "sg:phone":"+33 5 45 95 02 68",
    "sg:postcode":"16000",
    "sg:province":"Poitou-Charentes",
    "sg:tags":[
        "training",
        "advice"
    ],
    "wof:name":"College Sainte Marthe Chavagnes",
    "wof:placetype":"venue"
},
  "geometry": {"coordinates":[0.160064,45.653698],"type":"Point"}
}