{
  "type": "Feature",
  "properties": {
    "addr:full":"20 Av Aristide Briand 28000 Chartres Chartres Centre 28000",
    "addr:postcode":"28000;28000",
    "addr:street":"20 Av Aristide Briand",
    "iso:country":"FR",
    "sg:address":"20 Av Aristide Briand 28000 Chartres",
    "sg:city":"Chartres",
    "sg:classifiers":[
        {
            "category":"Professional",
            "subcategory":"Business Services",
            "type":"Services"
        }
    ],
    "sg:phone":"+33 2 37 34 97 88",
    "sg:postcode":"28000",
    "sg:province":"Centre",
    "sg:tags":[
        "training",
        "advice"
    ],
    "wof:name":"College Victor Hugo",
    "wof:placetype":"venue"
},
  "geometry": {"coordinates":[1.521093,48.444798],"type":"Point"}
}