{
  "type": "Feature",
  "properties": {
    "iso:country":"FR",
    "sg:address":"72, Av. Eisenhower, 84000 Avignon",
    "sg:orig_category":"Non-Classified Establishments",
    "sg:phone":"+33 4 90 13 84 84",
    "wof:name":"Rubis Avignon S.a.r.l.",
    "wof:placetype":"venue"
},
  "geometry": {"coordinates":[4.79591,43.93203],"type":"Point"}
}