{
  "type": "Feature",
  "properties": {
    "iso:country":"FR",
    "sg:address":"3, Rue de la Rocade, 70000 Noidans l\u00e8s Vesoul",
    "sg:orig_category":"Non-Classified Establishments",
    "sg:phone":"+33 3 84 76 83 77",
    "sg:province":"Franche Comt\u00e9",
    "wof:name":"I.f.c. Travaux S.a.r.l.",
    "wof:placetype":"venue"
},
  "geometry": {"coordinates":[6.134583,47.617867],"type":"Point"}
}