{
  "type": "Feature",
  "properties": {
    "addr:full":"48, Rue Nicolas Leblanc, 59000 Lille Nord Pas-de-Calais 59000",
    "addr:housenumber":"48",
    "addr:postcode":"59000;59000",
    "addr:street":"Rue Nicolas Leblanc",
    "iso:country":"FR",
    "sg:address":"48, Rue Nicolas Leblanc, 59000 Lille",
    "sg:orig_category":"Non-Classified Establishments",
    "sg:phone":"+33 3 20 54 17 78",
    "sg:postcode":"59000",
    "sg:province":"Nord Pas-de-Calais",
    "wof:name":"Diaphor S.a.r.l.",
    "wof:placetype":"venue"
},
  "geometry": {"coordinates":[3.061098,50.628685],"type":"Point"}
}