{
  "type": "Feature",
  "properties": {
    "addr:full":"67, Rue de Nantes, 59200 Tourcoing Nord Pas-de-Calais",
    "addr:housenumber":"67",
    "addr:postcode":"59200",
    "addr:street":"Rue De Nantes",
    "iso:country":"FR",
    "sg:address":"67, Rue de Nantes, 59200 Tourcoing",
    "sg:orig_category":"Non-Classified Establishments",
    "sg:phone":"+33 3 20 28 98 28",
    "sg:province":"Nord Pas-de-Calais",
    "wof:name":"Ferreira S.a.r.l.",
    "wof:placetype":"venue"
},
  "geometry": {"coordinates":[3.1653,50.709129],"type":"Point"}
}