{
  "type": "Feature",
  "properties": {
    "addr:full":"Parc d'Act. Vesoul Technologia Vesoul Franche Comt\u00e9 70000",
    "addr:postcode":"70000",
    "addr:street":"Franche Comte\u0301",
    "iso:country":"FR",
    "sg:address":"Parc d'Act. Vesoul Technologia",
    "sg:city":"Vesoul",
    "sg:orig_category":"Unclassifiable Establishments",
    "sg:phone":"+33 3 84 75 63 01",
    "sg:postcode":"70000",
    "sg:province":"Franche Comt\u00e9",
    "wof:name":"Vesoul Electro Diesel S.a.",
    "wof:placetype":"venue"
},
  "geometry": {"coordinates":[6.157128,47.620365],"type":"Point"}
}