{
  "type": "Feature",
  "properties": {
    "iso:country":"FR",
    "sg:address":"87 Rue De Lannoy 59800 Lille Cedex",
    "sg:classifiers":[
        {
            "category":"Manufacturing",
            "subcategory":"Rubber & Plastics",
            "type":"Manufacturing & Wholesale Goods"
        }
    ],
    "sg:phone":"+33 3 20 56 86 35",
    "sg:province":"Nord Pas-de-Calais",
    "sg:tags":[
        "packaging",
        "material",
        "-"
    ],
    "wof:name":"Plastiques Cim Sa",
    "wof:placetype":"venue"
},
  "geometry": {"coordinates":[3.094624,50.63414],"type":"Point"}
}