{
  "type": "Feature",
  "properties": {
    "addr:full":"43 Rue Marcel Brot 54017 Nancy Cedex Rhone-Alpes",
    "addr:housenumber":"43",
    "addr:postcode":"54017",
    "addr:street":"Rue Marcel Brot",
    "iso:country":"FR",
    "sg:address":"43 Rue Marcel Brot 54017 Nancy Cedex",
    "sg:classifiers":[
        {
            "category":"Professional",
            "subcategory":"Business Services",
            "type":"Services"
        }
    ],
    "sg:phone":"+33 3 83 39 28 00",
    "sg:province":"Rhone-Alpes",
    "sg:tags":[
        "travel",
        "-",
        "transport",
        "road",
        "air"
    ],
    "wof:name":"Danzas Sa",
    "wof:placetype":"venue"
},
  "geometry": {"coordinates":[6.204085,48.681171],"type":"Point"}
}