{
  "type": "Feature",
  "properties": {
    "iso:country":"FR",
    "sg:address":"avenue de la Peyrinie 12000 Rodez",
    "sg:classifiers":[
        {
            "category":"Professional",
            "subcategory":"Accounting & Tax Preparation",
            "type":"Services"
        }
    ],
    "sg:phone":"+33 5 65 42 21 13",
    "sg:postcode":"12000",
    "sg:province":"Midi Pyr\u00e9n\u00e9es",
    "sg:tags":[
        "balance"
    ],
    "wof:name":"Actbep S.a.r.l.",
    "wof:placetype":"venue"
},
  "geometry": {"coordinates":[2.541011,44.373802],"type":"Point"}
}