{
  "type": "Feature",
  "properties": {
    "addr:full":"B.P. 15, 62452 Bapaume C\u00e9dex^^6, Rue de Douai, 62450 Bapaume Nord Pas-de-Calais",
    "addr:postcode":"62452;62450",
    "addr:street":"B.P. 15;Rue De Douai",
    "iso:country":"FR",
    "sg:address":"B.P. 15, 62452 Bapaume C\u00e9dex^^6, Rue de Douai, 62450 Bapaume",
    "sg:orig_category":"Non-Classified Establishments",
    "sg:phone":"+33 3 21 59 88 00",
    "sg:province":"Nord Pas-de-Calais",
    "wof:name":"Soci\u00e9t\u00e9 D'affr\u00eatement Transport Routier Artois S.a.",
    "wof:placetype":"venue"
},
  "geometry": {"coordinates":[2.84946,50.10318],"type":"Point"}
}