{
  "type": "Feature",
  "properties": {
    "addr:full":"All L'Argiri\u00e8re 87036 Limoges Limoges Limousin 87280",
    "addr:postcode":"87036;87280",
    "addr:street":"\u0300Re",
    "iso:country":"FR",
    "sg:address":"All L'Argiri\u00e8re 87036 Limoges",
    "sg:city":"Limoges",
    "sg:classifiers":[
        {
            "category":"Professional",
            "subcategory":"Business Services",
            "type":"Services"
        }
    ],
    "sg:phone":"+33 5 55 01 59 66",
    "sg:postcode":"87280",
    "sg:province":"Limousin",
    "sg:tags":[
        "training",
        "advice"
    ],
    "wof:name":"College Nationalise Albert Calmette",
    "wof:placetype":"venue"
},
  "geometry": {"coordinates":[1.225427,45.828953],"type":"Point"}
}