{
  "type": "Feature",
  "properties": {
    "iso:country":"FR",
    "sg:address":"ZA Man\u00e9 Coedigo 56880 Ploeren",
    "sg:city":"Ploeren",
    "sg:classifiers":[
        {
            "category":"Recreation",
            "subcategory":"Sailing Club",
            "type":"Entertainment"
        }
    ],
    "sg:phone":"+33 2 97 40 06 00",
    "sg:postcode":"56880",
    "sg:province":"Bretagne",
    "sg:tags":[
        "sailboat"
    ],
    "wof:name":"Seagull Chars \u00e0 Voile",
    "wof:placetype":"venue"
},
  "geometry": {"coordinates":[-2.857454,47.6586],"type":"Point"}
}