{
  "type": "Feature",
  "properties": {
    "iso:country":"FR",
    "sg:address":"Rte de Ch\u00eane Brault",
    "sg:city":"Iteuil",
    "sg:orig_category":"Non-Classified Establishments",
    "sg:phone":"+33 5 49 89 02 02",
    "sg:postcode":"86240",
    "sg:province":"Poitou-Charentes",
    "wof:name":"S.t.a.f. S.a. - Soci\u00e9t\u00e9 De Transports Arpi Ferdovel",
    "wof:placetype":"venue"
},
  "geometry": {"coordinates":[0.301075,46.48605],"type":"Point"}
}