{
  "type": "Feature",
  "properties": {
    "iso:country":"FR",
    "sg:address":"13 R Louis Grandchavin 39400 Morez",
    "sg:classifiers":[
        {
            "category":"Manufacturing",
            "subcategory":"Paper Products",
            "type":"Manufacturing & Wholesale Goods"
        }
    ],
    "sg:phone":"+33 3 84 33 02 46",
    "sg:province":"Franche Comt\u00e9",
    "sg:tags":[
        "packaging",
        "material",
        "-",
        "cardboard"
    ],
    "wof:name":"Cornier Emballage Sarl",
    "wof:placetype":"venue"
},
  "geometry": {"coordinates":[6.022159,46.517147],"type":"Point"}
}