{
  "type": "Feature",
  "properties": {
    "addr:full":"Broissieu 73340 Bellecombe En Bauges Rhone-Alpes 73340",
    "addr:postcode":"73340;73340",
    "addr:street":"Broissieu;Rhone-Alpes",
    "iso:country":"FR",
    "sg:address":"Broissieu 73340 Bellecombe En Bauges",
    "sg:classifiers":[
        {
            "category":"Building & Trades",
            "subcategory":"Construction",
            "type":"Services"
        }
    ],
    "sg:phone":"+33 4 79 63 31 07",
    "sg:postcode":"73340",
    "sg:province":"Rhone-Alpes",
    "sg:tags":[
        "livestock",
        "business",
        "advice",
        "animal",
        "breeding",
        "agriculture"
    ],
    "wof:name":"Oxalis",
    "wof:placetype":"venue"
},
  "geometry": {"coordinates":[6.12376,45.738674],"type":"Point"}
}