{
  "type": "Feature",
  "properties": {
    "iso:country":"FR",
    "sg:address":"8, Rue de la Michodi\u00e8re, 75002 Paris",
    "sg:orig_category":"Unclassifiable Establishments",
    "sg:phone":"+33 1 47 42 10 10",
    "sg:province":"Ile de France",
    "wof:name":"M.a.c. 10 S.a.r.l. - Marketing Analyse Cr\u00e9ation",
    "wof:placetype":"venue"
},
  "geometry": {"coordinates":[2.334904,48.869656],"type":"Point"}
}