{
  "type": "Feature",
  "properties": {
    "addr:full":"92245 Malakoff C\u00e9dex^^102, Rue Etienne Dolet, 92240 Malakoff Ile de France",
    "addr:postcode":"92245;92240;ile",
    "addr:street":"Rue Etienne Dolet",
    "iso:country":"FR",
    "sg:address":"92245 Malakoff C\u00e9dex^^102, Rue Etienne Dolet, 92240 Malakoff",
    "sg:orig_category":"Non-Classified Establishments",
    "sg:phone":"+33 1 41 48 48 60",
    "sg:province":"Ile de France",
    "wof:name":"Planisware S.a.",
    "wof:placetype":"venue"
},
  "geometry": {"coordinates":[2.30092,48.821194],"type":"Point"}
}