{
  "type": "Feature",
  "properties": {
    "iso:country":"FR",
    "sg:address":"Vall\u00e9e de Seine - A\u00e9roport Rouen",
    "sg:city":"Boos",
    "sg:orig_category":"Non-Classified Establishments",
    "sg:phone":"+33 2 35 80 43 12",
    "sg:postcode":"76520",
    "sg:province":"Haute Normandie",
    "wof:name":"Saga Air S.a.",
    "wof:placetype":"venue"
},
  "geometry": {"coordinates":[1.17631,49.401428],"type":"Point"}
}