{
  "type": "Feature",
  "properties": {
    "iso:country":"FR",
    "sg:address":"B.P. 114, 59452 Toufflers C\u00e9dex^^ZI de Roubaix Est, 59452 Toufflers",
    "sg:orig_category":"Non-Classified Establishments",
    "sg:phone":"+33 3 20 89 37 89",
    "sg:province":"Nord Pas-de-Calais",
    "wof:name":"Probois S.a.",
    "wof:placetype":"venue"
},
  "geometry": {"coordinates":[3.21269,50.673889],"type":"Point"}
}