{
  "type": "Feature",
  "properties": {
    "addr:full":"5 R Des Fr\u00e8res Lumi\u00e8re 57200 Sarreguemines Lorraine 57200",
    "addr:housenumber":"5",
    "addr:postcode":"57200;57200",
    "addr:street":"R Des Fre\u0300Res Lumie\u0300Re",
    "iso:country":"FR",
    "sg:address":"5 R Des Fr\u00e8res Lumi\u00e8re 57200 Sarreguemines",
    "sg:classifiers":[
        {
            "category":"Utilities",
            "subcategory":"Electric",
            "type":"Services"
        }
    ],
    "sg:phone":"+33 3 87 98 14 24",
    "sg:postcode":"57200",
    "sg:province":"Lorraine",
    "sg:tags":[
        "electricity",
        "electronic",
        "electrical",
        "equipment"
    ],
    "wof:name":"Schwartz-hum Antenne-service",
    "wof:placetype":"venue"
},
  "geometry": {"coordinates":[7.096815,49.111595],"type":"Point"}
}