{
  "type": "Feature",
  "properties": {
    "addr:full":"Rue Principale 57510 Remering L\u00e8s Puttelange Lorraine 57510",
    "addr:postcode":"57510;57510",
    "addr:street":"Rue Principale;Puttelange Lorraine",
    "iso:country":"FR",
    "sg:address":"Rue Principale 57510 Remering L\u00e8s Puttelange",
    "sg:classifiers":[
        {
            "category":"Manufacturing",
            "subcategory":"Metals",
            "type":"Manufacturing & Wholesale Goods"
        }
    ],
    "sg:phone":"+33 3 87 09 41 08",
    "sg:postcode":"57510",
    "sg:province":"Lorraine",
    "sg:tags":[
        "metallurgy",
        "metalworking"
    ],
    "wof:name":"Sarl Fonderie Klein",
    "wof:placetype":"venue"
},
  "geometry": {"coordinates":[6.94027,49.03566],"type":"Point"}
}