{
  "type": "Feature",
  "properties": {
    "iso:country":"FR",
    "sg:address":"25 R De La R\u00e9publique 86000 Poitiers",
    "sg:classifiers":[
        {
            "category":"Professional",
            "type":"Services"
        }
    ],
    "sg:phone":"+33 5 49 88 28 56",
    "sg:province":"Poitou-Charentes",
    "sg:tags":[
        "transport",
        "road"
    ],
    "wof:name":"Mory Team Sa",
    "wof:placetype":"venue"
},
  "geometry": {"coordinates":[0.34194,46.61274],"type":"Point"}
}