{
  "type": "Feature",
  "properties": {
    "addr:full":"1, Rue du Ravelin - Case 64, 58020 Nevers C\u00e9dex Bourgogne",
    "addr:housenumber":"1;64",
    "addr:postcode":"58020",
    "addr:street":"Rue Du Ravelin Case",
    "iso:country":"FR",
    "sg:address":"1, Rue du Ravelin - Case 64, 58020 Nevers C\u00e9dex",
    "sg:orig_category":"Unclassifiable Establishments",
    "sg:phone":"+33 3 86 21 60 00",
    "sg:province":"Bourgogne",
    "wof:name":"E.d.f. - G.d.f. Services",
    "wof:placetype":"venue"
},
  "geometry": {"coordinates":[3.165435,46.987633],"type":"Point"}
}