{
  "type": "Feature",
  "properties": {
    "iso:country":"FR",
    "sg:address":"B.P. 120, 49001 Angers C\u00e9dex 1^^37, Rte de Bouchemaine, 49000 Angers",
    "sg:orig_category":"Non-Classified Establishments",
    "sg:phone":"+33 2 41 74 10 60",
    "sg:postcode":"49000",
    "sg:province":"Pays de Loire",
    "wof:name":"C.e.b. S.a. - Centre Europ\u00e9en De Biotechnologie",
    "wof:placetype":"venue"
},
  "geometry": {"coordinates":[-0.56339,47.46315],"type":"Point"}
}