{
  "type": "Feature",
  "properties": {
    "iso:country":"FR",
    "sg:address":"15 rue des R\u00e9mouleurs 51350 Cormontreuil",
    "sg:classifiers":[
        {
            "category":"Building & Trades",
            "subcategory":"Construction",
            "type":"Services"
        }
    ],
    "sg:phone":"+33 3 26 77 60 50",
    "sg:postcode":"51350",
    "sg:province":"Champagne",
    "sg:tags":[
        "work",
        "welding",
        "mechanical"
    ],
    "wof:name":"R.a.c. Sas",
    "wof:placetype":"venue"
},
  "geometry": {"coordinates":[4.06397,49.21558],"type":"Point"}
}