{
  "type": "Feature",
  "properties": {
    "addr:full":"300 Oratoire 31810 Vernet Midi Pyr\u00e9n\u00e9es 31810",
    "addr:housenumber":"300",
    "addr:postcode":"31810;31810",
    "addr:street":"Oratoire",
    "iso:country":"FR",
    "sg:address":"300",
    "sg:city":"Oratoire 31810 Vernet",
    "sg:classifiers":[
        {
            "category":"Professional",
            "subcategory":"Engineering",
            "type":"Services"
        }
    ],
    "sg:phone":"+33 5 61 08 62 75",
    "sg:postcode":"31810",
    "sg:province":"Midi Pyr\u00e9n\u00e9es",
    "sg:tags":[
        "machine",
        "-",
        "mechanical"
    ],
    "wof:name":"Sudembal (sarl)",
    "wof:placetype":"venue"
},
  "geometry": {"coordinates":[1.426416,43.434147],"type":"Point"}
}