{
  "type": "Feature",
  "properties": {
    "addr:full":"50 Avenue Pierre Piffault 72100 Le Mans Pays de Loire 72100",
    "addr:housenumber":"50",
    "addr:postcode":"72100;72100",
    "addr:street":"Avenue Pierre Piffault",
    "iso:country":"FR",
    "sg:address":"50 Avenue Pierre Piffault 72100 Le Mans",
    "sg:classifiers":[
        {
            "category":"Shopping",
            "subcategory":"Computers & Home Electronics",
            "type":"Retail Goods"
        }
    ],
    "sg:phone":"+33 2 43 84 38 10",
    "sg:postcode":"72100",
    "sg:province":"Pays de Loire",
    "sg:tags":[
        "electronic",
        "electrical",
        "equipment"
    ],
    "wof:name":"Electro-bobinage Angeard Sa",
    "wof:placetype":"venue"
},
  "geometry": {"coordinates":[0.175511,47.973537],"type":"Point"}
}