{
  "type": "Feature",
  "properties": {
    "addr:full":"Route D Orange 84350 COURTHEZON Centre",
    "addr:postcode":"84350",
    "addr:street":"Route D;Courthezon",
    "iso:country":"FR",
    "sg:address":"Route D Orange 84350 COURTHEZON",
    "sg:classifiers":[
        {
            "category":"Wholesale",
            "subcategory":"Wine & Distilled Alcoholic Beverages",
            "type":"Manufacturing & Wholesale Goods"
        }
    ],
    "sg:phone":"+33 4 90 70 42 00",
    "sg:province":"Centre",
    "sg:tags":[
        "french"
    ],
    "wof:name":"Etablissements Du Peloux Et Cie Sa",
    "wof:placetype":"venue"
},
  "geometry": {"coordinates":[4.871881,44.09586],"type":"Point"}
}