{
  "type": "Feature",
  "properties": {
    "iso:country":"FR",
    "sg:address":"2/6, Rue du Bois de l'Epine, 91080 Courcouronnes",
    "sg:orig_category":"Unclassifiable Establishments",
    "sg:phone":"+33 1 60 87 34 34",
    "sg:province":"Ile de France",
    "wof:name":"Routex S.a.",
    "wof:placetype":"venue"
},
  "geometry": {"coordinates":[2.40641,48.627941],"type":"Point"}
}