{
  "type": "Feature",
  "properties": {
    "addr:full":"33250 Pauillac Pauillac Aquitaine 33250",
    "addr:postcode":"33250;33250",
    "iso:country":"FR",
    "sg:address":"33250 Pauillac",
    "sg:city":"Pauillac",
    "sg:orig_category":"Non-Classified Establishments",
    "sg:phone":"+33 5 56 59 05 20",
    "sg:postcode":"33250",
    "sg:province":"Aquitaine",
    "wof:name":"Ch\u00e2teau Grand Puy Lacoste S.a.",
    "wof:placetype":"venue"
},
  "geometry": {"coordinates":[-0.80172,45.189289],"type":"Point"}
}