{
  "type": "Feature",
  "properties": {
    "addr:full":"Bd De L'Europe 14540 Bourgu\u00e9bus Bourgu\u00e9bus Basse Normandie 14540",
    "addr:postcode":"14540;14540",
    "addr:street":"Bd De L'Europe",
    "iso:country":"FR",
    "sg:address":"Bd De L'Europe 14540 Bourgu\u00e9bus",
    "sg:city":"Bourgu\u00e9bus",
    "sg:classifiers":[
        {
            "category":"Professional",
            "type":"Services"
        }
    ],
    "sg:phone":"+33 2 31 15 60 50",
    "sg:postcode":"14540",
    "sg:province":"Basse Normandie",
    "sg:tags":[
        "transport",
        "road"
    ],
    "wof:name":"Gandon Sa",
    "wof:placetype":"venue"
},
  "geometry": {"coordinates":[-0.309188,49.12249],"type":"Point"}
}