{
  "type": "Feature",
  "properties": {
    "iso:country":"FR",
    "sg:address":"Rte de la Clastre",
    "sg:city":"Aouste sur Sye",
    "sg:orig_category":"Unclassifiable Establishments",
    "sg:phone":"+33 4 75 25 56 00",
    "sg:postcode":"26400",
    "sg:province":"Rhone-Alpes",
    "wof:name":"Perrenot Transports S.a.",
    "wof:placetype":"venue"
},
  "geometry": {"coordinates":[5.084799,44.623848],"type":"Point"}
}