{
  "type": "Feature",
  "properties": {
    "addr:full":"ZAC de Moundran Fonsorbes Midi Pyr\u00e9n\u00e9es 31470",
    "addr:postcode":"31470",
    "addr:street":"Zac De Moundran",
    "iso:country":"FR",
    "sg:address":"ZAC de Moundran",
    "sg:city":"Fonsorbes",
    "sg:orig_category":"Non-Classified Establishments",
    "sg:phone":"+33 5 34 47 01 70",
    "sg:postcode":"31470",
    "sg:province":"Midi Pyr\u00e9n\u00e9es",
    "wof:name":"Roh\u00e9 France S.a.s.",
    "wof:placetype":"venue"
},
  "geometry": {"coordinates":[1.23072,43.536751],"type":"Point"}
}