{
  "type": "Feature",
  "properties": {
    "iso:country":"FR",
    "sg:address":"6, Rue Franklin Roosevelt, 69740 Genas",
    "sg:orig_category":"Unclassifiable Establishments",
    "sg:phone":"+33 4 78 90 07 77",
    "sg:postcode":"69740",
    "sg:province":"Rhone-Alpes",
    "wof:name":"I.f.i. S.a.r.l. - International Fitting Inoxydable",
    "wof:placetype":"venue"
},
  "geometry": {"coordinates":[5.000308,45.731804],"type":"Point"}
}