{
  "type": "Feature",
  "properties": {
    "addr:full":"15, Rue de la Perlerie - Parc d'affaires Roosevelt, 69120 Vaulx en Velin Rhone-Alpes 69120",
    "addr:housenumber":"15",
    "addr:postcode":"69120;69120",
    "addr:street":"Rue De La Perlerie Parc D'Affaires",
    "iso:country":"FR",
    "sg:address":"15, Rue de la Perlerie - Parc d'affaires Roosevelt, 69120 Vaulx en Velin",
    "sg:orig_category":"Unclassifiable Establishments",
    "sg:phone":"+33 4 72 37 03 39",
    "sg:postcode":"69120",
    "sg:province":"Rhone-Alpes",
    "wof:name":"Concr\u00e8te S.a.r.l.",
    "wof:placetype":"venue"
},
  "geometry": {"coordinates":[4.929361,45.750607],"type":"Point"}
}