{
  "type": "Feature",
  "properties": {
    "addr:full":"1 Rue Villaret De Joyeuse 75017 Paris Ile de France 75017",
    "addr:housenumber":"1",
    "addr:postcode":"75017;75017",
    "addr:street":"Rue Villaret De Joyeuse",
    "iso:country":"FR",
    "sg:address":"1 Rue Villaret De Joyeuse 75017 Paris",
    "sg:classifiers":[
        {
            "category":"Manufacturing",
            "subcategory":"Metals",
            "type":"Manufacturing & Wholesale Goods"
        }
    ],
    "sg:phone":"+33 1 48 88 88 88",
    "sg:postcode":"75017",
    "sg:province":"Ile de France",
    "sg:tags":[
        "-",
        "machine",
        "equipment",
        "engineering",
        "machinery",
        "mechanical"
    ],
    "wof:name":"S I E M Sa",
    "wof:placetype":"venue"
},
  "geometry": {"coordinates":[2.289049,48.876156],"type":"Point"}
}