{
  "type": "Feature",
  "properties": {
    "iso:country":"FR",
    "sg:address":"Domaine de la Voute",
    "sg:city":"Ambleville",
    "sg:orig_category":"Non-Classified Establishments",
    "sg:phone":"+33 5 45 80 54 61",
    "sg:postcode":"16300",
    "sg:province":"Poitou-Charentes",
    "wof:name":"Ragnaud Sabourin S.a.",
    "wof:placetype":"venue"
},
  "geometry": {"coordinates":[-0.223649,45.569191],"type":"Point"}
}