{
  "type": "Feature",
  "properties": {
    "iso:country":"FR",
    "sg:address":"B.P. 7510, 95040 Cergy Pontoise C\u00e9dex^^16, Rue Paul Painlev\u00e9 - ZI du Vert Galant, 95310 Saint Ouen l",
    "sg:orig_category":"Non-Classified Establishments",
    "sg:phone":"+33 1 30 37 67 67",
    "sg:postcode":"95310",
    "sg:province":"Ile de France",
    "wof:name":"Cobogest S.a.",
    "wof:placetype":"venue"
},
  "geometry": {"coordinates":[2.105935,49.046371],"type":"Point"}
}