{
  "type": "Feature",
  "properties": {
    "iso:country":"FR",
    "sg:address":"92-94, Av. Jean Baptiste Lebas, 59100 Roubaix",
    "sg:orig_category":"Unclassifiable Establishments",
    "sg:phone":"+33 3 20 68 30 68",
    "sg:province":"Nord Pas-de-Calais",
    "wof:name":"Arlor S.a.",
    "wof:placetype":"venue"
},
  "geometry": {"coordinates":[3.166757,50.69442],"type":"Point"}
}