{
  "type": "Feature",
  "properties": {
    "addr:full":"92-94, Av. Jean Baptiste Lebas, 59100 Roubaix Nord Pas-de-Calais",
    "addr:housenumber":"92-94",
    "addr:postcode":"59100",
    "addr:street":"Av. Jean Baptiste Lebas",
    "iso:country":"FR",
    "sg:address":"92-94, Av. Jean Baptiste Lebas, 59100 Roubaix",
    "sg:orig_category":"Unclassifiable Establishments",
    "sg:phone":"+33 3 20 68 30 68",
    "sg:province":"Nord Pas-de-Calais",
    "wof:name":"Arlor S.a.",
    "wof:placetype":"venue"
},
  "geometry": {"coordinates":[3.166757,50.69442],"type":"Point"}
}