{
  "type": "Feature",
  "properties": {
    "addr:full":"93, Rue Alexandre Fourny, 94500 Champigny sur Marne Ile de France",
    "addr:housenumber":"93",
    "addr:postcode":"94500",
    "addr:street":"Rue Alexandre Fourny",
    "iso:country":"FR",
    "sg:address":"93, Rue Alexandre Fourny, 94500 Champigny sur Marne",
    "sg:orig_category":"Unclassifiable Establishments",
    "sg:phone":"+33 1 45 16 60 60",
    "sg:province":"Ile de France",
    "wof:name":"Serflex S.a.",
    "wof:placetype":"venue"
},
  "geometry": {"coordinates":[2.524109,48.818962],"type":"Point"}
}