{
  "type": "Feature",
  "properties": {
    "addr:full":"Route De Gange Cc Trifontaine 34980 St Cl\u00e9ment De Rivi\u00e8re Languedoc-Roussillon 34980",
    "addr:housenumber":"cc trifontaine",
    "addr:postcode":"34980;34980",
    "addr:street":"Route De Gange;Rivie\u0300Re",
    "iso:country":"FR",
    "sg:address":"Route De Gange Cc Trifontaine 34980 St Cl\u00e9ment De Rivi\u00e8re",
    "sg:classifiers":[
        {
            "category":"Travel",
            "subcategory":"Hotels & Motels",
            "type":"Entertainment"
        }
    ],
    "sg:phone":"+33 4 67 52 27 41",
    "sg:postcode":"34980",
    "sg:province":"Languedoc-Roussillon",
    "sg:tags":[
        "hotels",
        "business",
        "restaurant"
    ],
    "wof:name":"Phenix Richelieu",
    "wof:placetype":"venue"
},
  "geometry": {"coordinates":[3.806955,43.69313],"type":"Point"}
}