{
  "type": "Feature",
  "properties": {
    "addr:full":"17, Rue de Ris - ZI des Noues de Seine, 91170 Viry Chatillon Ile de France",
    "addr:housenumber":"17",
    "addr:postcode":"91170",
    "addr:street":"Rue De Ris Zi Des Noues De Seine",
    "iso:country":"FR",
    "sg:address":"17, Rue de Ris - ZI des Noues de Seine, 91170 Viry Chatillon",
    "sg:orig_category":"Unclassifiable Establishments",
    "sg:phone":"+33 1 69 05 13 14",
    "sg:province":"Ile de France",
    "wof:name":"S.b.m. S.a.r.l. - Soci\u00e9t\u00e9 Bravo Martin",
    "wof:placetype":"venue"
},
  "geometry": {"coordinates":[2.375235,48.670761],"type":"Point"}
}