{
  "type": "Feature",
  "properties": {
    "iso:country":"FR",
    "sg:address":"10, Place Alphonse Jourdain, 31000 Toulouse",
    "sg:orig_category":"Unclassifiable Establishments",
    "sg:phone":"+33 5 62 30 12 02",
    "sg:province":"Midi Pyr\u00e9n\u00e9es",
    "wof:name":"Alt\u00e9dia S.a.",
    "wof:placetype":"venue"
},
  "geometry": {"coordinates":[1.430062,43.611145],"type":"Point"}
}