{
  "type": "Feature",
  "properties": {
    "addr:full":"3 Rue Albert Einstein 93200 St Denis Ile de France",
    "addr:housenumber":"3",
    "addr:postcode":"93200",
    "addr:street":"Rue Albert Einstein",
    "iso:country":"FR",
    "sg:address":"3 Rue Albert Einstein 93200 St Denis",
    "sg:classifiers":[
        {
            "category":"Professional",
            "subcategory":"Printing & Photocopies",
            "type":"Services"
        }
    ],
    "sg:phone":"+33 1 41 66 38 38",
    "sg:province":"Ile de France",
    "sg:tags":[
        "publishing"
    ],
    "wof:name":"Posters Services",
    "wof:placetype":"venue"
},
  "geometry": {"coordinates":[2.36801,48.934368],"type":"Point"}
}