{
  "type": "Feature",
  "properties": {
    "addr:full":"5, Rue du march\u00e9 - Immeuble le Triton, 78990 Elancourt Ile de France 78990",
    "addr:housenumber":"5",
    "addr:postcode":"78990;78990",
    "addr:street":"Rue Du Marche\u0301 Immeuble Le Triton;Ile De France",
    "iso:country":"FR",
    "sg:address":"5, Rue du march\u00e9 - Immeuble le Triton, 78990 Elancourt",
    "sg:orig_category":"Non-Classified Establishments",
    "sg:phone":"+33 1 30 66 79 96",
    "sg:postcode":"78990",
    "sg:province":"Ile de France",
    "wof:name":"Erfatec S.a.",
    "wof:placetype":"venue"
},
  "geometry": {"coordinates":[1.948204,48.768364],"type":"Point"}
}