{
  "type": "Feature",
  "properties": {
    "addr:full":"Route De Longue Zone Industrielle 49350 Les Rosiers Sur Loire Pays de Loire",
    "addr:postcode":"49350",
    "addr:street":"Route De Longue Zone Industrielle;Rosiers;Loire",
    "iso:country":"FR",
    "sg:address":"Route De Longue Zone Industrielle 49350 Les Rosiers Sur Loire",
    "sg:classifiers":[
        {
            "category":"Manufacturing",
            "subcategory":"Wood Products",
            "type":"Manufacturing & Wholesale Goods"
        }
    ],
    "sg:phone":"+33 2 41 51 80 93",
    "sg:province":"Pays de Loire",
    "sg:tags":[
        "professional",
        "furniture"
    ],
    "wof:name":"Mda Mobilier Decoration Agencement (mda)",
    "wof:placetype":"venue"
},
  "geometry": {"coordinates":[-0.255384,47.287113],"type":"Point"}
}