{
  "type": "Feature",
  "properties": {
    "addr:full":"RN 10 Par\u00e7ay Meslay Centre 37210",
    "addr:housenumber":"meslay",
    "addr:postcode":"37210",
    "addr:street":"Rn 10 Parc\u0327Ay",
    "iso:country":"FR",
    "sg:address":"RN 10",
    "sg:city":"Par\u00e7ay Meslay",
    "sg:orig_category":"Unclassifiable Establishments",
    "sg:phone":"+33 2 47 29 12 29",
    "sg:postcode":"37210",
    "sg:province":"Centre",
    "wof:name":"Foussier",
    "wof:placetype":"venue"
},
  "geometry": {"coordinates":[0.798817,47.41206],"type":"Point"}
}