{
  "type": "Feature",
  "properties": {
    "iso:country":"FR",
    "sg:address":"12 Rue Nungesser 32270 BLANQUEFORT",
    "sg:classifiers":[
        {
            "category":"Shopping",
            "subcategory":"Stationery & Office Supplies",
            "type":"Retail Goods"
        }
    ],
    "sg:phone":"+33 5 56 57 11 11",
    "sg:province":"Midi Pyr\u00e9n\u00e9es",
    "sg:tags":[
        "packaging"
    ],
    "wof:name":"Ste Emballage Manutention Aquitaine Sarl",
    "wof:placetype":"venue"
},
  "geometry": {"coordinates":[0.770215,43.61504],"type":"Point"}
}