{
  "type": "Feature",
  "properties": {
    "iso:country":"FR",
    "sg:address":"Av de Fl\u00f6ha - Parc de la Gohelle",
    "sg:city":"M\u00e9ricourt",
    "sg:orig_category":"Unclassifiable Establishments",
    "sg:phone":"+33 3 21 74 24 69",
    "sg:postcode":"62680",
    "sg:province":"Nord Pas-de-Calais",
    "wof:name":"Sofiplast S.a.r.l.",
    "wof:placetype":"venue"
},
  "geometry": {"coordinates":[2.870745,50.405327],"type":"Point"}
}