{
  "type": "Feature",
  "properties": {
    "addr:full":"Rte d'Orgerus Septeuil Ile de France 78790",
    "addr:postcode":"78790",
    "addr:street":"Rte D'Orgerus",
    "iso:country":"FR",
    "sg:address":"Rte d'Orgerus",
    "sg:city":"Septeuil",
    "sg:orig_category":"Non-Classified Establishments",
    "sg:phone":"+33 1 30 93 46 68",
    "sg:postcode":"78790",
    "sg:province":"Ile de France",
    "wof:name":"D.d.p. S.a. - D\u00e9lice Du Palais",
    "wof:placetype":"venue"
},
  "geometry": {"coordinates":[1.685049,48.888515],"type":"Point"}
}