{
  "type": "Feature",
  "properties": {
    "addr:full":"Z.A. Champfleury Champfleury Champagne 51500",
    "addr:postcode":"51500",
    "addr:street":"Z.A. Champfleury",
    "iso:country":"FR",
    "sg:address":"Z.A. Champfleury",
    "sg:city":"Champfleury",
    "sg:orig_category":"Non-Classified Establishments",
    "sg:phone":"+33 3 26 77 39 45",
    "sg:postcode":"51500",
    "sg:province":"Champagne",
    "wof:name":"M.g. R\u00e9alisation S.a.r.l.",
    "wof:placetype":"venue"
},
  "geometry": {"coordinates":[4.094877,49.213875],"type":"Point"}
}