{
  "type": "Feature",
  "properties": {
    "addr:full":"38118 Hi\u00e8res sur Amby Rhone-Alpes",
    "addr:postcode":"38118",
    "addr:street":"Hie\u0300Res;Amby Rhone-Alpes",
    "iso:country":"FR",
    "sg:address":"38118 Hi\u00e8res sur Amby",
    "sg:orig_category":"Unclassifiable Establishments",
    "sg:phone":"+33 4 74 95 15 55",
    "sg:province":"Rhone-Alpes",
    "wof:name":"Carrel S.a.",
    "wof:placetype":"venue"
},
  "geometry": {"coordinates":[5.298314,45.798771],"type":"Point"}
}