{
  "type": "Feature",
  "properties": {
    "iso:country":"FR",
    "sg:address":"ZA de Lapra",
    "sg:city":"Saint Bonnet les Oules",
    "sg:orig_category":"Non-Classified Establishments",
    "sg:phone":"+33 4 77 54 15 87",
    "sg:postcode":"42330",
    "sg:province":"Rhone-Alpes",
    "wof:name":"Bourgin S.a.r.l.",
    "wof:placetype":"venue"
},
  "geometry": {"coordinates":[4.32775,45.54314],"type":"Point"}
}