{
  "type": "Feature",
  "properties": {
    "iso:country":"FR",
    "sg:address":"Rte de Versillat - Z.I.",
    "sg:city":"La Souterraine",
    "sg:orig_category":"Unclassifiable Establishments",
    "sg:phone":"+33 5 55 89 49 49",
    "sg:postcode":"23300",
    "sg:province":"Limousin",
    "wof:name":"A.i.e. S.a. - Aries Industries Emboutissage",
    "wof:placetype":"venue"
},
  "geometry": {"coordinates":[1.53526,46.201057],"type":"Point"}
}