{
  "type": "Feature",
  "properties": {
    "addr:full":"1 A Route De Metz 57190 Florange Lorraine 57190",
    "addr:housenumber":"1 a",
    "addr:postcode":"57190;57190",
    "addr:street":"Route De Metz",
    "iso:country":"FR",
    "sg:address":"1 A Route De Metz 57190 Florange",
    "sg:classifiers":[
        {
            "category":"Government",
            "subcategory":"Department Of Motor Vehicles",
            "type":"Public Place"
        }
    ],
    "sg:phone":"+33 3 82 34 30 18",
    "sg:postcode":"57190",
    "sg:province":"Lorraine",
    "sg:tags":[
        "equipment",
        "industrial",
        "transport",
        "motor-cars"
    ],
    "wof:name":"Sarl Auto Casse Florange",
    "wof:placetype":"venue"
},
  "geometry": {"coordinates":[6.15335,49.325581],"type":"Point"}
}