{
  "type": "Feature",
  "properties": {
    "addr:full":"Av. des Pommerets Till\u00e9 Picardie 60000",
    "addr:postcode":"60000",
    "addr:street":"Av. Des Pommerets;Picardie",
    "iso:country":"FR",
    "sg:address":"Av. des Pommerets",
    "sg:city":"Till\u00e9",
    "sg:orig_category":"Unclassifiable Establishments",
    "sg:phone":"+33 3 44 11 17 17",
    "sg:postcode":"60000",
    "sg:province":"Picardie",
    "wof:name":"Escort Informatique S.a.",
    "wof:placetype":"venue"
},
  "geometry": {"coordinates":[2.09672,49.457596],"type":"Point"}
}