{
  "type": "Feature",
  "properties": {
    "iso:country":"FR",
    "sg:address":"Avenue Jean Moos 69550 AMPLEPUIS",
    "sg:classifiers":[
        {
            "category":"Industrial Area",
            "type":"Public Place"
        }
    ],
    "sg:phone":"+33 4 74 89 38 39",
    "sg:province":"Rhone-Alpes",
    "sg:tags":[
        "machine",
        "emulsifying"
    ],
    "wof:name":"Croda Uniser Sa",
    "wof:placetype":"venue"
},
  "geometry": {"coordinates":[4.334767,45.982677],"type":"Point"}
}