{
  "type": "Feature",
  "properties": {
    "addr:full":"Rue Maurice Perin 08090 TOURNES Aiglemont Champagne 08090",
    "addr:postcode":"08090;08090",
    "addr:street":"Rue Maurice Perin;Champagne",
    "iso:country":"FR",
    "sg:address":"Rue Maurice Perin 08090 TOURNES",
    "sg:city":"Aiglemont",
    "sg:classifiers":[
        {
            "category":"Building & Trades",
            "subcategory":"Equipment Rental",
            "type":"Services"
        }
    ],
    "sg:phone":"+33 3 24 59 70 00",
    "sg:postcode":"08090",
    "sg:province":"Champagne",
    "sg:tags":[
        "event"
    ],
    "wof:name":"Mobil-tech-france Sas",
    "wof:placetype":"venue"
},
  "geometry": {"coordinates":[4.632387,49.793259],"type":"Point"}
}