{
  "type": "Feature",
  "properties": {
    "iso:country":"FR",
    "sg:address":"23 rue Saint-Blaise 59200 Tourcoing",
    "sg:classifiers":[
        {
            "category":"Wholesale",
            "subcategory":"Vending Machines",
            "type":"Manufacturing & Wholesale Goods"
        }
    ],
    "sg:phone":"+33 3 20 01 41 29",
    "sg:province":"Nord Pas-de-Calais",
    "sg:tags":[
        "food",
        "special-design",
        "processing",
        "industry"
    ],
    "wof:name":"France Coupe Sarl",
    "wof:placetype":"venue"
},
  "geometry": {"coordinates":[3.157695,50.728832],"type":"Point"}
}