{
  "type": "Feature",
  "properties": {
    "addr:full":"2 Bis Rue De Seignelay 56100 Lorient Lorient Bretagne 56100",
    "addr:housenumber":"2 bis",
    "addr:postcode":"56100;56100",
    "addr:street":"Rue De Seignelay",
    "iso:country":"FR",
    "sg:address":"2 Bis Rue De Seignelay 56100 Lorient",
    "sg:city":"Lorient",
    "sg:classifiers":[
        {
            "category":"Shopping",
            "type":"Retail Goods"
        }
    ],
    "sg:phone":"+33 2 97 37 70 50",
    "sg:postcode":"56100",
    "sg:province":"Bretagne",
    "sg:tags":[
        "metallurgy",
        "finished",
        "-",
        "metalworking",
        "metallic"
    ],
    "wof:name":"Ste Clorec Fournitures Industrielles Sa",
    "wof:placetype":"venue"
},
  "geometry": {"coordinates":[-3.362852,47.73209],"type":"Point"}
}