{
  "type": "Feature",
  "properties": {
    "addr:full":"50 Rue Etienne Marcel Paris Ile de France 75002",
    "addr:housenumber":"50",
    "addr:postcode":"75002",
    "addr:street":"Rue Etienne Marcel",
    "iso:country":"FR",
    "sg:address":"50 Rue Etienne Marcel",
    "sg:city":"Paris",
    "sg:classifiers":[
        {
            "category":"Banks & Credit Unions",
            "subcategory":"Financial Services",
            "type":"Services"
        }
    ],
    "sg:phone":"+33 1 42 33 21 05",
    "sg:postcode":"75002",
    "sg:province":"Ile de France",
    "sg:tags":[
        "banking",
        "finance",
        "insurance"
    ],
    "wof:name":"Prudhomme Scp",
    "wof:placetype":"venue"
},
  "geometry": {"coordinates":[2.342239,48.865635],"type":"Point"}
}