{
  "type": "Feature",
  "properties": {
    "addr:full":"B.P. 2, 08800 Thilay^^Rue du Moulin, 08800 Thilay Deville Champagne 08800",
    "addr:housenumber":"2",
    "addr:postcode":"08800;08800;08800",
    "addr:street":"B.P.;Moulin;Champagne",
    "iso:country":"FR",
    "sg:address":"B.P. 2, 08800 Thilay^^Rue du Moulin, 08800 Thilay",
    "sg:city":"Deville",
    "sg:orig_category":"Non-Classified Establishments",
    "sg:phone":"+33 3 24 33 87 00",
    "sg:postcode":"08800",
    "sg:province":"Champagne",
    "wof:name":"H\u00e9non Fils S.a.",
    "wof:placetype":"venue"
},
  "geometry": {"coordinates":[4.76741,49.882038],"type":"Point"}
}