{
  "type": "Feature",
  "properties": {
    "addr:full":"Le Moulin Cass\u00e9 44710 St Leger Les Vignes Pays de Loire 44710",
    "addr:postcode":"44710;pays;44710",
    "addr:street":"Casse\u0301;Vignes",
    "iso:country":"FR",
    "sg:address":"Le Moulin Cass\u00e9 44710 St Leger Les Vignes",
    "sg:classifiers":[
        {
            "category":"Farming",
            "subcategory":"Farm & Veterinary Services",
            "type":"Manufacturing & Wholesale Goods"
        }
    ],
    "sg:phone":"+33 2 40 65 50 02",
    "sg:postcode":"44710",
    "sg:province":"Pays de Loire",
    "sg:tags":[
        "food",
        "product",
        "breeding",
        "animal",
        "related"
    ],
    "wof:name":"Cooperative Agricole La Noelle Ancenis (cana)",
    "wof:placetype":"venue"
},
  "geometry": {"coordinates":[-1.710394,47.156631],"type":"Point"}
}