{
  "type": "Feature",
  "properties": {
    "addr:full":"Rte de Saint Pompain Benet Pays de Loire 85490",
    "addr:postcode":"85490",
    "addr:street":"Rte De Saint;Benet Pays;Loire",
    "iso:country":"FR",
    "sg:address":"Rte de Saint Pompain",
    "sg:city":"Benet",
    "sg:orig_category":"Non-Classified Establishments",
    "sg:phone":"+33 2 51 53 71 71",
    "sg:postcode":"85490",
    "sg:province":"Pays de Loire",
    "wof:name":"Pomona S.a.",
    "wof:placetype":"venue"
},
  "geometry": {"coordinates":[-0.589282,46.406101],"type":"Point"}
}