{
  "type": "Feature",
  "properties": {
    "addr:full":"RN 516 - Evrieu La B\u00e2tie Montgascon Rhone-Alpes 38110",
    "addr:postcode":"38110",
    "addr:street":"Rn 516 Evrieu La;Rhone-Alpes",
    "iso:country":"FR",
    "sg:address":"RN 516 - Evrieu",
    "sg:city":"La B\u00e2tie Montgascon",
    "sg:orig_category":"Unclassifiable Establishments",
    "sg:phone":"+33 4 74 88 84 06",
    "sg:postcode":"38110",
    "sg:province":"Rhone-Alpes",
    "wof:name":"Mansey Visrivax S.a.",
    "wof:placetype":"venue"
},
  "geometry": {"coordinates":[5.454585,45.52478],"type":"Point"}
}