{
  "type": "Feature",
  "properties": {
    "addr:full":"route de Bourges 18400 ST FLORENT SUR CHER Lunery Centre 18400",
    "addr:postcode":"18400;18400",
    "addr:street":"Route De Bourges",
    "iso:country":"FR",
    "sg:address":"route de Bourges 18400 ST FLORENT SUR CHER",
    "sg:city":"Lunery",
    "sg:classifiers":[
        {
            "category":"Professional",
            "type":"Services"
        }
    ],
    "sg:phone":"+33 2 48 55 02 08",
    "sg:postcode":"18400",
    "sg:province":"Centre",
    "sg:tags":[
        "transport"
    ],
    "wof:name":"Boudet S.a.",
    "wof:placetype":"venue"
},
  "geometry": {"coordinates":[2.244945,46.992325],"type":"Point"}
}