{
  "type": "Feature",
  "properties": {
    "addr:full":"Rue Roncerays Za Du Roncerays 35150 Janz\u00e9 Janz\u00e9 Bretagne 35150",
    "addr:postcode":"35150;35150",
    "addr:street":"Rue Roncerays Za Du Roncerays",
    "iso:country":"FR",
    "sg:address":"Rue Roncerays Za Du Roncerays 35150 Janz\u00e9",
    "sg:city":"Janz\u00e9",
    "sg:classifiers":[
        {
            "category":"Home & Garden",
            "subcategory":"Furniture",
            "type":"Retail Goods"
        }
    ],
    "sg:phone":"+33 2 99 47 04 51",
    "sg:postcode":"35150",
    "sg:province":"Bretagne",
    "sg:tags":[
        "wood"
    ],
    "wof:name":"Chaussee Scop",
    "wof:placetype":"venue"
},
  "geometry": {"coordinates":[-1.495007,47.958996],"type":"Point"}
}