{
  "type": "Feature",
  "properties": {
    "iso:country":"FR",
    "sg:address":"Rue Evariste Galois 86130 Jaunay Clan",
    "sg:classifiers":[
        {
            "category":"Professional",
            "subcategory":"Engineering",
            "type":"Services"
        }
    ],
    "sg:phone":"+33 5 49 62 86 00",
    "sg:postcode":"86130",
    "sg:province":"Poitou-Charentes",
    "sg:tags":[
        "machine",
        "-",
        "mechanical"
    ],
    "wof:name":"Cemep Sas",
    "wof:placetype":"venue"
},
  "geometry": {"coordinates":[0.36217,46.681438],"type":"Point"}
}