{
  "type": "Feature",
  "properties": {
    "addr:full":"11, Rue des Fr\u00e8res Lumi\u00e8re, 45808 Saint Jean de Braye Champagne",
    "addr:housenumber":"11",
    "addr:postcode":"45808",
    "addr:street":"Rue Des Fre\u0300Res Lumie\u0300Re",
    "iso:country":"FR",
    "sg:address":"11, Rue des Fr\u00e8res Lumi\u00e8re, 45808 Saint Jean de Braye",
    "sg:orig_category":"Non-Classified Establishments",
    "sg:phone":"+33 2 38 86 68 53",
    "sg:province":"Champagne",
    "wof:name":"Atelier De M\u00e9tallerie De L'orl\u00e9annais S.a.",
    "wof:placetype":"venue"
},
  "geometry": {"coordinates":[1.946324,47.917938],"type":"Point"}
}