{
  "type": "Feature",
  "properties": {
    "addr:full":"370 Av Napol\u00e9on Bonaparte 92500 Rueil Malmaison Ile de France",
    "addr:housenumber":"370",
    "addr:postcode":"92500",
    "addr:street":"Av Napole\u0301On Bonaparte",
    "iso:country":"FR",
    "sg:address":"370 Av Napol\u00e9on Bonaparte 92500 Rueil Malmaison",
    "sg:classifiers":[
        {
            "category":"Professional",
            "subcategory":"Printing & Photocopies",
            "type":"Services"
        }
    ],
    "sg:phone":"+33 1 47 51 57 47",
    "sg:province":"Ile de France",
    "sg:tags":[
        "publishing"
    ],
    "wof:name":"Continental Hightech Services Sarl",
    "wof:placetype":"venue"
},
  "geometry": {"coordinates":[2.15522,48.869068],"type":"Point"}
}