{
  "type": "Feature",
  "properties": {
    "addr:full":"19, Place Johnston, 33000 Bordeaux Bordeaux Aquitaine 33000",
    "addr:housenumber":"19",
    "addr:postcode":"33000;33000",
    "addr:street":"Place",
    "iso:country":"FR",
    "sg:address":"19, Place Johnston, 33000 Bordeaux",
    "sg:city":"Bordeaux",
    "sg:orig_category":"Non-Classified Establishments",
    "sg:phone":"+33 5 56 51 44 12",
    "sg:postcode":"33000",
    "sg:province":"Aquitaine",
    "wof:name":"Wilson Cojuri S.a.r.l.",
    "wof:placetype":"venue"
},
  "geometry": {"coordinates":[-0.600209,44.82901],"type":"Point"}
}