{
  "type": "Feature",
  "properties": {
    "addr:full":"B.P. 62, 94700 Maisons Alfort^^39, Av. Gambetta, 94700 Maisons Alfort Ile de France 94700",
    "addr:postcode":"94700;94700;94700",
    "addr:street":"B.P. 62;Av. Gambetta",
    "iso:country":"FR",
    "sg:address":"B.P. 62, 94700 Maisons Alfort^^39, Av. Gambetta, 94700 Maisons Alfort",
    "sg:orig_category":"Non-Classified Establishments",
    "sg:phone":"+33 1 43 68 61 20",
    "sg:postcode":"94700",
    "sg:province":"Ile de France",
    "wof:name":"Detex S.a.",
    "wof:placetype":"venue"
},
  "geometry": {"coordinates":[2.431945,48.801445],"type":"Point"}
}