{
  "type": "Feature",
  "properties": {
    "iso:country":"FR",
    "sg:address":"6",
    "sg:city":"Morel 92120 Montrouge",
    "sg:classifiers":[
        {
            "category":"Manufacturing",
            "subcategory":"Paper Products",
            "type":"Manufacturing & Wholesale Goods"
        }
    ],
    "sg:phone":"+33 1 42 53 22 46",
    "sg:province":"Ile de France",
    "sg:tags":[
        "finished",
        "cardboard",
        "-"
    ],
    "wof:name":"Le Papier D'armenie",
    "wof:placetype":"venue"
},
  "geometry": {"coordinates":[2.3185,48.812988],"type":"Point"}
}