{
  "type": "Feature",
  "properties": {
    "addr:full":"Za De La Croix Aiguillon 19270 Ussac Limousin 19270",
    "addr:postcode":"19270;19270",
    "addr:street":"Za De La Croix Aiguillon",
    "iso:country":"FR",
    "sg:address":"Za De La Croix Aiguillon 19270 Ussac",
    "sg:classifiers":[
        {
            "category":"Autos & Motor Vehicles",
            "subcategory":"Automobile Sales",
            "type":"Retail Goods"
        }
    ],
    "sg:phone":"+33 5 55 87 06 00",
    "sg:postcode":"19270",
    "sg:province":"Limousin",
    "sg:tags":[
        "equipment",
        "motor-cars",
        "transport"
    ],
    "wof:name":"Ets Rouvet Sa",
    "wof:placetype":"venue"
},
  "geometry": {"coordinates":[1.50646,45.189976],"type":"Point"}
}