{
  "type": "Feature",
  "properties": {
    "addr:full":"137, Rte de Corbeil, 91160 Longjumeau Ile de France",
    "addr:housenumber":"137",
    "addr:postcode":"91160;ile",
    "addr:street":"Rte De Corbeil",
    "iso:country":"FR",
    "sg:address":"137, Rte de Corbeil, 91160 Longjumeau",
    "sg:orig_category":"Unclassifiable Establishments",
    "sg:phone":"+33 1 49 54 49 54",
    "sg:province":"Ile de France",
    "wof:name":"Les Editions Hatier C.t.r. S.n.c.",
    "wof:placetype":"venue"
},
  "geometry": {"coordinates":[2.310788,48.682938],"type":"Point"}
}