{
  "type": "Feature",
  "properties": {
    "addr:full":"B.P. 59, 49241 Avrill\u00e9 C\u00e9dex^^Chemin de la Beurri\u00e8re, 49240 Avrill\u00e9 Pays de Loire",
    "addr:postcode":"49241;49240",
    "addr:street":"B.P. 59",
    "iso:country":"FR",
    "sg:address":"B.P. 59, 49241 Avrill\u00e9 C\u00e9dex^^Chemin de la Beurri\u00e8re, 49240 Avrill\u00e9",
    "sg:orig_category":"Non-Classified Establishments",
    "sg:phone":"+33 2 41 34 62 34",
    "sg:province":"Pays de Loire",
    "wof:name":"Sacer Atlantique S.a.",
    "wof:placetype":"venue"
},
  "geometry": {"coordinates":[-0.587263,47.504822],"type":"Point"}
}