{
  "type": "Feature",
  "properties": {
    "iso:country":"FR",
    "sg:address":"5, Rue du G\u00e9ant, 02420 Gouy",
    "sg:orig_category":"Unclassifiable Establishments",
    "sg:phone":"+33 3 23 66 20 72",
    "sg:province":"Picardie",
    "wof:name":"Tabary S.a.",
    "wof:placetype":"venue"
},
  "geometry": {"coordinates":[3.254095,50.003777],"type":"Point"}
}