{
  "type": "Feature",
  "properties": {
    "addr:full":"Chemin Trinquet 64210 Guethary Gu\u00e9thary Aquitaine 64210",
    "addr:postcode":"64210;64210",
    "addr:street":"Chemin Trinquet",
    "iso:country":"FR",
    "sg:address":"Chemin Trinquet 64210 Guethary",
    "sg:city":"Gu\u00e9thary",
    "sg:classifiers":[
        {
            "category":"Professional",
            "subcategory":"Business Services",
            "type":"Services"
        }
    ],
    "sg:phone":"+33 5 59 51 89 89",
    "sg:postcode":"64210",
    "sg:province":"Aquitaine",
    "sg:tags":[
        "body",
        "advice"
    ],
    "wof:name":"Vacnciel Herrixta",
    "wof:placetype":"venue"
},
  "geometry": {"coordinates":[-1.616134,43.421028],"type":"Point"}
}