{
  "type": "Feature",
  "properties": {
    "iso:country":"FR",
    "sg:address":"B.P. 54, 59360 Le Cateau Cambr\u00e9sis^^72, Rue Faidherbe, 59360 Le Cateau Cambr\u00e9sis",
    "sg:orig_category":"Non-Classified Establishments",
    "sg:phone":"+33 3 27 84 16 64",
    "sg:postcode":"59360",
    "sg:province":"Nord Pas-de-Calais",
    "wof:name":"Duminy - Ruffin S.a.r.l.",
    "wof:placetype":"venue"
},
  "geometry": {"coordinates":[3.543052,50.105213],"type":"Point"}
}