{
  "type": "Feature",
  "properties": {
    "addr:full":"59, All\u00e9e L\u00e9on Gambetta, 13001 Marseille Poitou-Charentes",
    "addr:housenumber":"59",
    "addr:postcode":"13001",
    "addr:street":"Alle\u0301E Le\u0301On Gambetta",
    "iso:country":"FR",
    "sg:address":"59, All\u00e9e L\u00e9on Gambetta, 13001 Marseille",
    "sg:orig_category":"Unclassifiable Establishments",
    "sg:phone":"+33 4 91 64 44 55",
    "sg:province":"Poitou-Charentes",
    "wof:name":"S.e.t. S.a. - Soci\u00e9t\u00e9 Europ\u00e9enne De Textiles",
    "wof:placetype":"venue"
},
  "geometry": {"coordinates":[5.383957,43.299198],"type":"Point"}
}