{
  "type": "Feature",
  "properties": {
    "iso:country":"FR",
    "sg:address":"336, Rue de Lyon, 13343 Marseille",
    "sg:orig_category":"Unclassifiable Establishments",
    "sg:phone":"+33 4 91 09 46 00",
    "sg:province":"Poitou-Charentes",
    "wof:name":"Saint Louis Sucre S.n.c.",
    "wof:placetype":"venue"
},
  "geometry": {"coordinates":[5.36338,43.336033],"type":"Point"}
}