{
  "type": "Feature",
  "properties": {
    "addr:full":"1 Rte De Glonville 54122 Azerailles Lorraine",
    "addr:housenumber":"1",
    "addr:postcode":"54122",
    "addr:street":"Rte De Glonville",
    "iso:country":"FR",
    "sg:address":"1 Rte De Glonville 54122 Azerailles",
    "sg:classifiers":[
        {
            "category":"Professional",
            "type":"Services"
        }
    ],
    "sg:phone":"+33 3 83 75 15 28",
    "sg:province":"Lorraine",
    "sg:tags":[
        "transport",
        "road"
    ],
    "wof:name":"Transports Bernard Michel Et Fils Sarl",
    "wof:placetype":"venue"
},
  "geometry": {"coordinates":[6.700467,48.481857],"type":"Point"}
}