{
  "type": "Feature",
  "properties": {
    "addr:full":"B.P. 1, 01130 Nantua C\u00e9dex^^6, All\u00e9e des Cypr\u00e9s, 01130 Nantua Rhone-Alpes 01130",
    "addr:housenumber":"1",
    "addr:postcode":"01130;01130;01130",
    "addr:street":"B.P.;Alle\u0301E Des Cypre\u0301S",
    "iso:country":"FR",
    "sg:address":"B.P. 1, 01130 Nantua C\u00e9dex^^6, All\u00e9e des Cypr\u00e9s, 01130 Nantua",
    "sg:orig_category":"Non-Classified Establishments",
    "sg:phone":"+33 4 74 75 01 37",
    "sg:postcode":"01130",
    "sg:province":"Rhone-Alpes",
    "wof:name":"Jam'etic S.a.r.l.",
    "wof:placetype":"venue"
},
  "geometry": {"coordinates":[5.696632,46.19223],"type":"Point"}
}