{
  "type": "Feature",
  "properties": {
    "addr:full":"30, Rue Beausoleil, 49410 La Chapelle Saint Florent Pays de Loire",
    "addr:housenumber":"30",
    "addr:postcode":"49410;florent",
    "addr:street":"Rue Beausoleil",
    "iso:country":"FR",
    "sg:address":"30, Rue Beausoleil, 49410 La Chapelle Saint Florent",
    "sg:orig_category":"Unclassifiable Establishments",
    "sg:phone":"+33 2 41 72 13 20",
    "sg:province":"Pays de Loire",
    "wof:name":"Etablissements Pierre Bourr\u00e9 Et Fils S.a.",
    "wof:placetype":"venue"
},
  "geometry": {"coordinates":[-1.056493,47.332603],"type":"Point"}
}