{
  "type": "Feature",
  "properties": {
    "iso:country":"FR",
    "sg:address":"16, Rte Nationale de Saint Antoine, 13015 Marseille",
    "sg:orig_category":"Unclassifiable Establishments",
    "sg:phone":"+33 4 91 96 29 99",
    "sg:province":"Poitou-Charentes",
    "wof:name":"Biscuiterie Confiserie Du Lacydon S.a.r.l.",
    "wof:placetype":"venue"
},
  "geometry": {"coordinates":[5.35894,43.385788],"type":"Point"}
}