{
  "type": "Feature",
  "properties": {
    "iso:country":"FR",
    "sg:address":"8, Rue de l'Eglise, 57550 Merten",
    "sg:orig_category":"Unclassifiable Establishments",
    "sg:phone":"+33 3 87 93 60 97",
    "sg:province":"Lorraine",
    "wof:name":"Electro Distance E.u.r.l.",
    "wof:placetype":"venue"
},
  "geometry": {"coordinates":[6.603678,49.223415],"type":"Point"}
}