{
  "type": "Feature",
  "properties": {
    "iso:country":"FR",
    "sg:address":"Zi De La Frayere 06150 Cannes La Bocca",
    "sg:classifiers":[
        {
            "category":"Farming",
            "subcategory":"Livestock Farm",
            "type":"Manufacturing & Wholesale Goods"
        }
    ],
    "sg:phone":"+33 4 93 47 38 43",
    "sg:province":"Champagne",
    "sg:tags":[
        "breeding",
        "agriculture",
        "animal"
    ],
    "wof:name":"Societe Sauve Halle Aux Viandes",
    "wof:placetype":"venue"
},
  "geometry": {"coordinates":[6.99107,43.5504],"type":"Point"}
}