{
  "type": "Feature",
  "properties": {
    "addr:full":"Lieu Dit Chez Nauve 16430 Champniers Poitou-Charentes 16430",
    "addr:postcode":"16430;16430",
    "addr:street":"Lieu Dit Chez Nauve",
    "iso:country":"FR",
    "sg:address":"Lieu Dit Chez Nauve 16430 Champniers",
    "sg:classifiers":[
        {
            "category":"Manufacturing",
            "subcategory":"Textiles",
            "type":"Manufacturing & Wholesale Goods"
        }
    ],
    "sg:phone":"+33 5 45 94 54 20",
    "sg:postcode":"16430",
    "sg:province":"Poitou-Charentes",
    "sg:tags":[
        "clothing",
        "accessory"
    ],
    "wof:name":"Riva Destra",
    "wof:placetype":"venue"
},
  "geometry": {"coordinates":[0.20961,45.702274],"type":"Point"}
}