{
  "type": "Feature",
  "properties": {
    "addr:full":"130 Rue De Rosny 93100 Montreuil Ile de France 93100",
    "addr:housenumber":"130",
    "addr:postcode":"93100;93100",
    "addr:street":"Rue De Rosny",
    "iso:country":"FR",
    "sg:address":"130 Rue De Rosny 93100 Montreuil",
    "sg:classifiers":[
        {
            "category":"Manufacturing",
            "subcategory":"Food",
            "type":"Manufacturing & Wholesale Goods"
        }
    ],
    "sg:phone":"+33 1 42 87 20 20",
    "sg:postcode":"93100",
    "sg:province":"Ile de France",
    "sg:tags":[
        "preserve",
        "product",
        "related"
    ],
    "wof:name":"Safa",
    "wof:placetype":"venue"
},
  "geometry": {"coordinates":[2.452758,48.864361],"type":"Point"}
}