{
  "type": "Feature",
  "properties": {
    "iso:country":"FR",
    "sg:address":"Centre Commercial R\u00e9publique 2",
    "sg:city":"Notre Dame de Gravenchon",
    "sg:orig_category":"Unclassifiable Establishments",
    "sg:phone":"+33 2 35 31 58 85",
    "sg:postcode":"76330",
    "sg:province":"Haute Normandie",
    "wof:name":"C.r.i.t. Int\u00e9rim S.a.",
    "wof:placetype":"venue"
},
  "geometry": {"coordinates":[0.565613,49.489414],"type":"Point"}
}