{
  "type": "Feature",
  "properties": {
    "iso:country":"FR",
    "sg:address":"Za Triangle De Pacy 27120 Pacy Sur Eure",
    "sg:classifiers":[
        {
            "category":"Manufacturing",
            "subcategory":"Paper Products",
            "type":"Manufacturing & Wholesale Goods"
        }
    ],
    "sg:phone":"+33 2 32 22 36 66",
    "sg:province":"Haute Normandie",
    "sg:tags":[
        "finished",
        "cardboard",
        "-"
    ],
    "wof:name":"Empacabois Sa",
    "wof:placetype":"venue"
},
  "geometry": {"coordinates":[1.3812,49.014259],"type":"Point"}
}