{
  "type": "Feature",
  "properties": {
    "addr:full":"235, Rue de Courcelles, 51100 Reims Champagne",
    "addr:housenumber":"235",
    "addr:postcode":"51100",
    "addr:street":"Rue De Courcelles",
    "iso:country":"FR",
    "sg:address":"235, Rue de Courcelles, 51100 Reims",
    "sg:orig_category":"Non-Classified Establishments",
    "sg:phone":"+33 3 26 09 23 70",
    "sg:province":"Champagne",
    "wof:name":"Saffrec",
    "wof:placetype":"venue"
},
  "geometry": {"coordinates":[4.008185,49.26453],"type":"Point"}
}