{
  "type": "Feature",
  "properties": {
    "iso:country":"FR",
    "sg:address":"15ter, Rue du Madrillet, 76300 Sotteville l\u00e8s Rouen",
    "sg:orig_category":"Unclassifiable Establishments",
    "sg:phone":"+33 2 35 72 69 21",
    "sg:province":"Haute Normandie",
    "wof:name":"S.a.t.e.b. S.a. - Soci\u00e9t\u00e9 D'application Des Techniques D'equipement Du B\u00e2timent",
    "wof:placetype":"venue"
},
  "geometry": {"coordinates":[1.078884,49.416317],"type":"Point"}
}