{
  "type": "Feature",
  "properties": {
    "addr:full":"B.P. 11, 31701 Blagnac C\u00e9dex^^1, Av. du G\u00e9n\u00e9ral de Gaulle, 31700 Blagnac Midi Pyr\u00e9n\u00e9es",
    "addr:postcode":"31701;31700",
    "addr:street":"B.P. 11;Av. Du Ge\u0301Ne\u0301Ral De Gaulle",
    "iso:country":"FR",
    "sg:address":"B.P. 11, 31701 Blagnac C\u00e9dex^^1, Av. du G\u00e9n\u00e9ral de Gaulle, 31700 Blagnac",
    "sg:orig_category":"Non-Classified Establishments",
    "sg:phone":"+33 5 34 36 11 40",
    "sg:province":"Midi Pyr\u00e9n\u00e9es",
    "wof:name":"Soci\u00e9t\u00e9 Bayle S.a.r.l.",
    "wof:placetype":"venue"
},
  "geometry": {"coordinates":[1.39684,43.634586],"type":"Point"}
}