{
  "type": "Feature",
  "properties": {
    "addr:full":"Le Vieux Brulain 79230 Brulain Poitou-Charentes",
    "addr:postcode":"79230",
    "addr:street":"Brulain",
    "iso:country":"FR",
    "sg:address":"Le Vieux Brulain 79230 Brulain",
    "sg:orig_category":"Non-Classified Establishments",
    "sg:phone":"+33 5 49 26 48 03",
    "sg:province":"Poitou-Charentes",
    "wof:name":"Terres De S\u00e8vre S.a.",
    "wof:placetype":"venue"
},
  "geometry": {"coordinates":[-0.318069,46.197914],"type":"Point"}
}