{
  "type": "Feature",
  "properties": {
    "iso:country":"FR",
    "sg:address":"Le Bourg 14350 Saint Martin des Besaces",
    "sg:city":"Dampierre",
    "sg:orig_category":"Non-Classified Establishments",
    "sg:phone":"+33 2 31 68 71 21",
    "sg:postcode":"14350",
    "sg:province":"Basse Normandie",
    "wof:name":"S.n.e.m. S.n.c. - Soci\u00e9t\u00e9 Nouvelle De L'entreprise Madelaine",
    "wof:placetype":"venue"
},
  "geometry": {"coordinates":[-0.84472,49.011719],"type":"Point"}
}