{
  "type": "Feature",
  "properties": {
    "addr:full":"6 Rue Alain Colas BP 60219 44202 Nantes Cedex 2 Bourgogne",
    "addr:housenumber":"6",
    "addr:postcode":"44202",
    "addr:street":"Rue Alain Colas;60219",
    "iso:country":"FR",
    "sg:address":"6 Rue Alain Colas BP 60219 44202 Nantes Cedex 2",
    "sg:classifiers":[
        {
            "category":"Building & Trades",
            "subcategory":"Construction",
            "type":"Services"
        }
    ],
    "sg:phone":"+33 2 40 99 88 88",
    "sg:province":"Bourgogne",
    "sg:tags":[
        "work",
        "public"
    ],
    "wof:name":"Gtb Bouyer Du Chemin",
    "wof:placetype":"venue"
},
  "geometry": {"coordinates":[-1.526704,47.210869],"type":"Point"}
}