{
  "type": "Feature",
  "properties": {
    "iso:country":"FR",
    "sg:address":"4, Rue Django Rheinhardt, 95310 Saint Ouen l'Aum\u00f4ne",
    "sg:orig_category":"Unclassifiable Establishments",
    "sg:phone":"+33 1 30 37 42 86",
    "sg:province":"Ile de France",
    "wof:name":"Framatin S.a.",
    "wof:placetype":"venue"
},
  "geometry": {"coordinates":[0.490902,48.605492],"type":"Point"}
}