{
  "type": "Feature",
  "properties": {
    "addr:full":"Zac De Montimaran BP 401 34504 B\u00e9ziers B\u00e9ziers Languedoc-Roussillon 34500",
    "addr:housenumber":"401",
    "addr:postcode":"34504;34500",
    "addr:street":"Zac De Montimaran Bp",
    "iso:country":"FR",
    "sg:address":"Zac De Montimaran BP 401 34504 B\u00e9ziers",
    "sg:city":"B\u00e9ziers",
    "sg:classifiers":[
        {
            "category":"Autos & Motor Vehicles",
            "subcategory":"Automobile Sales",
            "type":"Retail Goods"
        }
    ],
    "sg:phone":"+33 4 67 35 91 00",
    "sg:postcode":"34500",
    "sg:province":"Languedoc-Roussillon",
    "sg:tags":[
        "equipment",
        "motor-cars",
        "transport"
    ],
    "wof:name":"Auto Service 34 Sa",
    "wof:placetype":"venue"
},
  "geometry": {"coordinates":[3.24495,43.344608],"type":"Point"}
}