{
  "type": "Feature",
  "properties": {
    "iso:country":"FR",
    "sg:address":"Zi Des Sables De Beauregard 36700 Ch\u00e2tillon Sur Indre",
    "sg:city":"Arpheuilles",
    "sg:classifiers":[
        {
            "category":"Shopping",
            "subcategory":"Clothing, Apparel, & Fashions",
            "type":"Retail Goods"
        }
    ],
    "sg:phone":"+33 2 54 38 75 01",
    "sg:postcode":"36700",
    "sg:province":"Centre",
    "sg:tags":[
        "textile",
        "clothing",
        "clothes"
    ],
    "wof:name":"Hervier Production Sarl",
    "wof:placetype":"venue"
},
  "geometry": {"coordinates":[1.17353,46.984276],"type":"Point"}
}