{
  "type": "Feature",
  "properties": {
    "addr:full":"1065 Rue Du Mar\u00e9chal Juin 45200 Amilly Amilly Centre 45200",
    "addr:housenumber":"1065",
    "addr:postcode":"45200;45200",
    "addr:street":"Rue Du Mare\u0301Chal Juin",
    "iso:country":"FR",
    "sg:address":"1065 Rue Du Mar\u00e9chal Juin 45200 Amilly",
    "sg:city":"Amilly",
    "sg:classifiers":[
        {
            "category":"Manufacturing",
            "subcategory":"Metals",
            "type":"Manufacturing & Wholesale Goods"
        }
    ],
    "sg:phone":"+33 2 38 85 58 07",
    "sg:postcode":"45200",
    "sg:province":"Centre",
    "sg:tags":[
        "metallurgy",
        "metalworking",
        "processing"
    ],
    "wof:name":"Metal Improvement Company",
    "wof:placetype":"venue"
},
  "geometry": {"coordinates":[2.784212,47.968647],"type":"Point"}
}