{
  "type": "Feature",
  "properties": {
    "addr:full":"177 Av M\u00e9l\u00e8zes 74300 Thyez Rhone-Alpes 74300",
    "addr:housenumber":"177",
    "addr:postcode":"74300;74300",
    "addr:street":"Av Me\u0301Le\u0300Zes;Rhone-Alpes",
    "iso:country":"FR",
    "sg:address":"177 Av M\u00e9l\u00e8zes 74300 Thyez",
    "sg:classifiers":[
        {
            "category":"Manufacturing",
            "subcategory":"Metals",
            "type":"Manufacturing & Wholesale Goods"
        }
    ],
    "sg:phone":"+33 4 50 98 96 71",
    "sg:postcode":"74300",
    "sg:province":"Rhone-Alpes",
    "sg:tags":[
        "metallurgy",
        "metalworking"
    ],
    "wof:name":"Hf Securite",
    "wof:placetype":"venue"
},
  "geometry": {"coordinates":[6.540547,46.077602],"type":"Point"}
}