{
  "type": "Feature",
  "properties": {
    "iso:country":"FR",
    "sg:address":"20 Rue Joseph Cugnot Zi No 2 37300 Joue Les Tours",
    "sg:city":"Jou\u00e9-l\u00e8s-Tours",
    "sg:orig_category":"Business advice and other services Goods handling - material and equipment Mechanical Engineering - ",
    "sg:phone":"+33 2 47 73 30 30",
    "sg:postcode":"37300",
    "sg:province":"Centre",
    "wof:name":"Cg2a Sa",
    "wof:placetype":"venue"
},
  "geometry": {"coordinates":[0.662555,47.350945],"type":"Point"}
}