{
  "type": "Feature",
  "properties": {
    "iso:country":"FR",
    "sg:address":"Sautes Le Bas Echang Autor Carcassonne E 11800 Trebes",
    "sg:classifiers":[
        {
            "category":"Manufacturing",
            "subcategory":"Paper Products",
            "type":"Manufacturing & Wholesale Goods"
        }
    ],
    "sg:phone":"+33 4 68 78 84 40",
    "sg:province":"Languedoc-Roussillon",
    "sg:tags":[
        "packaging",
        "material",
        "-",
        "cardboard"
    ],
    "wof:name":"Espe Emballages (espe)",
    "wof:placetype":"venue"
},
  "geometry": {"coordinates":[2.418498,43.201736],"type":"Point"}
}