{
  "type": "Feature",
  "properties": {
    "iso:country":"FR",
    "sg:address":"ZI de la Vespi\u00e8res",
    "sg:city":"Orbec",
    "sg:orig_category":"Unclassifiable Establishments",
    "sg:phone":"+33 2 31 32 86 88",
    "sg:postcode":"14290",
    "sg:province":"Basse Normandie",
    "wof:name":"Form Acier S.a.r.l.",
    "wof:placetype":"venue"
},
  "geometry": {"coordinates":[0.405945,49.023071],"type":"Point"}
}