{
  "type": "Feature",
  "properties": {
    "addr:full":"33 Rue Gutenberg 93012 Bobigny Berg Alsace 67320",
    "addr:housenumber":"33",
    "addr:postcode":"93012;67320",
    "addr:street":"Rue Gutenberg;Berg",
    "iso:country":"FR",
    "sg:address":"33 Rue Gutenberg 93012 Bobigny",
    "sg:city":"Berg",
    "sg:classifiers":[
        {
            "category":"Utilities",
            "subcategory":"Electric",
            "type":"Services"
        }
    ],
    "sg:phone":"+33 1 48 43 75 00",
    "sg:postcode":"67320",
    "sg:province":"Alsace",
    "sg:tags":[
        "electricity",
        "electronic",
        "electrical",
        "equipment"
    ],
    "wof:name":"Ets Ren\u00c9 Lambert Sarl",
    "wof:placetype":"venue"
},
  "geometry": {"coordinates":[2.426494,48.903214],"type":"Point"}
}