{
  "type": "Feature",
  "properties": {
    "iso:country":"FR",
    "sg:address":"53 Rue De La Lys 59250 Halluin",
    "sg:classifiers":[
        {
            "category":"Manufacturing",
            "subcategory":"Printing",
            "type":"Manufacturing & Wholesale Goods"
        }
    ],
    "sg:phone":"+33 3 20 28 83 20",
    "sg:province":"Nord Pas-de-Calais",
    "sg:tags":[
        "publishing"
    ],
    "wof:name":"Editions Plein Nord Et Cie Sarl",
    "wof:placetype":"venue"
},
  "geometry": {"coordinates":[3.122399,50.786545],"type":"Point"}
}