{
  "type": "Feature",
  "properties": {
    "addr:full":"Av. du Commando Vigan Braquet Bagnols sur C\u00e8ze Languedoc-Roussillon 30200",
    "addr:postcode":"30200",
    "addr:street":"Av. Du Commando;Ce\u0300Ze",
    "iso:country":"FR",
    "sg:address":"Av. du Commando Vigan Braquet",
    "sg:city":"Bagnols sur C\u00e8ze",
    "sg:orig_category":"Unclassifiable Establishments",
    "sg:phone":"+33 4 66 90 39 00",
    "sg:postcode":"30200",
    "sg:province":"Languedoc-Roussillon",
    "wof:name":"E.d.f. Et Gaz De France",
    "wof:placetype":"venue"
},
  "geometry": {"coordinates":[4.612055,44.166859],"type":"Point"}
}