{
  "type": "Feature",
  "properties": {
    "iso:country":"FR",
    "sg:address":"Av. du Commando Vigan Braquet",
    "sg:city":"Bagnols sur C\u00e8ze",
    "sg:orig_category":"Unclassifiable Establishments",
    "sg:phone":"+33 4 66 90 39 00",
    "sg:postcode":"30200",
    "sg:province":"Languedoc-Roussillon",
    "wof:name":"E.d.f. Et Gaz De France",
    "wof:placetype":"venue"
},
  "geometry": {"coordinates":[4.612055,44.166859],"type":"Point"}
}