{
  "type": "Feature",
  "properties": {
    "addr:full":"4 Rue Du Bordage Batiment E 35510 Cesson Sevigne Cesson-S\u00e9vign\u00e9 Bretagne 35510",
    "addr:housenumber":"4",
    "addr:postcode":"35510;35510",
    "addr:street":"Rue Du Bordage;Bretagne",
    "iso:country":"FR",
    "sg:address":"4 Rue Du Bordage Batiment E 35510 Cesson Sevigne",
    "sg:city":"Cesson-S\u00e9vign\u00e9",
    "sg:classifiers":[
        {
            "category":"Utilities",
            "subcategory":"Telephone",
            "type":"Services"
        }
    ],
    "sg:phone":"+33 2 99 83 04 04",
    "sg:postcode":"35510",
    "sg:province":"Bretagne",
    "sg:tags":[
        "telecommunication"
    ],
    "wof:name":"Axians L'ete Sa",
    "wof:placetype":"venue"
},
  "geometry": {"coordinates":[-1.598731,48.114185],"type":"Point"}
}