{
  "type": "Feature",
  "properties": {
    "iso:country":"FR",
    "sg:address":"ZI Brunehaut",
    "sg:city":"Calonne Ricouart",
    "sg:orig_category":"Unclassifiable Establishments",
    "sg:phone":"+33 3 21 65 52 91",
    "sg:postcode":"62470",
    "sg:province":"Nord Pas-de-Calais",
    "wof:name":"C.t.a. S.a.r.l. - Constructions Tubulaires De L'artois",
    "wof:placetype":"venue"
},
  "geometry": {"coordinates":[2.48421,50.487755],"type":"Point"}
}