{
  "type": "Feature",
  "properties": {
    "addr:full":"14, Av. Jean Perrin - Parc Industriel de l'Hyppodrome, 33700 M\u00e9rignac M\u00e9rignac Aquitaine 33700",
    "addr:postcode":"33700;33700",
    "addr:street":"14 Av. Jean Perrin;Industriel;L'Hyppodrome",
    "iso:country":"FR",
    "sg:address":"14, Av. Jean Perrin - Parc Industriel de l'Hyppodrome, 33700 M\u00e9rignac",
    "sg:city":"M\u00e9rignac",
    "sg:orig_category":"Unclassifiable Establishments",
    "sg:phone":"+33 5 57 92 26 00",
    "sg:postcode":"33700",
    "sg:province":"Aquitaine",
    "wof:name":"Fournie Grospaud S.a.",
    "wof:placetype":"venue"
},
  "geometry": {"coordinates":[-0.670346,44.838882],"type":"Point"}
}