{
  "type": "Feature",
  "properties": {
    "addr:full":"Av. du Gros Murger - Parc d'Activit\u00e9 de Bellevue Cergy \u00cele-de-France 95615",
    "addr:postcode":"95615",
    "addr:street":"Av. Du Gros Murger Parc D'Activite \u0301 De Bellevue",
    "iso:country":"FR",
    "sg:address":"Av. du Gros Murger - Parc d'Activit\u00e9 de Bellevue",
    "sg:city":"Cergy",
    "sg:orig_category":"Unclassifiable Establishments",
    "sg:phone":"+33 1 39 09 00 49",
    "sg:postcode":"95615",
    "sg:province":"\u00cele-de-France",
    "wof:name":"Valbruna France S.a.",
    "wof:placetype":"venue"
},
  "geometry": {"coordinates":[2.10003,49.020699],"type":"Point"}
}