{
  "type": "Feature",
  "properties": {
    "addr:full":"10 Sali\u00e8res 17410 Saint Martin de R\u00e9 Poitou-Charentes 17410",
    "addr:housenumber":"10",
    "addr:postcode":"17410;17410",
    "addr:street":"Salie\u0300Res;Re\u0301",
    "iso:country":"FR",
    "sg:address":"10",
    "sg:city":"Sali\u00e8res 17410 Saint Martin de R\u00e9",
    "sg:classifiers":[
        {
            "category":"Shopping",
            "subcategory":"Crafts & Fabrics",
            "type":"Retail Goods"
        }
    ],
    "sg:phone":"+33 5 46 09 41 93",
    "sg:postcode":"17410",
    "sg:province":"Poitou-Charentes",
    "sg:tags":[
        "textile",
        "clothing"
    ],
    "wof:name":"Societe Rethaise De Filets",
    "wof:placetype":"venue"
},
  "geometry": {"coordinates":[-1.353802,46.196407],"type":"Point"}
}