{
  "type": "Feature",
  "properties": {
    "iso:country":"FR",
    "sg:address":"La Gare 22250 Broons",
    "sg:city":"Broons",
    "sg:classifiers":[
        {
            "category":"Farming",
            "subcategory":"Farm & Veterinary Services",
            "type":"Manufacturing & Wholesale Goods"
        }
    ],
    "sg:phone":"+33 2 96 84 64 70",
    "sg:postcode":"22250",
    "sg:province":"Bretagne",
    "sg:tags":[
        "food",
        "product",
        "breeding",
        "animal",
        "related"
    ],
    "wof:name":"Cooperative Agricole De Broons",
    "wof:placetype":"venue"
},
  "geometry": {"coordinates":[-2.255893,48.318775],"type":"Point"}
}