{
  "type": "Feature",
  "properties": {
    "addr:full":"Route D'Annemasse Za 74160 Saint Julien En Genevois Rhone-Alpes 74160",
    "addr:postcode":"74160;74160",
    "addr:street":"Route D'Annemasse Za;Julien En Genevois Rhone-Alpes",
    "iso:country":"FR",
    "sg:address":"Route D'Annemasse Za 74160 Saint Julien En Genevois",
    "sg:classifiers":[
        {
            "category":"Manufacturing",
            "subcategory":"Tools & Machinery",
            "type":"Manufacturing & Wholesale Goods"
        }
    ],
    "sg:phone":"+33 4 50 49 35 99",
    "sg:postcode":"74160",
    "sg:province":"Rhone-Alpes",
    "sg:tags":[
        "metallurgy",
        "metalworking"
    ],
    "wof:name":"La Boite A Outils Sa",
    "wof:placetype":"venue"
},
  "geometry": {"coordinates":[6.140635,46.142563],"type":"Point"}
}