{
  "type": "Feature",
  "properties": {
    "addr:full":"74, Cours Lafayette, 69003 Lyon Rhone-Alpes",
    "addr:housenumber":"74",
    "addr:postcode":"69003",
    "addr:street":"Cours Lafayette",
    "iso:country":"FR",
    "sg:address":"74, Cours Lafayette, 69003 Lyon",
    "sg:orig_category":"Unclassifiable Establishments",
    "sg:phone":"+33 4 78 62 66 19",
    "sg:province":"Rhone-Alpes",
    "wof:name":"Adriant",
    "wof:placetype":"venue"
},
  "geometry": {"coordinates":[4.84829,45.76363],"type":"Point"}
}