{
  "type": "Feature",
  "properties": {
    "addr:full":"23 ave Grammont; Tours; 37000 Tours Centre 37000",
    "addr:postcode":"37000;37000",
    "addr:street":"23 Ave",
    "iso:country":"FR",
    "sg:address":"23 ave Grammont; Tours; 37000",
    "sg:city":"Tours",
    "sg:classifiers":[
        {
            "category":"Banks & Credit Unions",
            "subcategory":"Bank",
            "type":"Services"
        }
    ],
    "sg:phone":"+33 3347053601",
    "sg:postcode":"37000",
    "sg:province":"Centre",
    "wof:name":"Cr\u00e9dit Mutuel",
    "wof:placetype":"venue"
},
  "geometry": {"coordinates":[0.689795,47.386822],"type":"Point"}
}