{
  "type": "Feature",
  "properties": {
    "addr:full":"Rue Benjamin Gomez 64100 Bayonne Bayonne Aquitaine 64100",
    "addr:postcode":"64100 bayonne;64100",
    "addr:street":"Rue Benjamin Gomez",
    "iso:country":"FR",
    "sg:address":"Rue Benjamin Gomez 64100 Bayonne",
    "sg:city":"Bayonne",
    "sg:classifiers":[
        {
            "category":"Utilities",
            "type":"Services"
        }
    ],
    "sg:phone":"+33 5 59 50 35 00",
    "sg:postcode":"64100",
    "sg:province":"Aquitaine",
    "sg:tags":[
        "raw",
        "energy",
        "material"
    ],
    "wof:name":"Aquitaine Pyrenees Et Gaz",
    "wof:placetype":"venue"
},
  "geometry": {"coordinates":[-1.452469,43.487068],"type":"Point"}
}