{
  "type": "Feature",
  "properties": {
    "iso:country":"FR",
    "sg:address":"Rue De La Cooperative 66600 Salses Le Ch\u00e2teau",
    "sg:classifiers":[
        {
            "category":"Food Court",
            "type":"Food & Drink"
        }
    ],
    "sg:phone":"+33 4 68 38 62 07",
    "sg:postcode":"66600",
    "sg:province":"Languedoc-Roussillon",
    "sg:tags":[
        "product",
        "related"
    ],
    "wof:name":"Societe Cooperative Agricole De Vins Fins",
    "wof:placetype":"venue"
},
  "geometry": {"coordinates":[2.874005,42.770721],"type":"Point"}
}