{
  "type": "Feature",
  "properties": {
    "addr:full":"11, Rue de Marseille, 75010 Paris Ile de France",
    "addr:housenumber":"11",
    "addr:postcode":"75010",
    "addr:street":"Rue De Marseille",
    "iso:country":"FR",
    "sg:address":"11, Rue de Marseille, 75010 Paris",
    "sg:orig_category":"Unclassifiable Establishments",
    "sg:phone":"+33 1 44 52 91 03",
    "sg:province":"Ile de France",
    "wof:name":"D.b. Diffusion S.a.r.l.",
    "wof:placetype":"venue"
},
  "geometry": {"coordinates":[2.363416,48.871655],"type":"Point"}
}