{
  "type": "Feature",
  "properties": {
    "addr:full":"B.P. 4 Cl\u00e9der Bretagne 29233",
    "addr:postcode":"29233",
    "addr:street":"B.P. 4 Cle\u0301Der Bretagne",
    "iso:country":"FR",
    "sg:address":"B.P. 4",
    "sg:city":"Cl\u00e9der",
    "sg:orig_category":"Non-Classified Establishments",
    "sg:phone":"+33 2 98 69 31 04",
    "sg:postcode":"29233",
    "sg:province":"Bretagne",
    "wof:name":"A.c.d.s. S.a. - Agricole De Conditionnement Distribution Services",
    "wof:placetype":"venue"
},
  "geometry": {"coordinates":[-4.103399,48.662895],"type":"Point"}
}