{
  "type": "Feature",
  "properties": {
    "iso:country":"FR",
    "sg:address":"10, Rue de S\u00e9lestat, 67300 Schiltigheim",
    "sg:city":"Schiltigheim",
    "sg:orig_category":"Unclassifiable Establishments",
    "sg:phone":"+33 3 88 81 22 81",
    "sg:postcode":"67300",
    "sg:province":"Alsace",
    "wof:name":"Fibco S.a.r.l.",
    "wof:placetype":"venue"
},
  "geometry": {"coordinates":[7.737706,48.607857],"type":"Point"}
}