{
  "type": "Feature",
  "properties": {
    "addr:full":"B.P. 352, 27700 Les Andelys^^22, Rue Marcel Lefevre, 27700 Les Andelys Haute Normandie",
    "addr:housenumber":"b.p. 352",
    "addr:postcode":"27700;27700",
    "addr:street":"Rue Marcel Lefevre;Haute Normandie",
    "iso:country":"FR",
    "sg:address":"B.P. 352, 27700 Les Andelys^^22, Rue Marcel Lefevre, 27700 Les Andelys",
    "sg:orig_category":"Non-Classified Establishments",
    "sg:phone":"+33 2 32 54 09 57",
    "sg:province":"Haute Normandie",
    "wof:name":"Galerie Tuffier S.a.r.l.",
    "wof:placetype":"venue"
},
  "geometry": {"coordinates":[1.463625,49.195496],"type":"Point"}
}