{
  "type": "Feature",
  "properties": {
    "iso:country":"FR",
    "sg:address":"57, Rue Haute, 80500 Rollot",
    "sg:orig_category":"Unclassifiable Establishments",
    "sg:phone":"+33 3 22 78 77 40",
    "sg:province":"Picardie",
    "wof:name":"Paillet Services S.a.r.l. - Groupe Leroy Somer",
    "wof:placetype":"venue"
},
  "geometry": {"coordinates":[2.653605,49.590366],"type":"Point"}
}