{
  "type": "Feature",
  "properties": {
    "addr:full":"36 Bis Rue Jeanne D'Arc 59300 Valenciennes Nord Pas-de-Calais 59300",
    "addr:housenumber":"36 bis",
    "addr:postcode":"59300;59300",
    "addr:street":"Rue Jeanne D'Arc",
    "iso:country":"FR",
    "sg:address":"36 Bis Rue Jeanne D'Arc 59300 Valenciennes",
    "sg:classifiers":[
        {
            "category":"Shopping",
            "subcategory":"Clothing, Apparel, & Fashions",
            "type":"Retail Goods"
        }
    ],
    "sg:phone":"+33 3 27 33 82 82",
    "sg:postcode":"59300",
    "sg:province":"Nord Pas-de-Calais",
    "sg:tags":[
        "textile",
        "clothing",
        "clothes"
    ],
    "wof:name":"Gh Vetement",
    "wof:placetype":"venue"
},
  "geometry": {"coordinates":[3.505992,50.363785],"type":"Point"}
}