{
  "type": "Feature",
  "properties": {
    "iso:country":"FR",
    "sg:address":"Lieu Dit Champ Sever 38121 Chonas L Amballan",
    "sg:classifiers":[
        {
            "category":"Farming",
            "subcategory":"Farm",
            "type":"Manufacturing & Wholesale Goods"
        }
    ],
    "sg:phone":"+33 4 74 58 81 70",
    "sg:postcode":"38121",
    "sg:province":"Rhone-Alpes",
    "sg:tags":[
        "horticulture",
        "agriculture",
        "livestock"
    ],
    "wof:name":"Francois Pinet Et Fils Sarl",
    "wof:placetype":"venue"
},
  "geometry": {"coordinates":[4.823563,45.462887],"type":"Point"}
}