{
  "type": "Feature",
  "properties": {
    "addr:full":"R De La Croix P\u00e8lerine 62503 St Omer Franche Comt\u00e9",
    "addr:housenumber":"62503",
    "addr:street":"Pe\u0300Lerine;Franche Comte\u0301",
    "iso:country":"FR",
    "sg:address":"R De La Croix P\u00e8lerine 62503 St Omer",
    "sg:classifiers":[
        {
            "category":"Food Court",
            "type":"Food & Drink"
        }
    ],
    "sg:phone":"+33 3 21 38 68 68",
    "sg:province":"Franche Comt\u00e9",
    "sg:tags":[
        "product",
        "related"
    ],
    "wof:name":"Caves Saint Arnould",
    "wof:placetype":"venue"
},
  "geometry": {"coordinates":[2.249829,50.749756],"type":"Point"}
}