{
  "type": "Feature",
  "properties": {
    "addr:full":"37, Av. Raspail, 94250 Gentilly Ile de France",
    "addr:postcode":"94250;ile",
    "addr:street":"37 Av. Raspail",
    "iso:country":"FR",
    "sg:address":"37, Av. Raspail, 94250 Gentilly",
    "sg:orig_category":"Unclassifiable Establishments",
    "sg:phone":"+33 1 45 47 10 00",
    "sg:province":"Ile de France",
    "wof:name":"Corel Electronique S.a.",
    "wof:placetype":"venue"
},
  "geometry": {"coordinates":[2.350891,48.814369],"type":"Point"}
}