{
  "type": "Feature",
  "properties": {
    "iso:country":"FR",
    "sg:address":"Chemin des Peupliers - ZA des Nauzes",
    "sg:city":"Grisolles",
    "sg:orig_category":"Non-Classified Establishments",
    "sg:phone":"+33 5 63 67 30 28",
    "sg:postcode":"82170",
    "sg:province":"Midi Pyr\u00e9n\u00e9es",
    "wof:name":"Transports Mandico S.a.",
    "wof:placetype":"venue"
},
  "geometry": {"coordinates":[1.296795,43.826965],"type":"Point"}
}