{
  "type": "Feature",
  "properties": {
    "addr:full":"8 Rue Darwin 75018 Paris Ile de France",
    "addr:housenumber":"8",
    "addr:postcode":"75018",
    "addr:street":"Rue Darwin",
    "iso:country":"FR",
    "sg:address":"8 Rue Darwin 75018 Paris",
    "sg:classifiers":[
        {
            "category":"Professional",
            "subcategory":"Printing & Photocopies",
            "type":"Services"
        }
    ],
    "sg:phone":"+33 1 42 59 83 60",
    "sg:province":"Ile de France",
    "sg:tags":[
        "publishing"
    ],
    "wof:name":"Arys",
    "wof:placetype":"venue"
},
  "geometry": {"coordinates":[2.339709,48.890289],"type":"Point"}
}