{
  "type": "Feature",
  "properties": {
    "addr:full":"Av. Paul Signac Saint Tropez Aquitaine 83990",
    "addr:postcode":"83990",
    "addr:street":"Av. Paul Signac Saint Tropez",
    "iso:country":"FR",
    "sg:address":"Av. Paul Signac",
    "sg:city":"Saint Tropez",
    "sg:orig_category":"Non-Classified Establishments",
    "sg:phone":"+33 4 94 56 68 00",
    "sg:postcode":"83990",
    "sg:province":"Aquitaine",
    "wof:name":"Le Byblos",
    "wof:placetype":"venue"
},
  "geometry": {"coordinates":[6.644177,43.270451],"type":"Point"}
}