{
  "type": "Feature",
  "properties": {
    "addr:full":"7 Rue Du Moulin 59223 Roncq Nord Pas-de-Calais 59223",
    "addr:housenumber":"7",
    "addr:postcode":"59223;59223",
    "addr:street":"Rue Du Moulin",
    "iso:country":"FR",
    "sg:address":"7 Rue Du Moulin 59223 Roncq",
    "sg:classifiers":[
        {
            "category":"Manufacturing",
            "subcategory":"Rubber & Plastics",
            "type":"Manufacturing & Wholesale Goods"
        }
    ],
    "sg:phone":"+33 3 20 94 26 50",
    "sg:postcode":"59223",
    "sg:province":"Nord Pas-de-Calais",
    "sg:tags":[
        "metallurgy",
        "finished",
        "-",
        "metalworking",
        "metallic"
    ],
    "wof:name":"Millescamps Modelage Sa",
    "wof:placetype":"venue"
},
  "geometry": {"coordinates":[3.119098,50.739197],"type":"Point"}
}