{
  "type": "Feature",
  "properties": {
    "iso:country":"FR",
    "sg:address":"B.P. 100, 13881 G\u00e9menos C\u00e9dex^^Av. du Pic de Bretagne - Parc d'Activit\u00e9 de G\u00e9menos, 13420 G\u00e9menos",
    "sg:city":"Bretagne",
    "sg:orig_category":"Non-Classified Establishments",
    "sg:phone":"+33 4 42 36 50 00",
    "sg:postcode":"90130",
    "sg:province":"Franche Comt\u00e9",
    "wof:name":"Gemplus International",
    "wof:placetype":"venue"
},
  "geometry": {"coordinates":[5.65148,43.297081],"type":"Point"}
}