{
  "type": "Feature",
  "properties": {
    "addr:full":"140, Rue Pierre Paraf - ZAC de Courtine, 84000 Avignon Languedoc-Roussillon",
    "addr:housenumber":"140",
    "addr:postcode":"84000",
    "addr:street":"Rue Pierre Paraf Zac De Courtine",
    "iso:country":"FR",
    "sg:address":"140, Rue Pierre Paraf - ZAC de Courtine, 84000 Avignon",
    "sg:orig_category":"Non-Classified Establishments",
    "sg:phone":"+33 4 90 85 88 73",
    "sg:province":"Languedoc-Roussillon",
    "wof:name":"Aprolis S.a.s.",
    "wof:placetype":"venue"
},
  "geometry": {"coordinates":[4.840698,43.930595],"type":"Point"}
}