{
  "type": "Feature",
  "properties": {
    "addr:full":"B.P. 12, 60530 Neuilly en Thelle^^15, Av de l'Europe, 60530 Neuilly en Thelle Picardie",
    "addr:postcode":"60530;60530",
    "addr:street":"B.P. 12;Av De L'Europe;En Thelle",
    "iso:country":"FR",
    "sg:address":"B.P. 12, 60530 Neuilly en Thelle^^15, Av de l'Europe, 60530 Neuilly en Thelle",
    "sg:orig_category":"Non-Classified Establishments",
    "sg:phone":"+33 3 44 26 85 00",
    "sg:province":"Picardie",
    "wof:name":"Hek France S.a.r.l.",
    "wof:placetype":"venue"
},
  "geometry": {"coordinates":[2.295504,49.223469],"type":"Point"}
}