{
  "type": "Feature",
  "properties": {
    "addr:full":"Place de la Bastille; Paris; 75004 Ile de France 75004",
    "addr:postcode":"75004 ile;france 75004",
    "addr:street":"Place De La Bastille",
    "iso:country":"FR",
    "sg:address":"Place de la Bastille; Paris; 75004",
    "sg:classifiers":[
        {
            "category":"Banks & Credit Unions",
            "subcategory":"Bank",
            "type":"Services"
        }
    ],
    "sg:phone":"+33 1 44 61 15 00",
    "sg:postcode":"75004",
    "sg:province":"Ile de France",
    "wof:name":"Banque De France",
    "wof:placetype":"venue"
},
  "geometry": {"coordinates":[2.368495,48.852959],"type":"Point"}
}