{
  "type": "Feature",
  "properties": {
    "iso:country":"FR",
    "sg:address":"Place de la Bastille; Paris; 75004",
    "sg:classifiers":[
        {
            "category":"Banks & Credit Unions",
            "subcategory":"Bank",
            "type":"Services"
        }
    ],
    "sg:phone":"+33 1 44 61 15 00",
    "sg:postcode":"75004",
    "sg:province":"Ile de France",
    "wof:name":"Banque De France",
    "wof:placetype":"venue"
},
  "geometry": {"coordinates":[2.368495,48.852959],"type":"Point"}
}