{
  "type": "Feature",
  "properties": {
    "addr:full":"Ld Le Suiffet 38380 Entre Deux Guiers Rhone-Alpes",
    "addr:postcode":"38380",
    "addr:street":"Ld;Rhone-Alpes",
    "iso:country":"FR",
    "sg:address":"Ld Le Suiffet 38380 Entre Deux Guiers",
    "sg:classifiers":[
        {
            "category":"Manufacturing",
            "subcategory":"Wood Products",
            "type":"Manufacturing & Wholesale Goods"
        }
    ],
    "sg:phone":"+33 4 76 66 07 84",
    "sg:province":"Rhone-Alpes",
    "sg:tags":[
        "furniture"
    ],
    "wof:name":"Scierie Cote Freres",
    "wof:placetype":"venue"
},
  "geometry": {"coordinates":[5.75024,45.433521],"type":"Point"}
}