{
  "type": "Feature",
  "properties": {
    "iso:country":"FR",
    "sg:address":"60, Rue Emile Nivelet, 08000 Charleville M\u00e9zi\u00e8res",
    "sg:city":"Charleville-M\u00e9zi\u00e8res",
    "sg:orig_category":"Unclassifiable Establishments",
    "sg:phone":"+33 3 24 59 17 36",
    "sg:postcode":"08000",
    "sg:province":"Champagne",
    "wof:name":"Techniques Rev\u00eatements S.a.r.l.",
    "wof:placetype":"venue"
},
  "geometry": {"coordinates":[4.695799,49.779339],"type":"Point"}
}