{
  "type": "Feature",
  "properties": {
    "iso:country":"FR",
    "sg:address":"485 Avenue De Lossburg Z I Nord 69480 Anse",
    "sg:classifiers":[
        {
            "category":"Professional",
            "subcategory":"Computer Services",
            "type":"Services"
        }
    ],
    "sg:phone":"+33 4 74 67 26 00",
    "sg:province":"Rhone-Alpes",
    "sg:tags":[
        "information",
        "technology",
        "software"
    ],
    "wof:name":"Data Fit International Dfi (d F I)",
    "wof:placetype":"venue"
},
  "geometry": {"coordinates":[4.69342,45.888],"type":"Point"}
}