{
  "type": "Feature",
  "properties": {
    "iso:country":"FR",
    "sg:address":"Le Martinet 47500 Sauveterre la L\u00e9mance",
    "sg:city":"Blanquefort-sur-Briolance",
    "sg:orig_category":"Unclassifiable Establishments",
    "sg:phone":"+33 5 53 40 63 15",
    "sg:postcode":"47500",
    "sg:province":"Aquitaine",
    "wof:name":"Les Chaux Du P\u00e9rigord S.a.",
    "wof:placetype":"venue"
},
  "geometry": {"coordinates":[1.022006,44.596291],"type":"Point"}
}