{
  "type": "Feature",
  "properties": {
    "addr:full":"ZI S\u00e9es Basse Normandie 61500",
    "addr:postcode":"61500",
    "addr:street":"Se\u0301Es Basse",
    "iso:country":"FR",
    "sg:address":"ZI",
    "sg:city":"S\u00e9es",
    "sg:orig_category":"Non-Classified Establishments",
    "sg:phone":"+33 2 33 81 21 00",
    "sg:postcode":"61500",
    "sg:province":"Basse Normandie",
    "wof:name":"Seppim-elitech S.a. - Soci\u00e9t\u00e9 D'etude Et De Promotion De Produits Indus",
    "wof:placetype":"venue"
},
  "geometry": {"coordinates":[0.158736,48.533112],"type":"Point"}
}