{
  "type": "Feature",
  "properties": {
    "addr:full":"14, Rue Waldeck Rousseau, 52100 Saint Dizier Champagne",
    "addr:housenumber":"14",
    "addr:postcode":"52100",
    "addr:street":"Rue Waldeck Rousseau;Dizier",
    "iso:country":"FR",
    "sg:address":"14, Rue Waldeck Rousseau, 52100 Saint Dizier",
    "sg:orig_category":"Unclassifiable Establishments",
    "sg:phone":"+33 3 25 05 05 57",
    "sg:province":"Champagne",
    "wof:name":"Soci\u00e9t\u00e9 Nouvelle Conraux S.a.r.l.",
    "wof:placetype":"venue"
},
  "geometry": {"coordinates":[4.941844,48.637829],"type":"Point"}
}