{
  "type": "Feature",
  "properties": {
    "addr:full":"235, Rue des Canesteux - ZI des Estoublans, 13300 Salon de Provence Provence-Alpes-C\u00f4te d'Azur",
    "addr:housenumber":"235",
    "addr:postcode":"13300",
    "addr:street":"Rue Des Canesteux Zi Des Estoublans;Provence",
    "iso:country":"FR",
    "sg:address":"235, Rue des Canesteux - ZI des Estoublans, 13300 Salon de Provence",
    "sg:orig_category":"Non-Classified Establishments",
    "sg:phone":"+33 4 90 17 01 70",
    "sg:province":"Provence-Alpes-C\u00f4te d'Azur",
    "wof:name":"Self Process S.a.s.",
    "wof:placetype":"venue"
},
  "geometry": {"coordinates":[5.098957,43.638432],"type":"Point"}
}