{
  "type": "Feature",
  "properties": {
    "addr:full":"B.P. 1, 53440 La Chapelle au Riboul^^Rte de Mayenne - ZA, 53440 La Chapelle au Riboul Pays de Loire 53440",
    "addr:housenumber":"1;53440",
    "addr:postcode":"53440;53440",
    "addr:street":"B.P.;Za",
    "iso:country":"FR",
    "sg:address":"B.P. 1, 53440 La Chapelle au Riboul^^Rte de Mayenne - ZA, 53440 La Chapelle au Riboul",
    "sg:orig_category":"Non-Classified Establishments",
    "sg:phone":"+33 2 43 00 75 31",
    "sg:postcode":"53440",
    "sg:province":"Pays de Loire",
    "wof:name":"Etablissements Lambert S.a.",
    "wof:placetype":"venue"
},
  "geometry": {"coordinates":[-0.549272,48.255035],"type":"Point"}
}