{
  "type": "Feature",
  "properties": {
    "iso:country":"FR",
    "sg:address":"57 Boulevard R\u00e9publique",
    "sg:city":"Chatou",
    "sg:classifiers":[
        {
            "category":"Banks & Credit Unions",
            "subcategory":"Financial Services",
            "type":"Services"
        }
    ],
    "sg:phone":"+33 1 30 71 48 40",
    "sg:postcode":"78400",
    "sg:province":"Ile de France",
    "sg:tags":[
        "banking",
        "finance",
        "insurance"
    ],
    "wof:name":"Duranton Consultants Sarl",
    "wof:placetype":"venue"
},
  "geometry": {"coordinates":[2.151938,48.895069],"type":"Point"}
}