{
  "type": "Feature",
  "properties": {
    "addr:full":"38 Boulevard Fontainebleau 91100 Corbeil Essonnes Ile de France",
    "addr:housenumber":"38",
    "addr:postcode":"91100",
    "addr:street":"Boulevard",
    "iso:country":"FR",
    "sg:address":"38 Boulevard Fontainebleau 91100 Corbeil Essonnes",
    "sg:classifiers":[
        {
            "category":"Manufacturing",
            "subcategory":"Rubber & Plastics",
            "type":"Manufacturing & Wholesale Goods"
        }
    ],
    "sg:phone":"+33 1 60 89 01 34",
    "sg:province":"Ile de France",
    "wof:name":"Centre D'orthopedie Chartrain",
    "wof:placetype":"venue"
},
  "geometry": {"coordinates":[2.472708,48.598152],"type":"Point"}
}