{
  "type": "Feature",
  "properties": {
    "iso:country":"FR",
    "sg:address":"ZAC de la Baudini\u00e8re",
    "sg:city":"Thouar\u00e9 sur Loire",
    "sg:orig_category":"Non-Classified Establishments",
    "sg:phone":"+33 2 40 68 06 07",
    "sg:postcode":"44470",
    "sg:province":"Pays de Loire",
    "wof:name":"S.o.f.r.a.c.o.m. S.a. - Soci\u00e9t\u00e9 Fran\u00e7aise De Radio Communication Et D'electronique Industrielle",
    "wof:placetype":"venue"
},
  "geometry": {"coordinates":[-1.440899,47.266781],"type":"Point"}
}