{
  "type": "Feature",
  "properties": {
    "addr:full":"253, Rue Menchecourt, 80100 Abbeville Picardie",
    "addr:housenumber":"253",
    "addr:postcode":"80100",
    "addr:street":"Rue Menchecourt",
    "iso:country":"FR",
    "sg:address":"253, Rue Menchecourt, 80100 Abbeville",
    "sg:orig_category":"Unclassifiable Establishments",
    "sg:phone":"+33 3 22 19 00 87",
    "sg:province":"Picardie",
    "wof:name":"Venditelli Transports S.a.",
    "wof:placetype":"venue"
},
  "geometry": {"coordinates":[1.809905,50.122272],"type":"Point"}
}