{
  "type": "Feature",
  "properties": {
    "iso:country":"FR",
    "sg:address":"22 Bis Rue Romainville 03300 Cusset",
    "sg:city":"Cusset",
    "sg:classifiers":[
        {
            "category":"Professional",
            "type":"Services"
        }
    ],
    "sg:phone":"+33 4 70 97 76 36",
    "sg:postcode":"03300",
    "sg:province":"Auvergne",
    "sg:tags":[
        "transport",
        "road"
    ],
    "wof:name":"Pass France Et Cie Sa",
    "wof:placetype":"venue"
},
  "geometry": {"coordinates":[3.43332,46.141384],"type":"Point"}
}