{
  "type": "Feature",
  "properties": {
    "addr:full":"24 R De Montr\u00e9al 74100 Ville La Grand Rhone-Alpes 74100",
    "addr:housenumber":"24",
    "addr:postcode":"74100;74100",
    "addr:street":"R De Montre\u0301Al;La Grand Rhone-Alpes",
    "iso:country":"FR",
    "sg:address":"24 R De Montr\u00e9al 74100 Ville La Grand",
    "sg:classifiers":[
        {
            "category":"Banks & Credit Unions",
            "subcategory":"Investment Brokerage",
            "type":"Services"
        }
    ],
    "sg:phone":"+33 4 50 37 06 49",
    "sg:postcode":"74100",
    "sg:province":"Rhone-Alpes",
    "sg:tags":[
        "-",
        "transport",
        "related"
    ],
    "wof:name":"Bmv",
    "wof:placetype":"venue"
},
  "geometry": {"coordinates":[6.279786,46.204189],"type":"Point"}
}