{
  "type": "Feature",
  "properties": {
    "addr:full":"30 Rue Gambetta 03000 Moulins Moulins Auvergne 03000",
    "addr:housenumber":"30",
    "addr:postcode":"03000;03000",
    "addr:street":"Rue Gambetta",
    "iso:country":"FR",
    "sg:address":"30 Rue Gambetta 03000 Moulins",
    "sg:city":"Moulins",
    "sg:classifiers":[
        {
            "category":"Professional",
            "subcategory":"Printing & Photocopies",
            "type":"Services"
        }
    ],
    "sg:phone":"+33 4 70 48 13 33",
    "sg:postcode":"03000",
    "sg:province":"Auvergne",
    "sg:tags":[
        "publishing"
    ],
    "wof:name":"La Montagne Centre France",
    "wof:placetype":"venue"
},
  "geometry": {"coordinates":[3.332483,46.563648],"type":"Point"}
}