{
  "type": "Feature",
  "properties": {
    "addr:full":"21 Avenue Voie Au Coq 14760 Bretteville Sur Odon Bretteville-sur-Odon Basse Normandie 14760",
    "addr:housenumber":"21",
    "addr:postcode":"14760;14760",
    "addr:street":"Avenue Voie Au Coq",
    "iso:country":"FR",
    "sg:address":"21 Avenue Voie Au Coq 14760 Bretteville Sur Odon",
    "sg:city":"Bretteville-sur-Odon",
    "sg:classifiers":[
        {
            "category":"Manufacturing",
            "subcategory":"Metals",
            "type":"Manufacturing & Wholesale Goods"
        }
    ],
    "sg:phone":"+33 2 31 73 07 80",
    "sg:postcode":"14760",
    "sg:province":"Basse Normandie",
    "sg:tags":[
        "metallurgy",
        "steel",
        "metalworking"
    ],
    "wof:name":"Pierre Germain Services",
    "wof:placetype":"venue"
},
  "geometry": {"coordinates":[-0.424436,49.164925],"type":"Point"}
}