{
  "type": "Feature",
  "properties": {
    "addr:full":"20 Rue Moliere 59100 Roubaix Nord Pas-de-Calais 59100",
    "addr:housenumber":"20",
    "addr:postcode":"59100;59100",
    "addr:street":"Rue Moliere",
    "iso:country":"FR",
    "sg:address":"20 Rue Moliere 59100 Roubaix",
    "sg:classifiers":[
        {
            "category":"Shopping",
            "type":"Retail Goods"
        }
    ],
    "sg:phone":"+33 3 20 82 76 24",
    "sg:postcode":"59100",
    "sg:province":"Nord Pas-de-Calais",
    "sg:tags":[
        "metallurgy",
        "finished",
        "-",
        "metalworking",
        "metallic"
    ],
    "wof:name":"Etablissements Theodore Delaval",
    "wof:placetype":"venue"
},
  "geometry": {"coordinates":[3.20029,50.689758],"type":"Point"}
}