{
  "type": "Feature",
  "properties": {
    "addr:full":"10 impasse Bergerie 06400 Cannes Berg Alsace 67320",
    "addr:housenumber":"10",
    "addr:postcode":"06400;67320",
    "addr:street":"Impasse Bergerie;Berg",
    "iso:country":"FR",
    "sg:address":"10 impasse Bergerie 06400 Cannes",
    "sg:city":"Berg",
    "sg:classifiers":[
        {
            "category":"Shopping",
            "subcategory":"Beauty & Cosmetics",
            "type":"Retail Goods"
        }
    ],
    "sg:phone":"+33 4 93 99 79 00",
    "sg:postcode":"67320",
    "sg:province":"Alsace",
    "sg:tags":[
        "permanent"
    ],
    "wof:name":"Algovital S.a.",
    "wof:placetype":"venue"
},
  "geometry": {"coordinates":[7.014267,43.552788],"type":"Point"}
}