{
  "type": "Feature",
  "properties": {
    "iso:country":"FR",
    "sg:address":"Quartier le Farigoulier",
    "sg:city":"Pertuis C\u00e9dex",
    "sg:orig_category":"Non-Classified Establishments",
    "sg:phone":"+33 4 90 09 79 79",
    "sg:postcode":"84124",
    "sg:province":"Provence-Alpes-C\u00f4te d'Azur",
    "wof:name":"S.o. C.o. M.e. L.u. S.a.",
    "wof:placetype":"venue"
},
  "geometry": {"coordinates":[5.50137,43.693653],"type":"Point"}
}