{
  "type": "Feature",
  "properties": {
    "iso:country":"FR",
    "sg:address":"359 R Georges M\u00e9li\u00e8s 41350 St Gervais La For\u00eat",
    "sg:city":"Saint-Gervais-la-For\u00eat",
    "sg:classifiers":[
        {
            "category":"Wholesale",
            "subcategory":"Machinery & Supplies",
            "type":"Manufacturing & Wholesale Goods"
        }
    ],
    "sg:phone":"+33 2 54 42 50 18",
    "sg:postcode":"41350",
    "sg:province":"Centre",
    "sg:tags":[
        "handling",
        "material",
        "-",
        "machine",
        "equipment",
        "engineering",
        "mechanical"
    ],
    "wof:name":"Setra Levage Sa",
    "wof:placetype":"venue"
},
  "geometry": {"coordinates":[1.373309,47.565311],"type":"Point"}
}