{
  "type": "Feature",
  "properties": {
    "addr:full":"1, Place des Coquets, 76130 Mont Saint Aignan Haute Normandie",
    "addr:housenumber":"1",
    "addr:postcode":"76130",
    "addr:street":"Place Des Coquets",
    "iso:country":"FR",
    "sg:address":"1, Place des Coquets, 76130 Mont Saint Aignan",
    "sg:orig_category":"Unclassifiable Establishments",
    "sg:phone":"+33 3 32 76 17 00",
    "sg:province":"Haute Normandie",
    "wof:name":"Carrier Transicold France S.a.",
    "wof:placetype":"venue"
},
  "geometry": {"coordinates":[1.081071,49.462673],"type":"Point"}
}