{
  "type": "Feature",
  "properties": {
    "addr:full":"rue de la Petite Monnaie 67520 Marlenheim Marlenheim Alsace 67520",
    "addr:postcode":"67520;67520",
    "addr:street":"Rue De La Petite Monnaie",
    "iso:country":"FR",
    "sg:address":"rue de la Petite Monnaie 67520 Marlenheim",
    "sg:city":"Marlenheim",
    "sg:classifiers":[
        {
            "category":"Wholesale",
            "subcategory":"Auto Parts",
            "type":"Manufacturing & Wholesale Goods"
        }
    ],
    "sg:phone":"+33 3 88 59 28 25",
    "sg:postcode":"67520",
    "sg:province":"Alsace",
    "sg:tags":[
        "textile",
        "machine",
        "industry",
        "carpet"
    ],
    "wof:name":"Janser-france Sa",
    "wof:placetype":"venue"
},
  "geometry": {"coordinates":[7.48657,48.620094],"type":"Point"}
}