{
  "type": "Feature",
  "properties": {
    "addr:full":"Les Gaudi\u00e8res 37390 Mettray Mettray Centre 37390",
    "addr:postcode":"37390;37390",
    "iso:country":"FR",
    "sg:address":"Les Gaudi\u00e8res 37390 Mettray",
    "sg:city":"Mettray",
    "sg:classifiers":[
        {
            "category":"Manufacturing",
            "subcategory":"Motor Vehicles & Parts",
            "type":"Manufacturing & Wholesale Goods"
        }
    ],
    "sg:phone":"+33 2 47 42 62 00",
    "sg:postcode":"37390",
    "sg:province":"Centre",
    "sg:tags":[
        "precision",
        "mechanic"
    ],
    "wof:name":"Ettel Mecanique De Precision S.a.",
    "wof:placetype":"venue"
},
  "geometry": {"coordinates":[0.6727,47.458931],"type":"Point"}
}