{
  "type": "Feature",
  "properties": {
    "addr:full":"69 Avenue De Paris 51000 Chalons En Champagne Champagne 51000",
    "addr:housenumber":"69",
    "addr:postcode":"51000;51000",
    "addr:street":"Avenue De Paris",
    "iso:country":"FR",
    "sg:address":"69 Avenue De Paris 51000 Chalons En Champagne",
    "sg:classifiers":[
        {
            "category":"Food Court",
            "type":"Food & Drink"
        }
    ],
    "sg:phone":"+33 3 26 68 29 51",
    "sg:postcode":"51000",
    "sg:province":"Champagne",
    "sg:tags":[
        "product",
        "related"
    ],
    "wof:name":"Joseph Perrier Fils Et Compagnie Sa",
    "wof:placetype":"venue"
},
  "geometry": {"coordinates":[4.343753,48.952785],"type":"Point"}
}