{
  "type": "Feature",
  "properties": {
    "iso:country":"FR",
    "sg:address":"B.P. 235",
    "sg:city":"Li\u00e9vin",
    "sg:orig_category":"Non-Classified Establishments",
    "sg:phone":"+33 3 21 45 83 00",
    "sg:postcode":"62800",
    "sg:province":"Nord Pas-de-Calais",
    "wof:name":"Lef\u00e8bvre Menuiserie S.a.r.l.",
    "wof:placetype":"venue"
},
  "geometry": {"coordinates":[2.779565,50.4216],"type":"Point"}
}