{
  "type": "Feature",
  "properties": {
    "iso:country":"FR",
    "sg:address":"Le Bourg 42110 Pouilly l\u00e8s Feurs",
    "sg:orig_category":"Non-Classified Establishments",
    "sg:phone":"+33 4 77 26 63 00",
    "sg:postcode":"42110",
    "sg:province":"Rhone-Alpes",
    "wof:name":"Merle Et Compagnie Salaisons S.a.",
    "wof:placetype":"venue"
},
  "geometry": {"coordinates":[4.176355,45.697975],"type":"Point"}
}