{
  "type": "Feature",
  "properties": {
    "addr:full":"7, Rue Lesage, 75020 Paris Ile de France",
    "addr:housenumber":"7",
    "addr:postcode":"75020",
    "addr:street":"Rue Lesage",
    "iso:country":"FR",
    "sg:address":"7, Rue Lesage, 75020 Paris",
    "sg:orig_category":"Non-Classified Establishments",
    "sg:phone":"+33 1 46 36 64 29",
    "sg:province":"Ile de France",
    "wof:name":"Martin-prunier S.a.",
    "wof:placetype":"venue"
},
  "geometry": {"coordinates":[2.381164,48.872223],"type":"Point"}
}