{
  "type": "Feature",
  "properties": {
    "addr:full":"Aire De Ste-Maure Ouest Autoroute A10 37800 St-Epain Antogny le Tillac Centre 37800",
    "addr:housenumber":"antogny le tillac",
    "addr:postcode":"37800;37800",
    "addr:street":"Autoroute A10",
    "iso:country":"FR",
    "sg:address":"Aire De Ste-Maure Ouest Autoroute A10 37800 St-Epain",
    "sg:city":"Antogny le Tillac",
    "sg:classifiers":[
        {
            "category":"Travel",
            "subcategory":"Hotels & Motels",
            "type":"Entertainment"
        }
    ],
    "sg:phone":"+33 2 47 65 53 61",
    "sg:postcode":"37800",
    "sg:province":"Centre",
    "sg:tags":[
        "hotels",
        "business",
        "restaurant"
    ],
    "wof:name":"Holding De Restauration Conc\u00c9d\u00c9e-caf\u00c9 Route",
    "wof:placetype":"venue"
},
  "geometry": {"coordinates":[0.604883,47.136543],"type":"Point"}
}