{
  "type": "Feature",
  "properties": {
    "addr:full":"B.P. 1, 10250 Mussy sur Seine^^Rue Paul Terillon, 10250 Mussy sur Seine Champagne 10250",
    "addr:housenumber":"1",
    "addr:postcode":"10250;10250;10250",
    "addr:street":"B.P.;Seine^^Rue;Terillon",
    "iso:country":"FR",
    "sg:address":"B.P. 1, 10250 Mussy sur Seine^^Rue Paul Terillon, 10250 Mussy sur Seine",
    "sg:orig_category":"Non-Classified Establishments",
    "sg:phone":"+33 3 25 38 34 00",
    "sg:postcode":"10250",
    "sg:province":"Champagne",
    "wof:name":"Clip-look Pakers S.a.",
    "wof:placetype":"venue"
},
  "geometry": {"coordinates":[4.49762,47.977242],"type":"Point"}
}