{
  "type": "Feature",
  "properties": {
    "iso:country":"FR",
    "sg:address":"36, Rue Blaise Pascal, 07500 Guilherand Granges",
    "sg:orig_category":"Unclassifiable Establishments",
    "sg:phone":"+33 4 75 44 45 40",
    "sg:province":"Rhone-Alpes",
    "wof:name":"I.r.t.r.a. S.a. - Illustrations Et R\u00e9alisations Techniques Rh\u00f4ne Alpes",
    "wof:placetype":"venue"
},
  "geometry": {"coordinates":[4.86298,44.932777],"type":"Point"}
}