{
  "type": "Feature",
  "properties": {
    "iso:country":"FR",
    "sg:address":"2, Rue Rabelais, 38200 Vienne",
    "sg:orig_category":"Unclassifiable Establishments",
    "sg:phone":"+33 4 74 78 88 88",
    "sg:province":"Rhone-Alpes",
    "wof:name":"B\u00e9al S.a.",
    "wof:placetype":"venue"
},
  "geometry": {"coordinates":[4.881475,45.526768],"type":"Point"}
}