{
  "type": "Feature",
  "properties": {
    "addr:full":"Rue de l'Industrie - ZI de la Chapelette P\u00e9ronne Picardie 80200",
    "addr:postcode":"80200",
    "addr:street":"Rue De L'Industrie Zi De La Chapelette",
    "iso:country":"FR",
    "sg:address":"Rue de l'Industrie - ZI de la Chapelette",
    "sg:city":"P\u00e9ronne",
    "sg:orig_category":"Unclassifiable Establishments",
    "sg:phone":"+33 3 22 73 37 00",
    "sg:postcode":"80200",
    "sg:province":"Picardie",
    "wof:name":"Delaigle Transports S.a.",
    "wof:placetype":"venue"
},
  "geometry": {"coordinates":[2.928871,49.91436],"type":"Point"}
}