{
  "type": "Feature",
  "properties": {
    "iso:country":"FR",
    "sg:address":"8",
    "sg:city":"Charles Galland; La Fare les Oliviers",
    "sg:classifiers":[
        {
            "category":"Banks & Credit Unions",
            "subcategory":"Bank",
            "type":"Services"
        }
    ],
    "sg:phone":"+33 3390426272",
    "sg:province":"Rhone-Alpes",
    "wof:name":"Cr\u00e9dit Agricole",
    "wof:placetype":"venue"
},
  "geometry": {"coordinates":[5.194073,43.55106],"type":"Point"}
}