{
  "type": "Feature",
  "properties": {
    "addr:full":"6, Rue Jean Fran\u00e7ois Marmontel - R\u00e9sidence Parc de Bacchus, 66000 Perpignan Languedoc-Roussillon",
    "addr:housenumber":"6",
    "addr:postcode":"66000",
    "addr:street":"Rue Jean Franc\u0327Ois Marmontel Re\u0301Sidence Parc De Bacchus",
    "iso:country":"FR",
    "sg:address":"6, Rue Jean Fran\u00e7ois Marmontel - R\u00e9sidence Parc de Bacchus, 66000 Perpignan",
    "sg:orig_category":"Unclassifiable Establishments",
    "sg:phone":"+33 4 68 56 82 82",
    "sg:province":"Languedoc-Roussillon",
    "wof:name":"Oxxo S.a.",
    "wof:placetype":"venue"
},
  "geometry": {"coordinates":[2.886514,42.689171],"type":"Point"}
}