{
  "type": "Feature",
  "properties": {
    "iso:country":"FR",
    "sg:address":"B.P. 13 - 59, 59731 Saint Amand les Eaux C\u00e9dex^^ZA Champs des Oiseaux, 59230 Saint Amand les Eaux",
    "sg:orig_category":"Non-Classified Establishments",
    "sg:phone":"+33 3 27 27 88 00",
    "sg:province":"Nord Pas-de-Calais",
    "wof:name":"Saint G\u00e9ry S.a.",
    "wof:placetype":"venue"
},
  "geometry": {"coordinates":[3.40956,50.454521],"type":"Point"}
}