{
  "type": "Feature",
  "properties": {
    "iso:country":"FR",
    "sg:address":"52 Avenue Des Champs Elys\u00e9es",
    "sg:city":"Paris",
    "sg:classifiers":[
        {
            "category":"Banks & Credit Unions",
            "subcategory":"Financial Services",
            "type":"Services"
        }
    ],
    "sg:phone":"+33 1 40 74 15 15",
    "sg:postcode":"75008",
    "sg:province":"Ile de France",
    "sg:tags":[
        "banking",
        "finance",
        "insurance"
    ],
    "wof:name":"Gestion Participation Finacor Sa",
    "wof:placetype":"venue"
},
  "geometry": {"coordinates":[2.306304,48.870358],"type":"Point"}
}