{
  "type": "Feature",
  "properties": {
    "addr:full":"14 Rue De La Banque Bureau 0055 71100 Chalon Sur Sa\u00f4ne Chalon-sur-Sa\u00f4ne Bourgogne 71100",
    "addr:housenumber":"14;0055",
    "addr:postcode":"71100;71100",
    "addr:street":"Rue De La Banque",
    "iso:country":"FR",
    "sg:address":"14 Rue De La Banque Bureau 0055 71100 Chalon Sur Sa\u00f4ne",
    "sg:city":"Chalon-sur-Sa\u00f4ne",
    "sg:classifiers":[
        {
            "category":"Banks & Credit Unions",
            "subcategory":"Financial Services",
            "type":"Services"
        }
    ],
    "sg:phone":"+33 3 85 42 56 16",
    "sg:postcode":"71100",
    "sg:province":"Bourgogne",
    "sg:tags":[
        "banking",
        "insurance",
        "institution",
        "finance"
    ],
    "wof:name":"Caisse Regionale Credit Agricole Mutuel Centre Est",
    "wof:placetype":"venue"
},
  "geometry": {"coordinates":[4.85501,46.779694],"type":"Point"}
}