{
  "type": "Feature",
  "properties": {
    "iso:country":"FR",
    "sg:address":"1 Rue Traversi\u00e8re 94150 Rungis",
    "sg:classifiers":[
        {
            "category":"Utilities",
            "subcategory":"Natural Gas",
            "type":"Services"
        }
    ],
    "sg:phone":"+33 1 49 78 45 00",
    "sg:postcode":"94150",
    "sg:province":"Ile de France",
    "wof:name":"Praxair S.a.",
    "wof:placetype":"venue"
},
  "geometry": {"coordinates":[2.35284,48.746067],"type":"Point"}
}