{
  "type": "Feature",
  "properties": {
    "addr:full":"Cour de la Gare B\u00e9thune Nord Pas-de-Calais 62400",
    "addr:postcode":"62400",
    "addr:street":"Cour De La Gare Be\u0301Thune Nord",
    "iso:country":"FR",
    "sg:address":"Cour de la Gare",
    "sg:city":"B\u00e9thune",
    "sg:orig_category":"Non-Classified Establishments",
    "sg:phone":"+33 3 21 65 75 77",
    "sg:postcode":"62400",
    "sg:province":"Nord Pas-de-Calais",
    "wof:name":"B\u00e9thune Transports S.a.r.l.",
    "wof:placetype":"venue"
},
  "geometry": {"coordinates":[2.639628,50.519737],"type":"Point"}
}