{
  "type": "Feature",
  "properties": {
    "iso:country":"FR",
    "sg:address":"1735 avenue Julien Panchot 66000 Perpignan",
    "sg:classifiers":[
        {
            "category":"Organizations",
            "subcategory":"Non-profit Organization",
            "type":"Services"
        }
    ],
    "sg:phone":"+33 4 68 56 50 33",
    "sg:postcode":"66000",
    "sg:province":"Languedoc-Roussillon",
    "sg:tags":[
        "alarm",
        "system"
    ],
    "wof:name":"Gaz Protection Systemes S.a.",
    "wof:placetype":"venue"
},
  "geometry": {"coordinates":[2.87378,42.688091],"type":"Point"}
}