{
  "type": "Feature",
  "properties": {
    "iso:country":"FR",
    "sg:address":"40 rue de Seine 94400 VITRY SUR SEINE",
    "sg:classifiers":[
        {
            "category":"Professional",
            "subcategory":"Management & Consulting",
            "type":"Services"
        }
    ],
    "sg:phone":"+33 1 47 18 55 00",
    "sg:postcode":"94400",
    "sg:province":"Ile de France",
    "sg:tags":[
        "logistics"
    ],
    "wof:name":"Giraud Sa",
    "wof:placetype":"venue"
},
  "geometry": {"coordinates":[2.41251,48.797543],"type":"Point"}
}