{
  "type": "Feature",
  "properties": {
    "addr:full":"rue de Marcigny 42720 Pouilly sous Charlieu Rhone-Alpes 42720",
    "addr:postcode":"42720;42720",
    "addr:street":"Rue De Marcigny",
    "iso:country":"FR",
    "sg:address":"rue de Marcigny 42720 Pouilly sous Charlieu",
    "sg:classifiers":[
        {
            "category":"Wholesale",
            "subcategory":"Vending Machines",
            "type":"Manufacturing & Wholesale Goods"
        }
    ],
    "sg:phone":"+33 4 77 60 84 10",
    "sg:postcode":"42720",
    "sg:province":"Rhone-Alpes",
    "sg:tags":[
        "joiner's"
    ],
    "wof:name":"Glacever Alu Sa",
    "wof:placetype":"venue"
},
  "geometry": {"coordinates":[4.10866,46.149284],"type":"Point"}
}