{
  "type": "Feature",
  "properties": {
    "addr:full":"153 Chem De La Salade Ponsan 31400 Toulouse Midi Pyr\u00e9n\u00e9es 31400",
    "addr:housenumber":"153",
    "addr:postcode":"31400;31400",
    "addr:street":"Chem De La Salade Ponsan",
    "iso:country":"FR",
    "sg:address":"153 Chem De La Salade Ponsan 31400 Toulouse",
    "sg:classifiers":[
        {
            "category":"Professional",
            "subcategory":"Business Services",
            "type":"Services"
        }
    ],
    "sg:phone":"+33 5 62 26 38 37",
    "sg:postcode":"31400",
    "sg:province":"Midi Pyr\u00e9n\u00e9es",
    "sg:tags":[
        "body",
        "advice"
    ],
    "wof:name":"Federation Regionale Des Mjc Midi-pyrenees",
    "wof:placetype":"venue"
},
  "geometry": {"coordinates":[1.450153,43.570744],"type":"Point"}
}