{
  "type": "Feature",
  "properties": {
    "addr:full":"Le Bois Maulny 72650 St Saturnin Pays de Loire",
    "addr:postcode":"72650",
    "addr:street":"Bois Maulny;Saturnin",
    "iso:country":"FR",
    "sg:address":"Le Bois Maulny 72650 St Saturnin",
    "sg:classifiers":[
        {
            "category":"Home & Garden",
            "subcategory":"Furniture",
            "type":"Retail Goods"
        }
    ],
    "sg:phone":"+33 2 43 25 68 18",
    "sg:province":"Pays de Loire",
    "sg:tags":[
        "wood"
    ],
    "wof:name":"Le Mans Charpentes Sas",
    "wof:placetype":"venue"
},
  "geometry": {"coordinates":[0.16381,48.071705],"type":"Point"}
}