{
  "type": "Feature",
  "properties": {
    "iso:country":"FR",
    "sg:address":"50, Rue de Pontoise, 95870 Bezons",
    "sg:orig_category":"Non-Classified Establishments",
    "sg:phone":"+33 1 39 61 56 42",
    "sg:postcode":"95870",
    "sg:province":"Ile de France",
    "wof:name":"A.t.e.c. S.a.",
    "wof:placetype":"venue"
},
  "geometry": {"coordinates":[2.21727,48.924858],"type":"Point"}
}