{
  "type": "Feature",
  "properties": {
    "iso:country":"FR",
    "sg:address":"ZI de Longchamp",
    "sg:city":"Cerizay",
    "sg:orig_category":"Unclassifiable Establishments",
    "sg:phone":"+33 5 49 80 58 64",
    "sg:postcode":"79140",
    "sg:province":"Poitou-Charentes",
    "wof:name":"E.g.d.c. S.a.",
    "wof:placetype":"venue"
},
  "geometry": {"coordinates":[-0.669854,46.821056],"type":"Point"}
}