{
  "type": "Feature",
  "properties": {
    "iso:country":"FR",
    "sg:address":"21130 Villers les Pots",
    "sg:city":"Saint-Seine-en-B\u00e2che",
    "sg:orig_category":"Unclassifiable Establishments",
    "sg:phone":"+33 3 80 77 11 77",
    "sg:postcode":"21130",
    "sg:province":"Bourgogne",
    "wof:name":"S.i.t.p.a. S.a.",
    "wof:placetype":"venue"
},
  "geometry": {"coordinates":[5.35479,47.208313],"type":"Point"}
}