{
  "type": "Feature",
  "properties": {
    "addr:full":"Rue de Gere Belesten Serres Castet Aquitaine 64121",
    "addr:postcode":"64121",
    "addr:street":"Rue De Gere Belesten Serres",
    "iso:country":"FR",
    "sg:address":"Rue de Gere Belesten",
    "sg:city":"Serres Castet",
    "sg:orig_category":"Unclassifiable Establishments",
    "sg:phone":"+33 5 59 33 22 98",
    "sg:postcode":"64121",
    "sg:province":"Aquitaine",
    "wof:name":"S.e.p.s. S.a. - Synergie Etudes Productique Syst\u00e8mes",
    "wof:placetype":"venue"
},
  "geometry": {"coordinates":[-0.387523,43.364254],"type":"Point"}
}