{
  "type": "Feature",
  "properties": {
    "addr:full":"B.P. 174, 44145 Ch\u00e2teaubriant C\u00e9dex^^Rte de Laval, 44140 Ch\u00e2teaubriant Pays de Loire",
    "addr:housenumber":"b.p. 174",
    "addr:postcode":"44145;44140",
    "addr:street":"Laval",
    "iso:country":"FR",
    "sg:address":"B.P. 174, 44145 Ch\u00e2teaubriant C\u00e9dex^^Rte de Laval, 44140 Ch\u00e2teaubriant",
    "sg:orig_category":"Non-Classified Establishments",
    "sg:phone":"+33 2 40 81 17 85",
    "sg:province":"Pays de Loire",
    "wof:name":"R\u00e9cup 44 S.a.r.l.",
    "wof:placetype":"venue"
},
  "geometry": {"coordinates":[-1.426909,47.009285],"type":"Point"}
}