{
  "type": "Feature",
  "properties": {
    "iso:country":"FR",
    "sg:address":"quartier du Ch\u00e2teau 06580 Pegomas",
    "sg:city":"Ch\u00e2teau",
    "sg:classifiers":[
        {
            "category":"Manufacturing",
            "subcategory":"Chemicals & Compounds",
            "type":"Manufacturing & Wholesale Goods"
        }
    ],
    "sg:phone":"+33 4 93 40 54 80",
    "sg:postcode":"71250",
    "sg:province":"Bourgogne",
    "sg:tags":[
        "product",
        "aromatic"
    ],
    "wof:name":"Ets Ernest Cavasse Scs",
    "wof:placetype":"venue"
},
  "geometry": {"coordinates":[6.9316,43.596455],"type":"Point"}
}