{
  "type": "Feature",
  "properties": {
    "iso:country":"FR",
    "sg:address":"Rte d'Orchaire - Le Gaug\u00e9",
    "sg:city":"Saint Lubin en Vergonnois",
    "sg:orig_category":"Unclassifiable Establishments",
    "sg:phone":"+33 2 54 43 26 76",
    "sg:postcode":"41190",
    "sg:province":"Centre",
    "wof:name":"Hernandez Jean-michel",
    "wof:placetype":"venue"
},
  "geometry": {"coordinates":[1.228812,47.607941],"type":"Point"}
}