{
  "type": "Feature",
  "properties": {
    "addr:full":"11, Rue Montaigne, 37540 Saint Cyr sur Loire Saint-Cyr-sur-Loire Centre 37540",
    "addr:housenumber":"11",
    "addr:postcode":"37540;37540",
    "addr:street":"Rue Montaigne;Cyr",
    "iso:country":"FR",
    "sg:address":"11, Rue Montaigne, 37540 Saint Cyr sur Loire",
    "sg:city":"Saint-Cyr-sur-Loire",
    "sg:orig_category":"Non-Classified Establishments",
    "sg:phone":"+33 2 47 54 53 29",
    "sg:postcode":"37540",
    "sg:province":"Centre",
    "wof:name":"Placal Industries S.a.r.l.",
    "wof:placetype":"venue"
},
  "geometry": {"coordinates":[0.656917,47.418629],"type":"Point"}
}