{
  "type": "Feature",
  "properties": {
    "addr:full":"50, Av. du Pr\u00e9sident Sadate, 29562 Quimper C\u00e9dex Quimper Bretagne 29000",
    "addr:postcode":"29562;29000",
    "addr:street":"50 Av. Du Pre\u0301Sident Sadate",
    "iso:country":"FR",
    "sg:address":"50, Av. du Pr\u00e9sident Sadate, 29562 Quimper C\u00e9dex",
    "sg:city":"Quimper",
    "sg:orig_category":"Non-Classified Establishments",
    "sg:phone":"+33 2 98 76 70 00",
    "sg:postcode":"29000",
    "sg:province":"Bretagne",
    "wof:name":"Matra Nortel Communications S.a.",
    "wof:placetype":"venue"
},
  "geometry": {"coordinates":[-4.09986,47.99593],"type":"Point"}
}