{
  "type": "Feature",
  "properties": {
    "iso:country":"FR",
    "sg:address":"4, Rue Sainte Barbe, 68130 Altkirch",
    "sg:city":"Altkirch",
    "sg:orig_category":"Non-Classified Establishments",
    "sg:phone":"+33 3 89 40 98 12",
    "sg:postcode":"68130",
    "sg:province":"Alsace",
    "wof:name":"Bixel S.a.r.l.",
    "wof:placetype":"venue"
},
  "geometry": {"coordinates":[7.234875,47.625809],"type":"Point"}
}