{
  "type": "Feature",
  "properties": {
    "iso:country":"FR",
    "sg:address":"ZI de la Bastide Blanche",
    "sg:city":"Vitrolles",
    "sg:orig_category":"Non-Classified Establishments",
    "sg:phone":"+33 4 42 15 94 40",
    "sg:postcode":"13127",
    "sg:province":"Provence-Alpes-C\u00f4te d'Azur",
    "wof:name":"Tim Transitube S.a.",
    "wof:placetype":"venue"
},
  "geometry": {"coordinates":[5.253005,43.449944],"type":"Point"}
}