{
  "type": "Feature",
  "properties": {
    "addr:full":"20 Rue D'Aristide Berges 38800 Le Pont De Claix Rhone-Alpes 38800",
    "addr:housenumber":"20",
    "addr:postcode":"38800;38800",
    "addr:street":"Rue D'Aristide Berges;Pont De;Rhone-Alpes",
    "iso:country":"FR",
    "sg:address":"20 Rue D'Aristide Berges 38800 Le Pont De Claix",
    "sg:classifiers":[
        {
            "category":"Shopping",
            "subcategory":"Computers & Home Electronics",
            "type":"Retail Goods"
        }
    ],
    "sg:phone":"+33 4 76 98 30 99",
    "sg:postcode":"38800",
    "sg:province":"Rhone-Alpes",
    "sg:tags":[
        "information",
        "peripheral",
        "-",
        "technology"
    ],
    "wof:name":"Bks Electronique Sa",
    "wof:placetype":"venue"
},
  "geometry": {"coordinates":[5.694403,45.138149],"type":"Point"}
}