{
  "type": "Feature",
  "properties": {
    "addr:full":"Ccal Beaulieu Zone Commerciale 17284 Puilboreau Beaulieu Auvergne 15270",
    "addr:postcode":"17284;15270",
    "addr:street":"Zone Commerciale",
    "iso:country":"FR",
    "sg:address":"Ccal Beaulieu Zone Commerciale 17284 Puilboreau",
    "sg:city":"Beaulieu",
    "sg:classifiers":[
        {
            "category":"Banks & Credit Unions",
            "subcategory":"Financial Services",
            "type":"Services"
        }
    ],
    "sg:phone":"+33 5 46 67 18 66",
    "sg:postcode":"15270",
    "sg:province":"Auvergne",
    "sg:tags":[
        "banking",
        "insurance",
        "institution",
        "finance"
    ],
    "wof:name":"Cetelem",
    "wof:placetype":"venue"
},
  "geometry": {"coordinates":[-1.118,46.185532],"type":"Point"}
}