{
  "type": "Feature",
  "properties": {
    "iso:country":"FR",
    "sg:address":"B.P. 53505, 44335 Nantes C\u00e9dex 3^^3, Rue de la Garde, 44100 Nantes",
    "sg:orig_category":"Non-Classified Establishments",
    "sg:phone":"+33 2 40 18 42 00",
    "sg:province":"Pays de Loire",
    "wof:name":"T.t.o. Cariane Atlantique S.a. - Transport Et Tourisme De L'ouest",
    "wof:placetype":"venue"
},
  "geometry": {"coordinates":[-1.60436,47.211891],"type":"Point"}
}