{
  "type": "Feature",
  "properties": {
    "addr:full":"6 Rue Des Pins Mios Balanos 33470 Le Teich Le Teich Aquitaine 33470",
    "addr:housenumber":"6;teich;teich",
    "addr:postcode":"33470;33470",
    "addr:street":"Rue Des Pins;Balanos",
    "iso:country":"FR",
    "sg:address":"6 Rue Des Pins Mios Balanos 33470 Le Teich",
    "sg:city":"Le Teich",
    "sg:classifiers":[
        {
            "category":"Farming",
            "subcategory":"Livestock Farm",
            "type":"Manufacturing & Wholesale Goods"
        }
    ],
    "sg:phone":"+33 5 56 22 69 50",
    "sg:postcode":"33470",
    "sg:province":"Aquitaine",
    "sg:tags":[
        "preserve",
        "product",
        "food",
        "related",
        "animal",
        "breeding",
        "agriculture"
    ],
    "wof:name":"Ste Agricole Et Pisicole L'esturgeonniere",
    "wof:placetype":"venue"
},
  "geometry": {"coordinates":[-1.080779,44.636234],"type":"Point"}
}