{
  "type": "Feature",
  "properties": {
    "iso:country":"FR",
    "sg:address":"31, Rue Rouchet, 75017 Paris",
    "sg:orig_category":"Non-Classified Establishments",
    "sg:phone":"+33 1 44 85 65 07",
    "sg:province":"Ile de France",
    "wof:name":"O.g.i.c. S.a.",
    "wof:placetype":"venue"
},
  "geometry": {"coordinates":[2.318885,48.883629],"type":"Point"}
}