{
  "type": "Feature",
  "properties": {
    "iso:country":"FR",
    "sg:address":"11 ave N\u00f4tre Dame; Nice",
    "sg:classifiers":[
        {
            "category":"Banks & Credit Unions",
            "subcategory":"Bank",
            "type":"Services"
        }
    ],
    "sg:phone":"+33 3393856913",
    "wof:name":"Cr\u00e9dit Lyonnais, Agence Lepante",
    "wof:placetype":"venue"
},
  "geometry": {"coordinates":[-122.8386,39.121292],"type":"Point"}
}