{
  "type": "Feature",
  "properties": {
    "iso:country":"FR",
    "sg:address":"Rue Max Jacob - ZAC Montimaran",
    "sg:city":"B\u00e9ziers",
    "sg:orig_category":"Unclassifiable Establishments",
    "sg:phone":"+33 4 67 35 88 20",
    "sg:postcode":"34500",
    "sg:province":"Languedoc-Roussillon",
    "wof:name":"Alliance Sant\u00e9 S.a.s.",
    "wof:placetype":"venue"
},
  "geometry": {"coordinates":[3.216105,43.344234],"type":"Point"}
}