{
  "type": "Feature",
  "properties": {
    "iso:country":"FR",
    "sg:address":"Parking du Country Club; Gif; 91190",
    "sg:classifiers":[
        {
            "category":"Banks & Credit Unions",
            "subcategory":"Bank",
            "type":"Services"
        }
    ],
    "sg:phone":"+33 3360122800",
    "sg:postcode":"91190",
    "sg:province":"Ile de France",
    "wof:name":"Banque Nationale De Paris",
    "wof:placetype":"venue"
},
  "geometry": {"coordinates":[2.132455,48.702435],"type":"Point"}
}