{
  "type": "Feature",
  "properties": {
    "addr:full":"107 Rue De Siame 29200 Brest Brest Bretagne 29200",
    "addr:housenumber":"107",
    "addr:postcode":"29200;29200",
    "addr:street":"Rue De Siame",
    "iso:country":"FR",
    "sg:address":"107 Rue De Siame 29200 Brest",
    "sg:city":"Brest",
    "sg:classifiers":[
        {
            "category":"Shopping",
            "subcategory":"Clothing, Apparel, & Fashions",
            "type":"Retail Goods"
        }
    ],
    "sg:phone":"+33 2 98 33 24 76",
    "sg:postcode":"29200",
    "sg:province":"Bretagne",
    "sg:tags":[
        "textile",
        "clothing",
        "clothes"
    ],
    "wof:name":"Cyrillus Sa",
    "wof:placetype":"venue"
},
  "geometry": {"coordinates":[-4.487549,48.389172],"type":"Point"}
}