{
  "type": "Feature",
  "properties": {
    "iso:country":"FR",
    "sg:address":"25, Chemin des Croch\u00e8res, 39570 Montmorot",
    "sg:orig_category":"Unclassifiable Establishments",
    "sg:phone":"+33 3 84 47 41 77",
    "sg:province":"Franche Comt\u00e9",
    "wof:name":"Sodimav S.a.",
    "wof:placetype":"venue"
},
  "geometry": {"coordinates":[5.537196,46.677326],"type":"Point"}
}