{
  "type": "Feature",
  "properties": {
    "addr:full":"75 rue de Charonne 75011 Paris Ile de France 75011",
    "addr:housenumber":"75",
    "addr:postcode":"75011;75011",
    "addr:street":"Rue De Charonne",
    "iso:country":"FR",
    "sg:address":"75 rue de Charonne 75011 Paris",
    "sg:classifiers":[
        {
            "category":"Home & Garden",
            "subcategory":"Home Furnishings",
            "type":"Retail Goods"
        }
    ],
    "sg:phone":"+33 1 43 72 47 20",
    "sg:postcode":"75011",
    "sg:province":"Ile de France",
    "sg:tags":[
        "hostel"
    ],
    "wof:name":"Leobert Tobolski Freres Sarl",
    "wof:placetype":"venue"
},
  "geometry": {"coordinates":[2.381045,48.853859],"type":"Point"}
}