{
  "type": "Feature",
  "properties": {
    "iso:country":"FR",
    "sg:address":"ZI",
    "sg:city":"Serri\u00e8res en Chautagne",
    "sg:orig_category":"Non-Classified Establishments",
    "sg:phone":"+33 4 79 63 70 54",
    "sg:postcode":"73310",
    "sg:province":"Rhone-Alpes",
    "wof:name":"Cagnon S.a.",
    "wof:placetype":"venue"
},
  "geometry": {"coordinates":[5.82096,45.754227],"type":"Point"}
}