{
  "type": "Feature",
  "properties": {
    "addr:full":"17 Rue Franklin Roosevelt 49400 Saumur Pays de Loire 49400",
    "addr:housenumber":"17",
    "addr:postcode":"49400;49400",
    "addr:street":"Rue Franklin Roosevelt",
    "iso:country":"FR",
    "sg:address":"17 Rue Franklin Roosevelt 49400 Saumur",
    "sg:classifiers":[
        {
            "category":"Shopping",
            "subcategory":"Clothing, Apparel, & Fashions",
            "type":"Retail Goods"
        }
    ],
    "sg:phone":"+33 2 41 51 21 23",
    "sg:postcode":"49400",
    "sg:province":"Pays de Loire",
    "sg:tags":[
        "textile",
        "clothing",
        "clothes"
    ],
    "wof:name":"Promod",
    "wof:placetype":"venue"
},
  "geometry": {"coordinates":[-0.0782,47.259933],"type":"Point"}
}