{
  "type": "Feature",
  "properties": {
    "addr:full":"33220 Eynesse Eynesse Aquitaine 33220",
    "addr:postcode":"33220;33220",
    "iso:country":"FR",
    "sg:address":"33220 Eynesse",
    "sg:city":"Eynesse",
    "sg:orig_category":"Unclassifiable Establishments",
    "sg:phone":"+33 5 57 41 04 04",
    "sg:postcode":"33220",
    "sg:province":"Aquitaine",
    "wof:name":"M.d.s. S.a. - Maroquinerie Du Sablon",
    "wof:placetype":"venue"
},
  "geometry": {"coordinates":[0.15068,44.825985],"type":"Point"}
}