{
  "type": "Feature",
  "properties": {
    "addr:full":"1 Av Boutarey 69580 Sathonay Camp Rhone-Alpes 69580",
    "addr:postcode":"69580;69580",
    "addr:street":"Av Boutarey;Rhone-Alpes",
    "iso:country":"FR",
    "sg:address":"1 Av Boutarey 69580 Sathonay Camp",
    "sg:classifiers":[
        {
            "category":"Professional",
            "subcategory":"Advertising",
            "type":"Services"
        }
    ],
    "sg:phone":"+33 4 72 27 08 36",
    "sg:postcode":"69580",
    "sg:province":"Rhone-Alpes",
    "sg:tags":[
        "communication",
        "medium"
    ],
    "wof:name":"Publisud Sarl",
    "wof:placetype":"venue"
},
  "geometry": {"coordinates":[4.876217,45.821598],"type":"Point"}
}