{
  "type": "Feature",
  "properties": {
    "iso:country":"FR",
    "sg:address":"28, Rue Joseph Cugnot - ZI N\u00b0 2, 37300 Jou\u00e9 l\u00e8s Tours",
    "sg:city":"Jou\u00e9-l\u00e8s-Tours",
    "sg:orig_category":"Non-Classified Establishments",
    "sg:phone":"+33 2 47 53 66 48",
    "sg:postcode":"37300",
    "sg:province":"Centre",
    "wof:name":"Nidag Protection S.a.r.l.",
    "wof:placetype":"venue"
},
  "geometry": {"coordinates":[0.662555,47.350945],"type":"Point"}
}