{
  "type": "Feature",
  "properties": {
    "addr:full":"17, Rue de la Victoire, 69003 Lyon Rhone-Alpes",
    "addr:housenumber":"17",
    "addr:postcode":"69003",
    "addr:street":"Rue De La Victoire",
    "iso:country":"FR",
    "sg:address":"17, Rue de la Victoire, 69003 Lyon",
    "sg:orig_category":"Unclassifiable Establishments",
    "sg:phone":"+33 4 78 60 59 31",
    "sg:province":"Rhone-Alpes",
    "wof:name":"Actibase S.a.r.l.",
    "wof:placetype":"venue"
},
  "geometry": {"coordinates":[4.84158,45.757038],"type":"Point"}
}