{
  "type": "Feature",
  "properties": {
    "iso:country":"FR",
    "sg:address":"Rue Belle Croix 57365 ENNERY",
    "sg:classifiers":[
        {
            "category":"Banks & Credit Unions",
            "subcategory":"Investment Brokerage",
            "type":"Services"
        }
    ],
    "sg:phone":"+33 3 87 73 95 79",
    "sg:postcode":"57365",
    "sg:province":"Lorraine",
    "sg:tags":[
        "mobile",
        "cranes",
        "hydraulic"
    ],
    "wof:name":"Diesel Hydraulique Services S.a.",
    "wof:placetype":"venue"
},
  "geometry": {"coordinates":[6.21416,49.226429],"type":"Point"}
}