{
  "type": "Feature",
  "properties": {
    "iso:country":"FR",
    "sg:address":"253 boulevard P\u00e9reire 75017 Paris",
    "sg:classifiers":[
        {
            "category":"Military Area",
            "subcategory":"Army Base",
            "type":"Public Place"
        }
    ],
    "sg:phone":"+33 1 44 09 72 14",
    "sg:province":"Ile de France",
    "sg:tags":[
        "software",
        "program",
        "standard",
        "add-on"
    ],
    "wof:name":"3 V Finance Sa",
    "wof:placetype":"venue"
},
  "geometry": {"coordinates":[2.286272,48.878738],"type":"Point"}
}