{
  "type": "Feature",
  "properties": {
    "iso:country":"FR",
    "sg:address":"Pechuc 33690 LAVAZAN",
    "sg:city":"Lavazan",
    "sg:classifiers":[
        {
            "category":"Manufacturing",
            "subcategory":"Wood Products",
            "type":"Manufacturing & Wholesale Goods"
        }
    ],
    "sg:phone":"+33 5 56 25 53 05",
    "sg:postcode":"33690",
    "sg:province":"Aquitaine",
    "sg:tags":[
        "pallet",
        "made"
    ],
    "wof:name":"Mourlan Sa",
    "wof:placetype":"venue"
},
  "geometry": {"coordinates":[-0.061899,44.377605],"type":"Point"}
}