{
  "type": "Feature",
  "properties": {
    "addr:full":"50 Ave. des Champs-Elys\u00e9es; Paris; 75008 Ile de France",
    "addr:postcode":"75008 ile",
    "addr:street":"50 Ave. Des Champs-Elyse\u0301Es",
    "iso:country":"FR",
    "sg:address":"50 Ave. des Champs-Elys\u00e9es; Paris; 75008",
    "sg:classifiers":[
        {
            "category":"Industrial Area",
            "type":"Public Place"
        }
    ],
    "sg:phone":"+33 1 53 77 65 10",
    "sg:province":"Ile de France",
    "sg:tags":[
        "large",
        "private"
    ],
    "wof:name":"Paris Orl\u00e9ans Sa",
    "wof:placetype":"venue"
},
  "geometry": {"coordinates":[2.306555,48.870205],"type":"Point"}
}