{
  "type": "Feature",
  "properties": {
    "addr:full":"5, Rue Ing\u00e9nieur Verri\u00e8re, 56100 Lorient Lorient Bretagne 56100",
    "addr:housenumber":"5",
    "addr:postcode":"56100;56100",
    "addr:street":"Rue Inge\u0301Nieur Verrie\u0300Re",
    "iso:country":"FR",
    "sg:address":"5, Rue Ing\u00e9nieur Verri\u00e8re, 56100 Lorient",
    "sg:city":"Lorient",
    "sg:orig_category":"Unclassifiable Establishments",
    "sg:phone":"+33 2 97 37 07 67",
    "sg:postcode":"56100",
    "sg:province":"Bretagne",
    "wof:name":"Armor M\u00e9canique S.a.r.l.",
    "wof:placetype":"venue"
},
  "geometry": {"coordinates":[-3.368506,47.734676],"type":"Point"}
}