{
  "type": "Feature",
  "properties": {
    "addr:full":"Rue Madame de la Borde Chambretaud Pays de Loire 85500",
    "addr:postcode":"85500",
    "addr:street":"Rue Madame De La Borde",
    "iso:country":"FR",
    "sg:address":"Rue Madame de la Borde",
    "sg:city":"Chambretaud",
    "sg:orig_category":"Unclassifiable Establishments",
    "sg:phone":"+33 2 51 61 50 50",
    "sg:postcode":"85500",
    "sg:province":"Pays de Loire",
    "wof:name":"Lerin S.a.",
    "wof:placetype":"venue"
},
  "geometry": {"coordinates":[-0.957584,46.923546],"type":"Point"}
}