{
  "type": "Feature",
  "properties": {
    "addr:full":"ZA Chassal Franche Comt\u00e9 39360",
    "addr:postcode":"39360",
    "addr:street":"Za Chassal Franche Comte\u0301",
    "iso:country":"FR",
    "sg:address":"ZA",
    "sg:city":"Chassal",
    "sg:orig_category":"Unclassifiable Establishments",
    "sg:phone":"+33 3 84 42 43 76",
    "sg:postcode":"39360",
    "sg:province":"Franche Comt\u00e9",
    "wof:name":"Lahu Michel S.a.",
    "wof:placetype":"venue"
},
  "geometry": {"coordinates":[5.737995,46.29892],"type":"Point"}
}