{
  "type": "Feature",
  "properties": {
    "iso:country":"FR",
    "sg:address":"B.P. 6, 59229 Teteghem^^Rte du Chapeau Rouge, 59229 Teteghem",
    "sg:orig_category":"Non-Classified Establishments",
    "sg:phone":"+33 3 28 26 90 00",
    "sg:province":"Nord Pas-de-Calais",
    "wof:name":"Marquis Transports S.a.r.l.",
    "wof:placetype":"venue"
},
  "geometry": {"coordinates":[2.441,51.01672],"type":"Point"}
}