{
  "type": "Feature",
  "properties": {
    "iso:country":"FR",
    "sg:address":"Rn 4 77540 Rozay En Brie",
    "sg:classifiers":[
        {
            "category":"Building & Trades",
            "subcategory":"Construction",
            "type":"Services"
        }
    ],
    "sg:phone":"+33 1 64 42 74 74",
    "sg:postcode":"77540",
    "sg:province":"Ile de France",
    "sg:tags":[
        "eng",
        "-",
        "equipment",
        "machinery",
        "mechanical",
        "agriculture"
    ],
    "wof:name":"Etablissements Payen Et Cie Sa",
    "wof:placetype":"venue"
},
  "geometry": {"coordinates":[2.951665,48.737099],"type":"Point"}
}