{
  "type": "Feature",
  "properties": {
    "iso:country":"FR",
    "sg:address":"212 Rue La Tredonniere 01400 Chatillon Sur Chalaronne",
    "sg:classifiers":[
        {
            "category":"Wholesale",
            "subcategory":"Meat",
            "type":"Manufacturing & Wholesale Goods"
        }
    ],
    "sg:phone":"+33 4 74 55 04 83",
    "sg:postcode":"01400",
    "sg:province":"Rhone-Alpes",
    "sg:tags":[
        "food",
        "cooked",
        "product",
        "related"
    ],
    "wof:name":"Sa Deplatiere",
    "wof:placetype":"venue"
},
  "geometry": {"coordinates":[4.94955,46.120461],"type":"Point"}
}