{
  "type": "Feature",
  "properties": {
    "addr:full":"Route De Bonnevent 70150 Etuz Franche Comt\u00e9 70150",
    "addr:postcode":"70150;70150",
    "addr:street":"Route De Bonnevent;Franche Comte\u0301",
    "iso:country":"FR",
    "sg:address":"Route De Bonnevent 70150 Etuz",
    "sg:classifiers":[
        {
            "category":"Shopping",
            "subcategory":"Bicycles & Sporting Goods",
            "type":"Retail Goods"
        }
    ],
    "sg:phone":"+33 3 81 57 60 22",
    "sg:postcode":"70150",
    "sg:province":"Franche Comt\u00e9",
    "sg:tags":[
        "product",
        "sport",
        "miscellaneous"
    ],
    "wof:name":"Ellipse",
    "wof:placetype":"venue"
},
  "geometry": {"coordinates":[5.77014,47.290215],"type":"Point"}
}