{
  "type": "Feature",
  "properties": {
    "addr:full":"11 Rue Du Lazaret 64600 Anglet Anglet Aquitaine 64600",
    "addr:housenumber":"11",
    "addr:postcode":"64600;64600",
    "addr:street":"Rue Du Lazaret",
    "iso:country":"FR",
    "sg:address":"11 Rue Du Lazaret 64600 Anglet",
    "sg:city":"Anglet",
    "sg:classifiers":[
        {
            "category":"Farming",
            "subcategory":"Livestock Farm",
            "type":"Manufacturing & Wholesale Goods"
        }
    ],
    "sg:phone":"+33 5 59 52 09 62",
    "sg:postcode":"64600",
    "sg:province":"Aquitaine",
    "sg:tags":[
        "breeding",
        "agriculture",
        "animal"
    ],
    "wof:name":"Ferme Marine De L'adour",
    "wof:placetype":"venue"
},
  "geometry": {"coordinates":[-1.500619,43.523289],"type":"Point"}
}