{
  "type": "Feature",
  "properties": {
    "addr:full":"B.P. 126, 26001 Valence C\u00e9dex^^9, Rue Edouard Branly, 26000 Valence Rhone-Alpes",
    "addr:housenumber":"b.p. 126",
    "addr:postcode":"26001;26000",
    "addr:street":"Rue Edouard Branly",
    "iso:country":"FR",
    "sg:address":"B.P. 126, 26001 Valence C\u00e9dex^^9, Rue Edouard Branly, 26000 Valence",
    "sg:orig_category":"Non-Classified Establishments",
    "sg:phone":"+33 4 75 44 80 00",
    "sg:province":"Rhone-Alpes",
    "wof:name":"Scapa Tapes",
    "wof:placetype":"venue"
},
  "geometry": {"coordinates":[4.889246,44.930458],"type":"Point"}
}