{
  "type": "Feature",
  "properties": {
    "addr:full":"14, Rue des Jeuneurs, 75002 Paris Ile de France",
    "addr:housenumber":"14",
    "addr:postcode":"75002",
    "addr:street":"Rue Des Jeuneurs",
    "iso:country":"FR",
    "sg:address":"14, Rue des Jeuneurs, 75002 Paris",
    "sg:orig_category":"Non-Classified Establishments",
    "sg:phone":"+33 1 45 08 49 44",
    "sg:province":"Ile de France",
    "wof:name":"Fettatex S.a.r.l.",
    "wof:placetype":"venue"
},
  "geometry": {"coordinates":[2.346509,48.869186],"type":"Point"}
}