{
  "type": "Feature",
  "properties": {
    "iso:country":"FR",
    "sg:address":"10 Rue Chasseurs 74100 Ville La Grand",
    "sg:classifiers":[
        {
            "category":"Banks & Credit Unions",
            "subcategory":"Investment Brokerage",
            "type":"Services"
        }
    ],
    "sg:phone":"+33 4 50 84 20 84",
    "sg:postcode":"74100",
    "sg:province":"Rhone-Alpes",
    "sg:tags":[
        "-",
        "transport",
        "related"
    ],
    "wof:name":"Messageries Annemassiennes Sa",
    "wof:placetype":"venue"
},
  "geometry": {"coordinates":[6.282348,46.207542],"type":"Point"}
}