{
  "type": "Feature",
  "properties": {
    "addr:full":"25390 Guyans Vennes Franche Comt\u00e9",
    "addr:postcode":"25390",
    "addr:street":"Franche Comte\u0301",
    "iso:country":"FR",
    "sg:address":"25390 Guyans Vennes",
    "sg:orig_category":"Non-Classified Establishments",
    "sg:phone":"+33 3 81 43 51 98",
    "sg:province":"Franche Comt\u00e9",
    "wof:name":"Tattu Et Fils S.a.r.l.",
    "wof:placetype":"venue"
},
  "geometry": {"coordinates":[6.571465,47.155029],"type":"Point"}
}