{
  "type": "Feature",
  "properties": {
    "addr:full":"2-10 R Charles Edouard Jeanneret Aries Technoparc 78300 Poissy Ile de France 78300",
    "addr:housenumber":"2-10",
    "addr:postcode":"78300;ile;78300",
    "addr:street":"R Charles Edouard Jeanneret Aries Technoparc;France",
    "iso:country":"FR",
    "sg:address":"2-10 R Charles Edouard Jeanneret Aries Technoparc 78300 Poissy",
    "sg:classifiers":[
        {
            "category":"Banks & Credit Unions",
            "subcategory":"Financial Services",
            "type":"Services"
        }
    ],
    "sg:phone":"+33 1 39 22 70 00",
    "sg:postcode":"78300",
    "sg:province":"Ile de France",
    "sg:tags":[
        "banking",
        "insurance",
        "institution",
        "finance"
    ],
    "wof:name":"Aries Meca",
    "wof:placetype":"venue"
},
  "geometry": {"coordinates":[2.04256,48.927971],"type":"Point"}
}