{
  "type": "Feature",
  "properties": {
    "addr:full":"33126 Fronsac Fronsac Aquitaine 33126",
    "addr:postcode":"33126;33126",
    "iso:country":"FR",
    "sg:address":"33126 Fronsac",
    "sg:city":"Fronsac",
    "sg:orig_category":"Unclassifiable Establishments",
    "sg:phone":"+33 5 57 84 32 09",
    "sg:postcode":"33126",
    "sg:province":"Aquitaine",
    "wof:name":"Ch\u00e2teau Des Trois Croix S.c.e.a.",
    "wof:placetype":"venue"
},
  "geometry": {"coordinates":[-0.272819,44.924126],"type":"Point"}
}