{
  "type": "Feature",
  "properties": {
    "iso:country":"FR",
    "sg:address":"43 rue Jean Jaur\u00e8s 92300 Levallois Perret",
    "sg:orig_category":"Anticorrosives, Non-Toxic",
    "sg:phone":"+33 1 41 40 00 88",
    "sg:postcode":"92300",
    "sg:province":"Ile de France",
    "wof:name":"Denso France S.a.r.l.",
    "wof:placetype":"venue"
},
  "geometry": {"coordinates":[2.2926,48.891506],"type":"Point"}
}