{
  "type": "Feature",
  "properties": {
    "iso:country":"FR",
    "sg:address":"Lapra 42330 St Bonnet Les Oules",
    "sg:classifiers":[
        {
            "category":"Autos & Motor Vehicles",
            "subcategory":"Automobile Sales",
            "type":"Retail Goods"
        }
    ],
    "sg:phone":"+33 4 77 94 98 98",
    "sg:postcode":"42330",
    "sg:province":"Rhone-Alpes",
    "sg:tags":[
        "equipment",
        "industrial",
        "transport"
    ],
    "wof:name":"Frecon Sarl",
    "wof:placetype":"venue"
},
  "geometry": {"coordinates":[4.322315,45.540791],"type":"Point"}
}