{
  "type": "Feature",
  "properties": {
    "iso:country":"FR",
    "sg:address":"Rue Moulin de Pruniers",
    "sg:city":"Jouet sur l'Aubois",
    "sg:orig_category":"Unclassifiable Establishments",
    "sg:phone":"+33 2 48 77 72 20",
    "sg:postcode":"18320",
    "sg:province":"Centre",
    "wof:name":"Beno\u00eet S.a.",
    "wof:placetype":"venue"
},
  "geometry": {"coordinates":[-75.217392,41.052601],"type":"Point"}
}