{
  "type": "Feature",
  "properties": {
    "addr:full":"12, Rue du Palais, 41000 Blois Blois Centre 41000",
    "addr:housenumber":"12",
    "addr:postcode":"41000;41000",
    "addr:street":"Rue Du Palais",
    "iso:country":"FR",
    "sg:address":"12, Rue du Palais, 41000 Blois",
    "sg:city":"Blois",
    "sg:orig_category":"Non-Classified Establishments",
    "sg:phone":"+33 2 54 74 07 42",
    "sg:postcode":"41000",
    "sg:province":"Centre",
    "wof:name":"Atelier Bernard Nau",
    "wof:placetype":"venue"
},
  "geometry": {"coordinates":[1.333558,47.588448],"type":"Point"}
}