{
  "type": "Feature",
  "properties": {
    "addr:full":"29, Rue Bernardin, 36000 Ch\u00e2teauroux Ch\u00e2teauroux Centre 36000",
    "addr:housenumber":"29",
    "addr:postcode":"36000;36000",
    "addr:street":"Rue Bernardin;Cha\u0302Teauroux",
    "iso:country":"FR",
    "sg:address":"29, Rue Bernardin, 36000 Ch\u00e2teauroux",
    "sg:city":"Ch\u00e2teauroux",
    "sg:orig_category":"Non-Classified Establishments",
    "sg:phone":"+33 2 54 53 44 43",
    "sg:postcode":"36000",
    "sg:province":"Centre",
    "wof:name":"Intermaide",
    "wof:placetype":"venue"
},
  "geometry": {"coordinates":[1.700723,46.8074],"type":"Point"}
}