{
  "type": "Feature",
  "properties": {
    "iso:country":"FR",
    "sg:address":"25 Rue Jean Lebas 59252 Marquette En Ostrevant",
    "sg:classifiers":[
        {
            "category":"Wholesale",
            "subcategory":"Machinery & Supplies",
            "type":"Manufacturing & Wholesale Goods"
        }
    ],
    "sg:phone":"+33 3 27 35 71 55",
    "sg:postcode":"59252",
    "sg:province":"Nord Pas-de-Calais",
    "sg:tags":[
        "food",
        "processing",
        "-",
        "machine",
        "equipment",
        "engineering",
        "mechanical"
    ],
    "wof:name":"Gobert Et Cie",
    "wof:placetype":"venue"
},
  "geometry": {"coordinates":[3.266486,50.288391],"type":"Point"}
}