{
  "type": "Feature",
  "properties": {
    "addr:full":"2 Rue Nationale 72000 Le Mans Pays de Loire 72000",
    "addr:housenumber":"2",
    "addr:postcode":"72000;72000",
    "addr:street":"Rue Nationale",
    "iso:country":"FR",
    "sg:address":"2 Rue Nationale 72000 Le Mans",
    "sg:classifiers":[
        {
            "category":"Shopping",
            "subcategory":"Crafts & Fabrics",
            "type":"Retail Goods"
        }
    ],
    "sg:phone":"+33 2 43 23 71 52",
    "sg:postcode":"72000",
    "sg:province":"Pays de Loire",
    "sg:tags":[
        "textile",
        "linen",
        "clothing"
    ],
    "wof:name":"Neuftex Toto",
    "wof:placetype":"venue"
},
  "geometry": {"coordinates":[0.198046,48.00082],"type":"Point"}
}