{
  "type": "Feature",
  "properties": {
    "addr:full":"R Ren\u00e9 Cassin Z.I. 45308 Pithiviers Picardie",
    "addr:postcode":"45308",
    "addr:street":"Z.I.",
    "iso:country":"FR",
    "sg:address":"R Ren\u00e9 Cassin Z.I. 45308 Pithiviers",
    "sg:classifiers":[
        {
            "category":"Professional",
            "subcategory":"Engineering",
            "type":"Services"
        }
    ],
    "sg:phone":"+33 2 38 30 05 72",
    "sg:province":"Picardie",
    "sg:tags":[
        "machine",
        "-",
        "environment",
        "equipment",
        "machinery",
        "mechanical"
    ],
    "wof:name":"Sefi",
    "wof:placetype":"venue"
},
  "geometry": {"coordinates":[2.253205,48.172215],"type":"Point"}
}