{
  "type": "Feature",
  "properties": {
    "addr:full":"Rue Th\u00e9odore Botrel Pleyben Bretagne 29190",
    "addr:postcode":"29190",
    "addr:street":"Rue The\u0301Odore Botrel Pleyben Bretagne",
    "iso:country":"FR",
    "sg:address":"Rue Th\u00e9odore Botrel",
    "sg:city":"Pleyben",
    "sg:orig_category":"Unclassifiable Establishments",
    "sg:phone":"+33 2 98 26 60 21",
    "sg:postcode":"29190",
    "sg:province":"Bretagne",
    "wof:name":"Etablissements Galettes De Pleyben",
    "wof:placetype":"venue"
},
  "geometry": {"coordinates":[-3.973284,48.226318],"type":"Point"}
}