{
  "type": "Feature",
  "properties": {
    "addr:full":"9 Grande; Lambesc Aquitaine",
    "addr:housenumber":"9",
    "addr:street":"Grande",
    "iso:country":"FR",
    "sg:address":"9",
    "sg:city":"Grande; Lambesc",
    "sg:classifiers":[
        {
            "category":"Banks & Credit Unions",
            "subcategory":"Bank",
            "type":"Services"
        }
    ],
    "sg:phone":"+33 3342929303",
    "sg:province":"Aquitaine",
    "wof:name":"Banque Chaix",
    "wof:placetype":"venue"
},
  "geometry": {"coordinates":[5.262497,43.653049],"type":"Point"}
}