{
  "type": "Feature",
  "properties": {
    "addr:full":"30, Rue de Londres, 75009 Paris Ile de France",
    "addr:housenumber":"30",
    "addr:postcode":"75009",
    "addr:street":"Rue De Londres",
    "iso:country":"FR",
    "sg:address":"30, Rue de Londres, 75009 Paris",
    "sg:orig_category":"Unclassifiable Establishments",
    "sg:phone":"+33 1 48 74 42 13",
    "sg:province":"Ile de France",
    "wof:name":"C.e.f.b. S.a. - Comptoir D'electricit\u00e9 Franco-belge",
    "wof:placetype":"venue"
},
  "geometry": {"coordinates":[2.327995,48.877655],"type":"Point"}
}