{
  "type": "Feature",
  "properties": {
    "iso:country":"FR",
    "sg:address":"58 Boulevard Gustave Roch 44200 Nantes",
    "sg:classifiers":[
        {
            "category":"Farming",
            "subcategory":"Crops",
            "type":"Manufacturing & Wholesale Goods"
        }
    ],
    "sg:phone":"+33 2 51 72 93 50",
    "sg:postcode":"44200",
    "sg:province":"Pays de Loire",
    "sg:tags":[
        "vegetable",
        "fruit",
        "agriculture",
        "livestock"
    ],
    "wof:name":"Liegeois Sa",
    "wof:placetype":"venue"
},
  "geometry": {"coordinates":[-1.555667,47.200958],"type":"Point"}
}