{
  "type": "Feature",
  "properties": {
    "addr:full":"3274, Av. Etienne Mehul, 34070 Montpellier Languedoc-Roussillon",
    "addr:housenumber":"3274",
    "addr:postcode":"34070",
    "addr:street":"Av. Etienne Mehul",
    "iso:country":"FR",
    "sg:address":"3274, Av. Etienne Mehul, 34070 Montpellier",
    "sg:orig_category":"Unclassifiable Establishments",
    "sg:phone":"+33 4 67 07 70 00",
    "sg:province":"Languedoc-Roussillon",
    "wof:name":"M\u00e9tro Libre Service De Gros S.a.r.l.",
    "wof:placetype":"venue"
},
  "geometry": {"coordinates":[3.86011,43.575619],"type":"Point"}
}