{
  "type": "Feature",
  "properties": {
    "addr:full":"27, Rue Stanislas, 54000 Nancy Lorraine",
    "addr:housenumber":"27",
    "addr:postcode":"54000",
    "addr:street":"Rue Stanislas",
    "iso:country":"FR",
    "sg:address":"27, Rue Stanislas, 54000 Nancy",
    "sg:orig_category":"Unclassifiable Establishments",
    "sg:phone":"+33 3 83 19 19 19",
    "sg:province":"Lorraine",
    "wof:name":"Burotique 54 S.a.",
    "wof:placetype":"venue"
},
  "geometry": {"coordinates":[6.180841,48.692665],"type":"Point"}
}