{
  "type": "Feature",
  "properties": {
    "iso:country":"FR",
    "sg:address":"120, Rue Jules Siegfried - Immeuble le Wall Street, 76600 Le Havre",
    "sg:orig_category":"Non-Classified Establishments",
    "sg:phone":"+33 2 35 22 10 80",
    "sg:postcode":"76600",
    "sg:province":"Haute Normandie",
    "wof:name":"Cominfo S.a.",
    "wof:placetype":"venue"
},
  "geometry": {"coordinates":[0.118361,49.492001],"type":"Point"}
}