{
  "type": "Feature",
  "properties": {
    "addr:full":"Av Louis Sammut 13500 Martigues Artigue Midi Pyr\u00e9n\u00e9es 31110",
    "addr:postcode":"13500;31110",
    "addr:street":"Av Louis Sammut",
    "iso:country":"FR",
    "sg:address":"Av Louis Sammut 13500 Martigues",
    "sg:city":"Artigue",
    "sg:classifiers":[
        {
            "category":"Sports & Exercise",
            "subcategory":"Sports Center",
            "type":"Entertainment"
        }
    ],
    "sg:phone":"+33 4 42 44 32 10",
    "sg:postcode":"31110",
    "sg:province":"Midi Pyr\u00e9n\u00e9es",
    "sg:tags":[
        "game"
    ],
    "wof:name":"Service Du Sport Mairie Martigues",
    "wof:placetype":"venue"
},
  "geometry": {"coordinates":[5.049735,43.406509],"type":"Point"}
}