{
  "type": "Feature",
  "properties": {
    "iso:country":"FR",
    "sg:address":"480 Rte De Paris 82000 Montauban",
    "sg:classifiers":[
        {
            "category":"Utilities",
            "subcategory":"Mobile Phone",
            "type":"Services"
        }
    ],
    "sg:phone":"+33 5 63 21 30 00",
    "sg:postcode":"82000",
    "sg:province":"Midi Pyr\u00e9n\u00e9es",
    "sg:tags":[
        "telecommunication",
        "audio-visual"
    ],
    "wof:name":"Bouyer Sa",
    "wof:placetype":"venue"
},
  "geometry": {"coordinates":[1.375899,44.033638],"type":"Point"}
}