{
  "type": "Feature",
  "properties": {
    "addr:full":"8 Rue Fran\u00e7ois Bonvin 75015 Paris Ile de France",
    "addr:housenumber":"8",
    "addr:postcode":"75015",
    "addr:street":"Rue Franc\u0327Ois Bonvin",
    "iso:country":"FR",
    "sg:address":"8 Rue Fran\u00e7ois Bonvin 75015 Paris",
    "sg:classifiers":[
        {
            "category":"Banks & Credit Unions",
            "subcategory":"Investment Brokerage",
            "type":"Services"
        }
    ],
    "sg:phone":"+33 1 44 49 16 30",
    "sg:province":"Ile de France",
    "sg:tags":[
        "-",
        "transport",
        "related"
    ],
    "wof:name":"La Poste",
    "wof:placetype":"venue"
},
  "geometry": {"coordinates":[2.304972,48.845657],"type":"Point"}
}