{
  "type": "Feature",
  "properties": {
    "addr:full":"B.P. 5061, 14077 Caen C\u00e9dex 5^^5, Rue de la girafe - ZI Mont Coco, 14000 Caen Caen Basse Normandie 14000",
    "addr:housenumber":"^ 5",
    "addr:postcode":"14077;14000;14000",
    "addr:street":"B.P. 5061;Rue De La Girafe Zi Mont Coco",
    "iso:country":"FR",
    "sg:address":"B.P. 5061, 14077 Caen C\u00e9dex 5^^5, Rue de la girafe - ZI Mont Coco, 14000 Caen",
    "sg:city":"Caen",
    "sg:orig_category":"Non-Classified Establishments",
    "sg:phone":"+33 2 31 46 80 00",
    "sg:postcode":"14000",
    "sg:province":"Basse Normandie",
    "wof:name":"David Miroiterie S.a.",
    "wof:placetype":"venue"
},
  "geometry": {"coordinates":[-0.36111,49.184361],"type":"Point"}
}