{
  "type": "Feature",
  "properties": {
    "iso:country":"FR",
    "sg:address":"Rue des Grands Pr\u00e9s",
    "sg:city":"Nevers",
    "sg:orig_category":"Unclassifiable Establishments",
    "sg:phone":"+33 3 86 60 78 78",
    "sg:postcode":"58000",
    "sg:province":"Bourgogne",
    "wof:name":"Gates France S.a.",
    "wof:placetype":"venue"
},
  "geometry": {"coordinates":[3.177145,46.997559],"type":"Point"}
}