{
  "type": "Feature",
  "properties": {
    "iso:country":"FR",
    "sg:address":"39130 Etival",
    "sg:orig_category":"Non-Classified Establishments",
    "sg:phone":"+33 3 84 44 87 69",
    "sg:postcode":"39130",
    "sg:province":"Franche Comt\u00e9",
    "wof:name":"Dalloz S.a.",
    "wof:placetype":"venue"
},
  "geometry": {"coordinates":[5.793331,46.504929],"type":"Point"}
}