{
  "type": "Feature",
  "properties": {
    "iso:country":"FR",
    "sg:address":"B.P. 70, 92357 Le Pessis Robinson C\u00e9dex^^RN 186 - La Boussidi\u00e8re , 92350 Le Plessis Robinson",
    "sg:orig_category":"Non-Classified Establishments",
    "sg:phone":"+33 1 46 32 33 34",
    "sg:province":"Ile de France",
    "wof:name":"Navsys S.a.r.l.",
    "wof:placetype":"venue"
},
  "geometry": {"coordinates":[2.259315,48.779976],"type":"Point"}
}