{
  "type": "Feature",
  "properties": {
    "iso:country":"FR",
    "sg:address":"181 Rue De La Vall\u00e9e 80430 St Aubin Rivi\u00e8re",
    "sg:classifiers":[
        {
            "category":"Wholesale",
            "subcategory":"Machinery & Supplies",
            "type":"Manufacturing & Wholesale Goods"
        }
    ],
    "sg:phone":"+33 3 22 25 90 62",
    "sg:postcode":"80430",
    "sg:province":"Picardie",
    "sg:tags":[
        "-",
        "machine",
        "equipment",
        "engineering",
        "animal",
        "mechanical",
        "breeding",
        "agriculture"
    ],
    "wof:name":"Etablissements Dehan Sarl",
    "wof:placetype":"venue"
},
  "geometry": {"coordinates":[1.779758,49.872379],"type":"Point"}
}