{
  "type": "Feature",
  "properties": {
    "addr:full":"24, Rue de Lisbonne, 75008 Paris Ile de France 75008",
    "addr:housenumber":"24",
    "addr:postcode":"75008;75008",
    "addr:street":"Rue De Lisbonne",
    "iso:country":"FR",
    "sg:address":"24, Rue de Lisbonne, 75008 Paris",
    "sg:orig_category":"Non-Classified Establishments",
    "sg:phone":"+33 1 53 04 36 56",
    "sg:postcode":"75008",
    "sg:province":"Ile de France",
    "wof:name":"E.f.c. S.a. - Editiions Formation Carri\u00e8res",
    "wof:placetype":"venue"
},
  "geometry": {"coordinates":[2.314384,48.877831],"type":"Point"}
}