{
  "type": "Feature",
  "properties": {
    "addr:full":"Lot Artisanal 07800 Charmes Sur Rh\u00f4ne Rhone-Alpes 07800",
    "addr:postcode":"07800;07800",
    "iso:country":"FR",
    "sg:address":"Lot Artisanal 07800 Charmes Sur Rh\u00f4ne",
    "sg:classifiers":[
        {
            "category":"Manufacturing",
            "subcategory":"Glass & Minerals",
            "type":"Manufacturing & Wholesale Goods"
        }
    ],
    "sg:phone":"+33 4 75 60 95 13",
    "sg:postcode":"07800",
    "sg:province":"Rhone-Alpes",
    "sg:tags":[
        "building",
        "material"
    ],
    "wof:name":"Ardeche Vitrage",
    "wof:placetype":"venue"
},
  "geometry": {"coordinates":[4.788699,44.833321],"type":"Point"}
}