{
  "type": "Feature",
  "properties": {
    "addr:full":"Chemin de la Croise - ZAC des C\u00e9sardes Seynod Rhone-Alpes 74600",
    "addr:postcode":"74600",
    "addr:street":"Chemin De La Croise Zac Des Ce\u0301Sardes;Rhone-Alpes",
    "iso:country":"FR",
    "sg:address":"Chemin de la Croise - ZAC des C\u00e9sardes",
    "sg:city":"Seynod",
    "sg:orig_category":"Non-Classified Establishments",
    "sg:phone":"+33 4 50 69 03 55",
    "sg:postcode":"74600",
    "sg:province":"Rhone-Alpes",
    "wof:name":"Pum Plastiques S.a.",
    "wof:placetype":"venue"
},
  "geometry": {"coordinates":[6.100926,45.888924],"type":"Point"}
}