{
  "type": "Feature",
  "properties": {
    "iso:country":"FR",
    "sg:address":"Bellevue 81400 Blaye les Mines",
    "sg:orig_category":"Non-Classified Establishments",
    "sg:phone":"+33 5 63 80 20 00",
    "sg:province":"Midi Pyr\u00e9n\u00e9es",
    "wof:name":"Jean-pierre Rigal S.a.r.l.",
    "wof:placetype":"venue"
},
  "geometry": {"coordinates":[2.15314,44.034176],"type":"Point"}
}