{
  "type": "Feature",
  "properties": {
    "addr:full":"Rue Albert Einstein 37100 Tours Tours Centre 37100",
    "addr:postcode":"37100;37100",
    "addr:street":"Rue Albert Einstein",
    "iso:country":"FR",
    "sg:address":"Rue Albert Einstein 37100 Tours",
    "sg:city":"Tours",
    "sg:classifiers":[
        {
            "category":"Government",
            "subcategory":"Department Of Motor Vehicles",
            "type":"Public Place"
        }
    ],
    "sg:phone":"+33 2 47 80 77 36",
    "sg:postcode":"37100",
    "sg:province":"Centre",
    "sg:tags":[
        "equipment",
        "industrial",
        "transport",
        "motor-cars"
    ],
    "wof:name":"Renault",
    "wof:placetype":"venue"
},
  "geometry": {"coordinates":[0.702741,47.425701],"type":"Point"}
}