{
  "type": "Feature",
  "properties": {
    "iso:country":"FR",
    "sg:address":"Rte Ombr\u00e9e 18200 Orval",
    "sg:city":"Orval",
    "sg:classifiers":[
        {
            "category":"Shopping",
            "type":"Retail Goods"
        }
    ],
    "sg:phone":"+33 2 48 96 07 39",
    "sg:postcode":"18200",
    "sg:province":"Centre",
    "sg:tags":[
        "metallurgy",
        "finished",
        "-",
        "metalworking",
        "metallic"
    ],
    "wof:name":"Ateliers Dorval Sa",
    "wof:placetype":"venue"
},
  "geometry": {"coordinates":[2.47452,46.730919],"type":"Point"}
}