{
  "type": "Feature",
  "properties": {
    "iso:country":"FR",
    "sg:address":"B.P. 109, 45803 Saint Jean de Braye C\u00e9dex^^29, Rue Bernard Palissy - Parc Archim\u00e9de, 45800 Saint Jea",
    "sg:city":"Combleux",
    "sg:orig_category":"Non-Classified Establishments",
    "sg:phone":"+33 2 38 61 91 00",
    "sg:postcode":"45800",
    "sg:province":"Centre",
    "wof:name":"Kongskilde France S.a.",
    "wof:placetype":"venue"
},
  "geometry": {"coordinates":[-115.32508900000001,35.779205],"type":"Point"}
}