{
  "type": "Feature",
  "properties": {
    "addr:full":"B.P. 258 Marseille C\u00e9dex 08^^13006 Marseille Provence-Alpes-C\u00f4te d'Azur 13269",
    "addr:housenumber":"b.p. 258;08 ^ ^",
    "addr:postcode":"13006;13269",
    "addr:street":"Ce\u0301Dex",
    "iso:country":"FR",
    "sg:address":"B.P. 258",
    "sg:city":"Marseille C\u00e9dex 08^^13006 Marseille",
    "sg:orig_category":"Non-Classified Establishments",
    "sg:phone":"+33 4 91 29 57 00",
    "sg:postcode":"13269",
    "sg:province":"Provence-Alpes-C\u00f4te d'Azur",
    "wof:name":"Soci\u00e9t\u00e9 G\u00e9n\u00e9rale",
    "wof:placetype":"venue"
},
  "geometry": {"coordinates":[5.38324,43.290806],"type":"Point"}
}