{
  "type": "Feature",
  "properties": {
    "iso:country":"FR",
    "sg:address":"Rte de Faulquemont - Zone Industrielle",
    "sg:city":"Long\u00e9ville l\u00e8s Saint Avold",
    "sg:orig_category":"Non-Classified Establishments",
    "sg:phone":"+33 3 87 29 06 07",
    "sg:postcode":"57740",
    "sg:province":"Lorraine",
    "wof:name":"Xylotech Menuiserie Eb\u00e9nisterie S.a.r.l.",
    "wof:placetype":"venue"
},
  "geometry": {"coordinates":[6.64526,49.117481],"type":"Point"}
}