{
  "type": "Feature",
  "properties": {
    "iso:country":"FR",
    "sg:address":"Rue de la Voyette",
    "sg:city":"Lesquin",
    "sg:orig_category":"Unclassifiable Establishments",
    "sg:phone":"+33 3 20 62 55 00",
    "sg:postcode":"59812",
    "sg:province":"Nord Pas-de-Calais",
    "wof:name":"D.a.p.a.c. S.a. - Distributeurs Associ\u00e9s De Produits Alimentaires Charcuterie",
    "wof:placetype":"venue"
},
  "geometry": {"coordinates":[3.113615,50.592983],"type":"Point"}
}