{
  "type": "Feature",
  "properties": {
    "addr:full":"13 rue de Hurtigheim 67117 QUATZENHEIM Quatzenheim Alsace 67117",
    "addr:housenumber":"13",
    "addr:postcode":"67117;67117",
    "addr:street":"Rue De Hurtigheim",
    "iso:country":"FR",
    "sg:address":"13 rue de Hurtigheim 67117 QUATZENHEIM",
    "sg:city":"Quatzenheim",
    "sg:classifiers":[
        {
            "category":"Bus Stop",
            "subcategory":"None",
            "type":"Transportation"
        }
    ],
    "sg:phone":"+33 3 88 69 00 53",
    "sg:postcode":"67117",
    "sg:province":"Alsace",
    "sg:tags":[
        "period",
        "furniture"
    ],
    "wof:name":"Ste Bruckmann S.a.r.l.",
    "wof:placetype":"venue"
},
  "geometry": {"coordinates":[7.5708,48.624924],"type":"Point"}
}