{
  "type": "Feature",
  "properties": {
    "addr:full":"6 Rue Des Gamelines 78200 Buchelay Ile de France 78200",
    "addr:housenumber":"6",
    "addr:postcode":"78200;78200",
    "addr:street":"Rue Des Gamelines;Ile De France",
    "iso:country":"FR",
    "sg:address":"6 Rue Des Gamelines 78200 Buchelay",
    "sg:classifiers":[
        {
            "category":"Manufacturing",
            "subcategory":"Chemicals & Compounds",
            "type":"Manufacturing & Wholesale Goods"
        }
    ],
    "sg:phone":"+33 1 30 33 57 22",
    "sg:postcode":"78200",
    "sg:province":"Ile de France",
    "sg:tags":[
        "pharmaceutical",
        "chemistry",
        "-",
        "by-product"
    ],
    "wof:name":"Paille",
    "wof:placetype":"venue"
},
  "geometry": {"coordinates":[1.678168,48.991386],"type":"Point"}
}