{
  "type": "Feature",
  "properties": {
    "addr:full":"9, Rue Eug\u00e8ne Sue, 93360 Neuilly Plaisance Ile de France",
    "addr:housenumber":"9",
    "addr:postcode":"93360",
    "addr:street":"Rue Euge\u0300Ne Sue;Ile De France",
    "iso:country":"FR",
    "sg:address":"9, Rue Eug\u00e8ne Sue, 93360 Neuilly Plaisance",
    "sg:orig_category":"Non-Classified Establishments",
    "sg:phone":"+33 1 43 00 20 55",
    "sg:province":"Ile de France",
    "wof:name":"Expo 4 S.a.r.l.",
    "wof:placetype":"venue"
},
  "geometry": {"coordinates":[2.49924,48.863071],"type":"Point"}
}