{
  "type": "Feature",
  "properties": {
    "addr:full":"26, Rue Gay-Lussac - Zone Industrielle, 59147 Gondecourt Nord Pas-de-Calais",
    "addr:housenumber":"26",
    "addr:postcode":"59147",
    "addr:street":"Rue Gay-Lussac Zone Industrielle",
    "iso:country":"FR",
    "sg:address":"26, Rue Gay-Lussac - Zone Industrielle, 59147 Gondecourt",
    "sg:orig_category":"Unclassifiable Establishments",
    "sg:phone":"+33 3 20 62 91 91",
    "sg:province":"Nord Pas-de-Calais",
    "wof:name":"S.h.l. S.a. - Soci\u00e9t\u00e9 Des Huiles Lemahieu",
    "wof:placetype":"venue"
},
  "geometry": {"coordinates":[2.986804,50.548714],"type":"Point"}
}