{
  "type": "Feature",
  "properties": {
    "iso:country":"FR",
    "sg:address":"1, Rue Bayard, 59000 Lille",
    "sg:orig_category":"Unclassifiable Establishments",
    "sg:phone":"+33 3 20 30 42 60",
    "sg:province":"Nord Pas-de-Calais",
    "wof:name":"Corpus Conseils S.a.r.l.",
    "wof:placetype":"venue"
},
  "geometry": {"coordinates":[3.05416,50.618351],"type":"Point"}
}