{
  "type": "Feature",
  "properties": {
    "addr:full":"B.P. 7, 59780 Baisieux^^55, Rue des Ecoles, 59780 Willems Nord Pas-de-Calais",
    "addr:housenumber":"7",
    "addr:postcode":"59780;59780",
    "addr:street":"B.P.;Rue Des Ecoles",
    "iso:country":"FR",
    "sg:address":"B.P. 7, 59780 Baisieux^^55, Rue des Ecoles, 59780 Willems",
    "sg:orig_category":"Non-Classified Establishments",
    "sg:phone":"+33 3 20 79 38 55",
    "sg:province":"Nord Pas-de-Calais",
    "wof:name":"Heuls Et Fiquoy Etiquettes S.a.r.l.",
    "wof:placetype":"venue"
},
  "geometry": {"coordinates":[3.240535,50.614738],"type":"Point"}
}