{
  "type": "Feature",
  "properties": {
    "iso:country":"FR",
    "sg:address":"37/39, Rue Pleyel, 93200 Saint Denis",
    "sg:orig_category":"Unclassifiable Establishments",
    "sg:phone":"+33 1 48 09 10 00",
    "sg:province":"Ile de France",
    "wof:name":"Alpa S.a.",
    "wof:placetype":"venue"
},
  "geometry": {"coordinates":[2.343584,48.920967],"type":"Point"}
}