{
  "type": "Feature",
  "properties": {
    "addr:full":"250, Av. Pasteur, 49000 Angers Pays de Loire",
    "addr:housenumber":"250",
    "addr:postcode":"49000",
    "addr:street":"Av. Pasteur",
    "iso:country":"FR",
    "sg:address":"250, Av. Pasteur, 49000 Angers",
    "sg:orig_category":"Unclassifiable Establishments",
    "sg:phone":"+33 2 41 27 26 20",
    "sg:province":"Pays de Loire",
    "wof:name":"O.g.i. - C.s.o. S.a.",
    "wof:placetype":"venue"
},
  "geometry": {"coordinates":[-0.525192,47.480354],"type":"Point"}
}