{
  "type": "Feature",
  "properties": {
    "iso:country":"FR",
    "sg:address":"38, Rue des Montagnes Novies, 56630 Langonnet",
    "sg:city":"Langonnet",
    "sg:orig_category":"Unclassifiable Establishments",
    "sg:phone":"+33 2 97 23 95 22",
    "sg:postcode":"56630",
    "sg:province":"Bretagne",
    "wof:name":"Cr\u00eaperie Lebreton S.a.",
    "wof:placetype":"venue"
},
  "geometry": {"coordinates":[-3.497776,48.107761],"type":"Point"}
}