{
  "type": "Feature",
  "properties": {
    "iso:country":"FR",
    "sg:address":"29, La Cannebi\u00e8re, 13001 Marseille",
    "sg:orig_category":"Non-Classified Establishments",
    "sg:phone":"+33 4 95 09 37 10",
    "sg:province":"Poitou-Charentes",
    "wof:name":"Emergences Formation",
    "wof:placetype":"venue"
},
  "geometry": {"coordinates":[5.376914,43.296326],"type":"Point"}
}