{
  "type": "Feature",
  "properties": {
    "addr:full":"9, Bd S\u00e9bastopol, 47400 Tonneins Tonneins Aquitaine 47400",
    "addr:housenumber":"9",
    "addr:postcode":"47400;47400",
    "addr:street":"Bd Se\u0301Bastopol",
    "iso:country":"FR",
    "sg:address":"9, Bd S\u00e9bastopol, 47400 Tonneins",
    "sg:city":"Tonneins",
    "sg:orig_category":"Non-Classified Establishments",
    "sg:phone":"+33 5 53 79 14 37",
    "sg:postcode":"47400",
    "sg:province":"Aquitaine",
    "wof:name":"Bigmat Lab\u00e9 S.a.r.l.",
    "wof:placetype":"venue"
},
  "geometry": {"coordinates":[0.31108,44.39529],"type":"Point"}
}