{
  "type": "Feature",
  "properties": {
    "iso:country":"FR",
    "sg:address":"Zi De Noyon 205 Rue De L'Europe 60403 Noyon Cedex",
    "sg:classifiers":[
        {
            "category":"Manufacturing",
            "subcategory":"Motor Vehicles & Parts",
            "type":"Manufacturing & Wholesale Goods"
        }
    ],
    "sg:phone":"+33 3 44 09 85 00",
    "sg:province":"Haute Normandie",
    "sg:tags":[
        "engine",
        "machine",
        "engineering",
        "-",
        "mechanical"
    ],
    "wof:name":"Federal Mogul Friction Products Sa",
    "wof:placetype":"venue"
},
  "geometry": {"coordinates":[3.020969,49.574524],"type":"Point"}
}