{
  "type": "Feature",
  "properties": {
    "iso:country":"FR",
    "sg:address":"22",
    "sg:city":"Tr\u00e9moille 75008 PARIS",
    "sg:classifiers":[
        {
            "category":"Banks & Credit Unions",
            "subcategory":"Financial Services",
            "type":"Services"
        }
    ],
    "sg:phone":"+33 1 56 62 43 00",
    "sg:postcode":"75008",
    "sg:province":"Ile de France",
    "sg:tags":[
        "banking",
        "consulting",
        "finance",
        "insurance"
    ],
    "wof:name":"Invesco France (sa)",
    "wof:placetype":"venue"
},
  "geometry": {"coordinates":[2.303558,48.867279],"type":"Point"}
}