{
  "type": "Feature",
  "properties": {
    "addr:full":"21, Rue de Pont des Halles, 94536 Rungis C\u00e9dex Bourgogne",
    "addr:housenumber":"21",
    "addr:postcode":"94536",
    "addr:street":"Rue De Pont Des Halles",
    "iso:country":"FR",
    "sg:address":"21, Rue de Pont des Halles, 94536 Rungis C\u00e9dex",
    "sg:orig_category":"Non-Classified Establishments",
    "sg:phone":"+33 1 49 61 48 00",
    "sg:province":"Bourgogne",
    "wof:name":"Botte- Btp S.n.c.",
    "wof:placetype":"venue"
},
  "geometry": {"coordinates":[2.35325,48.751419],"type":"Point"}
}