{
  "type": "Feature",
  "properties": {
    "iso:country":"FR",
    "sg:address":"Les Sentes Zone D Activites 35470 Bain De Bretagne",
    "sg:city":"Bain-de-Bretagne",
    "sg:classifiers":[
        {
            "category":"Wholesale",
            "subcategory":"Meat",
            "type":"Manufacturing & Wholesale Goods"
        }
    ],
    "sg:phone":"+33 2 99 43 73 02",
    "sg:postcode":"35470",
    "sg:province":"Bretagne",
    "sg:tags":[
        "food",
        "cooked",
        "product",
        "related"
    ],
    "wof:name":"Charcuterie Orain",
    "wof:placetype":"venue"
},
  "geometry": {"coordinates":[-1.741624,47.803226],"type":"Point"}
}