{
  "type": "Feature",
  "properties": {
    "addr:full":"236, Av. Albert Thomas, 81000 Albi Midi Pyr\u00e9n\u00e9es",
    "addr:housenumber":"236",
    "addr:postcode":"81000",
    "addr:street":"Av. Albert Thomas",
    "iso:country":"FR",
    "sg:address":"236, Av. Albert Thomas, 81000 Albi",
    "sg:orig_category":"Unclassifiable Establishments",
    "sg:phone":"+33 5 63 77 80 77",
    "sg:province":"Midi Pyr\u00e9n\u00e9es",
    "wof:name":"Rexel Comptoir Electrique S.a.",
    "wof:placetype":"venue"
},
  "geometry": {"coordinates":[2.15188,43.946499],"type":"Point"}
}