{
  "type": "Feature",
  "properties": {
    "addr:full":"B.P. 138, 67404 Illkirch C\u00e9dex^^69, Rte du Rhin, 67400 Illkirch Graffenstaden Geispolsheim Alsace 67400",
    "addr:housenumber":"b.p. 138",
    "addr:postcode":"67404;67400;67400",
    "addr:street":"Rte Du Rhin",
    "iso:country":"FR",
    "sg:address":"B.P. 138, 67404 Illkirch C\u00e9dex^^69, Rte du Rhin, 67400 Illkirch Graffenstaden",
    "sg:city":"Geispolsheim",
    "sg:orig_category":"Non-Classified Establishments",
    "sg:phone":"+33 3 88 66 34 23",
    "sg:postcode":"67400",
    "sg:province":"Alsace",
    "wof:name":"Syndrog S.c.i.a.r.l.",
    "wof:placetype":"venue"
},
  "geometry": {"coordinates":[7.711838,48.528809],"type":"Point"}
}