{
  "type": "Feature",
  "properties": {
    "addr:full":"B.P. 6, 59211 Santes^^185, Rue Marx Dormoy, 59211 Santes Nord Pas-de-Calais",
    "addr:housenumber":"6",
    "addr:postcode":"59211;59211",
    "addr:street":"B.P.;Rue Marx Dormoy",
    "iso:country":"FR",
    "sg:address":"B.P. 6, 59211 Santes^^185, Rue Marx Dormoy, 59211 Santes",
    "sg:orig_category":"Non-Classified Establishments",
    "sg:phone":"+33 3 20 17 22 22",
    "sg:province":"Nord Pas-de-Calais",
    "wof:name":"Pacquet Paul Transports S.a.",
    "wof:placetype":"venue"
},
  "geometry": {"coordinates":[2.963288,50.590366],"type":"Point"}
}