{
  "type": "Feature",
  "properties": {
    "addr:full":"Quai D Estienne D Orves 29730 GUILVINEC Guilvinec Bretagne 29730",
    "addr:postcode":"29730;29730",
    "addr:street":"Quai D Estienne D Orves",
    "iso:country":"FR",
    "sg:address":"Quai D Estienne D Orves 29730 GUILVINEC",
    "sg:city":"Guilvinec",
    "sg:orig_category":"Armaments, Armours",
    "sg:phone":"+33 2 98 58 13 80",
    "sg:postcode":"29730",
    "sg:province":"Bretagne",
    "wof:name":"Armement Bigouden S.a.",
    "wof:placetype":"venue"
},
  "geometry": {"coordinates":[-4.283333,47.793884],"type":"Point"}
}