{
  "type": "Feature",
  "properties": {
    "addr:full":"47, Rue Principale, 33460 Lamarque Lamarque Aquitaine 33460",
    "addr:housenumber":"47",
    "addr:postcode":"33460;33460",
    "addr:street":"Rue Principale",
    "iso:country":"FR",
    "sg:address":"47, Rue Principale, 33460 Lamarque",
    "sg:city":"Lamarque",
    "sg:orig_category":"Non-Classified Establishments",
    "sg:phone":"+33 5 56 58 91 74",
    "sg:postcode":"33460",
    "sg:province":"Aquitaine",
    "wof:name":"Boissenot Jacques",
    "wof:placetype":"venue"
},
  "geometry": {"coordinates":[-0.716754,45.096062],"type":"Point"}
}