{
  "type": "Feature",
  "properties": {
    "addr:full":"4, Rue Jules Vedrines, 31400 Toulouse Midi Pyr\u00e9n\u00e9es",
    "addr:housenumber":"4",
    "addr:postcode":"31400",
    "addr:street":"Rue Jules Vedrines",
    "iso:country":"FR",
    "sg:address":"4, Rue Jules Vedrines, 31400 Toulouse",
    "sg:orig_category":"Unclassifiable Establishments",
    "sg:phone":"+33 5 62 16 72 72",
    "sg:province":"Midi Pyr\u00e9n\u00e9es",
    "wof:name":"Ide Ing\u00e9nierie S.a.",
    "wof:placetype":"venue"
},
  "geometry": {"coordinates":[1.489578,43.56992],"type":"Point"}
}