{
  "type": "Feature",
  "properties": {
    "iso:country":"FR",
    "sg:address":"12 rue Deguerry 75011 Paris",
    "sg:classifiers":[
        {
            "category":"Government",
            "subcategory":"Fire Station",
            "type":"Public Place"
        }
    ],
    "sg:phone":"+33 1 48 06 15 17",
    "sg:postcode":"75011",
    "sg:province":"Ile de France",
    "sg:tags":[
        "insulation",
        "element"
    ],
    "wof:name":"C.m.e.t. Sarl",
    "wof:placetype":"venue"
},
  "geometry": {"coordinates":[2.373691,48.868725],"type":"Point"}
}