{
  "type": "Feature",
  "properties": {
    "addr:full":"ZA Oizon Centre 18700",
    "addr:postcode":"18700",
    "addr:street":"Za Oizon",
    "iso:country":"FR",
    "sg:address":"ZA",
    "sg:city":"Oizon",
    "sg:orig_category":"Unclassifiable Establishments",
    "sg:phone":"+33 2 48 58 14 47",
    "sg:postcode":"18700",
    "sg:province":"Centre",
    "wof:name":"A.c.c.a. S.a.r.l.",
    "wof:placetype":"venue"
},
  "geometry": {"coordinates":[2.50778,47.421684],"type":"Point"}
}