{
  "type": "Feature",
  "properties": {
    "addr:full":"Rugles 27250 AMBENAY Haute Normandie 27250",
    "addr:postcode":"27250;27250",
    "addr:street":"Haute Normandie",
    "iso:country":"FR",
    "sg:address":"Rugles 27250 AMBENAY",
    "sg:classifiers":[
        {
            "category":"Utilities",
            "subcategory":"Cable",
            "type":"Services"
        }
    ],
    "sg:phone":"+33 2 32 24 71 11",
    "sg:postcode":"27250",
    "sg:province":"Haute Normandie",
    "sg:tags":[
        "mass-produced",
        "article",
        "wire",
        "bent",
        "articles"
    ],
    "wof:name":"Caliste Marquis S.a.",
    "wof:placetype":"venue"
},
  "geometry": {"coordinates":[0.70806,48.822361],"type":"Point"}
}