{
  "type": "Feature",
  "properties": {
    "iso:country":"FR",
    "sg:address":"Ch\u00e2teau de Hielle",
    "sg:city":"Rupt sur Moselle",
    "sg:orig_category":"Non-Classified Establishments",
    "sg:phone":"+33 3 29 61 04 04",
    "sg:postcode":"88360",
    "sg:province":"Lorraine",
    "wof:name":"Graphco Publicit\u00e9",
    "wof:placetype":"venue"
},
  "geometry": {"coordinates":[6.661985,47.921665],"type":"Point"}
}