{
  "type": "Feature",
  "properties": {
    "addr:full":"9, Rue du Bochet, 38230 Tignieu Jameyzieu Rhone-Alpes 38230",
    "addr:housenumber":"9",
    "addr:postcode":"38230;38230",
    "addr:street":"Rue Du Bochet;Rhone-Alpes",
    "iso:country":"FR",
    "sg:address":"9, Rue du Bochet, 38230 Tignieu Jameyzieu",
    "sg:orig_category":"Unclassifiable Establishments",
    "sg:phone":"+33 4 78 32 13 33",
    "sg:postcode":"38230",
    "sg:province":"Rhone-Alpes",
    "wof:name":"S.o.c.o.m.a.t. S.a.",
    "wof:placetype":"venue"
},
  "geometry": {"coordinates":[5.186492,45.7467],"type":"Point"}
}