{
  "type": "Feature",
  "properties": {
    "addr:full":"Centre d'Affaires des Coteaux Muizon Champagne 51140",
    "addr:postcode":"51140",
    "addr:street":"Champagne",
    "iso:country":"FR",
    "sg:address":"Centre d'Affaires des Coteaux",
    "sg:city":"Muizon",
    "sg:orig_category":"Non-Classified Establishments",
    "sg:phone":"+33 3 26 02 99 33",
    "sg:postcode":"51140",
    "sg:province":"Champagne",
    "wof:name":"Applicom S.a.r.l.",
    "wof:placetype":"venue"
},
  "geometry": {"coordinates":[3.88908,49.27599],"type":"Point"}
}