{
  "type": "Feature",
  "properties": {
    "iso:country":"FR",
    "sg:address":"460, Rue du Valibout, 78370 Plaisir",
    "sg:orig_category":"Unclassifiable Establishments",
    "sg:phone":"+33 1 30 07 78 10",
    "sg:province":"Ile de France",
    "wof:name":"U.p.s. S.n.c. - United Parcel Service France",
    "wof:placetype":"venue"
},
  "geometry": {"coordinates":[1.957611,48.819977],"type":"Point"}
}