{
  "type": "Feature",
  "properties": {
    "addr:full":"65, Grande Rue - Nohan sur Semoy , 08800 Thilay Deville Champagne 08800",
    "addr:housenumber":"65",
    "addr:postcode":"08800;08800",
    "addr:street":"Grande Rue Nohan Sur Semoy;Champagne",
    "iso:country":"FR",
    "sg:address":"65, Grande Rue - Nohan sur Semoy , 08800 Thilay",
    "sg:city":"Deville",
    "sg:orig_category":"Unclassifiable Establishments",
    "sg:phone":"+33 3 24 53 41 72",
    "sg:postcode":"08800",
    "sg:province":"Champagne",
    "wof:name":"Bisiaux Theault S.a.r.l.",
    "wof:placetype":"venue"
},
  "geometry": {"coordinates":[4.767382,49.882172],"type":"Point"}
}