{
  "type": "Feature",
  "properties": {
    "addr:full":"3, Rue Marc Seguin, 01000 Bourg en Bresse Rhone-Alpes 01000",
    "addr:housenumber":"3",
    "addr:postcode":"01000;01000",
    "addr:street":"Rue Marc Seguin;Rhone-Alpes",
    "iso:country":"FR",
    "sg:address":"3, Rue Marc Seguin, 01000 Bourg en Bresse",
    "sg:orig_category":"Unclassifiable Establishments",
    "sg:phone":"+33 4 74 23 41 90",
    "sg:postcode":"01000",
    "sg:province":"Rhone-Alpes",
    "wof:name":"Favrat Blanchisserie S.a.",
    "wof:placetype":"venue"
},
  "geometry": {"coordinates":[5.219438,46.214733],"type":"Point"}
}