{
  "type": "Feature",
  "properties": {
    "iso:country":"FR",
    "sg:address":"Av. du Stade",
    "sg:city":"Ayse",
    "sg:orig_category":"Unclassifiable Establishments",
    "sg:phone":"+33 4 50 97 03 21",
    "sg:postcode":"74130",
    "sg:province":"Rhone-Alpes",
    "wof:name":"Broisin Eug\u00e8ne S.a.",
    "wof:placetype":"venue"
},
  "geometry": {"coordinates":[6.388322,45.95652],"type":"Point"}
}