{
  "type": "Feature",
  "properties": {
    "addr:full":"Rte de Lourdes Asson Aquitaine 64800",
    "addr:postcode":"64800",
    "addr:street":"Rte De Lourdes",
    "iso:country":"FR",
    "sg:address":"Rte de Lourdes",
    "sg:city":"Asson",
    "sg:orig_category":"Unclassifiable Establishments",
    "sg:phone":"+33 5 59 71 02 98",
    "sg:postcode":"64800",
    "sg:province":"Aquitaine",
    "wof:name":"Etablissements Rib\u00e8re",
    "wof:placetype":"venue"
},
  "geometry": {"coordinates":[-0.299389,43.099781],"type":"Point"}
}