{
  "type": "Feature",
  "properties": {
    "addr:full":"20 Rte Maisons 78400 Chatou Ile de France 78400",
    "addr:housenumber":"20",
    "addr:postcode":"78400;78400",
    "addr:street":"Rte Maisons;Ile De France",
    "iso:country":"FR",
    "sg:address":"20 Rte Maisons 78400 Chatou",
    "sg:classifiers":[
        {
            "category":"Professional",
            "subcategory":"Business Services",
            "type":"Services"
        }
    ],
    "sg:phone":"+33 1 30 15 98 98",
    "sg:postcode":"78400",
    "sg:province":"Ile de France",
    "sg:tags":[
        "training",
        "advice"
    ],
    "wof:name":"Institut De Pedagogie Curative",
    "wof:placetype":"venue"
},
  "geometry": {"coordinates":[2.156141,48.897449],"type":"Point"}
}