{
  "type": "Feature",
  "properties": {
    "addr:full":"8 All Des Peupliers Zi 54180 Houdemont Heillecourt Lorraine 54180",
    "addr:housenumber":"8",
    "addr:postcode":"54180;54180",
    "addr:street":"All Des Peupliers Zi",
    "iso:country":"FR",
    "sg:address":"8 All Des Peupliers Zi 54180 Houdemont Heillecourt",
    "sg:orig_category":"Jewellery Mechanical Engineering - machines Miscellaneous Products",
    "sg:phone":"+33 3 83 56 03 21",
    "sg:postcode":"54180",
    "sg:province":"Lorraine",
    "wof:name":"L\u00c9ry Bouvier Sa",
    "wof:placetype":"venue"
},
  "geometry": {"coordinates":[6.176609,48.647343],"type":"Point"}
}