{
  "type": "Feature",
  "properties": {
    "addr:full":"15 Quai Leray; Pornic Champagne",
    "addr:housenumber":"15",
    "addr:street":"Quai Leray",
    "iso:country":"FR",
    "sg:address":"15 Quai Leray; Pornic",
    "sg:classifiers":[
        {
            "category":"Banks & Credit Unions",
            "subcategory":"Bank",
            "type":"Services"
        }
    ],
    "sg:phone":"+33 3340820081",
    "sg:province":"Champagne",
    "wof:name":"Banque Cio",
    "wof:placetype":"venue"
},
  "geometry": {"coordinates":[-2.099449,47.115742],"type":"Point"}
}