{
  "type": "Feature",
  "properties": {
    "addr:full":"26 rue Berthe de Boissieux 38000 Grenoble Rhone-Alpes 38000",
    "addr:housenumber":"26",
    "addr:postcode":"38000;38000",
    "addr:street":"Rue Berthe De Boissieux",
    "iso:country":"FR",
    "sg:address":"26 rue Berthe de Boissieux 38000 Grenoble",
    "sg:orig_category":"Drag\u00e9es Sweets",
    "sg:phone":"+33 4 76 46 18 23",
    "sg:postcode":"38000",
    "sg:province":"Rhone-Alpes",
    "wof:name":"Dragees Adjy S.a.r.l.",
    "wof:placetype":"venue"
},
  "geometry": {"coordinates":[5.721686,45.183723],"type":"Point"}
}