{
  "type": "Feature",
  "properties": {
    "iso:country":"FR",
    "sg:address":"Av. Henry Deluc",
    "sg:city":"Boulazac",
    "sg:orig_category":"Unclassifiable Establishments",
    "sg:phone":"+33 5 53 45 52 22",
    "sg:postcode":"24750",
    "sg:province":"Aquitaine",
    "wof:name":"Confort 24 S.a.",
    "wof:placetype":"venue"
},
  "geometry": {"coordinates":[0.77935,45.182819],"type":"Point"}
}