{
  "type": "Feature",
  "properties": {
    "addr:full":"Av. Auguste Marius Peyr\u00e9 - ZI la Grand'Colle Port de Bouc Centre 13110",
    "addr:postcode":"13110",
    "addr:street":"Av. Auguste Marius Peyre\u0301 Zi La Grand'Colle Port De Bouc",
    "iso:country":"FR",
    "sg:address":"Av. Auguste Marius Peyr\u00e9 - ZI la Grand'Colle",
    "sg:city":"Port de Bouc",
    "sg:orig_category":"Unclassifiable Establishments",
    "sg:phone":"+33 4 42 40 52 40",
    "sg:postcode":"13110",
    "sg:province":"Centre",
    "wof:name":"Saybolt France S.a.",
    "wof:placetype":"venue"
},
  "geometry": {"coordinates":[5.020552,43.440903],"type":"Point"}
}