{
  "type": "Feature",
  "properties": {
    "addr:full":"49/51 ave George V; Paris; 75008 Ile de France 75008",
    "addr:housenumber":"49 / 51",
    "addr:postcode":"75008;75008",
    "addr:street":"Ave George V Paris;France",
    "iso:country":"FR",
    "sg:address":"49/51 ave George V; Paris; 75008",
    "sg:classifiers":[
        {
            "category":"Banks & Credit Unions",
            "subcategory":"Bank",
            "type":"Services"
        }
    ],
    "sg:phone":"+33 1 40 70 01 01",
    "sg:postcode":"75008",
    "sg:province":"Ile de France",
    "wof:name":"Arab Banking Corporation",
    "wof:placetype":"venue"
},
  "geometry": {"coordinates":[2.300748,48.870548],"type":"Point"}
}