{
  "type": "Feature",
  "properties": {
    "addr:full":"8 Av De La R\u00e9publique 51304 Vitry Le Fran\u00e7ois Fran\u00e7ois Poitou-Charentes 79260",
    "addr:postcode":"51304;79260",
    "addr:street":"Av De La Re\u0301Publique;Franc\u0327Ois Franc\u0327Ois",
    "iso:country":"FR",
    "sg:address":"8 Av De La R\u00e9publique 51304 Vitry Le Fran\u00e7ois",
    "sg:city":"Fran\u00e7ois",
    "sg:classifiers":[
        {
            "category":"Professional",
            "subcategory":"Computer Services",
            "type":"Services"
        }
    ],
    "sg:phone":"+33 3 26 73 07 61",
    "sg:postcode":"79260",
    "sg:province":"Poitou-Charentes",
    "sg:tags":[
        "information",
        "technology",
        "software"
    ],
    "wof:name":"Business Solutions",
    "wof:placetype":"venue"
},
  "geometry": {"coordinates":[4.588224,48.719105],"type":"Point"}
}