{
  "type": "Feature",
  "properties": {
    "addr:full":"B.P. 17, 57255 Sainte Marie aux Ch\u00eanes C\u00e9dex^^ZI, 57255 Sainte Marie aux Ch\u00eanes Lorraine",
    "addr:postcode":"57255;57255",
    "addr:street":"B.P. 17;Aux Che\u0302Nes Ce\u0301Dex^^Zi;Aux Che\u0302Nes",
    "iso:country":"FR",
    "sg:address":"B.P. 17, 57255 Sainte Marie aux Ch\u00eanes C\u00e9dex^^ZI, 57255 Sainte Marie aux Ch\u00eanes",
    "sg:orig_category":"Non-Classified Establishments",
    "sg:phone":"+33 3 87 34 26 00",
    "sg:province":"Lorraine",
    "wof:name":"Mauchoff\u00e9 S.a.",
    "wof:placetype":"venue"
},
  "geometry": {"coordinates":[6.00664,49.190941],"type":"Point"}
}