{
  "type": "Feature",
  "properties": {
    "addr:full":"55, Rue Jean Giraudoux, 67200 Strasbourg Strasbourg Alsace 67200",
    "addr:housenumber":"55",
    "addr:postcode":"67200;67200",
    "addr:street":"Rue Jean Giraudoux",
    "iso:country":"FR",
    "sg:address":"55, Rue Jean Giraudoux, 67200 Strasbourg",
    "sg:city":"Strasbourg",
    "sg:orig_category":"Unclassifiable Establishments",
    "sg:phone":"+33 3 88 29 76 66",
    "sg:postcode":"67200",
    "sg:province":"Alsace",
    "wof:name":"Levy Frey S.a.",
    "wof:placetype":"venue"
},
  "geometry": {"coordinates":[7.701136,48.587635],"type":"Point"}
}