{
  "type": "Feature",
  "properties": {
    "addr:full":"100 A, Rue Nationale 3, 57350 Stiring Wendel Lorraine",
    "addr:housenumber":"100 a",
    "addr:postcode":"57350",
    "addr:street":"Rue Nationale 3;Wendel",
    "iso:country":"FR",
    "sg:address":"100 A, Rue Nationale 3, 57350 Stiring Wendel",
    "sg:orig_category":"Non-Classified Establishments",
    "sg:phone":"+33 3 87 88 00 00",
    "sg:province":"Lorraine",
    "wof:name":"Services Franoux Jean-pierre",
    "wof:placetype":"venue"
},
  "geometry": {"coordinates":[6.928195,49.200981],"type":"Point"}
}