{
  "type": "Feature",
  "properties": {
    "iso:country":"FR",
    "sg:address":"100 A, Rue Nationale 3, 57350 Stiring Wendel",
    "sg:orig_category":"Non-Classified Establishments",
    "sg:phone":"+33 3 87 88 00 00",
    "sg:province":"Lorraine",
    "wof:name":"Services Franoux Jean-pierre",
    "wof:placetype":"venue"
},
  "geometry": {"coordinates":[6.928195,49.200981],"type":"Point"}
}