{
  "type": "Feature",
  "properties": {
    "iso:country":"FR",
    "sg:address":"16 Rte De La Schlucht 68140 Stosswihr",
    "sg:city":"Stosswihr",
    "sg:classifiers":[
        {
            "category":"Bakery",
            "type":"Food & Drink"
        }
    ],
    "sg:phone":"+33 3 89 77 88 00",
    "sg:postcode":"68140",
    "sg:province":"Alsace",
    "sg:tags":[
        "cake",
        "product",
        "related",
        "bread"
    ],
    "wof:name":"Ste Baste",
    "wof:placetype":"venue"
},
  "geometry": {"coordinates":[7.114758,48.049355],"type":"Point"}
}