{
  "type": "Feature",
  "properties": {
    "addr:full":"63, Rue d'Angleterre, 59800 Lille Nord Pas-de-Calais",
    "addr:housenumber":"63",
    "addr:postcode":"59800",
    "addr:street":"Rue D'Angleterre",
    "iso:country":"FR",
    "sg:address":"63, Rue d'Angleterre, 59800 Lille",
    "sg:orig_category":"Non-Classified Establishments",
    "sg:phone":"+33 3 20 63 11 70",
    "sg:province":"Nord Pas-de-Calais",
    "wof:name":"Netco S.a.",
    "wof:placetype":"venue"
},
  "geometry": {"coordinates":[3.060039,50.641079],"type":"Point"}
}