{
  "type": "Feature",
  "properties": {
    "addr:full":"B.P. 83, 26802 Porte l\u00e8s Valence C\u00e9dex^^Rue Louis Saillant, 26800 Porte l\u00e8s Valence Rhone-Alpes",
    "addr:postcode":"26802;26800",
    "addr:street":"B.P. 83;Le\u0300S;Louis Saillant;Le\u0300S",
    "iso:country":"FR",
    "sg:address":"B.P. 83, 26802 Porte l\u00e8s Valence C\u00e9dex^^Rue Louis Saillant, 26800 Porte l\u00e8s Valence",
    "sg:orig_category":"Non-Classified Establishments",
    "sg:phone":"+33 4 75 57 57 57",
    "sg:province":"Rhone-Alpes",
    "wof:name":"T\u00e9zier S.a.",
    "wof:placetype":"venue"
},
  "geometry": {"coordinates":[4.907647,44.794395],"type":"Point"}
}