{
  "type": "Feature",
  "properties": {
    "addr:full":"La Ville Cognac 56430 Mauron Mauron Bretagne 56430",
    "addr:postcode":"56430;56430",
    "addr:street":"La Ville;Mauron",
    "iso:country":"FR",
    "sg:address":"La Ville Cognac 56430 Mauron",
    "sg:city":"Mauron",
    "sg:orig_category":"Non-Classified Establishments",
    "sg:phone":"+33 2 97 22 79 72",
    "sg:postcode":"56430",
    "sg:province":"Bretagne",
    "wof:name":"Aurecom E.u.r.l.",
    "wof:placetype":"venue"
},
  "geometry": {"coordinates":[-2.256674,48.086609],"type":"Point"}
}