{
  "type": "Feature",
  "properties": {
    "addr:full":"Rue de Verdun Le Pin Ile de France 77181",
    "addr:postcode":"77181",
    "addr:street":"Rue De Verdun",
    "iso:country":"FR",
    "sg:address":"Rue de Verdun",
    "sg:city":"Le Pin",
    "sg:orig_category":"Unclassifiable Establishments",
    "sg:phone":"+33 1 60 26 06 20",
    "sg:postcode":"77181",
    "sg:province":"Ile de France",
    "wof:name":"A.d.f.r. S.a.r.l. - Aspiration D\u00e9poussi\u00e9rage Filtration Et R\u00e9alisation",
    "wof:placetype":"venue"
},
  "geometry": {"coordinates":[2.627655,48.914387],"type":"Point"}
}