{
  "type": "Feature",
  "properties": {
    "iso:country":"FR",
    "sg:address":"27, Rue Desseaux, 76100 Rouen",
    "sg:orig_category":"Unclassifiable Establishments",
    "sg:phone":"+33 2 35 72 91 45",
    "sg:province":"Haute Normandie",
    "wof:name":"Bricard S.a.",
    "wof:placetype":"venue"
},
  "geometry": {"coordinates":[1.093019,49.430794],"type":"Point"}
}