{
  "type": "Feature",
  "properties": {
    "iso:country":"FR",
    "sg:address":"rue Trieu du Quesnoy 59390 Toufflers",
    "sg:classifiers":[
        {
            "category":"Real Estate",
            "subcategory":"Surveying",
            "type":"Services"
        }
    ],
    "sg:phone":"+33 3 20 89 37 89",
    "sg:postcode":"59390",
    "sg:province":"Nord Pas-de-Calais",
    "sg:tags":[
        "wooden",
        "moulding",
        "carved"
    ],
    "wof:name":"Probois Sa",
    "wof:placetype":"venue"
},
  "geometry": {"coordinates":[3.234615,50.669254],"type":"Point"}
}