{
  "type": "Feature",
  "properties": {
    "addr:full":"149, Rue de France, 57200 Sarreguemines Lorraine",
    "addr:housenumber":"149",
    "addr:postcode":"57200",
    "addr:street":"Rue De France",
    "iso:country":"FR",
    "sg:address":"149, Rue de France, 57200 Sarreguemines",
    "sg:orig_category":"Non-Classified Establishments",
    "sg:phone":"+33 3 87 98 27 37",
    "sg:province":"Lorraine",
    "wof:name":"N.i.l. S.a.r.l. - Nettoyage Industriel Des Locaux",
    "wof:placetype":"venue"
},
  "geometry": {"coordinates":[7.052837,49.112015],"type":"Point"}
}