{
  "type": "Feature",
  "properties": {
    "addr:full":"Sainte Marie aux Anglais - Saint Maclou Le Mesnil Mauger Basse Normandie 14270",
    "addr:postcode":"14270",
    "addr:street":"Saint Maclou Le",
    "iso:country":"FR",
    "sg:address":"Sainte Marie aux Anglais - Saint Maclou",
    "sg:city":"Le Mesnil Mauger",
    "sg:orig_category":"Unclassifiable Establishments",
    "sg:phone":"+33 2 31 63 82 05",
    "sg:postcode":"14270",
    "sg:province":"Basse Normandie",
    "wof:name":"Soci\u00e9t\u00e9 Fromag\u00e8re De Saint Maclou S.n.c.",
    "wof:placetype":"venue"
},
  "geometry": {"coordinates":[0.00455,49.06942],"type":"Point"}
}