{
  "type": "Feature",
  "properties": {
    "iso:country":"FR",
    "sg:address":"2 R Du K\u00e9fir S\u00e9nia 343 Sud 94537 Orly Cedex",
    "sg:classifiers":[
        {
            "category":"Utilities",
            "subcategory":"Telephone",
            "type":"Services"
        }
    ],
    "sg:phone":"+33 1 49 79 45 45",
    "sg:province":"Ile de France",
    "sg:tags":[
        "telecommunication"
    ],
    "wof:name":"Castor Informatique Sarl",
    "wof:placetype":"venue"
},
  "geometry": {"coordinates":[2.40116,48.742931],"type":"Point"}
}