{
  "type": "Feature",
  "properties": {
    "iso:country":"FR",
    "sg:address":"55, Av. de la Fontaine, 33560 Carbon Blanc",
    "sg:city":"Carbon-Blanc",
    "sg:orig_category":"Non-Classified Establishments",
    "sg:phone":"+33 5 56 38 00 34",
    "sg:postcode":"33560",
    "sg:province":"Aquitaine",
    "wof:name":"U.p.s. S.a. - United Parcelle Services",
    "wof:placetype":"venue"
},
  "geometry": {"coordinates":[-0.495299,44.90823],"type":"Point"}
}