{
  "type": "Feature",
  "properties": {
    "addr:full":"76730 Bacqueville en Caux Haute Normandie",
    "addr:postcode":"76730",
    "addr:street":"Bacqueville En Caux Haute Normandie",
    "iso:country":"FR",
    "sg:address":"76730 Bacqueville en Caux",
    "sg:orig_category":"Unclassifiable Establishments",
    "sg:phone":"+33 2 35 83 23 91",
    "sg:province":"Haute Normandie",
    "wof:name":"De Sutter Fr\u00e8res S.a.",
    "wof:placetype":"venue"
},
  "geometry": {"coordinates":[0.999626,49.786495],"type":"Point"}
}