{
  "type": "Feature",
  "properties": {
    "iso:country":"FR",
    "sg:address":"356, Rue Pierre et Marie Curie - Zone Industrielle, 54710 Ludres",
    "sg:orig_category":"Non-Classified Establishments",
    "sg:phone":"+33 3 83 25 90 06",
    "sg:province":"Lorraine",
    "wof:name":"Plexinox S.a.r.l.",
    "wof:placetype":"venue"
},
  "geometry": {"coordinates":[6.161059,48.621563],"type":"Point"}
}