{
  "type": "Feature",
  "properties": {
    "addr:full":"9 Rue Christophe Colomb 94600 Choisy Le Roi Ile de France 94600",
    "addr:housenumber":"9",
    "addr:postcode":"94600;94600",
    "addr:street":"Rue Christophe Colomb",
    "iso:country":"FR",
    "sg:address":"9 Rue Christophe Colomb 94600 Choisy Le Roi",
    "sg:classifiers":[
        {
            "category":"Manufacturing",
            "subcategory":"Building Materials",
            "type":"Manufacturing & Wholesale Goods"
        }
    ],
    "sg:phone":"+33 1 48 92 68 67",
    "sg:postcode":"94600",
    "sg:province":"Ile de France",
    "sg:tags":[
        "-",
        "machine",
        "raw",
        "engineering",
        "paper",
        "mechanical",
        "cardboard"
    ],
    "wof:name":"Atelier Creations Formess (acf)",
    "wof:placetype":"venue"
},
  "geometry": {"coordinates":[2.416103,48.75349],"type":"Point"}
}