{
  "type": "Feature",
  "properties": {
    "iso:country":"FR",
    "sg:address":"Quartier des Pessades",
    "sg:city":"S\u00e9rignan du Comtat",
    "sg:orig_category":"Non-Classified Establishments",
    "sg:phone":"+33 4 90 70 00 13",
    "sg:postcode":"84830",
    "sg:province":"Midi Pyr\u00e9n\u00e9es",
    "wof:name":"Huileries De S\u00e9rignan S.a.r.l.",
    "wof:placetype":"venue"
},
  "geometry": {"coordinates":[4.838843,44.186501],"type":"Point"}
}