{
  "type": "Feature",
  "properties": {
    "iso:country":"FR",
    "sg:address":"Parc d'Activit\u00e9s du Ch\u00e2teau",
    "sg:city":"M\u00e9lamare",
    "sg:orig_category":"Unclassifiable Establishments",
    "sg:phone":"+33 2 35 39 37 00",
    "sg:postcode":"76170",
    "sg:province":"Haute Normandie",
    "wof:name":"Johnson Controls S.a.",
    "wof:placetype":"venue"
},
  "geometry": {"coordinates":[0.4533,49.536579],"type":"Point"}
}