{
  "type": "Feature",
  "properties": {
    "addr:full":"Route De Marange 57282 Maizi\u00e8res L\u00e8s Metz Lorraine",
    "addr:postcode":"57282",
    "addr:street":"Route De Marange",
    "iso:country":"FR",
    "sg:address":"Route De Marange 57282 Maizi\u00e8res L\u00e8s Metz",
    "sg:classifiers":[
        {
            "category":"Professional",
            "type":"Services"
        }
    ],
    "sg:phone":"+33 3 87 80 11 33",
    "sg:province":"Lorraine",
    "sg:tags":[
        "transport",
        "road"
    ],
    "wof:name":"Str Lorafret",
    "wof:placetype":"venue"
},
  "geometry": {"coordinates":[6.155825,49.2127],"type":"Point"}
}