{
  "type": "Feature",
  "properties": {
    "addr:full":"38, Av. Hoche, 75008 Paris Ile de France",
    "addr:postcode":"75008",
    "addr:street":"38 Av. Hoche",
    "iso:country":"FR",
    "sg:address":"38, Av. Hoche, 75008 Paris",
    "sg:orig_category":"Unclassifiable Establishments",
    "sg:phone":"+33 1 42 89 14 34",
    "sg:province":"Ile de France",
    "wof:name":"J.s.b. S.a. - John Stephen B",
    "wof:placetype":"venue"
},
  "geometry": {"coordinates":[2.299413,48.875847],"type":"Point"}
}