{
  "type": "Feature",
  "properties": {
    "iso:country":"FR",
    "sg:address":"55, Rue des Francs Bourgeois, 75004 Paris",
    "sg:orig_category":"Unclassifiable Establishments",
    "sg:phone":"+33 1 44 61 64 00",
    "sg:province":"Ile de France",
    "wof:name":"C.m.p. - Cr\u00e9dit Municipal De Paris",
    "wof:placetype":"venue"
},
  "geometry": {"coordinates":[2.357652,48.859287],"type":"Point"}
}