{
  "type": "Feature",
  "properties": {
    "iso:country":"FR",
    "sg:address":"B.P. 80006, 08201 Sedan C\u00e9dex^^7, Bd Chanzy, 08200 Sedan",
    "sg:orig_category":"Consoles Ferronnerie de b\u00e2timent Quincaillerie de b\u00e2timent Volets, Arr\u00eats de Volets, Quincaillerie p",
    "sg:phone":"+33 3 24 27 01 40",
    "sg:postcode":"08200",
    "sg:province":"Champagne",
    "wof:name":"L'industrielle De Sedan S.a.",
    "wof:placetype":"venue"
},
  "geometry": {"coordinates":[4.93936,49.709202],"type":"Point"}
}