{
  "type": "Feature",
  "properties": {
    "addr:full":"38, Rue Robert Degon, 02170 Le Nouvion en Thi\u00e9rache Picardie",
    "addr:housenumber":"38",
    "addr:postcode":"02170",
    "addr:street":"Rue Robert Degon;Nouvion",
    "iso:country":"FR",
    "sg:address":"38, Rue Robert Degon, 02170 Le Nouvion en Thi\u00e9rache",
    "sg:orig_category":"Non-Classified Establishments",
    "sg:phone":"+33 3 23 97 88 88",
    "sg:province":"Picardie",
    "wof:name":"West Pharmaceutical Services France S.a.",
    "wof:placetype":"venue"
},
  "geometry": {"coordinates":[3.78398,50.020664],"type":"Point"}
}