{
  "type": "Feature",
  "properties": {
    "iso:country":"FR",
    "sg:address":"33 Rue Carnot 59113 Seclin",
    "sg:classifiers":[
        {
            "category":"Wholesale",
            "subcategory":"Machinery & Supplies",
            "type":"Manufacturing & Wholesale Goods"
        }
    ],
    "sg:phone":"+33 3 20 32 19 00",
    "sg:province":"Nord Pas-de-Calais",
    "sg:tags":[
        "equipment",
        "precision"
    ],
    "wof:name":"Securite Alarme Vol Incendie",
    "wof:placetype":"venue"
},
  "geometry": {"coordinates":[3.028209,50.550831],"type":"Point"}
}