{
  "type": "Feature",
  "properties": {
    "addr:full":"10, Rue de la Tuilerie, 25500 Montlebon Franche Comt\u00e9",
    "addr:housenumber":"10",
    "addr:postcode":"25500",
    "addr:street":"Rue De La Tuilerie;Franche Comte\u0301",
    "iso:country":"FR",
    "sg:address":"10, Rue de la Tuilerie, 25500 Montlebon",
    "sg:orig_category":"Unclassifiable Establishments",
    "sg:phone":"+33 3 81 67 01 41",
    "sg:province":"Franche Comt\u00e9",
    "wof:name":"Jacques Gaiffe",
    "wof:placetype":"venue"
},
  "geometry": {"coordinates":[6.612973,47.043983],"type":"Point"}
}