{
  "type": "Feature",
  "properties": {
    "iso:country":"FR",
    "sg:address":"Rue Du Milieu 59190 Hazebrouck",
    "sg:classifiers":[
        {
            "category":"Shopping",
            "subcategory":"Clothing, Apparel, & Fashions",
            "type":"Retail Goods"
        }
    ],
    "sg:phone":"+33 3 28 41 41 08",
    "sg:postcode":"59190",
    "sg:province":"Nord Pas-de-Calais",
    "sg:tags":[
        "textile",
        "clothing",
        "clothes"
    ],
    "wof:name":"Marketing Licensed Products (mlp)",
    "wof:placetype":"venue"
},
  "geometry": {"coordinates":[2.54502,50.71743],"type":"Point"}
}