{
  "type": "Feature",
  "properties": {
    "addr:full":"Le Vignal 07530 Saint Joseph des Bancs Rhone-Alpes 07530",
    "addr:postcode":"07530;07530",
    "addr:street":"Le Vignal;Des Bancs Rhone-Alpes",
    "iso:country":"FR",
    "sg:address":"Le Vignal 07530 Saint Joseph des Bancs",
    "sg:orig_category":"Unclassifiable Establishments",
    "sg:phone":"+33 4 75 88 22 65",
    "sg:postcode":"07530",
    "sg:province":"Rhone-Alpes",
    "wof:name":"C\u00e9ma Electronique S.a.r.l.",
    "wof:placetype":"venue"
},
  "geometry": {"coordinates":[4.351755,44.756084],"type":"Point"}
}