{
  "type": "Feature",
  "properties": {
    "iso:country":"FR",
    "sg:address":"5 rue Mairie; L'Hopital Camfrout",
    "sg:classifiers":[
        {
            "category":"Banks & Credit Unions",
            "subcategory":"Bank",
            "type":"Services"
        }
    ],
    "sg:phone":"+33 3398200165",
    "sg:province":"Basse Normandie",
    "wof:name":"Cr\u00e9dit Mutuel De Bretagne",
    "wof:placetype":"venue"
},
  "geometry": {"coordinates":[-4.242243,48.327812],"type":"Point"}
}