{
  "type": "Feature",
  "properties": {
    "addr:full":"25, Rte de Saint Leu, 95600 Eaubonne Ile de France",
    "addr:housenumber":"25",
    "addr:postcode":"95600",
    "addr:street":"Rte De Saint Leu",
    "iso:country":"FR",
    "sg:address":"25, Rte de Saint Leu, 95600 Eaubonne",
    "sg:orig_category":"Unclassifiable Establishments",
    "sg:phone":"+33 1 34 27 54 00",
    "sg:province":"Ile de France",
    "wof:name":"Val Joly Organisation S.a.r.l.",
    "wof:placetype":"venue"
},
  "geometry": {"coordinates":[2.271592,48.996292],"type":"Point"}
}