{
  "type": "Feature",
  "properties": {
    "iso:country":"FR",
    "sg:address":"ZI RUE CASSIN 39300 Champagnole",
    "sg:classifiers":[
        {
            "category":"Professional",
            "type":"Services"
        }
    ],
    "sg:phone":"+33 3 84 52 05 07",
    "sg:province":"Franche Comt\u00e9",
    "sg:tags":[
        "transport",
        "road"
    ],
    "wof:name":"Transport Salvi",
    "wof:placetype":"venue"
},
  "geometry": {"coordinates":[5.907597,46.747177],"type":"Point"}
}