{
  "type": "Feature",
  "properties": {
    "addr:full":"CD 412 - ZI Nord Amiens Picardie 80046",
    "addr:housenumber":"cd 412",
    "addr:postcode":"80046",
    "iso:country":"FR",
    "sg:address":"CD 412 - ZI Nord",
    "sg:city":"Amiens",
    "sg:orig_category":"Unclassifiable Establishments",
    "sg:phone":"+33 3 22 54 98 10",
    "sg:postcode":"80046",
    "sg:province":"Picardie",
    "wof:name":"Picardie Manutention Services S.a.r.l.",
    "wof:placetype":"venue"
},
  "geometry": {"coordinates":[2.30253,49.893959],"type":"Point"}
}