{
  "type": "Feature",
  "properties": {
    "addr:full":"2 Rue Caroline 75017 Paris Ile de France",
    "addr:housenumber":"2",
    "addr:postcode":"75017",
    "addr:street":"Rue Caroline",
    "iso:country":"FR",
    "sg:address":"2 Rue Caroline 75017 Paris",
    "sg:classifiers":[
        {
            "category":"Professional",
            "subcategory":"Printing & Photocopies",
            "type":"Services"
        }
    ],
    "sg:phone":"+33 1 55 30 40 50",
    "sg:province":"Ile de France",
    "sg:tags":[
        "publishing"
    ],
    "wof:name":"Mango Presse",
    "wof:placetype":"venue"
},
  "geometry": {"coordinates":[2.324729,48.883862],"type":"Point"}
}