{
  "type": "Feature",
  "properties": {
    "addr:full":"B.P. CS 87703 Cesson S\u00e9vign\u00e9 C\u00e9dex^^35510 Cesson S\u00e9vign\u00e9 Bretagne 35577",
    "addr:postcode":"35577",
    "addr:street":"B.P. Cs 87703;Ce\u0301Dex^^35510;Se\u0301Vigne\u0301 Bretagne",
    "iso:country":"FR",
    "sg:address":"B.P. CS 87703",
    "sg:city":"Cesson S\u00e9vign\u00e9 C\u00e9dex^^35510 Cesson S\u00e9vign\u00e9",
    "sg:orig_category":"Non-Classified Establishments",
    "sg:phone":"+33 2 99 51 21 21",
    "sg:postcode":"35577",
    "sg:province":"Bretagne",
    "wof:name":"S\u00e9curitas France S.a.r.l.",
    "wof:placetype":"venue"
},
  "geometry": {"coordinates":[-1.604404,48.117016],"type":"Point"}
}