{
  "type": "Feature",
  "properties": {
    "addr:full":"2-4, Rue Kuss, 75013 Paris Ile de France",
    "addr:housenumber":"2-4",
    "addr:postcode":"75013",
    "addr:street":"Rue Kuss",
    "iso:country":"FR",
    "sg:address":"2-4, Rue Kuss, 75013 Paris",
    "sg:orig_category":"Non-Classified Establishments",
    "sg:phone":"+33 1 53 80 86 90",
    "sg:province":"Ile de France",
    "wof:name":"Industrie Int\u00e9rim Services S.a.",
    "wof:placetype":"venue"
},
  "geometry": {"coordinates":[2.352433,48.822277],"type":"Point"}
}