{
  "type": "Feature",
  "properties": {
    "addr:full":"136 Avenue Jean Mermoz 33320 Eysines Eysines Aquitaine 33320",
    "addr:housenumber":"136",
    "addr:postcode":"33320;33320",
    "addr:street":"Avenue Jean Mermoz",
    "iso:country":"FR",
    "sg:address":"136 Avenue Jean Mermoz 33320 Eysines",
    "sg:city":"Eysines",
    "sg:classifiers":[
        {
            "category":"Bakery",
            "type":"Food & Drink"
        }
    ],
    "sg:phone":"+33 5 56 57 80 59",
    "sg:postcode":"33320",
    "sg:province":"Aquitaine",
    "sg:tags":[
        "cake",
        "product",
        "related",
        "bread"
    ],
    "wof:name":"Maitetxu",
    "wof:placetype":"venue"
},
  "geometry": {"coordinates":[-0.663649,44.86705],"type":"Point"}
}