{
  "type": "Feature",
  "properties": {
    "addr:full":"Quai Ranconnet 26260 Marges Rhone-Alpes 26260",
    "addr:postcode":"26260;26260",
    "addr:street":"Quai Ranconnet",
    "iso:country":"FR",
    "sg:address":"Quai Ranconnet 26260 Marges",
    "sg:classifiers":[
        {
            "category":"Home & Garden",
            "subcategory":"Furniture",
            "type":"Retail Goods"
        }
    ],
    "sg:phone":"+33 4 75 45 60 34",
    "sg:postcode":"26260",
    "sg:province":"Rhone-Alpes",
    "sg:tags":[
        "wood"
    ],
    "wof:name":"Etablissements Didier Freres",
    "wof:placetype":"venue"
},
  "geometry": {"coordinates":[5.033158,45.134609],"type":"Point"}
}