{
  "type": "Feature",
  "properties": {
    "addr:full":"Creissels 12100 Millau Midi Pyr\u00e9n\u00e9es",
    "addr:postcode":"12100",
    "iso:country":"FR",
    "sg:address":"Creissels 12100 Millau",
    "sg:orig_category":"Unclassifiable Establishments",
    "sg:phone":"+33 5 65 59 26 00",
    "sg:province":"Midi Pyr\u00e9n\u00e9es",
    "wof:name":"Megisserie Richard S.a.r.l.",
    "wof:placetype":"venue"
},
  "geometry": {"coordinates":[3.06317,44.087101],"type":"Point"}
}