{
  "type": "Feature",
  "properties": {
    "iso:country":"FR",
    "sg:address":"ZA de Vraux",
    "sg:city":"Vraux",
    "sg:orig_category":"Non-Classified Establishments",
    "sg:phone":"+33 3 26 67 91 07",
    "sg:postcode":"51150",
    "sg:province":"Champagne",
    "wof:name":"Poly Champagne S.a.r.l.",
    "wof:placetype":"venue"
},
  "geometry": {"coordinates":[4.237321,49.028145],"type":"Point"}
}