{
  "type": "Feature",
  "properties": {
    "iso:country":"FR",
    "sg:address":"Parc Activites Tournebride 44118 La Chevroliere",
    "sg:classifiers":[
        {
            "category":"Professional",
            "subcategory":"Engineering",
            "type":"Services"
        }
    ],
    "sg:phone":"+33 2 51 70 91 70",
    "sg:postcode":"44118",
    "sg:province":"Pays de Loire",
    "sg:tags":[
        "machine",
        "-",
        "mechanical"
    ],
    "wof:name":"Dto Sa",
    "wof:placetype":"venue"
},
  "geometry": {"coordinates":[-1.566585,47.079666],"type":"Point"}
}