{
  "type": "Feature",
  "properties": {
    "addr:full":"4, Rue Roger Bacon, 75017 Paris Ile de France 75017",
    "addr:housenumber":"4",
    "addr:postcode":"75017;75017",
    "addr:street":"Rue Roger Bacon",
    "iso:country":"FR",
    "sg:address":"4, Rue Roger Bacon, 75017 Paris",
    "sg:orig_category":"Non-Classified Establishments",
    "sg:phone":"+33 1 55 37 23 23",
    "sg:postcode":"75017",
    "sg:province":"Ile de France",
    "wof:name":"Atelier Industria S.a.",
    "wof:placetype":"venue"
},
  "geometry": {"coordinates":[2.289047,48.882256],"type":"Point"}
}