{
  "type": "Feature",
  "properties": {
    "addr:full":"Morgon 69910 Villi\u00e9 Morgon Rhone-Alpes 69910",
    "addr:postcode":"69910;69910",
    "addr:street":"Morgon;Rhone-Alpes",
    "iso:country":"FR",
    "sg:address":"Morgon 69910 Villi\u00e9 Morgon",
    "sg:orig_category":"Unclassifiable Establishments",
    "sg:phone":"+33 4 74 69 10 20",
    "sg:postcode":"69910",
    "sg:province":"Rhone-Alpes",
    "wof:name":"Piron Pierre Et Dominique S.a.r.l.",
    "wof:placetype":"venue"
},
  "geometry": {"coordinates":[4.675069,46.147202],"type":"Point"}
}