{
  "type": "Feature",
  "properties": {
    "iso:country":"FR",
    "sg:address":"6 all\u00e9e Megevie 33170 Gradignan",
    "sg:city":"Gradignan",
    "sg:classifiers":[
        {
            "category":"Professional",
            "subcategory":"Employment Agencies",
            "type":"Services"
        }
    ],
    "sg:phone":"+33 5 56 75 01 01",
    "sg:postcode":"33170",
    "sg:province":"Aquitaine",
    "sg:tags":[
        "import"
    ],
    "wof:name":"Sarl Feuillazur Bordeaux",
    "wof:placetype":"venue"
},
  "geometry": {"coordinates":[-0.639745,44.774422],"type":"Point"}
}