{
  "type": "Feature",
  "properties": {
    "iso:country":"FR",
    "sg:address":"B.P. 229, 84306 Cavaillon C\u00e9dex^^Av. Pierre Semard - Halte Routi\u00e8re, 84300 Cavaillon",
    "sg:orig_category":"Non-Classified Establishments",
    "sg:phone":"+33 4 90 06 64 64",
    "sg:province":"Languedoc-Roussillon",
    "wof:name":"Autocars Barlatier S.a.",
    "wof:placetype":"venue"
},
  "geometry": {"coordinates":[5.039415,43.837685],"type":"Point"}
}