{
  "type": "Feature",
  "properties": {
    "addr:full":"88 Rue Du 26 Mars 1944 24600 Riberac Rib\u00e9rac Aquitaine 24600",
    "addr:housenumber":"88",
    "addr:postcode":"24600;24600",
    "addr:street":"Rue Du 26 Mars 1944",
    "iso:country":"FR",
    "sg:address":"88 Rue Du 26 Mars 1944 24600 Riberac",
    "sg:city":"Rib\u00e9rac",
    "sg:classifiers":[
        {
            "category":"Home & Garden",
            "subcategory":"Building Materials",
            "type":"Retail Goods"
        }
    ],
    "sg:phone":"+33 5 53 90 07 35",
    "sg:postcode":"24600",
    "sg:province":"Aquitaine",
    "sg:tags":[
        "equipment",
        "energy",
        "-",
        "environment",
        "raw",
        "machinery"
    ],
    "wof:name":"Ssogedo",
    "wof:placetype":"venue"
},
  "geometry": {"coordinates":[0.393947,45.204483],"type":"Point"}
}