{
  "type": "Feature",
  "properties": {
    "addr:full":"98 Route Thann 68130 Aspach Aspach Alsace 68130",
    "addr:housenumber":"98",
    "addr:postcode":"68130;68130",
    "addr:street":"Route Thann",
    "iso:country":"FR",
    "sg:address":"98 Route Thann 68130 Aspach",
    "sg:city":"Aspach",
    "sg:classifiers":[
        {
            "category":"Shopping",
            "subcategory":"Stationery & Office Supplies",
            "type":"Retail Goods"
        }
    ],
    "sg:phone":"+33 3 89 40 95 44",
    "sg:postcode":"68130",
    "sg:province":"Alsace",
    "sg:tags":[
        "information",
        "technology",
        "telecommunication",
        "equipment"
    ],
    "wof:name":"Ets Ellenbach Sarl",
    "wof:placetype":"venue"
},
  "geometry": {"coordinates":[7.227571,47.650066],"type":"Point"}
}