{
  "type": "Feature",
  "properties": {
    "addr:full":"35, Rue Alexandre Dumas, 80094 Amiens Picardie",
    "addr:housenumber":"35;80094",
    "addr:street":"Rue Alexandre Dumas",
    "iso:country":"FR",
    "sg:address":"35, Rue Alexandre Dumas, 80094 Amiens",
    "sg:orig_category":"Non-Classified Establishments",
    "sg:phone":"+33 3 22 53 56 59",
    "sg:province":"Picardie",
    "wof:name":"O.c.e.a. - Office Comptabilit\u00e9 Economie Amiens",
    "wof:placetype":"venue"
},
  "geometry": {"coordinates":[2.303435,49.870903],"type":"Point"}
}