{
  "type": "Feature",
  "properties": {
    "iso:country":"FR",
    "sg:address":"ZI Madraz\u00e8s",
    "sg:city":"Sarlat la Can\u00e9da",
    "sg:orig_category":"Unclassifiable Establishments",
    "sg:phone":"+33 5 53 31 58 58",
    "sg:postcode":"24200",
    "sg:province":"Aquitaine",
    "wof:name":"Iperbois S.a.",
    "wof:placetype":"venue"
},
  "geometry": {"coordinates":[1.21522,44.891651],"type":"Point"}
}