{
  "type": "Feature",
  "properties": {
    "iso:country":"FR",
    "sg:address":"81 Rue Carnot 94700 Maisons Alfort",
    "sg:classifiers":[
        {
            "category":"Autos & Motor Vehicles",
            "subcategory":"Automobile Sales",
            "type":"Retail Goods"
        }
    ],
    "sg:phone":"+33 1 46 76 21 43",
    "sg:postcode":"94700",
    "sg:province":"Ile de France",
    "sg:tags":[
        "equipment",
        "motor-cars",
        "transport"
    ],
    "wof:name":"Delphi France Sas",
    "wof:placetype":"venue"
},
  "geometry": {"coordinates":[2.440531,48.80481],"type":"Point"}
}