{
  "type": "Feature",
  "properties": {
    "addr:full":"82, Rue du Landy, 93200 Saint Denis Ile de France",
    "addr:housenumber":"82",
    "addr:postcode":"93200",
    "addr:street":"Rue Du Landy",
    "iso:country":"FR",
    "sg:address":"82, Rue du Landy, 93200 Saint Denis",
    "sg:orig_category":"Unclassifiable Establishments",
    "sg:phone":"+33 1 48 20 59 05",
    "sg:province":"Ile de France",
    "wof:name":"Brasilia S.a.",
    "wof:placetype":"venue"
},
  "geometry": {"coordinates":[2.34411,48.914059],"type":"Point"}
}