{
  "type": "Feature",
  "properties": {
    "addr:full":"Chem De Bouttes 11100 Narbonne Languedoc-Roussillon 11100",
    "addr:postcode":"11100;11100",
    "addr:street":"Chem",
    "iso:country":"FR",
    "sg:address":"Chem De Bouttes 11100 Narbonne",
    "sg:classifiers":[
        {
            "category":"Home & Garden",
            "subcategory":"Furniture",
            "type":"Retail Goods"
        }
    ],
    "sg:phone":"+33 4 68 41 51 68",
    "sg:postcode":"11100",
    "sg:province":"Languedoc-Roussillon",
    "sg:tags":[
        "household",
        "wood"
    ],
    "wof:name":"Encadrements Artistiques Europeennes",
    "wof:placetype":"venue"
},
  "geometry": {"coordinates":[3.005285,43.209045],"type":"Point"}
}