{
  "type": "Feature",
  "properties": {
    "addr:full":"rue Ilet 51520 St Martin sur le Pr\u00e9 Champagne",
    "addr:postcode":"51520",
    "addr:street":"Rue Ilet;Sur Le Pre\u0301 Champagne",
    "iso:country":"FR",
    "sg:address":"rue Ilet 51520 St Martin sur le Pr\u00e9",
    "sg:classifiers":[
        {
            "category":"Structure",
            "subcategory":"Building",
            "type":"Public Place"
        }
    ],
    "sg:phone":"+33 3 26 69 25 69",
    "sg:province":"Champagne",
    "sg:tags":[
        "attic",
        "addition",
        "finishing",
        "roof",
        "trusses"
    ],
    "wof:name":"Poreaux Et Cie Sa",
    "wof:placetype":"venue"
},
  "geometry": {"coordinates":[4.345474,48.97657],"type":"Point"}
}