{
  "type": "Feature",
  "properties": {
    "iso:country":"FR",
    "sg:address":"Rue Fourny - ZI 606",
    "sg:city":"Buc",
    "sg:orig_category":"Unclassifiable Establishments",
    "sg:phone":"+33 1 39 67 67 67",
    "sg:postcode":"78530",
    "sg:province":"Ile de France",
    "wof:name":"M.b. Electronique S.a.",
    "wof:placetype":"venue"
},
  "geometry": {"coordinates":[2.126343,48.774464],"type":"Point"}
}