{
  "type": "Feature",
  "properties": {
    "addr:full":"61-63 Av Aristide Briand 94230 Cachan Ile de France 94230",
    "addr:housenumber":"61-63",
    "addr:postcode":"94230;ile;94230",
    "addr:street":"Av Aristide Briand;France",
    "iso:country":"FR",
    "sg:address":"61-63 Av Aristide Briand 94230 Cachan",
    "sg:classifiers":[
        {
            "category":"Shopping",
            "subcategory":"Computers & Home Electronics",
            "type":"Retail Goods"
        }
    ],
    "sg:phone":"+33 1 46 65 30 11",
    "sg:postcode":"94230",
    "sg:province":"Ile de France",
    "sg:tags":[
        "household",
        "appliance",
        "telecommunication",
        "audio-visual"
    ],
    "wof:name":"Sud Electronic",
    "wof:placetype":"venue"
},
  "geometry": {"coordinates":[2.323118,48.798962],"type":"Point"}
}