{
  "type": "Feature",
  "properties": {
    "iso:country":"FR",
    "sg:address":"Hangar 17 - Cap Janet",
    "sg:city":"Marseille C\u00e9dex 15",
    "sg:orig_category":"Non-Classified Establishments",
    "sg:phone":"+33 4 91 03 29 92",
    "sg:postcode":"13344",
    "sg:province":"Provence-Alpes-C\u00f4te d'Azur",
    "wof:name":"Perosol S.a.",
    "wof:placetype":"venue"
},
  "geometry": {"coordinates":[5.36491,43.35313],"type":"Point"}
}