{
  "type": "Feature",
  "properties": {
    "iso:country":"FR",
    "sg:address":"14, Rue Saint Gilles - ZI, 28800 Bonneval",
    "sg:city":"Bonneval",
    "sg:orig_category":"Unclassifiable Establishments",
    "sg:phone":"+33 2 37 44 58 58",
    "sg:postcode":"28800",
    "sg:province":"Centre",
    "wof:name":"Agralys Aliments S.a.",
    "wof:placetype":"venue"
},
  "geometry": {"coordinates":[1.49009,48.133808],"type":"Point"}
}