{
  "type": "Feature",
  "properties": {
    "addr:full":"RN 41 Sailly labourse Nord Pas-de-Calais 62113",
    "addr:postcode":"62113",
    "addr:street":"Rn 41",
    "iso:country":"FR",
    "sg:address":"RN 41",
    "sg:city":"Sailly labourse",
    "sg:orig_category":"Unclassifiable Establishments",
    "sg:phone":"+33 2 31 52 10 10",
    "sg:postcode":"62113",
    "sg:province":"Nord Pas-de-Calais",
    "wof:name":"T.c.i.a. S.a.r.l. - Tuyauterie Chaudronnerie Industrielle Alciaquoise",
    "wof:placetype":"venue"
},
  "geometry": {"coordinates":[2.696664,50.500561],"type":"Point"}
}