{
  "type": "Feature",
  "properties": {
    "addr:full":"rue des Garennes 01602 Trevoux Aquitaine",
    "addr:postcode":"01602",
    "addr:street":"Rue Des Garennes",
    "iso:country":"FR",
    "sg:address":"rue des Garennes 01602 Trevoux",
    "sg:classifiers":[
        {
            "category":"Building & Trades",
            "subcategory":"Construction",
            "type":"Services"
        }
    ],
    "sg:phone":"+33 4 74 00 20 60",
    "sg:province":"Aquitaine",
    "sg:tags":[
        "stair"
    ],
    "wof:name":"Plasse Sa",
    "wof:placetype":"venue"
},
  "geometry": {"coordinates":[4.77654,45.940369],"type":"Point"}
}