{
  "type": "Feature",
  "properties": {
    "addr:full":"Rue Charles Tellier - Z.I. Caminasse B\u00e8gles Aquitaine 33130",
    "addr:housenumber":"z.i.",
    "addr:postcode":"33130",
    "addr:street":"Rue Charles Tellier",
    "iso:country":"FR",
    "sg:address":"Rue Charles Tellier - Z.I. Caminasse",
    "sg:city":"B\u00e8gles",
    "sg:orig_category":"Non-Classified Establishments",
    "sg:phone":"+33 5 56 49 00 30",
    "sg:postcode":"33130",
    "sg:province":"Aquitaine",
    "wof:name":"P.m.s.o. S.a.",
    "wof:placetype":"venue"
},
  "geometry": {"coordinates":[-0.553904,44.808079],"type":"Point"}
}