{
  "type": "Feature",
  "properties": {
    "addr:full":"1 Boulevard Frederic Sauvage 13014 Marseille Poitou-Charentes",
    "addr:housenumber":"1",
    "addr:postcode":"13014",
    "addr:street":"Boulevard Frederic Sauvage",
    "iso:country":"FR",
    "sg:address":"1 Boulevard Frederic Sauvage 13014 Marseille",
    "sg:classifiers":[
        {
            "category":"Professional",
            "subcategory":"Engineering",
            "type":"Services"
        }
    ],
    "sg:phone":"+33 4 95 05 11 04",
    "sg:province":"Poitou-Charentes",
    "sg:tags":[
        "machine",
        "-",
        "mechanical"
    ],
    "wof:name":"Trane",
    "wof:placetype":"venue"
},
  "geometry": {"coordinates":[5.369304,43.335625],"type":"Point"}
}