{
  "type": "Feature",
  "properties": {
    "iso:country":"FR",
    "sg:address":"ZA Les 10 Muids",
    "sg:city":"Marly C\u00e9dex",
    "sg:orig_category":"Unclassifiable Establishments",
    "sg:phone":"+33 3 27 28 23 50",
    "sg:postcode":"59583",
    "sg:province":"Lorraine",
    "wof:name":"Dmv Sovalec S.a.",
    "wof:placetype":"venue"
},
  "geometry": {"coordinates":[3.54824,50.34108],"type":"Point"}
}