{
  "type": "Feature",
  "properties": {
    "addr:full":"2, Av. de la Noue - Esplanade Lucien Barri\u00e8re, 44500 La Baule Escoublac Pays de Loire",
    "addr:postcode":"44500",
    "addr:street":"Av. De La Noue Esplanade Lucien Barrie\u0300Re",
    "iso:country":"FR",
    "sg:address":"2, Av. de la Noue - Esplanade Lucien Barri\u00e8re, 44500 La Baule Escoublac",
    "sg:orig_category":"Unclassifiable Establishments",
    "sg:phone":"+33 2 40 60 24 86",
    "sg:province":"Pays de Loire",
    "wof:name":"H\u00f4tel Majestic",
    "wof:placetype":"venue"
},
  "geometry": {"coordinates":[-2.391584,47.281715],"type":"Point"}
}