{
  "type": "Feature",
  "properties": {
    "addr:full":"B.P. 1525, 68015 Colmar C\u00e9dex^^5A, Rue Lavoisier, 68000 Colmar Colmar Alsace 68000",
    "addr:postcode":"68015;68000;68000",
    "addr:street":"B.P. 1525;Rue Lavoisier",
    "iso:country":"FR",
    "sg:address":"B.P. 1525, 68015 Colmar C\u00e9dex^^5A, Rue Lavoisier, 68000 Colmar",
    "sg:city":"Colmar",
    "sg:orig_category":"Non-Classified Establishments",
    "sg:phone":"+33 3 89 41 74 61",
    "sg:postcode":"68000",
    "sg:province":"Alsace",
    "wof:name":"Bioforce France S.a.r.l.",
    "wof:placetype":"venue"
},
  "geometry": {"coordinates":[7.363583,48.081985],"type":"Point"}
}