{
  "type": "Feature",
  "properties": {
    "addr:full":"Rue Jean Pierre Timbaud 95190 Goussainville Ile de France 95190",
    "addr:postcode":"95190;95190",
    "addr:street":"Rue Jean Pierre Timbaud",
    "iso:country":"FR",
    "sg:address":"Rue Jean Pierre Timbaud 95190 Goussainville",
    "sg:classifiers":[
        {
            "category":"Transit Center",
            "subcategory":"Freight",
            "type":"Transportation"
        }
    ],
    "sg:phone":"+33 1 39 88 68 00",
    "sg:postcode":"95190",
    "sg:province":"Ile de France",
    "sg:tags":[
        "metallurgy",
        "pipe",
        "metalworking",
        "sheet"
    ],
    "wof:name":"Cqft (sa)",
    "wof:placetype":"venue"
},
  "geometry": {"coordinates":[2.450305,49.021255],"type":"Point"}
}