{
  "type": "Feature",
  "properties": {
    "addr:full":"25330 Flagey Franche Comt\u00e9 25330",
    "addr:postcode":"25330;25330",
    "addr:street":"Franche Comte\u0301",
    "iso:country":"FR",
    "sg:address":"25330 Flagey",
    "sg:classifiers":[
        {
            "category":"Farming",
            "subcategory":"Livestock Farm",
            "type":"Manufacturing & Wholesale Goods"
        }
    ],
    "sg:phone":"+33 3 81 86 58 56",
    "sg:postcode":"25330",
    "sg:province":"Franche Comt\u00e9",
    "sg:tags":[
        "agriculture"
    ],
    "wof:name":"Production Des Elevages Bourgon (peb)",
    "wof:placetype":"venue"
},
  "geometry": {"coordinates":[6.12531,47.035515],"type":"Point"}
}