{
  "type": "Feature",
  "properties": {
    "iso:country":"FR",
    "sg:address":"12 Rue Jean Solvain 43000 Le Puy En Velay",
    "sg:city":"Le Puy-en-Velay",
    "sg:classifiers":[
        {
            "category":"Professional",
            "type":"Services"
        }
    ],
    "sg:phone":"+33 4 71 09 69 56",
    "sg:postcode":"43000",
    "sg:province":"Auvergne",
    "sg:tags":[
        "transport",
        "road"
    ],
    "wof:name":"Sarl Pierre Chanut Les Demenageurs Bretons",
    "wof:placetype":"venue"
},
  "geometry": {"coordinates":[3.892827,45.044754],"type":"Point"}
}