{
  "type": "Feature",
  "properties": {
    "iso:country":"FR",
    "sg:address":"B.P. 501, 77015 Melun c\u00e9dex^^1, Rue Foch - ZI Vaux le P\u00e9nil, 77000 Vaux le P\u00e9nil",
    "sg:orig_category":"Non-Classified Establishments",
    "sg:phone":"+33 1 64 10 48 80",
    "sg:province":"Ile de France",
    "wof:name":"Etablissements Paillard S.a.",
    "wof:placetype":"venue"
},
  "geometry": {"coordinates":[2.664085,48.539577],"type":"Point"}
}