{
  "type": "Feature",
  "properties": {
    "addr:full":"23, Av. de Lourdes, 65310 Odos Midi Pyr\u00e9n\u00e9es",
    "addr:postcode":"65310",
    "addr:street":"23 Av. De Lourdes",
    "iso:country":"FR",
    "sg:address":"23, Av. de Lourdes, 65310 Odos",
    "sg:orig_category":"Unclassifiable Establishments",
    "sg:phone":"+33 5 62 44 02 02",
    "sg:province":"Midi Pyr\u00e9n\u00e9es",
    "wof:name":"Soci\u00e9t\u00e9 Commerciale Tout\u00e9lectric S.a.",
    "wof:placetype":"venue"
},
  "geometry": {"coordinates":[0.05222,43.214081],"type":"Point"}
}