{
  "type": "Feature",
  "properties": {
    "iso:country":"FR",
    "sg:address":"4 Imp Plez Postry BP 18 59540 Caudry",
    "sg:classifiers":[
        {
            "category":"Shopping",
            "subcategory":"Crafts & Fabrics",
            "type":"Retail Goods"
        }
    ],
    "sg:phone":"+33 3 27 85 11 50",
    "sg:postcode":"59540",
    "sg:province":"Nord Pas-de-Calais",
    "sg:tags":[
        "textile",
        "clothing"
    ],
    "wof:name":"Knecht Bancourt Sarl",
    "wof:placetype":"venue"
},
  "geometry": {"coordinates":[3.412677,50.12006],"type":"Point"}
}