{
  "type": "Feature",
  "properties": {
    "addr:full":"Rn 751 37700 St Pierre Des Corps Cedex La Ville-aux-Dames Centre 37700",
    "addr:postcode":"37700;37700",
    "addr:street":"Rn 751;St Pierre Des Corps Cedex",
    "iso:country":"FR",
    "sg:address":"Rn 751 37700 St Pierre Des Corps Cedex",
    "sg:city":"La Ville-aux-Dames",
    "sg:classifiers":[
        {
            "category":"Manufacturing",
            "subcategory":"Rubber & Plastics",
            "type":"Manufacturing & Wholesale Goods"
        }
    ],
    "sg:phone":"+33 2 47 32 38 00",
    "sg:postcode":"37700",
    "sg:province":"Centre",
    "sg:tags":[
        "packaging",
        "material",
        "-"
    ],
    "wof:name":"Societe Metallurgique Liotard Freres",
    "wof:placetype":"venue"
},
  "geometry": {"coordinates":[0.718755,47.389648],"type":"Point"}
}