{
  "type": "Feature",
  "properties": {
    "addr:full":"route de Jouques 83560 Rians Basse Normandie",
    "addr:postcode":"83560",
    "addr:street":"Route De Jouques;Basse Normandie",
    "iso:country":"FR",
    "sg:address":"route de Jouques 83560 Rians",
    "sg:classifiers":[
        {
            "category":"Wholesale",
            "subcategory":"Wine & Distilled Alcoholic Beverages",
            "type":"Manufacturing & Wholesale Goods"
        }
    ],
    "sg:phone":"+33 4 94 37 21 10",
    "sg:province":"Basse Normandie",
    "sg:tags":[
        "french"
    ],
    "wof:name":"Vignelaure Sa",
    "wof:placetype":"venue"
},
  "geometry": {"coordinates":[5.81047,43.592949],"type":"Point"}
}