{
  "type": "Feature",
  "properties": {
    "addr:full":"Chemin De Lortenia 64200 Arcangues Arcangues Aquitaine 64200",
    "addr:postcode":"64200;64200",
    "addr:street":"Chemin De Lortenia",
    "iso:country":"FR",
    "sg:address":"Chemin De Lortenia 64200 Arcangues",
    "sg:city":"Arcangues",
    "sg:classifiers":[
        {
            "category":"Food & Beverages",
            "subcategory":"Groceries & Convenience Stores",
            "type":"Retail Goods"
        }
    ],
    "sg:phone":"+33 5 59 43 13 43",
    "sg:postcode":"64200",
    "sg:province":"Aquitaine",
    "sg:tags":[
        "product",
        "related"
    ],
    "wof:name":"Armand Gaboriau Et Fils",
    "wof:placetype":"venue"
},
  "geometry": {"coordinates":[-1.525823,43.45282],"type":"Point"}
}