{
  "type": "Feature",
  "properties": {
    "iso:country":"FR",
    "sg:address":"49 Rue Marrel Bertholon 42800 St Martin La Plaine",
    "sg:classifiers":[
        {
            "category":"Manufacturing",
            "subcategory":"Metals",
            "type":"Manufacturing & Wholesale Goods"
        }
    ],
    "sg:phone":"+33 4 77 83 65 08",
    "sg:province":"Rhone-Alpes",
    "sg:tags":[
        "metallurgy",
        "metalworking",
        "processing"
    ],
    "wof:name":"Tandem Batiment Smart",
    "wof:placetype":"venue"
},
  "geometry": {"coordinates":[4.591924,45.544525],"type":"Point"}
}