{
  "type": "Feature",
  "properties": {
    "addr:full":"43 Rue Sainte Genevieve 27203 Vernon Cedex Haute-Normandie",
    "addr:housenumber":"43",
    "addr:postcode":"27203;cedex",
    "addr:street":"Rue Sainte Genevieve",
    "iso:country":"FR",
    "sg:address":"43 Rue Sainte Genevieve 27203 Vernon Cedex",
    "sg:classifiers":[
        {
            "category":"Utilities",
            "subcategory":"Telephone",
            "type":"Services"
        }
    ],
    "sg:phone":"+33 2 32 64 54 54",
    "sg:province":"Haute-Normandie",
    "sg:tags":[
        "telecommunication"
    ],
    "wof:name":"Ouest Telecom",
    "wof:placetype":"venue"
},
  "geometry": {"coordinates":[1.48399,49.092865],"type":"Point"}
}