{
  "type": "Feature",
  "properties": {
    "iso:country":"FR",
    "sg:address":"1, Rue du Tertre - Z.I. de Nantes Carquefou, 44470 Carquefou",
    "sg:orig_category":"Unclassifiable Establishments",
    "sg:phone":"+33 2 40 68 63 91",
    "sg:province":"Pays de Loire",
    "wof:name":"Modyn S.a. - Moulage Dynamique",
    "wof:placetype":"venue"
},
  "geometry": {"coordinates":[-1.440899,47.266781],"type":"Point"}
}