{
  "type": "Feature",
  "properties": {
    "addr:full":"ZI des Soustons Soustons Aquitaine 40141",
    "addr:postcode":"40141",
    "addr:street":"Des Soustons",
    "iso:country":"FR",
    "sg:address":"ZI des Soustons",
    "sg:city":"Soustons",
    "sg:orig_category":"Non-Classified Establishments",
    "sg:phone":"+33 5 58 49 99 30",
    "sg:postcode":"40141",
    "sg:province":"Aquitaine",
    "wof:name":"Cpi S.a.r.l. - Cork Product International",
    "wof:placetype":"venue"
},
  "geometry": {"coordinates":[-1.327244,43.755615],"type":"Point"}
}