{
  "type": "Feature",
  "properties": {
    "iso:country":"FR",
    "sg:address":"2, Av. de Montboulon - ZA du Sauvoy, 77165 Saint Soupplets",
    "sg:orig_category":"Unclassifiable Establishments",
    "sg:phone":"+33 1 60 61 67 67",
    "sg:province":"Ile de France",
    "wof:name":"Andr\u00e9 Laurent S.a.",
    "wof:placetype":"venue"
},
  "geometry": {"coordinates":[2.805387,49.039413],"type":"Point"}
}