{
  "type": "Feature",
  "properties": {
    "addr:full":"B.P. 18 Ouzouer sur Loire C\u00e9dex^^45570 Ouzouer sur Loire Centre 45570",
    "addr:postcode":"45570",
    "addr:street":"B.P. 18 Ouzouer Sur Loire;Ouzouer",
    "iso:country":"FR",
    "sg:address":"B.P. 18",
    "sg:city":"Ouzouer sur Loire C\u00e9dex^^45570 Ouzouer sur Loire",
    "sg:orig_category":"Non-Classified Establishments",
    "sg:phone":"+33 2 38 29 70 70",
    "sg:postcode":"45570",
    "sg:province":"Centre",
    "wof:name":"C.n.p.e. De Dampierre - Centrale Nucl\u00e9aire De Production D'electricit\u00e9",
    "wof:placetype":"venue"
},
  "geometry": {"coordinates":[2.479925,47.766441],"type":"Point"}
}