{
  "type": "Feature",
  "properties": {
    "addr:full":"Rte de Gilley Orchamps Vennes Franche Comt\u00e9 25390",
    "addr:postcode":"25390",
    "addr:street":"Rte De Gilley;Comte\u0301",
    "iso:country":"FR",
    "sg:address":"Rte de Gilley",
    "sg:city":"Orchamps Vennes",
    "sg:orig_category":"Non-Classified Establishments",
    "sg:phone":"+33 3 81 43 59 80",
    "sg:postcode":"25390",
    "sg:province":"Franche Comt\u00e9",
    "wof:name":"Philippe Cattet S.a.r.l.",
    "wof:placetype":"venue"
},
  "geometry": {"coordinates":[6.523946,47.126949],"type":"Point"}
}