{
  "type": "Feature",
  "properties": {
    "addr:full":"20C, Rue du G\u00e9n\u00e9ral Leclerc, 25200 Montb\u00e9liard Franche Comt\u00e9",
    "addr:housenumber":"20c",
    "addr:postcode":"25200",
    "addr:street":"Rue Du Ge\u0301Ne\u0301Ral Leclerc;Franche Comte\u0301",
    "iso:country":"FR",
    "sg:address":"20C, Rue du G\u00e9n\u00e9ral Leclerc, 25200 Montb\u00e9liard",
    "sg:orig_category":"Non-Classified Establishments",
    "sg:phone":"+33 3 81 31 22 49",
    "sg:province":"Franche Comt\u00e9",
    "wof:name":"Solmon",
    "wof:placetype":"venue"
},
  "geometry": {"coordinates":[6.79783,47.511971],"type":"Point"}
}