{
  "type": "Feature",
  "properties": {
    "addr:full":"All\u00e9e du Titane - Parc Technologique Orl\u00e9ans C\u00e9dex 2 Centre 45072",
    "addr:housenumber":"2",
    "addr:postcode":"45072",
    "addr:street":"Alle\u0301E Du Titane Parc Technologique",
    "iso:country":"FR",
    "sg:address":"All\u00e9e du Titane - Parc Technologique",
    "sg:city":"Orl\u00e9ans C\u00e9dex 2",
    "sg:orig_category":"Non-Classified Establishments",
    "sg:phone":"+33 2 38 69 57 57",
    "sg:postcode":"45072",
    "sg:province":"Centre",
    "wof:name":"Schneider Electric Industries S.a.",
    "wof:placetype":"venue"
},
  "geometry": {"coordinates":[1.940965,47.844856],"type":"Point"}
}