{
  "type": "Feature",
  "properties": {
    "iso:country":"FR",
    "sg:address":"4, Place de Londres - B\u00e2t. Saturne, 95700 Roissy en France",
    "sg:orig_category":"Unclassifiable Establishments",
    "sg:phone":"+33 1 48 62 52 90",
    "sg:province":"Ile de France",
    "wof:name":"Rabot Dutilleul Entreprise S.a.",
    "wof:placetype":"venue"
},
  "geometry": {"coordinates":[2.517005,49.003883],"type":"Point"}
}