{
  "type": "Feature",
  "properties": {
    "addr:full":"Z I La Sereine 01390 Saint Andr\u00e9 de Corcy Rhone-Alpes 01390",
    "addr:postcode":"01390;01390",
    "addr:street":"Z I La Sereine;Rhone-Alpes",
    "iso:country":"FR",
    "sg:address":"Z I La Sereine 01390 Saint Andr\u00e9 de Corcy",
    "sg:classifiers":[
        {
            "category":"Manufacturing",
            "subcategory":"Textiles",
            "type":"Manufacturing & Wholesale Goods"
        }
    ],
    "sg:phone":"+33 4 72 26 45 45",
    "sg:postcode":"01390",
    "sg:province":"Rhone-Alpes",
    "sg:tags":[
        "clothing",
        "accessory"
    ],
    "wof:name":"Marlybag",
    "wof:placetype":"venue"
},
  "geometry": {"coordinates":[4.93107,45.919559],"type":"Point"}
}