{
  "type": "Feature",
  "properties": {
    "iso:country":"FR",
    "sg:address":"Chemin Ajaccio A Appietto Quartier Mezzavia 20167 Mezzavia",
    "sg:classifiers":[
        {
            "category":"Food & Beverages",
            "subcategory":"Groceries & Convenience Stores",
            "type":"Retail Goods"
        }
    ],
    "sg:phone":"+33 4 95 22 41 91",
    "sg:postcode":"20167",
    "sg:province":"Corse",
    "sg:tags":[
        "product",
        "related"
    ],
    "wof:name":"Pates Fraiches Colomba (sarl)",
    "wof:placetype":"venue"
},
  "geometry": {"coordinates":[8.668294,41.959526],"type":"Point"}
}