{
  "type": "Feature",
  "properties": {
    "addr:full":"29 Av Qu\u00e9bec 26240 St Vallier Rhone-Alpes 26240",
    "addr:postcode":"26240;26240",
    "addr:street":"29 Av",
    "iso:country":"FR",
    "sg:address":"29 Av Qu\u00e9bec 26240 St Vallier",
    "sg:classifiers":[
        {
            "category":"Manufacturing",
            "subcategory":"Building Materials",
            "type":"Manufacturing & Wholesale Goods"
        }
    ],
    "sg:phone":"+33 4 75 23 88 88",
    "sg:postcode":"26240",
    "sg:province":"Rhone-Alpes",
    "sg:tags":[
        "glass",
        "ceramic"
    ],
    "wof:name":"Ceralep Sa",
    "wof:placetype":"venue"
},
  "geometry": {"coordinates":[4.836268,45.159122],"type":"Point"}
}