{
  "type": "Feature",
  "properties": {
    "iso:country":"FR",
    "sg:address":"18, Rue Saint Denis, 75001 Paris",
    "sg:orig_category":"Unclassifiable Establishments",
    "sg:phone":"+33 1 44 76 86 00",
    "sg:province":"Ile de France",
    "wof:name":"Jouve S.a.",
    "wof:placetype":"venue"
},
  "geometry": {"coordinates":[2.347994,48.859329],"type":"Point"}
}