{
  "type": "Feature",
  "properties": {
    "addr:full":"B.P. 18, 60270 Gouvieux^^77, Rue Corbier Thi\u00e9baut, 60270 Gouvieux Picardie 60270",
    "addr:postcode":"60270;60270;60270",
    "addr:street":"B.P. 18;Rue Corbier Thie\u0301Baut",
    "iso:country":"FR",
    "sg:address":"B.P. 18, 60270 Gouvieux^^77, Rue Corbier Thi\u00e9baut, 60270 Gouvieux",
    "sg:orig_category":"Non-Classified Establishments",
    "sg:phone":"+33 3 44 67 13 30",
    "sg:postcode":"60270",
    "sg:province":"Picardie",
    "wof:name":"Atelier M\u00e9canique De Gouvieux S.a.r.l.",
    "wof:placetype":"venue"
},
  "geometry": {"coordinates":[2.413886,49.184452],"type":"Point"}
}