{
  "type": "Feature",
  "properties": {
    "addr:full":"Rue Lavoisier Des Renardieres 21700 Nuits St Georges Bourgogne 21700",
    "addr:postcode":"21700;21700",
    "addr:street":"Rue Lavoisier Des Renardieres;Nuits",
    "iso:country":"FR",
    "sg:address":"Rue Lavoisier",
    "sg:city":"Des Renardieres 21700 Nuits St Georges",
    "sg:classifiers":[
        {
            "category":"Wholesale",
            "subcategory":"Meat",
            "type":"Manufacturing & Wholesale Goods"
        }
    ],
    "sg:phone":"+33 3 80 61 19 38",
    "sg:postcode":"21700",
    "sg:province":"Bourgogne",
    "sg:tags":[
        "food",
        "cooked",
        "product",
        "related"
    ],
    "wof:name":"Au Jambon De Bourgogne",
    "wof:placetype":"venue"
},
  "geometry": {"coordinates":[4.962984,47.12352],"type":"Point"}
}