{
  "type": "Feature",
  "properties": {
    "addr:full":"Za Les 2 B La Valbonne 01360 B\u00e9ligneux La Valbonne Rhone-Alpes 01360",
    "addr:housenumber":"2 b",
    "addr:postcode":"01360;01360",
    "addr:street":"Za Les;La Valbonne",
    "iso:country":"FR",
    "sg:address":"Za Les 2 B La Valbonne 01360 B\u00e9ligneux La Valbonne",
    "sg:classifiers":[
        {
            "category":"Utilities",
            "subcategory":"Electric",
            "type":"Services"
        }
    ],
    "sg:phone":"+33 4 78 06 57 57",
    "sg:postcode":"01360",
    "sg:province":"Rhone-Alpes",
    "sg:tags":[
        "electricity",
        "electronic",
        "electrical",
        "equipment"
    ],
    "wof:name":"Sovicam Sarl",
    "wof:placetype":"venue"
},
  "geometry": {"coordinates":[5.120386,45.829571],"type":"Point"}
}