{
  "type": "Feature",
  "properties": {
    "addr:full":"Za Le Landreau 85130 La Verrie Pays de Loire",
    "addr:postcode":"85130",
    "addr:street":"Za Le Landreau;Verrie",
    "iso:country":"FR",
    "sg:address":"Za Le Landreau 85130 La Verrie",
    "sg:classifiers":[
        {
            "category":"Professional",
            "type":"Services"
        }
    ],
    "sg:phone":"+33 2 51 66 56 56",
    "sg:province":"Pays de Loire",
    "sg:tags":[
        "transport",
        "road"
    ],
    "wof:name":"Societe Des Transports Graveleau Sa",
    "wof:placetype":"venue"
},
  "geometry": {"coordinates":[-0.993547,46.965427],"type":"Point"}
}