{
  "type": "Feature",
  "properties": {
    "iso:country":"FR",
    "sg:address":"9 Grande Rue 37120 Richelieu",
    "sg:city":"Richelieu",
    "sg:classifiers":[
        {
            "category":"Banks & Credit Unions",
            "subcategory":"Financial Services",
            "type":"Services"
        }
    ],
    "sg:phone":"+33 2 47 93 68 68",
    "sg:postcode":"37120",
    "sg:province":"Centre",
    "sg:tags":[
        "banking",
        "finance",
        "insurance"
    ],
    "wof:name":"Tap Assurances",
    "wof:placetype":"venue"
},
  "geometry": {"coordinates":[0.324094,47.013519],"type":"Point"}
}