{
  "type": "Feature",
  "properties": {
    "iso:country":"FR",
    "sg:address":"11, Bd de l'Engrenier - ZI de la Grand'Colle, 13110 Port de Bouc",
    "sg:orig_category":"Non-Classified Establishments",
    "sg:phone":"+33 4 42 06 02 02",
    "sg:province":"Centre",
    "wof:name":"C.t.p.",
    "wof:placetype":"venue"
},
  "geometry": {"coordinates":[4.986919,43.420143],"type":"Point"}
}