{
  "type": "Feature",
  "properties": {
    "iso:country":"FR",
    "sg:address":"59, Av. Marguerit Renaudin, 92140 Clamart",
    "sg:orig_category":"Unclassifiable Establishments",
    "sg:phone":"+33 1 55 95 71 22",
    "sg:province":"Ile de France",
    "wof:name":"R.c. Entreprise S.a.r.l.",
    "wof:placetype":"venue"
},
  "geometry": {"coordinates":[2.272635,48.804127],"type":"Point"}
}