{
  "type": "Feature",
  "properties": {
    "addr:full":"B.P. 60, 21702 Nuits Saint Georges C\u00e9dex^^Av du Jura - Zone Industrielle, 21700 Nuits Saint Georges Agencourt Bourgogne 21700",
    "addr:postcode":"21702;21700;21700",
    "addr:street":"B.P. 60;Zone Industrielle;Bourgogne",
    "iso:country":"FR",
    "sg:address":"B.P. 60, 21702 Nuits Saint Georges C\u00e9dex^^Av du Jura - Zone Industrielle, 21700 Nuits Saint Georges",
    "sg:city":"Agencourt",
    "sg:orig_category":"Non-Classified Establishments",
    "sg:phone":"+33 3 80 61 12 36",
    "sg:postcode":"21700",
    "sg:province":"Bourgogne",
    "wof:name":"Socar Parnalland S.a.",
    "wof:placetype":"venue"
},
  "geometry": {"coordinates":[4.960159,47.12648],"type":"Point"}
}