{
  "type": "Feature",
  "properties": {
    "iso:country":"FR",
    "sg:address":"5 Rue Paul Gauguin Zac Des Luats 94354 Villiers Sur Marne Cedex",
    "sg:classifiers":[
        {
            "category":"Government",
            "subcategory":"Department Of Motor Vehicles",
            "type":"Public Place"
        }
    ],
    "sg:phone":"+33 1 49 41 22 90",
    "sg:province":"Midi Pyr\u00e9n\u00e9es",
    "sg:tags":[
        "equipment",
        "industrial",
        "transport",
        "motor-cars"
    ],
    "wof:name":"Euraltech Rambure",
    "wof:placetype":"venue"
},
  "geometry": {"coordinates":[2.540365,48.826324],"type":"Point"}
}