{
  "type": "Feature",
  "properties": {
    "iso:country":"FR",
    "sg:address":"171 Av G\u00e9n\u00e9ral Pruneau 83000 Toulon",
    "sg:classifiers":[
        {
            "category":"Autos & Motor Vehicles",
            "subcategory":"Automobile Sales",
            "type":"Retail Goods"
        }
    ],
    "sg:phone":"+33 4 94 41 18 14",
    "sg:province":"Pays de Loire",
    "sg:tags":[
        "equipment",
        "motor-cars",
        "transport"
    ],
    "wof:name":"Autorex Sarl",
    "wof:placetype":"venue"
},
  "geometry": {"coordinates":[5.955693,43.121059],"type":"Point"}
}