{
  "type": "Feature",
  "properties": {
    "iso:country":"FR",
    "sg:address":"27 rue Sebastien Guiziou; Loctudy",
    "sg:city":"Loctudy",
    "sg:classifiers":[
        {
            "category":"Banks & Credit Unions",
            "subcategory":"Bank",
            "type":"Services"
        }
    ],
    "sg:phone":"+33 3398879636",
    "sg:postcode":"29750",
    "sg:province":"Bretagne",
    "wof:name":"Cr\u00e9dit Mutuel De Bretagne",
    "wof:placetype":"venue"
},
  "geometry": {"coordinates":[-4.175847,47.832073],"type":"Point"}
}