{
  "type": "Feature",
  "properties": {
    "iso:country":"FR",
    "sg:address":"B.P. 12, 68870 Bartenheim^^15, Rue de Huningue, 68870 Bartenheim",
    "sg:city":"Bartenheim",
    "sg:orig_category":"Non-Classified Establishments",
    "sg:phone":"+33 3 89 68 34 85",
    "sg:postcode":"68870",
    "sg:province":"Alsace",
    "wof:name":"Vlym S.a.",
    "wof:placetype":"venue"
},
  "geometry": {"coordinates":[7.477075,47.633919],"type":"Point"}
}