{
  "type": "Feature",
  "properties": {
    "iso:country":"FR",
    "sg:address":"Av Montaigne",
    "sg:city":"Carvin",
    "sg:orig_category":"Unclassifiable Establishments",
    "sg:phone":"+33 3 21 74 74 00",
    "sg:postcode":"62220",
    "sg:province":"Nord Pas-de-Calais",
    "wof:name":"Barre Carrosserie S.a.",
    "wof:placetype":"venue"
},
  "geometry": {"coordinates":[2.949073,50.492706],"type":"Point"}
}