{
  "type": "Feature",
  "properties": {
    "iso:country":"FR",
    "sg:address":"19, Rue de Chatillon, 35065 Rennes C\u00e9dex",
    "sg:city":"Ch\u00e2tillon",
    "sg:orig_category":"Non-Classified Establishments",
    "sg:phone":"+33 2 23 35 55 55",
    "sg:postcode":"92320",
    "sg:province":"Ile de France",
    "wof:name":"C.d.c. - Caisse De D\u00e9pot Et Consignation",
    "wof:placetype":"venue"
},
  "geometry": {"coordinates":[-1.673197,48.102131],"type":"Point"}
}