{
  "type": "Feature",
  "properties": {
    "addr:full":"29 Rue Emile Zola 69190 St Fons Rhone-Alpes 69190",
    "addr:housenumber":"29",
    "addr:postcode":"69190;69190",
    "addr:street":"Rue Emile Zola;Rhone-Alpes",
    "iso:country":"FR",
    "sg:address":"29 Rue Emile Zola 69190 St Fons",
    "sg:classifiers":[
        {
            "category":"Transit Center",
            "subcategory":"Freight",
            "type":"Transportation"
        }
    ],
    "sg:phone":"+33 4 78 70 95 48",
    "sg:postcode":"69190",
    "sg:province":"Rhone-Alpes",
    "sg:tags":[
        "metallurgy",
        "pipe",
        "metalworking",
        "sheet"
    ],
    "wof:name":"Cuprofil Trefileries Et Laminoirs Du Rhone",
    "wof:placetype":"venue"
},
  "geometry": {"coordinates":[4.858462,45.710754],"type":"Point"}
}