{
  "type": "Feature",
  "properties": {
    "addr:full":"B.P. 54, 58027 Nevers C\u00e9dex^^11, Rue des Perri\u00e8res, 58000 Nevers Nevers Bourgogne 58000",
    "addr:postcode":"58027;58000;58000",
    "addr:street":"B.P. 54;Rue Des Perrie\u0300Res",
    "iso:country":"FR",
    "sg:address":"B.P. 54, 58027 Nevers C\u00e9dex^^11, Rue des Perri\u00e8res, 58000 Nevers",
    "sg:city":"Nevers",
    "sg:orig_category":"Non-Classified Establishments",
    "sg:phone":"+33 3 86 93 09 50",
    "sg:postcode":"58000",
    "sg:province":"Bourgogne",
    "wof:name":"Sade S.a.",
    "wof:placetype":"venue"
},
  "geometry": {"coordinates":[3.12953,46.920444],"type":"Point"}
}