{
  "type": "Feature",
  "properties": {
    "addr:full":"La Saline 50760 Gatteville le Phare Anneville-en-Saire Basse Normandie 50760",
    "addr:postcode":"50760;50760",
    "addr:street":"La Saline;Basse",
    "iso:country":"FR",
    "sg:address":"La Saline 50760 Gatteville le Phare",
    "sg:city":"Anneville-en-Saire",
    "sg:classifiers":[
        {
            "category":"Real Estate",
            "subcategory":"Real Estate Services",
            "type":"Services"
        }
    ],
    "sg:phone":"+33 2 33 23 41 60",
    "sg:postcode":"50760",
    "sg:province":"Basse Normandie",
    "sg:tags":[
        "crustacean",
        "shellfish"
    ],
    "wof:name":"Satmar Sa",
    "wof:placetype":"venue"
},
  "geometry": {"coordinates":[-1.271951,49.685192],"type":"Point"}
}