{
  "type": "Feature",
  "properties": {
    "iso:country":"FR",
    "sg:address":"Av. de Gen\u00e8ve",
    "sg:city":"Divonne les Bains",
    "sg:orig_category":"Unclassifiable Establishments",
    "sg:phone":"+33 4 50 20 26 44",
    "sg:postcode":"01220",
    "sg:province":"Rhone-Alpes",
    "wof:name":"Laperri\u00e8re S.a.",
    "wof:placetype":"venue"
},
  "geometry": {"coordinates":[6.149957,46.346653],"type":"Point"}
}