{
  "type": "Feature",
  "properties": {
    "iso:country":"FR",
    "sg:address":"Zac Des Plati\u00e8res 71000 Sance",
    "sg:city":"Sanc\u00e9",
    "sg:classifiers":[
        {
            "category":"Travel",
            "subcategory":"Hotels & Motels",
            "type":"Entertainment"
        }
    ],
    "sg:phone":"+33 3 85 38 64 60",
    "sg:postcode":"71000",
    "sg:province":"Bourgogne",
    "sg:tags":[
        "hotels",
        "business",
        "restaurant"
    ],
    "wof:name":"Buffalo Grill",
    "wof:placetype":"venue"
},
  "geometry": {"coordinates":[4.828295,46.340324],"type":"Point"}
}