{
  "type": "Feature",
  "properties": {
    "iso:country":"FR",
    "sg:address":"123 Bd De La Milli\u00e8re 13011 Marseille",
    "sg:classifiers":[
        {
            "category":"Manufacturing",
            "subcategory":"Chemicals & Compounds",
            "type":"Manufacturing & Wholesale Goods"
        }
    ],
    "sg:phone":"+33 4 91 24 10 00",
    "sg:province":"Poitou-Charentes",
    "sg:tags":[
        "pharmaceutical",
        "chemistry"
    ],
    "wof:name":"Elf Atofina Sa",
    "wof:placetype":"venue"
},
  "geometry": {"coordinates":[5.437165,43.289322],"type":"Point"}
}