{
  "type": "Feature",
  "properties": {
    "addr:full":"37 Rue De La Marne 93600 Aulnay Sous Bois Ile de France 93600",
    "addr:housenumber":"37",
    "addr:postcode":"93600;93600",
    "addr:street":"Rue De La Marne",
    "iso:country":"FR",
    "sg:address":"37 Rue De La Marne 93600 Aulnay Sous Bois",
    "sg:classifiers":[
        {
            "category":"Professional",
            "subcategory":"Engineering",
            "type":"Services"
        }
    ],
    "sg:phone":"+33 1 48 66 48 68",
    "sg:postcode":"93600",
    "sg:province":"Ile de France",
    "sg:tags":[
        "machine",
        "-",
        "mechanical"
    ],
    "wof:name":"Aulnay Froid Sarl",
    "wof:placetype":"venue"
},
  "geometry": {"coordinates":[2.48228,48.919228],"type":"Point"}
}