{
  "type": "Feature",
  "properties": {
    "addr:full":"Quai De La Gare 13810 Eygalieres Midi Pyr\u00e9n\u00e9es",
    "addr:postcode":"13810",
    "addr:street":"Quai De La Gare",
    "iso:country":"FR",
    "sg:address":"Quai De La Gare 13810 Eygalieres",
    "sg:classifiers":[
        {
            "category":"Wholesale",
            "subcategory":"Farm Supplies",
            "type":"Manufacturing & Wholesale Goods"
        }
    ],
    "sg:phone":"+33 4 90 95 14 68",
    "sg:province":"Midi Pyr\u00e9n\u00e9es",
    "sg:tags":[
        "-",
        "machine",
        "equipment",
        "engineering",
        "machinery",
        "mechanical",
        "agriculture"
    ],
    "wof:name":"Richel Serres De France",
    "wof:placetype":"venue"
},
  "geometry": {"coordinates":[4.957597,43.770657],"type":"Point"}
}