{
  "type": "Feature",
  "properties": {
    "addr:full":"144, Bd P\u00e9reire, 75017 Paris Ile de France",
    "addr:housenumber":"144",
    "addr:postcode":"75017",
    "addr:street":"Bd Pe\u0301Reire",
    "iso:country":"FR",
    "sg:address":"144, Bd P\u00e9reire, 75017 Paris",
    "sg:orig_category":"Unclassifiable Establishments",
    "sg:phone":"+33 1 44 29 63 63",
    "sg:province":"Ile de France",
    "wof:name":"Groupecyber S.a.",
    "wof:placetype":"venue"
},
  "geometry": {"coordinates":[2.294206,48.883724],"type":"Point"}
}