{
  "type": "Feature",
  "properties": {
    "addr:full":"10, Rue Dani\u00e8le Casanova, 95600 Eaubonne Ile de France",
    "addr:housenumber":"10",
    "addr:postcode":"95600",
    "addr:street":"Rue Danie\u0300Le Casanova",
    "iso:country":"FR",
    "sg:address":"10, Rue Dani\u00e8le Casanova, 95600 Eaubonne",
    "sg:orig_category":"Unclassifiable Establishments",
    "sg:phone":"+33 1 39 59 97 33",
    "sg:province":"Ile de France",
    "wof:name":"Mecanobois S.a.r.l.",
    "wof:placetype":"venue"
},
  "geometry": {"coordinates":[2.285443,48.979782],"type":"Point"}
}