{
  "type": "Feature",
  "properties": {
    "iso:country":"FR",
    "sg:address":"210, Rue de la Pradelle, 63000 Clermont Ferrand",
    "sg:city":"Clermont-Ferrand",
    "sg:orig_category":"Unclassifiable Establishments",
    "sg:phone":"+33 4 73 90 10 36",
    "sg:postcode":"63000",
    "sg:province":"Auvergne",
    "wof:name":"Azur S.a.r.l.",
    "wof:placetype":"venue"
},
  "geometry": {"coordinates":[3.113304,45.772949],"type":"Point"}
}