{
  "type": "Feature",
  "properties": {
    "addr:full":"rue de l'Albeck 59640 Dunkerque Alb\u00e9 Alsace 67220",
    "addr:postcode":"59640;67220",
    "addr:street":"Rue De L'Albeck",
    "iso:country":"FR",
    "sg:address":"rue de l'Albeck 59640 Dunkerque",
    "sg:city":"Alb\u00e9",
    "sg:classifiers":[
        {
            "category":"Food & Beverages",
            "subcategory":"Fruits & Vegetables",
            "type":"Retail Goods"
        }
    ],
    "sg:phone":"+33 3 28 25 93 00",
    "sg:postcode":"67220",
    "sg:province":"Alsace",
    "wof:name":"Sca Sipenord",
    "wof:placetype":"venue"
},
  "geometry": {"coordinates":[2.343984,51.008953],"type":"Point"}
}