{
  "type": "Feature",
  "properties": {
    "iso:country":"FR",
    "sg:address":"46 Rue Sainte Anne 75002 Paris",
    "sg:classifiers":[
        {
            "category":"Professional",
            "subcategory":"Business Services",
            "type":"Services"
        }
    ],
    "sg:phone":"+33 1 42 96 64 50",
    "sg:postcode":"75002",
    "sg:province":"Ile de France",
    "sg:tags":[
        "travel",
        "fair"
    ],
    "wof:name":"Agence Win Sa",
    "wof:placetype":"venue"
},
  "geometry": {"coordinates":[2.336252,48.867378],"type":"Point"}
}