{
  "type": "Feature",
  "properties": {
    "iso:country":"FR",
    "sg:address":"Rue Broceliande 35380 Treffendel",
    "sg:city":"Treffendel",
    "sg:classifiers":[
        {
            "category":"Manufacturing",
            "subcategory":"Chemicals & Compounds",
            "type":"Manufacturing & Wholesale Goods"
        }
    ],
    "sg:phone":"+33 2 99 61 02 02",
    "sg:postcode":"35380",
    "sg:province":"Bretagne",
    "sg:tags":[
        "pharmaceutical",
        "energy",
        "chemistry",
        "-",
        "by-product"
    ],
    "wof:name":"Combustibles De L'ouest",
    "wof:placetype":"venue"
},
  "geometry": {"coordinates":[-2.009544,48.04142],"type":"Point"}
}