{
  "type": "Feature",
  "properties": {
    "addr:full":"B.P. 2, 27830 Neaufles Saint Martin^^Rte de Vernon, 27830 Neaufles Saint Martin Haute Normandie",
    "addr:housenumber":"2",
    "addr:postcode":"27830;27830",
    "addr:street":"B.P.;Haute Normandie",
    "iso:country":"FR",
    "sg:address":"B.P. 2, 27830 Neaufles Saint Martin^^Rte de Vernon, 27830 Neaufles Saint Martin",
    "sg:orig_category":"Non-Classified Establishments",
    "sg:phone":"+33 2 32 27 80 80",
    "sg:province":"Haute Normandie",
    "wof:name":"Sofimah Industries S.a.r.l.",
    "wof:placetype":"venue"
},
  "geometry": {"coordinates":[1.72264,49.279007],"type":"Point"}
}