{
  "type": "Feature",
  "properties": {
    "iso:country":"FR",
    "sg:address":"33 Rue Victor Berard 39300 Champagnole",
    "sg:classifiers":[
        {
            "category":"Professional",
            "subcategory":"Engineering",
            "type":"Services"
        }
    ],
    "sg:phone":"+33 3 84 52 64 94",
    "sg:postcode":"39300",
    "sg:province":"Franche Comt\u00e9",
    "sg:tags":[
        "metallurgy",
        "metal",
        "processing",
        "-",
        "machine",
        "metalworking",
        "machinery",
        "mechanical"
    ],
    "wof:name":"Snts",
    "wof:placetype":"venue"
},
  "geometry": {"coordinates":[5.898179,46.749851],"type":"Point"}
}