{
  "type": "Feature",
  "properties": {
    "iso:country":"FR",
    "sg:address":"44, Av. de la R\u00e9publique, 92320 Chatillon",
    "sg:orig_category":"Unclassifiable Establishments",
    "sg:phone":"+33 1 55 58 90 00",
    "sg:province":"Ile de France",
    "wof:name":"Jacquim S.a.",
    "wof:placetype":"venue"
},
  "geometry": {"coordinates":[2.294494,48.801533],"type":"Point"}
}