{
  "type": "Feature",
  "properties": {
    "addr:full":"Le Genievre 72210 Voivres Les Le Mans Pays de Loire 72210",
    "addr:postcode":"72210;72210",
    "addr:street":"Voivres Les",
    "iso:country":"FR",
    "sg:address":"Le Genievre 72210 Voivres Les Le Mans",
    "sg:classifiers":[
        {
            "category":"Manufacturing",
            "subcategory":"Tools & Machinery",
            "type":"Manufacturing & Wholesale Goods"
        }
    ],
    "sg:phone":"+33 2 43 14 35 35",
    "sg:postcode":"72210",
    "sg:province":"Pays de Loire",
    "sg:tags":[
        "metallurgy",
        "metalworking"
    ],
    "wof:name":"Tls Monsieur Bricolage",
    "wof:placetype":"venue"
},
  "geometry": {"coordinates":[0.197813,48.008095],"type":"Point"}
}