{
  "type": "Feature",
  "properties": {
    "iso:country":"FR",
    "sg:address":"6 Rue Salomon Rothschild 92150 Suresnes",
    "sg:classifiers":[
        {
            "category":"Manufacturing",
            "subcategory":"Chemicals & Compounds",
            "type":"Manufacturing & Wholesale Goods"
        }
    ],
    "sg:phone":"+33 1 46 97 53 40",
    "sg:postcode":"92150",
    "sg:province":"Ile de France",
    "sg:tags":[
        "pharmaceutical",
        "chemistry",
        "-",
        "by-product"
    ],
    "wof:name":"Certified Laboratories",
    "wof:placetype":"venue"
},
  "geometry": {"coordinates":[2.232013,48.872482],"type":"Point"}
}