{
  "type": "Feature",
  "properties": {
    "addr:full":"6 Rue Salomon Rothschild 92150 Suresnes Ile de France 92150",
    "addr:housenumber":"6",
    "addr:postcode":"92150;ile;92150",
    "addr:street":"Rue Salomon Rothschild;France",
    "iso:country":"FR",
    "sg:address":"6 Rue Salomon Rothschild 92150 Suresnes",
    "sg:classifiers":[
        {
            "category":"Manufacturing",
            "subcategory":"Chemicals & Compounds",
            "type":"Manufacturing & Wholesale Goods"
        }
    ],
    "sg:phone":"+33 1 46 97 53 40",
    "sg:postcode":"92150",
    "sg:province":"Ile de France",
    "sg:tags":[
        "pharmaceutical",
        "chemistry",
        "-",
        "by-product"
    ],
    "wof:name":"Certified Laboratories",
    "wof:placetype":"venue"
},
  "geometry": {"coordinates":[2.232013,48.872482],"type":"Point"}
}