{
  "type": "Feature",
  "properties": {
    "addr:full":"34 Rue Edouard Bollaert 62300 Lens Nord Pas-de-Calais",
    "addr:housenumber":"34",
    "addr:postcode":"62300",
    "addr:street":"Rue Edouard Bollaert",
    "iso:country":"FR",
    "sg:address":"34 Rue Edouard Bollaert 62300 Lens",
    "sg:classifiers":[
        {
            "category":"Manufacturing",
            "subcategory":"Rubber & Plastics",
            "type":"Manufacturing & Wholesale Goods"
        }
    ],
    "sg:phone":"+33 3 21 42 37 37",
    "sg:province":"Nord Pas-de-Calais",
    "wof:name":"Fermoba Franciaflex",
    "wof:placetype":"venue"
},
  "geometry": {"coordinates":[2.82261,50.430611],"type":"Point"}
}