{
  "type": "Feature",
  "properties": {
    "iso:country":"FR",
    "sg:address":"La Ville 38210 Poli\u00e9nas",
    "sg:orig_category":"Non-Classified Establishments",
    "sg:phone":"+33 4 76 07 22 60",
    "sg:postcode":"38210",
    "sg:province":"Rhone-Alpes",
    "wof:name":"P\u00e9pinoix S.a.r.l.",
    "wof:placetype":"venue"
},
  "geometry": {"coordinates":[5.471695,45.249222],"type":"Point"}
}