{
  "type": "Feature",
  "properties": {
    "addr:full":"Zai Le Petit Parc 78920 Ecquevilly Ile de France",
    "addr:postcode":"78920;ile",
    "addr:street":"Zai;Petit Parc",
    "iso:country":"FR",
    "sg:address":"Zai Le Petit Parc 78920 Ecquevilly",
    "sg:classifiers":[
        {
            "category":"Shopping",
            "subcategory":"Crafts & Fabrics",
            "type":"Retail Goods"
        }
    ],
    "sg:phone":"+33 1 34 75 15 15",
    "sg:province":"Ile de France",
    "sg:tags":[
        "silk"
    ],
    "wof:name":"Henri Portier Sas",
    "wof:placetype":"venue"
},
  "geometry": {"coordinates":[1.918925,48.949734],"type":"Point"}
}