{
  "type": "Feature",
  "properties": {
    "iso:country":"FR",
    "sg:address":"Avenue Du Lac Les Granges Galands 37550 St Avertin",
    "sg:city":"Saint-Avertin",
    "sg:classifiers":[
        {
            "category":"Shopping",
            "subcategory":"Stationery & Office Supplies",
            "type":"Retail Goods"
        }
    ],
    "sg:phone":"+33 2 47 80 27 27",
    "sg:postcode":"37550",
    "sg:province":"Centre",
    "sg:tags":[
        "information",
        "technology",
        "telecommunication",
        "equipment"
    ],
    "wof:name":"Ricoh France Centre Atlantique",
    "wof:placetype":"venue"
},
  "geometry": {"coordinates":[0.726945,47.366928],"type":"Point"}
}