{
  "type": "Feature",
  "properties": {
    "addr:full":"44, Rue de Rosi\u00e8re, 95100 Argenteuil Ile de France",
    "addr:housenumber":"44",
    "addr:postcode":"95100;ile",
    "addr:street":"Rue De Rosie\u0300Re",
    "iso:country":"FR",
    "sg:address":"44, Rue de Rosi\u00e8re, 95100 Argenteuil",
    "sg:orig_category":"Unclassifiable Establishments",
    "sg:phone":"+33 1 39 82 39 55",
    "sg:province":"Ile de France",
    "wof:name":"Imprimerie Pagniez S.a.r.l.",
    "wof:placetype":"venue"
},
  "geometry": {"coordinates":[2.234574,48.964417],"type":"Point"}
}