{
  "type": "Feature",
  "properties": {
    "iso:country":"FR",
    "sg:address":"6, Rue Joseph Cugnot - ZI Gutemberg - Parc Industriel Sud, 57200 Sarreguemines",
    "sg:orig_category":"Unclassifiable Establishments",
    "sg:phone":"+33 3 87 95 07 50",
    "sg:province":"Lorraine",
    "wof:name":"Schultz Equipements S.a.r.l.",
    "wof:placetype":"venue"
},
  "geometry": {"coordinates":[7.070569,49.108246],"type":"Point"}
}