{
  "type": "Feature",
  "properties": {
    "addr:full":"6 rue du Docteur Schweitzer 38180 Seyssins Rhone-Alpes 38180",
    "addr:housenumber":"6",
    "addr:postcode":"38180;38180",
    "addr:street":"Rue Du Docteur Schweitzer",
    "iso:country":"FR",
    "sg:address":"6 rue du Docteur Schweitzer 38180 Seyssins",
    "sg:classifiers":[
        {
            "category":"Shopping",
            "subcategory":"Shoes",
            "type":"Retail Goods"
        }
    ],
    "sg:phone":"+33 4 76 48 49 19",
    "sg:postcode":"38180",
    "sg:province":"Rhone-Alpes",
    "sg:tags":[
        "children's"
    ],
    "wof:name":"Ymc S.a.r.l.",
    "wof:placetype":"venue"
},
  "geometry": {"coordinates":[5.697001,45.158871],"type":"Point"}
}