{
  "type": "Feature",
  "properties": {
    "addr:full":"24 Cours De L Intendance 33000 Bordeaux Bordeaux Aquitaine 33000",
    "addr:housenumber":"24",
    "addr:postcode":"33000;33000",
    "addr:street":"Cours De L Intendance",
    "iso:country":"FR",
    "sg:address":"24 Cours De L Intendance 33000 Bordeaux",
    "sg:city":"Bordeaux",
    "sg:classifiers":[
        {
            "category":"Manufacturing",
            "subcategory":"Printing",
            "type":"Manufacturing & Wholesale Goods"
        }
    ],
    "sg:phone":"+33 5 56 44 02 73",
    "sg:postcode":"33000",
    "sg:province":"Aquitaine",
    "sg:tags":[
        "publishing"
    ],
    "wof:name":"Objectif Aquitaine",
    "wof:placetype":"venue"
},
  "geometry": {"coordinates":[-0.577555,44.841984],"type":"Point"}
}