{
  "type": "Feature",
  "properties": {
    "iso:country":"FR",
    "sg:address":"3 Av Fran\u00e7ois Cuzin 83000 Toulon",
    "sg:city":"Fran\u00e7ois",
    "sg:classifiers":[
        {
            "category":"Autos & Motor Vehicles",
            "subcategory":"Automobile Sales",
            "type":"Retail Goods"
        }
    ],
    "sg:phone":"+33 4 94 41 64 16",
    "sg:postcode":"79260",
    "sg:province":"Poitou-Charentes",
    "sg:tags":[
        "equipment",
        "transport"
    ],
    "wof:name":"Mbk Darmon Sa Toulon Motocycles",
    "wof:placetype":"venue"
},
  "geometry": {"coordinates":[5.941466,43.121582],"type":"Point"}
}