{
  "type": "Feature",
  "properties": {
    "addr:full":"Rue des Cinq Fr\u00e8res Robinet - Centre de Production La Fert\u00e9 Mac\u00e9 Basse Normandie 61600",
    "addr:postcode":"61600",
    "addr:street":"Rue Des Cinq Fre\u0300Res Robinet",
    "iso:country":"FR",
    "sg:address":"Rue des Cinq Fr\u00e8res Robinet - Centre de Production",
    "sg:city":"La Fert\u00e9 Mac\u00e9",
    "sg:orig_category":"Unclassifiable Establishments",
    "sg:phone":"+33 2 33 37 14 01",
    "sg:postcode":"61600",
    "sg:province":"Basse Normandie",
    "wof:name":"Cantillana S.a.r.l.",
    "wof:placetype":"venue"
},
  "geometry": {"coordinates":[-0.358504,48.587021],"type":"Point"}
}