{
  "type": "Feature",
  "properties": {
    "addr:full":"Rue du Pont VI Le Havre Haute Normandie 76600",
    "addr:postcode":"76600",
    "addr:street":"Rue Du Pont Vi",
    "iso:country":"FR",
    "sg:address":"Rue du Pont VI",
    "sg:city":"Le Havre",
    "sg:orig_category":"Non-Classified Establishments",
    "sg:phone":"+33 2 35 24 62 40",
    "sg:postcode":"76600",
    "sg:province":"Haute Normandie",
    "wof:name":"Soci\u00e9t\u00e9 Nouvelle Solma S.a.",
    "wof:placetype":"venue"
},
  "geometry": {"coordinates":[0.160241,49.484314],"type":"Point"}
}