{
  "type": "Feature",
  "properties": {
    "addr:full":"Z I Du Moulin 01100 Bellignat Rhone-Alpes",
    "addr:postcode":"01100",
    "addr:street":"Z I Du Moulin",
    "iso:country":"FR",
    "sg:address":"Z I Du Moulin 01100 Bellignat",
    "sg:orig_category":"Special Injection Moulding Machines",
    "sg:phone":"+33 4 74 77 67 50",
    "sg:province":"Rhone-Alpes",
    "wof:name":"Etablissements Alain Chosson Sarl",
    "wof:placetype":"venue"
},
  "geometry": {"coordinates":[5.64405,46.24968],"type":"Point"}
}