{
  "type": "Feature",
  "properties": {
    "addr:full":"2 Rue Des Teinturiers 42630 REGNY Rhone-Alpes 42630",
    "addr:housenumber":"2",
    "addr:postcode":"42630;42630",
    "addr:street":"Rue Des Teinturiers",
    "iso:country":"FR",
    "sg:address":"2 Rue Des Teinturiers 42630 REGNY",
    "sg:orig_category":"Fabrics, Finished, For Ladies' Outerwear, Men's And Boys' Wear, Sportswear",
    "sg:phone":"+33 4 77 63 06 65",
    "sg:postcode":"42630",
    "sg:province":"Rhone-Alpes",
    "wof:name":"Rdv Associes Sarl",
    "wof:placetype":"venue"
},
  "geometry": {"coordinates":[4.217293,45.990414],"type":"Point"}
}