{
  "type": "Feature",
  "properties": {
    "iso:country":"FR",
    "sg:address":"16, Rue de la Tour Carr\u00e9e, 50100 Cherbourg",
    "sg:city":"Cherbourg-Octeville",
    "sg:orig_category":"Unclassifiable Establishments",
    "sg:phone":"+33 2 33 93 33 76",
    "sg:postcode":"50100",
    "sg:province":"Basse Normandie",
    "wof:name":"Electronique 50 S.a.r.l.",
    "wof:placetype":"venue"
},
  "geometry": {"coordinates":[-1.624562,49.64175],"type":"Point"}
}