{
  "type": "Feature",
  "properties": {
    "iso:country":"FR",
    "sg:address":"Port Grimaud Sud - Chantier Naval",
    "sg:city":"Grimaud",
    "sg:orig_category":"Unclassifiable Establishments",
    "sg:phone":"+33 4 94 56 02 25",
    "sg:postcode":"83310",
    "sg:province":"Rhone-Alpes",
    "wof:name":"Soci\u00e9t\u00e9 Manutentions Navales De Port Grimaud S.a.",
    "wof:placetype":"venue"
},
  "geometry": {"coordinates":[6.465188,43.207832],"type":"Point"}
}