{
  "type": "Feature",
  "properties": {
    "addr:full":"21 Rue De Varenne 75007 Paris Ile de France 75007",
    "addr:housenumber":"21",
    "addr:postcode":"75007;75007",
    "addr:street":"Rue De Varenne",
    "iso:country":"FR",
    "sg:address":"21 Rue De Varenne 75007 Paris",
    "sg:classifiers":[
        {
            "category":"Professional",
            "subcategory":"Business Services",
            "type":"Services"
        }
    ],
    "sg:phone":"+33 1 45 48 34 67",
    "sg:postcode":"75007",
    "sg:province":"Ile de France",
    "sg:tags":[
        "training",
        "advice"
    ],
    "wof:name":"Asso Gestion Cours Catho Hulst",
    "wof:placetype":"venue"
},
  "geometry": {"coordinates":[2.324757,48.853619],"type":"Point"}
}