{
  "type": "Feature",
  "properties": {
    "addr:full":"125, Rue de Saussure, 75017 Paris Ile de France",
    "addr:housenumber":"125",
    "addr:postcode":"75017",
    "addr:street":"Rue De Saussure",
    "iso:country":"FR",
    "sg:address":"125, Rue de Saussure, 75017 Paris",
    "sg:orig_category":"Non-Classified Establishments",
    "sg:phone":"+33 1 56 79 18 00",
    "sg:province":"Ile de France",
    "wof:name":"Sellotape France S.a.",
    "wof:placetype":"venue"
},
  "geometry": {"coordinates":[2.309003,48.88855],"type":"Point"}
}