{
  "type": "Feature",
  "properties": {
    "addr:full":"19, Rue de l'Abreuvoir, 77100 Meaux Ile de France",
    "addr:housenumber":"19",
    "addr:postcode":"77100;ile",
    "addr:street":"Rue De L'Abreuvoir",
    "iso:country":"FR",
    "sg:address":"19, Rue de l'Abreuvoir, 77100 Meaux",
    "sg:orig_category":"Unclassifiable Establishments",
    "sg:phone":"+33 1 64 34 31 69",
    "sg:province":"Ile de France",
    "wof:name":"Saturne Informatique S.a.r.l.",
    "wof:placetype":"venue"
},
  "geometry": {"coordinates":[2.886433,48.957581],"type":"Point"}
}