{
  "type": "Feature",
  "properties": {
    "addr:full":"35, Av de Montrapon, 25000 Besan\u00e7on Franche Comt\u00e9",
    "addr:postcode":"25000",
    "addr:street":"35 Av De Montrapon;Franche Comte\u0301",
    "iso:country":"FR",
    "sg:address":"35, Av de Montrapon, 25000 Besan\u00e7on",
    "sg:orig_category":"Unclassifiable Establishments",
    "sg:phone":"+33 3 81 88 25 94",
    "sg:province":"Franche Comt\u00e9",
    "wof:name":"Greta De Besan\u00e7on",
    "wof:placetype":"venue"
},
  "geometry": {"coordinates":[6.003273,47.248863],"type":"Point"}
}