{
  "type": "Feature",
  "properties": {
    "addr:full":"3, rue Paul Dautier - Z.I., 78140 V\u00e9lizy Villacoublay Ile de France",
    "addr:housenumber":"3",
    "addr:postcode":"78140",
    "addr:street":"Rue Paul Dautier Z.I.",
    "iso:country":"FR",
    "sg:address":"3, rue Paul Dautier - Z.I., 78140 V\u00e9lizy Villacoublay",
    "sg:orig_category":"Unclassifiable Establishments",
    "sg:phone":"+33 1 39 26 22 22",
    "sg:province":"Ile de France",
    "wof:name":"Brancher Fr\u00e8res S.a.",
    "wof:placetype":"venue"
},
  "geometry": {"coordinates":[2.18246,48.78503],"type":"Point"}
}