{
  "type": "Feature",
  "properties": {
    "addr:full":"B.P. 57, 25150 Pont de Roide^^Rue du Moulin R\u00e9mondans, 25150 R\u00e9mondans Vaivre Franche Comt\u00e9",
    "addr:postcode":"25150;25150",
    "addr:street":"B.P. 57;Re\u0301Mondans;Franche Comte\u0301",
    "iso:country":"FR",
    "sg:address":"B.P. 57, 25150 Pont de Roide^^Rue du Moulin R\u00e9mondans, 25150 R\u00e9mondans Vaivre",
    "sg:orig_category":"Non-Classified Establishments",
    "sg:phone":"+33 3 81 96 92 44",
    "sg:province":"Franche Comt\u00e9",
    "wof:name":"Savreux Clausse S.a.",
    "wof:placetype":"venue"
},
  "geometry": {"coordinates":[6.770996,47.382812],"type":"Point"}
}