{
  "type": "Feature",
  "properties": {
    "addr:full":"Parc D'Activit\u00e9s Hauts -Pyr\u00e9n\u00e9es BP 833 Zi De L'Echangeur 64008 Pau Cedex Centre",
    "addr:housenumber":"833",
    "addr:postcode":"64008",
    "addr:street":"Zi De L'Echangeur",
    "iso:country":"FR",
    "sg:address":"Parc D'Activit\u00e9s Hauts -Pyr\u00e9n\u00e9es BP 833 Zi De L'Echangeur 64008 Pau Cedex",
    "sg:classifiers":[
        {
            "category":"Wholesale",
            "subcategory":"Medical Equipment & Supplies",
            "type":"Manufacturing & Wholesale Goods"
        }
    ],
    "sg:phone":"+33 5 59 14 02 02",
    "sg:province":"Centre",
    "sg:tags":[
        "instrument",
        "health",
        "-",
        "precision"
    ],
    "wof:name":"Airox",
    "wof:placetype":"venue"
},
  "geometry": {"coordinates":[-0.372156,43.311535],"type":"Point"}
}