{
  "type": "Feature",
  "properties": {
    "iso:country":"FR",
    "sg:address":"6, Rue Four, 60620 Bouillancy",
    "sg:orig_category":"Non-Classified Establishments",
    "sg:phone":"+33 3 44 87 26 16",
    "sg:province":"Picardie",
    "wof:name":"S.t.d.s. S.a.r.l. - Soci\u00e9t\u00e9 De Transports Duchaussoy Et Susset",
    "wof:placetype":"venue"
},
  "geometry": {"coordinates":[2.919694,49.112045],"type":"Point"}
}