{
  "type": "Feature",
  "properties": {
    "iso:country":"FR",
    "sg:address":"302, Rue Edouard Vaillant, 59184 Sainghin en Weppes",
    "sg:orig_category":"Unclassifiable Establishments",
    "sg:phone":"+33 3 20 58 18 00",
    "sg:province":"Nord Pas-de-Calais",
    "wof:name":"Hocq Jules S.a.",
    "wof:placetype":"venue"
},
  "geometry": {"coordinates":[2.893568,50.562641],"type":"Point"}
}