{
  "type": "Feature",
  "properties": {
    "addr:full":"Quartier Pouchonnet 30120 AVEZE Languedoc-Roussillon 30120",
    "addr:postcode":"30120;30120",
    "addr:street":"Aveze",
    "iso:country":"FR",
    "sg:address":"Quartier Pouchonnet 30120 AVEZE",
    "sg:classifiers":[
        {
            "category":"Home & Garden",
            "subcategory":"Home Furnishings",
            "type":"Retail Goods"
        }
    ],
    "sg:phone":"+33 4 67 81 67 81",
    "sg:postcode":"30120",
    "sg:province":"Languedoc-Roussillon",
    "sg:tags":[
        "interior",
        "decoration"
    ],
    "wof:name":"Etablissements Vincent Cadeaux S.a.",
    "wof:placetype":"venue"
},
  "geometry": {"coordinates":[3.598691,43.976933],"type":"Point"}
}