{
  "type": "Feature",
  "properties": {
    "addr:full":"15, Rue Lambert - Cours des Mar\u00e9chaux, 68100 Mulhouse Mulhouse Alsace 68100",
    "addr:housenumber":"15",
    "addr:postcode":"68100;68100",
    "addr:street":"Rue Lambert Cours Des Mare\u0301Chaux",
    "iso:country":"FR",
    "sg:address":"15, Rue Lambert - Cours des Mar\u00e9chaux, 68100 Mulhouse",
    "sg:city":"Mulhouse",
    "sg:orig_category":"Unclassifiable Establishments",
    "sg:phone":"+33 3 89 66 44 77",
    "sg:postcode":"68100",
    "sg:province":"Alsace",
    "wof:name":"Tulip Inn Mulhouse Centre S.a.r.l.",
    "wof:placetype":"venue"
},
  "geometry": {"coordinates":[7.34365,47.751709],"type":"Point"}
}