{
  "type": "Feature",
  "properties": {
    "iso:country":"FR",
    "sg:address":"Bd deBeaubourg - ZAC Paris Est",
    "sg:city":"Croissy Beaubourg",
    "sg:orig_category":"Unclassifiable Establishments",
    "sg:phone":"+33 1 60 17 75 22",
    "sg:postcode":"77183",
    "sg:province":"Ile de France",
    "wof:name":"Forbo Helmitin",
    "wof:placetype":"venue"
},
  "geometry": {"coordinates":[2.659334,48.828526],"type":"Point"}
}