{
  "type": "Feature",
  "properties": {
    "addr:full":"2 Avenue Emile 95160 Montmorency Ile de France 95160",
    "addr:housenumber":"2",
    "addr:postcode":"95160;95160",
    "addr:street":"Avenue Emile",
    "iso:country":"FR",
    "sg:address":"2 Avenue Emile 95160 Montmorency",
    "sg:classifiers":[
        {
            "category":"Manufacturing",
            "subcategory":"Jewelry",
            "type":"Manufacturing & Wholesale Goods"
        }
    ],
    "sg:phone":"+33 1 39 64 23 17",
    "sg:postcode":"95160",
    "sg:province":"Ile de France",
    "sg:tags":[
        "product",
        "miscellaneous",
        "jewellery"
    ],
    "wof:name":"Mb Creations Michel Barrial Creations",
    "wof:placetype":"venue"
},
  "geometry": {"coordinates":[2.31898,48.988892],"type":"Point"}
}