{
  "type": "Feature",
  "properties": {
    "addr:full":"5, Rue du P\u00e2tis, 89200 Avallon Avallon Bourgogne 89200",
    "addr:housenumber":"5",
    "addr:postcode":"89200;89200",
    "addr:street":"Rue Du Pa\u0302Tis",
    "iso:country":"FR",
    "sg:address":"5, Rue du P\u00e2tis, 89200 Avallon",
    "sg:city":"Avallon",
    "sg:orig_category":"Unclassifiable Establishments",
    "sg:phone":"+33 3 86 34 33 42",
    "sg:postcode":"89200",
    "sg:province":"Bourgogne",
    "wof:name":"Laboureau S.a.r.l.",
    "wof:placetype":"venue"
},
  "geometry": {"coordinates":[3.887556,47.496323],"type":"Point"}
}