{
  "type": "Feature",
  "properties": {
    "addr:full":"Rte de Chalais - La Font Close Barbezieux Saint Hilaire Poitou-Charentes 16300",
    "addr:postcode":"16300",
    "addr:street":"Rte De Chalais La Font Close",
    "iso:country":"FR",
    "sg:address":"Rte de Chalais - La Font Close",
    "sg:city":"Barbezieux Saint Hilaire",
    "sg:orig_category":"Unclassifiable Establishments",
    "sg:phone":"+33 5 45 78 16 33",
    "sg:postcode":"16300",
    "sg:province":"Poitou-Charentes",
    "wof:name":"Fornel Fr\u00e8res S.a.",
    "wof:placetype":"venue"
},
  "geometry": {"coordinates":[-0.079554,45.41621],"type":"Point"}
}