{
  "type": "Feature",
  "properties": {
    "addr:full":"36 D Rue Vingt Toises 38950 St Martin Le Vinoux Rhone-Alpes 38950",
    "addr:housenumber":"36 d;38950",
    "addr:postcode":"38950",
    "addr:street":"Rue Vingt Toises;St Martin Le;Rhone-Alpes",
    "iso:country":"FR",
    "sg:address":"36 D Rue Vingt Toises 38950 St Martin Le Vinoux",
    "sg:classifiers":[
        {
            "category":"Professional",
            "subcategory":"Computer Services",
            "type":"Services"
        }
    ],
    "sg:phone":"+33 4 76 75 91 59",
    "sg:postcode":"38950",
    "sg:province":"Rhone-Alpes",
    "sg:tags":[
        "information",
        "technology",
        "software"
    ],
    "wof:name":"Cso Informatique Sa",
    "wof:placetype":"venue"
},
  "geometry": {"coordinates":[5.689249,45.212307],"type":"Point"}
}