{
  "type": "Feature",
  "properties": {
    "addr:full":"18 Rue De Londres Port Fluvial 59120 Loos Nord Pas-de-Calais 59120",
    "addr:housenumber":"18",
    "addr:postcode":"59120;59120",
    "addr:street":"Rue De Londres",
    "iso:country":"FR",
    "sg:address":"18 Rue De Londres Port Fluvial 59120 Loos",
    "sg:classifiers":[
        {
            "category":"Manufacturing",
            "subcategory":"Glass & Minerals",
            "type":"Manufacturing & Wholesale Goods"
        }
    ],
    "sg:phone":"+33 3 20 17 03 80",
    "sg:postcode":"59120",
    "sg:province":"Nord Pas-de-Calais",
    "sg:tags":[
        "building",
        "material"
    ],
    "wof:name":"Beton De France Nord Ouest",
    "wof:placetype":"venue"
},
  "geometry": {"coordinates":[3.015711,50.615021],"type":"Point"}
}