{
  "type": "Feature",
  "properties": {
    "iso:country":"FR",
    "sg:address":"B.P. 84, 08002 Charleville M\u00e9zi\u00e8res C\u00e9dex^^Rue Paulin Richier - ZAC du Bois Fortant - La Croisette ,",
    "sg:city":"Vill\u00e9",
    "sg:orig_category":"Equipements de protection individuelle Fournitures industrielles Levage, Accessoires de Lubrifiants ",
    "sg:phone":"+33 3 24 59 73 73",
    "sg:postcode":"67220",
    "sg:province":"Alsace",
    "wof:name":"Mairiaux Distribution S.a.",
    "wof:placetype":"venue"
},
  "geometry": {"coordinates":[4.71944,49.77087],"type":"Point"}
}