{
  "type": "Feature",
  "properties": {
    "addr:full":"4, Rue Enrico Fermi, 77400 Saint Thibault des Vignes Ile de France 77400",
    "addr:housenumber":"4",
    "addr:postcode":"77400;ile;77400",
    "addr:street":"Rue Enrico Fermi;France",
    "iso:country":"FR",
    "sg:address":"4, Rue Enrico Fermi, 77400 Saint Thibault des Vignes",
    "sg:orig_category":"Non-Classified Establishments",
    "sg:phone":"+33 1 64 02 90 82",
    "sg:postcode":"77400",
    "sg:province":"Ile de France",
    "wof:name":"A.d.i. France S.a. - Advenced Datum Information",
    "wof:placetype":"venue"
},
  "geometry": {"coordinates":[2.671221,48.865307],"type":"Point"}
}