{
  "type": "Feature",
  "properties": {
    "addr:full":"308 Rue Fontaines 74130 Vougy Rhone-Alpes",
    "addr:housenumber":"308",
    "addr:postcode":"74130",
    "addr:street":"Rue Fontaines",
    "iso:country":"FR",
    "sg:address":"308 Rue Fontaines 74130 Vougy",
    "sg:classifiers":[
        {
            "category":"Manufacturing",
            "subcategory":"Paper Products",
            "type":"Manufacturing & Wholesale Goods"
        }
    ],
    "sg:phone":"+33 4 50 34 57 15",
    "sg:province":"Rhone-Alpes",
    "sg:tags":[
        "raw",
        "material",
        "-",
        "cardboard"
    ],
    "wof:name":"Prapack Cartonnages Sarl",
    "wof:placetype":"venue"
},
  "geometry": {"coordinates":[6.46892,46.066204],"type":"Point"}
}