{
  "type": "Feature",
  "properties": {
    "addr:full":"61, Rue de Gassicourt, 78200 Mantes la Jolie Ile de France",
    "addr:housenumber":"61",
    "addr:postcode":"78200",
    "addr:street":"Rue De Gassicourt",
    "iso:country":"FR",
    "sg:address":"61, Rue de Gassicourt, 78200 Mantes la Jolie",
    "sg:orig_category":"Non-Classified Establishments",
    "sg:phone":"+33 1 30 33 49 85",
    "sg:province":"Ile de France",
    "wof:name":"P.o.m. - Protection Outillage Mantais",
    "wof:placetype":"venue"
},
  "geometry": {"coordinates":[1.707138,48.993458],"type":"Point"}
}