{
  "type": "Feature",
  "properties": {
    "iso:country":"FR",
    "sg:address":"66, Rue de Nancy, 59100 Roubaix",
    "sg:orig_category":"Unclassifiable Establishments",
    "sg:phone":"+33 3 20 20 09 10",
    "sg:province":"Nord Pas-de-Calais",
    "wof:name":"Craye S.a.",
    "wof:placetype":"venue"
},
  "geometry": {"coordinates":[3.196605,50.683701],"type":"Point"}
}