{
  "type": "Feature",
  "properties": {
    "addr:full":"12, Av. de Jalday - ZI, 64500 Saint Jean de Luz Ciboure Aquitaine 64500",
    "addr:postcode":"64500;64500",
    "addr:street":"12 Av. De Jalday Zi",
    "iso:country":"FR",
    "sg:address":"12, Av. de Jalday - ZI, 64500 Saint Jean de Luz",
    "sg:city":"Ciboure",
    "sg:orig_category":"Unclassifiable Establishments",
    "sg:phone":"+33 5 59 26 36 71",
    "sg:postcode":"64500",
    "sg:province":"Aquitaine",
    "wof:name":"Bascogel S.a.r.l.",
    "wof:placetype":"venue"
},
  "geometry": {"coordinates":[-1.660884,43.38773],"type":"Point"}
}