{
  "type": "Feature",
  "properties": {
    "iso:country":"FR",
    "sg:address":"4 Imp Des Fabriques 67700 Saverne",
    "sg:city":"Saverne",
    "sg:classifiers":[
        {
            "category":"Wholesale",
            "subcategory":"Farm Supplies",
            "type":"Manufacturing & Wholesale Goods"
        }
    ],
    "sg:phone":"+33 3 88 01 81 00",
    "sg:postcode":"67700",
    "sg:province":"Alsace",
    "sg:tags":[
        "-",
        "machine",
        "equipment",
        "engineering",
        "machinery",
        "mechanical",
        "agriculture"
    ],
    "wof:name":"Kuhn Sa",
    "wof:placetype":"venue"
},
  "geometry": {"coordinates":[7.355442,48.744476],"type":"Point"}
}