{
  "type": "Feature",
  "properties": {
    "addr:full":"Parc d'Activit\u00e9s St\u00e9lytec Saint Chamond Rhone-Alpes 42400",
    "addr:postcode":"42400",
    "addr:street":"Rhone-Alpes",
    "iso:country":"FR",
    "sg:address":"Parc d'Activit\u00e9s St\u00e9lytec",
    "sg:city":"Saint Chamond",
    "sg:orig_category":"Non-Classified Establishments",
    "sg:phone":"+33 4 77 29 39 66",
    "sg:postcode":"42400",
    "sg:province":"Rhone-Alpes",
    "wof:name":"Micel S.a.",
    "wof:placetype":"venue"
},
  "geometry": {"coordinates":[4.50826,45.468658],"type":"Point"}
}