{
  "type": "Feature",
  "properties": {
    "addr:full":"Lieu Dit Clerette Rn 124 32110 Lanne Soubiran Midi Pyr\u00e9n\u00e9es 32110",
    "addr:housenumber":"124",
    "addr:postcode":"32110;32110",
    "addr:street":"Lieu Dit Clerette Rn",
    "iso:country":"FR",
    "sg:address":"Lieu Dit Clerette Rn 124 32110 Lanne Soubiran",
    "sg:classifiers":[
        {
            "category":"Wholesale",
            "subcategory":"Farm Supplies",
            "type":"Manufacturing & Wholesale Goods"
        }
    ],
    "sg:phone":"+33 5 62 09 05 27",
    "sg:postcode":"32110",
    "sg:province":"Midi Pyr\u00e9n\u00e9es",
    "sg:tags":[
        "-",
        "machine",
        "equipment",
        "engineering",
        "machinery",
        "mechanical",
        "agriculture"
    ],
    "wof:name":"Eurosama",
    "wof:placetype":"venue"
},
  "geometry": {"coordinates":[-0.062689,43.71439],"type":"Point"}
}