{
  "type": "Feature",
  "properties": {
    "addr:full":"Av De La Republique 39500 Tavaux Franche Comt\u00e9 39500",
    "addr:postcode":"39500;39500",
    "addr:street":"Av De La Republique;Franche Comte\u0301",
    "iso:country":"FR",
    "sg:address":"Av De La Republique 39500 Tavaux",
    "sg:classifiers":[
        {
            "category":"Manufacturing",
            "subcategory":"Chemicals & Compounds",
            "type":"Manufacturing & Wholesale Goods"
        }
    ],
    "sg:phone":"+33 3 84 71 20 00",
    "sg:postcode":"39500",
    "sg:province":"Franche Comt\u00e9",
    "sg:tags":[
        "pharmaceutical",
        "chemistry",
        "-",
        "by-product"
    ],
    "wof:name":"Solvay",
    "wof:placetype":"venue"
},
  "geometry": {"coordinates":[5.413688,47.047749],"type":"Point"}
}