{
  "type": "Feature",
  "properties": {
    "addr:full":"Le Grand Epagny 74330 Epagny Rhone-Alpes 74330",
    "addr:postcode":"74330;74330",
    "iso:country":"FR",
    "sg:address":"Le Grand Epagny 74330 Epagny",
    "sg:orig_category":"Unclassifiable Establishments",
    "sg:phone":"+33 4 50 22 14 77",
    "sg:postcode":"74330",
    "sg:province":"Rhone-Alpes",
    "wof:name":"Mada Echafaudages S.a.",
    "wof:placetype":"venue"
},
  "geometry": {"coordinates":[6.08946,45.934399],"type":"Point"}
}