{
  "type": "Feature",
  "properties": {
    "addr:full":"ZI de la Motte Portes l\u00e8s Valence Rhone-Alpes 26800",
    "addr:postcode":"26800",
    "addr:street":"Zi De La Motte",
    "iso:country":"FR",
    "sg:address":"ZI de la Motte",
    "sg:city":"Portes l\u00e8s Valence",
    "sg:orig_category":"Unclassifiable Establishments",
    "sg:phone":"+33 4 75 57 17 44",
    "sg:postcode":"26800",
    "sg:province":"Rhone-Alpes",
    "wof:name":"Etablissements Gascheau S.a.",
    "wof:placetype":"venue"
},
  "geometry": {"coordinates":[4.87721,44.876316],"type":"Point"}
}