{
  "type": "Feature",
  "properties": {
    "addr:full":"4, Rue Belle Aurore, 56150 Baud Baud Bretagne 56150",
    "addr:housenumber":"4",
    "addr:postcode":"56150;56150",
    "addr:street":"Rue Belle Aurore;Baud",
    "iso:country":"FR",
    "sg:address":"4, Rue Belle Aurore, 56150 Baud",
    "sg:city":"Baud",
    "sg:orig_category":"Unclassifiable Establishments",
    "sg:phone":"+33 2 97 51 02 66",
    "sg:postcode":"56150",
    "sg:province":"Bretagne",
    "wof:name":"Soci\u00e9t\u00e9 Mandragore S.a.r.l.",
    "wof:placetype":"venue"
},
  "geometry": {"coordinates":[-3.006721,47.882111],"type":"Point"}
}