{
  "type": "Feature",
  "properties": {
    "iso:country":"FR",
    "sg:address":"16, Rue Cordelle, 49100 Angers",
    "sg:orig_category":"Unclassifiable Establishments",
    "sg:phone":"+33 2 41 88 59 86",
    "sg:province":"Pays de Loire",
    "wof:name":"Cetradel Val De Loire S.a.r.l.",
    "wof:placetype":"venue"
},
  "geometry": {"coordinates":[-0.551539,47.471352],"type":"Point"}
}