{
  "type": "Feature",
  "properties": {
    "addr:full":"64 Rue Du Mal Joffre 59155 Faches Thumesnil Nord Pas-de-Calais 59155",
    "addr:housenumber":"64",
    "addr:postcode":"59155;59155",
    "addr:street":"Rue Du Mal Joffre;Thumesnil",
    "iso:country":"FR",
    "sg:address":"64 Rue Du Mal Joffre 59155 Faches Thumesnil",
    "sg:classifiers":[
        {
            "category":"Professional",
            "subcategory":"Engineering",
            "type":"Services"
        }
    ],
    "sg:phone":"+33 3 20 52 57 27",
    "sg:postcode":"59155",
    "sg:province":"Nord Pas-de-Calais",
    "sg:tags":[
        "machine",
        "-",
        "mechanical"
    ],
    "wof:name":"Antoine Camar Sarl",
    "wof:placetype":"venue"
},
  "geometry": {"coordinates":[3.062095,50.605141],"type":"Point"}
}