{
  "type": "Feature",
  "properties": {
    "addr:full":"163, Av. de Limoges, 87270 Couzeix Limousin 87270",
    "addr:postcode":"87270;87270",
    "addr:street":"163 Av. De Limoges",
    "iso:country":"FR",
    "sg:address":"163, Av. de Limoges, 87270 Couzeix",
    "sg:orig_category":"Non-Classified Establishments",
    "sg:phone":"+33 5 55 38 85 50",
    "sg:postcode":"87270",
    "sg:province":"Limousin",
    "wof:name":"B.p.c. - Banque Populaire Du Centre",
    "wof:placetype":"venue"
},
  "geometry": {"coordinates":[1.237614,45.876057],"type":"Point"}
}