{
  "type": "Feature",
  "properties": {
    "addr:full":"14, Rue de la Madeleine, 53100 Mayenne Pays de Loire",
    "addr:housenumber":"14",
    "addr:postcode":"53100 mayenne",
    "addr:street":"Rue De La Madeleine",
    "iso:country":"FR",
    "sg:address":"14, Rue de la Madeleine, 53100 Mayenne",
    "sg:orig_category":"Unclassifiable Establishments",
    "sg:phone":"+33 2 43 08 69 77",
    "sg:province":"Pays de Loire",
    "wof:name":"Octopus S.a.r.l.",
    "wof:placetype":"venue"
},
  "geometry": {"coordinates":[-0.611396,48.301113],"type":"Point"}
}