{
  "type": "Feature",
  "properties": {
    "addr:full":"3, Rue Ariane - Parc Technologique du Canal, 31520 Ramonville Saint Agne Midi Pyr\u00e9n\u00e9es 31520",
    "addr:housenumber":"3",
    "addr:postcode":"31520;31520",
    "addr:street":"Rue Ariane",
    "iso:country":"FR",
    "sg:address":"3, Rue Ariane - Parc Technologique du Canal, 31520 Ramonville Saint Agne",
    "sg:orig_category":"Non-Classified Establishments",
    "sg:phone":"+33 5 61 73 41 41",
    "sg:postcode":"31520",
    "sg:province":"Midi Pyr\u00e9n\u00e9es",
    "wof:name":"Anotech S.a.",
    "wof:placetype":"venue"
},
  "geometry": {"coordinates":[1.485107,43.548874],"type":"Point"}
}