{
  "type": "Feature",
  "properties": {
    "addr:full":"55, Rue Jean-Baptiste Colbert, 10600 La Chapelle Saint Luc Champagne",
    "addr:housenumber":"55",
    "addr:postcode":"10600",
    "addr:street":"Rue Jean-Baptiste Colbert",
    "iso:country":"FR",
    "sg:address":"55, Rue Jean-Baptiste Colbert, 10600 La Chapelle Saint Luc",
    "sg:orig_category":"Non-Classified Establishments",
    "sg:phone":"+33 3 25 71 71 25",
    "sg:province":"Champagne",
    "wof:name":"Thiriet S.a.r.l.",
    "wof:placetype":"venue"
},
  "geometry": {"coordinates":[4.024498,48.32],"type":"Point"}
}