{
  "type": "Feature",
  "properties": {
    "iso:country":"FR",
    "sg:address":"ZA Grand Chemin",
    "sg:city":"Aubais",
    "sg:orig_category":"Unclassifiable Establishments",
    "sg:phone":"+33 4 66 80 21 21",
    "sg:postcode":"30250",
    "sg:province":"Languedoc-Roussillon",
    "wof:name":"J.c.b. A\u00e9ro S.a. - Jean-claude Baudet A\u00e9ronautique",
    "wof:placetype":"venue"
},
  "geometry": {"coordinates":[4.14743,43.753586],"type":"Point"}
}