{
  "type": "Feature",
  "properties": {
    "addr:full":"9 Villa De La Pr\u00e9voyance 93400 St Ouen Ile de France 93400",
    "addr:housenumber":"9",
    "addr:postcode":"93400;93400",
    "addr:street":"Villa De La Pre\u0301Voyance;St;Ile De France",
    "iso:country":"FR",
    "sg:address":"9 Villa De La Pr\u00e9voyance 93400 St Ouen",
    "sg:classifiers":[
        {
            "category":"Professional",
            "subcategory":"Engineering",
            "type":"Services"
        }
    ],
    "sg:phone":"+33 1 40 11 09 10",
    "sg:postcode":"93400",
    "sg:province":"Ile de France",
    "sg:tags":[
        "machine",
        "-",
        "mechanical"
    ],
    "wof:name":"Albasini Freres",
    "wof:placetype":"venue"
},
  "geometry": {"coordinates":[2.334922,48.906097],"type":"Point"}
}