{
  "type": "Feature",
  "properties": {
    "iso:country":"FR",
    "sg:address":"Rn 15 76190 Valliquerville",
    "sg:classifiers":[
        {
            "category":"Shopping",
            "subcategory":"Crafts & Fabrics",
            "type":"Retail Goods"
        }
    ],
    "sg:phone":"+33 2 32 70 42 20",
    "sg:postcode":"76190",
    "sg:province":"Haute Normandie",
    "sg:tags":[
        "textile",
        "clothing"
    ],
    "wof:name":"Techni Lin Sa",
    "wof:placetype":"venue"
},
  "geometry": {"coordinates":[0.795155,49.553596],"type":"Point"}
}