{
  "type": "Feature",
  "properties": {
    "addr:full":"Le Fayet 01360 B\u00e9ligneux Rhone-Alpes 01360",
    "addr:postcode":"01360;01360",
    "addr:street":"Le Fayet;Rhone-Alpes",
    "iso:country":"FR",
    "sg:address":"Le Fayet 01360 B\u00e9ligneux",
    "sg:orig_category":"Non-Classified Establishments",
    "sg:phone":"+33 4 78 89 00 24",
    "sg:postcode":"01360",
    "sg:province":"Rhone-Alpes",
    "wof:name":"B.l.m. S.a. -b\u00e9ligneux Location Mat\u00e9riels",
    "wof:placetype":"venue"
},
  "geometry": {"coordinates":[5.125896,45.869102],"type":"Point"}
}