{
  "type": "Feature",
  "properties": {
    "addr:full":"Les Grandes Auges 42460 Coutouvre Rhone-Alpes 42460",
    "addr:postcode":"42460;42460",
    "addr:street":"Les Grandes Auges;Rhone-Alpes",
    "iso:country":"FR",
    "sg:address":"Les Grandes Auges 42460 Coutouvre",
    "sg:classifiers":[
        {
            "category":"Shopping",
            "subcategory":"Clothing, Apparel, & Fashions",
            "type":"Retail Goods"
        }
    ],
    "sg:phone":"+33 4 77 66 22 96",
    "sg:postcode":"42460",
    "sg:province":"Rhone-Alpes",
    "sg:tags":[
        "textile",
        "clothing",
        "clothes"
    ],
    "wof:name":"Sarl Tricotage Duinat",
    "wof:placetype":"venue"
},
  "geometry": {"coordinates":[4.201145,46.073025],"type":"Point"}
}