{
  "type": "Feature",
  "properties": {
    "iso:country":"FR",
    "sg:address":"Rte d'Uz\u00e8s",
    "sg:city":"Al\u00e8s",
    "sg:orig_category":"Non-Classified Establishments",
    "sg:phone":"+33 4 66 86 15 20",
    "sg:postcode":"30100",
    "sg:province":"Languedoc-Roussillon",
    "wof:name":"Le Froid C\u00e9venol S.a.r.l.",
    "wof:placetype":"venue"
},
  "geometry": {"coordinates":[4.098727,44.115372],"type":"Point"}
}