{
  "type": "Feature",
  "properties": {
    "addr:full":"2750, Rte de Montpellier, 30000 N\u00eemes Languedoc-Roussillon",
    "addr:housenumber":"2750",
    "addr:postcode":"30000",
    "addr:street":"Rte De Montpellier",
    "iso:country":"FR",
    "sg:address":"2750, Rte de Montpellier, 30000 N\u00eemes",
    "sg:orig_category":"Non-Classified Establishments",
    "sg:phone":"+33 4 66 04 28 04",
    "sg:province":"Languedoc-Roussillon",
    "wof:name":"Fenwick-linde S.a.r.l.",
    "wof:placetype":"venue"
},
  "geometry": {"coordinates":[4.328679,43.810188],"type":"Point"}
}