{
  "type": "Feature",
  "properties": {
    "addr:full":"138 Av Jean Jaur\u00e8s 95100 Argenteuil Ile de France 95100",
    "addr:postcode":"95100;ile;95100",
    "addr:street":"138 Av Jean Jaure\u0300S;France",
    "iso:country":"FR",
    "sg:address":"138 Av Jean Jaur\u00e8s 95100 Argenteuil",
    "sg:classifiers":[
        {
            "category":"Shopping",
            "subcategory":"Hobbies, Toys, & Games",
            "type":"Retail Goods"
        }
    ],
    "sg:phone":"+33 1 39 98 98 98",
    "sg:postcode":"95100",
    "sg:province":"Ile de France",
    "sg:tags":[
        "product",
        "miscellaneous",
        "entertainment"
    ],
    "wof:name":"Lansay France",
    "wof:placetype":"venue"
},
  "geometry": {"coordinates":[2.226112,48.940384],"type":"Point"}
}