{
  "type": "Feature",
  "properties": {
    "addr:full":"Les Moulins Saint Babel Auvergne 63500",
    "addr:postcode":"63500",
    "iso:country":"FR",
    "sg:address":"Les Moulins",
    "sg:city":"Saint Babel",
    "sg:orig_category":"Non-Classified Establishments",
    "sg:phone":"+33 4 73 71 55 43",
    "sg:postcode":"63500",
    "sg:province":"Auvergne",
    "wof:name":"Etablissements Lagreulet S.a.",
    "wof:placetype":"venue"
},
  "geometry": {"coordinates":[3.311355,45.604355],"type":"Point"}
}