{
  "type": "Feature",
  "properties": {
    "addr:full":"414, Bd de la Madeleine, 06000 Nice Provence-Alpes-C\u00f4te d'Azur",
    "addr:housenumber":"414",
    "addr:postcode":"06000",
    "addr:street":"Bd De La Madeleine",
    "iso:country":"FR",
    "sg:address":"414, Bd de la Madeleine, 06000 Nice",
    "sg:orig_category":"Unclassifiable Establishments",
    "sg:phone":"+33 4 93 97 69 00",
    "sg:province":"Provence-Alpes-C\u00f4te d'Azur",
    "wof:name":"T.v.i. S.a.r.l. - Technique Vapeur Industrielle",
    "wof:placetype":"venue"
},
  "geometry": {"coordinates":[7.224111,43.7164],"type":"Point"}
}