{
  "type": "Feature",
  "properties": {
    "addr:full":"8 - 10 R Henri Barbusse 94200 Ivry Sur Seine Ile de France",
    "addr:housenumber":"10 r",
    "addr:postcode":"94200",
    "addr:street":"8;Henri Barbusse",
    "iso:country":"FR",
    "sg:address":"8 - 10 R Henri Barbusse 94200 Ivry Sur Seine",
    "sg:classifiers":[
        {
            "category":"Professional",
            "subcategory":"Printing & Photocopies",
            "type":"Services"
        }
    ],
    "sg:phone":"+33 1 46 58 65 44",
    "sg:province":"Ile de France",
    "sg:tags":[
        "publishing"
    ],
    "wof:name":"Etablissements Andre Leconte Sa",
    "wof:placetype":"venue"
},
  "geometry": {"coordinates":[2.378629,48.809967],"type":"Point"}
}