{
  "type": "Feature",
  "properties": {
    "iso:country":"FR",
    "sg:address":"B.P. 1404",
    "sg:city":"Colmar C\u00e9dex",
    "sg:orig_category":"Non-Classified Establishments",
    "sg:phone":"+33 3 89 41 11 50",
    "sg:postcode":"68014",
    "sg:province":"Alsace",
    "wof:name":"Tout Pour Le B\u00e2timent Justin Bleger S.a.s.",
    "wof:placetype":"venue"
},
  "geometry": {"coordinates":[7.36206,48.08844],"type":"Point"}
}