{
  "type": "Feature",
  "properties": {
    "addr:full":"R De La Butte Du Moulin 77090 Coll\u00e9gien Ile de France 77090",
    "addr:postcode":"77090;77090",
    "addr:street":"Ile De France",
    "iso:country":"FR",
    "sg:address":"R De La Butte Du Moulin 77090 Coll\u00e9gien",
    "sg:classifiers":[
        {
            "category":"Home & Garden",
            "subcategory":"Furniture",
            "type":"Retail Goods"
        }
    ],
    "sg:phone":"+33 1 60 05 24 54",
    "sg:postcode":"77090",
    "sg:province":"Ile de France",
    "sg:tags":[
        "household",
        "wood"
    ],
    "wof:name":"Jardins Et Loisirs Sarl",
    "wof:placetype":"venue"
},
  "geometry": {"coordinates":[2.679133,48.828156],"type":"Point"}
}