{
  "type": "Feature",
  "properties": {
    "addr:full":"Zac Du Champ Bossu 71600 Paray Le Monial Varenne-Saint-Germain Bourgogne 71600",
    "addr:postcode":"71600;71600",
    "addr:street":"Zac Du Champ Bossu",
    "iso:country":"FR",
    "sg:address":"Zac Du Champ Bossu 71600 Paray Le Monial",
    "sg:city":"Varenne-Saint-Germain",
    "sg:classifiers":[
        {
            "category":"Shopping",
            "type":"Retail Goods"
        }
    ],
    "sg:phone":"+33 3 85 81 50 20",
    "sg:postcode":"71600",
    "sg:province":"Bourgogne",
    "sg:tags":[
        "metallurgy",
        "finished",
        "-",
        "metalworking",
        "metallic"
    ],
    "wof:name":"Ste Parodienne Construction Metallique",
    "wof:placetype":"venue"
},
  "geometry": {"coordinates":[4.119105,46.452839],"type":"Point"}
}