{
  "type": "Feature",
  "properties": {
    "addr:full":"chemin de Beauversant 69230 St Genis Laval Rhone-Alpes 69230",
    "addr:postcode":"69230;69230",
    "addr:street":"Chemin De Beauversant;Genis;Rhone-Alpes",
    "iso:country":"FR",
    "sg:address":"chemin de Beauversant 69230 St Genis Laval",
    "sg:classifiers":[
        {
            "category":"Professional",
            "type":"Services"
        }
    ],
    "sg:phone":"+33 4 78 56 99 99",
    "sg:postcode":"69230",
    "sg:province":"Rhone-Alpes",
    "sg:tags":[
        "transport"
    ],
    "wof:name":"Piegay Freres Transports S.a.",
    "wof:placetype":"venue"
},
  "geometry": {"coordinates":[4.77744,45.696766],"type":"Point"}
}