{
  "type": "Feature",
  "properties": {
    "addr:full":"12 rue de la Lib\u00e9ration 55300 Dompcevrin Lorraine",
    "addr:housenumber":"12",
    "addr:postcode":"55300",
    "addr:street":"Rue De La Libe\u0301Ration",
    "iso:country":"FR",
    "sg:address":"12 rue de la Lib\u00e9ration 55300 Dompcevrin",
    "sg:classifiers":[
        {
            "category":"Manufacturing",
            "subcategory":"Rubber & Plastics",
            "type":"Manufacturing & Wholesale Goods"
        }
    ],
    "sg:phone":"+33 3 29 90 19 04",
    "sg:province":"Lorraine",
    "sg:tags":[
        "silicone",
        "article"
    ],
    "wof:name":"Sereca Sarl",
    "wof:placetype":"venue"
},
  "geometry": {"coordinates":[5.489985,48.931339],"type":"Point"}
}