{
  "type": "Feature",
  "properties": {
    "iso:country":"FR",
    "sg:address":"Site Mcc Europole De Sarreguemines 57910 Hambach",
    "sg:classifiers":[
        {
            "category":"Autos & Motor Vehicles",
            "subcategory":"Automobile Sales",
            "type":"Retail Goods"
        }
    ],
    "sg:phone":"+33 3 87 28 26 50",
    "sg:province":"Lorraine",
    "sg:tags":[
        "equipment",
        "transport"
    ],
    "wof:name":"Uniport",
    "wof:placetype":"venue"
},
  "geometry": {"coordinates":[7.034485,49.047215],"type":"Point"}
}