{
  "type": "Feature",
  "properties": {
    "addr:full":"CROIX DE FEROLLES LA 77173 CHEVRY COSSIGNY Ile de France 77173",
    "addr:postcode":"77173;ile;77173",
    "addr:street":"La;France",
    "iso:country":"FR",
    "sg:address":"CROIX",
    "sg:city":"DE FEROLLES LA 77173 CHEVRY COSSIGNY",
    "sg:orig_category":"Miscellaneous Products",
    "sg:phone":"+33 1 64 05 20 23",
    "sg:postcode":"77173",
    "sg:province":"Ile de France",
    "wof:name":"Brosseries Thomas",
    "wof:placetype":"venue"
},
  "geometry": {"coordinates":[2.65364,48.722618],"type":"Point"}
}