{
  "type": "Feature",
  "properties": {
    "iso:country":"FR",
    "sg:address":"Rue Auguste Perret - ZA des Greffi\u00e8res",
    "sg:city":"Lagord",
    "sg:orig_category":"Non-Classified Establishments",
    "sg:phone":"+33 5 46 67 39 00",
    "sg:postcode":"17140",
    "sg:province":"Poitou-Charentes",
    "wof:name":"Larime S.a.",
    "wof:placetype":"venue"
},
  "geometry": {"coordinates":[-1.152969,46.190434],"type":"Point"}
}