{
  "type": "Feature",
  "properties": {
    "addr:full":"Les Salins 01750 Replonges Picardie",
    "addr:postcode":"01750",
    "iso:country":"FR",
    "sg:address":"Les Salins 01750 Replonges",
    "sg:classifiers":[
        {
            "category":"Bakery",
            "type":"Food & Drink"
        }
    ],
    "sg:phone":"+33 3 85 31 03 56",
    "sg:province":"Picardie",
    "sg:tags":[
        "cake",
        "product",
        "related",
        "bread"
    ],
    "wof:name":"Panavi Holding Production",
    "wof:placetype":"venue"
},
  "geometry": {"coordinates":[4.878369,46.317699],"type":"Point"}
}