{
  "type": "Feature",
  "properties": {
    "addr:full":"6 Rue Louis Philippe 92200 Neuilly Sur Seine Ile de France 92200",
    "addr:housenumber":"6",
    "addr:postcode":"92200;92200",
    "addr:street":"Rue Louis Philippe",
    "iso:country":"FR",
    "sg:address":"6 Rue Louis Philippe 92200 Neuilly Sur Seine",
    "sg:classifiers":[
        {
            "category":"Shopping",
            "subcategory":"Computers & Home Electronics",
            "type":"Retail Goods"
        }
    ],
    "sg:phone":"+33 1 47 47 60 20",
    "sg:postcode":"92200",
    "sg:province":"Ile de France",
    "sg:tags":[
        "household",
        "appliance",
        "telecommunication",
        "audio-visual"
    ],
    "wof:name":"Technifrance",
    "wof:placetype":"venue"
},
  "geometry": {"coordinates":[2.271897,48.882084],"type":"Point"}
}