{
  "type": "Feature",
  "properties": {
    "iso:country":"FR",
    "sg:address":"1 Rue Des Grands Pres Zac Du Chanois 54280 Seichamps",
    "sg:classifiers":[
        {
            "category":"Home & Garden",
            "subcategory":"Furniture",
            "type":"Retail Goods"
        }
    ],
    "sg:phone":"+33 3 83 29 57 68",
    "sg:province":"Lorraine",
    "sg:tags":[
        "wood"
    ],
    "wof:name":"Cenpac Sa",
    "wof:placetype":"venue"
},
  "geometry": {"coordinates":[6.255398,48.715652],"type":"Point"}
}