{
  "type": "Feature",
  "properties": {
    "iso:country":"FR",
    "sg:address":"84450 St Saturnin Les Avignon",
    "sg:classifiers":[
        {
            "category":"Food & Beverages",
            "subcategory":"Groceries & Convenience Stores",
            "type":"Retail Goods"
        }
    ],
    "sg:phone":"+33 4 90 22 47 04",
    "sg:province":"Aquitaine",
    "sg:tags":[
        "product",
        "grain",
        "cereal",
        "related"
    ],
    "wof:name":"Minoterie Tarascon",
    "wof:placetype":"venue"
},
  "geometry": {"coordinates":[4.94452,43.953579],"type":"Point"}
}