{
  "type": "Feature",
  "properties": {
    "addr:full":"10 Pl Audissred 10001 Troyes Bourgogne",
    "addr:housenumber":"10",
    "addr:postcode":"10001",
    "addr:street":"Pl Audissred",
    "iso:country":"FR",
    "sg:address":"10 Pl Audissred 10001 Troyes",
    "sg:classifiers":[
        {
            "category":"Sports & Exercise",
            "subcategory":"Sports Center",
            "type":"Entertainment"
        }
    ],
    "sg:phone":"+33 3 25 43 70 00",
    "sg:province":"Bourgogne",
    "sg:tags":[
        "game"
    ],
    "wof:name":"Chambre De Commerce Et D'industrie",
    "wof:placetype":"venue"
},
  "geometry": {"coordinates":[4.074345,48.297874],"type":"Point"}
}