{
  "type": "Feature",
  "properties": {
    "iso:country":"FR",
    "sg:address":"4 rue du commerce 49400 Saumur",
    "sg:classifiers":[
        {
            "category":"Manufacturing",
            "subcategory":"Rubber & Plastics",
            "type":"Manufacturing & Wholesale Goods"
        }
    ],
    "sg:phone":"+33 2 41 50 45 18",
    "sg:province":"Pays de Loire",
    "sg:tags":[
        "technical",
        "parts"
    ],
    "wof:name":"S.p.m. Sa",
    "wof:placetype":"venue"
},
  "geometry": {"coordinates":[-0.09794,47.264408],"type":"Point"}
}