{
  "type": "Feature",
  "properties": {
    "addr:full":"Chabrits 48000 Mende Languedoc-Roussillon",
    "addr:postcode":"48000",
    "addr:street":"Chabrits",
    "iso:country":"FR",
    "sg:address":"Chabrits 48000 Mende",
    "sg:orig_category":"Non-Classified Establishments",
    "sg:phone":"+33 4 66 65 35 97",
    "sg:province":"Languedoc-Roussillon",
    "wof:name":"Meyrueix Et Fils S.a.r.l.",
    "wof:placetype":"venue"
},
  "geometry": {"coordinates":[3.455804,44.532829],"type":"Point"}
}