{
  "type": "Feature",
  "properties": {
    "addr:full":"Findrol 74130 Contamine sur Arve Rhone-Alpes",
    "addr:postcode":"74130",
    "addr:street":"Findrol;Arve Rhone-Alpes",
    "iso:country":"FR",
    "sg:address":"Findrol 74130 Contamine sur Arve",
    "sg:orig_category":"Non-Classified Establishments",
    "sg:phone":"+33 4 50 03 62 12",
    "sg:province":"Rhone-Alpes",
    "wof:name":"Pinget Fran\u00e7ois Et Fils S.a.r.l.",
    "wof:placetype":"venue"
},
  "geometry": {"coordinates":[6.31955,46.14666],"type":"Point"}
}