{
  "type": "Feature",
  "properties": {
    "iso:country":"FR",
    "sg:address":"B.P. 26, 95501 Gonesse C\u00e9dex^^Impasse Louis L\u00e9pine - ZAC de la Grande Vall\u00e9e, 95500 Gonesse",
    "sg:orig_category":"Non-Classified Establishments",
    "sg:phone":"+33 1 34 07 98 00",
    "sg:postcode":"95500",
    "sg:province":"Ile de France",
    "wof:name":"Actilas Actijet S.a.r.l.",
    "wof:placetype":"venue"
},
  "geometry": {"coordinates":[2.449633,48.986462],"type":"Point"}
}