{
  "type": "Feature",
  "properties": {
    "addr:full":"18 Bd Andr\u00e9 Maginot 77300 Fontainebleau Ile de France 77300",
    "addr:housenumber":"18",
    "addr:postcode":"77300;ile;77300",
    "addr:street":"Bd Andre\u0301 Maginot;France",
    "iso:country":"FR",
    "sg:address":"18 Bd Andr\u00e9 Maginot 77300 Fontainebleau",
    "sg:classifiers":[
        {
            "category":"Professional",
            "subcategory":"Business Services",
            "type":"Services"
        }
    ],
    "sg:phone":"+33 1 64 22 24 89",
    "sg:postcode":"77300",
    "sg:province":"Ile de France",
    "sg:tags":[
        "training",
        "advice"
    ],
    "wof:name":"Ogec Jeanne D Arc Saint Aspais",
    "wof:placetype":"venue"
},
  "geometry": {"coordinates":[2.689498,48.405941],"type":"Point"}
}