{
  "type": "Feature",
  "properties": {
    "addr:full":"Route de Sille 72350 BRULON Pays de Loire 72350",
    "addr:postcode":"72350;72350",
    "addr:street":"Route De Sille;Brulon",
    "iso:country":"FR",
    "sg:address":"Route de Sille 72350 BRULON",
    "sg:classifiers":[
        {
            "category":"Shopping",
            "subcategory":"Baby Store",
            "type":"Retail Goods"
        }
    ],
    "sg:phone":"+33 2 43 92 46 28",
    "sg:postcode":"72350",
    "sg:province":"Pays de Loire",
    "sg:tags":[
        "clothing"
    ],
    "wof:name":"Emile Et Julien Sa",
    "wof:placetype":"venue"
},
  "geometry": {"coordinates":[-0.231729,47.969955],"type":"Point"}
}