{
  "type": "Feature",
  "properties": {
    "addr:full":"Fbg de Niederbronn Reichshoffen Alsace 67110",
    "addr:postcode":"67110",
    "addr:street":"Reichshoffen",
    "iso:country":"FR",
    "sg:address":"Fbg de Niederbronn",
    "sg:city":"Reichshoffen",
    "sg:orig_category":"Non-Classified Establishments",
    "sg:phone":"+33 3 88 80 86 30",
    "sg:postcode":"67110",
    "sg:province":"Alsace",
    "wof:name":"Fehr Alsace-nord B\u00e9ton S.a.",
    "wof:placetype":"venue"
},
  "geometry": {"coordinates":[7.651998,48.93808],"type":"Point"}
}