{
  "type": "Feature",
  "properties": {
    "iso:country":"FR",
    "sg:address":"374 rue de Kerlo 56850 Caudan",
    "sg:city":"Caudan",
    "sg:classifiers":[
        {
            "category":"Manufacturing",
            "subcategory":"Rubber & Plastics",
            "type":"Manufacturing & Wholesale Goods"
        }
    ],
    "sg:phone":"+33 2 97 81 16 00",
    "sg:postcode":"56850",
    "sg:province":"Bretagne",
    "sg:tags":[
        "technical",
        "part",
        "transparent"
    ],
    "wof:name":"Pps International Sa",
    "wof:placetype":"venue"
},
  "geometry": {"coordinates":[-3.330429,47.783302],"type":"Point"}
}