{
  "type": "Feature",
  "properties": {
    "iso:country":"FR",
    "sg:address":"Zi Du Cardonnoy 76390 Aumale",
    "sg:classifiers":[
        {
            "category":"Manufacturing",
            "subcategory":"Metals",
            "type":"Manufacturing & Wholesale Goods"
        }
    ],
    "sg:phone":"+33 2 35 93 43 61",
    "sg:postcode":"76390",
    "sg:province":"Haute Normandie",
    "sg:tags":[
        "metallurgy",
        "steel",
        "metalworking"
    ],
    "wof:name":"Bou\u00c9",
    "wof:placetype":"venue"
},
  "geometry": {"coordinates":[1.753135,49.767895],"type":"Point"}
}