{
  "type": "Feature",
  "properties": {
    "addr:full":"ZA la Palun Buis les Baronnies Rhone-Alpes 26170",
    "addr:postcode":"26170",
    "addr:street":"Za La Palun Buis Les;Rhone-Alpes",
    "iso:country":"FR",
    "sg:address":"ZA la Palun",
    "sg:city":"Buis les Baronnies",
    "sg:orig_category":"Unclassifiable Establishments",
    "sg:phone":"+33 4 75 28 02 92",
    "sg:postcode":"26170",
    "sg:province":"Rhone-Alpes",
    "wof:name":"F.m.g. S.a.",
    "wof:placetype":"venue"
},
  "geometry": {"coordinates":[5.272175,44.275398],"type":"Point"}
}