{
  "type": "Feature",
  "properties": {
    "addr:full":"R De La Fronti\u00e8re 57490 Carling Lorraine 57490",
    "addr:postcode":"57490;57490",
    "iso:country":"FR",
    "sg:address":"R De La Fronti\u00e8re 57490 Carling",
    "sg:classifiers":[
        {
            "category":"Manufacturing",
            "subcategory":"Tools & Machinery",
            "type":"Manufacturing & Wholesale Goods"
        }
    ],
    "sg:phone":"+33 3 87 93 20 66",
    "sg:postcode":"57490",
    "sg:province":"Lorraine",
    "sg:tags":[
        "metallurgy",
        "metalworking"
    ],
    "wof:name":"Cami Sa",
    "wof:placetype":"venue"
},
  "geometry": {"coordinates":[6.723034,49.170605],"type":"Point"}
}