{
  "type": "Feature",
  "properties": {
    "addr:full":"15, Av. Terreblanque - Z.I. Casablanca, 40230 Saint Vincent de Tyrosse B\u00e9nesse-Maremne Aquitaine 40230",
    "addr:postcode":"40230;40230",
    "addr:street":"15 Av. Terreblanque Z.I.",
    "iso:country":"FR",
    "sg:address":"15, Av. Terreblanque - Z.I. Casablanca, 40230 Saint Vincent de Tyrosse",
    "sg:city":"B\u00e9nesse-Maremne",
    "sg:orig_category":"Unclassifiable Establishments",
    "sg:phone":"+33 5 58 77 48 87",
    "sg:postcode":"40230",
    "sg:province":"Aquitaine",
    "wof:name":"Hirica S.a.",
    "wof:placetype":"venue"
},
  "geometry": {"coordinates":[-1.368627,43.60276],"type":"Point"}
}