{
  "type": "Feature",
  "properties": {
    "iso:country":"FR",
    "sg:address":"31 Rue Saint Sever",
    "sg:city":"Rouen",
    "sg:classifiers":[
        {
            "category":"Banks & Credit Unions",
            "subcategory":"Financial Services",
            "type":"Services"
        }
    ],
    "sg:phone":"+33 2 32 81 30 20",
    "sg:postcode":"76100",
    "sg:province":"Haute Normandie",
    "sg:tags":[
        "banking",
        "finance",
        "insurance"
    ],
    "wof:name":"Caisse Regionale De Credit Agricole Mutuel De La Haute Norm (crcamh N)",
    "wof:placetype":"venue"
},
  "geometry": {"coordinates":[1.089039,49.433971],"type":"Point"}
}