{
  "type": "Feature",
  "properties": {
    "iso:country":"FR",
    "sg:address":"7 all\u00e9e Libraire 33610 Cestas",
    "sg:city":"Cestas",
    "sg:classifiers":[
        {
            "category":"Communications",
            "type":"Services"
        }
    ],
    "sg:phone":"+33 5 56 21 81 88",
    "sg:postcode":"33610",
    "sg:province":"Aquitaine",
    "sg:tags":[
        "laser"
    ],
    "wof:name":"Laser Technologies S.a.",
    "wof:placetype":"venue"
},
  "geometry": {"coordinates":[-0.685714,44.741707],"type":"Point"}
}