{
  "type": "Feature",
  "properties": {
    "addr:full":"Zi La Prade Zone Industrielle 33650 St Medard D Eyrans Cabanac-et-Villagrains Aquitaine 33650",
    "addr:housenumber":"cabanac-et-villagrains",
    "addr:postcode":"33650;33650",
    "addr:street":"Zi La Prade Zone Industrielle",
    "iso:country":"FR",
    "sg:address":"Zi La Prade Zone Industrielle 33650 St Medard D Eyrans",
    "sg:city":"Cabanac-et-Villagrains",
    "sg:classifiers":[
        {
            "category":"Shopping",
            "subcategory":"Computers & Home Electronics",
            "type":"Retail Goods"
        }
    ],
    "sg:phone":"+33 5 56 78 48 00",
    "sg:postcode":"33650",
    "sg:province":"Aquitaine",
    "sg:tags":[
        "equipment",
        "electrical",
        "component",
        "electric",
        "electronic"
    ],
    "wof:name":"Cec",
    "wof:placetype":"venue"
},
  "geometry": {"coordinates":[-0.508946,44.717876],"type":"Point"}
}