{
  "type": "Feature",
  "properties": {
    "iso:country":"FR",
    "sg:address":"Av De Ouagadougou 86200 Loudun",
    "sg:classifiers":[
        {
            "category":"Manufacturing",
            "subcategory":"Metals",
            "type":"Manufacturing & Wholesale Goods"
        }
    ],
    "sg:phone":"+33 5 49 98 80 60",
    "sg:postcode":"86200",
    "sg:province":"Poitou-Charentes",
    "sg:tags":[
        "metallurgy",
        "metalworking",
        "processing"
    ],
    "wof:name":"M3m",
    "wof:placetype":"venue"
},
  "geometry": {"coordinates":[0.0889,47.019047],"type":"Point"}
}