{
  "type": "Feature",
  "properties": {
    "iso:country":"FR",
    "sg:address":"B.P. 35, 78540 Vernouillet^^Rue des Entrepreneurs - ZI de la Grosse Pierre, 78540 Vernouillet",
    "sg:orig_category":"Non-Classified Establishments",
    "sg:phone":"+33 1 39 71 77 63",
    "sg:postcode":"78540",
    "sg:province":"Ile de France",
    "wof:name":"Brosse Vachette S.a.",
    "wof:placetype":"venue"
},
  "geometry": {"coordinates":[1.98695,48.974518],"type":"Point"}
}