{
  "type": "Feature",
  "properties": {
    "addr:full":"49 Rue Germain 69006 Lyon Rhone-Alpes",
    "addr:housenumber":"49",
    "addr:postcode":"69006",
    "addr:street":"Rue Germain",
    "iso:country":"FR",
    "sg:address":"49 Rue Germain 69006 Lyon",
    "sg:classifiers":[
        {
            "category":"Manufacturing",
            "subcategory":"Jewelry",
            "type":"Manufacturing & Wholesale Goods"
        }
    ],
    "sg:phone":"+33 4 78 24 36 10",
    "sg:province":"Rhone-Alpes",
    "sg:tags":[
        "product",
        "miscellaneous",
        "jewellery"
    ],
    "wof:name":"Auscar",
    "wof:placetype":"venue"
},
  "geometry": {"coordinates":[4.868325,45.765392],"type":"Point"}
}