{
  "type": "Feature",
  "properties": {
    "addr:full":"3 Chemin Thil 01700 St Maurice De Beynost Rhone-Alpes 01700",
    "addr:housenumber":"3",
    "addr:postcode":"01700;01700",
    "addr:street":"Chemin Thil",
    "iso:country":"FR",
    "sg:address":"3 Chemin Thil 01700 St Maurice De Beynost",
    "sg:classifiers":[
        {
            "category":"Professional",
            "subcategory":"Engineering",
            "type":"Services"
        }
    ],
    "sg:phone":"+33 4 78 55 15 81",
    "sg:postcode":"01700",
    "sg:province":"Rhone-Alpes",
    "sg:tags":[
        "machine",
        "-",
        "mechanical"
    ],
    "wof:name":"Ets Mouton Sa",
    "wof:placetype":"venue"
},
  "geometry": {"coordinates":[4.98174,45.825859],"type":"Point"}
}