{
  "type": "Feature",
  "properties": {
    "addr:full":"22d Rue De La Fr\u00e9bardi\u00e8re 35000 Rennes Rennes Bretagne 35000",
    "addr:housenumber":"22d",
    "addr:postcode":"35000;35000",
    "addr:street":"Rue De La Fre\u0301Bardie\u0300Re",
    "iso:country":"FR",
    "sg:address":"22d Rue De La Fr\u00e9bardi\u00e8re 35000 Rennes",
    "sg:city":"Rennes",
    "sg:classifiers":[
        {
            "category":"Professional",
            "subcategory":"Engineering",
            "type":"Services"
        }
    ],
    "sg:phone":"+33 2 99 53 66 53",
    "sg:postcode":"35000",
    "sg:province":"Bretagne",
    "sg:tags":[
        "machine",
        "-",
        "mechanical"
    ],
    "wof:name":"Weishaupt Sa",
    "wof:placetype":"venue"
},
  "geometry": {"coordinates":[-1.628356,48.100479],"type":"Point"}
}