{
  "type": "Feature",
  "properties": {
    "iso:country":"FR",
    "sg:address":"235 Rue Tuboeuf Pa Du Tuboeuf 77170 Brie Comte Robert",
    "sg:classifiers":[
        {
            "category":"Manufacturing",
            "subcategory":"Wood Products",
            "type":"Manufacturing & Wholesale Goods"
        }
    ],
    "sg:phone":"+33 1 60 62 07 55",
    "sg:province":"Ile de France",
    "sg:tags":[
        "professional",
        "furniture"
    ],
    "wof:name":"Bcr Display",
    "wof:placetype":"venue"
},
  "geometry": {"coordinates":[2.612735,48.691845],"type":"Point"}
}