{
  "type": "Feature",
  "properties": {
    "iso:country":"FR",
    "sg:address":"zi la Plaine BP 42 01580 Izernore",
    "sg:classifiers":[
        {
            "category":"Manufacturing",
            "subcategory":"Rubber & Plastics",
            "type":"Manufacturing & Wholesale Goods"
        }
    ],
    "sg:phone":"+33 4 74 49 13 46",
    "sg:postcode":"01580",
    "sg:province":"Rhone-Alpes",
    "sg:tags":[
        "metallurgy",
        "metalworking"
    ],
    "wof:name":"Groupe Dtp",
    "wof:placetype":"venue"
},
  "geometry": {"coordinates":[5.55378,46.218575],"type":"Point"}
}