{
  "type": "Feature",
  "properties": {
    "addr:full":"RN 7 26800 ETOILE SUR RHONE Rhone-Alpes",
    "addr:postcode":"26800",
    "addr:street":"Rn 7",
    "iso:country":"FR",
    "sg:address":"RN 7 26800 ETOILE SUR RHONE",
    "sg:orig_category":"Tank Truck Bodies",
    "sg:phone":"+33 4 75 60 68 29",
    "sg:province":"Rhone-Alpes",
    "wof:name":"Ets Guhur S.a.r.l.",
    "wof:placetype":"venue"
},
  "geometry": {"coordinates":[4.907647,44.794395],"type":"Point"}
}