{
  "type": "Feature",
  "properties": {
    "iso:country":"FR",
    "sg:address":"14, Rue du Canal, 76380 Bapeaume les Rouen",
    "sg:orig_category":"Non-Classified Establishments",
    "sg:phone":"+33 2 35 36 34 91",
    "sg:province":"Haute Normandie",
    "wof:name":"Pub'flock S.a.r.l.",
    "wof:placetype":"venue"
},
  "geometry": {"coordinates":[1.034765,49.4506],"type":"Point"}
}