{
  "type": "Feature",
  "properties": {
    "addr:full":"10, Chemin de la Plaine, 31770 Colomiers Midi Pyr\u00e9n\u00e9es",
    "addr:housenumber":"10",
    "addr:postcode":"31770",
    "addr:street":"Chemin De La Plaine",
    "iso:country":"FR",
    "sg:address":"10, Chemin de la Plaine, 31770 Colomiers",
    "sg:orig_category":"Unclassifiable Establishments",
    "sg:phone":"+33 5 61 30 13 57",
    "sg:province":"Midi Pyr\u00e9n\u00e9es",
    "wof:name":"Brosse Packaging S.a.",
    "wof:placetype":"venue"
},
  "geometry": {"coordinates":[1.298769,43.595959],"type":"Point"}
}