{
  "type": "Feature",
  "properties": {
    "addr:full":"B.P. 335, 59463 Lomme C\u00e9dex^^Av de la Rethonde - Plateforme Multimodale, 59160 Lomme Nord Pas-de-Calais",
    "addr:housenumber":"b.p. 335",
    "addr:postcode":"59463;59160",
    "iso:country":"FR",
    "sg:address":"B.P. 335, 59463 Lomme C\u00e9dex^^Av de la Rethonde - Plateforme Multimodale, 59160 Lomme",
    "sg:orig_category":"Non-Classified Establishments",
    "sg:phone":"+33 3 20 08 18 70",
    "sg:province":"Nord Pas-de-Calais",
    "wof:name":"Millecamps T.p. S.a.",
    "wof:placetype":"venue"
},
  "geometry": {"coordinates":[2.961047,50.643799],"type":"Point"}
}