{
  "type": "Feature",
  "properties": {
    "addr:full":"20 Rue De Labaroche 67100 Strasbourg Strasbourg Alsace 67100",
    "addr:housenumber":"20",
    "addr:postcode":"67100;67100",
    "addr:street":"Rue De Labaroche",
    "iso:country":"FR",
    "sg:address":"20 Rue De Labaroche 67100 Strasbourg",
    "sg:city":"Strasbourg",
    "sg:classifiers":[
        {
            "category":"Home & Garden",
            "subcategory":"Furniture",
            "type":"Retail Goods"
        }
    ],
    "sg:phone":"+33 3 88 39 98 99",
    "sg:postcode":"67100",
    "sg:province":"Alsace",
    "sg:tags":[
        "household",
        "wood"
    ],
    "wof:name":"Smithers Oasis France",
    "wof:placetype":"venue"
},
  "geometry": {"coordinates":[7.77138,48.563507],"type":"Point"}
}