{
  "type": "Feature",
  "properties": {
    "addr:full":"7, All\u00e9e du Closeau, 93160 Noisy le Grand Ile de France",
    "addr:housenumber":"7",
    "addr:postcode":"93160",
    "addr:street":"Alle\u0301E Du Closeau",
    "iso:country":"FR",
    "sg:address":"7, All\u00e9e du Closeau, 93160 Noisy le Grand",
    "sg:orig_category":"Unclassifiable Establishments",
    "sg:phone":"+33 1 45 92 18 18",
    "sg:province":"Ile de France",
    "wof:name":"A.g.s. S.a.",
    "wof:placetype":"venue"
},
  "geometry": {"coordinates":[2.575056,48.836205],"type":"Point"}
}