{
  "type": "Feature",
  "properties": {
    "addr:full":"Rue du Caporal Maupas Cherbourg Basse Normandie 50100",
    "addr:postcode":"50100",
    "addr:street":"Rue Du Caporal Maupas Cherbourg Basse",
    "iso:country":"FR",
    "sg:address":"Rue du Caporal Maupas",
    "sg:city":"Cherbourg",
    "sg:orig_category":"Unclassifiable Establishments",
    "sg:phone":"+33 2 33 23 43 43",
    "sg:postcode":"50100",
    "sg:province":"Basse Normandie",
    "wof:name":"Masselin S.a.s.",
    "wof:placetype":"venue"
},
  "geometry": {"coordinates":[-1.616124,49.640484],"type":"Point"}
}