{
  "type": "Feature",
  "properties": {
    "addr:full":"B.P. 35, 67891 Niederbronn C\u00e9dex^^Rte de Strasbourg, 67110 Reichshoffen Reichshoffen Alsace 67110",
    "addr:postcode":"67891;67110;67110",
    "addr:street":"B.P. 35;Strasbourg",
    "iso:country":"FR",
    "sg:address":"B.P. 35, 67891 Niederbronn C\u00e9dex^^Rte de Strasbourg, 67110 Reichshoffen",
    "sg:city":"Reichshoffen",
    "sg:orig_category":"Non-Classified Establishments",
    "sg:phone":"+33 3 88 80 25 00",
    "sg:postcode":"67110",
    "sg:province":"Alsace",
    "wof:name":"Alsthom D.d.f. S.a.",
    "wof:placetype":"venue"
},
  "geometry": {"coordinates":[7.663385,48.932232],"type":"Point"}
}