{
  "type": "Feature",
  "properties": {
    "iso:country":"FR",
    "sg:address":"za",
    "sg:city":"Compagnons 66200 Al\u00e9nya",
    "sg:classifiers":[
        {
            "category":"Manufacturing",
            "subcategory":"Metals",
            "type":"Manufacturing & Wholesale Goods"
        }
    ],
    "sg:phone":"+33 4 68 22 82 82",
    "sg:postcode":"66200",
    "sg:province":"Languedoc-Roussillon",
    "sg:tags":[
        "metallurgy",
        "-",
        "metalworking",
        "metallic",
        "machine",
        "engineering",
        "finished",
        "mechanical"
    ],
    "wof:name":"Delonca Concept",
    "wof:placetype":"venue"
},
  "geometry": {"coordinates":[2.98073,42.638664],"type":"Point"}
}