{
  "type": "Feature",
  "properties": {
    "iso:country":"FR",
    "sg:address":"10 quai Charles de Gaulle; Ch\u00e2teaulin",
    "sg:city":"Ch\u00e2teau",
    "sg:classifiers":[
        {
            "category":"Banks & Credit Unions",
            "subcategory":"Bank",
            "type":"Services"
        }
    ],
    "sg:phone":"+33 3398861036",
    "sg:postcode":"71250",
    "sg:province":"Bourgogne",
    "wof:name":"Banque C.i.o.",
    "wof:placetype":"venue"
},
  "geometry": {"coordinates":[-4.092101,48.196255],"type":"Point"}
}