{
  "type": "Feature",
  "properties": {
    "addr:full":"5/9, Rue de l'Etain, 77546 Savigny le Temple C\u00e9dex Lorraine",
    "addr:housenumber":"5 / 9",
    "addr:postcode":"77546",
    "addr:street":"Rue De L'Etain;Ce\u0301Dex",
    "iso:country":"FR",
    "sg:address":"5/9, Rue de l'Etain, 77546 Savigny le Temple C\u00e9dex",
    "sg:orig_category":"Non-Classified Establishments",
    "sg:phone":"+33 1 64 41 60 65",
    "sg:province":"Lorraine",
    "wof:name":"Sofrafix-kkv France",
    "wof:placetype":"venue"
},
  "geometry": {"coordinates":[2.587746,48.590054],"type":"Point"}
}