{
  "type": "Feature",
  "properties": {
    "iso:country":"FR",
    "sg:address":"6, Place du Village des Barbanniers, 92632 Gennevilliers C\u00e9dex",
    "sg:orig_category":"Non-Classified Establishments",
    "sg:phone":"+33 1 41 21 95 95",
    "sg:province":"Limousin",
    "wof:name":"Dap Technologies S.a.",
    "wof:placetype":"venue"
},
  "geometry": {"coordinates":[2.29927,48.933479],"type":"Point"}
}