{
  "type": "Feature",
  "properties": {
    "addr:full":"6 rue du Mont-Blanc 74150 Rumilly Rhone-Alpes",
    "addr:housenumber":"6",
    "addr:postcode":"74150",
    "addr:street":"Rue Du Mont-Blanc",
    "iso:country":"FR",
    "sg:address":"6 rue du Mont-Blanc 74150 Rumilly",
    "sg:classifiers":[
        {
            "category":"Home & Garden",
            "subcategory":"Building Materials",
            "type":"Retail Goods"
        }
    ],
    "sg:phone":"+33 4 50 01 27 56",
    "sg:province":"Rhone-Alpes",
    "sg:tags":[
        "household",
        "cleaning",
        "system"
    ],
    "wof:name":"Sir S.a.r.l.",
    "wof:placetype":"venue"
},
  "geometry": {"coordinates":[5.950442,45.862206],"type":"Point"}
}