{
  "type": "Feature",
  "properties": {
    "iso:country":"FR",
    "sg:address":"47, Chemin de Ranquinat, 31600 Muret",
    "sg:orig_category":"Non-Classified Establishments",
    "sg:phone":"+33 5 61 51 13 16",
    "sg:postcode":"31600",
    "sg:province":"Midi Pyr\u00e9n\u00e9es",
    "wof:name":"Aminios S.a.r.l.",
    "wof:placetype":"venue"
},
  "geometry": {"coordinates":[1.34314,43.464211],"type":"Point"}
}