{
  "type": "Feature",
  "properties": {
    "iso:country":"FR",
    "sg:address":"Zac Actinov 01120 Thil",
    "sg:orig_category":"Sub-Assemblies, Electronic, For Switching Cabinets",
    "sg:phone":"+33 4 78 55 54 09",
    "sg:postcode":"01120",
    "sg:province":"Rhone-Alpes",
    "wof:name":"Airad Sarl",
    "wof:placetype":"venue"
},
  "geometry": {"coordinates":[5.021158,45.81501],"type":"Point"}
}