{
  "type": "Feature",
  "properties": {
    "addr:full":"400, Chemin des Primev\u00e8res, 06250 Mougins Provence-Alpes-C\u00f4te d'Azur",
    "addr:housenumber":"400",
    "addr:postcode":"06250",
    "addr:street":"Chemin Des Primeve\u0300Res",
    "iso:country":"FR",
    "sg:address":"400, Chemin des Primev\u00e8res, 06250 Mougins",
    "sg:orig_category":"Non-Classified Establishments",
    "sg:phone":"+33 4 93 46 80 57",
    "sg:province":"Provence-Alpes-C\u00f4te d'Azur",
    "wof:name":"R.a.s.i. S.a.r.l. - R\u00e9alisation A\u00e9ronautique Sous-traitance Industrie",
    "wof:placetype":"venue"
},
  "geometry": {"coordinates":[6.988925,43.579887],"type":"Point"}
}