{
  "type": "Feature",
  "properties": {
    "addr:full":"10, Place de la Joliette - Les Docks Atrium 10.1, 13002 Marseille Provence-Alpes-C\u00f4te d'Azur",
    "addr:housenumber":"10;10.1",
    "addr:postcode":"13002",
    "addr:street":"Place De La Joliette",
    "iso:country":"FR",
    "sg:address":"10, Place de la Joliette - Les Docks Atrium 10.1, 13002 Marseille",
    "sg:orig_category":"Non-Classified Establishments",
    "sg:phone":"+33 4 91 60 68 51",
    "sg:province":"Provence-Alpes-C\u00f4te d'Azur",
    "wof:name":"So.vi.pa S.a.r.l. - Soci\u00e9t\u00e9 Des Viandes Et Produits Alimentaires",
    "wof:placetype":"venue"
},
  "geometry": {"coordinates":[5.37001,43.296101],"type":"Point"}
}