{
  "type": "Feature",
  "properties": {
    "iso:country":"FR",
    "sg:address":"35 Rue Gambetta 72000 Le Mans",
    "sg:classifiers":[
        {
            "category":"Professional",
            "subcategory":"Printing & Photocopies",
            "type":"Services"
        }
    ],
    "sg:phone":"+33 2 43 21 76 61",
    "sg:province":"Pays de Loire",
    "sg:tags":[
        "publishing"
    ],
    "wof:name":"Ouest France",
    "wof:placetype":"venue"
},
  "geometry": {"coordinates":[0.192936,48.005383],"type":"Point"}
}