{
  "type": "Feature",
  "properties": {
    "addr:full":"8 rue de Verdun 57100 Thionville Lorraine",
    "addr:housenumber":"8",
    "addr:postcode":"57100",
    "addr:street":"Rue De Verdun",
    "iso:country":"FR",
    "sg:address":"8 rue de Verdun 57100 Thionville",
    "sg:classifiers":[
        {
            "category":"Manufacturing",
            "subcategory":"Metals",
            "type":"Manufacturing & Wholesale Goods"
        }
    ],
    "sg:phone":"+33 3 82 82 41 00",
    "sg:province":"Lorraine",
    "sg:tags":[
        "piping"
    ],
    "wof:name":"Groupe Eurosid Sa",
    "wof:placetype":"venue"
},
  "geometry": {"coordinates":[6.159265,49.350834],"type":"Point"}
}