{
  "type": "Feature",
  "properties": {
    "iso:country":"FR",
    "sg:address":"B.P. 105, 74604 Seynod C\u00e9dex^^4, Rte de Branchy, 74600 Seynod",
    "sg:orig_category":"Non-Classified Establishments",
    "sg:phone":"+33 4 50 69 33 73",
    "sg:province":"Rhone-Alpes",
    "wof:name":"Initial S.a.",
    "wof:placetype":"venue"
},
  "geometry": {"coordinates":[6.100926,45.888924],"type":"Point"}
}