{
  "type": "Feature",
  "properties": {
    "addr:full":"82, Rue Paul Vaillant-Couturier, 51100 Reims Champagne",
    "addr:housenumber":"82",
    "addr:postcode":"51100",
    "addr:street":"Rue Paul Vaillant-Couturier",
    "iso:country":"FR",
    "sg:address":"82, Rue Paul Vaillant-Couturier, 51100 Reims",
    "sg:orig_category":"Unclassifiable Establishments",
    "sg:phone":"+33 3 26 87 50 87",
    "sg:province":"Champagne",
    "wof:name":"Onet S.a.",
    "wof:placetype":"venue"
},
  "geometry": {"coordinates":[4.02233,49.268524],"type":"Point"}
}