{
  "type": "Feature",
  "properties": {
    "addr:full":"Za La Croix De La Combes 63610 Besse Et St Anastaise Besse-et-Saint-Anastaise Auvergne 63610",
    "addr:postcode":"63610;63610",
    "addr:street":"Za La Croix De La Combes;St",
    "iso:country":"FR",
    "sg:address":"Za La Croix De La Combes 63610 Besse Et St Anastaise",
    "sg:city":"Besse-et-Saint-Anastaise",
    "sg:classifiers":[
        {
            "category":"Food & Beverages",
            "subcategory":"Dairy",
            "type":"Retail Goods"
        }
    ],
    "sg:phone":"+33 4 73 79 88 88",
    "sg:postcode":"63610",
    "sg:province":"Auvergne",
    "sg:tags":[
        "product",
        "related"
    ],
    "wof:name":"Les Terres D'auvergne",
    "wof:placetype":"venue"
},
  "geometry": {"coordinates":[2.945173,45.509369],"type":"Point"}
}