{
  "type": "Feature",
  "properties": {
    "iso:country":"FR",
    "sg:address":"B.P. 6, 01115 Oyonnax C\u00e9dex^^6, Rue Castellion, 01100 Bellignat",
    "sg:orig_category":"Non-Classified Establishments",
    "sg:phone":"+33 4 74 77 48 47",
    "sg:province":"Rhone-Alpes",
    "wof:name":"T.j.c. S.a.r.l. - Trans Jura Cars",
    "wof:placetype":"venue"
},
  "geometry": {"coordinates":[5.64405,46.24968],"type":"Point"}
}