{
  "type": "Feature",
  "properties": {
    "iso:country":"FR",
    "sg:address":"9, Av. Alexandre Maistrasse, 92500 Rueil Malmaison",
    "sg:orig_category":"Non-Classified Establishments",
    "sg:phone":"+33 1 47 14 00 66",
    "sg:province":"Ile de France",
    "wof:name":"L.c. Support Industriel S.a.r.l.",
    "wof:placetype":"venue"
},
  "geometry": {"coordinates":[2.200417,48.86327],"type":"Point"}
}