{
  "type": "Feature",
  "properties": {
    "addr:full":"5 impasse des Trois Chaussons 69330 Meyzieu Rhone-Alpes",
    "addr:housenumber":"5",
    "addr:postcode":"69330",
    "addr:street":"Impasse Des Trois Chaussons",
    "iso:country":"FR",
    "sg:address":"5 impasse des Trois Chaussons 69330 Meyzieu",
    "sg:orig_category":"Plastic Jointings",
    "sg:phone":"+33 4 72 45 03 45",
    "sg:province":"Rhone-Alpes",
    "wof:name":"Sofacome Sa",
    "wof:placetype":"venue"
},
  "geometry": {"coordinates":[5.027765,45.771095],"type":"Point"}
}