{
  "type": "Feature",
  "properties": {
    "addr:full":"190, Rue Fr\u00e9d\u00e9ric Mistral, 06560 Valbonne Rhone-Alpes",
    "addr:housenumber":"190",
    "addr:postcode":"06560",
    "addr:street":"Rue Fre\u0301De\u0301Ric Mistral",
    "iso:country":"FR",
    "sg:address":"190, Rue Fr\u00e9d\u00e9ric Mistral, 06560 Valbonne",
    "sg:orig_category":"Unclassifiable Establishments",
    "sg:phone":"+33 4 92 96 52 52",
    "sg:province":"Rhone-Alpes",
    "wof:name":"Greta Antipolis",
    "wof:placetype":"venue"
},
  "geometry": {"coordinates":[7.0412,43.621624],"type":"Point"}
}