{
  "type": "Feature",
  "properties": {
    "addr:full":"B.P. 26, 59494 Petite For\u00eat^^308, Rue Laplace - Parc d'Activit\u00e9 Lavoisier, 59410 Petite For\u00eat Nord Pas-de-Calais",
    "addr:postcode":"59494;59410",
    "addr:street":"B.P. 26;Rue Laplace Parc D'Activite \u0301 Lavoisier;Fore\u0302T Nord",
    "iso:country":"FR",
    "sg:address":"B.P. 26, 59494 Petite For\u00eat^^308, Rue Laplace - Parc d'Activit\u00e9 Lavoisier, 59410 Petite For\u00eat",
    "sg:orig_category":"Non-Classified Establishments",
    "sg:phone":"+33 3 27 20 00 60",
    "sg:province":"Nord Pas-de-Calais",
    "wof:name":"Roth S.a.",
    "wof:placetype":"venue"
},
  "geometry": {"coordinates":[3.495697,50.371639],"type":"Point"}
}