{
  "type": "Feature",
  "properties": {
    "iso:country":"FR",
    "sg:address":"ZAC du Mas de Grille Parc Saint Jean - B\u00e2t. 1",
    "sg:city":"Saint Jean de Vedas C\u00e9dex",
    "sg:orig_category":"Non-Classified Establishments",
    "sg:phone":"+33 4 67 07 07 10",
    "sg:postcode":"34433",
    "sg:province":"Basse Normandie",
    "wof:name":"Unib\u00e9ton",
    "wof:placetype":"venue"
},
  "geometry": {"coordinates":[3.851534,43.573048],"type":"Point"}
}