{
  "type": "Feature",
  "properties": {
    "iso:country":"FR",
    "sg:address":"Rue de Fleurenne - ZI",
    "sg:city":"Blanquefort",
    "sg:orig_category":"Unclassifiable Establishments",
    "sg:phone":"+33 5 56 95 51 61",
    "sg:postcode":"33290",
    "sg:province":"Aquitaine",
    "wof:name":"S.a.r.e.f. S.a. - Soci\u00e9t\u00e9 Rasoirs Electriques Fabrication",
    "wof:placetype":"venue"
},
  "geometry": {"coordinates":[-0.634838,44.914902],"type":"Point"}
}