{
  "type": "Feature",
  "properties": {
    "addr:full":"111 Rte De La Paoute 06130 Grasse Rhone-Alpes",
    "addr:housenumber":"111",
    "addr:postcode":"06130",
    "addr:street":"Rte De La Paoute",
    "iso:country":"FR",
    "sg:address":"111 Rte De La Paoute 06130 Grasse",
    "sg:classifiers":[
        {
            "category":"Manufacturing",
            "subcategory":"Rubber & Plastics",
            "type":"Manufacturing & Wholesale Goods"
        }
    ],
    "sg:phone":"+33 4 93 09 14 14",
    "sg:province":"Rhone-Alpes",
    "wof:name":"Paoute Pneus Sarl",
    "wof:placetype":"venue"
},
  "geometry": {"coordinates":[6.95771,43.633224],"type":"Point"}
}