{
  "type": "Feature",
  "properties": {
    "addr:full":"4/6, Rue du Vestiaire, 34000 Montpellier Languedoc-Roussillon 34000",
    "addr:housenumber":"4 / 6",
    "addr:postcode":"34000;34000",
    "addr:street":"Rue Du Vestiaire",
    "iso:country":"FR",
    "sg:address":"4/6, Rue du Vestiaire, 34000 Montpellier",
    "sg:orig_category":"Non-Classified Establishments",
    "sg:phone":"+33 4 67 60 44 60",
    "sg:postcode":"34000",
    "sg:province":"Languedoc-Roussillon",
    "wof:name":"Claude O'sughrue",
    "wof:placetype":"venue"
},
  "geometry": {"coordinates":[3.875082,43.611565],"type":"Point"}
}