{
  "type": "Feature",
  "properties": {
    "addr:full":"2, Rue Columbia - Parc d'Esther, 87100 Limoges Limousin",
    "addr:housenumber":"2",
    "addr:postcode":"87100",
    "addr:street":"Rue Columbia Parc D'Esther",
    "iso:country":"FR",
    "sg:address":"2, Rue Columbia - Parc d'Esther, 87100 Limoges",
    "sg:orig_category":"Unclassifiable Establishments",
    "sg:phone":"+33 5 55 35 09 15",
    "sg:province":"Limousin",
    "wof:name":"Ceric Thermic S.a.",
    "wof:placetype":"venue"
},
  "geometry": {"coordinates":[1.290288,45.862122],"type":"Point"}
}