{
  "type": "Feature",
  "properties": {
    "addr:full":"Mille Rd 27 35520 Melesse Melesse Bretagne 35520",
    "addr:housenumber":"27",
    "addr:postcode":"35520;35520",
    "addr:street":"Mille Rd;Melesse",
    "iso:country":"FR",
    "sg:address":"Mille Rd 27 35520 Melesse",
    "sg:city":"Melesse",
    "sg:classifiers":[
        {
            "category":"Manufacturing",
            "subcategory":"Building Materials",
            "type":"Manufacturing & Wholesale Goods"
        }
    ],
    "sg:phone":"+33 2 99 13 13 00",
    "sg:postcode":"35520",
    "sg:province":"Bretagne",
    "sg:tags":[
        "glass",
        "ceramic"
    ],
    "wof:name":"Keramon",
    "wof:placetype":"venue"
},
  "geometry": {"coordinates":[-1.734432,48.178051],"type":"Point"}
}