{
  "type": "Feature",
  "properties": {
    "iso:country":"FR",
    "sg:address":"84 Rue Grande 77570 Bougligny",
    "sg:classifiers":[
        {
            "category":"Manufacturing",
            "subcategory":"Building Materials",
            "type":"Manufacturing & Wholesale Goods"
        }
    ],
    "sg:phone":"+33 1 64 28 77 01",
    "sg:postcode":"77570",
    "sg:province":"Ile de France",
    "sg:tags":[
        "glass",
        "ceramic"
    ],
    "wof:name":"Siecle Sarl",
    "wof:placetype":"venue"
},
  "geometry": {"coordinates":[2.657017,48.19532],"type":"Point"}
}