{
  "type": "Feature",
  "properties": {
    "iso:country":"FR",
    "sg:address":"24400 Mussidan Sourzac",
    "sg:city":"Sourzac",
    "sg:classifiers":[
        {
            "category":"Home & Garden",
            "subcategory":"Furniture",
            "type":"Retail Goods"
        }
    ],
    "sg:phone":"+33 5 53 81 01 84",
    "sg:postcode":"24400",
    "sg:province":"Aquitaine",
    "sg:tags":[
        "household",
        "wood"
    ],
    "wof:name":"Meubles R Ranouil",
    "wof:placetype":"venue"
},
  "geometry": {"coordinates":[0.36504,45.03511],"type":"Point"}
}