{
  "type": "Feature",
  "properties": {
    "addr:full":"131 avenue de Wagram 75017 Paris Ile de France",
    "addr:housenumber":"131",
    "addr:postcode":"75017",
    "addr:street":"Avenue De Wagram",
    "iso:country":"FR",
    "sg:address":"131 avenue de Wagram 75017 Paris",
    "sg:classifiers":[
        {
            "category":"Sports & Exercise",
            "subcategory":"Athletic Track",
            "type":"Entertainment"
        }
    ],
    "sg:phone":"+33 1 44 40 60 60",
    "sg:province":"Ile de France",
    "sg:tags":[
        "record"
    ],
    "wof:name":"Sony Music Entertainment S.a.",
    "wof:placetype":"venue"
},
  "geometry": {"coordinates":[2.301854,48.883453],"type":"Point"}
}