{
  "type": "Feature",
  "properties": {
    "addr:full":"rue de l'Europe 51300 Marolles Champagne 51300",
    "addr:postcode":"51300;51300",
    "addr:street":"Rue De L'Europe;Champagne",
    "iso:country":"FR",
    "sg:address":"rue de l'Europe 51300 Marolles",
    "sg:orig_category":"Air Deflectors For Passenger Cars",
    "sg:phone":"+33 3 26 73 64 64",
    "sg:postcode":"51300",
    "sg:province":"Champagne",
    "wof:name":"Nobel Plastiques Sa",
    "wof:placetype":"venue"
},
  "geometry": {"coordinates":[4.544489,48.759445],"type":"Point"}
}