{
  "type": "Feature",
  "properties": {
    "iso:country":"FR",
    "sg:address":"Port de Commerce 20290 Bastia",
    "sg:orig_category":"Unclassifiable Establishments",
    "sg:phone":"+33 4 95 31 02 83",
    "sg:province":"Corse",
    "wof:name":"A.m.c. S.a. - Armement Maritime Cyrnos",
    "wof:placetype":"venue"
},
  "geometry": {"coordinates":[-81.149948,37.151981],"type":"Point"}
}