{
  "type": "Feature",
  "properties": {
    "addr:full":"5, Rue du Saule Trapu, 91300 Massy Ile de France",
    "addr:housenumber":"5",
    "addr:postcode":"91300",
    "addr:street":"Rue Du Saule Trapu;Ile De France",
    "iso:country":"FR",
    "sg:address":"5, Rue du Saule Trapu, 91300 Massy",
    "sg:orig_category":"Unclassifiable Establishments",
    "sg:phone":"+33 1 60 13 54 70",
    "sg:province":"Ile de France",
    "wof:name":"Alligator S.a.",
    "wof:placetype":"venue"
},
  "geometry": {"coordinates":[2.301219,48.729248],"type":"Point"}
}