{
  "type": "Feature",
  "properties": {
    "iso:country":"FR",
    "sg:address":"1 Pl De La Republique 67350 Pfaffenhoffen",
    "sg:city":"Pfaffenhoffen",
    "sg:classifiers":[
        {
            "category":"Wholesale",
            "subcategory":"Medical Equipment & Supplies",
            "type":"Manufacturing & Wholesale Goods"
        }
    ],
    "sg:phone":"+33 3 88 72 29 99",
    "sg:postcode":"67350",
    "sg:province":"Alsace",
    "sg:tags":[
        "instrument",
        "health",
        "-",
        "precision"
    ],
    "wof:name":"M. Jung Jean-marie",
    "wof:placetype":"venue"
},
  "geometry": {"coordinates":[7.60783,48.843861],"type":"Point"}
}