{
  "type": "Feature",
  "properties": {
    "addr:full":"1 rue Sainte-Victoire 78000 Versailles Ile de France 78000",
    "addr:housenumber":"1",
    "addr:postcode":"78000;78000",
    "addr:street":"Rue Sainte-Victoire",
    "iso:country":"FR",
    "sg:address":"1 rue Sainte-Victoire 78000 Versailles",
    "sg:classifiers":[
        {
            "category":"Home & Garden",
            "subcategory":"Carpets & Floor Coverings",
            "type":"Retail Goods"
        }
    ],
    "sg:phone":"+33 1 39 02 74 82",
    "sg:postcode":"78000",
    "sg:province":"Ile de France",
    "sg:tags":[
        "carpeting"
    ],
    "wof:name":"Agence Cholleton",
    "wof:placetype":"venue"
},
  "geometry": {"coordinates":[2.131061,48.809498],"type":"Point"}
}