{
  "type": "Feature",
  "properties": {
    "addr:full":"Rte de Saint Saturnin Mori\u00e8res les Avignon Aquitaine 84310",
    "addr:postcode":"84310",
    "addr:street":"Rte De Saint Saturnin Morie\u0300Res Les",
    "iso:country":"FR",
    "sg:address":"Rte de Saint Saturnin",
    "sg:city":"Mori\u00e8res les Avignon",
    "sg:orig_category":"Unclassifiable Establishments",
    "sg:phone":"+33 4 90 31 25 88",
    "sg:postcode":"84310",
    "sg:province":"Aquitaine",
    "wof:name":"Cyanamid Agro S.a.",
    "wof:placetype":"venue"
},
  "geometry": {"coordinates":[4.90244,43.954105],"type":"Point"}
}