{
  "type": "Feature",
  "properties": {
    "iso:country":"FR",
    "sg:address":"lieu dit Lev\u00e9e de Lacrost 71700 Tournus",
    "sg:city":"Tournus",
    "sg:classifiers":[
        {
            "category":"Professional",
            "type":"Services"
        }
    ],
    "sg:phone":"+33 3 85 51 01 35",
    "sg:postcode":"71700",
    "sg:province":"Bourgogne",
    "sg:tags":[
        "transport"
    ],
    "wof:name":"Transports Berthelard S.a.r.l.",
    "wof:placetype":"venue"
},
  "geometry": {"coordinates":[4.830926,46.504631],"type":"Point"}
}