{
  "type": "Feature",
  "properties": {
    "iso:country":"FR",
    "sg:address":"44 rue Pierre Curie 78370 Plaisir",
    "sg:classifiers":[
        {
            "category":"Autos & Motor Vehicles",
            "subcategory":"Fuel & Gas Station",
            "type":"Retail Goods"
        }
    ],
    "sg:phone":"+33 1 30 07 57 57",
    "sg:province":"Ile de France",
    "sg:tags":[
        "restoration",
        "tank"
    ],
    "wof:name":"Panol S.a.",
    "wof:placetype":"venue"
},
  "geometry": {"coordinates":[1.976271,48.80262],"type":"Point"}
}