{
  "type": "Feature",
  "properties": {
    "iso:country":"FR",
    "sg:address":"R Pierre Frapin 16130 Segonzac",
    "sg:classifiers":[
        {
            "category":"Food Court",
            "type":"Food & Drink"
        }
    ],
    "sg:phone":"+33 5 45 83 40 03",
    "sg:postcode":"16130",
    "sg:province":"Poitou-Charentes",
    "sg:tags":[
        "product",
        "related"
    ],
    "wof:name":"Frapin Et Cie",
    "wof:placetype":"venue"
},
  "geometry": {"coordinates":[-0.217734,45.617615],"type":"Point"}
}