{
  "type": "Feature",
  "properties": {
    "iso:country":"FR",
    "sg:address":"Rue Comtesse de Mons",
    "sg:city":"Argenvilliers",
    "sg:orig_category":"Unclassifiable Establishments",
    "sg:phone":"+33 2 37 29 44 60",
    "sg:postcode":"28480",
    "sg:province":"Centre",
    "wof:name":"Fran\u00e7ois Soleille",
    "wof:placetype":"venue"
},
  "geometry": {"coordinates":[0.95782,48.26096],"type":"Point"}
}