{
  "type": "Feature",
  "properties": {
    "iso:country":"FR",
    "sg:address":"52 ave Hoche; Paris; 75008",
    "sg:classifiers":[
        {
            "category":"Banks & Credit Unions",
            "subcategory":"Bank",
            "type":"Services"
        }
    ],
    "sg:phone":"+33 1 47 54 40 40",
    "sg:postcode":"75008",
    "sg:province":"Ile de France",
    "wof:name":"Banque Sanpaolo",
    "wof:placetype":"venue"
},
  "geometry": {"coordinates":[2.298294,48.875381],"type":"Point"}
}