{
  "type": "Feature",
  "properties": {
    "addr:full":"B.P. 21, 63650 La Monnerie le Montel^^Rue de la Rouill\u00e8re, 63650 La Monnerie le Montel Monnerie-le-Montel Auvergne 63650",
    "addr:housenumber":"63650",
    "addr:postcode":"63650;63650",
    "addr:street":"B.P. 21;Monnerie Le Montel^^Rue De La Rouille\u0300Re;Monnerie Le",
    "iso:country":"FR",
    "sg:address":"B.P. 21, 63650 La Monnerie le Montel^^Rue de la Rouill\u00e8re, 63650 La Monnerie le Montel",
    "sg:city":"Monnerie-le-Montel",
    "sg:orig_category":"Non-Classified Establishments",
    "sg:phone":"+33 4 73 51 40 30",
    "sg:postcode":"63650",
    "sg:province":"Auvergne",
    "wof:name":"Etablissements Dumas S.a.r.l.",
    "wof:placetype":"venue"
},
  "geometry": {"coordinates":[3.604876,45.869713],"type":"Point"}
}