{
  "type": "Feature",
  "properties": {
    "iso:country":"FR",
    "sg:address":"3255, Rte des Pyr\u00e9n\u00e9es - ZA du Tr\u00e9ma, 40270 Caz\u00e8res sur l'Adour",
    "sg:city":"Renung",
    "sg:orig_category":"Unclassifiable Establishments",
    "sg:phone":"+33 5 58 71 91 91",
    "sg:postcode":"40270",
    "sg:province":"Aquitaine",
    "wof:name":"S.m.e.e. S.a. - Soci\u00e9t\u00e9 Maintenance De L'eau Et De L'environnemen",
    "wof:placetype":"venue"
},
  "geometry": {"coordinates":[-0.325593,43.765354],"type":"Point"}
}