{
  "type": "Feature",
  "properties": {
    "iso:country":"FR",
    "sg:address":"Rte de Charolles - Bertillon",
    "sg:city":"Saint Bonnet de Joux",
    "sg:orig_category":"Unclassifiable Establishments",
    "sg:phone":"+33 3 85 24 70 94",
    "sg:postcode":"71220",
    "sg:province":"Bourgogne",
    "wof:name":"Bernigal S.a.",
    "wof:placetype":"venue"
},
  "geometry": {"coordinates":[4.43418,46.480934],"type":"Point"}
}