{
  "type": "Feature",
  "properties": {
    "addr:full":"2, Rue Kl\u00e9der, 92300 Levallois Perret Ile de France",
    "addr:housenumber":"2",
    "addr:postcode":"92300;ile",
    "addr:street":"Rue Kle\u0301Der",
    "iso:country":"FR",
    "sg:address":"2, Rue Kl\u00e9der, 92300 Levallois Perret",
    "sg:orig_category":"Unclassifiable Establishments",
    "sg:phone":"+33 1 41 49 18 00",
    "sg:province":"Ile de France",
    "wof:name":"Osis S.a.r.l.",
    "wof:placetype":"venue"
},
  "geometry": {"coordinates":[2.28505,48.890995],"type":"Point"}
}