{
  "type": "Feature",
  "properties": {
    "addr:full":"183 avenue du 18 Juin 1940; Rueil-Malmaison Cedex; 92508 Picardie",
    "addr:housenumber":"183",
    "addr:postcode":"92508",
    "addr:street":"Avenue Du 18 Juin 1940",
    "iso:country":"FR",
    "sg:address":"183 avenue du 18 Juin 1940; Rueil-Malmaison Cedex; 92508",
    "sg:classifiers":[
        {
            "category":"Industrial Area",
            "type":"Public Place"
        }
    ],
    "sg:phone":"+33 1 46 25 60 00",
    "sg:province":"Picardie",
    "sg:tags":[
        "large",
        "private"
    ],
    "wof:name":"Ondeo-degr\u00e9mont",
    "wof:placetype":"venue"
},
  "geometry": {"coordinates":[2.17913,48.877399],"type":"Point"}
}