{
  "type": "Feature",
  "properties": {
    "iso:country":"FR",
    "sg:address":"5, Av. du Parana, 91952 Les Ulis C\u00e9dex",
    "sg:city":"Les Ulis",
    "sg:orig_category":"Non-Classified Establishments",
    "sg:phone":"+33 1 60 92 39 39",
    "sg:postcode":"91940",
    "sg:province":"Ile de France",
    "wof:name":"M.g. S.a.r.l.",
    "wof:placetype":"venue"
},
  "geometry": {"coordinates":[2.197419,48.68066],"type":"Point"}
}