{
  "type": "Feature",
  "properties": {
    "iso:country":"FR",
    "sg:address":"10 boulevard de l'Europe 28500 Vernouillet",
    "sg:city":"Vernouillet",
    "sg:classifiers":[
        {
            "category":"Banks & Credit Unions",
            "subcategory":"Investment Brokerage",
            "type":"Services"
        }
    ],
    "sg:phone":"+33 2 37 46 88 08",
    "sg:postcode":"28500",
    "sg:province":"Centre",
    "sg:tags":[
        "cell",
        "alkaline",
        "manganese"
    ],
    "wof:name":"Ades Eclairage S.a.",
    "wof:placetype":"venue"
},
  "geometry": {"coordinates":[1.44802,48.719109],"type":"Point"}
}