{
  "type": "Feature",
  "properties": {
    "addr:full":"40, Av. de Terroir de France - Immeuble Bercy Exposition, 75611 Paris C\u00e9dex Aquitaine",
    "addr:postcode":"75611",
    "addr:street":"40 Av. De Terroir De France",
    "iso:country":"FR",
    "sg:address":"40, Av. de Terroir de France - Immeuble Bercy Exposition, 75611 Paris C\u00e9dex",
    "sg:orig_category":"Non-Classified Establishments",
    "sg:phone":"+33 1 44 74 29 46",
    "sg:province":"Aquitaine",
    "wof:name":"Hor\u00e9col S.a.r.l.",
    "wof:placetype":"venue"
},
  "geometry": {"coordinates":[2.38681,48.830635],"type":"Point"}
}