{
  "type": "Feature",
  "properties": {
    "iso:country":"FR",
    "sg:address":"3 rue Descartes 28350 ST LUBIN DES JONCHERETS",
    "sg:city":"Dampierre-sur-Avre",
    "sg:orig_category":"Caoutchouc",
    "sg:phone":"+33 2 32 58 10 09",
    "sg:postcode":"28350",
    "sg:province":"Centre",
    "wof:name":"Etancheite Et Frottement J. Massot S.a.",
    "wof:placetype":"venue"
},
  "geometry": {"coordinates":[1.206133,48.759583],"type":"Point"}
}