{
  "type": "Feature",
  "properties": {
    "addr:full":"8, Place Davilla, 11000 Carcassonne Languedoc-Roussillon",
    "addr:housenumber":"8",
    "addr:postcode":"11000",
    "addr:street":"Place Davilla",
    "iso:country":"FR",
    "sg:address":"8, Place Davilla, 11000 Carcassonne",
    "sg:orig_category":"Unclassifiable Establishments",
    "sg:phone":"+33 4 68 10 26 00",
    "sg:province":"Languedoc-Roussillon",
    "wof:name":"B.f.c.c. - Banque Fran\u00e7aise Cr\u00e9dit Coop\u00e9rative",
    "wof:placetype":"venue"
},
  "geometry": {"coordinates":[2.351127,43.210037],"type":"Point"}
}