{
  "type": "Feature",
  "properties": {
    "addr:full":"avenue Didier Daurat 31700 Blagnac Midi Pyr\u00e9n\u00e9es 31700",
    "addr:postcode":"31700;31700",
    "addr:street":"Avenue Didier Daurat",
    "iso:country":"FR",
    "sg:address":"avenue Didier Daurat 31700 Blagnac",
    "sg:classifiers":[
        {
            "category":"Banks & Credit Unions",
            "subcategory":"Investment Brokerage",
            "type":"Services"
        }
    ],
    "sg:phone":"+33 5 61 71 00 67",
    "sg:postcode":"31700",
    "sg:province":"Midi Pyr\u00e9n\u00e9es",
    "sg:tags":[
        "aeronautics",
        "accessory"
    ],
    "wof:name":"Diehl Avionik System Sarl",
    "wof:placetype":"venue"
},
  "geometry": {"coordinates":[1.37925,43.63031],"type":"Point"}
}