{
  "type": "Feature",
  "properties": {
    "iso:country":"FR",
    "sg:address":"Hameau Lucinges 01370 Treffort Cuisiat",
    "sg:orig_category":"Unclassifiable Establishments",
    "sg:phone":"+33 4 74 42 10 50",
    "sg:postcode":"01370",
    "sg:province":"Rhone-Alpes",
    "wof:name":"Adapei-cat",
    "wof:placetype":"venue"
},
  "geometry": {"coordinates":[5.337565,46.298691],"type":"Point"}
}