{
  "type": "Feature",
  "properties": {
    "iso:country":"FR",
    "sg:address":"B.P. 8, 06901 Sophia Antipolis C\u00e9dex^^1208, Rte des Lucioles - Espace Beethoven B\u00e2t. 1, 06560 Sophia",
    "sg:orig_category":"Non-Classified Establishments",
    "sg:phone":"+33 4 93 65 38 38",
    "sg:province":"North Carolina",
    "wof:name":"S.a.a.s. S.a.r.l. - Sophia Antipolis Assistance Et Services",
    "wof:placetype":"venue"
},
  "geometry": {"coordinates":[-79.856499,35.821194],"type":"Point"}
}