{
  "type": "Feature",
  "properties": {
    "addr:full":"21, Rue de l'Estacade, 60200 Compi\u00e8gne Picardie 60200",
    "addr:housenumber":"21",
    "addr:postcode":"60200;60200",
    "addr:street":"Rue De L'Estacade",
    "iso:country":"FR",
    "sg:address":"21, Rue de l'Estacade, 60200 Compi\u00e8gne",
    "sg:orig_category":"Non-Classified Establishments",
    "sg:phone":"+33 3 44 38 49 49",
    "sg:postcode":"60200",
    "sg:province":"Picardie",
    "wof:name":"Espace Info Com S.a.r.l.",
    "wof:placetype":"venue"
},
  "geometry": {"coordinates":[2.832269,49.423462],"type":"Point"}
}