{
  "type": "Feature",
  "properties": {
    "addr:full":"Rue 8\u00e8me Ra 54500 Vandoeuvre L\u00e8s Nancy Lorraine 54500",
    "addr:postcode":"54500;54500",
    "addr:street":"Rue 8E\u0300Me",
    "iso:country":"FR",
    "sg:address":"Rue 8\u00e8me Ra 54500 Vandoeuvre L\u00e8s Nancy",
    "sg:classifiers":[
        {
            "category":"Home & Garden",
            "subcategory":"Furniture",
            "type":"Retail Goods"
        }
    ],
    "sg:phone":"+33 3 83 51 00 99",
    "sg:postcode":"54500",
    "sg:province":"Lorraine",
    "sg:tags":[
        "household",
        "wood"
    ],
    "wof:name":"Rego Distribution (sa)",
    "wof:placetype":"venue"
},
  "geometry": {"coordinates":[6.181393,48.670692],"type":"Point"}
}