{
  "type": "Feature",
  "properties": {
    "iso:country":"FR",
    "sg:address":"22 Chemin Des Presses 06800 Cagnes Sur Mer",
    "sg:classifiers":[
        {
            "category":"Building & Trades",
            "subcategory":"Construction",
            "type":"Services"
        }
    ],
    "sg:phone":"+33 4 92 13 72 20",
    "sg:province":"Franche Comt\u00e9",
    "sg:tags":[
        "work",
        "public"
    ],
    "wof:name":"Entreprise De Travaux Publics Jean Spada",
    "wof:placetype":"venue"
},
  "geometry": {"coordinates":[7.131561,43.672546],"type":"Point"}
}