{
  "type": "Feature",
  "properties": {
    "addr:full":"B.P. 2429, 49024 Angers C\u00e9dex 02^^5, Bd du Mar\u00e9chal Foch, 49000 Angers Pays de Loire 49000",
    "addr:housenumber":"02 ^ ^ 5",
    "addr:postcode":"49024;49000;49000",
    "addr:street":"B.P. 2429;Ce\u0301Dex;Bd Du Mare\u0301Chal Foch",
    "iso:country":"FR",
    "sg:address":"B.P. 2429, 49024 Angers C\u00e9dex 02^^5, Bd du Mar\u00e9chal Foch, 49000 Angers",
    "sg:orig_category":"Non-Classified Establishments",
    "sg:phone":"+33 2 41 81 71 61",
    "sg:postcode":"49000",
    "sg:province":"Pays de Loire",
    "wof:name":"Caisse D'epargne Pr\u00e9voyance Pays De La Loire",
    "wof:placetype":"venue"
},
  "geometry": {"coordinates":[-0.56339,47.46315],"type":"Point"}
}