{
  "type": "Feature",
  "properties": {
    "iso:country":"FR",
    "sg:address":"109 rue L\u00e9on Jouhaux 78500 Sartrouville",
    "sg:classifiers":[
        {
            "category":"Manufacturing",
            "subcategory":"Electronics",
            "type":"Manufacturing & Wholesale Goods"
        }
    ],
    "sg:phone":"+33 1 61 04 46 00",
    "sg:province":"Ile de France",
    "sg:tags":[
        "monitoring",
        "proportion",
        "apparatus",
        "electronic"
    ],
    "wof:name":"Sodimate S.a.",
    "wof:placetype":"venue"
},
  "geometry": {"coordinates":[2.184572,48.945278],"type":"Point"}
}