{
  "type": "Feature",
  "properties": {
    "iso:country":"FR",
    "sg:address":"Zi Parc Logistique Du Port De Normandie Oudalle 76600 Le Havre",
    "sg:classifiers":[
        {
            "category":"Banks & Credit Unions",
            "subcategory":"Investment Brokerage",
            "type":"Services"
        }
    ],
    "sg:phone":"+33 2 35 11 35 65",
    "sg:province":"Haute Normandie",
    "sg:tags":[
        "-",
        "transport",
        "related"
    ],
    "wof:name":"Transcap International",
    "wof:placetype":"venue"
},
  "geometry": {"coordinates":[0.101405,49.493511],"type":"Point"}
}