{
  "type": "Feature",
  "properties": {
    "iso:country":"FR",
    "sg:address":"2 T Rue Denis Papin Za Des Arpents 77680 Roissy En Brie",
    "sg:classifiers":[
        {
            "category":"Autos & Motor Vehicles",
            "subcategory":"Automobile Sales",
            "type":"Retail Goods"
        }
    ],
    "sg:phone":"+33 1 60 28 36 62",
    "sg:postcode":"77680",
    "sg:province":"Ile de France",
    "sg:tags":[
        "equipment",
        "motor-cars",
        "transport"
    ],
    "wof:name":"Armobil",
    "wof:placetype":"venue"
},
  "geometry": {"coordinates":[2.65616,48.790733],"type":"Point"}
}