{
  "type": "Feature",
  "properties": {
    "addr:full":"ZI des Bracots Bons en Chablais Rhone-Alpes 74890",
    "addr:postcode":"74890",
    "addr:street":"Des",
    "iso:country":"FR",
    "sg:address":"ZI des Bracots",
    "sg:city":"Bons en Chablais",
    "sg:orig_category":"Non-Classified Establishments",
    "sg:phone":"+33 4 50 36 19 09",
    "sg:postcode":"74890",
    "sg:province":"Rhone-Alpes",
    "wof:name":"Transports M.c. Express S.a.",
    "wof:placetype":"venue"
},
  "geometry": {"coordinates":[6.37106,46.264935],"type":"Point"}
}