{
  "type": "Feature",
  "properties": {
    "addr:full":"38, Rue Montesquieu, 80000 Amiens Picardie",
    "addr:housenumber":"38",
    "addr:postcode":"80000",
    "addr:street":"Rue Montesquieu",
    "iso:country":"FR",
    "sg:address":"38, Rue Montesquieu, 80000 Amiens",
    "sg:orig_category":"Unclassifiable Establishments",
    "sg:phone":"+33 3 22 66 53 53",
    "sg:province":"Picardie",
    "wof:name":"Lavielle S.a.r.l.",
    "wof:placetype":"venue"
},
  "geometry": {"coordinates":[2.293875,49.905056],"type":"Point"}
}