{
  "type": "Feature",
  "properties": {
    "iso:country":"FR",
    "sg:address":"70, Rue L\u00e9on Gambetta, 93700 Drancy",
    "sg:orig_category":"Non-Classified Establishments",
    "sg:phone":"+33 1 41 50 14 90",
    "sg:province":"Ile de France",
    "wof:name":"T.h.p. S.a.r.l. - Techniques Hygi\u00e8ne Propret\u00e9",
    "wof:placetype":"venue"
},
  "geometry": {"coordinates":[2.429909,48.926979],"type":"Point"}
}