{
  "type": "Feature",
  "properties": {
    "iso:country":"FR",
    "sg:address":"27 avenue Beausejour 60800 Crepy En Valois",
    "sg:classifiers":[
        {
            "category":"Building & Trades",
            "subcategory":"Landscaping Services",
            "type":"Services"
        }
    ],
    "sg:phone":"+33 3 44 94 45 00",
    "sg:postcode":"60800",
    "sg:province":"Picardie",
    "sg:tags":[
        "east-west"
    ],
    "wof:name":"Van Rookhuijzen Sarl",
    "wof:placetype":"venue"
},
  "geometry": {"coordinates":[2.88267,49.231819],"type":"Point"}
}