{
  "type": "Feature",
  "properties": {
    "iso:country":"FR",
    "sg:address":"55, Rue de Savoie - ZI Loire Saint Romain, 69700 Loire sur Rh\u00f4ne",
    "sg:orig_category":"Unclassifiable Establishments",
    "sg:phone":"+33 4 37 20 20 10",
    "sg:postcode":"69700",
    "sg:province":"Rhone-Alpes",
    "wof:name":"Chep France S.a.",
    "wof:placetype":"venue"
},
  "geometry": {"coordinates":[4.813849,45.562035],"type":"Point"}
}