{
  "type": "Feature",
  "properties": {
    "addr:full":"Vaugoust 72170 Piac\u00e9 Pays de Loire",
    "addr:postcode":"72170",
    "addr:street":"Vaugoust",
    "iso:country":"FR",
    "sg:address":"Vaugoust 72170 Piac\u00e9",
    "sg:orig_category":"Unclassifiable Establishments",
    "sg:phone":"+33 2 43 97 02 01",
    "sg:province":"Pays de Loire",
    "wof:name":"Huttepain-bouix S.a.",
    "wof:placetype":"venue"
},
  "geometry": {"coordinates":[0.115412,48.259796],"type":"Point"}
}