{
  "type": "Feature",
  "properties": {
    "addr:full":"53, Rue de Chateaudun, 75311 Paris C\u00e9dex 9 \u00cele-de-France",
    "addr:housenumber":"53",
    "addr:postcode":"75311",
    "addr:street":"Rue De Chateaudun",
    "iso:country":"FR",
    "sg:address":"53, Rue de Chateaudun, 75311 Paris C\u00e9dex 9",
    "sg:orig_category":"Non-Classified Establishments",
    "sg:phone":"+33 1 44 83 74 00",
    "sg:province":"\u00cele-de-France",
    "wof:name":"F.c.i. S.a. - Framatone Connection International",
    "wof:placetype":"venue"
},
  "geometry": {"coordinates":[2.333466,48.876163],"type":"Point"}
}