{
  "type": "Feature",
  "properties": {
    "iso:country":"FR",
    "sg:address":"Av. du Commandant Marchand",
    "sg:city":"Toulon",
    "sg:orig_category":"Non-Classified Establishments",
    "sg:phone":"+33 4 94 24 71 00",
    "sg:postcode":"83000",
    "sg:province":"Bourgogne",
    "wof:name":"Calberson M\u00e9diterrann\u00e9e",
    "wof:placetype":"venue"
},
  "geometry": {"coordinates":[5.938915,43.123131],"type":"Point"}
}