{
  "type": "Feature",
  "properties": {
    "addr:full":"Rue Jean Poulmarch Argenteuil Ile de France 95100",
    "addr:postcode":"95100",
    "addr:street":"Rue Jean Poulmarch;Ile De France",
    "iso:country":"FR",
    "sg:address":"Rue Jean Poulmarch",
    "sg:city":"Argenteuil",
    "sg:orig_category":"Unclassifiable Establishments",
    "sg:phone":"+33 1 39 98 26 26",
    "sg:postcode":"95100",
    "sg:province":"Ile de France",
    "wof:name":"T.v.o. S.a. - Transports Du Val D'oise",
    "wof:placetype":"venue"
},
  "geometry": {"coordinates":[2.212315,48.954556],"type":"Point"}
}