{
  "type": "Feature",
  "properties": {
    "addr:full":"12, Rue Thiers, 51500 Mailly Champagne Champagne",
    "addr:housenumber":"12",
    "addr:postcode":"51500",
    "addr:street":"Rue Thiers",
    "iso:country":"FR",
    "sg:address":"12, Rue Thiers, 51500 Mailly Champagne",
    "sg:orig_category":"Unclassifiable Establishments",
    "sg:phone":"+33 3 26 49 00 99",
    "sg:province":"Champagne",
    "wof:name":"Champagne Fluide Service S.a.r.l.",
    "wof:placetype":"venue"
},
  "geometry": {"coordinates":[4.112707,49.157223],"type":"Point"}
}