{
  "type": "Feature",
  "properties": {
    "iso:country":"FR",
    "sg:address":"24 Rue De Mogador 75009 Paris",
    "sg:classifiers":[
        {
            "category":"Shopping",
            "subcategory":"Clothing, Apparel, & Fashions",
            "type":"Retail Goods"
        }
    ],
    "sg:phone":"+33 1 42 82 13 33",
    "sg:postcode":"75009",
    "sg:province":"Ile de France",
    "sg:tags":[
        "textile",
        "clothing",
        "clothes"
    ],
    "wof:name":"Du Pareil Au Meme",
    "wof:placetype":"venue"
},
  "geometry": {"coordinates":[2.331563,48.875191],"type":"Point"}
}