{
  "type": "Feature",
  "properties": {
    "iso:country":"FR",
    "sg:address":"21 rue Domer 69909 Lyon CEDEX",
    "sg:classifiers":[
        {
            "category":"Banks & Credit Unions",
            "subcategory":"Investment Brokerage",
            "type":"Services"
        }
    ],
    "sg:phone":"+33 4 72 80 70 00",
    "sg:province":"Rhone-Alpes",
    "sg:tags":[
        "bearing",
        "ball"
    ],
    "wof:name":"Michaud Et Chailly Sas",
    "wof:placetype":"venue"
},
  "geometry": {"coordinates":[4.846681,45.747227],"type":"Point"}
}