{
  "type": "Feature",
  "properties": {
    "iso:country":"FR",
    "sg:address":"Avenue Zone Industrielle 06511 CARROS CEDEX",
    "sg:classifiers":[
        {
            "category":"Manufacturing",
            "subcategory":"Chemicals & Compounds",
            "type":"Manufacturing & Wholesale Goods"
        }
    ],
    "sg:phone":"+33 4 92 08 06 08",
    "sg:province":"Corse",
    "sg:tags":[
        "packing",
        "bag-in-box"
    ],
    "wof:name":"Direct 1000 Sa",
    "wof:placetype":"venue"
},
  "geometry": {"coordinates":[7.191765,43.766804],"type":"Point"}
}