{
  "type": "Feature",
  "properties": {
    "iso:country":"FR",
    "sg:address":"Lieudit Courbouvin 51210 Verdon",
    "sg:classifiers":[
        {
            "category":"Manufacturing",
            "subcategory":"Tools & Machinery",
            "type":"Manufacturing & Wholesale Goods"
        }
    ],
    "sg:phone":"+33 3 26 81 16 28",
    "sg:postcode":"51210",
    "sg:province":"Champagne",
    "sg:tags":[
        "environment",
        "equipment",
        "-"
    ],
    "wof:name":"Biome France",
    "wof:placetype":"venue"
},
  "geometry": {"coordinates":[3.60095,48.942696],"type":"Point"}
}