{
  "type": "Feature",
  "properties": {
    "iso:country":"FR",
    "sg:address":"1, Rue Sauveur Durand, 84500 Boll\u00e8ne",
    "sg:orig_category":"Unclassifiable Establishments",
    "sg:phone":"+33 4 74 70 04 87",
    "sg:province":"Champagne",
    "wof:name":"Serge Balat S.a.",
    "wof:placetype":"venue"
},
  "geometry": {"coordinates":[4.757351,44.298737],"type":"Point"}
}