{
  "type": "Feature",
  "properties": {
    "iso:country":"FR",
    "sg:address":"5, Rue Henri Dunant - ZA les Bordes, 91070 Bondoufle",
    "sg:orig_category":"Non-Classified Establishments",
    "sg:phone":"+33 1 60 86 53 53",
    "sg:province":"Ile de France",
    "wof:name":"Pum Paris-normandie S.a.",
    "wof:placetype":"venue"
},
  "geometry": {"coordinates":[2.379516,48.615681],"type":"Point"}
}