{
  "type": "Feature",
  "properties": {
    "addr:full":"B.P. 400, 14914 Caen C\u00e9dex 9^^19, Quai de Juillet, 14000 Caen Caen Basse Normandie 14000",
    "addr:housenumber":"b.p. 400;^ 19",
    "addr:postcode":"14914;14000;14000",
    "addr:street":"Quai De Juillet",
    "iso:country":"FR",
    "sg:address":"B.P. 400, 14914 Caen C\u00e9dex 9^^19, Quai de Juillet, 14000 Caen",
    "sg:city":"Caen",
    "sg:orig_category":"Non-Classified Establishments",
    "sg:phone":"+33 2 31 35 65 00",
    "sg:postcode":"14000",
    "sg:province":"Basse Normandie",
    "wof:name":"Aptime S.a.r.l.",
    "wof:placetype":"venue"
},
  "geometry": {"coordinates":[-0.36111,49.184361],"type":"Point"}
}