{
  "type": "Feature",
  "properties": {
    "addr:full":"1, Rue de la Nouette - ZI d'Angers Beaucouz\u00e9, 49070 Beaucouz\u00e9 Pays de Loire",
    "addr:housenumber":"1",
    "addr:postcode":"49070",
    "addr:street":"Rue De La Nouette Zi D'Angers",
    "iso:country":"FR",
    "sg:address":"1, Rue de la Nouette - ZI d'Angers Beaucouz\u00e9, 49070 Beaucouz\u00e9",
    "sg:orig_category":"Unclassifiable Establishments",
    "sg:phone":"+33 2 41 72 10 23",
    "sg:province":"Pays de Loire",
    "wof:name":"Coyard S.a.",
    "wof:placetype":"venue"
},
  "geometry": {"coordinates":[-0.622006,47.460049],"type":"Point"}
}