{
  "type": "Feature",
  "properties": {
    "addr:full":"30, Rue de la Poterie, 41170 Mondoubleau Mondoubleau Centre 41170",
    "addr:housenumber":"30;mondoubleau",
    "addr:postcode":"41170;41170",
    "addr:street":"Rue De La Poterie",
    "iso:country":"FR",
    "sg:address":"30, Rue de la Poterie, 41170 Mondoubleau",
    "sg:city":"Mondoubleau",
    "sg:orig_category":"Non-Classified Establishments",
    "sg:phone":"+33 2 54 73 70 70",
    "sg:postcode":"41170",
    "sg:province":"Centre",
    "wof:name":"Siplast Sa S.a.",
    "wof:placetype":"venue"
},
  "geometry": {"coordinates":[0.85072,47.924099],"type":"Point"}
}