{
  "type": "Feature",
  "properties": {
    "iso:country":"FR",
    "sg:address":"B.P. 5, 74970 Marignier C\u00e9dex^^70, Rte du Giffre, 74970 Marignier",
    "sg:orig_category":"Non-Classified Establishments",
    "sg:phone":"+33 4 50 34 63 54",
    "sg:postcode":"74970",
    "sg:province":"Rhone-Alpes",
    "wof:name":"Experd\u00e9co S.a.",
    "wof:placetype":"venue"
},
  "geometry": {"coordinates":[6.500625,46.090221],"type":"Point"}
}