{
  "type": "Feature",
  "properties": {
    "iso:country":"FR",
    "sg:address":"Avenue Col Georges Kaminski 74500 Champanges",
    "sg:classifiers":[
        {
            "category":"Building & Trades",
            "subcategory":"Construction",
            "type":"Services"
        }
    ],
    "sg:phone":"+33 4 50 73 41 33",
    "sg:postcode":"74500",
    "sg:province":"Rhone-Alpes",
    "sg:tags":[
        "good",
        "work",
        "wood",
        "professional",
        "public",
        "furniture"
    ],
    "wof:name":"Eurosieges Sarl",
    "wof:placetype":"venue"
},
  "geometry": {"coordinates":[6.64146,46.330173],"type":"Point"}
}