{
  "type": "Feature",
  "properties": {
    "iso:country":"FR",
    "sg:address":"1, Rue du 8 Mai 1945, 27230 Thiberville",
    "sg:orig_category":"Unclassifiable Establishments",
    "sg:phone":"+33 2 32 46 93 07",
    "sg:province":"Haute Normandie",
    "wof:name":"Delafosse S.a.r.l.",
    "wof:placetype":"venue"
},
  "geometry": {"coordinates":[0.40679,49.049824],"type":"Point"}
}