{
  "type": "Feature",
  "properties": {
    "addr:full":"14 pl de l'H\u00f4tel de Ville; Sotteville; 76300 Haute Normandie 76300",
    "addr:housenumber":"14",
    "addr:postcode":"76300;76300",
    "addr:street":"Pl De L'Ho \u0302Tel De Ville;Normandie",
    "iso:country":"FR",
    "sg:address":"14 pl de l'H\u00f4tel de Ville; Sotteville; 76300",
    "sg:classifiers":[
        {
            "category":"Banks & Credit Unions",
            "subcategory":"Bank",
            "type":"Services"
        }
    ],
    "sg:phone":"+33 3335725839",
    "sg:postcode":"76300",
    "sg:province":"Haute Normandie",
    "wof:name":"Banque Nationale De Paris",
    "wof:placetype":"venue"
},
  "geometry": {"coordinates":[1.090519,49.339542],"type":"Point"}
}