{
  "type": "Feature",
  "properties": {
    "addr:full":"22 Rue Pierre Martinet Ch\u00e2teau Gontier Pays de Loire 53200",
    "addr:housenumber":"22",
    "addr:postcode":"53200",
    "addr:street":"Rue Pierre Martinet Cha\u0302Teau Gontier Pays",
    "iso:country":"FR",
    "sg:address":"22 Rue Pierre Martinet",
    "sg:city":"Ch\u00e2teau Gontier",
    "sg:classifiers":[
        {
            "category":"Banks & Credit Unions",
            "subcategory":"Financial Services",
            "type":"Services"
        }
    ],
    "sg:phone":"+33 2 43 07 10 61",
    "sg:postcode":"53200",
    "sg:province":"Pays de Loire",
    "sg:tags":[
        "banking",
        "finance",
        "insurance"
    ],
    "wof:name":"Reaute Michel Jean Arthuis Et Associes Sa",
    "wof:placetype":"venue"
},
  "geometry": {"coordinates":[-0.706981,47.825649],"type":"Point"}
}