{
  "type": "Feature",
  "properties": {
    "iso:country":"FR",
    "sg:address":"27, Rte de Jouy, 91570 Bi\u00e8vres",
    "sg:orig_category":"Non-Classified Establishments",
    "sg:phone":"+33 1 69 41 06 10",
    "sg:province":"Ile de France",
    "wof:name":"Europa S.a.",
    "wof:placetype":"venue"
},
  "geometry": {"coordinates":[2.203197,48.752853],"type":"Point"}
}