{
  "type": "Feature",
  "properties": {
    "addr:full":"5, Rue Rambeaud, 17026 La Rochelle C\u00e9dex 1 La Rochelle Poitou-Charentes 17000",
    "addr:housenumber":"5;1",
    "addr:postcode":"17026;17000",
    "addr:street":"Rue Rambeaud;Ce\u0301Dex;La Rochelle",
    "iso:country":"FR",
    "sg:address":"5, Rue Rambeaud, 17026 La Rochelle C\u00e9dex 1",
    "sg:city":"La Rochelle",
    "sg:orig_category":"Non-Classified Establishments",
    "sg:phone":"+33 5 46 51 52 53",
    "sg:postcode":"17000",
    "sg:province":"Poitou-Charentes",
    "wof:name":"C.e.p.c. S.a. - Caisse D'epargne De Poitou Charentes",
    "wof:placetype":"venue"
},
  "geometry": {"coordinates":[-1.152724,46.163044],"type":"Point"}
}