{
  "type": "Feature",
  "properties": {
    "addr:full":"4 Rue Du Tribunal 67160 Wissembourg Wissembourg Alsace 67160",
    "addr:housenumber":"4",
    "addr:postcode":"67160;67160",
    "addr:street":"Rue Du Tribunal",
    "iso:country":"FR",
    "sg:address":"4 Rue Du Tribunal 67160 Wissembourg",
    "sg:city":"Wissembourg",
    "sg:classifiers":[
        {
            "category":"Farming",
            "subcategory":"Farm & Veterinary Services",
            "type":"Manufacturing & Wholesale Goods"
        }
    ],
    "sg:phone":"+33 3 88 54 19 50",
    "sg:postcode":"67160",
    "sg:province":"Alsace",
    "sg:tags":[
        "advice",
        "agriculture",
        "livestock",
        "business"
    ],
    "wof:name":"Office National Des Forets (onf)",
    "wof:placetype":"venue"
},
  "geometry": {"coordinates":[7.94598,49.03426],"type":"Point"}
}