{
  "type": "Feature",
  "properties": {
    "addr:full":"Lav\u00e9e 43200 Yssingeaux Yssingeaux Auvergne 43200",
    "addr:postcode":"43200;yssingeaux;43200",
    "addr:street":"Lave\u0301E",
    "iso:country":"FR",
    "sg:address":"Lav\u00e9e 43200 Yssingeaux",
    "sg:city":"Yssingeaux",
    "sg:orig_category":"Non-Classified Establishments",
    "sg:phone":"+33 4 71 59 58 00",
    "sg:postcode":"43200",
    "sg:province":"Auvergne",
    "wof:name":"Autobar Recyclage S.a.",
    "wof:placetype":"venue"
},
  "geometry": {"coordinates":[4.119395,45.149876],"type":"Point"}
}