{
  "type": "Feature",
  "properties": {
    "addr:full":"1/3, Rue des Moulins aux Moines, 72650 La Chapelle Saint Aubin Pays de Loire",
    "addr:housenumber":"1 / 3",
    "addr:postcode":"72650",
    "addr:street":"Rue Des Moulins Aux Moines",
    "iso:country":"FR",
    "sg:address":"1/3, Rue des Moulins aux Moines, 72650 La Chapelle Saint Aubin",
    "sg:orig_category":"Non-Classified Establishments",
    "sg:phone":"+33 2 43 24 46 02",
    "sg:province":"Pays de Loire",
    "wof:name":"F.p.l. S.a. - Soci\u00e9t\u00e9 D'expertise Comptable Fiduciare Pays De Loire",
    "wof:placetype":"venue"
},
  "geometry": {"coordinates":[0.17649,48.036419],"type":"Point"}
}