{
  "type": "Feature",
  "properties": {
    "addr:full":"B.P. 1 Villers Saint S\u00e9pulcre^^60134 Villers Saint S\u00e9pulcre Picardie 60134",
    "addr:housenumber":"1",
    "addr:postcode":"60134",
    "addr:street":"B.P.;Saint Se\u0301Pulcre Picardie",
    "iso:country":"FR",
    "sg:address":"B.P. 1",
    "sg:city":"Villers Saint S\u00e9pulcre^^60134 Villers Saint S\u00e9pulcre",
    "sg:orig_category":"Non-Classified Establishments",
    "sg:phone":"+33 3 44 89 49 49",
    "sg:postcode":"60134",
    "sg:province":"Picardie",
    "wof:name":"G.e. Plastics Abs S.a.",
    "wof:placetype":"venue"
},
  "geometry": {"coordinates":[2.236816,49.379963],"type":"Point"}
}