{
  "type": "Feature",
  "properties": {
    "addr:full":"Za De La Bouysse 12500 Espalion Midi Pyr\u00e9n\u00e9es 12500",
    "addr:postcode":"12500;12500",
    "addr:street":"Za De La Bouysse",
    "iso:country":"FR",
    "sg:address":"Za De La Bouysse 12500 Espalion",
    "sg:classifiers":[
        {
            "category":"Wholesale",
            "subcategory":"Meat",
            "type":"Manufacturing & Wholesale Goods"
        }
    ],
    "sg:phone":"+33 5 65 44 08 14",
    "sg:postcode":"12500",
    "sg:province":"Midi Pyr\u00e9n\u00e9es",
    "sg:tags":[
        "food",
        "cooked",
        "product",
        "related"
    ],
    "wof:name":"Etablissements Semenzin Et Fils",
    "wof:placetype":"venue"
},
  "geometry": {"coordinates":[2.762437,44.522015],"type":"Point"}
}