{
  "type": "Feature",
  "properties": {
    "iso:country":"FR",
    "sg:address":"PA de la Maison Neuve",
    "sg:city":"Vigneux de Bretagne",
    "sg:orig_category":"Unclassifiable Establishments",
    "sg:phone":"+33 2 40 57 39 39",
    "sg:postcode":"44360",
    "sg:province":"Pays de Loire",
    "wof:name":"Le Guillerm",
    "wof:placetype":"venue"
},
  "geometry": {"coordinates":[-1.749463,47.240623],"type":"Point"}
}