{
  "type": "Feature",
  "properties": {
    "addr:full":"2, Rue Robert d'Arbrissel, 35000 Rennes Rennes Bretagne 35000",
    "addr:housenumber":"2",
    "addr:postcode":"35000;35000",
    "addr:street":"Rue Robert D'Arbrissel",
    "iso:country":"FR",
    "sg:address":"2, Rue Robert d'Arbrissel, 35000 Rennes",
    "sg:city":"Rennes",
    "sg:orig_category":"Unclassifiable Establishments",
    "sg:phone":"+33 2 99 54 51 73",
    "sg:postcode":"35000",
    "sg:province":"Bretagne",
    "wof:name":"Entrep'rennes",
    "wof:placetype":"venue"
},
  "geometry": {"coordinates":[-1.691358,48.127674],"type":"Point"}
}