{
  "type": "Feature",
  "properties": {
    "addr:full":"32, Cours Aristide Briand, 69300 Caluire et Cuire Rhone-Alpes 69300",
    "addr:housenumber":"32",
    "addr:postcode":"69300;69300",
    "addr:street":"Cours Aristide Briand",
    "iso:country":"FR",
    "sg:address":"32, Cours Aristide Briand, 69300 Caluire et Cuire",
    "sg:orig_category":"Unclassifiable Establishments",
    "sg:phone":"+33 4 78 23 29 71",
    "sg:postcode":"69300",
    "sg:province":"Rhone-Alpes",
    "wof:name":"Atelier Roland J\u00e9ol S.a.r.l.",
    "wof:placetype":"venue"
},
  "geometry": {"coordinates":[4.844287,45.783329],"type":"Point"}
}