{
  "type": "Feature",
  "properties": {
    "addr:full":"B.P. 5, 67370 Truchtersheim^^2, Rue des Artisans, 67370 Truchtersheim Truchtersheim Alsace 67370",
    "addr:housenumber":"5",
    "addr:postcode":"67370;67370;67370",
    "addr:street":"B.P.;Rue Des Artisans",
    "iso:country":"FR",
    "sg:address":"B.P. 5, 67370 Truchtersheim^^2, Rue des Artisans, 67370 Truchtersheim",
    "sg:city":"Truchtersheim",
    "sg:orig_category":"Non-Classified Establishments",
    "sg:phone":"+33 3 88 69 77 88",
    "sg:postcode":"67370",
    "sg:province":"Alsace",
    "wof:name":"Socomat Lestingi S.a.r.l.",
    "wof:placetype":"venue"
},
  "geometry": {"coordinates":[7.657589,48.678986],"type":"Point"}
}