{
  "type": "Feature",
  "properties": {
    "addr:full":"4 Rue Des Falaises 36360 Lucay Le Male Faverolles Centre 36360",
    "addr:housenumber":"4",
    "addr:postcode":"36360;36360",
    "addr:street":"Rue Des Falaises",
    "iso:country":"FR",
    "sg:address":"4 Rue Des Falaises 36360 Lucay Le Male",
    "sg:city":"Faverolles",
    "sg:classifiers":[
        {
            "category":"Manufacturing",
            "subcategory":"Rubber & Plastics",
            "type":"Manufacturing & Wholesale Goods"
        }
    ],
    "sg:phone":"+33 2 54 40 42 68",
    "sg:postcode":"36360",
    "sg:province":"Centre",
    "sg:tags":[
        "packaging",
        "material",
        "-"
    ],
    "wof:name":"Gomendy",
    "wof:placetype":"venue"
},
  "geometry": {"coordinates":[1.44457,47.134544],"type":"Point"}
}