{
  "type": "Feature",
  "properties": {
    "iso:country":"FR",
    "sg:address":"108, Rue du Cherche Midi, 75006 Paris",
    "sg:orig_category":"Unclassifiable Establishments",
    "sg:phone":"+33 1 42 22 42 55",
    "sg:province":"Ile de France",
    "wof:name":"Volevatch S.a.r.l.",
    "wof:placetype":"venue"
},
  "geometry": {"coordinates":[2.320889,48.846745],"type":"Point"}
}