{
  "type": "Feature",
  "properties": {
    "iso:country":"FR",
    "sg:address":"Rue Charles Jourde",
    "sg:city":"Brest",
    "sg:orig_category":"Unclassifiable Establishments",
    "sg:phone":"+33 2 98 02 03 40",
    "sg:postcode":"29200",
    "sg:province":"Bretagne",
    "wof:name":"I.e.b. S.a.",
    "wof:placetype":"venue"
},
  "geometry": {"coordinates":[-4.46206,48.422165],"type":"Point"}
}