{
  "type": "Feature",
  "properties": {
    "addr:full":"Bd Du Mal Juin 52000 Chaumont Champagne 52000",
    "addr:postcode":"52000;52000",
    "addr:street":"Bd Du Mal Juin",
    "iso:country":"FR",
    "sg:address":"Bd Du Mal Juin 52000 Chaumont",
    "sg:classifiers":[
        {
            "category":"Wholesale",
            "subcategory":"Medical Equipment & Supplies",
            "type":"Manufacturing & Wholesale Goods"
        }
    ],
    "sg:phone":"+33 3 25 32 28 32",
    "sg:postcode":"52000",
    "sg:province":"Champagne",
    "sg:tags":[
        "instrument",
        "health",
        "-",
        "precision"
    ],
    "wof:name":"Aesculap Sa",
    "wof:placetype":"venue"
},
  "geometry": {"coordinates":[5.1525,48.100258],"type":"Point"}
}