{
  "type": "Feature",
  "properties": {
    "iso:country":"FR",
    "sg:address":"96, Rue Bugeaud, 69006 Lyon",
    "sg:orig_category":"Non-Classified Establishments",
    "sg:phone":"+33 4 72 83 70 04",
    "sg:postcode":"69006",
    "sg:province":"Rhone-Alpes",
    "wof:name":"J.m.m. S.a.r.l. - Jacques Mont\u00e9mont Marketing",
    "wof:placetype":"venue"
},
  "geometry": {"coordinates":[4.852074,45.766132],"type":"Point"}
}