{
  "type": "Feature",
  "properties": {
    "addr:full":"B.P. 10816, 57208 Sarreguemines C\u00e9dex^^1, Rue des Fr\u00e8res R\u00e9my, 57200 Sarreguemines Lorraine 57200",
    "addr:housenumber":"10816",
    "addr:postcode":"57208;57200;57200",
    "addr:street":"Rue Des Fre\u0300Res Re\u0301My",
    "iso:country":"FR",
    "sg:address":"B.P. 10816, 57208 Sarreguemines C\u00e9dex^^1, Rue des Fr\u00e8res R\u00e9my, 57200 Sarreguemines",
    "sg:orig_category":"Air comprim\u00e9 G\u00e9n\u00e9rateurs d'air froid Purgeurs",
    "sg:phone":"+33 3 87 28 38 00",
    "sg:postcode":"57200",
    "sg:province":"Lorraine",
    "wof:name":"Beko Technologies S.a.r.l.",
    "wof:placetype":"venue"
},
  "geometry": {"coordinates":[7.070569,49.108246],"type":"Point"}
}