{
  "type": "Feature",
  "properties": {
    "iso:country":"FR",
    "sg:address":"10, Rue de l'Epalu, 89220 Bl\u00e9neau",
    "sg:city":"Bl\u00e9neau",
    "sg:orig_category":"Unclassifiable Establishments",
    "sg:phone":"+33 3 86 74 84 48",
    "sg:postcode":"89220",
    "sg:province":"Bourgogne",
    "wof:name":"Andopack S.a.",
    "wof:placetype":"venue"
},
  "geometry": {"coordinates":[2.943025,47.697769],"type":"Point"}
}