{
  "type": "Feature",
  "properties": {
    "iso:country":"FR",
    "sg:address":"120 boulevard Cl\u00e9menceau 76600 Le Havre",
    "sg:classifiers":[
        {
            "category":"Retail",
            "subcategory":"Storage",
            "type":"Services"
        }
    ],
    "sg:phone":"+33 2 32 74 67 20",
    "sg:postcode":"76600",
    "sg:province":"Haute Normandie",
    "sg:tags":[
        "transport",
        "groupage"
    ],
    "wof:name":"Sotecan Esc France Sarl",
    "wof:placetype":"venue"
},
  "geometry": {"coordinates":[0.098199,49.489025],"type":"Point"}
}