{
  "type": "Feature",
  "properties": {
    "addr:full":"Moulin de la Roquette 44310 Saint Colomban Pays de Loire",
    "addr:postcode":"44310;colomban",
    "addr:street":"Moulin De La Roquette",
    "iso:country":"FR",
    "sg:address":"Moulin de la Roquette 44310 Saint Colomban",
    "sg:orig_category":"Non-Classified Establishments",
    "sg:phone":"+33 2 40 05 88 08",
    "sg:province":"Pays de Loire",
    "wof:name":"Guiot S.a.r.l.",
    "wof:placetype":"venue"
},
  "geometry": {"coordinates":[-1.641945,47.038834],"type":"Point"}
}