{
  "type": "Feature",
  "properties": {
    "iso:country":"FR",
    "sg:address":"62, Rue Maurice Sarrault, 59200 Tourcoing",
    "sg:orig_category":"Unclassifiable Establishments",
    "sg:phone":"+33 3 20 01 55 45",
    "sg:province":"Nord Pas-de-Calais",
    "wof:name":"Imprima S.a.r.l.",
    "wof:placetype":"venue"
},
  "geometry": {"coordinates":[3.159604,50.73571],"type":"Point"}
}