{
  "type": "Feature",
  "properties": {
    "addr:full":"Chemin Mure 69780 St Pierre De Chandieu Rhone-Alpes",
    "addr:postcode":"69780",
    "addr:street":"Chemin Mure",
    "iso:country":"FR",
    "sg:address":"Chemin Mure 69780 St Pierre De Chandieu",
    "sg:classifiers":[
        {
            "category":"Manufacturing",
            "subcategory":"Paper Products",
            "type":"Manufacturing & Wholesale Goods"
        }
    ],
    "sg:phone":"+33 4 72 48 09 10",
    "sg:province":"Rhone-Alpes",
    "sg:tags":[
        "packaging",
        "material",
        "-",
        "cardboard"
    ],
    "wof:name":"Abzac Packaging Sa",
    "wof:placetype":"venue"
},
  "geometry": {"coordinates":[5.007485,45.658813],"type":"Point"}
}