{
  "type": "Feature",
  "properties": {
    "addr:full":"RN 113 - ZI la Baume Servian Languedoc-Roussillon 34290",
    "addr:postcode":"34290",
    "addr:street":"Rn 113 Zi La Baume",
    "iso:country":"FR",
    "sg:address":"RN 113 - ZI la Baume",
    "sg:city":"Servian",
    "sg:orig_category":"Non-Classified Establishments",
    "sg:phone":"+33 4 67 39 29 39",
    "sg:postcode":"34290",
    "sg:province":"Languedoc-Roussillon",
    "wof:name":"T.m.f. Languedoc S.a.r.l.",
    "wof:placetype":"venue"
},
  "geometry": {"coordinates":[3.307045,43.428188],"type":"Point"}
}