{
  "type": "Feature",
  "properties": {
    "addr:full":"B.P. 8313, 95000 Cergy C\u00e9dex^^21, Rue du Petit Albi, 95000 Cergy Ile de France 95000",
    "addr:postcode":"95000;95000;ile;95000",
    "addr:street":"B.P. 8313;Rue Du Petit Albi;France",
    "iso:country":"FR",
    "sg:address":"B.P. 8313, 95000 Cergy C\u00e9dex^^21, Rue du Petit Albi, 95000 Cergy",
    "sg:orig_category":"Non-Classified Establishments",
    "sg:phone":"+33 1 30 31 21 21",
    "sg:postcode":"95000",
    "sg:province":"Ile de France",
    "wof:name":"Applied France S.a.",
    "wof:placetype":"venue"
},
  "geometry": {"coordinates":[2.07982,49.035198],"type":"Point"}
}