{
  "type": "Feature",
  "properties": {
    "addr:full":"97 Avenue Victor Hugo 75116 Paris Ile de France",
    "addr:housenumber":"97",
    "addr:postcode":"75116",
    "addr:street":"Avenue Victor Hugo",
    "iso:country":"FR",
    "sg:address":"97 Avenue Victor Hugo 75116 Paris",
    "sg:classifiers":[
        {
            "category":"Shopping",
            "subcategory":"Luggage & Leather Goods",
            "type":"Retail Goods"
        }
    ],
    "sg:phone":"+33 1 47 04 23 75",
    "sg:province":"Ile de France",
    "sg:tags":[
        "shoe"
    ],
    "wof:name":"Jm Weston",
    "wof:placetype":"venue"
},
  "geometry": {"coordinates":[2.284501,48.869194],"type":"Point"}
}