{
  "type": "Feature",
  "properties": {
    "iso:country":"FR",
    "sg:address":"Zone Euronord 4 R Du B\u00e9nelux Pi Euronord 31150 Lespinasse",
    "sg:classifiers":[
        {
            "category":"Manufacturing",
            "subcategory":"Metals",
            "type":"Manufacturing & Wholesale Goods"
        }
    ],
    "sg:phone":"+33 5 34 27 20 90",
    "sg:postcode":"31150",
    "sg:province":"Midi Pyr\u00e9n\u00e9es",
    "sg:tags":[
        "metallurgy",
        "steel",
        "metalworking"
    ],
    "wof:name":"Aubert Et Duval",
    "wof:placetype":"venue"
},
  "geometry": {"coordinates":[1.411975,43.726673],"type":"Point"}
}