{
  "type": "Feature",
  "properties": {
    "addr:full":"13, Chemin du Levaut - B\u00e2timent B, 01210 Ferney Voltaire Rhone-Alpes",
    "addr:housenumber":"13",
    "addr:postcode":"01210",
    "addr:street":"Chemin Du",
    "iso:country":"FR",
    "sg:address":"13, Chemin du Levaut - B\u00e2timent B, 01210 Ferney Voltaire",
    "sg:orig_category":"Non-Classified Establishments",
    "sg:phone":"+33 4 50 40 85 15",
    "sg:province":"Rhone-Alpes",
    "wof:name":"Technomic Consultants S.a.r.l.",
    "wof:placetype":"venue"
},
  "geometry": {"coordinates":[6.114651,46.260101],"type":"Point"}
}