{
  "type": "Feature",
  "properties": {
    "addr:full":"4 Rue Tanneries Grosjean 88160 Le Thillot Lorraine",
    "addr:housenumber":"4",
    "addr:postcode":"88160",
    "addr:street":"Rue Tanneries Grosjean",
    "iso:country":"FR",
    "sg:address":"4 Rue Tanneries Grosjean 88160 Le Thillot",
    "sg:classifiers":[
        {
            "category":"Professional",
            "type":"Services"
        }
    ],
    "sg:phone":"+33 3 29 25 88 88",
    "sg:province":"Lorraine",
    "sg:tags":[
        "transport",
        "road"
    ],
    "wof:name":"Transports Peureux Sa",
    "wof:placetype":"venue"
},
  "geometry": {"coordinates":[6.765106,47.875072],"type":"Point"}
}