{
  "type": "Feature",
  "properties": {
    "addr:full":"4 Petite Rue De La Course 67000 Strasbourg Strasbourg Alsace 67000",
    "addr:housenumber":"4",
    "addr:postcode":"67000;67000",
    "addr:street":"Petite Rue De La Course",
    "iso:country":"FR",
    "sg:address":"4 Petite Rue De La Course 67000 Strasbourg",
    "sg:city":"Strasbourg",
    "sg:classifiers":[
        {
            "category":"Professional",
            "subcategory":"Advertising",
            "type":"Services"
        }
    ],
    "sg:phone":"+33 3 88 32 72 65",
    "sg:postcode":"67000",
    "sg:province":"Alsace",
    "sg:tags":[
        "information",
        "medium",
        "communication"
    ],
    "wof:name":"Video Select Sa",
    "wof:placetype":"venue"
},
  "geometry": {"coordinates":[7.735898,48.582809],"type":"Point"}
}