{
  "type": "Feature",
  "properties": {
    "addr:full":"La Planche 63600 AMBERT Ambert Auvergne 63600",
    "addr:postcode":"63600;63600",
    "addr:street":"La",
    "iso:country":"FR",
    "sg:address":"La Planche 63600 AMBERT",
    "sg:city":"Ambert",
    "sg:classifiers":[
        {
            "category":"Professional",
            "subcategory":"Advertising",
            "type":"Services"
        }
    ],
    "sg:phone":"+33 4 73 82 34 34",
    "sg:postcode":"63600",
    "sg:province":"Auvergne",
    "sg:tags":[
        "articles"
    ],
    "wof:name":"Beraudy Et Vaure Sa",
    "wof:placetype":"venue"
},
  "geometry": {"coordinates":[3.76001,45.542831],"type":"Point"}
}