{
  "type": "Feature",
  "properties": {
    "iso:country":"FR",
    "sg:address":"ZI",
    "sg:city":"Montpon Menesterol",
    "sg:orig_category":"Unclassifiable Establishments",
    "sg:phone":"+33 5 53 80 85 00",
    "sg:postcode":"24700",
    "sg:province":"Aquitaine",
    "wof:name":"Kimo S.a.",
    "wof:placetype":"venue"
},
  "geometry": {"coordinates":[0.180984,44.944614],"type":"Point"}
}