{
  "type": "Feature",
  "properties": {
    "addr:full":"6, Rue du Buisson Saint Louis, 75010 Paris Ile de France",
    "addr:housenumber":"6",
    "addr:postcode":"75010",
    "addr:street":"Rue Du Buisson",
    "iso:country":"FR",
    "sg:address":"6, Rue du Buisson Saint Louis, 75010 Paris",
    "sg:orig_category":"Non-Classified Establishments",
    "sg:phone":"+33 1 42 41 18 19",
    "sg:province":"Ile de France",
    "wof:name":"Onet Propret\u00e9 S.a.",
    "wof:placetype":"venue"
},
  "geometry": {"coordinates":[2.373003,48.872009],"type":"Point"}
}