{
  "type": "Feature",
  "properties": {
    "addr:full":"64 Route De Calas Domaine De La Croix D Or 13320 Bouc Bel Air Centre",
    "addr:housenumber":"64",
    "addr:postcode":"13320",
    "addr:street":"Route De Calas Domaine De La Croix D;Bel Air",
    "iso:country":"FR",
    "sg:address":"64 Route De Calas Domaine De La Croix D Or 13320 Bouc Bel Air",
    "sg:classifiers":[
        {
            "category":"Professional",
            "subcategory":"Engineering",
            "type":"Services"
        }
    ],
    "sg:phone":"+33 4 42 94 06 60",
    "sg:province":"Centre",
    "sg:tags":[
        "machine",
        "-",
        "mechanical"
    ],
    "wof:name":"Sesar",
    "wof:placetype":"venue"
},
  "geometry": {"coordinates":[5.413305,43.451939],"type":"Point"}
}