{
  "type": "Feature",
  "properties": {
    "addr:full":"Rte D'Ivry 21630 Pommard Pommard Bourgogne 21630",
    "addr:postcode":"21630;21630",
    "addr:street":"Rte D'Ivry",
    "iso:country":"FR",
    "sg:address":"Rte D'Ivry 21630 Pommard",
    "sg:city":"Pommard",
    "sg:classifiers":[
        {
            "category":"Food Court",
            "type":"Food & Drink"
        }
    ],
    "sg:phone":"+33 3 80 22 17 33",
    "sg:postcode":"21630",
    "sg:province":"Bourgogne",
    "sg:tags":[
        "product",
        "related"
    ],
    "wof:name":"Domaine Billard Gonnet",
    "wof:placetype":"venue"
},
  "geometry": {"coordinates":[4.791035,47.014248],"type":"Point"}
}