{
  "type": "Feature",
  "properties": {
    "addr:full":"14, Rue Timbal, 81012 Albi C\u00e9dex 9 Midi Pyr\u00e9n\u00e9es",
    "addr:housenumber":"14;9",
    "addr:postcode":"81012",
    "addr:street":"Rue Timbal;Ce\u0301Dex",
    "iso:country":"FR",
    "sg:address":"14, Rue Timbal, 81012 Albi C\u00e9dex 9",
    "sg:orig_category":"Non-Classified Establishments",
    "sg:phone":"+33 5 63 49 48 47",
    "sg:province":"Midi Pyr\u00e9n\u00e9es",
    "wof:name":"C.c.i. Dalbi - Chambre De Commerce Et D'industrie D'albi",
    "wof:placetype":"venue"
},
  "geometry": {"coordinates":[2.146996,43.927944],"type":"Point"}
}