{
  "type": "Feature",
  "properties": {
    "addr:full":"20, Chemin des Paysans, 67500 Haguenau Haguenau Alsace 67500",
    "addr:housenumber":"20",
    "addr:postcode":"67500;67500",
    "addr:street":"Chemin Des Paysans",
    "iso:country":"FR",
    "sg:address":"20, Chemin des Paysans, 67500 Haguenau",
    "sg:city":"Haguenau",
    "sg:orig_category":"Non-Classified Establishments",
    "sg:phone":"+33 3 88 93 02 50",
    "sg:postcode":"67500",
    "sg:province":"Alsace",
    "wof:name":"Alsa Fermeture S.a.r.l.",
    "wof:placetype":"venue"
},
  "geometry": {"coordinates":[7.791833,48.793938],"type":"Point"}
}