{
  "type": "Feature",
  "properties": {
    "iso:country":"FR",
    "sg:address":"10, Av. du Clocher, 93130 Noisy le Sec",
    "sg:orig_category":"Non-Classified Establishments",
    "sg:phone":"+33 1 48 60 02 65",
    "sg:province":"Ile de France",
    "wof:name":"Robine S.a.r.l.",
    "wof:placetype":"venue"
},
  "geometry": {"coordinates":[2.468608,48.902496],"type":"Point"}
}