{
  "type": "Feature",
  "properties": {
    "addr:full":"B.P. 76, 93302 Aubervilliers C\u00e9dex^^75, Bd F\u00e9lix Faure, 93300 Aubervilliers Ile de France",
    "addr:postcode":"93302;93300",
    "addr:street":"B.P. 76;Bd Fe\u0301Lix Faure",
    "iso:country":"FR",
    "sg:address":"B.P. 76, 93302 Aubervilliers C\u00e9dex^^75, Bd F\u00e9lix Faure, 93300 Aubervilliers",
    "sg:orig_category":"Non-Classified Establishments",
    "sg:phone":"+33 1 48 34 91 36",
    "sg:province":"Ile de France",
    "wof:name":"Sodilap S.a.",
    "wof:placetype":"venue"
},
  "geometry": {"coordinates":[2.382535,48.913391],"type":"Point"}
}