{
  "type": "Feature",
  "properties": {
    "addr:full":"71, Chemin Fompigasses, 31620 Bouloc Midi Pyr\u00e9n\u00e9es 31620",
    "addr:housenumber":"71",
    "addr:postcode":"31620;31620",
    "addr:street":"Chemin Fompigasses",
    "iso:country":"FR",
    "sg:address":"71, Chemin Fompigasses, 31620 Bouloc",
    "sg:orig_category":"Non-Classified Establishments",
    "sg:phone":"+33 5 61 82 65 14",
    "sg:postcode":"31620",
    "sg:province":"Midi Pyr\u00e9n\u00e9es",
    "wof:name":"Devos Pr\u00e9-print S.a.r.l.",
    "wof:placetype":"venue"
},
  "geometry": {"coordinates":[1.414206,43.786469],"type":"Point"}
}