{
  "type": "Feature",
  "properties": {
    "addr:full":"31 Rue Eug\u00e8ne Sue 03100 Montlu\u00e7on Montlu\u00e7on Auvergne 03100",
    "addr:housenumber":"31",
    "addr:postcode":"03100;03100",
    "addr:street":"Rue Euge\u0300Ne Sue",
    "iso:country":"FR",
    "sg:address":"31 Rue Eug\u00e8ne Sue 03100 Montlu\u00e7on",
    "sg:city":"Montlu\u00e7on",
    "sg:classifiers":[
        {
            "category":"Wholesale",
            "subcategory":"Machinery & Supplies",
            "type":"Manufacturing & Wholesale Goods"
        }
    ],
    "sg:phone":"+33 4 70 28 42 86",
    "sg:postcode":"03100",
    "sg:province":"Auvergne",
    "sg:tags":[
        "food",
        "processing",
        "-",
        "machine",
        "equipment",
        "engineering",
        "mechanical"
    ],
    "wof:name":"Genedis Promocash",
    "wof:placetype":"venue"
},
  "geometry": {"coordinates":[2.599693,46.356579],"type":"Point"}
}