{
  "type": "Feature",
  "properties": {
    "iso:country":"FR",
    "sg:address":"2 rue Nicolas Copernic 93600 Aulnay Sous Bois",
    "sg:classifiers":[
        {
            "category":"Professional",
            "type":"Services"
        }
    ],
    "sg:phone":"+33 1 49 39 68 50",
    "sg:province":"Ile de France",
    "sg:tags":[
        "transport"
    ],
    "wof:name":"Multimodal Multi-cargo Leader S.a.",
    "wof:placetype":"venue"
},
  "geometry": {"coordinates":[2.473425,48.94775],"type":"Point"}
}