{
  "type": "Feature",
  "properties": {
    "addr:full":"RN 110 - ZI Grande Terre Saint Christol l\u00e8s Al\u00e8s Languedoc-Roussillon 30380",
    "addr:postcode":"30380",
    "addr:street":"Rn 110 Zi Grande Terre Saint Christol",
    "iso:country":"FR",
    "sg:address":"RN 110 - ZI Grande Terre",
    "sg:city":"Saint Christol l\u00e8s Al\u00e8s",
    "sg:orig_category":"Unclassifiable Establishments",
    "sg:phone":"+33 4 66 60 77 50",
    "sg:postcode":"30380",
    "sg:province":"Languedoc-Roussillon",
    "wof:name":"Michel Coud\u00e8ne S.a.",
    "wof:placetype":"venue"
},
  "geometry": {"coordinates":[4.07704,44.084621],"type":"Point"}
}