{
  "type": "Feature",
  "properties": {
    "addr:full":"Jardenat 16260 Chasseneuil sur Bonnieure Poitou-Charentes",
    "addr:postcode":"16260",
    "addr:street":"Jardenat;Bonnieure",
    "iso:country":"FR",
    "sg:address":"Jardenat 16260 Chasseneuil sur Bonnieure",
    "sg:orig_category":"Unclassifiable Establishments",
    "sg:phone":"+33 5 45 39 50 15",
    "sg:province":"Poitou-Charentes",
    "wof:name":"Mat\u00e9riaux Fourgeaud S.a.r.l.",
    "wof:placetype":"venue"
},
  "geometry": {"coordinates":[0.444569,45.806656],"type":"Point"}
}