{
  "type": "Feature",
  "properties": {
    "iso:country":"FR",
    "sg:address":"ZI Kerbriant",
    "sg:city":"Plouigneau",
    "sg:orig_category":"Unclassifiable Establishments",
    "sg:phone":"+33 2 98 67 71 41",
    "sg:postcode":"29610",
    "sg:province":"Bretagne",
    "wof:name":"Biscuits Roc'helou S.a.s.",
    "wof:placetype":"venue"
},
  "geometry": {"coordinates":[-3.701579,48.569355],"type":"Point"}
}