{
  "type": "Feature",
  "properties": {
    "iso:country":"FR",
    "sg:address":"ZA des Lots",
    "sg:city":"Messimy",
    "sg:orig_category":"Unclassifiable Establishments",
    "sg:phone":"+33 4 78 45 14 37",
    "sg:postcode":"69510",
    "sg:province":"Rhone-Alpes",
    "wof:name":"Novopac S.a.",
    "wof:placetype":"venue"
},
  "geometry": {"coordinates":[4.674172,45.696644],"type":"Point"}
}