{
  "type": "Feature",
  "properties": {
    "addr:full":"71, Rue de la Voie Romaine, 31150 Gagnac sur Garonne Midi Pyr\u00e9n\u00e9es",
    "addr:housenumber":"71",
    "addr:postcode":"31150",
    "addr:street":"Rue De La Voie Romaine",
    "iso:country":"FR",
    "sg:address":"71, Rue de la Voie Romaine, 31150 Gagnac sur Garonne",
    "sg:orig_category":"Unclassifiable Establishments",
    "sg:phone":"+33 5 34 27 07 07",
    "sg:province":"Midi Pyr\u00e9n\u00e9es",
    "wof:name":"A.c E.u.r.l. - A\u00e9ro Composite Toulousain",
    "wof:placetype":"venue"
},
  "geometry": {"coordinates":[1.377156,43.703934],"type":"Point"}
}