{
  "type": "Feature",
  "properties": {
    "iso:country":"FR",
    "sg:address":"18 rue Maurice Caunes 31200 Toulouse",
    "sg:classifiers":[
        {
            "category":"Professional",
            "subcategory":"Advertising",
            "type":"Services"
        }
    ],
    "sg:phone":"+33 5 61 99 99 99",
    "sg:postcode":"31200",
    "sg:province":"Midi Pyr\u00e9n\u00e9es",
    "sg:tags":[
        "agency"
    ],
    "wof:name":"Ips Publicit\u00e9 S.a.",
    "wof:placetype":"venue"
},
  "geometry": {"coordinates":[1.474363,43.640411],"type":"Point"}
}