{
  "type": "Feature",
  "properties": {
    "iso:country":"FR",
    "sg:address":"B.P. 429, 74108 Ville la Grand C\u00e9dex^^ZAC du Village d'Entreprises, 74100 Ville la Grand",
    "sg:orig_category":"Non-Classified Establishments",
    "sg:phone":"+33 4 50 92 51 00",
    "sg:postcode":"74100",
    "sg:province":"Rhone-Alpes",
    "wof:name":"Avelli Bruno Successeurs S.a.",
    "wof:placetype":"venue"
},
  "geometry": {"coordinates":[6.24942,46.20285],"type":"Point"}
}