{
  "type": "Feature",
  "properties": {
    "iso:country":"FR",
    "sg:address":"17, Av. de Fontcouverte, 84000 Avignon",
    "sg:city":"Fontcouverte",
    "sg:orig_category":"Unclassifiable Establishments",
    "sg:phone":"+33 4 90 87 55 50",
    "sg:postcode":"17100",
    "sg:province":"Poitou-Charentes",
    "wof:name":"Etablissements Viau S.a.",
    "wof:placetype":"venue"
},
  "geometry": {"coordinates":[4.843405,43.937538],"type":"Point"}
}