{
  "type": "Feature",
  "properties": {
    "addr:full":"ZI de Bal\u00e9one - Panchetta Sarrola Carcopino Corse 20167",
    "addr:postcode":"20167",
    "addr:street":"Zi De Bale\u0301One Panchetta",
    "iso:country":"FR",
    "sg:address":"ZI de Bal\u00e9one - Panchetta",
    "sg:city":"Sarrola Carcopino",
    "sg:orig_category":"Unclassifiable Establishments",
    "sg:phone":"+33 4 95 23 77 40",
    "sg:postcode":"20167",
    "sg:province":"Corse",
    "wof:name":"Vibel S.a.s.",
    "wof:placetype":"venue"
},
  "geometry": {"coordinates":[8.838952,42.025784],"type":"Point"}
}