{
  "type": "Feature",
  "properties": {
    "addr:full":"B.P. 3109, 03105 Montlu\u00e7on C\u00e9dex^^Rte de Chambon, 03410 Pr\u00e9milhat Pr\u00e9milhat Auvergne 03410",
    "addr:postcode":"03105;03410;pre\u0301milhat;03410",
    "addr:street":"B.P. 3109",
    "iso:country":"FR",
    "sg:address":"B.P. 3109, 03105 Montlu\u00e7on C\u00e9dex^^Rte de Chambon, 03410 Pr\u00e9milhat",
    "sg:city":"Pr\u00e9milhat",
    "sg:orig_category":"Non-Classified Establishments",
    "sg:phone":"+33 4 70 51 52 97",
    "sg:postcode":"03410",
    "sg:province":"Auvergne",
    "wof:name":"Peintures T.l.m. S.a.",
    "wof:placetype":"venue"
},
  "geometry": {"coordinates":[2.559067,46.350773],"type":"Point"}
}