{
  "type": "Feature",
  "properties": {
    "iso:country":"FR",
    "sg:address":"1, Rue de la Croix Bougard, 59810 Lesquin",
    "sg:orig_category":"Unclassifiable Establishments",
    "sg:phone":"+33 3 20 87 02 87",
    "sg:province":"Nord Pas-de-Calais",
    "wof:name":"Dubois R\u00e9my S.a.",
    "wof:placetype":"venue"
},
  "geometry": {"coordinates":[3.11421,50.581921],"type":"Point"}
}