{
  "type": "Feature",
  "properties": {
    "addr:full":"ZI Sous la Croze Loyettes Rhone-Alpes 01360",
    "addr:postcode":"01360",
    "addr:street":"Zi Sous La Croze;Rhone-Alpes",
    "iso:country":"FR",
    "sg:address":"ZI Sous la Croze",
    "sg:city":"Loyettes",
    "sg:orig_category":"Unclassifiable Establishments",
    "sg:phone":"+33 4 72 93 96 96",
    "sg:postcode":"01360",
    "sg:province":"Rhone-Alpes",
    "wof:name":"S.i.g.e.d. S.a. - Soci\u00e9t\u00e9 D'industrie G\u00e9n\u00e9rale Et D'equipements Divers",
    "wof:placetype":"venue"
},
  "geometry": {"coordinates":[5.20678,45.774937],"type":"Point"}
}