{
  "type": "Feature",
  "properties": {
    "addr:full":"47 Bis Rue Jeanne D'Arc 52100 St Dizier Champagne 52100",
    "addr:housenumber":"47 bis",
    "addr:postcode":"52100;52100",
    "addr:street":"Rue Jeanne D'Arc;Champagne",
    "iso:country":"FR",
    "sg:address":"47 Bis Rue Jeanne D'Arc 52100 St Dizier",
    "sg:classifiers":[
        {
            "category":"Manufacturing",
            "subcategory":"Metals",
            "type":"Manufacturing & Wholesale Goods"
        }
    ],
    "sg:phone":"+33 3 25 56 10 15",
    "sg:postcode":"52100",
    "sg:province":"Champagne",
    "sg:tags":[
        "metallurgy",
        "steel",
        "metalworking"
    ],
    "wof:name":"Realisations Industrielles Bragarde Sarl",
    "wof:placetype":"venue"
},
  "geometry": {"coordinates":[4.944951,48.645309],"type":"Point"}
}