{
  "type": "Feature",
  "properties": {
    "addr:full":"53 Rue Saint Aubert 62000 Arras Nord Pas-de-Calais",
    "addr:housenumber":"53",
    "addr:postcode":"62000",
    "addr:street":"Rue Saint Aubert",
    "iso:country":"FR",
    "sg:address":"53 Rue Saint Aubert 62000 Arras",
    "sg:classifiers":[
        {
            "category":"Professional",
            "subcategory":"Printing & Photocopies",
            "type":"Services"
        }
    ],
    "sg:phone":"+33 3 21 23 94 94",
    "sg:province":"Nord Pas-de-Calais",
    "sg:tags":[
        "publishing"
    ],
    "wof:name":"Le Galibot",
    "wof:placetype":"venue"
},
  "geometry": {"coordinates":[2.771145,50.290985],"type":"Point"}
}