{
  "type": "Feature",
  "properties": {
    "addr:full":"Rte de Martinsart Aveluy Picardie 80300",
    "addr:postcode":"80300",
    "addr:street":"Rte De Martinsart;Picardie",
    "iso:country":"FR",
    "sg:address":"Rte de Martinsart",
    "sg:city":"Aveluy",
    "sg:orig_category":"Unclassifiable Establishments",
    "sg:phone":"+33 3 22 75 13 30",
    "sg:postcode":"80300",
    "sg:province":"Picardie",
    "wof:name":"Carr\u00e9 Et Compagnie S.a.r.l.",
    "wof:placetype":"venue"
},
  "geometry": {"coordinates":[2.652559,50.02536],"type":"Point"}
}