{
  "type": "Feature",
  "properties": {
    "iso:country":"FR",
    "sg:address":"34 rue Nationale; Amboise; 37400",
    "sg:city":"Amboise",
    "sg:classifiers":[
        {
            "category":"Banks & Credit Unions",
            "subcategory":"Bank",
            "type":"Services"
        }
    ],
    "sg:phone":"+33 3347305252",
    "sg:postcode":"37400",
    "sg:province":"Centre",
    "wof:name":"Cr\u00e9dit Lyonnais",
    "wof:placetype":"venue"
},
  "geometry": {"coordinates":[0.983144,47.412003],"type":"Point"}
}