{
  "type": "Feature",
  "properties": {
    "addr:full":"B.P. 15, 79014 Bessines C\u00e9dex^^Impasse des Ch\u00eanes, 79000 Bessines Poitou-Charentes 79000",
    "addr:postcode":"79014;79000;79000",
    "addr:street":"B.P. 15;Des Che\u0302Nes",
    "iso:country":"FR",
    "sg:address":"B.P. 15, 79014 Bessines C\u00e9dex^^Impasse des Ch\u00eanes, 79000 Bessines",
    "sg:orig_category":"Non-Classified Establishments",
    "sg:phone":"+33 5 49 04 78 40",
    "sg:postcode":"79000",
    "sg:province":"Poitou-Charentes",
    "wof:name":"Saunier Techna S.a.",
    "wof:placetype":"venue"
},
  "geometry": {"coordinates":[-0.504137,46.298],"type":"Point"}
}