{
  "type": "Feature",
  "properties": {
    "iso:country":"FR",
    "sg:address":"20 bis, Av. des Deux Routes, 84000 Avignon",
    "sg:orig_category":"Unclassifiable Establishments",
    "sg:phone":"+33 4 90 89 33 00",
    "sg:province":"Provence-Alpes-C\u00f4te d'Azur",
    "wof:name":"H\u00e9lios International S.a.",
    "wof:placetype":"venue"
},
  "geometry": {"coordinates":[4.805546,43.933296],"type":"Point"}
}