{
  "type": "Feature",
  "properties": {
    "addr:full":"B.P. 100, 29206 Landerneau C\u00e9dex^^ZI Lanrinou, 29800 Landerneau Landerneau Bretagne 29800",
    "addr:housenumber":"b.p. 100",
    "addr:postcode":"29206;29800;29800",
    "addr:street":"Lanrinou",
    "iso:country":"FR",
    "sg:address":"B.P. 100, 29206 Landerneau C\u00e9dex^^ZI Lanrinou, 29800 Landerneau",
    "sg:city":"Landerneau",
    "sg:orig_category":"Non-Classified Establishments",
    "sg:phone":"+33 2 98 25 30 00",
    "sg:postcode":"29800",
    "sg:province":"Bretagne",
    "wof:name":"Coop\u00e9rative Agriculteurs Bretagne",
    "wof:placetype":"venue"
},
  "geometry": {"coordinates":[-4.228497,48.400295],"type":"Point"}
}