{
  "type": "Feature",
  "properties": {
    "addr:full":"43 rue Nationale; La Membrolle Centre",
    "addr:housenumber":"43",
    "addr:street":"Rue Nationale La",
    "iso:country":"FR",
    "sg:address":"43 rue Nationale; La Membrolle",
    "sg:classifiers":[
        {
            "category":"Banks & Credit Unions",
            "subcategory":"Bank",
            "type":"Services"
        }
    ],
    "sg:phone":"+33 3347411935",
    "sg:province":"Centre",
    "wof:name":"Cr\u00e9dit Agricole Mutuel",
    "wof:placetype":"venue"
},
  "geometry": {"coordinates":[1.466895,47.985153],"type":"Point"}
}