{
  "type": "Feature",
  "properties": {
    "iso:country":"FR",
    "sg:address":"3, Rue de la Pointe Sirette, 91600 Savigny sur Orge",
    "sg:orig_category":"Non-Classified Establishments",
    "sg:phone":"+33 1 69 96 89 68",
    "sg:province":"Ile de France",
    "wof:name":"Istel S.a.",
    "wof:placetype":"venue"
},
  "geometry": {"coordinates":[2.355896,48.687923],"type":"Point"}
}