{
  "type": "Feature",
  "properties": {
    "iso:country":"FR",
    "sg:address":"31, Rue Ing\u00e9nieur Verri\u00e8re, 56100 Lorient",
    "sg:city":"Lorient",
    "sg:orig_category":"Non-Classified Establishments",
    "sg:phone":"+33 2 97 37 27 77",
    "sg:postcode":"56100",
    "sg:province":"Bretagne",
    "wof:name":"Tecnorope S.a.",
    "wof:placetype":"venue"
},
  "geometry": {"coordinates":[-3.368721,47.731007],"type":"Point"}
}