{
  "type": "Feature",
  "properties": {
    "iso:country":"FR",
    "sg:address":"126, Rte de Reims, 02200 Soissons",
    "sg:orig_category":"Non-Classified Establishments",
    "sg:phone":"+33 3 23 73 50 50",
    "sg:province":"Picardie",
    "wof:name":"Remex S.a.",
    "wof:placetype":"venue"
},
  "geometry": {"coordinates":[3.34279,49.37355],"type":"Point"}
}