{
  "type": "Feature",
  "properties": {
    "addr:full":"60, Av. du G\u00e9n\u00e9ral de Gaulle, 92800 Puteaux Ile de France",
    "addr:postcode":"92800",
    "addr:street":"60 Av. Du Ge\u0301Ne\u0301Ral De Gaulle",
    "iso:country":"FR",
    "sg:address":"60, Av. du G\u00e9n\u00e9ral de Gaulle, 92800 Puteaux",
    "sg:orig_category":"Non-Classified Establishments",
    "sg:phone":"+33 1 55 91 09 09",
    "sg:province":"Ile de France",
    "wof:name":"H.d.i. S.a. - Horizontal Drilling International",
    "wof:placetype":"venue"
},
  "geometry": {"coordinates":[2.232988,48.887951],"type":"Point"}
}