{
  "type": "Feature",
  "properties": {
    "iso:country":"FR",
    "sg:address":"60, Av. du G\u00e9n\u00e9ral de Gaulle, 92800 Puteaux",
    "sg:orig_category":"Non-Classified Establishments",
    "sg:phone":"+33 1 55 91 09 09",
    "sg:province":"Ile de France",
    "wof:name":"H.d.i. S.a. - Horizontal Drilling International",
    "wof:placetype":"venue"
},
  "geometry": {"coordinates":[2.232988,48.887951],"type":"Point"}
}