{
  "type": "Feature",
  "properties": {
    "iso:country":"FR",
    "sg:address":"B.P. 41",
    "sg:city":"Varennes les M\u00e2con C\u00e9dex^^Les Combes 71000 Varennes les M\u00e2con",
    "sg:orig_category":"Non-Classified Establishments",
    "sg:phone":"+33 3 85 34 89 15",
    "sg:postcode":"71002",
    "sg:province":"Bourgogne",
    "wof:name":"Papeterie Durand E.u.r.l.",
    "wof:placetype":"venue"
},
  "geometry": {"coordinates":[4.833055,46.303043],"type":"Point"}
}