{
  "type": "Feature",
  "properties": {
    "addr:full":"Le Grand Jardin Lauris Provence-Alpes-C\u00f4te d'Azur 84360",
    "addr:postcode":"84360",
    "addr:street":"Lauris",
    "iso:country":"FR",
    "sg:address":"Le Grand Jardin",
    "sg:city":"Lauris",
    "sg:orig_category":"Unclassifiable Establishments",
    "sg:phone":"+33 4 90 08 26 36",
    "sg:postcode":"84360",
    "sg:province":"Provence-Alpes-C\u00f4te d'Azur",
    "wof:name":"A.v.s. S.a.r.l. - Actuel Vins S\u00e9lection",
    "wof:placetype":"venue"
},
  "geometry": {"coordinates":[5.31155,43.746964],"type":"Point"}
}