{
  "type": "Feature",
  "properties": {
    "iso:country":"FR",
    "sg:address":"Rte Nantes 85670 Falleron",
    "sg:classifiers":[
        {
            "category":"Home & Garden",
            "subcategory":"Furniture",
            "type":"Retail Goods"
        }
    ],
    "sg:phone":"+33 2 51 93 01 03",
    "sg:postcode":"85670",
    "sg:province":"Pays de Loire",
    "sg:tags":[
        "household",
        "wood"
    ],
    "wof:name":"Ligne Delorme Sarl",
    "wof:placetype":"venue"
},
  "geometry": {"coordinates":[-1.703189,46.885891],"type":"Point"}
}