{
  "type": "Feature",
  "properties": {
    "addr:full":"64, Bd Malesherbes, 75008 Paris Ile de France",
    "addr:housenumber":"64",
    "addr:postcode":"75008",
    "addr:street":"Bd Malesherbes",
    "iso:country":"FR",
    "sg:address":"64, Bd Malesherbes, 75008 Paris",
    "sg:orig_category":"Unclassifiable Establishments",
    "sg:phone":"+33 1 44 90 10 10",
    "sg:province":"Ile de France",
    "wof:name":"Cosmopolitan Services Unlimited S.a.",
    "wof:placetype":"venue"
},
  "geometry": {"coordinates":[2.316213,48.878059],"type":"Point"}
}