{
  "type": "Feature",
  "properties": {
    "addr:full":"Briqueterie Justin Za Plateau Ouest 76460 St Valery En Caux Haute Normandie 76460",
    "addr:postcode":"76460;76460",
    "addr:street":"Za Plateau Ouest;Haute Normandie",
    "iso:country":"FR",
    "sg:address":"Briqueterie Justin Za Plateau Ouest 76460 St Valery En Caux",
    "sg:classifiers":[
        {
            "category":"Wholesale",
            "subcategory":"Construction Materials",
            "type":"Manufacturing & Wholesale Goods"
        }
    ],
    "sg:phone":"+33 2 35 57 85 20",
    "sg:postcode":"76460",
    "sg:province":"Haute Normandie",
    "sg:tags":[
        "work",
        "-",
        "metalworking",
        "metallic",
        "metallurgy",
        "finished",
        "public"
    ],
    "wof:name":"Cms",
    "wof:placetype":"venue"
},
  "geometry": {"coordinates":[0.711761,49.868813],"type":"Point"}
}