{
  "type": "Feature",
  "properties": {
    "iso:country":"FR",
    "sg:address":"Les Beauplans 17260 GEMOZAC",
    "sg:classifiers":[
        {
            "category":"Wholesale",
            "subcategory":"Wine & Distilled Alcoholic Beverages",
            "type":"Manufacturing & Wholesale Goods"
        }
    ],
    "sg:phone":"+33 5 46 96 52 25",
    "sg:postcode":"17260",
    "sg:province":"Poitou-Charentes",
    "sg:tags":[
        "french"
    ],
    "wof:name":"Adis France Sa",
    "wof:placetype":"venue"
},
  "geometry": {"coordinates":[-0.668119,45.572563],"type":"Point"}
}