{
  "type": "Feature",
  "properties": {
    "addr:full":"8, Rue de la Mairie, 91590 Cerny Ile de France",
    "addr:housenumber":"8",
    "addr:postcode":"91590;ile",
    "addr:street":"Rue De La Mairie",
    "iso:country":"FR",
    "sg:address":"8, Rue de la Mairie, 91590 Cerny",
    "sg:orig_category":"Non-Classified Establishments",
    "sg:phone":"+33 1 64 57 47 61",
    "sg:province":"Ile de France",
    "wof:name":"Magalu S.a.r.l.",
    "wof:placetype":"venue"
},
  "geometry": {"coordinates":[2.329635,48.475746],"type":"Point"}
}