{
  "type": "Feature",
  "properties": {
    "iso:country":"FR",
    "sg:address":"Rte Eyragues",
    "sg:city":"Maillane",
    "sg:orig_category":"Unclassifiable Establishments",
    "sg:phone":"+33 4 90 95 73 35",
    "sg:postcode":"13190",
    "sg:province":"Provence-Alpes-C\u00f4te d'Azur",
    "wof:name":"Combe Joseph S.a.r.l.",
    "wof:placetype":"venue"
},
  "geometry": {"coordinates":[4.784225,43.833469],"type":"Point"}
}