{
  "type": "Feature",
  "properties": {
    "iso:country":"FR",
    "sg:address":"Rue de la Gare - Z.I.",
    "sg:city":"Muizon",
    "sg:orig_category":"Unclassifiable Establishments",
    "sg:phone":"+33 3 26 89 91 00",
    "sg:postcode":"51140",
    "sg:province":"Champagne",
    "wof:name":"S.a.v.r. S.a.r.l. - Soci\u00e9t\u00e9 Ardennaise De V\u00e9hicules Roulants",
    "wof:placetype":"venue"
},
  "geometry": {"coordinates":[3.889085,49.275993],"type":"Point"}
}