{
  "type": "Feature",
  "properties": {
    "addr:full":"La Placette 13790 Rousset Aquitaine",
    "addr:postcode":"13790",
    "addr:street":"La Placette",
    "iso:country":"FR",
    "sg:address":"La Placette 13790 Rousset",
    "sg:classifiers":[
        {
            "category":"Health Services",
            "subcategory":"Medical Lab",
            "type":"Services"
        }
    ],
    "sg:phone":"+33 4 42 29 06 43",
    "sg:province":"Aquitaine",
    "sg:tags":[
        "upholstery"
    ],
    "wof:name":"Symagec Siplastec International S.a.",
    "wof:placetype":"venue"
},
  "geometry": {"coordinates":[5.621766,43.480957],"type":"Point"}
}