{
  "type": "Feature",
  "properties": {
    "iso:country":"FR",
    "sg:address":"Chemin de Meyne Clair - ZI",
    "sg:city":"Orange",
    "sg:orig_category":"Unclassifiable Establishments",
    "sg:phone":"+33 4 90 11 86 00",
    "sg:postcode":"84100",
    "sg:province":"Provence-Alpes-C\u00f4te d'Azur",
    "wof:name":"Rabillon Et Compagnie S.a.s.",
    "wof:placetype":"venue"
},
  "geometry": {"coordinates":[4.80867,44.136169],"type":"Point"}
}