{
  "type": "Feature",
  "properties": {
    "addr:full":"ZI de Lanvilou 29370 Coray Coray Bretagne 29370",
    "addr:postcode":"29370;29370",
    "addr:street":"Zi De Lanvilou",
    "iso:country":"FR",
    "sg:address":"ZI de Lanvilou 29370 Coray",
    "sg:city":"Coray",
    "sg:orig_category":"Tray-Formers",
    "sg:phone":"+33 2 98 59 76 20",
    "sg:postcode":"29370",
    "sg:province":"Bretagne",
    "wof:name":"Letang Fils S.a.r.l.",
    "wof:placetype":"venue"
},
  "geometry": {"coordinates":[-3.831229,48.060757],"type":"Point"}
}