{
  "type": "Feature",
  "properties": {
    "addr:full":"64 Bd Jean Jaur\u00e8s 91100 Corbeil Essonnes Ile de France",
    "addr:housenumber":"64",
    "addr:postcode":"91100",
    "addr:street":"Bd Jean Jaure\u0300S",
    "iso:country":"FR",
    "sg:address":"64 Bd Jean Jaur\u00e8s 91100 Corbeil Essonnes",
    "sg:classifiers":[
        {
            "category":"Autos & Motor Vehicles",
            "subcategory":"Automobile Sales",
            "type":"Retail Goods"
        }
    ],
    "sg:phone":"+33 1 60 89 76 76",
    "sg:province":"Ile de France",
    "sg:tags":[
        "equipment",
        "transport"
    ],
    "wof:name":"Essonne Motos Sa",
    "wof:placetype":"venue"
},
  "geometry": {"coordinates":[2.463741,48.609516],"type":"Point"}
}