{
  "type": "Feature",
  "properties": {
    "addr:full":"310, Chemin des Berthilliers - Espace d'Activit\u00e9s des Berthilliers, 71850 Charnay l\u00e8s M\u00e2con Charnay-l\u00e8s-M\u00e2con Bourgogne 71850",
    "addr:housenumber":"310",
    "addr:postcode":"71850;71850",
    "addr:street":"Chemin Des Berthilliers Espace",
    "iso:country":"FR",
    "sg:address":"310, Chemin des Berthilliers - Espace d'Activit\u00e9s des Berthilliers, 71850 Charnay l\u00e8s M\u00e2con",
    "sg:city":"Charnay-l\u00e8s-M\u00e2con",
    "sg:orig_category":"Non-Classified Establishments",
    "sg:phone":"+33 3 85 34 93 00",
    "sg:postcode":"71850",
    "sg:province":"Bourgogne",
    "wof:name":"G.e.f.i. S.a.",
    "wof:placetype":"venue"
},
  "geometry": {"coordinates":[4.786419,46.288811],"type":"Point"}
}