{
  "type": "Feature",
  "properties": {
    "addr:full":"47, Rue Diog\u00e8ne Maillart, 60480 Lachauss\u00e9e du Bois d'Ecu Picardie",
    "addr:housenumber":"47",
    "addr:postcode":"60480",
    "addr:street":"Rue Dioge\u0300Ne Maillart",
    "iso:country":"FR",
    "sg:address":"47, Rue Diog\u00e8ne Maillart, 60480 Lachauss\u00e9e du Bois d'Ecu",
    "sg:orig_category":"Unclassifiable Establishments",
    "sg:phone":"+33 3 44 80 72 53",
    "sg:province":"Picardie",
    "wof:name":"Blancard S.a.",
    "wof:placetype":"venue"
},
  "geometry": {"coordinates":[2.176245,49.564201],"type":"Point"}
}