{
  "type": "Feature",
  "properties": {
    "addr:full":"Z.I. des Tourondes Caussade Midi Pyr\u00e9n\u00e9es 82300",
    "addr:postcode":"82300",
    "addr:street":"Z.I. Des Tourondes",
    "iso:country":"FR",
    "sg:address":"Z.I. des Tourondes",
    "sg:city":"Caussade",
    "sg:orig_category":"Unclassifiable Establishments",
    "sg:phone":"+33 5 63 26 22 22",
    "sg:postcode":"82300",
    "sg:province":"Midi Pyr\u00e9n\u00e9es",
    "wof:name":"Guima S.a.",
    "wof:placetype":"venue"
},
  "geometry": {"coordinates":[1.525309,44.150475],"type":"Point"}
}