{
  "type": "Feature",
  "properties": {
    "iso:country":"FR",
    "sg:address":"6, Rue L\u00e9onard de Vinci - Parc d'Activit\u00e9 Technologiques, 53410 La Brulatte",
    "sg:orig_category":"Unclassifiable Establishments",
    "sg:phone":"+33 2 43 68 80 55",
    "sg:province":"Pays de Loire",
    "wof:name":"Psypharm S.a.",
    "wof:placetype":"venue"
},
  "geometry": {"coordinates":[-0.95187,48.085869],"type":"Point"}
}