{
  "type": "Feature",
  "properties": {
    "iso:country":"FR",
    "sg:address":"ZI de Silardi\u00e8re",
    "sg:city":"Le Chambon Feugerolles",
    "sg:orig_category":"Unclassifiable Establishments",
    "sg:phone":"+33 4 77 61 15 15",
    "sg:postcode":"42500",
    "sg:province":"Rhone-Alpes",
    "wof:name":"L.r.a. S.a.r.l. - Laurent Raby Assainissement",
    "wof:placetype":"venue"
},
  "geometry": {"coordinates":[4.321885,45.396324],"type":"Point"}
}