{
  "type": "Feature",
  "properties": {
    "iso:country":"FR",
    "sg:address":"22, Rue Panicale, 78320 La Verri\u00e8re",
    "sg:orig_category":"Non-Classified Establishments",
    "sg:phone":"+33 1 34 82 64 26",
    "sg:postcode":"78320",
    "sg:province":"Ile de France",
    "wof:name":"A.f.e. S.a.r.l.",
    "wof:placetype":"venue"
},
  "geometry": {"coordinates":[1.947238,48.757549],"type":"Point"}
}