{
  "type": "Feature",
  "properties": {
    "addr:full":"8 Rue Charlemagne 88600 Bruyeres Lorraine 88600",
    "addr:housenumber":"8",
    "addr:postcode":"88600;88600",
    "addr:street":"Rue Charlemagne",
    "iso:country":"FR",
    "sg:address":"8 Rue Charlemagne 88600 Bruyeres",
    "sg:classifiers":[
        {
            "category":"Manufacturing",
            "subcategory":"Glass & Minerals",
            "type":"Manufacturing & Wholesale Goods"
        }
    ],
    "sg:phone":"+33 3 29 52 40 00",
    "sg:postcode":"88600",
    "sg:province":"Lorraine",
    "sg:tags":[
        "building",
        "motor-cars",
        "material",
        "equipment",
        "vehicle",
        "transport"
    ],
    "wof:name":"Ficocipa Sarl",
    "wof:placetype":"venue"
},
  "geometry": {"coordinates":[6.71723,48.20554],"type":"Point"}
}