{
  "type": "Feature",
  "properties": {
    "addr:full":"2, Rue L\u00e9onard de Vinci, 69120 Vaulx en Velin Rhone-Alpes 69120",
    "addr:housenumber":"2",
    "addr:postcode":"69120;69120",
    "addr:street":"Rue Le\u0301Onard De Vinci",
    "iso:country":"FR",
    "sg:address":"2, Rue L\u00e9onard de Vinci, 69120 Vaulx en Velin",
    "sg:orig_category":"Unclassifiable Establishments",
    "sg:phone":"+33 4 78 79 38 39",
    "sg:postcode":"69120",
    "sg:province":"Rhone-Alpes",
    "wof:name":"Timar Leisystem S.a.r.l.",
    "wof:placetype":"venue"
},
  "geometry": {"coordinates":[4.930858,45.778919],"type":"Point"}
}