{
  "type": "Feature",
  "properties": {
    "iso:country":"FR",
    "sg:address":"51, Av. Franklin Roosevelt, 69150 D\u00e9cines Charpieu",
    "sg:orig_category":"Unclassifiable Establishments",
    "sg:phone":"+33 4 72 02 69 90",
    "sg:postcode":"69150",
    "sg:province":"Rhone-Alpes",
    "wof:name":"S.c.m.p. S.a. - Soci\u00e9t\u00e9 De Constructions Moules Plastiques",
    "wof:placetype":"venue"
},
  "geometry": {"coordinates":[4.937278,45.762466],"type":"Point"}
}