{
  "type": "Feature",
  "properties": {
    "iso:country":"FR",
    "sg:address":"La Chauss\u00e9e 16140 Villej\u00e9sus",
    "sg:orig_category":"Unclassifiable Establishments",
    "sg:phone":"+33 5 45 21 10 89",
    "sg:province":"Poitou-Charentes",
    "wof:name":"Carti Meubles S.a.r.l.",
    "wof:placetype":"venue"
},
  "geometry": {"coordinates":[0.015605,45.89782],"type":"Point"}
}