{
  "type": "Feature",
  "properties": {
    "iso:country":"FR",
    "sg:address":"Rte du Midi",
    "sg:city":"Tremblay en France",
    "sg:orig_category":"Unclassifiable Establishments",
    "sg:phone":"+33 1 48 62 48 00",
    "sg:postcode":"93290",
    "sg:province":"Ile de France",
    "wof:name":"C.a.t. S.a. - Compagnie D'affr\u00e8tement Et De Transport",
    "wof:placetype":"venue"
},
  "geometry": {"coordinates":[2.5279,48.996819],"type":"Point"}
}