{
  "type": "Feature",
  "properties": {
    "addr:full":"1 Rue Du Ch\u00eane Lass\u00e9 Cp 1006 44806 St Herblain Pays de Loire",
    "addr:housenumber":"1;44806",
    "addr:street":"Rue Du Che\u0302Ne;St Herblain",
    "iso:country":"FR",
    "sg:address":"1 Rue Du Ch\u00eane Lass\u00e9 Cp 1006 44806 St Herblain",
    "sg:classifiers":[
        {
            "category":"Food & Beverages",
            "subcategory":"Groceries & Convenience Stores",
            "type":"Retail Goods"
        }
    ],
    "sg:phone":"+33 2 28 03 09 30",
    "sg:province":"Pays de Loire",
    "sg:tags":[
        "product",
        "related"
    ],
    "wof:name":"Snd - Societe Nouvelle Duteil Groupe Tipiak",
    "wof:placetype":"venue"
},
  "geometry": {"coordinates":[-1.654052,47.211758],"type":"Point"}
}