{
  "type": "Feature",
  "properties": {
    "addr:full":"12 Rue Pasteur Caen Basse Normandie 14000",
    "addr:housenumber":"12",
    "addr:postcode":"14000",
    "addr:street":"Rue Pasteur",
    "iso:country":"FR",
    "sg:address":"12 Rue Pasteur",
    "sg:city":"Caen",
    "sg:classifiers":[
        {
            "category":"Banks & Credit Unions",
            "subcategory":"Financial Services",
            "type":"Services"
        }
    ],
    "sg:phone":"+33 2 31 27 14 74",
    "sg:postcode":"14000",
    "sg:province":"Basse Normandie",
    "sg:tags":[
        "banking",
        "finance",
        "insurance"
    ],
    "wof:name":"Maitre Mauduit Et Maitre Pelletier",
    "wof:placetype":"venue"
},
  "geometry": {"coordinates":[-0.36789,49.183483],"type":"Point"}
}