{
  "type": "Feature",
  "properties": {
    "iso:country":"FR",
    "sg:address":"4, Rue Henry Monnier, 75009 Paris",
    "sg:orig_category":"Non-Classified Establishments",
    "sg:phone":"+33 1 48 78 59 76",
    "sg:province":"Ile de France",
    "wof:name":"F.h. Diedrichs & Ludwig Post S.a.r.l.",
    "wof:placetype":"venue"
},
  "geometry": {"coordinates":[2.337074,48.879196],"type":"Point"}
}