{
  "type": "Feature",
  "properties": {
    "iso:country":"FR",
    "sg:address":"Av. de la Vistrenque - Zone Euro 2000",
    "sg:city":"Caissargues",
    "sg:orig_category":"Unclassifiable Establishments",
    "sg:phone":"+33 4 66 38 93 98",
    "sg:postcode":"30132",
    "sg:province":"Languedoc-Roussillon",
    "wof:name":"Unanimes Sica S.a.",
    "wof:placetype":"venue"
},
  "geometry": {"coordinates":[4.377945,43.796341],"type":"Point"}
}