{
  "type": "Feature",
  "properties": {
    "addr:full":"All De L'Industrie Zi 80800 Corbie Picardie 80800",
    "addr:postcode":"80800;80800",
    "addr:street":"Zi",
    "iso:country":"FR",
    "sg:address":"All De L'Industrie Zi 80800 Corbie",
    "sg:classifiers":[
        {
            "category":"Utilities",
            "subcategory":"Electric",
            "type":"Services"
        }
    ],
    "sg:phone":"+33 3 22 48 32 44",
    "sg:postcode":"80800",
    "sg:province":"Picardie",
    "sg:tags":[
        "electricity",
        "electronic",
        "electrical",
        "equipment"
    ],
    "wof:name":"Sopelec Reseaux",
    "wof:placetype":"venue"
},
  "geometry": {"coordinates":[2.492721,49.916637],"type":"Point"}
}