{
  "type": "Feature",
  "properties": {
    "addr:full":"104, Bd des Plages, 64600 Anglet Anglet Aquitaine 64600",
    "addr:housenumber":"104",
    "addr:postcode":"64600;64600",
    "addr:street":"Bd Des Plages",
    "iso:country":"FR",
    "sg:address":"104, Bd des Plages, 64600 Anglet",
    "sg:city":"Anglet",
    "sg:orig_category":"Non-Classified Establishments",
    "sg:phone":"+33 5 59 58 48 48",
    "sg:postcode":"64600",
    "sg:province":"Aquitaine",
    "wof:name":"Espace Chiberta",
    "wof:placetype":"venue"
},
  "geometry": {"coordinates":[-1.524939,43.513786],"type":"Point"}
}