{
  "type": "Feature",
  "properties": {
    "iso:country":"FR",
    "sg:address":"Quaigeneral Lawton Collins 50100 Cherbourg Octeville",
    "sg:city":"Cherbourg-Octeville",
    "sg:classifiers":[
        {
            "category":"Autos & Motor Vehicles",
            "subcategory":"Boat Sales",
            "type":"Retail Goods"
        }
    ],
    "sg:phone":"+33 2 33 88 73 00",
    "sg:postcode":"50100",
    "sg:province":"Basse Normandie",
    "sg:tags":[
        "equipment",
        "transport"
    ],
    "wof:name":"Ateliers H C T",
    "wof:placetype":"venue"
},
  "geometry": {"coordinates":[-1.618959,49.63942],"type":"Point"}
}