{
  "type": "Feature",
  "properties": {
    "iso:country":"FR",
    "sg:address":"Z Artisanale 43000 POLIGNAC",
    "sg:city":"Le Puy-en-Velay",
    "sg:classifiers":[
        {
            "category":"Food & Beverages",
            "subcategory":"Fruits & Vegetables",
            "type":"Retail Goods"
        }
    ],
    "sg:phone":"+33 4 71 09 66 44",
    "sg:postcode":"43000",
    "sg:province":"Auvergne",
    "sg:tags":[
        "canned"
    ],
    "wof:name":"La Tour De Polignac Sa",
    "wof:placetype":"venue"
},
  "geometry": {"coordinates":[3.895839,45.017532],"type":"Point"}
}