{
  "type": "Feature",
  "properties": {
    "addr:full":"25, Av. G\u00e9n\u00e9ral de Gaulle, 33290 Blanquefort Blanquefort Aquitaine 33290",
    "addr:postcode":"33290;33290",
    "addr:street":"25 Av. Ge\u0301Ne\u0301Ral De Gaulle",
    "iso:country":"FR",
    "sg:address":"25, Av. G\u00e9n\u00e9ral de Gaulle, 33290 Blanquefort",
    "sg:city":"Blanquefort",
    "sg:orig_category":"Non-Classified Establishments",
    "sg:phone":"+33 5 56 95 05 06",
    "sg:postcode":"33290",
    "sg:province":"Aquitaine",
    "wof:name":"Editions Dussaut S.a.r.l.",
    "wof:placetype":"venue"
},
  "geometry": {"coordinates":[-0.634809,44.919392],"type":"Point"}
}