{
  "type": "Feature",
  "properties": {
    "addr:full":"ZI Saint Maurice; 04100 Manosque-en-Provence Aquitaine",
    "addr:postcode":"04100",
    "iso:country":"FR",
    "sg:address":"ZI Saint Maurice; 04100 Manosque-en-Provence",
    "sg:classifiers":[
        {
            "category":"Industrial Area",
            "type":"Public Place"
        }
    ],
    "sg:phone":"+33 4 92 70 19 00",
    "sg:province":"Aquitaine",
    "sg:tags":[
        "large",
        "private"
    ],
    "wof:name":"L'occitane Limited",
    "wof:placetype":"venue"
},
  "geometry": {"coordinates":[5.784205,43.831474],"type":"Point"}
}