{
  "type": "Feature",
  "properties": {
    "addr:full":"41, Rue de la Tour, 77410 Villevaud\u00e9 Ile de France",
    "addr:housenumber":"41",
    "addr:postcode":"77410",
    "addr:street":"Rue De La Tour;Ile De France",
    "iso:country":"FR",
    "sg:address":"41, Rue de la Tour, 77410 Villevaud\u00e9",
    "sg:orig_category":"Unclassifiable Establishments",
    "sg:phone":"+33 1 60 26 92 70",
    "sg:province":"Ile de France",
    "wof:name":"Jardem S.a.",
    "wof:placetype":"venue"
},
  "geometry": {"coordinates":[2.669064,48.907948],"type":"Point"}
}