{
  "type": "Feature",
  "properties": {
    "iso:country":"FR",
    "sg:address":"rue du G\u00e9n\u00e9ral de Gaulle 45130 Meung sur Loire",
    "sg:city":"Baule",
    "sg:classifiers":[
        {
            "category":"Food & Beverages",
            "subcategory":"Groceries & Convenience Stores",
            "type":"Retail Goods"
        }
    ],
    "sg:phone":"+33 2 38 44 31 04",
    "sg:postcode":"45130",
    "sg:province":"Centre",
    "sg:tags":[
        "flour",
        "meal"
    ],
    "wof:name":"Minoterie Du Coutelet Sa",
    "wof:placetype":"venue"
},
  "geometry": {"coordinates":[1.698766,47.828362],"type":"Point"}
}