{
  "type": "Feature",
  "properties": {
    "iso:country":"FR",
    "sg:address":"Rue Jean Moulin Zi 52260 Rolampont",
    "sg:classifiers":[
        {
            "category":"Shopping",
            "subcategory":"Clothing, Apparel, & Fashions",
            "type":"Retail Goods"
        }
    ],
    "sg:phone":"+33 3 25 84 72 20",
    "sg:postcode":"52260",
    "sg:province":"Champagne",
    "sg:tags":[
        "textile",
        "clothing",
        "clothes"
    ],
    "wof:name":"Sntb",
    "wof:placetype":"venue"
},
  "geometry": {"coordinates":[5.28544,47.948673],"type":"Point"}
}