{
  "type": "Feature",
  "properties": {
    "addr:full":"14 Rue Aulnes BP 1 88230 Fraize Lorraine",
    "addr:housenumber":"14;1",
    "addr:postcode":"88230",
    "addr:street":"Rue Aulnes Bp",
    "iso:country":"FR",
    "sg:address":"14 Rue Aulnes BP 1 88230 Fraize",
    "sg:classifiers":[
        {
            "category":"Manufacturing",
            "subcategory":"Wood Products",
            "type":"Manufacturing & Wholesale Goods"
        }
    ],
    "sg:phone":"+33 3 29 52 39 00",
    "sg:province":"Lorraine",
    "sg:tags":[
        "professional",
        "furniture"
    ],
    "wof:name":"Malora Simeuble Sarl",
    "wof:placetype":"venue"
},
  "geometry": {"coordinates":[6.99383,48.187923],"type":"Point"}
}