{
  "type": "Feature",
  "properties": {
    "iso:country":"FR",
    "sg:address":"14 Rue Aulnes BP 1 88230 Fraize",
    "sg:classifiers":[
        {
            "category":"Manufacturing",
            "subcategory":"Wood Products",
            "type":"Manufacturing & Wholesale Goods"
        }
    ],
    "sg:phone":"+33 3 29 52 39 00",
    "sg:province":"Lorraine",
    "sg:tags":[
        "professional",
        "furniture"
    ],
    "wof:name":"Malora Simeuble Sarl",
    "wof:placetype":"venue"
},
  "geometry": {"coordinates":[6.99383,48.187923],"type":"Point"}
}