{
  "type": "Feature",
  "properties": {
    "addr:full":"Hangard d'Aviation Aeroport Perigue 24330 BASSILAC Bassillac Aquitaine 24330",
    "addr:postcode":"24330;24330",
    "iso:country":"FR",
    "sg:address":"Hangard d'Aviation Aeroport Perigue 24330 BASSILAC",
    "sg:city":"Bassillac",
    "sg:classifiers":[
        {
            "category":"Wholesale",
            "subcategory":"Books, Periodicals, & Newspapers",
            "type":"Manufacturing & Wholesale Goods"
        }
    ],
    "sg:phone":"+33 5 53 35 91 21",
    "sg:postcode":"24330",
    "sg:province":"Aquitaine",
    "sg:tags":[
        "publisher",
        "journal"
    ],
    "wof:name":"Ste Jacques Legrand S.a.",
    "wof:placetype":"venue"
},
  "geometry": {"coordinates":[0.81252,45.19191],"type":"Point"}
}