{
  "type": "Feature",
  "properties": {
    "iso:country":"FR",
    "sg:address":"B.P. 53, 22202 Guingamp C\u00e9dex^^ZA Keranfeuillen Treglamus, 22200 Guingamp",
    "sg:city":"Guingamp",
    "sg:orig_category":"Non-Classified Establishments",
    "sg:phone":"+33 2 96 40 16 60",
    "sg:postcode":"22200",
    "sg:province":"Bretagne",
    "wof:name":"Tr\u00e9gor Oeuf S.a.",
    "wof:placetype":"venue"
},
  "geometry": {"coordinates":[-3.240289,48.517059],"type":"Point"}
}