{
  "type": "Feature",
  "properties": {
    "iso:country":"FR",
    "sg:address":"10 rue Jean Jaur\u00e8s 92800 Puteaux",
    "sg:classifiers":[
        {
            "category":"Social Services",
            "subcategory":"Job Training",
            "type":"Services"
        }
    ],
    "sg:phone":"+33 1 49 07 85 55",
    "sg:postcode":"92800",
    "sg:province":"Ile de France",
    "sg:tags":[
        "calculation",
        "engineering",
        "mechanical",
        "software"
    ],
    "wof:name":"American Software France S.a.",
    "wof:placetype":"venue"
},
  "geometry": {"coordinates":[2.249529,48.885403],"type":"Point"}
}