{
  "type": "Feature",
  "properties": {
    "addr:full":"Route Du Rouvray Le Pont Aux Moines Cd 13 76440 Roncherolles En Bray Haute Normandie 76440",
    "addr:postcode":"76440;76440",
    "addr:street":"Route Du Rouvray;Cd 13;Haute Normandie",
    "iso:country":"FR",
    "sg:address":"Route Du Rouvray Le Pont Aux Moines Cd 13 76440 Roncherolles En Bray",
    "sg:classifiers":[
        {
            "category":"Professional",
            "subcategory":"Engineering",
            "type":"Services"
        }
    ],
    "sg:phone":"+33 2 32 89 92 60",
    "sg:postcode":"76440",
    "sg:province":"Haute Normandie",
    "sg:tags":[
        "machine",
        "-",
        "mechanical"
    ],
    "wof:name":"Energie Lait Lefranc",
    "wof:placetype":"venue"
},
  "geometry": {"coordinates":[1.5073,49.5956],"type":"Point"}
}