{
  "type": "Feature",
  "properties": {
    "addr:full":"Rte Du Coin 42402 St Chamond Cedex Picardie",
    "addr:postcode":"42402;chamond cedex",
    "addr:street":"Rte Du Coin",
    "iso:country":"FR",
    "sg:address":"Rte Du Coin 42402 St Chamond Cedex",
    "sg:classifiers":[
        {
            "category":"Government",
            "subcategory":"Department Of Motor Vehicles",
            "type":"Public Place"
        }
    ],
    "sg:phone":"+33 4 77 31 73 73",
    "sg:province":"Picardie",
    "sg:tags":[
        "engine",
        "machine",
        "good",
        "-",
        "metalwo",
        "engineering",
        "metallic",
        "metallurgy",
        "finished",
        "part",
        "mechanical"
    ],
    "wof:name":"Rafer Sa",
    "wof:placetype":"venue"
},
  "geometry": {"coordinates":[4.518753,45.471889],"type":"Point"}
}