{
  "type": "Feature",
  "properties": {
    "addr:full":"7, Rte du Paradis - ZAC du Paradis, 18500 Mehun sur Y\u00e8vre Marmagne Centre 18500",
    "addr:housenumber":"7",
    "addr:postcode":"18500;18500",
    "addr:street":"Rte Du Paradis Zac Du Paradis",
    "iso:country":"FR",
    "sg:address":"7, Rte du Paradis - ZAC du Paradis, 18500 Mehun sur Y\u00e8vre",
    "sg:city":"Marmagne",
    "sg:orig_category":"Unclassifiable Establishments",
    "sg:phone":"+33 2 48 57 30 52",
    "sg:postcode":"18500",
    "sg:province":"Centre",
    "wof:name":"O.p.b. S.a.r.l. - Outillage De Pr\u00e9cision Du Berry",
    "wof:placetype":"venue"
},
  "geometry": {"coordinates":[2.318975,47.076126],"type":"Point"}
}