{
  "type": "Feature",
  "properties": {
    "addr:full":"39 rue du 3e Zouave 68130 Altkirch Altkirch Alsace 68130",
    "addr:housenumber":"39",
    "addr:postcode":"68130;68130",
    "addr:street":"Rue Du 3E Zouave",
    "iso:country":"FR",
    "sg:address":"39 rue du 3e Zouave 68130 Altkirch",
    "sg:city":"Altkirch",
    "sg:classifiers":[
        {
            "category":"Shopping",
            "subcategory":"Pharmacy",
            "type":"Retail Goods"
        }
    ],
    "sg:phone":"+33 3 89 08 96 30",
    "sg:postcode":"68130",
    "sg:province":"Alsace",
    "sg:tags":[
        "preparation",
        "pharmaceutical"
    ],
    "wof:name":"Sankyo Farma Sarl",
    "wof:placetype":"venue"
},
  "geometry": {"coordinates":[7.257308,47.625961],"type":"Point"}
}