{
  "type": "Feature",
  "properties": {
    "iso:country":"FR",
    "sg:address":"Les Laburets 18570 La Chapelle Saint Ursin",
    "sg:city":"Le Subdray",
    "sg:orig_category":"Non-Classified Establishments",
    "sg:phone":"+33 2 48 66 64 00",
    "sg:postcode":"18570",
    "sg:province":"Centre",
    "wof:name":"Rehau Tube S.a.",
    "wof:placetype":"venue"
},
  "geometry": {"coordinates":[2.30327,47.050404],"type":"Point"}
}