{
  "type": "Feature",
  "properties": {
    "iso:country":"FR",
    "sg:address":"10, Rue Pierre Timbaud, 69200 V\u00e9nissieux",
    "sg:orig_category":"Unclassifiable Establishments",
    "sg:phone":"+33 4 72 90 17 17",
    "sg:postcode":"69200",
    "sg:province":"Rhone-Alpes",
    "wof:name":"Frascone Industrie S.a.s.",
    "wof:placetype":"venue"
},
  "geometry": {"coordinates":[4.903567,45.692547],"type":"Point"}
}