{
  "type": "Feature",
  "properties": {
    "iso:country":"FR",
    "sg:address":"7, Rue des Flobarts, 62200 Boulogne sur Mer",
    "sg:orig_category":"Non-Classified Establishments",
    "sg:phone":"+33 3 21 83 32 32",
    "sg:postcode":"62200",
    "sg:province":"Nord Pas-de-Calais",
    "wof:name":"Co. Bo. Ma. S.a.r.l. - Compagnie Boulonnaise De Mar\u00e9e",
    "wof:placetype":"venue"
},
  "geometry": {"coordinates":[1.615514,50.727444],"type":"Point"}
}