{
  "type": "Feature",
  "properties": {
    "addr:full":"3, Rue du Docteur Blanche, 75016 Paris Ile de France",
    "addr:housenumber":"3",
    "addr:postcode":"75016",
    "addr:street":"Rue Du Docteur Blanche",
    "iso:country":"FR",
    "sg:address":"3, Rue du Docteur Blanche, 75016 Paris",
    "sg:orig_category":"Non-Classified Establishments",
    "sg:phone":"+33 1 45 27 41 43",
    "sg:province":"Ile de France",
    "wof:name":"L.m.j. Lienard S.a.r.l.",
    "wof:placetype":"venue"
},
  "geometry": {"coordinates":[2.266092,48.855301],"type":"Point"}
}