{
  "type": "Feature",
  "properties": {
    "iso:country":"FR",
    "sg:address":"Rue Forges 49600 Beaupr\u00e9au",
    "sg:classifiers":[
        {
            "category":"Shopping",
            "subcategory":"Luggage & Leather Goods",
            "type":"Retail Goods"
        }
    ],
    "sg:phone":"+33 2 41 63 61 22",
    "sg:postcode":"49600",
    "sg:province":"Pays de Loire",
    "sg:tags":[
        "shoe"
    ],
    "wof:name":"Gbb Sa",
    "wof:placetype":"venue"
},
  "geometry": {"coordinates":[-0.972509,47.207596],"type":"Point"}
}