{
  "type": "Feature",
  "properties": {
    "addr:full":"15, Rue Charles Bertheau, 75013 Paris Ile de France",
    "addr:housenumber":"15",
    "addr:postcode":"75013",
    "addr:street":"Rue Charles Bertheau",
    "iso:country":"FR",
    "sg:address":"15, Rue Charles Bertheau, 75013 Paris",
    "sg:orig_category":"Non-Classified Establishments",
    "sg:phone":"+33 1 45 85 12 81",
    "sg:province":"Ile de France",
    "wof:name":"Oriental Kitchen S.a.r.l.",
    "wof:placetype":"venue"
},
  "geometry": {"coordinates":[2.363554,48.822678],"type":"Point"}
}