{
  "type": "Feature",
  "properties": {
    "addr:full":"1, Rue Charles de Gaulle, 01200 Bellegarde sur Valserine Rhone-Alpes 01200",
    "addr:housenumber":"1",
    "addr:postcode":"01200;01200",
    "addr:street":"Rue Charles De Gaulle;Rhone-Alpes",
    "iso:country":"FR",
    "sg:address":"1, Rue Charles de Gaulle, 01200 Bellegarde sur Valserine",
    "sg:orig_category":"Non-Classified Establishments",
    "sg:phone":"+33 4 50 56 67 20",
    "sg:postcode":"01200",
    "sg:province":"Rhone-Alpes",
    "wof:name":"Cariane Touriscar Ain S.a.r.l.",
    "wof:placetype":"venue"
},
  "geometry": {"coordinates":[5.824142,46.109688],"type":"Point"}
}