{
  "type": "Feature",
  "properties": {
    "addr:full":"23 avenue de Compi\u00e8gne 02200 Soissons Picardie 02200",
    "addr:housenumber":"23",
    "addr:postcode":"02200;02200",
    "addr:street":"Avenue De Compie\u0300Gne",
    "iso:country":"FR",
    "sg:address":"23 avenue de Compi\u00e8gne 02200 Soissons",
    "sg:classifiers":[
        {
            "category":"Wholesale",
            "subcategory":"Home Furnishings",
            "type":"Manufacturing & Wholesale Goods"
        }
    ],
    "sg:phone":"+33 3 23 53 14 40",
    "sg:postcode":"02200",
    "sg:province":"Picardie",
    "sg:tags":[
        "house",
        "paint"
    ],
    "wof:name":"Paille Onip Sa",
    "wof:placetype":"venue"
},
  "geometry": {"coordinates":[3.314135,49.381706],"type":"Point"}
}