{
  "type": "Feature",
  "properties": {
    "iso:country":"FR",
    "sg:address":"1 rte Armorique; Landeda",
    "sg:classifiers":[
        {
            "category":"Banks & Credit Unions",
            "subcategory":"Bank",
            "type":"Services"
        }
    ],
    "sg:phone":"+33 3398049349",
    "sg:province":"Haute Normandie",
    "wof:name":"Cr\u00e9dit Agricole Mutuel",
    "wof:placetype":"venue"
},
  "geometry": {"coordinates":[-4.573203,48.587372],"type":"Point"}
}