{
  "type": "Feature",
  "properties": {
    "iso:country":"FR",
    "sg:address":"42, Av. du Mar\u00e9chal Foch, 06000 Nice",
    "sg:orig_category":"Non-Classified Establishments",
    "sg:phone":"+33 4 92 17 41 61",
    "sg:province":"Outre-Mer",
    "wof:name":"X\u00e9rox S.a.",
    "wof:placetype":"venue"
},
  "geometry": {"coordinates":[7.267276,43.702885],"type":"Point"}
}