{
  "type": "Feature",
  "properties": {
    "addr:full":"33, Bd Fr\u00e9d\u00e9ric Mistral, 30400 Villeneuve les Avignon Languedoc-Roussillon",
    "addr:housenumber":"33",
    "addr:postcode":"30400",
    "addr:street":"Bd Fre\u0301De\u0301Ric Mistral",
    "iso:country":"FR",
    "sg:address":"33, Bd Fr\u00e9d\u00e9ric Mistral, 30400 Villeneuve les Avignon",
    "sg:orig_category":"Non-Classified Establishments",
    "sg:phone":"+33 4 90 25 09 94",
    "sg:province":"Languedoc-Roussillon",
    "wof:name":"P.s.i. S.a.r.l. - Produits Sp\u00e9ciaux D'isolation",
    "wof:placetype":"venue"
},
  "geometry": {"coordinates":[4.796088,43.972809],"type":"Point"}
}