{
  "type": "Feature",
  "properties": {
    "iso:country":"FR",
    "sg:address":"18 Rte Mardyck 59380 Spycker",
    "sg:classifiers":[
        {
            "category":"Professional",
            "subcategory":"Engineering",
            "type":"Services"
        }
    ],
    "sg:phone":"+33 3 28 27 77 37",
    "sg:postcode":"59380",
    "sg:province":"Nord Pas-de-Calais",
    "sg:tags":[
        "machine",
        "-",
        "mechanical"
    ],
    "wof:name":"Egi Sa",
    "wof:placetype":"venue"
},
  "geometry": {"coordinates":[2.302787,50.983269],"type":"Point"}
}