{
  "type": "Feature",
  "properties": {
    "iso:country":"FR",
    "sg:address":"75 Rue De Gerland 69007 Lyon",
    "sg:classifiers":[
        {
            "category":"Manufacturing",
            "subcategory":"Textiles",
            "type":"Manufacturing & Wholesale Goods"
        }
    ],
    "sg:phone":"+33 4 72 71 91 48",
    "sg:province":"Rhone-Alpes",
    "sg:tags":[
        "clothing",
        "accessory"
    ],
    "wof:name":"Maison Jean Minodier",
    "wof:placetype":"venue"
},
  "geometry": {"coordinates":[4.839916,45.737625],"type":"Point"}
}