{
  "type": "Feature",
  "properties": {
    "addr:full":"22 Place La Fayette Angers Pays de Loire 49000",
    "addr:housenumber":"22",
    "addr:postcode":"49000",
    "addr:street":"Place La Fayette Angers Pays",
    "iso:country":"FR",
    "sg:address":"22 Place La Fayette",
    "sg:city":"Angers",
    "sg:classifiers":[
        {
            "category":"Banks & Credit Unions",
            "subcategory":"Financial Services",
            "type":"Services"
        }
    ],
    "sg:phone":"+33 2 41 23 54 54",
    "sg:postcode":"49000",
    "sg:province":"Pays de Loire",
    "sg:tags":[
        "banking",
        "finance",
        "insurance"
    ],
    "wof:name":"Ste Organis Gestion Expertise Comptable Sa",
    "wof:placetype":"venue"
},
  "geometry": {"coordinates":[-0.553269,47.46241],"type":"Point"}
}