{
  "type": "Feature",
  "properties": {
    "iso:country":"FR",
    "sg:address":"56 Rue De La Gare 57300 Hagondange",
    "sg:classifiers":[
        {
            "category":"Shopping",
            "subcategory":"Crafts & Fabrics",
            "type":"Retail Goods"
        }
    ],
    "sg:phone":"+33 3 87 72 21 83",
    "sg:postcode":"57300",
    "sg:province":"Lorraine",
    "sg:tags":[
        "textile",
        "clothing"
    ],
    "wof:name":"Societe Au Fil Des Idees",
    "wof:placetype":"venue"
},
  "geometry": {"coordinates":[6.165297,49.252422],"type":"Point"}
}