{
  "type": "Feature",
  "properties": {
    "addr:full":"La Taffarette 77164 Ferri\u00e8res en Brie Ile de France 77164",
    "addr:postcode":"77164;77164",
    "iso:country":"FR",
    "sg:address":"La Taffarette 77164 Ferri\u00e8res en Brie",
    "sg:orig_category":"Non-Classified Establishments",
    "sg:phone":"+33 1 64 66 31 16",
    "sg:postcode":"77164",
    "sg:province":"Ile de France",
    "wof:name":"Etablissements B.l.m. S.a.",
    "wof:placetype":"venue"
},
  "geometry": {"coordinates":[2.704695,48.821323],"type":"Point"}
}