{
  "type": "Feature",
  "properties": {
    "addr:full":"Rue de Longpont Montlh\u00e9ry Ile de France 91310",
    "addr:postcode":"91310",
    "addr:street":"Rue De Longpont;Ile De France",
    "iso:country":"FR",
    "sg:address":"Rue de Longpont",
    "sg:city":"Montlh\u00e9ry",
    "sg:orig_category":"Unclassifiable Establishments",
    "sg:phone":"+33 1 69 80 21 00",
    "sg:postcode":"91310",
    "sg:province":"Ile de France",
    "wof:name":"Bergerat Monnoyeur Energie S.a.",
    "wof:placetype":"venue"
},
  "geometry": {"coordinates":[2.277845,48.646065],"type":"Point"}
}