{
  "type": "Feature",
  "properties": {
    "addr:full":"Le Village 01560 Saint Nizier le Bouchoux Rhone-Alpes 01560",
    "addr:postcode":"01560;01560",
    "addr:street":"Le Village;Nizier Le;Rhone-Alpes",
    "iso:country":"FR",
    "sg:address":"Le Village 01560 Saint Nizier le Bouchoux",
    "sg:orig_category":"Unclassifiable Establishments",
    "sg:phone":"+33 4 74 52 92 34",
    "sg:postcode":"01560",
    "sg:province":"Rhone-Alpes",
    "wof:name":"So.di.ca. S.a.r.l.",
    "wof:placetype":"venue"
},
  "geometry": {"coordinates":[5.116601,46.439442],"type":"Point"}
}