{
  "type": "Feature",
  "properties": {
    "iso:country":"FR",
    "sg:address":"Z.A. Les Bruott\u00e9es",
    "sg:city":"Vignoles",
    "sg:orig_category":"Unclassifiable Establishments",
    "sg:phone":"+33 3 80 22 21 20",
    "sg:postcode":"21200",
    "sg:province":"Bourgogne",
    "wof:name":"O.m.c. S.a.r.l. - Outillage Moules Cr\u00e9ation",
    "wof:placetype":"venue"
},
  "geometry": {"coordinates":[4.872662,47.020493],"type":"Point"}
}