{
  "type": "Feature",
  "properties": {
    "iso:country":"FR",
    "sg:address":"Rue Des Abattoirs 50200 Coutances",
    "sg:city":"Coutances",
    "sg:classifiers":[
        {
            "category":"Banks & Credit Unions",
            "subcategory":"Investment Brokerage",
            "type":"Services"
        }
    ],
    "sg:phone":"+33 2 33 76 53 53",
    "sg:postcode":"50200",
    "sg:province":"Basse Normandie",
    "sg:tags":[
        "-",
        "transport",
        "related"
    ],
    "wof:name":"Sofrino Sogena",
    "wof:placetype":"venue"
},
  "geometry": {"coordinates":[-1.441718,49.039745],"type":"Point"}
}