{
  "type": "Feature",
  "properties": {
    "iso:country":"FR",
    "sg:address":"B.P. 418, 06515 Carros C\u00e9dex 1^^1 \u00e8re Avenue, 509 M\u00e8tres, 06510 Carros",
    "sg:orig_category":"Non-Classified Establishments",
    "sg:phone":"+33 4 92 08 40 00",
    "sg:province":"Corse",
    "wof:name":"Biotherm Distribution S.a.",
    "wof:placetype":"venue"
},
  "geometry": {"coordinates":[7.17573,43.785782],"type":"Point"}
}