{
  "type": "Feature",
  "properties": {
    "iso:country":"FR",
    "sg:address":"Lac au Duc",
    "sg:city":"Plo\u00ebrmel",
    "sg:orig_category":"Non-Classified Establishments",
    "sg:phone":"+33 2 97 73 64 64",
    "sg:postcode":"56800",
    "sg:province":"Bretagne",
    "wof:name":"Le Domaine Du Lac Au Duc Le Roi Arthur - Golf H\u00f4tel Club Et Lancelot",
    "wof:placetype":"venue"
},
  "geometry": {"coordinates":[-2.357955,47.879848],"type":"Point"}
}