{
  "type": "Feature",
  "properties": {
    "iso:country":"FR",
    "sg:address":"B.P. 56, 13751 Les Pennes Mirabeau C\u00e9dex^^RN 113 - Quartier le Repos, 13170 Les Pennes Mirabeau",
    "sg:orig_category":"Non-Classified Establishments",
    "sg:phone":"+33 4 42 46 69 69",
    "sg:province":"Midi Pyr\u00e9n\u00e9es",
    "wof:name":"L'auxiliaire M\u00e9ridionale De D\u00e9chets S.a.",
    "wof:placetype":"venue"
},
  "geometry": {"coordinates":[5.316214,43.410835],"type":"Point"}
}