{
  "type": "Feature",
  "properties": {
    "iso:country":"FR",
    "sg:address":"Observatoire de Nice",
    "sg:city":"Nice",
    "sg:orig_category":"Unclassifiable Establishments",
    "sg:phone":"+33 4 92 00 30 11",
    "sg:postcode":"06300",
    "sg:province":"Provence-Alpes-C\u00f4te d'Azur",
    "wof:name":"O.c.a. - Observatoire De La C\u00f4te D'azur",
    "wof:placetype":"venue"
},
  "geometry": {"coordinates":[7.300287,43.723518],"type":"Point"}
}