{
  "type": "Feature",
  "properties": {
    "iso:country":"FR",
    "sg:address":"85, Av. de la Paix - Village d'Entreprise, 41700 Contres",
    "sg:city":"Contres",
    "sg:orig_category":"Unclassifiable Establishments",
    "sg:phone":"+33 2 54 79 09 01",
    "sg:postcode":"41700",
    "sg:province":"Centre",
    "wof:name":"Mat-fonte S.a.r.l.",
    "wof:placetype":"venue"
},
  "geometry": {"coordinates":[1.447484,47.427135],"type":"Point"}
}