{
  "type": "Feature",
  "properties": {
    "iso:country":"FR",
    "sg:address":"34 ZAC Haute B\u00e9doule",
    "sg:city":"Sept\u00e8mes les Vallons",
    "sg:orig_category":"Non-Classified Establishments",
    "sg:phone":"+33 4 91 96 28 78",
    "sg:postcode":"13240",
    "sg:province":"Provence-Alpes-C\u00f4te d'Azur",
    "wof:name":"Locapharm S.a.",
    "wof:placetype":"venue"
},
  "geometry": {"coordinates":[5.351914,43.402073],"type":"Point"}
}