{
  "type": "Feature",
  "properties": {
    "addr:full":"16, Chemin Vert, 78240 Chambourcy Ile de France 78240",
    "addr:housenumber":"16",
    "addr:postcode":"78240;ile;78240",
    "addr:street":"Chemin Vert;France",
    "iso:country":"FR",
    "sg:address":"16, Chemin Vert, 78240 Chambourcy",
    "sg:orig_category":"Non-Classified Establishments",
    "sg:phone":"+33 1 30 74 14 24",
    "sg:postcode":"78240",
    "sg:province":"Ile de France",
    "wof:name":"Del Pozo S.a.",
    "wof:placetype":"venue"
},
  "geometry": {"coordinates":[2.049775,48.905163],"type":"Point"}
}