{
  "type": "Feature",
  "properties": {
    "addr:full":"B.P. 186, 13466 Marseille C\u00e9dex 16^^Rue Anne Gacon - Village d'Entreprise de Saint Henri, 13000 Mars Haute Normandie",
    "addr:housenumber":"b.p. 186",
    "addr:postcode":"13466;13000",
    "addr:street":"Gacon Village D'Entreprise De Saint Henri;Haute Normandie",
    "iso:country":"FR",
    "sg:address":"B.P. 186, 13466 Marseille C\u00e9dex 16^^Rue Anne Gacon - Village d'Entreprise de Saint Henri, 13000 Mars",
    "sg:orig_category":"Non-Classified Establishments",
    "sg:phone":"+33 4 91 46 61 00",
    "sg:province":"Haute Normandie",
    "wof:name":"A.c.t. S.a.r.l. - Accessoires De Tuyauterie",
    "wof:placetype":"venue"
},
  "geometry": {"coordinates":[5.332172,43.364864],"type":"Point"}
}