{
  "type": "Feature",
  "properties": {
    "addr:full":"March\u00e9 Saint Charles Perpignan Languedoc-Roussillon 66000",
    "addr:postcode":"66000",
    "addr:street":"Charles",
    "iso:country":"FR",
    "sg:address":"March\u00e9 Saint Charles",
    "sg:city":"Perpignan",
    "sg:orig_category":"Unclassifiable Establishments",
    "sg:phone":"+33 4 68 55 32 33",
    "sg:postcode":"66000",
    "sg:province":"Languedoc-Roussillon",
    "wof:name":"Etablissement Buonanno S.a.",
    "wof:placetype":"venue"
},
  "geometry": {"coordinates":[2.851745,42.691494],"type":"Point"}
}