{
  "type": "Feature",
  "properties": {
    "iso:country":"FR",
    "sg:address":"350 Bd Pierre Et Marie Curie 44152 Ancenis Cedex",
    "sg:classifiers":[
        {
            "category":"Wholesale",
            "subcategory":"Farm Supplies",
            "type":"Manufacturing & Wholesale Goods"
        }
    ],
    "sg:phone":"+33 2 40 83 05 60",
    "sg:province":"Aquitaine",
    "sg:tags":[
        "-",
        "machine",
        "equipment",
        "engineering",
        "machinery",
        "mechanical",
        "agriculture"
    ],
    "wof:name":"Renault Agriculture Sa",
    "wof:placetype":"venue"
},
  "geometry": {"coordinates":[-1.179869,47.377296],"type":"Point"}
}