{
  "type": "Feature",
  "properties": {
    "iso:country":"FR",
    "sg:address":"B.P. 40149",
    "sg:city":"Kingersheim C\u00e9dex",
    "sg:orig_category":"Non-Classified Establishments",
    "sg:phone":"+33 3 89 53 28 00",
    "sg:postcode":"68264",
    "sg:province":"Basse Normandie",
    "wof:name":"Eurovia Alsace Franche Comt\u00e9 S.n.c.",
    "wof:placetype":"venue"
},
  "geometry": {"coordinates":[7.335795,47.790257],"type":"Point"}
}