{
  "type": "Feature",
  "properties": {
    "addr:full":"17 Rue Amiral Troude BP 324 29274 Brest Bretagne",
    "addr:housenumber":"17;324",
    "addr:postcode":"29274",
    "addr:street":"Rue Amiral Troude Bp",
    "iso:country":"FR",
    "sg:address":"17 Rue Amiral Troude BP 324 29274 Brest",
    "sg:classifiers":[
        {
            "category":"Manufacturing",
            "subcategory":"Printing",
            "type":"Manufacturing & Wholesale Goods"
        }
    ],
    "sg:phone":"+33 2 98 46 17 71",
    "sg:province":"Bretagne",
    "sg:tags":[
        "publishing"
    ],
    "wof:name":"Publitex",
    "wof:placetype":"venue"
},
  "geometry": {"coordinates":[-4.478403,48.386543],"type":"Point"}
}