{
  "type": "Feature",
  "properties": {
    "iso:country":"FR",
    "sg:address":"79, Av. Estienne d'Orves, 92100 Antony",
    "sg:orig_category":"Non-Classified Establishments",
    "sg:phone":"+33 1 46 60 55 20",
    "sg:province":"Ile de France",
    "wof:name":"Standard M\u00e9dical Sud S.a.r.l.",
    "wof:placetype":"venue"
},
  "geometry": {"coordinates":[-103.218224,39.741161],"type":"Point"}
}