{
  "type": "Feature",
  "properties": {
    "addr:full":"18 Avenue Notre Dame Nice Provence-Alpes-C\u00f4te d'Azur 06000",
    "addr:housenumber":"18",
    "addr:postcode":"06000",
    "addr:street":"Avenue Notre Dame Nice",
    "iso:country":"FR",
    "sg:address":"18 Avenue Notre Dame",
    "sg:city":"Nice",
    "sg:classifiers":[
        {
            "category":"Banks & Credit Unions",
            "subcategory":"Financial Services",
            "type":"Services"
        }
    ],
    "sg:phone":"+33 4 92 17 56 60",
    "sg:postcode":"06000",
    "sg:province":"Provence-Alpes-C\u00f4te d'Azur",
    "sg:tags":[
        "banking",
        "finance",
        "insurance"
    ],
    "wof:name":"Banque Francaise Du Credit Cooperatif (credit Cooperatif Ou Bfcc) Bfcc",
    "wof:placetype":"venue"
},
  "geometry": {"coordinates":[7.268228,43.704205],"type":"Point"}
}