{
  "type": "Feature",
  "properties": {
    "iso:country":"FR",
    "sg:address":"22, Rue Prosper Gresy, 13006 Marseille",
    "sg:orig_category":"Unclassifiable Establishments",
    "sg:phone":"+33 4 96 10 21 89",
    "sg:province":"Poitou-Charentes",
    "wof:name":"Cent Pour Cent Origine S.a.r.l.",
    "wof:placetype":"venue"
},
  "geometry": {"coordinates":[5.37536,43.2864],"type":"Point"}
}