{
  "type": "Feature",
  "properties": {
    "addr:full":"26 Bd Robert Schumann 93190 Livry Gargan Ile de France 93190",
    "addr:housenumber":"26",
    "addr:postcode":"93190;93190",
    "addr:street":"Bd Robert Schumann",
    "iso:country":"FR",
    "sg:address":"26 Bd Robert Schumann 93190 Livry Gargan",
    "sg:classifiers":[
        {
            "category":"Wholesale",
            "subcategory":"Meat",
            "type":"Manufacturing & Wholesale Goods"
        }
    ],
    "sg:phone":"+33 1 41 52 52 00",
    "sg:postcode":"93190",
    "sg:province":"Ile de France",
    "sg:tags":[
        "food",
        "cooked",
        "product",
        "related"
    ],
    "wof:name":"Societe Yvas",
    "wof:placetype":"venue"
},
  "geometry": {"coordinates":[2.547725,48.927273],"type":"Point"}
}