{
  "type": "Feature",
  "properties": {
    "iso:country":"FR",
    "sg:address":"69, Rue Pautrier, 13004 Marseille",
    "sg:orig_category":"Unclassifiable Establishments",
    "sg:phone":"+33 4 91 62 60 25",
    "sg:province":"Poitou-Charentes",
    "wof:name":"S.v.p. S.a.r.l. - Soufflage De Verre Phoc\u00e9en",
    "wof:placetype":"venue"
},
  "geometry": {"coordinates":[5.39336,43.311642],"type":"Point"}
}