{
  "type": "Feature",
  "properties": {
    "addr:full":"551, Rte de la Reine Blanche, 78955 Carri\u00e8res sous Poissy Ile de France",
    "addr:housenumber":"551",
    "addr:postcode":"78955",
    "addr:street":"Rte De La Reine Blanche",
    "iso:country":"FR",
    "sg:address":"551, Rte de la Reine Blanche, 78955 Carri\u00e8res sous Poissy",
    "sg:orig_category":"Non-Classified Establishments",
    "sg:phone":"+33 1 39 70 26 66",
    "sg:province":"Ile de France",
    "wof:name":"Tecm\u00e9tal S.a.",
    "wof:placetype":"venue"
},
  "geometry": {"coordinates":[2.031101,48.939915],"type":"Point"}
}