{
  "type": "Feature",
  "properties": {
    "iso:country":"FR",
    "sg:address":"Plantes 21700 Premeaux Prissey",
    "sg:city":"Agencourt",
    "sg:classifiers":[
        {
            "category":"Food Court",
            "type":"Food & Drink"
        }
    ],
    "sg:phone":"+33 3 80 62 30 61",
    "sg:postcode":"21700",
    "sg:province":"Bourgogne",
    "sg:tags":[
        "product",
        "related"
    ],
    "wof:name":"R Dubois Et Fils",
    "wof:placetype":"venue"
},
  "geometry": {"coordinates":[4.932477,47.111015],"type":"Point"}
}