{
  "type": "Feature",
  "properties": {
    "addr:full":"8, Rue du Commerce, 67118 Geispolsheim Alsace",
    "addr:housenumber":"8",
    "addr:postcode":"67118",
    "addr:street":"Rue Du Commerce",
    "iso:country":"FR",
    "sg:address":"8, Rue du Commerce, 67118 Geispolsheim",
    "sg:orig_category":"Unclassifiable Establishments",
    "sg:phone":"+33 3 88 40 67 67",
    "sg:province":"Alsace",
    "wof:name":"Daniel Muller & Compagnie S.a.",
    "wof:placetype":"venue"
},
  "geometry": {"coordinates":[7.682862,48.532345],"type":"Point"}
}