{
  "type": "Feature",
  "properties": {
    "addr:full":"19 chemin des Forges 87200 St Brice sur Vienne Limousin 87200",
    "addr:housenumber":"19",
    "addr:postcode":"87200;87200",
    "addr:street":"Chemin Des Forges",
    "iso:country":"FR",
    "sg:address":"19 chemin des Forges 87200 St Brice sur Vienne",
    "sg:classifiers":[
        {
            "category":"Banks & Credit Unions",
            "subcategory":"Bureau De Change",
            "type":"Services"
        }
    ],
    "sg:phone":"+33 5 55 02 05 34",
    "sg:postcode":"87200",
    "sg:province":"Limousin",
    "sg:tags":[
        "decoration",
        "accessory"
    ],
    "wof:name":"Christian B Cr\u00e9ation Sarl",
    "wof:placetype":"venue"
},
  "geometry": {"coordinates":[0.942679,45.93351],"type":"Point"}
}