{
  "type": "Feature",
  "properties": {
    "iso:country":"FR",
    "sg:address":"Rue Du Val Clair Z I La Pompelle 51100 Reims",
    "sg:classifiers":[
        {
            "category":"Autos & Motor Vehicles",
            "subcategory":"Automobile Sales",
            "type":"Retail Goods"
        }
    ],
    "sg:phone":"+33 3 26 85 49 16",
    "sg:postcode":"51100",
    "sg:province":"Champagne",
    "sg:tags":[
        "equipment",
        "industrial",
        "transport"
    ],
    "wof:name":"Frenalu",
    "wof:placetype":"venue"
},
  "geometry": {"coordinates":[4.028445,49.26284],"type":"Point"}
}