{
  "type": "Feature",
  "properties": {
    "iso:country":"FR",
    "sg:address":"ZA Soumagne",
    "sg:city":"Saint L\u00e9onard de Noblat",
    "sg:orig_category":"Unclassifiable Establishments",
    "sg:phone":"+33 5 55 56 10 47",
    "sg:postcode":"87400",
    "sg:province":"Limousin",
    "wof:name":"Brosserie Val S.a.",
    "wof:placetype":"venue"
},
  "geometry": {"coordinates":[1.49221,45.837944],"type":"Point"}
}