{
  "type": "Feature",
  "properties": {
    "iso:country":"FR",
    "sg:address":"9 B Quai Du Dr H\u00e9berl\u00e9 68570 Soultzmatt",
    "sg:city":"Soultzmatt",
    "sg:classifiers":[
        {
            "category":"Professional",
            "type":"Services"
        }
    ],
    "sg:phone":"+33 3 89 47 00 37",
    "sg:postcode":"68570",
    "sg:province":"Alsace",
    "sg:tags":[
        "transport",
        "road"
    ],
    "wof:name":"Achatz Transports Sa",
    "wof:placetype":"venue"
},
  "geometry": {"coordinates":[7.246903,47.957249],"type":"Point"}
}