{
  "type": "Feature",
  "properties": {
    "addr:full":"63, Av. de Verdun, 84100 Orange Centre",
    "addr:postcode":"84100",
    "addr:street":"63 Av. De Verdun",
    "iso:country":"FR",
    "sg:address":"63, Av. de Verdun, 84100 Orange",
    "sg:orig_category":"Unclassifiable Establishments",
    "sg:phone":"+33 4 90 11 85 85",
    "sg:province":"Centre",
    "wof:name":"Lamanu - S.v.p.f. S.a.",
    "wof:placetype":"venue"
},
  "geometry": {"coordinates":[4.8264,44.124748],"type":"Point"}
}