{
  "type": "Feature",
  "properties": {
    "addr:full":"ZI Puits Barrois Creutzwald Lorraine 57150",
    "addr:postcode":"57150",
    "addr:street":"Zi Puits Barrois",
    "iso:country":"FR",
    "sg:address":"ZI Puits Barrois",
    "sg:city":"Creutzwald",
    "sg:orig_category":"Non-Classified Establishments",
    "sg:phone":"+33 3 87 90 17 76",
    "sg:postcode":"57150",
    "sg:province":"Lorraine",
    "wof:name":"Lorraine Palettes",
    "wof:placetype":"venue"
},
  "geometry": {"coordinates":[6.694479,49.204865],"type":"Point"}
}