{
  "type": "Feature",
  "properties": {
    "iso:country":"FR",
    "sg:address":"6, Rue de la Maison Rouge - ZAC du Parc du Village de Lognes, 77185 Lognes",
    "sg:orig_category":"Unclassifiable Establishments",
    "sg:phone":"+33 1 60 37 47 00",
    "sg:province":"Ile de France",
    "wof:name":"Cerberus S.a.",
    "wof:placetype":"venue"
},
  "geometry": {"coordinates":[2.6324,48.837631],"type":"Point"}
}