{
  "type": "Feature",
  "properties": {
    "iso:country":"FR",
    "sg:address":"1, Rue Ferdinand Lasalle, 31200 Toulouse",
    "sg:orig_category":"Unclassifiable Establishments",
    "sg:phone":"+33 5 61 13 59 13",
    "sg:province":"Midi Pyr\u00e9n\u00e9es",
    "wof:name":"S.a.d.",
    "wof:placetype":"venue"
},
  "geometry": {"coordinates":[1.421251,43.616581],"type":"Point"}
}