{
  "type": "Feature",
  "properties": {
    "addr:full":"1, Rue Ferdinand Lasalle, 31200 Toulouse Midi Pyr\u00e9n\u00e9es",
    "addr:housenumber":"1",
    "addr:postcode":"31200",
    "addr:street":"Rue Ferdinand Lasalle",
    "iso:country":"FR",
    "sg:address":"1, Rue Ferdinand Lasalle, 31200 Toulouse",
    "sg:orig_category":"Unclassifiable Establishments",
    "sg:phone":"+33 5 61 13 59 13",
    "sg:province":"Midi Pyr\u00e9n\u00e9es",
    "wof:name":"S.a.d.",
    "wof:placetype":"venue"
},
  "geometry": {"coordinates":[1.421251,43.616581],"type":"Point"}
}