{
  "type": "Feature",
  "properties": {
    "addr:full":"Rte N\u00eemes Arles Km 4 30230 Bouillargues Languedoc-Roussillon 30230",
    "addr:housenumber":"4",
    "addr:postcode":"30230;30230",
    "addr:street":"Rte",
    "iso:country":"FR",
    "sg:address":"Rte N\u00eemes Arles Km 4",
    "sg:city":"30230 Bouillargues",
    "sg:classifiers":[
        {
            "category":"Banks & Credit Unions",
            "subcategory":"Financial Services",
            "type":"Services"
        }
    ],
    "sg:phone":"+33 4 66 04 97 01",
    "sg:postcode":"30230",
    "sg:province":"Languedoc-Roussillon",
    "sg:tags":[
        "banking",
        "finance",
        "insurance"
    ],
    "wof:name":"Centre De Gestion Agree Economie Rurale Du Gard Ass",
    "wof:placetype":"venue"
},
  "geometry": {"coordinates":[4.42806,43.798744],"type":"Point"}
}