{
  "type": "Feature",
  "properties": {
    "addr:full":"540, All\u00e9e des H\u00eatres - Parc d'Activit\u00e9 - Hall 4, 69760 Limonest Rhone-Alpes 69760",
    "addr:housenumber":"540;4",
    "addr:postcode":"69760;69760",
    "addr:street":"Alle\u0301E Des He\u0302Tres Parc D'Activite",
    "iso:country":"FR",
    "sg:address":"540, All\u00e9e des H\u00eatres - Parc d'Activit\u00e9 - Hall 4, 69760 Limonest",
    "sg:orig_category":"Unclassifiable Establishments",
    "sg:phone":"+33 4 78 43 24 95",
    "sg:postcode":"69760",
    "sg:province":"Rhone-Alpes",
    "wof:name":"Asp Engineering S.a.",
    "wof:placetype":"venue"
},
  "geometry": {"coordinates":[4.775331,45.809032],"type":"Point"}
}