{
  "type": "Feature",
  "properties": {
    "addr:full":"4, Rue du Docteur Job, 57185 Clouange Lorraine",
    "addr:housenumber":"4",
    "addr:postcode":"57185",
    "addr:street":"Rue Du Docteur Job",
    "iso:country":"FR",
    "sg:address":"4, Rue du Docteur Job, 57185 Clouange",
    "sg:orig_category":"Unclassifiable Establishments",
    "sg:phone":"+33 3 87 58 20 63",
    "sg:province":"Lorraine",
    "wof:name":"E.b.i. S.a.r.l. - Electricit\u00e9 B\u00e2timent Industrie",
    "wof:placetype":"venue"
},
  "geometry": {"coordinates":[6.100298,49.261517],"type":"Point"}
}