{
  "type": "Feature",
  "properties": {
    "addr:full":"3 R Vignes 68320 Holtzwihr Holtzwihr Alsace 68320",
    "addr:housenumber":"3",
    "addr:postcode":"68320;68320",
    "addr:street":"R Vignes",
    "iso:country":"FR",
    "sg:address":"3 R Vignes 68320 Holtzwihr",
    "sg:city":"Holtzwihr",
    "sg:classifiers":[
        {
            "category":"Shopping",
            "type":"Retail Goods"
        }
    ],
    "sg:phone":"+33 3 89 47 74 98",
    "sg:postcode":"68320",
    "sg:province":"Alsace",
    "sg:tags":[
        "metallurgy",
        "finished",
        "-",
        "metalworking",
        "metallic"
    ],
    "wof:name":"Est Signalisation (sarl)",
    "wof:placetype":"venue"
},
  "geometry": {"coordinates":[7.426801,48.10968],"type":"Point"}
}