{
  "type": "Feature",
  "properties": {
    "addr:full":"100, Av. du G\u00e9n\u00e9ral Leclerc, 78220 Viroflay Ile de France",
    "addr:postcode":"78220;ile",
    "addr:street":"100 Av. Du Ge\u0301Ne\u0301Ral Leclerc",
    "iso:country":"FR",
    "sg:address":"100, Av. du G\u00e9n\u00e9ral Leclerc, 78220 Viroflay",
    "sg:orig_category":"Unclassifiable Establishments",
    "sg:phone":"+33 1 30 24 75 72",
    "sg:province":"Ile de France",
    "wof:name":"Xuan S.a.r.l.",
    "wof:placetype":"venue"
},
  "geometry": {"coordinates":[2.17231,48.80423],"type":"Point"}
}