{
  "type": "Feature",
  "properties": {
    "addr:full":"Beaumont 44520 Iss\u00e9 Pays de Loire",
    "addr:postcode":"44520",
    "iso:country":"FR",
    "sg:address":"Beaumont 44520 Iss\u00e9",
    "sg:orig_category":"Non-Classified Establishments",
    "sg:phone":"+33 2 40 55 16 34",
    "sg:province":"Pays de Loire",
    "wof:name":"Porman S.a.",
    "wof:placetype":"venue"
},
  "geometry": {"coordinates":[-1.441839,47.601437],"type":"Point"}
}