{
  "type": "Feature",
  "properties": {
    "iso:country":"FR",
    "sg:address":"23 Avenue Georges Haupinot 24570 Le Lardin St Lazare",
    "sg:city":"Condat-sur-V\u00e9z\u00e8re",
    "sg:classifiers":[
        {
            "category":"Utilities",
            "subcategory":"Electric",
            "type":"Services"
        }
    ],
    "sg:phone":"+33 5 53 51 73 73",
    "sg:postcode":"24570",
    "sg:province":"Aquitaine",
    "sg:tags":[
        "electricity",
        "raw",
        "energy",
        "material"
    ],
    "wof:name":"Perigord Energie",
    "wof:placetype":"venue"
},
  "geometry": {"coordinates":[1.225484,45.126678],"type":"Point"}
}