{
  "type": "Feature",
  "properties": {
    "addr:full":"Elbes 12200 Martiel Midi Pyr\u00e9n\u00e9es",
    "addr:postcode":"12200",
    "addr:street":"Elbes",
    "iso:country":"FR",
    "sg:address":"Elbes 12200 Martiel",
    "sg:classifiers":[
        {
            "category":"Professional",
            "type":"Services"
        }
    ],
    "sg:phone":"+33 5 65 29 51 78",
    "sg:province":"Midi Pyr\u00e9n\u00e9es",
    "sg:tags":[
        "transport",
        "road"
    ],
    "wof:name":"Vaissier Pierre",
    "wof:placetype":"venue"
},
  "geometry": {"coordinates":[1.916185,44.343655],"type":"Point"}
}