{
  "type": "Feature",
  "properties": {
    "iso:country":"FR",
    "sg:address":"8 Cours Andre Philip Immeuble L'Arc",
    "sg:city":"Villeurbanne",
    "sg:classifiers":[
        {
            "category":"Banks & Credit Unions",
            "subcategory":"Financial Services",
            "type":"Services"
        }
    ],
    "sg:phone":"+33 4 78 17 66 00",
    "sg:postcode":"69100",
    "sg:province":"Rhone-Alpes",
    "sg:tags":[
        "banking",
        "finance",
        "insurance"
    ],
    "wof:name":"Diac (diac)",
    "wof:placetype":"venue"
},
  "geometry": {"coordinates":[4.863446,45.77248],"type":"Point"}
}