{
  "type": "Feature",
  "properties": {
    "iso:country":"FR",
    "sg:address":"B.P. 57, 62240 Desvres^^Rue de la Gare, 62240 Desvres",
    "sg:orig_category":"Non-Classified Establishments",
    "sg:phone":"+33 3 21 99 98 97",
    "sg:province":"Nord Pas-de-Calais",
    "wof:name":"Rcfc Routes S.n.c.",
    "wof:placetype":"venue"
},
  "geometry": {"coordinates":[1.912178,50.63652],"type":"Point"}
}