{
  "type": "Feature",
  "properties": {
    "iso:country":"FR",
    "sg:address":"10, Chemin Salli\u00e9nard, 59440 Bas-Lieu",
    "sg:orig_category":"Unclassifiable Establishments",
    "sg:phone":"+33 3 27 61 18 81",
    "sg:province":"Nord Pas-de-Calais",
    "wof:name":"Huart Garage Rectification",
    "wof:placetype":"venue"
},
  "geometry": {"coordinates":[3.898459,50.077618],"type":"Point"}
}