{
  "type": "Feature",
  "properties": {
    "addr:full":"24 Rue De L'Etang 62138 Violaines Nord Pas-de-Calais 62138",
    "addr:housenumber":"24",
    "addr:postcode":"62138;62138",
    "addr:street":"Rue De L'Etang",
    "iso:country":"FR",
    "sg:address":"24 Rue De L'Etang 62138 Violaines",
    "sg:classifiers":[
        {
            "category":"Wholesale",
            "subcategory":"Machinery & Supplies",
            "type":"Manufacturing & Wholesale Goods"
        }
    ],
    "sg:phone":"+33 3 20 29 23 67",
    "sg:postcode":"62138",
    "sg:province":"Nord Pas-de-Calais",
    "sg:tags":[
        "handling",
        "material",
        "-",
        "machine",
        "equipment",
        "engineering",
        "mechanical"
    ],
    "wof:name":"Guffroy Freres Sa",
    "wof:placetype":"venue"
},
  "geometry": {"coordinates":[2.78001,50.532585],"type":"Point"}
}