{
  "type": "Feature",
  "properties": {
    "addr:full":"Zi Bordeneuve Du Rooy 47302 Villeneuve Sur Lot Vill\u00e9 Alsace 67220",
    "addr:postcode":"47302;67220",
    "addr:street":"Ville\u0301",
    "iso:country":"FR",
    "sg:address":"Zi Bordeneuve Du Rooy 47302 Villeneuve Sur Lot",
    "sg:city":"Vill\u00e9",
    "sg:classifiers":[
        {
            "category":"Home & Garden",
            "subcategory":"Furniture",
            "type":"Retail Goods"
        }
    ],
    "sg:phone":"+33 5 53 36 24 10",
    "sg:postcode":"67220",
    "sg:province":"Alsace",
    "sg:tags":[
        "wood"
    ],
    "wof:name":"Siga Sa",
    "wof:placetype":"venue"
},
  "geometry": {"coordinates":[0.712917,44.395134],"type":"Point"}
}