{
  "type": "Feature",
  "properties": {
    "iso:country":"FR",
    "sg:address":"Le Mollard 01340 Foissiat",
    "sg:orig_category":"Non-Classified Establishments",
    "sg:phone":"+33 4 74 52 39 23",
    "sg:province":"Rhone-Alpes",
    "wof:name":"Poncin S.a.r.l.",
    "wof:placetype":"venue"
},
  "geometry": {"coordinates":[5.179121,46.377167],"type":"Point"}
}