{
  "type": "Feature",
  "properties": {
    "addr:full":"Av. des Cures Andilly Ile de France 95580",
    "addr:postcode":"95580",
    "addr:street":"Av. Des Cures",
    "iso:country":"FR",
    "sg:address":"Av. des Cures",
    "sg:city":"Andilly",
    "sg:orig_category":"Unclassifiable Establishments",
    "sg:phone":"+33 1 34 27 96 05",
    "sg:postcode":"95580",
    "sg:province":"Ile de France",
    "wof:name":"Trilogiq S.a.",
    "wof:placetype":"venue"
},
  "geometry": {"coordinates":[2.298055,48.996529],"type":"Point"}
}