{
  "type": "Feature",
  "properties": {
    "addr:full":"99 Avenue De La Pyramide Zac Paris Nord Ii 95911 Roissy Ch De Gaulle Cedex Picardie",
    "addr:housenumber":"99",
    "addr:postcode":"95911",
    "addr:street":"Avenue De La;Zac Paris;Ch De Gaulle",
    "iso:country":"FR",
    "sg:address":"99 Avenue De La Pyramide Zac Paris Nord Ii 95911 Roissy Ch De Gaulle Cedex",
    "sg:classifiers":[
        {
            "category":"Professional",
            "type":"Services"
        }
    ],
    "sg:phone":"+33 1 49 38 24 00",
    "sg:province":"Picardie",
    "sg:tags":[
        "transport",
        "road"
    ],
    "wof:name":"L'oreal",
    "wof:placetype":"venue"
},
  "geometry": {"coordinates":[2.51524,49.004028],"type":"Point"}
}