{
  "type": "Feature",
  "properties": {
    "iso:country":"FR",
    "sg:address":"Rue Delbecque 62660 BEUVRY",
    "sg:classifiers":[
        {
            "category":"Manufacturing",
            "subcategory":"Food",
            "type":"Manufacturing & Wholesale Goods"
        }
    ],
    "sg:phone":"+33 3 21 61 39 00",
    "sg:postcode":"62660",
    "sg:province":"Nord Pas-de-Calais",
    "sg:tags":[
        "frozen"
    ],
    "wof:name":"Les Moulins De St Aubert Snc",
    "wof:placetype":"venue"
},
  "geometry": {"coordinates":[2.677643,50.518867],"type":"Point"}
}