{
  "type": "Feature",
  "properties": {
    "iso:country":"FR",
    "sg:address":"74140 Ballaison",
    "sg:classifiers":[
        {
            "category":"Food & Beverages",
            "subcategory":"Meat & Fish",
            "type":"Retail Goods"
        }
    ],
    "sg:phone":"+33 4 50 94 01 18",
    "sg:postcode":"74140",
    "sg:province":"Rhone-Alpes",
    "sg:tags":[
        "preserve",
        "cooked",
        "product",
        "related"
    ],
    "wof:name":"Sarl La Mere Gaud",
    "wof:placetype":"venue"
},
  "geometry": {"coordinates":[6.328814,46.298435],"type":"Point"}
}