{
  "type": "Feature",
  "properties": {
    "iso:country":"FR",
    "sg:address":"18 Route Villegenon 18260 Vailly Sur Sauldre",
    "sg:city":"Villegenon",
    "sg:classifiers":[
        {
            "category":"Farming",
            "subcategory":"Livestock Farm",
            "type":"Manufacturing & Wholesale Goods"
        }
    ],
    "sg:phone":"+33 2 48 73 73 19",
    "sg:postcode":"18260",
    "sg:province":"Centre",
    "sg:tags":[
        "grain",
        "agriculture",
        "cereal"
    ],
    "wof:name":"Etablissement Martignon Sas",
    "wof:placetype":"venue"
},
  "geometry": {"coordinates":[2.643938,47.456387],"type":"Point"}
}