{
  "type": "Feature",
  "properties": {
    "addr:full":"9 Rue Gustave Eiffel 31140 Aucamville Midi Pyr\u00e9n\u00e9es 31140",
    "addr:housenumber":"9",
    "addr:postcode":"31140;31140",
    "addr:street":"Rue Gustave Eiffel",
    "iso:country":"FR",
    "sg:address":"9 Rue Gustave Eiffel 31140 Aucamville",
    "sg:classifiers":[
        {
            "category":"Manufacturing",
            "subcategory":"Tools & Machinery",
            "type":"Manufacturing & Wholesale Goods"
        }
    ],
    "sg:phone":"+33 5 61 37 51 37",
    "sg:postcode":"31140",
    "sg:province":"Midi Pyr\u00e9n\u00e9es",
    "sg:tags":[
        "equipment",
        "measurement",
        "-",
        "precision",
        "instrument"
    ],
    "wof:name":"Vdo France",
    "wof:placetype":"venue"
},
  "geometry": {"coordinates":[1.418445,43.664474],"type":"Point"}
}