{
  "type": "Feature",
  "properties": {
    "iso:country":"FR",
    "sg:address":"61, Rue Robespierre, 42100 Saint Etienne",
    "sg:orig_category":"Unclassifiable Establishments",
    "sg:phone":"+33 4 77 57 14 96",
    "sg:province":"Rhone-Alpes",
    "wof:name":"Stefanox S.a.r.l.",
    "wof:placetype":"venue"
},
  "geometry": {"coordinates":[4.397902,45.411667],"type":"Point"}
}