{
  "type": "Feature",
  "properties": {
    "iso:country":"FR",
    "sg:address":"3, Rue Nicolas Copernic - ZAC du Moulin \u00e0 Vent, 78280 Guyancourt",
    "sg:orig_category":"Unclassifiable Establishments",
    "sg:phone":"+33 1 30 44 07 65",
    "sg:province":"Ile de France",
    "wof:name":"Voisin Maintenance S.a.",
    "wof:placetype":"venue"
},
  "geometry": {"coordinates":[2.06956,48.771046],"type":"Point"}
}