{
  "type": "Feature",
  "properties": {
    "addr:full":"9, Impasse Pistou, 13009 Marseille Poitou-Charentes",
    "addr:housenumber":"9",
    "addr:postcode":"13009",
    "addr:street":"Impasse Pistou",
    "iso:country":"FR",
    "sg:address":"9, Impasse Pistou, 13009 Marseille",
    "sg:orig_category":"Non-Classified Establishments",
    "sg:phone":"+33 4 91 72 05 06",
    "sg:province":"Poitou-Charentes",
    "wof:name":"V.m.p. Communication S.a.r.l.",
    "wof:placetype":"venue"
},
  "geometry": {"coordinates":[5.400836,43.24107],"type":"Point"}
}