{
  "type": "Feature",
  "properties": {
    "addr:full":"B.P. 19, 49630 Corn\u00e9^^Rue Raymond Meignan, 49630 Corn\u00e9 Champagne",
    "addr:postcode":"49630;49630",
    "addr:street":"B.P. 19;Raymond Meignan",
    "iso:country":"FR",
    "sg:address":"B.P. 19, 49630 Corn\u00e9^^Rue Raymond Meignan, 49630 Corn\u00e9",
    "sg:orig_category":"Non-Classified Establishments",
    "sg:phone":"+33 2 41 66 12 12",
    "sg:province":"Champagne",
    "wof:name":"Atm S.a.",
    "wof:placetype":"venue"
},
  "geometry": {"coordinates":[-0.272204,47.456097],"type":"Point"}
}