{
  "type": "Feature",
  "properties": {
    "addr:full":"Rue Nicolas Appert 87280 Limoges Limousin",
    "addr:postcode":"87280",
    "addr:street":"Rue Nicolas Appert",
    "iso:country":"FR",
    "sg:address":"Rue Nicolas Appert 87280 Limoges",
    "sg:classifiers":[
        {
            "category":"Manufacturing",
            "subcategory":"Printing",
            "type":"Manufacturing & Wholesale Goods"
        }
    ],
    "sg:phone":"+33 5 55 37 03 07",
    "sg:province":"Limousin",
    "sg:tags":[
        "publishing"
    ],
    "wof:name":"Gds Imprimeurs Sa",
    "wof:placetype":"venue"
},
  "geometry": {"coordinates":[1.282554,45.881241],"type":"Point"}
}