{
  "type": "Feature",
  "properties": {
    "iso:country":"FR",
    "sg:address":"Chemin Lats",
    "sg:city":"Messimy",
    "sg:orig_category":"Unclassifiable Establishments",
    "sg:phone":"+33 4 78 16 05 18",
    "sg:postcode":"69510",
    "sg:province":"Rhone-Alpes",
    "wof:name":"Soci\u00e9t\u00e9 Civile Bastide Et Bondoux S.a.r.l.",
    "wof:placetype":"venue"
},
  "geometry": {"coordinates":[4.689747,45.701359],"type":"Point"}
}