{
  "type": "Feature",
  "properties": {
    "addr:full":"3 R Augustin Ramon 62580 Oppy Nord Pas-de-Calais 62580",
    "addr:housenumber":"3",
    "addr:postcode":"62580;62580",
    "addr:street":"R Augustin Ramon",
    "iso:country":"FR",
    "sg:address":"3 R Augustin Ramon 62580 Oppy",
    "sg:classifiers":[
        {
            "category":"Professional",
            "subcategory":"Printing & Photocopies",
            "type":"Services"
        }
    ],
    "sg:phone":"+33 3 21 16 16 32",
    "sg:postcode":"62580",
    "sg:province":"Nord Pas-de-Calais",
    "sg:tags":[
        "machine",
        "engineering",
        "-",
        "mechanical"
    ],
    "wof:name":"M. Duponchel Patrice",
    "wof:placetype":"venue"
},
  "geometry": {"coordinates":[2.888447,50.349384],"type":"Point"}
}