{
  "type": "Feature",
  "properties": {
    "iso:country":"FR",
    "sg:address":"bd Sadi Carnot; Le Cannet",
    "sg:classifiers":[
        {
            "category":"Banks & Credit Unions",
            "subcategory":"Bank",
            "type":"Services"
        }
    ],
    "sg:phone":"+33 3393454000",
    "sg:province":"Midi Pyr\u00e9n\u00e9es",
    "wof:name":"Cr\u00e9dit Lyonnais",
    "wof:placetype":"venue"
},
  "geometry": {"coordinates":[7.019475,43.576237],"type":"Point"}
}