{
  "type": "Feature",
  "properties": {
    "addr:full":"242, Rue Rivoli, 75001 Paris Ile de France",
    "addr:housenumber":"242",
    "addr:postcode":"75001",
    "addr:street":"Rue Rivoli",
    "iso:country":"FR",
    "sg:address":"242, Rue Rivoli, 75001 Paris",
    "sg:orig_category":"Unclassifiable Establishments",
    "sg:phone":"+33 1 40 15 01 22",
    "sg:province":"Ile de France",
    "wof:name":"Cogitique Syst\u00e8mes S.a.",
    "wof:placetype":"venue"
},
  "geometry": {"coordinates":[2.325611,48.865971],"type":"Point"}
}