{
  "type": "Feature",
  "properties": {
    "addr:full":"B.P. 24, 84301 Cavaillon C\u00e9dex^^Rte de l'Isle sur Sorgue, 84300 Cavaillon Limousin",
    "addr:postcode":"84301;84300",
    "addr:street":"B.P. 24",
    "iso:country":"FR",
    "sg:address":"B.P. 24, 84301 Cavaillon C\u00e9dex^^Rte de l'Isle sur Sorgue, 84300 Cavaillon",
    "sg:orig_category":"Non-Classified Establishments",
    "sg:phone":"+33 4 90 06 46 46",
    "sg:province":"Limousin",
    "wof:name":"Gerland Provence S.n.c.",
    "wof:placetype":"venue"
},
  "geometry": {"coordinates":[5.04855,43.84869],"type":"Point"}
}