{
  "type": "Feature",
  "properties": {
    "addr:full":"5, Rue Vivaldi, 25200 Montb\u00e9liard Franche Comt\u00e9 25200",
    "addr:housenumber":"5",
    "addr:postcode":"25200;25200",
    "addr:street":"Rue Vivaldi;Franche Comte\u0301",
    "iso:country":"FR",
    "sg:address":"5, Rue Vivaldi, 25200 Montb\u00e9liard",
    "sg:orig_category":"Non-Classified Establishments",
    "sg:phone":"+33 3 81 98 31 83",
    "sg:postcode":"25200",
    "sg:province":"Franche Comt\u00e9",
    "wof:name":"Cetec S.a.",
    "wof:placetype":"venue"
},
  "geometry": {"coordinates":[6.800102,47.501102],"type":"Point"}
}