{
  "type": "Feature",
  "properties": {
    "addr:full":"9, Rue des Artisans - ZA de Cormontaigne, 57100 Thionville Lorraine",
    "addr:housenumber":"9",
    "addr:postcode":"57100",
    "addr:street":"Rue Des Artisans Za De Cormontaigne",
    "iso:country":"FR",
    "sg:address":"9, Rue des Artisans - ZA de Cormontaigne, 57100 Thionville",
    "sg:orig_category":"Non-Classified Establishments",
    "sg:phone":"+33 3 82 51 13 30",
    "sg:province":"Lorraine",
    "wof:name":"Prim' 1 S.a.r.l.",
    "wof:placetype":"venue"
},
  "geometry": {"coordinates":[6.16909,49.357601],"type":"Point"}
}