{
  "type": "Feature",
  "properties": {
    "addr:full":"28, Rue du Grenier Saint Lazare, 75003 Paris Ile de France",
    "addr:housenumber":"28",
    "addr:postcode":"75003",
    "addr:street":"Rue Du Grenier Saint Lazare",
    "iso:country":"FR",
    "sg:address":"28, Rue du Grenier Saint Lazare, 75003 Paris",
    "sg:orig_category":"Non-Classified Establishments",
    "sg:phone":"+33 1 48 87 70 00",
    "sg:province":"Ile de France",
    "wof:name":"F.s.k. S.a. - France Sales Knitwear",
    "wof:placetype":"venue"
},
  "geometry": {"coordinates":[2.353096,48.863186],"type":"Point"}
}