{
  "type": "Feature",
  "properties": {
    "addr:full":"B.P. 42, 84231 Ch\u00e2teauneuf du Pape C\u00e9dex^^Av. Saint Joseph, 84230 Ch\u00e2teauneuf du Pape Provence-Alpes-C\u00f4te d'Azur",
    "addr:postcode":"84231;84230",
    "addr:street":"B.P. 42;Saint;Pape",
    "iso:country":"FR",
    "sg:address":"B.P. 42, 84231 Ch\u00e2teauneuf du Pape C\u00e9dex^^Av. Saint Joseph, 84230 Ch\u00e2teauneuf du Pape",
    "sg:orig_category":"Non-Classified Establishments",
    "sg:phone":"+33 4 90 83 71 74",
    "sg:province":"Provence-Alpes-C\u00f4te d'Azur",
    "wof:name":"Les Clefs D'or Deydier S.c.e.a.",
    "wof:placetype":"venue"
},
  "geometry": {"coordinates":[4.835999,44.049744],"type":"Point"}
}