{
  "type": "Feature",
  "properties": {
    "iso:country":"FR",
    "sg:address":"3 Rue Du Pr\u00e9 Brenot Za De Valentin 25046 Besan\u00e7on",
    "sg:city":"Besan\u00e7on",
    "sg:classifiers":[
        {
            "category":"Shopping",
            "subcategory":"Stationery & Office Supplies",
            "type":"Retail Goods"
        }
    ],
    "sg:phone":"+33 3 81 47 48 30",
    "sg:postcode":"25000",
    "sg:province":"Franche Comt\u00e9",
    "sg:tags":[
        "information",
        "technology",
        "telecommunication",
        "equipment"
    ],
    "wof:name":"Ricoh Besancon",
    "wof:placetype":"venue"
},
  "geometry": {"coordinates":[6.02091,47.239639],"type":"Point"}
}