{
  "type": "Feature",
  "properties": {
    "iso:country":"FR",
    "sg:address":"11, Rue de Provence, 69800 Saint Priest",
    "sg:orig_category":"Non-Classified Establishments",
    "sg:phone":"+33 4 78 20 07 62",
    "sg:province":"Rhone-Alpes",
    "wof:name":"Soci\u00e9t\u00e9 Robert S.a.r.l.",
    "wof:placetype":"venue"
},
  "geometry": {"coordinates":[4.924888,45.694984],"type":"Point"}
}