{
  "type": "Feature",
  "properties": {
    "addr:full":"11, Rue de Provence, 69800 Saint Priest Rhone-Alpes",
    "addr:housenumber":"11",
    "addr:postcode":"69800",
    "addr:street":"Rue De Provence;Priest Rhone-Alpes",
    "iso:country":"FR",
    "sg:address":"11, Rue de Provence, 69800 Saint Priest",
    "sg:orig_category":"Non-Classified Establishments",
    "sg:phone":"+33 4 78 20 07 62",
    "sg:province":"Rhone-Alpes",
    "wof:name":"Soci\u00e9t\u00e9 Robert S.a.r.l.",
    "wof:placetype":"venue"
},
  "geometry": {"coordinates":[4.924888,45.694984],"type":"Point"}
}