{
  "type": "Feature",
  "properties": {
    "iso:country":"FR",
    "sg:address":"Rue Gay Lussac 33700 M\u00e9rignac",
    "sg:city":"M\u00e9rignac",
    "sg:classifiers":[
        {
            "category":"Manufacturing",
            "subcategory":"Glass & Minerals",
            "type":"Manufacturing & Wholesale Goods"
        }
    ],
    "sg:phone":"+33 5 57 92 31 31",
    "sg:postcode":"33700",
    "sg:province":"Aquitaine",
    "sg:tags":[
        "building",
        "material"
    ],
    "wof:name":"Courbu Vitrages Sas",
    "wof:placetype":"venue"
},
  "geometry": {"coordinates":[-0.680159,44.849415],"type":"Point"}
}