{
  "type": "Feature",
  "properties": {
    "addr:full":"7 Rue Louise Michel La Neuvillette 51100 Reims Champagne 51100",
    "addr:housenumber":"7",
    "addr:postcode":"51100;51100",
    "addr:street":"Rue Louise Michel La Neuvillette",
    "iso:country":"FR",
    "sg:address":"7 Rue Louise Michel La Neuvillette 51100 Reims",
    "sg:classifiers":[
        {
            "category":"Building & Trades",
            "subcategory":"Construction",
            "type":"Services"
        }
    ],
    "sg:phone":"+33 3 26 87 31 55",
    "sg:postcode":"51100",
    "sg:province":"Champagne",
    "sg:tags":[
        "work",
        "public"
    ],
    "wof:name":"Spim Off Shore D'exploitation En Commun",
    "wof:placetype":"venue"
},
  "geometry": {"coordinates":[4.018572,49.286247],"type":"Point"}
}