{
  "type": "Feature",
  "properties": {
    "addr:full":"47 rue Maurice Flandin 69003 Lyon Rhone-Alpes 69003",
    "addr:housenumber":"47",
    "addr:postcode":"69003;69003",
    "addr:street":"Rue Maurice Flandin",
    "iso:country":"FR",
    "sg:address":"47 rue Maurice Flandin 69003 Lyon",
    "sg:classifiers":[
        {
            "category":"Government",
            "subcategory":"Court House",
            "type":"Public Place"
        }
    ],
    "sg:phone":"+33 4 72 13 23 23",
    "sg:postcode":"69003",
    "sg:province":"Rhone-Alpes",
    "sg:tags":[
        "administration",
        "central"
    ],
    "wof:name":"Lyon Buro Services Sa",
    "wof:placetype":"venue"
},
  "geometry": {"coordinates":[4.862794,45.757648],"type":"Point"}
}