{
  "type": "Feature",
  "properties": {
    "iso:country":"FR",
    "sg:address":"4 place du G\u00e9n\u00e9ral de Gaulle 59112 Annoeullin",
    "sg:classifiers":[
        {
            "category":"Wholesale",
            "subcategory":"Beer",
            "type":"Manufacturing & Wholesale Goods"
        }
    ],
    "sg:phone":"+33 3 20 86 83 60",
    "sg:postcode":"59112",
    "sg:province":"Nord Pas-de-Calais",
    "wof:name":"Brasserie D'annoeullin S.a.r.l.",
    "wof:placetype":"venue"
},
  "geometry": {"coordinates":[2.931709,50.529278],"type":"Point"}
}