{
  "type": "Feature",
  "properties": {
    "iso:country":"FR",
    "sg:address":"ZA La Charbonni\u00e8re",
    "sg:city":"Cuiseaux",
    "sg:orig_category":"Non-Classified Establishments",
    "sg:phone":"+33 3 85 72 75 51",
    "sg:postcode":"71480",
    "sg:province":"Bourgogne",
    "wof:name":"Caillon Fr\u00e8res S.a.r.l.",
    "wof:placetype":"venue"
},
  "geometry": {"coordinates":[5.38771,46.494301],"type":"Point"}
}