{
  "type": "Feature",
  "properties": {
    "iso:country":"FR",
    "sg:address":"27 Porte de France; Menton",
    "sg:classifiers":[
        {
            "category":"Banks & Credit Unions",
            "subcategory":"Bank",
            "type":"Services"
        }
    ],
    "sg:phone":"+33 3393356739",
    "sg:province":"Aquitaine",
    "wof:name":"Soci\u00e9t\u00e9 G\u00e9n\u00e9rale",
    "wof:placetype":"venue"
},
  "geometry": {"coordinates":[7.511713,43.782593],"type":"Point"}
}