{
  "type": "Feature",
  "properties": {
    "iso:country":"FR",
    "sg:address":"1 rue Parc Autoport du Mt Blanc 74300 Cluses",
    "sg:classifiers":[
        {
            "category":"Professional",
            "type":"Services"
        }
    ],
    "sg:phone":"+33 4 50 98 71 11",
    "sg:postcode":"74300",
    "sg:province":"Rhone-Alpes",
    "sg:tags":[
        "transport"
    ],
    "wof:name":"Sotracom Sarl",
    "wof:placetype":"venue"
},
  "geometry": {"coordinates":[6.591815,46.050533],"type":"Point"}
}