{
  "type": "Feature",
  "properties": {
    "addr:full":"11 Rue Emile Basly 62700 Bruay La Buissiere Nord Pas-de-Calais 62700",
    "addr:housenumber":"11",
    "addr:postcode":"62700;62700",
    "addr:street":"Rue Emile Basly;Buissiere Nord",
    "iso:country":"FR",
    "sg:address":"11 Rue Emile Basly 62700 Bruay La Buissiere",
    "sg:classifiers":[
        {
            "category":"Utilities",
            "subcategory":"Electric",
            "type":"Services"
        }
    ],
    "sg:phone":"+33 3 21 62 59 80",
    "sg:postcode":"62700",
    "sg:province":"Nord Pas-de-Calais",
    "sg:tags":[
        "electricity",
        "raw",
        "energy",
        "material"
    ],
    "wof:name":"Electricite De France (edf)",
    "wof:placetype":"venue"
},
  "geometry": {"coordinates":[2.537242,50.482761],"type":"Point"}
}