{
  "type": "Feature",
  "properties": {
    "iso:country":"FR",
    "sg:address":"Les Cinq Chemins 56580 Credin",
    "sg:city":"Cr\u00e9din",
    "sg:classifiers":[
        {
            "category":"Food & Beverages",
            "subcategory":"Groceries & Convenience Stores",
            "type":"Retail Goods"
        }
    ],
    "sg:phone":"+33 2 97 38 58 58",
    "sg:postcode":"56580",
    "sg:province":"Bretagne",
    "sg:tags":[
        "product",
        "related"
    ],
    "wof:name":"Seltea",
    "wof:placetype":"venue"
},
  "geometry": {"coordinates":[-2.764234,48.057163],"type":"Point"}
}