{
  "type": "Feature",
  "properties": {
    "addr:full":"62, Av. Georges Alquier - Les Salvages , 81100 Castres Midi Pyr\u00e9n\u00e9es",
    "addr:postcode":"81100",
    "addr:street":"62 Av. Georges Alquier Les Salvages",
    "iso:country":"FR",
    "sg:address":"62, Av. Georges Alquier - Les Salvages , 81100 Castres",
    "sg:orig_category":"Non-Classified Establishments",
    "sg:phone":"+33 5 63 35 10 39",
    "sg:province":"Midi Pyr\u00e9n\u00e9es",
    "wof:name":"Filature Assemat S.a.r.l.",
    "wof:placetype":"venue"
},
  "geometry": {"coordinates":[2.257356,43.56094],"type":"Point"}
}