{
  "type": "Feature",
  "properties": {
    "addr:full":"Site Industriel de Saint Pierre de S\u00e9nos Boll\u00e8ne Provence-Alpes-C\u00f4te d'Azur 84500",
    "addr:postcode":"84500",
    "addr:street":"Pierre;Bolle\u0300Ne",
    "iso:country":"FR",
    "sg:address":"Site Industriel de Saint Pierre de S\u00e9nos",
    "sg:city":"Boll\u00e8ne",
    "sg:orig_category":"Unclassifiable Establishments",
    "sg:phone":"+33 4 90 30 97 11",
    "sg:postcode":"84500",
    "sg:province":"Provence-Alpes-C\u00f4te d'Azur",
    "wof:name":"Egide",
    "wof:placetype":"venue"
},
  "geometry": {"coordinates":[4.748432,44.282192],"type":"Point"}
}