{
  "type": "Feature",
  "properties": {
    "iso:country":"FR",
    "sg:address":"62, Rue Beaubourg, 75003 Paris",
    "sg:orig_category":"Non-Classified Establishments",
    "sg:phone":"+33 1 42 78 28 78",
    "sg:province":"Ile de France",
    "wof:name":"Perles Box S.a.r.l.",
    "wof:placetype":"venue"
},
  "geometry": {"coordinates":[2.354764,48.863297],"type":"Point"}
}