{
  "type": "Feature",
  "properties": {
    "iso:country":"FR",
    "sg:address":"B.P. 584, 93261 Aulnay sous Bois C\u00e9dex^^ZI Garonor - B\u00e2t.19-porte K, 93600 Aulnay sous Bois",
    "sg:orig_category":"Non-Classified Establishments",
    "sg:phone":"+33 1 45 91 24 61",
    "sg:province":"Ile de France",
    "wof:name":"M.r.t.i. S.a.r.l.",
    "wof:placetype":"venue"
},
  "geometry": {"coordinates":[2.49124,48.927509],"type":"Point"}
}