{
  "type": "Feature",
  "properties": {
    "addr:full":"Quartier Chave Simiane Collongue Provence-Alpes-C\u00f4te d'Azur 13109",
    "addr:postcode":"13109",
    "addr:street":"Quartier;Collongue",
    "iso:country":"FR",
    "sg:address":"Quartier Chave",
    "sg:city":"Simiane Collongue",
    "sg:orig_category":"Unclassifiable Establishments",
    "sg:phone":"+33 4 42 22 60 11",
    "sg:postcode":"13109",
    "sg:province":"Provence-Alpes-C\u00f4te d'Azur",
    "wof:name":"Immitra S.a.s. -importation De Mat\u00e9riel Pour Mines Industrie Et Travaux Publics",
    "wof:placetype":"venue"
},
  "geometry": {"coordinates":[5.422672,43.434875],"type":"Point"}
}