{
  "type": "Feature",
  "properties": {
    "addr:full":"16 rue L\u00e9on Gambetta; Vouvray Champagne",
    "addr:housenumber":"16",
    "addr:street":"Rue Le\u0301On Gambetta",
    "iso:country":"FR",
    "sg:address":"16 rue L\u00e9on Gambetta; Vouvray",
    "sg:classifiers":[
        {
            "category":"Banks & Credit Unions",
            "subcategory":"Bank",
            "type":"Services"
        }
    ],
    "sg:phone":"+33 3347527170",
    "sg:province":"Champagne",
    "wof:name":"Cr\u00e9dit Agricole Mutuel",
    "wof:placetype":"venue"
},
  "geometry": {"coordinates":[0.797705,47.415161],"type":"Point"}
}