{
  "type": "Feature",
  "properties": {
    "addr:full":"49, Av. Garibaldi, 87000 Limoges Limousin",
    "addr:postcode":"87000",
    "addr:street":"49 Av. Garibaldi",
    "iso:country":"FR",
    "sg:address":"49, Av. Garibaldi, 87000 Limoges",
    "sg:orig_category":"Non-Classified Establishments",
    "sg:phone":"+33 5 55 79 32 83",
    "sg:province":"Limousin",
    "wof:name":"G.s.f. Atlantis S.a. - Groupe Service France",
    "wof:placetype":"venue"
},
  "geometry": {"coordinates":[1.258859,45.837685],"type":"Point"}
}