{
  "type": "Feature",
  "properties": {
    "addr:full":"59, Rue de Richelieu, 75002 Paris Ile de France",
    "addr:housenumber":"59",
    "addr:postcode":"75002",
    "addr:street":"Rue De Richelieu",
    "iso:country":"FR",
    "sg:address":"59, Rue de Richelieu, 75002 Paris",
    "sg:orig_category":"Non-Classified Establishments",
    "sg:phone":"+33 1 55 35 07 00",
    "sg:province":"Ile de France",
    "wof:name":"M.v.c.d. S.a.r.l.",
    "wof:placetype":"venue"
},
  "geometry": {"coordinates":[2.337339,48.867046],"type":"Point"}
}