{
  "type": "Feature",
  "properties": {
    "iso:country":"FR",
    "sg:address":"Rue Du Pr\u00e9 Magne 69126 Brindas",
    "sg:classifiers":[
        {
            "category":"Professional",
            "subcategory":"Engineering",
            "type":"Services"
        }
    ],
    "sg:phone":"+33 4 78 45 14 63",
    "sg:postcode":"69126",
    "sg:province":"Rhone-Alpes",
    "sg:tags":[
        "machine",
        "-",
        "mechanical"
    ],
    "wof:name":"Steec Apmv",
    "wof:placetype":"venue"
},
  "geometry": {"coordinates":[4.697782,45.718861],"type":"Point"}
}