{
  "type": "Feature",
  "properties": {
    "addr:full":"3 Av Georges Pompidou BP 32 69403 Lyon Cedex 03 Rhone-Alpes",
    "addr:housenumber":"bp 32",
    "addr:postcode":"69403;cedex 03",
    "addr:street":"Av Georges Pompidou",
    "iso:country":"FR",
    "sg:address":"3 Av Georges Pompidou BP 32 69403 Lyon Cedex 03",
    "sg:classifiers":[
        {
            "category":"Banks & Credit Unions",
            "subcategory":"Financial Services",
            "type":"Services"
        }
    ],
    "sg:phone":"+33 4 72 13 20 50",
    "sg:province":"Rhone-Alpes",
    "sg:tags":[
        "banking",
        "insurance",
        "institution",
        "finance"
    ],
    "wof:name":"Caisse Interprofessionnelle Du Logement Ass",
    "wof:placetype":"venue"
},
  "geometry": {"coordinates":[4.86843,45.751369],"type":"Point"}
}