{
  "type": "Feature",
  "properties": {
    "addr:full":"46 Rue D Isly 16100 Cognac Poitou-Charentes 16100",
    "addr:housenumber":"46",
    "addr:postcode":"16100;16100",
    "addr:street":"Rue D Isly",
    "iso:country":"FR",
    "sg:address":"46 Rue D Isly 16100 Cognac",
    "sg:classifiers":[
        {
            "category":"Wholesale",
            "subcategory":"Farm Supplies",
            "type":"Manufacturing & Wholesale Goods"
        }
    ],
    "sg:phone":"+33 5 45 36 16 00",
    "sg:postcode":"16100",
    "sg:province":"Poitou-Charentes",
    "sg:tags":[
        "-",
        "machine",
        "equipment",
        "engineering",
        "machinery",
        "mechanical",
        "agriculture"
    ],
    "wof:name":"Roullet Et Fils",
    "wof:placetype":"venue"
},
  "geometry": {"coordinates":[-0.329631,45.687664],"type":"Point"}
}