{
  "type": "Feature",
  "properties": {
    "addr:full":"Avenue De Nantes 49300 Cholet Pays de Loire 49300",
    "addr:postcode":"49300;49300",
    "addr:street":"Avenue De Nantes",
    "iso:country":"FR",
    "sg:address":"Avenue De Nantes 49300 Cholet",
    "sg:classifiers":[
        {
            "category":"Home & Garden",
            "subcategory":"Furniture",
            "type":"Retail Goods"
        }
    ],
    "sg:phone":"+33 2 41 62 46 34",
    "sg:postcode":"49300",
    "sg:province":"Pays de Loire",
    "sg:tags":[
        "household",
        "wood"
    ],
    "wof:name":"Les Meubles De La Moriniere Societe Prl",
    "wof:placetype":"venue"
},
  "geometry": {"coordinates":[-0.892909,47.060936],"type":"Point"}
}