{
  "type": "Feature",
  "properties": {
    "addr:full":"ZA la Baticole Saint Pardoux la Rivi\u00e8re Aquitaine 24470",
    "addr:postcode":"24470",
    "addr:street":"Za La Baticole Saint Pardoux",
    "iso:country":"FR",
    "sg:address":"ZA la Baticole",
    "sg:city":"Saint Pardoux la Rivi\u00e8re",
    "sg:orig_category":"Unclassifiable Establishments",
    "sg:phone":"+33 5 53 56 75 11",
    "sg:postcode":"24470",
    "sg:province":"Aquitaine",
    "wof:name":"Bouthet Alain",
    "wof:placetype":"venue"
},
  "geometry": {"coordinates":[0.746157,45.492882],"type":"Point"}
}