{
  "type": "Feature",
  "properties": {
    "addr:full":"Zi De Gutenberg 28240 Meauc\u00e9 Meauc\u00e9 Centre 28240",
    "addr:housenumber":"meauce\u0301",
    "addr:postcode":"28240;28240",
    "addr:street":"Zi De Gutenberg",
    "iso:country":"FR",
    "sg:address":"Zi De Gutenberg 28240 Meauc\u00e9",
    "sg:city":"Meauc\u00e9",
    "sg:classifiers":[
        {
            "category":"Manufacturing",
            "subcategory":"Printing",
            "type":"Manufacturing & Wholesale Goods"
        }
    ],
    "sg:phone":"+33 2 37 53 64 14",
    "sg:postcode":"28240",
    "sg:province":"Centre",
    "sg:tags":[
        "publishing"
    ],
    "wof:name":"Cartor Security Printing",
    "wof:placetype":"venue"
},
  "geometry": {"coordinates":[1.00242,48.486248],"type":"Point"}
}