{
  "type": "Feature",
  "properties": {
    "addr:full":"1935, Rte de la Gare, 40290 Misson Misson Aquitaine 40290",
    "addr:housenumber":"1935",
    "addr:postcode":"40290;40290",
    "addr:street":"Rte De;Gare",
    "iso:country":"FR",
    "sg:address":"1935, Rte de la Gare, 40290 Misson",
    "sg:city":"Misson",
    "sg:orig_category":"Non-Classified Establishments",
    "sg:phone":"+33 5 59 98 00 32",
    "sg:postcode":"40290",
    "sg:province":"Aquitaine",
    "wof:name":"S.c.p.a. Sud Ouest S.a. - Soci\u00e9t\u00e9 Commerciale Des Potasses Et De L'azote",
    "wof:placetype":"venue"
},
  "geometry": {"coordinates":[-0.957019,43.59457],"type":"Point"}
}