{
  "type": "Feature",
  "properties": {
    "iso:country":"FR",
    "sg:address":"15, Av. de Vend\u00f4me, 41018 Blois C\u00e9dex",
    "sg:orig_category":"Non-Classified Establishments",
    "sg:phone":"+33 2 54 78 02 88",
    "sg:province":"Centre",
    "wof:name":"Ocgsa - Office De Comptabilit\u00e9 De Gestion Et De Fiscalit\u00e9",
    "wof:placetype":"venue"
},
  "geometry": {"coordinates":[1.328059,47.595707],"type":"Point"}
}