{
  "type": "Feature",
  "properties": {
    "iso:country":"FR",
    "sg:address":"16, Rte de Watten, 59380 Spycker",
    "sg:orig_category":"Non-Classified Establishments",
    "sg:phone":"+33 3 28 27 09 40",
    "sg:province":"Nord Pas-de-Calais",
    "wof:name":"Siatma S.a.r.l.",
    "wof:placetype":"venue"
},
  "geometry": {"coordinates":[2.327398,50.959892],"type":"Point"}
}