{
  "type": "Feature",
  "properties": {
    "addr:full":"83, Rue du 8 Mai 1945, 41200 Romorantin Lanthenay Villefranche-sur-Cher Centre 41200",
    "addr:housenumber":"83",
    "addr:postcode":"41200;41200",
    "addr:street":"Rue Du 8 Mai 1945",
    "iso:country":"FR",
    "sg:address":"83, Rue du 8 Mai 1945, 41200 Romorantin Lanthenay",
    "sg:city":"Villefranche-sur-Cher",
    "sg:orig_category":"Unclassifiable Establishments",
    "sg:phone":"+33 2 54 76 06 21",
    "sg:postcode":"41200",
    "sg:province":"Centre",
    "wof:name":"Jamet S.a.r.l.",
    "wof:placetype":"venue"
},
  "geometry": {"coordinates":[1.738755,47.359936],"type":"Point"}
}