{
  "type": "Feature",
  "properties": {
    "addr:full":"9 Bis Av Mar\u00e9chal De Lattre De Tassigny 69330 Meyzieu Rhone-Alpes",
    "addr:housenumber":"9 bis",
    "addr:postcode":"69330",
    "addr:street":"Av Mare\u0301Chal De Lattre De Tassigny",
    "iso:country":"FR",
    "sg:address":"9 Bis Av Mar\u00e9chal De Lattre De Tassigny 69330 Meyzieu",
    "sg:classifiers":[
        {
            "category":"Manufacturing",
            "subcategory":"Metals",
            "type":"Manufacturing & Wholesale Goods"
        }
    ],
    "sg:phone":"+33 4 72 02 72 06",
    "sg:province":"Rhone-Alpes",
    "sg:tags":[
        "metallurgy",
        "metalworking",
        "processing"
    ],
    "wof:name":"Color Metal Industries Sa",
    "wof:placetype":"venue"
},
  "geometry": {"coordinates":[5.02775,45.77742],"type":"Point"}
}