{
  "type": "Feature",
  "properties": {
    "addr:full":"90 Bd National 92257 La Garenne Colombes Aquitaine",
    "addr:housenumber":"90",
    "addr:postcode":"92257",
    "addr:street":"Bd National",
    "iso:country":"FR",
    "sg:address":"90 Bd National 92257 La Garenne Colombes",
    "sg:classifiers":[
        {
            "category":"Shopping",
            "subcategory":"Computers & Home Electronics",
            "type":"Retail Goods"
        }
    ],
    "sg:phone":"+33 1 41 19 29 00",
    "sg:province":"Aquitaine",
    "sg:tags":[
        "equipment",
        "electrical",
        "component",
        "electric",
        "electronic"
    ],
    "wof:name":"Siemens Automotive Sa",
    "wof:placetype":"venue"
},
  "geometry": {"coordinates":[2.238076,48.908409],"type":"Point"}
}