{
  "type": "Feature",
  "properties": {
    "addr:full":"5, Av Mercuria, 51470 Saint Memmie Champagne",
    "addr:postcode":"51470",
    "addr:street":"Av Mercuria",
    "iso:country":"FR",
    "sg:address":"5, Av Mercuria, 51470 Saint Memmie",
    "sg:orig_category":"Unclassifiable Establishments",
    "sg:phone":"+33 3 26 69 30 10",
    "sg:province":"Champagne",
    "wof:name":"Leviel S.a.",
    "wof:placetype":"venue"
},
  "geometry": {"coordinates":[4.385442,48.945717],"type":"Point"}
}