{
  "type": "Feature",
  "properties": {
    "iso:country":"FR",
    "sg:address":"5 quai des Etroits 69005 Lyon",
    "sg:classifiers":[
        {
            "category":"Professional",
            "subcategory":"Business Services",
            "type":"Services"
        }
    ],
    "sg:phone":"+33 4 78 42 36 26",
    "sg:province":"Rhone-Alpes",
    "sg:tags":[
        "agency",
        "export"
    ],
    "wof:name":"Acoex Sas",
    "wof:placetype":"venue"
},
  "geometry": {"coordinates":[4.82015,45.75098],"type":"Point"}
}