{
  "type": "Feature",
  "properties": {
    "addr:full":"11, Rue Charles de Gaulle, 02630 Wassigny Picardie",
    "addr:housenumber":"11",
    "addr:postcode":"02630",
    "addr:street":"Rue Charles De Gaulle",
    "iso:country":"FR",
    "sg:address":"11, Rue Charles de Gaulle, 02630 Wassigny",
    "sg:orig_category":"Unclassifiable Establishments",
    "sg:phone":"+33 3 23 60 62 08",
    "sg:province":"Picardie",
    "wof:name":"Fonderies De Wassigny - Joassart S.a.",
    "wof:placetype":"venue"
},
  "geometry": {"coordinates":[3.605368,50.008816],"type":"Point"}
}