{
  "type": "Feature",
  "properties": {
    "addr:full":"B.P. 215, 91882 Massy C\u00e9dex^^21, Rue du Saule Trapu - Parc du Moulin de Massy, 91300 Massy Ile de France",
    "addr:housenumber":"b.p. 215",
    "addr:postcode":"91882;91300",
    "addr:street":"Rue Du Saule Trapu Parc;Moulin De Massy;Ile De France",
    "iso:country":"FR",
    "sg:address":"B.P. 215, 91882 Massy C\u00e9dex^^21, Rue du Saule Trapu - Parc du Moulin de Massy, 91300 Massy",
    "sg:orig_category":"Non-Classified Establishments",
    "sg:phone":"+33 1 60 11 11 60",
    "sg:province":"Ile de France",
    "wof:name":"Terca Briques S.a.s.",
    "wof:placetype":"venue"
},
  "geometry": {"coordinates":[2.27325,48.730282],"type":"Point"}
}