{
  "type": "Feature",
  "properties": {
    "iso:country":"FR",
    "sg:address":"B.P. 42, 77312 Marne la Vall\u00e9e C\u00e9dex 02^^Bd Beaubourg - ZI Paris Est, 77184 Emerainville",
    "sg:orig_category":"Non-Classified Establishments",
    "sg:phone":"+33 1 64 62 35 00",
    "sg:province":"Ile de France",
    "wof:name":"Sick S.a.r.l.",
    "wof:placetype":"venue"
},
  "geometry": {"coordinates":[2.622175,48.811619],"type":"Point"}
}