{
  "type": "Feature",
  "properties": {
    "addr:full":"B.P. 512 Thouars C\u00e9dex^^Motte des Justices 79100 Thouars Poitou-Charentes 79100",
    "addr:housenumber":"b.p. 512",
    "addr:postcode":"79100;79100",
    "iso:country":"FR",
    "sg:address":"B.P. 512",
    "sg:city":"Thouars C\u00e9dex^^Motte des Justices 79100 Thouars",
    "sg:orig_category":"Non-Classified Establishments",
    "sg:phone":"+33 5 49 66 45 55",
    "sg:postcode":"79100",
    "sg:province":"Poitou-Charentes",
    "wof:name":"Edanel S.a.r.l.",
    "wof:placetype":"venue"
},
  "geometry": {"coordinates":[-0.099814,46.907261],"type":"Point"}
}