{
  "type": "Feature",
  "properties": {
    "addr:full":"Gallery Gray d'Albion Cannes Midi Pyr\u00e9n\u00e9es 06400",
    "addr:postcode":"06400",
    "iso:country":"FR",
    "sg:address":"Gallery Gray d'Albion",
    "sg:city":"Cannes",
    "sg:orig_category":"Unclassifiable Establishments",
    "sg:phone":"+33 4 93 68 45 45",
    "sg:postcode":"06400",
    "sg:province":"Midi Pyr\u00e9n\u00e9es",
    "wof:name":"Canne Voyages International S.a.r.l.",
    "wof:placetype":"venue"
},
  "geometry": {"coordinates":[7.01978,43.552101],"type":"Point"}
}