{
  "type": "Feature",
  "properties": {
    "addr:full":"24/28, Av. Jean Mermoz, 89000 Auxerre Auxerre Bourgogne 89000",
    "addr:housenumber":"24 / 28",
    "addr:postcode":"89000;89000",
    "addr:street":"Av. Jean Mermoz",
    "iso:country":"FR",
    "sg:address":"24/28, Av. Jean Mermoz, 89000 Auxerre",
    "sg:city":"Auxerre",
    "sg:orig_category":"Unclassifiable Establishments",
    "sg:phone":"+33 3 86 94 42 42",
    "sg:postcode":"89000",
    "sg:province":"Bourgogne",
    "wof:name":"General Trailers",
    "wof:placetype":"venue"
},
  "geometry": {"coordinates":[3.585644,47.812275],"type":"Point"}
}