{
  "type": "Feature",
  "properties": {
    "iso:country":"FR",
    "sg:address":"Za 43300 Mazeyrat D'Allier",
    "sg:city":"Chanteuges",
    "sg:classifiers":[
        {
            "category":"Manufacturing",
            "subcategory":"Rubber & Plastics",
            "type":"Manufacturing & Wholesale Goods"
        }
    ],
    "sg:phone":"+33 4 71 74 54 00",
    "sg:postcode":"43300",
    "sg:province":"Auvergne",
    "wof:name":"Recticel Sa",
    "wof:placetype":"venue"
},
  "geometry": {"coordinates":[3.52889,45.12133],"type":"Point"}
}