{
  "type": "Feature",
  "properties": {
    "iso:country":"FR",
    "sg:address":"rue Johannes Gutenberg 82000 Montauban",
    "sg:classifiers":[
        {
            "category":"Shopping",
            "subcategory":"Shoes",
            "type":"Retail Goods"
        }
    ],
    "sg:phone":"+33 5 63 03 03 35",
    "sg:province":"Midi Pyr\u00e9n\u00e9es",
    "sg:tags":[
        "model"
    ],
    "wof:name":"M.b.c. Sa",
    "wof:placetype":"venue"
},
  "geometry": {"coordinates":[1.364208,44.039169],"type":"Point"}
}