{
  "type": "Feature",
  "properties": {
    "iso:country":"FR",
    "sg:address":"12, Cours Lumi\u00e8re, 94306 Vincennes C\u00e9dex",
    "sg:orig_category":"Non-Classified Establishments",
    "sg:phone":"+33 1 49 57 51 51",
    "sg:province":"Midi Pyr\u00e9n\u00e9es",
    "wof:name":"Audit De France Sodip S.a.",
    "wof:placetype":"venue"
},
  "geometry": {"coordinates":[2.428771,48.843552],"type":"Point"}
}