{
  "type": "Feature",
  "properties": {
    "iso:country":"FR",
    "sg:address":"14, Rte de Chauny, 02100 Saint Quentin",
    "sg:orig_category":"Non-Classified Establishments",
    "sg:phone":"+33 3 23 68 08 00",
    "sg:postcode":"02100",
    "sg:province":"Picardie",
    "wof:name":"C\u00e9g\u00e9lec S.a.",
    "wof:placetype":"venue"
},
  "geometry": {"coordinates":[3.30555,49.831711],"type":"Point"}
}