{
  "type": "Feature",
  "properties": {
    "iso:country":"FR",
    "sg:address":"10, Rue des Peupliers, 68120 Pfastatt",
    "sg:city":"Pfastatt",
    "sg:orig_category":"Non-Classified Establishments",
    "sg:phone":"+33 3 89 52 18 00",
    "sg:postcode":"68120",
    "sg:province":"Alsace",
    "wof:name":"C.c.r. Schmitt S.a.r.l.",
    "wof:placetype":"venue"
},
  "geometry": {"coordinates":[7.302891,47.776413],"type":"Point"}
}