{
  "type": "Feature",
  "properties": {
    "iso:country":"FR",
    "sg:address":"194, Rue Nationale, 59000 Lille",
    "sg:orig_category":"Unclassifiable Establishments",
    "sg:phone":"+33 3 28 36 14 21",
    "sg:province":"Nord Pas-de-Calais",
    "wof:name":"C.a.t. Atelier Prot\u00e9g\u00e9 Du Nord",
    "wof:placetype":"venue"
},
  "geometry": {"coordinates":[3.051376,50.632439],"type":"Point"}
}