{
  "type": "Feature",
  "properties": {
    "iso:country":"FR",
    "sg:address":"682, Av. Gaston F\u00e9bus, 64170 Artix",
    "sg:city":"Artix",
    "sg:orig_category":"Unclassifiable Establishments",
    "sg:phone":"+33 5 59 60 32 63",
    "sg:postcode":"64170",
    "sg:province":"Aquitaine",
    "wof:name":"Diez S.a.",
    "wof:placetype":"venue"
},
  "geometry": {"coordinates":[-0.579293,43.3992],"type":"Point"}
}