{
  "type": "Feature",
  "properties": {
    "iso:country":"FR",
    "sg:address":"B.P. 85, 33605 Pessac C\u00e9dex^^94, Av. de Canejan, 33600 Pessac",
    "sg:city":"Pessac",
    "sg:orig_category":"Non-Classified Establishments",
    "sg:phone":"+33 5 57 89 18 00",
    "sg:postcode":"33600",
    "sg:province":"Aquitaine",
    "wof:name":"A.f.p.a.",
    "wof:placetype":"venue"
},
  "geometry": {"coordinates":[-0.630989,44.80616],"type":"Point"}
}