{
  "type": "Feature",
  "properties": {
    "addr:full":"344, Bd Michelet, 13009 Marseille Poitou-Charentes",
    "addr:housenumber":"344",
    "addr:postcode":"13009",
    "addr:street":"Bd Michelet",
    "iso:country":"FR",
    "sg:address":"344, Bd Michelet, 13009 Marseille",
    "sg:orig_category":"Unclassifiable Establishments",
    "sg:phone":"+33 4 96 20 33 70",
    "sg:province":"Poitou-Charentes",
    "wof:name":"S.m.a.b.t.p. - Soci\u00e9t\u00e9 Mutuelle D'assurance Du B\u00e2timent Et Des Tr",
    "wof:placetype":"venue"
},
  "geometry": {"coordinates":[5.400934,43.254654],"type":"Point"}
}