{
  "type": "Feature",
  "properties": {
    "addr:full":"18 Pardenri\u00e8res 04200 Sisteron Basse Normandie",
    "addr:housenumber":"18",
    "addr:postcode":"04200",
    "addr:street":"Pardenrie\u0300Res",
    "iso:country":"FR",
    "sg:address":"18",
    "sg:city":"Pardenri\u00e8res 04200 Sisteron",
    "sg:classifiers":[
        {
            "category":"Shopping",
            "subcategory":"Crafts & Fabrics",
            "type":"Retail Goods"
        }
    ],
    "sg:phone":"+33 4 92 61 28 93",
    "sg:province":"Basse Normandie",
    "sg:tags":[
        "textile",
        "linen",
        "clothing"
    ],
    "wof:name":"Graine Deux Sellerie",
    "wof:placetype":"venue"
},
  "geometry": {"coordinates":[5.9441,44.197495],"type":"Point"}
}