{
  "type": "Feature",
  "properties": {
    "iso:country":"FR",
    "sg:address":"2 r Gustave Madiot 91989 Bondoufle CEDEX",
    "sg:orig_category":"Proximity Switches, Capacitance Switches",
    "sg:phone":"+33 1 60 86 87 98",
    "sg:province":"\u00cele-de-France",
    "wof:name":"Siccom Sa",
    "wof:placetype":"venue"
},
  "geometry": {"coordinates":[2.367335,48.602966],"type":"Point"}
}