{
  "type": "Feature",
  "properties": {
    "addr:full":"189 Rue Du Temple 75003 Paris Ile de France 75003",
    "addr:housenumber":"189",
    "addr:postcode":"75003;75003",
    "addr:street":"Rue Du Temple",
    "iso:country":"FR",
    "sg:address":"189 Rue Du Temple 75003 Paris",
    "sg:classifiers":[
        {
            "category":"Manufacturing",
            "subcategory":"Metals",
            "type":"Manufacturing & Wholesale Goods"
        }
    ],
    "sg:phone":"+33 1 42 72 95 70",
    "sg:postcode":"75003",
    "sg:province":"Ile de France",
    "sg:tags":[
        "metallurgy",
        "metalworking",
        "processing"
    ],
    "wof:name":"Rouge Pullon - Dorure Et Argenture",
    "wof:placetype":"venue"
},
  "geometry": {"coordinates":[2.360549,48.865738],"type":"Point"}
}