{
  "type": "Feature",
  "properties": {
    "addr:full":"18, Av. des Champs Elys\u00e9es, 75008 Paris Ile de France",
    "addr:postcode":"75008",
    "addr:street":"18 Av. Des Champs Elyse\u0301Es",
    "iso:country":"FR",
    "sg:address":"18, Av. des Champs Elys\u00e9es, 75008 Paris",
    "sg:orig_category":"Non-Classified Establishments",
    "sg:phone":"+33 1 40 36 55 36",
    "sg:province":"Ile de France",
    "wof:name":"France Med Diffusion S.a.r.l.",
    "wof:placetype":"venue"
},
  "geometry": {"coordinates":[2.309053,48.869427],"type":"Point"}
}