{
  "type": "Feature",
  "properties": {
    "iso:country":"FR",
    "sg:address":", 10250 NEUVILLE SUR SEINE",
    "sg:city":"NEUVILLE SUR SEINE",
    "sg:classifiers":[
        {
            "category":"Winery",
            "type":"Food & Drink"
        }
    ],
    "sg:phone":"+33 3 25 38 21 51",
    "sg:postcode":"10250",
    "sg:province":"Champagne",
    "sg:tags":[
        "sparkling",
        "wine"
    ],
    "wof:name":"Etablissements Philippe Herard Sa",
    "wof:placetype":"venue"
},
  "geometry": {"coordinates":[4.411015,48.040905],"type":"Point"}
}