{
  "type": "Feature",
  "properties": {
    "addr:full":"51320 Vatry Champagne",
    "addr:postcode":"51320",
    "iso:country":"FR",
    "sg:address":"51320 Vatry",
    "sg:orig_category":"Unclassifiable Establishments",
    "sg:phone":"+33 3 26 67 41 57",
    "sg:province":"Champagne",
    "wof:name":"Prod\u00e9va S.a.",
    "wof:placetype":"venue"
},
  "geometry": {"coordinates":[4.245865,48.82357],"type":"Point"}
}