{
  "type": "Feature",
  "properties": {
    "iso:country":"FR",
    "sg:address":"Za De Kerdadic 22700 Perros Guirec",
    "sg:city":"Louannec",
    "sg:classifiers":[
        {
            "category":"Manufacturing",
            "subcategory":"Printing",
            "type":"Manufacturing & Wholesale Goods"
        }
    ],
    "sg:phone":"+33 2 96 49 00 49",
    "sg:postcode":"22700",
    "sg:province":"Bretagne",
    "sg:tags":[
        "publishing"
    ],
    "wof:name":"Ouest Pack Sas",
    "wof:placetype":"venue"
},
  "geometry": {"coordinates":[-3.443839,48.813995],"type":"Point"}
}