{
  "type": "Feature",
  "properties": {
    "addr:full":"Rte de la Moutonne - Le Beau V\u00e8ze Carqueiranne Provence-Alpes-C\u00f4te d'Azur 83320",
    "addr:postcode":"83320",
    "addr:street":"Rte De La Moutonne Le;Carqueiranne",
    "iso:country":"FR",
    "sg:address":"Rte de la Moutonne - Le Beau V\u00e8ze",
    "sg:city":"Carqueiranne",
    "sg:orig_category":"Unclassifiable Establishments",
    "sg:phone":"+33 4 94 08 24 57",
    "sg:postcode":"83320",
    "sg:province":"Provence-Alpes-C\u00f4te d'Azur",
    "wof:name":"Soleil Du Var G.a.e.c.",
    "wof:placetype":"venue"
},
  "geometry": {"coordinates":[6.074445,43.09417],"type":"Point"}
}