{
  "type": "Feature",
  "properties": {
    "addr:full":"Le Colombier 81240 Saint Amans Soult Midi Pyr\u00e9n\u00e9es",
    "addr:postcode":"81240 saint",
    "iso:country":"FR",
    "sg:address":"Le Colombier 81240 Saint Amans Soult",
    "sg:orig_category":"Unclassifiable Establishments",
    "sg:phone":"+33 5 63 98 33 37",
    "sg:province":"Midi Pyr\u00e9n\u00e9es",
    "wof:name":"Codico Chabert S.a.",
    "wof:placetype":"venue"
},
  "geometry": {"coordinates":[2.540027,43.45966],"type":"Point"}
}