{
  "type": "Feature",
  "properties": {
    "iso:country":"FR",
    "sg:address":"224, Av. Hoff, 01300 Belley",
    "sg:orig_category":"Unclassifiable Establishments",
    "sg:phone":"+33 4 79 81 02 55",
    "sg:postcode":"01300",
    "sg:province":"Rhone-Alpes",
    "wof:name":"D.e.r.l.k.a. S.a. - Distillerie Etoile Rameaux Laboratoire Kario",
    "wof:placetype":"venue"
},
  "geometry": {"coordinates":[5.684605,45.751415],"type":"Point"}
}