{
  "type": "Feature",
  "properties": {
    "iso:country":"FR",
    "sg:address":"178 R D'Alger 59100 Roubaix",
    "sg:classifiers":[
        {
            "category":"Banks & Credit Unions",
            "subcategory":"Investment Brokerage",
            "type":"Services"
        }
    ],
    "sg:phone":"+33 3 59 00 88 00",
    "sg:province":"Nord Pas-de-Calais",
    "sg:tags":[
        "-",
        "transport",
        "related"
    ],
    "wof:name":"Miellet Louis Sarl",
    "wof:placetype":"venue"
},
  "geometry": {"coordinates":[3.195265,50.696369],"type":"Point"}
}