{
  "type": "Feature",
  "properties": {
    "addr:full":"Rte du Pont d'Ain Montagnat Rhone-Alpes 01250",
    "addr:postcode":"01250",
    "addr:street":"Rte Du Pont D'Ain;Rhone-Alpes",
    "iso:country":"FR",
    "sg:address":"Rte du Pont d'Ain",
    "sg:city":"Montagnat",
    "sg:orig_category":"Unclassifiable Establishments",
    "sg:phone":"+33 4 74 22 49 58",
    "sg:postcode":"01250",
    "sg:province":"Rhone-Alpes",
    "wof:name":"Intech S.a.r.l.",
    "wof:placetype":"venue"
},
  "geometry": {"coordinates":[5.309248,46.245743],"type":"Point"}
}