{
  "type": "Feature",
  "properties": {
    "addr:full":"Labarde 33460 Labarde Labarde Aquitaine 33460",
    "addr:postcode":"33460;33460",
    "iso:country":"FR",
    "sg:address":"Labarde 33460 Labarde",
    "sg:city":"Labarde",
    "sg:orig_category":"Unclassifiable Establishments",
    "sg:phone":"+33 5 57 88 34 04",
    "sg:postcode":"33460",
    "sg:province":"Aquitaine",
    "wof:name":"Ch\u00e2teau Siran S.c.e.a.",
    "wof:placetype":"venue"
},
  "geometry": {"coordinates":[-0.639827,45.021534],"type":"Point"}
}