{
  "type": "Feature",
  "properties": {
    "iso:country":"FR",
    "sg:address":"40, Rue Notre Dame, 08400 Falaise",
    "sg:orig_category":"Unclassifiable Establishments",
    "sg:phone":"+33 3 24 71 73 34",
    "sg:province":"Champagne",
    "wof:name":"Lith'or S.a.r.l.",
    "wof:placetype":"venue"
},
  "geometry": {"coordinates":[4.729852,49.376869],"type":"Point"}
}