{
  "type": "Feature",
  "properties": {
    "addr:full":"1, Rue des Vergers, 69760 Limonest Rhone-Alpes 69760",
    "addr:housenumber":"1",
    "addr:postcode":"69760;69760",
    "addr:street":"Rue Des Vergers",
    "iso:country":"FR",
    "sg:address":"1, Rue des Vergers, 69760 Limonest",
    "sg:orig_category":"Non-Classified Establishments",
    "sg:phone":"+33 4 78 66 82 60",
    "sg:postcode":"69760",
    "sg:province":"Rhone-Alpes",
    "wof:name":"B.v.q.i. S.a. - Bureau V\u00e9ritas Quality International France",
    "wof:placetype":"venue"
},
  "geometry": {"coordinates":[4.77387,45.807426],"type":"Point"}
}