{
  "type": "Feature",
  "properties": {
    "iso:country":"FR",
    "sg:address":"Rue Alphonse Delavau",
    "sg:city":"Pouzauges",
    "sg:orig_category":"Unclassifiable Establishments",
    "sg:phone":"+33 2 51 91 36 60",
    "sg:postcode":"85700",
    "sg:province":"Pays de Loire",
    "wof:name":"Les Cars Du Bocage S.a.r.l.",
    "wof:placetype":"venue"
},
  "geometry": {"coordinates":[-0.826542,46.784111],"type":"Point"}
}