{
  "type": "Feature",
  "properties": {
    "addr:full":"77 Avenue Marceau 75116 Paris Bourgogne",
    "addr:housenumber":"77",
    "addr:postcode":"75116",
    "addr:street":"Avenue Marceau",
    "iso:country":"FR",
    "sg:address":"77 Avenue Marceau 75116 Paris",
    "sg:classifiers":[
        {
            "category":"Professional",
            "subcategory":"Business Services",
            "type":"Services"
        }
    ],
    "sg:phone":"+33 1 44 31 21 21",
    "sg:province":"Bourgogne",
    "sg:tags":[
        "body",
        "advice"
    ],
    "wof:name":"Danemark - Cci",
    "wof:placetype":"venue"
},
  "geometry": {"coordinates":[2.296696,48.87138],"type":"Point"}
}