{
  "type": "Feature",
  "properties": {
    "addr:full":"B.P. 81, 48002 Mende C\u00e9dex^^16, Bd du Soubeyran, 48000 Mende Languedoc-Roussillon 48000",
    "addr:postcode":"48002;ce\u0301dex^^16;48000;48000",
    "addr:street":"B.P. 81;Bd Du Soubeyran",
    "iso:country":"FR",
    "sg:address":"B.P. 81, 48002 Mende C\u00e9dex^^16, Bd du Soubeyran, 48000 Mende",
    "sg:orig_category":"Non-Classified Establishments",
    "sg:phone":"+33 4 66 49 00 33",
    "sg:postcode":"48000",
    "sg:province":"Languedoc-Roussillon",
    "wof:name":"C.c.i. De Mend\u00e9 - Chambre De Commerce Et D'industrie De Mend\u00e9",
    "wof:placetype":"venue"
},
  "geometry": {"coordinates":[3.559072,44.456753],"type":"Point"}
}