{
  "type": "Feature",
  "properties": {
    "iso:country":"FR",
    "sg:address":"rue des Genets 01600 Reyrieux",
    "sg:orig_category":"Fittings, Valves",
    "sg:phone":"+33 4 74 08 94 44",
    "sg:postcode":"01600",
    "sg:province":"Rhone-Alpes",
    "wof:name":"Equip Inox Sas",
    "wof:placetype":"venue"
},
  "geometry": {"coordinates":[4.819201,45.943676],"type":"Point"}
}