{
  "type": "Feature",
  "properties": {
    "addr:full":"577 Rue Du Pommarin Zi Centralp 38340 Voreppe Rhone-Alpes 38340",
    "addr:housenumber":"577",
    "addr:postcode":"38340;38340",
    "addr:street":"Rue Du Pommarin Zi",
    "iso:country":"FR",
    "sg:address":"577 Rue Du Pommarin Zi Centralp 38340 Voreppe",
    "sg:classifiers":[
        {
            "category":"Shopping",
            "type":"Retail Goods"
        }
    ],
    "sg:phone":"+33 4 76 50 85 50",
    "sg:postcode":"38340",
    "sg:province":"Rhone-Alpes",
    "sg:tags":[
        "metallurgy",
        "finished",
        "-",
        "metalworking",
        "metallic"
    ],
    "wof:name":"Sico",
    "wof:placetype":"venue"
},
  "geometry": {"coordinates":[5.63766,45.298351],"type":"Point"}
}