{
  "type": "Feature",
  "properties": {
    "addr:full":"3, Rue du Bosphore Almacity, 35074 Rennes C\u00e9dex Brittany",
    "addr:housenumber":"3",
    "addr:postcode":"35074",
    "addr:street":"Rue Du Bosphore Almacity",
    "iso:country":"FR",
    "sg:address":"3, Rue du Bosphore Almacity, 35074 Rennes C\u00e9dex",
    "sg:orig_category":"Unclassifiable Establishments",
    "sg:phone":"+33 2 99 51 17 18",
    "sg:province":"Brittany",
    "wof:name":"Gerpi S.a.",
    "wof:placetype":"venue"
},
  "geometry": {"coordinates":[-1.67777,48.111721],"type":"Point"}
}