{
  "type": "Feature",
  "properties": {
    "addr:full":"31/33, Rue Pleyel, 93200 Saint Denis Ile de France",
    "addr:housenumber":"31 / 33",
    "addr:postcode":"93200",
    "addr:street":"Rue Pleyel",
    "iso:country":"FR",
    "sg:address":"31/33, Rue Pleyel, 93200 Saint Denis",
    "sg:orig_category":"Non-Classified Establishments",
    "sg:phone":"+33 1 48 13 74 74",
    "sg:province":"Ile de France",
    "wof:name":"Soeximex S.a. - Soci\u00e9t\u00e9 D'exploitation D'importation Et D'exporta",
    "wof:placetype":"venue"
},
  "geometry": {"coordinates":[2.343584,48.920967],"type":"Point"}
}