{
  "type": "Feature",
  "properties": {
    "addr:full":"8, Av. de Verdun, 13440 Cabannes Provence-Alpes-C\u00f4te d'Azur",
    "addr:postcode":"13440",
    "addr:street":"Av. De Verdun",
    "iso:country":"FR",
    "sg:address":"8, Av. de Verdun, 13440 Cabannes",
    "sg:orig_category":"Non-Classified Establishments",
    "sg:phone":"+33 4 90 95 24 04",
    "sg:province":"Provence-Alpes-C\u00f4te d'Azur",
    "wof:name":"France Primeurs S.a.",
    "wof:placetype":"venue"
},
  "geometry": {"coordinates":[4.944012,43.861038],"type":"Point"}
}