{
  "type": "Feature",
  "properties": {
    "addr:full":"B.P. 23, 54181 Heillecourt C\u00e9dex^^15, All\u00e9e des Peupliers - ZI Ouest, 54180 Heillecourt Lorraine",
    "addr:postcode":"54181;54180",
    "addr:street":"B.P. 23;Alle\u0301E Des Peupliers Zi Ouest",
    "iso:country":"FR",
    "sg:address":"B.P. 23, 54181 Heillecourt C\u00e9dex^^15, All\u00e9e des Peupliers - ZI Ouest, 54180 Heillecourt",
    "sg:orig_category":"Non-Classified Establishments",
    "sg:phone":"+33 3 83 55 20 33",
    "sg:province":"Lorraine",
    "wof:name":"Miroiterie Petitjean S.a.r.l.",
    "wof:placetype":"venue"
},
  "geometry": {"coordinates":[6.194192,48.653137],"type":"Point"}
}