{
  "type": "Feature",
  "properties": {
    "iso:country":"FR",
    "sg:address":"15, Av des Tilleuls - La Vaivre, 71500 Louhans",
    "sg:city":"Louhans",
    "sg:orig_category":"Unclassifiable Establishments",
    "sg:phone":"+33 3 85 76 08 80",
    "sg:postcode":"71500",
    "sg:province":"Bourgogne",
    "wof:name":"Mcr Novabresse S.a.r.l.",
    "wof:placetype":"venue"
},
  "geometry": {"coordinates":[5.190305,46.591961],"type":"Point"}
}