{
  "type": "Feature",
  "properties": {
    "iso:country":"FR",
    "sg:address":"B.P. 113, 27401 Louviers C\u00e9dex^^Rte de Pacy Le Hamet, 27400 Acquigny",
    "sg:orig_category":"Non-Classified Establishments",
    "sg:phone":"+33 2 32 50 23 12",
    "sg:province":"Haute Normandie",
    "wof:name":"S.m.e.h. S.a. - Soci\u00e9t\u00e9 De M\u00e9canique Et D'emboutissage Du Hamet",
    "wof:placetype":"venue"
},
  "geometry": {"coordinates":[1.134962,49.107613],"type":"Point"}
}