{
  "type": "Feature",
  "properties": {
    "iso:country":"FR",
    "sg:address":"104 Rue De Seze 69006 Lyon",
    "sg:classifiers":[
        {
            "category":"Professional",
            "subcategory":"Engineering",
            "type":"Services"
        }
    ],
    "sg:phone":"+33 4 78 52 24 97",
    "sg:province":"Rhone-Alpes",
    "sg:tags":[
        "machine",
        "-",
        "mechanical"
    ],
    "wof:name":"Sarl Leouzon Vamp",
    "wof:placetype":"venue"
},
  "geometry": {"coordinates":[4.853943,45.768723],"type":"Point"}
}