{
  "type": "Feature",
  "properties": {
    "addr:full":"Chemin des Combes Biot Provence-Alpes-C\u00f4te d'Azur 06410",
    "addr:postcode":"06410",
    "addr:street":"Chemin Des Combes Biot",
    "iso:country":"FR",
    "sg:address":"Chemin des Combes",
    "sg:city":"Biot",
    "sg:orig_category":"Unclassifiable Establishments",
    "sg:phone":"+33 4 93 65 03 00",
    "sg:postcode":"06410",
    "sg:province":"Provence-Alpes-C\u00f4te d'Azur",
    "wof:name":"La Verrerie De Biot S.a.",
    "wof:placetype":"venue"
},
  "geometry": {"coordinates":[7.101925,43.627457],"type":"Point"}
}