{
  "type": "Feature",
  "properties": {
    "iso:country":"FR",
    "sg:address":"62 Rampe Bouvreuil 76000 Rouen",
    "sg:classifiers":[
        {
            "category":"Wholesale",
            "subcategory":"Medical Equipment & Supplies",
            "type":"Manufacturing & Wholesale Goods"
        }
    ],
    "sg:phone":"+33 2 35 71 00 95",
    "sg:postcode":"76000",
    "sg:province":"Haute Normandie",
    "sg:tags":[
        "instrument",
        "health",
        "-",
        "precision"
    ],
    "wof:name":"Villeret De La Motte Philippe",
    "wof:placetype":"venue"
},
  "geometry": {"coordinates":[1.090694,49.447025],"type":"Point"}
}