{
  "type": "Feature",
  "properties": {
    "iso:country":"FR",
    "sg:address":"Rte de la Chanade - ZI de la Ponchonni\u00e8re",
    "sg:city":"Savigny",
    "sg:orig_category":"Unclassifiable Establishments",
    "sg:phone":"+33 4 74 71 00 71",
    "sg:postcode":"69210",
    "sg:province":"Rhone-Alpes",
    "wof:name":"Fr\u00e9s\u00e9nius Hemocare France S.a.",
    "wof:placetype":"venue"
},
  "geometry": {"coordinates":[4.606841,45.7701],"type":"Point"}
}