{
  "type": "Feature",
  "properties": {
    "addr:full":"81 Bd Jean Jaur\u00e8s 92110 Clichy Ile de France",
    "addr:housenumber":"81",
    "addr:postcode":"92110",
    "addr:street":"Bd Jean Jaure\u0300S;Ile De France",
    "iso:country":"FR",
    "sg:address":"81 Bd Jean Jaur\u00e8s 92110 Clichy",
    "sg:classifiers":[
        {
            "category":"Banks & Credit Unions",
            "subcategory":"Investment Brokerage",
            "type":"Services"
        }
    ],
    "sg:phone":"+33 1 49 68 06 51",
    "sg:province":"Ile de France",
    "sg:tags":[
        "-",
        "transport",
        "related"
    ],
    "wof:name":"La Poste",
    "wof:placetype":"venue"
},
  "geometry": {"coordinates":[2.304369,48.902023],"type":"Point"}
}