{
  "type": "Feature",
  "properties": {
    "addr:full":"15 Rue Du Ried 67150 Nordhouse Nordhouse Alsace 67150",
    "addr:housenumber":"15",
    "addr:postcode":"67150;67150",
    "addr:street":"Rue Du Ried;Nordhouse",
    "iso:country":"FR",
    "sg:address":"15 Rue Du Ried 67150 Nordhouse",
    "sg:city":"Nordhouse",
    "sg:classifiers":[
        {
            "category":"Food & Beverages",
            "subcategory":"Groceries & Convenience Stores",
            "type":"Retail Goods"
        }
    ],
    "sg:phone":"+33 3 88 59 01 70",
    "sg:postcode":"67150",
    "sg:province":"Alsace",
    "sg:tags":[
        "product",
        "grain",
        "cereal",
        "related"
    ],
    "wof:name":"Grieshaber Production",
    "wof:placetype":"venue"
},
  "geometry": {"coordinates":[7.68349,48.44606],"type":"Point"}
}