{
  "type": "Feature",
  "properties": {
    "addr:full":"33, Rue Mailly, 51360 Verzenay Champagne",
    "addr:housenumber":"33",
    "addr:postcode":"51360",
    "addr:street":"Rue Mailly",
    "iso:country":"FR",
    "sg:address":"33, Rue Mailly, 51360 Verzenay",
    "sg:orig_category":"Unclassifiable Establishments",
    "sg:phone":"+33 3 26 49 48 14",
    "sg:province":"Champagne",
    "wof:name":"Champagne Marc Henriet E.a.r.l.",
    "wof:placetype":"venue"
},
  "geometry": {"coordinates":[4.14102,49.159016],"type":"Point"}
}