{
  "type": "Feature",
  "properties": {
    "iso:country":"FR",
    "sg:address":"B.P. 32, 49430 Durtal C\u00e9dex^^ZA Pont de Pont Ram\u00e9, 49430 Durtal",
    "sg:orig_category":"Non-Classified Establishments",
    "sg:phone":"+33 2 41 76 10 10",
    "sg:province":"Pays de Loire",
    "wof:name":"Etablissements Renou S.a.r.l.",
    "wof:placetype":"venue"
},
  "geometry": {"coordinates":[-0.207179,47.624077],"type":"Point"}
}