{
  "type": "Feature",
  "properties": {
    "iso:country":"FR",
    "sg:address":"16, Rue du Pont, 41500 Maves",
    "sg:city":"Maves",
    "sg:orig_category":"Unclassifiable Establishments",
    "sg:phone":"+33 2 54 87 34 89",
    "sg:postcode":"41500",
    "sg:province":"Centre",
    "wof:name":"Upsilonn S.a.r.l.",
    "wof:placetype":"venue"
},
  "geometry": {"coordinates":[1.334571,47.742401],"type":"Point"}
}