{
  "type": "Feature",
  "properties": {
    "addr:full":"Rue des Gu\u00e9rins Le Coteau Rhone-Alpes 42120",
    "addr:postcode":"42120",
    "addr:street":"Rue Des Gue\u0301Rins;Rhone-Alpes",
    "iso:country":"FR",
    "sg:address":"Rue des Gu\u00e9rins",
    "sg:city":"Le Coteau",
    "sg:orig_category":"Unclassifiable Establishments",
    "sg:phone":"+33 4 77 23 77 23",
    "sg:postcode":"42120",
    "sg:province":"Rhone-Alpes",
    "wof:name":"Henitex International S.a.",
    "wof:placetype":"venue"
},
  "geometry": {"coordinates":[4.100443,46.012012],"type":"Point"}
}