{
  "type": "Feature",
  "properties": {
    "addr:full":"38, Rue Laffitte, 75009 Paris Ile de France",
    "addr:housenumber":"38",
    "addr:postcode":"75009",
    "addr:street":"Rue Laffitte",
    "iso:country":"FR",
    "sg:address":"38, Rue Laffitte, 75009 Paris",
    "sg:orig_category":"Unclassifiable Establishments",
    "sg:phone":"+33 1 44 79 05 79",
    "sg:province":"Ile de France",
    "wof:name":"Comptoir Des Signaux S.a.",
    "wof:placetype":"venue"
},
  "geometry": {"coordinates":[2.338188,48.87389],"type":"Point"}
}