{
  "type": "Feature",
  "properties": {
    "addr:full":"Bd de Courcerin - ZI Pariest Croissy Beaubourg Ile de France 77183",
    "addr:postcode":"77183",
    "addr:street":"Bd De Courcerin Zi Pariest Croissy Beaubourg Ile De France",
    "iso:country":"FR",
    "sg:address":"Bd de Courcerin - ZI Pariest",
    "sg:city":"Croissy Beaubourg",
    "sg:orig_category":"Unclassifiable Establishments",
    "sg:phone":"+33 1 64 80 12 12",
    "sg:postcode":"77183",
    "sg:province":"Ile de France",
    "wof:name":"Red Lion Controls France S.a.r.l.",
    "wof:placetype":"venue"
},
  "geometry": {"coordinates":[2.659334,48.828526],"type":"Point"}
}