{
  "type": "Feature",
  "properties": {
    "addr:full":"All\u00e9e du Moura - ZI La N\u00e9gresse Biarritz Aquitaine 64200",
    "addr:postcode":"64200",
    "addr:street":"Alle\u0301E Du Moura Zi La Ne\u0301Gresse",
    "iso:country":"FR",
    "sg:address":"All\u00e9e du Moura - ZI La N\u00e9gresse",
    "sg:city":"Biarritz",
    "sg:orig_category":"Non-Classified Establishments",
    "sg:phone":"+33 5 59 23 66 22",
    "sg:postcode":"64200",
    "sg:province":"Aquitaine",
    "wof:name":"Davigel S.a.",
    "wof:placetype":"venue"
},
  "geometry": {"coordinates":[-1.558793,43.482571],"type":"Point"}
}