{
  "type": "Feature",
  "properties": {
    "iso:country":"FR",
    "sg:address":"B.P. 2, 42290 Sorbiers C\u00e9dex^^1, Rue Louis Blanchard, 42290 Sorbiers",
    "sg:orig_category":"Non-Classified Establishments",
    "sg:phone":"+33 4 77 53 61 41",
    "sg:province":"Rhone-Alpes",
    "wof:name":"Rascle Et Lorenzi S.a.",
    "wof:placetype":"venue"
},
  "geometry": {"coordinates":[4.450189,45.490181],"type":"Point"}
}