{
  "type": "Feature",
  "properties": {
    "addr:full":"B.P. 930 Tarbes C\u00e9dex^^65000 Tarbes Midi Pyr\u00e9n\u00e9es 65009",
    "addr:housenumber":"b.p. 930",
    "addr:postcode":"65009",
    "iso:country":"FR",
    "sg:address":"B.P. 930",
    "sg:city":"Tarbes C\u00e9dex^^65000 Tarbes",
    "sg:orig_category":"Non-Classified Establishments",
    "sg:phone":"+33 5 62 41 73 00",
    "sg:postcode":"65009",
    "sg:province":"Midi Pyr\u00e9n\u00e9es",
    "wof:name":"Socata S.a.",
    "wof:placetype":"venue"
},
  "geometry": {"coordinates":[0.073125,43.230011],"type":"Point"}
}