{
  "type": "Feature",
  "properties": {
    "iso:country":"FR",
    "sg:address":"Route De Laval 35500 Vitre",
    "sg:city":"Vitr\u00e9",
    "sg:classifiers":[
        {
            "category":"Home & Garden",
            "subcategory":"Furniture",
            "type":"Retail Goods"
        }
    ],
    "sg:phone":"+33 2 99 75 04 31",
    "sg:postcode":"35500",
    "sg:province":"Bretagne",
    "sg:tags":[
        "household",
        "wood"
    ],
    "wof:name":"Meubles Andre Bazin Sa",
    "wof:placetype":"venue"
},
  "geometry": {"coordinates":[-1.181169,48.121326],"type":"Point"}
}