{
  "type": "Feature",
  "properties": {
    "addr:full":"10 - 1, Rue Latt\u00e9ral, 92051 Courbevoie C\u00e9dex Courbevoie Ile de France 92400",
    "addr:housenumber":"1",
    "addr:postcode":"92051;92400",
    "addr:street":"10;Rue Latte\u0301Ral",
    "iso:country":"FR",
    "sg:address":"10 - 1, Rue Latt\u00e9ral, 92051 Courbevoie C\u00e9dex",
    "sg:city":"Courbevoie",
    "sg:orig_category":"Non-Classified Establishments",
    "sg:phone":"+33 1 41 16 31 40",
    "sg:postcode":"92400",
    "sg:province":"Ile de France",
    "wof:name":"S\u00e9curicor Valeurs",
    "wof:placetype":"venue"
},
  "geometry": {"coordinates":[-117.38054700000001,33.19717],"type":"Point"}
}