{
  "type": "Feature",
  "properties": {
    "iso:country":"FR",
    "sg:address":"5/7, Rue des Lyanes, 75020 Paris",
    "sg:orig_category":"Unclassifiable Establishments",
    "sg:phone":"+33 1 40 31 57 17",
    "sg:province":"Ile de France",
    "wof:name":"Les Impressions Offset S.a.",
    "wof:placetype":"venue"
},
  "geometry": {"coordinates":[2.406047,48.862816],"type":"Point"}
}