{
  "type": "Feature",
  "properties": {
    "iso:country":"FR",
    "sg:address":"29 blvd de Vanteaux; Limoges; 87000",
    "sg:classifiers":[
        {
            "category":"Banks & Credit Unions",
            "subcategory":"Bank",
            "type":"Services"
        }
    ],
    "sg:phone":"+33 5 55 05 75 50",
    "sg:postcode":"87000",
    "sg:province":"Limousin",
    "wof:name":"Cr\u00e9dit Agricole, Centre-ouest",
    "wof:placetype":"venue"
},
  "geometry": {"coordinates":[1.234331,45.822975],"type":"Point"}
}