{
  "type": "Feature",
  "properties": {
    "iso:country":"FR",
    "sg:address":"10, Rue Saint Just, 93100 Montreuil",
    "sg:orig_category":"Unclassifiable Establishments",
    "sg:phone":"+33 1 42 87 89 00",
    "sg:province":"Ile de France",
    "wof:name":"Laboratoire Bioryl S.a.r.l.",
    "wof:placetype":"venue"
},
  "geometry": {"coordinates":[2.454006,48.863701],"type":"Point"}
}