{
  "type": "Feature",
  "properties": {
    "addr:full":"Rue De La Baume 70190 Beaumotte Aubertans Franche Comt\u00e9 70190",
    "addr:postcode":"70190;70190",
    "addr:street":"Rue De La Baume;Franche Comte\u0301",
    "iso:country":"FR",
    "sg:address":"Rue De La Baume 70190 Beaumotte Aubertans",
    "sg:classifiers":[
        {
            "category":"Transit Center",
            "subcategory":"Freight",
            "type":"Transportation"
        }
    ],
    "sg:phone":"+33 3 84 68 31 31",
    "sg:postcode":"70190",
    "sg:province":"Franche Comt\u00e9",
    "sg:tags":[
        "metallurgy",
        "pipe",
        "metalworking",
        "sheet"
    ],
    "wof:name":"Gindro Sa",
    "wof:placetype":"venue"
},
  "geometry": {"coordinates":[6.17886,47.419346],"type":"Point"}
}