{
  "type": "Feature",
  "properties": {
    "addr:full":"5, Square michelet, 95100 Argenteuil Ile de France",
    "addr:housenumber":"5",
    "addr:postcode":"95100;ile",
    "addr:street":"Square Michelet",
    "iso:country":"FR",
    "sg:address":"5, Square michelet, 95100 Argenteuil",
    "sg:orig_category":"Non-Classified Establishments",
    "sg:phone":"+33 1 39 47 11 33",
    "sg:province":"Ile de France",
    "wof:name":"S.t.s. S.a.",
    "wof:placetype":"venue"
},
  "geometry": {"coordinates":[2.252645,48.947418],"type":"Point"}
}