{
  "type": "Feature",
  "properties": {
    "iso:country":"FR",
    "sg:address":"11 bis, Chemin Malep\u00e8re, 31400 Toulouse",
    "sg:orig_category":"Unclassifiable Establishments",
    "sg:phone":"+33 5 62 16 25 00",
    "sg:province":"Midi Pyr\u00e9n\u00e9es",
    "wof:name":"Cl\u00f4tures Plus S.a.r.l.",
    "wof:placetype":"venue"
},
  "geometry": {"coordinates":[1.503004,43.561958],"type":"Point"}
}