{
  "type": "Feature",
  "properties": {
    "iso:country":"FR",
    "sg:address":"11 rue du G\u00e9n\u00e9ral Bernard 57170 CHATEAU SALINS",
    "sg:classifiers":[
        {
            "category":"Food & Beverages",
            "subcategory":"Dairy",
            "type":"Retail Goods"
        }
    ],
    "sg:phone":"+33 3 87 05 16 86",
    "sg:postcode":"57170",
    "sg:province":"Lorraine",
    "sg:tags":[
        "product",
        "milk"
    ],
    "wof:name":"Est Distribution Biogam S.a.r.l.",
    "wof:placetype":"venue"
},
  "geometry": {"coordinates":[6.50625,48.82196],"type":"Point"}
}