{
  "type": "Feature",
  "properties": {
    "iso:country":"FR",
    "sg:address":"258, Rue Pascal - ZI de Vaux le Penil, 77000 Melun",
    "sg:orig_category":"Unclassifiable Establishments",
    "sg:phone":"+33 1 64 83 52 00",
    "sg:province":"Ile de France",
    "wof:name":"Ppc Fournier S.a.s. - Pigments Pr\u00e9parations Colorants Fournier",
    "wof:placetype":"venue"
},
  "geometry": {"coordinates":[2.664085,48.539577],"type":"Point"}
}