{
  "type": "Feature",
  "properties": {
    "addr:full":"Zone artisanale 74250 Viuz En Sallaz Rhone-Alpes 74250",
    "addr:postcode":"74250;74250",
    "addr:street":"Zone Artisanale",
    "iso:country":"FR",
    "sg:address":"Zone artisanale 74250 Viuz En Sallaz",
    "sg:orig_category":"Fine Wire Coils",
    "sg:phone":"+33 4 50 36 80 20",
    "sg:postcode":"74250",
    "sg:province":"Rhone-Alpes",
    "wof:name":"Gavard Sa",
    "wof:placetype":"venue"
},
  "geometry": {"coordinates":[6.41043,46.147919],"type":"Point"}
}