{
  "type": "Feature",
  "properties": {
    "addr:full":"B.P. 55, 67017 Strasbourg C\u00e9dex^^2, Rue de Dunkerque, 67000 Strasbourg Strasbourg Alsace 67000",
    "addr:postcode":"67017;67000;67000",
    "addr:street":"B.P. 55;Rue De Dunkerque",
    "iso:country":"FR",
    "sg:address":"B.P. 55, 67017 Strasbourg C\u00e9dex^^2, Rue de Dunkerque, 67000 Strasbourg",
    "sg:city":"Strasbourg",
    "sg:orig_category":"Non-Classified Establishments",
    "sg:phone":"+33 3 88 45 59 59",
    "sg:postcode":"67000",
    "sg:province":"Alsace",
    "wof:name":"Brill S.a.",
    "wof:placetype":"venue"
},
  "geometry": {"coordinates":[7.73643,48.585079],"type":"Point"}
}