{
  "type": "Feature",
  "properties": {
    "addr:full":"Z.I. de Marches Castelsarrasin Midi Pyr\u00e9n\u00e9es 82100",
    "addr:postcode":"82100",
    "addr:street":"Z.I. De Marches",
    "iso:country":"FR",
    "sg:address":"Z.I. de Marches",
    "sg:city":"Castelsarrasin",
    "sg:orig_category":"Non-Classified Establishments",
    "sg:phone":"+33 5 63 32 59 60",
    "sg:postcode":"82100",
    "sg:province":"Midi Pyr\u00e9n\u00e9es",
    "wof:name":"S.e.r.p. S.a.r.l. - Soci\u00e9t\u00e9 D'etudes Recherches Produits",
    "wof:placetype":"venue"
},
  "geometry": {"coordinates":[1.109529,43.941746],"type":"Point"}
}