{
  "type": "Feature",
  "properties": {
    "addr:full":"Lotissement Tes De Pachins 12220 Vaureilles Midi Pyr\u00e9n\u00e9es 12220",
    "addr:postcode":"12220;12220",
    "addr:street":"Lotissement Tes De Pachins",
    "iso:country":"FR",
    "sg:address":"Lotissement Tes De Pachins 12220 Vaureilles",
    "sg:classifiers":[
        {
            "category":"Professional",
            "subcategory":"Engineering",
            "type":"Services"
        }
    ],
    "sg:phone":"+33 5 65 80 63 53",
    "sg:postcode":"12220",
    "sg:province":"Midi Pyr\u00e9n\u00e9es",
    "sg:tags":[
        "machine",
        "-",
        "mechanical"
    ],
    "wof:name":"Calmettes Froid Climatisation (cfc)",
    "wof:placetype":"venue"
},
  "geometry": {"coordinates":[2.183452,44.460461],"type":"Point"}
}