{
  "type": "Feature",
  "properties": {
    "addr:full":"B.P. 3 Vocance^^Les Tr\u00e9vottes 07690 Vocance Rhone-Alpes 07690",
    "addr:postcode":"07690;07690",
    "addr:street":"B.P. 3 Vocance^^Les Tre\u0301Vottes;Rhone-Alpes",
    "iso:country":"FR",
    "sg:address":"B.P. 3",
    "sg:city":"Vocance^^Les Tr\u00e9vottes 07690 Vocance",
    "sg:orig_category":"Non-Classified Establishments",
    "sg:phone":"+33 4 75 34 69 09",
    "sg:postcode":"07690",
    "sg:province":"Rhone-Alpes",
    "wof:name":"Andance Textiles & Cr\u00e9ations S.a.s.",
    "wof:placetype":"venue"
},
  "geometry": {"coordinates":[4.52175,45.198303],"type":"Point"}
}