{
  "type": "Feature",
  "properties": {
    "addr:full":"3, Place Sterling, 40140 Soustons Soustons Aquitaine 40140",
    "addr:housenumber":"3",
    "addr:postcode":"40140;40140",
    "addr:street":"Place",
    "iso:country":"FR",
    "sg:address":"3, Place Sterling, 40140 Soustons",
    "sg:city":"Soustons",
    "sg:orig_category":"Unclassifiable Establishments",
    "sg:phone":"+33 5 58 41 30 11",
    "sg:postcode":"40140",
    "sg:province":"Aquitaine",
    "wof:name":"Christian B\u00e9gards S.a.r.l.",
    "wof:placetype":"venue"
},
  "geometry": {"coordinates":[-1.328829,43.751373],"type":"Point"}
}