{
  "type": "Feature",
  "properties": {
    "iso:country":"FR",
    "sg:address":"14 Rue Gervais 16000 Angouleme",
    "sg:classifiers":[
        {
            "category":"Wholesale",
            "subcategory":"Medical Equipment & Supplies",
            "type":"Manufacturing & Wholesale Goods"
        }
    ],
    "sg:phone":"+33 5 45 95 18 23",
    "sg:postcode":"16000",
    "sg:province":"Poitou-Charentes",
    "sg:tags":[
        "instrument",
        "health",
        "-",
        "precision"
    ],
    "wof:name":"Laboratoire Gouttebroze",
    "wof:placetype":"venue"
},
  "geometry": {"coordinates":[0.171921,45.650002],"type":"Point"}
}