{
  "type": "Feature",
  "properties": {
    "iso:country":"FR",
    "sg:address":"995, Rue du Coin, 74970 Marignier",
    "sg:orig_category":"Unclassifiable Establishments",
    "sg:phone":"+33 4 50 34 64 53",
    "sg:province":"Rhone-Alpes",
    "wof:name":"S.g.r.o. Et Associ\u00e9s S.a.r.l.",
    "wof:placetype":"venue"
},
  "geometry": {"coordinates":[6.50417,46.080959],"type":"Point"}
}