{
  "type": "Feature",
  "properties": {
    "addr:full":"81 Rue La Bo\u00e9tie 75008 Paris Ile de France 75008",
    "addr:housenumber":"81",
    "addr:postcode":"75008;75008",
    "addr:street":"Rue La Boe\u0301Tie",
    "iso:country":"FR",
    "sg:address":"81 Rue La Bo\u00e9tie 75008 Paris",
    "sg:classifiers":[
        {
            "category":"Travel",
            "subcategory":"Hotels & Motels",
            "type":"Entertainment"
        }
    ],
    "sg:phone":"+33 1 42 25 56 54",
    "sg:postcode":"75008",
    "sg:province":"Ile de France",
    "sg:tags":[
        "hotels",
        "business",
        "restaurant"
    ],
    "wof:name":"Hotel La Boetie",
    "wof:placetype":"venue"
},
  "geometry": {"coordinates":[2.308738,48.871864],"type":"Point"}
}