{
  "type": "Feature",
  "properties": {
    "iso:country":"FR",
    "sg:address":"B.P. 4",
    "sg:city":"Quettreville sur Sienne",
    "sg:orig_category":"Non-Classified Establishments",
    "sg:phone":"+33 2 33 45 91 91",
    "sg:postcode":"50660",
    "sg:province":"Basse Normandie",
    "wof:name":"Soci\u00e9t\u00e9 Ryckeboer S.a.",
    "wof:placetype":"venue"
},
  "geometry": {"coordinates":[-1.468444,48.969688],"type":"Point"}
}