{
  "type": "Feature",
  "properties": {
    "addr:full":"26, Grande Rue, 21120 Di\u00e9nay Di\u00e9nay Bourgogne 21120",
    "addr:housenumber":"26",
    "addr:postcode":"21120;21120",
    "addr:street":"Grande Rue",
    "iso:country":"FR",
    "sg:address":"26, Grande Rue, 21120 Di\u00e9nay",
    "sg:city":"Di\u00e9nay",
    "sg:orig_category":"Unclassifiable Establishments",
    "sg:phone":"+33 3 80 95 02 59",
    "sg:postcode":"21120",
    "sg:province":"Bourgogne",
    "wof:name":"Godet Corderie Industrielle S.a.",
    "wof:placetype":"venue"
},
  "geometry": {"coordinates":[5.069857,47.51907],"type":"Point"}
}