{
  "type": "Feature",
  "properties": {
    "addr:full":"13 Place St Etienne Residence St Etienne 15000 Aurillac Aurillac Auvergne 15000",
    "addr:housenumber":"13",
    "addr:postcode":"15000;15000",
    "addr:street":"Place St;Residence St Etienne",
    "iso:country":"FR",
    "sg:address":"13 Place St Etienne Residence St Etienne 15000 Aurillac",
    "sg:city":"Aurillac",
    "sg:classifiers":[
        {
            "category":"Wholesale",
            "subcategory":"Medical Equipment & Supplies",
            "type":"Manufacturing & Wholesale Goods"
        }
    ],
    "sg:phone":"+33 4 71 48 17 29",
    "sg:postcode":"15000",
    "sg:province":"Auvergne",
    "sg:tags":[
        "instrument",
        "health",
        "-",
        "precision"
    ],
    "wof:name":"Prodent 15 000",
    "wof:placetype":"venue"
},
  "geometry": {"coordinates":[2.44745,44.933022],"type":"Point"}
}