{
  "type": "Feature",
  "properties": {
    "iso:country":"FR",
    "sg:address":"Port Plaisan Moulin Blanc 29200 Brest",
    "sg:city":"Brest",
    "sg:classifiers":[
        {
            "category":"Autos & Motor Vehicles",
            "subcategory":"Boat Sales",
            "type":"Retail Goods"
        }
    ],
    "sg:phone":"+33 2 98 41 43 70",
    "sg:postcode":"29200",
    "sg:province":"Bretagne",
    "sg:tags":[
        "equipment",
        "transport"
    ],
    "wof:name":"Brest Nautic",
    "wof:placetype":"venue"
},
  "geometry": {"coordinates":[-4.436142,48.395187],"type":"Point"}
}