{
  "type": "Feature",
  "properties": {
    "addr:full":"8, Rue Jean Cottin, 75018 Paris Ile de France",
    "addr:housenumber":"8",
    "addr:postcode":"75018",
    "addr:street":"Rue Jean Cottin",
    "iso:country":"FR",
    "sg:address":"8, Rue Jean Cottin, 75018 Paris",
    "sg:orig_category":"Unclassifiable Establishments",
    "sg:phone":"+33 1 42 09 53 96",
    "sg:province":"Ile de France",
    "wof:name":"Varia France S.a.r.l.",
    "wof:placetype":"venue"
},
  "geometry": {"coordinates":[2.361822,48.893764],"type":"Point"}
}