{
  "type": "Feature",
  "properties": {
    "addr:full":"La Croix 87260 Saint Hilaire Bonneval Limousin",
    "addr:postcode":"87260",
    "addr:street":"La Croix",
    "iso:country":"FR",
    "sg:address":"La Croix 87260 Saint Hilaire Bonneval",
    "sg:orig_category":"Unclassifiable Establishments",
    "sg:phone":"+33 5 55 00 60 45",
    "sg:province":"Limousin",
    "wof:name":"Dugenie Entreprise S.a.r.l.",
    "wof:placetype":"venue"
},
  "geometry": {"coordinates":[1.36184,45.711674],"type":"Point"}
}