{
  "type": "Feature",
  "properties": {
    "iso:country":"FR",
    "sg:address":"Zi Pierre Bru Zi Est 85110 Chantonnay",
    "sg:classifiers":[
        {
            "category":"Professional",
            "subcategory":"Engineering",
            "type":"Services"
        }
    ],
    "sg:phone":"+33 2 51 94 35 14",
    "sg:postcode":"85110",
    "sg:province":"Pays de Loire",
    "sg:tags":[
        "machine",
        "-",
        "mechanical"
    ],
    "wof:name":"Sumeg",
    "wof:placetype":"venue"
},
  "geometry": {"coordinates":[-1.048249,46.685089],"type":"Point"}
}