{
  "type": "Feature",
  "properties": {
    "iso:country":"FR",
    "sg:address":"Campredon 09600 La Bastide sur l'Hers",
    "sg:orig_category":"Non-Classified Establishments",
    "sg:phone":"+33 5 61 01 11 09",
    "sg:postcode":"09600",
    "sg:province":"Midi Pyr\u00e9n\u00e9es",
    "wof:name":"Azema Bigou S.a.r.l.",
    "wof:placetype":"venue"
},
  "geometry": {"coordinates":[1.90912,42.955742],"type":"Point"}
}