{
  "type": "Feature",
  "properties": {
    "iso:country":"FR",
    "sg:address":"30 Rue Nationale",
    "sg:city":"Tint\u00e9niac",
    "sg:classifiers":[
        {
            "category":"Banks & Credit Unions",
            "subcategory":"Financial Services",
            "type":"Services"
        }
    ],
    "sg:phone":"+33 2 99 68 16 97",
    "sg:postcode":"35190",
    "sg:province":"Bretagne",
    "sg:tags":[
        "banking",
        "finance",
        "insurance"
    ],
    "wof:name":"C E R G I V Centre D Economie Rurale Et De Gestion D Ille Et Vilaine Ass",
    "wof:placetype":"venue"
},
  "geometry": {"coordinates":[-1.835362,48.328663],"type":"Point"}
}