{
  "type": "Feature",
  "properties": {
    "addr:full":"120 rue Paul Langevin 60740 ST MAXIMIN Picardie 60740",
    "addr:housenumber":"120",
    "addr:postcode":"60740;60740",
    "addr:street":"Rue Paul Langevin",
    "iso:country":"FR",
    "sg:address":"120 rue Paul Langevin 60740 ST MAXIMIN",
    "sg:classifiers":[
        {
            "category":"Organizations",
            "subcategory":"Labor Organization",
            "type":"Services"
        }
    ],
    "sg:phone":"+33 3 44 28 55 80",
    "sg:postcode":"60740",
    "sg:province":"Picardie",
    "sg:tags":[
        "extrusion",
        "dy"
    ],
    "wof:name":"Meca Vernouillet S.a.r.l.",
    "wof:placetype":"venue"
},
  "geometry": {"coordinates":[2.46162,49.24044],"type":"Point"}
}