{
  "type": "Feature",
  "properties": {
    "addr:full":"61, Rue Moulin de Cage, 92230 Gennevilliers Ile de France 92230",
    "addr:housenumber":"61",
    "addr:postcode":"92230;ile;92230",
    "addr:street":"Rue Moulin De Cage;France",
    "iso:country":"FR",
    "sg:address":"61, Rue Moulin de Cage, 92230 Gennevilliers",
    "sg:orig_category":"Non-Classified Establishments",
    "sg:phone":"+33 1 41 47 87 35",
    "sg:postcode":"92230",
    "sg:province":"Ile de France",
    "wof:name":"Enduitelle S.a.r.l.",
    "wof:placetype":"venue"
},
  "geometry": {"coordinates":[2.306285,48.93008],"type":"Point"}
}