{
  "type": "Feature",
  "properties": {
    "iso:country":"FR",
    "sg:address":"Cit\u00e9 de Phalsbourg",
    "sg:city":"Paris",
    "sg:orig_category":"Non-Classified Establishments",
    "sg:phone":"+33 1 43 70 74 74",
    "sg:postcode":"75011",
    "sg:province":"Ile de France",
    "wof:name":"Suisse Imprimerie S.a.r.l.",
    "wof:placetype":"venue"
},
  "geometry": {"coordinates":[2.384577,48.855484],"type":"Point"}
}