{
  "type": "Feature",
  "properties": {
    "iso:country":"FR",
    "sg:address":"Rue Fleming 62400 B\u00e9thune",
    "sg:orig_category":"Miscellaneous Products",
    "sg:phone":"+33 3 21 64 29 42",
    "sg:postcode":"62400",
    "sg:province":"Nord Pas-de-Calais",
    "wof:name":"Decade Eurl",
    "wof:placetype":"venue"
},
  "geometry": {"coordinates":[2.645554,50.544235],"type":"Point"}
}