{
  "type": "Feature",
  "properties": {
    "iso:country":"FR",
    "sg:address":"5 R De Velennes 60510 Bonlier",
    "sg:classifiers":[
        {
            "category":"Manufacturing",
            "subcategory":"Wood Products",
            "type":"Manufacturing & Wholesale Goods"
        }
    ],
    "sg:phone":"+33 3 44 79 20 55",
    "sg:province":"Picardie",
    "sg:tags":[
        "professional",
        "furniture"
    ],
    "wof:name":"M. Bonniec Philippe Presta Service",
    "wof:placetype":"venue"
},
  "geometry": {"coordinates":[2.153398,49.472191],"type":"Point"}
}