{
  "type": "Feature",
  "properties": {
    "addr:full":"2, All\u00e9e de la For\u00eat de la Reine - Technop\u00f4le de Brabois, 54500 Vandoeuvre l\u00e8s Nancy Lorraine",
    "addr:housenumber":"2",
    "addr:postcode":"54500",
    "addr:street":"Alle\u0301E De La Fore\u0302T De La Reine Technopo\u0302Le De Brabois",
    "iso:country":"FR",
    "sg:address":"2, All\u00e9e de la For\u00eat de la Reine - Technop\u00f4le de Brabois, 54500 Vandoeuvre l\u00e8s Nancy",
    "sg:orig_category":"Unclassifiable Establishments",
    "sg:phone":"+33 3 83 44 04 44",
    "sg:province":"Lorraine",
    "wof:name":"J.s.i. S.a. - Jouve Syst\u00e8mes Information",
    "wof:placetype":"venue"
},
  "geometry": {"coordinates":[6.172675,48.659737],"type":"Point"}
}