{
  "type": "Feature",
  "properties": {
    "addr:full":"60, Rue Isa\u00efe Sellier, 80130 Friville Escarbotin Picardie",
    "addr:housenumber":"60",
    "addr:postcode":"80130",
    "addr:street":"Rue Isai\u0308E Sellier",
    "iso:country":"FR",
    "sg:address":"60, Rue Isa\u00efe Sellier, 80130 Friville Escarbotin",
    "sg:orig_category":"Unclassifiable Establishments",
    "sg:phone":"+33 3 22 20 77 88",
    "sg:province":"Picardie",
    "wof:name":"Beauval S.a.",
    "wof:placetype":"venue"
},
  "geometry": {"coordinates":[1.55762,50.092628],"type":"Point"}
}