{
  "type": "Feature",
  "properties": {
    "iso:country":"FR",
    "sg:address":"11, Rue de Verdun, 58640 Varennes Vauzelles",
    "sg:city":"Varennes-Vauzelles",
    "sg:orig_category":"Unclassifiable Establishments",
    "sg:phone":"+33 3 86 93 20 00",
    "sg:postcode":"58640",
    "sg:province":"Bourgogne",
    "wof:name":"Alliance Sant\u00e9 S.a.s.",
    "wof:placetype":"venue"
},
  "geometry": {"coordinates":[3.150774,47.017677],"type":"Point"}
}