{
  "type": "Feature",
  "properties": {
    "addr:full":"Zone A\u00e9ronautique Louis Bourget V\u00e9lizy Villacoublay Ile de France 78140",
    "addr:postcode":"78140",
    "addr:street":"Zone;Louis",
    "iso:country":"FR",
    "sg:address":"Zone A\u00e9ronautique Louis Bourget",
    "sg:city":"V\u00e9lizy Villacoublay",
    "sg:orig_category":"Unclassifiable Establishments",
    "sg:phone":"+33 1 40 83 22 12",
    "sg:postcode":"78140",
    "sg:province":"Ile de France",
    "wof:name":"Dassault Aviation S.a.",
    "wof:placetype":"venue"
},
  "geometry": {"coordinates":[2.18246,48.78503],"type":"Point"}
}