{
  "type": "Feature",
  "properties": {
    "iso:country":"FR",
    "sg:address":"7 Rue De Pacalaire 38170 Seyssinet Pariset",
    "sg:classifiers":[
        {
            "category":"Utilities",
            "subcategory":"Telephone",
            "type":"Services"
        }
    ],
    "sg:phone":"+33 4 76 84 21 21",
    "sg:postcode":"38170",
    "sg:province":"Rhone-Alpes",
    "sg:tags":[
        "telecommunication"
    ],
    "wof:name":"Cie Fran\u00c7aise De Telecommunication Rhone",
    "wof:placetype":"venue"
},
  "geometry": {"coordinates":[5.692732,45.179649],"type":"Point"}
}