{
  "type": "Feature",
  "properties": {
    "addr:full":"Rte De Sarrians 84810 Aubignan Bretagne",
    "addr:postcode":"84810",
    "addr:street":"Rte De Sarrians",
    "iso:country":"FR",
    "sg:address":"Rte De Sarrians 84810 Aubignan",
    "sg:classifiers":[
        {
            "category":"Farming",
            "subcategory":"Livestock Farm",
            "type":"Manufacturing & Wholesale Goods"
        }
    ],
    "sg:phone":"+33 4 90 62 61 30",
    "sg:province":"Bretagne",
    "sg:tags":[
        "agriculture"
    ],
    "wof:name":"Bessac Julien Sarl",
    "wof:placetype":"venue"
},
  "geometry": {"coordinates":[4.993245,44.095451],"type":"Point"}
}