{
  "type": "Feature",
  "properties": {
    "iso:country":"FR",
    "sg:address":"78 Rue Saint-Louis 27000 Ovreux",
    "sg:orig_category":"Miscellaneous Products",
    "sg:phone":"+33 2 32 33 04 00",
    "sg:postcode":"27000",
    "sg:province":"Haute Normandie",
    "wof:name":"Marbrerie Denis Normandie",
    "wof:placetype":"venue"
},
  "geometry": {"coordinates":[-90.198952,38.62759],"type":"Point"}
}