{
  "type": "Feature",
  "properties": {
    "iso:country":"FR",
    "sg:address":"18 Av Fr\u00e8res Roustan 06220 Vallauris",
    "sg:classifiers":[
        {
            "category":"Autos & Motor Vehicles",
            "subcategory":"Boat Sales",
            "type":"Retail Goods"
        }
    ],
    "sg:phone":"+33 4 93 63 06 97",
    "sg:province":"Rhone-Alpes",
    "sg:tags":[
        "equipment",
        "transport"
    ],
    "wof:name":"G Rodriguez Sa",
    "wof:placetype":"venue"
},
  "geometry": {"coordinates":[7.069954,43.563747],"type":"Point"}
}