{
  "type": "Feature",
  "properties": {
    "addr:full":"26, Rue Gabriel Peri, 92110 Clichy Ile de France",
    "addr:housenumber":"26",
    "addr:postcode":"92110",
    "addr:street":"Rue Gabriel Peri;Ile De France",
    "iso:country":"FR",
    "sg:address":"26, Rue Gabriel Peri, 92110 Clichy",
    "sg:orig_category":"Unclassifiable Establishments",
    "sg:phone":"+33 1 41 40 99 00",
    "sg:province":"Ile de France",
    "wof:name":"Itras S.a.",
    "wof:placetype":"venue"
},
  "geometry": {"coordinates":[2.303885,48.907318],"type":"Point"}
}