{
  "type": "Feature",
  "properties": {
    "addr:full":"32 rue de Caumartin 75009 Paris Ile de France",
    "addr:housenumber":"32",
    "addr:postcode":"75009",
    "addr:street":"Rue De Caumartin",
    "iso:country":"FR",
    "sg:address":"32 rue de Caumartin 75009 Paris",
    "sg:classifiers":[
        {
            "category":"Shopping",
            "subcategory":"Beauty & Cosmetics",
            "type":"Retail Goods"
        }
    ],
    "sg:phone":"+33 1 47 42 50 20",
    "sg:province":"Ile de France",
    "sg:tags":[
        "perfume"
    ],
    "wof:name":"Badi Import Export Sarl",
    "wof:placetype":"venue"
},
  "geometry": {"coordinates":[2.328449,48.872681],"type":"Point"}
}