{
  "type": "Feature",
  "properties": {
    "iso:country":"FR",
    "sg:address":"Lieu Dit Querry Pigeon 85440 Talmont St Hilaire",
    "sg:classifiers":[
        {
            "category":"Farming",
            "subcategory":"Livestock Farm",
            "type":"Manufacturing & Wholesale Goods"
        }
    ],
    "sg:phone":"+33 2 51 22 22 22",
    "sg:postcode":"85440",
    "sg:province":"Pays de Loire",
    "sg:tags":[
        "breeding",
        "agriculture",
        "animal"
    ],
    "wof:name":"Cooperative Sud Vendeenne De Conchyliculture (co Su Ve Co)",
    "wof:placetype":"venue"
},
  "geometry": {"coordinates":[-1.666729,46.447823],"type":"Point"}
}