{
  "type": "Feature",
  "properties": {
    "addr:full":"63 Rue De Tavaux 21800 Chevigny St Sauveur Neuilly-l\u00e8s-Dijon Bourgogne 21800",
    "addr:housenumber":"63",
    "addr:postcode":"21800;21800",
    "addr:street":"Rue De Tavaux;Chevigny St;Bourgogne",
    "iso:country":"FR",
    "sg:address":"63 Rue De Tavaux 21800 Chevigny St Sauveur",
    "sg:city":"Neuilly-l\u00e8s-Dijon",
    "sg:classifiers":[
        {
            "category":"Shopping",
            "subcategory":"Computers & Home Electronics",
            "type":"Retail Goods"
        }
    ],
    "sg:phone":"+33 3 80 48 99 71",
    "sg:postcode":"21800",
    "sg:province":"Bourgogne",
    "sg:tags":[
        "electronic",
        "electrical",
        "equipment"
    ],
    "wof:name":"Selecta Safaa",
    "wof:placetype":"venue"
},
  "geometry": {"coordinates":[5.134167,47.28767],"type":"Point"}
}