{
  "type": "Feature",
  "properties": {
    "addr:full":"Rte de la Fl\u00eache Le Lude Pays de Loire 72800",
    "addr:postcode":"72800",
    "addr:street":"Rte De La Fle\u0302Che",
    "iso:country":"FR",
    "sg:address":"Rte de la Fl\u00eache",
    "sg:city":"Le Lude",
    "sg:orig_category":"Unclassifiable Establishments",
    "sg:phone":"+33 2 43 94 63 37",
    "sg:postcode":"72800",
    "sg:province":"Pays de Loire",
    "wof:name":"V\u00eatra S.a.",
    "wof:placetype":"venue"
},
  "geometry": {"coordinates":[0.154635,47.647072],"type":"Point"}
}