{
  "type": "Feature",
  "properties": {
    "iso:country":"FR",
    "sg:address":"lieu dit Apigne 35650 Le Rheu",
    "sg:city":"Le Rheu",
    "sg:classifiers":[
        {
            "category":"Bus Stop",
            "subcategory":"None",
            "type":"Transportation"
        }
    ],
    "sg:phone":"+33 2 99 14 62 33",
    "sg:postcode":"35650",
    "sg:province":"Bretagne",
    "sg:tags":[
        "switch",
        "low-voltage"
    ],
    "wof:name":"Apia - Transitube S.a.",
    "wof:placetype":"venue"
},
  "geometry": {"coordinates":[-1.747104,48.099236],"type":"Point"}
}