{
  "type": "Feature",
  "properties": {
    "addr:full":"54 Rue D Hauteville 75010 Paris Ile de France",
    "addr:housenumber":"54",
    "addr:postcode":"75010",
    "addr:street":"Rue D",
    "iso:country":"FR",
    "sg:address":"54 Rue D Hauteville 75010 Paris",
    "sg:classifiers":[
        {
            "category":"Professional",
            "subcategory":"Printing & Photocopies",
            "type":"Services"
        }
    ],
    "sg:phone":"+33 1 56 03 92 20",
    "sg:province":"Ile de France",
    "sg:tags":[
        "publishing"
    ],
    "wof:name":"Guy Delcourt Productions",
    "wof:placetype":"venue"
},
  "geometry": {"coordinates":[2.350851,48.874313],"type":"Point"}
}