{
  "type": "Feature",
  "properties": {
    "addr:full":"B.P. 1518, 87020 Limoges C\u00e9dex 9^^27/31, Rue Auguste Comt\u00e9 - ZI Nord, 87280 Limoges Limousin",
    "addr:housenumber":"9 ^ ^ 27 / 31",
    "addr:postcode":"87020;87280",
    "addr:street":"B.P. 1518;Ce\u0301Dex;Rue Auguste Comte\u0301 Zi Nord",
    "iso:country":"FR",
    "sg:address":"B.P. 1518, 87020 Limoges C\u00e9dex 9^^27/31, Rue Auguste Comt\u00e9 - ZI Nord, 87280 Limoges",
    "sg:orig_category":"Non-Classified Establishments",
    "sg:phone":"+33 5 55 38 95 70",
    "sg:province":"Limousin",
    "wof:name":"Kdi B\u00e9raud Sudreau S.a.",
    "wof:placetype":"venue"
},
  "geometry": {"coordinates":[1.299435,45.914837],"type":"Point"}
}