{
  "type": "Feature",
  "properties": {
    "iso:country":"FR",
    "sg:address":"37-41, Rue Fernand Pelloutier, 92100 Boulogne Billancourt",
    "sg:orig_category":"Unclassifiable Establishments",
    "sg:phone":"+33 1 55 38 21 21",
    "sg:province":"Ile de France",
    "wof:name":"Global Event System S.a.",
    "wof:placetype":"venue"
},
  "geometry": {"coordinates":[2.234517,48.834103],"type":"Point"}
}