{
  "type": "Feature",
  "properties": {
    "addr:full":"B.P. 6, 67280 Urmatt^^Rue de la Chapelle, 67280 Urmatt Urmatt Alsace 67280",
    "addr:housenumber":"6",
    "addr:postcode":"67280;67280;67280",
    "addr:street":"B.P.;La Chapelle;Urmatt",
    "iso:country":"FR",
    "sg:address":"B.P. 6, 67280 Urmatt^^Rue de la Chapelle, 67280 Urmatt",
    "sg:city":"Urmatt",
    "sg:orig_category":"Non-Classified Establishments",
    "sg:phone":"+33 3 88 97 40 41",
    "sg:postcode":"67280",
    "sg:province":"Alsace",
    "wof:name":"Taglang S.a.",
    "wof:placetype":"venue"
},
  "geometry": {"coordinates":[7.330461,48.549908],"type":"Point"}
}