{
  "type": "Feature",
  "properties": {
    "iso:country":"FR",
    "sg:address":"Rue Joseph Cugnot",
    "sg:city":"De La R\u00e9publique 86062 Poitiers Cedex 9",
    "sg:classifiers":[
        {
            "category":"Banks & Credit Unions",
            "subcategory":"Investment Brokerage",
            "type":"Services"
        }
    ],
    "sg:phone":"+33 5 49 52 76 06",
    "sg:province":"Poitou-Charentes",
    "sg:tags":[
        "industrial",
        "business",
        "advice",
        "equipment",
        "vehicle",
        "transport"
    ],
    "wof:name":"Ets Riondel Vi Sas",
    "wof:placetype":"venue"
},
  "geometry": {"coordinates":[0.34265,46.58699],"type":"Point"}
}