{
  "type": "Feature",
  "properties": {
    "addr:full":"108, Chemin de la Fouillouse, 69800 Saint Priest Rhone-Alpes 69800",
    "addr:housenumber":"108",
    "addr:postcode":"69800;69800",
    "addr:street":"Chemin De La Fouillouse;Priest Rhone-Alpes",
    "iso:country":"FR",
    "sg:address":"108, Chemin de la Fouillouse, 69800 Saint Priest",
    "sg:orig_category":"Non-Classified Establishments",
    "sg:phone":"+33 4 78 20 50 87",
    "sg:postcode":"69800",
    "sg:province":"Rhone-Alpes",
    "wof:name":"Denis Carron Paysages S.a.r.l.",
    "wof:placetype":"venue"
},
  "geometry": {"coordinates":[4.961541,45.684601],"type":"Point"}
}