{
  "type": "Feature",
  "properties": {
    "iso:country":"FR",
    "sg:address":"57 Rue De La Mairie 59147 Chemy",
    "sg:orig_category":"Food and Related Products Food processing - machinery and equipment Meats and cooked meat Mechanical",
    "sg:phone":"+33 3 20 90 32 52",
    "sg:postcode":"59147",
    "sg:province":"Nord Pas-de-Calais",
    "wof:name":"Etablissements Lesage Et Fils Sa",
    "wof:placetype":"venue"
},
  "geometry": {"coordinates":[2.990613,50.530167],"type":"Point"}
}