{
  "type": "Feature",
  "properties": {
    "iso:country":"FR",
    "sg:address":"B.P. 4, 73330 Le Pont de Beauvoisin^^ZI de la Baronnie, 73330 Le Pont de Beauvoisin",
    "sg:orig_category":"Non-Classified Establishments",
    "sg:phone":"+33 4 76 32 81 20",
    "sg:province":"Rhone-Alpes",
    "wof:name":"Favotex S.a.",
    "wof:placetype":"venue"
},
  "geometry": {"coordinates":[5.709858,45.536922],"type":"Point"}
}