{
  "type": "Feature",
  "properties": {
    "addr:full":"94, Av. des Cantini\u00e8res, 38300 Ruy Rhone-Alpes 38300",
    "addr:postcode":"38300;38300",
    "addr:street":"94 Av. Des Cantinie\u0300Res;Ruy Rhone-Alpes",
    "iso:country":"FR",
    "sg:address":"94, Av. des Cantini\u00e8res, 38300 Ruy",
    "sg:orig_category":"Unclassifiable Establishments",
    "sg:phone":"+33 4 74 93 38 10",
    "sg:postcode":"38300",
    "sg:province":"Rhone-Alpes",
    "wof:name":"C.r.n.c. S.a. - Cherry Rocher Neyret Chavin",
    "wof:placetype":"venue"
},
  "geometry": {"coordinates":[5.296311,45.591961],"type":"Point"}
}