{
  "type": "Feature",
  "properties": {
    "addr:full":"Le Pr\u00e9s Brun Marches Rhone-Alpes 26300",
    "addr:postcode":"26300",
    "addr:street":"Le",
    "iso:country":"FR",
    "sg:address":"Le Pr\u00e9s Brun",
    "sg:city":"Marches",
    "sg:orig_category":"Unclassifiable Establishments",
    "sg:phone":"+33 4 75 47 16 80",
    "sg:postcode":"26300",
    "sg:province":"Rhone-Alpes",
    "wof:name":"E.a.i. D\u00e9marreurs S.a.r.l.",
    "wof:placetype":"venue"
},
  "geometry": {"coordinates":[5.10596,44.982792],"type":"Point"}
}