{
  "type": "Feature",
  "properties": {
    "iso:country":"FR",
    "sg:address":"Samsara 84220 Roussillon",
    "sg:classifiers":[
        {
            "category":"Professional",
            "subcategory":"Printing & Photocopies",
            "type":"Services"
        }
    ],
    "sg:phone":"+33 4 90 05 64 95",
    "sg:province":"Provence-Alpes-C\u00f4te d'Azur",
    "sg:tags":[
        "publishing"
    ],
    "wof:name":"Finev",
    "wof:placetype":"venue"
},
  "geometry": {"coordinates":[5.201208,43.858566],"type":"Point"}
}