{
  "type": "Feature",
  "properties": {
    "addr:full":"Rue d'Ossau - ZI Berlanne Morla\u00e0s Aquitaine 64160",
    "addr:postcode":"64160",
    "addr:street":"Rue D'Ossau Zi Berlanne",
    "iso:country":"FR",
    "sg:address":"Rue d'Ossau - ZI Berlanne",
    "sg:city":"Morla\u00e0s",
    "sg:orig_category":"Unclassifiable Establishments",
    "sg:phone":"+33 5 59 02 50 68",
    "sg:postcode":"64160",
    "sg:province":"Aquitaine",
    "wof:name":"Sonovision-itep S.a.",
    "wof:placetype":"venue"
},
  "geometry": {"coordinates":[-0.303239,43.328445],"type":"Point"}
}