{
  "type": "Feature",
  "properties": {
    "addr:full":"172 Rue Auguste Potie 59320 Haubourdin Nord Pas-de-Calais 59320",
    "addr:housenumber":"172",
    "addr:postcode":"59320;59320",
    "addr:street":"Rue Auguste Potie",
    "iso:country":"FR",
    "sg:address":"172 Rue Auguste Potie 59320 Haubourdin",
    "sg:classifiers":[
        {
            "category":"Transit Center",
            "subcategory":"Freight",
            "type":"Transportation"
        }
    ],
    "sg:phone":"+33 3 20 17 24 24",
    "sg:postcode":"59320",
    "sg:province":"Nord Pas-de-Calais",
    "sg:tags":[
        "metallurgy",
        "pipe",
        "metalworking",
        "sheet"
    ],
    "wof:name":"Toltec",
    "wof:placetype":"venue"
},
  "geometry": {"coordinates":[2.99678,50.61026],"type":"Point"}
}