{
  "type": "Feature",
  "properties": {
    "iso:country":"FR",
    "sg:address":"B.P. 35, 68600 Neuf Brisach^^Zone Industrielle de Biesheim, 68600 Neuf Brisach",
    "sg:city":"Biesheim",
    "sg:orig_category":"Non-Classified Establishments",
    "sg:phone":"+33 3 89 72 77 78",
    "sg:postcode":"68600",
    "sg:province":"Alsace",
    "wof:name":"Rhenaroll S.a.",
    "wof:placetype":"venue"
},
  "geometry": {"coordinates":[7.552925,48.01693],"type":"Point"}
}