{
  "type": "Feature",
  "properties": {
    "addr:full":"ZI de Tauxigny 37310 REIGNAC SUR INDRE Tauxigny Centre 37310",
    "addr:postcode":"37310;37310",
    "addr:street":"Zi De Tauxigny",
    "iso:country":"FR",
    "sg:address":"ZI de Tauxigny 37310 REIGNAC SUR INDRE",
    "sg:city":"Tauxigny",
    "sg:classifiers":[
        {
            "category":"Banks & Credit Unions",
            "subcategory":"Investment Brokerage",
            "type":"Services"
        }
    ],
    "sg:phone":"+33 2 47 34 63 46",
    "sg:postcode":"37310",
    "sg:province":"Centre",
    "sg:tags":[
        "parabolic",
        "dish",
        "antenna"
    ],
    "wof:name":"Metronic Sas",
    "wof:placetype":"venue"
},
  "geometry": {"coordinates":[0.91251,47.227829],"type":"Point"}
}