{
  "type": "Feature",
  "properties": {
    "addr:full":"Zi Evre Et Loire 49600 Beaupr\u00e9au Pays de Loire",
    "addr:postcode":"49600",
    "addr:street":"Beaupre\u0301Au",
    "iso:country":"FR",
    "sg:address":"Zi Evre Et Loire 49600 Beaupr\u00e9au",
    "sg:classifiers":[
        {
            "category":"Professional",
            "type":"Services"
        }
    ],
    "sg:phone":"+33 2 41 63 06 11",
    "sg:province":"Pays de Loire",
    "sg:tags":[
        "transport",
        "road"
    ],
    "wof:name":"Ripoche Transports Sarl",
    "wof:placetype":"venue"
},
  "geometry": {"coordinates":[-0.992154,47.201691],"type":"Point"}
}