{
  "type": "Feature",
  "properties": {
    "addr:full":"Z I 08350 DONCHERY Vrigne-Meuse Champagne 08350",
    "addr:postcode":"08350;08350",
    "addr:street":"Z;Champagne",
    "iso:country":"FR",
    "sg:address":"Z I 08350 DONCHERY",
    "sg:city":"Vrigne-Meuse",
    "sg:classifiers":[
        {
            "category":"Manufacturing",
            "subcategory":"Rubber & Plastics",
            "type":"Manufacturing & Wholesale Goods"
        }
    ],
    "sg:phone":"+33 3 24 27 75 80",
    "sg:postcode":"08350",
    "sg:province":"Champagne",
    "sg:tags":[
        "material"
    ],
    "wof:name":"Spartech Polycom Et Inc Sas",
    "wof:placetype":"venue"
},
  "geometry": {"coordinates":[4.88706,49.692299],"type":"Point"}
}