{
  "type": "Feature",
  "properties": {
    "addr:full":"9 Rue Jacob Meyer Les Cedres Strasbourg Alsace 67200",
    "addr:housenumber":"9",
    "addr:postcode":"67200",
    "addr:street":"Rue Jacob Meyer",
    "iso:country":"FR",
    "sg:address":"9 Rue Jacob Meyer Les Cedres",
    "sg:city":"Strasbourg",
    "sg:classifiers":[
        {
            "category":"Banks & Credit Unions",
            "subcategory":"Financial Services",
            "type":"Services"
        }
    ],
    "sg:phone":"+33 3 88 77 79 88",
    "sg:postcode":"67200",
    "sg:province":"Alsace",
    "sg:tags":[
        "banking",
        "finance",
        "insurance"
    ],
    "wof:name":"Adp Gsi",
    "wof:placetype":"venue"
},
  "geometry": {"coordinates":[7.71425,48.578671],"type":"Point"}
}