{
  "type": "Feature",
  "properties": {
    "iso:country":"FR",
    "sg:address":"17, Rue de la Batardi\u00e8re, 45140 Saint Jean de la Ruelle",
    "sg:city":"Ingr\u00e9",
    "sg:orig_category":"Non-Classified Establishments",
    "sg:phone":"+33 803 84 50 00",
    "sg:postcode":"45140",
    "sg:province":"Centre",
    "wof:name":"Audas Distribution S.a.",
    "wof:placetype":"venue"
},
  "geometry": {"coordinates":[1.86761,47.90799],"type":"Point"}
}