{
  "type": "Feature",
  "properties": {
    "addr:full":"ZI de Campagnac L\u00e9dat Aquitaine 47300",
    "addr:postcode":"47300",
    "addr:street":"Zi De Campagnac",
    "iso:country":"FR",
    "sg:address":"ZI de Campagnac",
    "sg:city":"L\u00e9dat",
    "sg:orig_category":"Unclassifiable Establishments",
    "sg:phone":"+33 5 53 70 28 27",
    "sg:postcode":"47300",
    "sg:province":"Aquitaine",
    "wof:name":"Publitiss E.u.r.l.",
    "wof:placetype":"venue"
},
  "geometry": {"coordinates":[0.669185,44.455551],"type":"Point"}
}