{
  "type": "Feature",
  "properties": {
    "addr:full":"Les Aubuis 37500 Chinon Chinon Centre 37500",
    "addr:postcode":"37500;37500",
    "addr:street":"Chinon",
    "iso:country":"FR",
    "sg:address":"Les Aubuis 37500 Chinon",
    "sg:city":"Chinon",
    "sg:orig_category":"Unclassifiable Establishments",
    "sg:phone":"+33 2 47 93 42 70",
    "sg:postcode":"37500",
    "sg:province":"Centre",
    "wof:name":"Sicavira",
    "wof:placetype":"venue"
},
  "geometry": {"coordinates":[0.210205,47.170437],"type":"Point"}
}