{
  "type": "Feature",
  "properties": {
    "addr:full":"All\u00e9e de la Grange Magnien P\u00e9ronnas Rhone-Alpes 01960",
    "addr:postcode":"01960",
    "addr:street":"Alle\u0301E De La Grange;Rhone-Alpes",
    "iso:country":"FR",
    "sg:address":"All\u00e9e de la Grange Magnien",
    "sg:city":"P\u00e9ronnas",
    "sg:orig_category":"Non-Classified Establishments",
    "sg:phone":"+33 4 74 32 87 50",
    "sg:postcode":"01960",
    "sg:province":"Rhone-Alpes",
    "wof:name":"P.s.i. S.a. - Proc\u00e9d\u00e9 Syst\u00e8me Ing\u00e9nierie",
    "wof:placetype":"venue"
},
  "geometry": {"coordinates":[5.210562,46.176414],"type":"Point"}
}