{
  "type": "Feature",
  "properties": {
    "addr:full":"73 rte des Romains; Strasbourg; 67034 Strasbourg Alsace 67000",
    "addr:housenumber":"73",
    "addr:postcode":"67034;67000",
    "addr:street":"Rte Des Romains",
    "iso:country":"FR",
    "sg:address":"73 rte des Romains; Strasbourg; 67034",
    "sg:city":"Strasbourg",
    "sg:classifiers":[
        {
            "category":"Banks & Credit Unions",
            "subcategory":"Bank",
            "type":"Services"
        }
    ],
    "sg:phone":"+33 3 88 29 44 00",
    "sg:postcode":"67000",
    "sg:province":"Alsace",
    "wof:name":"Cr\u00e9dit Industriel D'alsace, Et De Lorraine Sa",
    "wof:placetype":"venue"
},
  "geometry": {"coordinates":[7.712129,48.578873],"type":"Point"}
}