{
  "type": "Feature",
  "properties": {
    "iso:country":"FR",
    "sg:address":"Rue de la Tuilerie",
    "sg:city":"Balma",
    "sg:orig_category":"Non-Classified Establishments",
    "sg:phone":"+33 5 61 61 10 40",
    "sg:postcode":"31130",
    "sg:province":"Midi Pyr\u00e9n\u00e9es",
    "wof:name":"Ch\u00e8que De Table S.a.",
    "wof:placetype":"venue"
},
  "geometry": {"coordinates":[1.486138,43.62928],"type":"Point"}
}