{
  "type": "Feature",
  "properties": {
    "addr:full":"Impasse Rouge-Coq Le Meix Saint Epoing Champagne 51120",
    "addr:postcode":"51120",
    "addr:street":"Impasse Rouge-Coq;Champagne",
    "iso:country":"FR",
    "sg:address":"Impasse Rouge-Coq",
    "sg:city":"Le Meix Saint Epoing",
    "sg:orig_category":"Non-Classified Establishments",
    "sg:phone":"+33 3 26 42 81 81",
    "sg:postcode":"51120",
    "sg:province":"Champagne",
    "wof:name":"Schumer Menuiserie S.a.",
    "wof:placetype":"venue"
},
  "geometry": {"coordinates":[3.652444,48.703438],"type":"Point"}
}