{
  "type": "Feature",
  "properties": {
    "addr:full":"13 rue de la Ferronnerie; Dinan; 22100 Dinan Bretagne 22100",
    "addr:housenumber":"13",
    "addr:postcode":"22100;22100",
    "addr:street":"Rue De La Ferronnerie;Bretagne",
    "iso:country":"FR",
    "sg:address":"13 rue de la Ferronnerie; Dinan; 22100",
    "sg:city":"Dinan",
    "sg:classifiers":[
        {
            "category":"Banks & Credit Unions",
            "subcategory":"Bank",
            "type":"Services"
        }
    ],
    "sg:phone":"+33 3396394304",
    "sg:postcode":"22100",
    "sg:province":"Bretagne",
    "wof:name":"Soci\u00e9t\u00e9 G\u00e9n\u00e9rale",
    "wof:placetype":"venue"
},
  "geometry": {"coordinates":[-2.04561,48.453426],"type":"Point"}
}