{
  "type": "Feature",
  "properties": {
    "addr:full":"75 rue de Strasbourg 94150 Rungis Ile de France 94150",
    "addr:housenumber":"75",
    "addr:postcode":"94150;94150",
    "addr:street":"Rue De Strasbourg",
    "iso:country":"FR",
    "sg:address":"75 rue de Strasbourg 94150 Rungis",
    "sg:classifiers":[
        {
            "category":"Food & Beverages",
            "subcategory":"Meat & Fish",
            "type":"Retail Goods"
        }
    ],
    "sg:phone":"+33 1 46 75 05 19",
    "sg:postcode":"94150",
    "sg:province":"Ile de France",
    "sg:tags":[
        "sausage",
        "cured",
        "product",
        "dried"
    ],
    "wof:name":"Ets Vandekerckhove (vdk) S.a.r.l.",
    "wof:placetype":"venue"
},
  "geometry": {"coordinates":[2.357485,48.759331],"type":"Point"}
}