{
  "type": "Feature",
  "properties": {
    "addr:full":"La Maladi\u00e8re 42580 La Tour en Jarez Rhone-Alpes 42580",
    "addr:housenumber":"42580",
    "addr:postcode":"42580",
    "addr:street":"Rhone-Alpes",
    "iso:country":"FR",
    "sg:address":"La Maladi\u00e8re 42580 La Tour en Jarez",
    "sg:orig_category":"Non-Classified Establishments",
    "sg:phone":"+33 4 77 92 99 11",
    "sg:postcode":"42580",
    "sg:province":"Rhone-Alpes",
    "wof:name":"Airmat S.a.r.l.",
    "wof:placetype":"venue"
},
  "geometry": {"coordinates":[4.392824,45.481125],"type":"Point"}
}