{
  "type": "Feature",
  "properties": {
    "addr:full":"154, Av. du Brezet, 63100 Clermont Ferrand Clermont-Ferrand Auvergne 63100",
    "addr:postcode":"63100;63100",
    "addr:street":"154 Av. Du Brezet",
    "iso:country":"FR",
    "sg:address":"154, Av. du Brezet, 63100 Clermont Ferrand",
    "sg:city":"Clermont-Ferrand",
    "sg:orig_category":"Unclassifiable Establishments",
    "sg:phone":"+33 4 73 42 67 67",
    "sg:postcode":"63100",
    "sg:province":"Auvergne",
    "wof:name":"Areste Informatique S.a.",
    "wof:placetype":"venue"
},
  "geometry": {"coordinates":[3.135245,45.77948],"type":"Point"}
}