{
  "type": "Feature",
  "properties": {
    "iso:country":"FR",
    "sg:address":"83570 Cotignac",
    "sg:orig_category":"Non-Classified Establishments",
    "sg:phone":"+33 4 94 04 60 04",
    "sg:province":"Midi Pyr\u00e9n\u00e9es",
    "wof:name":"Coop\u00e9rative Agricole Les Vignerons De Cotignac S.c.a.",
    "wof:placetype":"venue"
},
  "geometry": {"coordinates":[6.149938,43.524582],"type":"Point"}
}