{
  "type": "Feature",
  "properties": {
    "addr:full":"15 Rue Des Fontaines 56100 Lorient Lorient Bretagne 56100",
    "addr:housenumber":"15",
    "addr:postcode":"56100;56100",
    "addr:street":"Rue Des Fontaines",
    "iso:country":"FR",
    "sg:address":"15 Rue Des Fontaines 56100 Lorient",
    "sg:city":"Lorient",
    "sg:classifiers":[
        {
            "category":"Shopping",
            "subcategory":"Crafts & Fabrics",
            "type":"Retail Goods"
        }
    ],
    "sg:phone":"+33 2 97 64 28 48",
    "sg:postcode":"56100",
    "sg:province":"Bretagne",
    "sg:tags":[
        "textile",
        "linen",
        "clothing"
    ],
    "wof:name":"Tissus Duret",
    "wof:placetype":"venue"
},
  "geometry": {"coordinates":[-3.383309,47.738914],"type":"Point"}
}