{
  "type": "Feature",
  "properties": {
    "iso:country":"FR",
    "sg:address":"35 Rue Pleyel 93200 St Denis",
    "sg:classifiers":[
        {
            "category":"Wholesale",
            "subcategory":"Machinery & Supplies",
            "type":"Manufacturing & Wholesale Goods"
        }
    ],
    "sg:phone":"+33 1 48 13 25 50",
    "sg:province":"Ile de France",
    "sg:tags":[
        "equipment",
        "optical",
        "precision",
        "instrument"
    ],
    "wof:name":"Panavision Alga - Paris",
    "wof:placetype":"venue"
},
  "geometry": {"coordinates":[2.343584,48.920967],"type":"Point"}
}