{
  "type": "Feature",
  "properties": {
    "iso:country":"FR",
    "sg:address":"174 Quai De Jemmapes 75010 Paris",
    "sg:classifiers":[
        {
            "category":"Shopping",
            "type":"Retail Goods"
        }
    ],
    "sg:phone":"+33 1 42 03 06 15",
    "sg:postcode":"75010",
    "sg:province":"Ile de France",
    "sg:tags":[
        "metallurgy",
        "finished",
        "-",
        "metalworking",
        "metallic"
    ],
    "wof:name":"Deville Entretien",
    "wof:placetype":"venue"
},
  "geometry": {"coordinates":[2.367353,48.878849],"type":"Point"}
}