{
  "type": "Feature",
  "properties": {
    "addr:full":"70, Rue Rivay, 92300 Levallois Perret Ile de France",
    "addr:housenumber":"70",
    "addr:postcode":"92300;ile",
    "addr:street":"Rue Rivay",
    "iso:country":"FR",
    "sg:address":"70, Rue Rivay, 92300 Levallois Perret",
    "sg:orig_category":"Unclassifiable Establishments",
    "sg:phone":"+33 1 47 56 21 31",
    "sg:province":"Ile de France",
    "wof:name":"Reed Exposition France S.a.s.",
    "wof:placetype":"venue"
},
  "geometry": {"coordinates":[2.287373,48.89711],"type":"Point"}
}