{
  "type": "Feature",
  "properties": {
    "iso:country":"FR",
    "sg:address":"161, Rte de Calmare, 76210 Beuzeville la Grenier",
    "sg:orig_category":"Non-Classified Establishments",
    "sg:phone":"+33 2 35 31 83 88",
    "sg:province":"Haute Normandie",
    "wof:name":"Maugard Espaces Verts S.a.",
    "wof:placetype":"venue"
},
  "geometry": {"coordinates":[0.425942,49.594528],"type":"Point"}
}