{
  "type": "Feature",
  "properties": {
    "iso:country":"FR",
    "sg:address":"Route Grange Au Gui 39260 Moirans En Montagne",
    "sg:classifiers":[
        {
            "category":"Manufacturing",
            "subcategory":"Rubber & Plastics",
            "type":"Manufacturing & Wholesale Goods"
        }
    ],
    "sg:phone":"+33 3 84 42 00 03",
    "sg:province":"Franche Comt\u00e9",
    "wof:name":"Jacquier Plastiques Sarl",
    "wof:placetype":"venue"
},
  "geometry": {"coordinates":[5.721997,46.434971],"type":"Point"}
}