{
  "type": "Feature",
  "properties": {
    "addr:full":"2, Chemin du G\u00e9nie - Parc d'Activit\u00e9 du G\u00e9nie, 69200 V\u00e9nissieux Rhone-Alpes",
    "addr:housenumber":"2",
    "addr:postcode":"69200",
    "addr:street":"Chemin Du Ge\u0301Nie Parc D'Activite \u0301 Du Ge\u0301Nie",
    "iso:country":"FR",
    "sg:address":"2, Chemin du G\u00e9nie - Parc d'Activit\u00e9 du G\u00e9nie, 69200 V\u00e9nissieux",
    "sg:orig_category":"Unclassifiable Establishments",
    "sg:phone":"+33 4 72 97 07 20",
    "sg:province":"Rhone-Alpes",
    "wof:name":"Rh\u00f4ne Inox Industrie S.a.r.l.",
    "wof:placetype":"venue"
},
  "geometry": {"coordinates":[4.860421,45.71566],"type":"Point"}
}