{
  "type": "Feature",
  "properties": {
    "addr:full":"Rue De L'Industrie 01460 Port Rhone-Alpes",
    "addr:postcode":"01460",
    "addr:street":"Rue De L'Industrie",
    "iso:country":"FR",
    "sg:address":"Rue De L'Industrie 01460 Port",
    "sg:classifiers":[
        {
            "category":"Manufacturing",
            "subcategory":"Rubber & Plastics",
            "type":"Manufacturing & Wholesale Goods"
        }
    ],
    "sg:phone":"+33 4 74 76 14 53",
    "sg:province":"Rhone-Alpes",
    "wof:name":"Padije (societe) Sarl",
    "wof:placetype":"venue"
},
  "geometry": {"coordinates":[5.570415,46.165993],"type":"Point"}
}