{
  "type": "Feature",
  "properties": {
    "iso:country":"FR",
    "sg:address":"20, Rue du Chalet, 75010 Paris",
    "sg:orig_category":"Unclassifiable Establishments",
    "sg:phone":"+33 1 42 08 38 72",
    "sg:province":"Ile de France",
    "wof:name":"Ateliers Billon S.a.",
    "wof:placetype":"venue"
},
  "geometry": {"coordinates":[2.373363,48.873943],"type":"Point"}
}