{
  "type": "Feature",
  "properties": {
    "iso:country":"FR",
    "sg:address":"185 Rue Marx Dormoy 59211 Santes",
    "sg:classifiers":[
        {
            "category":"Professional",
            "type":"Services"
        }
    ],
    "sg:phone":"+33 3 20 17 22 22",
    "sg:province":"Nord Pas-de-Calais",
    "sg:tags":[
        "transport",
        "road"
    ],
    "wof:name":"Transports Pacquet Paul Sa",
    "wof:placetype":"venue"
},
  "geometry": {"coordinates":[2.962476,50.600098],"type":"Point"}
}