{
  "type": "Feature",
  "properties": {
    "addr:full":"Zi La Prairie 91141 Villebon Sur Yvette Cedex \u00cele-de-France",
    "addr:postcode":"91141;cedex",
    "addr:street":"Zi La Prairie",
    "iso:country":"FR",
    "sg:address":"Zi La Prairie 91141 Villebon Sur Yvette Cedex",
    "sg:classifiers":[
        {
            "category":"Manufacturing",
            "subcategory":"Paper Products",
            "type":"Manufacturing & Wholesale Goods"
        }
    ],
    "sg:phone":"+33 1 69 34 15 61",
    "sg:province":"\u00cele-de-France",
    "sg:tags":[
        "packaging",
        "material",
        "-",
        "cardboard"
    ],
    "wof:name":"Wauters Et Fils",
    "wof:placetype":"venue"
},
  "geometry": {"coordinates":[2.267745,48.699326],"type":"Point"}
}