{
  "type": "Feature",
  "properties": {
    "addr:full":"1/3, Rue de Caumartin, 75009 Paris Ile de France",
    "addr:housenumber":"1 / 3",
    "addr:postcode":"75009",
    "addr:street":"Rue De Caumartin",
    "iso:country":"FR",
    "sg:address":"1/3, Rue de Caumartin, 75009 Paris",
    "sg:orig_category":"Unclassifiable Establishments",
    "sg:phone":"+33 1 44 94 72 70",
    "sg:province":"Ile de France",
    "wof:name":"Beachcomber Tours S.a.r.l.",
    "wof:placetype":"venue"
},
  "geometry": {"coordinates":[2.32786,48.870007],"type":"Point"}
}