{
  "type": "Feature",
  "properties": {
    "addr:full":"26 rue Pasteur 94450 Limeil Brevannes Ile de France 94450",
    "addr:housenumber":"26",
    "addr:postcode":"94450;94450",
    "addr:street":"Rue Pasteur",
    "iso:country":"FR",
    "sg:address":"26 rue Pasteur 94450 Limeil Brevannes",
    "sg:classifiers":[
        {
            "category":"Health Services",
            "subcategory":"Medical Lab",
            "type":"Services"
        }
    ],
    "sg:phone":"+33 1 45 98 17 39",
    "sg:postcode":"94450",
    "sg:province":"Ile de France",
    "sg:tags":[
        "laboratory",
        "accessory"
    ],
    "wof:name":"Gassalem S.a.r.l.",
    "wof:placetype":"venue"
},
  "geometry": {"coordinates":[2.479687,48.746044],"type":"Point"}
}