{
  "type": "Feature",
  "properties": {
    "addr:full":"3, Av. Louis Antoine Beaunier, 42160 Andr\u00e9zieux Bouth\u00e9on Rhone-Alpes",
    "addr:postcode":"42160",
    "addr:street":"Av. Louis Antoine Beaunier",
    "iso:country":"FR",
    "sg:address":"3, Av. Louis Antoine Beaunier, 42160 Andr\u00e9zieux Bouth\u00e9on",
    "sg:orig_category":"Unclassifiable Establishments",
    "sg:phone":"+33 4 77 55 55 30",
    "sg:province":"Rhone-Alpes",
    "wof:name":"Euramax Industries S.a.",
    "wof:placetype":"venue"
},
  "geometry": {"coordinates":[4.281533,45.523266],"type":"Point"}
}