{
  "type": "Feature",
  "properties": {
    "addr:full":"Route D'Aunay 14111 Louvigny Louvigny Basse Normandie 14111",
    "addr:postcode":"14111;14111",
    "addr:street":"Route D'Aunay",
    "iso:country":"FR",
    "sg:address":"Route D'Aunay 14111 Louvigny",
    "sg:city":"Louvigny",
    "sg:classifiers":[
        {
            "category":"Professional",
            "subcategory":"Business Services",
            "type":"Services"
        }
    ],
    "sg:phone":"+33 2 31 29 18 80",
    "sg:postcode":"14111",
    "sg:province":"Basse Normandie",
    "sg:tags":[
        "body",
        "advice"
    ],
    "wof:name":"Ass Des Amis Jean Bosco",
    "wof:placetype":"venue"
},
  "geometry": {"coordinates":[-0.37861,49.152142],"type":"Point"}
}