{
  "type": "Feature",
  "properties": {
    "addr:full":"B.P. 324, 92003 Nanterre C\u00e9dex^^28, Rue Lavoisier, 92000 Nanterre Ile de France",
    "addr:housenumber":"b.p. 324",
    "addr:postcode":"92003;92000",
    "addr:street":"Rue Lavoisier",
    "iso:country":"FR",
    "sg:address":"B.P. 324, 92003 Nanterre C\u00e9dex^^28, Rue Lavoisier, 92000 Nanterre",
    "sg:orig_category":"Non-Classified Establishments",
    "sg:phone":"+33 1 41 37 16 00",
    "sg:province":"Ile de France",
    "wof:name":"Forclum",
    "wof:placetype":"venue"
},
  "geometry": {"coordinates":[2.194875,48.888084],"type":"Point"}
}