{
  "type": "Feature",
  "properties": {
    "addr:full":"L'Europarc de Pichaury - B\u00e2t. B8 Aix en Provence Provence-Alpes-C\u00f4te d'Azur 13100",
    "addr:housenumber":"ba\u0302t b8",
    "addr:postcode":"13100",
    "addr:street":"Aix;Provence",
    "iso:country":"FR",
    "sg:address":"L'Europarc de Pichaury - B\u00e2t. B8",
    "sg:city":"Aix en Provence",
    "sg:orig_category":"Unclassifiable Establishments",
    "sg:phone":"+33 4 42 39 45 33",
    "sg:postcode":"13100",
    "sg:province":"Provence-Alpes-C\u00f4te d'Azur",
    "wof:name":"Octopus S.a.",
    "wof:placetype":"venue"
},
  "geometry": {"coordinates":[5.448121,43.5299],"type":"Point"}
}