{
  "type": "Feature",
  "properties": {
    "iso:country":"FR",
    "sg:address":"29, Clos des Baz, 74700 Sallanches",
    "sg:orig_category":"Unclassifiable Establishments",
    "sg:phone":"+33 4 50 58 56 02",
    "sg:province":"Rhone-Alpes",
    "wof:name":"Acro - B.t.p. S.a.r.l.",
    "wof:placetype":"venue"
},
  "geometry": {"coordinates":[6.636076,45.939251],"type":"Point"}
}