{
  "type": "Feature",
  "properties": {
    "iso:country":"FR",
    "sg:address":"ZI",
    "sg:city":"Auneuil",
    "sg:orig_category":"Unclassifiable Establishments",
    "sg:phone":"+33 3 44 47 55 55",
    "sg:postcode":"60390",
    "sg:province":"Picardie",
    "wof:name":"Lafarge Pl\u00e2tres S.a.",
    "wof:placetype":"venue"
},
  "geometry": {"coordinates":[1.997038,49.369747],"type":"Point"}
}