{
  "type": "Feature",
  "properties": {
    "iso:country":"FR",
    "sg:address":"10 ave Pierre et Marie; Le Blanc Mesnil; 93150",
    "sg:classifiers":[
        {
            "category":"Banks & Credit Unions",
            "subcategory":"Bank",
            "type":"Services"
        }
    ],
    "sg:phone":"+33 18674575",
    "sg:postcode":"93150",
    "sg:province":"Ile de France",
    "wof:name":"Banque Nationale De Paris",
    "wof:placetype":"venue"
},
  "geometry": {"coordinates":[2.458996,48.936291],"type":"Point"}
}