{
  "type": "Feature",
  "properties": {
    "addr:full":"Le Puech 12000 Rodez Midi Pyr\u00e9n\u00e9es",
    "addr:postcode":"12000",
    "iso:country":"FR",
    "sg:address":"Le Puech 12000 Rodez",
    "sg:orig_category":"Unclassifiable Establishments",
    "sg:phone":"+33 5 65 77 65 00",
    "sg:province":"Midi Pyr\u00e9n\u00e9es",
    "wof:name":"Alstom Entreprise S.a.",
    "wof:placetype":"venue"
},
  "geometry": {"coordinates":[2.577643,44.348526],"type":"Point"}
}