{
  "type": "Feature",
  "properties": {
    "iso:country":"FR",
    "sg:address":"Rue Du Gal Haxo BP 73 Maison Des Associations 88002 Epinal",
    "sg:city":"\u00c9pinal",
    "sg:classifiers":[
        {
            "category":"Sports & Exercise",
            "subcategory":"Sports Center",
            "type":"Entertainment"
        }
    ],
    "sg:phone":"+33 3 29 35 06 70",
    "sg:postcode":"88000",
    "sg:province":"Lorraine",
    "sg:tags":[
        "game"
    ],
    "wof:name":"Psa 88 (profession Sports Annimation 88)",
    "wof:placetype":"venue"
},
  "geometry": {"coordinates":[6.4497,48.175686],"type":"Point"}
}