{
  "type": "Feature",
  "properties": {
    "addr:full":"18-20 Av Du 8 Mai 1945 77290 Mitry Mory Ile de France 77290",
    "addr:housenumber":"18-20",
    "addr:postcode":"77290;77290",
    "addr:street":"Av Du 8 Mai 1945",
    "iso:country":"FR",
    "sg:address":"18-20 Av Du 8 Mai 1945 77290 Mitry Mory",
    "sg:classifiers":[
        {
            "category":"Professional",
            "subcategory":"Business Services",
            "type":"Services"
        }
    ],
    "sg:phone":"+33 1 60 21 25 25",
    "sg:postcode":"77290",
    "sg:province":"Ile de France",
    "sg:tags":[
        "travel",
        "fair"
    ],
    "wof:name":"General Location",
    "wof:placetype":"venue"
},
  "geometry": {"coordinates":[2.620801,48.983189],"type":"Point"}
}