{
  "type": "Feature",
  "properties": {
    "iso:country":"FR",
    "sg:address":"257 Rue Des Nauzes Zone Artisanale 82170 Grisolles",
    "sg:classifiers":[
        {
            "category":"Food Court",
            "type":"Food & Drink"
        }
    ],
    "sg:phone":"+33 5 63 27 12 30",
    "sg:postcode":"82170",
    "sg:province":"Midi Pyr\u00e9n\u00e9es",
    "sg:tags":[
        "product",
        "related"
    ],
    "wof:name":"Sarl Laboratoires Lebeau",
    "wof:placetype":"venue"
},
  "geometry": {"coordinates":[1.296795,43.826965],"type":"Point"}
}