{
  "type": "Feature",
  "properties": {
    "addr:full":"18, Rue Meyerbeer, 06000 Nice Provence-Alpes-C\u00f4te d'Azur",
    "addr:housenumber":"18",
    "addr:postcode":"06000",
    "addr:street":"Rue Meyerbeer",
    "iso:country":"FR",
    "sg:address":"18, Rue Meyerbeer, 06000 Nice",
    "sg:orig_category":"Unclassifiable Establishments",
    "sg:phone":"+33 4 93 88 00 80",
    "sg:province":"Provence-Alpes-C\u00f4te d'Azur",
    "wof:name":"Sun Conseil C\u00f4te D'azur S.a.",
    "wof:placetype":"venue"
},
  "geometry": {"coordinates":[7.260786,43.696598],"type":"Point"}
}