{
  "type": "Feature",
  "properties": {
    "addr:full":"14 Rue Gabriel Plan\u00e7on 25000 Besan\u00e7on Franche Comt\u00e9 25000",
    "addr:housenumber":"14",
    "addr:postcode":"25000;25000",
    "addr:street":"Rue Gabriel Planc\u0327On;Franche Comte\u0301",
    "iso:country":"FR",
    "sg:address":"14 Rue Gabriel Plan\u00e7on 25000 Besan\u00e7on",
    "sg:classifiers":[
        {
            "category":"Farming",
            "subcategory":"Farm & Veterinary Services",
            "type":"Manufacturing & Wholesale Goods"
        }
    ],
    "sg:phone":"+33 3 81 65 78 80",
    "sg:postcode":"25000",
    "sg:province":"Franche Comt\u00e9",
    "sg:tags":[
        "advice",
        "agriculture",
        "livestock",
        "business"
    ],
    "wof:name":"Office National Des Forets",
    "wof:placetype":"venue"
},
  "geometry": {"coordinates":[6.014658,47.23365],"type":"Point"}
}