{
  "type": "Feature",
  "properties": {
    "addr:full":"5 rue Jean Rodier 31400 Toulouse Midi Pyr\u00e9n\u00e9es 31400",
    "addr:housenumber":"5",
    "addr:postcode":"31400;31400",
    "addr:street":"Rue Jean Rodier",
    "iso:country":"FR",
    "sg:address":"5 rue Jean Rodier 31400 Toulouse",
    "sg:classifiers":[
        {
            "category":"Professional",
            "subcategory":"Engineering",
            "type":"Services"
        }
    ],
    "sg:phone":"+33 5 62 71 69 39",
    "sg:postcode":"31400",
    "sg:province":"Midi Pyr\u00e9n\u00e9es",
    "sg:tags":[
        "bio",
        "genetic"
    ],
    "wof:name":"Cayla Sarl",
    "wof:placetype":"venue"
},
  "geometry": {"coordinates":[1.487557,43.567371],"type":"Point"}
}