{
  "type": "Feature",
  "properties": {
    "iso:country":"FR",
    "sg:address":"40 Rue Du Champ De Mars 42600 Savigneux",
    "sg:classifiers":[
        {
            "category":"Wholesale",
            "subcategory":"Auto Parts",
            "type":"Manufacturing & Wholesale Goods"
        }
    ],
    "sg:phone":"+33 4 77 96 70 50",
    "sg:postcode":"42600",
    "sg:province":"Rhone-Alpes",
    "sg:tags":[
        "pharmaceutical",
        "-",
        "chemical",
        "engineering",
        "machine",
        "mechanical",
        "chemistry",
        "by-product"
    ],
    "wof:name":"Becker Industrie Sa",
    "wof:placetype":"venue"
},
  "geometry": {"coordinates":[4.092162,45.60218],"type":"Point"}
}