{
  "type": "Feature",
  "properties": {
    "addr:full":"B.P. 74 Garges l\u00e8s Gonesse C\u00e9dex Ile-de-France 95144",
    "addr:postcode":"95144",
    "addr:street":"B.P. 74",
    "iso:country":"FR",
    "sg:address":"B.P. 74",
    "sg:city":"Garges l\u00e8s Gonesse C\u00e9dex",
    "sg:orig_category":"Non-Classified Establishments",
    "sg:phone":"+33 1 34 45 46 00",
    "sg:postcode":"95144",
    "sg:province":"Ile-de-France",
    "wof:name":"L\u00e9co France S.a.r.l.",
    "wof:placetype":"venue"
},
  "geometry": {"coordinates":[2.39924,48.970955],"type":"Point"}
}