{
  "type": "Feature",
  "properties": {
    "iso:country":"FR",
    "sg:address":"8, Place Charles de Gaulle, 78180 Montigny le Bretonneux",
    "sg:orig_category":"Non-Classified Establishments",
    "sg:phone":"+33 1 30 64 43 43",
    "sg:province":"Ile de France",
    "wof:name":"Plus Int\u00e9rim S.a.",
    "wof:placetype":"venue"
},
  "geometry": {"coordinates":[2.045745,48.786709],"type":"Point"}
}