{
  "type": "Feature",
  "properties": {
    "addr:full":"25 Parc D'Activit\u00e9 De La Calarde 95500 Gonesse Ile de France",
    "addr:housenumber":"25",
    "addr:postcode":"95500;ile",
    "addr:street":"Parc D'Activite \u0301 De La Calarde",
    "iso:country":"FR",
    "sg:address":"25 Parc D'Activit\u00e9 De La Calarde 95500 Gonesse",
    "sg:classifiers":[
        {
            "category":"Manufacturing",
            "subcategory":"Rubber & Plastics",
            "type":"Manufacturing & Wholesale Goods"
        }
    ],
    "sg:phone":"+33 1 39 85 78 79",
    "sg:province":"Ile de France",
    "wof:name":"Pms Sa",
    "wof:placetype":"venue"
},
  "geometry": {"coordinates":[2.46029,48.985668],"type":"Point"}
}