{
  "type": "Feature",
  "properties": {
    "addr:full":"6 Rue Des Clos Zi Nord 77109 Meaux Cedex Ile de France",
    "addr:housenumber":"6",
    "addr:postcode":"77109;ile",
    "addr:street":"Rue Des Clos Zi Nord",
    "iso:country":"FR",
    "sg:address":"6 Rue Des Clos Zi Nord 77109 Meaux Cedex",
    "sg:classifiers":[
        {
            "category":"Professional",
            "subcategory":"Engineering",
            "type":"Services"
        }
    ],
    "sg:phone":"+33 1 60 09 93 70",
    "sg:province":"Ile de France",
    "sg:tags":[
        "machine",
        "-",
        "mechanical"
    ],
    "wof:name":"Ab Industrie",
    "wof:placetype":"venue"
},
  "geometry": {"coordinates":[2.883054,48.959351],"type":"Point"}
}