{
  "type": "Feature",
  "properties": {
    "iso:country":"FR",
    "sg:address":"108 av Pierre Dumond; Craponne",
    "sg:city":"Craponne",
    "sg:classifiers":[
        {
            "category":"Banks & Credit Unions",
            "subcategory":"Bank",
            "type":"Services"
        }
    ],
    "sg:phone":"+33 3378571404",
    "sg:postcode":"69290",
    "sg:province":"Rhone-Alpes",
    "wof:name":"Cr\u00e9dit Lyonnais",
    "wof:placetype":"venue"
},
  "geometry": {"coordinates":[4.720689,45.747486],"type":"Point"}
}