{
  "type": "Feature",
  "properties": {
    "addr:full":"B.P. 10322, 95705 Roissy Charles de Gaulle C\u00e9dex^^14, Rue de la Belle Borne, 93290 Tremblay en Franc Ile de France",
    "addr:housenumber":"95705",
    "addr:postcode":"93290",
    "addr:street":"Roissy;De;Rue De La Belle Borne",
    "iso:country":"FR",
    "sg:address":"B.P. 10322, 95705 Roissy Charles de Gaulle C\u00e9dex^^14, Rue de la Belle Borne, 93290 Tremblay en Franc",
    "sg:orig_category":"Non-Classified Establishments",
    "sg:phone":"+33 1 48 62 33 94",
    "sg:province":"Ile de France",
    "wof:name":"Yamato Transport Europe",
    "wof:placetype":"venue"
},
  "geometry": {"coordinates":[-111.276329,43.972591],"type":"Point"}
}