{
  "type": "Feature",
  "properties": {
    "iso:country":"FR",
    "sg:address":"9",
    "sg:city":"Vladimir-Komarov; Trappes; 78192",
    "sg:classifiers":[
        {
            "category":"Banks & Credit Unions",
            "subcategory":"Bank",
            "type":"Services"
        }
    ],
    "sg:phone":"+33 30514527",
    "sg:province":"Ile de France",
    "wof:name":"Banque Nationale De Paris",
    "wof:placetype":"venue"
},
  "geometry": {"coordinates":[1.999285,48.774651],"type":"Point"}
}