{
  "type": "Feature",
  "properties": {
    "addr:full":"13 Route De Villemeneux 77170 Brie Comte Robert Ile de France",
    "addr:housenumber":"13",
    "addr:postcode":"77170",
    "addr:street":"Route De Villemeneux",
    "iso:country":"FR",
    "sg:address":"13 Route De Villemeneux 77170 Brie Comte Robert",
    "sg:classifiers":[
        {
            "category":"Manufacturing",
            "subcategory":"Rubber & Plastics",
            "type":"Manufacturing & Wholesale Goods"
        }
    ],
    "sg:phone":"+33 1 64 05 65 95",
    "sg:province":"Ile de France",
    "wof:name":"Polyplast Sa",
    "wof:placetype":"venue"
},
  "geometry": {"coordinates":[2.601805,48.686611],"type":"Point"}
}