{
  "type": "Feature",
  "properties": {
    "iso:country":"FR",
    "sg:address":"8, Rue Saint Antoine, 75004 Paris",
    "sg:orig_category":"Non-Classified Establishments",
    "sg:phone":"+33 1 40 27 02 23",
    "sg:postcode":"75004",
    "sg:province":"Ile de France",
    "wof:name":"Cosmopolis S.a.r.l.",
    "wof:placetype":"venue"
},
  "geometry": {"coordinates":[2.367486,48.853523],"type":"Point"}
}