{
  "type": "Feature",
  "properties": {
    "iso:country":"FR",
    "sg:address":"73/77, Rue de la Paix, 50120 Equeurdreville Hainneville",
    "sg:city":"\u00c9queurdreville-Hainneville",
    "sg:orig_category":"Non-Classified Establishments",
    "sg:phone":"+33 2 33 87 63 63",
    "sg:postcode":"50120",
    "sg:province":"Basse Normandie",
    "wof:name":"Etablissements Hochet S.a.",
    "wof:placetype":"venue"
},
  "geometry": {"coordinates":[-1.650856,49.649746],"type":"Point"}
}