{
  "type": "Feature",
  "properties": {
    "iso:country":"FR",
    "sg:address":"66, Chemin des Fins Nord, 74000 Annecy",
    "sg:orig_category":"Unclassifiable Establishments",
    "sg:phone":"+33 4 50 57 60 35",
    "sg:postcode":"74000",
    "sg:province":"Rhone-Alpes",
    "wof:name":"Millet Racing S.a.r.l.",
    "wof:placetype":"venue"
},
  "geometry": {"coordinates":[6.122092,45.916817],"type":"Point"}
}