{
  "type": "Feature",
  "properties": {
    "addr:full":"Zone Emploi La Touche D'Anais 16560 Tourriers Poitou-Charentes",
    "addr:postcode":"16560",
    "addr:street":"Tourriers",
    "iso:country":"FR",
    "sg:address":"Zone Emploi La Touche D'Anais 16560 Tourriers",
    "sg:classifiers":[
        {
            "category":"Manufacturing",
            "subcategory":"Rubber & Plastics",
            "type":"Manufacturing & Wholesale Goods"
        }
    ],
    "sg:phone":"+33 5 45 20 68 89",
    "sg:province":"Poitou-Charentes",
    "wof:name":"Atelier De Materiaux De Synthese Sarl",
    "wof:placetype":"venue"
},
  "geometry": {"coordinates":[0.20944,45.774029],"type":"Point"}
}