{
  "type": "Feature",
  "properties": {
    "iso:country":"FR",
    "sg:address":"247bis, Av. de la Marne, 59700 Marcq en Baroeul",
    "sg:orig_category":"Unclassifiable Establishments",
    "sg:phone":"+33 3 20 99 22 22",
    "sg:province":"Nord Pas-de-Calais",
    "wof:name":"Omega Concept S.a.",
    "wof:placetype":"venue"
},
  "geometry": {"coordinates":[3.10722,50.673412],"type":"Point"}
}