{
  "type": "Feature",
  "properties": {
    "iso:country":"FR",
    "sg:address":"27, Rue de la Poste, 36000 Ch\u00e2teauroux",
    "sg:city":"Ch\u00e2teauroux",
    "sg:orig_category":"Unclassifiable Establishments",
    "sg:phone":"+33 2 54 22 64 20",
    "sg:postcode":"36000",
    "sg:province":"Centre",
    "wof:name":"Bureau Moderne S.a.r.l.",
    "wof:placetype":"venue"
},
  "geometry": {"coordinates":[1.693797,46.810444],"type":"Point"}
}