{
  "type": "Feature",
  "properties": {
    "addr:full":"321, Rue Fourny - ZI, 78531 Buc C\u00e9dex Centre",
    "addr:housenumber":"321",
    "addr:postcode":"78531",
    "addr:street":"Rue Fourny Zi",
    "iso:country":"FR",
    "sg:address":"321, Rue Fourny - ZI, 78531 Buc C\u00e9dex",
    "sg:orig_category":"Non-Classified Establishments",
    "sg:phone":"+33 1 39 24 89 89",
    "sg:province":"Centre",
    "wof:name":"A.f.o. S.a.s. - Atelier De Fabrication Outillage",
    "wof:placetype":"venue"
},
  "geometry": {"coordinates":[2.126343,48.774464],"type":"Point"}
}