{
  "type": "Feature",
  "properties": {
    "addr:full":"ZI les Gallinaux Creysse Aquitaine 24100",
    "addr:housenumber":"creysse",
    "addr:postcode":"24100",
    "addr:street":"Zi Les",
    "iso:country":"FR",
    "sg:address":"ZI les Gallinaux",
    "sg:city":"Creysse",
    "sg:orig_category":"Non-Classified Establishments",
    "sg:phone":"+33 5 53 57 70 52",
    "sg:postcode":"24100",
    "sg:province":"Aquitaine",
    "wof:name":"S.n.d.p.i. S.a.r.l. - Soci\u00e9t\u00e9 Nouvelle De Distribution De Produits Industriels",
    "wof:placetype":"venue"
},
  "geometry": {"coordinates":[0.563535,44.854851],"type":"Point"}
}