{
  "type": "Feature",
  "properties": {
    "addr:full":"1541 Rue De La Ferme Larrouquere Zi 40000 Mont De Marsan Mont-de-Marsan Aquitaine 40000",
    "addr:housenumber":"1541",
    "addr:postcode":"40000;40000",
    "addr:street":"Rue De La Ferme Larrouquere Zi",
    "iso:country":"FR",
    "sg:address":"1541 Rue De La Ferme Larrouquere Zi 40000 Mont De Marsan",
    "sg:city":"Mont-de-Marsan",
    "sg:classifiers":[
        {
            "category":"Manufacturing",
            "subcategory":"Chemicals & Compounds",
            "type":"Manufacturing & Wholesale Goods"
        }
    ],
    "sg:phone":"+33 5 58 05 81 05",
    "sg:postcode":"40000",
    "sg:province":"Aquitaine",
    "sg:tags":[
        "pharmaceutical",
        "chemistry",
        "-",
        "by-product"
    ],
    "wof:name":"Ets Pierre Bouneau",
    "wof:placetype":"venue"
},
  "geometry": {"coordinates":[-0.498939,43.889503],"type":"Point"}
}