{
  "type": "Feature",
  "properties": {
    "addr:full":"27 M\u00e9tiers 14123 Cormelles le Royal Basse Normandie 14123",
    "addr:housenumber":"27",
    "addr:postcode":"14123;14123",
    "addr:street":"Me\u0301Tiers",
    "iso:country":"FR",
    "sg:address":"27",
    "sg:city":"M\u00e9tiers 14123 Cormelles le Royal",
    "sg:classifiers":[
        {
            "category":"Manufacturing",
            "subcategory":"Metals",
            "type":"Manufacturing & Wholesale Goods"
        }
    ],
    "sg:phone":"+33 2 31 82 62 62",
    "sg:postcode":"14123",
    "sg:province":"Basse Normandie",
    "sg:tags":[
        "-",
        "machine",
        "equipment",
        "engineering",
        "machinery",
        "mechanical"
    ],
    "wof:name":"Lepareur Industries (sa)",
    "wof:placetype":"venue"
},
  "geometry": {"coordinates":[-0.325976,49.160728],"type":"Point"}
}