{
  "type": "Feature",
  "properties": {
    "addr:full":"B.P. 70, 41102 Vend\u00f4me C\u00e9dex^^74, Rte de Paris, 41100 Saint Ouen Vend\u00f4me Centre 41100",
    "addr:postcode":"41102;41100;41100",
    "addr:street":"B.P. 70;Rte De Paris",
    "iso:country":"FR",
    "sg:address":"B.P. 70, 41102 Vend\u00f4me C\u00e9dex^^74, Rte de Paris, 41100 Saint Ouen",
    "sg:city":"Vend\u00f4me",
    "sg:orig_category":"Non-Classified Establishments",
    "sg:phone":"+33 2 54 77 26 28",
    "sg:postcode":"41100",
    "sg:province":"Centre",
    "wof:name":"Chavigny S.a.",
    "wof:placetype":"venue"
},
  "geometry": {"coordinates":[1.17829,47.712414],"type":"Point"}
}