{
  "type": "Feature",
  "properties": {
    "addr:full":"route De Corbie 80450 CAMON Picardie 80450",
    "addr:postcode":"80450;80450",
    "addr:street":"Route De Corbie",
    "iso:country":"FR",
    "sg:address":"route De Corbie 80450 CAMON",
    "sg:classifiers":[
        {
            "category":"Organizations",
            "subcategory":"Non-profit Organization",
            "type":"Services"
        }
    ],
    "sg:phone":"+33 3 22 70 20 40",
    "sg:postcode":"80450",
    "sg:province":"Picardie",
    "sg:tags":[
        "industrial",
        "system",
        "hydraulic"
    ],
    "wof:name":"Henrion Hydraulique S.a.",
    "wof:placetype":"venue"
},
  "geometry": {"coordinates":[2.34342,49.887493],"type":"Point"}
}