{
  "type": "Feature",
  "properties": {
    "addr:full":"38, Rte Nationale, 28200 Saint Denis les Ponts Ch\u00e2teaudun Centre 28200",
    "addr:housenumber":"38",
    "addr:postcode":"28200;28200",
    "addr:street":"Rte Nationale;Denis",
    "iso:country":"FR",
    "sg:address":"38, Rte Nationale, 28200 Saint Denis les Ponts",
    "sg:city":"Ch\u00e2teaudun",
    "sg:orig_category":"Non-Classified Establishments",
    "sg:phone":"+33 2 37 45 10 32",
    "sg:postcode":"28200",
    "sg:province":"Centre",
    "wof:name":"Lemoult S.a.r.l.",
    "wof:placetype":"venue"
},
  "geometry": {"coordinates":[1.301196,48.067978],"type":"Point"}
}