{
  "type": "Feature",
  "properties": {
    "iso:country":"FR",
    "sg:address":"Route De Corbeilles 45700 Villevoques",
    "sg:city":"Villevoques",
    "sg:classifiers":[
        {
            "category":"Wholesale",
            "subcategory":"Machinery & Supplies",
            "type":"Manufacturing & Wholesale Goods"
        }
    ],
    "sg:phone":"+33 2 38 87 93 15",
    "sg:postcode":"45700",
    "sg:province":"Centre",
    "sg:tags":[
        "handling",
        "material",
        "-",
        "machine",
        "equipment",
        "engineering",
        "mechanical"
    ],
    "wof:name":"Diffusion Service Sarl",
    "wof:placetype":"venue"
},
  "geometry": {"coordinates":[2.765315,47.896927],"type":"Point"}
}