{
  "type": "Feature",
  "properties": {
    "addr:full":"210 rue du Beau Marais 62400 BETHUNE Nord Pas-de-Calais 62400",
    "addr:housenumber":"210",
    "addr:postcode":"62400;62400",
    "addr:street":"Rue Du Beau Marais;Bethune Nord",
    "iso:country":"FR",
    "sg:address":"210 rue du Beau Marais 62400 BETHUNE",
    "sg:classifiers":[
        {
            "category":"Manufacturing",
            "subcategory":"Metals",
            "type":"Manufacturing & Wholesale Goods"
        }
    ],
    "sg:phone":"+33 3 21 01 01 21",
    "sg:postcode":"62400",
    "sg:province":"Nord Pas-de-Calais",
    "sg:tags":[
        "ironmongery"
    ],
    "wof:name":"Etablissements Max Mine S.a.r.l.",
    "wof:placetype":"venue"
},
  "geometry": {"coordinates":[2.648377,50.532642],"type":"Point"}
}