{
  "type": "Feature",
  "properties": {
    "addr:full":"29 Jules Guesde 92300 Levallois Perret Ile de France 92300",
    "addr:housenumber":"29",
    "addr:postcode":"92300;ile;92300",
    "addr:street":"Jules Guesde;France",
    "iso:country":"FR",
    "sg:address":"29",
    "sg:city":"Jules Guesde 92300 Levallois Perret",
    "sg:classifiers":[
        {
            "category":"Professional",
            "subcategory":"Engineering",
            "type":"Services"
        }
    ],
    "sg:phone":"+33 1 55 21 07 77",
    "sg:postcode":"92300",
    "sg:province":"Ile de France",
    "sg:tags":[
        "machine",
        "-",
        "environment",
        "equipment",
        "machinery",
        "mechanical"
    ],
    "wof:name":"Phr Industrie",
    "wof:placetype":"venue"
},
  "geometry": {"coordinates":[2.293016,48.892471],"type":"Point"}
}