{
  "type": "Feature",
  "properties": {
    "addr:full":"23 rue du Tour de Ville 02440 Clastres Picardie",
    "addr:housenumber":"23",
    "addr:postcode":"02440",
    "addr:street":"Rue Du Tour De Ville",
    "iso:country":"FR",
    "sg:address":"23 rue du Tour de Ville 02440 Clastres",
    "sg:orig_category":"Photographic Paper Backing-Up Machines",
    "sg:phone":"+33 3 23 63 30 74",
    "sg:province":"Picardie",
    "wof:name":"Marcel Latruffe Eurl",
    "wof:placetype":"venue"
},
  "geometry": {"coordinates":[3.234099,49.748287],"type":"Point"}
}