{
  "type": "Feature",
  "properties": {
    "addr:full":"B.P. 8301, 95803 Cergy C\u00e9dex^^10, Av. du Centaure, 95800 Cergy Ile de France",
    "addr:postcode":"95803;95800;ile",
    "addr:street":"B.P. 8301;Av. Du Centaure",
    "iso:country":"FR",
    "sg:address":"B.P. 8301, 95803 Cergy C\u00e9dex^^10, Av. du Centaure, 95800 Cergy",
    "sg:orig_category":"Non-Classified Establishments",
    "sg:phone":"+33 1 34 43 27 27",
    "sg:province":"Ile de France",
    "wof:name":"Satchwell S.a.",
    "wof:placetype":"venue"
},
  "geometry": {"coordinates":[2.000455,49.035156],"type":"Point"}
}