{
  "type": "Feature",
  "properties": {
    "addr:full":"141, Rue des Tuileries, 38920 Crolles Crolles Rhone-Alpes 38190",
    "addr:housenumber":"141",
    "addr:postcode":"38920;38190",
    "addr:street":"Rue Des Tuileries",
    "iso:country":"FR",
    "sg:address":"141, Rue des Tuileries, 38920 Crolles",
    "sg:city":"Crolles",
    "sg:orig_category":"Non-Classified Establishments",
    "sg:phone":"+33 4 38 92 03 71",
    "sg:postcode":"38190",
    "sg:province":"Rhone-Alpes",
    "wof:name":"E.c.t.r.a. S.a. - Emballage Conditionnement Transit",
    "wof:placetype":"venue"
},
  "geometry": {"coordinates":[5.890466,45.273548],"type":"Point"}
}