{
  "type": "Feature",
  "properties": {
    "iso:country":"FR",
    "sg:address":"4 rue du G\u00e9n\u00e9ral Leclerc 94520 P\u00e9rigny sur Yerres",
    "sg:orig_category":"Model Building For Industrial Plant",
    "sg:phone":"+33 1 45 98 92 55",
    "sg:postcode":"94520",
    "sg:province":"Ile de France",
    "wof:name":"Polymaquettes",
    "wof:placetype":"venue"
},
  "geometry": {"coordinates":[2.548104,48.696121],"type":"Point"}
}