{
  "type": "Feature",
  "properties": {
    "addr:full":"9, Rue de S\u00e9gur, 33000 Bordeaux Bordeaux Aquitaine 33000",
    "addr:housenumber":"9",
    "addr:postcode":"33000;33000",
    "addr:street":"Rue De Se\u0301Gur",
    "iso:country":"FR",
    "sg:address":"9, Rue de S\u00e9gur, 33000 Bordeaux",
    "sg:city":"Bordeaux",
    "sg:orig_category":"Non-Classified Establishments",
    "sg:phone":"+33 5 56 99 30 20",
    "sg:postcode":"33000",
    "sg:province":"Aquitaine",
    "wof:name":"Gertrude S.a.",
    "wof:placetype":"venue"
},
  "geometry": {"coordinates":[-0.588262,44.825306],"type":"Point"}
}