{
  "type": "Feature",
  "properties": {
    "iso:country":"FR",
    "sg:address":"ZI du Coudrier",
    "sg:city":"Boissy l'Aillerie",
    "sg:orig_category":"Unclassifiable Establishments",
    "sg:phone":"+33 1 34 42 15 15",
    "sg:postcode":"95650",
    "sg:province":"Ile de France",
    "wof:name":"Patibio S.a.r.l.",
    "wof:placetype":"venue"
},
  "geometry": {"coordinates":[-121.167381,38.815128],"type":"Point"}
}