{
  "type": "Feature",
  "properties": {
    "addr:full":"ZI Pr\u00e9 \u00e0 Varois Custines Lorraine 54670",
    "addr:postcode":"54670",
    "addr:street":"Zi Pre\u0301 A\u0300 Varois Custines Lorraine",
    "iso:country":"FR",
    "sg:address":"ZI Pr\u00e9 \u00e0 Varois",
    "sg:city":"Custines",
    "sg:orig_category":"Unclassifiable Establishments",
    "sg:phone":"+33 3 83 24 37 24",
    "sg:postcode":"54670",
    "sg:province":"Lorraine",
    "wof:name":"Gardiennage Lorrain S.a.r.l.",
    "wof:placetype":"venue"
},
  "geometry": {"coordinates":[6.142335,48.791302],"type":"Point"}
}