{
  "type": "Feature",
  "properties": {
    "addr:full":"ZI de Fosses Saint Witz Ile de France 95470",
    "addr:postcode":"95470",
    "addr:street":"Zi De Fosses Saint Witz Ile De France",
    "iso:country":"FR",
    "sg:address":"ZI de Fosses",
    "sg:city":"Saint Witz",
    "sg:orig_category":"Unclassifiable Establishments",
    "sg:phone":"+33 1 34 68 69 00",
    "sg:postcode":"95470",
    "sg:province":"Ile de France",
    "wof:name":"G\u00e9n\u00e9ral Trailers Industries S.a.",
    "wof:placetype":"venue"
},
  "geometry": {"coordinates":[2.567709,49.091995],"type":"Point"}
}