{
  "type": "Feature",
  "properties": {
    "addr:full":"Rue Dr Bianchi Res De Galice Bt C 13100 Aix En Provence Nord Pas-de-Calais",
    "addr:postcode":"13100",
    "addr:street":"Rue Dr Bianchi Res De Galice Bt C;En Provence Nord",
    "iso:country":"FR",
    "sg:address":"Rue Dr Bianchi Res De Galice Bt C 13100 Aix En Provence",
    "sg:classifiers":[
        {
            "category":"Utilities",
            "subcategory":"Electric",
            "type":"Services"
        }
    ],
    "sg:phone":"+33 4 42 52 51 60",
    "sg:province":"Nord Pas-de-Calais",
    "sg:tags":[
        "electricity",
        "electronic",
        "electrical",
        "equipment"
    ],
    "wof:name":"Sdmo Industries Sas",
    "wof:placetype":"venue"
},
  "geometry": {"coordinates":[5.49167,43.509033],"type":"Point"}
}