{
  "type": "Feature",
  "properties": {
    "addr:full":"19, Rue des Indes, 95100 Argenteuil Ile de France 95100",
    "addr:housenumber":"19",
    "addr:postcode":"95100;ile;95100",
    "addr:street":"Rue Des Indes;France",
    "iso:country":"FR",
    "sg:address":"19, Rue des Indes, 95100 Argenteuil",
    "sg:orig_category":"Non-Classified Establishments",
    "sg:phone":"+33 1 34 10 47 15",
    "sg:postcode":"95100",
    "sg:province":"Ile de France",
    "wof:name":"Etablissements Bianco S.a.r.l.",
    "wof:placetype":"venue"
},
  "geometry": {"coordinates":[2.206697,48.947918],"type":"Point"}
}