{
  "type": "Feature",
  "properties": {
    "addr:full":"1 Rue Du Mal Leclerc 50100 Cherbourg Cherbourg-Octeville Basse Normandie 50100",
    "addr:housenumber":"1",
    "addr:postcode":"50100;50100",
    "addr:street":"Rue Du Mal Leclerc",
    "iso:country":"FR",
    "sg:address":"1 Rue Du Mal Leclerc 50100 Cherbourg",
    "sg:city":"Cherbourg-Octeville",
    "sg:classifiers":[
        {
            "category":"Professional",
            "subcategory":"Business Services",
            "type":"Services"
        }
    ],
    "sg:phone":"+33 2 33 93 31 23",
    "sg:postcode":"50100",
    "sg:province":"Basse Normandie",
    "sg:tags":[
        "body",
        "advice"
    ],
    "wof:name":"Ass Solidarite Travail Recherche Emploi",
    "wof:placetype":"venue"
},
  "geometry": {"coordinates":[-1.616124,49.640484],"type":"Point"}
}