{
  "type": "Feature",
  "properties": {
    "addr:full":"49, Rue Saint Roch, 75001 Paris Ile de France",
    "addr:housenumber":"49",
    "addr:postcode":"75001",
    "addr:street":"Rue Saint Roch",
    "iso:country":"FR",
    "sg:address":"49, Rue Saint Roch, 75001 Paris",
    "sg:orig_category":"Unclassifiable Establishments",
    "sg:phone":"+33 1 42 61 80 59",
    "sg:province":"Ile de France",
    "wof:name":"L.b.p. Communication S.a.",
    "wof:placetype":"venue"
},
  "geometry": {"coordinates":[2.333009,48.866814],"type":"Point"}
}