{
  "type": "Feature",
  "properties": {
    "iso:country":"FR",
    "sg:address":"155, Av. Charles Rouxel, 77340 Pontault Combault",
    "sg:orig_category":"Non-Classified Establishments",
    "sg:phone":"+33 1 60 28 66 97",
    "sg:province":"Ile de France",
    "wof:name":"P.m.s. S.a.r.l.- Prestation, Maintenance, Surveillance",
    "wof:placetype":"venue"
},
  "geometry": {"coordinates":[2.602226,48.785946],"type":"Point"}
}