{
  "type": "Feature",
  "properties": {
    "addr:full":"217, Rue de Beauvais, 60280 Margny l\u00e8s Compi\u00e8gne Picardie 60280",
    "addr:housenumber":"217",
    "addr:postcode":"60280;60280",
    "addr:street":"Rue De Beauvais",
    "iso:country":"FR",
    "sg:address":"217, Rue de Beauvais, 60280 Margny l\u00e8s Compi\u00e8gne",
    "sg:orig_category":"Non-Classified Establishments",
    "sg:phone":"+33 3 44 83 31 99",
    "sg:postcode":"60280",
    "sg:province":"Picardie",
    "wof:name":"Entreprise Picarde De Pr\u00e9servation Des Bois S.a.r.l.",
    "wof:placetype":"venue"
},
  "geometry": {"coordinates":[2.814598,49.418087],"type":"Point"}
}