{
  "type": "Feature",
  "properties": {
    "iso:country":"FR",
    "sg:address":"Le Pont de la Cote 69240 ST VINCENT DE REINS",
    "sg:classifiers":[
        {
            "category":"Retail",
            "subcategory":"Laundry & Dry Cleaning",
            "type":"Services"
        }
    ],
    "sg:phone":"+33 4 74 89 69 68",
    "sg:postcode":"69240",
    "sg:province":"Rhone-Alpes",
    "sg:tags":[
        "textile"
    ],
    "wof:name":"Deveaux Sa",
    "wof:placetype":"venue"
},
  "geometry": {"coordinates":[4.389523,46.083019],"type":"Point"}
}