{
  "type": "Feature",
  "properties": {
    "addr:full":"B.P. 64, 87202 Saint Junien C\u00e9dex^^Parc d'Activit\u00e9s Axial, 87200 Saint Junien Limousin 87200",
    "addr:postcode":"87202;87200;87200",
    "addr:street":"B.P. 64",
    "iso:country":"FR",
    "sg:address":"B.P. 64, 87202 Saint Junien C\u00e9dex^^Parc d'Activit\u00e9s Axial, 87200 Saint Junien",
    "sg:orig_category":"Non-Classified Establishments",
    "sg:phone":"+33 5 55 43 05 55",
    "sg:postcode":"87200",
    "sg:province":"Limousin",
    "wof:name":"A.f.c. S.a.r.l. - Atelier De Fa\u00e7onnage Et Conditionnement",
    "wof:placetype":"venue"
},
  "geometry": {"coordinates":[0.90707,45.890388],"type":"Point"}
}