{
  "type": "Feature",
  "properties": {
    "iso:country":"FR",
    "sg:address":"ZI les Rippes",
    "sg:city":"Certines",
    "sg:orig_category":"Unclassifiable Establishments",
    "sg:phone":"+33 4 74 42 68 37",
    "sg:postcode":"01240",
    "sg:province":"Rhone-Alpes",
    "wof:name":"P.a.v. S.a.r.l. - Plastiques Andr\u00e9 Verch\u00e8re",
    "wof:placetype":"venue"
},
  "geometry": {"coordinates":[5.264672,46.132278],"type":"Point"}
}