{
  "type": "Feature",
  "properties": {
    "addr:full":"274, All\u00e9e Henri II de Montmorency, 34064 Montpellier C\u00e9dex 2^^274, All\u00e9e Henri II de Montmorency, 3 Aquitaine",
    "addr:housenumber":"274;2 ^ ^ 274;3",
    "addr:postcode":"34064",
    "addr:street":"Alle\u0301E Henri Ii De Montmorency;Ce\u0301Dex;Alle\u0301E Henri Ii De Montmorency",
    "iso:country":"FR",
    "sg:address":"274, All\u00e9e Henri II de Montmorency, 34064 Montpellier C\u00e9dex 2^^274, All\u00e9e Henri II de Montmorency, 3",
    "sg:orig_category":"Non-Classified Establishments",
    "sg:phone":"+33 4 67 15 70 00",
    "sg:province":"Aquitaine",
    "wof:name":"I.n.s.e.e. - Institut National De La Statistique Et Des Etudes",
    "wof:placetype":"venue"
},
  "geometry": {"coordinates":[3.886514,43.610138],"type":"Point"}
}