{
  "type": "Feature",
  "properties": {
    "addr:full":"10, Rue Chevreul, 92150 Suresnes Ile de France",
    "addr:housenumber":"10",
    "addr:postcode":"92150;ile",
    "addr:street":"Rue Chevreul",
    "iso:country":"FR",
    "sg:address":"10, Rue Chevreul, 92150 Suresnes",
    "sg:orig_category":"Non-Classified Establishments",
    "sg:phone":"+33 1 42 04 20 00",
    "sg:province":"Ile de France",
    "wof:name":"Orph\u00e9e Diffusion Conseil S.a.r.l.",
    "wof:placetype":"venue"
},
  "geometry": {"coordinates":[2.223041,48.86702],"type":"Point"}
}