{
  "type": "Feature",
  "properties": {
    "addr:full":"Les Douzes 01390 St Jean De Thurigneux Rhone-Alpes 01390",
    "addr:postcode":"01390;01390",
    "addr:street":"Rhone-Alpes",
    "iso:country":"FR",
    "sg:address":"Les Douzes 01390 St Jean De Thurigneux",
    "sg:classifiers":[
        {
            "category":"Manufacturing",
            "subcategory":"Tools & Machinery",
            "type":"Manufacturing & Wholesale Goods"
        }
    ],
    "sg:phone":"+33 4 74 00 82 14",
    "sg:postcode":"01390",
    "sg:province":"Rhone-Alpes",
    "sg:tags":[
        "metallurgy",
        "metalworking"
    ],
    "wof:name":"Secomi (secomi)",
    "wof:placetype":"venue"
},
  "geometry": {"coordinates":[4.90113,45.958912],"type":"Point"}
}