{
  "type": "Feature",
  "properties": {
    "addr:full":"116 Rue Des Poilus 59192 Beuvrages Nord Pas-de-Calais 59192",
    "addr:housenumber":"116",
    "addr:postcode":"59192;59192",
    "addr:street":"Rue Des Poilus",
    "iso:country":"FR",
    "sg:address":"116 Rue Des Poilus 59192 Beuvrages",
    "sg:classifiers":[
        {
            "category":"Building & Trades",
            "subcategory":"Construction",
            "type":"Services"
        }
    ],
    "sg:phone":"+33 3 27 46 82 21",
    "sg:postcode":"59192",
    "sg:province":"Nord Pas-de-Calais",
    "sg:tags":[
        "work",
        "public"
    ],
    "wof:name":"Societe Du Valenciennois De Travaux Publics",
    "wof:placetype":"venue"
},
  "geometry": {"coordinates":[3.507312,50.392918],"type":"Point"}
}