{
  "type": "Feature",
  "properties": {
    "iso:country":"FR",
    "sg:address":"ZA du Boulais",
    "sg:city":"Acign\u00e9",
    "sg:orig_category":"Non-Classified Establishments",
    "sg:phone":"+33 2 99 04 32 32",
    "sg:postcode":"35690",
    "sg:province":"Bretagne",
    "wof:name":"Alliance P.c.b. S.a.r.l.",
    "wof:placetype":"venue"
},
  "geometry": {"coordinates":[-1.534322,48.132721],"type":"Point"}
}