{
  "type": "Feature",
  "properties": {
    "iso:country":"FR",
    "sg:address":"648, Rue d'Orroire, 60400 Noyon",
    "sg:orig_category":"Unclassifiable Establishments",
    "sg:phone":"+33 3 44 09 32 32",
    "sg:province":"Picardie",
    "wof:name":"Oural France S.a.r.l.",
    "wof:placetype":"venue"
},
  "geometry": {"coordinates":[3.00871,49.576729],"type":"Point"}
}