{
  "type": "Feature",
  "properties": {
    "iso:country":"FR",
    "sg:address":"ZI de Mouguerre",
    "sg:city":"Mouguerre",
    "sg:orig_category":"Non-Classified Establishments",
    "sg:phone":"+33 5 59 31 89 01",
    "sg:postcode":"64990",
    "sg:province":"Aquitaine",
    "wof:name":"Atelier De Mouguerre S.a.r.l.",
    "wof:placetype":"venue"
},
  "geometry": {"coordinates":[-1.417994,43.467365],"type":"Point"}
}