{
  "type": "Feature",
  "properties": {
    "addr:full":"B.P. 18 Oyonnax C\u00e9dex Rhone-Alpes 01101",
    "addr:postcode":"01101",
    "addr:street":"B.P. 18;Rhone-Alpes",
    "iso:country":"FR",
    "sg:address":"B.P. 18",
    "sg:city":"Oyonnax C\u00e9dex",
    "sg:orig_category":"Non-Classified Establishments",
    "sg:phone":"+33 4 74 73 17 40",
    "sg:postcode":"01101",
    "sg:province":"Rhone-Alpes",
    "wof:name":"Maubourg S.a.",
    "wof:placetype":"venue"
},
  "geometry": {"coordinates":[5.658239,46.259094],"type":"Point"}
}