{
  "type": "Feature",
  "properties": {
    "addr:full":"21, Rue Amp\u00e8re - Parc d'activit\u00e9 Eurochanel, 76378 Dieppe C\u00e9dex Rhone-Alpes",
    "addr:housenumber":"21",
    "addr:postcode":"76378",
    "addr:street":"Rue Ampe\u0300Re Parc D'Activite \u0301 Eurochanel",
    "iso:country":"FR",
    "sg:address":"21, Rue Amp\u00e8re - Parc d'activit\u00e9 Eurochanel, 76378 Dieppe C\u00e9dex",
    "sg:orig_category":"Non-Classified Establishments",
    "sg:phone":"+33 2 35 82 68 66",
    "sg:province":"Rhone-Alpes",
    "wof:name":"Onet Propret\u00e9 S.a.r.l.",
    "wof:placetype":"venue"
},
  "geometry": {"coordinates":[1.120168,49.926033],"type":"Point"}
}