{
  "type": "Feature",
  "properties": {
    "iso:country":"FR",
    "sg:address":"33 Rue De La Maladrie 44120 Vertou",
    "sg:classifiers":[
        {
            "category":"Manufacturing",
            "subcategory":"Paper Products",
            "type":"Manufacturing & Wholesale Goods"
        }
    ],
    "sg:phone":"+33 2 40 80 25 25",
    "sg:province":"Pays de Loire",
    "sg:tags":[
        "packaging",
        "material",
        "-",
        "cardboard"
    ],
    "wof:name":"Tallineau Emballage Service Sa",
    "wof:placetype":"venue"
},
  "geometry": {"coordinates":[-1.487899,47.184574],"type":"Point"}
}