{
  "type": "Feature",
  "properties": {
    "addr:full":"70, Petit Chemin des Bruy\u00e8res, 69150 D\u00e9cines Charpieu Rhone-Alpes 69150",
    "addr:housenumber":"70",
    "addr:postcode":"69150;69150",
    "addr:street":"Petit Chemin Des Bruye\u0300Res;Rhone-Alpes",
    "iso:country":"FR",
    "sg:address":"70, Petit Chemin des Bruy\u00e8res, 69150 D\u00e9cines Charpieu",
    "sg:orig_category":"Non-Classified Establishments",
    "sg:phone":"+33 4 72 02 14 89",
    "sg:postcode":"69150",
    "sg:province":"Rhone-Alpes",
    "wof:name":"C.p.s. Cl\u00f4tures Pose S.a.r.l.",
    "wof:placetype":"venue"
},
  "geometry": {"coordinates":[4.939098,45.754871],"type":"Point"}
}