{
  "type": "Feature",
  "properties": {
    "iso:country":"FR",
    "sg:address":"Saint Joseph De Porterie Chemin Des Garniers Le Patis 44300 Nantes",
    "sg:classifiers":[
        {
            "category":"Shopping",
            "subcategory":"Hobbies, Toys, & Games",
            "type":"Retail Goods"
        }
    ],
    "sg:phone":"+33 2 28 01 02 89",
    "sg:postcode":"44300",
    "sg:province":"Pays de Loire",
    "sg:tags":[
        "product",
        "miscellaneous",
        "entertainment"
    ],
    "wof:name":"Manufacture Bretonne D'orgues Sarl",
    "wof:placetype":"venue"
},
  "geometry": {"coordinates":[-1.5359,47.25631],"type":"Point"}
}