{
  "type": "Feature",
  "properties": {
    "iso:country":"FR",
    "sg:address":"5 pl de Lille; Clermont Ferrand; 63000",
    "sg:city":"Clermont-Ferrand",
    "sg:classifiers":[
        {
            "category":"Banks & Credit Unions",
            "subcategory":"Bank",
            "type":"Services"
        }
    ],
    "sg:phone":"+33 3373914363",
    "sg:postcode":"63000",
    "sg:province":"Auvergne",
    "wof:name":"Banco Pinto & Sotto Mayor",
    "wof:placetype":"venue"
},
  "geometry": {"coordinates":[3.08183,45.777618],"type":"Point"}
}