{
  "type": "Feature",
  "properties": {
    "addr:full":"ZA Saint Didier des Bois Haute Normandie 27370",
    "addr:postcode":"27370",
    "addr:street":"Za Saint Didier Des Bois Haute Normandie",
    "iso:country":"FR",
    "sg:address":"ZA",
    "sg:city":"Saint Didier des Bois",
    "sg:orig_category":"Non-Classified Establishments",
    "sg:phone":"+33 2 32 50 67 57",
    "sg:postcode":"27370",
    "sg:province":"Haute Normandie",
    "wof:name":"Rica S.a.r.l.",
    "wof:placetype":"venue"
},
  "geometry": {"coordinates":[1.02641,49.235809],"type":"Point"}
}