{
  "type": "Feature",
  "properties": {
    "addr:full":"1580, Av. de Cos, 82000 Montauban Midi Pyr\u00e9n\u00e9es",
    "addr:housenumber":"1580",
    "addr:postcode":"82000",
    "addr:street":"Av. De Cos",
    "iso:country":"FR",
    "sg:address":"1580, Av. de Cos, 82000 Montauban",
    "sg:orig_category":"Unclassifiable Establishments",
    "sg:phone":"+33 5 63 91 01 46",
    "sg:province":"Midi Pyr\u00e9n\u00e9es",
    "wof:name":"Rosa Cat\u00e8ne France S.a.r.l.",
    "wof:placetype":"venue"
},
  "geometry": {"coordinates":[1.36463,44.037338],"type":"Point"}
}