{
  "type": "Feature",
  "properties": {
    "iso:country":"FR",
    "sg:address":"22, Rue Pierren Martin, 72000 Le Mans",
    "sg:orig_category":"Unclassifiable Establishments",
    "sg:phone":"+33 2 43 85 43 43",
    "sg:province":"Pays de Loire",
    "wof:name":"A.m.b. S.a.r.l. - Atelier Manceau De Bobinage",
    "wof:placetype":"venue"
},
  "geometry": {"coordinates":[0.207305,48.007851],"type":"Point"}
}