{
  "type": "Feature",
  "properties": {
    "iso:country":"FR",
    "sg:address":"B.P. 9",
    "sg:city":"Saint Paul les Durance C\u00e9dex^^13115 Saint Paul les Durance",
    "sg:orig_category":"Non-Classified Establishments",
    "sg:phone":"+33 4 42 25 13 00",
    "sg:postcode":"13115",
    "sg:province":"Provence-Alpes-C\u00f4te d'Azur",
    "wof:name":"Technicatome S.a.",
    "wof:placetype":"venue"
},
  "geometry": {"coordinates":[5.710884,43.689045],"type":"Point"}
}