{
  "type": "Feature",
  "properties": {
    "addr:full":"451, Rue du Mas Grenier, 82600 Verdun sur Garonne Midi Pyr\u00e9n\u00e9es",
    "addr:housenumber":"451",
    "addr:postcode":"82600",
    "addr:street":"Rue Du Mas Grenier",
    "iso:country":"FR",
    "sg:address":"451, Rue du Mas Grenier, 82600 Verdun sur Garonne",
    "sg:orig_category":"Unclassifiable Establishments",
    "sg:phone":"+33 5 63 27 00 10",
    "sg:province":"Midi Pyr\u00e9n\u00e9es",
    "wof:name":"Coop\u00e9rative Agricole L'union",
    "wof:placetype":"venue"
},
  "geometry": {"coordinates":[1.215425,43.802906],"type":"Point"}
}