{
  "type": "Feature",
  "properties": {
    "addr:full":"B.P. 5, 91620 Nozay C\u00e9dex^^4, Rue Gutemberg, 91620 Nozay Ile de France",
    "addr:housenumber":"5",
    "addr:postcode":"91620;91620;ile",
    "addr:street":"B.P.;Rue Gutemberg",
    "iso:country":"FR",
    "sg:address":"B.P. 5, 91620 Nozay C\u00e9dex^^4, Rue Gutemberg, 91620 Nozay",
    "sg:orig_category":"Non-Classified Establishments",
    "sg:phone":"+33 1 69 80 20 20",
    "sg:province":"Ile de France",
    "wof:name":"Roulement Service Agence Stock Central S.a.",
    "wof:placetype":"venue"
},
  "geometry": {"coordinates":[2.242235,48.66037],"type":"Point"}
}