{
  "type": "Feature",
  "properties": {
    "addr:full":"107, RN 20, 45520 Cercottes Cercottes Centre 45520",
    "addr:housenumber":"107;cercottes",
    "addr:postcode":"45520;45520",
    "addr:street":"Rn 20",
    "iso:country":"FR",
    "sg:address":"107, RN 20, 45520 Cercottes",
    "sg:city":"Cercottes",
    "sg:orig_category":"Unclassifiable Establishments",
    "sg:phone":"+33 2 38 75 31 05",
    "sg:postcode":"45520",
    "sg:province":"Centre",
    "wof:name":"B.m.i. S.a. - B\u00e9ton Moul\u00e9 Industriel",
    "wof:placetype":"venue"
},
  "geometry": {"coordinates":[1.87434,48.029846],"type":"Point"}
}