{
  "type": "Feature",
  "properties": {
    "addr:full":"Au Ch\u00e2teau 45200 Montargis Montargis Centre 45200",
    "addr:postcode":"45200;45200",
    "addr:street":"Au Cha\u0302Teau",
    "iso:country":"FR",
    "sg:address":"Au Ch\u00e2teau 45200 Montargis",
    "sg:city":"Montargis",
    "sg:classifiers":[
        {
            "category":"Professional",
            "subcategory":"Business Services",
            "type":"Services"
        }
    ],
    "sg:phone":"+33 2 38 95 06 30",
    "sg:postcode":"45200",
    "sg:province":"Centre",
    "sg:tags":[
        "training",
        "advice"
    ],
    "wof:name":"Ogec St Louis",
    "wof:placetype":"venue"
},
  "geometry": {"coordinates":[2.728704,47.997883],"type":"Point"}
}