{
  "type": "Feature",
  "properties": {
    "addr:full":"17, Bd Amp\u00e8re, 13014 Marseille Provence-Alpes-C\u00f4te d'Azur",
    "addr:housenumber":"17",
    "addr:postcode":"13014",
    "addr:street":"Bd Ampe\u0300Re",
    "iso:country":"FR",
    "sg:address":"17, Bd Amp\u00e8re, 13014 Marseille",
    "sg:orig_category":"Unclassifiable Establishments",
    "sg:phone":"+33 4 91 11 26 26",
    "sg:province":"Provence-Alpes-C\u00f4te d'Azur",
    "wof:name":"C.m.g.t. S.a. - Compagnie Maritime G\u00e9n\u00e9rale De Transit",
    "wof:placetype":"venue"
},
  "geometry": {"coordinates":[5.373127,43.338264],"type":"Point"}
}