{
  "type": "Feature",
  "properties": {
    "iso:country":"FR",
    "sg:address":"B.P. 164, 76410 Cl\u00e9on^^18, Rue de la Paix, 76410 Saint Aubin l\u00e8s Elbeuf",
    "sg:orig_category":"Non-Classified Establishments",
    "sg:phone":"+33 2 32 96 07 90",
    "sg:postcode":"76410",
    "sg:province":"Haute Normandie",
    "wof:name":"Coflexal S.a. - Complexes Flexibles D'aluminium",
    "wof:placetype":"venue"
},
  "geometry": {"coordinates":[1.010978,49.308239],"type":"Point"}
}