{
  "type": "Feature",
  "properties": {
    "iso:country":"FR",
    "sg:address":"Zi Bourdine 36200 Le P\u00eachereau",
    "sg:city":"Le P\u00eachereau",
    "sg:classifiers":[
        {
            "category":"Manufacturing",
            "subcategory":"Aerospace",
            "type":"Manufacturing & Wholesale Goods"
        }
    ],
    "sg:phone":"+33 2 54 01 63 00",
    "sg:postcode":"36200",
    "sg:province":"Centre",
    "sg:tags":[
        "equipment",
        "aeronautic",
        "transport",
        "vehicle"
    ],
    "wof:name":"Indraero Sa",
    "wof:placetype":"venue"
},
  "geometry": {"coordinates":[1.5476,46.57711],"type":"Point"}
}