{
  "type": "Feature",
  "properties": {
    "iso:country":"FR",
    "sg:address":"9, Cours Xavier Arnozan, 33000 Bordeaux",
    "sg:city":"Bordeaux",
    "sg:orig_category":"Unclassifiable Establishments",
    "sg:phone":"+33 5 56 52 98 92",
    "sg:postcode":"33000",
    "sg:province":"Aquitaine",
    "wof:name":"Beyerman H Et O S.a.",
    "wof:placetype":"venue"
},
  "geometry": {"coordinates":[-0.57343,44.848846],"type":"Point"}
}