{
  "type": "Feature",
  "properties": {
    "addr:full":"La Fossette Plage 83980 Le Lavandou Midi Pyr\u00e9n\u00e9es",
    "addr:postcode":"83980",
    "addr:street":"Plage",
    "iso:country":"FR",
    "sg:address":"La Fossette Plage 83980 Le Lavandou",
    "sg:classifiers":[
        {
            "category":"Travel",
            "subcategory":"Hotels & Motels",
            "type":"Entertainment"
        }
    ],
    "sg:phone":"+33 4 94 71 20 15",
    "sg:province":"Midi Pyr\u00e9n\u00e9es",
    "sg:tags":[
        "hotels",
        "business",
        "restaurant"
    ],
    "wof:name":"Hotel 83 ****",
    "wof:placetype":"venue"
},
  "geometry": {"coordinates":[6.3912,43.146694],"type":"Point"}
}