{
  "type": "Feature",
  "properties": {
    "iso:country":"FR",
    "sg:address":"12, Rue du Clos de Brye, 28630 Sours",
    "sg:city":"Sours",
    "sg:orig_category":"Unclassifiable Establishments",
    "sg:phone":"+33 2 37 25 93 17",
    "sg:postcode":"28630",
    "sg:province":"Centre",
    "wof:name":"Casseri De La Vall\u00e9e S.a.r.l.",
    "wof:placetype":"venue"
},
  "geometry": {"coordinates":[1.593423,48.408485],"type":"Point"}
}