{
  "type": "Feature",
  "properties": {
    "addr:full":"1 Rue Jean Carasso 95870 Bezons Ile de France",
    "addr:housenumber":"1",
    "addr:postcode":"95870;ile",
    "addr:street":"Rue Jean Carasso",
    "iso:country":"FR",
    "sg:address":"1 Rue Jean Carasso 95870 Bezons",
    "sg:classifiers":[
        {
            "category":"Manufacturing",
            "subcategory":"Rubber & Plastics",
            "type":"Manufacturing & Wholesale Goods"
        }
    ],
    "sg:phone":"+33 1 34 23 38 43",
    "sg:province":"Ile de France",
    "wof:name":"Pergo Sa",
    "wof:placetype":"venue"
},
  "geometry": {"coordinates":[2.21361,48.92646],"type":"Point"}
}