{
  "type": "Feature",
  "properties": {
    "iso:country":"FR",
    "sg:address":"Za La Mothe 48500 Banassac",
    "sg:classifiers":[
        {
            "category":"Food & Beverages",
            "subcategory":"Dairy",
            "type":"Retail Goods"
        }
    ],
    "sg:phone":"+33 4 66 32 99 74",
    "sg:postcode":"48500",
    "sg:province":"Languedoc-Roussillon",
    "sg:tags":[
        "product",
        "related"
    ],
    "wof:name":"Sa La Bergerie De Lozere",
    "wof:placetype":"venue"
},
  "geometry": {"coordinates":[3.200146,44.436512],"type":"Point"}
}