{
  "type": "Feature",
  "properties": {
    "addr:full":"55 All\u00e9e Cavali\u00e8re Meg\u00e8ve Rhone-Alpes 74120",
    "addr:housenumber":"55",
    "addr:postcode":"74120",
    "addr:street":"Alle\u0301E Cavalie\u0300Re;Rhone-Alpes",
    "iso:country":"FR",
    "sg:address":"55 All\u00e9e Cavali\u00e8re",
    "sg:city":"Meg\u00e8ve",
    "sg:classifiers":[
        {
            "category":"Banks & Credit Unions",
            "subcategory":"Financial Services",
            "type":"Services"
        }
    ],
    "sg:phone":"+33 4 50 21 26 30",
    "sg:postcode":"74120",
    "sg:province":"Rhone-Alpes",
    "sg:tags":[
        "banking",
        "finance",
        "insurance"
    ],
    "wof:name":"Altitude Conseil Sa",
    "wof:placetype":"venue"
},
  "geometry": {"coordinates":[6.6162,45.859329],"type":"Point"}
}