{
  "type": "Feature",
  "properties": {
    "iso:country":"FR",
    "sg:address":"8, Rue Jean Rostand, 69740 Genas",
    "sg:orig_category":"Unclassifiable Establishments",
    "sg:phone":"+33 4 72 79 59 90",
    "sg:province":"Rhone-Alpes",
    "wof:name":"I.m.p.c.o. B\u00e9ru Technologies S.a.r.l.",
    "wof:placetype":"venue"
},
  "geometry": {"coordinates":[4.983635,45.718784],"type":"Point"}
}