{
  "type": "Feature",
  "properties": {
    "addr:full":"39 rue du 11 Novembre 42100 ST ETIENNE Rhone-Alpes 42100",
    "addr:housenumber":"39",
    "addr:postcode":"42100;42100",
    "addr:street":"Rue Du 11 Novembre",
    "iso:country":"FR",
    "sg:address":"39 rue du 11 Novembre 42100 ST ETIENNE",
    "sg:orig_category":"Diamond Grinders For Polycrystalline Diamond Tools",
    "sg:phone":"+33 4 77 57 17 68",
    "sg:postcode":"42100",
    "sg:province":"Rhone-Alpes",
    "wof:name":"Adamax France S.a.",
    "wof:placetype":"venue"
},
  "geometry": {"coordinates":[4.391502,45.425198],"type":"Point"}
}