{
  "type": "Feature",
  "properties": {
    "addr:full":"4 Rue Adolphe Crespin 45000 Orl\u00e9ans Orl\u00e9ans Centre 45000",
    "addr:housenumber":"4",
    "addr:postcode":"45000;45000",
    "addr:street":"Rue Adolphe Crespin",
    "iso:country":"FR",
    "sg:address":"4 Rue Adolphe Crespin 45000 Orl\u00e9ans",
    "sg:city":"Orl\u00e9ans",
    "sg:classifiers":[
        {
            "category":"Professional",
            "subcategory":"Business Services",
            "type":"Services"
        }
    ],
    "sg:phone":"+33 2 38 77 44 55",
    "sg:postcode":"45000",
    "sg:province":"Centre",
    "sg:tags":[
        "body",
        "advice"
    ],
    "wof:name":"Association Aide Domicile Personnes Agees Agglomeration Orleans",
    "wof:placetype":"venue"
},
  "geometry": {"coordinates":[1.904875,47.903385],"type":"Point"}
}