{
  "type": "Feature",
  "properties": {
    "addr:full":"Route D Invault 45300 Manchecourt Courcelles Centre 45300",
    "addr:postcode":"45300;45300",
    "addr:street":"Route D Invault;Courcelles",
    "iso:country":"FR",
    "sg:address":"Route D Invault 45300 Manchecourt",
    "sg:city":"Courcelles",
    "sg:classifiers":[
        {
            "category":"Home & Garden",
            "subcategory":"Furniture",
            "type":"Retail Goods"
        }
    ],
    "sg:phone":"+33 2 38 30 13 73",
    "sg:postcode":"45300",
    "sg:province":"Centre",
    "sg:tags":[
        "household",
        "wood"
    ],
    "wof:name":"Pincon Sa",
    "wof:placetype":"venue"
},
  "geometry": {"coordinates":[2.21384,48.064007],"type":"Point"}
}