{
  "type": "Feature",
  "properties": {
    "addr:full":"652 Bd Jacques Barthelemy 13190 Allauch Nord Pas-de-Calais",
    "addr:housenumber":"652",
    "addr:postcode":"13190",
    "addr:street":"Bd Jacques Barthelemy",
    "iso:country":"FR",
    "sg:address":"652 Bd Jacques Barthelemy 13190 Allauch",
    "sg:classifiers":[
        {
            "category":"Building & Trades",
            "subcategory":"Construction",
            "type":"Services"
        }
    ],
    "sg:phone":"+33 4 91 68 13 91",
    "sg:province":"Nord Pas-de-Calais",
    "sg:tags":[
        "work",
        "public"
    ],
    "wof:name":"Entreprise De Travaux Publics Mediterranees Etpm",
    "wof:placetype":"venue"
},
  "geometry": {"coordinates":[5.482075,43.336685],"type":"Point"}
}