{
  "type": "Feature",
  "properties": {
    "addr:full":"A\u00e9roport Bordeaux M\u00e9rignac 33700 M\u00e9rignac M\u00e9rignac Aquitaine 33700",
    "addr:postcode":"33700;33700",
    "iso:country":"FR",
    "sg:address":"A\u00e9roport Bordeaux M\u00e9rignac 33700 M\u00e9rignac",
    "sg:city":"M\u00e9rignac",
    "sg:classifiers":[
        {
            "category":"Professional",
            "subcategory":"Business Services",
            "type":"Services"
        }
    ],
    "sg:phone":"+33 5 56 47 84 22",
    "sg:postcode":"33700",
    "sg:province":"Aquitaine",
    "sg:tags":[
        "travel",
        "transport",
        "road"
    ],
    "wof:name":"Budget Merignac",
    "wof:placetype":"venue"
},
  "geometry": {"coordinates":[-0.70278,44.82909],"type":"Point"}
}