{
  "type": "Feature",
  "properties": {
    "iso:country":"FR",
    "sg:address":"32 Rue Danton 10500 Pont Ste Marie",
    "sg:classifiers":[
        {
            "category":"Professional",
            "subcategory":"Business Services",
            "type":"Services"
        }
    ],
    "sg:phone":"+33 3 25 74 32 76",
    "sg:postcode":"10500",
    "sg:province":"Champagne",
    "sg:tags":[
        "pharmaceutical",
        "advice",
        "-",
        "chemical",
        "chemistry",
        "by-product"
    ],
    "wof:name":"Di Prot Net Sarl",
    "wof:placetype":"venue"
},
  "geometry": {"coordinates":[-90.082191,35.611755],"type":"Point"}
}