{
  "type": "Feature",
  "properties": {
    "iso:country":"FR",
    "sg:address":"B.P. 39, 56230 Questembert C\u00e9dex^^ZA K\u00e9rabraham, 56230 Questembert",
    "sg:city":"Questembert",
    "sg:orig_category":"Non-Classified Establishments",
    "sg:phone":"+33 2 97 26 56 56",
    "sg:postcode":"56230",
    "sg:province":"Bretagne",
    "wof:name":"Plastigraf S.a.r.l.",
    "wof:placetype":"venue"
},
  "geometry": {"coordinates":[-2.524527,47.63282],"type":"Point"}
}