{
  "type": "Feature",
  "properties": {
    "iso:country":"FR",
    "sg:address":"Prairie Du Chateau 46120 Lacapelle Marival",
    "sg:classifiers":[
        {
            "category":"Utilities",
            "subcategory":"Electric",
            "type":"Services"
        }
    ],
    "sg:phone":"+33 5 65 40 82 70",
    "sg:postcode":"46120",
    "sg:province":"Midi Pyr\u00e9n\u00e9es",
    "sg:tags":[
        "electricity",
        "raw",
        "energy",
        "material"
    ],
    "wof:name":"Electricite De France (edf)",
    "wof:placetype":"venue"
},
  "geometry": {"coordinates":[1.922292,44.727261],"type":"Point"}
}