{
  "type": "Feature",
  "properties": {
    "iso:country":"FR",
    "sg:address":"167/169, Av. Pablo Picasso, 92024 Nanterre",
    "sg:orig_category":"Non-Classified Establishments",
    "sg:phone":"+33 1 55 51 10 20",
    "sg:province":"Languedoc-Roussillon",
    "wof:name":"Coriolis T\u00e9l\u00e9com S.a.s.",
    "wof:placetype":"venue"
},
  "geometry": {"coordinates":[2.229967,48.890892],"type":"Point"}
}