{
  "type": "Feature",
  "properties": {
    "addr:full":"ZA le Planet Ribiers Centre 05300",
    "addr:housenumber":"ribiers",
    "addr:postcode":"05300",
    "addr:street":"Za Le",
    "iso:country":"FR",
    "sg:address":"ZA le Planet",
    "sg:city":"Ribiers",
    "sg:orig_category":"Non-Classified Establishments",
    "sg:phone":"+33 4 92 63 25 25",
    "sg:postcode":"05300",
    "sg:province":"Centre",
    "wof:name":"Alp'union S.a.",
    "wof:placetype":"venue"
},
  "geometry": {"coordinates":[5.85629,44.231346],"type":"Point"}
}