{
  "type": "Feature",
  "properties": {
    "addr:full":"B.P. 53, 31675 Lab\u00e8ge C\u00e9dex^^Voie de l'Occitane - Immeuble Arizona B, 31670 Lab\u00e8ge Midi Pyr\u00e9n\u00e9es",
    "addr:postcode":"31675;31670",
    "addr:street":"B.P. 53",
    "iso:country":"FR",
    "sg:address":"B.P. 53, 31675 Lab\u00e8ge C\u00e9dex^^Voie de l'Occitane - Immeuble Arizona B, 31670 Lab\u00e8ge",
    "sg:orig_category":"Non-Classified Establishments",
    "sg:phone":"+33 5 61 00 51 30",
    "sg:province":"Midi Pyr\u00e9n\u00e9es",
    "wof:name":"T\u00e9ra Syst\u00e8mes S.a.",
    "wof:placetype":"venue"
},
  "geometry": {"coordinates":[1.521972,43.536385],"type":"Point"}
}