{
  "type": "Feature",
  "properties": {
    "iso:country":"FR",
    "sg:address":"ZI Nord",
    "sg:city":"Marmande",
    "sg:orig_category":"Unclassifiable Establishments",
    "sg:phone":"+33 5 53 64 02 75",
    "sg:postcode":"47200",
    "sg:province":"Aquitaine",
    "wof:name":"Arici Et Fils S.a.",
    "wof:placetype":"venue"
},
  "geometry": {"coordinates":[0.165555,44.50359],"type":"Point"}
}