{
  "type": "Feature",
  "properties": {
    "addr:full":"Rte de la Drance - Z.I. d'Amphion Amphion les Bains Rhone-Alpes 74500",
    "addr:postcode":"74500",
    "addr:street":"Rte De La Drance Z.I. D'Amphion",
    "iso:country":"FR",
    "sg:address":"Rte de la Drance - Z.I. d'Amphion",
    "sg:city":"Amphion les Bains",
    "sg:orig_category":"Unclassifiable Establishments",
    "sg:phone":"+33 4 50 70 02 17",
    "sg:postcode":"74500",
    "sg:province":"Rhone-Alpes",
    "wof:name":"Orelec S.a.",
    "wof:placetype":"venue"
},
  "geometry": {"coordinates":[6.54014,46.394909],"type":"Point"}
}