{
  "type": "Feature",
  "properties": {
    "addr:full":"Av. de Londres - Grand Saint Charles Perpignan C\u00e9dex Midi Pyr\u00e9n\u00e9es 66030",
    "addr:postcode":"66030",
    "addr:street":"Av. De Londres;Charles",
    "iso:country":"FR",
    "sg:address":"Av. de Londres - Grand Saint Charles",
    "sg:city":"Perpignan C\u00e9dex",
    "sg:orig_category":"Non-Classified Establishments",
    "sg:phone":"+33 4 68 54 50 55",
    "sg:postcode":"66030",
    "sg:province":"Midi Pyr\u00e9n\u00e9es",
    "wof:name":"Arco Fruits S.a.s.",
    "wof:placetype":"venue"
},
  "geometry": {"coordinates":[2.8966,42.700611],"type":"Point"}
}