{
  "type": "Feature",
  "properties": {
    "addr:full":"985, Rte des Villards - La Tours Clerton, 74300 Magland Rhone-Alpes",
    "addr:housenumber":"985",
    "addr:postcode":"74300",
    "addr:street":"Rte Des Villards La;Clerton",
    "iso:country":"FR",
    "sg:address":"985, Rte des Villards - La Tours Clerton, 74300 Magland",
    "sg:orig_category":"Non-Classified Establishments",
    "sg:phone":"+33 4 50 34 70 59",
    "sg:province":"Rhone-Alpes",
    "wof:name":"Soci\u00e9t\u00e9 Nouvelle Anthoine Emile Magland S.a.",
    "wof:placetype":"venue"
},
  "geometry": {"coordinates":[6.633185,45.987919],"type":"Point"}
}