{
  "type": "Feature",
  "properties": {
    "iso:country":"FR",
    "sg:address":"35, Rue Louis de Broglie, 21000 Dijon",
    "sg:city":"Dijon",
    "sg:orig_category":"Unclassifiable Establishments",
    "sg:phone":"+33 3 80 78 82 40",
    "sg:postcode":"21000",
    "sg:province":"Bourgogne",
    "wof:name":"Banque De D\u00e9veloppement Des Pme S.a.",
    "wof:placetype":"venue"
},
  "geometry": {"coordinates":[5.044019,47.357559],"type":"Point"}
}