{
  "type": "Feature",
  "properties": {
    "addr:full":"54/56, Rue du Faubourg Saint Honor\u00e9, 75008 Paris Ile de France",
    "addr:housenumber":"54 / 56",
    "addr:postcode":"75008",
    "addr:street":"Rue Du Faubourg Saint Honore\u0301",
    "iso:country":"FR",
    "sg:address":"54/56, Rue du Faubourg Saint Honor\u00e9, 75008 Paris",
    "sg:orig_category":"Unclassifiable Establishments",
    "sg:phone":"+33 1 44 94 33 33",
    "sg:province":"Ile de France",
    "wof:name":"Chlo\u00e9 International S.a.",
    "wof:placetype":"venue"
},
  "geometry": {"coordinates":[2.319485,48.86961],"type":"Point"}
}