{
  "type": "Feature",
  "properties": {
    "iso:country":"FR",
    "sg:address":"B.P. 157, 42160 Andr\u00e9zieux Bouth\u00e9on C\u00e9dex^^Impasse Charles Dalli\u00e8re - ZI Sud, 42160 Andr\u00e9zieux Bouth",
    "sg:orig_category":"Non-Classified Establishments",
    "sg:phone":"+33 4 77 36 42 02",
    "sg:postcode":"42160",
    "sg:province":"Rhone-Alpes",
    "wof:name":"C.s.e. S.a.r.l. - Cartonnages Services Emballages",
    "wof:placetype":"venue"
},
  "geometry": {"coordinates":[4.25674,45.52943],"type":"Point"}
}