{
  "type": "Feature",
  "properties": {
    "addr:full":"Rue Port Aux Planches 54480 Cirey Sur Vezouze Lorraine 54480",
    "addr:postcode":"54480;54480",
    "addr:street":"Rue Port Aux Planches;Vezouze Lorraine",
    "iso:country":"FR",
    "sg:address":"Rue Port Aux Planches 54480 Cirey Sur Vezouze",
    "sg:classifiers":[
        {
            "category":"Manufacturing",
            "subcategory":"Glass & Minerals",
            "type":"Manufacturing & Wholesale Goods"
        }
    ],
    "sg:phone":"+33 3 83 42 50 22",
    "sg:postcode":"54480",
    "sg:province":"Lorraine",
    "sg:tags":[
        "building",
        "material"
    ],
    "wof:name":"Lhuillier Seyer Sa",
    "wof:placetype":"venue"
},
  "geometry": {"coordinates":[6.945875,48.577583],"type":"Point"}
}