{
  "type": "Feature",
  "properties": {
    "addr:full":"Bd Pierre Lefaucheux 72230 Arnage Pays de Loire 72230",
    "addr:postcode":"72230;72230",
    "addr:street":"Bd Pierre Lefaucheux",
    "iso:country":"FR",
    "sg:address":"Bd Pierre Lefaucheux 72230 Arnage",
    "sg:classifiers":[
        {
            "category":"Airport",
            "type":"Transportation"
        }
    ],
    "sg:phone":"+33 2 43 39 34 50",
    "sg:postcode":"72230",
    "sg:province":"Pays de Loire",
    "sg:tags":[
        "transport",
        "air"
    ],
    "wof:name":"Sdv Logistik International",
    "wof:placetype":"venue"
},
  "geometry": {"coordinates":[0.186801,47.935577],"type":"Point"}
}