{
  "type": "Feature",
  "properties": {
    "iso:country":"FR",
    "sg:address":"28 ter, Rue Belgrand, 75020 Paris",
    "sg:orig_category":"Non-Classified Establishments",
    "sg:phone":"+33 1 47 97 98 41",
    "sg:postcode":"75020",
    "sg:province":"Ile de France",
    "wof:name":"Bier Stores De Tournus S.a.",
    "wof:placetype":"venue"
},
  "geometry": {"coordinates":[2.402424,48.864605],"type":"Point"}
}