{
  "type": "Feature",
  "properties": {
    "addr:full":"3 rue de la Plaine 68500 Guebwiller Guebwiller Alsace 68500",
    "addr:housenumber":"3",
    "addr:postcode":"68500;68500",
    "addr:street":"Rue De La Plaine",
    "iso:country":"FR",
    "sg:address":"3 rue de la Plaine 68500 Guebwiller",
    "sg:city":"Guebwiller",
    "sg:classifiers":[
        {
            "category":"Shopping",
            "subcategory":"Computers & Home Electronics",
            "type":"Retail Goods"
        }
    ],
    "sg:phone":"+33 3 89 74 99 99",
    "sg:postcode":"68500",
    "sg:province":"Alsace",
    "sg:tags":[
        "coupler",
        "quick-acting"
    ],
    "wof:name":"Staubli Raccord France Sas",
    "wof:placetype":"venue"
},
  "geometry": {"coordinates":[7.230021,47.897099],"type":"Point"}
}