{
  "type": "Feature",
  "properties": {
    "addr:full":"37, Rue de Blanzet, 63100 Clermont Ferrand Clermont-Ferrand Auvergne 63100",
    "addr:housenumber":"37",
    "addr:postcode":"63100;63100",
    "addr:street":"Rue De Blanzet",
    "iso:country":"FR",
    "sg:address":"37, Rue de Blanzet, 63100 Clermont Ferrand",
    "sg:city":"Clermont-Ferrand",
    "sg:orig_category":"Non-Classified Establishments",
    "sg:phone":"+33 4 73 91 09 15",
    "sg:postcode":"63100",
    "sg:province":"Auvergne",
    "wof:name":"Secofi S.a.r.l.",
    "wof:placetype":"venue"
},
  "geometry": {"coordinates":[3.08452,45.787159],"type":"Point"}
}