{
  "type": "Feature",
  "properties": {
    "addr:full":"Rue des Condamines - ZI les Condamines Pignan Languedoc-Roussillon 34570",
    "addr:postcode":"34570",
    "addr:street":"Rue Des Condamines Zi Les",
    "iso:country":"FR",
    "sg:address":"Rue des Condamines - ZI les Condamines",
    "sg:city":"Pignan",
    "sg:orig_category":"Non-Classified Establishments",
    "sg:phone":"+33 4 67 47 75 27",
    "sg:postcode":"34570",
    "sg:province":"Languedoc-Roussillon",
    "wof:name":"Languedoc Hygi\u00e8ne Assist. S.a.r.l.",
    "wof:placetype":"venue"
},
  "geometry": {"coordinates":[3.75978,43.583614],"type":"Point"}
}