{
  "type": "Feature",
  "properties": {
    "iso:country":"FR",
    "sg:address":"Rte de Carpentras",
    "sg:city":"Le Pontet",
    "sg:orig_category":"Unclassifiable Establishments",
    "sg:phone":"+33 4 90 31 67 00",
    "sg:postcode":"84130",
    "sg:province":"Provence-Alpes-C\u00f4te d'Azur",
    "wof:name":"Campbell France S.a.s",
    "wof:placetype":"venue"
},
  "geometry": {"coordinates":[4.87167,43.973705],"type":"Point"}
}