{
  "type": "Feature",
  "properties": {
    "addr:full":"Boulevard Pierre Lefaucheux Zis 72000 Le Mans Pays de Loire 72000",
    "addr:postcode":"72000;72000",
    "addr:street":"Boulevard Pierre Lefaucheux Zis",
    "iso:country":"FR",
    "sg:address":"Boulevard Pierre Lefaucheux Zis 72000 Le Mans",
    "sg:classifiers":[
        {
            "category":"Government",
            "subcategory":"Department Of Motor Vehicles",
            "type":"Public Place"
        }
    ],
    "sg:phone":"+33 2 43 50 65 05",
    "sg:postcode":"72000",
    "sg:province":"Pays de Loire",
    "sg:tags":[
        "equipment",
        "industrial",
        "transport",
        "motor-cars"
    ],
    "wof:name":"Les Grands Garages De La Sarthe Peugeot",
    "wof:placetype":"venue"
},
  "geometry": {"coordinates":[0.197813,48.008095],"type":"Point"}
}