{
  "type": "Feature",
  "properties": {
    "iso:country":"FR",
    "sg:address":"94537 Thiais C\u00e9dex^^16, Rue des Oliviers - Senia 331, 94320 Thiais",
    "sg:orig_category":"Non-Classified Establishments",
    "sg:phone":"+33 1 46 75 01 23",
    "sg:postcode":"94320",
    "sg:province":"Ile de France",
    "wof:name":"Cork International S.a.",
    "wof:placetype":"venue"
},
  "geometry": {"coordinates":[2.390409,48.765186],"type":"Point"}
}