{
  "type": "Feature",
  "properties": {
    "addr:full":"3, Rue de la D\u00e9couverte, 31670 Lab\u00e8ge Midi Pyr\u00e9n\u00e9es",
    "addr:housenumber":"3",
    "addr:postcode":"31670",
    "addr:street":"Rue De La De\u0301Couverte",
    "iso:country":"FR",
    "sg:address":"3, Rue de la D\u00e9couverte, 31670 Lab\u00e8ge",
    "sg:orig_category":"Unclassifiable Establishments",
    "sg:phone":"+33 5 61 00 73 73",
    "sg:province":"Midi Pyr\u00e9n\u00e9es",
    "wof:name":"Papeterie De France S.n.c.",
    "wof:placetype":"venue"
},
  "geometry": {"coordinates":[1.504438,43.546341],"type":"Point"}
}