{
  "type": "Feature",
  "properties": {
    "addr:full":"38-46 Rue Calmette Et Gu\u00e9rin 78501 Sartrouville Vill\u00e9 Alsace 67220",
    "addr:housenumber":"38-46",
    "addr:postcode":"78501;67220",
    "addr:street":"Rue Calmette Et Gue\u0301Rin;Ville\u0301",
    "iso:country":"FR",
    "sg:address":"38-46 Rue Calmette Et Gu\u00e9rin 78501 Sartrouville",
    "sg:city":"Vill\u00e9",
    "sg:classifiers":[
        {
            "category":"Professional",
            "subcategory":"Engineering",
            "type":"Services"
        }
    ],
    "sg:phone":"+33 1 30 86 56 00",
    "sg:postcode":"67220",
    "sg:province":"Alsace",
    "sg:tags":[
        "machine",
        "-",
        "mechanical"
    ],
    "wof:name":"Busak Plus Shamban Sa",
    "wof:placetype":"venue"
},
  "geometry": {"coordinates":[2.190531,48.94973],"type":"Point"}
}