{
  "type": "Feature",
  "properties": {
    "addr:full":"Quartier Arnauds 83690 Salernes Basse Normandie",
    "addr:postcode":"83690",
    "iso:country":"FR",
    "sg:address":"Quartier Arnauds 83690 Salernes",
    "sg:classifiers":[
        {
            "category":"Manufacturing",
            "subcategory":"Building Materials",
            "type":"Manufacturing & Wholesale Goods"
        }
    ],
    "sg:phone":"+33 4 94 70 70 70",
    "sg:province":"Basse Normandie",
    "sg:tags":[
        "glass",
        "ceramic"
    ],
    "wof:name":"Ste D'exploitation Des Etablissements Basset",
    "wof:placetype":"venue"
},
  "geometry": {"coordinates":[6.234065,43.563431],"type":"Point"}
}