{
  "type": "Feature",
  "properties": {
    "addr:full":"18, Rue de Folin, 64200 Biarritz Biarritz Aquitaine 64200",
    "addr:housenumber":"18",
    "addr:postcode":"64200;64200",
    "addr:street":"Rue De Folin",
    "iso:country":"FR",
    "sg:address":"18, Rue de Folin, 64200 Biarritz",
    "sg:city":"Biarritz",
    "sg:orig_category":"Non-Classified Establishments",
    "sg:phone":"+33 5 59 43 80 30",
    "sg:postcode":"64200",
    "sg:province":"Aquitaine",
    "wof:name":"S.a.i. S.a. - Soci\u00e9t\u00e9 Atlantique D'impression",
    "wof:placetype":"venue"
},
  "geometry": {"coordinates":[-1.543781,43.479206],"type":"Point"}
}