{
  "type": "Feature",
  "properties": {
    "addr:full":"B.P. 47, 25502 Morteau C\u00e9dex^^3, Rue Victor Hugo, 25500 Morteau Franche Comt\u00e9 25500",
    "addr:postcode":"25502;25500;25500",
    "addr:street":"B.P. 47;Rue Victor Hugo;Franche Comte\u0301",
    "iso:country":"FR",
    "sg:address":"B.P. 47, 25502 Morteau C\u00e9dex^^3, Rue Victor Hugo, 25500 Morteau",
    "sg:orig_category":"Non-Classified Establishments",
    "sg:phone":"+33 3 81 67 47 43",
    "sg:postcode":"25500",
    "sg:province":"Franche Comt\u00e9",
    "wof:name":"Chocolats Klaus S.a.",
    "wof:placetype":"venue"
},
  "geometry": {"coordinates":[6.610826,47.022823],"type":"Point"}
}