{
  "type": "Feature",
  "properties": {
    "iso:country":"FR",
    "sg:address":"B.P. 5, 41200 Romorantin Lanthenay^^26, Rte de Bois Joly, 41200 Romorantin Lanthenay",
    "sg:city":"Villefranche-sur-Cher",
    "sg:orig_category":"Non-Classified Establishments",
    "sg:phone":"+33 2 54 76 24 70",
    "sg:postcode":"41200",
    "sg:province":"Centre",
    "wof:name":"Graphi Contact S.a.r.l.",
    "wof:placetype":"venue"
},
  "geometry": {"coordinates":[1.76969,47.294876],"type":"Point"}
}