{
  "type": "Feature",
  "properties": {
    "addr:full":"Pl R\u00e9sistance; Plon\u00e9vez du Faou; 29530 Collorec Bretagne 29530",
    "addr:postcode":"29530;29530",
    "addr:street":"Pl Re\u0301Sistance Plone\u0301Vez Du Faou;Collorec Bretagne",
    "iso:country":"FR",
    "sg:address":"Pl R\u00e9sistance; Plon\u00e9vez du Faou; 29530",
    "sg:city":"Collorec",
    "sg:classifiers":[
        {
            "category":"Banks & Credit Unions",
            "subcategory":"Bank",
            "type":"Services"
        }
    ],
    "sg:phone":"+33 2 98 86 81 43",
    "sg:postcode":"29530",
    "sg:province":"Bretagne",
    "wof:name":"Cr\u00e9dit Agricole Mutuel",
    "wof:placetype":"venue"
},
  "geometry": {"coordinates":[-3.825969,48.25256],"type":"Point"}
}