{
  "type": "Feature",
  "properties": {
    "iso:country":"FR",
    "sg:address":"BP 1 Cedex 69551 Feyzin",
    "sg:classifiers":[
        {
            "category":"Manufacturing",
            "subcategory":"Rubber & Plastics",
            "type":"Manufacturing & Wholesale Goods"
        }
    ],
    "sg:phone":"+33 4 72 09 29 29",
    "sg:province":"Rhone-Alpes",
    "wof:name":"Plymouth",
    "wof:placetype":"venue"
},
  "geometry": {"coordinates":[4.85674,45.669941],"type":"Point"}
}