{
  "type": "Feature",
  "properties": {
    "addr:full":"157 Rue Du Ladhof 68025 Colmar Cedex Alsace",
    "addr:housenumber":"157",
    "addr:postcode":"68025;cedex",
    "addr:street":"Rue Du Ladhof",
    "iso:country":"FR",
    "sg:address":"157 Rue Du Ladhof 68025 Colmar Cedex",
    "sg:classifiers":[
        {
            "category":"Professional",
            "subcategory":"Business Services",
            "type":"Services"
        }
    ],
    "sg:phone":"+33 3 89 21 16 21",
    "sg:province":"Alsace",
    "sg:tags":[
        "food",
        "product",
        "dairy",
        "advice",
        "related"
    ],
    "wof:name":"Scapalsace",
    "wof:placetype":"venue"
},
  "geometry": {"coordinates":[7.36206,48.08844],"type":"Point"}
}