{
  "type": "Feature",
  "properties": {
    "iso:country":"FR",
    "sg:address":"ZI du Coin 42400 ST CHAMOND",
    "sg:classifiers":[
        {
            "category":"Banks & Credit Unions",
            "subcategory":"Investment Brokerage",
            "type":"Services"
        }
    ],
    "sg:phone":"+33 4 77 22 27 71",
    "sg:postcode":"42400",
    "sg:province":"Rhone-Alpes",
    "sg:tags":[
        "ovens",
        "industrial",
        "heated",
        "gas",
        "oil-fired",
        "electrically",
        "furnace"
    ],
    "wof:name":"Elti",
    "wof:placetype":"venue"
},
  "geometry": {"coordinates":[4.512304,45.473969],"type":"Point"}
}