{
  "type": "Feature",
  "properties": {
    "addr:full":"40, Av. des Terroirs de France, 75611 Paris C\u00e9dex 12 Aquitaine",
    "addr:housenumber":"12",
    "addr:postcode":"75611",
    "addr:street":"40 Av. Des Terroirs De France",
    "iso:country":"FR",
    "sg:address":"40, Av. des Terroirs de France, 75611 Paris C\u00e9dex 12",
    "sg:orig_category":"Non-Classified Establishments",
    "sg:phone":"+33 1 44 73 44 13",
    "sg:province":"Aquitaine",
    "wof:name":"Casademont France S.a.r.l.",
    "wof:placetype":"venue"
},
  "geometry": {"coordinates":[2.38681,48.830635],"type":"Point"}
}