{
  "type": "Feature",
  "properties": {
    "addr:full":"B.P. 302, 59020 Lille C\u00e9dex^^111, Rue Saint Luc, 59800 Lille Nord Pas-de-Calais 59800",
    "addr:housenumber":"b.p. 302",
    "addr:postcode":"59020;59800;59800",
    "addr:street":"Rue Saint Luc",
    "iso:country":"FR",
    "sg:address":"B.P. 302, 59020 Lille C\u00e9dex^^111, Rue Saint Luc, 59800 Lille",
    "sg:orig_category":"Butoirs en caoutchouc Caoutchouc Caoutchouc anti-usure, Garnissage de Caoutchouc cellulaire et/ou pr",
    "sg:phone":"+33 3 20 21 99 50",
    "sg:postcode":"59800",
    "sg:province":"Nord Pas-de-Calais",
    "wof:name":"Cafac S.a.",
    "wof:placetype":"venue"
},
  "geometry": {"coordinates":[3.08024,50.636189],"type":"Point"}
}