{
  "type": "Feature",
  "properties": {
    "iso:country":"FR",
    "sg:address":"19, Bd du Midi, 76108 Rouen C\u00e9dex",
    "sg:orig_category":"Non-Classified Establishments",
    "sg:phone":"+33 2 35 73 63 10",
    "sg:province":"Haute Normandie",
    "wof:name":"Promaritime International S.a.r.l.",
    "wof:placetype":"venue"
},
  "geometry": {"coordinates":[1.039141,49.43185],"type":"Point"}
}