{
  "type": "Feature",
  "properties": {
    "addr:full":"24190 St Germain Du Salembre Chant\u00e9rac Aquitaine 24190",
    "addr:housenumber":"24190;chante\u0301rac",
    "addr:postcode":"24190",
    "addr:street":"St",
    "iso:country":"FR",
    "sg:address":"24190 St Germain Du Salembre",
    "sg:city":"Chant\u00e9rac",
    "sg:classifiers":[
        {
            "category":"Shopping",
            "subcategory":"Luggage & Leather Goods",
            "type":"Retail Goods"
        }
    ],
    "sg:phone":"+33 5 53 80 84 00",
    "sg:postcode":"24190",
    "sg:province":"Aquitaine",
    "sg:tags":[
        "shoe"
    ],
    "wof:name":"Aster Chaussures",
    "wof:placetype":"venue"
},
  "geometry": {"coordinates":[0.451108,45.138561],"type":"Point"}
}