{
  "type": "Feature",
  "properties": {
    "addr:full":"B.P. 312, 94589 Rungis C\u00e9dex^^13, Av. de Franche Comt\u00e9, 94150 Rungis Ile de France 94150",
    "addr:housenumber":"b.p. 312",
    "addr:postcode":"94589;94150;94150",
    "addr:street":"Av. De Franche Comte\u0301",
    "iso:country":"FR",
    "sg:address":"B.P. 312, 94589 Rungis C\u00e9dex^^13, Av. de Franche Comt\u00e9, 94150 Rungis",
    "sg:orig_category":"Non-Classified Establishments",
    "sg:phone":"+33 1 41 73 25 00",
    "sg:postcode":"94150",
    "sg:province":"Ile de France",
    "wof:name":"Buisson S.a.",
    "wof:placetype":"venue"
},
  "geometry": {"coordinates":[2.35142,48.74918],"type":"Point"}
}