{
  "type": "Feature",
  "properties": {
    "addr:full":"Rte de Pont Audemer Cormeilles Haute Normandie 27260",
    "addr:postcode":"27260",
    "addr:street":"Rte De Pont Audemer;Haute Normandie",
    "iso:country":"FR",
    "sg:address":"Rte de Pont Audemer",
    "sg:city":"Cormeilles",
    "sg:orig_category":"Unclassifiable Establishments",
    "sg:phone":"+33 2 32 57 82 81",
    "sg:postcode":"27260",
    "sg:province":"Haute Normandie",
    "wof:name":"A.b.r. Beaurain S.a.",
    "wof:placetype":"venue"
},
  "geometry": {"coordinates":[0.378115,49.252853],"type":"Point"}
}