{
  "type": "Feature",
  "properties": {
    "iso:country":"FR",
    "sg:address":"Route D Etrepagny 27660 Bernouville",
    "sg:classifiers":[
        {
            "category":"Home & Garden",
            "subcategory":"Furniture",
            "type":"Retail Goods"
        }
    ],
    "sg:phone":"+33 2 32 55 96 30",
    "sg:province":"Haute Normandie",
    "sg:tags":[
        "wood"
    ],
    "wof:name":"Societe A Responsabilite Limitee 1 Metre 20",
    "wof:placetype":"venue"
},
  "geometry": {"coordinates":[1.686747,49.295444],"type":"Point"}
}