{
  "type": "Feature",
  "properties": {
    "iso:country":"FR",
    "sg:address":"Rue du Paquis",
    "sg:city":"Sevenans",
    "sg:orig_category":"Unclassifiable Establishments",
    "sg:phone":"+33 3 84 46 62 00",
    "sg:postcode":"90400",
    "sg:province":"Franche Comt\u00e9",
    "wof:name":"C.s.o. Informatique S.a.",
    "wof:placetype":"venue"
},
  "geometry": {"coordinates":[6.864247,47.585735],"type":"Point"}
}