{
  "type": "Feature",
  "properties": {
    "iso:country":"FR",
    "sg:address":"Za 25330 Cl\u00e9ron",
    "sg:classifiers":[
        {
            "category":"Manufacturing",
            "subcategory":"Metals",
            "type":"Manufacturing & Wholesale Goods"
        }
    ],
    "sg:phone":"+33 3 81 62 23 99",
    "sg:postcode":"25330",
    "sg:province":"Franche Comt\u00e9",
    "sg:tags":[
        "-",
        "machine",
        "equipment",
        "engineering",
        "machinery",
        "mechanical"
    ],
    "wof:name":"Diamac Sarl",
    "wof:placetype":"venue"
},
  "geometry": {"coordinates":[6.029655,47.007851],"type":"Point"}
}