{
  "type": "Feature",
  "properties": {
    "iso:country":"FR",
    "sg:address":"23 bis, Rue du Petit Chasseur, 45000 Orl\u00e9ans",
    "sg:city":"Orl\u00e9ans",
    "sg:orig_category":"Non-Classified Establishments",
    "sg:phone":"+33 2 38 88 59 53",
    "sg:postcode":"45000",
    "sg:province":"Centre",
    "wof:name":"Dautry Tromas S.a.",
    "wof:placetype":"venue"
},
  "geometry": {"coordinates":[1.885496,47.90361],"type":"Point"}
}