{
  "type": "Feature",
  "properties": {
    "iso:country":"FR",
    "sg:address":"23, Rue Fran\u00e7ois Simon - P\u00f4le Multim\u00e9dia, 13003 Marseille",
    "sg:orig_category":"Unclassifiable Establishments",
    "sg:phone":"+33 4 95 04 37 37",
    "sg:province":"Provence-Alpes-C\u00f4te d'Azur",
    "wof:name":"Madec & Co S.a.r.l.",
    "wof:placetype":"venue"
},
  "geometry": {"coordinates":[5.37755,43.30265],"type":"Point"}
}