{
  "type": "Feature",
  "properties": {
    "addr:full":"7, Rue de la Mer Rouge, 68200 Mulhouse Mulhouse Alsace 68200",
    "addr:housenumber":"7",
    "addr:postcode":"68200;68200",
    "addr:street":"Rue De La Mer Rouge",
    "iso:country":"FR",
    "sg:address":"7, Rue de la Mer Rouge, 68200 Mulhouse",
    "sg:city":"Mulhouse",
    "sg:orig_category":"Unclassifiable Establishments",
    "sg:phone":"+33 3 89 59 12 19",
    "sg:postcode":"68200",
    "sg:province":"Alsace",
    "wof:name":"Alsa N\u00e9on",
    "wof:placetype":"venue"
},
  "geometry": {"coordinates":[7.306795,47.746944],"type":"Point"}
}