{
  "type": "Feature",
  "properties": {
    "iso:country":"FR",
    "sg:address":"B.P. 42, 39160 Saint Amour^^ZI des Ni\u00e8vres, 39160 Saint Amour",
    "sg:orig_category":"Non-Classified Establishments",
    "sg:phone":"+33 3 84 44 05 00",
    "sg:province":"Franche Comt\u00e9",
    "wof:name":"Sarrade Galtier Fillod S.a.",
    "wof:placetype":"venue"
},
  "geometry": {"coordinates":[5.344974,46.4352],"type":"Point"}
}