{
  "type": "Feature",
  "properties": {
    "iso:country":"FR",
    "sg:address":"Zone Industrielle",
    "sg:city":"Aillevillers et Lyaumont",
    "sg:orig_category":"Non-Classified Establishments",
    "sg:phone":"+33 3 84 49 25 65",
    "sg:postcode":"70320",
    "sg:province":"Franche Comt\u00e9",
    "wof:name":"Lyonnet S.a.",
    "wof:placetype":"venue"
},
  "geometry": {"coordinates":[6.336723,47.919704],"type":"Point"}
}