{
  "type": "Feature",
  "properties": {
    "addr:full":"182, Av. du Stade, 74460 Marnaz Rhone-Alpes 74460",
    "addr:postcode":"74460;74460",
    "addr:street":"182 Av. Du Stade;Rhone-Alpes",
    "iso:country":"FR",
    "sg:address":"182, Av. du Stade, 74460 Marnaz",
    "sg:orig_category":"Unclassifiable Establishments",
    "sg:phone":"+33 4 50 98 12 81",
    "sg:postcode":"74460",
    "sg:province":"Rhone-Alpes",
    "wof:name":"Solliet Maurice S.a.r.l.",
    "wof:placetype":"venue"
},
  "geometry": {"coordinates":[6.528196,46.061085],"type":"Point"}
}