{
  "type": "Feature",
  "properties": {
    "addr:full":"23 rue Saint Exup\u00e9ry 33320 Eysines Eysines Aquitaine 33320",
    "addr:housenumber":"23",
    "addr:postcode":"33320;33320",
    "addr:street":"Rue Saint Exupe\u0301Ry",
    "iso:country":"FR",
    "sg:address":"23 rue Saint Exup\u00e9ry 33320 Eysines",
    "sg:city":"Eysines",
    "sg:classifiers":[
        {
            "category":"Autos & Motor Vehicles",
            "subcategory":"Auto Supplies",
            "type":"Retail Goods"
        }
    ],
    "sg:phone":"+33 5 57 92 60 40",
    "sg:postcode":"33320",
    "sg:province":"Aquitaine",
    "sg:tags":[
        "wiper",
        "windscreen"
    ],
    "wof:name":"Unitec S.a.r.l.",
    "wof:placetype":"venue"
},
  "geometry": {"coordinates":[-0.660724,44.863682],"type":"Point"}
}