{
  "type": "Feature",
  "properties": {
    "addr:full":"20bis, Rue de Sausheim - Modenheim , 68110 Illzach Illzach Alsace 68110",
    "addr:housenumber":"20bis",
    "addr:postcode":"68110;68110",
    "addr:street":"Rue De Sausheim Modenheim",
    "iso:country":"FR",
    "sg:address":"20bis, Rue de Sausheim - Modenheim , 68110 Illzach",
    "sg:city":"Illzach",
    "sg:orig_category":"Non-Classified Establishments",
    "sg:phone":"+33 3 89 56 39 10",
    "sg:postcode":"68110",
    "sg:province":"Alsace",
    "wof:name":"Meyer Isolation S.a.",
    "wof:placetype":"venue"
},
  "geometry": {"coordinates":[7.349416,47.779305],"type":"Point"}
}