{
  "type": "Feature",
  "properties": {
    "iso:country":"FR",
    "sg:address":"La Pauvertrie",
    "sg:city":"Cheverny",
    "sg:orig_category":"Non-Classified Establishments",
    "sg:phone":"+33 2 54 44 23 05",
    "sg:postcode":"41700",
    "sg:province":"Centre",
    "wof:name":"Aertec Ing\u00e9nierie",
    "wof:placetype":"venue"
},
  "geometry": {"coordinates":[1.415192,47.49931],"type":"Point"}
}