{
  "type": "Feature",
  "properties": {
    "iso:country":"FR",
    "sg:address":"Maupas 16220 Ecuras",
    "sg:classifiers":[
        {
            "category":"Manufacturing",
            "subcategory":"Leather Goods",
            "type":"Manufacturing & Wholesale Goods"
        }
    ],
    "sg:phone":"+33 5 45 70 86 61",
    "sg:postcode":"16220",
    "sg:province":"Poitou-Charentes",
    "sg:tags":[
        "shoe"
    ],
    "wof:name":"Plastiques Du Bandiat Tardoire",
    "wof:placetype":"venue"
},
  "geometry": {"coordinates":[0.5432,45.642506],"type":"Point"}
}