{
  "type": "Feature",
  "properties": {
    "addr:full":"23 Av Du Campon 06110 Le Cannet Corse",
    "addr:postcode":"06110",
    "addr:street":"23 Av Du Campon",
    "iso:country":"FR",
    "sg:address":"23 Av Du Campon 06110 Le Cannet",
    "sg:classifiers":[
        {
            "category":"Utilities",
            "subcategory":"Telephone",
            "type":"Services"
        }
    ],
    "sg:phone":"+33 4 93 45 71 87",
    "sg:province":"Corse",
    "sg:tags":[
        "telecommunication"
    ],
    "wof:name":"Artplex Azurea Sarl",
    "wof:placetype":"venue"
},
  "geometry": {"coordinates":[7.012746,43.574265],"type":"Point"}
}