{
  "type": "Feature",
  "properties": {
    "iso:country":"FR",
    "sg:address":"11 R De La Tremblaie 35170 Bruz",
    "sg:city":"Bruz",
    "sg:classifiers":[
        {
            "category":"Food & Beverages",
            "subcategory":"Meat & Fish",
            "type":"Retail Goods"
        }
    ],
    "sg:phone":"+33 2 99 52 50 21",
    "sg:postcode":"35170",
    "sg:province":"Bretagne",
    "sg:tags":[
        "preserve",
        "cooked",
        "product",
        "related"
    ],
    "wof:name":"M. Hoarau Helio",
    "wof:placetype":"venue"
},
  "geometry": {"coordinates":[-1.76314,48.03804],"type":"Point"}
}