{
  "type": "Feature",
  "properties": {
    "iso:country":"FR",
    "sg:address":"77 Avenue Jean Jaures 93120 La Courneuve",
    "sg:classifiers":[
        {
            "category":"Professional",
            "subcategory":"Engineering",
            "type":"Services"
        }
    ],
    "sg:phone":"+33 1 48 36 04 83",
    "sg:postcode":"93120",
    "sg:province":"Ile de France",
    "sg:tags":[
        "machine",
        "-",
        "mechanical"
    ],
    "wof:name":"Parabis Froid Industriel",
    "wof:placetype":"venue"
},
  "geometry": {"coordinates":[2.405703,48.923431],"type":"Point"}
}