{
  "type": "Feature",
  "properties": {
    "addr:full":"92, Rue Richelieu, 75002 Paris Ile de France",
    "addr:housenumber":"92",
    "addr:postcode":"75002",
    "addr:street":"Rue Richelieu",
    "iso:country":"FR",
    "sg:address":"92, Rue Richelieu, 75002 Paris",
    "sg:orig_category":"Unclassifiable Establishments",
    "sg:phone":"+33 1 55 04 79 79",
    "sg:province":"Ile de France",
    "wof:name":"Lafayette Travel S.a.",
    "wof:placetype":"venue"
},
  "geometry": {"coordinates":[2.339452,48.870319],"type":"Point"}
}