{
  "type": "Feature",
  "properties": {
    "addr:full":"42 Rue Edouard Vaillant 59540 Caudry Nord Pas-de-Calais 59540",
    "addr:housenumber":"42",
    "addr:postcode":"59540;59540",
    "addr:street":"Rue Edouard Vaillant",
    "iso:country":"FR",
    "sg:address":"42 Rue Edouard Vaillant 59540 Caudry",
    "sg:classifiers":[
        {
            "category":"Manufacturing",
            "subcategory":"Metals",
            "type":"Manufacturing & Wholesale Goods"
        }
    ],
    "sg:phone":"+33 3 27 85 07 55",
    "sg:postcode":"59540",
    "sg:province":"Nord Pas-de-Calais",
    "sg:tags":[
        "-",
        "machine",
        "equipment",
        "engineering",
        "machinery",
        "mechanical"
    ],
    "wof:name":"Bricout St Yves (ste De Mecanique) Sarl",
    "wof:placetype":"venue"
},
  "geometry": {"coordinates":[3.406162,50.116058],"type":"Point"}
}