{
  "type": "Feature",
  "properties": {
    "iso:country":"FR",
    "sg:address":"55, Rue Rennequin, 75017 Paris",
    "sg:orig_category":"Non-Classified Establishments",
    "sg:phone":"+33 1 43 80 73 38",
    "sg:province":"Ile de France",
    "wof:name":"Expopart S.a.",
    "wof:placetype":"venue"
},
  "geometry": {"coordinates":[2.295615,48.883293],"type":"Point"}
}