{
  "type": "Feature",
  "properties": {
    "iso:country":"FR",
    "sg:address":"20, Rue des Dagneaux, 63200 Riom",
    "sg:city":"Riom",
    "sg:orig_category":"Unclassifiable Establishments",
    "sg:phone":"+33 4 73 64 65 40",
    "sg:postcode":"63200",
    "sg:province":"Auvergne",
    "wof:name":"G\u00e9rin S.a.",
    "wof:placetype":"venue"
},
  "geometry": {"coordinates":[3.12631,45.891411],"type":"Point"}
}