{
  "type": "Feature",
  "properties": {
    "addr:full":"Av. de la R\u00e9publique Cattenom Lorraine 57570",
    "addr:postcode":"57570",
    "addr:street":"Av. De La Re\u0301Publique",
    "iso:country":"FR",
    "sg:address":"Av. de la R\u00e9publique",
    "sg:city":"Cattenom",
    "sg:orig_category":"Non-Classified Establishments",
    "sg:phone":"+33 3 82 84 81 81",
    "sg:postcode":"57570",
    "sg:province":"Lorraine",
    "wof:name":"L.t.f. S.a. - Location Transport Fontoy",
    "wof:placetype":"venue"
},
  "geometry": {"coordinates":[6.242402,49.404606],"type":"Point"}
}