{
  "type": "Feature",
  "properties": {
    "addr:full":"1, Rue Camille Desmoulins, 94230 Cachan Ile de France",
    "addr:housenumber":"1",
    "addr:postcode":"94230;ile",
    "addr:street":"Rue Camille Desmoulins",
    "iso:country":"FR",
    "sg:address":"1, Rue Camille Desmoulins, 94230 Cachan",
    "sg:orig_category":"Unclassifiable Establishments",
    "sg:phone":"+33 1 46 15 82 00",
    "sg:province":"Ile de France",
    "wof:name":"Fiduciaire Moncey D'expertise S.a.",
    "wof:placetype":"venue"
},
  "geometry": {"coordinates":[2.334813,48.79435],"type":"Point"}
}