{
  "type": "Feature",
  "properties": {
    "addr:full":"3 Impasse Bagatelle 14000 Caen Caen Basse Normandie 14000",
    "addr:housenumber":"3",
    "addr:postcode":"14000;14000",
    "addr:street":"Impasse Bagatelle",
    "iso:country":"FR",
    "sg:address":"3 Impasse Bagatelle 14000 Caen",
    "sg:city":"Caen",
    "sg:classifiers":[
        {
            "category":"Wholesale",
            "subcategory":"Medical Equipment & Supplies",
            "type":"Manufacturing & Wholesale Goods"
        }
    ],
    "sg:phone":"+33 2 31 86 02 26",
    "sg:postcode":"14000",
    "sg:province":"Basse Normandie",
    "sg:tags":[
        "instrument",
        "health",
        "-",
        "precision"
    ],
    "wof:name":"Laboratoires Richard Dantas",
    "wof:placetype":"venue"
},
  "geometry": {"coordinates":[-0.369005,49.186089],"type":"Point"}
}