{
  "type": "Feature",
  "properties": {
    "iso:country":"FR",
    "sg:address":"1 rue Pr\u00e9sident Carnot; Lyon; 69002",
    "sg:classifiers":[
        {
            "category":"Banks & Credit Unions",
            "subcategory":"Bank",
            "type":"Services"
        }
    ],
    "sg:phone":"+33 4 72 40 76 00",
    "sg:postcode":"69002",
    "sg:province":"Rhone-Alpes",
    "wof:name":"Cr\u00e9dit Agricole, Indosuez",
    "wof:placetype":"venue"
},
  "geometry": {"coordinates":[4.838157,45.763367],"type":"Point"}
}