{
  "type": "Feature",
  "properties": {
    "iso:country":"FR",
    "sg:address":"150 Ancienne Route De Beaujeu 69400 Gleize",
    "sg:classifiers":[
        {
            "category":"Shopping",
            "subcategory":"Clothing, Apparel, & Fashions",
            "type":"Retail Goods"
        }
    ],
    "sg:phone":"+33 4 74 62 47 03",
    "sg:postcode":"69400",
    "sg:province":"Rhone-Alpes",
    "sg:tags":[
        "textile",
        "clothing",
        "clothes"
    ],
    "wof:name":"Cepovett",
    "wof:placetype":"venue"
},
  "geometry": {"coordinates":[4.71547,46.004593],"type":"Point"}
}