{
  "type": "Feature",
  "properties": {
    "iso:country":"FR",
    "sg:address":"Site EDF les Creusets CD 15 13250 ST CHAMAS",
    "sg:classifiers":[
        {
            "category":"Government",
            "subcategory":"Fire Station",
            "type":"Public Place"
        }
    ],
    "sg:phone":"+33 4 90 45 67 67",
    "sg:province":"Pays de Loire",
    "sg:tags":[
        "inverter",
        "power"
    ],
    "wof:name":"Ipsos Electric S.a.r.l.",
    "wof:placetype":"venue"
},
  "geometry": {"coordinates":[5.032915,43.550137],"type":"Point"}
}