{
  "type": "Feature",
  "properties": {
    "iso:country":"FR",
    "sg:address":"44 Rue Des Halles",
    "sg:city":"Saint Nazaire",
    "sg:classifiers":[
        {
            "category":"Banks & Credit Unions",
            "subcategory":"Financial Services",
            "type":"Services"
        }
    ],
    "sg:phone":"+33 2 51 10 00 60",
    "sg:postcode":"44600",
    "sg:province":"Pays de Loire",
    "sg:tags":[
        "banking",
        "finance",
        "insurance"
    ],
    "wof:name":"Fiducial Bureautique (fidinfor)",
    "wof:placetype":"venue"
},
  "geometry": {"coordinates":[-2.215012,47.27977],"type":"Point"}
}