{
  "type": "Feature",
  "properties": {
    "addr:full":"Rte du XXIe si\u00e8cle - ZI Chasseneuil du Poitou Poitou-Charentes 86360",
    "addr:postcode":"86360",
    "addr:street":"Rte Du Xxie Sie\u0300Cle Zi Chasseneuil Du Poitou",
    "iso:country":"FR",
    "sg:address":"Rte du XXIe si\u00e8cle - ZI",
    "sg:city":"Chasseneuil du Poitou",
    "sg:orig_category":"Unclassifiable Establishments",
    "sg:phone":"+33 5 49 62 07 07",
    "sg:postcode":"86360",
    "sg:province":"Poitou-Charentes",
    "wof:name":"Free M\u00e9tal S.a.",
    "wof:placetype":"venue"
},
  "geometry": {"coordinates":[0.37477,46.650494],"type":"Point"}
}