{
  "type": "Feature",
  "properties": {
    "iso:country":"FR",
    "sg:address":"ZI Palisse",
    "sg:city":"Le Cheylard",
    "sg:orig_category":"Unclassifiable Establishments",
    "sg:phone":"+33 4 75 29 90 12",
    "sg:postcode":"07160",
    "sg:province":"Rhone-Alpes",
    "wof:name":"S\u00e9rigraphie Plantier",
    "wof:placetype":"venue"
},
  "geometry": {"coordinates":[4.422196,44.908443],"type":"Point"}
}