{
  "type": "Feature",
  "properties": {
    "iso:country":"FR",
    "sg:address":"54, Rue du Chatelard, 01200 Ch\u00e2tillon en Michaille",
    "sg:orig_category":"Non-Classified Establishments",
    "sg:phone":"+33 4 50 59 72 54",
    "sg:postcode":"01200",
    "sg:province":"Rhone-Alpes",
    "wof:name":"Entreprise Bride Roland",
    "wof:placetype":"venue"
},
  "geometry": {"coordinates":[5.79472,46.138084],"type":"Point"}
}