{
  "type": "Feature",
  "properties": {
    "addr:full":"Av Guillaume Seznec 35550 Sixt Sur Aff Bruc-sur-Aff Bretagne 35550",
    "addr:postcode":"35550;35550",
    "addr:street":"Av Guillaume Seznec;Bruc-Sur-Aff",
    "iso:country":"FR",
    "sg:address":"Av Guillaume Seznec 35550 Sixt Sur Aff",
    "sg:city":"Bruc-sur-Aff",
    "sg:orig_category":"Ceramics Electrical and Electronic Equipment Household goods Lighting Wood and Furniture",
    "sg:phone":"+33 2 99 70 08 82",
    "sg:postcode":"35550",
    "sg:province":"Bretagne",
    "wof:name":"Francois Chatain Et Les Autres",
    "wof:placetype":"venue"
},
  "geometry": {"coordinates":[-2.060804,47.779495],"type":"Point"}
}