{
  "type": "Feature",
  "properties": {
    "addr:full":"17-21 Rue De Javel 75015 Paris Ile de France 75015",
    "addr:housenumber":"17-21",
    "addr:postcode":"75015;75015",
    "addr:street":"Rue De Javel",
    "iso:country":"FR",
    "sg:address":"17-21 Rue De Javel 75015 Paris",
    "sg:classifiers":[
        {
            "category":"Professional",
            "subcategory":"Advertising",
            "type":"Services"
        }
    ],
    "sg:phone":"+33 1 44 37 50 50",
    "sg:postcode":"75015",
    "sg:province":"Ile de France",
    "sg:tags":[
        "information",
        "medium",
        "communication"
    ],
    "wof:name":"Pictorial Service Sarl",
    "wof:placetype":"venue"
},
  "geometry": {"coordinates":[2.280453,48.846695],"type":"Point"}
}