{
  "type": "Feature",
  "properties": {
    "addr:full":"2 rue de la Petite Ruelle 95100 Argenteuil Ile de France 95100",
    "addr:housenumber":"2",
    "addr:postcode":"95100;ile;95100",
    "addr:street":"Rue De La Petite Ruelle;France",
    "iso:country":"FR",
    "sg:address":"2 rue de la Petite Ruelle 95100 Argenteuil",
    "sg:classifiers":[
        {
            "category":"Structure",
            "subcategory":"Office Building",
            "type":"Public Place"
        }
    ],
    "sg:phone":"+33 1 34 11 29 42",
    "sg:postcode":"95100",
    "sg:province":"Ile de France",
    "sg:tags":[
        "industrial",
        "assembly"
    ],
    "wof:name":"Ste Diffus Et Fournitures Materiel Inter Sarl",
    "wof:placetype":"venue"
},
  "geometry": {"coordinates":[2.238265,48.963558],"type":"Point"}
}