{
  "type": "Feature",
  "properties": {
    "iso:country":"FR",
    "sg:address":"18, Place des Reflets - Tour Aurore IBC, 92975 Paris la D\u00e9fense C\u00e9dex 2",
    "sg:orig_category":"Non-Classified Establishments",
    "sg:phone":"+33 1 47 78 50 50",
    "sg:province":"Midi Pyr\u00e9n\u00e9es",
    "wof:name":"Editions Haynes S.a.r.l.",
    "wof:placetype":"venue"
},
  "geometry": {"coordinates":[2.24119,48.888939],"type":"Point"}
}