{
  "type": "Feature",
  "properties": {
    "addr:full":"B.P. 69, 59580 Aniche^^48, Rue du G\u00e9n\u00e9ral Delestraint, 59580 Aniche Nord Pas-de-Calais",
    "addr:postcode":"59580;59580",
    "addr:street":"B.P. 69;Rue Du Ge\u0301Ne\u0301Ral Delestraint",
    "iso:country":"FR",
    "sg:address":"B.P. 69, 59580 Aniche^^48, Rue du G\u00e9n\u00e9ral Delestraint, 59580 Aniche",
    "sg:orig_category":"Non-Classified Establishments",
    "sg:phone":"+33 3 27 95 83 40",
    "sg:province":"Nord Pas-de-Calais",
    "wof:name":"Sicover Industries S.a.",
    "wof:placetype":"venue"
},
  "geometry": {"coordinates":[3.249528,50.331013],"type":"Point"}
}