{
  "type": "Feature",
  "properties": {
    "addr:full":"Ch\u00e2teau Foucaud 33410 Cardan Cardan Aquitaine 33410",
    "addr:postcode":"33410;33410",
    "iso:country":"FR",
    "sg:address":"Ch\u00e2teau Foucaud 33410 Cardan",
    "sg:city":"Cardan",
    "sg:orig_category":"Non-Classified Establishments",
    "sg:phone":"+33 5 56 62 60 93",
    "sg:postcode":"33410",
    "sg:province":"Aquitaine",
    "wof:name":"Vignobles Reyne G.a.e.c.",
    "wof:placetype":"venue"
},
  "geometry": {"coordinates":[-0.280539,44.59306],"type":"Point"}
}