{
  "type": "Feature",
  "properties": {
    "addr:full":"112, Av du G\u00e9n\u00e9ral Leclerc, 54000 Nancy Lorraine",
    "addr:postcode":"54000",
    "addr:street":"112 Av Du Ge\u0301Ne\u0301Ral Leclerc",
    "iso:country":"FR",
    "sg:address":"112, Av du G\u00e9n\u00e9ral Leclerc, 54000 Nancy",
    "sg:orig_category":"Unclassifiable Establishments",
    "sg:phone":"+33 3 83 15 88 88",
    "sg:province":"Lorraine",
    "wof:name":"Ar\u00e8s Lorraine S.a.",
    "wof:placetype":"venue"
},
  "geometry": {"coordinates":[6.180615,48.67944],"type":"Point"}
}