{
  "type": "Feature",
  "properties": {
    "addr:full":"103 Rue Bourbon 08000 Charleville M\u00e9zi\u00e8res Charleville-M\u00e9zi\u00e8res Champagne 08000",
    "addr:housenumber":"103",
    "addr:postcode":"08000;08000",
    "addr:street":"Rue Bourbon",
    "iso:country":"FR",
    "sg:address":"103 Rue Bourbon 08000 Charleville M\u00e9zi\u00e8res",
    "sg:city":"Charleville-M\u00e9zi\u00e8res",
    "sg:classifiers":[
        {
            "category":"Health Services",
            "subcategory":"Optometrist",
            "type":"Services"
        }
    ],
    "sg:phone":"+33 3 24 56 03 16",
    "sg:postcode":"08000",
    "sg:province":"Champagne",
    "sg:tags":[
        "instrument",
        "optical",
        "-",
        "precision",
        "equipment"
    ],
    "wof:name":"Auror Diffusion Sa",
    "wof:placetype":"venue"
},
  "geometry": {"coordinates":[4.713782,49.773067],"type":"Point"}
}