{
  "type": "Feature",
  "properties": {
    "addr:full":"4 Rue Du Roi Gradlon 29000 Quimper Quimper Bretagne 29000",
    "addr:housenumber":"4",
    "addr:postcode":"29000;29000",
    "addr:street":"Rue Du Roi Gradlon",
    "iso:country":"FR",
    "sg:address":"4 Rue Du Roi Gradlon 29000 Quimper",
    "sg:city":"Quimper",
    "sg:classifiers":[
        {
            "category":"Home & Garden",
            "subcategory":"Furniture",
            "type":"Retail Goods"
        }
    ],
    "sg:phone":"+33 2 98 95 31 54",
    "sg:postcode":"29000",
    "sg:province":"Bretagne",
    "sg:tags":[
        "household",
        "wood"
    ],
    "wof:name":"Sarl Francois Le Villec",
    "wof:placetype":"venue"
},
  "geometry": {"coordinates":[-4.102902,47.995136],"type":"Point"}
}