{
  "type": "Feature",
  "properties": {
    "addr:full":"10, Grand' Rue, 88500 Dombasle en Xaintois Lorraine",
    "addr:housenumber":"10",
    "addr:postcode":"88500",
    "addr:street":"Grand ' Rue;Xaintois",
    "iso:country":"FR",
    "sg:address":"10, Grand' Rue, 88500 Dombasle en Xaintois",
    "sg:orig_category":"Unclassifiable Establishments",
    "sg:phone":"+33 3 29 65 68 18",
    "sg:province":"Lorraine",
    "wof:name":"Delpierre Transports S.a.r.l.",
    "wof:placetype":"venue"
},
  "geometry": {"coordinates":[5.99322,48.307999],"type":"Point"}
}