{
  "type": "Feature",
  "properties": {
    "iso:country":"FR",
    "sg:address":"Les Tuileries Rn 113 47490 St Hilaire De Lusignan",
    "sg:classifiers":[
        {
            "category":"Manufacturing",
            "subcategory":"Metals",
            "type":"Manufacturing & Wholesale Goods"
        }
    ],
    "sg:phone":"+33 5 53 67 60 00",
    "sg:province":"Champagne",
    "sg:tags":[
        "-",
        "machine",
        "equipment",
        "engineering",
        "machinery",
        "mechanical"
    ],
    "wof:name":"Etablissements Bernabeu Tony Sa",
    "wof:placetype":"venue"
},
  "geometry": {"coordinates":[0.123935,46.436016],"type":"Point"}
}