{
  "type": "Feature",
  "properties": {
    "addr:full":"B.P. 2172, 31086 Toulouse C\u00e9dex^^11, Rue de Berne, 31200 Toulouse Midi Pyr\u00e9n\u00e9es 31200",
    "addr:postcode":"31086;31200;31200",
    "addr:street":"B.P. 2172;Rue De Berne",
    "iso:country":"FR",
    "sg:address":"B.P. 2172, 31086 Toulouse C\u00e9dex^^11, Rue de Berne, 31200 Toulouse",
    "sg:orig_category":"Non-Classified Establishments",
    "sg:phone":"+33 5 34 40 23 31",
    "sg:postcode":"31200",
    "sg:province":"Midi Pyr\u00e9n\u00e9es",
    "wof:name":"Elis Midi Pyr\u00e9n\u00e9es S.a.",
    "wof:placetype":"venue"
},
  "geometry": {"coordinates":[1.44954,43.639011],"type":"Point"}
}