{
  "type": "Feature",
  "properties": {
    "iso:country":"FR",
    "sg:address":"2, Place de l'Eglise, 91910 Saint Sulpice de Favi\u00e8res",
    "sg:orig_category":"Unclassifiable Establishments",
    "sg:phone":"+33 1 64 58 72 67",
    "sg:province":"Ile de France",
    "wof:name":"Informatique Et Documentation S.a.r.l.",
    "wof:placetype":"venue"
},
  "geometry": {"coordinates":[2.178623,48.541115],"type":"Point"}
}