{
  "type": "Feature",
  "properties": {
    "iso:country":"FR",
    "sg:address":"Route De Rousson 89500 Villeneuve Sur Yonne",
    "sg:city":"Rousson",
    "sg:classifiers":[
        {
            "category":"Professional",
            "subcategory":"Printing & Photocopies",
            "type":"Services"
        }
    ],
    "sg:phone":"+33 3 86 87 37 79",
    "sg:postcode":"89500",
    "sg:province":"Bourgogne",
    "sg:tags":[
        "machine",
        "engineering",
        "-",
        "mechanical"
    ],
    "wof:name":"Cliches 2000",
    "wof:placetype":"venue"
},
  "geometry": {"coordinates":[3.281652,48.086655],"type":"Point"}
}