{
  "type": "Feature",
  "properties": {
    "iso:country":"FR",
    "sg:address":"Lieu-Dit La Croze 01160 NEUVILLE SUR AIN",
    "sg:classifiers":[
        {
            "category":"Sports & Exercise",
            "subcategory":"Tennis Court",
            "type":"Entertainment"
        }
    ],
    "sg:phone":"+33 4 74 37 77 33",
    "sg:province":"Rhone-Alpes",
    "sg:tags":[
        "piano",
        "stool",
        "bench"
    ],
    "wof:name":"Inter Musique Sa Exploit Ets Bourbon",
    "wof:placetype":"venue"
},
  "geometry": {"coordinates":[5.370656,46.082375],"type":"Point"}
}