{
  "type": "Feature",
  "properties": {
    "iso:country":"FR",
    "sg:address":"B.P. 2017, 44406 Rez\u00e9 C\u00e9dex^^1, Rue de l'Ile Mac\u00e9 - B\u00e2t Cap Sud, 44400 Rez\u00e9",
    "sg:orig_category":"Non-Classified Establishments",
    "sg:phone":"+33 2 51 70 04 94",
    "sg:province":"Pays de Loire",
    "wof:name":"Sonats S.a. - Soci\u00e9t\u00e9 Des Nouvelles Applications Des Techniques",
    "wof:placetype":"venue"
},
  "geometry": {"coordinates":[-1.55687,47.1749],"type":"Point"}
}