{
  "type": "Feature",
  "properties": {
    "addr:full":"321 Rte De St Nazaire 53013 Laval Champagne",
    "addr:housenumber":"321",
    "addr:postcode":"53013",
    "addr:street":"Rte De St",
    "iso:country":"FR",
    "sg:address":"321 Rte De St Nazaire 53013 Laval",
    "sg:classifiers":[
        {
            "category":"Professional",
            "subcategory":"Business Services",
            "type":"Services"
        }
    ],
    "sg:phone":"+33 2 43 68 24 93",
    "sg:province":"Champagne",
    "sg:tags":[
        "training",
        "advice"
    ],
    "wof:name":"Lycee Agricole",
    "wof:placetype":"venue"
},
  "geometry": {"coordinates":[-0.803678,48.036098],"type":"Point"}
}