{
  "type": "Feature",
  "properties": {
    "iso:country":"FR",
    "sg:address":"B.P. 15, 57120 Rombas^^25, Rue de l'Usine, 57120 Rombas",
    "sg:orig_category":"Non-Classified Establishments",
    "sg:phone":"+33 3 87 17 15 18",
    "sg:province":"Lorraine",
    "wof:name":"Sodie S.a. - D\u00e9veloppement R\u00e9gional Usinor-sacilor",
    "wof:placetype":"venue"
},
  "geometry": {"coordinates":[6.098323,49.256344],"type":"Point"}
}