{
  "type": "Feature",
  "properties": {
    "iso:country":"FR",
    "sg:address":"La Creuse 79800 Sainte Eanne",
    "sg:orig_category":"Unclassifiable Establishments",
    "sg:phone":"+33 5 49 06 28 28",
    "sg:province":"Poitou-Charentes",
    "wof:name":"Serval S.a.",
    "wof:placetype":"venue"
},
  "geometry": {"coordinates":[-0.131979,46.382675],"type":"Point"}
}