{
  "type": "Feature",
  "properties": {
    "addr:full":"42, Rue de Cl\u00e9ry, 75002 Paris Ile de France",
    "addr:housenumber":"42",
    "addr:postcode":"75002",
    "addr:street":"Rue De Cle\u0301Ry",
    "iso:country":"FR",
    "sg:address":"42, Rue de Cl\u00e9ry, 75002 Paris",
    "sg:orig_category":"Non-Classified Establishments",
    "sg:phone":"+33 1 42 21 12 03",
    "sg:province":"Ile de France",
    "wof:name":"Les Tissus Marey S.a.",
    "wof:placetype":"venue"
},
  "geometry": {"coordinates":[2.347441,48.868294],"type":"Point"}
}