{
  "type": "Feature",
  "properties": {
    "iso:country":"FR",
    "sg:address":"Pr\u00e9 Colombier 03250 Le Mayet de Montagne",
    "sg:city":"Arronnes",
    "sg:orig_category":"Unclassifiable Establishments",
    "sg:phone":"+33 4 70 59 71 27",
    "sg:postcode":"03250",
    "sg:province":"Auvergne",
    "wof:name":"Mayet Maille S.a.r.l.",
    "wof:placetype":"venue"
},
  "geometry": {"coordinates":[3.677729,46.069004],"type":"Point"}
}