{
  "type": "Feature",
  "properties": {
    "iso:country":"FR",
    "sg:address":"290 rue du Breuil 25460 Etupes",
    "sg:classifiers":[
        {
            "category":"Banks & Credit Unions",
            "subcategory":"Investment Brokerage",
            "type":"Services"
        }
    ],
    "sg:phone":"+33 3 81 90 78 78",
    "sg:postcode":"25460",
    "sg:province":"Franche Comt\u00e9",
    "sg:tags":[
        "lift",
        "truck"
    ],
    "wof:name":"Etablissements Laibe S.a.",
    "wof:placetype":"venue"
},
  "geometry": {"coordinates":[6.860941,47.511002],"type":"Point"}
}