{
  "type": "Feature",
  "properties": {
    "addr:full":"B.P. 21, 16101 Cognac C\u00e9dex^^7, Place Edouard Martell, 16100 Cognac Poitou-Charentes",
    "addr:postcode":"16101;16100",
    "addr:street":"B.P. 21;Place Edouard Martell",
    "iso:country":"FR",
    "sg:address":"B.P. 21, 16101 Cognac C\u00e9dex^^7, Place Edouard Martell, 16100 Cognac",
    "sg:orig_category":"Non-Classified Establishments",
    "sg:phone":"+33 5 45 36 33 33",
    "sg:province":"Poitou-Charentes",
    "wof:name":"Martell Et Compagnie S.a.",
    "wof:placetype":"venue"
},
  "geometry": {"coordinates":[-0.313384,45.67149],"type":"Point"}
}