{
  "type": "Feature",
  "properties": {
    "iso:country":"FR",
    "sg:address":"7, Rue Jean-Pierre Timbaud, 95100 Argenteuil",
    "sg:orig_category":"Unclassifiable Establishments",
    "sg:phone":"+33 1 34 11 50 00",
    "sg:province":"Ile de France",
    "wof:name":"Scati S.a.",
    "wof:placetype":"venue"
},
  "geometry": {"coordinates":[2.214352,48.949688],"type":"Point"}
}