{
  "type": "Feature",
  "properties": {
    "addr:full":"67, Rue des Epoux Contoux, 03400 Yzeure Yzeure Auvergne 03400",
    "addr:housenumber":"67",
    "addr:postcode":"03400;03400",
    "addr:street":"Rue Des Epoux Contoux",
    "iso:country":"FR",
    "sg:address":"67, Rue des Epoux Contoux, 03400 Yzeure",
    "sg:city":"Yzeure",
    "sg:orig_category":"Unclassifiable Establishments",
    "sg:phone":"+33 4 70 20 96 50",
    "sg:postcode":"03400",
    "sg:province":"Auvergne",
    "wof:name":"Plastyzeure S.a.",
    "wof:placetype":"venue"
},
  "geometry": {"coordinates":[3.344164,46.543446],"type":"Point"}
}