{
  "type": "Feature",
  "properties": {
    "addr:full":"5 Za Croix St Mathieu 28320 Gallardon Gallardon Centre 28320",
    "addr:housenumber":"5",
    "addr:postcode":"28320;28320",
    "addr:street":"Za Croix St Mathieu",
    "iso:country":"FR",
    "sg:address":"5 Za Croix St Mathieu 28320 Gallardon",
    "sg:city":"Gallardon",
    "sg:classifiers":[
        {
            "category":"Manufacturing",
            "subcategory":"Printing",
            "type":"Manufacturing & Wholesale Goods"
        }
    ],
    "sg:phone":"+33 2 37 31 08 00",
    "sg:postcode":"28320",
    "sg:province":"Centre",
    "sg:tags":[
        "publishing"
    ],
    "wof:name":"T O P P Typo Offset Photogravure Publicite",
    "wof:placetype":"venue"
},
  "geometry": {"coordinates":[1.68767,48.52486],"type":"Point"}
}