{
  "type": "Feature",
  "properties": {
    "addr:full":"20 Rue Charles Blanchet 76290 Montivilliers Haute Normandie 76290",
    "addr:housenumber":"20",
    "addr:postcode":"76290;76290",
    "addr:street":"Rue Charles Blanchet;Haute Normandie",
    "iso:country":"FR",
    "sg:address":"20 Rue Charles Blanchet 76290 Montivilliers",
    "sg:classifiers":[
        {
            "category":"Professional",
            "subcategory":"Business Services",
            "type":"Services"
        }
    ],
    "sg:phone":"+33 2 35 30 26 73",
    "sg:postcode":"76290",
    "sg:province":"Haute Normandie",
    "sg:tags":[
        "training",
        "advice"
    ],
    "wof:name":"Ogec",
    "wof:placetype":"venue"
},
  "geometry": {"coordinates":[0.193177,49.546654],"type":"Point"}
}