{
  "type": "Feature",
  "properties": {
    "iso:country":"FR",
    "sg:address":"4 Avenue Lafayette",
    "sg:city":"Rochefort",
    "sg:classifiers":[
        {
            "category":"Banks & Credit Unions",
            "subcategory":"Financial Services",
            "type":"Services"
        }
    ],
    "sg:phone":"+33 5 46 87 30 66",
    "sg:postcode":"17300",
    "sg:province":"Poitou-Charentes",
    "sg:tags":[
        "banking",
        "finance",
        "insurance"
    ],
    "wof:name":"S M A B T P Ste Mutuelle Assurance Batiment Et Travaux Publics",
    "wof:placetype":"venue"
},
  "geometry": {"coordinates":[-0.958704,45.934818],"type":"Point"}
}