{
  "type": "Feature",
  "properties": {
    "addr:full":"3, Rue Victor Lerey, 91130 Ris Orangis Ile de France 91130",
    "addr:housenumber":"3",
    "addr:postcode":"91130;91130",
    "addr:street":"Rue Victor Lerey",
    "iso:country":"FR",
    "sg:address":"3, Rue Victor Lerey, 91130 Ris Orangis",
    "sg:orig_category":"Non-Classified Establishments",
    "sg:phone":"+33 1 69 02 09 64",
    "sg:postcode":"91130",
    "sg:province":"Ile de France",
    "wof:name":"A' Bis S.a.r.l.",
    "wof:placetype":"venue"
},
  "geometry": {"coordinates":[2.415489,48.649853],"type":"Point"}
}