{
  "type": "Feature",
  "properties": {
    "addr:full":"61 Av Du Pdt Jf Kennedy 33700 M\u00e9rignac M\u00e9rignac Aquitaine 33700",
    "addr:postcode":"33700;33700",
    "addr:street":"61 Av Du Pdt;Kennedy",
    "iso:country":"FR",
    "sg:address":"61 Av Du Pdt Jf Kennedy 33700 M\u00e9rignac",
    "sg:city":"M\u00e9rignac",
    "sg:classifiers":[
        {
            "category":"Manufacturing",
            "subcategory":"Building Materials",
            "type":"Manufacturing & Wholesale Goods"
        }
    ],
    "sg:phone":"+33 5 56 34 34 08",
    "sg:postcode":"33700",
    "sg:province":"Aquitaine",
    "sg:tags":[
        "glass",
        "ceramic"
    ],
    "wof:name":"Etablissements Boch Freres",
    "wof:placetype":"venue"
},
  "geometry": {"coordinates":[-0.64762,44.841808],"type":"Point"}
}