{
  "type": "Feature",
  "properties": {
    "addr:full":"Carrefour de la Grotte Saint Sulpice des Landes Pays de Loire 44540",
    "addr:postcode":"44540",
    "addr:street":"Carrefour De La Grotte Saint Sulpice Des Landes",
    "iso:country":"FR",
    "sg:address":"Carrefour de la Grotte",
    "sg:city":"Saint Sulpice des Landes",
    "sg:orig_category":"Non-Classified Establishments",
    "sg:phone":"+33 2 40 97 01 69",
    "sg:postcode":"44540",
    "sg:province":"Pays de Loire",
    "wof:name":"Thier\u00e9 S.a.",
    "wof:placetype":"venue"
},
  "geometry": {"coordinates":[-1.208252,47.574638],"type":"Point"}
}