{
  "type": "Feature",
  "properties": {
    "iso:country":"FR",
    "sg:address":"301, Rue de Lille - Centre Activa 2, 59223 Roncq",
    "sg:orig_category":"Unclassifiable Establishments",
    "sg:phone":"+33 3 20 94 75 78",
    "sg:province":"Nord Pas-de-Calais",
    "wof:name":"Couleurs De Flandres S.a.r.l.",
    "wof:placetype":"venue"
},
  "geometry": {"coordinates":[3.120765,50.753166],"type":"Point"}
}