{
  "type": "Feature",
  "properties": {
    "addr:full":"ZAC de la Croix Verte Nanteuil le Haudouin Picardie 60440",
    "addr:postcode":"60440",
    "addr:street":"Zac De La Croix Verte Nanteuil Le Haudouin Picardie",
    "iso:country":"FR",
    "sg:address":"ZAC de la Croix Verte",
    "sg:city":"Nanteuil le Haudouin",
    "sg:orig_category":"Non-Classified Establishments",
    "sg:phone":"+33 3 44 87 72 22",
    "sg:postcode":"60440",
    "sg:province":"Picardie",
    "wof:name":"D.m. S.a.r.l.",
    "wof:placetype":"venue"
},
  "geometry": {"coordinates":[2.812994,49.140255],"type":"Point"}
}