{
  "type": "Feature",
  "properties": {
    "addr:full":"76 Rue Eugene Pons 69004 Lyon Rhone-Alpes 69004",
    "addr:housenumber":"76",
    "addr:postcode":"69004;69004",
    "addr:street":"Rue Eugene Pons",
    "iso:country":"FR",
    "sg:address":"76 Rue Eugene Pons 69004 Lyon",
    "sg:classifiers":[
        {
            "category":"Home & Garden",
            "subcategory":"Furniture",
            "type":"Retail Goods"
        }
    ],
    "sg:phone":"+33 4 78 39 18 18",
    "sg:postcode":"69004",
    "sg:province":"Rhone-Alpes",
    "sg:tags":[
        "household",
        "-",
        "finished",
        "metallic",
        "metallurgy",
        "metalworking",
        "wood"
    ],
    "wof:name":"Societe L'acces",
    "wof:placetype":"venue"
},
  "geometry": {"coordinates":[4.840542,45.779198],"type":"Point"}
}