{
  "type": "Feature",
  "properties": {
    "iso:country":"FR",
    "sg:address":"136 Rue Grande Saint Paterne 36109 ISSOUDUN",
    "sg:classifiers":[
        {
            "category":"Wholesale",
            "subcategory":"Fruits & Vegetables",
            "type":"Manufacturing & Wholesale Goods"
        }
    ],
    "sg:phone":"+33 2 54 03 45 45",
    "sg:province":"Haute Normandie",
    "sg:tags":[
        "product",
        "cereal"
    ],
    "wof:name":"Agroberry - Bionnet Sa",
    "wof:placetype":"venue"
},
  "geometry": {"coordinates":[1.984436,46.944691],"type":"Point"}
}