{
  "type": "Feature",
  "properties": {
    "addr:full":"35, Av. Pierre S\u00e9mard, 95400 Arnouville l\u00e8s Gonesse Ile de France",
    "addr:postcode":"95400",
    "addr:street":"35 Av. Pierre Se\u0301Mard",
    "iso:country":"FR",
    "sg:address":"35, Av. Pierre S\u00e9mard, 95400 Arnouville l\u00e8s Gonesse",
    "sg:orig_category":"Unclassifiable Establishments",
    "sg:phone":"+33 1 39 85 21 64",
    "sg:province":"Ile de France",
    "wof:name":"Comme Une Image S.a.r.l.",
    "wof:placetype":"venue"
},
  "geometry": {"coordinates":[2.41493,48.99625],"type":"Point"}
}