{
  "type": "Feature",
  "properties": {
    "iso:country":"FR",
    "sg:address":"4 rue de Nantes 67100 Strasbourg",
    "sg:city":"Strasbourg",
    "sg:classifiers":[
        {
            "category":"Coffee & Tea",
            "type":"Food & Drink"
        }
    ],
    "sg:phone":"+33 3 88 34 63 36",
    "sg:postcode":"67100",
    "sg:province":"Alsace",
    "sg:tags":[
        "raw"
    ],
    "wof:name":"Ste Alsac Importation De Cafes Sa",
    "wof:placetype":"venue"
},
  "geometry": {"coordinates":[7.781294,48.570469],"type":"Point"}
}