{
  "type": "Feature",
  "properties": {
    "addr:full":"B.P. 90223 Le Boulou C\u00e9dex^^Distriport 66160 Le Boulou Languedoc-Roussillon 66160",
    "addr:postcode":"90223;66160;66160",
    "iso:country":"FR",
    "sg:address":"B.P. 90223",
    "sg:city":"Le Boulou C\u00e9dex^^Distriport 66160 Le Boulou",
    "sg:orig_category":"Non-Classified Establishments",
    "sg:phone":"+33 4 68 87 73 88",
    "sg:postcode":"66160",
    "sg:province":"Languedoc-Roussillon",
    "wof:name":"Danzas S.a.",
    "wof:placetype":"venue"
},
  "geometry": {"coordinates":[2.830395,42.52483],"type":"Point"}
}