{
  "type": "Feature",
  "properties": {
    "iso:country":"FR",
    "sg:address":"B.P. 23, 94460 Valenton C\u00e9dex^^Rue du 8 Mai 1945, 94460 Valenton",
    "sg:orig_category":"Non-Classified Establishments",
    "sg:phone":"+33 1 45 10 86 00",
    "sg:postcode":"94460",
    "sg:province":"Ile de France",
    "wof:name":"Alkan S.a.",
    "wof:placetype":"venue"
},
  "geometry": {"coordinates":[2.47036,48.744244],"type":"Point"}
}