{
  "type": "Feature",
  "properties": {
    "addr:full":"Rue Ch\u00e2teau Colombe l\u00e8s Vesoul Franche Comt\u00e9 70000",
    "addr:postcode":"70000",
    "addr:street":"Rue Cha\u0302Teau;Franche Comte\u0301",
    "iso:country":"FR",
    "sg:address":"Rue Ch\u00e2teau",
    "sg:city":"Colombe l\u00e8s Vesoul",
    "sg:orig_category":"Non-Classified Establishments",
    "sg:phone":"+33 3 84 75 19 38",
    "sg:postcode":"70000",
    "sg:province":"Franche Comt\u00e9",
    "wof:name":"Dufils Joseph",
    "wof:placetype":"venue"
},
  "geometry": {"coordinates":[6.207261,47.612019],"type":"Point"}
}