{
  "type": "Feature",
  "properties": {
    "iso:country":"FR",
    "sg:address":"Le Prieur\u00e9",
    "sg:city":"Donges",
    "sg:orig_category":"Unclassifiable Establishments",
    "sg:phone":"+33 2 40 45 32 70",
    "sg:postcode":"44480",
    "sg:province":"Pays de Loire",
    "wof:name":"Boccard S.a.",
    "wof:placetype":"venue"
},
  "geometry": {"coordinates":[-2.044924,47.323128],"type":"Point"}
}