{
  "type": "Feature",
  "properties": {
    "iso:country":"FR",
    "sg:address":"Rue du Groupe Scolaire",
    "sg:city":"H\u00e9ricourt",
    "sg:orig_category":"Unclassifiable Establishments",
    "sg:phone":"+33 3 84 56 77 05",
    "sg:postcode":"70400",
    "sg:province":"Franche Comt\u00e9",
    "wof:name":"A.s.ser.vis S.a.r.l.",
    "wof:placetype":"venue"
},
  "geometry": {"coordinates":[6.756111,47.570438],"type":"Point"}
}