{
  "type": "Feature",
  "properties": {
    "iso:country":"FR",
    "sg:address":"12C, Rue des Vosges, 90150 Foussemagne",
    "sg:orig_category":"Non-Classified Establishments",
    "sg:phone":"+33 3 84 23 42 42",
    "sg:province":"Franche Comt\u00e9",
    "wof:name":"Robotec Industries S.a.",
    "wof:placetype":"venue"
},
  "geometry": {"coordinates":[7.005215,47.635727],"type":"Point"}
}