{
  "type": "Feature",
  "properties": {
    "addr:full":"12 rue de Serre les Sapins 25115 POUILLEY LES VIGNES Franche Comt\u00e9",
    "addr:housenumber":"12",
    "addr:postcode":"25115",
    "addr:street":"Rue De Serre Les;Pouilley Les;Franche Comte\u0301",
    "iso:country":"FR",
    "sg:address":"12 rue de Serre les Sapins 25115 POUILLEY LES VIGNES",
    "sg:orig_category":"Smoke Protection Flaps, Smoke Extraction Flaps",
    "sg:phone":"+33 3 81 55 00 56",
    "sg:province":"Franche Comt\u00e9",
    "wof:name":"Sanitrap Technic S.a.r.l.",
    "wof:placetype":"venue"
},
  "geometry": {"coordinates":[5.933281,47.256176],"type":"Point"}
}