{
  "type": "Feature",
  "properties": {
    "addr:full":"13 avenue de Montpellier 34770 Gigean Languedoc-Roussillon 34770",
    "addr:housenumber":"13",
    "addr:postcode":"34770;34770",
    "addr:street":"Avenue De Montpellier",
    "iso:country":"FR",
    "sg:address":"13 avenue de Montpellier 34770 Gigean",
    "sg:classifiers":[
        {
            "category":"Wholesale",
            "subcategory":"Wine & Distilled Alcoholic Beverages",
            "type":"Manufacturing & Wholesale Goods"
        }
    ],
    "sg:phone":"+33 4 67 78 71 26",
    "sg:postcode":"34770",
    "sg:province":"Languedoc-Roussillon",
    "sg:tags":[
        "french"
    ],
    "wof:name":"Terroirs De La Voie Domitienne Coop",
    "wof:placetype":"venue"
},
  "geometry": {"coordinates":[3.717058,43.504921],"type":"Point"}
}