{
  "type": "Feature",
  "properties": {
    "iso:country":"FR",
    "sg:address":"33 Chemin Usine 88120 Sapois",
    "sg:classifiers":[
        {
            "category":"Manufacturing",
            "subcategory":"Tools & Machinery",
            "type":"Manufacturing & Wholesale Goods"
        }
    ],
    "sg:phone":"+33 3 29 24 80 60",
    "sg:postcode":"88120",
    "sg:province":"Lorraine",
    "sg:tags":[
        "metallurgy",
        "metalworking"
    ],
    "wof:name":"Fonderie (compagnie Europeenne De) Sa",
    "wof:placetype":"venue"
},
  "geometry": {"coordinates":[6.746969,48.016552],"type":"Point"}
}