{
  "type": "Feature",
  "properties": {
    "iso:country":"FR",
    "sg:address":"27110 Crosville La Vieille",
    "sg:orig_category":"Unclassifiable Establishments",
    "sg:phone":"+33 2 32 35 14 88",
    "sg:province":"Haute Normandie",
    "wof:name":"Cooperative Agricole Teillage De Lin",
    "wof:placetype":"venue"
},
  "geometry": {"coordinates":[0.934551,49.160969],"type":"Point"}
}