{
  "type": "Feature",
  "properties": {
    "iso:country":"FR",
    "sg:address":"B.P. 81033, 57214 Sarreguemines C\u00e9dex^^17, Rue Jean-Baptiste Dumaire - ZI Edison - Parc Industriel S",
    "sg:orig_category":"Non-Classified Establishments",
    "sg:phone":"+33 3 87 98 60 99",
    "sg:province":"Champagne",
    "wof:name":"S.m. France S.a.r.l.",
    "wof:placetype":"venue"
},
  "geometry": {"coordinates":[7.07192,49.113911],"type":"Point"}
}