{
  "type": "Feature",
  "properties": {
    "addr:full":"101, Av John Kennedy, 36000 Ch\u00e2teauroux Ch\u00e2teauroux Centre 36000",
    "addr:housenumber":"101",
    "addr:postcode":"36000;36000",
    "addr:street":"Av John Kennedy;Cha\u0302Teauroux",
    "iso:country":"FR",
    "sg:address":"101, Av John Kennedy, 36000 Ch\u00e2teauroux",
    "sg:city":"Ch\u00e2teauroux",
    "sg:orig_category":"Unclassifiable Establishments",
    "sg:phone":"+33 2 54 22 35 67",
    "sg:postcode":"36000",
    "sg:province":"Centre",
    "wof:name":"Rousseau S.a.s.",
    "wof:placetype":"venue"
},
  "geometry": {"coordinates":[1.692632,46.800022],"type":"Point"}
}