{
  "type": "Feature",
  "properties": {
    "iso:country":"FR",
    "sg:address":"Rue Jules Guesde - ZAI du Bois de l'Epine",
    "sg:city":"Ris Orangis",
    "sg:orig_category":"Unclassifiable Establishments",
    "sg:phone":"+33 1 60 91 13 00",
    "sg:postcode":"91130",
    "sg:province":"Ile de France",
    "wof:name":"Stordy Combustion France S.a.",
    "wof:placetype":"venue"
},
  "geometry": {"coordinates":[2.41432,48.656807],"type":"Point"}
}