{
  "type": "Feature",
  "properties": {
    "addr:full":"39 all\u00e9e Gl\u00fcck 68200 Mulhouse Mulhouse Alsace 68200",
    "addr:housenumber":"39",
    "addr:postcode":"68200;68200",
    "addr:street":"Alle\u0301E Glueck",
    "iso:country":"FR",
    "sg:address":"39 all\u00e9e Gl\u00fcck 68200 Mulhouse",
    "sg:city":"Mulhouse",
    "sg:classifiers":[
        {
            "category":"Communications",
            "subcategory":"Television Station",
            "type":"Services"
        }
    ],
    "sg:phone":"+33 3 89 32 75 75",
    "sg:postcode":"68200",
    "sg:province":"Alsace",
    "sg:tags":[
        "uhf",
        "ultra",
        "high",
        "frequency",
        "receiver",
        "vhf"
    ],
    "wof:name":"Est Vid\u00e9ocommunication Haut-rhin Sa",
    "wof:placetype":"venue"
},
  "geometry": {"coordinates":[7.320534,47.755348],"type":"Point"}
}