{
  "type": "Feature",
  "properties": {
    "iso:country":"FR",
    "sg:address":"3, Rue de la Savonnerie, 68460 Lutterbach",
    "sg:city":"Lutterbach",
    "sg:orig_category":"Unclassifiable Establishments",
    "sg:phone":"+33 3 89 52 89 89",
    "sg:postcode":"68460",
    "sg:province":"Alsace",
    "wof:name":"S\u00e9curitas France Est S.a.",
    "wof:placetype":"venue"
},
  "geometry": {"coordinates":[7.265727,47.755405],"type":"Point"}
}