{
  "type": "Feature",
  "properties": {
    "addr:full":"Langolvas BP 117 29600 St Martin Des Champs Morlaix Bretagne 29600",
    "addr:housenumber":"117",
    "addr:postcode":"29600;29600",
    "iso:country":"FR",
    "sg:address":"Langolvas BP 117 29600 St Martin Des Champs",
    "sg:city":"Morlaix",
    "sg:classifiers":[
        {
            "category":"Building & Trades",
            "subcategory":"Construction",
            "type":"Services"
        }
    ],
    "sg:phone":"+33 2 98 88 57 20",
    "sg:postcode":"29600",
    "sg:province":"Bretagne",
    "sg:tags":[
        "work",
        "public"
    ],
    "wof:name":"Eurovia Bretagne",
    "wof:placetype":"venue"
},
  "geometry": {"coordinates":[-3.790329,48.535446],"type":"Point"}
}