{
  "type": "Feature",
  "properties": {
    "addr:full":"Rte du Village Furiani Bastia Corse 20600",
    "addr:postcode":"20600",
    "addr:street":"Rte Du Village",
    "iso:country":"FR",
    "sg:address":"Rte du Village Furiani",
    "sg:city":"Bastia",
    "sg:orig_category":"Non-Classified Establishments",
    "sg:phone":"+33 4 95 33 00 33",
    "sg:postcode":"20600",
    "sg:province":"Corse",
    "wof:name":"Pastis Dami S.a.r.l.",
    "wof:placetype":"venue"
},
  "geometry": {"coordinates":[9.415856,42.658413],"type":"Point"}
}