{
  "type": "Feature",
  "properties": {
    "addr:full":"482 Rue Du Luxemburg 27000 Evreux Haute Normandie",
    "addr:housenumber":"482",
    "addr:postcode":"27000",
    "addr:street":"Rue Du Luxemburg;Haute Normandie",
    "iso:country":"FR",
    "sg:address":"482 Rue Du Luxemburg 27000 Evreux",
    "sg:classifiers":[
        {
            "category":"Professional",
            "type":"Services"
        }
    ],
    "sg:phone":"+33 2 32 33 55 90",
    "sg:province":"Haute Normandie",
    "sg:tags":[
        "transport",
        "road"
    ],
    "wof:name":"Frans Maas Center Sa",
    "wof:placetype":"venue"
},
  "geometry": {"coordinates":[1.185488,49.033009],"type":"Point"}
}