{
  "type": "Feature",
  "properties": {
    "iso:country":"FR",
    "sg:address":"302 Rue Georges Duma 30350 Ledignan",
    "sg:classifiers":[
        {
            "category":"Building & Trades",
            "subcategory":"Construction",
            "type":"Services"
        }
    ],
    "sg:phone":"+33 4 66 83 40 96",
    "sg:postcode":"30350",
    "sg:province":"Languedoc-Roussillon",
    "sg:tags":[
        "work",
        "public"
    ],
    "wof:name":"Mulero Et Fils",
    "wof:placetype":"venue"
},
  "geometry": {"coordinates":[4.108555,43.99017],"type":"Point"}
}