{
  "type": "Feature",
  "properties": {
    "addr:full":"44 Av Gustave Eiffel 33603 Pessac Cedex Basse Normandie",
    "addr:postcode":"33603",
    "addr:street":"44 Av Gustave Eiffel",
    "iso:country":"FR",
    "sg:address":"44 Av Gustave Eiffel 33603 Pessac Cedex",
    "sg:classifiers":[
        {
            "category":"Utilities",
            "subcategory":"Electric",
            "type":"Services"
        }
    ],
    "sg:phone":"+33 5 56 36 28 28",
    "sg:province":"Basse Normandie",
    "sg:tags":[
        "electricity",
        "electronic",
        "electrical",
        "equipment"
    ],
    "wof:name":"Guy Fargamel Sa",
    "wof:placetype":"venue"
},
  "geometry": {"coordinates":[-0.65789,44.777489],"type":"Point"}
}