{
  "type": "Feature",
  "properties": {
    "iso:country":"FR",
    "sg:address":"10 Rue Des Entrepreneurs 77270 Villeparisis",
    "sg:classifiers":[
        {
            "category":"Building & Trades",
            "subcategory":"Electrical",
            "type":"Services"
        }
    ],
    "sg:phone":"+33 1 64 27 08 44",
    "sg:postcode":"77270",
    "sg:province":"Ile de France",
    "sg:tags":[
        "electronic",
        "lighting",
        "equipment"
    ],
    "wof:name":"Ngn (ets) Sarl",
    "wof:placetype":"venue"
},
  "geometry": {"coordinates":[2.622167,48.949982],"type":"Point"}
}