{
  "type": "Feature",
  "properties": {
    "addr:full":"RN 1 Sainte Genevi\u00e8ve Picardie 60730",
    "addr:postcode":"60730",
    "addr:street":"Rn 1 Sainte Genevie\u0300Ve Picardie",
    "iso:country":"FR",
    "sg:address":"RN 1",
    "sg:city":"Sainte Genevi\u00e8ve",
    "sg:orig_category":"Unclassifiable Establishments",
    "sg:phone":"+33 3 44 08 21 51",
    "sg:postcode":"60730",
    "sg:province":"Picardie",
    "wof:name":"Draka Paricable S.a.",
    "wof:placetype":"venue"
},
  "geometry": {"coordinates":[2.281035,49.27602],"type":"Point"}
}