{
  "type": "Feature",
  "properties": {
    "addr:full":"Rte de Lyon - ZAC du Baconnet Montagny Rhone-Alpes 69700",
    "addr:postcode":"69700",
    "addr:street":"Rte De Lyon Zac Du Baconnet;Rhone-Alpes",
    "iso:country":"FR",
    "sg:address":"Rte de Lyon - ZAC du Baconnet",
    "sg:city":"Montagny",
    "sg:orig_category":"Unclassifiable Establishments",
    "sg:phone":"+33 4 78 73 04 88",
    "sg:postcode":"69700",
    "sg:province":"Rhone-Alpes",
    "wof:name":"Sodep S.a.",
    "wof:placetype":"venue"
},
  "geometry": {"coordinates":[4.715199,45.551682],"type":"Point"}
}