{
  "type": "Feature",
  "properties": {
    "addr:full":"6, Rue Christiaan Huygens - Parc Lafayette, 25000 Besan\u00e7on Franche Comt\u00e9 25000",
    "addr:housenumber":"6",
    "addr:postcode":"25000;25000",
    "addr:street":"Rue Christiaan Huygens;Franche Comte\u0301",
    "iso:country":"FR",
    "sg:address":"6, Rue Christiaan Huygens - Parc Lafayette, 25000 Besan\u00e7on",
    "sg:orig_category":"Non-Classified Establishments",
    "sg:phone":"+33 3 81 51 40 28",
    "sg:postcode":"25000",
    "sg:province":"Franche Comt\u00e9",
    "wof:name":"Ciatripa S.a.",
    "wof:placetype":"venue"
},
  "geometry": {"coordinates":[5.973418,47.212471],"type":"Point"}
}