{
  "type": "Feature",
  "properties": {
    "addr:full":"84300 Cavaillon Languedoc-Roussillon",
    "addr:postcode":"84300",
    "iso:country":"FR",
    "sg:address":"84300 Cavaillon",
    "sg:orig_category":"Unclassifiable Establishments",
    "sg:phone":"+33 4 90 76 14 00",
    "sg:province":"Languedoc-Roussillon",
    "wof:name":"Fruidor M\u00fbrisserie S.a.",
    "wof:placetype":"venue"
},
  "geometry": {"coordinates":[5.04855,43.84869],"type":"Point"}
}