{
  "type": "Feature",
  "properties": {
    "iso:country":"FR",
    "sg:address":"Zi Kergaradec 29490 Guipavas",
    "sg:city":"Guipavas",
    "sg:classifiers":[
        {
            "category":"Food & Beverages",
            "subcategory":"Fruits & Vegetables",
            "type":"Retail Goods"
        }
    ],
    "sg:phone":"+33 2 98 34 48 48",
    "sg:postcode":"29490",
    "sg:province":"Bretagne",
    "sg:tags":[
        "frozen",
        "product",
        "related"
    ],
    "wof:name":"Kermad Societe Sa",
    "wof:placetype":"venue"
},
  "geometry": {"coordinates":[-4.400551,48.435982],"type":"Point"}
}