{
  "type": "Feature",
  "properties": {
    "addr:full":"rue des Purelles 42600 Montbrison Rhone-Alpes 42600",
    "addr:postcode":"42600;42600",
    "addr:street":"Rue Des Purelles",
    "iso:country":"FR",
    "sg:address":"rue des Purelles 42600 Montbrison",
    "sg:orig_category":"Steelworks, Turnkey",
    "sg:phone":"+33 4 77 96 20 10",
    "sg:postcode":"42600",
    "sg:province":"Rhone-Alpes",
    "wof:name":"Ste Metallurgique Du Forez S.a.",
    "wof:placetype":"venue"
},
  "geometry": {"coordinates":[4.080865,45.597019],"type":"Point"}
}