{
  "type": "Feature",
  "properties": {
    "addr:full":"228, Chemin du Canal, 74300 Thyez Rhone-Alpes 74300",
    "addr:housenumber":"228",
    "addr:postcode":"74300;74300",
    "addr:street":"Chemin Du Canal;Rhone-Alpes",
    "iso:country":"FR",
    "sg:address":"228, Chemin du Canal, 74300 Thyez",
    "sg:orig_category":"Non-Classified Establishments",
    "sg:phone":"+33 4 50 98 54 91",
    "sg:postcode":"74300",
    "sg:province":"Rhone-Alpes",
    "wof:name":"Bacchetti Et Fils S.a.r.l.",
    "wof:placetype":"venue"
},
  "geometry": {"coordinates":[6.55417,46.076881],"type":"Point"}
}