{
  "type": "Feature",
  "properties": {
    "iso:country":"FR",
    "sg:address":"13 rue des Communes 78260 ACHERES",
    "sg:classifiers":[
        {
            "category":"Shopping",
            "subcategory":"Baby Store",
            "type":"Retail Goods"
        }
    ],
    "sg:phone":"+33 1 39 11 36 52",
    "sg:postcode":"78260",
    "sg:province":"Ile de France",
    "sg:tags":[
        "children's",
        "underwear"
    ],
    "wof:name":"Fopem Distribution Sa",
    "wof:placetype":"venue"
},
  "geometry": {"coordinates":[2.059332,48.964661],"type":"Point"}
}