{
  "type": "Feature",
  "properties": {
    "addr:full":"ZI des Deux Montagnes BP 218 74100 Ville la Grand Rhone-Alpes 74100",
    "addr:housenumber":"218",
    "addr:postcode":"74100;74100",
    "addr:street":"Des Deux Montagnes Bp;La Grand Rhone-Alpes",
    "iso:country":"FR",
    "sg:address":"ZI",
    "sg:city":"des Deux Montagnes BP 218 74100 Ville la Grand",
    "sg:classifiers":[
        {
            "category":"Professional",
            "subcategory":"Engineering",
            "type":"Services"
        }
    ],
    "sg:phone":"+33 4 50 87 73 00",
    "sg:postcode":"74100",
    "sg:province":"Rhone-Alpes",
    "sg:tags":[
        "machine",
        "-",
        "mechanical"
    ],
    "wof:name":"Mecasonic",
    "wof:placetype":"venue"
},
  "geometry": {"coordinates":[6.249424,46.202831],"type":"Point"}
}