{
  "type": "Feature",
  "properties": {
    "addr:full":"Route De Dax 40260 Castets Castets Aquitaine 40260",
    "addr:postcode":"40260;40260",
    "addr:street":"Route De Dax",
    "iso:country":"FR",
    "sg:address":"Route De Dax 40260 Castets",
    "sg:city":"Castets",
    "sg:classifiers":[
        {
            "category":"Home & Garden",
            "subcategory":"Furniture",
            "type":"Retail Goods"
        }
    ],
    "sg:phone":"+33 5 58 55 09 80",
    "sg:postcode":"40260",
    "sg:province":"Aquitaine",
    "sg:tags":[
        "wood"
    ],
    "wof:name":"Escobois",
    "wof:placetype":"venue"
},
  "geometry": {"coordinates":[-1.131537,43.868031],"type":"Point"}
}