{
  "type": "Feature",
  "properties": {
    "iso:country":"FR",
    "sg:address":"B.P. 7, 77920 Samois sur Seine^^121, Rte de Courbuisson, 77920 Samois sur Seine",
    "sg:orig_category":"Non-Classified Establishments",
    "sg:phone":"+33 1 64 69 56 00",
    "sg:province":"Ile de France",
    "wof:name":"Gride S.a.",
    "wof:placetype":"venue"
},
  "geometry": {"coordinates":[2.75183,48.451469],"type":"Point"}
}