{
  "type": "Feature",
  "properties": {
    "addr:full":"14 Pl Des Terreaux 01300 Belley Rhone-Alpes 01300",
    "addr:housenumber":"14",
    "addr:postcode":"01300;01300",
    "addr:street":"Pl Des Terreaux",
    "iso:country":"FR",
    "sg:address":"14 Pl Des Terreaux 01300 Belley",
    "sg:classifiers":[
        {
            "category":"Banks & Credit Unions",
            "subcategory":"Financial Services",
            "type":"Services"
        }
    ],
    "sg:phone":"+33 4 79 81 23 27",
    "sg:postcode":"01300",
    "sg:province":"Rhone-Alpes",
    "sg:tags":[
        "banking",
        "insurance",
        "institution",
        "finance"
    ],
    "wof:name":"Lyonnaise De Banque",
    "wof:placetype":"venue"
},
  "geometry": {"coordinates":[5.686344,45.760349],"type":"Point"}
}