{
  "type": "Feature",
  "properties": {
    "addr:full":"47, Rue de Montgrand, 13006 Marseille Provence-Alpes-C\u00f4te d'Azur",
    "addr:housenumber":"47",
    "addr:postcode":"13006",
    "addr:street":"Rue De Montgrand",
    "iso:country":"FR",
    "sg:address":"47, Rue de Montgrand, 13006 Marseille",
    "sg:orig_category":"Unclassifiable Establishments",
    "sg:phone":"+33 4 91 54 31 00",
    "sg:province":"Provence-Alpes-C\u00f4te d'Azur",
    "wof:name":"Consomatel S.a.r.l.",
    "wof:placetype":"venue"
},
  "geometry": {"coordinates":[5.37579,43.290939],"type":"Point"}
}