{
  "type": "Feature",
  "properties": {
    "iso:country":"FR",
    "sg:address":"ZI All\u00e9e du Puits",
    "sg:city":"Fontenay le Comte",
    "sg:orig_category":"Unclassifiable Establishments",
    "sg:phone":"+33 2 51 53 13 10",
    "sg:postcode":"85200",
    "sg:province":"Pays de Loire",
    "wof:name":"Horo Quartz S.a.",
    "wof:placetype":"venue"
},
  "geometry": {"coordinates":[-0.802274,46.464867],"type":"Point"}
}