{
  "type": "Feature",
  "properties": {
    "iso:country":"FR",
    "sg:address":"71, Rue Fromentel, 37000 Tours",
    "sg:city":"Tours",
    "sg:orig_category":"Unclassifiable Establishments",
    "sg:phone":"+33 2 47 39 39 52",
    "sg:postcode":"37000",
    "sg:province":"Centre",
    "wof:name":"Imprimerie Rotos Vincent S.a.",
    "wof:placetype":"venue"
},
  "geometry": {"coordinates":[0.672341,47.377823],"type":"Point"}
}