{
  "type": "Feature",
  "properties": {
    "addr:full":"Z.I. Artois Flandres - Zone D Douvrin Nord Pas-de-Calais 62138",
    "addr:housenumber":"flandres",
    "addr:postcode":"62138",
    "addr:street":"Z.I. Artois;Zone D Douvrin Nord",
    "iso:country":"FR",
    "sg:address":"Z.I. Artois Flandres - Zone D",
    "sg:city":"Douvrin",
    "sg:orig_category":"Unclassifiable Establishments",
    "sg:phone":"+33 3 21 40 99 99",
    "sg:postcode":"62138",
    "sg:province":"Nord Pas-de-Calais",
    "wof:name":"Marsy S.a.",
    "wof:placetype":"venue"
},
  "geometry": {"coordinates":[2.831475,50.508141],"type":"Point"}
}