{
  "type": "Feature",
  "properties": {
    "iso:country":"FR",
    "sg:address":"21, Rue du Fer \u00e0 Cheval, 95200 Sarcelles",
    "sg:orig_category":"Unclassifiable Establishments",
    "sg:phone":"+33 1 34 38 38 38",
    "sg:province":"Ile de France",
    "wof:name":"Manustra Ile De France S.a.",
    "wof:placetype":"venue"
},
  "geometry": {"coordinates":[2.391682,48.994598],"type":"Point"}
}