{
  "type": "Feature",
  "properties": {
    "addr:full":"Rte de la Massane - ZA Saint R\u00e9my de Provence Nord Pas-de-Calais 13210",
    "addr:postcode":"13210",
    "addr:street":"Rte De La Massane Za Saint Re\u0301My De Provence Nord",
    "iso:country":"FR",
    "sg:address":"Rte de la Massane - ZA",
    "sg:city":"Saint R\u00e9my de Provence",
    "sg:orig_category":"Non-Classified Establishments",
    "sg:phone":"+33 4 90 92 75 07",
    "sg:postcode":"13210",
    "sg:province":"Nord Pas-de-Calais",
    "wof:name":"S.i.c.a.p. S.a. - Soci\u00e9t\u00e9 Industrielle De Construction D'appareil De Piscine",
    "wof:placetype":"venue"
},
  "geometry": {"coordinates":[4.829515,43.788704],"type":"Point"}
}