{
  "type": "Feature",
  "properties": {
    "iso:country":"FR",
    "sg:address":"2 Rue Moli\u00e8re 38000 Grenoble",
    "sg:classifiers":[
        {
            "category":"Manufacturing",
            "subcategory":"Leather Goods",
            "type":"Manufacturing & Wholesale Goods"
        }
    ],
    "sg:phone":"+33 4 76 46 29 94",
    "sg:postcode":"38000",
    "sg:province":"Rhone-Alpes",
    "sg:tags":[
        "shoe"
    ],
    "wof:name":"Ets Gandy Pere Et Fils Sa",
    "wof:placetype":"venue"
},
  "geometry": {"coordinates":[5.725108,45.189671],"type":"Point"}
}