{
  "type": "Feature",
  "properties": {
    "addr:full":"47, Av. des Grenottes, 95800 Cergy Ile de France",
    "addr:postcode":"95800;ile",
    "addr:street":"47 Av. Des Grenottes",
    "iso:country":"FR",
    "sg:address":"47, Av. des Grenottes, 95800 Cergy",
    "sg:orig_category":"Unclassifiable Establishments",
    "sg:phone":"+33 1 34 22 95 22",
    "sg:province":"Ile de France",
    "wof:name":"Eurosep Instruments S.a.s.",
    "wof:placetype":"venue"
},
  "geometry": {"coordinates":[2.000455,49.035156],"type":"Point"}
}