{
  "type": "Feature",
  "properties": {
    "iso:country":"FR",
    "sg:address":"Route De L Ancienne Gare 77460 Chaintreaux",
    "sg:classifiers":[
        {
            "category":"Professional",
            "subcategory":"Engineering",
            "type":"Services"
        }
    ],
    "sg:phone":"+33 1 60 55 50 13",
    "sg:postcode":"77460",
    "sg:province":"Ile de France",
    "sg:tags":[
        "machine",
        "-",
        "mechanical"
    ],
    "wof:name":"Panex Product",
    "wof:placetype":"venue"
},
  "geometry": {"coordinates":[2.812829,48.196316],"type":"Point"}
}