{
  "type": "Feature",
  "properties": {
    "addr:full":"B.P. 95, 59560 Comines^^62, Rte d'Armenti\u00e8res, 59560 Comines Nord Pas-de-Calais",
    "addr:postcode":"59560;59560",
    "addr:street":"B.P. 95;Rte D'Armentie \u0300Res",
    "iso:country":"FR",
    "sg:address":"B.P. 95, 59560 Comines^^62, Rte d'Armenti\u00e8res, 59560 Comines",
    "sg:orig_category":"Non-Classified Establishments",
    "sg:phone":"+33 3 20 63 06 51",
    "sg:province":"Nord Pas-de-Calais",
    "wof:name":"Matiba S.a.r.l.",
    "wof:placetype":"venue"
},
  "geometry": {"coordinates":[2.999968,50.761131],"type":"Point"}
}