{
  "type": "Feature",
  "properties": {
    "addr:full":"Lot. Industriel Ouest - Usine C\u00e9raver Bazet Midi Pyr\u00e9n\u00e9es 65460",
    "addr:postcode":"65460",
    "addr:street":"Lot. Industriel Ouest",
    "iso:country":"FR",
    "sg:address":"Lot. Industriel Ouest - Usine C\u00e9raver",
    "sg:city":"Bazet",
    "sg:orig_category":"Non-Classified Establishments",
    "sg:phone":"+33 5 62 33 39 12",
    "sg:postcode":"65460",
    "sg:province":"Midi Pyr\u00e9n\u00e9es",
    "wof:name":"Soci\u00e9t\u00e9 De M\u00e9canique G\u00e9n\u00e9rale Bernad S.a.r.l.",
    "wof:placetype":"venue"
},
  "geometry": {"coordinates":[0.074286,43.290794],"type":"Point"}
}