{
  "type": "Feature",
  "properties": {
    "addr:full":"1 rue des Fusilles; Besan\u00e7on; 25000 Franche Comt\u00e9 25000",
    "addr:housenumber":"1",
    "addr:postcode":"25000;25000",
    "addr:street":"Rue Des Fusilles;Comte\u0301",
    "iso:country":"FR",
    "sg:address":"1 rue des Fusilles; Besan\u00e7on; 25000",
    "sg:classifiers":[
        {
            "category":"Banks & Credit Unions",
            "subcategory":"Bank",
            "type":"Services"
        }
    ],
    "sg:phone":"+33 3381820620",
    "sg:postcode":"25000",
    "sg:province":"Franche Comt\u00e9",
    "wof:name":"Banque De Neuflize, Schlumburger Mallet",
    "wof:placetype":"venue"
},
  "geometry": {"coordinates":[6.031414,47.23362],"type":"Point"}
}