{
  "type": "Feature",
  "properties": {
    "iso:country":"FR",
    "sg:address":"37, Av du Pr\u00e9sident Wilson, 10120 Saint Andr\u00e9 les Vergers",
    "sg:orig_category":"Unclassifiable Establishments",
    "sg:phone":"+33 3 25 73 09 45",
    "sg:province":"Champagne",
    "wof:name":"Nouvelle Bonneterie De Saint Andr\u00e9",
    "wof:placetype":"venue"
},
  "geometry": {"coordinates":[4.063421,48.288761],"type":"Point"}
}