{
  "type": "Feature",
  "properties": {
    "addr:full":"4, Av. d'Espagne - ZAC des Vignes, 80090 Amiens Picardie",
    "addr:postcode":"80090",
    "addr:street":"Av. D'Espagne Zac Des Vignes",
    "iso:country":"FR",
    "sg:address":"4, Av. d'Espagne - ZAC des Vignes, 80090 Amiens",
    "sg:orig_category":"Unclassifiable Establishments",
    "sg:phone":"+33 3 22 53 03 07",
    "sg:province":"Picardie",
    "wof:name":"Locapharm S.a.",
    "wof:placetype":"venue"
},
  "geometry": {"coordinates":[2.328541,49.864941],"type":"Point"}
}