{
  "type": "Feature",
  "properties": {
    "addr:full":"B.P. 15, 06901 Sophia Antipolis C\u00e9dex^^3550, Rte des Dolines, 06410 Biot Midi Pyr\u00e9n\u00e9es",
    "addr:postcode":"06901;06410",
    "addr:street":"B.P. 15;Rte Des Dolines",
    "iso:country":"FR",
    "sg:address":"B.P. 15, 06901 Sophia Antipolis C\u00e9dex^^3550, Rte des Dolines, 06410 Biot",
    "sg:orig_category":"Non-Classified Establishments",
    "sg:phone":"+33 4 92 96 68 78",
    "sg:province":"Midi Pyr\u00e9n\u00e9es",
    "wof:name":"Esn\u00e9e Hardouin S.n.c.",
    "wof:placetype":"venue"
},
  "geometry": {"coordinates":[7.08509,43.626709],"type":"Point"}
}