{
  "type": "Feature",
  "properties": {
    "addr:full":"29, Av. du Docteur Heckel, 13011 Marseille Poitou-Charentes",
    "addr:postcode":"13011",
    "addr:street":"29 Av. Du Docteur Heckel",
    "iso:country":"FR",
    "sg:address":"29, Av. du Docteur Heckel, 13011 Marseille",
    "sg:orig_category":"Unclassifiable Establishments",
    "sg:phone":"+33 4 91 44 87 42",
    "sg:province":"Poitou-Charentes",
    "wof:name":"Gavroche S.a.",
    "wof:placetype":"venue"
},
  "geometry": {"coordinates":[5.44151,43.288658],"type":"Point"}
}