{
  "type": "Feature",
  "properties": {
    "addr:full":"1, Rue Edmond Besse, 33000 Bordeaux Bordeaux Aquitaine 33000",
    "addr:housenumber":"1",
    "addr:postcode":"33000;33000",
    "addr:street":"Rue Edmond Besse",
    "iso:country":"FR",
    "sg:address":"1, Rue Edmond Besse, 33000 Bordeaux",
    "sg:city":"Bordeaux",
    "sg:orig_category":"Unclassifiable Establishments",
    "sg:phone":"+33 5 56 69 68 68",
    "sg:postcode":"33000",
    "sg:province":"Aquitaine",
    "wof:name":"Verceral S.a.",
    "wof:placetype":"venue"
},
  "geometry": {"coordinates":[-0.57826,44.830975],"type":"Point"}
}