{
  "type": "Feature",
  "properties": {
    "iso:country":"FR",
    "sg:address":"Rue Gustave Eiffel - ZI",
    "sg:city":"Villeneuve Saint Germain",
    "sg:orig_category":"Abrasifs Aff\u00fbtage d'outils Cabines de peintures Chants PVC Colles Lasures Machines et/ou appareils p",
    "sg:phone":"+33 3 23 73 40 90",
    "sg:postcode":"02200",
    "sg:province":"Picardie",
    "wof:name":"B.v.d. S.a.r.l.",
    "wof:placetype":"venue"
},
  "geometry": {"coordinates":[3.32451,49.366711],"type":"Point"}
}