{
  "type": "Feature",
  "properties": {
    "iso:country":"FR",
    "sg:address":"36, Bd Pasteur, 63000 Clermont Ferrand",
    "sg:city":"Clermont-Ferrand",
    "sg:orig_category":"Unclassifiable Establishments",
    "sg:phone":"+33 4 73 29 30 31",
    "sg:postcode":"63000",
    "sg:province":"Auvergne",
    "wof:name":"Marc Andrieux Consultants S.a.",
    "wof:placetype":"venue"
},
  "geometry": {"coordinates":[3.078041,45.772923],"type":"Point"}
}