{
  "type": "Feature",
  "properties": {
    "iso:country":"FR",
    "sg:address":"151, Av. des Aygalades, 13015 Marseille",
    "sg:orig_category":"Non-Classified Establishments",
    "sg:phone":"+33 4 91 03 20 95",
    "sg:province":"Midi Pyr\u00e9n\u00e9es",
    "wof:name":"Stockinox S.a.",
    "wof:placetype":"venue"
},
  "geometry": {"coordinates":[5.366048,43.345402],"type":"Point"}
}