{
  "type": "Feature",
  "properties": {
    "addr:full":"Rue de la Roseraie Beaumont C\u00e9dex Franche Comt\u00e9 63109",
    "addr:postcode":"63109",
    "addr:street":"Rue De La Roseraie;Franche Comte\u0301",
    "iso:country":"FR",
    "sg:address":"Rue de la Roseraie",
    "sg:city":"Beaumont C\u00e9dex",
    "sg:orig_category":"Non-Classified Establishments",
    "sg:phone":"+33 4 73 27 67 93",
    "sg:postcode":"63109",
    "sg:province":"Franche Comt\u00e9",
    "wof:name":"B. Gouineau S.a.r.l.",
    "wof:placetype":"venue"
},
  "geometry": {"coordinates":[3.08562,45.75024],"type":"Point"}
}