{
  "type": "Feature",
  "properties": {
    "addr:full":"6, Av. de Norv\u00e8ge - B\u00e2t. Hightec, 91940 Les Ulis Ile de France",
    "addr:housenumber":"ba\u0302t",
    "addr:postcode":"91940",
    "addr:street":"Av. De Norve\u0300Ge",
    "iso:country":"FR",
    "sg:address":"6, Av. de Norv\u00e8ge - B\u00e2t. Hightec, 91940 Les Ulis",
    "sg:orig_category":"Unclassifiable Establishments",
    "sg:phone":"+33 1 69 59 15 15",
    "sg:province":"Ile de France",
    "wof:name":"A.l.c.e.a. S.a. - Automatismes Logiciels Conceptions Etudes Et Appl",
    "wof:placetype":"venue"
},
  "geometry": {"coordinates":[2.169475,48.68161],"type":"Point"}
}