{
  "type": "Feature",
  "properties": {
    "iso:country":"FR",
    "sg:address":"33 Rue Sartoris 92250 La Garenne Colombes",
    "sg:classifiers":[
        {
            "category":"Home & Garden",
            "subcategory":"Furniture",
            "type":"Retail Goods"
        }
    ],
    "sg:phone":"+33 1 42 42 78 52",
    "sg:postcode":"92250",
    "sg:province":"Ile de France",
    "sg:tags":[
        "household",
        "wood"
    ],
    "wof:name":"Phelippeau Decoration Sa",
    "wof:placetype":"venue"
},
  "geometry": {"coordinates":[2.249499,48.908161],"type":"Point"}
}