{
  "type": "Feature",
  "properties": {
    "iso:country":"FR",
    "sg:address":"1, Rue du Gatinais, 89150 Saint Val\u00e9rien",
    "sg:city":"Brannay",
    "sg:orig_category":"Non-Classified Establishments",
    "sg:phone":"+33 3 86 88 60 11",
    "sg:postcode":"89150",
    "sg:province":"Bourgogne",
    "wof:name":"Soci\u00e9t\u00e9 Nouvelle Simon S.a.r.l.",
    "wof:placetype":"venue"
},
  "geometry": {"coordinates":[3.086341,48.177597],"type":"Point"}
}