{
  "type": "Feature",
  "properties": {
    "iso:country":"FR",
    "sg:address":"B.P. 42093, 14102 Lisieux C\u00e9dex 2^^Rue Edouard Branly, 14100 Lisieux",
    "sg:city":"Lisieux",
    "sg:orig_category":"Non-Classified Establishments",
    "sg:phone":"+33 2 31 32 56 55",
    "sg:postcode":"14100",
    "sg:province":"Basse Normandie",
    "wof:name":"Europfil C\u00e9ralnor S.a.",
    "wof:placetype":"venue"
},
  "geometry": {"coordinates":[0.189525,49.074329],"type":"Point"}
}