{
  "type": "Feature",
  "properties": {
    "iso:country":"FR",
    "sg:address":"ZI de Felet",
    "sg:city":"Thiers",
    "sg:orig_category":"Unclassifiable Establishments",
    "sg:phone":"+33 4 73 80 72 67",
    "sg:postcode":"63300",
    "sg:province":"Auvergne",
    "wof:name":"Parembal S.a.",
    "wof:placetype":"venue"
},
  "geometry": {"coordinates":[3.548272,45.855244],"type":"Point"}
}