{
  "type": "Feature",
  "properties": {
    "addr:full":"Rte de Sologne - ZA de Gaudet Mennetou sur Cher Centre 41320",
    "addr:postcode":"41320",
    "addr:street":"Rte De Sologne Za De Gaudet Mennetou",
    "iso:country":"FR",
    "sg:address":"Rte de Sologne - ZA de Gaudet",
    "sg:city":"Mennetou sur Cher",
    "sg:orig_category":"Unclassifiable Establishments",
    "sg:phone":"+33 2 54 98 03 40",
    "sg:postcode":"41320",
    "sg:province":"Centre",
    "wof:name":"Cartonnages Cl\u00e9ment Papin S.a.",
    "wof:placetype":"venue"
},
  "geometry": {"coordinates":[1.749941,47.248085],"type":"Point"}
}