{
  "type": "Feature",
  "properties": {
    "iso:country":"FR",
    "sg:address":"60, Rue Eug\u00e8ne Caron, 92400 Courbevoie",
    "sg:orig_category":"Unclassifiable Establishments",
    "sg:phone":"+33 1 43 33 00 62",
    "sg:province":"Ile de France",
    "wof:name":"Imprimerie Arci S.a.r.l.",
    "wof:placetype":"venue"
},
  "geometry": {"coordinates":[2.243805,48.897186],"type":"Point"}
}