{
  "type": "Feature",
  "properties": {
    "addr:full":"8 Rue Martel 75010 Paris Ile de France 75010",
    "addr:housenumber":"8",
    "addr:postcode":"75010;75010",
    "addr:street":"Rue Martel",
    "iso:country":"FR",
    "sg:address":"8 Rue Martel 75010 Paris",
    "sg:classifiers":[
        {
            "category":"Shopping",
            "subcategory":"Clothing, Apparel, & Fashions",
            "type":"Retail Goods"
        }
    ],
    "sg:phone":"+33 1 44 83 06 83",
    "sg:postcode":"75010",
    "sg:province":"Ile de France",
    "sg:tags":[
        "textile",
        "clothing",
        "clothes"
    ],
    "wof:name":"Jeux Calins",
    "wof:placetype":"venue"
},
  "geometry": {"coordinates":[2.353154,48.873917],"type":"Point"}
}