{
  "type": "Feature",
  "properties": {
    "iso:country":"FR",
    "sg:address":"99, Rue de la Colline, 54000 Nancy",
    "sg:orig_category":"Non-Classified Establishments",
    "sg:phone":"+33 3 83 96 38 61",
    "sg:postcode":"54000",
    "sg:province":"Lorraine",
    "wof:name":"Amau",
    "wof:placetype":"venue"
},
  "geometry": {"coordinates":[6.152716,48.697742],"type":"Point"}
}