{
  "type": "Feature",
  "properties": {
    "addr:full":"ZI de Saint-Ouen Saint-Ouen Centre 41100",
    "addr:postcode":"41100",
    "addr:street":"Zi De Saint-Ouen",
    "iso:country":"FR",
    "sg:address":"ZI de Saint-Ouen",
    "sg:city":"Saint-Ouen",
    "sg:orig_category":"Unclassifiable Establishments",
    "sg:phone":"+33 2 54 73 33 33",
    "sg:postcode":"41100",
    "sg:province":"Centre",
    "wof:name":"V.f.m. S.a. - Vend\u00f4me Fermeture Menuiserie",
    "wof:placetype":"venue"
},
  "geometry": {"coordinates":[1.064763,47.792313],"type":"Point"}
}