{
  "type": "Feature",
  "properties": {
    "addr:full":"6 Rue Jean Perrin 69680 Chassieu Rhone-Alpes",
    "addr:housenumber":"6",
    "addr:postcode":"69680",
    "addr:street":"Rue Jean Perrin",
    "iso:country":"FR",
    "sg:address":"6 Rue Jean Perrin 69680 Chassieu",
    "sg:classifiers":[
        {
            "category":"Manufacturing",
            "subcategory":"Rubber & Plastics",
            "type":"Manufacturing & Wholesale Goods"
        }
    ],
    "sg:phone":"+33 4 72 47 74 30",
    "sg:province":"Rhone-Alpes",
    "wof:name":"Applications Industrielles Des Plastiques Sa (aip)",
    "wof:placetype":"venue"
},
  "geometry": {"coordinates":[4.97484,45.72813],"type":"Point"}
}