{
  "type": "Feature",
  "properties": {
    "addr:full":"Ch\u00e2teau Jolys Gan Aquitaine 64290",
    "addr:postcode":"64290",
    "iso:country":"FR",
    "sg:address":"Ch\u00e2teau Jolys",
    "sg:city":"Gan",
    "sg:orig_category":"Non-Classified Establishments",
    "sg:phone":"+33 5 59 21 72 79",
    "sg:postcode":"64290",
    "sg:province":"Aquitaine",
    "wof:name":"Domaine Latrille S.a.r.l.",
    "wof:placetype":"venue"
},
  "geometry": {"coordinates":[-0.458197,43.171352],"type":"Point"}
}