{
  "type": "Feature",
  "properties": {
    "iso:country":"FR",
    "sg:address":"3 Rue Emaux 54400 Longwy",
    "sg:classifiers":[
        {
            "category":"Home & Garden",
            "subcategory":"Furniture",
            "type":"Retail Goods"
        }
    ],
    "sg:phone":"+33 3 82 24 30 94",
    "sg:postcode":"54400",
    "sg:province":"Lorraine",
    "sg:tags":[
        "household",
        "wood"
    ],
    "wof:name":"Faienceries Et Emaux De Longwy",
    "wof:placetype":"venue"
},
  "geometry": {"coordinates":[5.774887,49.515499],"type":"Point"}
}