{
  "type": "Feature",
  "properties": {
    "iso:country":"FR",
    "sg:address":"Rte de Cize",
    "sg:city":"Hautecourt Roman\u00e8che",
    "sg:orig_category":"Unclassifiable Establishments",
    "sg:phone":"+33 4 74 51 83 07",
    "sg:postcode":"01250",
    "sg:province":"Rhone-Alpes",
    "wof:name":"Blanquart S.a.r.l.",
    "wof:placetype":"venue"
},
  "geometry": {"coordinates":[5.36418,46.190819],"type":"Point"}
}