{
  "type": "Feature",
  "properties": {
    "iso:country":"FR",
    "sg:address":"57, Rue Victor Hugo, 76000 Rouen",
    "sg:orig_category":"Unclassifiable Establishments",
    "sg:phone":"+33 2 35 71 10 76",
    "sg:province":"Haute Normandie",
    "wof:name":"Etablissements Bouley S.a.",
    "wof:placetype":"venue"
},
  "geometry": {"coordinates":[1.100527,49.440235],"type":"Point"}
}