{
  "type": "Feature",
  "properties": {
    "iso:country":"FR",
    "sg:address":"ZI",
    "sg:city":"Blangy sur Bresle",
    "sg:orig_category":"Non-Classified Establishments",
    "sg:phone":"+33 2 32 97 52 50",
    "sg:postcode":"76340",
    "sg:province":"Haute Normandie",
    "wof:name":"La Pr\u00e9cison Plastique S.a.",
    "wof:placetype":"venue"
},
  "geometry": {"coordinates":[1.593718,49.821468],"type":"Point"}
}