{
  "type": "Feature",
  "properties": {
    "addr:full":"Qrt Hardy 40140 Soustons Soustons Aquitaine 40140",
    "addr:postcode":"40140;40140",
    "addr:street":"Qrt Hardy",
    "iso:country":"FR",
    "sg:address":"Qrt Hardy 40140 Soustons",
    "sg:city":"Soustons",
    "sg:classifiers":[
        {
            "category":"Manufacturing",
            "subcategory":"Wood Products",
            "type":"Manufacturing & Wholesale Goods"
        }
    ],
    "sg:phone":"+33 5 58 41 18 25",
    "sg:postcode":"40140",
    "sg:province":"Aquitaine",
    "sg:tags":[
        "furniture"
    ],
    "wof:name":"Etablissements Gilardenghi Et Compagnie La Forestiere D'hardy",
    "wof:placetype":"venue"
},
  "geometry": {"coordinates":[-1.327244,43.755615],"type":"Point"}
}