{
  "type": "Feature",
  "properties": {
    "iso:country":"FR",
    "sg:address":"6, Rue d'Ouessant, 44600 Saint Nazaire",
    "sg:orig_category":"Unclassifiable Establishments",
    "sg:phone":"+33 2 40 22 31 37",
    "sg:province":"Pays de Loire",
    "wof:name":"C.t.m. - Compagnie De Transports Du Morbihan",
    "wof:placetype":"venue"
},
  "geometry": {"coordinates":[-2.23916,47.276218],"type":"Point"}
}