{
  "type": "Feature",
  "properties": {
    "iso:country":"FR",
    "sg:address":"Rue Jean Jaur\u00e8s - ZI des Clotais",
    "sg:city":"Champlan",
    "sg:orig_category":"Unclassifiable Establishments",
    "sg:phone":"+33 1 69 79 39 79",
    "sg:postcode":"91160",
    "sg:province":"Ile de France",
    "wof:name":"A 34 S\u00e9rigraphie S.a.",
    "wof:placetype":"venue"
},
  "geometry": {"coordinates":[2.29005,48.691734],"type":"Point"}
}