{
  "type": "Feature",
  "properties": {
    "addr:full":"16 Rue Des Gu\u00e9rins BP 39 42124 Le Coteau Nord Pas-de-Calais",
    "addr:housenumber":"16;39",
    "addr:postcode":"42124",
    "addr:street":"Rue Des Gue\u0301Rins Bp;Coteau Nord",
    "iso:country":"FR",
    "sg:address":"16 Rue Des Gu\u00e9rins BP 39 42124 Le Coteau",
    "sg:classifiers":[
        {
            "category":"Shopping",
            "subcategory":"Crafts & Fabrics",
            "type":"Retail Goods"
        }
    ],
    "sg:phone":"+33 4 77 72 34 34",
    "sg:province":"Nord Pas-de-Calais",
    "sg:tags":[
        "textile",
        "clothing"
    ],
    "wof:name":"Danjoux Transfert Sarl",
    "wof:placetype":"venue"
},
  "geometry": {"coordinates":[4.100265,46.011955],"type":"Point"}
}