{
  "type": "Feature",
  "properties": {
    "addr:full":"5 Rue Guy De Maupassant Zac De L'Avagon 13170 Les Pennes Mirabeau Midi Pyr\u00e9n\u00e9es",
    "addr:housenumber":"5",
    "addr:postcode":"13170",
    "addr:street":"Rue Guy De Maupassant Zac De L'Avagon",
    "iso:country":"FR",
    "sg:address":"5 Rue Guy De Maupassant Zac De L'Avagon 13170 Les Pennes Mirabeau",
    "sg:classifiers":[
        {
            "category":"Transit Center",
            "subcategory":"Freight",
            "type":"Transportation"
        }
    ],
    "sg:phone":"+33 4 42 02 65 99",
    "sg:province":"Midi Pyr\u00e9n\u00e9es",
    "sg:tags":[
        "metallurgy",
        "pipe",
        "metalworking",
        "sheet"
    ],
    "wof:name":"Loire Industrie",
    "wof:placetype":"venue"
},
  "geometry": {"coordinates":[5.32224,43.40062],"type":"Point"}
}