{
  "type": "Feature",
  "properties": {
    "addr:full":"Traverse De La Bourgade 13400 Aubagne Midi Pyr\u00e9n\u00e9es",
    "addr:postcode":"13400",
    "addr:street":"Traverse De La Bourgade",
    "iso:country":"FR",
    "sg:address":"Traverse De La Bourgade 13400 Aubagne",
    "sg:classifiers":[
        {
            "category":"Manufacturing",
            "subcategory":"Metals",
            "type":"Manufacturing & Wholesale Goods"
        }
    ],
    "sg:phone":"+33 4 91 87 77 00",
    "sg:province":"Midi Pyr\u00e9n\u00e9es",
    "sg:tags":[
        "metallurgy",
        "metalworking"
    ],
    "wof:name":"Softal Sa",
    "wof:placetype":"venue"
},
  "geometry": {"coordinates":[5.523875,43.283257],"type":"Point"}
}