{
  "type": "Feature",
  "properties": {
    "iso:country":"FR",
    "sg:address":"54, Bd Capitaine G\u00e8ze, 13003 Marseille",
    "sg:orig_category":"Unclassifiable Establishments",
    "sg:phone":"+33 4 95 05 16 80",
    "sg:province":"Provence-Alpes-C\u00f4te d'Azur",
    "wof:name":"Dewco Provence S.a.r.l.",
    "wof:placetype":"venue"
},
  "geometry": {"coordinates":[5.373144,43.330887],"type":"Point"}
}