{
  "type": "Feature",
  "properties": {
    "iso:country":"FR",
    "sg:address":"B.P. 5124",
    "sg:city":"Perpignan C\u00e9dex",
    "sg:orig_category":"Non-Classified Establishments",
    "sg:phone":"+33 4 68 68 50 50",
    "sg:postcode":"66031",
    "sg:province":"Midi Pyr\u00e9n\u00e9es",
    "wof:name":"Imexco S.a.s.",
    "wof:placetype":"venue"
},
  "geometry": {"coordinates":[2.8966,42.700611],"type":"Point"}
}