{
  "type": "Feature",
  "properties": {
    "iso:country":"FR",
    "sg:address":"route de Roman 73420 Mery",
    "sg:classifiers":[
        {
            "category":"Manufacturing",
            "subcategory":"Motor Vehicles & Parts",
            "type":"Manufacturing & Wholesale Goods"
        }
    ],
    "sg:phone":"+33 4 79 63 61 00",
    "sg:province":"Rhone-Alpes",
    "sg:tags":[
        "precision",
        "mechanic"
    ],
    "wof:name":"Serain Gachet Sa",
    "wof:placetype":"venue"
},
  "geometry": {"coordinates":[5.922059,45.643379],"type":"Point"}
}