{
  "type": "Feature",
  "properties": {
    "iso:country":"FR",
    "sg:address":"21, Rue Christophe Plantin, 37230 Fondettes",
    "sg:city":"Fondettes",
    "sg:orig_category":"Unclassifiable Establishments",
    "sg:phone":"+33 2 47 42 22 10",
    "sg:postcode":"37230",
    "sg:province":"Centre",
    "wof:name":"Engineering Data S.a.r.l.",
    "wof:placetype":"venue"
},
  "geometry": {"coordinates":[0.623007,47.409321],"type":"Point"}
}