{
  "type": "Feature",
  "properties": {
    "iso:country":"FR",
    "sg:address":"35, Av. de la Convention, 78500 Sartrouville",
    "sg:orig_category":"Non-Classified Establishments",
    "sg:phone":"+33 1 39 14 10 45",
    "sg:province":"Ile de France",
    "wof:name":"V.f.i. S.a. - Vanlaer Filtration Industrielle",
    "wof:placetype":"venue"
},
  "geometry": {"coordinates":[2.169112,48.936321],"type":"Point"}
}