{
  "type": "Feature",
  "properties": {
    "iso:country":"FR",
    "sg:address":"Voie Bleue - ZI Sainte Consorce",
    "sg:city":"Sainte Consorce",
    "sg:orig_category":"Non-Classified Establishments",
    "sg:phone":"+33 4 78 44 26 95",
    "sg:postcode":"69280",
    "sg:province":"Rhone-Alpes",
    "wof:name":"Lymac S.a.r.l.",
    "wof:placetype":"venue"
},
  "geometry": {"coordinates":[4.69055,45.776863],"type":"Point"}
}