{
  "type": "Feature",
  "properties": {
    "iso:country":"FR",
    "sg:address":"11 rue Marcel Luquet 32020 AUCH",
    "sg:classifiers":[
        {
            "category":"Professional",
            "subcategory":"Engineering",
            "type":"Services"
        }
    ],
    "sg:phone":"+33 5 62 60 63 63",
    "sg:province":"Midi Pyr\u00e9n\u00e9es",
    "sg:tags":[
        "plant",
        "industrial"
    ],
    "wof:name":"Critt Agro Alimentaire Ctcpa Ass.",
    "wof:placetype":"venue"
},
  "geometry": {"coordinates":[0.625761,43.660038],"type":"Point"}
}