{
  "type": "Feature",
  "properties": {
    "iso:country":"FR",
    "sg:address":"Pl. Occitane; Toulouse; 31000",
    "sg:classifiers":[
        {
            "category":"Banks & Credit Unions",
            "subcategory":"Bank",
            "type":"Services"
        }
    ],
    "sg:phone":"+33 3361212696",
    "sg:postcode":"31000",
    "sg:province":"Midi Pyr\u00e9n\u00e9es",
    "wof:name":"Sovac",
    "wof:placetype":"venue"
},
  "geometry": {"coordinates":[1.44945,43.602558],"type":"Point"}
}