{
  "type": "Feature",
  "properties": {
    "addr:full":"Zi Les Pierrelets 45380 Chaingy La Chapelle-Saint-Mesmin Centre 45380",
    "addr:housenumber":"chapelle-saint-mesmin",
    "addr:postcode":"45380;45380",
    "addr:street":"Zi Les Pierrelets",
    "iso:country":"FR",
    "sg:address":"Zi Les Pierrelets 45380 Chaingy",
    "sg:city":"La Chapelle-Saint-Mesmin",
    "sg:classifiers":[
        {
            "category":"Wholesale",
            "subcategory":"Machinery & Supplies",
            "type":"Manufacturing & Wholesale Goods"
        }
    ],
    "sg:phone":"+33 2 38 88 91 45",
    "sg:postcode":"45380",
    "sg:province":"Centre",
    "sg:tags":[
        "handling",
        "material",
        "-",
        "machine",
        "equipment",
        "engineering",
        "mechanical"
    ],
    "wof:name":"Claisse Bruno",
    "wof:placetype":"venue"
},
  "geometry": {"coordinates":[1.77233,47.88353],"type":"Point"}
}