{
  "type": "Feature",
  "properties": {
    "iso:country":"FR",
    "sg:address":"2 Rue Joseph Flouest BP 115 76203 Dieppe Cedex",
    "sg:classifiers":[
        {
            "category":"Manufacturing",
            "subcategory":"Building Materials",
            "type":"Manufacturing & Wholesale Goods"
        }
    ],
    "sg:phone":"+33 2 35 82 53 50",
    "sg:province":"Rhone-Alpes",
    "sg:tags":[
        "glass",
        "ceramic"
    ],
    "wof:name":"Delarue Sas",
    "wof:placetype":"venue"
},
  "geometry": {"coordinates":[1.075928,49.921211],"type":"Point"}
}