{
  "type": "Feature",
  "properties": {
    "addr:full":"2, Av. Carnot, 44000 Nantes Pays de Loire",
    "addr:postcode":"44000",
    "addr:street":"Av. Carnot",
    "iso:country":"FR",
    "sg:address":"2, Av. Carnot, 44000 Nantes",
    "sg:orig_category":"Unclassifiable Establishments",
    "sg:phone":"+33 2 40 41 24 00",
    "sg:province":"Pays de Loire",
    "wof:name":"Groupe Scet",
    "wof:placetype":"venue"
},
  "geometry": {"coordinates":[-1.545064,47.213898],"type":"Point"}
}