{
  "type": "Feature",
  "properties": {
    "addr:full":"3, Rue de la Fabrique, 67820 Wittisheim Wittisheim Alsace 67820",
    "addr:housenumber":"3",
    "addr:postcode":"67820;67820",
    "addr:street":"Rue De La Fabrique;Wittisheim",
    "iso:country":"FR",
    "sg:address":"3, Rue de la Fabrique, 67820 Wittisheim",
    "sg:city":"Wittisheim",
    "sg:orig_category":"Unclassifiable Establishments",
    "sg:phone":"+33 3 88 85 89 00",
    "sg:postcode":"67820",
    "sg:province":"Alsace",
    "wof:name":"Baumlin Nijhof S.a.r.l.",
    "wof:placetype":"venue"
},
  "geometry": {"coordinates":[7.583031,48.264069],"type":"Point"}
}