{
  "type": "Feature",
  "properties": {
    "addr:full":"Rue Four le Challenger; Rouen; 76000 Haute Normandie 76000",
    "addr:postcode":"76000;76000",
    "addr:street":"Rue Four Le;Normandie",
    "iso:country":"FR",
    "sg:address":"Rue Four",
    "sg:city":"le Challenger; Rouen; 76000",
    "sg:classifiers":[
        {
            "category":"Banks & Credit Unions",
            "subcategory":"Bank",
            "type":"Services"
        }
    ],
    "sg:phone":"+33 3335630843",
    "sg:postcode":"76000",
    "sg:province":"Haute Normandie",
    "wof:name":"Cr\u00e9dit Lyonnais",
    "wof:placetype":"venue"
},
  "geometry": {"coordinates":[1.082031,49.432522],"type":"Point"}
}