{
  "type": "Feature",
  "properties": {
    "iso:country":"FR",
    "sg:address":"2 rue de la R\u00e9pblique; S. Mande; 94160",
    "sg:classifiers":[
        {
            "category":"Banks & Credit Unions",
            "subcategory":"Bank",
            "type":"Services"
        }
    ],
    "sg:phone":"+33 3283675",
    "sg:postcode":"94160",
    "sg:province":"Ile de France",
    "wof:name":"Banque Nationale De Paris",
    "wof:placetype":"venue"
},
  "geometry": {"coordinates":[-122.42009,37.77916],"type":"Point"}
}