{
  "type": "Feature",
  "properties": {
    "addr:full":"2 rue de la R\u00e9pblique; S. Mande; 94160 Ile de France 94160",
    "addr:housenumber":"2",
    "addr:postcode":"94160;94160",
    "addr:street":"Rue De La Re\u0301Pblique S. Mande;France",
    "iso:country":"FR",
    "sg:address":"2 rue de la R\u00e9pblique; S. Mande; 94160",
    "sg:classifiers":[
        {
            "category":"Banks & Credit Unions",
            "subcategory":"Bank",
            "type":"Services"
        }
    ],
    "sg:phone":"+33 3283675",
    "sg:postcode":"94160",
    "sg:province":"Ile de France",
    "wof:name":"Banque Nationale De Paris",
    "wof:placetype":"venue"
},
  "geometry": {"coordinates":[-122.42009,37.77916],"type":"Point"}
}