{
  "type": "Feature",
  "properties": {
    "addr:full":"4 all\u00e9e Billonne 13170 Les Pennes Mirabeau Aquitaine",
    "addr:housenumber":"4",
    "addr:postcode":"13170",
    "addr:street":"Alle\u0301E Billonne",
    "iso:country":"FR",
    "sg:address":"4 all\u00e9e Billonne 13170 Les Pennes Mirabeau",
    "sg:classifiers":[
        {
            "category":"Organizations",
            "subcategory":"Non-profit Organization",
            "type":"Services"
        }
    ],
    "sg:phone":"+33 4 42 02 96 95",
    "sg:province":"Aquitaine",
    "sg:tags":[
        "industrial",
        "system",
        "hydraulic"
    ],
    "wof:name":"Ste Technique Indust Meridionale Sarl",
    "wof:placetype":"venue"
},
  "geometry": {"coordinates":[5.296353,43.417793],"type":"Point"}
}