{
  "type": "Feature",
  "properties": {
    "iso:country":"FR",
    "sg:address":"40 Rue Moulin Des Bruy\u00e8res 92400 Courbevoie",
    "sg:classifiers":[
        {
            "category":"Manufacturing",
            "subcategory":"Wood Products",
            "type":"Manufacturing & Wholesale Goods"
        }
    ],
    "sg:phone":"+33 1 41 16 39 38",
    "sg:province":"Ile de France",
    "sg:tags":[
        "professional",
        "furniture"
    ],
    "wof:name":"Standimage",
    "wof:placetype":"venue"
},
  "geometry": {"coordinates":[2.260823,48.904594],"type":"Point"}
}