{
  "type": "Feature",
  "properties": {
    "addr:full":"1 Place Saint Francois 74000 Annecy Rhone-Alpes 74000",
    "addr:housenumber":"1",
    "addr:postcode":"74000;74000",
    "addr:street":"Place Saint",
    "iso:country":"FR",
    "sg:address":"1 Place Saint Francois 74000 Annecy",
    "sg:classifiers":[
        {
            "category":"Travel",
            "subcategory":"Hotels & Motels",
            "type":"Entertainment"
        }
    ],
    "sg:phone":"+33 4 50 45 03 05",
    "sg:postcode":"74000",
    "sg:province":"Rhone-Alpes",
    "sg:tags":[
        "hotels",
        "business",
        "restaurant"
    ],
    "wof:name":"Meresto",
    "wof:placetype":"venue"
},
  "geometry": {"coordinates":[6.12789,45.898621],"type":"Point"}
}