{
  "type": "Feature",
  "properties": {
    "iso:country":"FR",
    "sg:address":"B.P. 58, 31123 Portet sur Garonne C\u00e9dex^^3, Av. de la Saudrune - Parc d'Activit\u00e9s du Bois Vert, 3112",
    "sg:orig_category":"Non-Classified Establishments",
    "sg:phone":"+33 5 61 72 06 08",
    "sg:province":"Midi-Pyr\u00e9n\u00e9es",
    "wof:name":"Sucres Et Services S.a.",
    "wof:placetype":"venue"
},
  "geometry": {"coordinates":[1.385182,43.532139],"type":"Point"}
}