{
  "type": "Feature",
  "properties": {
    "iso:country":"FR",
    "sg:address":"11, Impasse les Chasses Marees, 95610 Eragny",
    "sg:orig_category":"Non-Classified Establishments",
    "sg:phone":"+33 1 30 38 74 04",
    "sg:province":"Ile de France",
    "wof:name":"Techni Isol S.a.",
    "wof:placetype":"venue"
},
  "geometry": {"coordinates":[2.094865,49.013],"type":"Point"}
}