{
  "type": "Feature",
  "properties": {
    "addr:full":"ZA Ch\u00e2teaudun Centre 28200",
    "addr:postcode":"28200",
    "addr:street":"Za Cha\u0302Teaudun",
    "iso:country":"FR",
    "sg:address":"ZA",
    "sg:city":"Ch\u00e2teaudun",
    "sg:classifiers":[
        {
            "category":"Government",
            "subcategory":"Department Of Motor Vehicles",
            "type":"Public Place"
        }
    ],
    "sg:phone":"+33 2 37 44 70 70",
    "sg:postcode":"28200",
    "sg:province":"Centre",
    "sg:tags":[
        "equipment",
        "industrial",
        "transport",
        "motor-cars"
    ],
    "wof:name":"Paulstra",
    "wof:placetype":"venue"
},
  "geometry": {"coordinates":[1.332165,48.070324],"type":"Point"}
}