{
  "type": "Feature",
  "properties": {
    "addr:full":"Rue Grahuches 89100 Sens Sens Bourgogne 89100",
    "addr:postcode":"89100;89100",
    "addr:street":"Rue Grahuches",
    "iso:country":"FR",
    "sg:address":"Rue Grahuches 89100 Sens",
    "sg:city":"Sens",
    "sg:classifiers":[
        {
            "category":"Bakery",
            "type":"Food & Drink"
        }
    ],
    "sg:phone":"+33 3 86 83 14 30",
    "sg:postcode":"89100",
    "sg:province":"Bourgogne",
    "sg:tags":[
        "cake",
        "product",
        "related",
        "bread"
    ],
    "wof:name":"Societe De Viennoiserie Fine Sa",
    "wof:placetype":"venue"
},
  "geometry": {"coordinates":[3.319095,48.195019],"type":"Point"}
}