{
  "type": "Feature",
  "properties": {
    "addr:full":"12, Rue de Bellune, 79000 Niort Poitou-Charentes 79000",
    "addr:housenumber":"12",
    "addr:postcode":"79000;79000",
    "addr:street":"Rue De Bellune",
    "iso:country":"FR",
    "sg:address":"12, Rue de Bellune, 79000 Niort",
    "sg:orig_category":"Non-Classified Establishments",
    "sg:phone":"+33 5 49 24 03 95",
    "sg:postcode":"79000",
    "sg:province":"Poitou-Charentes",
    "wof:name":"Imprimerie Nouvelle Angevin S.a.",
    "wof:placetype":"venue"
},
  "geometry": {"coordinates":[-0.452763,46.323841],"type":"Point"}
}