{
  "type": "Feature",
  "properties": {
    "addr:full":"7, Rue Leuck Mathieu, 75020 Paris Ile de France",
    "addr:housenumber":"7",
    "addr:postcode":"75020",
    "addr:street":"Rue Leuck Mathieu",
    "iso:country":"FR",
    "sg:address":"7, Rue Leuck Mathieu, 75020 Paris",
    "sg:orig_category":"Non-Classified Establishments",
    "sg:phone":"+33 1 43 66 08 30",
    "sg:province":"Ile de France",
    "wof:name":"L'industrielle Textile S.a.",
    "wof:placetype":"venue"
},
  "geometry": {"coordinates":[2.402903,48.863422],"type":"Point"}
}