{
  "type": "Feature",
  "properties": {
    "iso:country":"FR",
    "sg:address":"30, Chauss\u00e9e Brunehaut, 80200 Estr\u00e9es Mons",
    "sg:orig_category":"Unclassifiable Establishments",
    "sg:phone":"+33 3 22 83 53 53",
    "sg:province":"Picardie",
    "wof:name":"B.p.l. L\u00e9gumes S.a.s.",
    "wof:placetype":"venue"
},
  "geometry": {"coordinates":[2.828895,49.875259],"type":"Point"}
}