{
  "type": "Feature",
  "properties": {
    "addr:full":"255 rue de Vaugirard; 75719 Paris, cedex 15, France \u00cele-de-France",
    "addr:housenumber":"255",
    "addr:postcode":"75719",
    "addr:street":"Rue De Vaugirard",
    "iso:country":"FR",
    "sg:address":"255 rue de Vaugirard; 75719 Paris, cedex 15, France",
    "sg:classifiers":[
        {
            "category":"Industrial Area",
            "type":"Public Place"
        }
    ],
    "sg:phone":"+33 1 40 43 30 30",
    "sg:province":"\u00cele-de-France",
    "sg:tags":[
        "large",
        "private"
    ],
    "wof:name":"F\u00e9d\u00e9ration Nationale De La Mutualit\u00e9 Fran\u00e7aise",
    "wof:placetype":"venue"
},
  "geometry": {"coordinates":[2.30382,48.840141],"type":"Point"}
}