{
  "type": "Feature",
  "properties": {
    "addr:full":"30960 Saint Florent sur Auzonnet Languedoc-Roussillon",
    "addr:housenumber":"30960",
    "addr:street":"Saint Florent Sur Auzonnet",
    "iso:country":"FR",
    "sg:address":"30960 Saint Florent sur Auzonnet",
    "sg:orig_category":"Non-Classified Establishments",
    "sg:phone":"+33 4 66 25 61 74",
    "sg:province":"Languedoc-Roussillon",
    "wof:name":"Germain S.a.s.",
    "wof:placetype":"venue"
},
  "geometry": {"coordinates":[4.114004,44.241436],"type":"Point"}
}