{
  "type": "Feature",
  "properties": {
    "addr:full":"23BIS Rue de la Roche 41201 ROMORANTIN LANTHENAY CEDEX Aquitaine",
    "addr:housenumber":"23bis",
    "addr:postcode":"41201",
    "addr:street":"Rue De La Roche",
    "iso:country":"FR",
    "sg:address":"23BIS Rue de la Roche 41201 ROMORANTIN LANTHENAY CEDEX",
    "sg:classifiers":[
        {
            "category":"Manufacturing",
            "subcategory":"Metals",
            "type":"Manufacturing & Wholesale Goods"
        }
    ],
    "sg:phone":"+33 2 54 76 56 29",
    "sg:province":"Aquitaine",
    "sg:tags":[
        "blanking",
        "dy"
    ],
    "wof:name":"M\u00e9canique De Sologne Sarl",
    "wof:placetype":"venue"
},
  "geometry": {"coordinates":[1.751017,47.352989],"type":"Point"}
}