{
  "type": "Feature",
  "properties": {
    "iso:country":"FR",
    "sg:address":"49 Rue D'Alsace 88440 Nomexy",
    "sg:classifiers":[
        {
            "category":"Shopping",
            "subcategory":"Crafts & Fabrics",
            "type":"Retail Goods"
        }
    ],
    "sg:phone":"+33 3 29 67 17 17",
    "sg:postcode":"88440",
    "sg:province":"Lorraine",
    "sg:tags":[
        "textile",
        "clothing"
    ],
    "wof:name":"Filatures De Chenimenil",
    "wof:placetype":"venue"
},
  "geometry": {"coordinates":[6.386559,48.305553],"type":"Point"}
}