{
  "type": "Feature",
  "properties": {
    "iso:country":"FR",
    "sg:address":"48 bis, Av. A. Belmontet, 92210 Saint Cloud",
    "sg:orig_category":"Unclassifiable Establishments",
    "sg:phone":"+33 1 47 71 20 98",
    "sg:province":"Ile de France",
    "wof:name":"Buyfacilities.com S.a.r.l.",
    "wof:placetype":"venue"
},
  "geometry": {"coordinates":[2.217386,48.857635],"type":"Point"}
}