{
  "type": "Feature",
  "properties": {
    "addr:full":"9 St. Jer\u00f4me; Aix en Provence; 13100 Nord Pas-de-Calais",
    "addr:housenumber":"9;13100",
    "addr:street":"St. Jero\u0302Me",
    "iso:country":"FR",
    "sg:address":"9",
    "sg:city":"St. Jer\u00f4me; Aix en Provence; 13100",
    "sg:classifiers":[
        {
            "category":"Banks & Credit Unions",
            "subcategory":"Bank",
            "type":"Services"
        }
    ],
    "sg:phone":"+33 3342267094",
    "sg:province":"Nord Pas-de-Calais",
    "wof:name":"Cr\u00e9dit Agricole",
    "wof:placetype":"venue"
},
  "geometry": {"coordinates":[5.451303,43.522556],"type":"Point"}
}