{
  "type": "Feature",
  "properties": {
    "iso:country":"FR",
    "sg:address":"39 avenue des Acacias 06500 Menton",
    "sg:orig_category":"Kits, Electronic",
    "sg:phone":"+33 4 92 41 75 75",
    "wof:name":"Comsystems International Sarl",
    "wof:placetype":"venue"
},
  "geometry": {"coordinates":[7.4847,43.783379],"type":"Point"}
}