{
  "type": "Feature",
  "properties": {
    "iso:country":"FR",
    "sg:address":"CD 919 - ZA du Val de Moder",
    "sg:city":"Niedermodern",
    "sg:orig_category":"Non-Classified Establishments",
    "sg:phone":"+33 3 88 72 59 10",
    "sg:postcode":"67350",
    "sg:province":"Alsace",
    "wof:name":"E.c.r. Rebstock S.a.r.l.",
    "wof:placetype":"venue"
},
  "geometry": {"coordinates":[7.60881,48.844219],"type":"Point"}
}