{
  "type": "Feature",
  "properties": {
    "iso:country":"FR",
    "sg:address":"32, Bd de la R\u00e9publique, 92100 Boulogne Billancourt",
    "sg:orig_category":"Non-Classified Establishments",
    "sg:phone":"+33 1 46 20 04 58",
    "sg:postcode":"92100",
    "sg:province":"Ile de France",
    "wof:name":"Bizot P\u00e8re Et Fils S.a.r.l.",
    "wof:placetype":"venue"
},
  "geometry": {"coordinates":[2.252849,48.832222],"type":"Point"}
}