{
  "type": "Feature",
  "properties": {
    "addr:full":"6 Av Des Fr\u00e8res Lumi\u00e8re 69730 Genay Rhone-Alpes 69730",
    "addr:postcode":"69730;69730",
    "addr:street":"Av Des Fre\u0300Res Lumie\u0300Re",
    "iso:country":"FR",
    "sg:address":"6 Av Des Fr\u00e8res Lumi\u00e8re 69730 Genay",
    "sg:classifiers":[
        {
            "category":"Shopping",
            "subcategory":"Crafts & Fabrics",
            "type":"Retail Goods"
        }
    ],
    "sg:phone":"+33 4 72 08 10 00",
    "sg:postcode":"69730",
    "sg:province":"Rhone-Alpes",
    "sg:tags":[
        "textile",
        "clothing"
    ],
    "wof:name":"Komar Et Cie Sa",
    "wof:placetype":"venue"
},
  "geometry": {"coordinates":[4.82411,45.890202],"type":"Point"}
}