{
  "type": "Feature",
  "properties": {
    "addr:full":"B.P. 6, 80210 Feuqui\u00e8res en Vimeu^^ZI, 80210 Feuqui\u00e8res en Vimeu Picardie 80210",
    "addr:housenumber":"6",
    "addr:postcode":"80210;80210;80210",
    "addr:street":"B.P.",
    "iso:country":"FR",
    "sg:address":"B.P. 6, 80210 Feuqui\u00e8res en Vimeu^^ZI, 80210 Feuqui\u00e8res en Vimeu",
    "sg:orig_category":"Non-Classified Establishments",
    "sg:phone":"+33 3 22 30 30 75",
    "sg:postcode":"80210",
    "sg:province":"Picardie",
    "wof:name":"Etablissements Couillet P\u00e8re Et Fils S.a.r.l.",
    "wof:placetype":"venue"
},
  "geometry": {"coordinates":[1.604313,50.06144],"type":"Point"}
}