{
  "type": "Feature",
  "properties": {
    "iso:country":"FR",
    "sg:address":"ZI la Moune",
    "sg:city":"La Planche",
    "sg:orig_category":"Unclassifiable Establishments",
    "sg:phone":"+33 2 40 31 99 77",
    "sg:postcode":"44140",
    "sg:province":"Pays de Loire",
    "wof:name":"Caliplast S.a.s.",
    "wof:placetype":"venue"
},
  "geometry": {"coordinates":[-1.440544,47.019257],"type":"Point"}
}