{
  "type": "Feature",
  "properties": {
    "iso:country":"FR",
    "sg:address":"7 bis, Rte du P\u00e9rollier, 69570 Dardilly",
    "sg:orig_category":"Unclassifiable Establishments",
    "sg:phone":"+33 4 78 47 45 00",
    "sg:postcode":"69570",
    "sg:province":"Rhone-Alpes",
    "wof:name":"Logitrans Manutention France E.u.r.l.",
    "wof:placetype":"venue"
},
  "geometry": {"coordinates":[4.766519,45.802261],"type":"Point"}
}