{
  "type": "Feature",
  "properties": {
    "iso:country":"FR",
    "sg:address":"37-39 Rue Gustave Eiffel 77220 Gretz Armainvilliers",
    "sg:classifiers":[
        {
            "category":"Professional",
            "subcategory":"Advertising",
            "type":"Services"
        }
    ],
    "sg:phone":"+33 1 64 42 53 50",
    "sg:postcode":"77220",
    "sg:province":"Ile de France",
    "sg:tags":[
        "communication",
        "medium"
    ],
    "wof:name":"Sofrap Sa",
    "wof:placetype":"venue"
},
  "geometry": {"coordinates":[2.76256,48.739803],"type":"Point"}
}