{
  "type": "Feature",
  "properties": {
    "iso:country":"FR",
    "sg:address":"40, Rue des Cosmonautes, 91120 Palaiseau",
    "sg:orig_category":"Non-Classified Establishments",
    "sg:phone":"+33 1 69 20 55 50",
    "sg:province":"Ile de France",
    "wof:name":"G.s.f. Atlas S.a.",
    "wof:placetype":"venue"
},
  "geometry": {"coordinates":[2.260581,48.717163],"type":"Point"}
}