{
  "type": "Feature",
  "properties": {
    "addr:full":"7, Rue du Chemin Vert - ZA, 59710 Avelin Nord Pas-de-Calais 59710",
    "addr:housenumber":"7",
    "addr:postcode":"59710;59710",
    "addr:street":"Rue Du Chemin Vert Za",
    "iso:country":"FR",
    "sg:address":"7, Rue du Chemin Vert - ZA, 59710 Avelin",
    "sg:orig_category":"Distributeur: Mat\u00e9riels \u00e9lectriques BT/MT, tertiaire industrie, EP et r\u00e9seaux MAT\u00c9RIELS EX ANTI-D\u00c9FL",
    "sg:phone":"+33 3 20 32 94 94",
    "sg:postcode":"59710",
    "sg:province":"Nord Pas-de-Calais",
    "wof:name":"Hoffman Et Boulanger S.a.",
    "wof:placetype":"venue"
},
  "geometry": {"coordinates":[3.080295,50.53793],"type":"Point"}
}