{
  "type": "Feature",
  "properties": {
    "addr:full":"181 Rue Des Ch\u00eanes 77590 Chartrettes Ile de France 77590",
    "addr:housenumber":"181",
    "addr:postcode":"77590;77590",
    "addr:street":"Rue Des Che\u0302Nes;Ile De France",
    "iso:country":"FR",
    "sg:address":"181 Rue Des Ch\u00eanes 77590 Chartrettes",
    "sg:classifiers":[
        {
            "category":"Manufacturing",
            "subcategory":"Metals",
            "type":"Manufacturing & Wholesale Goods"
        }
    ],
    "sg:phone":"+33 1 60 69 10 69",
    "sg:postcode":"77590",
    "sg:province":"Ile de France",
    "sg:tags":[
        "metallurgy",
        "metalworking",
        "processing"
    ],
    "wof:name":"Brassas Sa",
    "wof:placetype":"venue"
},
  "geometry": {"coordinates":[2.68283,48.492588],"type":"Point"}
}