{
  "type": "Feature",
  "properties": {
    "addr:full":"53, Av. du Champ de Mars, 73200 Albertville Rhone-Alpes",
    "addr:postcode":"73200",
    "addr:street":"53 Av. Du Champ De Mars",
    "iso:country":"FR",
    "sg:address":"53, Av. du Champ de Mars, 73200 Albertville",
    "sg:orig_category":"Unclassifiable Establishments",
    "sg:phone":"+33 4 79 31 18 00",
    "sg:province":"Rhone-Alpes",
    "wof:name":"G\u00e9cors S.a.",
    "wof:placetype":"venue"
},
  "geometry": {"coordinates":[6.384294,45.662399],"type":"Point"}
}