{
  "type": "Feature",
  "properties": {
    "iso:country":"FR",
    "sg:address":"78, Rue JB Colbert - ZI Ouest, 10600 La Chapelle Saint Luc",
    "sg:orig_category":"Non-Classified Establishments",
    "sg:phone":"+33 3 25 79 82 00",
    "sg:province":"Champagne",
    "wof:name":"Loxam S.a.",
    "wof:placetype":"venue"
},
  "geometry": {"coordinates":[4.04779,48.311729],"type":"Point"}
}