{
  "type": "Feature",
  "properties": {
    "addr:full":"Rte de Rivas - La Grange Chamboeuf Rhone-Alpes 42330",
    "addr:postcode":"42330",
    "addr:street":"Rte De Rivas La;Rhone-Alpes",
    "iso:country":"FR",
    "sg:address":"Rte de Rivas - La Grange",
    "sg:city":"Chamboeuf",
    "sg:orig_category":"Unclassifiable Establishments",
    "sg:phone":"+33 4 77 36 34 83",
    "sg:postcode":"42330",
    "sg:province":"Rhone-Alpes",
    "wof:name":"G.o.p. S.a. - Gestion Organisation Production",
    "wof:placetype":"venue"
},
  "geometry": {"coordinates":[4.32775,45.54314],"type":"Point"}
}