{
  "type": "Feature",
  "properties": {
    "iso:country":"FR",
    "sg:address":"33 Rue Des Grandes Arcades 67000 Strasbourg",
    "sg:city":"Strasbourg",
    "sg:classifiers":[
        {
            "category":"Travel",
            "subcategory":"Hotels & Motels",
            "type":"Entertainment"
        }
    ],
    "sg:phone":"+33 3 88 32 36 56",
    "sg:postcode":"67000",
    "sg:province":"Alsace",
    "sg:tags":[
        "hotels",
        "business",
        "restaurant"
    ],
    "wof:name":"Madison Sa",
    "wof:placetype":"venue"
},
  "geometry": {"coordinates":[7.746973,48.583065],"type":"Point"}
}