{
  "type": "Feature",
  "properties": {
    "addr:full":"33 Rue Des Grandes Arcades 67000 Strasbourg Strasbourg Alsace 67000",
    "addr:housenumber":"33",
    "addr:postcode":"67000;67000",
    "addr:street":"Rue Des Grandes Arcades",
    "iso:country":"FR",
    "sg:address":"33 Rue Des Grandes Arcades 67000 Strasbourg",
    "sg:city":"Strasbourg",
    "sg:classifiers":[
        {
            "category":"Travel",
            "subcategory":"Hotels & Motels",
            "type":"Entertainment"
        }
    ],
    "sg:phone":"+33 3 88 32 36 56",
    "sg:postcode":"67000",
    "sg:province":"Alsace",
    "sg:tags":[
        "hotels",
        "business",
        "restaurant"
    ],
    "wof:name":"Madison Sa",
    "wof:placetype":"venue"
},
  "geometry": {"coordinates":[7.746973,48.583065],"type":"Point"}
}