{
  "type": "Feature",
  "properties": {
    "addr:full":"11 Rue D'Hellieule St Die Lorraine 88100",
    "addr:housenumber":"11",
    "addr:postcode":"88100",
    "addr:street":"Rue D'Hellieule St;Lorraine",
    "iso:country":"FR",
    "sg:address":"11 Rue D'Hellieule",
    "sg:city":"St Die",
    "sg:classifiers":[
        {
            "category":"Banks & Credit Unions",
            "subcategory":"Financial Services",
            "type":"Services"
        }
    ],
    "sg:phone":"+33 3 29 55 29 10",
    "sg:postcode":"88100",
    "sg:province":"Lorraine",
    "sg:tags":[
        "banking",
        "finance",
        "insurance"
    ],
    "wof:name":"Caisse Regionale De Credit Agricole Des Vosges (crcam Des Vosges)",
    "wof:placetype":"venue"
},
  "geometry": {"coordinates":[6.942892,48.285076],"type":"Point"}
}