{
  "type": "Feature",
  "properties": {
    "addr:full":"02290 Vassens Picardie",
    "addr:postcode":"02290",
    "iso:country":"FR",
    "sg:address":"02290 Vassens",
    "sg:orig_category":"Unclassifiable Establishments",
    "sg:phone":"+33 3 23 39 61 57",
    "sg:province":"Picardie",
    "wof:name":"Carri\u00e8re De Vassens S.a.r.l.",
    "wof:placetype":"venue"
},
  "geometry": {"coordinates":[3.15515,49.467484],"type":"Point"}
}