{
  "type": "Feature",
  "properties": {
    "addr:full":"881, Rue de la Division Leclerc, 88800 Vittel Lorraine",
    "addr:housenumber":"881",
    "addr:postcode":"88800",
    "addr:street":"Rue De La Division Leclerc",
    "iso:country":"FR",
    "sg:address":"881, Rue de la Division Leclerc, 88800 Vittel",
    "sg:orig_category":"Unclassifiable Establishments",
    "sg:phone":"+33 3 29 05 80 30",
    "sg:province":"Lorraine",
    "wof:name":"S.d.v.m. Del Vitto Masini S.n.c.",
    "wof:placetype":"venue"
},
  "geometry": {"coordinates":[5.951605,48.198921],"type":"Point"}
}