{
  "type": "Feature",
  "properties": {
    "addr:full":"La For\u00eat 38790 ST GEORGES D ESPERANCHE Rhone-Alpes",
    "addr:postcode":"38790",
    "addr:street":"La Fore\u0302T",
    "iso:country":"FR",
    "sg:address":"La For\u00eat 38790 ST GEORGES D ESPERANCHE",
    "sg:orig_category":"Rose Cultivations",
    "sg:phone":"+33 4 74 59 02 10",
    "sg:province":"Rhone-Alpes",
    "wof:name":"Roseries Reuter Fr\u00e8res Gaec",
    "wof:placetype":"venue"
},
  "geometry": {"coordinates":[5.11672,45.567638],"type":"Point"}
}