{
  "type": "Feature",
  "properties": {
    "addr:full":"89, Rue Gabriel P\u00e9ri, 78500 Sartrouville Ile de France",
    "addr:housenumber":"89",
    "addr:postcode":"78500;ile",
    "addr:street":"Rue Gabriel Pe\u0301Ri",
    "iso:country":"FR",
    "sg:address":"89, Rue Gabriel P\u00e9ri, 78500 Sartrouville",
    "sg:orig_category":"Non-Classified Establishments",
    "sg:phone":"+33 1 39 13 90 90",
    "sg:province":"Ile de France",
    "wof:name":"S.n.e.p. S.a.r.l. - Soci\u00e9t\u00e9 Nouvelle Entretien Peinture",
    "wof:placetype":"venue"
},
  "geometry": {"coordinates":[2.179254,48.939171],"type":"Point"}
}