{
  "type": "Feature",
  "properties": {
    "addr:full":"B.P. 56, 44550 Montoir de Bretagne C\u00e9dex^^Zone des Rochettes, 44550 Montoir de Bretagne Pays de Loire",
    "addr:postcode":"44550;44550",
    "addr:street":"B.P. 56",
    "iso:country":"FR",
    "sg:address":"B.P. 56, 44550 Montoir de Bretagne C\u00e9dex^^Zone des Rochettes, 44550 Montoir de Bretagne",
    "sg:orig_category":"Non-Classified Establishments",
    "sg:phone":"+33 2 40 00 23 23",
    "sg:province":"Pays de Loire",
    "wof:name":"Miroiteries De L'ouest Atlantique S.a.s.",
    "wof:placetype":"venue"
},
  "geometry": {"coordinates":[-2.177519,47.308414],"type":"Point"}
}