{
  "type": "Feature",
  "properties": {
    "addr:full":"7, rue Belin, 25000 Besan\u00e7on Franche Comt\u00e9",
    "addr:housenumber":"7",
    "addr:postcode":"25000",
    "addr:street":"Rue Belin;Franche Comte\u0301",
    "iso:country":"FR",
    "sg:address":"7, rue Belin, 25000 Besan\u00e7on",
    "sg:orig_category":"Non-Classified Establishments",
    "sg:phone":"+33 3 81 51 63 63",
    "sg:province":"Franche Comt\u00e9",
    "wof:name":"Transport Vuillemenot S.a.r.l.",
    "wof:placetype":"venue"
},
  "geometry": {"coordinates":[5.970055,47.226376],"type":"Point"}
}