{
  "type": "Feature",
  "properties": {
    "addr:full":"ZI Nord Altkirch Alsace 68130",
    "addr:postcode":"68130",
    "addr:street":"Zi Nord Altkirch",
    "iso:country":"FR",
    "sg:address":"ZI Nord",
    "sg:city":"Altkirch",
    "sg:orig_category":"Unclassifiable Establishments",
    "sg:phone":"+33 3 89 08 93 80",
    "sg:postcode":"68130",
    "sg:province":"Alsace",
    "wof:name":"D.h.s. Equipements S.a.r.l.",
    "wof:placetype":"venue"
},
  "geometry": {"coordinates":[7.24009,47.625919],"type":"Point"}
}