{
  "type": "Feature",
  "properties": {
    "addr:full":"25210 Bonn\u00e9tage Franche Comt\u00e9 25210",
    "addr:postcode":"25210;25210",
    "addr:street":"Franche Comte\u0301",
    "iso:country":"FR",
    "sg:address":"25210 Bonn\u00e9tage",
    "sg:orig_category":"Gravure Gravure au diamant Gravure au laser Gravure chimique Gravure m\u00e9canique Gravure \u00e0 l'acide Imp",
    "sg:phone":"+33 3 81 68 90 14",
    "sg:postcode":"25210",
    "sg:province":"Franche Comt\u00e9",
    "wof:name":"Berma S.a.",
    "wof:placetype":"venue"
},
  "geometry": {"coordinates":[6.70733,47.198849],"type":"Point"}
}