{
  "type": "Feature",
  "properties": {
    "addr:full":"3, Rue Andr\u00e9 Malraux, 54630 Richardm\u00e9nil Lorraine 54630",
    "addr:housenumber":"3",
    "addr:postcode":"54630;54630",
    "addr:street":"Rue Andre\u0301 Malraux",
    "iso:country":"FR",
    "sg:address":"3, Rue Andr\u00e9 Malraux, 54630 Richardm\u00e9nil",
    "sg:orig_category":"Non-Classified Establishments",
    "sg:phone":"+33 3 83 25 79 27",
    "sg:postcode":"54630",
    "sg:province":"Lorraine",
    "wof:name":"A.m.d. Communication S.a.r.l.",
    "wof:placetype":"venue"
},
  "geometry": {"coordinates":[6.165526,48.594582],"type":"Point"}
}