{
  "type": "Feature",
  "properties": {
    "addr:full":"146, Bd Voltaire, 78230 Le Pecq Ile de France",
    "addr:housenumber":"146",
    "addr:postcode":"78230",
    "addr:street":"Bd Voltaire",
    "iso:country":"FR",
    "sg:address":"146, Bd Voltaire, 78230 Le Pecq",
    "sg:orig_category":"Non-Classified Establishments",
    "sg:phone":"+33 1 41 11 79 00",
    "sg:province":"Ile de France",
    "wof:name":"L.3.s. Produits S.a.",
    "wof:placetype":"venue"
},
  "geometry": {"coordinates":[2.10782,48.9062],"type":"Point"}
}