{
  "type": "Feature",
  "properties": {
    "addr:full":"B.P. 8, 51500 Sillery^^7, Rue Jean Monnet - ZA, 51500 Sillery Champagne 51500",
    "addr:housenumber":"8",
    "addr:postcode":"51500;51500;51500",
    "addr:street":"B.P.;Rue Jean Monnet Za",
    "iso:country":"FR",
    "sg:address":"B.P. 8, 51500 Sillery^^7, Rue Jean Monnet - ZA, 51500 Sillery",
    "sg:orig_category":"Chariots de manutention Chariots \u00e9l\u00e9vateurs \u00e0 fourche Chariots \u00e9l\u00e9vateurs \u00e0 fourche d'occasion Locat",
    "sg:phone":"+33 6 73 69 39 15",
    "sg:postcode":"51500",
    "sg:province":"Champagne",
    "wof:name":"Gallor\u00e9ma S.a.r.l.",
    "wof:placetype":"venue"
},
  "geometry": {"coordinates":[4.148544,49.191273],"type":"Point"}
}