{
  "type": "Feature",
  "properties": {
    "iso:country":"FR",
    "sg:address":"1 Rue Camille Desmoulins Tsa 20005 92787 Issy Les Moulineaux Cedex 9",
    "sg:city":"Esmoulins",
    "sg:classifiers":[
        {
            "category":"Health Services",
            "subcategory":"Medical Lab",
            "type":"Services"
        }
    ],
    "sg:phone":"+33 1 55 00 35 00",
    "sg:postcode":"70100",
    "sg:province":"Franche Comt\u00e9",
    "sg:tags":[
        "chemical",
        "pharmaceutical",
        "pharmacy"
    ],
    "wof:name":"Laboratoires Martin - Johnson Et Johnson",
    "wof:placetype":"venue"
},
  "geometry": {"coordinates":[2.27332,48.823071],"type":"Point"}
}