{
  "type": "Feature",
  "properties": {
    "addr:full":"28/29, Rue du Bois d'Orly, 57685 Augny Lorraine",
    "addr:housenumber":"28 / 29",
    "addr:postcode":"57685",
    "addr:street":"Rue Du Bois D'Orly",
    "iso:country":"FR",
    "sg:address":"28/29, Rue du Bois d'Orly, 57685 Augny",
    "sg:orig_category":"Non-Classified Establishments",
    "sg:phone":"+33 3 87 38 48 47",
    "sg:province":"Lorraine",
    "wof:name":"Axima R\u00e9frig\u00e9ration France S.a.",
    "wof:placetype":"venue"
},
  "geometry": {"coordinates":[6.10956,49.053631],"type":"Point"}
}