{
  "type": "Feature",
  "properties": {
    "iso:country":"FR",
    "sg:address":"8, Rue Antoine Becquerel, 21300 Chen\u00f4ve",
    "sg:city":"Chen\u00f4ve",
    "sg:orig_category":"Non-Classified Establishments",
    "sg:phone":"+33 3 80 52 20 44",
    "sg:postcode":"21300",
    "sg:province":"Bourgogne",
    "wof:name":"21 Express S.a.",
    "wof:placetype":"venue"
},
  "geometry": {"coordinates":[5.022588,47.28738],"type":"Point"}
}