{
  "type": "Feature",
  "properties": {
    "addr:full":"7, Rue des Osiers - ZI des Marais, 78310 Coigni\u00e8res Ile de France",
    "addr:housenumber":"7",
    "addr:postcode":"78310;ile",
    "addr:street":"Rue Des Osiers Zi Des Marais",
    "iso:country":"FR",
    "sg:address":"7, Rue des Osiers - ZI des Marais, 78310 Coigni\u00e8res",
    "sg:orig_category":"Non-Classified Establishments",
    "sg:phone":"+33 1 30 49 43 60",
    "sg:province":"Ile de France",
    "wof:name":"Merlo France S.a.r.l.",
    "wof:placetype":"venue"
},
  "geometry": {"coordinates":[1.944855,48.761749],"type":"Point"}
}