{
  "type": "Feature",
  "properties": {
    "addr:full":"15 Rue De Vaugirard 75006 Paris Ile de France 75006",
    "addr:housenumber":"15",
    "addr:postcode":"75006;75006",
    "addr:street":"Rue De Vaugirard",
    "iso:country":"FR",
    "sg:address":"15 Rue De Vaugirard 75006 Paris",
    "sg:classifiers":[
        {
            "category":"Professional",
            "subcategory":"Business Services",
            "type":"Services"
        }
    ],
    "sg:phone":"+33 1 42 34 20 00",
    "sg:postcode":"75006",
    "sg:province":"Ile de France",
    "sg:tags":[
        "body",
        "advice"
    ],
    "wof:name":"Ass Gestion Assistants De Senateurs",
    "wof:placetype":"venue"
},
  "geometry": {"coordinates":[2.337559,48.849152],"type":"Point"}
}