{
  "type": "Feature",
  "properties": {
    "addr:full":"Dorrondeguy Zone Artisanale 64700 Hendaye Hendaye Aquitaine 64700",
    "addr:postcode":"64700;64700",
    "addr:street":"Zone Artisanale",
    "iso:country":"FR",
    "sg:address":"Dorrondeguy Zone Artisanale 64700 Hendaye",
    "sg:city":"Hendaye",
    "sg:classifiers":[
        {
            "category":"Banks & Credit Unions",
            "subcategory":"Financial Services",
            "type":"Services"
        }
    ],
    "sg:phone":"+33 5 59 48 30 22",
    "sg:postcode":"64700",
    "sg:province":"Aquitaine",
    "sg:tags":[
        "banking",
        "finance",
        "insurance"
    ],
    "wof:name":"Bruno Scherer Entreprise",
    "wof:placetype":"venue"
},
  "geometry": {"coordinates":[-1.776094,43.358524],"type":"Point"}
}