{
  "type": "Feature",
  "properties": {
    "addr:full":"B.P. 34, 67038 Strasbourg C\u00e9dex 2^^3, Rue Ettore Bugatti - Parc d'Activit\u00e9 d'Eckbolsheim, 67200 Eckb Strasbourg Alsace 67200",
    "addr:housenumber":"2 ^ ^ 3",
    "addr:postcode":"67038;67200;67200",
    "addr:street":"B.P. 34;Ce\u0301Dex;Rue Ettore Bugatti Parc D'Activite \u0301 D'Eckbolsheim",
    "iso:country":"FR",
    "sg:address":"B.P. 34, 67038 Strasbourg C\u00e9dex 2^^3, Rue Ettore Bugatti - Parc d'Activit\u00e9 d'Eckbolsheim, 67200 Eckb",
    "sg:city":"Strasbourg",
    "sg:orig_category":"Non-Classified Establishments",
    "sg:phone":"+33 3 88 76 90 90",
    "sg:postcode":"67200",
    "sg:province":"Alsace",
    "wof:name":"Almet S.a.",
    "wof:placetype":"venue"
},
  "geometry": {"coordinates":[7.78995,48.604046],"type":"Point"}
}