{
  "type": "Feature",
  "properties": {
    "addr:full":"Rue Tuilerie - Saint Beno\u00eet Auffargis Ile de France 78610",
    "addr:postcode":"78610",
    "addr:street":"Rue Tuilerie",
    "iso:country":"FR",
    "sg:address":"Rue Tuilerie - Saint Beno\u00eet",
    "sg:city":"Auffargis",
    "sg:orig_category":"Unclassifiable Establishments",
    "sg:phone":"+33 1 30 59 88 00",
    "sg:postcode":"78610",
    "sg:province":"Ile de France",
    "wof:name":"Prosoft Ing\u00e9nierie Sa",
    "wof:placetype":"venue"
},
  "geometry": {"coordinates":[1.886312,48.690052],"type":"Point"}
}