{
  "type": "Feature",
  "properties": {
    "iso:country":"FR",
    "sg:address":"March\u00e9 D'Int\u00e9r\u00eat National BP 1009 84300 Cavaillon",
    "sg:classifiers":[
        {
            "category":"Farming",
            "subcategory":"Crops",
            "type":"Manufacturing & Wholesale Goods"
        }
    ],
    "sg:phone":"+33 4 90 06 63 63",
    "sg:province":"Languedoc-Roussillon",
    "sg:tags":[
        "vegetable",
        "fruit",
        "agriculture",
        "livestock"
    ],
    "wof:name":"Pom Azur Sica",
    "wof:placetype":"venue"
},
  "geometry": {"coordinates":[5.04855,43.84869],"type":"Point"}
}