{
  "type": "Feature",
  "properties": {
    "iso:country":"FR",
    "sg:address":"17, Place Magellan - Le Ponant 2 Zone Atlantis, 44812 Saint Herblain C\u00e9dex",
    "sg:orig_category":"Non-Classified Establishments",
    "sg:phone":"+33 2 40 92 19 36",
    "sg:province":"Languedoc-Roussillon",
    "wof:name":"E.e.g. Simecsol S.a.",
    "wof:placetype":"venue"
},
  "geometry": {"coordinates":[-1.63888,47.21442],"type":"Point"}
}