{
  "type": "Feature",
  "properties": {
    "iso:country":"FR",
    "sg:address":"373, Rue de la Garenne, 92000 Nanterre",
    "sg:orig_category":"Non-Classified Establishments",
    "sg:phone":"+33 1 47 81 24 61",
    "sg:province":"Ile de France",
    "wof:name":"M\u00e9taufer S.a.r.l.",
    "wof:placetype":"venue"
},
  "geometry": {"coordinates":[2.231305,48.900719],"type":"Point"}
}