{
  "type": "Feature",
  "properties": {
    "iso:country":"FR",
    "sg:address":"17, Rue Croix, 80540 Seux",
    "sg:orig_category":"Non-Classified Establishments",
    "sg:phone":"+33 3 22 38 15 49",
    "sg:province":"Picardie",
    "wof:name":"Limatec S.a.",
    "wof:placetype":"venue"
},
  "geometry": {"coordinates":[2.104852,49.874836],"type":"Point"}
}