{
  "type": "Feature",
  "properties": {
    "iso:country":"FR",
    "sg:address":"B.P. 2, 36240 Ecueille C\u00e9dex^^Rue Jacques Morin, 36240 Ecueille",
    "sg:city":"\u00c9cueill\u00e9",
    "sg:orig_category":"Non-Classified Establishments",
    "sg:phone":"+33 2 54 40 22 61",
    "sg:postcode":"36240",
    "sg:province":"Centre",
    "wof:name":"Soci\u00e9t\u00e9 Anita Pr\u00eat \u00e0 Porter De Luxe S.a.r.l.",
    "wof:placetype":"venue"
},
  "geometry": {"coordinates":[1.293085,47.021324],"type":"Point"}
}