{
  "type": "Feature",
  "properties": {
    "iso:country":"FR",
    "sg:address":"7",
    "sg:city":"Portefoin 75003 PARIS",
    "sg:orig_category":"Chemicals and Pharmaceuticals Cosmetics Gifts Leather and Shoes Leather goods Miscellaneous Products",
    "sg:phone":"+33 1 42 72 35 19",
    "sg:postcode":"75003",
    "sg:province":"Ile de France",
    "wof:name":"Artimport (sa)",
    "wof:placetype":"venue"
},
  "geometry": {"coordinates":[2.35996,48.863461],"type":"Point"}
}