{
  "type": "Feature",
  "properties": {
    "iso:country":"FR",
    "sg:address":"B.P. 42, 38360 Sassenage^^9, Rue du Moucherotte, 38360 Sassenage",
    "sg:orig_category":"Non-Classified Establishments",
    "sg:phone":"+33 4 76 27 42 90",
    "sg:province":"Rhone-Alpes",
    "wof:name":"Satel S.a.",
    "wof:placetype":"venue"
},
  "geometry": {"coordinates":[5.662875,45.206551],"type":"Point"}
}