{
  "type": "Feature",
  "properties": {
    "addr:full":"Zi De La Peupleraie Boulevard Ferdinand De Lesseps 62110 Henin Beaumont Nord Pas-de-Calais",
    "addr:postcode":"62110",
    "addr:street":"Zi De La Peupleraie Boulevard Ferdinand De Lesseps",
    "iso:country":"FR",
    "sg:address":"Zi De La Peupleraie Boulevard Ferdinand De Lesseps 62110 Henin Beaumont",
    "sg:classifiers":[
        {
            "category":"Banks & Credit Unions",
            "subcategory":"Investment Brokerage",
            "type":"Services"
        }
    ],
    "sg:phone":"+33 3 21 79 15 79",
    "sg:province":"Nord Pas-de-Calais",
    "sg:tags":[
        "-",
        "transport",
        "related"
    ],
    "wof:name":"Snc Boulanger",
    "wof:placetype":"venue"
},
  "geometry": {"coordinates":[2.947094,50.41885],"type":"Point"}
}