{
  "type": "Feature",
  "properties": {
    "addr:full":"Av. de Bellande - ZI Aubenas Rhone-Alpes 07200",
    "addr:postcode":"07200",
    "addr:street":"Av. De Bellande Zi;Rhone-Alpes",
    "iso:country":"FR",
    "sg:address":"Av. de Bellande - ZI",
    "sg:city":"Aubenas",
    "sg:orig_category":"Unclassifiable Establishments",
    "sg:phone":"+33 4 75 35 41 11",
    "sg:postcode":"07200",
    "sg:province":"Rhone-Alpes",
    "wof:name":"Etablissements Louis Mazet S.a.",
    "wof:placetype":"venue"
},
  "geometry": {"coordinates":[4.39417,44.613239],"type":"Point"}
}