{
  "type": "Feature",
  "properties": {
    "addr:full":"450 Route De Rosporden 29000 Quimper Quimper Bretagne 29000",
    "addr:housenumber":"450",
    "addr:postcode":"29000;29000",
    "addr:street":"Route De Rosporden",
    "iso:country":"FR",
    "sg:address":"450 Route De Rosporden 29000 Quimper",
    "sg:city":"Quimper",
    "sg:classifiers":[
        {
            "category":"Food & Beverages",
            "subcategory":"Fruits & Vegetables",
            "type":"Retail Goods"
        }
    ],
    "sg:phone":"+33 2 98 52 82 82",
    "sg:postcode":"29000",
    "sg:province":"Bretagne",
    "sg:tags":[
        "frozen",
        "product",
        "related"
    ],
    "wof:name":"Doux Pere Dodu Sas",
    "wof:placetype":"venue"
},
  "geometry": {"coordinates":[-4.020291,47.980782],"type":"Point"}
}