{
  "type": "Feature",
  "properties": {
    "addr:full":"ZI la Californie Fontanil Cornillon Rhone-Alpes 38120",
    "addr:postcode":"38120",
    "addr:street":"Zi La;Rhone-Alpes",
    "iso:country":"FR",
    "sg:address":"ZI la Californie",
    "sg:city":"Fontanil Cornillon",
    "sg:orig_category":"Unclassifiable Establishments",
    "sg:phone":"+33 4 76 58 20 00",
    "sg:postcode":"38120",
    "sg:province":"Rhone-Alpes",
    "wof:name":"Bourgey Montreuil Dauphin\u00e9 S.a.s.",
    "wof:placetype":"venue"
},
  "geometry": {"coordinates":[5.66544,45.256554],"type":"Point"}
}