{
  "type": "Feature",
  "properties": {
    "addr:full":"Zi Kergoustard BP 92 56303 Pontivy Cedex Midi Pyr\u00e9n\u00e9es",
    "addr:housenumber":"bp 92",
    "addr:postcode":"56303",
    "iso:country":"FR",
    "sg:address":"Zi Kergoustard BP 92 56303 Pontivy Cedex",
    "sg:classifiers":[
        {
            "category":"Building & Trades",
            "subcategory":"Construction",
            "type":"Services"
        }
    ],
    "sg:phone":"+33 2 97 25 11 92",
    "sg:province":"Midi Pyr\u00e9n\u00e9es",
    "sg:tags":[
        "work",
        "public"
    ],
    "wof:name":"Appia Bretagne",
    "wof:placetype":"venue"
},
  "geometry": {"coordinates":[-2.966129,48.064919],"type":"Point"}
}