{
  "type": "Feature",
  "properties": {
    "addr:full":"1, Rue de Cavaillon, 13420 G\u00e9menos Languedoc-Roussillon",
    "addr:housenumber":"1",
    "addr:postcode":"13420",
    "addr:street":"Rue De Cavaillon",
    "iso:country":"FR",
    "sg:address":"1, Rue de Cavaillon, 13420 G\u00e9menos",
    "sg:orig_category":"Non-Classified Establishments",
    "sg:phone":"+33 4 91 36 12 46",
    "sg:province":"Languedoc-Roussillon",
    "wof:name":"A.2.m.s.",
    "wof:placetype":"venue"
},
  "geometry": {"coordinates":[5.629708,43.29594],"type":"Point"}
}