{
  "type": "Feature",
  "properties": {
    "addr:full":"8 rue Chanoine Nahot; La Chapelle Heulin Haute Normandie",
    "addr:housenumber":"8",
    "addr:street":"Rue Chanoine Nahot La",
    "iso:country":"FR",
    "sg:address":"8 rue Chanoine Nahot; La Chapelle Heulin",
    "sg:classifiers":[
        {
            "category":"Banks & Credit Unions",
            "subcategory":"Bank",
            "type":"Services"
        }
    ],
    "sg:phone":"+33 3340067068",
    "sg:province":"Haute Normandie",
    "wof:name":"Cr\u00e9dit Mutuel",
    "wof:placetype":"venue"
},
  "geometry": {"coordinates":[-1.33833,47.176189],"type":"Point"}
}