{
  "type": "Feature",
  "properties": {
    "addr:full":"90, Bd Saint Michel, 91150 Etampes Ile de France",
    "addr:housenumber":"90",
    "addr:postcode":"91150",
    "addr:street":"Bd Saint Michel",
    "iso:country":"FR",
    "sg:address":"90, Bd Saint Michel, 91150 Etampes",
    "sg:orig_category":"Unclassifiable Establishments",
    "sg:phone":"+33 1 69 78 04 04",
    "sg:province":"Ile de France",
    "wof:name":"Alpha Sciage S.a.r.l.",
    "wof:placetype":"venue"
},
  "geometry": {"coordinates":[2.170957,48.446865],"type":"Point"}
}