{
  "type": "Feature",
  "properties": {
    "iso:country":"FR",
    "sg:address":"156 Rue Julien Grimau 94400 Vitry Sur Seine",
    "sg:classifiers":[
        {
            "category":"Professional",
            "subcategory":"Advertising",
            "type":"Services"
        }
    ],
    "sg:phone":"+33 1 47 18 63 64",
    "sg:postcode":"94400",
    "sg:province":"Ile de France",
    "sg:tags":[
        "information",
        "medium",
        "communication"
    ],
    "wof:name":"Photographes Reunis",
    "wof:placetype":"venue"
},
  "geometry": {"coordinates":[2.375603,48.778637],"type":"Point"}
}