{
  "type": "Feature",
  "properties": {
    "iso:country":"FR",
    "sg:address":"3, Rte des Vignes, 74160 Saint Julien en Genevois",
    "sg:orig_category":"Unclassifiable Establishments",
    "sg:phone":"+33 4 50 49 23 86",
    "sg:province":"Rhone-Alpes",
    "wof:name":"Falda P\u00e8re Et Fils S.a.r.l.",
    "wof:placetype":"venue"
},
  "geometry": {"coordinates":[6.071952,46.13929],"type":"Point"}
}