{
  "type": "Feature",
  "properties": {
    "addr:full":"B.P. 101, 67721 Hoerdt C\u00e9dex^^21, Rue de l'Industrie - Zone Industrielle, 67720 Hoerdt Hoerdt Alsace 67720",
    "addr:housenumber":"b.p. 101",
    "addr:postcode":"67721;67720;67720",
    "addr:street":"Rue De L'Industrie Zone Industrielle",
    "iso:country":"FR",
    "sg:address":"B.P. 101, 67721 Hoerdt C\u00e9dex^^21, Rue de l'Industrie - Zone Industrielle, 67720 Hoerdt",
    "sg:city":"Hoerdt",
    "sg:orig_category":"Non-Classified Establishments",
    "sg:phone":"+33 3 88 69 20 04",
    "sg:postcode":"67720",
    "sg:province":"Alsace",
    "wof:name":"Gelco Mod S.a.",
    "wof:placetype":"venue"
},
  "geometry": {"coordinates":[7.795894,48.676208],"type":"Point"}
}