{
  "type": "Feature",
  "properties": {
    "iso:country":"FR",
    "sg:address":"B.P. 369, 88009 Epinal C\u00e9dex^^79, Rue d'Alsace, 88000 Epinal",
    "sg:orig_category":"Non-Classified Establishments",
    "sg:phone":"+33 3 29 29 51 51",
    "sg:province":"Lorraine",
    "wof:name":"Robert Et Houot S.a.",
    "wof:placetype":"venue"
},
  "geometry": {"coordinates":[6.517128,48.19949],"type":"Point"}
}