{
  "type": "Feature",
  "properties": {
    "iso:country":"FR",
    "sg:address":"3 pl de l'H\u00f4tel de Ville; Pontorson; 50170",
    "sg:city":"Pontorson",
    "sg:classifiers":[
        {
            "category":"Banks & Credit Unions",
            "subcategory":"Bank",
            "type":"Services"
        }
    ],
    "sg:phone":"+33 33601299",
    "sg:postcode":"50170",
    "sg:province":"Basse Normandie",
    "wof:name":"Banque Nationale De Paris",
    "wof:placetype":"venue"
},
  "geometry": {"coordinates":[-1.5064,48.553398],"type":"Point"}
}