{
  "type": "Feature",
  "properties": {
    "iso:country":"FR",
    "sg:address":"25 rue Voltaire 88300 Harchechamp",
    "sg:classifiers":[
        {
            "category":"Wholesale",
            "subcategory":"Construction Materials",
            "type":"Manufacturing & Wholesale Goods"
        }
    ],
    "sg:phone":"+33 3 29 06 82 52",
    "sg:province":"Lorraine",
    "sg:tags":[
        "concrete",
        "reinforced"
    ],
    "wof:name":"Entreprise Paul Calin S.a.",
    "wof:placetype":"venue"
},
  "geometry": {"coordinates":[5.77679,48.385101],"type":"Point"}
}