{
  "type": "Feature",
  "properties": {
    "addr:full":"B.P. 1000, 42335 Roanne C\u00e9dex^^58, Bd Jean Baptiste Cl\u00e9ment, 42300 Roanne Rhone-Alpes",
    "addr:postcode":"42335;ce\u0301dex^^58;42300",
    "addr:street":"B.P. 1000;Bd Jean Baptiste Cle\u0301Ment",
    "iso:country":"FR",
    "sg:address":"B.P. 1000, 42335 Roanne C\u00e9dex^^58, Bd Jean Baptiste Cl\u00e9ment, 42300 Roanne",
    "sg:orig_category":"Non-Classified Establishments",
    "sg:phone":"+33 4 77 44 44 00",
    "sg:province":"Rhone-Alpes",
    "wof:name":"J.p.v. Navar Diffusion S.a.",
    "wof:placetype":"venue"
},
  "geometry": {"coordinates":[4.040056,45.992947],"type":"Point"}
}