{
  "type": "Feature",
  "properties": {
    "addr:full":"Nationale 7 Mormant sur Vernisson Centre 45700",
    "addr:postcode":"45700",
    "addr:street":"Nationale 7 Mormant Sur Vernisson",
    "iso:country":"FR",
    "sg:address":"Nationale 7",
    "sg:city":"Mormant sur Vernisson",
    "sg:orig_category":"Non-Classified Establishments",
    "sg:phone":"+33 2 38 94 94 64",
    "sg:postcode":"45700",
    "sg:province":"Centre",
    "wof:name":"Pakameko Conditionnement S.a.r.l.",
    "wof:placetype":"venue"
},
  "geometry": {"coordinates":[2.765315,47.896927],"type":"Point"}
}