{
  "type": "Feature",
  "properties": {
    "addr:full":"Chemin des Gr\u00e8ves Ch\u00e2lons en Champagne Champagne 51000",
    "addr:postcode":"51000",
    "addr:street":"Chemin Des Gre\u0300Ves",
    "iso:country":"FR",
    "sg:address":"Chemin des Gr\u00e8ves",
    "sg:city":"Ch\u00e2lons en Champagne",
    "sg:orig_category":"Unclassifiable Establishments",
    "sg:phone":"+33 3 26 68 57 42",
    "sg:postcode":"51000",
    "sg:province":"Champagne",
    "wof:name":"A.a.m.c. S.a.r.l. - Atelier D'agencement De Menuiserie De Champagne",
    "wof:placetype":"venue"
},
  "geometry": {"coordinates":[4.34068,48.963097],"type":"Point"}
}