{
  "type": "Feature",
  "properties": {
    "addr:full":"La Croix Gall 56230 Questembert Questembert Bretagne 56230",
    "addr:postcode":"56230;56230",
    "addr:street":"La Croix Gall",
    "iso:country":"FR",
    "sg:address":"La Croix Gall 56230 Questembert",
    "sg:city":"Questembert",
    "sg:classifiers":[
        {
            "category":"Manufacturing",
            "subcategory":"Electronics",
            "type":"Manufacturing & Wholesale Goods"
        }
    ],
    "sg:phone":"+33 2 97 26 68 58",
    "sg:postcode":"56230",
    "sg:province":"Bretagne",
    "sg:tags":[
        "pcb",
        "printed",
        "circuit",
        "board"
    ],
    "wof:name":"Cablage Electronique Professionnel Aero Sarl",
    "wof:placetype":"venue"
},
  "geometry": {"coordinates":[-2.48424,47.66507],"type":"Point"}
}