{
  "type": "Feature",
  "properties": {
    "addr:full":"13 Rue Louis Rosier Parc Technologique La Pard 63000 Clermont Ferrand Clermont-Ferrand Auvergne 63000",
    "addr:housenumber":"13",
    "addr:postcode":"pard 63000;63000",
    "addr:street":"Rue Louis Rosier",
    "iso:country":"FR",
    "sg:address":"13 Rue Louis Rosier Parc Technologique La Pard 63000 Clermont Ferrand",
    "sg:city":"Clermont-Ferrand",
    "sg:classifiers":[
        {
            "category":"Professional",
            "subcategory":"Computer Services",
            "type":"Services"
        }
    ],
    "sg:phone":"+33 4 73 27 20 02",
    "sg:postcode":"63000",
    "sg:province":"Auvergne",
    "sg:tags":[
        "information",
        "technology",
        "software"
    ],
    "wof:name":"Cegid Sa",
    "wof:placetype":"venue"
},
  "geometry": {"coordinates":[3.136041,45.763599],"type":"Point"}
}