{
  "type": "Feature",
  "properties": {
    "addr:full":"175, Rue de Noisy le Sec, 93260 Les Lilas Ile de France",
    "addr:housenumber":"175",
    "addr:postcode":"93260",
    "addr:street":"Rue De Noisy Le Sec",
    "iso:country":"FR",
    "sg:address":"175, Rue de Noisy le Sec, 93260 Les Lilas",
    "sg:orig_category":"Unclassifiable Establishments",
    "sg:phone":"+33 1 43 62 75 11",
    "sg:province":"Ile de France",
    "wof:name":"Seif Industrie S.a.r.l.",
    "wof:placetype":"venue"
},
  "geometry": {"coordinates":[2.419005,48.877174],"type":"Point"}
}