{
  "type": "Feature",
  "properties": {
    "addr:full":"B.P. 301, 33820 Saint Aubin de Blaye^^2, Brasse Mis\u00e8re - ZI, 33820 Saint Aubin de Blaye Braud-et-Saint-Louis Aquitaine 33820",
    "addr:housenumber":"b.p. 301",
    "addr:postcode":"33820;33820;33820",
    "addr:street":"Zi",
    "iso:country":"FR",
    "sg:address":"B.P. 301, 33820 Saint Aubin de Blaye^^2, Brasse Mis\u00e8re - ZI, 33820 Saint Aubin de Blaye",
    "sg:city":"Braud-et-Saint-Louis",
    "sg:orig_category":"Non-Classified Establishments",
    "sg:phone":"+33 5 57 94 06 40",
    "sg:postcode":"33820",
    "sg:province":"Aquitaine",
    "wof:name":"A.2.m. S.a. - Assistance Maintenance Industrielle",
    "wof:placetype":"venue"
},
  "geometry": {"coordinates":[-0.5622,45.269951],"type":"Point"}
}