{
  "type": "Feature",
  "properties": {
    "addr:full":"20, Rue V\u00e9soul, 25000 Besan\u00e7on Franche Comt\u00e9",
    "addr:housenumber":"20",
    "addr:postcode":"25000",
    "addr:street":"Rue Ve\u0301Soul;Franche Comte\u0301",
    "iso:country":"FR",
    "sg:address":"20, Rue V\u00e9soul, 25000 Besan\u00e7on",
    "sg:orig_category":"Non-Classified Establishments",
    "sg:phone":"+33 3 81 88 71 29",
    "sg:province":"Franche Comt\u00e9",
    "wof:name":"Otea S.a.r.l.",
    "wof:placetype":"venue"
},
  "geometry": {"coordinates":[6.018993,47.250439],"type":"Point"}
}