{
  "type": "Feature",
  "properties": {
    "addr:full":"29, Rue du Bois Galon, 94120 Fontenay sous Bois Ile de France",
    "addr:housenumber":"29",
    "addr:postcode":"94120",
    "addr:street":"Rue Du Bois Galon;Bois Ile De France",
    "iso:country":"FR",
    "sg:address":"29, Rue du Bois Galon, 94120 Fontenay sous Bois",
    "sg:orig_category":"Unclassifiable Establishments",
    "sg:phone":"+33 1 45 14 21 80",
    "sg:province":"Ile de France",
    "wof:name":"Graph'm S.a.r.l.",
    "wof:placetype":"venue"
},
  "geometry": {"coordinates":[2.492981,48.859306],"type":"Point"}
}