{
  "type": "Feature",
  "properties": {
    "addr:full":"Rue Jean Jacques Mention Zi Nord Village Pmi N 2 80000 Amiens Picardie 80000",
    "addr:housenumber":"2",
    "addr:postcode":"80000;80000",
    "addr:street":"Rue Jean Jacques Mention Zi Nord Village Pmi N",
    "iso:country":"FR",
    "sg:address":"Rue Jean Jacques Mention Zi Nord Village Pmi N 2 80000 Amiens",
    "sg:classifiers":[
        {
            "category":"Wholesale",
            "subcategory":"Machinery & Supplies",
            "type":"Manufacturing & Wholesale Goods"
        }
    ],
    "sg:phone":"+33 3 22 44 82 19",
    "sg:postcode":"80000",
    "sg:province":"Picardie",
    "sg:tags":[
        "handling",
        "material",
        "-",
        "machine",
        "equipment",
        "engineering",
        "mechanical"
    ],
    "wof:name":"Belteam",
    "wof:placetype":"venue"
},
  "geometry": {"coordinates":[2.293165,49.894733],"type":"Point"}
}