{
  "type": "Feature",
  "properties": {
    "addr:full":"77, Rue du Martroy, 02220 Braine Picardie 02220",
    "addr:housenumber":"77",
    "addr:postcode":"02220;02220",
    "addr:street":"Rue Du Martroy;Picardie",
    "iso:country":"FR",
    "sg:address":"77, Rue du Martroy, 02220 Braine",
    "sg:orig_category":"M\u00c9TALLERIE, SERRURERIE, MENUISERIE ALUMINIUM",
    "sg:phone":"+33 3 23 74 11 24",
    "sg:postcode":"02220",
    "sg:province":"Picardie",
    "wof:name":"Ruffy S.a.r.l.",
    "wof:placetype":"venue"
},
  "geometry": {"coordinates":[3.53192,49.341118],"type":"Point"}
}