{
  "type": "Feature",
  "properties": {
    "iso:country":"FR",
    "sg:address":"Village 21500 Touillon",
    "sg:city":"Touillon",
    "sg:classifiers":[
        {
            "category":"Home & Garden",
            "subcategory":"Furniture",
            "type":"Retail Goods"
        }
    ],
    "sg:phone":"+33 3 80 89 00 30",
    "sg:postcode":"21500",
    "sg:province":"Bourgogne",
    "sg:tags":[
        "wood"
    ],
    "wof:name":"Jacquenet Malin (ets) Sa",
    "wof:placetype":"venue"
},
  "geometry": {"coordinates":[4.33617,47.621639],"type":"Point"}
}