{
  "type": "Feature",
  "properties": {
    "addr:full":"165, Rue des Verriers, 51230 F\u00e8re Champenoise Champagne",
    "addr:housenumber":"165",
    "addr:postcode":"51230",
    "addr:street":"Rue Des Verriers",
    "iso:country":"FR",
    "sg:address":"165, Rue des Verriers, 51230 F\u00e8re Champenoise",
    "sg:orig_category":"Unclassifiable Establishments",
    "sg:phone":"+33 3 26 42 40 51",
    "sg:province":"Champagne",
    "wof:name":"Pr\u00e9ciculture S.a.",
    "wof:placetype":"venue"
},
  "geometry": {"coordinates":[3.992425,48.756882],"type":"Point"}
}