{
  "type": "Feature",
  "properties": {
    "addr:full":"3, Av des Tirverts - ZI des Ecrevolles, 10150 Pont Sainte Marie Champagne",
    "addr:postcode":"10150",
    "addr:street":"Av Des Tirverts Zi Des Ecrevolles",
    "iso:country":"FR",
    "sg:address":"3, Av des Tirverts - ZI des Ecrevolles, 10150 Pont Sainte Marie",
    "sg:orig_category":"Non-Classified Establishments",
    "sg:phone":"+33 3 25 45 24 24",
    "sg:province":"Champagne",
    "wof:name":"Stelec S.a.r.l.",
    "wof:placetype":"venue"
},
  "geometry": {"coordinates":[4.09298,48.317806],"type":"Point"}
}