{
  "type": "Feature",
  "properties": {
    "iso:country":"FR",
    "sg:address":"6, Rue de Watford, 92000 Nanterre",
    "sg:orig_category":"Unclassifiable Establishments",
    "sg:phone":"+33 1 47 76 42 62",
    "sg:province":"Ile de France",
    "wof:name":"Sol\u00e9tanche Bachy France S.a.",
    "wof:placetype":"venue"
},
  "geometry": {"coordinates":[2.222864,48.885872],"type":"Point"}
}