{
  "type": "Feature",
  "properties": {
    "iso:country":"FR",
    "sg:address":"4, Rue du Moulin, 55130 Baudign\u00e9court",
    "sg:orig_category":"Non-Classified Establishments",
    "sg:phone":"+33 3 29 89 61 06",
    "sg:postcode":"55130",
    "sg:province":"Lorraine",
    "wof:name":"Collinet S.a.",
    "wof:placetype":"venue"
},
  "geometry": {"coordinates":[5.463375,48.570744],"type":"Point"}
}