{
  "type": "Feature",
  "properties": {
    "addr:full":"76, Rue R\u00e9aumur, 75002 Paris Ile de France 75002",
    "addr:housenumber":"76",
    "addr:postcode":"75002;75002",
    "addr:street":"Rue Re\u0301Aumur",
    "iso:country":"FR",
    "sg:address":"76, Rue R\u00e9aumur, 75002 Paris",
    "sg:orig_category":"Non-Classified Establishments",
    "sg:phone":"+33 1 40 26 12 42",
    "sg:postcode":"75002",
    "sg:province":"Ile de France",
    "wof:name":"Akopian Ory S.a.",
    "wof:placetype":"venue"
},
  "geometry": {"coordinates":[2.351889,48.866474],"type":"Point"}
}