{
  "type": "Feature",
  "properties": {
    "iso:country":"FR",
    "sg:address":"138, Rte de Riottier, 69400 Villefranche sur Sa\u00f4ne",
    "sg:orig_category":"Unclassifiable Establishments",
    "sg:phone":"+33 4 74 60 05 36",
    "sg:postcode":"69400",
    "sg:province":"Rhone-Alpes",
    "wof:name":"Epona S.a.r.l.",
    "wof:placetype":"venue"
},
  "geometry": {"coordinates":[4.72174,45.984142],"type":"Point"}
}