{
  "type": "Feature",
  "properties": {
    "addr:full":"RN 151 Le Subdray Centre 18570",
    "addr:postcode":"18570",
    "addr:street":"Rn 151 Le",
    "iso:country":"FR",
    "sg:address":"RN 151",
    "sg:city":"Le Subdray",
    "sg:orig_category":"Unclassifiable Establishments",
    "sg:phone":"+33 2 48 55 97 60",
    "sg:postcode":"18570",
    "sg:province":"Centre",
    "wof:name":"S.e.r.a.t. S.a. - Soci\u00e9t\u00e9 D' Etudes, De R\u00e9alisations Et D' Applications Techniques",
    "wof:placetype":"venue"
},
  "geometry": {"coordinates":[2.355745,47.008541],"type":"Point"}
}