{
  "type": "Feature",
  "properties": {
    "iso:country":"FR",
    "sg:address":"16 Rue Michael Faraday 72100 Le Mans",
    "sg:classifiers":[
        {
            "category":"Professional",
            "type":"Services"
        }
    ],
    "sg:phone":"+33 2 43 61 22 33",
    "sg:province":"Pays de Loire",
    "sg:tags":[
        "transport",
        "road"
    ],
    "wof:name":"Maine Denrees Sarl",
    "wof:placetype":"venue"
},
  "geometry": {"coordinates":[0.186392,47.961315],"type":"Point"}
}