{
  "type": "Feature",
  "properties": {
    "iso:country":"FR",
    "sg:address":"7, Rte de Bessi\u00e8res, 31240 L'Union",
    "sg:orig_category":"Unclassifiable Establishments",
    "sg:phone":"+33 5 62 89 19 00",
    "sg:province":"Midi Pyr\u00e9n\u00e9es",
    "wof:name":"C.g.s.t. Save S.a.s. - Compagnie Gazi\u00e8re Service Technique Save",
    "wof:placetype":"venue"
},
  "geometry": {"coordinates":[-87.905098,32.996254],"type":"Point"}
}