{
  "type": "Feature",
  "properties": {
    "addr:full":"12, Rue du Chemin Vert, 57050 Plappeville Lorraine",
    "addr:housenumber":"12",
    "addr:postcode":"57050",
    "addr:street":"Rue Du Chemin Vert",
    "iso:country":"FR",
    "sg:address":"12, Rue du Chemin Vert, 57050 Plappeville",
    "sg:orig_category":"Non-Classified Establishments",
    "sg:phone":"+33 3 87 30 46 84",
    "sg:province":"Lorraine",
    "wof:name":"Renner Marc",
    "wof:placetype":"venue"
},
  "geometry": {"coordinates":[6.125417,49.127144],"type":"Point"}
}