{
  "type": "Feature",
  "properties": {
    "iso:country":"FR",
    "sg:address":"34, Rue Sainte H\u00e9l\u00e8ne, 69002 Lyon",
    "sg:orig_category":"Unclassifiable Establishments",
    "sg:phone":"+33 4 78 37 31 67",
    "sg:postcode":"69002",
    "sg:province":"Rhone-Alpes",
    "wof:name":"Revol S.a.r.l.",
    "wof:placetype":"venue"
},
  "geometry": {"coordinates":[4.832203,45.753716],"type":"Point"}
}