{
  "type": "Feature",
  "properties": {
    "iso:country":"FR",
    "sg:address":"1 Rue M\u00e9tairie 95640 Marines",
    "sg:classifiers":[
        {
            "category":"Shopping",
            "type":"Retail Goods"
        }
    ],
    "sg:phone":"+33 1 34 67 52 25",
    "sg:postcode":"95640",
    "sg:province":"Ile de France",
    "sg:tags":[
        "metallurgy",
        "finished",
        "-",
        "metalworking",
        "metallic"
    ],
    "wof:name":"Brument Starflow Sa",
    "wof:placetype":"venue"
},
  "geometry": {"coordinates":[1.97022,49.149612],"type":"Point"}
}