{
  "type": "Feature",
  "properties": {
    "addr:full":"B.P. 1, 02690 Urvillers^^Rte de Lambay, 02690 Urvillers Picardie 02690",
    "addr:housenumber":"1",
    "addr:postcode":"02690;02690;02690",
    "addr:street":"B.P.;Lambay;Picardie",
    "iso:country":"FR",
    "sg:address":"B.P. 1, 02690 Urvillers^^Rte de Lambay, 02690 Urvillers",
    "sg:orig_category":"Non-Classified Establishments",
    "sg:phone":"+33 3 23 50 31 31",
    "sg:postcode":"02690",
    "sg:province":"Picardie",
    "wof:name":"B\u00e9tems Et Compagnie S.a.r.l.",
    "wof:placetype":"venue"
},
  "geometry": {"coordinates":[3.30754,49.785931],"type":"Point"}
}