{
  "type": "Feature",
  "properties": {
    "iso:country":"FR",
    "sg:address":"18",
    "sg:city":"Givry",
    "sg:classifiers":[
        {
            "category":"Food Court",
            "type":"Food & Drink"
        }
    ],
    "sg:phone":"+33 3 85 44 38 60",
    "sg:postcode":"71640",
    "sg:province":"Bourgogne",
    "sg:tags":[
        "product",
        "related"
    ],
    "wof:name":"Parize Pere Et Fils",
    "wof:placetype":"venue"
},
  "geometry": {"coordinates":[4.731314,46.776295],"type":"Point"}
}