{
  "type": "Feature",
  "properties": {
    "addr:full":"14 Avenue Ars\u00e8ne D'Arsonval Bourg En Bresse Rhone-Alpes 01000",
    "addr:housenumber":"14",
    "addr:postcode":"01000",
    "addr:street":"Avenue Arse\u0300Ne D'Arsonval",
    "iso:country":"FR",
    "sg:address":"14 Avenue Ars\u00e8ne D'Arsonval",
    "sg:city":"Bourg En Bresse",
    "sg:classifiers":[
        {
            "category":"Banks & Credit Unions",
            "subcategory":"Financial Services",
            "type":"Services"
        }
    ],
    "sg:phone":"+33 4 74 45 57 33",
    "sg:postcode":"01000",
    "sg:province":"Rhone-Alpes",
    "sg:tags":[
        "banking",
        "finance",
        "insurance"
    ],
    "wof:name":"Dupont Bedu Sa",
    "wof:placetype":"venue"
},
  "geometry": {"coordinates":[5.2201,46.223568],"type":"Point"}
}