{
  "type": "Feature",
  "properties": {
    "addr:full":"945, Pic de Bertagne - Zone de la Plaine de Jouques, 13420 G\u00e9menos Plaine Alsace 67420",
    "addr:housenumber":"945",
    "addr:postcode":"13420;67420",
    "addr:street":"Pic De Bertagne Zone De La Plaine De Jouques;Plaine",
    "iso:country":"FR",
    "sg:address":"945, Pic de Bertagne - Zone de la Plaine de Jouques, 13420 G\u00e9menos",
    "sg:city":"Plaine",
    "sg:orig_category":"Unclassifiable Establishments",
    "sg:phone":"+33 4 42 32 76 10",
    "sg:postcode":"67420",
    "sg:province":"Alsace",
    "wof:name":"Cegip Service E.u.r.l.",
    "wof:placetype":"venue"
},
  "geometry": {"coordinates":[5.627487,43.294132],"type":"Point"}
}