{
  "type": "Feature",
  "properties": {
    "iso:country":"FR",
    "sg:address":"3 Av De L'Industrie 08000 Charleville-M\u00e9zi\u00e8res",
    "sg:city":"Charleville-M\u00e9zi\u00e8res",
    "sg:classifiers":[
        {
            "category":"Manufacturing",
            "subcategory":"Motor Vehicles & Parts",
            "type":"Manufacturing & Wholesale Goods"
        }
    ],
    "sg:phone":"+33 3 24 59 59 59",
    "sg:postcode":"08000",
    "sg:province":"Champagne",
    "sg:tags":[
        "engine",
        "machine",
        "engineering",
        "-",
        "mechanical"
    ],
    "wof:name":"Visteon Sas",
    "wof:placetype":"venue"
},
  "geometry": {"coordinates":[4.710658,49.768295],"type":"Point"}
}