{
  "type": "Feature",
  "properties": {
    "addr:full":"quai Valmy 51800 STE MENEHOULD Champagne 51800",
    "addr:postcode":"51800;51800",
    "addr:street":"Quai Valmy;Menehould Champagne",
    "iso:country":"FR",
    "sg:address":"quai Valmy 51800 STE MENEHOULD",
    "sg:classifiers":[
        {
            "category":"Communications",
            "subcategory":"Film & Video Production",
            "type":"Services"
        }
    ],
    "sg:phone":"+33 3 26 60 05 45",
    "sg:postcode":"51800",
    "sg:province":"Champagne",
    "sg:tags":[
        "coating",
        "fa\u00e7ade"
    ],
    "wof:name":"Assistance Comm Developpement Industriel S.a.r.l.",
    "wof:placetype":"venue"
},
  "geometry": {"coordinates":[4.891645,49.090473],"type":"Point"}
}