{
  "type": "Feature",
  "properties": {
    "iso:country":"FR",
    "sg:address":"Zi Eigen 67490 Dettwiller",
    "sg:city":"Dettwiller",
    "sg:classifiers":[
        {
            "category":"Manufacturing",
            "subcategory":"Metals",
            "type":"Manufacturing & Wholesale Goods"
        }
    ],
    "sg:phone":"+33 3 88 71 95 15",
    "sg:postcode":"67490",
    "sg:province":"Alsace",
    "sg:tags":[
        "-",
        "machine",
        "equipment",
        "engineering",
        "machinery",
        "mechanical"
    ],
    "wof:name":"Electropoli Production Sa",
    "wof:placetype":"venue"
},
  "geometry": {"coordinates":[7.46685,48.754059],"type":"Point"}
}