{
  "type": "Feature",
  "properties": {
    "iso:country":"FR",
    "sg:address":"Rte De Taulignan BP 55 84600 Valr\u00e9as",
    "sg:city":"Taulignan",
    "sg:classifiers":[
        {
            "category":"Manufacturing",
            "subcategory":"Building Materials",
            "type":"Manufacturing & Wholesale Goods"
        }
    ],
    "sg:phone":"+33 4 90 37 35 90",
    "sg:postcode":"26770",
    "sg:province":"Rhone-Alpes",
    "sg:tags":[
        "-",
        "machine",
        "raw",
        "engineering",
        "paper",
        "mechanical",
        "cardboard"
    ],
    "wof:name":"Valformes Sarl",
    "wof:placetype":"venue"
},
  "geometry": {"coordinates":[4.990725,44.386776],"type":"Point"}
}