{
  "type": "Feature",
  "properties": {
    "iso:country":"FR",
    "sg:address":"Zi St M\u00e9dard Des Pr\u00e9s 85204 Fontenay Le Comte",
    "sg:classifiers":[
        {
            "category":"Professional",
            "subcategory":"Engineering",
            "type":"Services"
        }
    ],
    "sg:phone":"+33 2 51 53 16 16",
    "sg:province":"Champagne",
    "sg:tags":[
        "machine",
        "-",
        "mechanical"
    ],
    "wof:name":"Imeca Sa",
    "wof:placetype":"venue"
},
  "geometry": {"coordinates":[-0.802274,46.464867],"type":"Point"}
}