{
  "type": "Feature",
  "properties": {
    "addr:full":"27, Chemin des Vieux Fours, 78270 Limetz Villez Ile de France 78270",
    "addr:housenumber":"27",
    "addr:postcode":"78270;78270",
    "addr:street":"Chemin Des Vieux Fours",
    "iso:country":"FR",
    "sg:address":"27, Chemin des Vieux Fours, 78270 Limetz Villez",
    "sg:orig_category":"Non-Classified Establishments",
    "sg:phone":"+33 1 30 98 97 50",
    "sg:postcode":"78270",
    "sg:province":"Ile de France",
    "wof:name":"Compresseurs Et Techniques S.a.r.l.",
    "wof:placetype":"venue"
},
  "geometry": {"coordinates":[1.534965,49.05864],"type":"Point"}
}