{
  "type": "Feature",
  "properties": {
    "iso:country":"FR",
    "sg:address":"1 bd Reni Levasseur; B.P. 22385; LE MANS; 72002 CEDEX",
    "sg:classifiers":[
        {
            "category":"Shopping",
            "subcategory":"Computers & Home Electronics",
            "type":"Retail Goods"
        }
    ],
    "sg:phone":"+33 2 43 21 00 00",
    "sg:province":"Haute Normandie",
    "sg:tags":[
        "chamber",
        "commerce"
    ],
    "wof:name":"Chambre De Commerce Du Mans Et De La Sarthe",
    "wof:placetype":"venue"
},
  "geometry": {"coordinates":[0.20303,47.99527],"type":"Point"}
}