{
  "type": "Feature",
  "properties": {
    "iso:country":"FR",
    "sg:address":"B.P. 60, 92152 Suresnes C\u00e9dex^^116, Rue Carnot, 92150 Suresnes",
    "sg:orig_category":"Non-Classified Establishments",
    "sg:phone":"+33 1 46 97 55 00",
    "sg:province":"Ile de France",
    "wof:name":"Lipha S.a.",
    "wof:placetype":"venue"
},
  "geometry": {"coordinates":[2.22677,48.867504],"type":"Point"}
}