{
  "type": "Feature",
  "properties": {
    "addr:full":"11, Rue Henri Barbusse, 26000 Valence Rhone-Alpes 26000",
    "addr:housenumber":"11",
    "addr:postcode":"26000;26000",
    "addr:street":"Rue Henri Barbusse",
    "iso:country":"FR",
    "sg:address":"11, Rue Henri Barbusse, 26000 Valence",
    "sg:orig_category":"Non-Classified Establishments",
    "sg:phone":"+33 4 75 43 63 70",
    "sg:postcode":"26000",
    "sg:province":"Rhone-Alpes",
    "wof:name":"Elpack S.a.",
    "wof:placetype":"venue"
},
  "geometry": {"coordinates":[4.913435,44.919323],"type":"Point"}
}