{
  "type": "Feature",
  "properties": {
    "iso:country":"FR",
    "sg:address":"Domaine de la Grande Ferrade",
    "sg:city":"Villenave d'Ornon",
    "sg:orig_category":"Unclassifiable Establishments",
    "sg:phone":"+33 5 56 84 30 02",
    "sg:postcode":"33140",
    "sg:province":"Aquitaine",
    "wof:name":"I.n.r.a.",
    "wof:placetype":"venue"
},
  "geometry": {"coordinates":[-0.568254,44.759846],"type":"Point"}
}