{
  "type": "Feature",
  "properties": {
    "iso:country":"FR",
    "sg:address":"1, Av. Edouard Herriot, 69400 Limas",
    "sg:orig_category":"Unclassifiable Establishments",
    "sg:phone":"+33 4 74 62 76 76",
    "sg:postcode":"69400",
    "sg:province":"Rhone-Alpes",
    "wof:name":"Aventis Crop Sciences S.a.",
    "wof:placetype":"venue"
},
  "geometry": {"coordinates":[4.723519,45.978397],"type":"Point"}
}