{
  "type": "Feature",
  "properties": {
    "addr:full":"B.P. 68, 67152 Erstein C\u00e9dex^^Rue Georges Besse - Zone Industrielle Ouest, 67150 Erstein Erstein Alsace 67150",
    "addr:postcode":"67152;67150;67150",
    "addr:street":"B.P. 68;Georges Besse Zone Industrielle Ouest",
    "iso:country":"FR",
    "sg:address":"B.P. 68, 67152 Erstein C\u00e9dex^^Rue Georges Besse - Zone Industrielle Ouest, 67150 Erstein",
    "sg:city":"Erstein",
    "sg:orig_category":"Non-Classified Establishments",
    "sg:phone":"+33 3 88 59 01 23",
    "sg:postcode":"67150",
    "sg:province":"Alsace",
    "wof:name":"Acheson France S.a.",
    "wof:placetype":"venue"
},
  "geometry": {"coordinates":[7.66295,48.421101],"type":"Point"}
}