{
  "type": "Feature",
  "properties": {
    "iso:country":"FR",
    "sg:address":"2, Rue Yves Toudic, 69200 V\u00e9nissieux",
    "sg:orig_category":"Unclassifiable Establishments",
    "sg:phone":"+33 4 72 51 72 51",
    "sg:province":"Rhone-Alpes",
    "wof:name":"R\u00e9bar S.a.r.l.",
    "wof:placetype":"venue"
},
  "geometry": {"coordinates":[4.900289,45.692268],"type":"Point"}
}