{
  "type": "Feature",
  "properties": {
    "iso:country":"FR",
    "sg:address":"69 Rue Du Dr. Pontier 62380 Lundres",
    "sg:classifiers":[
        {
            "category":"Manufacturing",
            "subcategory":"Paper Products",
            "type":"Manufacturing & Wholesale Goods"
        }
    ],
    "sg:phone":"+33 3 21 38 60 00",
    "sg:province":"Nord Pas-de-Calais",
    "sg:tags":[
        "raw",
        "material",
        "-",
        "cardboard"
    ],
    "wof:name":"Sical Sa",
    "wof:placetype":"venue"
},
  "geometry": {"coordinates":[-91.238159,40.24049],"type":"Point"}
}