{
  "type": "Feature",
  "properties": {
    "addr:full":"3, Impasse du Ch\u00e2teau, 80220 Gamaches Picardie",
    "addr:housenumber":"3",
    "addr:postcode":"80220",
    "addr:street":"Impasse Du Cha\u0302Teau",
    "iso:country":"FR",
    "sg:address":"3, Impasse du Ch\u00e2teau, 80220 Gamaches",
    "sg:orig_category":"Unclassifiable Establishments",
    "sg:phone":"+33 3 22 60 31 30",
    "sg:province":"Picardie",
    "wof:name":"Verreries De Courval S.a.",
    "wof:placetype":"venue"
},
  "geometry": {"coordinates":[1.558425,49.984001],"type":"Point"}
}