{
  "type": "Feature",
  "properties": {
    "addr:full":"Gransac 31620 Fronton Midi Pyr\u00e9n\u00e9es 31620",
    "addr:postcode":"31620;31620",
    "addr:street":"Gransac",
    "iso:country":"FR",
    "sg:address":"Gransac 31620 Fronton",
    "sg:classifiers":[
        {
            "category":"Building & Trades",
            "subcategory":"Electrical",
            "type":"Services"
        }
    ],
    "sg:phone":"+33 5 61 82 11 12",
    "sg:postcode":"31620",
    "sg:province":"Midi Pyr\u00e9n\u00e9es",
    "sg:tags":[
        "electronic",
        "lighting",
        "equipment"
    ],
    "wof:name":"Cubi Spot Sa",
    "wof:placetype":"venue"
},
  "geometry": {"coordinates":[1.35712,43.835941],"type":"Point"}
}