{
  "type": "Feature",
  "properties": {
    "addr:full":"13 Rue Du Ballon 93165 Noisy Le Grand Poitou-Charentes",
    "addr:housenumber":"13",
    "addr:postcode":"93165",
    "addr:street":"Rue Du Ballon;Grand",
    "iso:country":"FR",
    "sg:address":"13 Rue Du Ballon 93165 Noisy Le Grand",
    "sg:classifiers":[
        {
            "category":"Manufacturing",
            "subcategory":"Glass & Minerals",
            "type":"Manufacturing & Wholesale Goods"
        }
    ],
    "sg:phone":"+33 1 43 03 78 81",
    "sg:province":"Poitou-Charentes",
    "sg:tags":[
        "building",
        "material"
    ],
    "wof:name":"Verre Industriel Et Ouvr\u00c9 Sa",
    "wof:placetype":"venue"
},
  "geometry": {"coordinates":[2.576511,48.833199],"type":"Point"}
}