{
  "type": "Feature",
  "properties": {
    "addr:full":"Bd Arago Chang\u00e9 - Z.I. des Touches Laval R\u00e9gion Pays de la Loire 53093",
    "addr:postcode":"53093",
    "addr:street":"Bd Arago;Touches",
    "iso:country":"FR",
    "sg:address":"Bd Arago Chang\u00e9 - Z.I. des Touches",
    "sg:city":"Laval",
    "sg:orig_category":"Non-Classified Establishments",
    "sg:phone":"+33 2 43 67 45 50",
    "sg:postcode":"53093",
    "sg:province":"R\u00e9gion Pays de la Loire",
    "wof:name":"Pr\u00e9sident S.n.c.",
    "wof:placetype":"venue"
},
  "geometry": {"coordinates":[-0.765489,48.050179],"type":"Point"}
}