{
  "type": "Feature",
  "properties": {
    "addr:full":"31, Rue Pierre Vincendon, 38110 La Tour du Pin Rhone-Alpes 38110",
    "addr:housenumber":"31",
    "addr:postcode":"38110;38110",
    "addr:street":"Rue Pierre Vincendon",
    "iso:country":"FR",
    "sg:address":"31, Rue Pierre Vincendon, 38110 La Tour du Pin",
    "sg:orig_category":"Unclassifiable Establishments",
    "sg:phone":"+33 4 74 97 13 11",
    "sg:postcode":"38110",
    "sg:province":"Rhone-Alpes",
    "wof:name":"Muller Tube Pneumatique S.a.r.l.",
    "wof:placetype":"venue"
},
  "geometry": {"coordinates":[5.440617,45.565998],"type":"Point"}
}