{
  "type": "Feature",
  "properties": {
    "addr:full":"16 Av Des Ch\u00e2teaupieds 92500 Rueil Malmaison Ile de France 92500",
    "addr:postcode":"92500;92500",
    "addr:street":"16 Av Des Cha\u0302Teaupieds",
    "iso:country":"FR",
    "sg:address":"16 Av Des Ch\u00e2teaupieds 92500 Rueil Malmaison",
    "sg:classifiers":[
        {
            "category":"Manufacturing",
            "subcategory":"Chemicals & Compounds",
            "type":"Manufacturing & Wholesale Goods"
        }
    ],
    "sg:phone":"+33 1 55 47 94 50",
    "sg:postcode":"92500",
    "sg:province":"Ile de France",
    "sg:tags":[
        "pharmaceutical",
        "energy",
        "chemistry",
        "-",
        "by-product"
    ],
    "wof:name":"Europe Service Restauration",
    "wof:placetype":"venue"
},
  "geometry": {"coordinates":[2.17454,48.881096],"type":"Point"}
}