{
  "type": "Feature",
  "properties": {
    "addr:full":"45, Rue Gustave Nicolle, 76600 Le Havre Haute Normandie",
    "addr:housenumber":"45",
    "addr:postcode":"76600",
    "addr:street":"Rue Gustave Nicolle",
    "iso:country":"FR",
    "sg:address":"45, Rue Gustave Nicolle, 76600 Le Havre",
    "sg:orig_category":"Unclassifiable Establishments",
    "sg:phone":"+33 2 35 26 60 06",
    "sg:province":"Haute Normandie",
    "wof:name":"M\u00e9riel S.a.",
    "wof:placetype":"venue"
},
  "geometry": {"coordinates":[0.14484,49.491329],"type":"Point"}
}