{
  "type": "Feature",
  "properties": {
    "iso:country":"FR",
    "sg:address":"25, Rue de la Gazelle, 43000 Le Puy en Velay",
    "sg:city":"Le Puy-en-Velay",
    "sg:orig_category":"Unclassifiable Establishments",
    "sg:phone":"+33 4 71 02 11 34",
    "sg:postcode":"43000",
    "sg:province":"Auvergne",
    "wof:name":"Imprimerie Jeanne D'arc S.a.",
    "wof:placetype":"venue"
},
  "geometry": {"coordinates":[3.892591,45.044266],"type":"Point"}
}