{
  "type": "Feature",
  "properties": {
    "iso:country":"FR",
    "sg:address":"Le Ch\u00eane Guillemot 77160 Saint Hilliers",
    "sg:classifiers":[
        {
            "category":"Manufacturing",
            "subcategory":"Leather Goods",
            "type":"Manufacturing & Wholesale Goods"
        }
    ],
    "sg:phone":"+33 1 64 01 00 34",
    "sg:postcode":"77160",
    "sg:province":"Ile de France",
    "sg:tags":[
        "shoe"
    ],
    "wof:name":"Delgrange Sa",
    "wof:placetype":"venue"
},
  "geometry": {"coordinates":[3.247915,48.657814],"type":"Point"}
}