{
  "type": "Feature",
  "properties": {
    "addr:full":"10, Rue Laennec, 29900 Concarneau Concarneau Bretagne 29900",
    "addr:housenumber":"10",
    "addr:postcode":"29900;29900",
    "addr:street":"Rue Laennec",
    "iso:country":"FR",
    "sg:address":"10, Rue Laennec, 29900 Concarneau",
    "sg:city":"Concarneau",
    "sg:orig_category":"Non-Classified Establishments",
    "sg:phone":"+33 2 98 60 40 06",
    "sg:postcode":"29900",
    "sg:province":"Bretagne",
    "wof:name":"B.l.b. Habitat S.a.r.l.",
    "wof:placetype":"venue"
},
  "geometry": {"coordinates":[-3.920004,47.870789],"type":"Point"}
}