{
  "type": "Feature",
  "properties": {
    "addr:full":"Rue Tobias Simmer Illkirch Graffenstaden Alsace 67400",
    "addr:postcode":"67400",
    "addr:street":"Rue Tobias Simmer Illkirch Graffenstaden",
    "iso:country":"FR",
    "sg:address":"Rue Tobias Simmer",
    "sg:city":"Illkirch Graffenstaden",
    "sg:orig_category":"Non-Classified Establishments",
    "sg:phone":"+33 3 90 40 58 00",
    "sg:postcode":"67400",
    "sg:province":"Alsace",
    "wof:name":"Entomed S.a.",
    "wof:placetype":"venue"
},
  "geometry": {"coordinates":[7.74433,48.521488],"type":"Point"}
}