{
  "type": "Feature",
  "properties": {
    "addr:full":"Balot 33410 Monprimblanc Monprimblanc Aquitaine 33410",
    "addr:postcode":"33410;33410",
    "addr:street":"Balot",
    "iso:country":"FR",
    "sg:address":"Balot 33410 Monprimblanc",
    "sg:city":"Monprimblanc",
    "sg:orig_category":"Unclassifiable Establishments",
    "sg:phone":"+33 5 56 62 98 96",
    "sg:postcode":"33410",
    "sg:province":"Aquitaine",
    "wof:name":"Yvan R\u00e9glat Et Fils Vins S.a.r.l.",
    "wof:placetype":"venue"
},
  "geometry": {"coordinates":[-0.264613,44.626892],"type":"Point"}
}