{
  "type": "Feature",
  "properties": {
    "iso:country":"FR",
    "sg:address":"Imp Du Teinchurier BP 228 19108 Brive La Gaillarde Cedex",
    "sg:city":"Gaillard",
    "sg:classifiers":[
        {
            "category":"Manufacturing",
            "subcategory":"Metals",
            "type":"Manufacturing & Wholesale Goods"
        }
    ],
    "sg:phone":"+33 5 55 86 01 01",
    "sg:postcode":"74240",
    "sg:province":"Rhone-Alpes",
    "sg:tags":[
        "metallurgy",
        "steel",
        "metalworking"
    ],
    "wof:name":"Limoujoux Brive",
    "wof:placetype":"venue"
},
  "geometry": {"coordinates":[1.48169,45.147606],"type":"Point"}
}