{
  "type": "Feature",
  "properties": {
    "addr:full":"B.P. 5, 59932 La Chapelle d'Armenti\u00e8res C\u00e9dex^^64, Rue L\u00e9on Beauchamp, 59930 La Chapelle d'Armenti\u00e8r Nord Pas-de-Calais 59930",
    "addr:housenumber":"5",
    "addr:postcode":"59932;59930;59930",
    "addr:street":"B.P.;Rue Le\u0301On Beauchamp;Pas-De-Calais",
    "iso:country":"FR",
    "sg:address":"B.P. 5, 59932 La Chapelle d'Armenti\u00e8res C\u00e9dex^^64, Rue L\u00e9on Beauchamp, 59930 La Chapelle d'Armenti\u00e8r",
    "sg:orig_category":"Non-Classified Establishments",
    "sg:phone":"+33 3 20 48 42 42",
    "sg:postcode":"59930",
    "sg:province":"Nord Pas-de-Calais",
    "wof:name":"C.a.f. Grains Et Compagnie Sa.",
    "wof:placetype":"venue"
},
  "geometry": {"coordinates":[2.884455,50.677677],"type":"Point"}
}