{
  "type": "Feature",
  "properties": {
    "iso:country":"FR",
    "sg:address":"40, Rue Robert Desnos, 76290 Montivilliers",
    "sg:orig_category":"Unclassifiable Establishments",
    "sg:phone":"+33 2 35 30 38 02",
    "sg:province":"Haute Normandie",
    "wof:name":"B.e.i.v. S.a.r.l. - Bureau D'etudes Industrielles Et Verri\u00e8res",
    "wof:placetype":"venue"
},
  "geometry": {"coordinates":[0.175943,49.543991],"type":"Point"}
}