{
  "type": "Feature",
  "properties": {
    "addr:full":"Rte de Grasse - ZI La Festre Sud Saint C\u00e9zaire sur Siagne Provence-Alpes-C\u00f4te d'Azur 06530",
    "addr:postcode":"06530",
    "addr:street":"Rte De Grasse Zi La Festre Sud Saint Ce\u0301Zaire Sur Siagne",
    "iso:country":"FR",
    "sg:address":"Rte de Grasse - ZI La Festre Sud",
    "sg:city":"Saint C\u00e9zaire sur Siagne",
    "sg:orig_category":"Unclassifiable Establishments",
    "sg:phone":"+33 4 93 60 84 44",
    "sg:postcode":"06530",
    "sg:province":"Provence-Alpes-C\u00f4te d'Azur",
    "wof:name":"Aromatech S.a.",
    "wof:placetype":"venue"
},
  "geometry": {"coordinates":[6.85967,43.644451],"type":"Point"}
}