{
  "type": "Feature",
  "properties": {
    "addr:full":"Rue Jules Guesde Du Bas Pontet 69360 St Symphorien D'Ozon Rhone-Alpes 69360",
    "addr:postcode":"69360;69360",
    "addr:street":"Rue Jules Guesde Du Bas;Rhone-Alpes",
    "iso:country":"FR",
    "sg:address":"Rue Jules Guesde",
    "sg:city":"Du Bas Pontet 69360 St Symphorien D'Ozon",
    "sg:classifiers":[
        {
            "category":"Shopping",
            "type":"Retail Goods"
        }
    ],
    "sg:phone":"+33 4 78 02 92 93",
    "sg:postcode":"69360",
    "sg:province":"Rhone-Alpes",
    "sg:tags":[
        "metallurgy",
        "finished",
        "-",
        "metalworking",
        "metallic"
    ],
    "wof:name":"Merlin Tcm",
    "wof:placetype":"venue"
},
  "geometry": {"coordinates":[-101.20152299999999,30.710594],"type":"Point"}
}