{
  "type": "Feature",
  "properties": {
    "addr:full":"rue du Meunynck 59640 Dunkerque Midi Pyr\u00e9n\u00e9es",
    "addr:postcode":"59640",
    "addr:street":"Rue Du Meunynck",
    "iso:country":"FR",
    "sg:address":"rue du Meunynck 59640 Dunkerque",
    "sg:classifiers":[
        {
            "category":"Banks & Credit Unions",
            "subcategory":"Investment Brokerage",
            "type":"Services"
        }
    ],
    "sg:phone":"+33 3 28 60 20 02",
    "sg:province":"Midi Pyr\u00e9n\u00e9es",
    "sg:tags":[
        "packaging",
        "equipment",
        "machinery",
        "maintenance",
        "servicing"
    ],
    "wof:name":"Nempon Mimeca S.a.",
    "wof:placetype":"venue"
},
  "geometry": {"coordinates":[2.347115,51.00489],"type":"Point"}
}