{
  "type": "Feature",
  "properties": {
    "addr:full":"B.P. 33, 42406 Saint Chamond C\u00e9dex^^16, Rue Galli\u00e9ni, 42400 Saint Chamond Rhone-Alpes 42400",
    "addr:postcode":"42406;42400;42400",
    "addr:street":"B.P. 33;Chamond;Rue Gallie\u0301Ni;Chamond Rhone-Alpes",
    "iso:country":"FR",
    "sg:address":"B.P. 33, 42406 Saint Chamond C\u00e9dex^^16, Rue Galli\u00e9ni, 42400 Saint Chamond",
    "sg:orig_category":"Non-Classified Establishments",
    "sg:phone":"+33 4 77 31 20 01",
    "sg:postcode":"42400",
    "sg:province":"Rhone-Alpes",
    "wof:name":"C.s.b. S.a.r.l. - Constructions Sp\u00e9ciales A. Barillets",
    "wof:placetype":"venue"
},
  "geometry": {"coordinates":[4.502065,45.459641],"type":"Point"}
}