{
  "type": "Feature",
  "properties": {
    "iso:country":"FR",
    "sg:address":"Chem De La Gare 72130 Fresnay Sur Sarthe",
    "sg:orig_category":"Agriculture and Livestock Cereals and grains Games and entertainment Horticulture Metallurgy and Met",
    "sg:phone":"+33 2 43 97 21 10",
    "sg:postcode":"72130",
    "sg:province":"Pays de Loire",
    "wof:name":"Union Set",
    "wof:placetype":"venue"
},
  "geometry": {"coordinates":[0.029351,48.280525],"type":"Point"}
}