{
  "type": "Feature",
  "properties": {
    "iso:country":"FR",
    "sg:address":"16 Rue Condorcet 95150 Taverny",
    "sg:classifiers":[
        {
            "category":"Professional",
            "subcategory":"Engineering",
            "type":"Services"
        }
    ],
    "sg:phone":"+33 1 39 95 96 96",
    "sg:postcode":"95150",
    "sg:province":"Ile de France",
    "sg:tags":[
        "machine",
        "-",
        "mechanical"
    ],
    "wof:name":"Etudes Et Realisations Industrielles Sa",
    "wof:placetype":"venue"
},
  "geometry": {"coordinates":[2.18832,49.028011],"type":"Point"}
}