{
  "type": "Feature",
  "properties": {
    "iso:country":"FR",
    "sg:address":"2 Bis Avenue Le Corbeiller 92190 Meudon",
    "sg:classifiers":[
        {
            "category":"Banks & Credit Unions",
            "subcategory":"Financial Services",
            "type":"Services"
        }
    ],
    "sg:phone":"+33 1 41 14 29 92",
    "sg:postcode":"92190",
    "sg:province":"Ile de France",
    "sg:tags":[
        "banking",
        "finance",
        "insurance"
    ],
    "wof:name":"Brisse Poustis Gorbin Vachon Clus",
    "wof:placetype":"venue"
},
  "geometry": {"coordinates":[2.241027,48.813477],"type":"Point"}
}