{
  "type": "Feature",
  "properties": {
    "addr:full":"10 Rue Andr\u00e9 Amp\u00e8re 57150 Creutzwald Lorraine 57150",
    "addr:housenumber":"10",
    "addr:postcode":"57150;57150",
    "addr:street":"Rue Andre\u0301 Ampe\u0300Re",
    "iso:country":"FR",
    "sg:address":"10 Rue Andr\u00e9 Amp\u00e8re 57150 Creutzwald",
    "sg:classifiers":[
        {
            "category":"Wholesale",
            "subcategory":"Meat",
            "type":"Manufacturing & Wholesale Goods"
        }
    ],
    "sg:phone":"+33 3 87 29 30 40",
    "sg:postcode":"57150",
    "sg:province":"Lorraine",
    "sg:tags":[
        "food",
        "cooked",
        "product",
        "related"
    ],
    "wof:name":"Braun Charculor Sa",
    "wof:placetype":"venue"
},
  "geometry": {"coordinates":[6.710076,49.195881],"type":"Point"}
}