{
  "type": "Feature",
  "properties": {
    "addr:full":"B.P. 346, 94503 Champigny sur Marne C\u00e9dex^^107, Av. du G\u00e9n\u00e9ral Leclerc, 94500 Champigny sur Marne Ile de France",
    "addr:housenumber":"b.p. 346",
    "addr:postcode":"94503;94500;france",
    "addr:street":"Av. Du Ge\u0301Ne\u0301Ral Leclerc",
    "iso:country":"FR",
    "sg:address":"B.P. 346, 94503 Champigny sur Marne C\u00e9dex^^107, Av. du G\u00e9n\u00e9ral Leclerc, 94500 Champigny sur Marne",
    "sg:orig_category":"Non-Classified Establishments",
    "sg:phone":"+33 1 48 82 27 77",
    "sg:province":"Ile de France",
    "wof:name":"Fabory Ile De France S.a.",
    "wof:placetype":"venue"
},
  "geometry": {"coordinates":[2.51158,48.813404],"type":"Point"}
}