{
  "type": "Feature",
  "properties": {
    "addr:full":"37-68 cours de la Martinique 33000 Bordeaux Bordeaux Aquitaine 33000",
    "addr:housenumber":"37-68",
    "addr:postcode":"33000;33000",
    "addr:street":"Cours De La Martinique",
    "iso:country":"FR",
    "sg:address":"37-68 cours de la Martinique 33000 Bordeaux",
    "sg:city":"Bordeaux",
    "sg:classifiers":[
        {
            "category":"Wholesale",
            "subcategory":"Books, Periodicals, & Newspapers",
            "type":"Manufacturing & Wholesale Goods"
        }
    ],
    "sg:phone":"+33 5 56 79 10 55",
    "sg:postcode":"33000",
    "sg:province":"Aquitaine",
    "sg:tags":[
        "professional",
        "journal",
        "journals",
        "publisher"
    ],
    "wof:name":"Soci\u00e9t\u00e9 D' Edition Pr\u00e9ventique Sarl",
    "wof:placetype":"venue"
},
  "geometry": {"coordinates":[-0.570957,44.853886],"type":"Point"}
}