{
  "type": "Feature",
  "properties": {
    "iso:country":"FR",
    "sg:address":"3 Impasse Minerva 91100 Corbeil Essonnes",
    "sg:classifiers":[
        {
            "category":"Manufacturing",
            "subcategory":"Rubber & Plastics",
            "type":"Manufacturing & Wholesale Goods"
        }
    ],
    "sg:phone":"+33 1 64 96 21 04",
    "sg:province":"Ile de France",
    "wof:name":"Trace Lettres Minerva",
    "wof:placetype":"venue"
},
  "geometry": {"coordinates":[2.469446,48.6031],"type":"Point"}
}