{
  "type": "Feature",
  "properties": {
    "addr:full":"813 Rte De Vernes Zi 74370 Pringy Rhone-Alpes 74370",
    "addr:housenumber":"813",
    "addr:postcode":"74370;74370",
    "addr:street":"Rte De Vernes Zi",
    "iso:country":"FR",
    "sg:address":"813 Rte De Vernes Zi 74370 Pringy",
    "sg:classifiers":[
        {
            "category":"Manufacturing",
            "subcategory":"Metals",
            "type":"Manufacturing & Wholesale Goods"
        }
    ],
    "sg:phone":"+33 4 50 27 24 62",
    "sg:postcode":"74370",
    "sg:province":"Rhone-Alpes",
    "sg:tags":[
        "-",
        "machine",
        "equipment",
        "engineering",
        "machinery",
        "mechanical"
    ],
    "wof:name":"Alpal Sarl",
    "wof:placetype":"venue"
},
  "geometry": {"coordinates":[6.109395,45.934166],"type":"Point"}
}