{
  "type": "Feature",
  "properties": {
    "iso:country":"FR",
    "sg:address":"rue des Fus\u00e9es 77390 Champdeuil",
    "sg:classifiers":[
        {
            "category":"Wholesale",
            "subcategory":"Tobacco Products",
            "type":"Manufacturing & Wholesale Goods"
        }
    ],
    "sg:phone":"+33 1 64 14 18 00",
    "sg:province":"Ile de France",
    "sg:tags":[
        "raw",
        "waste"
    ],
    "wof:name":"Ourry Sa",
    "wof:placetype":"venue"
},
  "geometry": {"coordinates":[2.726041,48.622097],"type":"Point"}
}