{
  "type": "Feature",
  "properties": {
    "iso:country":"FR",
    "sg:address":"21, Av. Villermont, 06000 Nice",
    "sg:city":"Vill\u00e9",
    "sg:orig_category":"Non-Classified Establishments",
    "sg:phone":"+33 4 93 85 30 09",
    "sg:postcode":"67220",
    "sg:province":"Alsace",
    "wof:name":"Cash Alimentaire Du Sud -est S.a.r.l.",
    "wof:placetype":"venue"
},
  "geometry": {"coordinates":[7.264418,43.709389],"type":"Point"}
}