{
  "type": "Feature",
  "properties": {
    "iso:country":"FR",
    "sg:address":"La Garenne 22110 Rostrenen",
    "sg:city":"Rostrenen",
    "sg:classifiers":[
        {
            "category":"Wholesale",
            "subcategory":"Farm Supplies",
            "type":"Manufacturing & Wholesale Goods"
        }
    ],
    "sg:phone":"+33 2 96 29 02 81",
    "sg:postcode":"22110",
    "sg:province":"Bretagne",
    "sg:tags":[
        "-",
        "machine",
        "equipment",
        "engineering",
        "machinery",
        "mechanical",
        "agriculture"
    ],
    "wof:name":"Matavicol 22 Sas",
    "wof:placetype":"venue"
},
  "geometry": {"coordinates":[-3.303874,48.252331],"type":"Point"}
}