{
  "type": "Feature",
  "properties": {
    "iso:country":"FR",
    "sg:address":"16 Rue Magellan 94370 Sucy En Brie",
    "sg:classifiers":[
        {
            "category":"Shopping",
            "subcategory":"Shoes",
            "type":"Retail Goods"
        }
    ],
    "sg:phone":"+33 1 49 82 95 10",
    "sg:postcode":"94370",
    "sg:province":"Ile de France",
    "sg:tags":[
        "leather",
        "machine",
        "engineering",
        "-",
        "mechanical"
    ],
    "wof:name":"Daude-scovill Sa",
    "wof:placetype":"venue"
},
  "geometry": {"coordinates":[2.503597,48.772663],"type":"Point"}
}