{
  "type": "Feature",
  "properties": {
    "addr:full":"16 Av Morane Saulnier 78941 V\u00e9lizy Cedex Picardie",
    "addr:postcode":"78941",
    "addr:street":"16 Av Morane Saulnier",
    "iso:country":"FR",
    "sg:address":"16 Av Morane Saulnier 78941 V\u00e9lizy Cedex",
    "sg:classifiers":[
        {
            "category":"Professional",
            "subcategory":"Computer Services",
            "type":"Services"
        }
    ],
    "sg:phone":"+33 1 39 26 01 01",
    "sg:province":"Picardie",
    "sg:tags":[
        "information",
        "technology"
    ],
    "wof:name":"Tandberg Data Sa",
    "wof:placetype":"venue"
},
  "geometry": {"coordinates":[-97.15870700000001,29.78508],"type":"Point"}
}