{
  "type": "Feature",
  "properties": {
    "addr:full":"ZAC de la Baudini\u00e8re Thouar\u00e9 sur Loire Pays de Loire 44470",
    "addr:postcode":"44470",
    "addr:street":"Zac De La Baudinie\u0300Re Thouare\u0301;Loire",
    "iso:country":"FR",
    "sg:address":"ZAC de la Baudini\u00e8re",
    "sg:city":"Thouar\u00e9 sur Loire",
    "sg:orig_category":"Unclassifiable Establishments",
    "sg:phone":"+33 2 40 68 01 72",
    "sg:postcode":"44470",
    "sg:province":"Pays de Loire",
    "wof:name":"Graphy Oc\u00e9ane S.a.",
    "wof:placetype":"venue"
},
  "geometry": {"coordinates":[-1.440899,47.266781],"type":"Point"}
}