{
  "type": "Feature",
  "properties": {
    "addr:full":"15 Rue Jules Verne 63100 Clermont Ferrand Clermont-Ferrand Auvergne 63100",
    "addr:housenumber":"15",
    "addr:postcode":"63100;63100",
    "addr:street":"Rue Jules Verne",
    "iso:country":"FR",
    "sg:address":"15 Rue Jules Verne 63100 Clermont Ferrand",
    "sg:city":"Clermont-Ferrand",
    "sg:classifiers":[
        {
            "category":"Shopping Center",
            "type":"Public Place"
        }
    ],
    "sg:phone":"+33 4 73 91 10 78",
    "sg:postcode":"63100",
    "sg:province":"Auvergne",
    "sg:tags":[
        "product",
        "meat",
        "cooked",
        "frozen",
        "related",
        "food"
    ],
    "wof:name":"Krill",
    "wof:placetype":"venue"
},
  "geometry": {"coordinates":[3.129782,45.783417],"type":"Point"}
}