{
  "type": "Feature",
  "properties": {
    "iso:country":"FR",
    "sg:address":"1 R Pierre M\u00e9tairie 78120 Rambouillet",
    "sg:classifiers":[
        {
            "category":"Manufacturing",
            "subcategory":"Metals",
            "type":"Manufacturing & Wholesale Goods"
        }
    ],
    "sg:phone":"+33 1 30 59 25 91",
    "sg:postcode":"78120",
    "sg:province":"Ile de France",
    "sg:tags":[
        "metallurgy",
        "steel",
        "metalworking"
    ],
    "wof:name":"Plessis (entreprise) Eurl",
    "wof:placetype":"venue"
},
  "geometry": {"coordinates":[1.826723,48.622723],"type":"Point"}
}