{
  "type": "Feature",
  "properties": {
    "iso:country":"FR",
    "sg:address":"B.P. 28, 10121 Saint Andr\u00e9 les Vergers C\u00e9dex^^143, Av. d'Echenilly, 10120 Saint Andr\u00e9 les Vergers",
    "sg:orig_category":"Non-Classified Establishments",
    "sg:phone":"+33 3 25 49 42 32",
    "sg:province":"Champagne",
    "wof:name":"S.a.b.a. S.a.r.l. - Soci\u00e9t\u00e9 D'application B\u00e9tons De L'aube",
    "wof:placetype":"venue"
},
  "geometry": {"coordinates":[4.00822,48.245281],"type":"Point"}
}