{
  "type": "Feature",
  "properties": {
    "addr:full":"B.P. 62, 36200 Argenton sur Creuse C\u00e9dex^^Rte de Vaux, 36200 Argenton sur Creuse Argenton-sur-Creuse Centre 36200",
    "addr:postcode":"36200;36200;36200",
    "addr:street":"B.P. 62;Vaux",
    "iso:country":"FR",
    "sg:address":"B.P. 62, 36200 Argenton sur Creuse C\u00e9dex^^Rte de Vaux, 36200 Argenton sur Creuse",
    "sg:city":"Argenton-sur-Creuse",
    "sg:orig_category":"Non-Classified Establishments",
    "sg:phone":"+33 2 54 24 12 98",
    "sg:postcode":"36200",
    "sg:province":"Centre",
    "wof:name":"Allignet Fr\u00e8res S.a.r.l.",
    "wof:placetype":"venue"
},
  "geometry": {"coordinates":[1.561745,46.516987],"type":"Point"}
}