{
  "type": "Feature",
  "properties": {
    "addr:full":"11 Rue De L'Helv\u00e9tie BP 72039 25112 Baume Les Dames Cedex Nord Pas-de-Calais",
    "addr:housenumber":"11",
    "addr:postcode":"25112",
    "addr:street":"Rue De L'Helve \u0301Tie Bp 72039",
    "iso:country":"FR",
    "sg:address":"11 Rue De L'Helv\u00e9tie BP 72039 25112 Baume Les Dames Cedex",
    "sg:classifiers":[
        {
            "category":"Professional",
            "subcategory":"Business Services",
            "type":"Services"
        }
    ],
    "sg:phone":"+33 3 81 84 15 88",
    "sg:province":"Nord Pas-de-Calais",
    "sg:tags":[
        "training",
        "advice"
    ],
    "wof:name":"College Rene Cassin",
    "wof:placetype":"venue"
},
  "geometry": {"coordinates":[6.352018,47.351505],"type":"Point"}
}