{
  "type": "Feature",
  "properties": {
    "addr:full":"12 Rue Emile Zola 10000 Troyes Champagne 10000",
    "addr:housenumber":"12",
    "addr:postcode":"10000;10000",
    "addr:street":"Rue Emile Zola",
    "iso:country":"FR",
    "sg:address":"12 Rue Emile Zola 10000 Troyes",
    "sg:classifiers":[
        {
            "category":"Wholesale",
            "subcategory":"Medical Equipment & Supplies",
            "type":"Manufacturing & Wholesale Goods"
        }
    ],
    "sg:phone":"+33 3 25 76 10 10",
    "sg:postcode":"10000",
    "sg:province":"Champagne",
    "sg:tags":[
        "instrument",
        "health",
        "-",
        "precision"
    ],
    "wof:name":"Neut Sa",
    "wof:placetype":"venue"
},
  "geometry": {"coordinates":[4.076439,48.297512],"type":"Point"}
}