{
  "type": "Feature",
  "properties": {
    "iso:country":"FR",
    "sg:address":"23, Av. Franklin Roosevelt, 75008 Paris",
    "sg:orig_category":"Non-Classified Establishments",
    "sg:phone":"+33 1 56 88 22 40",
    "sg:postcode":"75008",
    "sg:province":"Ile de France",
    "wof:name":"A.m.c. Promotion S.a. - Auto Moto Cycle Promotion",
    "wof:placetype":"venue"
},
  "geometry": {"coordinates":[2.309893,48.866863],"type":"Point"}
}