{
  "type": "Feature",
  "properties": {
    "iso:country":"FR",
    "sg:address":"Chemin De La Pierre Grise 91630 Marolles En Hurepoix",
    "sg:classifiers":[
        {
            "category":"Wholesale",
            "subcategory":"Machinery & Supplies",
            "type":"Manufacturing & Wholesale Goods"
        }
    ],
    "sg:phone":"+33 1 64 56 17 88",
    "sg:postcode":"91630",
    "sg:province":"Ile de France",
    "sg:tags":[
        "handling",
        "material",
        "-",
        "machine",
        "equipment",
        "engineering",
        "mechanical"
    ],
    "wof:name":"Societe Technique De Montage Europeen (stme)",
    "wof:placetype":"venue"
},
  "geometry": {"coordinates":[2.289198,48.568165],"type":"Point"}
}