{
  "type": "Feature",
  "properties": {
    "iso:country":"FR",
    "sg:address":"46-48 Av Des Fenots 28100 Dreux",
    "sg:city":"Dreux",
    "sg:classifiers":[
        {
            "category":"Professional",
            "subcategory":"Engineering",
            "type":"Services"
        }
    ],
    "sg:phone":"+33 2 37 38 07 00",
    "sg:postcode":"28100",
    "sg:province":"Centre",
    "sg:tags":[
        "machine",
        "-",
        "mechanical"
    ],
    "wof:name":"Abb Iti",
    "wof:placetype":"venue"
},
  "geometry": {"coordinates":[1.346696,48.740829],"type":"Point"}
}