{
  "type": "Feature",
  "properties": {
    "addr:full":"22, Rue du 134\u00e8me RI, 71000 M\u00e2con Sanc\u00e9 Bourgogne 71000",
    "addr:housenumber":"22",
    "addr:postcode":"71000;71000",
    "addr:street":"Rue Du 134E\u0300Me",
    "iso:country":"FR",
    "sg:address":"22, Rue du 134\u00e8me RI, 71000 M\u00e2con",
    "sg:city":"Sanc\u00e9",
    "sg:orig_category":"Unclassifiable Establishments",
    "sg:phone":"+33 3 85 32 82 32",
    "sg:postcode":"71000",
    "sg:province":"Bourgogne",
    "wof:name":"Macon Imprimerie S.a.s.",
    "wof:placetype":"venue"
},
  "geometry": {"coordinates":[4.807743,46.285755],"type":"Point"}
}