{
  "type": "Feature",
  "properties": {
    "addr:full":"2 Rue De La Claie 49070 Beaucouz\u00e9 Pays de Loire 49070",
    "addr:housenumber":"2",
    "addr:postcode":"49070;49070",
    "addr:street":"Rue De La Claie",
    "iso:country":"FR",
    "sg:address":"2 Rue De La Claie 49070 Beaucouz\u00e9",
    "sg:classifiers":[
        {
            "category":"Wholesale",
            "subcategory":"Machinery & Supplies",
            "type":"Manufacturing & Wholesale Goods"
        }
    ],
    "sg:phone":"+33 2 41 73 35 05",
    "sg:postcode":"49070",
    "sg:province":"Pays de Loire",
    "sg:tags":[
        "food",
        "processing",
        "-",
        "machine",
        "equipment",
        "engineering",
        "mechanical"
    ],
    "wof:name":"Tca Industrie Sarl",
    "wof:placetype":"venue"
},
  "geometry": {"coordinates":[-0.627475,47.460793],"type":"Point"}
}