{
  "type": "Feature",
  "properties": {
    "addr:full":"18, Rue Raymond Lef\u00e8vre, 94200 Ivry sur Seine Ile de France",
    "addr:housenumber":"18",
    "addr:postcode":"94200",
    "addr:street":"Rue Raymond Lefe\u0300Vre",
    "iso:country":"FR",
    "sg:address":"18, Rue Raymond Lef\u00e8vre, 94200 Ivry sur Seine",
    "sg:orig_category":"Unclassifiable Establishments",
    "sg:phone":"+33 1 45 15 61 40",
    "sg:province":"Ile de France",
    "wof:name":"Sifa S.a.s. - Soci\u00e9t\u00e9 Industrielle Fran\u00e7aise Alimentaire",
    "wof:placetype":"venue"
},
  "geometry": {"coordinates":[2.368538,48.807774],"type":"Point"}
}