{
  "type": "Feature",
  "properties": {
    "addr:full":"B.P. 25, 08001 Charleville M\u00e9zi\u00e8res C\u00e9dex^^6, Rue Camille Didier - Zone Industrielle Mohon, 08000 Ch Charleville-M\u00e9zi\u00e8res Champagne 08000",
    "addr:postcode":"08001;08000;08000",
    "addr:street":"B.P. 25;Rue Camille Didier Zone Industrielle",
    "iso:country":"FR",
    "sg:address":"B.P. 25, 08001 Charleville M\u00e9zi\u00e8res C\u00e9dex^^6, Rue Camille Didier - Zone Industrielle Mohon, 08000 Ch",
    "sg:city":"Charleville-M\u00e9zi\u00e8res",
    "sg:orig_category":"Non-Classified Establishments",
    "sg:phone":"+33 3 24 57 17 43",
    "sg:postcode":"08000",
    "sg:province":"Champagne",
    "wof:name":"Bernard Et Compagnie S.a.",
    "wof:placetype":"venue"
},
  "geometry": {"coordinates":[4.7174,49.758801],"type":"Point"}
}