{
  "type": "Feature",
  "properties": {
    "addr:full":"Les Tours 69460 Saint Etienne la Varenne Rhone-Alpes 69460",
    "addr:housenumber":"69460",
    "addr:postcode":"69460",
    "iso:country":"FR",
    "sg:address":"Les Tours 69460 Saint Etienne la Varenne",
    "sg:orig_category":"Unclassifiable Establishments",
    "sg:phone":"+33 4 74 03 40 86",
    "sg:postcode":"69460",
    "sg:province":"Rhone-Alpes",
    "wof:name":"Domaine Tours",
    "wof:placetype":"venue"
},
  "geometry": {"coordinates":[4.635157,46.077145],"type":"Point"}
}