{
  "type": "Feature",
  "properties": {
    "iso:country":"FR",
    "sg:address":"19 Rue Thomas Edison Zi La Peyrinie 12000 Rodez",
    "sg:classifiers":[
        {
            "category":"Autos & Motor Vehicles",
            "subcategory":"Boat Sales",
            "type":"Retail Goods"
        }
    ],
    "sg:phone":"+33 5 65 42 61 11",
    "sg:postcode":"12000",
    "sg:province":"Midi Pyr\u00e9n\u00e9es",
    "sg:tags":[
        "equipment",
        "transport"
    ],
    "wof:name":"Sats",
    "wof:placetype":"venue"
},
  "geometry": {"coordinates":[2.57289,44.349735],"type":"Point"}
}