{
  "type": "Feature",
  "properties": {
    "iso:country":"FR",
    "sg:address":"14, Rue Nationale, 91670 Angerville",
    "sg:orig_category":"Non-Classified Establishments",
    "sg:phone":"+33 1 64 95 34 45",
    "sg:postcode":"91670",
    "sg:province":"Ile de France",
    "wof:name":"B.i.c.s.",
    "wof:placetype":"venue"
},
  "geometry": {"coordinates":[1.999057,48.312618],"type":"Point"}
}