{
  "type": "Feature",
  "properties": {
    "addr:full":"Av Denis Sem\u00e9ria Gare St Roch 06300 Nice Provence-Alpes-C\u00f4te d'Azur",
    "addr:postcode":"06300",
    "addr:street":"Av Denis Seme\u0301Ria Gare",
    "iso:country":"FR",
    "sg:address":"Av Denis Sem\u00e9ria Gare St Roch 06300 Nice",
    "sg:classifiers":[
        {
            "category":"Professional",
            "type":"Services"
        }
    ],
    "sg:phone":"+33 4 92 00 17 20",
    "sg:province":"Provence-Alpes-C\u00f4te d'Azur",
    "sg:tags":[
        "transport",
        "road"
    ],
    "wof:name":"Xt",
    "wof:placetype":"venue"
},
  "geometry": {"coordinates":[7.291057,43.709461],"type":"Point"}
}