{
  "type": "Feature",
  "properties": {
    "addr:full":"Lieu-Dit Grand Chemin 45470 LOURY Loury Centre 45470",
    "addr:housenumber":"loury",
    "addr:postcode":"45470;45470",
    "addr:street":"Lieu-Dit Grand Chemin",
    "iso:country":"FR",
    "sg:address":"Lieu-Dit Grand Chemin 45470 LOURY",
    "sg:city":"Loury",
    "sg:classifiers":[
        {
            "category":"Manufacturing",
            "subcategory":"Lumber",
            "type":"Manufacturing & Wholesale Goods"
        }
    ],
    "sg:phone":"+33 2 38 65 60 29",
    "sg:postcode":"45470",
    "sg:province":"Centre",
    "sg:tags":[
        "hardwood",
        "sawmill"
    ],
    "wof:name":"Etablissements Pillette Et Fils Sa",
    "wof:placetype":"venue"
},
  "geometry": {"coordinates":[2.10121,47.975922],"type":"Point"}
}