{
  "type": "Feature",
  "properties": {
    "addr:full":"173 R Des R\u00e9sistants 65300 Lannemezan Midi Pyr\u00e9n\u00e9es 65300",
    "addr:housenumber":"173",
    "addr:postcode":"65300;65300",
    "addr:street":"R Des Re\u0301Sistants",
    "iso:country":"FR",
    "sg:address":"173 R Des R\u00e9sistants 65300 Lannemezan",
    "sg:classifiers":[
        {
            "category":"Building & Trades",
            "subcategory":"Construction",
            "type":"Services"
        }
    ],
    "sg:phone":"+33 5 62 98 05 75",
    "sg:postcode":"65300",
    "sg:province":"Midi Pyr\u00e9n\u00e9es",
    "sg:tags":[
        "work",
        "transport",
        "public",
        "road"
    ],
    "wof:name":"Stpl Travaux Publics",
    "wof:placetype":"venue"
},
  "geometry": {"coordinates":[0.385535,43.111923],"type":"Point"}
}