{
  "type": "Feature",
  "properties": {
    "iso:country":"FR",
    "sg:address":"Cite Du Cambresis 59151 Arleux",
    "sg:classifiers":[
        {
            "category":"Manufacturing",
            "subcategory":"Chemicals & Compounds",
            "type":"Manufacturing & Wholesale Goods"
        }
    ],
    "sg:phone":"+33 3 27 89 33 27",
    "sg:postcode":"59151",
    "sg:province":"Nord Pas-de-Calais",
    "sg:tags":[
        "pharmaceutical",
        "energy",
        "chemistry",
        "-",
        "by-product"
    ],
    "wof:name":"Totalgaz Centre Emplisseur Snc",
    "wof:placetype":"venue"
},
  "geometry": {"coordinates":[3.11741,50.294006],"type":"Point"}
}