{
  "type": "Feature",
  "properties": {
    "iso:country":"FR",
    "sg:address":"Base De Plein Air Rue De Savoie 27740 Poses",
    "sg:classifiers":[
        {
            "category":"Sports & Exercise",
            "subcategory":"Sports Center",
            "type":"Entertainment"
        }
    ],
    "sg:phone":"+33 2 32 59 13 13",
    "sg:postcode":"27740",
    "sg:province":"Haute Normandie",
    "sg:tags":[
        "game"
    ],
    "wof:name":"Association Des Etangs Des 2 Amants",
    "wof:placetype":"venue"
},
  "geometry": {"coordinates":[1.23844,49.307251],"type":"Point"}
}