{
  "type": "Feature",
  "properties": {
    "iso:country":"FR",
    "sg:address":"B.P. 27, 84320 Entraigues sur la Sorgue^^354, Rte d'Avignon, 84320 Entraigues sur la Sorgue",
    "sg:orig_category":"Non-Classified Establishments",
    "sg:phone":"+33 4 90 83 16 41",
    "sg:province":"Provence-Alpes-C\u00f4te d'Azur",
    "wof:name":"G\u00e9cebel Publicit\u00e9 S.a.r.l.",
    "wof:placetype":"venue"
},
  "geometry": {"coordinates":[4.919942,43.999863],"type":"Point"}
}