{
  "type": "Feature",
  "properties": {
    "addr:full":"ZI sud plastics Vall\u00e9e 01100 Bellignat Rhone-Alpes 01100",
    "addr:postcode":"01100;01100",
    "addr:street":"Valle\u0301E;Rhone-Alpes",
    "iso:country":"FR",
    "sg:address":"ZI sud plastics Vall\u00e9e 01100 Bellignat",
    "sg:classifiers":[
        {
            "category":"Bars & Pubs",
            "type":"Food & Drink"
        }
    ],
    "sg:phone":"+33 4 74 73 81 72",
    "sg:postcode":"01100",
    "sg:province":"Rhone-Alpes",
    "sg:tags":[
        "natural",
        "colourings",
        "artificial"
    ],
    "wof:name":"Elian Sas",
    "wof:placetype":"venue"
},
  "geometry": {"coordinates":[5.62927,46.242184],"type":"Point"}
}