{
  "type": "Feature",
  "properties": {
    "iso:country":"FR",
    "sg:address":"23 Rue D Estienne D Orves 92130 Issy Les Moulineaux",
    "sg:classifiers":[
        {
            "category":"Manufacturing",
            "subcategory":"Rubber & Plastics",
            "type":"Manufacturing & Wholesale Goods"
        }
    ],
    "sg:phone":"+33 1 46 42 74 62",
    "sg:province":"Ile de France",
    "wof:name":"Ste Auxiliaire De Fabrication D'articles En Caoutchouc Safac",
    "wof:placetype":"venue"
},
  "geometry": {"coordinates":[2.26637,48.823647],"type":"Point"}
}