{
  "type": "Feature",
  "properties": {
    "iso:country":"FR",
    "sg:address":"97 Rue Scierie 42600 Champdieu",
    "sg:classifiers":[
        {
            "category":"Shopping",
            "subcategory":"Clothing, Apparel, & Fashions",
            "type":"Retail Goods"
        }
    ],
    "sg:phone":"+33 4 77 97 00 97",
    "sg:postcode":"42600",
    "sg:province":"Rhone-Alpes",
    "sg:tags":[
        "textile",
        "clothing",
        "clothes"
    ],
    "wof:name":"Julien Productions",
    "wof:placetype":"venue"
},
  "geometry": {"coordinates":[4.050411,45.645447],"type":"Point"}
}