{
  "type": "Feature",
  "properties": {
    "iso:country":"FR",
    "sg:address":"Frm St Georges Les Jardins 68190 Ensisheim",
    "sg:city":"Ensisheim",
    "sg:classifiers":[
        {
            "category":"Farming",
            "subcategory":"Livestock Farm",
            "type":"Manufacturing & Wholesale Goods"
        }
    ],
    "sg:phone":"+33 3 89 57 66 29",
    "sg:postcode":"68190",
    "sg:province":"Alsace",
    "sg:tags":[
        "breeding",
        "agriculture",
        "animal"
    ],
    "wof:name":"Elevage De Porcs Georgenfeld Sarl",
    "wof:placetype":"venue"
},
  "geometry": {"coordinates":[7.354325,47.865231],"type":"Point"}
}