{
  "type": "Feature",
  "properties": {
    "addr:full":"B.P. 7325, 69357 Lyons la For\u00eat C\u00e9dex 7^^259, Rue Marcel M\u00e9rieux, 69350 Lyons la For\u00eat Rhone-Alpes 69350",
    "addr:housenumber":"7325;7 ^ ^ 259",
    "addr:postcode":"69357;69350;69350",
    "addr:street":"B.P.;Ce\u0301Dex;Rue Marcel Me\u0301Rieux;Rhone-Alpes",
    "iso:country":"FR",
    "sg:address":"B.P. 7325, 69357 Lyons la For\u00eat C\u00e9dex 7^^259, Rue Marcel M\u00e9rieux, 69350 Lyons la For\u00eat",
    "sg:orig_category":"Non-Classified Establishments",
    "sg:phone":"+33 4 72 71 23 83",
    "sg:postcode":"69350",
    "sg:province":"Rhone-Alpes",
    "wof:name":"Rex-rotary S.a.",
    "wof:placetype":"venue"
},
  "geometry": {"coordinates":[4.816185,45.726791],"type":"Point"}
}