{
  "type": "Feature",
  "properties": {
    "addr:full":"41, Rte d'Aulnay, 91180 Saint Germain l\u00e8s Arpajon Ile de France",
    "addr:housenumber":"41",
    "addr:postcode":"91180",
    "addr:street":"Rte D'Aulnay",
    "iso:country":"FR",
    "sg:address":"41, Rte d'Aulnay, 91180 Saint Germain l\u00e8s Arpajon",
    "sg:orig_category":"Non-Classified Establishments",
    "sg:phone":"+33 1 60 84 03 27",
    "sg:province":"Ile de France",
    "wof:name":"France Ponte Inovo S.a.",
    "wof:placetype":"venue"
},
  "geometry": {"coordinates":[2.26499,48.598129],"type":"Point"}
}