{
  "type": "Feature",
  "properties": {
    "addr:full":"26 Rue Merigonde 81100 Castres Midi Pyr\u00e9n\u00e9es 81100",
    "addr:housenumber":"26",
    "addr:postcode":"81100;81100",
    "addr:street":"Rue Merigonde",
    "iso:country":"FR",
    "sg:address":"26 Rue Merigonde 81100 Castres",
    "sg:classifiers":[
        {
            "category":"Wholesale",
            "subcategory":"Machinery & Supplies",
            "type":"Manufacturing & Wholesale Goods"
        }
    ],
    "sg:phone":"+33 5 63 62 60 00",
    "sg:postcode":"81100",
    "sg:province":"Midi Pyr\u00e9n\u00e9es",
    "sg:tags":[
        "handling",
        "material",
        "-",
        "machine",
        "equipment",
        "engineering",
        "mechanical"
    ],
    "wof:name":"Pierre Benne Sa",
    "wof:placetype":"venue"
},
  "geometry": {"coordinates":[2.253666,43.602776],"type":"Point"}
}