{
  "type": "Feature",
  "properties": {
    "iso:country":"FR",
    "sg:address":"B.P. 22, 62400 B\u00e9thune^^Rue Franklin Roosevelt, 62400 B\u00e9thune",
    "sg:orig_category":"Non-Classified Establishments",
    "sg:phone":"+33 3 21 68 12 60",
    "sg:province":"Nord Pas-de-Calais",
    "wof:name":"S.m.a.g. De Broutelles S.a.",
    "wof:placetype":"venue"
},
  "geometry": {"coordinates":[2.63787,50.530472],"type":"Point"}
}