{
  "type": "Feature",
  "properties": {
    "addr:full":"102 Rue Roger Salengro 59157 Fontaine Au Pire Nord Pas-de-Calais 59157",
    "addr:housenumber":"102",
    "addr:postcode":"59157;59157",
    "addr:street":"Rue Roger Salengro;Au Pire Nord",
    "iso:country":"FR",
    "sg:address":"102 Rue Roger Salengro 59157 Fontaine Au Pire",
    "sg:classifiers":[
        {
            "category":"Professional",
            "subcategory":"Engineering",
            "type":"Services"
        }
    ],
    "sg:phone":"+33 3 27 85 07 57",
    "sg:postcode":"59157",
    "sg:province":"Nord Pas-de-Calais",
    "sg:tags":[
        "machine",
        "-",
        "mechanical"
    ],
    "wof:name":"Bracq (ets Pierre) Sa",
    "wof:placetype":"venue"
},
  "geometry": {"coordinates":[3.389512,50.12899],"type":"Point"}
}