{
  "type": "Feature",
  "properties": {
    "iso:country":"FR",
    "sg:address":"67 Rue Fernand Combette 93100 Montreuil",
    "sg:classifiers":[
        {
            "category":"Wholesale",
            "subcategory":"Machinery & Supplies",
            "type":"Manufacturing & Wholesale Goods"
        }
    ],
    "sg:phone":"+33 1 42 87 70 69",
    "sg:postcode":"93100",
    "sg:province":"Ile de France",
    "sg:tags":[
        "handling",
        "material",
        "-",
        "machine",
        "equipment",
        "engineering",
        "mechanical"
    ],
    "wof:name":"Societe D Exploitation Des Procedes Mecaniques (sepm)",
    "wof:placetype":"venue"
},
  "geometry": {"coordinates":[2.45264,48.873489],"type":"Point"}
}