{
  "type": "Feature",
  "properties": {
    "iso:country":"FR",
    "sg:address":"2791, Chemin Saint Bernard - Parc les Moulins, 06220 Vallauris",
    "sg:orig_category":"Unclassifiable Establishments",
    "sg:phone":"+33 4 97 21 31 38",
    "sg:province":"Provence-Alpes-C\u00f4te d'Azur",
    "wof:name":"E.r.i. S.a.r.l. - Etudes Et R\u00e9alisations Industrielles",
    "wof:placetype":"venue"
},
  "geometry": {"coordinates":[7.0601,43.600765],"type":"Point"}
}