{
  "type": "Feature",
  "properties": {
    "iso:country":"FR",
    "sg:address":"32 rue Gambetta 59243 ONNAING",
    "sg:orig_category":"Glass-Fibre Reinforced Plastic Grp Sandwich Panels",
    "sg:phone":"+33 3 27 23 90 25",
    "sg:postcode":"59243",
    "sg:province":"Nord Pas-de-Calais",
    "wof:name":"Pab Nord S.a.",
    "wof:placetype":"venue"
},
  "geometry": {"coordinates":[3.599332,50.391022],"type":"Point"}
}