{
  "type": "Feature",
  "properties": {
    "addr:full":"457, Rue Issanchou, 82000 Montauban Midi Pyr\u00e9n\u00e9es",
    "addr:housenumber":"457",
    "addr:postcode":"82000",
    "addr:street":"Rue Issanchou",
    "iso:country":"FR",
    "sg:address":"457, Rue Issanchou, 82000 Montauban",
    "sg:orig_category":"Unclassifiable Establishments",
    "sg:phone":"+33 5 63 66 41 00",
    "sg:province":"Midi Pyr\u00e9n\u00e9es",
    "wof:name":"Albafruit S.a.r.l.",
    "wof:placetype":"venue"
},
  "geometry": {"coordinates":[1.349121,44.02869],"type":"Point"}
}