{
  "type": "Feature",
  "properties": {
    "addr:full":"6, Rue Fran\u00e7ois Sommer, 92167 Antony C\u00e9dex \u00cele-de-France",
    "addr:housenumber":"6",
    "addr:postcode":"92167",
    "addr:street":"Rue Franc\u0327Ois Sommer;Ce\u0301Dex",
    "iso:country":"FR",
    "sg:address":"6, Rue Fran\u00e7ois Sommer, 92167 Antony C\u00e9dex",
    "sg:orig_category":"Non-Classified Establishments",
    "sg:phone":"+33 1 46 68 05 05",
    "sg:province":"\u00cele-de-France",
    "wof:name":"Locat S.a.",
    "wof:placetype":"venue"
},
  "geometry": {"coordinates":[2.3083,48.73378],"type":"Point"}
}