{
  "type": "Feature",
  "properties": {
    "iso:country":"FR",
    "sg:address":"B.P. 66, 44141 Ch\u00e2teaubriant C\u00e9dex^^Rte de Saint Nazaire - ZI, 44140 Ch\u00e2teaubriant",
    "sg:orig_category":"Non-Classified Establishments",
    "sg:phone":"+33 2 40 81 24 72",
    "sg:postcode":"44140",
    "sg:province":"Pays de Loire",
    "wof:name":"Castel Carrosserie S.a.",
    "wof:placetype":"venue"
},
  "geometry": {"coordinates":[-1.426909,47.009285],"type":"Point"}
}