{
  "type": "Feature",
  "properties": {
    "iso:country":"FR",
    "sg:address":"9, Rue des Artisans - ZA, 61250 Cond\u00e9 sur Sarthe",
    "sg:city":"Colombiers",
    "sg:orig_category":"Non-Classified Establishments",
    "sg:phone":"+33 2 33 82 31 41",
    "sg:postcode":"61250",
    "sg:province":"Basse Normandie",
    "wof:name":"B.e.c.b. S.n.c.",
    "wof:placetype":"venue"
},
  "geometry": {"coordinates":[-0.052958,48.380058],"type":"Point"}
}