{
  "type": "Feature",
  "properties": {
    "addr:full":"13, Rte Industrielle de la Hardt, 67120 Molsheim Molsheim Alsace 67120",
    "addr:housenumber":"13",
    "addr:postcode":"67120;67120",
    "addr:street":"Rte Industrielle De La Hardt",
    "iso:country":"FR",
    "sg:address":"13, Rte Industrielle de la Hardt, 67120 Molsheim",
    "sg:city":"Molsheim",
    "sg:orig_category":"Non-Classified Establishments",
    "sg:phone":"+33 3 88 48 57 57",
    "sg:postcode":"67120",
    "sg:province":"Alsace",
    "wof:name":"Vogel & Noot France S.a.r.l.",
    "wof:placetype":"venue"
},
  "geometry": {"coordinates":[7.510742,48.538307],"type":"Point"}
}