{
  "type": "Feature",
  "properties": {
    "addr:full":"Za La Bruyere 61260 Le Theil Le Theil Basse Normandie 61260",
    "addr:housenumber":"theil",
    "addr:postcode":"61260;61260",
    "addr:street":"Za La Bruyere;Theil Basse",
    "iso:country":"FR",
    "sg:address":"Za La Bruyere 61260 Le Theil",
    "sg:city":"Le Theil",
    "sg:classifiers":[
        {
            "category":"Home & Garden",
            "subcategory":"Furniture",
            "type":"Retail Goods"
        }
    ],
    "sg:phone":"+33 2 37 53 55 20",
    "sg:postcode":"61260",
    "sg:province":"Basse Normandie",
    "sg:tags":[
        "household",
        "wood"
    ],
    "wof:name":"Msv Sa",
    "wof:placetype":"venue"
},
  "geometry": {"coordinates":[0.687183,48.26384],"type":"Point"}
}