{
  "type": "Feature",
  "properties": {
    "iso:country":"FR",
    "sg:address":"Zi La Chevalerie 50000 St Lo",
    "sg:city":"Saint-L\u00f4",
    "sg:classifiers":[
        {
            "category":"Utilities",
            "subcategory":"Electric",
            "type":"Services"
        }
    ],
    "sg:phone":"+33 2 33 77 84 00",
    "sg:postcode":"50000",
    "sg:province":"Basse Normandie",
    "sg:tags":[
        "electricity",
        "electronic",
        "electrical",
        "equipment"
    ],
    "wof:name":"Axians Masselin Communications",
    "wof:placetype":"venue"
},
  "geometry": {"coordinates":[-1.090344,49.115974],"type":"Point"}
}