{
  "type": "Feature",
  "properties": {
    "addr:full":"7, Rue des Trois Obus, 08700 Nouzonville Gespunsart Champagne 08700",
    "addr:housenumber":"7",
    "addr:postcode":"08700;08700",
    "addr:street":"Rue Des Trois Obus;Champagne",
    "iso:country":"FR",
    "sg:address":"7, Rue des Trois Obus, 08700 Nouzonville",
    "sg:city":"Gespunsart",
    "sg:orig_category":"Unclassifiable Establishments",
    "sg:phone":"+33 3 24 53 37 26",
    "sg:postcode":"08700",
    "sg:province":"Champagne",
    "wof:name":"Warsmann S.a.",
    "wof:placetype":"venue"
},
  "geometry": {"coordinates":[4.73744,49.813351],"type":"Point"}
}