{
  "type": "Feature",
  "properties": {
    "addr:full":"16 Cours Mirabeau; Aix en Provence; 13100 Nord Pas-de-Calais",
    "addr:housenumber":"16;13100",
    "addr:street":"Cours Mirabeau",
    "iso:country":"FR",
    "sg:address":"16 Cours Mirabeau; Aix en Provence; 13100",
    "sg:classifiers":[
        {
            "category":"Banks & Credit Unions",
            "subcategory":"Bank",
            "type":"Services"
        }
    ],
    "sg:phone":"+33 3342933640",
    "sg:province":"Nord Pas-de-Calais",
    "wof:name":"Soci\u00e9t\u00e9 G\u00e9n\u00e9rale",
    "wof:placetype":"venue"
},
  "geometry": {"coordinates":[5.447918,43.526398],"type":"Point"}
}