{
  "type": "Feature",
  "properties": {
    "addr:full":"44, Grande Rue, 78480 Verneuil sur Seine Ile de France",
    "addr:housenumber":"44",
    "addr:postcode":"78480",
    "addr:street":"Grande Rue",
    "iso:country":"FR",
    "sg:address":"44, Grande Rue, 78480 Verneuil sur Seine",
    "sg:orig_category":"Non-Classified Establishments",
    "sg:phone":"+33 1 39 65 79 79",
    "sg:province":"Ile de France",
    "wof:name":"S.c.d.l. S.a.r.l. - Soci\u00e9t\u00e9 De Conception Et De Diffusion De Logiciels",
    "wof:placetype":"venue"
},
  "geometry": {"coordinates":[1.977842,48.97971],"type":"Point"}
}