{
  "type": "Feature",
  "properties": {
    "addr:full":"44, Rue Desjoyaux, 42000 Saint Etienne Rhone-Alpes 42000",
    "addr:housenumber":"44",
    "addr:postcode":"42000;42000",
    "addr:street":"Rue Desjoyaux",
    "iso:country":"FR",
    "sg:address":"44, Rue Desjoyaux, 42000 Saint Etienne",
    "sg:orig_category":"Non-Classified Establishments",
    "sg:phone":"+33 4 77 33 72 45",
    "sg:postcode":"42000",
    "sg:province":"Rhone-Alpes",
    "wof:name":"D\u00e9coupe St\u00e9phanoise S.a.r.l.",
    "wof:placetype":"venue"
},
  "geometry": {"coordinates":[4.392842,45.44593],"type":"Point"}
}