{
  "type": "Feature",
  "properties": {
    "iso:country":"FR",
    "sg:address":"30 B, Saint Georges, 37210 Rochecorbon",
    "sg:city":"Rochecorbon",
    "sg:orig_category":"Non-Classified Establishments",
    "sg:phone":"+33 2 47 52 50 72",
    "sg:postcode":"37210",
    "sg:province":"Centre",
    "wof:name":"Villain Claude",
    "wof:placetype":"venue"
},
  "geometry": {"coordinates":[0.736222,47.408356],"type":"Point"}
}