{
  "type": "Feature",
  "properties": {
    "iso:country":"FR",
    "sg:address":"192, Rue de Tolbiac, 75013 Paris",
    "sg:orig_category":"Non-Classified Establishments",
    "sg:phone":"+33 1 45 89 18 12",
    "sg:province":"Ile de France",
    "wof:name":"Maison Schott S.a.r.l.",
    "wof:placetype":"venue"
},
  "geometry": {"coordinates":[2.349145,48.825893],"type":"Point"}
}