{
  "type": "Feature",
  "properties": {
    "iso:country":"FR",
    "sg:address":"140 avenue Jean Jaur\u00e8s 26200 MONTELIMAR",
    "sg:classifiers":[
        {
            "category":"Food & Beverages",
            "subcategory":"Chocolate",
            "type":"Retail Goods"
        }
    ],
    "sg:phone":"+33 4 75 01 55 55",
    "sg:postcode":"26200",
    "sg:province":"Rhone-Alpes",
    "wof:name":"Nougat Gerbe D'or S.a.",
    "wof:placetype":"venue"
},
  "geometry": {"coordinates":[4.746433,44.542217],"type":"Point"}
}