{
  "type": "Feature",
  "properties": {
    "addr:full":"4, Rue Dugay Trouin, 44800 Saint Herblain Pays de Loire",
    "addr:housenumber":"4",
    "addr:postcode":"44800",
    "addr:street":"Rue Dugay Trouin;Herblain",
    "iso:country":"FR",
    "sg:address":"4, Rue Dugay Trouin, 44800 Saint Herblain",
    "sg:orig_category":"Non-Classified Establishments",
    "sg:phone":"+33 2 40 92 92 92",
    "sg:province":"Pays de Loire",
    "wof:name":"Sonovision Itep S.a.",
    "wof:placetype":"venue"
},
  "geometry": {"coordinates":[-1.620089,47.223534],"type":"Point"}
}