{
  "type": "Feature",
  "properties": {
    "iso:country":"FR",
    "sg:address":"Rte Sainte Alv\u00e8re",
    "sg:city":"Creysse",
    "sg:orig_category":"Non-Classified Establishments",
    "sg:phone":"+33 5 53 23 27 63",
    "sg:postcode":"24100",
    "sg:province":"Aquitaine",
    "wof:name":"Helg\u00e9 Beaut\u00e9 S.a.r.l.",
    "wof:placetype":"venue"
},
  "geometry": {"coordinates":[0.540515,44.860382],"type":"Point"}
}