{
  "type": "Feature",
  "properties": {
    "addr:full":"14 Rue Claire Pauilhac 31000 Toulouse Midi Pyr\u00e9n\u00e9es 31000",
    "addr:housenumber":"14",
    "addr:postcode":"31000;31000",
    "addr:street":"Rue Claire",
    "iso:country":"FR",
    "sg:address":"14 Rue Claire Pauilhac 31000 Toulouse",
    "sg:classifiers":[
        {
            "category":"Professional",
            "subcategory":"Business Services",
            "type":"Services"
        }
    ],
    "sg:phone":"+33 5 61 62 35 37",
    "sg:postcode":"31000",
    "sg:province":"Midi Pyr\u00e9n\u00e9es",
    "sg:tags":[
        "training",
        "advice"
    ],
    "wof:name":"Iseg Toulouse",
    "wof:placetype":"venue"
},
  "geometry": {"coordinates":[1.44516,43.611073],"type":"Point"}
}