{
  "type": "Feature",
  "properties": {
    "addr:full":"Za Sauvy 01510 Virieu Le Grand Rhone-Alpes 01510",
    "addr:postcode":"01510;01510",
    "addr:street":"Za Sauvy;Grand Rhone-Alpes",
    "iso:country":"FR",
    "sg:address":"Za Sauvy 01510 Virieu Le Grand",
    "sg:classifiers":[
        {
            "category":"Professional",
            "subcategory":"Engineering",
            "type":"Services"
        }
    ],
    "sg:phone":"+33 4 79 87 80 08",
    "sg:postcode":"01510",
    "sg:province":"Rhone-Alpes",
    "sg:tags":[
        "machine",
        "-",
        "mechanical"
    ],
    "wof:name":"Landot Industrie Sa",
    "wof:placetype":"venue"
},
  "geometry": {"coordinates":[5.649133,45.848362],"type":"Point"}
}