{
  "type": "Feature",
  "properties": {
    "addr:full":"222rue Du 12 Sep 1944 88300 Neufch\u00e2teau Lorraine 88300",
    "addr:housenumber":"1944",
    "addr:postcode":"88300;88300",
    "addr:street":"Du 12",
    "iso:country":"FR",
    "sg:address":"222rue Du 12 Sep 1944 88300 Neufch\u00e2teau",
    "sg:classifiers":[
        {
            "category":"Home & Garden",
            "subcategory":"Furniture",
            "type":"Retail Goods"
        }
    ],
    "sg:phone":"+33 3 29 94 07 26",
    "sg:postcode":"88300",
    "sg:province":"Lorraine",
    "sg:tags":[
        "household",
        "wood"
    ],
    "wof:name":"Ets Jacques Rague Sa",
    "wof:placetype":"venue"
},
  "geometry": {"coordinates":[5.680708,48.350868],"type":"Point"}
}