{
  "type": "Feature",
  "properties": {
    "iso:country":"FR",
    "sg:address":"5, Rue des Garennes, 78440 Gargenville",
    "sg:orig_category":"Unclassifiable Establishments",
    "sg:phone":"+33 1 34 97 36 36",
    "sg:province":"Ile de France",
    "wof:name":"E.i.t.e.m. S.a.r.l. - Entreprise Industrielle Tuyauterie Electro-m\u00e9canique",
    "wof:placetype":"venue"
},
  "geometry": {"coordinates":[1.805555,48.976398],"type":"Point"}
}