{
  "type": "Feature",
  "properties": {
    "addr:full":"1 All Gay Lussac 69230 St Genis Laval Rhone-Alpes 69230",
    "addr:housenumber":"1",
    "addr:postcode":"69230;69230",
    "addr:street":"All Gay Lussac;Genis;Rhone-Alpes",
    "iso:country":"FR",
    "sg:address":"1 All Gay Lussac 69230 St Genis Laval",
    "sg:classifiers":[
        {
            "category":"Building & Trades",
            "subcategory":"Construction",
            "type":"Services"
        }
    ],
    "sg:phone":"+33 4 72 39 90 33",
    "sg:postcode":"69230",
    "sg:province":"Rhone-Alpes",
    "sg:tags":[
        "work",
        "public"
    ],
    "wof:name":"Duc Et Preneuf",
    "wof:placetype":"venue"
},
  "geometry": {"coordinates":[4.767171,45.698112],"type":"Point"}
}