{
  "type": "Feature",
  "properties": {
    "iso:country":"FR",
    "sg:address":"1 All Gay Lussac 69230 St Genis Laval",
    "sg:classifiers":[
        {
            "category":"Building & Trades",
            "subcategory":"Construction",
            "type":"Services"
        }
    ],
    "sg:phone":"+33 4 72 39 90 33",
    "sg:postcode":"69230",
    "sg:province":"Rhone-Alpes",
    "sg:tags":[
        "work",
        "public"
    ],
    "wof:name":"Duc Et Preneuf",
    "wof:placetype":"venue"
},
  "geometry": {"coordinates":[4.767171,45.698112],"type":"Point"}
}