{
  "type": "Feature",
  "properties": {
    "addr:full":"35 Rue Yerres 91230 Montgeron Ile de France",
    "addr:housenumber":"35",
    "addr:postcode":"91230;ile",
    "addr:street":"Rue Yerres",
    "iso:country":"FR",
    "sg:address":"35 Rue Yerres 91230 Montgeron",
    "sg:classifiers":[
        {
            "category":"Manufacturing",
            "subcategory":"Rubber & Plastics",
            "type":"Manufacturing & Wholesale Goods"
        }
    ],
    "sg:phone":"+33 1 69 03 51 73",
    "sg:province":"Ile de France",
    "wof:name":"Scoro Sarl",
    "wof:placetype":"venue"
},
  "geometry": {"coordinates":[2.468258,48.704014],"type":"Point"}
}