{
  "type": "Feature",
  "properties": {
    "iso:country":"FR",
    "sg:address":"25 Avenue Gabriel Peri 84300 Cavaillon",
    "sg:classifiers":[
        {
            "category":"Manufacturing",
            "subcategory":"Jewelry",
            "type":"Manufacturing & Wholesale Goods"
        }
    ],
    "sg:phone":"+33 4 90 71 12 37",
    "sg:province":"Bretagne",
    "sg:tags":[
        "product",
        "miscellaneous",
        "jewellery"
    ],
    "wof:name":"Offrir",
    "wof:placetype":"venue"
},
  "geometry": {"coordinates":[5.04093,43.835136],"type":"Point"}
}