{
  "type": "Feature",
  "properties": {
    "addr:full":"46 rue Jean Roger; Agde; 34300 Languedoc-Roussillon 34300",
    "addr:housenumber":"46",
    "addr:postcode":"34300;34300",
    "addr:street":"Rue Jean Roger",
    "iso:country":"FR",
    "sg:address":"46 rue Jean Roger; Agde; 34300",
    "sg:classifiers":[
        {
            "category":"Banks & Credit Unions",
            "subcategory":"Bank",
            "type":"Services"
        }
    ],
    "sg:phone":"+33 3367948755",
    "sg:postcode":"34300",
    "sg:province":"Languedoc-Roussillon",
    "wof:name":"Banque Nationale De Paris",
    "wof:placetype":"venue"
},
  "geometry": {"coordinates":[3.469854,43.312618],"type":"Point"}
}