{
  "type": "Feature",
  "properties": {
    "addr:full":"9A, Rue de la Sabli\u00e8re, 92634 Gennevilliers C\u00e9dex Gennevilliers Ile de France 92230",
    "addr:housenumber":"9a",
    "addr:postcode":"92634;92230",
    "addr:street":"Rue De La Sablie\u0300Re",
    "iso:country":"FR",
    "sg:address":"9A, Rue de la Sabli\u00e8re, 92634 Gennevilliers C\u00e9dex",
    "sg:city":"Gennevilliers",
    "sg:orig_category":"Non-Classified Establishments",
    "sg:phone":"+33 1 46 88 40 40",
    "sg:postcode":"92230",
    "sg:province":"Ile de France",
    "wof:name":"Ebizcuss. Com S.a.",
    "wof:placetype":"venue"
},
  "geometry": {"coordinates":[2.30617,48.917343],"type":"Point"}
}