{
  "type": "Feature",
  "properties": {
    "iso:country":"FR",
    "sg:address":"91, Bd Raspail, 75006 Paris",
    "sg:orig_category":"Unclassifiable Establishments",
    "sg:phone":"+33 1 45 49 33 48",
    "sg:province":"Ile de France",
    "wof:name":"B.r.c.s. S.a.r.l. - Brisson Recherches Conseils Services",
    "wof:placetype":"venue"
},
  "geometry": {"coordinates":[2.32842,48.847164],"type":"Point"}
}