{
  "type": "Feature",
  "properties": {
    "addr:full":"Rue de la Jouette Vitry le Fran\u00e7ois Champagne 51300",
    "addr:postcode":"51300",
    "addr:street":"Rue De La Jouette Vitry Le Franc\u0327Ois Champagne",
    "iso:country":"FR",
    "sg:address":"Rue de la Jouette",
    "sg:city":"Vitry le Fran\u00e7ois",
    "sg:orig_category":"Non-Classified Establishments",
    "sg:phone":"+33 3 26 74 19 32",
    "sg:postcode":"51300",
    "sg:province":"Champagne",
    "wof:name":"Devanlay S.a.",
    "wof:placetype":"venue"
},
  "geometry": {"coordinates":[4.602305,48.72501],"type":"Point"}
}