{
  "type": "Feature",
  "properties": {
    "iso:country":"FR",
    "sg:address":"B.P. 3, 45141 Saint Jean de la Ruelle C\u00e9dex^^139, Rue Paul Doumer, 45140 Saint Jean de la Ruelle",
    "sg:city":"Ingr\u00e9",
    "sg:orig_category":"Non-Classified Establishments",
    "sg:phone":"+33 2 38 71 20 21",
    "sg:postcode":"45140",
    "sg:province":"Centre",
    "wof:name":"Soci\u00e9t\u00e9 D'exploitation Bernard Demaison S.a.",
    "wof:placetype":"venue"
},
  "geometry": {"coordinates":[1.862242,47.912434],"type":"Point"}
}