{
  "type": "Feature",
  "properties": {
    "iso:country":"FR",
    "sg:address":"181 Rue D'Argentan 61005 Alen\u00e7on Cedex",
    "sg:city":"Alen\u00e7on",
    "sg:classifiers":[
        {
            "category":"Autos & Motor Vehicles",
            "subcategory":"Automobile Sales",
            "type":"Retail Goods"
        }
    ],
    "sg:phone":"+33 2 33 80 40 00",
    "sg:postcode":"61000",
    "sg:province":"Basse Normandie",
    "sg:tags":[
        "equipment",
        "motor-cars",
        "transport"
    ],
    "wof:name":"Carrier Carrosserie",
    "wof:placetype":"venue"
},
  "geometry": {"coordinates":[0.08575,48.436977],"type":"Point"}
}