{
  "type": "Feature",
  "properties": {
    "addr:full":"18 Rue De La Girafe 14000 Caen Caen Basse Normandie 14000",
    "addr:housenumber":"18",
    "addr:postcode":"14000;14000",
    "addr:street":"Rue De La Girafe",
    "iso:country":"FR",
    "sg:address":"18 Rue De La Girafe 14000 Caen",
    "sg:city":"Caen",
    "sg:classifiers":[
        {
            "category":"Shopping",
            "subcategory":"Hobbies, Toys, & Games",
            "type":"Retail Goods"
        }
    ],
    "sg:phone":"+33 2 31 95 75 88",
    "sg:postcode":"14000",
    "sg:province":"Basse Normandie",
    "sg:tags":[
        "product",
        "breeding",
        "miscellaneous",
        "animal",
        "entertainment"
    ],
    "wof:name":"Herve Sarl",
    "wof:placetype":"venue"
},
  "geometry": {"coordinates":[-0.364716,49.203388],"type":"Point"}
}