{
  "type": "Feature",
  "properties": {
    "iso:country":"FR",
    "sg:address":"B.P. 442, 95005 Cergy C\u00e9dex^^6, Rue de Picardie, 95310 Saint Ouen l'Aum\u00f4ne",
    "sg:orig_category":"Non-Classified Establishments",
    "sg:phone":"+33 1 30 37 72 11",
    "sg:province":"Ile de France",
    "wof:name":"S.e.r.a.g. S.a. - Soci\u00e9t\u00e9 Etudes Et R\u00e9alisations D'arts Graphiques",
    "wof:placetype":"venue"
},
  "geometry": {"coordinates":[2.140032,49.043896],"type":"Point"}
}