{
  "type": "Feature",
  "properties": {
    "iso:country":"FR",
    "sg:address":"ZA les Pignadas",
    "sg:city":"Hasparren",
    "sg:orig_category":"Non-Classified Establishments",
    "sg:phone":"+33 5 59 29 62 39",
    "sg:postcode":"64240",
    "sg:province":"Aquitaine",
    "wof:name":"Darra\u00efdou S.a.r.l.",
    "wof:placetype":"venue"
},
  "geometry": {"coordinates":[-1.305359,43.383945],"type":"Point"}
}