{
  "type": "Feature",
  "properties": {
    "iso:country":"FR",
    "sg:address":"7 Imp Charles Garnier 93400 St Ouen",
    "sg:classifiers":[
        {
            "category":"Shopping",
            "subcategory":"Hobbies, Toys, & Games",
            "type":"Retail Goods"
        }
    ],
    "sg:phone":"+33 1 40 10 89 10",
    "sg:postcode":"93400",
    "sg:province":"Ile de France",
    "sg:tags":[
        "product",
        "miscellaneous",
        "entertainment"
    ],
    "wof:name":"Dalbe Sarl",
    "wof:placetype":"venue"
},
  "geometry": {"coordinates":[2.338956,48.905045],"type":"Point"}
}