{
  "type": "Feature",
  "properties": {
    "iso:country":"FR",
    "sg:address":"14, Bd de la R\u00e9publique, 13100 Aix en Provence",
    "sg:orig_category":"Non-Classified Establishments",
    "sg:phone":"+33 820 33 74 60",
    "sg:province":"Nord Pas-de-Calais",
    "wof:name":"B.p.p.c. - Banque Populaire Proven\u00e7ale Et Corse",
    "wof:placetype":"venue"
},
  "geometry": {"coordinates":[5.444204,43.526989],"type":"Point"}
}