{
  "type": "Feature",
  "properties": {
    "addr:full":"RD 559 La Londe les Maures Provence-Alpes-C\u00f4te d'Azur 83250",
    "addr:postcode":"83250",
    "addr:street":"Rd 559 La Londe Les Maures",
    "iso:country":"FR",
    "sg:address":"RD 559",
    "sg:city":"La Londe les Maures",
    "sg:orig_category":"Unclassifiable Establishments",
    "sg:phone":"+33 4 94 05 17 87",
    "sg:postcode":"83250",
    "sg:province":"Provence-Alpes-C\u00f4te d'Azur",
    "wof:name":"P\u00e9pini\u00e8res Jean Rey S.a.",
    "wof:placetype":"venue"
},
  "geometry": {"coordinates":[6.23746,43.138893],"type":"Point"}
}