{
  "type": "Feature",
  "properties": {
    "addr:full":"B.P. 149, 59760 Grande Synthe^^Place F Mitterand, 59760 Grande Synthe Nord Pas-de-Calais",
    "addr:housenumber":"b.p. 149",
    "addr:postcode":"59760;59760",
    "addr:street":"F Mitterand",
    "iso:country":"FR",
    "sg:address":"B.P. 149, 59760 Grande Synthe^^Place F Mitterand, 59760 Grande Synthe",
    "sg:orig_category":"Non-Classified Establishments",
    "sg:phone":"+33 3 28 62 77 00",
    "sg:province":"Nord Pas-de-Calais",
    "wof:name":"Mairie De Grande Synthe",
    "wof:placetype":"venue"
},
  "geometry": {"coordinates":[2.30272,51.013069],"type":"Point"}
}