{
  "type": "Feature",
  "properties": {
    "addr:full":"26, Rue des Ardennes, 38230 Tignieu Jameyzieu Rhone-Alpes 38230",
    "addr:housenumber":"26",
    "addr:postcode":"38230;38230",
    "addr:street":"Rue Des Ardennes;Rhone-Alpes",
    "iso:country":"FR",
    "sg:address":"26, Rue des Ardennes, 38230 Tignieu Jameyzieu",
    "sg:orig_category":"Non-Classified Establishments",
    "sg:phone":"+33 4 78 32 25 22",
    "sg:postcode":"38230",
    "sg:province":"Rhone-Alpes",
    "wof:name":"C.m.a.t. S.a.r.l. - Constructions M\u00e9caniques Des Ardennes De Tignieu",
    "wof:placetype":"venue"
},
  "geometry": {"coordinates":[5.182433,45.746342],"type":"Point"}
}