{
  "type": "Feature",
  "properties": {
    "iso:country":"FR",
    "sg:address":"P.A. de l'Orne",
    "sg:city":"Andr\u00e9zieux Bouth\u00e9on",
    "sg:orig_category":"Unclassifiable Establishments",
    "sg:phone":"+33 4 77 55 58 88",
    "sg:postcode":"42160",
    "sg:province":"Rhone-Alpes",
    "wof:name":"Imprimerie J. Haubtmann S.a.",
    "wof:placetype":"venue"
},
  "geometry": {"coordinates":[4.203219,45.529629],"type":"Point"}
}