{
  "type": "Feature",
  "properties": {
    "iso:country":"FR",
    "sg:address":"Zi De L'Arsenal 17300 Rochefort",
    "sg:classifiers":[
        {
            "category":"Autos & Motor Vehicles",
            "subcategory":"Boat Sales",
            "type":"Retail Goods"
        }
    ],
    "sg:phone":"+33 5 46 87 29 39",
    "sg:postcode":"17300",
    "sg:province":"Poitou-Charentes",
    "sg:tags":[
        "equipment",
        "transport"
    ],
    "wof:name":"Zodiac International Sa",
    "wof:placetype":"venue"
},
  "geometry": {"coordinates":[-0.958379,45.935261],"type":"Point"}
}