{
  "type": "Feature",
  "properties": {
    "addr:full":"Rte de Quinquis Lech - ZI Keriel Landerneau Bretagne 29800",
    "addr:postcode":"29800",
    "addr:street":"Rte De Quinquis Lech Zi Keriel Landerneau Bretagne",
    "iso:country":"FR",
    "sg:address":"Rte de Quinquis Lech - ZI Keriel",
    "sg:city":"Landerneau",
    "sg:orig_category":"Unclassifiable Establishments",
    "sg:phone":"+33 2 98 20 96 96",
    "sg:postcode":"29800",
    "sg:province":"Bretagne",
    "wof:name":"Etablissements Joncqueur S.a.",
    "wof:placetype":"venue"
},
  "geometry": {"coordinates":[-4.228497,48.400295],"type":"Point"}
}