{
  "type": "Feature",
  "properties": {
    "iso:country":"FR",
    "sg:address":"B.P. 2069",
    "sg:city":"Vitrolles C\u00e9dex 9",
    "sg:orig_category":"Non-Classified Establishments",
    "sg:phone":"+33 4 42 77 49 10",
    "sg:postcode":"13841",
    "sg:province":"Centre",
    "wof:name":"Alpha Isolation S.a.",
    "wof:placetype":"venue"
},
  "geometry": {"coordinates":[5.24853,43.46043],"type":"Point"}
}