{
  "type": "Feature",
  "properties": {
    "iso:country":"FR",
    "sg:address":"Pa Le Pommier Chem De Noyelles 62256 Henin-Beaumont",
    "sg:classifiers":[
        {
            "category":"Autos & Motor Vehicles",
            "subcategory":"Automobile Sales",
            "type":"Retail Goods"
        }
    ],
    "sg:phone":"+33 3 21 79 62 29",
    "sg:province":"Franche Comt\u00e9",
    "sg:tags":[
        "equipment",
        "motor-cars",
        "transport"
    ],
    "wof:name":"Faurecia Industries",
    "wof:placetype":"venue"
},
  "geometry": {"coordinates":[3.341874,45.313515],"type":"Point"}
}