{
  "type": "Feature",
  "properties": {
    "addr:full":"11, Rue Alfred Kastler - Rue Alfred Kastler , 76137 Mont Saint Aignan C\u00e9dex Aignan Midi Pyr\u00e9n\u00e9es 32290",
    "addr:housenumber":"11",
    "addr:postcode":"76137;ce\u0301dex;pyre\u0301ne\u0301es 32290",
    "addr:street":"Rue Alfred;Rue Alfred Kastler",
    "iso:country":"FR",
    "sg:address":"11, Rue Alfred Kastler - Rue Alfred Kastler , 76137 Mont Saint Aignan C\u00e9dex",
    "sg:city":"Aignan",
    "sg:orig_category":"Non-Classified Establishments",
    "sg:phone":"+33 2 35 59 21 96",
    "sg:postcode":"32290",
    "sg:province":"Midi Pyr\u00e9n\u00e9es",
    "wof:name":"Desk S.a.",
    "wof:placetype":"venue"
},
  "geometry": {"coordinates":[1.096291,49.47226],"type":"Point"}
}