{
  "type": "Feature",
  "properties": {
    "addr:full":"B.P. 66, 22230 Merdrignac^^Rte d'Illifaut, 22230 Merdrignac Merdrignac Bretagne 22230",
    "addr:postcode":"22230;22230;22230",
    "addr:street":"B.P. 66;D'Illifaut",
    "iso:country":"FR",
    "sg:address":"B.P. 66, 22230 Merdrignac^^Rte d'Illifaut, 22230 Merdrignac",
    "sg:city":"Merdrignac",
    "sg:orig_category":"Non-Classified Establishments",
    "sg:phone":"+33 2 96 28 41 54",
    "sg:postcode":"22230",
    "sg:province":"Bretagne",
    "wof:name":"Imprimerie Le Maire S.a.r.l.",
    "wof:placetype":"venue"
},
  "geometry": {"coordinates":[-2.228816,48.133598],"type":"Point"}
}