{
  "type": "Feature",
  "properties": {
    "addr:full":"Rue Philippe Lebon Alen\u00e7on Basse Normandie 61000",
    "addr:postcode":"61000",
    "addr:street":"Rue Philippe Lebon;Basse",
    "iso:country":"FR",
    "sg:address":"Rue Philippe Lebon",
    "sg:city":"Alen\u00e7on",
    "sg:orig_category":"Unclassifiable Establishments",
    "sg:phone":"+33 2 33 29 30 36",
    "sg:postcode":"61000",
    "sg:province":"Basse Normandie",
    "wof:name":"Agence Atelier Demolin Caen S.a.",
    "wof:placetype":"venue"
},
  "geometry": {"coordinates":[0.082589,48.443417],"type":"Point"}
}