{
  "type": "Feature",
  "properties": {
    "addr:full":"144, Chemin Saint Marc - Le Plan de Grasse, 06130 Grasse Franche Comt\u00e9",
    "addr:housenumber":"144",
    "addr:postcode":"06130",
    "addr:street":"Chemin Saint Marc Le Plan De Grasse;Franche Comte\u0301",
    "iso:country":"FR",
    "sg:address":"144, Chemin Saint Marc - Le Plan de Grasse, 06130 Grasse",
    "sg:orig_category":"Non-Classified Establishments",
    "sg:phone":"+33 4 93 70 49 60",
    "sg:province":"Franche Comt\u00e9",
    "wof:name":"S.m.a. S.a. - Soci\u00e9t\u00e9 M\u00e9diterran\u00e9enne D'a\u00e9rosols",
    "wof:placetype":"venue"
},
  "geometry": {"coordinates":[6.931648,43.649738],"type":"Point"}
}