{
  "type": "Feature",
  "properties": {
    "iso:country":"FR",
    "sg:address":"19, Rue Roger Bacon, 75017 Paris",
    "sg:orig_category":"Unclassifiable Establishments",
    "sg:phone":"+33 1 53 81 79 10",
    "sg:province":"Ile de France",
    "wof:name":"Addform Sa",
    "wof:placetype":"venue"
},
  "geometry": {"coordinates":[2.290232,48.883152],"type":"Point"}
}