{
  "type": "Feature",
  "properties": {
    "addr:full":"B.P. 53, 85111 Chantonnay C\u00e9dex^^Parc Polaris, 85110 Chantonnay Pays de Loire",
    "addr:postcode":"85111;85110",
    "addr:street":"B.P. 53;Polaris",
    "iso:country":"FR",
    "sg:address":"B.P. 53, 85111 Chantonnay C\u00e9dex^^Parc Polaris, 85110 Chantonnay",
    "sg:orig_category":"Non-Classified Establishments",
    "sg:phone":"+33 2 51 94 46 57",
    "sg:province":"Pays de Loire",
    "wof:name":"Garczynski - Traploir S.a.",
    "wof:placetype":"venue"
},
  "geometry": {"coordinates":[-0.963094,46.642857],"type":"Point"}
}