{
  "type": "Feature",
  "properties": {
    "addr:full":"7, Rue des Acacias, 57140 La Maxe Lorraine",
    "addr:housenumber":"7",
    "addr:postcode":"57140",
    "addr:street":"Rue Des Acacias",
    "iso:country":"FR",
    "sg:address":"7, Rue des Acacias, 57140 La Maxe",
    "sg:orig_category":"Unclassifiable Establishments",
    "sg:phone":"+33 3 87 31 77 00",
    "sg:province":"Lorraine",
    "wof:name":"Equitronic - Equipement Electronique De L'est S.a.r.l.",
    "wof:placetype":"venue"
},
  "geometry": {"coordinates":[6.186108,49.154453],"type":"Point"}
}