{
  "type": "Feature",
  "properties": {
    "iso:country":"FR",
    "sg:address":"83, Rte de Lyon, 69960 Corbas",
    "sg:orig_category":"Non-Classified Establishments",
    "sg:phone":"+33 4 72 50 31 82",
    "sg:postcode":"69960",
    "sg:province":"Rhone-Alpes",
    "wof:name":"Thivard Fr\u00e8res S.a.r.l.",
    "wof:placetype":"venue"
},
  "geometry": {"coordinates":[4.89617,45.678322],"type":"Point"}
}