{
  "type": "Feature",
  "properties": {
    "iso:country":"FR",
    "sg:address":"ZA de Charray",
    "sg:city":"V\u00e9zeronce Curtin",
    "sg:orig_category":"Unclassifiable Establishments",
    "sg:phone":"+33 4 74 80 40 22",
    "sg:postcode":"38510",
    "sg:province":"Rhone-Alpes",
    "wof:name":"Acuiplast S.a.r.l.",
    "wof:placetype":"venue"
},
  "geometry": {"coordinates":[5.47057,45.650745],"type":"Point"}
}