{
  "type": "Feature",
  "properties": {
    "iso:country":"FR",
    "sg:address":"Route De Roanne 42840 MONTAGNY",
    "sg:classifiers":[
        {
            "category":"Manufacturing",
            "subcategory":"Paper Products",
            "type":"Manufacturing & Wholesale Goods"
        }
    ],
    "sg:phone":"+33 4 77 66 10 53",
    "sg:postcode":"42840",
    "sg:province":"Rhone-Alpes",
    "sg:tags":[
        "adhesive",
        "self-adhesive",
        "labels",
        "label"
    ],
    "wof:name":"Sextant Etiquettes Sa",
    "wof:placetype":"venue"
},
  "geometry": {"coordinates":[4.23152,46.032902],"type":"Point"}
}