{
  "type": "Feature",
  "properties": {
    "iso:country":"FR",
    "sg:address":"ZI de Ponteau",
    "sg:city":"Lav\u00e9ra",
    "sg:orig_category":"Unclassifiable Establishments",
    "sg:phone":"+33 4 42 07 04 66",
    "sg:postcode":"13117",
    "sg:province":"Provence-Alpes-C\u00f4te d'Azur",
    "wof:name":"So.prov.is.e. S.a.r.l. - Soci\u00e9t\u00e9 Proven\u00e7ale D'isolation Et D'echafaudage",
    "wof:placetype":"venue"
},
  "geometry": {"coordinates":[5.026036,43.388462],"type":"Point"}
}