{
  "type": "Feature",
  "properties": {
    "addr:full":"52, Quai Gaston Boulet, 76000 Rouen Haute Normandie 76000",
    "addr:housenumber":"52",
    "addr:postcode":"76000;76000",
    "addr:street":"Quai Gaston Boulet;Haute Normandie",
    "iso:country":"FR",
    "sg:address":"52, Quai Gaston Boulet, 76000 Rouen",
    "sg:orig_category":"Non-Classified Establishments",
    "sg:phone":"+33 2 32 76 69 60",
    "sg:postcode":"76000",
    "sg:province":"Haute Normandie",
    "wof:name":"Ant\u00e9a S.a.",
    "wof:placetype":"venue"
},
  "geometry": {"coordinates":[1.079474,49.442505],"type":"Point"}
}