{
  "type": "Feature",
  "properties": {
    "iso:country":"FR",
    "sg:address":"52 Rue Jeanne D Arc 94160 St Mande",
    "sg:classifiers":[
        {
            "category":"Manufacturing",
            "subcategory":"Printing",
            "type":"Manufacturing & Wholesale Goods"
        }
    ],
    "sg:phone":"+33 1 43 98 16 31",
    "sg:province":"Ile de France",
    "sg:tags":[
        "publishing"
    ],
    "wof:name":"Sarl New Color Compogravure",
    "wof:placetype":"venue"
},
  "geometry": {"coordinates":[2.420395,48.836517],"type":"Point"}
}