{
  "type": "Feature",
  "properties": {
    "iso:country":"FR",
    "sg:address":"4, Rue Amp\u00e8re, 69680 Chassieu",
    "sg:orig_category":"Non-Classified Establishments",
    "sg:phone":"+33 4 72 47 00 33",
    "sg:postcode":"69680",
    "sg:province":"Rhone-Alpes",
    "wof:name":"Cerruti M.g. S.a.",
    "wof:placetype":"venue"
},
  "geometry": {"coordinates":[4.972698,45.731331],"type":"Point"}
}