{
  "type": "Feature",
  "properties": {
    "iso:country":"FR",
    "sg:address":"Zone des Boitiaux",
    "sg:city":"Libercourt",
    "sg:orig_category":"Unclassifiable Establishments",
    "sg:phone":"+33 3 21 74 27 00",
    "sg:postcode":"62820",
    "sg:province":"Nord Pas-de-Calais",
    "wof:name":"Juan Carrion Transports S.a.r.l.",
    "wof:placetype":"venue"
},
  "geometry": {"coordinates":[3.009885,50.480518],"type":"Point"}
}