{
  "type": "Feature",
  "properties": {
    "addr:full":"179 Rue Du Faubourg St-Antoine 75011 Paris Ile de France 75011",
    "addr:housenumber":"179",
    "addr:postcode":"75011;75011",
    "addr:street":"Rue Du Faubourg St-Antoine",
    "iso:country":"FR",
    "sg:address":"179 Rue Du Faubourg St-Antoine 75011 Paris",
    "sg:classifiers":[
        {
            "category":"Home & Garden",
            "subcategory":"Furniture",
            "type":"Retail Goods"
        }
    ],
    "sg:phone":"+33 1 43 07 24 75",
    "sg:postcode":"75011",
    "sg:province":"Ile de France",
    "sg:tags":[
        "household",
        "wood"
    ],
    "wof:name":"Les Nouveaux Meubles D'art Sarl",
    "wof:placetype":"venue"
},
  "geometry": {"coordinates":[2.380989,48.850571],"type":"Point"}
}