{
  "type": "Feature",
  "properties": {
    "addr:full":"Lieu-Dit Pizay 69220 St Jean d'Ardieres Rhone-Alpes 69220",
    "addr:postcode":"69220;69220",
    "addr:street":"Lieu-Dit Pizay;Rhone-Alpes",
    "iso:country":"FR",
    "sg:address":"Lieu-Dit Pizay 69220 St Jean d'Ardieres",
    "sg:classifiers":[
        {
            "category":"Wholesale",
            "subcategory":"Wine & Distilled Alcoholic Beverages",
            "type":"Manufacturing & Wholesale Goods"
        }
    ],
    "sg:phone":"+33 4 74 06 55 55",
    "sg:postcode":"69220",
    "sg:province":"Rhone-Alpes",
    "sg:tags":[
        "french"
    ],
    "wof:name":"Ste L. Metairie Sa",
    "wof:placetype":"venue"
},
  "geometry": {"coordinates":[4.703907,46.118435],"type":"Point"}
}