{
  "type": "Feature",
  "properties": {
    "iso:country":"FR",
    "sg:address":"71 av Lanessan; Champagne au Mont d'Or",
    "sg:city":"Champagn\u00e9",
    "sg:classifiers":[
        {
            "category":"Banks & Credit Unions",
            "subcategory":"Bank",
            "type":"Services"
        }
    ],
    "sg:phone":"+33 3378474494",
    "sg:postcode":"72470",
    "sg:province":"Pays de Loire",
    "wof:name":"Soci\u00e9t\u00e9 G\u00e9n\u00e9rale",
    "wof:placetype":"venue"
},
  "geometry": {"coordinates":[-0.100754,47.869232],"type":"Point"}
}