{
  "type": "Feature",
  "properties": {
    "iso:country":"FR",
    "sg:address":"7, Rue Notre Dame de Bonne Nouvelle, 75002 Paris",
    "sg:orig_category":"Unclassifiable Establishments",
    "sg:phone":"+33 1 53 00 97 00",
    "sg:province":"Ile de France",
    "wof:name":"Omnium Central S.a.",
    "wof:placetype":"venue"
},
  "geometry": {"coordinates":[2.349617,48.869675],"type":"Point"}
}