{
  "type": "Feature",
  "properties": {
    "addr:full":"43, Bd Lavoisier, 63000 Clermont Ferrand Clermont-Ferrand Auvergne 63000",
    "addr:housenumber":"43",
    "addr:postcode":"63000;63000",
    "addr:street":"Bd Lavoisier",
    "iso:country":"FR",
    "sg:address":"43, Bd Lavoisier, 63000 Clermont Ferrand",
    "sg:city":"Clermont-Ferrand",
    "sg:orig_category":"Unclassifiable Establishments",
    "sg:phone":"+33 4 73 37 59 68",
    "sg:postcode":"63000",
    "sg:province":"Auvergne",
    "wof:name":"Gerin S.a.",
    "wof:placetype":"venue"
},
  "geometry": {"coordinates":[3.080111,45.786148],"type":"Point"}
}