{
  "type": "Feature",
  "properties": {
    "iso:country":"FR",
    "sg:address":"Route De Lavaur 81300 Graulhet",
    "sg:classifiers":[
        {
            "category":"Shopping",
            "subcategory":"Computers & Home Electronics",
            "type":"Retail Goods"
        }
    ],
    "sg:phone":"+33 5 63 42 86 30",
    "sg:postcode":"81300",
    "sg:province":"Midi Pyr\u00e9n\u00e9es",
    "sg:tags":[
        "equipment",
        "household",
        "electrical",
        "appliance",
        "electronic"
    ],
    "wof:name":"Societe Tarnaise D'electronique Et D'electrotechnique",
    "wof:placetype":"venue"
},
  "geometry": {"coordinates":[1.948225,43.754921],"type":"Point"}
}