{
  "type": "Feature",
  "properties": {
    "iso:country":"FR",
    "sg:address":"4 Pl Francheville 24400 P\u00e9rigueux",
    "sg:city":"Les L\u00e8ches",
    "sg:classifiers":[
        {
            "category":"Professional",
            "subcategory":"Business Services",
            "type":"Services"
        }
    ],
    "sg:phone":"+33 5 53 05 37 62",
    "sg:postcode":"24400",
    "sg:province":"Aquitaine",
    "sg:tags":[
        "body",
        "advice"
    ],
    "wof:name":"Assoc Des Eleveurs De Dordogne",
    "wof:placetype":"venue"
},
  "geometry": {"coordinates":[0.426855,44.981491],"type":"Point"}
}