{
  "type": "Feature",
  "properties": {
    "iso:country":"FR",
    "sg:address":"Route Des Gabions 76700 Rogerville",
    "sg:orig_category":"Miscellaneous Products",
    "sg:phone":"+33 2 35 26 20 20",
    "sg:postcode":"76700",
    "sg:province":"Haute Normandie",
    "wof:name":"Extract Ion",
    "wof:placetype":"venue"
},
  "geometry": {"coordinates":[0.256478,49.456985],"type":"Point"}
}