{
  "type": "Feature",
  "properties": {
    "addr:full":"Champgrand Za 26270 Loriol Sur Drome Rhone-Alpes 26270",
    "addr:postcode":"26270;26270",
    "addr:street":"Za",
    "iso:country":"FR",
    "sg:address":"Champgrand Za 26270 Loriol Sur Drome",
    "sg:classifiers":[
        {
            "category":"Food & Beverages",
            "subcategory":"Groceries & Convenience Stores",
            "type":"Retail Goods"
        }
    ],
    "sg:phone":"+33 4 75 85 18 51",
    "sg:postcode":"26270",
    "sg:province":"Rhone-Alpes",
    "sg:tags":[
        "product",
        "related"
    ],
    "wof:name":"Laboratoire D'innovation Vegetale",
    "wof:placetype":"venue"
},
  "geometry": {"coordinates":[4.797704,44.692307],"type":"Point"}
}