{
  "type": "Feature",
  "properties": {
    "addr:full":"B.P. 1701, 73817 Barberaz C\u00e9dex^^10, Av. du Mont Saint Michel, 73000 Barberaz Rhone-Alpes 73000",
    "addr:housenumber":"1701",
    "addr:postcode":"73817;73000;73000",
    "addr:street":"B.P.;Av. Du Mont Saint Michel;Rhone-Alpes",
    "iso:country":"FR",
    "sg:address":"B.P. 1701, 73817 Barberaz C\u00e9dex^^10, Av. du Mont Saint Michel, 73000 Barberaz",
    "sg:orig_category":"Non-Classified Establishments",
    "sg:phone":"+33 4 79 33 35 09",
    "sg:postcode":"73000",
    "sg:province":"Rhone-Alpes",
    "wof:name":"La Maison De Savoie S.a.",
    "wof:placetype":"venue"
},
  "geometry": {"coordinates":[5.90839,45.538151],"type":"Point"}
}