{
  "type": "Feature",
  "properties": {
    "iso:country":"FR",
    "sg:address":"La Noelle 44150 Ancenis",
    "sg:classifiers":[
        {
            "category":"Shopping Center",
            "type":"Public Place"
        }
    ],
    "sg:phone":"+33 2 40 78 28 05",
    "sg:postcode":"44150",
    "sg:province":"Pays de Loire",
    "sg:tags":[
        "product",
        "meat",
        "cooked",
        "frozen",
        "related",
        "food"
    ],
    "wof:name":"Soparvol Industrie Le Bignon (sovipral)",
    "wof:placetype":"venue"
},
  "geometry": {"coordinates":[-1.174325,47.372646],"type":"Point"}
}