{
  "type": "Feature",
  "properties": {
    "addr:full":"Prat Bihan 29810 Ploumoguer Ploumoguer Bretagne 29810",
    "addr:postcode":"29810;29810",
    "addr:street":"Prat Bihan;Ploumoguer",
    "iso:country":"FR",
    "sg:address":"Prat Bihan 29810 Ploumoguer",
    "sg:city":"Ploumoguer",
    "sg:orig_category":"Unclassifiable Establishments",
    "sg:phone":"+33 2 98 89 65 16",
    "sg:postcode":"29810",
    "sg:province":"Bretagne",
    "wof:name":"Gourmelon Le Bars Marie Claire",
    "wof:placetype":"venue"
},
  "geometry": {"coordinates":[-4.736941,48.416553],"type":"Point"}
}