{
  "type": "Feature",
  "properties": {
    "iso:country":"FR",
    "sg:address":"30, Rue G. Boussinecq, 51100 Reims",
    "sg:orig_category":"Unclassifiable Establishments",
    "sg:phone":"+33 3 26 47 12 44",
    "sg:province":"Champagne",
    "wof:name":"B.a.c. S.a.r.l. - Bronze Alliage De Champagne",
    "wof:placetype":"venue"
},
  "geometry": {"coordinates":[4.050268,49.254745],"type":"Point"}
}