{
  "type": "Feature",
  "properties": {
    "iso:country":"FR",
    "sg:address":"B.P. 1453, 26014 Valence C\u00e9dex^^163 - 171, Av. des Aur\u00e9ats, 26000 Valence",
    "sg:orig_category":"Non-Classified Establishments",
    "sg:phone":"+33 4 75 75 27 00",
    "sg:province":"Rhone-Alpes",
    "wof:name":"I.t.w. - Surfaces Et Finitions S.a.s.",
    "wof:placetype":"venue"
},
  "geometry": {"coordinates":[4.889246,44.930458],"type":"Point"}
}