{
  "type": "Feature",
  "properties": {
    "iso:country":"FR",
    "sg:address":"31 rue de la Mairie 35320 Crevin",
    "sg:city":"Cr\u00e9vin",
    "sg:classifiers":[
        {
            "category":"Wholesale",
            "subcategory":"Auto Parts",
            "type":"Manufacturing & Wholesale Goods"
        }
    ],
    "sg:phone":"+33 2 99 42 40 40",
    "sg:postcode":"35320",
    "sg:province":"Bretagne",
    "sg:tags":[
        "spun",
        "metal"
    ],
    "wof:name":"Larcher Sarl",
    "wof:placetype":"venue"
},
  "geometry": {"coordinates":[-1.660511,47.935822],"type":"Point"}
}