{
  "type": "Feature",
  "properties": {
    "iso:country":"FR",
    "sg:address":"B.P. 03, 73460 Notre Dame des Milli\u00e8res^^ZA du Rotey, 73460 Notre Dame des Milli\u00e8res",
    "sg:orig_category":"Non-Classified Establishments",
    "sg:phone":"+33 4 79 38 40 23",
    "sg:province":"Rhone-Alpes",
    "wof:name":"G.v.c. Entreprises S.a.",
    "wof:placetype":"venue"
},
  "geometry": {"coordinates":[6.306249,45.587067],"type":"Point"}
}