{
  "type": "Feature",
  "properties": {
    "addr:full":"Rte des Signes Signes Provence-Alpes-C\u00f4te d'Azur 83870",
    "addr:postcode":"83870",
    "addr:street":"Rte Des Signes",
    "iso:country":"FR",
    "sg:address":"Rte des Signes",
    "sg:city":"Signes",
    "sg:orig_category":"Unclassifiable Establishments",
    "sg:phone":"+33 4 94 10 00 51",
    "sg:postcode":"83870",
    "sg:province":"Provence-Alpes-C\u00f4te d'Azur",
    "wof:name":"T.m.e. - Techniques Modernes D'extensom\u00e9trie S.a.",
    "wof:placetype":"venue"
},
  "geometry": {"coordinates":[5.866634,43.303154],"type":"Point"}
}