{
  "type": "Feature",
  "properties": {
    "iso:country":"FR",
    "sg:address":"Zi St Etienne 64116 Bayonne",
    "sg:classifiers":[
        {
            "category":"Professional",
            "subcategory":"Engineering",
            "type":"Services"
        }
    ],
    "sg:phone":"+33 5 59 50 36 00",
    "sg:province":"Champagne",
    "sg:tags":[
        "machine",
        "-",
        "mechanical"
    ],
    "wof:name":"Inoxyform",
    "wof:placetype":"venue"
},
  "geometry": {"coordinates":[-1.462787,43.49678],"type":"Point"}
}