{
  "type": "Feature",
  "properties": {
    "iso:country":"FR",
    "sg:address":"3 Rue Ampere 95500 Gonesse",
    "sg:classifiers":[
        {
            "category":"Professional",
            "subcategory":"Advertising",
            "type":"Services"
        }
    ],
    "sg:phone":"+33 1 34 53 99 77",
    "sg:postcode":"95500",
    "sg:province":"Ile de France",
    "sg:tags":[
        "communication",
        "medium"
    ],
    "wof:name":"Lasergraph Sa",
    "wof:placetype":"venue"
},
  "geometry": {"coordinates":[2.457472,48.979801],"type":"Point"}
}