{
  "type": "Feature",
  "properties": {
    "addr:full":"route de Strasbourg 67250 SOULTZ SOUS FORETS Aschbach Alsace 67250",
    "addr:postcode":"67250;67250",
    "addr:street":"Route De Strasbourg;Forets Aschbach",
    "iso:country":"FR",
    "sg:address":"route de Strasbourg 67250 SOULTZ SOUS FORETS",
    "sg:city":"Aschbach",
    "sg:classifiers":[
        {
            "category":"Building & Trades",
            "subcategory":"Construction",
            "type":"Services"
        }
    ],
    "sg:phone":"+33 3 88 80 20 00",
    "sg:postcode":"67250",
    "sg:province":"Alsace",
    "sg:tags":[
        "tool",
        "cutting"
    ],
    "wof:name":"Gunther Sa",
    "wof:placetype":"venue"
},
  "geometry": {"coordinates":[7.880835,48.933205],"type":"Point"}
}