{
  "type": "Feature",
  "properties": {
    "iso:country":"FR",
    "sg:address":"21, Rue Elis\u00e9e Reclus - Parc Technologique la Haute Borne, 59650 Villeneuve d'Ascq",
    "sg:city":"Vill\u00e9",
    "sg:orig_category":"Non-Classified Establishments",
    "sg:phone":"+33 3 20 05 55 36",
    "sg:postcode":"67220",
    "sg:province":"Alsace",
    "wof:name":"Nortek S.a.r.l.",
    "wof:placetype":"venue"
},
  "geometry": {"coordinates":[3.16081,48.220181],"type":"Point"}
}