{
  "type": "Feature",
  "properties": {
    "addr:full":"Z.I. Les Ayvelles Villers Semeuse Champagne 08000",
    "addr:housenumber":"ayvelles",
    "addr:postcode":"08000",
    "addr:street":"Z.I. Les;Champagne",
    "iso:country":"FR",
    "sg:address":"Z.I. Les Ayvelles",
    "sg:city":"Villers Semeuse",
    "sg:orig_category":"Unclassifiable Establishments",
    "sg:phone":"+33 3 24 37 76 99",
    "sg:postcode":"08000",
    "sg:province":"Champagne",
    "wof:name":"Lambot Mat\u00e9riel S.a.r.l.",
    "wof:placetype":"venue"
},
  "geometry": {"coordinates":[4.7174,49.758801],"type":"Point"}
}