{
  "type": "Feature",
  "properties": {
    "addr:full":"pl de l'Eglise; Nevez Picardie",
    "addr:street":"Pl De L'Eglise Nevez",
    "iso:country":"FR",
    "sg:address":"pl de l'Eglise; Nevez",
    "sg:classifiers":[
        {
            "category":"Banks & Credit Unions",
            "subcategory":"Bank",
            "type":"Services"
        }
    ],
    "sg:phone":"+33 3398068163",
    "sg:province":"Picardie",
    "wof:name":"Cr\u00e9dit Mutuel Bretagne",
    "wof:placetype":"venue"
},
  "geometry": {"coordinates":[19.136471,51.922508],"type":"Point"}
}