{
  "type": "Feature",
  "properties": {
    "iso:country":"FR",
    "sg:address":"B.P. 67, 05002 Gap C\u00e9dex^^6, Rue du verger, 05000 Gap",
    "sg:orig_category":"Non-Classified Establishments",
    "sg:phone":"+33 4 92 40 30 30",
    "sg:province":"Basse Normandie",
    "wof:name":"Edf Gdf",
    "wof:placetype":"venue"
},
  "geometry": {"coordinates":[6.07483,44.554939],"type":"Point"}
}