{
  "type": "Feature",
  "properties": {
    "addr:full":"45 Rue Du Chemin Vert 75011 Paris Ile de France 75011",
    "addr:housenumber":"45",
    "addr:postcode":"75011;75011",
    "addr:street":"Rue Du Chemin Vert",
    "iso:country":"FR",
    "sg:address":"45 Rue Du Chemin Vert 75011 Paris",
    "sg:classifiers":[
        {
            "category":"Shopping",
            "subcategory":"Clothing, Apparel, & Fashions",
            "type":"Retail Goods"
        }
    ],
    "sg:phone":"+33 1 48 07 12 13",
    "sg:postcode":"75011",
    "sg:province":"Ile de France",
    "sg:tags":[
        "textile",
        "clothing",
        "clothes"
    ],
    "wof:name":"Lucy",
    "wof:placetype":"venue"
},
  "geometry": {"coordinates":[2.375022,48.859283],"type":"Point"}
}