{
  "type": "Feature",
  "properties": {
    "addr:full":"22, Rue Gustave Eiffel - Technoparc - Espace Cristal, 78306 Poissy C\u00e9dex Basse Normandie",
    "addr:housenumber":"22",
    "addr:postcode":"78306",
    "addr:street":"Rue Gustave Eiffel Technoparc Espace",
    "iso:country":"FR",
    "sg:address":"22, Rue Gustave Eiffel - Technoparc - Espace Cristal, 78306 Poissy C\u00e9dex",
    "sg:orig_category":"Non-Classified Establishments",
    "sg:phone":"+33 1 39 22 39 64",
    "sg:province":"Basse Normandie",
    "wof:name":"Tornos Technologies France S.a.r.l.",
    "wof:placetype":"venue"
},
  "geometry": {"coordinates":[2.04256,48.927971],"type":"Point"}
}