{
  "type": "Feature",
  "properties": {
    "iso:country":"FR",
    "sg:address":"125 Av Louis Roche 92230 Gennevilliers",
    "sg:classifiers":[
        {
            "category":"Manufacturing",
            "subcategory":"Chemicals & Compounds",
            "type":"Manufacturing & Wholesale Goods"
        }
    ],
    "sg:phone":"+33 1 47 92 41 80",
    "sg:postcode":"92230",
    "sg:province":"Ile de France",
    "sg:tags":[
        "pharmaceutical",
        "chemistry",
        "-",
        "by-product"
    ],
    "wof:name":"Eleco-produits Sa",
    "wof:placetype":"venue"
},
  "geometry": {"coordinates":[2.314166,48.92691],"type":"Point"}
}