{
  "type": "Feature",
  "properties": {
    "addr:full":"17, Place Jean Monnet, 16100 Cognac Poitou-Charentes",
    "addr:housenumber":"17",
    "addr:postcode":"16100",
    "addr:street":"Place Jean Monnet",
    "iso:country":"FR",
    "sg:address":"17, Place Jean Monnet, 16100 Cognac",
    "sg:orig_category":"Unclassifiable Establishments",
    "sg:phone":"+33 5 45 36 31 00",
    "sg:province":"Poitou-Charentes",
    "wof:name":"Agence B.p.c. - Banque Populaire Centre",
    "wof:placetype":"venue"
},
  "geometry": {"coordinates":[-0.327181,45.692944],"type":"Point"}
}