{
  "type": "Feature",
  "properties": {
    "addr:full":"La Boursidi\u00e8re 92350 Le Plessis Robinson Ile de France 92350",
    "addr:postcode":"92350;92350",
    "iso:country":"FR",
    "sg:address":"La Boursidi\u00e8re 92350 Le Plessis Robinson",
    "sg:orig_category":"Devices For Urological Aiding",
    "sg:phone":"+33 1 46 01 32 32",
    "sg:postcode":"92350",
    "sg:province":"Ile de France",
    "wof:name":"Porg\u00e8s S.a.",
    "wof:placetype":"venue"
},
  "geometry": {"coordinates":[2.236615,48.774796],"type":"Point"}
}