{
  "type": "Feature",
  "properties": {
    "addr:full":"Les Ajoncs 85000 La Roche sur Yon Pays de Loire 85000",
    "addr:postcode":"85000;85000",
    "addr:street":"Roche;Yon",
    "iso:country":"FR",
    "sg:address":"Les Ajoncs 85000 La Roche sur Yon",
    "sg:classifiers":[
        {
            "category":"Shopping",
            "subcategory":"Used Merchandise",
            "type":"Retail Goods"
        }
    ],
    "sg:phone":"+33 2 51 62 66 16",
    "sg:postcode":"85000",
    "sg:province":"Pays de Loire",
    "sg:tags":[
        "agricultural",
        "machinery"
    ],
    "wof:name":"Socomhy Sa",
    "wof:placetype":"venue"
},
  "geometry": {"coordinates":[-1.373189,46.69482],"type":"Point"}
}