{
  "type": "Feature",
  "properties": {
    "iso:country":"FR",
    "sg:address":"18 grand rue 67500 Haguenau",
    "sg:city":"Haguenau",
    "sg:classifiers":[
        {
            "category":"Food & Beverages",
            "subcategory":"Dairy",
            "type":"Retail Goods"
        }
    ],
    "sg:phone":"+33 3 88 06 17 18",
    "sg:postcode":"67500",
    "sg:province":"Alsace",
    "sg:tags":[
        "product",
        "milk"
    ],
    "wof:name":"Micha\u00ebl Zuber Import Export Sa",
    "wof:placetype":"venue"
},
  "geometry": {"coordinates":[7.786982,48.812672],"type":"Point"}
}