{
  "type": "Feature",
  "properties": {
    "addr:full":"666, Rte la Combe de l'Eau - La Feuillasse , 01220 Divonne les Bains Rhone-Alpes 01220",
    "addr:housenumber":"666",
    "addr:postcode":"01220;01220",
    "addr:street":"Rte La Combe De L'Eau La Feuillasse",
    "iso:country":"FR",
    "sg:address":"666, Rte la Combe de l'Eau - La Feuillasse , 01220 Divonne les Bains",
    "sg:orig_category":"Non-Classified Establishments",
    "sg:phone":"+33 4 50 20 15 97",
    "sg:postcode":"01220",
    "sg:province":"Rhone-Alpes",
    "wof:name":"Dupenloup P\u00e8re Et Fils S.a.r.l.",
    "wof:placetype":"venue"
},
  "geometry": {"coordinates":[6.132714,46.367931],"type":"Point"}
}