{
  "type": "Feature",
  "properties": {
    "iso:country":"FR",
    "sg:address":"Cardry 22800 Saint Brandan",
    "sg:city":"Cohiniac",
    "sg:orig_category":"Unclassifiable Establishments",
    "sg:phone":"+33 2 96 74 87 52",
    "sg:postcode":"22800",
    "sg:province":"Bretagne",
    "wof:name":"Cardry Services S.a.r.l.",
    "wof:placetype":"venue"
},
  "geometry": {"coordinates":[-2.907845,48.393955],"type":"Point"}
}