{
  "type": "Feature",
  "properties": {
    "iso:country":"FR",
    "sg:address":"6 Rue Dewoitine 78140 V\u00e9lizy Villacoublay",
    "sg:classifiers":[
        {
            "category":"Professional",
            "subcategory":"Computer Services",
            "type":"Services"
        }
    ],
    "sg:phone":"+33 1 34 63 70 00",
    "sg:postcode":"78140",
    "sg:province":"Ile de France",
    "sg:tags":[
        "information",
        "technology",
        "software"
    ],
    "wof:name":"E A D S Systemes Et Electronics Sa",
    "wof:placetype":"venue"
},
  "geometry": {"coordinates":[2.216227,48.782681],"type":"Point"}
}