{
  "type": "Feature",
  "properties": {
    "iso:country":"FR",
    "sg:address":"17184 P\u00e9rigny C\u00e9dex^^6, Av. Louis Lumi\u00e8re - ZI, 17180 P\u00e9rigny",
    "sg:orig_category":"Non-Classified Establishments",
    "sg:phone":"+33 5 46 44 15 97",
    "sg:province":"Poitou-Charentes",
    "wof:name":"Sorom\u00e9tal S.a.r.l.",
    "wof:placetype":"venue"
},
  "geometry": {"coordinates":[-1.096665,46.15501],"type":"Point"}
}