{
  "type": "Feature",
  "properties": {
    "iso:country":"FR",
    "sg:address":"Chemin Des Basses Vallieres",
    "sg:city":"Industrielle Nord 69530 Brignais",
    "sg:classifiers":[
        {
            "category":"Manufacturing",
            "subcategory":"Metals",
            "type":"Manufacturing & Wholesale Goods"
        }
    ],
    "sg:phone":"+33 4 72 31 81 81",
    "sg:province":"Rhone-Alpes",
    "sg:tags":[
        "metallurgy",
        "metalworking",
        "processing"
    ],
    "wof:name":"Berard Sa",
    "wof:placetype":"venue"
},
  "geometry": {"coordinates":[4.753949,45.674034],"type":"Point"}
}