{
  "type": "Feature",
  "properties": {
    "addr:full":"2 Rue Ernest Cauvin 80480 Saleux Picardie 80480",
    "addr:housenumber":"2",
    "addr:postcode":"80480;80480",
    "addr:street":"Rue Ernest Cauvin;Picardie",
    "iso:country":"FR",
    "sg:address":"2 Rue Ernest Cauvin 80480 Saleux",
    "sg:classifiers":[
        {
            "category":"Professional",
            "subcategory":"Advertising",
            "type":"Services"
        }
    ],
    "sg:phone":"+33 3 22 89 02 02",
    "sg:postcode":"80480",
    "sg:province":"Picardie",
    "sg:tags":[
        "communication",
        "medium"
    ],
    "wof:name":"Editions Norsud Sa",
    "wof:placetype":"venue"
},
  "geometry": {"coordinates":[2.246425,49.865318],"type":"Point"}
}