{
  "type": "Feature",
  "properties": {
    "addr:full":"Chemin des 3 Croix Miserey Salines Franche Comt\u00e9 25480",
    "addr:postcode":"25480",
    "addr:street":"Chemin Des 3 Croix Miserey Salines Franche Comte\u0301",
    "iso:country":"FR",
    "sg:address":"Chemin des 3 Croix",
    "sg:city":"Miserey Salines",
    "sg:orig_category":"OUTILLAGE DE PRESSE D\u00c9COUPAGE JUSQU'\u00c0 60 T, EMBOUTISSAGE",
    "sg:phone":"+33 3 81 53 88 00",
    "sg:postcode":"25480",
    "sg:province":"Franche Comt\u00e9",
    "wof:name":"Ateco S.a.r.l. - Atelier Etudes Conception Outillages",
    "wof:placetype":"venue"
},
  "geometry": {"coordinates":[5.982078,47.27187],"type":"Point"}
}