{
  "type": "Feature",
  "properties": {
    "iso:country":"FR",
    "sg:address":"Rte de Sainte Roseline - Centre Pierre Bourdaire",
    "sg:city":"La Motte",
    "sg:orig_category":"Unclassifiable Establishments",
    "sg:phone":"+33 4 94 70 82 79",
    "sg:postcode":"83920",
    "sg:province":"Bretagne",
    "wof:name":"Stogaz",
    "wof:placetype":"venue"
},
  "geometry": {"coordinates":[6.53494,43.493317],"type":"Point"}
}