{
  "type": "Feature",
  "properties": {
    "addr:full":"4, Place Saint Pierre, 31000 Toulouse Midi Pyr\u00e9n\u00e9es 31000",
    "addr:housenumber":"4",
    "addr:postcode":"31000;31000",
    "addr:street":"Place Saint Pierre",
    "iso:country":"FR",
    "sg:address":"4, Place Saint Pierre, 31000 Toulouse",
    "sg:orig_category":"Non-Classified Establishments",
    "sg:phone":"+33 5 61 21 58 73",
    "sg:postcode":"31000",
    "sg:province":"Midi Pyr\u00e9n\u00e9es",
    "wof:name":"Acanthe S.a.r.l.",
    "wof:placetype":"venue"
},
  "geometry": {"coordinates":[1.436362,43.603409],"type":"Point"}
}