{
  "type": "Feature",
  "properties": {
    "addr:full":"19, Galerie George Sand, 30900 N\u00eemes Languedoc-Roussillon",
    "addr:housenumber":"19",
    "addr:postcode":"30900",
    "addr:street":"Galerie George Sand",
    "iso:country":"FR",
    "sg:address":"19, Galerie George Sand, 30900 N\u00eemes",
    "sg:orig_category":"Unclassifiable Establishments",
    "sg:phone":"+33 4 66 68 17 76",
    "sg:province":"Languedoc-Roussillon",
    "wof:name":"D'asta Net S.a.r.l.",
    "wof:placetype":"venue"
},
  "geometry": {"coordinates":[4.338755,43.821724],"type":"Point"}
}