{
  "type": "Feature",
  "properties": {
    "iso:country":"FR",
    "sg:address":"RN 23 - ZI",
    "sg:city":"M\u00e2le",
    "sg:orig_category":"Non-Classified Establishments",
    "sg:phone":"+33 2 37 49 76 50",
    "sg:postcode":"61260",
    "sg:province":"Basse Normandie",
    "wof:name":"G.m.m. S.a.",
    "wof:placetype":"venue"
},
  "geometry": {"coordinates":[0.7477,48.22686],"type":"Point"}
}