{
  "type": "Feature",
  "properties": {
    "iso:country":"FR",
    "sg:address":"Rue Du Bicentenaire Zone Industrielle 01120 Dagneux",
    "sg:classifiers":[
        {
            "category":"Professional",
            "subcategory":"Printing & Photocopies",
            "type":"Services"
        }
    ],
    "sg:phone":"+33 4 78 06 55 72",
    "sg:postcode":"01120",
    "sg:province":"Rhone-Alpes",
    "sg:tags":[
        "machine",
        "engineering",
        "-",
        "mechanical"
    ],
    "wof:name":"Com Diff",
    "wof:placetype":"venue"
},
  "geometry": {"coordinates":[5.05126,45.85828],"type":"Point"}
}