{
  "type": "Feature",
  "properties": {
    "iso:country":"FR",
    "sg:address":"All\u00e9e Maryse Bastie Parc D'Activit\u00e9s Du B\u00e9al 06150 Cannes La Bocca",
    "sg:classifiers":[
        {
            "category":"Professional",
            "subcategory":"Printing & Photocopies",
            "type":"Services"
        }
    ],
    "sg:phone":"+33 4 93 48 00 58",
    "sg:province":"Provence-Alpes-C\u00f4te d'Azur",
    "sg:tags":[
        "publishing"
    ],
    "wof:name":"Adrexo",
    "wof:placetype":"venue"
},
  "geometry": {"coordinates":[6.963072,43.546547],"type":"Point"}
}