{
  "type": "Feature",
  "properties": {
    "iso:country":"FR",
    "sg:address":"rue du Chemin de Paris 28250 SENONCHES",
    "sg:city":"Senonches",
    "sg:classifiers":[
        {
            "category":"Professional",
            "subcategory":"Employment Agencies",
            "type":"Services"
        }
    ],
    "sg:phone":"+33 2 37 53 65 30",
    "sg:postcode":"28250",
    "sg:province":"Centre",
    "sg:tags":[
        "special-design",
        "drive"
    ],
    "wof:name":"Catep International S.a.",
    "wof:placetype":"venue"
},
  "geometry": {"coordinates":[1.02159,48.564255],"type":"Point"}
}