{
  "type": "Feature",
  "properties": {
    "iso:country":"FR",
    "sg:address":"314, Impasse Cl\u00e9ment Ader - Zone Industrielle, 54710 Ludres",
    "sg:orig_category":"Unclassifiable Establishments",
    "sg:phone":"+33 3 83 25 84 46",
    "sg:province":"Lorraine",
    "wof:name":"Eurovia C.a.l. S.n.c. - Champagne Ardennes Lorraine",
    "wof:placetype":"venue"
},
  "geometry": {"coordinates":[6.161059,48.621563],"type":"Point"}
}