{
  "type": "Feature",
  "properties": {
    "iso:country":"FR",
    "sg:address":"5BIS avenue Docteur Schweitzer 69330 Meyzieu",
    "sg:classifiers":[
        {
            "category":"Banks & Credit Unions",
            "subcategory":"Investment Brokerage",
            "type":"Services"
        }
    ],
    "sg:phone":"+33 4 78 04 03 43",
    "sg:province":"Rhone-Alpes",
    "sg:tags":[
        "machine",
        "cnc",
        "special"
    ],
    "wof:name":"Ets Tahmizian Sarl",
    "wof:placetype":"venue"
},
  "geometry": {"coordinates":[5.02993,45.766079],"type":"Point"}
}