{
  "type": "Feature",
  "properties": {
    "addr:full":"17 rue Merlet de la Boulaye 49000 Angers Pays de Loire 49000",
    "addr:housenumber":"17",
    "addr:postcode":"49000;49000",
    "addr:street":"Rue Merlet De La Boulaye",
    "iso:country":"FR",
    "sg:address":"17 rue Merlet de la Boulaye 49000 Angers",
    "sg:classifiers":[
        {
            "category":"Professional",
            "subcategory":"Advertising",
            "type":"Services"
        }
    ],
    "sg:phone":"+33 2 41 88 24 50",
    "sg:postcode":"49000",
    "sg:province":"Pays de Loire",
    "sg:tags":[
        "technology"
    ],
    "wof:name":"E.e.g.p. Sarl",
    "wof:placetype":"venue"
},
  "geometry": {"coordinates":[-0.545937,47.461487],"type":"Point"}
}