{
  "type": "Feature",
  "properties": {
    "addr:full":"5 rue le Brun 75013 Paris Ile de France",
    "addr:housenumber":"5",
    "addr:postcode":"75013",
    "addr:street":"Rue Le Brun",
    "iso:country":"FR",
    "sg:address":"5 rue le Brun 75013 Paris",
    "sg:orig_category":"Temperature And Humidity Measuring Systems Haccp",
    "sg:phone":"+33 1 45 87 22 99",
    "sg:province":"Ile de France",
    "wof:name":"Domosystem France S.a.",
    "wof:placetype":"venue"
},
  "geometry": {"coordinates":[2.355245,48.837433],"type":"Point"}
}