{
  "type": "Feature",
  "properties": {
    "addr:full":"1 Chemin des Romains 25720 BEURE Franche Comt\u00e9",
    "addr:housenumber":"1",
    "addr:postcode":"25720",
    "addr:street":"Chemin Des Romains;Franche Comte\u0301",
    "iso:country":"FR",
    "sg:address":"1 Chemin des Romains 25720 BEURE",
    "sg:classifiers":[
        {
            "category":"Education",
            "subcategory":"Dance Studio",
            "type":"Public Place"
        }
    ],
    "sg:phone":"+33 3 81 41 28 41",
    "sg:province":"Franche Comt\u00e9",
    "sg:tags":[
        "spring",
        "special-purpose"
    ],
    "wof:name":"Simonin S.a.",
    "wof:placetype":"venue"
},
  "geometry": {"coordinates":[6.00169,47.212475],"type":"Point"}
}