{
  "type": "Feature",
  "properties": {
    "addr:full":"Zi Du Pr\u00e9 Noir BP 12 38490 Charancieu Rhone-Alpes 38490",
    "addr:housenumber":"12",
    "addr:postcode":"38490;38490",
    "addr:street":"Zi Du Pre\u0301 Noir Bp;Rhone-Alpes",
    "iso:country":"FR",
    "sg:address":"Zi Du Pr\u00e9 Noir BP 12 38490 Charancieu",
    "sg:classifiers":[
        {
            "category":"Bakery",
            "type":"Food & Drink"
        }
    ],
    "sg:phone":"+33 4 76 32 68 00",
    "sg:postcode":"38490",
    "sg:province":"Rhone-Alpes",
    "sg:tags":[
        "cake",
        "product",
        "related",
        "bread"
    ],
    "wof:name":"Brioches Pasquier Alpes Sa",
    "wof:placetype":"venue"
},
  "geometry": {"coordinates":[5.582035,45.526814],"type":"Point"}
}