{
  "type": "Feature",
  "properties": {
    "iso:country":"FR",
    "sg:address":"Rue de Champfleury 49360 MAULEVRIER",
    "sg:orig_category":"Poultry, Slaughtered",
    "sg:phone":"+33 2 41 49 00 55",
    "sg:province":"Pays de Loire",
    "wof:name":"Elefa S.a.",
    "wof:placetype":"venue"
},
  "geometry": {"coordinates":[-0.757678,47.015095],"type":"Point"}
}