{
  "type": "Feature",
  "properties": {
    "addr:full":"84 rue Victor Clement 69240 THIZY Rhone-Alpes",
    "addr:housenumber":"84",
    "addr:postcode":"69240",
    "addr:street":"Rue Victor Clement",
    "iso:country":"FR",
    "sg:address":"84 rue Victor Clement 69240 THIZY",
    "sg:classifiers":[
        {
            "category":"Shopping",
            "subcategory":"Stationery & Office Supplies",
            "type":"Retail Goods"
        }
    ],
    "sg:phone":"+33 4 74 64 08 88",
    "sg:province":"Rhone-Alpes",
    "sg:tags":[
        "packaging"
    ],
    "wof:name":"Cellocoup International Sa",
    "wof:placetype":"venue"
},
  "geometry": {"coordinates":[4.317062,46.034004],"type":"Point"}
}