{
  "type": "Feature",
  "properties": {
    "addr:full":"4, Rue Bossuet, 42240 Unieux Rhone-Alpes",
    "addr:housenumber":"4",
    "addr:postcode":"42240",
    "addr:street":"Rue Bossuet",
    "iso:country":"FR",
    "sg:address":"4, Rue Bossuet, 42240 Unieux",
    "sg:orig_category":"Unclassifiable Establishments",
    "sg:phone":"+33 4 77 61 73 55",
    "sg:province":"Rhone-Alpes",
    "wof:name":"Aptelec Industrie S.a.r.l.",
    "wof:placetype":"venue"
},
  "geometry": {"coordinates":[4.2608,45.406261],"type":"Point"}
}