{
  "type": "Feature",
  "properties": {
    "iso:country":"FR",
    "sg:address":"B.P. 724, 42480 La Fouillouse^^ZI - La Gouyonni\u00e8re , 42480 La Fouillouse",
    "sg:orig_category":"Non-Classified Establishments",
    "sg:phone":"+33 4 77 36 68 01",
    "sg:postcode":"42480",
    "sg:province":"Rhone-Alpes",
    "wof:name":"A.p.f. S.a.r.l. - Ateliers Plastiques Du Forez",
    "wof:placetype":"venue"
},
  "geometry": {"coordinates":[4.316932,45.501125],"type":"Point"}
}