{
  "type": "Feature",
  "properties": {
    "addr:full":"Reygnaguet 19360 Cosnac Limousin 19360",
    "addr:postcode":"19360;19360",
    "addr:street":"Reygnaguet",
    "iso:country":"FR",
    "sg:address":"Reygnaguet 19360 Cosnac",
    "sg:classifiers":[
        {
            "category":"Shopping",
            "type":"Retail Goods"
        }
    ],
    "sg:phone":"+33 5 55 74 00 96",
    "sg:postcode":"19360",
    "sg:province":"Limousin",
    "sg:tags":[
        "metallurgy",
        "finished",
        "-",
        "metalworking",
        "metallic"
    ],
    "wof:name":"Precitol Sarl",
    "wof:placetype":"venue"
},
  "geometry": {"coordinates":[1.563955,45.124599],"type":"Point"}
}