{
  "type": "Feature",
  "properties": {
    "addr:full":"37, Rte de la Justice, 05000 Gap Provence-Alpes-C\u00f4te d'Azur",
    "addr:housenumber":"37",
    "addr:postcode":"05000",
    "addr:street":"Rte De La Justice",
    "iso:country":"FR",
    "sg:address":"37, Rte de la Justice, 05000 Gap",
    "sg:orig_category":"Unclassifiable Establishments",
    "sg:phone":"+33 4 92 52 24 00",
    "sg:province":"Provence-Alpes-C\u00f4te d'Azur",
    "wof:name":"Cabus Et Raulot S.a.",
    "wof:placetype":"venue"
},
  "geometry": {"coordinates":[6.108134,44.566719],"type":"Point"}
}