{
  "type": "Feature",
  "properties": {
    "addr:full":"30 Rue De Stalingrad Immeuble Descartes 92370 Chaville Ile de France 92370",
    "addr:housenumber":"30",
    "addr:postcode":"92370;ile;92370",
    "addr:street":"Rue De Stalingrad;Descartes;France",
    "iso:country":"FR",
    "sg:address":"30 Rue De Stalingrad Immeuble Descartes 92370 Chaville",
    "sg:classifiers":[
        {
            "category":"Manufacturing",
            "subcategory":"Tools & Machinery",
            "type":"Manufacturing & Wholesale Goods"
        }
    ],
    "sg:phone":"+33 1 47 50 03 03",
    "sg:postcode":"92370",
    "sg:province":"Ile de France",
    "sg:tags":[
        "equipment",
        "measurement",
        "-",
        "precision",
        "instrument"
    ],
    "wof:name":"Andilog",
    "wof:placetype":"venue"
},
  "geometry": {"coordinates":[2.188234,48.808445],"type":"Point"}
}