{
  "type": "Feature",
  "properties": {
    "iso:country":"FR",
    "sg:address":"1 Rue Ettore Bugatti 67201 Strasbourg Cedex",
    "sg:city":"Eckbolsheim",
    "sg:classifiers":[
        {
            "category":"Wholesale",
            "subcategory":"Machinery & Supplies",
            "type":"Manufacturing & Wholesale Goods"
        }
    ],
    "sg:phone":"+33 3 88 78 97 60",
    "sg:postcode":"67201",
    "sg:province":"Alsace",
    "sg:tags":[
        "equipment",
        "precision"
    ],
    "wof:name":"Asitel",
    "wof:placetype":"venue"
},
  "geometry": {"coordinates":[7.687253,48.579323],"type":"Point"}
}