{
  "type": "Feature",
  "properties": {
    "addr:full":"B.P. 74, 88203 Remiremont C\u00e9dex^^ZI de l'Encensement, 88200 Saint Nabord Lorraine 88200",
    "addr:postcode":"88203;88200 saint nabord;88200",
    "addr:street":"B.P. 74",
    "iso:country":"FR",
    "sg:address":"B.P. 74, 88203 Remiremont C\u00e9dex^^ZI de l'Encensement, 88200 Saint Nabord",
    "sg:orig_category":"Non-Classified Establishments",
    "sg:phone":"+33 3 29 23 63 63",
    "sg:postcode":"88200",
    "sg:province":"Lorraine",
    "wof:name":"Cleurie E.u.r.l.",
    "wof:placetype":"venue"
},
  "geometry": {"coordinates":[6.5814,48.049309],"type":"Point"}
}