{
  "type": "Feature",
  "properties": {
    "addr:full":"84, Rue Haguenau, 62100 Calais Nord Pas-de-Calais",
    "addr:housenumber":"84",
    "addr:postcode":"62100",
    "addr:street":"Rue Haguenau;Calais;Pas-De-Calais",
    "iso:country":"FR",
    "sg:address":"84, Rue Haguenau, 62100 Calais",
    "sg:orig_category":"Unclassifiable Establishments",
    "sg:phone":"+33 3 21 46 09 50",
    "sg:province":"Nord Pas-de-Calais",
    "wof:name":"Apave Nord Ouest",
    "wof:placetype":"venue"
},
  "geometry": {"coordinates":[1.878474,50.942547],"type":"Point"}
}