{
  "type": "Feature",
  "properties": {
    "addr:full":"B.P. 1012, 21601 Longvic C\u00e9dex^^3, Bd Eiffel, 21600 Longvic Longvic Bourgogne 21600",
    "addr:housenumber":"1012",
    "addr:postcode":"21601;ce\u0301dex^^3;21600;21600",
    "addr:street":"B.P.;Eiffel",
    "iso:country":"FR",
    "sg:address":"B.P. 1012, 21601 Longvic C\u00e9dex^^3, Bd Eiffel, 21600 Longvic",
    "sg:city":"Longvic",
    "sg:orig_category":"Non-Classified Establishments",
    "sg:phone":"+33 3 80 69 14 00",
    "sg:postcode":"21600",
    "sg:province":"Bourgogne",
    "wof:name":"Sim\u00e9lectro S.a.",
    "wof:placetype":"venue"
},
  "geometry": {"coordinates":[5.06327,47.286015],"type":"Point"}
}