{
  "type": "Feature",
  "properties": {
    "iso:country":"FR",
    "sg:address":"B.P. 34, 78192 Trappes C\u00e9dex^^38, Av. Roger Hennequin, 78190 Trappes",
    "sg:orig_category":"Non-Classified Establishments",
    "sg:phone":"+33 1 30 51 18 36",
    "sg:province":"Ile de France",
    "wof:name":"Partek Cargotec S.a.",
    "wof:placetype":"venue"
},
  "geometry": {"coordinates":[1.999285,48.774651],"type":"Point"}
}