{
  "type": "Feature",
  "properties": {
    "iso:country":"FR",
    "sg:address":"22, Rue des Grosses Pierres, 76250 D\u00e9ville l\u00e8s Rouen",
    "sg:orig_category":"Unclassifiable Establishments",
    "sg:phone":"+33 2 35 74 35 86",
    "sg:province":"Haute Normandie",
    "wof:name":"Menuiserie Devilloise S.a.",
    "wof:placetype":"venue"
},
  "geometry": {"coordinates":[1.03761,49.471939],"type":"Point"}
}