{
  "type": "Feature",
  "properties": {
    "iso:country":"FR",
    "sg:address":"Av Du Noyer Lambert Centre Omnisport 91300 Massy",
    "sg:classifiers":[
        {
            "category":"Sports & Exercise",
            "subcategory":"Sports Center",
            "type":"Entertainment"
        }
    ],
    "sg:phone":"+33 1 69 20 48 30",
    "sg:postcode":"91300",
    "sg:province":"Ile de France",
    "sg:tags":[
        "game"
    ],
    "wof:name":"Entente Sportive Massy",
    "wof:placetype":"venue"
},
  "geometry": {"coordinates":[2.27325,48.730282],"type":"Point"}
}