{
  "type": "Feature",
  "properties": {
    "addr:full":"1, Av. du Mar\u00e9chal Foch, 83550 Vidauban Provence-Alpes-C\u00f4te d'Azur",
    "addr:postcode":"83550",
    "addr:street":"Av. Du Mare\u0301Chal Foch",
    "iso:country":"FR",
    "sg:address":"1, Av. du Mar\u00e9chal Foch, 83550 Vidauban",
    "sg:orig_category":"Non-Classified Establishments",
    "sg:phone":"+33 4 94 73 00 01",
    "sg:province":"Provence-Alpes-C\u00f4te d'Azur",
    "wof:name":"Sofral Cave S.a.",
    "wof:placetype":"venue"
},
  "geometry": {"coordinates":[6.433443,43.428997],"type":"Point"}
}