{
  "type": "Feature",
  "properties": {
    "addr:full":"4 Rue Paul Langevin 49240 Avrill\u00e9 Pays de Loire 49240",
    "addr:housenumber":"4",
    "addr:postcode":"49240;49240",
    "addr:street":"Rue Paul Langevin",
    "iso:country":"FR",
    "sg:address":"4 Rue Paul Langevin 49240 Avrill\u00e9",
    "sg:classifiers":[
        {
            "category":"Professional",
            "subcategory":"Advertising",
            "type":"Services"
        }
    ],
    "sg:phone":"+33 2 41 42 35 25",
    "sg:postcode":"49240",
    "sg:province":"Pays de Loire",
    "sg:tags":[
        "marketing",
        "medium",
        "communication"
    ],
    "wof:name":"Ouet Routage",
    "wof:placetype":"venue"
},
  "geometry": {"coordinates":[-0.611665,47.518433],"type":"Point"}
}