{
  "type": "Feature",
  "properties": {
    "addr:full":"Goulardi\u00e8re 44130 Saint Philbert de Grand Lieu Pays de Loire",
    "addr:postcode":"44130",
    "addr:street":"Goulardie\u0300Re;Philbert De Grand Lieu",
    "iso:country":"FR",
    "sg:address":"Goulardi\u00e8re 44130 Saint Philbert de Grand Lieu",
    "sg:orig_category":"Non-Classified Establishments",
    "sg:phone":"+33 6 07 90 29 90",
    "sg:province":"Pays de Loire",
    "wof:name":"Recoquill\u00e9 Joseph",
    "wof:placetype":"venue"
},
  "geometry": {"coordinates":[-1.709864,47.38155],"type":"Point"}
}