{
  "type": "Feature",
  "properties": {
    "addr:full":"B.P. 32, 11590 Cuxac d'Aude^^ZA, 11590 Cuxac d'Aude Languedoc-Roussillon 11590",
    "addr:postcode":"11590;11590;d'aude;11590",
    "addr:street":"B.P. 32;^^Za",
    "iso:country":"FR",
    "sg:address":"B.P. 32, 11590 Cuxac d'Aude^^ZA, 11590 Cuxac d'Aude",
    "sg:orig_category":"Non-Classified Establishments",
    "sg:phone":"+33 4 68 46 62 20",
    "sg:postcode":"11590",
    "sg:province":"Languedoc-Roussillon",
    "wof:name":"Balcap E.u.r.l.",
    "wof:placetype":"venue"
},
  "geometry": {"coordinates":[2.97681,43.275631],"type":"Point"}
}