{
  "type": "Feature",
  "properties": {
    "iso:country":"FR",
    "sg:address":"CD 56 - Rte des Michels",
    "sg:city":"Peynier",
    "sg:orig_category":"Unclassifiable Establishments",
    "sg:phone":"+33 4 42 29 19 79",
    "sg:postcode":"13790",
    "sg:province":"Aquitaine",
    "wof:name":"Picopolish S.a.",
    "wof:placetype":"venue"
},
  "geometry": {"coordinates":[5.63957,43.446781],"type":"Point"}
}