{
  "type": "Feature",
  "properties": {
    "iso:country":"FR",
    "sg:address":"Rue Hector Berlioz - ZAC de l'Oserai",
    "sg:city":"Le Mans",
    "sg:orig_category":"Non-Classified Establishments",
    "sg:phone":"+33 2 43 87 02 02",
    "sg:postcode":"72000",
    "sg:province":"Pays de Loire",
    "wof:name":"Locapharm S.a.",
    "wof:placetype":"venue"
},
  "geometry": {"coordinates":[0.187369,48.003181],"type":"Point"}
}