{
  "type": "Feature",
  "properties": {
    "addr:full":"B.P. 62 Ploemeur Bretagne 56270",
    "addr:postcode":"56270",
    "addr:street":"B.P. 62;Bretagne",
    "iso:country":"FR",
    "sg:address":"B.P. 62",
    "sg:city":"Ploemeur",
    "sg:orig_category":"Non-Classified Establishments",
    "sg:phone":"+33 2 97 86 33 91",
    "sg:postcode":"56270",
    "sg:province":"Bretagne",
    "wof:name":"S.g.c.o. - S.a. - Soci\u00e9t\u00e9 De G\u00e9nie Civil De L'ouest",
    "wof:placetype":"venue"
},
  "geometry": {"coordinates":[-3.433759,47.701954],"type":"Point"}
}