{
  "type": "Feature",
  "properties": {
    "iso:country":"FR",
    "sg:address":"135, Rue des Caboeufs, 92230 Gennevilliers",
    "sg:orig_category":"Unclassifiable Establishments",
    "sg:phone":"+33 1 46 13 83 00",
    "sg:province":"Ile de France",
    "wof:name":"Thomintex S.a.",
    "wof:placetype":"venue"
},
  "geometry": {"coordinates":[2.30943,48.924202],"type":"Point"}
}