{
  "type": "Feature",
  "properties": {
    "addr:full":"114, Rue de Montmorency, 95230 Soisy sous Montmorency Ile de France",
    "addr:housenumber":"114",
    "addr:postcode":"95230",
    "addr:street":"Rue De Montmorency",
    "iso:country":"FR",
    "sg:address":"114, Rue de Montmorency, 95230 Soisy sous Montmorency",
    "sg:orig_category":"Unclassifiable Establishments",
    "sg:phone":"+33 1 38 89 24 51",
    "sg:province":"Ile de France",
    "wof:name":"Mirclair S.a.",
    "wof:placetype":"venue"
},
  "geometry": {"coordinates":[2.30953,48.99263],"type":"Point"}
}