{
  "type": "Feature",
  "properties": {
    "addr:full":"16, Rte de Niort, 85200 Fontenay le Comte Pays de Loire",
    "addr:housenumber":"16",
    "addr:postcode":"85200",
    "addr:street":"Rte De Niort;Le Comte Pays",
    "iso:country":"FR",
    "sg:address":"16, Rte de Niort, 85200 Fontenay le Comte",
    "sg:orig_category":"Unclassifiable Establishments",
    "sg:phone":"+33 2 51 69 50 22",
    "sg:province":"Pays de Loire",
    "wof:name":"P.b.m. Aquitaine Redon S.n.c.",
    "wof:placetype":"venue"
},
  "geometry": {"coordinates":[-0.807965,46.392536],"type":"Point"}
}