{
  "type": "Feature",
  "properties": {
    "addr:full":"Za Du Pr\u00e9 St Germain 71250 Cluny Cluny Bourgogne 71250",
    "addr:postcode":"71250;71250",
    "addr:street":"Za Du Pre\u0301 St",
    "iso:country":"FR",
    "sg:address":"Za Du Pr\u00e9 St Germain 71250 Cluny",
    "sg:city":"Cluny",
    "sg:classifiers":[
        {
            "category":"Home & Garden",
            "subcategory":"Building Materials",
            "type":"Retail Goods"
        }
    ],
    "sg:phone":"+33 3 85 59 04 58",
    "sg:postcode":"71250",
    "sg:province":"Bourgogne",
    "sg:tags":[
        "equipment",
        "energy",
        "-",
        "environment",
        "raw",
        "machinery"
    ],
    "wof:name":"Ste De Distribution D'eau Intercommunale Sdei",
    "wof:placetype":"venue"
},
  "geometry": {"coordinates":[4.652685,46.435692],"type":"Point"}
}