{
  "type": "Feature",
  "properties": {
    "iso:country":"FR",
    "sg:address":"10 Avenue De Lyon",
    "sg:city":"Roanne",
    "sg:classifiers":[
        {
            "category":"Banks & Credit Unions",
            "subcategory":"Financial Services",
            "type":"Services"
        }
    ],
    "sg:phone":"+33 4 77 44 24 44",
    "sg:postcode":"42300",
    "sg:province":"Rhone-Alpes",
    "sg:tags":[
        "banking",
        "finance",
        "insurance"
    ],
    "wof:name":"Cabinet Gaillard Neyret Et Associes Sa",
    "wof:placetype":"venue"
},
  "geometry": {"coordinates":[4.077108,46.035118],"type":"Point"}
}