{
  "type": "Feature",
  "properties": {
    "iso:country":"FR",
    "sg:address":"Rue du Fresne",
    "sg:city":"Bretteville sur Odon",
    "sg:orig_category":"Unclassifiable Establishments",
    "sg:phone":"+33 2 31 73 86 86",
    "sg:postcode":"14760",
    "sg:province":"Basse Normandie",
    "wof:name":"G.l.s. S.a.r.l. - Garantie Label Services",
    "wof:placetype":"venue"
},
  "geometry": {"coordinates":[-0.422409,49.164215],"type":"Point"}
}