{
  "type": "Feature",
  "properties": {
    "iso:country":"FR",
    "sg:address":"Rn 568 13751 Les Pennes Mirabeau",
    "sg:classifiers":[
        {
            "category":"Food Court",
            "type":"Food & Drink"
        }
    ],
    "sg:phone":"+33 4 42 02 39 00",
    "sg:province":"Midi Pyr\u00e9n\u00e9es",
    "sg:tags":[
        "product",
        "related"
    ],
    "wof:name":"Coca Cola Entreprise Sa",
    "wof:placetype":"venue"
},
  "geometry": {"coordinates":[6.090269,44.062668],"type":"Point"}
}