{
  "type": "Feature",
  "properties": {
    "iso:country":"FR",
    "sg:address":"Rue du Cabotage - ZI du Ty-Mor",
    "sg:city":"Hennebont",
    "sg:orig_category":"Non-Classified Establishments",
    "sg:phone":"+33 2 97 36 39 24",
    "sg:postcode":"56700",
    "sg:province":"Bretagne",
    "wof:name":"Sobra S.a.r.l.",
    "wof:placetype":"venue"
},
  "geometry": {"coordinates":[-3.204294,47.719566],"type":"Point"}
}