{
  "type": "Feature",
  "properties": {
    "iso:country":"FR",
    "sg:address":"92182 Antony C\u00e9dex^^21, Rue Alexis de Tocqueville - Parc Haute Technologie, 92160 Antony",
    "sg:orig_category":"Non-Classified Establishments",
    "sg:phone":"+33 1 46 11 54 54",
    "sg:postcode":"92160",
    "sg:province":"Ile de France",
    "wof:name":"Carrier",
    "wof:placetype":"venue"
},
  "geometry": {"coordinates":[2.302653,48.752647],"type":"Point"}
}