{
  "type": "Feature",
  "properties": {
    "addr:full":"126, Av. Paul Painlev\u00e9, 01500 Amb\u00e9rieu en Bugey Rhone-Alpes",
    "addr:postcode":"01500",
    "addr:street":"126 Av. Paul Painleve\u0301",
    "iso:country":"FR",
    "sg:address":"126, Av. Paul Painlev\u00e9, 01500 Amb\u00e9rieu en Bugey",
    "sg:orig_category":"Unclassifiable Establishments",
    "sg:phone":"+33 4 74 34 00 86",
    "sg:province":"Rhone-Alpes",
    "wof:name":"C\u00e9rapi S.a.r.l.",
    "wof:placetype":"venue"
},
  "geometry": {"coordinates":[5.333769,45.957394],"type":"Point"}
}