{
  "type": "Feature",
  "properties": {
    "addr:full":"244 Av Andr\u00e9 Amp\u00e8re Zac Chalys 77190 Dammarie Les Lys Ile de France 77190",
    "addr:postcode":"77190;lys ile;france 77190",
    "addr:street":"244 Av Andre\u0301 Ampe\u0300Re Zac Chalys",
    "iso:country":"FR",
    "sg:address":"244 Av Andr\u00e9 Amp\u00e8re Zac Chalys 77190 Dammarie Les Lys",
    "sg:classifiers":[
        {
            "category":"Wholesale",
            "subcategory":"Medical Equipment & Supplies",
            "type":"Manufacturing & Wholesale Goods"
        }
    ],
    "sg:phone":"+33 1 64 37 81 96",
    "sg:postcode":"77190",
    "sg:province":"Ile de France",
    "sg:tags":[
        "instrument",
        "health",
        "-",
        "precision"
    ],
    "wof:name":"Thermofina",
    "wof:placetype":"venue"
},
  "geometry": {"coordinates":[2.63454,48.51474],"type":"Point"}
}