{
  "type": "Feature",
  "properties": {
    "iso:country":"FR",
    "sg:address":"8 bis, Rue de la Garde, 44300 Nantes",
    "sg:orig_category":"Unclassifiable Establishments",
    "sg:phone":"+33 2 40 93 00 20",
    "sg:province":"Pays de Loire",
    "wof:name":"Onet Propret\u00e9",
    "wof:placetype":"venue"
},
  "geometry": {"coordinates":[-1.502779,47.249958],"type":"Point"}
}