{
  "type": "Feature",
  "properties": {
    "addr:full":"B.P. 4, 67430 Diemeringen^^3, Rue des Remparts, 67430 Diemeringen Diemeringen Alsace 67430",
    "addr:housenumber":"4",
    "addr:postcode":"67430;67430;67430",
    "addr:street":"B.P.;Rue Des Remparts",
    "iso:country":"FR",
    "sg:address":"B.P. 4, 67430 Diemeringen^^3, Rue des Remparts, 67430 Diemeringen",
    "sg:city":"Diemeringen",
    "sg:orig_category":"Non-Classified Establishments",
    "sg:phone":"+33 3 88 00 42 46",
    "sg:postcode":"67430",
    "sg:province":"Alsace",
    "wof:name":"Epesem Stoebner S.a.r.l.",
    "wof:placetype":"venue"
},
  "geometry": {"coordinates":[7.18686,48.940609],"type":"Point"}
}