{
  "type": "Feature",
  "properties": {
    "addr:full":"Ch\u00e2teau Berliquet Saint Emilion Aquitaine 33330",
    "addr:postcode":"33330",
    "addr:street":"Saint",
    "iso:country":"FR",
    "sg:address":"Ch\u00e2teau Berliquet",
    "sg:city":"Saint Emilion",
    "sg:orig_category":"Unclassifiable Establishments",
    "sg:phone":"+33 5 57 24 70 48",
    "sg:postcode":"33330",
    "sg:province":"Aquitaine",
    "wof:name":"Ch\u00e2teau Berliquet S.c.e.a.",
    "wof:placetype":"venue"
},
  "geometry": {"coordinates":[-0.163873,44.889786],"type":"Point"}
}