{
  "type": "Feature",
  "properties": {
    "addr:full":"33, Rue Saint Denis, 86000 Poitiers Poitou-Charentes",
    "addr:housenumber":"33",
    "addr:postcode":"86000",
    "addr:street":"Rue Saint Denis",
    "iso:country":"FR",
    "sg:address":"33, Rue Saint Denis, 86000 Poitiers",
    "sg:orig_category":"Non-Classified Establishments",
    "sg:phone":"+33 5 49 88 88 29",
    "sg:province":"Poitou-Charentes",
    "wof:name":"Irfrep",
    "wof:placetype":"venue"
},
  "geometry": {"coordinates":[0.347428,46.584209],"type":"Point"}
}