{
  "type": "Feature",
  "properties": {
    "iso:country":"FR",
    "sg:address":"B.P. 401, 73104 Aix les Bains C\u00e9dex^^Rue Jacqueline Auriol, 73100 Aix les Bains",
    "sg:orig_category":"Non-Classified Establishments",
    "sg:phone":"+33 4 79 61 40 00",
    "sg:province":"Rhone-Alpes",
    "wof:name":"Guichon Valves S.a.",
    "wof:placetype":"venue"
},
  "geometry": {"coordinates":[5.899685,45.672455],"type":"Point"}
}