{
  "type": "Feature",
  "properties": {
    "addr:full":"17 Rue Pierre Rollin 80091 Amiens Cedex 3 Amiens Picardie 80000",
    "addr:housenumber":"17",
    "addr:postcode":"80091 amiens;80000",
    "addr:street":"Rue Pierre Rollin",
    "iso:country":"FR",
    "sg:address":"17 Rue Pierre Rollin 80091 Amiens Cedex 3",
    "sg:city":"Amiens",
    "sg:classifiers":[
        {
            "category":"Professional",
            "subcategory":"Business Services",
            "type":"Services"
        }
    ],
    "sg:phone":"+33 3 22 46 87 77",
    "sg:postcode":"80000",
    "sg:province":"Picardie",
    "sg:tags":[
        "training",
        "advice"
    ],
    "wof:name":"Centre De Formation Des Apprentis Du Btp",
    "wof:placetype":"venue"
},
  "geometry": {"coordinates":[2.312065,49.878769],"type":"Point"}
}