{
  "type": "Feature",
  "properties": {
    "addr:full":"Rue du Ch\u00eane Vert - ZI Saint Barth\u00e9l\u00e9my d'Anjou Pays de Loire 49124",
    "addr:postcode":"49124",
    "addr:street":"Rue Du Che\u0302Ne Vert Zi Saint Barthe\u0301Le\u0301My D'Anjou Pays",
    "iso:country":"FR",
    "sg:address":"Rue du Ch\u00eane Vert - ZI",
    "sg:city":"Saint Barth\u00e9l\u00e9my d'Anjou",
    "sg:orig_category":"Non-Classified Establishments",
    "sg:phone":"+33 2 41 43 43 15",
    "sg:postcode":"49124",
    "sg:province":"Pays de Loire",
    "wof:name":"Rineau S.a.",
    "wof:placetype":"venue"
},
  "geometry": {"coordinates":[-1.334822,47.273693],"type":"Point"}
}