{
  "type": "Feature",
  "properties": {
    "addr:full":"34, Rue Hamel, 80270 Airaines Picardie",
    "addr:housenumber":"34",
    "addr:postcode":"80270",
    "addr:street":"Rue Hamel",
    "iso:country":"FR",
    "sg:address":"34, Rue Hamel, 80270 Airaines",
    "sg:orig_category":"Unclassifiable Establishments",
    "sg:phone":"+33 3 22 28 63 15",
    "sg:province":"Picardie",
    "wof:name":"Ferr\u00e9 Christian S.a.",
    "wof:placetype":"venue"
},
  "geometry": {"coordinates":[1.918019,49.967716],"type":"Point"}
}