{
  "type": "Feature",
  "properties": {
    "iso:country":"FR",
    "sg:address":"28-32, Bd Vauban, 26000 Valence",
    "sg:orig_category":"Unclassifiable Establishments",
    "sg:phone":"+33 4 75 42 03 88",
    "sg:postcode":"26000",
    "sg:province":"Rhone-Alpes",
    "wof:name":"Bnp Lease",
    "wof:placetype":"venue"
},
  "geometry": {"coordinates":[4.89482,44.935101],"type":"Point"}
}