{
  "type": "Feature",
  "properties": {
    "addr:full":"29 route Saint-Germain Lembrom 63500 Issoire Issoire Auvergne 63500",
    "addr:housenumber":"29",
    "addr:postcode":"63500;63500",
    "addr:street":"Route Saint-Germain Lembrom",
    "iso:country":"FR",
    "sg:address":"29 route Saint-Germain Lembrom 63500 Issoire",
    "sg:city":"Issoire",
    "sg:classifiers":[
        {
            "category":"Professional",
            "type":"Services"
        }
    ],
    "sg:phone":"+33 4 73 89 23 90",
    "sg:postcode":"63500",
    "sg:province":"Auvergne",
    "sg:tags":[
        "transport"
    ],
    "wof:name":"Coudert Transports Sarl",
    "wof:placetype":"venue"
},
  "geometry": {"coordinates":[3.252968,45.533363],"type":"Point"}
}