{
  "type": "Feature",
  "properties": {
    "iso:country":"FR",
    "sg:address":"5, Rue Bellini, 92806 Puteaux C\u00e9dex",
    "sg:city":"Puteaux",
    "sg:orig_category":"Non-Classified Establishments",
    "sg:phone":"+33 1 49 06 43 66",
    "sg:postcode":"92800",
    "sg:province":"Ile de France",
    "wof:name":"P\u00eache Et Froid S.a.",
    "wof:placetype":"venue"
},
  "geometry": {"coordinates":[2.249817,48.886192],"type":"Point"}
}