{
  "type": "Feature",
  "properties": {
    "addr:full":"284 Raspail 75014 Paris Ile de France 75014",
    "addr:housenumber":"284",
    "addr:postcode":"75014;75014",
    "addr:street":"Raspail",
    "iso:country":"FR",
    "sg:address":"284",
    "sg:city":"Raspail 75014 Paris",
    "sg:classifiers":[
        {
            "category":"Building & Trades",
            "subcategory":"Electrical",
            "type":"Services"
        }
    ],
    "sg:phone":"+33 1 43 35 30 42",
    "sg:postcode":"75014",
    "sg:province":"Ile de France",
    "sg:tags":[
        "electronic",
        "lighting",
        "equipment"
    ],
    "wof:name":"Lumiere Et Fonction",
    "wof:placetype":"venue"
},
  "geometry": {"coordinates":[2.331647,48.835449],"type":"Point"}
}