{
  "type": "Feature",
  "properties": {
    "addr:full":"49 Rue De La R\u00e9publique 76250 Deville Les Rouen Haute Normandie 76250",
    "addr:housenumber":"49",
    "addr:postcode":"76250;76250",
    "addr:street":"Rue De La Re\u0301Publique;Deville;Haute Normandie",
    "iso:country":"FR",
    "sg:address":"49 Rue De La R\u00e9publique 76250 Deville Les Rouen",
    "sg:classifiers":[
        {
            "category":"Shopping",
            "subcategory":"Computers & Home Electronics",
            "type":"Retail Goods"
        }
    ],
    "sg:phone":"+33 2 32 10 70 00",
    "sg:postcode":"76250",
    "sg:province":"Haute Normandie",
    "sg:tags":[
        "equipment",
        "electrical",
        "component",
        "electric",
        "electronic"
    ],
    "wof:name":"Via Systemes",
    "wof:placetype":"venue"
},
  "geometry": {"coordinates":[1.04194,49.473705],"type":"Point"}
}