{
  "type": "Feature",
  "properties": {
    "iso:country":"FR",
    "sg:address":"Quartier la Gare 26250 Livron sur Drome",
    "sg:orig_category":"Unclassifiable Establishments",
    "sg:phone":"+33 4 75 61 60 64",
    "sg:province":"Rhone-Alpes",
    "wof:name":"Vedesche",
    "wof:placetype":"venue"
},
  "geometry": {"coordinates":[4.861636,44.77092],"type":"Point"}
}