{
  "type": "Feature",
  "properties": {
    "addr:full":"Zone Industrielle du District 76400 FECAMP Haute Normandie 76400",
    "addr:postcode":"76400;76400",
    "addr:street":"Zone Industrielle Du District;Haute Normandie",
    "iso:country":"FR",
    "sg:address":"Zone Industrielle du District 76400 FECAMP",
    "sg:orig_category":"Fish, Frozen",
    "sg:phone":"+33 2 35 10 25 30",
    "sg:postcode":"76400",
    "sg:province":"Haute Normandie",
    "wof:name":"St\u00e9 Des Produits Servifrais Sa",
    "wof:placetype":"venue"
},
  "geometry": {"coordinates":[0.37631,49.757568],"type":"Point"}
}