{
  "type": "Feature",
  "properties": {
    "addr:full":"5 Rue De La Ferme Du Sac 02590 Douchy Picardie 02590",
    "addr:housenumber":"5",
    "addr:postcode":"02590;02590",
    "addr:street":"Rue De La Ferme Du Sac",
    "iso:country":"FR",
    "sg:address":"5 Rue De La Ferme Du Sac 02590 Douchy",
    "sg:classifiers":[
        {
            "category":"Farming",
            "subcategory":"Crops",
            "type":"Manufacturing & Wholesale Goods"
        }
    ],
    "sg:phone":"+33 3 23 50 81 00",
    "sg:postcode":"02590",
    "sg:province":"Picardie",
    "sg:tags":[
        "vegetable",
        "fruit",
        "agriculture",
        "livestock"
    ],
    "wof:name":"Endives Du Bosquet",
    "wof:placetype":"venue"
},
  "geometry": {"coordinates":[3.133874,49.79628],"type":"Point"}
}