{
  "type": "Feature",
  "properties": {
    "addr:full":"Rue Du Chene 25480 Pirey Franche Comt\u00e9 25480",
    "addr:postcode":"25480;25480",
    "addr:street":"Rue Du Chene;Franche Comte\u0301",
    "iso:country":"FR",
    "sg:address":"Rue Du Chene 25480 Pirey",
    "sg:classifiers":[
        {
            "category":"Manufacturing",
            "subcategory":"Metals",
            "type":"Manufacturing & Wholesale Goods"
        }
    ],
    "sg:phone":"+33 3 81 47 47 00",
    "sg:postcode":"25480",
    "sg:province":"Franche Comt\u00e9",
    "sg:tags":[
        "-",
        "machine",
        "equipment",
        "engineering",
        "machinery",
        "mechanical"
    ],
    "wof:name":"Societe Francaise Des Outilleurs Reunis Sofor (sofor)",
    "wof:placetype":"venue"
},
  "geometry": {"coordinates":[5.969913,47.253914],"type":"Point"}
}