{
  "type": "Feature",
  "properties": {
    "iso:country":"FR",
    "sg:address":"14, Rue Lafon, 33400 Talence",
    "sg:city":"Talence",
    "sg:orig_category":"Unclassifiable Establishments",
    "sg:phone":"+33 5 56 99 50 70",
    "sg:postcode":"33400",
    "sg:province":"Aquitaine",
    "wof:name":"Entreprise G\u00e9n\u00e9rale Courbu S.a.",
    "wof:placetype":"venue"
},
  "geometry": {"coordinates":[-0.598552,44.817348],"type":"Point"}
}