{
  "type": "Feature",
  "properties": {
    "iso:country":"FR",
    "sg:address":"28 Rue Vincent Chevard 28000 Chartres",
    "sg:city":"Chartres",
    "sg:classifiers":[
        {
            "category":"Professional",
            "subcategory":"Printing & Photocopies",
            "type":"Services"
        }
    ],
    "sg:phone":"+33 2 37 88 28 50",
    "sg:postcode":"28000",
    "sg:province":"Centre",
    "sg:tags":[
        "publishing"
    ],
    "wof:name":"Dactyl Buro Du Centre",
    "wof:placetype":"venue"
},
  "geometry": {"coordinates":[1.504276,48.431328],"type":"Point"}
}