{
  "type": "Feature",
  "properties": {
    "addr:full":"70, Rue Jean Jaur\u00e8s, 92800 Puteaux Ile de France",
    "addr:housenumber":"70",
    "addr:postcode":"92800",
    "addr:street":"Rue Jean Jaure\u0300S",
    "iso:country":"FR",
    "sg:address":"70, Rue Jean Jaur\u00e8s, 92800 Puteaux",
    "sg:orig_category":"Non-Classified Establishments",
    "sg:phone":"+33 1 47 78 02 30",
    "sg:province":"Ile de France",
    "wof:name":"Sotratech S.a.r.l.",
    "wof:placetype":"venue"
},
  "geometry": {"coordinates":[2.243683,48.883743],"type":"Point"}
}