{
  "type": "Feature",
  "properties": {
    "iso:country":"FR",
    "sg:address":"5, Rue du Brulet, 69110 Sainte Foy l\u00e8s Lyon",
    "sg:orig_category":"Non-Classified Establishments",
    "sg:phone":"+33 4 78 25 38 94",
    "sg:province":"Rhone-Alpes",
    "wof:name":"Evoluance",
    "wof:placetype":"venue"
},
  "geometry": {"coordinates":[4.802667,45.746132],"type":"Point"}
}