{
  "type": "Feature",
  "properties": {
    "iso:country":"FR",
    "sg:address":"67 Bd Du G\u00e9n\u00e9ral Martial Valin 75015 Paris",
    "sg:classifiers":[
        {
            "category":"Shopping",
            "subcategory":"Clothing, Apparel, & Fashions",
            "type":"Retail Goods"
        }
    ],
    "sg:phone":"+33 1 44 25 23 10",
    "sg:postcode":"75015",
    "sg:province":"Ile de France",
    "sg:tags":[
        "textile",
        "clothing",
        "clothes"
    ],
    "wof:name":"Phist Sa",
    "wof:placetype":"venue"
},
  "geometry": {"coordinates":[2.27442,48.837059],"type":"Point"}
}