{
  "type": "Feature",
  "properties": {
    "iso:country":"FR",
    "sg:address":"Chemin de Riante Colline",
    "sg:city":"Meg\u00e8ve",
    "sg:orig_category":"Unclassifiable Establishments",
    "sg:phone":"+33 4 50 93 03 10",
    "sg:postcode":"74120",
    "sg:province":"Rhone-Alpes",
    "wof:name":"Compagnie Des H\u00f4tels De Montagnes",
    "wof:placetype":"venue"
},
  "geometry": {"coordinates":[6.610462,45.857098],"type":"Point"}
}