{
  "type": "Feature",
  "properties": {
    "addr:full":"227, Chemin Teura CIX 8B - ZA, 38190 Bernin Rhone-Alpes",
    "addr:housenumber":"227;8b",
    "addr:postcode":"38190",
    "addr:street":"Chemin Teura Cix;Za",
    "iso:country":"FR",
    "sg:address":"227, Chemin Teura CIX 8B - ZA, 38190 Bernin",
    "sg:orig_category":"Non-Classified Establishments",
    "sg:phone":"+33 4 76 08 02 53",
    "sg:province":"Rhone-Alpes",
    "wof:name":"Zapoly S.a.r.l.",
    "wof:placetype":"venue"
},
  "geometry": {"coordinates":[5.897916,45.212601],"type":"Point"}
}