{
  "type": "Feature",
  "properties": {
    "iso:country":"FR",
    "sg:address":"Rue de Verdun",
    "sg:city":"La Gorgue",
    "sg:orig_category":"Non-Classified Establishments",
    "sg:phone":"+33 3 28 48 82 94",
    "sg:postcode":"59253",
    "sg:province":"Nord Pas-de-Calais",
    "wof:name":"Verwaerde Et Pluquin Transports S.a.r.l.",
    "wof:placetype":"venue"
},
  "geometry": {"coordinates":[2.713581,50.630753],"type":"Point"}
}