{
  "type": "Feature",
  "properties": {
    "iso:country":"FR",
    "sg:address":"967, Chemin Pierre Drevet, 69300 Caluire et Cuire",
    "sg:orig_category":"Non-Classified Establishments",
    "sg:phone":"+33 4 78 98 79 40",
    "sg:postcode":"69300",
    "sg:province":"Rhone-Alpes",
    "wof:name":"Corefic S.a.",
    "wof:placetype":"venue"
},
  "geometry": {"coordinates":[4.871452,45.808189],"type":"Point"}
}