{
  "type": "Feature",
  "properties": {
    "addr:full":"229, Rue de Paris, 91300 Massy Ile de France",
    "addr:housenumber":"229",
    "addr:postcode":"91300",
    "addr:street":"Rue De Paris;Ile De France",
    "iso:country":"FR",
    "sg:address":"229, Rue de Paris, 91300 Massy",
    "sg:orig_category":"Unclassifiable Establishments",
    "sg:phone":"+33 1 64 53 16 10",
    "sg:province":"Ile de France",
    "wof:name":"Sodatec",
    "wof:placetype":"venue"
},
  "geometry": {"coordinates":[2.26231,48.722569],"type":"Point"}
}