{
  "type": "Feature",
  "properties": {
    "addr:full":"Rte de Dhuizon Neuvy Centre 41250",
    "addr:housenumber":"neuvy",
    "addr:postcode":"41250",
    "addr:street":"Rte De Dhuizon",
    "iso:country":"FR",
    "sg:address":"Rte de Dhuizon",
    "sg:city":"Neuvy",
    "sg:orig_category":"Non-Classified Establishments",
    "sg:phone":"+33 2 54 56 00 02",
    "sg:postcode":"41250",
    "sg:province":"Centre",
    "wof:name":"Transports Automobiles De Sologne S.a.",
    "wof:placetype":"venue"
},
  "geometry": {"coordinates":[1.60675,47.565182],"type":"Point"}
}