{
  "type": "Feature",
  "properties": {
    "iso:country":"FR",
    "sg:address":"B.P. 28, 38280 Villette d'Anthon^^9, Rue des Fauvettes, 38280 Villette d'Anthon",
    "sg:orig_category":"Non-Classified Establishments",
    "sg:phone":"+33 4 72 02 23 34",
    "sg:postcode":"38280",
    "sg:province":"Rhone-Alpes",
    "wof:name":"A.m.m. S.a.r.l. - Applications M\u00e9caniques Murillon",
    "wof:placetype":"venue"
},
  "geometry": {"coordinates":[5.166468,45.791191],"type":"Point"}
}