{
  "type": "Feature",
  "properties": {
    "iso:country":"FR",
    "sg:address":"18, Rue Bernard Palissy, 45800 Saint Jean de Braye",
    "sg:city":"Combleux",
    "sg:orig_category":"Non-Classified Establishments",
    "sg:phone":"+33 2 38 86 70 00",
    "sg:postcode":"45800",
    "sg:province":"Centre",
    "wof:name":"Form'ed S.a.r.l.",
    "wof:placetype":"venue"
},
  "geometry": {"coordinates":[1.94372,47.914886],"type":"Point"}
}