{
  "type": "Feature",
  "properties": {
    "iso:country":"FR",
    "sg:address":"56 Rte De Portet 31270 Villeneuve Tolosane",
    "sg:classifiers":[
        {
            "category":"Food Court",
            "type":"Food & Drink"
        }
    ],
    "sg:phone":"+33 5 61 76 81 91",
    "sg:postcode":"31270",
    "sg:province":"Midi Pyr\u00e9n\u00e9es",
    "sg:tags":[
        "product",
        "related"
    ],
    "wof:name":"Tropico",
    "wof:placetype":"venue"
},
  "geometry": {"coordinates":[1.364332,43.523544],"type":"Point"}
}