{
  "type": "Feature",
  "properties": {
    "addr:full":"433 Chemin Des Matouses 84470 Ch\u00e2teauneuf De Gadagne Provence-Alpes-C\u00f4te d'Azur",
    "addr:housenumber":"433",
    "addr:postcode":"84470",
    "addr:street":"Chemin Des Matouses;Gadagne",
    "iso:country":"FR",
    "sg:address":"433 Chemin Des Matouses 84470 Ch\u00e2teauneuf De Gadagne",
    "sg:classifiers":[
        {
            "category":"Manufacturing",
            "subcategory":"Rubber & Plastics",
            "type":"Manufacturing & Wholesale Goods"
        }
    ],
    "sg:phone":"+33 4 90 32 76 00",
    "sg:province":"Provence-Alpes-C\u00f4te d'Azur",
    "sg:tags":[
        "packaging",
        "material",
        "-"
    ],
    "wof:name":"L'europeenne D'embouteillage Snc",
    "wof:placetype":"venue"
},
  "geometry": {"coordinates":[4.952858,43.930286],"type":"Point"}
}