{
  "type": "Feature",
  "properties": {
    "iso:country":"FR",
    "sg:address":"7 Rue Rabelais 93120 La Courneuve",
    "sg:classifiers":[
        {
            "category":"Shopping",
            "subcategory":"Computers & Home Electronics",
            "type":"Retail Goods"
        }
    ],
    "sg:phone":"+33 1 49 92 87 10",
    "sg:postcode":"93120",
    "sg:province":"Ile de France",
    "sg:tags":[
        "equipment",
        "electrical",
        "component",
        "electric",
        "electronic"
    ],
    "wof:name":"Rielka",
    "wof:placetype":"venue"
},
  "geometry": {"coordinates":[2.408093,48.919205],"type":"Point"}
}