{
  "type": "Feature",
  "properties": {
    "iso:country":"FR",
    "sg:address":"73 ave du G\u00e9n\u00e9ral de Gaulle; Colmar; 68000",
    "sg:city":"Colmar",
    "sg:classifiers":[
        {
            "category":"Banks & Credit Unions",
            "subcategory":"Bank",
            "type":"Services"
        }
    ],
    "sg:phone":"+33 3 89 22 95 23",
    "sg:postcode":"68000",
    "sg:province":"Alsace",
    "wof:name":"Cr\u00e9dit Industriel D'alsace, Et De Lorraine Sa",
    "wof:placetype":"venue"
},
  "geometry": {"coordinates":[7.339925,48.072807],"type":"Point"}
}