{
  "type": "Feature",
  "properties": {
    "iso:country":"FR",
    "sg:address":"31, Rue des Trois Obus, 08700 Nouzonville",
    "sg:city":"Gespunsart",
    "sg:orig_category":"Unclassifiable Establishments",
    "sg:phone":"+33 3 24 53 83 87",
    "sg:postcode":"08700",
    "sg:province":"Champagne",
    "wof:name":"Arden'm\u00e9ca S.a.r.l.",
    "wof:placetype":"venue"
},
  "geometry": {"coordinates":[4.734693,49.81353],"type":"Point"}
}