{
  "type": "Feature",
  "properties": {
    "iso:country":"FR",
    "sg:address":"Rte de Cordes - ZI",
    "sg:city":"Gaillac",
    "sg:orig_category":"Unclassifiable Establishments",
    "sg:phone":"+33 5 63 57 10 69",
    "sg:postcode":"81600",
    "sg:province":"Midi Pyr\u00e9n\u00e9es",
    "wof:name":"Transports Henri Rizzo",
    "wof:placetype":"venue"
},
  "geometry": {"coordinates":[1.94877,43.843327],"type":"Point"}
}