{
  "type": "Feature",
  "properties": {
    "iso:country":"FR",
    "sg:address":"Rue E. Rutherford - ZI Marcerolles",
    "sg:city":"Bourg les Valence",
    "sg:orig_category":"Unclassifiable Establishments",
    "sg:phone":"+33 4 75 83 40 25",
    "sg:postcode":"26500",
    "sg:province":"Rhone-Alpes",
    "wof:name":"Daroma David Micka\u00ebl S.a.s.",
    "wof:placetype":"venue"
},
  "geometry": {"coordinates":[4.893225,44.947048],"type":"Point"}
}