{
  "type": "Feature",
  "properties": {
    "addr:full":"11 ave Georges Clemenceau; Le Puy en Velay; 43000 Le Puy-en-Velay Auvergne 43000",
    "addr:postcode":"43000;43000",
    "addr:street":"11 Ave Georges Clemenceau Le",
    "iso:country":"FR",
    "sg:address":"11 ave Georges Clemenceau; Le Puy en Velay; 43000",
    "sg:city":"Le Puy-en-Velay",
    "sg:classifiers":[
        {
            "category":"Banks & Credit Unions",
            "subcategory":"Bank",
            "type":"Services"
        }
    ],
    "sg:phone":"+33 3371020474",
    "sg:postcode":"43000",
    "sg:province":"Auvergne",
    "wof:name":"Banque Nationale De Paris",
    "wof:placetype":"venue"
},
  "geometry": {"coordinates":[3.887303,45.041954],"type":"Point"}
}