{
  "type": "Feature",
  "properties": {
    "iso:country":"FR",
    "sg:address":"47 Rue Roger Vaugeois 61340 Noc\u00e9",
    "sg:city":"Noc\u00e9",
    "sg:classifiers":[
        {
            "category":"Manufacturing",
            "subcategory":"Metals",
            "type":"Manufacturing & Wholesale Goods"
        }
    ],
    "sg:phone":"+33 2 33 85 19 00",
    "sg:postcode":"61340",
    "sg:province":"Basse Normandie",
    "sg:tags":[
        "metallurgy",
        "metalworking",
        "processing"
    ],
    "wof:name":"Decoration Protection Des Metaux Sa",
    "wof:placetype":"venue"
},
  "geometry": {"coordinates":[0.679965,48.378956],"type":"Point"}
}