{
  "type": "Feature",
  "properties": {
    "iso:country":"FR",
    "sg:address":"B.P. 1232, 13783 Aubagne C\u00e9dex^^227, Rue de Penche, 13780 Aubagne",
    "sg:orig_category":"Non-Classified Establishments",
    "sg:phone":"+33 4 42 18 64 44",
    "sg:province":"Provence-Alpes-C\u00f4te d'Azur",
    "wof:name":"Saravelli S.a.",
    "wof:placetype":"venue"
},
  "geometry": {"coordinates":[5.699832,43.27586],"type":"Point"}
}