{
  "type": "Feature",
  "properties": {
    "addr:full":"Ch\u00e2teau Pasquier Camblanes et Meynac Aquitaine 33360",
    "addr:postcode":"33360",
    "iso:country":"FR",
    "sg:address":"Ch\u00e2teau Pasquier",
    "sg:city":"Camblanes et Meynac",
    "sg:orig_category":"Unclassifiable Establishments",
    "sg:phone":"+33 5 56 20 00 34",
    "sg:postcode":"33360",
    "sg:province":"Aquitaine",
    "wof:name":"Perret Philippe",
    "wof:placetype":"venue"
},
  "geometry": {"coordinates":[-0.464711,44.766701],"type":"Point"}
}