{
  "type": "Feature",
  "properties": {
    "addr:full":"66 Av De La Margeride 63170 Aubi\u00e8re Aubi\u00e8re Auvergne 63170",
    "addr:postcode":"63170;63170",
    "addr:street":"66 Av De La Margeride",
    "iso:country":"FR",
    "sg:address":"66 Av De La Margeride 63170 Aubi\u00e8re",
    "sg:city":"Aubi\u00e8re",
    "sg:classifiers":[
        {
            "category":"Autos & Motor Vehicles",
            "subcategory":"Automobile Sales",
            "type":"Retail Goods"
        }
    ],
    "sg:phone":"+33 4 73 27 17 29",
    "sg:postcode":"63170",
    "sg:province":"Auvergne",
    "sg:tags":[
        "equipment",
        "motor-cars",
        "transport"
    ],
    "wof:name":"Norauto",
    "wof:placetype":"venue"
},
  "geometry": {"coordinates":[3.118861,45.762657],"type":"Point"}
}