{
  "type": "Feature",
  "properties": {
    "addr:full":"Rte Du Canal Bossi\u00e8re 76700 Gonfreville L'Orcher Haute Normandie 76700",
    "addr:postcode":"76700;l'orcher;76700",
    "addr:street":"Rte Du Canal Bossie\u0300Re;Haute Normandie",
    "iso:country":"FR",
    "sg:address":"Rte Du Canal Bossi\u00e8re 76700 Gonfreville L'Orcher",
    "sg:classifiers":[
        {
            "category":"Building & Trades",
            "subcategory":"Construction",
            "type":"Services"
        }
    ],
    "sg:phone":"+33 2 35 53 23 34",
    "sg:postcode":"76700",
    "sg:province":"Haute Normandie",
    "sg:tags":[
        "work",
        "public"
    ],
    "wof:name":"Entreprise De Travaux Publics De L'ouest",
    "wof:placetype":"venue"
},
  "geometry": {"coordinates":[0.199494,49.497059],"type":"Point"}
}