{
  "type": "Feature",
  "properties": {
    "addr:full":"Zac Des Hauts De Ferri\u00e8res Pa Du Nid De Grive 77164 Ferri\u00e8res En Brie Ile de France 77164",
    "addr:housenumber":"zac",
    "addr:postcode":"77164;77164",
    "addr:street":"Des Hauts De Ferrie\u0300Res",
    "iso:country":"FR",
    "sg:address":"Zac Des Hauts De Ferri\u00e8res Pa Du Nid De Grive 77164 Ferri\u00e8res En Brie",
    "sg:classifiers":[
        {
            "category":"Utilities",
            "type":"Services"
        }
    ],
    "sg:phone":"+33 1 64 76 12 12",
    "sg:postcode":"77164",
    "sg:province":"Ile de France",
    "sg:tags":[
        "road",
        "transport",
        "air"
    ],
    "wof:name":"Hays Logistique France",
    "wof:placetype":"venue"
},
  "geometry": {"coordinates":[2.704695,48.821323],"type":"Point"}
}