{
  "type": "Feature",
  "properties": {
    "iso:country":"FR",
    "sg:address":"Av Du Mal De Lattre De Tassigny 38480 Le Pont De Beauvoisin",
    "sg:classifiers":[
        {
            "category":"Home & Garden",
            "subcategory":"Furniture",
            "type":"Retail Goods"
        }
    ],
    "sg:phone":"+33 4 76 32 90 71",
    "sg:postcode":"38480",
    "sg:province":"Rhone-Alpes",
    "sg:tags":[
        "wood"
    ],
    "wof:name":"Sylvalpes Sas",
    "wof:placetype":"venue"
},
  "geometry": {"coordinates":[5.680155,45.527046],"type":"Point"}
}