{
  "type": "Feature",
  "properties": {
    "addr:full":"Za De La Verdiere 44470 Mauves Sur Loire Pays de Loire 44470",
    "addr:postcode":"44470;44470",
    "addr:street":"Za De La Verdiere",
    "iso:country":"FR",
    "sg:address":"Za De La Verdiere 44470 Mauves Sur Loire",
    "sg:classifiers":[
        {
            "category":"Autos & Motor Vehicles",
            "subcategory":"Automobile Sales",
            "type":"Retail Goods"
        }
    ],
    "sg:phone":"+33 2 40 25 01 02",
    "sg:postcode":"44470",
    "sg:province":"Pays de Loire",
    "sg:tags":[
        "equipment",
        "industrial",
        "transport"
    ],
    "wof:name":"Atlantic Trucks Services (ats)",
    "wof:placetype":"venue"
},
  "geometry": {"coordinates":[-1.394536,47.297615],"type":"Point"}
}