{
  "type": "Feature",
  "properties": {
    "iso:country":"FR",
    "sg:address":"345 Avenue Georges Clemenceau",
    "sg:city":"Nanterre",
    "sg:classifiers":[
        {
            "category":"Banks & Credit Unions",
            "subcategory":"Financial Services",
            "type":"Services"
        }
    ],
    "sg:phone":"+33 1 41 35 17 00",
    "sg:postcode":"92000",
    "sg:province":"Ile de France",
    "sg:tags":[
        "banking",
        "finance",
        "insurance"
    ],
    "wof:name":"Dun Et Bradstreet Sa",
    "wof:placetype":"venue"
},
  "geometry": {"coordinates":[2.224062,48.885448],"type":"Point"}
}