{
  "type": "Feature",
  "properties": {
    "addr:full":"18, Chemin du Moulin Rouge, 02600 Villers Cotter\u00eats Picardie",
    "addr:housenumber":"18",
    "addr:postcode":"02600",
    "addr:street":"Chemin Du Moulin Rouge",
    "iso:country":"FR",
    "sg:address":"18, Chemin du Moulin Rouge, 02600 Villers Cotter\u00eats",
    "sg:orig_category":"Unclassifiable Establishments",
    "sg:phone":"+33 3 23 96 58 58",
    "sg:province":"Picardie",
    "wof:name":"Plafond\u00e9cor S.a.",
    "wof:placetype":"venue"
},
  "geometry": {"coordinates":[3.09451,49.246891],"type":"Point"}
}