{
  "type": "Feature",
  "properties": {
    "addr:full":"Za Kerherve 29270 Cleden Poher Carhaix-Plouguer Bretagne 29270",
    "addr:postcode":"29270;29270",
    "addr:street":"Za Kerherve;Poher Carhaix-Plouguer Bretagne",
    "iso:country":"FR",
    "sg:address":"Za Kerherve 29270 Cleden Poher",
    "sg:city":"Carhaix-Plouguer",
    "sg:classifiers":[
        {
            "category":"Wholesale",
            "subcategory":"Machinery & Supplies",
            "type":"Manufacturing & Wholesale Goods"
        }
    ],
    "sg:phone":"+33 2 98 93 62 30",
    "sg:postcode":"29270",
    "sg:province":"Bretagne",
    "sg:tags":[
        "handling",
        "material",
        "-",
        "machine",
        "equipment",
        "engineering",
        "mechanical"
    ],
    "wof:name":"Sarl Areb (ops)",
    "wof:placetype":"venue"
},
  "geometry": {"coordinates":[-3.669579,48.235725],"type":"Point"}
}