{
  "type": "Feature",
  "properties": {
    "addr:full":"ZAC les Sablonni\u00e8res Epannes Poitou-Charentes 79270",
    "addr:postcode":"79270",
    "addr:street":"Zac Les Sablonnie\u0300Res Epannes",
    "iso:country":"FR",
    "sg:address":"ZAC les Sablonni\u00e8res",
    "sg:city":"Epannes",
    "sg:orig_category":"Unclassifiable Establishments",
    "sg:phone":"+33 5 49 04 68 10",
    "sg:postcode":"79270",
    "sg:province":"Poitou-Charentes",
    "wof:name":"Atlantic T\u00f4lerie S.a.r.l.",
    "wof:placetype":"venue"
},
  "geometry": {"coordinates":[-0.579065,46.229485],"type":"Point"}
}