{
  "type": "Feature",
  "properties": {
    "addr:full":"38470 Beaulieu Rhone-Alpes 38470",
    "addr:postcode":"38470;38470",
    "addr:street":"Rhone-Alpes",
    "iso:country":"FR",
    "sg:address":"38470 Beaulieu",
    "sg:orig_category":"Non-Classified Establishments",
    "sg:phone":"+33 4 76 36 73 73",
    "sg:postcode":"38470",
    "sg:province":"Rhone-Alpes",
    "wof:name":"A.m.b. S.a.r.l. - Atelier M\u00e9caniques De Beaulieu",
    "wof:placetype":"venue"
},
  "geometry": {"coordinates":[5.392384,45.193703],"type":"Point"}
}