{
  "type": "Feature",
  "properties": {
    "iso:country":"FR",
    "sg:address":"Site Nucl\u00e9aire du Bugey",
    "sg:city":"Saint Vulbas",
    "sg:orig_category":"Unclassifiable Establishments",
    "sg:phone":"+33 4 74 34 10 10",
    "sg:postcode":"01150",
    "sg:province":"Rhone-Alpes",
    "wof:name":"E.d.f",
    "wof:placetype":"venue"
},
  "geometry": {"coordinates":[5.3382,45.88237],"type":"Point"}
}