{
  "type": "Feature",
  "properties": {
    "addr:full":"Rue Costes Et Bellonte 39100 Dole Franche Comt\u00e9 39100",
    "addr:postcode":"39100;39100",
    "addr:street":"Rue Costes Et Bellonte;Franche Comte\u0301",
    "iso:country":"FR",
    "sg:address":"Rue Costes Et Bellonte 39100 Dole",
    "sg:classifiers":[
        {
            "category":"Farming",
            "subcategory":"Livestock Farm",
            "type":"Manufacturing & Wholesale Goods"
        }
    ],
    "sg:phone":"+33 3 84 72 10 07",
    "sg:postcode":"39100",
    "sg:province":"Franche Comt\u00e9",
    "sg:tags":[
        "product",
        "cereal",
        "food",
        "related",
        "horticul",
        "grain",
        "animal",
        "breeding",
        "agriculture"
    ],
    "wof:name":"Cooperative Agricole Interval",
    "wof:placetype":"venue"
},
  "geometry": {"coordinates":[5.49093,47.085258],"type":"Point"}
}