{
  "type": "Feature",
  "properties": {
    "iso:country":"FR",
    "sg:address":"9, Rue de S\u00e9bastopol, 31100 Toulouse",
    "sg:orig_category":"Non-Classified Establishments",
    "sg:phone":"+33 5 62 30 44 00",
    "sg:postcode":"31100",
    "sg:province":"Midi Pyr\u00e9n\u00e9es",
    "wof:name":"Adhara Informatique S.a.r.l.",
    "wof:placetype":"venue"
},
  "geometry": {"coordinates":[1.428979,43.612133],"type":"Point"}
}