{
  "type": "Feature",
  "properties": {
    "addr:full":"11, Rue des Hautes P\u00e2tures, 92737 Nanterre C\u00e9dex Aquitaine",
    "addr:housenumber":"11",
    "addr:postcode":"92737",
    "addr:street":"Rue Des Hautes Pa\u0302Tures",
    "iso:country":"FR",
    "sg:address":"11, Rue des Hautes P\u00e2tures, 92737 Nanterre C\u00e9dex",
    "sg:orig_category":"Non-Classified Establishments",
    "sg:phone":"+33 1 47 69 69 80",
    "sg:province":"Aquitaine",
    "wof:name":"Amex Gestion Service S.a.",
    "wof:placetype":"venue"
},
  "geometry": {"coordinates":[2.217329,48.914986],"type":"Point"}
}