{
  "type": "Feature",
  "properties": {
    "iso:country":"FR",
    "sg:address":"34 Rue Berg\u00e8re 75009 Paris",
    "sg:classifiers":[
        {
            "category":"Travel",
            "subcategory":"Hotels & Motels",
            "type":"Entertainment"
        }
    ],
    "sg:phone":"+33 1 47 70 34 34",
    "sg:postcode":"75009",
    "sg:province":"Ile de France",
    "sg:tags":[
        "hotels",
        "business",
        "restaurant"
    ],
    "wof:name":"Hotel Bergere Opera Sa",
    "wof:placetype":"venue"
},
  "geometry": {"coordinates":[2.343655,48.872761],"type":"Point"}
}