{
  "type": "Feature",
  "properties": {
    "iso:country":"FR",
    "sg:address":"Rue du Progr\u00e8s - ZA La Croix Danet",
    "sg:city":"Geneston",
    "sg:orig_category":"Non-Classified Establishments",
    "sg:phone":"+33 2 40 26 13 16",
    "sg:postcode":"44140",
    "sg:province":"Pays de Loire",
    "wof:name":"E.c.p. Group S.a.",
    "wof:placetype":"venue"
},
  "geometry": {"coordinates":[-1.426909,47.009285],"type":"Point"}
}