{
  "type": "Feature",
  "properties": {
    "iso:country":"FR",
    "sg:address":"Rue Aristide Berg\u00e8s - ZI",
    "sg:city":"La Ravoire",
    "sg:orig_category":"Unclassifiable Establishments",
    "sg:phone":"+33 4 79 72 98 00",
    "sg:postcode":"73490",
    "sg:province":"Rhone-Alpes",
    "wof:name":"Gauthey S.n.c.",
    "wof:placetype":"venue"
},
  "geometry": {"coordinates":[5.96835,45.566654],"type":"Point"}
}