{
  "type": "Feature",
  "properties": {
    "addr:full":"Zi St Lambert Des Lev\u00e9es 49412 Saumur Cedex Ambert Auvergne 63600",
    "addr:postcode":"49412;63600",
    "addr:street":"Zi St Lambert Des Leve\u0301Es",
    "iso:country":"FR",
    "sg:address":"Zi St Lambert Des Lev\u00e9es 49412 Saumur Cedex",
    "sg:city":"Ambert",
    "sg:classifiers":[
        {
            "category":"Professional",
            "subcategory":"Engineering",
            "type":"Services"
        }
    ],
    "sg:phone":"+33 2 41 83 23 23",
    "sg:postcode":"63600",
    "sg:province":"Auvergne",
    "sg:tags":[
        "-",
        "metal",
        "precision",
        "machine",
        "equipment",
        "machinery",
        "mechanical"
    ],
    "wof:name":"Languepin Soudage",
    "wof:placetype":"venue"
},
  "geometry": {"coordinates":[-0.086852,47.250114],"type":"Point"}
}