{
  "type": "Feature",
  "properties": {
    "iso:country":"FR",
    "sg:address":"33 rue des Chardonnerets 93290 Tremblay en France",
    "sg:classifiers":[
        {
            "category":"Manufacturing",
            "subcategory":"Building Materials",
            "type":"Manufacturing & Wholesale Goods"
        }
    ],
    "sg:phone":"+33 1 48 63 00 88",
    "sg:postcode":"93290",
    "sg:province":"Ile de France",
    "sg:tags":[
        "machine",
        "refractory",
        "injection",
        "gunning",
        "moulding"
    ],
    "wof:name":"Idra-france S.a.",
    "wof:placetype":"venue"
},
  "geometry": {"coordinates":[2.516223,48.981495],"type":"Point"}
}