{
  "type": "Feature",
  "properties": {
    "addr:full":"447 Rue Jean Perrin 59500 Douai Nord Pas-de-Calais 59500",
    "addr:housenumber":"447",
    "addr:postcode":"59500;59500",
    "addr:street":"Rue Jean Perrin",
    "iso:country":"FR",
    "sg:address":"447 Rue Jean Perrin 59500 Douai",
    "sg:classifiers":[
        {
            "category":"Professional",
            "subcategory":"Business Services",
            "type":"Services"
        }
    ],
    "sg:phone":"+33 3 27 95 89 00",
    "sg:postcode":"59500",
    "sg:province":"Nord Pas-de-Calais",
    "sg:tags":[
        "training",
        "advice"
    ],
    "wof:name":"Avenir Formation Sarl",
    "wof:placetype":"venue"
},
  "geometry": {"coordinates":[3.097511,50.396263],"type":"Point"}
}