{
  "type": "Feature",
  "properties": {
    "addr:full":"62 Rue Du Sancy 63370 LEMPDES Lempdes Auvergne 63370",
    "addr:housenumber":"62",
    "addr:postcode":"63370;63370",
    "addr:street":"Rue Du Sancy",
    "iso:country":"FR",
    "sg:address":"62 Rue Du Sancy 63370 LEMPDES",
    "sg:city":"Lempdes",
    "sg:classifiers":[
        {
            "category":"Food & Beverages",
            "subcategory":"Meat & Fish",
            "type":"Retail Goods"
        }
    ],
    "sg:phone":"+33 4 73 91 63 96",
    "sg:postcode":"63370",
    "sg:province":"Auvergne",
    "sg:tags":[
        "product"
    ],
    "wof:name":"Clermont Viandes S.a.",
    "wof:placetype":"venue"
},
  "geometry": {"coordinates":[3.184605,45.773075],"type":"Point"}
}