{
  "type": "Feature",
  "properties": {
    "addr:full":"86, Rue de la Poudrette, 69100 Villeurbanne Rhone-Alpes 69100",
    "addr:housenumber":"86",
    "addr:postcode":"69100;69100",
    "addr:street":"Rue De La Poudrette",
    "iso:country":"FR",
    "sg:address":"86, Rue de la Poudrette, 69100 Villeurbanne",
    "sg:orig_category":"Non-Classified Establishments",
    "sg:phone":"+33 4 72 37 01 49",
    "sg:postcode":"69100",
    "sg:province":"Rhone-Alpes",
    "wof:name":"Vercor S.a.",
    "wof:placetype":"venue"
},
  "geometry": {"coordinates":[4.92044,45.760818],"type":"Point"}
}