{
  "type": "Feature",
  "properties": {
    "addr:full":"189 Rue D Aubervilliers 75018 Paris Ile de France",
    "addr:housenumber":"189",
    "addr:postcode":"75018",
    "addr:street":"Rue D Aubervilliers",
    "iso:country":"FR",
    "sg:address":"189 Rue D Aubervilliers 75018 Paris",
    "sg:classifiers":[
        {
            "category":"Manufacturing",
            "subcategory":"Rubber & Plastics",
            "type":"Manufacturing & Wholesale Goods"
        }
    ],
    "sg:phone":"+33 1 40 38 13 55",
    "sg:province":"Ile de France",
    "wof:name":"Plasti Collage Service",
    "wof:placetype":"venue"
},
  "geometry": {"coordinates":[2.370354,48.896683],"type":"Point"}
}