{
  "type": "Feature",
  "properties": {
    "addr:full":"6 B Rue Campagne Premiere 75014 Paris Ile de France",
    "addr:housenumber":"6 b",
    "addr:postcode":"75014",
    "addr:street":"Rue Campagne Premiere",
    "iso:country":"FR",
    "sg:address":"6 B Rue Campagne Premiere 75014 Paris",
    "sg:classifiers":[
        {
            "category":"Professional",
            "subcategory":"Printing & Photocopies",
            "type":"Services"
        }
    ],
    "sg:phone":"+33 1 56 80 20 80",
    "sg:province":"Ile de France",
    "sg:tags":[
        "publishing"
    ],
    "wof:name":"Communication Presse Publication Diffusion Cppd (cppd)",
    "wof:placetype":"venue"
},
  "geometry": {"coordinates":[2.332946,48.84024],"type":"Point"}
}