{
  "type": "Feature",
  "properties": {
    "addr:full":"100, Rue Blaise Pascal, 93600 Aulnay sous Bois Ile de France",
    "addr:housenumber":"100",
    "addr:postcode":"93600",
    "addr:street":"Rue Blaise Pascal",
    "iso:country":"FR",
    "sg:address":"100, Rue Blaise Pascal, 93600 Aulnay sous Bois",
    "sg:orig_category":"Non-Classified Establishments",
    "sg:phone":"+33 1 58 03 05 00",
    "sg:province":"Ile de France",
    "wof:name":"Pacific-scientific Instruments S.a.s.",
    "wof:placetype":"venue"
},
  "geometry": {"coordinates":[2.476736,48.94836],"type":"Point"}
}