{
  "type": "Feature",
  "properties": {
    "iso:country":"FR",
    "sg:address":"1 Rte Limoges 23210 Marsac",
    "sg:classifiers":[
        {
            "category":"Manufacturing",
            "subcategory":"Rubber & Plastics",
            "type":"Manufacturing & Wholesale Goods"
        }
    ],
    "sg:phone":"+33 5 55 81 53 50",
    "sg:province":"Limousin",
    "wof:name":"Hyeres Profiles Sarl",
    "wof:placetype":"venue"
},
  "geometry": {"coordinates":[1.580715,46.091633],"type":"Point"}
}