{
  "type": "Feature",
  "properties": {
    "iso:country":"FR",
    "sg:address":"10 Rue Roberval 72100 Le Mans",
    "sg:classifiers":[
        {
            "category":"Professional",
            "subcategory":"Engineering",
            "type":"Services"
        }
    ],
    "sg:phone":"+33 2 43 50 31 40",
    "sg:postcode":"72100",
    "sg:province":"Pays de Loire",
    "sg:tags":[
        "machine",
        "-",
        "mechanical"
    ],
    "wof:name":"Msp Sa",
    "wof:placetype":"venue"
},
  "geometry": {"coordinates":[4.29189,46.374798],"type":"Point"}
}