{
  "type": "Feature",
  "properties": {
    "addr:full":"Route De Bayeux 50000 St L\u00f4 Saint-L\u00f4 Basse Normandie 50000",
    "addr:postcode":"50000;50000",
    "addr:street":"Route De Bayeux",
    "iso:country":"FR",
    "sg:address":"Route De Bayeux 50000 St L\u00f4",
    "sg:city":"Saint-L\u00f4",
    "sg:classifiers":[
        {
            "category":"Banks & Credit Unions",
            "subcategory":"Investment Brokerage",
            "type":"Services"
        }
    ],
    "sg:phone":"+33 2 33 57 72 68",
    "sg:postcode":"50000",
    "sg:province":"Basse Normandie",
    "sg:tags":[
        "good",
        "business",
        "advice",
        "wood",
        "household",
        "furniture"
    ],
    "wof:name":"Ets Lechevalier",
    "wof:placetype":"venue"
},
  "geometry": {"coordinates":[-1.039143,49.117458],"type":"Point"}
}