{
  "type": "Feature",
  "properties": {
    "iso:country":"FR",
    "sg:address":"4 Rue Jacques Coeur 77440 Lizy Sur Ourcq",
    "sg:classifiers":[
        {
            "category":"Utilities",
            "subcategory":"Electric",
            "type":"Services"
        }
    ],
    "sg:phone":"+33 1 60 01 79 58",
    "sg:postcode":"77440",
    "sg:province":"Ile de France",
    "sg:tags":[
        "electricity",
        "electronic",
        "electrical",
        "equipment"
    ],
    "wof:name":"Godard",
    "wof:placetype":"venue"
},
  "geometry": {"coordinates":[3.025726,49.027592],"type":"Point"}
}