{
  "type": "Feature",
  "properties": {
    "iso:country":"FR",
    "sg:address":"12, Rue Albert Thierry, 45200 Montargis",
    "sg:city":"Montargis",
    "sg:orig_category":"Non-Classified Establishments",
    "sg:phone":"+33 2 38 85 65 65",
    "sg:postcode":"45200",
    "sg:province":"Centre",
    "wof:name":"Eraipe S.a.r.l.",
    "wof:placetype":"venue"
},
  "geometry": {"coordinates":[2.749053,47.995918],"type":"Point"}
}