{
  "type": "Feature",
  "properties": {
    "addr:full":"Rue Franklin Roosevelt 62400 Bethune Nord Pas-de-Calais 62400",
    "addr:postcode":"62400;62400",
    "addr:street":"Rue Franklin Roosevelt;Bethune Nord",
    "iso:country":"FR",
    "sg:address":"Rue Franklin Roosevelt 62400 Bethune",
    "sg:classifiers":[
        {
            "category":"Professional",
            "subcategory":"Engineering",
            "type":"Services"
        }
    ],
    "sg:phone":"+33 3 21 01 28 67",
    "sg:postcode":"62400",
    "sg:province":"Nord Pas-de-Calais",
    "sg:tags":[
        "machine",
        "-",
        "mechanical"
    ],
    "wof:name":"Bianchi Industrie",
    "wof:placetype":"venue"
},
  "geometry": {"coordinates":[2.655983,50.538269],"type":"Point"}
}