{
  "type": "Feature",
  "properties": {
    "iso:country":"FR",
    "sg:address":"34/60, Rue Edouard Vaillant, 91200 Athis Mons",
    "sg:orig_category":"Unclassifiable Establishments",
    "sg:phone":"+33 1 69 38 45 27",
    "sg:province":"Ile de France",
    "wof:name":"Suprex S.a.",
    "wof:placetype":"venue"
},
  "geometry": {"coordinates":[2.396567,48.70715],"type":"Point"}
}