{
  "type": "Feature",
  "properties": {
    "addr:full":"57, Rue de Lille, 59710 Avelin Nord Pas-de-Calais",
    "addr:housenumber":"57",
    "addr:postcode":"59710",
    "addr:street":"Rue De Lille",
    "iso:country":"FR",
    "sg:address":"57, Rue de Lille, 59710 Avelin",
    "sg:orig_category":"Unclassifiable Establishments",
    "sg:phone":"+33 3 20 32 87 70",
    "sg:province":"Nord Pas-de-Calais",
    "wof:name":"Choquet Bernard S.a.",
    "wof:placetype":"venue"
},
  "geometry": {"coordinates":[3.086884,50.543694],"type":"Point"}
}