{
  "type": "Feature",
  "properties": {
    "iso:country":"FR",
    "sg:address":"Rue Emile Rouz\u00e9",
    "sg:city":"Lille",
    "sg:orig_category":"Unclassifiable Establishments",
    "sg:phone":"+33 3 20 52 11 64",
    "sg:postcode":"59000",
    "sg:province":"Nord Pas-de-Calais",
    "wof:name":"M.c.n. Machines Outils S.a.r.l.",
    "wof:placetype":"venue"
},
  "geometry": {"coordinates":[3.051038,50.614277],"type":"Point"}
}