{
  "type": "Feature",
  "properties": {
    "iso:country":"FR",
    "sg:address":"Le Mons 19250 Meymac",
    "sg:classifiers":[
        {
            "category":"Farming",
            "subcategory":"Farm & Veterinary Services",
            "type":"Manufacturing & Wholesale Goods"
        }
    ],
    "sg:phone":"+33 5 55 95 25 73",
    "sg:postcode":"19250",
    "sg:province":"Limousin",
    "sg:tags":[
        "advice",
        "agriculture",
        "livestock",
        "business"
    ],
    "wof:name":"Sarl Marliac",
    "wof:placetype":"venue"
},
  "geometry": {"coordinates":[2.147815,45.53532],"type":"Point"}
}