{
  "type": "Feature",
  "properties": {
    "addr:full":"21 d'Arbrissel 49120 Chemill\u00e9 Pays de Loire 49120",
    "addr:housenumber":"21",
    "addr:postcode":"49120;49120",
    "addr:street":"D'Arbrissel",
    "iso:country":"FR",
    "sg:address":"21",
    "sg:city":"d'Arbrissel 49120 Chemill\u00e9",
    "sg:classifiers":[
        {
            "category":"Health Services",
            "subcategory":"Medical Lab",
            "type":"Services"
        }
    ],
    "sg:phone":"+33 2 41 30 32 34",
    "sg:postcode":"49120",
    "sg:province":"Pays de Loire",
    "sg:tags":[
        "chemical",
        "pharmaceutical",
        "pharmacy"
    ],
    "wof:name":"Cailleau Herboristerie",
    "wof:placetype":"venue"
},
  "geometry": {"coordinates":[-0.726068,47.210098],"type":"Point"}
}