{
  "type": "Feature",
  "properties": {
    "addr:full":"38 R De Gournay 60110 Lormaison Picardie 60110",
    "addr:housenumber":"38",
    "addr:postcode":"60110;60110",
    "addr:street":"R De Gournay",
    "iso:country":"FR",
    "sg:address":"38 R De Gournay 60110 Lormaison",
    "sg:classifiers":[
        {
            "category":"Manufacturing",
            "subcategory":"Textiles",
            "type":"Manufacturing & Wholesale Goods"
        }
    ],
    "sg:phone":"+33 3 44 22 18 55",
    "sg:postcode":"60110",
    "sg:province":"Picardie",
    "sg:tags":[
        "clothing",
        "accessory"
    ],
    "wof:name":"Etablissements Tabary Et Compagnie Sa",
    "wof:placetype":"venue"
},
  "geometry": {"coordinates":[2.11282,49.255997],"type":"Point"}
}