{
  "type": "Feature",
  "properties": {
    "addr:full":"29, Rue de la Poterie, 22300 Lannion Lannion Bretagne 22300",
    "addr:housenumber":"29",
    "addr:postcode":"22300;22300",
    "addr:street":"Rue De La Poterie",
    "iso:country":"FR",
    "sg:address":"29, Rue de la Poterie, 22300 Lannion",
    "sg:city":"Lannion",
    "sg:orig_category":"Unclassifiable Establishments",
    "sg:phone":"+33 2 96 37 46 41",
    "sg:postcode":"22300",
    "sg:province":"Bretagne",
    "wof:name":"O.e.e. Informatique S.a.r.l. - Organisation Et Equipement Entreprises",
    "wof:placetype":"venue"
},
  "geometry": {"coordinates":[-3.455459,48.734402],"type":"Point"}
}