{
  "type": "Feature",
  "properties": {
    "addr:full":"Zi Bayon 42150 La Ricamarie Rhone-Alpes 42150",
    "addr:postcode":"42150;42150",
    "addr:street":"Ricamarie Rhone-Alpes",
    "iso:country":"FR",
    "sg:address":"Zi Bayon 42150 La Ricamarie",
    "sg:orig_category":"Chemicals and Pharmaceuticals Chemistry - by-products Engines and parts Finished goods - metallic Me",
    "sg:phone":"+33 4 77 81 83 80",
    "sg:postcode":"42150",
    "sg:province":"Rhone-Alpes",
    "wof:name":"Fica Sa",
    "wof:placetype":"venue"
},
  "geometry": {"coordinates":[4.36615,45.40406],"type":"Point"}
}