{
  "type": "Feature",
  "properties": {
    "iso:country":"FR",
    "sg:address":"Z.I. Le Fief Du Parc 44190 GETIGNE",
    "sg:classifiers":[
        {
            "category":"Insurance",
            "subcategory":"Insurance Agent",
            "type":"Services"
        }
    ],
    "sg:phone":"+33 2 40 54 03 59",
    "sg:province":"Pays de Loire",
    "sg:tags":[
        "slipper",
        "woollen"
    ],
    "wof:name":"Soci\u00e9t\u00e9 La Coll\u00e9giale Sa",
    "wof:placetype":"venue"
},
  "geometry": {"coordinates":[-1.185822,47.044689],"type":"Point"}
}