{
  "type": "Feature",
  "properties": {
    "iso:country":"FR",
    "sg:address":"Av Blanqui 08120 Bogny Sur Meuse",
    "sg:city":"Bogny-sur-Meuse",
    "sg:classifiers":[
        {
            "category":"Building & Trades",
            "subcategory":"Construction",
            "type":"Services"
        }
    ],
    "sg:phone":"+33 3 24 32 13 66",
    "sg:postcode":"08120",
    "sg:province":"Champagne",
    "sg:tags":[
        "work",
        "public"
    ],
    "wof:name":"Ste Mecani General Reparat Tetes Filiere",
    "wof:placetype":"venue"
},
  "geometry": {"coordinates":[4.768861,49.853294],"type":"Point"}
}