{
  "type": "Feature",
  "properties": {
    "addr:full":"19 Bd Des Italiens 75002 Paris Ile de France 75002",
    "addr:housenumber":"19",
    "addr:postcode":"75002;75002",
    "addr:street":"Bd Des Italiens",
    "iso:country":"FR",
    "sg:address":"19 Bd Des Italiens 75002 Paris",
    "sg:classifiers":[
        {
            "category":"Banks & Credit Unions",
            "subcategory":"Financial Services",
            "type":"Services"
        }
    ],
    "sg:phone":"+33 1 42 95 70 00",
    "sg:postcode":"75002",
    "sg:province":"Ile de France",
    "sg:tags":[
        "banking",
        "insurance",
        "institution",
        "finance"
    ],
    "wof:name":"Credit Lyonnais",
    "wof:placetype":"venue"
},
  "geometry": {"coordinates":[2.336604,48.871296],"type":"Point"}
}