{
  "type": "Feature",
  "properties": {
    "iso:country":"FR",
    "sg:address":"ZA Sud",
    "sg:city":"Brian\u00e7on C\u00e9dex",
    "sg:orig_category":"Non-Classified Establishments",
    "sg:phone":"+33 4 92 21 09 48",
    "sg:postcode":"05103",
    "sg:province":"Basse Normandie",
    "wof:name":"Boulangerie Petit S.a.",
    "wof:placetype":"venue"
},
  "geometry": {"coordinates":[6.635696,44.896965],"type":"Point"}
}