{
  "type": "Feature",
  "properties": {
    "iso:country":"FR",
    "sg:address":"Grande Rue BP 18 50116 Mont St Michel",
    "sg:classifiers":[
        {
            "category":"Travel",
            "subcategory":"Hotels & Motels",
            "type":"Entertainment"
        }
    ],
    "sg:phone":"+33 2 33 89 02 02",
    "sg:province":"Haute Normandie",
    "sg:tags":[
        "hotels",
        "business",
        "restaurant"
    ],
    "wof:name":"Terrasses Poulard",
    "wof:placetype":"venue"
},
  "geometry": {"coordinates":[-1.51083,48.636082],"type":"Point"}
}