{
  "type": "Feature",
  "properties": {
    "addr:full":"7 Pl Du March\u00e9 Au Bois 24000 Perigueux P\u00e9rigueux Aquitaine 24000",
    "addr:housenumber":"7",
    "addr:postcode":"24000;24000",
    "addr:street":"Pl Du Marche\u0301 Au Bois",
    "iso:country":"FR",
    "sg:address":"7 Pl Du March\u00e9 Au Bois 24000 Perigueux",
    "sg:city":"P\u00e9rigueux",
    "sg:classifiers":[
        {
            "category":"Professional",
            "subcategory":"Business Services",
            "type":"Services"
        }
    ],
    "sg:phone":"+33 5 53 09 60 60",
    "sg:postcode":"24000",
    "sg:province":"Aquitaine",
    "sg:tags":[
        "body",
        "advice"
    ],
    "wof:name":"Association Des Oeuvres La\u00cfques De Perigueux",
    "wof:placetype":"venue"
},
  "geometry": {"coordinates":[0.722761,45.185497],"type":"Point"}
}