{
  "type": "Feature",
  "properties": {
    "addr:full":"16 rue de Normandie 94000 Creteil Ile de France",
    "addr:housenumber":"16",
    "addr:postcode":"94000;ile",
    "addr:street":"Rue De Normandie",
    "iso:country":"FR",
    "sg:address":"16 rue de Normandie 94000 Creteil",
    "sg:orig_category":"Protective Cabinets For Gas Cylinders",
    "sg:phone":"+33 1 42 07 98 87",
    "sg:province":"Ile de France",
    "wof:name":"Tableaux Services Sarl",
    "wof:placetype":"venue"
},
  "geometry": {"coordinates":[2.453044,48.79221],"type":"Point"}
}