{
  "type": "Feature",
  "properties": {
    "iso:country":"FR",
    "sg:address":"Rte de Clermont",
    "sg:city":"Beauvais",
    "sg:orig_category":"Unclassifiable Establishments",
    "sg:phone":"+33 3 44 10 51 00",
    "sg:postcode":"60000",
    "sg:province":"Picardie",
    "wof:name":"Bordage S.a.",
    "wof:placetype":"venue"
},
  "geometry": {"coordinates":[2.10356,49.431934],"type":"Point"}
}