{
  "type": "Feature",
  "properties": {
    "iso:country":"FR",
    "sg:address":"Av. Magudas - Parc H\u00e9liopolis B3",
    "sg:city":"M\u00e9rignac",
    "sg:orig_category":"Non-Classified Establishments",
    "sg:phone":"+33 5 56 34 32 59",
    "sg:postcode":"33700",
    "sg:province":"Aquitaine",
    "wof:name":"Airelec Industries S.a.",
    "wof:placetype":"venue"
},
  "geometry": {"coordinates":[-0.665269,44.858124],"type":"Point"}
}