{
  "type": "Feature",
  "properties": {
    "iso:country":"FR",
    "sg:address":"4 Rue Des Carmes",
    "sg:city":"Nancy",
    "sg:classifiers":[
        {
            "category":"Banks & Credit Unions",
            "subcategory":"Financial Services",
            "type":"Services"
        }
    ],
    "sg:phone":"+33 3 83 17 45 90",
    "sg:postcode":"54000",
    "sg:province":"Lorraine",
    "sg:tags":[
        "banking",
        "finance",
        "insurance"
    ],
    "wof:name":"Dexia Credit Local De France",
    "wof:placetype":"venue"
},
  "geometry": {"coordinates":[6.179877,48.692204],"type":"Point"}
}