{
  "type": "Feature",
  "properties": {
    "addr:full":"Cours 4 Septembre; Auriol Midi Pyr\u00e9n\u00e9es",
    "addr:housenumber":"4",
    "addr:street":"Cours;Septembre Auriol",
    "iso:country":"FR",
    "sg:address":"Cours 4 Septembre; Auriol",
    "sg:classifiers":[
        {
            "category":"Banks & Credit Unions",
            "subcategory":"Bank",
            "type":"Services"
        }
    ],
    "sg:phone":"+33 3342047093",
    "sg:province":"Midi Pyr\u00e9n\u00e9es",
    "wof:name":"Cr\u00e9dit Agricole",
    "wof:placetype":"venue"
},
  "geometry": {"coordinates":[5.634165,43.369308],"type":"Point"}
}