{
  "type": "Feature",
  "properties": {
    "iso:country":"FR",
    "sg:address":"35, Rue de Valenton - ZI des Petites Haies, 94015 Cr\u00e9teil C\u00e9dex",
    "sg:orig_category":"Non-Classified Establishments",
    "sg:phone":"+33 1 45 17 04 45",
    "sg:province":"\u00cele-de-France",
    "wof:name":"Visiograph S.a.",
    "wof:placetype":"venue"
},
  "geometry": {"coordinates":[2.45203,48.788891],"type":"Point"}
}