{
  "type": "Feature",
  "properties": {
    "addr:full":"B.P. 634, 95196 Goussainville^^1, Rue Len\u00f4tre, 95190 Goussainville Ile de France",
    "addr:housenumber":"b.p. 634",
    "addr:postcode":"95196;95190",
    "addr:street":"Rue Leno\u0302Tre",
    "iso:country":"FR",
    "sg:address":"B.P. 634, 95196 Goussainville^^1, Rue Len\u00f4tre, 95190 Goussainville",
    "sg:orig_category":"Non-Classified Establishments",
    "sg:phone":"+33 1 39 33 81 81",
    "sg:province":"Ile de France",
    "wof:name":"S\u00e9da S.a.",
    "wof:placetype":"venue"
},
  "geometry": {"coordinates":[2.47375,49.032452],"type":"Point"}
}