{
  "type": "Feature",
  "properties": {
    "addr:full":"5 Boulevard De La Republique Chalon Sur Saone Bourgogne 71100",
    "addr:housenumber":"5",
    "addr:postcode":"71100",
    "addr:street":"Boulevard De La",
    "iso:country":"FR",
    "sg:address":"5 Boulevard De La Republique",
    "sg:city":"Chalon Sur Saone",
    "sg:classifiers":[
        {
            "category":"Banks & Credit Unions",
            "subcategory":"Financial Services",
            "type":"Services"
        }
    ],
    "sg:phone":"+33 3 85 42 51 10",
    "sg:postcode":"71100",
    "sg:province":"Bourgogne",
    "sg:tags":[
        "banking",
        "finance",
        "insurance"
    ],
    "wof:name":"Lyonnaise De Banque Lb (lb)",
    "wof:placetype":"venue"
},
  "geometry": {"coordinates":[4.851991,46.783951],"type":"Point"}
}