{
  "type": "Feature",
  "properties": {
    "addr:full":"2 Rue Des P\u00e2tis 95520 Osny Ile de France",
    "addr:housenumber":"2",
    "addr:postcode":"95520",
    "addr:street":"Rue Des Pa\u0302Tis;Ile De France",
    "iso:country":"FR",
    "sg:address":"2 Rue Des P\u00e2tis 95520 Osny",
    "sg:classifiers":[
        {
            "category":"Manufacturing",
            "subcategory":"Printing",
            "type":"Manufacturing & Wholesale Goods"
        }
    ],
    "sg:phone":"+33 1 30 30 08 42",
    "sg:province":"Ile de France",
    "sg:tags":[
        "publishing"
    ],
    "wof:name":"Imprimerie De Busagny",
    "wof:placetype":"venue"
},
  "geometry": {"coordinates":[2.075003,49.053772],"type":"Point"}
}