{
  "type": "Feature",
  "properties": {
    "addr:full":"B.P. 57, 36102 Issoudun C\u00e9dex^^ZI, 36100 Issoudun Issoudun Centre 36100",
    "addr:postcode":"36102;36100;36100",
    "addr:street":"B.P. 57",
    "iso:country":"FR",
    "sg:address":"B.P. 57, 36102 Issoudun C\u00e9dex^^ZI, 36100 Issoudun",
    "sg:city":"Issoudun",
    "sg:orig_category":"Non-Classified Establishments",
    "sg:phone":"+33 2 54 21 07 77",
    "sg:postcode":"36100",
    "sg:province":"Centre",
    "wof:name":"Devin S.a.",
    "wof:placetype":"venue"
},
  "geometry": {"coordinates":[1.927415,46.825329],"type":"Point"}
}