{
  "type": "Feature",
  "properties": {
    "iso:country":"FR",
    "sg:address":"86, Rue de la Libert\u00e9 - Immeuble le Saint Georges, 38180 Seyssins",
    "sg:orig_category":"Unclassifiable Establishments",
    "sg:phone":"+33 4 76 49 76 76",
    "sg:province":"Rhone-Alpes",
    "wof:name":"A.e.m.c. S.a.r.l. - Assistance Electro-magn\u00e9tique Conseil",
    "wof:placetype":"venue"
},
  "geometry": {"coordinates":[5.696423,45.163475],"type":"Point"}
}