{
  "type": "Feature",
  "properties": {
    "iso:country":"FR",
    "sg:address":"12 pl Lucien de Gracia; Arcachon",
    "sg:city":"Arcachon",
    "sg:classifiers":[
        {
            "category":"Banks & Credit Unions",
            "subcategory":"Bank",
            "type":"Services"
        }
    ],
    "sg:phone":"+33 3356831368",
    "sg:postcode":"33120",
    "sg:province":"Aquitaine",
    "wof:name":"Caisse Cr\u00e9dit Mutuel D'arcachon",
    "wof:placetype":"venue"
},
  "geometry": {"coordinates":[-1.170627,44.66095],"type":"Point"}
}