{
  "type": "Feature",
  "properties": {
    "iso:country":"FR",
    "sg:address":"B.P. 81, 69493 Pierre B\u00e9nite C\u00e9dex^^15, Chemin d'Yvours, 69310 Pierre B\u00e9nite",
    "sg:orig_category":"Non-Classified Establishments",
    "sg:phone":"+33 4 78 50 26 19",
    "sg:postcode":"69310",
    "sg:province":"Rhone-Alpes",
    "wof:name":"Epiflore S.a.",
    "wof:placetype":"venue"
},
  "geometry": {"coordinates":[4.82466,45.702888],"type":"Point"}
}