{
  "type": "Feature",
  "properties": {
    "addr:full":"Route De Nerac Le Foureste 32100 Condom Midi Pyr\u00e9n\u00e9es",
    "addr:postcode":"32100",
    "addr:street":"Route De Nerac Le Foureste",
    "iso:country":"FR",
    "sg:address":"Route De Nerac Le Foureste 32100 Condom",
    "sg:classifiers":[
        {
            "category":"Manufacturing",
            "subcategory":"Paper Products",
            "type":"Manufacturing & Wholesale Goods"
        }
    ],
    "sg:phone":"+33 5 62 68 31 21",
    "sg:province":"Midi Pyr\u00e9n\u00e9es",
    "sg:tags":[
        "packaging",
        "material",
        "-",
        "cardboard"
    ],
    "wof:name":"Sa Pierre Lebbe Caisserie De L'armagnac",
    "wof:placetype":"venue"
},
  "geometry": {"coordinates":[0.334099,43.908184],"type":"Point"}
}