{
  "type": "Feature",
  "properties": {
    "iso:country":"FR",
    "sg:address":"94 rue de l'Amiral Courbet 59200 Tourcoing",
    "sg:classifiers":[
        {
            "category":"Manufacturing",
            "subcategory":"Textiles",
            "type":"Manufacturing & Wholesale Goods"
        }
    ],
    "sg:phone":"+33 3 20 76 39 94",
    "sg:postcode":"59200",
    "sg:province":"Nord Pas-de-Calais",
    "sg:tags":[
        "fibre",
        "natural"
    ],
    "wof:name":"Peignage Dumortier Sa",
    "wof:placetype":"venue"
},
  "geometry": {"coordinates":[3.161176,50.728142],"type":"Point"}
}