{
  "type": "Feature",
  "properties": {
    "addr:full":"B.P. 13, 13910 Maillane C\u00e9dex^^ZA la Praderie, 13910 Maillane Midi Pyr\u00e9n\u00e9es",
    "addr:postcode":"13910;13910",
    "addr:street":"B.P. 13",
    "iso:country":"FR",
    "sg:address":"B.P. 13, 13910 Maillane C\u00e9dex^^ZA la Praderie, 13910 Maillane",
    "sg:orig_category":"Non-Classified Establishments",
    "sg:phone":"+33 4 90 95 77 66",
    "sg:province":"Midi Pyr\u00e9n\u00e9es",
    "wof:name":"E.c.t. Industries S.a.",
    "wof:placetype":"venue"
},
  "geometry": {"coordinates":[4.78243,43.83231],"type":"Point"}
}