{
  "type": "Feature",
  "properties": {
    "addr:full":"7 Rue Louis Martin Zac Des Cerisiers 77400 Thorigny Sur Marne Ile de France",
    "addr:housenumber":"7",
    "addr:postcode":"77400",
    "addr:street":"Rue Louis Martin Zac Des Cerisiers",
    "iso:country":"FR",
    "sg:address":"7 Rue Louis Martin Zac Des Cerisiers 77400 Thorigny Sur Marne",
    "sg:classifiers":[
        {
            "category":"Wholesale",
            "subcategory":"Machinery & Supplies",
            "type":"Manufacturing & Wholesale Goods"
        }
    ],
    "sg:phone":"+33 1 64 02 88 88",
    "sg:province":"Ile de France",
    "sg:tags":[
        "equipment",
        "precision"
    ],
    "wof:name":"Paris Distribution Dpms",
    "wof:placetype":"venue"
},
  "geometry": {"coordinates":[2.671145,48.859123],"type":"Point"}
}