{
  "type": "Feature",
  "properties": {
    "addr:full":"Rue du Mouton Vierzon Centre 18108",
    "addr:postcode":"18108",
    "addr:street":"Rue Du Mouton",
    "iso:country":"FR",
    "sg:address":"Rue du Mouton",
    "sg:city":"Vierzon",
    "sg:orig_category":"Unclassifiable Establishments",
    "sg:phone":"+33 2 48 83 15 10",
    "sg:postcode":"18108",
    "sg:province":"Centre",
    "wof:name":"R.s.b.d. S.a.",
    "wof:placetype":"venue"
},
  "geometry": {"coordinates":[2.081986,47.230888],"type":"Point"}
}