{
  "type": "Feature",
  "properties": {
    "addr:full":"4, Bd de la Rochelle, 55000 Bar le Duc Lorraine",
    "addr:housenumber":"4",
    "addr:postcode":"55000",
    "addr:street":"Bd De La Rochelle;Le Duc",
    "iso:country":"FR",
    "sg:address":"4, Bd de la Rochelle, 55000 Bar le Duc",
    "sg:orig_category":"Unclassifiable Establishments",
    "sg:phone":"+33 3 29 77 51 00",
    "sg:province":"Lorraine",
    "wof:name":"Banque Snvb S.a.",
    "wof:placetype":"venue"
},
  "geometry": {"coordinates":[5.160429,48.773949],"type":"Point"}
}