{
  "type": "Feature",
  "properties": {
    "addr:full":"B.P. 592, 54009 Nancy C\u00e9dex^^87, Rue Mac Mahon, 54000 Nancy Lorraine",
    "addr:housenumber":"b.p. 592",
    "addr:postcode":"54009;54000",
    "addr:street":"Rue Mac Mahon",
    "iso:country":"FR",
    "sg:address":"B.P. 592, 54009 Nancy C\u00e9dex^^87, Rue Mac Mahon, 54000 Nancy",
    "sg:orig_category":"Non-Classified Establishments",
    "sg:phone":"+33 3 83 30 90 00",
    "sg:province":"Lorraine",
    "wof:name":"Olitec S.a.",
    "wof:placetype":"venue"
},
  "geometry": {"coordinates":[6.183405,48.689548],"type":"Point"}
}