{
  "type": "Feature",
  "properties": {
    "addr:full":"B.P. 323, 27703 Les Andelys C\u00e9dex^^32, Rue Dumont, 27700 Les Andelys Haute Normandie",
    "addr:housenumber":"b.p. 323",
    "addr:postcode":"27703;27700",
    "addr:street":"Rue Dumont;Haute Normandie",
    "iso:country":"FR",
    "sg:address":"B.P. 323, 27703 Les Andelys C\u00e9dex^^32, Rue Dumont, 27700 Les Andelys",
    "sg:orig_category":"Non-Classified Establishments",
    "sg:phone":"+33 2 32 54 21 68",
    "sg:province":"Haute Normandie",
    "wof:name":"Lain\u00e9 Minoterie S.a.",
    "wof:placetype":"venue"
},
  "geometry": {"coordinates":[1.463625,49.195496],"type":"Point"}
}