{
  "type": "Feature",
  "properties": {
    "iso:country":"FR",
    "sg:address":"B.P. 329, 38509 Voiron C\u00e9dex^^Rue du Docteur Butterlin, 38500 Voiron",
    "sg:orig_category":"Non-Classified Establishments",
    "sg:phone":"+33 4 76 66 65 65",
    "sg:province":"Rhone-Alpes",
    "wof:name":"Skis Rossignol S.a.",
    "wof:placetype":"venue"
},
  "geometry": {"coordinates":[5.621252,45.335114],"type":"Point"}
}