{
  "type": "Feature",
  "properties": {
    "iso:country":"FR",
    "sg:address":"25, Rue Robert Schuman - ZI, 77330 Ozoir la Ferri\u00e8re",
    "sg:orig_category":"Non-Classified Establishments",
    "sg:phone":"+33 1 60 02 97 77",
    "sg:postcode":"77330",
    "sg:province":"Ile de France",
    "wof:name":"Beuvant S.a.r.l.",
    "wof:placetype":"venue"
},
  "geometry": {"coordinates":[2.668752,48.762421],"type":"Point"}
}