{
  "type": "Feature",
  "properties": {
    "addr:full":"Aeroport Montpellier Mediterrannee 34134 Mauguio Languedoc-Roussillon",
    "addr:postcode":"34134",
    "addr:street":"Aeroport",
    "iso:country":"FR",
    "sg:address":"Aeroport Montpellier Mediterrannee 34134 Mauguio",
    "sg:classifiers":[
        {
            "category":"Banks & Credit Unions",
            "subcategory":"Investment Brokerage",
            "type":"Services"
        }
    ],
    "sg:phone":"+33 4 67 15 81 06",
    "sg:province":"Languedoc-Roussillon",
    "sg:tags":[
        "-",
        "transport",
        "related"
    ],
    "wof:name":"Geodis Logistics Sud",
    "wof:placetype":"venue"
},
  "geometry": {"coordinates":[4.0079,43.617867],"type":"Point"}
}