{
  "type": "Feature",
  "properties": {
    "addr:full":"route Nationale 51 08320 HIERGES Aubrives Champagne 08320",
    "addr:housenumber":"51",
    "addr:postcode":"08320;08320",
    "addr:street":"Route Nationale;Champagne",
    "iso:country":"FR",
    "sg:address":"route Nationale 51 08320 HIERGES",
    "sg:city":"Aubrives",
    "sg:classifiers":[
        {
            "category":"Farming",
            "subcategory":"Fish & Marine Products",
            "type":"Manufacturing & Wholesale Goods"
        }
    ],
    "sg:phone":"+33 3 24 41 56 56",
    "sg:postcode":"08320",
    "sg:province":"Champagne",
    "sg:tags":[
        "ceramic"
    ],
    "wof:name":"Pousseur R\u00e9fractaires Sa",
    "wof:placetype":"venue"
},
  "geometry": {"coordinates":[4.73813,50.087101],"type":"Point"}
}