{
  "type": "Feature",
  "properties": {
    "iso:country":"FR",
    "sg:address":"48, Rue des Colombes, 92600 Asni\u00e8res sur Seine",
    "sg:orig_category":"Unclassifiable Establishments",
    "sg:phone":"+33 1 47 90 61 25",
    "sg:province":"Ile de France",
    "wof:name":"S.i.m.p.r.a. S.a. - Soci\u00e9t\u00e9 Ind\u00e9pendante De Mat\u00e9riels Pour La Rationa",
    "wof:placetype":"venue"
},
  "geometry": {"coordinates":[2.281672,48.913708],"type":"Point"}
}