{
  "type": "Feature",
  "properties": {
    "iso:country":"FR",
    "sg:address":"5, Impasse Saint Paul - Le Saint Paul , 06400 Cannes",
    "sg:orig_category":"Non-Classified Establishments",
    "sg:phone":"+33 4 92 98 44 22",
    "sg:province":"Provence-Alpes-C\u00f4te d'Azur",
    "wof:name":"New Mode Services S.a.r.l.",
    "wof:placetype":"venue"
},
  "geometry": {"coordinates":[7.02038,43.562069],"type":"Point"}
}