{
  "type": "Feature",
  "properties": {
    "addr:full":"56 Rte Tarare 42360 Panissi\u00e8res Rhone-Alpes",
    "addr:housenumber":"56",
    "addr:postcode":"42360",
    "addr:street":"Rte Tarare",
    "iso:country":"FR",
    "sg:address":"56 Rte Tarare 42360 Panissi\u00e8res",
    "sg:classifiers":[
        {
            "category":"Professional",
            "type":"Services"
        }
    ],
    "sg:phone":"+33 4 77 28 60 20",
    "sg:province":"Rhone-Alpes",
    "sg:tags":[
        "transport",
        "road"
    ],
    "wof:name":"Fougere Marius Transports Sarl",
    "wof:placetype":"venue"
},
  "geometry": {"coordinates":[4.33865,45.794205],"type":"Point"}
}