{
  "type": "Feature",
  "properties": {
    "iso:country":"FR",
    "sg:address":"10, Av. Eiffel, 77220 Gretz Armainvilliers",
    "sg:orig_category":"Unclassifiable Establishments",
    "sg:phone":"+33 1 64 06 40 80",
    "sg:province":"Ile de France",
    "wof:name":"Telemac S.a.",
    "wof:placetype":"venue"
},
  "geometry": {"coordinates":[2.731246,48.735142],"type":"Point"}
}