{
  "type": "Feature",
  "properties": {
    "addr:full":"8 Rue Edouard Branly 37550 St Avertin Saint-Avertin Centre 37550",
    "addr:housenumber":"8;saint-avertin",
    "addr:postcode":"37550;37550",
    "addr:street":"Rue Edouard Branly",
    "iso:country":"FR",
    "sg:address":"8 Rue Edouard Branly 37550 St Avertin",
    "sg:city":"Saint-Avertin",
    "sg:classifiers":[
        {
            "category":"Manufacturing",
            "subcategory":"Tools & Machinery",
            "type":"Manufacturing & Wholesale Goods"
        }
    ],
    "sg:phone":"+33 2 47 48 86 86",
    "sg:postcode":"37550",
    "sg:province":"Centre",
    "sg:tags":[
        "metallurgy",
        "metal",
        "-",
        "metalworking",
        "machine",
        "equipment",
        "engineering",
        "mechanical"
    ],
    "wof:name":"Stellram",
    "wof:placetype":"venue"
},
  "geometry": {"coordinates":[0.730205,47.345043],"type":"Point"}
}