{
  "type": "Feature",
  "properties": {
    "addr:full":"2, Chemin des Glirettes - ZI, 95500 Le Thillay Ile de France",
    "addr:housenumber":"2",
    "addr:postcode":"95500",
    "addr:street":"Chemin Des Glirettes Zi",
    "iso:country":"FR",
    "sg:address":"2, Chemin des Glirettes - ZI, 95500 Le Thillay",
    "sg:orig_category":"Unclassifiable Establishments",
    "sg:phone":"+33 1 34 38 80 40",
    "sg:province":"Ile de France",
    "wof:name":"Jacret S.a.",
    "wof:placetype":"venue"
},
  "geometry": {"coordinates":[2.449633,48.986462],"type":"Point"}
}