{
  "type": "Feature",
  "properties": {
    "addr:full":"60 Jardin Valmy 92918 Paris La D\u00e9fense Poitou-Charentes",
    "addr:housenumber":"60",
    "addr:postcode":"92918",
    "addr:street":"Jardin Valmy",
    "iso:country":"FR",
    "sg:address":"60 Jardin Valmy 92918 Paris La D\u00e9fense",
    "sg:classifiers":[
        {
            "category":"Travel",
            "subcategory":"Hotels & Motels",
            "type":"Entertainment"
        }
    ],
    "sg:phone":"+33 1 41 97 50 50",
    "sg:province":"Poitou-Charentes",
    "sg:tags":[
        "hotels",
        "business",
        "restaurant"
    ],
    "wof:name":"Renaissance Paris Hotel La Defense",
    "wof:placetype":"venue"
},
  "geometry": {"coordinates":[2.24119,48.888939],"type":"Point"}
}