{
  "type": "Feature",
  "properties": {
    "addr:full":"20 rue de la Corderie 75003 Paris Ile de France",
    "addr:housenumber":"20",
    "addr:postcode":"75003",
    "addr:street":"Rue De La Corderie",
    "iso:country":"FR",
    "sg:address":"20 rue de la Corderie 75003 Paris",
    "sg:classifiers":[
        {
            "category":"Shopping",
            "subcategory":"Clothing, Apparel, & Fashions",
            "type":"Retail Goods"
        }
    ],
    "sg:phone":"+33 1 42 72 45 78",
    "sg:province":"Ile de France",
    "sg:tags":[
        "weather",
        "clothing",
        "rain",
        "wet"
    ],
    "wof:name":"Brett Sarl",
    "wof:placetype":"venue"
},
  "geometry": {"coordinates":[2.362431,48.865402],"type":"Point"}
}