{
  "type": "Feature",
  "properties": {
    "addr:full":"167, Rue de Gode, 95110 Sannois Ile de France",
    "addr:housenumber":"167",
    "addr:postcode":"95110;ile",
    "addr:street":"Rue De Gode",
    "iso:country":"FR",
    "sg:address":"167, Rue de Gode, 95110 Sannois",
    "sg:orig_category":"Unclassifiable Establishments",
    "sg:phone":"+33 1 34 10 85 12",
    "sg:province":"Ile de France",
    "wof:name":"Ermo S.a. - Etude R\u00e9alisation Moule Industriel Chaussure",
    "wof:placetype":"venue"
},
  "geometry": {"coordinates":[2.273952,48.964024],"type":"Point"}
}