{
  "type": "Feature",
  "properties": {
    "iso:country":"FR",
    "sg:address":"B.P. 77, 01212 Ferney Voltaire C\u00e9dex^^Av. du Jura, 01210 Ferney Voltaire",
    "sg:orig_category":"Non-Classified Establishments",
    "sg:phone":"+33 4 50 40 77 90",
    "sg:province":"Rhone-Alpes",
    "wof:name":"Voltaire Palace H\u00f4tel S.a.",
    "wof:placetype":"venue"
},
  "geometry": {"coordinates":[6.09829,46.272331],"type":"Point"}
}