{
  "type": "Feature",
  "properties": {
    "iso:country":"FR",
    "sg:address":"B.P. 244, 38202 Vienne C\u00e9dex^^48, Av. du G\u00e9n\u00e9ral Leclerc, 38200 Vienne",
    "sg:orig_category":"Non-Classified Establishments",
    "sg:phone":"+33 4 74 85 08 57",
    "sg:postcode":"38200",
    "sg:province":"Rhone-Alpes",
    "wof:name":"Comptoir Des Viandes Godel S.a.",
    "wof:placetype":"venue"
},
  "geometry": {"coordinates":[4.942395,45.467644],"type":"Point"}
}