{
  "type": "Feature",
  "properties": {
    "iso:country":"FR",
    "sg:address":"109 Avenue Du Marechal Foch 78300 Poissy",
    "sg:classifiers":[
        {
            "category":"Home & Garden",
            "subcategory":"Furniture",
            "type":"Retail Goods"
        }
    ],
    "sg:phone":"+33 1 39 65 05 69",
    "sg:postcode":"78300",
    "sg:province":"Ile de France",
    "sg:tags":[
        "household",
        "wood"
    ],
    "wof:name":"Le Corre Gilles",
    "wof:placetype":"venue"
},
  "geometry": {"coordinates":[2.053338,48.931259],"type":"Point"}
}