{
  "type": "Feature",
  "properties": {
    "addr:full":"13 avenue de la Trentaine 77500 Chelles Ile de France",
    "addr:housenumber":"13",
    "addr:postcode":"77500;ile",
    "addr:street":"Avenue De La Trentaine",
    "iso:country":"FR",
    "sg:address":"13 avenue de la Trentaine 77500 Chelles",
    "sg:classifiers":[
        {
            "category":"Manufacturing",
            "subcategory":"Motor Vehicles & Parts",
            "type":"Manufacturing & Wholesale Goods"
        }
    ],
    "sg:phone":"+33 1 60 08 71 71",
    "sg:province":"Ile de France",
    "sg:tags":[
        "precision",
        "mechanic"
    ],
    "wof:name":"Moderne M\u00e9canique Sa",
    "wof:placetype":"venue"
},
  "geometry": {"coordinates":[2.600322,48.869545],"type":"Point"}
}