{
  "type": "Feature",
  "properties": {
    "addr:full":"B.P. 51, 92354 Le Plessis Robinson C\u00e9dex^^7, Av. Descartes, 92350 Le Plessis Robinson Ile de France",
    "addr:postcode":"92354;92350",
    "addr:street":"B.P. 51;Av. Descartes",
    "iso:country":"FR",
    "sg:address":"B.P. 51, 92354 Le Plessis Robinson C\u00e9dex^^7, Av. Descartes, 92350 Le Plessis Robinson",
    "sg:orig_category":"Non-Classified Establishments",
    "sg:phone":"+33 1 69 74 85 50",
    "sg:province":"Ile de France",
    "wof:name":"M\u00e9caelec S.a.r.l.",
    "wof:placetype":"venue"
},
  "geometry": {"coordinates":[2.259315,48.779976],"type":"Point"}
}