{
  "type": "Feature",
  "properties": {
    "iso:country":"FR",
    "sg:address":"32 Av Europe 78148 V\u00e9lizy",
    "sg:classifiers":[
        {
            "category":"Utilities",
            "subcategory":"Telephone",
            "type":"Services"
        }
    ],
    "sg:phone":"+33 1 39 26 50 00",
    "sg:province":"Haute Normandie",
    "sg:tags":[
        "telecommunication"
    ],
    "wof:name":"Softway Groupe",
    "wof:placetype":"venue"
},
  "geometry": {"coordinates":[7.85784,52.976181],"type":"Point"}
}