{
  "type": "Feature",
  "properties": {
    "addr:full":"61 Av De La Villette 94637 Rungis Vill\u00e9 Alsace 67220",
    "addr:postcode":"94637;67220",
    "addr:street":"61 Av De La Villette",
    "iso:country":"FR",
    "sg:address":"61 Av De La Villette 94637 Rungis",
    "sg:city":"Vill\u00e9",
    "sg:classifiers":[
        {
            "category":"Farming",
            "subcategory":"Farm",
            "type":"Manufacturing & Wholesale Goods"
        }
    ],
    "sg:phone":"+33 1 46 87 12 30",
    "sg:postcode":"67220",
    "sg:province":"Alsace",
    "sg:tags":[
        "horticulture",
        "agriculture",
        "livestock"
    ],
    "wof:name":"Florimex Rungis Sarl",
    "wof:placetype":"venue"
},
  "geometry": {"coordinates":[2.35325,48.751419],"type":"Point"}
}