{
  "type": "Feature",
  "properties": {
    "iso:country":"FR",
    "sg:address":"11 B Rue D Aguesseau 75008 Paris",
    "sg:classifiers":[
        {
            "category":"Professional",
            "subcategory":"Printing & Photocopies",
            "type":"Services"
        }
    ],
    "sg:phone":"+33 1 53 43 82 32",
    "sg:province":"Ile de France",
    "sg:tags":[
        "publishing"
    ],
    "wof:name":"Sonopress France Societe Par Actions Simplifiee",
    "wof:placetype":"venue"
},
  "geometry": {"coordinates":[2.31931,48.870438],"type":"Point"}
}