{
  "type": "Feature",
  "properties": {
    "iso:country":"FR",
    "sg:address":"16, Rue Pierre Nobel - ZAC, 45700 Villemandeur",
    "sg:city":"Villemandeur",
    "sg:orig_category":"Unclassifiable Establishments",
    "sg:phone":"+33 2 38 85 46 70",
    "sg:postcode":"45700",
    "sg:province":"Centre",
    "wof:name":"Plus 60 S.a.",
    "wof:placetype":"venue"
},
  "geometry": {"coordinates":[2.720284,47.976044],"type":"Point"}
}