{
  "type": "Feature",
  "properties": {
    "addr:full":"13, Rue Baudin, 93100 Montreuil Ile de France",
    "addr:housenumber":"13",
    "addr:postcode":"93100",
    "addr:street":"Rue Baudin",
    "iso:country":"FR",
    "sg:address":"13, Rue Baudin, 93100 Montreuil",
    "sg:orig_category":"Unclassifiable Establishments",
    "sg:phone":"+33 1 42 87 37 36",
    "sg:province":"Ile de France",
    "wof:name":"Dumont S.a.",
    "wof:placetype":"venue"
},
  "geometry": {"coordinates":[2.447308,48.867783],"type":"Point"}
}