{
  "type": "Feature",
  "properties": {
    "addr:full":"B.P. 135, 59820 Gravelines^^Rue de l'Industrie, 59820 Gravelines Nord Pas-de-Calais",
    "addr:housenumber":"b.p. 135",
    "addr:postcode":"59820;59820",
    "addr:street":"L'Industrie",
    "iso:country":"FR",
    "sg:address":"B.P. 135, 59820 Gravelines^^Rue de l'Industrie, 59820 Gravelines",
    "sg:orig_category":"Non-Classified Establishments",
    "sg:phone":"+33 3 28 23 81 40",
    "sg:province":"Nord Pas-de-Calais",
    "wof:name":"Ultra Sons Nettoyage S.a.r.l.",
    "wof:placetype":"venue"
},
  "geometry": {"coordinates":[2.121793,50.977947],"type":"Point"}
}