{
  "type": "Feature",
  "properties": {
    "iso:country":"FR",
    "sg:address":"Rte Philippeville 08600 Givet",
    "sg:city":"Charnois",
    "sg:classifiers":[
        {
            "category":"Manufacturing",
            "subcategory":"Chemicals & Compounds",
            "type":"Manufacturing & Wholesale Goods"
        }
    ],
    "sg:phone":"+33 3 24 42 35 70",
    "sg:postcode":"08600",
    "sg:province":"Champagne",
    "sg:tags":[
        "pharmaceutical",
        "chemistry",
        "-",
        "by-product"
    ],
    "wof:name":"Sorochimie Sa",
    "wof:placetype":"venue"
},
  "geometry": {"coordinates":[4.797165,50.148483],"type":"Point"}
}