{
  "type": "Feature",
  "properties": {
    "addr:full":"66 R du Faubourg Saint-Martin 75010 Paris Ile de France 75010",
    "addr:housenumber":"66",
    "addr:postcode":"75010;75010",
    "addr:street":"R Du Faubourg Saint-Martin",
    "iso:country":"FR",
    "sg:address":"66 R du Faubourg Saint-Martin 75010 Paris",
    "sg:classifiers":[
        {
            "category":"Shopping",
            "subcategory":"Clothing, Apparel, & Fashions",
            "type":"Retail Goods"
        }
    ],
    "sg:phone":"+33 1 42 41 19 14",
    "sg:postcode":"75010",
    "sg:province":"Ile de France",
    "sg:tags":[
        "blouse",
        "ladies'",
        "dress"
    ],
    "wof:name":"Jean Coste Sarl",
    "wof:placetype":"venue"
},
  "geometry": {"coordinates":[2.357153,48.871376],"type":"Point"}
}