{
  "type": "Feature",
  "properties": {
    "addr:full":"33 Arloing 69009 Lyon Rhone-Alpes 69009",
    "addr:housenumber":"33",
    "addr:postcode":"69009;69009",
    "addr:street":"Arloing",
    "iso:country":"FR",
    "sg:address":"33",
    "sg:city":"Arloing 69009 Lyon",
    "sg:classifiers":[
        {
            "category":"Manufacturing",
            "subcategory":"Metals",
            "type":"Manufacturing & Wholesale Goods"
        }
    ],
    "sg:phone":"+33 4 78 64 19 27",
    "sg:postcode":"69009",
    "sg:province":"Rhone-Alpes",
    "sg:tags":[
        "metallurgy",
        "steel",
        "metalworking"
    ],
    "wof:name":"Fonderie D'art Et De Precision",
    "wof:placetype":"venue"
},
  "geometry": {"coordinates":[4.8117,45.770836],"type":"Point"}
}