{
  "type": "Feature",
  "properties": {
    "addr:full":"5 Rue St Philippe Du Roule 75008 Paris Ile de France 75008",
    "addr:housenumber":"5",
    "addr:postcode":"75008;75008",
    "addr:street":"Rue St Philippe Du Roule",
    "iso:country":"FR",
    "sg:address":"5 Rue St Philippe Du Roule 75008 Paris",
    "sg:classifiers":[
        {
            "category":"Communications",
            "type":"Services"
        }
    ],
    "sg:phone":"+33 1 49 53 96 81",
    "sg:postcode":"75008",
    "sg:province":"Ile de France",
    "sg:tags":[
        "translation",
        "training",
        "interpretation",
        "advice",
        "business"
    ],
    "wof:name":"Adele Sa",
    "wof:placetype":"venue"
},
  "geometry": {"coordinates":[2.308722,48.873028],"type":"Point"}
}