{
  "type": "Feature",
  "properties": {
    "iso:country":"FR",
    "sg:address":"2 Rue Gustave Courbet 25660 Sa\u00f4ne",
    "sg:classifiers":[
        {
            "category":"Manufacturing",
            "subcategory":"Rubber & Plastics",
            "type":"Manufacturing & Wholesale Goods"
        }
    ],
    "sg:phone":"+33 3 81 55 83 55",
    "sg:province":"Franche Comt\u00e9",
    "wof:name":"Inodip",
    "wof:placetype":"venue"
},
  "geometry": {"coordinates":[6.101324,47.206905],"type":"Point"}
}