{
  "type": "Feature",
  "properties": {
    "addr:full":"19, Rue Mohamed Elaoufi, 27370 Tourville la Campagne Haute Normandie",
    "addr:housenumber":"19",
    "addr:postcode":"27370",
    "addr:street":"Rue Mohamed Elaoufi",
    "iso:country":"FR",
    "sg:address":"19, Rue Mohamed Elaoufi, 27370 Tourville la Campagne",
    "sg:orig_category":"Unclassifiable Establishments",
    "sg:phone":"+33 2 32 29 81 87",
    "sg:province":"Haute Normandie",
    "wof:name":"J.c. Poyer Charpente S.a.r.l.",
    "wof:placetype":"venue"
},
  "geometry": {"coordinates":[0.90167,49.238602],"type":"Point"}
}