{
  "type": "Feature",
  "properties": {
    "addr:full":"B.P. 6, 76280 Criquetot l'Esneval^^7, Rue du 8 Mai, 76280 Criquetot l'Esneval Haute Normandie",
    "addr:housenumber":"6;^ 7",
    "addr:postcode":"76280;^;76280",
    "addr:street":"B.P.;Rue Du 8 Mai;Haute Normandie",
    "iso:country":"FR",
    "sg:address":"B.P. 6, 76280 Criquetot l'Esneval^^7, Rue du 8 Mai, 76280 Criquetot l'Esneval",
    "sg:orig_category":"Non-Classified Establishments",
    "sg:phone":"+33 2 35 27 23 63",
    "sg:province":"Haute Normandie",
    "wof:name":"Golain Imprimerie",
    "wof:placetype":"venue"
},
  "geometry": {"coordinates":[0.266879,49.644028],"type":"Point"}
}