{
  "type": "Feature",
  "properties": {
    "iso:country":"FR",
    "sg:address":"790, Av. de la Qui\u00e8ra, 06370 Mouans Sartoux",
    "sg:orig_category":"Non-Classified Establishments",
    "sg:phone":"+33 4 92 28 26 00",
    "sg:province":"Midi Pyr\u00e9n\u00e9es",
    "wof:name":"Azur Cosm\u00e9tic S.a.r.l.",
    "wof:placetype":"venue"
},
  "geometry": {"coordinates":[6.9561,43.606789],"type":"Point"}
}