{
  "type": "Feature",
  "properties": {
    "addr:full":"Rue Maryse Bastie Zac De Maignon Lot C 10 64600 Anglet Anglet Aquitaine 64600",
    "addr:housenumber":"lot c 10",
    "addr:postcode":"64600;64600",
    "addr:street":"Rue Maryse Bastie Zac De Maignon",
    "iso:country":"FR",
    "sg:address":"Rue Maryse Bastie Zac De Maignon Lot C 10 64600 Anglet",
    "sg:city":"Anglet",
    "sg:classifiers":[
        {
            "category":"Shopping",
            "type":"Retail Goods"
        }
    ],
    "sg:phone":"+33 5 59 31 36 44",
    "sg:postcode":"64600",
    "sg:province":"Aquitaine",
    "sg:tags":[
        "metallurgy",
        "finished",
        "-",
        "metalworking",
        "metallic"
    ],
    "wof:name":"Armafer",
    "wof:placetype":"venue"
},
  "geometry": {"coordinates":[-1.514707,43.481705],"type":"Point"}
}