{
  "type": "Feature",
  "properties": {
    "iso:country":"FR",
    "sg:address":"26 Rue Lacla\u00fc 64800 Nay",
    "sg:city":"Nay",
    "sg:classifiers":[
        {
            "category":"Professional",
            "subcategory":"Engineering",
            "type":"Services"
        }
    ],
    "sg:phone":"+33 5 59 61 38 21",
    "sg:postcode":"64800",
    "sg:province":"Aquitaine",
    "sg:tags":[
        "machine",
        "-",
        "mechanical"
    ],
    "wof:name":"Larroze Sarl",
    "wof:placetype":"venue"
},
  "geometry": {"coordinates":[-0.257454,43.177189],"type":"Point"}
}