{
  "type": "Feature",
  "properties": {
    "iso:country":"FR",
    "sg:address":"3, Rue de la Plaine - ZI des Bauches, 38640 Claix",
    "sg:orig_category":"Non-Classified Establishments",
    "sg:phone":"+33 4 76 98 78 10",
    "sg:province":"Rhone-Alpes",
    "wof:name":"Moulage Plastiques Industriels S.a.r.l.",
    "wof:placetype":"venue"
},
  "geometry": {"coordinates":[5.672615,45.120255],"type":"Point"}
}