{
  "type": "Feature",
  "properties": {
    "addr:full":"13/17, Rue d'Epluches, 95310 Saint Ouen l'Aum\u00f4ne Ile de France",
    "addr:housenumber":"13 / 17",
    "addr:postcode":"95310",
    "addr:street":"Rue D'Epluches",
    "iso:country":"FR",
    "sg:address":"13/17, Rue d'Epluches, 95310 Saint Ouen l'Aum\u00f4ne",
    "sg:orig_category":"Unclassifiable Establishments",
    "sg:phone":"+33 1 34 21 33 33",
    "sg:province":"Ile de France",
    "wof:name":"S.a.f. S.a. - La Soudure Autog\u00e8ne Fran\u00e7aise",
    "wof:placetype":"venue"
},
  "geometry": {"coordinates":[0.490902,48.605492],"type":"Point"}
}