{
  "type": "Feature",
  "properties": {
    "iso:country":"FR",
    "sg:address":"Zac Montimaran 34500 B\u00e9ziers",
    "sg:classifiers":[
        {
            "category":"Shopping",
            "subcategory":"Clothing, Apparel, & Fashions",
            "type":"Retail Goods"
        }
    ],
    "sg:phone":"+33 4 67 76 25 75",
    "sg:postcode":"34500",
    "sg:province":"Languedoc-Roussillon",
    "sg:tags":[
        "textile",
        "clothing",
        "clothes"
    ],
    "wof:name":"Kiabi",
    "wof:placetype":"venue"
},
  "geometry": {"coordinates":[3.216105,43.344234],"type":"Point"}
}