{
  "type": "Feature",
  "properties": {
    "iso:country":"FR",
    "sg:address":"472 Rue Paul Claudel 69651 Villefranche Sur Sa\u00f4ne",
    "sg:city":"Vill\u00e9",
    "sg:classifiers":[
        {
            "category":"Shopping",
            "type":"Retail Goods"
        }
    ],
    "sg:phone":"+33 4 74 02 72 49",
    "sg:postcode":"67220",
    "sg:province":"Alsace",
    "sg:tags":[
        "metallurgy",
        "finished",
        "-",
        "metalworking",
        "metallic"
    ],
    "wof:name":"Titan Aviation Sa",
    "wof:placetype":"venue"
},
  "geometry": {"coordinates":[4.722757,45.978996],"type":"Point"}
}