{
  "type": "Feature",
  "properties": {
    "iso:country":"FR",
    "sg:address":"1 Rue Georges Guynemer 87220 Feytiat",
    "sg:classifiers":[
        {
            "category":"Shopping",
            "subcategory":"Computers & Home Electronics",
            "type":"Retail Goods"
        }
    ],
    "sg:phone":"+33 5 55 31 01 50",
    "sg:postcode":"87220",
    "sg:province":"Limousin",
    "sg:tags":[
        "electronic",
        "electrical",
        "equipment"
    ],
    "wof:name":"Rexel Celm",
    "wof:placetype":"venue"
},
  "geometry": {"coordinates":[1.29428,45.802608],"type":"Point"}
}