{
  "type": "Feature",
  "properties": {
    "iso:country":"FR",
    "sg:address":"5 R De La Liberation 44110 Chateaubriant",
    "sg:classifiers":[
        {
            "category":"Wholesale",
            "subcategory":"Medical Equipment & Supplies",
            "type":"Manufacturing & Wholesale Goods"
        }
    ],
    "sg:phone":"+33 2 40 81 01 68",
    "sg:postcode":"44110",
    "sg:province":"Pays de Loire",
    "sg:tags":[
        "instrument",
        "health",
        "-",
        "precision"
    ],
    "wof:name":"C Fetis Claude",
    "wof:placetype":"venue"
},
  "geometry": {"coordinates":[-1.377865,47.715843],"type":"Point"}
}