{
  "type": "Feature",
  "properties": {
    "addr:full":"Rte de Craon - ZA Ballots Pays de Loire 53350",
    "addr:postcode":"53350",
    "addr:street":"Rte De Craon Za Ballots Pays",
    "iso:country":"FR",
    "sg:address":"Rte de Craon - ZA",
    "sg:city":"Ballots",
    "sg:orig_category":"Unclassifiable Establishments",
    "sg:phone":"+33 2 43 06 52 52",
    "sg:postcode":"53350",
    "sg:province":"Pays de Loire",
    "wof:name":"Soci\u00e9t\u00e9 De Voyages Benatre S.a.r.l.",
    "wof:placetype":"venue"
},
  "geometry": {"coordinates":[-1.128019,47.879379],"type":"Point"}
}