{
  "type": "Feature",
  "properties": {
    "iso:country":"FR",
    "sg:address":"B.P. 66, 59111 Hordain^^Rue Lucien Sampaix, 59111 Hordain",
    "sg:orig_category":"Non-Classified Establishments",
    "sg:phone":"+33 3 27 27 79 79",
    "sg:province":"Nord Pas-de-Calais",
    "wof:name":"Sergui E.u.r.l.",
    "wof:placetype":"venue"
},
  "geometry": {"coordinates":[3.31871,50.282871],"type":"Point"}
}