{
  "type": "Feature",
  "properties": {
    "iso:country":"FR",
    "sg:address":"23, Rue Ferdinand Hamelin, 51450 B\u00e9theny",
    "sg:orig_category":"Non-Classified Establishments",
    "sg:phone":"+33 3 26 47 14 99",
    "sg:province":"Champagne",
    "wof:name":"Imprimerie Des Docks S.a.r.l.",
    "wof:placetype":"venue"
},
  "geometry": {"coordinates":[4.044329,49.271381],"type":"Point"}
}