{
  "type": "Feature",
  "properties": {
    "iso:country":"FR",
    "sg:address":"3, Bd. Amp\u00e8re - ZI Nord, 13014 Marseille",
    "sg:orig_category":"Non-Classified Establishments",
    "sg:phone":"+33 4 91 61 83 00",
    "sg:province":"Provence-Alpes-C\u00f4te d'Azur",
    "wof:name":"Soci\u00e9t\u00e9 Nouvelle De Transport Comett S.a.",
    "wof:placetype":"venue"
},
  "geometry": {"coordinates":[5.382571,43.334103],"type":"Point"}
}