{
  "type": "Feature",
  "properties": {
    "addr:full":"18/20, Av. Edouard Herriot - B\u00e2t Kl\u00e9ber, 92350 Le Plessis Robinson Ile de France 92350",
    "addr:housenumber":"18 / 20;ba\u0302t",
    "addr:postcode":"92350;92350",
    "addr:street":"Av. Edouard Herriot",
    "iso:country":"FR",
    "sg:address":"18/20, Av. Edouard Herriot - B\u00e2t Kl\u00e9ber, 92350 Le Plessis Robinson",
    "sg:orig_category":"Non-Classified Establishments",
    "sg:phone":"+33 1 45 37 05 05",
    "sg:postcode":"92350",
    "sg:province":"Ile de France",
    "wof:name":"Cotecma Inspection France S.a.r.l.",
    "wof:placetype":"venue"
},
  "geometry": {"coordinates":[2.25248,48.782349],"type":"Point"}
}