{
  "type": "Feature",
  "properties": {
    "addr:full":"48 Boulevard Du Mar\u00e9chal Foch Angers Pays de Loire 49100",
    "addr:housenumber":"48",
    "addr:postcode":"49100",
    "addr:street":"Boulevard Du Mare\u0301Chal Foch",
    "iso:country":"FR",
    "sg:address":"48 Boulevard Du Mar\u00e9chal Foch",
    "sg:city":"Angers",
    "sg:classifiers":[
        {
            "category":"Banks & Credit Unions",
            "subcategory":"Financial Services",
            "type":"Services"
        }
    ],
    "sg:phone":"+33 2 41 86 43 43",
    "sg:postcode":"49100",
    "sg:province":"Pays de Loire",
    "sg:tags":[
        "banking",
        "finance",
        "insurance"
    ],
    "wof:name":"Credit Lyonnais",
    "wof:placetype":"venue"
},
  "geometry": {"coordinates":[-0.5514,47.467865],"type":"Point"}
}