{
  "type": "Feature",
  "properties": {
    "addr:full":"131, Av. Corot, 13013 Marseille Provence-Alpes-C\u00f4te d'Azur",
    "addr:postcode":"13013",
    "addr:street":"131 Av. Corot",
    "iso:country":"FR",
    "sg:address":"131, Av. Corot, 13013 Marseille",
    "sg:orig_category":"Unclassifiable Establishments",
    "sg:phone":"+33 4 91 10 02 00",
    "sg:province":"Provence-Alpes-C\u00f4te d'Azur",
    "wof:name":"Panzani S.a.",
    "wof:placetype":"venue"
},
  "geometry": {"coordinates":[5.403259,43.324207],"type":"Point"}
}