{
  "type": "Feature",
  "properties": {
    "iso:country":"FR",
    "sg:address":"B.P. 28, 67320 Drulingen^^3, Rue de Bettwiller, 67320 Drulingen",
    "sg:city":"Drulingen",
    "sg:orig_category":"Non-Classified Establishments",
    "sg:phone":"+33 3 88 01 68 00",
    "sg:postcode":"67320",
    "sg:province":"Alsace",
    "wof:name":"Sotralentz Packaging S.a.",
    "wof:placetype":"venue"
},
  "geometry": {"coordinates":[7.189794,48.866207],"type":"Point"}
}