{
  "type": "Feature",
  "properties": {
    "addr:full":"Rue Fr\u00e9d\u00e9ric Niemann - Z.I. Sarreguemines Lorraine 57200",
    "addr:postcode":"57200",
    "addr:street":"Rue Fre\u0301De\u0301Ric Niemann Z.I.",
    "iso:country":"FR",
    "sg:address":"Rue Fr\u00e9d\u00e9ric Niemann - Z.I.",
    "sg:city":"Sarreguemines",
    "sg:orig_category":"Non-Classified Establishments",
    "sg:phone":"+33 3 87 95 26 15",
    "sg:postcode":"57200",
    "sg:province":"Lorraine",
    "wof:name":"Transak Transports S.a.",
    "wof:placetype":"venue"
},
  "geometry": {"coordinates":[7.104245,49.106167],"type":"Point"}
}