{
  "type": "Feature",
  "properties": {
    "iso:country":"FR",
    "sg:address":"37 Rue De Stalingrad 76200 Dieppe",
    "sg:orig_category":"Business advice and other services Goods handling - material and equipment Mechanical Engineering - ",
    "sg:phone":"+33 2 35 06 38 70",
    "sg:postcode":"76200",
    "sg:province":"Haute Normandie",
    "wof:name":"Societe Cooperative Ouvriere De Production",
    "wof:placetype":"venue"
},
  "geometry": {"coordinates":[1.083309,49.916485],"type":"Point"}
}