{
  "type": "Feature",
  "properties": {
    "addr:full":"Av. Belle Fontaine Cesson S\u00e9vign\u00e9 Bretagne 35510",
    "addr:postcode":"35510",
    "addr:street":"Av. Belle Fontaine;Se\u0301Vigne\u0301",
    "iso:country":"FR",
    "sg:address":"Av. Belle Fontaine",
    "sg:city":"Cesson S\u00e9vign\u00e9",
    "sg:orig_category":"Unclassifiable Establishments",
    "sg:phone":"+33 801 31 14 97",
    "sg:postcode":"35510",
    "sg:province":"Bretagne",
    "wof:name":"E.d.f. - G.d.f.",
    "wof:placetype":"venue"
},
  "geometry": {"coordinates":[-1.621694,48.127106],"type":"Point"}
}