{
  "type": "Feature",
  "properties": {
    "addr:full":"B.P. 45, 81400 Carmaux^^116, Av. du Roucan, 81400 Carmaux Midi Pyr\u00e9n\u00e9es 81400",
    "addr:postcode":"81400;81400;81400",
    "addr:street":"B.P. 45;Av. Du Roucan",
    "iso:country":"FR",
    "sg:address":"B.P. 45, 81400 Carmaux^^116, Av. du Roucan, 81400 Carmaux",
    "sg:orig_category":"Broyeurs D\u00e9chets de mati\u00e8res plastiques Recyclage du plastique",
    "sg:phone":"+33 5 63 80 11 00",
    "sg:postcode":"81400",
    "sg:province":"Midi Pyr\u00e9n\u00e9es",
    "wof:name":"Transdemap S.a.r.l.",
    "wof:placetype":"venue"
},
  "geometry": {"coordinates":[2.132425,44.032146],"type":"Point"}
}