{
  "type": "Feature",
  "properties": {
    "iso:country":"FR",
    "sg:address":"26/36, Rue Notre Dame de Nazareth, 75003 Paris",
    "sg:orig_category":"Unclassifiable Establishments",
    "sg:phone":"+33 1 42 77 97 02",
    "sg:province":"Ile de France",
    "wof:name":"A. Marciano",
    "wof:placetype":"venue"
},
  "geometry": {"coordinates":[2.359961,48.867352],"type":"Point"}
}