{
  "type": "Feature",
  "properties": {
    "addr:full":"26/36, Rue Notre Dame de Nazareth, 75003 Paris Ile de France",
    "addr:housenumber":"26 / 36",
    "addr:postcode":"75003",
    "addr:street":"Rue Notre Dame De Nazareth",
    "iso:country":"FR",
    "sg:address":"26/36, Rue Notre Dame de Nazareth, 75003 Paris",
    "sg:orig_category":"Unclassifiable Establishments",
    "sg:phone":"+33 1 42 77 97 02",
    "sg:province":"Ile de France",
    "wof:name":"A. Marciano",
    "wof:placetype":"venue"
},
  "geometry": {"coordinates":[2.359961,48.867352],"type":"Point"}
}