{
  "type": "Feature",
  "properties": {
    "iso:country":"FR",
    "sg:address":"1 rue Lavoisier 21600 LONGVIC",
    "sg:city":"Longvic",
    "sg:classifiers":[
        {
            "category":"Utilities",
            "subcategory":"Fuel Oil & Lpg",
            "type":"Services"
        }
    ],
    "sg:phone":"+33 3 80 70 60 70",
    "sg:postcode":"21600",
    "sg:province":"Bourgogne",
    "sg:tags":[
        "pump"
    ],
    "wof:name":"Suntec Industries France S.a.",
    "wof:placetype":"venue"
},
  "geometry": {"coordinates":[5.044128,47.28352],"type":"Point"}
}