{
  "type": "Feature",
  "properties": {
    "iso:country":"FR",
    "sg:address":"53 Rue Albert Thomas 42300 Roanne",
    "sg:classifiers":[
        {
            "category":"Professional",
            "subcategory":"Computer Services",
            "type":"Services"
        }
    ],
    "sg:phone":"+33 4 77 70 21 11",
    "sg:postcode":"42300",
    "sg:province":"Rhone-Alpes",
    "sg:tags":[
        "information",
        "technology",
        "software"
    ],
    "wof:name":"Solid Dynamics",
    "wof:placetype":"venue"
},
  "geometry": {"coordinates":[4.074263,46.045174],"type":"Point"}
}