{
  "type": "Feature",
  "properties": {
    "iso:country":"FR",
    "sg:address":"1 Rue Des Fleurs 55500 Menil Sur Saulx",
    "sg:classifiers":[
        {
            "category":"Food & Beverages",
            "subcategory":"Dairy",
            "type":"Retail Goods"
        }
    ],
    "sg:phone":"+33 3 29 78 61 61",
    "sg:postcode":"55500",
    "sg:province":"Lorraine",
    "sg:tags":[
        "product",
        "related"
    ],
    "wof:name":"Sarl Fromagerie Barthelemy Et Fils",
    "wof:placetype":"venue"
},
  "geometry": {"coordinates":[5.21989,48.625858],"type":"Point"}
}