{
  "type": "Feature",
  "properties": {
    "iso:country":"FR",
    "sg:address":"B.P. 5, 62801 Li\u00e9vin C\u00e9dex^^Z.I. de l'Alouette, 62800 Li\u00e9vin",
    "sg:orig_category":"Non-Classified Establishments",
    "sg:phone":"+33 3 21 72 22 22",
    "sg:province":"Nord Pas-de-Calais",
    "wof:name":"S.e.r.t.i. S.a. - Soci\u00e9t\u00e9 D'etudes Et De R\u00e9alisations Techniques Et Industrielles",
    "wof:placetype":"venue"
},
  "geometry": {"coordinates":[2.754515,50.437798],"type":"Point"}
}