{
  "type": "Feature",
  "properties": {
    "iso:country":"FR",
    "sg:address":"B.P. 05",
    "sg:city":"Le Teil C\u00e9dex^^07400 Le Teil",
    "sg:orig_category":"Non-Classified Establishments",
    "sg:phone":"+33 4 75 49 50 00",
    "sg:postcode":"07400",
    "sg:province":"Rhone-Alpes",
    "wof:name":"Lafarge Ciments S.a.",
    "wof:placetype":"venue"
},
  "geometry": {"coordinates":[4.66402,44.567711],"type":"Point"}
}