{
  "type": "Feature",
  "properties": {
    "iso:country":"FR",
    "sg:address":". 16160 GOND PONTOUVRE",
    "sg:classifiers":[
        {
            "category":"Industrial Area",
            "type":"Public Place"
        }
    ],
    "sg:phone":"+33 5 45 68 32 55",
    "sg:postcode":"16160",
    "sg:province":"Poitou-Charentes",
    "sg:tags":[
        "engraving"
    ],
    "wof:name":"Sopelpa S.a.",
    "wof:placetype":"venue"
},
  "geometry": {"coordinates":[0.166295,45.668095],"type":"Point"}
}