{
  "type": "Feature",
  "properties": {
    "addr:full":"3 Rue Jean Le Ho 35000 Rennes Rennes Bretagne 35000",
    "addr:housenumber":"3",
    "addr:postcode":"35000;35000",
    "addr:street":"Rue Jean Le Ho",
    "iso:country":"FR",
    "sg:address":"3 Rue Jean Le Ho 35000 Rennes",
    "sg:city":"Rennes",
    "sg:classifiers":[
        {
            "category":"Home & Garden",
            "subcategory":"Furniture",
            "type":"Retail Goods"
        }
    ],
    "sg:phone":"+33 2 99 14 24 44",
    "sg:postcode":"35000",
    "sg:province":"Bretagne",
    "sg:tags":[
        "household",
        "wood"
    ],
    "wof:name":"Societe De Fab De Transformation Et De Distribution (sftd)",
    "wof:placetype":"venue"
},
  "geometry": {"coordinates":[-1.723642,48.103863],"type":"Point"}
}