{
  "type": "Feature",
  "properties": {
    "addr:full":"81, Rue Romain Rolland, 93260 Les Lilas Ile de France 93260",
    "addr:housenumber":"81",
    "addr:postcode":"93260;93260",
    "addr:street":"Rue Romain Rolland;France",
    "iso:country":"FR",
    "sg:address":"81, Rue Romain Rolland, 93260 Les Lilas",
    "sg:orig_category":"Non-Classified Establishments",
    "sg:phone":"+33 1 43 62 86 50",
    "sg:postcode":"93260",
    "sg:province":"Ile de France",
    "wof:name":"Etablissements Maignet Fr\u00e8res S.a.r.l.",
    "wof:placetype":"venue"
},
  "geometry": {"coordinates":[2.420804,48.879478],"type":"Point"}
}