{
  "type": "Feature",
  "properties": {
    "addr:full":"15, Rte de Villiers, 78710 Rosny sur Seine Ile de France 78710",
    "addr:housenumber":"15",
    "addr:postcode":"78710;78710",
    "addr:street":"Rte De Villiers;France",
    "iso:country":"FR",
    "sg:address":"15, Rte de Villiers, 78710 Rosny sur Seine",
    "sg:orig_category":"Non-Classified Establishments",
    "sg:phone":"+33 1 30 42 80 24",
    "sg:postcode":"78710",
    "sg:province":"Ile de France",
    "wof:name":"Cr\u00e9a Graphic",
    "wof:placetype":"venue"
},
  "geometry": {"coordinates":[1.628637,49.000576],"type":"Point"}
}