{
  "type": "Feature",
  "properties": {
    "iso:country":"FR",
    "sg:address":"7 Pl Du Chancelier Adenauer 75016 Paris",
    "sg:classifiers":[
        {
            "category":"Manufacturing",
            "subcategory":"Rubber & Plastics",
            "type":"Manufacturing & Wholesale Goods"
        }
    ],
    "sg:phone":"+33 1 56 28 20 00",
    "sg:postcode":"75016",
    "sg:province":"Ile de France",
    "sg:tags":[
        "packaging",
        "material",
        "-",
        "metalworking",
        "metallic",
        "metallurgy",
        "finished",
        "plast"
    ],
    "wof:name":"Pechiney",
    "wof:placetype":"venue"
},
  "geometry": {"coordinates":[2.25657,48.857079],"type":"Point"}
}