{
  "type": "Feature",
  "properties": {
    "iso:country":"FR",
    "sg:address":"Rue de la Croix de Pierre - Espace Industriel Nord",
    "sg:city":"Amiens C\u00e9dex 2",
    "sg:orig_category":"D\u00e9poussi\u00e9rage centralis\u00e9, Installations de D\u00e9poussi\u00e9rage, Installations de D\u00e9sulfuration, Installati",
    "sg:phone":"+33 3 22 67 31 31",
    "sg:postcode":"80084",
    "sg:province":"Picardie",
    "wof:name":"Fls Milj\u00f8 France S.a.",
    "wof:placetype":"venue"
},
  "geometry": {"coordinates":[2.30253,49.893959],"type":"Point"}
}