{
  "type": "Feature",
  "properties": {
    "addr:full":"36 bis, Av. du Pr\u00e9sident Roosevelt, 77210 Avon Ile de France",
    "addr:housenumber":"36 bis",
    "addr:postcode":"77210",
    "addr:street":"Av. Du Pre\u0301Sident Roosevelt;Ile De France",
    "iso:country":"FR",
    "sg:address":"36 bis, Av. du Pr\u00e9sident Roosevelt, 77210 Avon",
    "sg:orig_category":"Unclassifiable Establishments",
    "sg:phone":"+33 1 60 71 56 20",
    "sg:province":"Ile de France",
    "wof:name":"G\u00e9n\u00e9ral Electric Quartz Europe S.a.r.l.",
    "wof:placetype":"venue"
},
  "geometry": {"coordinates":[2.719624,48.415108],"type":"Point"}
}