{
  "type": "Feature",
  "properties": {
    "iso:country":"FR",
    "sg:address":"5",
    "sg:city":"Masevaux",
    "sg:classifiers":[
        {
            "category":"Wholesale",
            "subcategory":"Auto Parts",
            "type":"Manufacturing & Wholesale Goods"
        }
    ],
    "sg:phone":"+33 3 89 38 05 38",
    "sg:postcode":"68290",
    "sg:province":"Alsace",
    "sg:tags":[
        "engine",
        "handling",
        "material",
        "-",
        "machine",
        "equipment",
        "engineering",
        "mechanical"
    ],
    "wof:name":"Tanals (sa)",
    "wof:placetype":"venue"
},
  "geometry": {"coordinates":[6.996676,47.773243],"type":"Point"}
}