{
  "type": "Feature",
  "properties": {
    "iso:country":"FR",
    "sg:address":"Route De Beaumes De Venise 84330 Caromb",
    "sg:classifiers":[
        {
            "category":"Farming",
            "subcategory":"Farm",
            "type":"Manufacturing & Wholesale Goods"
        }
    ],
    "sg:phone":"+33 4 90 62 41 56",
    "sg:province":"Languedoc-Roussillon",
    "sg:tags":[
        "horticulture",
        "agriculture",
        "livestock"
    ],
    "wof:name":"Societe D'exploitation Des Etablissements Jacques Richard",
    "wof:placetype":"venue"
},
  "geometry": {"coordinates":[5.105398,44.109108],"type":"Point"}
}