{
  "type": "Feature",
  "properties": {
    "iso:country":"FR",
    "sg:address":"B.P. 31, 05001 Gap C\u00e9dex^^48, Bd Georges Pompidou - Immeuble le Concorde, 05000 Gap",
    "sg:orig_category":"Non-Classified Establishments",
    "sg:phone":"+33 4 92 53 98 98",
    "sg:province":"Provence-Alpes-C\u00f4te d'Azur",
    "wof:name":"N\u00e9ra S.a.",
    "wof:placetype":"venue"
},
  "geometry": {"coordinates":[6.07483,44.554939],"type":"Point"}
}