{
  "type": "Feature",
  "properties": {
    "addr:full":"Rte d'Ancenis Vallet Pays de Loire 44330",
    "addr:postcode":"44330",
    "addr:street":"Rte D'Ancenis",
    "iso:country":"FR",
    "sg:address":"Rte d'Ancenis",
    "sg:city":"Vallet",
    "sg:orig_category":"Non-Classified Establishments",
    "sg:phone":"+33 2 40 80 18 15",
    "sg:postcode":"44330",
    "sg:province":"Pays de Loire",
    "wof:name":"Barr\u00e9 S.a.s.",
    "wof:placetype":"venue"
},
  "geometry": {"coordinates":[-1.2686,47.16431],"type":"Point"}
}