{
  "type": "Feature",
  "properties": {
    "addr:full":"23, Av. Prat Gimont, 31130 Balma Midi Pyr\u00e9n\u00e9es",
    "addr:postcode":"31130",
    "addr:street":"23 Av. Prat",
    "iso:country":"FR",
    "sg:address":"23, Av. Prat Gimont, 31130 Balma",
    "sg:orig_category":"Unclassifiable Establishments",
    "sg:phone":"+33 5 61 24 71 24",
    "sg:province":"Midi Pyr\u00e9n\u00e9es",
    "wof:name":"Domoservices Maintenance S.a.",
    "wof:placetype":"venue"
},
  "geometry": {"coordinates":[1.486888,43.627026],"type":"Point"}
}