{
  "type": "Feature",
  "properties": {
    "addr:full":"ZA du Bois Vert Plo\u00ebrmel Bretagne 56800",
    "addr:postcode":"56800",
    "addr:street":"Za Du Bois Vert Ploe\u0308Rmel Bretagne",
    "iso:country":"FR",
    "sg:address":"ZA du Bois Vert",
    "sg:city":"Plo\u00ebrmel",
    "sg:orig_category":"Unclassifiable Establishments",
    "sg:phone":"+33 2 97 74 10 20",
    "sg:postcode":"56800",
    "sg:province":"Bretagne",
    "wof:name":"Locarmor S.a.",
    "wof:placetype":"venue"
},
  "geometry": {"coordinates":[-2.398204,47.931625],"type":"Point"}
}