{
  "type": "Feature",
  "properties": {
    "iso:country":"FR",
    "sg:address":"B.P. 10802, 56178 Quiberon^^Pointe de Goulvars, 56170 Quiberon",
    "sg:city":"Quiberon",
    "sg:orig_category":"Non-Classified Establishments",
    "sg:phone":"+33 2 97 50 20 00",
    "sg:postcode":"56170",
    "sg:province":"Bretagne",
    "wof:name":"Sofitel Thalassa S.a.",
    "wof:placetype":"venue"
},
  "geometry": {"coordinates":[-3.119144,47.485565],"type":"Point"}
}