{
  "type": "Feature",
  "properties": {
    "iso:country":"FR",
    "sg:address":"1 rue de Strasbourg; BP 104; ARMENTIERES; 59427 CEDEX",
    "sg:city":"Strasbourg",
    "sg:classifiers":[
        {
            "category":"Shopping",
            "subcategory":"Computers & Home Electronics",
            "type":"Retail Goods"
        }
    ],
    "sg:phone":"+33 3 20 44 06 20",
    "sg:postcode":"67000",
    "sg:province":"Alsace",
    "sg:tags":[
        "chamber",
        "commerce"
    ],
    "wof:name":"Chambre De Commerce D'armentihres-hazebrouck",
    "wof:placetype":"venue"
},
  "geometry": {"coordinates":[2.87789,50.689949],"type":"Point"}
}