{
  "type": "Feature",
  "properties": {
    "addr:full":"8, Rue Jean Roisin, 59800 Lille Nord Pas-de-Calais 59800",
    "addr:housenumber":"8",
    "addr:postcode":"59800;59800",
    "addr:street":"Rue Jean Roisin",
    "iso:country":"FR",
    "sg:address":"8, Rue Jean Roisin, 59800 Lille",
    "sg:orig_category":"Non-Classified Establishments",
    "sg:phone":"+33 3 20 74 69 80",
    "sg:postcode":"59800",
    "sg:province":"Nord Pas-de-Calais",
    "wof:name":"Air France",
    "wof:placetype":"venue"
},
  "geometry": {"coordinates":[3.062037,50.636417],"type":"Point"}
}