{
  "type": "Feature",
  "properties": {
    "addr:full":"Route De Mugron 40250 St Aubin Mugron Aquitaine 40250",
    "addr:postcode":"40250;40250",
    "addr:street":"Route De Mugron;St",
    "iso:country":"FR",
    "sg:address":"Route De Mugron 40250 St Aubin",
    "sg:city":"Mugron",
    "sg:classifiers":[
        {
            "category":"Food & Beverages",
            "subcategory":"Meat & Fish",
            "type":"Retail Goods"
        }
    ],
    "sg:phone":"+33 5 58 97 95 26",
    "sg:postcode":"40250",
    "sg:province":"Aquitaine",
    "sg:tags":[
        "preserve",
        "cooked",
        "product",
        "related"
    ],
    "wof:name":"Sa Palmi Decoupe Foie Gras",
    "wof:placetype":"venue"
},
  "geometry": {"coordinates":[-0.720519,43.668835],"type":"Point"}
}