{
  "type": "Feature",
  "properties": {
    "addr:full":"34 Avenue Marceau Paris Ile de France 75008",
    "addr:housenumber":"34",
    "addr:postcode":"75008",
    "addr:street":"Avenue Marceau",
    "iso:country":"FR",
    "sg:address":"34 Avenue Marceau",
    "sg:city":"Paris",
    "sg:classifiers":[
        {
            "category":"Banks & Credit Unions",
            "subcategory":"Financial Services",
            "type":"Services"
        }
    ],
    "sg:phone":"+33 1 47 20 22 48",
    "sg:postcode":"75008",
    "sg:province":"Ile de France",
    "sg:tags":[
        "banking",
        "finance",
        "insurance"
    ],
    "wof:name":"Weissberg Gaetjens Ziegenfeuter",
    "wof:placetype":"venue"
},
  "geometry": {"coordinates":[2.299463,48.867622],"type":"Point"}
}