{
  "type": "Feature",
  "properties": {
    "addr:full":"51 Chemin De Barriol 13200 Arles Barr Alsace 67140",
    "addr:housenumber":"51",
    "addr:postcode":"13200;67140",
    "addr:street":"Chemin De Barriol;Barr",
    "iso:country":"FR",
    "sg:address":"51 Chemin De Barriol 13200 Arles",
    "sg:city":"Barr",
    "sg:classifiers":[
        {
            "category":"Autos & Motor Vehicles",
            "subcategory":"Boat Sales",
            "type":"Retail Goods"
        }
    ],
    "sg:phone":"+33 4 90 93 74 60",
    "sg:postcode":"67140",
    "sg:province":"Alsace",
    "sg:tags":[
        "equipment",
        "transport"
    ],
    "wof:name":"Chantiers Navals De Barriol (scop)",
    "wof:placetype":"venue"
},
  "geometry": {"coordinates":[4.609696,43.661694],"type":"Point"}
}