{
  "type": "Feature",
  "properties": {
    "addr:full":"All\u00e9e Des Ch\u00eanes La Voivre 88000 Epinal Lorraine 88000",
    "addr:postcode":"88000;88000",
    "addr:street":"Alle\u0301E Des Che\u0302Nes La",
    "iso:country":"FR",
    "sg:address":"All\u00e9e Des Ch\u00eanes",
    "sg:city":"La Voivre 88000 Epinal",
    "sg:classifiers":[
        {
            "category":"Building & Trades",
            "subcategory":"Electrical",
            "type":"Services"
        }
    ],
    "sg:phone":"+33 3 29 81 83 83",
    "sg:postcode":"88000",
    "sg:province":"Lorraine",
    "sg:tags":[
        "electronic",
        "lighting",
        "equipment"
    ],
    "wof:name":"Georges Evrard Sa",
    "wof:placetype":"venue"
},
  "geometry": {"coordinates":[6.4497,48.175686],"type":"Point"}
}