{
  "type": "Feature",
  "properties": {
    "iso:country":"FR",
    "sg:address":"R Leon Foucault Zi De La Sph\u00e8re 14200 Herouville St Clair",
    "sg:city":"H\u00e9rouville-Saint-Clair",
    "sg:classifiers":[
        {
            "category":"Food & Beverages",
            "subcategory":"Meat & Fish",
            "type":"Retail Goods"
        }
    ],
    "sg:phone":"+33 2 31 53 10 20",
    "sg:postcode":"14200",
    "sg:province":"Basse Normandie",
    "sg:tags":[
        "preserve",
        "cooked",
        "product",
        "related"
    ],
    "wof:name":"Sa Maxiviande Gros",
    "wof:placetype":"venue"
},
  "geometry": {"coordinates":[-0.328299,49.203964],"type":"Point"}
}