{
  "type": "Feature",
  "properties": {
    "addr:full":"420 R Aristide Briand 50110 Tourlaville Tourlaville Basse Normandie 50110",
    "addr:housenumber":"420",
    "addr:postcode":"50110;50110",
    "addr:street":"R Aristide Briand",
    "iso:country":"FR",
    "sg:address":"420 R Aristide Briand 50110 Tourlaville",
    "sg:city":"Tourlaville",
    "sg:classifiers":[
        {
            "category":"Shopping",
            "type":"Retail Goods"
        }
    ],
    "sg:phone":"+33 2 33 23 64 70",
    "sg:postcode":"50110",
    "sg:province":"Basse Normandie",
    "sg:tags":[
        "metallurgy",
        "finished",
        "-",
        "metalworking",
        "metallic"
    ],
    "wof:name":"Chaudronnerie - Tuyauterie Nsb",
    "wof:placetype":"venue"
},
  "geometry": {"coordinates":[-1.590279,49.645828],"type":"Point"}
}