{
  "type": "Feature",
  "properties": {
    "addr:full":"70 Boulevard De Magenta 75010 Paris Ile de France",
    "addr:housenumber":"70",
    "addr:postcode":"75010",
    "addr:street":"Boulevard De Magenta",
    "iso:country":"FR",
    "sg:address":"70 Boulevard De Magenta 75010 Paris",
    "sg:classifiers":[
        {
            "category":"Professional",
            "subcategory":"Printing & Photocopies",
            "type":"Services"
        }
    ],
    "sg:phone":"+33 1 40 34 15 15",
    "sg:province":"Ile de France",
    "sg:tags":[
        "publishing"
    ],
    "wof:name":"Les Editions De L'enseigne",
    "wof:placetype":"venue"
},
  "geometry": {"coordinates":[2.357389,48.875034],"type":"Point"}
}