{
  "type": "Feature",
  "properties": {
    "iso:country":"FR",
    "sg:address":"Vallin Ccal Des Vallins 13270 Fos Sur Mer",
    "sg:classifiers":[
        {
            "category":"Manufacturing",
            "subcategory":"Chemicals & Compounds",
            "type":"Manufacturing & Wholesale Goods"
        }
    ],
    "sg:phone":"+33 4 42 05 17 18",
    "sg:province":"Midi Pyr\u00e9n\u00e9es",
    "sg:tags":[
        "pharmaceutical",
        "energy",
        "chemistry",
        "-",
        "by-product"
    ],
    "wof:name":"Dyneff Sa",
    "wof:placetype":"venue"
},
  "geometry": {"coordinates":[4.946065,43.436958],"type":"Point"}
}