{
  "type": "Feature",
  "properties": {
    "addr:full":"Zone D'Activit\u00e9 Bussoy 45290 Varennes Changy Nogent-sur-Vernisson Centre 45290",
    "addr:postcode":"45290;45290",
    "addr:street":"Zone;Bussoy",
    "iso:country":"FR",
    "sg:address":"Zone D'Activit\u00e9 Bussoy 45290 Varennes Changy",
    "sg:city":"Nogent-sur-Vernisson",
    "sg:classifiers":[
        {
            "category":"Professional",
            "subcategory":"Engineering",
            "type":"Services"
        }
    ],
    "sg:phone":"+33 2 38 94 51 07",
    "sg:postcode":"45290",
    "sg:province":"Centre",
    "sg:tags":[
        "machine",
        "-",
        "mechanical"
    ],
    "wof:name":"Metal Service",
    "wof:placetype":"venue"
},
  "geometry": {"coordinates":[2.673605,47.843838],"type":"Point"}
}