{
  "type": "Feature",
  "properties": {
    "addr:full":"Z.I. Canal des Soeurs Rochefort Poitou-Charentes 17300",
    "addr:housenumber":"z.i.",
    "addr:postcode":"17300",
    "addr:street":"Canal Des Soeurs Rochefort",
    "iso:country":"FR",
    "sg:address":"Z.I. Canal des Soeurs",
    "sg:city":"Rochefort",
    "sg:orig_category":"Unclassifiable Establishments",
    "sg:phone":"+33 5 46 99 54 51",
    "sg:postcode":"17300",
    "sg:province":"Poitou-Charentes",
    "wof:name":"C.i.m. S.a. - Constructions Industrielles Et Maritimes",
    "wof:placetype":"venue"
},
  "geometry": {"coordinates":[-0.958704,45.934818],"type":"Point"}
}