{
  "type": "Feature",
  "properties": {
    "iso:country":"FR",
    "sg:address":"22, Rue Salonique, 95812 Argenteuil",
    "sg:orig_category":"Non-Classified Establishments",
    "sg:phone":"+33 1 30 25 87 40",
    "sg:province":"Outre-Mer",
    "wof:name":"Gastaldy Lapeyre",
    "wof:placetype":"venue"
},
  "geometry": {"coordinates":[2.208077,48.950958],"type":"Point"}
}