{
  "type": "Feature",
  "properties": {
    "addr:full":"Zac De Bellevue 56850 Caudan Caudan Bretagne 56850",
    "addr:postcode":"56850;56850",
    "addr:street":"Zac De Bellevue;Caudan",
    "iso:country":"FR",
    "sg:address":"Zac De Bellevue 56850 Caudan",
    "sg:city":"Caudan",
    "sg:classifiers":[
        {
            "category":"Building & Trades",
            "subcategory":"Construction",
            "type":"Services"
        }
    ],
    "sg:phone":"+33 2 97 76 00 17",
    "sg:postcode":"56850",
    "sg:province":"Bretagne",
    "sg:tags":[
        "work",
        "public"
    ],
    "wof:name":"Sacer Atlantique",
    "wof:placetype":"venue"
},
  "geometry": {"coordinates":[-3.340384,47.810596],"type":"Point"}
}