{
  "type": "Feature",
  "properties": {
    "iso:country":"FR",
    "sg:address":"145, Rte d'Apremont, 73190 Saint Badolph",
    "sg:orig_category":"Unclassifiable Establishments",
    "sg:phone":"+33 4 79 28 22 08",
    "sg:postcode":"73190",
    "sg:province":"Rhone-Alpes",
    "wof:name":"Pastel Impression",
    "wof:placetype":"venue"
},
  "geometry": {"coordinates":[5.95945,45.5131],"type":"Point"}
}