{
  "type": "Feature",
  "properties": {
    "iso:country":"FR",
    "sg:address":"B.P. 41, 62801 Li\u00e9vin C\u00e9dex^^Rue du Moulinage - ZAL de Saint Ame, 62800 Li\u00e9vin",
    "sg:orig_category":"Non-Classified Establishments",
    "sg:phone":"+33 3 21 44 01 13",
    "sg:postcode":"62800",
    "sg:province":"Nord Pas-de-Calais",
    "wof:name":"A.b.a.c. S.a. - Aciers B\u00e9ton Arm\u00e9 Conseil",
    "wof:placetype":"venue"
},
  "geometry": {"coordinates":[2.779565,50.4216],"type":"Point"}
}