{
  "type": "Feature",
  "properties": {
    "addr:full":"4, Rue Charles Gounod, 77185 Lognes Ile de France",
    "addr:housenumber":"4",
    "addr:postcode":"77185;ile",
    "addr:street":"Rue Charles Gounod",
    "iso:country":"FR",
    "sg:address":"4, Rue Charles Gounod, 77185 Lognes",
    "sg:orig_category":"Non-Classified Establishments",
    "sg:phone":"+33 1 64 80 11 00",
    "sg:province":"Ile de France",
    "wof:name":"X Altair Sa",
    "wof:placetype":"venue"
},
  "geometry": {"coordinates":[2.639615,48.83535],"type":"Point"}
}