{
  "type": "Feature",
  "properties": {
    "addr:full":"Rue De Franche Comte Valparc Batiment C 25480 Ecole Valentin Franche Comt\u00e9 25480",
    "addr:postcode":"25480;25480",
    "addr:street":"Rue De Franche Comte Valparc;Franche Comte\u0301",
    "iso:country":"FR",
    "sg:address":"Rue De Franche Comte Valparc Batiment C 25480 Ecole Valentin",
    "sg:classifiers":[
        {
            "category":"Wholesale",
            "subcategory":"Medical Equipment & Supplies",
            "type":"Manufacturing & Wholesale Goods"
        }
    ],
    "sg:phone":"+33 3 81 88 53 82",
    "sg:postcode":"25480",
    "sg:province":"Franche Comt\u00e9",
    "sg:tags":[
        "instrument",
        "health",
        "-",
        "precision"
    ],
    "wof:name":"Sophysa",
    "wof:placetype":"venue"
},
  "geometry": {"coordinates":[5.991565,47.275944],"type":"Point"}
}