{
  "type": "Feature",
  "properties": {
    "addr:full":"9, Rue Andrei Sakkarov, 76130 Mont Saint Aignan Haute Normandie",
    "addr:housenumber":"9",
    "addr:postcode":"76130",
    "addr:street":"Rue Andrei Sakkarov",
    "iso:country":"FR",
    "sg:address":"9, Rue Andrei Sakkarov, 76130 Mont Saint Aignan",
    "sg:orig_category":"Unclassifiable Establishments",
    "sg:phone":"+33 2 35 59 44 00",
    "sg:province":"Haute Normandie",
    "wof:name":"C.e.p.p.i.c. - Centre De Perfectionnement Pour L'industrie Et Le Commerce",
    "wof:placetype":"venue"
},
  "geometry": {"coordinates":[1.091078,49.474571],"type":"Point"}
}