{
  "type": "Feature",
  "properties": {
    "iso:country":"FR",
    "sg:address":"B.P. 141",
    "sg:city":"Morez C\u00e9dex^^La Doye 39150 Saint Laurent en Grandvaux",
    "sg:orig_category":"Non-Classified Establishments",
    "sg:phone":"+33 3 84 60 25 25",
    "sg:postcode":"39150",
    "sg:province":"Franche Comt\u00e9",
    "wof:name":"Axebo S.a.r.l.",
    "wof:placetype":"venue"
},
  "geometry": {"coordinates":[5.828622,46.495934],"type":"Point"}
}