{
  "type": "Feature",
  "properties": {
    "iso:country":"FR",
    "sg:address":"Quai Des Moulins 34200 S\u00e8te",
    "sg:classifiers":[
        {
            "category":"Professional",
            "type":"Services"
        }
    ],
    "sg:phone":"+33 4 67 48 62 76",
    "sg:province":"Languedoc-Roussillon",
    "sg:tags":[
        "transport",
        "road"
    ],
    "wof:name":"Robert Et Jean Galano Sarl",
    "wof:placetype":"venue"
},
  "geometry": {"coordinates":[3.715975,43.414612],"type":"Point"}
}