{
  "type": "Feature",
  "properties": {
    "addr:full":"B.P. 386, 02108 Saint Quentin C\u00e9dex^^35, Quai Gayant, 02100 Saint Quentin Picardie",
    "addr:housenumber":"b.p. 386",
    "addr:postcode":"02108;02100",
    "addr:street":"Quai Gayant",
    "iso:country":"FR",
    "sg:address":"B.P. 386, 02108 Saint Quentin C\u00e9dex^^35, Quai Gayant, 02100 Saint Quentin",
    "sg:orig_category":"Non-Classified Establishments",
    "sg:phone":"+33 3 23 64 12 50",
    "sg:province":"Picardie",
    "wof:name":"S.n.e.m.a. S.a.r.l.",
    "wof:placetype":"venue"
},
  "geometry": {"coordinates":[3.291286,49.850952],"type":"Point"}
}