{
  "type": "Feature",
  "properties": {
    "iso:country":"FR",
    "sg:address":"4 Place Stalingrad; Bordeaux; 33100",
    "sg:city":"Bordeaux",
    "sg:classifiers":[
        {
            "category":"Banks & Credit Unions",
            "subcategory":"Bank",
            "type":"Services"
        }
    ],
    "sg:phone":"+33 5 56 86 17 31",
    "sg:postcode":"33100",
    "sg:province":"Aquitaine",
    "wof:name":"Cr\u00e9dit Commercial, Du Sud-ouest",
    "wof:placetype":"venue"
},
  "geometry": {"coordinates":[-0.559622,44.839787],"type":"Point"}
}