{
  "type": "Feature",
  "properties": {
    "iso:country":"FR",
    "sg:address":"ZI de M\u00e9zaubert",
    "sg:city":"Javen\u00e9",
    "sg:orig_category":"Non-Classified Establishments",
    "sg:phone":"+33 2 99 94 28 18",
    "sg:postcode":"35133",
    "sg:province":"Bretagne",
    "wof:name":"Loca M\u00e9tal E.u.r.l.",
    "wof:placetype":"venue"
},
  "geometry": {"coordinates":[-1.216757,48.319748],"type":"Point"}
}