{
  "type": "Feature",
  "properties": {
    "iso:country":"FR",
    "sg:address":"Route d'Amance 70160 FAVERNEY",
    "sg:classifiers":[
        {
            "category":"Place Of Worship",
            "subcategory":"Church",
            "type":"Public Place"
        }
    ],
    "sg:phone":"+33 3 84 91 31 00",
    "sg:postcode":"70160",
    "sg:province":"Franche Comt\u00e9",
    "sg:tags":[
        "figurine",
        "saint"
    ],
    "wof:name":"Prime Sa",
    "wof:placetype":"venue"
},
  "geometry": {"coordinates":[6.05902,47.801189],"type":"Point"}
}