{
  "type": "Feature",
  "properties": {
    "addr:full":"14, Rue Louis Blanchard - ZI de la Vaure, 42290 Sorbiers Rhone-Alpes 42290",
    "addr:housenumber":"14",
    "addr:postcode":"42290;42290",
    "addr:street":"Rue Louis Blanchard Zi De La Vaure;Rhone-Alpes",
    "iso:country":"FR",
    "sg:address":"14, Rue Louis Blanchard - ZI de la Vaure, 42290 Sorbiers",
    "sg:orig_category":"Unclassifiable Establishments",
    "sg:phone":"+33 4 77 53 81 56",
    "sg:postcode":"42290",
    "sg:province":"Rhone-Alpes",
    "wof:name":"Isom\u00e9canique S.a.",
    "wof:placetype":"venue"
},
  "geometry": {"coordinates":[4.450189,45.490181],"type":"Point"}
}