{
  "type": "Feature",
  "properties": {
    "addr:full":"44932 Nantes R\u00e9gion Pays de la Loire",
    "addr:postcode":"44932",
    "iso:country":"FR",
    "sg:address":"44932 Nantes",
    "sg:orig_category":"Unclassifiable Establishments",
    "sg:phone":"+33 2 51 72 44 00",
    "sg:province":"R\u00e9gion Pays de la Loire",
    "wof:name":"B.n. S.a. - Biscuiterie Nantaise",
    "wof:placetype":"venue"
},
  "geometry": {"coordinates":[-1.623,47.271351],"type":"Point"}
}