{
  "type": "Feature",
  "properties": {
    "addr:full":"3, Chemin d'Huy, 38240 Meylan Rhone-Alpes 38240",
    "addr:housenumber":"3",
    "addr:postcode":"38240;38240",
    "addr:street":"Chemin D'Huy",
    "iso:country":"FR",
    "sg:address":"3, Chemin d'Huy, 38240 Meylan",
    "sg:orig_category":"Unclassifiable Establishments",
    "sg:phone":"+33 4 76 18 04 36",
    "sg:postcode":"38240",
    "sg:province":"Rhone-Alpes",
    "wof:name":"Cr\u00e9ation D'images S.a.r.l.",
    "wof:placetype":"venue"
},
  "geometry": {"coordinates":[5.795311,45.212727],"type":"Point"}
}