{
  "type": "Feature",
  "properties": {
    "iso:country":"FR",
    "sg:address":"Allee Hector Pintus Lotissement Les Nertieres 06610 La Gaude",
    "sg:classifiers":[
        {
            "category":"Utilities",
            "subcategory":"Electric",
            "type":"Services"
        }
    ],
    "sg:phone":"+33 4 93 24 88 50",
    "sg:province":"Champagne",
    "sg:tags":[
        "electricity",
        "electronic",
        "electrical",
        "equipment"
    ],
    "wof:name":"Sud Littoral Electricite Sle (sle)",
    "wof:placetype":"venue"
},
  "geometry": {"coordinates":[7.15433,43.722321],"type":"Point"}
}