{
  "type": "Feature",
  "properties": {
    "addr:full":"4 Rte De C\u00e9zanne 51530 Vinay Champagne",
    "addr:housenumber":"4",
    "addr:postcode":"51530",
    "addr:street":"Rte De Ce\u0301Zanne",
    "iso:country":"FR",
    "sg:address":"4 Rte De C\u00e9zanne 51530 Vinay",
    "sg:classifiers":[
        {
            "category":"Travel",
            "subcategory":"Hotels & Motels",
            "type":"Entertainment"
        }
    ],
    "sg:phone":"+33 3 26 59 99 99",
    "sg:province":"Champagne",
    "sg:tags":[
        "hotels",
        "business",
        "restaurant"
    ],
    "wof:name":"Hostellerie La Briqueterie",
    "wof:placetype":"venue"
},
  "geometry": {"coordinates":[3.93405,49.05574],"type":"Point"}
}