{
  "type": "Feature",
  "properties": {
    "addr:full":"70, Rue Carnot, 61250 Damigny Damigny Basse Normandie 61250",
    "addr:housenumber":"70",
    "addr:postcode":"61250;61250",
    "addr:street":"Rue Carnot",
    "iso:country":"FR",
    "sg:address":"70, Rue Carnot, 61250 Damigny",
    "sg:city":"Damigny",
    "sg:orig_category":"Non-Classified Establishments",
    "sg:phone":"+33 2 33 80 45 80",
    "sg:postcode":"61250",
    "sg:province":"Basse Normandie",
    "wof:name":"Soci\u00e9t\u00e9 B\u00e9quet",
    "wof:placetype":"venue"
},
  "geometry": {"coordinates":[0.081623,48.448006],"type":"Point"}
}