{
  "type": "Feature",
  "properties": {
    "addr:full":"Chaban De Chauray Niort Poitou-Charentes 79000",
    "addr:postcode":"79000",
    "addr:street":"Niort",
    "iso:country":"FR",
    "sg:address":"Chaban De Chauray",
    "sg:city":"Niort",
    "sg:classifiers":[
        {
            "category":"Banks & Credit Unions",
            "subcategory":"Financial Services",
            "type":"Services"
        }
    ],
    "sg:phone":"+33 5 49 08 52 52",
    "sg:postcode":"79000",
    "sg:province":"Poitou-Charentes",
    "sg:tags":[
        "banking",
        "finance",
        "insurance"
    ],
    "wof:name":"Gie Euro Gestion Sante",
    "wof:placetype":"venue"
},
  "geometry": {"coordinates":[-0.504137,46.298],"type":"Point"}
}