{
  "type": "Feature",
  "properties": {
    "iso:country":"FR",
    "sg:address":"Zon Industrielle 76370 Rouxmesnil Bouteilles",
    "sg:classifiers":[
        {
            "category":"Wholesale",
            "subcategory":"Machinery & Supplies",
            "type":"Manufacturing & Wholesale Goods"
        }
    ],
    "sg:phone":"+33 2 35 82 11 67",
    "sg:province":"Haute Normandie",
    "sg:tags":[
        "equipment",
        "precision"
    ],
    "wof:name":"Le Barbier",
    "wof:placetype":"venue"
},
  "geometry": {"coordinates":[1.093,49.904709],"type":"Point"}
}