{
  "type": "Feature",
  "properties": {
    "iso:country":"FR",
    "sg:address":"18, Rue Gustave Eiffel, 91100 Corbeil Essonnes",
    "sg:orig_category":"Non-Classified Establishments",
    "sg:phone":"+33 1 60 88 29 29",
    "sg:postcode":"91100",
    "sg:province":"Ile de France",
    "wof:name":"Comexia",
    "wof:placetype":"venue"
},
  "geometry": {"coordinates":[2.466201,48.618004],"type":"Point"}
}