{
  "type": "Feature",
  "properties": {
    "addr:full":"5, Bd Jules Ferry, 02200 Soissons Picardie",
    "addr:housenumber":"5",
    "addr:postcode":"02200",
    "addr:street":"Bd Jules Ferry",
    "iso:country":"FR",
    "sg:address":"5, Bd Jules Ferry, 02200 Soissons",
    "sg:orig_category":"Unclassifiable Establishments",
    "sg:phone":"+33 3 23 53 20 78",
    "sg:province":"Picardie",
    "wof:name":"Chapsol S.a.",
    "wof:placetype":"venue"
},
  "geometry": {"coordinates":[3.337198,49.380566],"type":"Point"}
}