{
  "type": "Feature",
  "properties": {
    "addr:full":"Rte de Faulquemont - ZI Longeville l\u00e8s Saint Avold Lorraine 57740",
    "addr:postcode":"57740",
    "addr:street":"Rte De Faulquemont Zi;Lorraine",
    "iso:country":"FR",
    "sg:address":"Rte de Faulquemont - ZI",
    "sg:city":"Longeville l\u00e8s Saint Avold",
    "sg:orig_category":"Non-Classified Establishments",
    "sg:phone":"+33 3 87 92 13 19",
    "sg:postcode":"57740",
    "sg:province":"Lorraine",
    "wof:name":"Palemball S.a.r.l.",
    "wof:placetype":"venue"
},
  "geometry": {"coordinates":[6.64526,49.117481],"type":"Point"}
}