{
  "type": "Feature",
  "properties": {
    "addr:full":"Rn 113 13655 Rognac Franche Comt\u00e9",
    "addr:postcode":"13655",
    "addr:street":"Rn 113;Franche Comte\u0301",
    "iso:country":"FR",
    "sg:address":"Rn 113 13655 Rognac",
    "sg:classifiers":[
        {
            "category":"Manufacturing",
            "subcategory":"Chemicals & Compounds",
            "type":"Manufacturing & Wholesale Goods"
        }
    ],
    "sg:phone":"+33 810 16 20 00",
    "sg:province":"Franche Comt\u00e9",
    "sg:tags":[
        "pharmaceutical",
        "chemistry",
        "-",
        "by-product"
    ],
    "wof:name":"Sopeco",
    "wof:placetype":"venue"
},
  "geometry": {"coordinates":[5.23412,43.487679],"type":"Point"}
}