{
  "type": "Feature",
  "properties": {
    "addr:full":"B.P. 55, 59611 Fourmies C\u00e9dex^^19, Rte d'Anord, 59610 Fourmies Nord Pas-de-Calais 59610",
    "addr:postcode":"59611;59610;59610",
    "addr:street":"B.P. 55;Rte D'Anord",
    "iso:country":"FR",
    "sg:address":"B.P. 55, 59611 Fourmies C\u00e9dex^^19, Rte d'Anord, 59610 Fourmies",
    "sg:orig_category":"Non-Classified Establishments",
    "sg:phone":"+33 3 27 60 22 60",
    "sg:postcode":"59610",
    "sg:province":"Nord Pas-de-Calais",
    "wof:name":"De Barba S.a.",
    "wof:placetype":"venue"
},
  "geometry": {"coordinates":[4.04044,50.02301],"type":"Point"}
}