{
  "type": "Feature",
  "properties": {
    "iso:country":"FR",
    "sg:address":"Zone Industrielle Eurochannel",
    "sg:city":"Neuville les Dieppe",
    "sg:orig_category":"Unclassifiable Establishments",
    "sg:phone":"+33 2 35 06 97 97",
    "sg:postcode":"76370",
    "sg:province":"Haute Normandie",
    "wof:name":"Scribe S.a.r.l.",
    "wof:placetype":"venue"
},
  "geometry": {"coordinates":[-98.92620100000001,33.4501],"type":"Point"}
}