{
  "type": "Feature",
  "properties": {
    "addr:full":"18, Rue de l'avenir, 93800 Epinay sur Seine Ile de France",
    "addr:housenumber":"18",
    "addr:postcode":"93800",
    "addr:street":"Rue De L'Avenir",
    "iso:country":"FR",
    "sg:address":"18, Rue de l'avenir, 93800 Epinay sur Seine",
    "sg:orig_category":"Non-Classified Establishments",
    "sg:phone":"+33 1 42 35 90 00",
    "sg:province":"Ile de France",
    "wof:name":"M\u00e9tarlac Industrie S.a.r.l.",
    "wof:placetype":"venue"
},
  "geometry": {"coordinates":[2.330187,48.955074],"type":"Point"}
}