{
  "type": "Feature",
  "properties": {
    "addr:full":"12 Av Sabli\u00e8re 91150 Etampes Ile de France 91150",
    "addr:postcode":"91150;91150",
    "addr:street":"12 Av Sablie\u0300Re",
    "iso:country":"FR",
    "sg:address":"12 Av Sabli\u00e8re 91150 Etampes",
    "sg:classifiers":[
        {
            "category":"Shopping Center",
            "type":"Public Place"
        }
    ],
    "sg:phone":"+33 1 64 94 25 86",
    "sg:postcode":"91150",
    "sg:province":"Ile de France",
    "sg:tags":[
        "product",
        "meat",
        "cooked",
        "frozen",
        "related",
        "food"
    ],
    "wof:name":"Courgeon Sa",
    "wof:placetype":"venue"
},
  "geometry": {"coordinates":[2.159568,48.450432],"type":"Point"}
}