{
  "type": "Feature",
  "properties": {
    "addr:full":"Avenue Maudet Mail Ii Cholet Pays de Loire 49300",
    "addr:postcode":"49300",
    "addr:street":"Avenue Maudet",
    "iso:country":"FR",
    "sg:address":"Avenue Maudet Mail Ii",
    "sg:city":"Cholet",
    "sg:classifiers":[
        {
            "category":"Banks & Credit Unions",
            "subcategory":"Financial Services",
            "type":"Services"
        }
    ],
    "sg:phone":"+33 2 41 49 53 00",
    "sg:postcode":"49300",
    "sg:province":"Pays de Loire",
    "sg:tags":[
        "banking",
        "finance",
        "insurance"
    ],
    "wof:name":"Fiduciaire De France Societe D'expertise Comptable Commissai (fidex)",
    "wof:placetype":"venue"
},
  "geometry": {"coordinates":[-0.892689,46.99659],"type":"Point"}
}