{
  "type": "Feature",
  "properties": {
    "addr:full":"Rue R\u00e9n\u00e9 Pri\u00e8re 61100 Flers Flers Basse Normandie 61100",
    "addr:postcode":"61100;61100",
    "addr:street":"Rue Re\u0301Ne\u0301 Prie\u0300Re",
    "iso:country":"FR",
    "sg:address":"Rue R\u00e9n\u00e9 Pri\u00e8re 61100 Flers",
    "sg:city":"Flers",
    "sg:classifiers":[
        {
            "category":"Autos & Motor Vehicles",
            "subcategory":"Automobile Sales",
            "type":"Retail Goods"
        }
    ],
    "sg:phone":"+33 2 33 65 25 83",
    "sg:postcode":"61100",
    "sg:province":"Basse Normandie",
    "sg:tags":[
        "equipment",
        "industrial",
        "transport"
    ],
    "wof:name":"Martenat Sas",
    "wof:placetype":"venue"
},
  "geometry": {"coordinates":[-0.580389,48.726589],"type":"Point"}
}