{
  "type": "Feature",
  "properties": {
    "addr:full":"Bd Cl\u00e9menceau 85300 Challans Pays de Loire 85300",
    "addr:postcode":"85300;85300",
    "addr:street":"Bd Cle\u0301Menceau",
    "iso:country":"FR",
    "sg:address":"Bd Cl\u00e9menceau 85300 Challans",
    "sg:classifiers":[
        {
            "category":"Autos & Motor Vehicles",
            "subcategory":"Automobile Sales",
            "type":"Retail Goods"
        }
    ],
    "sg:phone":"+33 2 51 93 16 09",
    "sg:postcode":"85300",
    "sg:province":"Pays de Loire",
    "sg:tags":[
        "equipment",
        "motor-cars",
        "transport"
    ],
    "wof:name":"Rembaud (ets) Sa",
    "wof:placetype":"venue"
},
  "geometry": {"coordinates":[-1.880174,46.84906],"type":"Point"}
}