{
  "type": "Feature",
  "properties": {
    "addr:full":"110 route de la Valentine 13011 Marseille Poitou-Charentes",
    "addr:housenumber":"110",
    "addr:postcode":"13011",
    "addr:street":"Route De La Valentine",
    "iso:country":"FR",
    "sg:address":"110 route de la Valentine 13011 Marseille",
    "sg:classifiers":[
        {
            "category":"Autos & Motor Vehicles",
            "subcategory":"Motorcycle Sales",
            "type":"Retail Goods"
        }
    ],
    "sg:phone":"+33 4 91 18 23 23",
    "sg:province":"Poitou-Charentes",
    "sg:tags":[
        "helmet"
    ],
    "wof:name":"Test Moto S.a.",
    "wof:placetype":"venue"
},
  "geometry": {"coordinates":[5.470452,43.289204],"type":"Point"}
}