{
  "type": "Feature",
  "properties": {
    "iso:country":"FR",
    "sg:address":"B.P. 141, 45201 Montargis C\u00e9dex^^5, Rue du Port, 45200 Montargis",
    "sg:city":"Montargis",
    "sg:orig_category":"Non-Classified Establishments",
    "sg:phone":"+33 2 38 93 07 44",
    "sg:postcode":"45200",
    "sg:province":"Centre",
    "wof:name":"P.r.o. S.a.",
    "wof:placetype":"venue"
},
  "geometry": {"coordinates":[2.767561,47.974705],"type":"Point"}
}