{
  "type": "Feature",
  "properties": {
    "addr:full":"2 Rue Leger Bertin Epernay Champagne 51200",
    "addr:housenumber":"2",
    "addr:postcode":"51200",
    "addr:street":"Rue Leger Bertin;Champagne",
    "iso:country":"FR",
    "sg:address":"2 Rue Leger Bertin",
    "sg:city":"Epernay",
    "sg:classifiers":[
        {
            "category":"Banks & Credit Unions",
            "subcategory":"Financial Services",
            "type":"Services"
        }
    ],
    "sg:phone":"+33 3 26 54 14 44",
    "sg:postcode":"51200",
    "sg:province":"Champagne",
    "sg:tags":[
        "banking",
        "finance",
        "insurance"
    ],
    "wof:name":"Fcn Societe Francaise De Revision",
    "wof:placetype":"venue"
},
  "geometry": {"coordinates":[3.950776,49.043755],"type":"Point"}
}