{
  "type": "Feature",
  "properties": {
    "iso:country":"FR",
    "sg:address":"La Fosse Aux Loups 50600 St Hilaire Du Harcouet",
    "sg:city":"Ch\u00e8vreville",
    "sg:classifiers":[
        {
            "category":"Wholesale",
            "subcategory":"Farm Supplies",
            "type":"Manufacturing & Wholesale Goods"
        }
    ],
    "sg:phone":"+33 2 33 79 36 64",
    "sg:postcode":"50600",
    "sg:province":"Basse Normandie",
    "sg:tags":[
        "-",
        "machine",
        "equipment",
        "engineering",
        "machinery",
        "mechanical",
        "agriculture"
    ],
    "wof:name":"Sm 3",
    "wof:placetype":"venue"
},
  "geometry": {"coordinates":[-1.074819,48.572815],"type":"Point"}
}