{
  "type": "Feature",
  "properties": {
    "addr:full":"B.P. 17, 49270 Landemont C\u00e9dex^^ZA de Belemont, 49270 Landemont Pays de Loire",
    "addr:postcode":"49270;49270",
    "addr:street":"B.P. 17",
    "iso:country":"FR",
    "sg:address":"B.P. 17, 49270 Landemont C\u00e9dex^^ZA de Belemont, 49270 Landemont",
    "sg:orig_category":"Non-Classified Establishments",
    "sg:phone":"+33 2 40 98 79 73",
    "sg:province":"Pays de Loire",
    "wof:name":"F.m.c.s. S.a.r.l.",
    "wof:placetype":"venue"
},
  "geometry": {"coordinates":[-1.184474,47.253479],"type":"Point"}
}