{
  "type": "Feature",
  "properties": {
    "iso:country":"FR",
    "sg:address":"107 rue Royale; Lille; 59000",
    "sg:classifiers":[
        {
            "category":"Banks & Credit Unions",
            "subcategory":"Bank",
            "type":"Services"
        }
    ],
    "sg:phone":"+33 3 20 42 19 19",
    "sg:postcode":"59000",
    "sg:province":"Nord Pas-de-Calais",
    "wof:name":"Banque De Gestion, Priv\u00e9e",
    "wof:placetype":"venue"
},
  "geometry": {"coordinates":[3.05482,50.643963],"type":"Point"}
}