{
  "type": "Feature",
  "properties": {
    "iso:country":"FR",
    "sg:address":"625 Bd Des Lucioles 83530 Agay",
    "sg:classifiers":[
        {
            "category":"Wholesale",
            "subcategory":"Machinery & Supplies",
            "type":"Manufacturing & Wholesale Goods"
        }
    ],
    "sg:phone":"+33 4 94 44 80 66",
    "sg:province":"Provence-Alpes-C\u00f4te d'Azur",
    "sg:tags":[
        "equipment",
        "optical",
        "precision",
        "instrument"
    ],
    "wof:name":"Planiciel Villette",
    "wof:placetype":"venue"
},
  "geometry": {"coordinates":[6.863745,43.434319],"type":"Point"}
}