{
  "type": "Feature",
  "properties": {
    "addr:full":"82 Rue De Wittelsheim 68700 Cernay Cernay Alsace 68700",
    "addr:housenumber":"82",
    "addr:postcode":"68700;68700",
    "addr:street":"Rue De Wittelsheim",
    "iso:country":"FR",
    "sg:address":"82 Rue De Wittelsheim 68700 Cernay",
    "sg:city":"Cernay",
    "sg:classifiers":[
        {
            "category":"Farming",
            "subcategory":"Farm",
            "type":"Manufacturing & Wholesale Goods"
        }
    ],
    "sg:phone":"+33 3 89 38 38 38",
    "sg:postcode":"68700",
    "sg:province":"Alsace",
    "sg:tags":[
        "horticulture",
        "agriculture",
        "livestock"
    ],
    "wof:name":"Du Pont De Nemours France Sa",
    "wof:placetype":"venue"
},
  "geometry": {"coordinates":[7.188933,47.802299],"type":"Point"}
}