{
  "type": "Feature",
  "properties": {
    "addr:full":"34, Rue Saint Romain, 69359 Lyon C\u00e9dex 8 Rhone-Alpes",
    "addr:housenumber":"34;8",
    "addr:postcode":"69359",
    "addr:street":"Rue Saint Romain;Ce\u0301Dex",
    "iso:country":"FR",
    "sg:address":"34, Rue Saint Romain, 69359 Lyon C\u00e9dex 8",
    "sg:orig_category":"Non-Classified Establishments",
    "sg:phone":"+33 4 72 78 27 35",
    "sg:province":"Rhone-Alpes",
    "wof:name":"Merck G\u00e9n\u00e9riques S.c.s.",
    "wof:placetype":"venue"
},
  "geometry": {"coordinates":[4.865513,45.740749],"type":"Point"}
}