{
  "type": "Feature",
  "properties": {
    "addr:full":"12 Rte De Blou 49160 Longu\u00e9 Jumelles Pays de Loire",
    "addr:housenumber":"12",
    "addr:postcode":"49160",
    "addr:street":"Rte De Blou",
    "iso:country":"FR",
    "sg:address":"12 Rte De Blou 49160 Longu\u00e9 Jumelles",
    "sg:classifiers":[
        {
            "category":"Home & Garden",
            "subcategory":"Furniture",
            "type":"Retail Goods"
        }
    ],
    "sg:phone":"+33 2 41 52 10 82",
    "sg:province":"Pays de Loire",
    "sg:tags":[
        "wood"
    ],
    "wof:name":"Cirie Chevrollier",
    "wof:placetype":"venue"
},
  "geometry": {"coordinates":[-0.100753,47.377602],"type":"Point"}
}