{
  "type": "Feature",
  "properties": {
    "addr:full":"B.P. 2, 46101 Figeac C\u00e9dex^^Rte de Cahors, 46100 Figeac Midi Pyr\u00e9n\u00e9es",
    "addr:housenumber":"2",
    "addr:postcode":"46101;46100",
    "addr:street":"B.P.",
    "iso:country":"FR",
    "sg:address":"B.P. 2, 46101 Figeac C\u00e9dex^^Rte de Cahors, 46100 Figeac",
    "sg:orig_category":"Non-Classified Establishments",
    "sg:phone":"+33 5 65 50 50 50",
    "sg:province":"Midi Pyr\u00e9n\u00e9es",
    "wof:name":"Ratier Figeac S.a.",
    "wof:placetype":"venue"
},
  "geometry": {"coordinates":[2.024565,44.560276],"type":"Point"}
}