{
  "type": "Feature",
  "properties": {
    "addr:full":"Rue de Gravigny; Chilly Mazarin; 91380 Ile de France 91380",
    "addr:postcode":"91380;91380",
    "addr:street":"Rue De Gravigny;Ile De France",
    "iso:country":"FR",
    "sg:address":"Rue de Gravigny; Chilly Mazarin; 91380",
    "sg:classifiers":[
        {
            "category":"Banks & Credit Unions",
            "subcategory":"Bank",
            "type":"Services"
        }
    ],
    "sg:phone":"+33 3369093703",
    "sg:postcode":"91380",
    "sg:province":"Ile de France",
    "wof:name":"Soci\u00e9t\u00e9 G\u00e9n\u00e9rale",
    "wof:placetype":"venue"
},
  "geometry": {"coordinates":[2.30599,48.696735],"type":"Point"}
}