{
  "type": "Feature",
  "properties": {
    "iso:country":"FR",
    "sg:address":"B.P. 79, 64232 Lescar C\u00e9dex^^Rue de Saint Exup\u00e9ry, 64230 Lescar",
    "sg:city":"Lescar",
    "sg:orig_category":"Non-Classified Establishments",
    "sg:phone":"+33 5 59 72 78 78",
    "sg:postcode":"64230",
    "sg:province":"Aquitaine",
    "wof:name":"A.d. Blanchardet - Gadso S.a.",
    "wof:placetype":"venue"
},
  "geometry": {"coordinates":[-0.469177,43.319443],"type":"Point"}
}