{
  "type": "Feature",
  "properties": {
    "iso:country":"FR",
    "sg:address":"Place de la Gare",
    "sg:city":"L'Hermitage",
    "sg:orig_category":"Unclassifiable Establishments",
    "sg:phone":"+33 2 99 01 87 87",
    "sg:postcode":"35590",
    "sg:province":"Bretagne",
    "wof:name":"Soci\u00e9t\u00e9 Laiti\u00e8re De L'hermitage S.n.c.",
    "wof:placetype":"venue"
},
  "geometry": {"coordinates":[6.085808,44.56356],"type":"Point"}
}