{
  "type": "Feature",
  "properties": {
    "iso:country":"FR",
    "sg:address":"21, Rue de la Marli\u00e8re, 95200 Sarcelles",
    "sg:orig_category":"Unclassifiable Establishments",
    "sg:phone":"+33 1 39 90 34 12",
    "sg:province":"Ile de France",
    "wof:name":"Elale S.a.",
    "wof:placetype":"venue"
},
  "geometry": {"coordinates":[2.37662,49.00079],"type":"Point"}
}