{
  "type": "Feature",
  "properties": {
    "addr:full":"21, Rue de la Marli\u00e8re, 95200 Sarcelles Ile de France",
    "addr:housenumber":"21",
    "addr:postcode":"95200;ile",
    "addr:street":"Rue De La Marlie\u0300Re",
    "iso:country":"FR",
    "sg:address":"21, Rue de la Marli\u00e8re, 95200 Sarcelles",
    "sg:orig_category":"Unclassifiable Establishments",
    "sg:phone":"+33 1 39 90 34 12",
    "sg:province":"Ile de France",
    "wof:name":"Elale S.a.",
    "wof:placetype":"venue"
},
  "geometry": {"coordinates":[2.37662,49.00079],"type":"Point"}
}