{
  "type": "Feature",
  "properties": {
    "addr:full":"2 Rte D'Angoul\u00eame BP 8 17160 Matha Poitou-Charentes 17160",
    "addr:housenumber":"2;8",
    "addr:postcode":"17160;17160",
    "addr:street":"Rte D'Angoule \u0302Me Bp",
    "iso:country":"FR",
    "sg:address":"2 Rte D'Angoul\u00eame BP 8 17160 Matha",
    "sg:classifiers":[
        {
            "category":"Home & Garden",
            "subcategory":"Furniture",
            "type":"Retail Goods"
        }
    ],
    "sg:phone":"+33 5 46 58 52 20",
    "sg:postcode":"17160",
    "sg:province":"Poitou-Charentes",
    "sg:tags":[
        "professional",
        "household",
        "wood"
    ],
    "wof:name":"Simmob Sa",
    "wof:placetype":"venue"
},
  "geometry": {"coordinates":[-0.31947,45.868252],"type":"Point"}
}