{
  "type": "Feature",
  "properties": {
    "addr:full":"66, Rue G\u00e9n\u00e9ral Leclerc, 95410 Groslay Ile de France",
    "addr:housenumber":"66",
    "addr:postcode":"95410",
    "addr:street":"Rue Ge\u0301Ne\u0301Ral Leclerc;Ile De France",
    "iso:country":"FR",
    "sg:address":"66, Rue G\u00e9n\u00e9ral Leclerc, 95410 Groslay",
    "sg:orig_category":"Unclassifiable Establishments",
    "sg:phone":"+33 1 39 83 69 09",
    "sg:province":"Ile de France",
    "wof:name":"Byblos Groupement Arts S.a.",
    "wof:placetype":"venue"
},
  "geometry": {"coordinates":[2.348343,48.985966],"type":"Point"}
}