{
  "type": "Feature",
  "properties": {
    "addr:full":"B.P. 285, 76121 Le Grand Quevilly C\u00e9dex^^Bd Franklin Roosevelt - ZI du Grand Launay, 76120 Le Grand  Haute Normandie",
    "addr:housenumber":"b.p. 285",
    "addr:postcode":"76121;76120",
    "addr:street":"Franklin Roosevelt Zi Du Grand Launay",
    "iso:country":"FR",
    "sg:address":"B.P. 285, 76121 Le Grand Quevilly C\u00e9dex^^Bd Franklin Roosevelt - ZI du Grand Launay, 76120 Le Grand ",
    "sg:orig_category":"Non-Classified Establishments",
    "sg:phone":"+33 2 35 68 83 83",
    "sg:province":"Haute Normandie",
    "wof:name":"Ici Paints S.a.",
    "wof:placetype":"venue"
},
  "geometry": {"coordinates":[-120.251221,37.228439],"type":"Point"}
}