{
  "type": "Feature",
  "properties": {
    "iso:country":"FR",
    "sg:address":"16, Rue Thales - Parc d'Activit\u00e9 Ch\u00e2teau Rouquey, 33700 M\u00e9rignac",
    "sg:city":"M\u00e9rignac",
    "sg:orig_category":"Unclassifiable Establishments",
    "sg:phone":"+33 5 57 92 45 45",
    "sg:postcode":"33700",
    "sg:province":"Aquitaine",
    "wof:name":"Sera Location Aquitaine S.a.",
    "wof:placetype":"venue"
},
  "geometry": {"coordinates":[-0.669891,44.833038],"type":"Point"}
}