{
  "type": "Feature",
  "properties": {
    "iso:country":"FR",
    "sg:address":"Rte De Fos 13800 Istres",
    "sg:classifiers":[
        {
            "category":"Travel",
            "subcategory":"Hotels & Motels",
            "type":"Entertainment"
        }
    ],
    "sg:phone":"+33 4 42 55 64 30",
    "sg:province":"Midi Pyr\u00e9n\u00e9es",
    "sg:tags":[
        "hotels",
        "business",
        "restaurant"
    ],
    "wof:name":"Casino Cafeteria",
    "wof:placetype":"venue"
},
  "geometry": {"coordinates":[4.967923,43.490612],"type":"Point"}
}