{
  "type": "Feature",
  "properties": {
    "addr:full":"Route De Marolles 41330 Fosse Marolles Centre 41330",
    "addr:postcode":"41330;41330",
    "addr:street":"Route De Marolles",
    "iso:country":"FR",
    "sg:address":"Route De Marolles 41330 Fosse",
    "sg:city":"Marolles",
    "sg:classifiers":[
        {
            "category":"Professional",
            "type":"Services"
        }
    ],
    "sg:phone":"+33 2 54 52 59 59",
    "sg:postcode":"41330",
    "sg:province":"Centre",
    "sg:tags":[
        "transport",
        "road"
    ],
    "wof:name":"Danzas Sa",
    "wof:placetype":"venue"
},
  "geometry": {"coordinates":[1.285927,47.637325],"type":"Point"}
}