{
  "type": "Feature",
  "properties": {
    "iso:country":"FR",
    "sg:address":"B.P. 12, 53110 Lassay les Ch\u00e2teaux C\u00e9dex^^Rte de Couterne - ZI, 53110 Lassay les Ch\u00e2teaux",
    "sg:orig_category":"Non-Classified Establishments",
    "sg:phone":"+33 2 43 08 20 50",
    "sg:province":"Pays de Loire",
    "wof:name":"Tryba Lassay S.a.s.",
    "wof:placetype":"venue"
},
  "geometry": {"coordinates":[-0.48579,48.42181],"type":"Point"}
}