{
  "type": "Feature",
  "properties": {
    "addr:full":"Les Bouvents 16200 Jarnac Poitou-Charentes",
    "addr:postcode":"16200",
    "iso:country":"FR",
    "sg:address":"Les Bouvents 16200 Jarnac",
    "sg:orig_category":"Unclassifiable Establishments",
    "sg:phone":"+33 5 45 81 11 17",
    "sg:province":"Poitou-Charentes",
    "wof:name":"Crouzilles Andr\u00e9 S.a.",
    "wof:placetype":"venue"
},
  "geometry": {"coordinates":[-0.182009,45.684467],"type":"Point"}
}