{
  "type": "Feature",
  "properties": {
    "addr:full":"B.P. 436, 50304 Avranches C\u00e9dex^^Rue des Gr\u00e8ves, 50300 Avranches Avranches Basse Normandie 50300",
    "addr:housenumber":"b.p. 436",
    "addr:postcode":"50304;50300;50300",
    "addr:street":"Des Gre\u0300Ves",
    "iso:country":"FR",
    "sg:address":"B.P. 436, 50304 Avranches C\u00e9dex^^Rue des Gr\u00e8ves, 50300 Avranches",
    "sg:city":"Avranches",
    "sg:orig_category":"Non-Classified Establishments",
    "sg:phone":"+33 2 33 68 75 00",
    "sg:postcode":"50300",
    "sg:province":"Basse Normandie",
    "wof:name":"Kdi Nozal S.a.s.",
    "wof:placetype":"venue"
},
  "geometry": {"coordinates":[-1.377784,48.663998],"type":"Point"}
}