{
  "type": "Feature",
  "properties": {
    "iso:country":"FR",
    "sg:address":"67 Rue Jean Baptiste Colbert 10600 La Chapelle St Luc",
    "sg:classifiers":[
        {
            "category":"Wholesale",
            "subcategory":"Machinery & Supplies",
            "type":"Manufacturing & Wholesale Goods"
        }
    ],
    "sg:phone":"+33 3 25 74 67 36",
    "sg:postcode":"10600",
    "sg:province":"Champagne",
    "sg:tags":[
        "handling",
        "material",
        "-",
        "machine",
        "equipment",
        "engineering",
        "mechanical"
    ],
    "wof:name":"Fenwick Linde Sarl",
    "wof:placetype":"venue"
},
  "geometry": {"coordinates":[4.027841,48.321571],"type":"Point"}
}