{
  "type": "Feature",
  "properties": {
    "addr:full":"43 Bv Devoux 78300 Poissy Ile de France",
    "addr:postcode":"78300;ile",
    "iso:country":"FR",
    "sg:address":"43 Bv Devoux 78300 Poissy",
    "sg:classifiers":[
        {
            "category":"Manufacturing",
            "subcategory":"Rubber & Plastics",
            "type":"Manufacturing & Wholesale Goods"
        }
    ],
    "sg:phone":"+33 1 39 65 29 09",
    "sg:province":"Ile de France",
    "wof:name":"Euromaster",
    "wof:placetype":"venue"
},
  "geometry": {"coordinates":[2.048622,48.932396],"type":"Point"}
}