{
  "type": "Feature",
  "properties": {
    "iso:country":"FR",
    "sg:address":"Zi Sainte Marie 44650 Lege",
    "sg:classifiers":[
        {
            "category":"Shopping",
            "subcategory":"Clothing, Apparel, & Fashions",
            "type":"Retail Goods"
        }
    ],
    "sg:phone":"+33 2 40 26 39 30",
    "sg:postcode":"44650",
    "sg:province":"Pays de Loire",
    "sg:tags":[
        "textile",
        "clothing",
        "clothes"
    ],
    "wof:name":"Acc Atelier Cannelle Couture",
    "wof:placetype":"venue"
},
  "geometry": {"coordinates":[-1.598079,46.885136],"type":"Point"}
}