{
  "type": "Feature",
  "properties": {
    "iso:country":"FR",
    "sg:address":"42, Rue Jean d'Abbans, 25220 Thise",
    "sg:orig_category":"Non-Classified Establishments",
    "sg:phone":"+33 3 81 47 71 90",
    "sg:province":"Franche Comt\u00e9",
    "wof:name":"Fraporlux S.a.",
    "wof:placetype":"venue"
},
  "geometry": {"coordinates":[6.070078,47.285576],"type":"Point"}
}