{
  "type": "Feature",
  "properties": {
    "addr:full":"20 Av L\u00e9on Jouhaux 33210 Langon Langon Aquitaine 33210",
    "addr:postcode":"33210;33210",
    "addr:street":"20 Av Le\u0301On Jouhaux",
    "iso:country":"FR",
    "sg:address":"20 Av L\u00e9on Jouhaux 33210 Langon",
    "sg:city":"Langon",
    "sg:classifiers":[
        {
            "category":"Shopping",
            "type":"Retail Goods"
        }
    ],
    "sg:phone":"+33 5 56 63 18 66",
    "sg:postcode":"33210",
    "sg:province":"Aquitaine",
    "sg:tags":[
        "metallurgy",
        "finished",
        "-",
        "metalworking",
        "metallic"
    ],
    "wof:name":"Atelier Langonnais Sarl",
    "wof:placetype":"venue"
},
  "geometry": {"coordinates":[-0.264876,44.547108],"type":"Point"}
}