{
  "type": "Feature",
  "properties": {
    "iso:country":"FR",
    "sg:address":"937, Rue Amp\u00e8re, 69400 Villefranche sur Sa\u00f4ne",
    "sg:orig_category":"Unclassifiable Establishments",
    "sg:phone":"+33 4 74 09 02 82",
    "sg:province":"Rhone-Alpes",
    "wof:name":"Filtisac France S.a.",
    "wof:placetype":"venue"
},
  "geometry": {"coordinates":[4.732899,45.985847],"type":"Point"}
}