{
  "type": "Feature",
  "properties": {
    "addr:full":"900, Chemin de la Vall\u00e9e, 13400 Aubagne Franche Comt\u00e9",
    "addr:housenumber":"900",
    "addr:postcode":"13400",
    "addr:street":"Chemin De La Valle\u0301E;Franche Comte\u0301",
    "iso:country":"FR",
    "sg:address":"900, Chemin de la Vall\u00e9e, 13400 Aubagne",
    "sg:orig_category":"Non-Classified Establishments",
    "sg:phone":"+33 4 42 18 88 87",
    "sg:province":"Franche Comt\u00e9",
    "wof:name":"G.t.e.i. S.a. - G\u00e9n\u00e9rale Technique Industrie",
    "wof:placetype":"venue"
},
  "geometry": {"coordinates":[5.521964,43.284332],"type":"Point"}
}