{
  "type": "Feature",
  "properties": {
    "iso:country":"FR",
    "sg:address":"20, Rue de Saint Denis de Gastines, 53500 Ern\u00e9e",
    "sg:orig_category":"Unclassifiable Establishments",
    "sg:phone":"+33 2 43 05 13 86",
    "sg:province":"Pays de Loire",
    "wof:name":"Corderie Henri Lancelin S.a.",
    "wof:placetype":"venue"
},
  "geometry": {"coordinates":[-1.027721,48.273811],"type":"Point"}
}