{
  "type": "Feature",
  "properties": {
    "addr:full":"Chem Du Pav\u00e9 De L'Ambre 62117 Brebi\u00e8res Nord Pas-de-Calais 62117",
    "addr:postcode":"62117;62117",
    "addr:street":"Chem Du Pave\u0301 De L'Ambre",
    "iso:country":"FR",
    "sg:address":"Chem Du Pav\u00e9 De L'Ambre 62117 Brebi\u00e8res",
    "sg:classifiers":[
        {
            "category":"Manufacturing",
            "subcategory":"Metals",
            "type":"Manufacturing & Wholesale Goods"
        }
    ],
    "sg:phone":"+33 3 27 87 10 40",
    "sg:postcode":"62117",
    "sg:province":"Nord Pas-de-Calais",
    "sg:tags":[
        "pipe",
        "sheet",
        "-",
        "metalworking",
        "metallic",
        "metallurgy",
        "finished"
    ],
    "wof:name":"Boccard Sa",
    "wof:placetype":"venue"
},
  "geometry": {"coordinates":[3.027271,50.338806],"type":"Point"}
}