{
  "type": "Feature",
  "properties": {
    "addr:full":"Rue de la Roche sur Yon - ZI Saint Gilles Croix de Vie Pays de Loire 85800",
    "addr:postcode":"85800",
    "addr:street":"Rue De La Roche Sur Yon Zi Saint Gilles Croix De Vie",
    "iso:country":"FR",
    "sg:address":"Rue de la Roche sur Yon - ZI",
    "sg:city":"Saint Gilles Croix de Vie",
    "sg:orig_category":"Unclassifiable Establishments",
    "sg:phone":"+33 2 51 60 09 00",
    "sg:postcode":"85800",
    "sg:province":"Pays de Loire",
    "wof:name":"Compagnie Saupiquet S.a.",
    "wof:placetype":"venue"
},
  "geometry": {"coordinates":[-1.884384,46.671253],"type":"Point"}
}