{
  "type": "Feature",
  "properties": {
    "iso:country":"FR",
    "sg:address":"38 Rue Gustave Eiffel 33600 Pessac",
    "sg:city":"Pessac",
    "sg:classifiers":[
        {
            "category":"Manufacturing",
            "subcategory":"Rubber & Plastics",
            "type":"Manufacturing & Wholesale Goods"
        }
    ],
    "sg:phone":"+33 5 56 36 43 24",
    "sg:postcode":"33600",
    "sg:province":"Aquitaine",
    "wof:name":"Frans Bonhomme",
    "wof:placetype":"venue"
},
  "geometry": {"coordinates":[-0.655413,44.778622],"type":"Point"}
}