{
  "type": "Feature",
  "properties": {
    "iso:country":"FR",
    "sg:address":"90, Rue Stanislas Torrents, 13006 Marseille",
    "sg:orig_category":"Unclassifiable Establishments",
    "sg:phone":"+33 4 91 13 81 80",
    "sg:province":"Provence-Alpes-C\u00f4te d'Azur",
    "wof:name":"S.p.2.i. S.a. - Soci\u00e9t\u00e9 Phoc\u00e9enne D'ing\u00e9nierie",
    "wof:placetype":"venue"
},
  "geometry": {"coordinates":[5.379732,43.284939],"type":"Point"}
}