{
  "type": "Feature",
  "properties": {
    "addr:full":"1/6, Bd de la Lib\u00e9ration, 93200 Saint Denis Ile de France",
    "addr:housenumber":"1 / 6",
    "addr:postcode":"93200",
    "addr:street":"Bd De La Libe\u0301Ration",
    "iso:country":"FR",
    "sg:address":"1/6, Bd de la Lib\u00e9ration, 93200 Saint Denis",
    "sg:orig_category":"Non-Classified Establishments",
    "sg:phone":"+33 1 41 34 95 00",
    "sg:province":"Ile de France",
    "wof:name":"Insert Centre Ville Communication S.a.",
    "wof:placetype":"venue"
},
  "geometry": {"coordinates":[2.342904,48.935795],"type":"Point"}
}