{
  "type": "Feature",
  "properties": {
    "addr:full":"B.P. 19, 88155 Thaon Les Vosges C\u00e9dex^^Rte de l'Avenir - Innova 3000, 88150 Thaon les Vosges Lorraine",
    "addr:housenumber":"3000",
    "addr:postcode":"88155;88150",
    "addr:street":"B.P. 19;Innova",
    "iso:country":"FR",
    "sg:address":"B.P. 19, 88155 Thaon Les Vosges C\u00e9dex^^Rte de l'Avenir - Innova 3000, 88150 Thaon les Vosges",
    "sg:orig_category":"Non-Classified Establishments",
    "sg:phone":"+33 3 29 81 30 60",
    "sg:province":"Lorraine",
    "wof:name":"Garret-engine-boosting-systems S.a.",
    "wof:placetype":"venue"
},
  "geometry": {"coordinates":[6.402621,48.25367],"type":"Point"}
}