{
  "type": "Feature",
  "properties": {
    "iso:country":"FR",
    "sg:address":"13, Rue Arthur Adamov, 94500 Champigny sur Marne",
    "sg:orig_category":"Unclassifiable Establishments",
    "sg:phone":"+33 1 47 06 29 96",
    "sg:province":"Ile de France",
    "wof:name":"A.a. S.a.r.l. - Agriclimat",
    "wof:placetype":"venue"
},
  "geometry": {"coordinates":[2.507378,48.824661],"type":"Point"}
}