{
  "type": "Feature",
  "properties": {
    "addr:full":"Z I 31130 Flourens Midi Pyr\u00e9n\u00e9es",
    "addr:postcode":"31130",
    "addr:street":"Z",
    "iso:country":"FR",
    "sg:address":"Z I 31130 Flourens",
    "sg:classifiers":[
        {
            "category":"Manufacturing",
            "subcategory":"Motor Vehicles & Parts",
            "type":"Manufacturing & Wholesale Goods"
        }
    ],
    "sg:phone":"+33 5 61 83 65 28",
    "sg:province":"Midi Pyr\u00e9n\u00e9es",
    "sg:tags":[
        "precision",
        "mechanic"
    ],
    "wof:name":"Remax S.a.",
    "wof:placetype":"venue"
},
  "geometry": {"coordinates":[1.550898,43.576588],"type":"Point"}
}