{
  "type": "Feature",
  "properties": {
    "addr:full":"BP 1X, 44040 Nantes CEDEX 01, Dept 44, France.^^2 Jean-Claude Bonduelle Ave, 44000 Nantes CEDEX, Dep Pays de Loire 44000",
    "addr:housenumber":"^ 2",
    "addr:postcode":"44040;44000;dep;44000",
    "addr:street":"Jean-Claude Bonduelle Ave",
    "iso:country":"FR",
    "sg:address":"BP 1X, 44040 Nantes CEDEX 01, Dept 44, France.^^2 Jean-Claude Bonduelle Ave, 44000 Nantes CEDEX, Dep",
    "sg:classifiers":[
        {
            "category":"Banks & Credit Unions",
            "subcategory":"Bank",
            "type":"Services"
        }
    ],
    "sg:postcode":"44000",
    "sg:province":"Pays de Loire",
    "wof:name":"Bail Ouest",
    "wof:placetype":"venue"
},
  "geometry": {"coordinates":[-1.553059,47.218117],"type":"Point"}
}