{
  "type": "Feature",
  "properties": {
    "iso:country":"FR",
    "sg:address":"6 Bis Rue Des Pentonniers 67000 Strasbourg",
    "sg:city":"Strasbourg",
    "sg:classifiers":[
        {
            "category":"Banks & Credit Unions",
            "subcategory":"Financial Services",
            "type":"Services"
        }
    ],
    "sg:phone":"+33 3 88 24 39 39",
    "sg:postcode":"67000",
    "sg:province":"Alsace",
    "sg:tags":[
        "banking",
        "finance",
        "insurance"
    ],
    "wof:name":"Groupement Des Assur\u00c9s",
    "wof:placetype":"venue"
},
  "geometry": {"coordinates":[7.757237,48.584309],"type":"Point"}
}