{
  "type": "Feature",
  "properties": {
    "addr:full":"Le Suq De La Peine 46300 St Cirq Madelon Midi Pyr\u00e9n\u00e9es 46300",
    "addr:postcode":"46300;46300",
    "iso:country":"FR",
    "sg:address":"Le Suq De La Peine 46300 St Cirq Madelon",
    "sg:classifiers":[
        {
            "category":"Farming",
            "subcategory":"Crops",
            "type":"Manufacturing & Wholesale Goods"
        }
    ],
    "sg:phone":"+33 5 65 41 36 46",
    "sg:postcode":"46300",
    "sg:province":"Midi Pyr\u00e9n\u00e9es",
    "sg:tags":[
        "vegetable",
        "fruit",
        "agriculture",
        "livestock"
    ],
    "wof:name":"Diamants Du Perigord Sarl",
    "wof:placetype":"venue"
},
  "geometry": {"coordinates":[1.41163,44.69997],"type":"Point"}
}