{
  "type": "Feature",
  "properties": {
    "addr:full":"337, Rue de la Combe Caude, 34090 Montpellier Languedoc-Roussillon",
    "addr:housenumber":"337",
    "addr:postcode":"34090",
    "addr:street":"Rue De La Combe Caude",
    "iso:country":"FR",
    "sg:address":"337, Rue de la Combe Caude, 34090 Montpellier",
    "sg:orig_category":"Non-Classified Establishments",
    "sg:phone":"+33 4 67 63 53 40",
    "sg:province":"Languedoc-Roussillon",
    "wof:name":"S.i.c.s. S.a.r.l. - Soci\u00e9t\u00e9 Internationale Congr\u00e8s Et Services",
    "wof:placetype":"venue"
},
  "geometry": {"coordinates":[3.886363,43.636833],"type":"Point"}
}