{
  "type": "Feature",
  "properties": {
    "iso:country":"FR",
    "sg:address":"1, Rue Saint Claude, 77340 Pontault Combault",
    "sg:orig_category":"Non-Classified Establishments",
    "sg:phone":"+33 1 64 43 51 10",
    "sg:province":"Ile de France",
    "wof:name":"Massor Term S.a.r.l",
    "wof:placetype":"venue"
},
  "geometry": {"coordinates":[2.610853,48.778019],"type":"Point"}
}