{
  "type": "Feature",
  "properties": {
    "iso:country":"FR",
    "sg:address":"3, Av. de Saint Germain, 78700 Conflans Sainte Honorine",
    "sg:orig_category":"Unclassifiable Establishments",
    "sg:phone":"+33 1 39 72 69 82",
    "sg:province":"Ile de France",
    "wof:name":"Le Bloc S.a.",
    "wof:placetype":"venue"
},
  "geometry": {"coordinates":[2.08383,48.987488],"type":"Point"}
}