{
  "type": "Feature",
  "properties": {
    "addr:full":"102, Av. Jean Jaur\u00e8s, 69007 Lyon Rhone-Alpes 69007",
    "addr:postcode":"69007;69007",
    "addr:street":"102 Av. Jean Jaure\u0300S",
    "iso:country":"FR",
    "sg:address":"102, Av. Jean Jaur\u00e8s, 69007 Lyon",
    "sg:orig_category":"Non-Classified Establishments",
    "sg:phone":"+33 4 72 80 76 76",
    "sg:postcode":"69007",
    "sg:province":"Rhone-Alpes",
    "wof:name":"Hertz France S.a.",
    "wof:placetype":"venue"
},
  "geometry": {"coordinates":[4.840617,45.743553],"type":"Point"}
}