{
  "type": "Feature",
  "properties": {
    "iso:country":"FR",
    "sg:address":"1 Rue Du Dauphin\u00e9 21121 Fontaine Les Dijon",
    "sg:city":"Ahuy",
    "sg:classifiers":[
        {
            "category":"Manufacturing",
            "subcategory":"Tools & Machinery",
            "type":"Manufacturing & Wholesale Goods"
        }
    ],
    "sg:phone":"+33 3 80 53 99 66",
    "sg:postcode":"21121",
    "sg:province":"Bourgogne",
    "sg:tags":[
        "equipment",
        "measurement",
        "-",
        "precision",
        "instrument"
    ],
    "wof:name":"Cerberus",
    "wof:placetype":"venue"
},
  "geometry": {"coordinates":[5.036845,47.338215],"type":"Point"}
}