{
  "type": "Feature",
  "properties": {
    "addr:full":"20 Rue Malher 75004 Paris Ile de France 75004",
    "addr:housenumber":"20",
    "addr:postcode":"75004;75004",
    "addr:street":"Rue Malher",
    "iso:country":"FR",
    "sg:address":"20 Rue Malher 75004 Paris",
    "sg:classifiers":[
        {
            "category":"Professional",
            "subcategory":"Advertising",
            "type":"Services"
        }
    ],
    "sg:phone":"+33 1 42 72 79 00",
    "sg:postcode":"75004",
    "sg:province":"Ile de France",
    "sg:tags":[
        "marketing",
        "medium",
        "communication"
    ],
    "wof:name":"Jpf Consultants Sa",
    "wof:placetype":"venue"
},
  "geometry": {"coordinates":[2.36158,48.856567],"type":"Point"}
}