{
  "type": "Feature",
  "properties": {
    "iso:country":"FR",
    "sg:address":"80, Rue Lazare-Carnot, 56100 Lorient",
    "sg:city":"Lorient",
    "sg:orig_category":"Unclassifiable Establishments",
    "sg:phone":"+33 2 97 64 46 42",
    "sg:postcode":"56100",
    "sg:province":"Bretagne",
    "wof:name":"Malherbe Transports De L'ouest Europ\u00e9en",
    "wof:placetype":"venue"
},
  "geometry": {"coordinates":[-3.363712,47.740932],"type":"Point"}
}