{
  "type": "Feature",
  "properties": {
    "addr:full":"ZAC de la Guenaudiere 35300 FOUGERES Foug\u00e8res Bretagne 35300",
    "addr:postcode":"35300;35300",
    "addr:street":"Zac De La Guenaudiere;Fouge\u0300Res",
    "iso:country":"FR",
    "sg:address":"ZAC de la Guenaudiere 35300 FOUGERES",
    "sg:city":"Foug\u00e8res",
    "sg:classifiers":[
        {
            "category":"Professional",
            "type":"Services"
        }
    ],
    "sg:phone":"+33 2 99 94 77 00",
    "sg:postcode":"35300",
    "sg:province":"Bretagne",
    "sg:tags":[
        "transport"
    ],
    "wof:name":"Transports Gelin S.a",
    "wof:placetype":"venue"
},
  "geometry": {"coordinates":[-1.200204,48.35429],"type":"Point"}
}