{
  "type": "Feature",
  "properties": {
    "iso:country":"FR",
    "sg:address":"Av de Bretagne - Immeuble Normandie I",
    "sg:city":"Rouen",
    "sg:orig_category":"Unclassifiable Establishments",
    "sg:phone":"+33 2 35 03 48 60",
    "sg:postcode":"76100",
    "sg:province":"Haute Normandie",
    "wof:name":"Dalkia S.c.a.",
    "wof:placetype":"venue"
},
  "geometry": {"coordinates":[1.083909,49.432251],"type":"Point"}
}