{
  "type": "Feature",
  "properties": {
    "iso:country":"FR",
    "sg:address":"123 rue de Douai 59000 Lille",
    "sg:classifiers":[
        {
            "category":"Farming",
            "subcategory":"Orchard",
            "type":"Manufacturing & Wholesale Goods"
        }
    ],
    "sg:phone":"+33 3 20 90 47 90",
    "sg:province":"Nord Pas-de-Calais",
    "sg:tags":[
        "switchgear"
    ],
    "wof:name":"Tibelec Sa",
    "wof:placetype":"venue"
},
  "geometry": {"coordinates":[3.072983,50.620522],"type":"Point"}
}