{
  "type": "Feature",
  "properties": {
    "addr:full":"17, Rue du Muguet, 54360 Damelevi\u00e8res Lorraine",
    "addr:housenumber":"17",
    "addr:postcode":"54360",
    "addr:street":"Rue Du Muguet",
    "iso:country":"FR",
    "sg:address":"17, Rue du Muguet, 54360 Damelevi\u00e8res",
    "sg:orig_category":"Non-Classified Establishments",
    "sg:phone":"+33 3 83 75 71 08",
    "sg:province":"Lorraine",
    "wof:name":"Fornoni Am\u00e9d\u00e9e S.a. - Travaux Ferroviaires",
    "wof:placetype":"venue"
},
  "geometry": {"coordinates":[6.402152,48.562908],"type":"Point"}
}