{
  "type": "Feature",
  "properties": {
    "iso:country":"FR",
    "sg:address":"Zi De La Lande Chemin De Bel Air 33450 St Loubes",
    "sg:city":"Saint-Loub\u00e8s",
    "sg:classifiers":[
        {
            "category":"Manufacturing",
            "subcategory":"Metals",
            "type":"Manufacturing & Wholesale Goods"
        }
    ],
    "sg:phone":"+33 5 56 38 62 62",
    "sg:postcode":"33450",
    "sg:province":"Aquitaine",
    "sg:tags":[
        "metallurgy",
        "metalworking",
        "processing"
    ],
    "wof:name":"Oxycoup Sa",
    "wof:placetype":"venue"
},
  "geometry": {"coordinates":[-0.429024,44.91724],"type":"Point"}
}