{
  "type": "Feature",
  "properties": {
    "iso:country":"FR",
    "sg:address":"14 Rue Du Foss\u00e9 Blanc B\u00e2t A3 92230 Gennevilliers",
    "sg:classifiers":[
        {
            "category":"Shopping",
            "type":"Retail Goods"
        }
    ],
    "sg:phone":"+33 1 41 11 53 90",
    "sg:postcode":"92230",
    "sg:province":"Ile de France",
    "sg:tags":[
        "metallurgy",
        "finished",
        "-",
        "metalworking",
        "metallic"
    ],
    "wof:name":"Parker Hannifin Rak Sa",
    "wof:placetype":"venue"
},
  "geometry": {"coordinates":[2.30653,48.922733],"type":"Point"}
}