{
  "type": "Feature",
  "properties": {
    "addr:full":"95 Fbg De Menil 54300 Luneville Lorraine",
    "addr:housenumber":"95",
    "addr:postcode":"54300",
    "addr:street":"Fbg De Menil",
    "iso:country":"FR",
    "sg:address":"95 Fbg De Menil 54300 Luneville",
    "sg:classifiers":[
        {
            "category":"Autos & Motor Vehicles",
            "subcategory":"Automobile Sales",
            "type":"Retail Goods"
        }
    ],
    "sg:phone":"+33 3 83 76 25 20",
    "sg:province":"Lorraine",
    "sg:tags":[
        "equipment",
        "transport"
    ],
    "wof:name":"Ste Distribution Automobile Lunevilloise",
    "wof:placetype":"venue"
},
  "geometry": {"coordinates":[6.489745,48.584122],"type":"Point"}
}