{
  "type": "Feature",
  "properties": {
    "addr:full":"La Plaine des Granges 72200 Bazouges sur le Loir Pays de Loire",
    "addr:postcode":"72200",
    "addr:street":"La;Des Granges;Le Loir",
    "iso:country":"FR",
    "sg:address":"La Plaine des Granges 72200 Bazouges sur le Loir",
    "sg:orig_category":"Unclassifiable Establishments",
    "sg:phone":"+33 2 43 45 30 03",
    "sg:province":"Pays de Loire",
    "wof:name":"Acar S.a.r.l.",
    "wof:placetype":"venue"
},
  "geometry": {"coordinates":[-0.169049,47.679852],"type":"Point"}
}