{
  "type": "Feature",
  "properties": {
    "addr:full":"43 rue de la R\u00e9publique; Marmande; 47200 Marmande Aquitaine 47200",
    "addr:housenumber":"43",
    "addr:postcode":"47200;47200",
    "addr:street":"Rue De La Re\u0301Publique",
    "iso:country":"FR",
    "sg:address":"43 rue de la R\u00e9publique; Marmande; 47200",
    "sg:city":"Marmande",
    "sg:classifiers":[
        {
            "category":"Banks & Credit Unions",
            "subcategory":"Bank",
            "type":"Services"
        }
    ],
    "sg:phone":"+33 3353643443",
    "sg:postcode":"47200",
    "sg:province":"Aquitaine",
    "wof:name":"Soci\u00e9t\u00e9 G\u00e9n\u00e9rale",
    "wof:placetype":"venue"
},
  "geometry": {"coordinates":[0.163794,44.49815],"type":"Point"}
}