{
  "type": "Feature",
  "properties": {
    "iso:country":"FR",
    "sg:address":"1, Rue des Longues Raies - ZA la Barogne, 77230 Moussy le Neuf",
    "sg:orig_category":"Unclassifiable Establishments",
    "sg:phone":"+33 1 60 03 93 89",
    "sg:province":"Ile de France",
    "wof:name":"Scala S.a.",
    "wof:placetype":"venue"
},
  "geometry": {"coordinates":[2.677655,49.053902],"type":"Point"}
}