{
  "type": "Feature",
  "properties": {
    "addr:full":"1, Rue des Longues Raies - ZA la Barogne, 77230 Moussy le Neuf Ile de France",
    "addr:housenumber":"1",
    "addr:postcode":"77230",
    "addr:street":"Rue Des Longues Raies Za La Barogne",
    "iso:country":"FR",
    "sg:address":"1, Rue des Longues Raies - ZA la Barogne, 77230 Moussy le Neuf",
    "sg:orig_category":"Unclassifiable Establishments",
    "sg:phone":"+33 1 60 03 93 89",
    "sg:province":"Ile de France",
    "wof:name":"Scala S.a.",
    "wof:placetype":"venue"
},
  "geometry": {"coordinates":[2.677655,49.053902],"type":"Point"}
}