{
  "type": "Feature",
  "properties": {
    "addr:full":"12 rue de Strasbourg 68150 Ostheim Ostheim Alsace 68150",
    "addr:housenumber":"12",
    "addr:postcode":"68150;68150",
    "addr:street":"Rue De Strasbourg",
    "iso:country":"FR",
    "sg:address":"12 rue de Strasbourg 68150 Ostheim",
    "sg:city":"Ostheim",
    "sg:classifiers":[
        {
            "category":"Banks & Credit Unions",
            "subcategory":"Atm",
            "type":"Services"
        }
    ],
    "sg:phone":"+33 3 89 47 90 78",
    "sg:postcode":"68150",
    "sg:province":"Alsace",
    "sg:tags":[
        "screed",
        "floor"
    ],
    "wof:name":"Fromelest Techn Du Carrelage S.a.r.l.",
    "wof:placetype":"venue"
},
  "geometry": {"coordinates":[7.371593,48.160995],"type":"Point"}
}