{
  "type": "Feature",
  "properties": {
    "iso:country":"FR",
    "sg:address":"2, Rue de l'Est\u00e9, 64100 Bayonne",
    "sg:city":"Bayonne",
    "sg:orig_category":"Unclassifiable Establishments",
    "sg:phone":"+33 5 59 55 11 42",
    "sg:postcode":"64100",
    "sg:province":"Aquitaine",
    "wof:name":"Lissement Dachary S.a.r.l.",
    "wof:placetype":"venue"
},
  "geometry": {"coordinates":[-1.46082,43.484428],"type":"Point"}
}