{
  "type": "Feature",
  "properties": {
    "addr:full":"57, Rue Bayard - Immeuble Le Tholose, 31000 Toulouse Midi Pyr\u00e9n\u00e9es",
    "addr:housenumber":"57",
    "addr:postcode":"31000",
    "addr:street":"Rue Bayard Immeuble Le Tholose",
    "iso:country":"FR",
    "sg:address":"57, Rue Bayard - Immeuble Le Tholose, 31000 Toulouse",
    "sg:orig_category":"Unclassifiable Establishments",
    "sg:phone":"+33 5 62 73 58 00",
    "sg:province":"Midi Pyr\u00e9n\u00e9es",
    "wof:name":"Groupe S.c.e.t. S.a. - Groupe Soci\u00e9t\u00e9 Centrale Pour Equipement Territoir",
    "wof:placetype":"venue"
},
  "geometry": {"coordinates":[1.450874,43.610748],"type":"Point"}
}