{
  "type": "Feature",
  "properties": {
    "iso:country":"FR",
    "sg:address":"route de Pugey 25660 Fontain",
    "sg:classifiers":[
        {
            "category":"Food & Beverages",
            "subcategory":"Bakery",
            "type":"Retail Goods"
        }
    ],
    "sg:phone":"+33 3 81 57 29 83",
    "sg:postcode":"25660",
    "sg:province":"Franche Comt\u00e9",
    "sg:tags":[
        "biscuit"
    ],
    "wof:name":"Sp\u00e9cialit\u00e9s De Fontain Cornu Sa",
    "wof:placetype":"venue"
},
  "geometry": {"coordinates":[6.11653,47.225906],"type":"Point"}
}