{
  "type": "Feature",
  "properties": {
    "addr:full":"1, Impasse du Tertre, 44470 Carquefou Pays de Loire",
    "addr:housenumber":"1",
    "addr:postcode":"44470",
    "addr:street":"Impasse Du Tertre",
    "iso:country":"FR",
    "sg:address":"1, Impasse du Tertre, 44470 Carquefou",
    "sg:orig_category":"Unclassifiable Establishments",
    "sg:phone":"+33 2 28 01 05 30",
    "sg:province":"Pays de Loire",
    "wof:name":"Aamipi",
    "wof:placetype":"venue"
},
  "geometry": {"coordinates":[-1.499428,47.261883],"type":"Point"}
}