{
  "type": "Feature",
  "properties": {
    "iso:country":"FR",
    "sg:address":"3, Rue du Mont de Guny, 02300 Guny",
    "sg:orig_category":"Non-Classified Establishments",
    "sg:phone":"+33 3 23 52 60 11",
    "sg:province":"Picardie",
    "wof:name":"L\u00e9v\u00eaque Montage Electricit\u00e9 Industrielle S.a.r.l.",
    "wof:placetype":"venue"
},
  "geometry": {"coordinates":[3.268499,49.514038],"type":"Point"}
}