{
  "type": "Feature",
  "properties": {
    "addr:full":"avenue de la Digue 13160 Chateaurenard Champagne",
    "addr:postcode":"13160",
    "addr:street":"Avenue De La Digue",
    "iso:country":"FR",
    "sg:address":"avenue de la Digue 13160 Chateaurenard",
    "sg:classifiers":[
        {
            "category":"Food & Beverages",
            "subcategory":"Fruits & Vegetables",
            "type":"Retail Goods"
        }
    ],
    "sg:phone":"+33 4 90 94 04 02",
    "sg:province":"Champagne",
    "wof:name":"2 G Primeurs Sas",
    "wof:placetype":"venue"
},
  "geometry": {"coordinates":[4.877406,43.89896],"type":"Point"}
}