{
  "type": "Feature",
  "properties": {
    "addr:full":"27 Mont\u00e9e St S\u00e9bastien 69001 Lyon Rhone-Alpes",
    "addr:housenumber":"27",
    "addr:postcode":"69001",
    "addr:street":"Monte\u0301E St Se\u0301Bastien",
    "iso:country":"FR",
    "sg:address":"27 Mont\u00e9e St S\u00e9bastien 69001 Lyon",
    "sg:classifiers":[
        {
            "category":"Professional",
            "subcategory":"Printing & Photocopies",
            "type":"Services"
        }
    ],
    "sg:phone":"+33 4 72 10 19 19",
    "sg:province":"Rhone-Alpes",
    "sg:tags":[
        "publishing"
    ],
    "wof:name":"Latitude - Cartagene Scop",
    "wof:placetype":"venue"
},
  "geometry": {"coordinates":[4.835869,45.771538],"type":"Point"}
}