{
  "type": "Feature",
  "properties": {
    "iso:country":"FR",
    "sg:address":"13 A, Chemin de la Curzeille, 74300 Cluses",
    "sg:orig_category":"Unclassifiable Establishments",
    "sg:phone":"+33 4 50 98 47 31",
    "sg:postcode":"74300",
    "sg:province":"Rhone-Alpes",
    "wof:name":"Airem S.a.",
    "wof:placetype":"venue"
},
  "geometry": {"coordinates":[6.581024,46.069309],"type":"Point"}
}