{
  "type": "Feature",
  "properties": {
    "iso:country":"FR",
    "sg:address":"Rte Du Dauphin 26260 Marg\u00e8s",
    "sg:classifiers":[
        {
            "category":"Manufacturing",
            "subcategory":"Wood Products",
            "type":"Manufacturing & Wholesale Goods"
        }
    ],
    "sg:phone":"+33 4 75 45 64 37",
    "sg:province":"Rhone-Alpes",
    "sg:tags":[
        "furniture"
    ],
    "wof:name":"Deroux Michel",
    "wof:placetype":"venue"
},
  "geometry": {"coordinates":[4.958345,45.077],"type":"Point"}
}