{
  "type": "Feature",
  "properties": {
    "addr:full":"4, Rue L\u00e9on Blum - ZI les Iles, 69320 Feyzin Rhone-Alpes",
    "addr:housenumber":"4",
    "addr:postcode":"69320",
    "addr:street":"Rue Le\u0301On Blum Zi Les Iles",
    "iso:country":"FR",
    "sg:address":"4, Rue L\u00e9on Blum - ZI les Iles, 69320 Feyzin",
    "sg:orig_category":"Unclassifiable Establishments",
    "sg:phone":"+33 4 72 89 19 98",
    "sg:province":"Rhone-Alpes",
    "wof:name":"F.c.f. Rh\u00f4ne Alpes S.a.r.l.",
    "wof:placetype":"venue"
},
  "geometry": {"coordinates":[4.860985,45.677135],"type":"Point"}
}