{
  "type": "Feature",
  "properties": {
    "addr:full":"Av Amp\u00e8re 77220 Gretz Armainvilliers Ile de France 77220",
    "addr:postcode":"77220;77220",
    "addr:street":"Av Ampe\u0300Re",
    "iso:country":"FR",
    "sg:address":"Av Amp\u00e8re 77220 Gretz Armainvilliers",
    "sg:classifiers":[
        {
            "category":"Manufacturing",
            "subcategory":"Motor Vehicles & Parts",
            "type":"Manufacturing & Wholesale Goods"
        }
    ],
    "sg:phone":"+33 1 64 07 27 27",
    "sg:postcode":"77220",
    "sg:province":"Ile de France",
    "sg:tags":[
        "engine",
        "machine",
        "engineering",
        "-",
        "mechanical"
    ],
    "wof:name":"Bernard Moteurs Sa",
    "wof:placetype":"venue"
},
  "geometry": {"coordinates":[2.736384,48.731316],"type":"Point"}
}