{
  "type": "Feature",
  "properties": {
    "iso:country":"FR",
    "sg:address":"6 Avenue Victor Hugo",
    "sg:city":"Sevran",
    "sg:classifiers":[
        {
            "category":"Banks & Credit Unions",
            "subcategory":"Financial Services",
            "type":"Services"
        }
    ],
    "sg:phone":"+33 1 43 83 70 60",
    "sg:postcode":"93270",
    "sg:province":"Ile de France",
    "sg:tags":[
        "banking",
        "finance",
        "insurance"
    ],
    "wof:name":"Secmer Sa",
    "wof:placetype":"venue"
},
  "geometry": {"coordinates":[2.534939,48.933853],"type":"Point"}
}