{
  "type": "Feature",
  "properties": {
    "iso:country":"FR",
    "sg:address":"32 rue Aristide Briand; Reze; 44400",
    "sg:classifiers":[
        {
            "category":"Banks & Credit Unions",
            "subcategory":"Bank",
            "type":"Services"
        }
    ],
    "sg:phone":"+33 3340755144",
    "sg:postcode":"44400",
    "sg:province":"Pays de Loire",
    "wof:name":"Banque Nationale De Paris",
    "wof:placetype":"venue"
},
  "geometry": {"coordinates":[-1.545843,47.182728],"type":"Point"}
}