{
  "type": "Feature",
  "properties": {
    "iso:country":"FR",
    "sg:address":"42, Rue de Ch\u00e2teaudun, 94207 Ivry sur Seine C\u00e9dex",
    "sg:city":"Ch\u00e2teau",
    "sg:orig_category":"Non-Classified Establishments",
    "sg:phone":"+33 1 46 71 57 00",
    "sg:postcode":"71250",
    "sg:province":"Bourgogne",
    "wof:name":"Industyl Pl\u00e9nilux S.a.s.",
    "wof:placetype":"venue"
},
  "geometry": {"coordinates":[2.365163,48.815414],"type":"Point"}
}