{
  "type": "Feature",
  "properties": {
    "addr:full":"3 square du Ch\u00eane Germain 35510 CESSON SEVIGNE Cesson-S\u00e9vign\u00e9 Bretagne 35510",
    "addr:housenumber":"3",
    "addr:postcode":"35510;35510",
    "addr:street":"Square Du Che\u0302Ne Germain;Bretagne",
    "iso:country":"FR",
    "sg:address":"3 square du Ch\u00eane Germain 35510 CESSON SEVIGNE",
    "sg:city":"Cesson-S\u00e9vign\u00e9",
    "sg:classifiers":[
        {
            "category":"Organizations",
            "subcategory":"Professional Association",
            "type":"Services"
        }
    ],
    "sg:phone":"+33 2 99 27 53 27",
    "sg:postcode":"35510",
    "sg:province":"Bretagne",
    "sg:tags":[
        "logistics",
        "planning",
        "software"
    ],
    "wof:name":"I.p.s.i.s. Sas",
    "wof:placetype":"venue"
},
  "geometry": {"coordinates":[-1.624309,48.132069],"type":"Point"}
}