{
  "type": "Feature",
  "properties": {
    "iso:country":"FR",
    "sg:address":"39-43 Quai Andr\u00e9 Citro\u00ebn 75015 Paris",
    "sg:classifiers":[
        {
            "category":"Professional",
            "subcategory":"Advertising",
            "type":"Services"
        }
    ],
    "sg:phone":"+33 1 40 58 38 00",
    "sg:postcode":"75015",
    "sg:province":"Ile de France",
    "sg:tags":[
        "information",
        "medium",
        "communication"
    ],
    "wof:name":"Conseil Superieur De L'audiovisuel",
    "wof:placetype":"venue"
},
  "geometry": {"coordinates":[2.278291,48.846409],"type":"Point"}
}