{
  "type": "Feature",
  "properties": {
    "addr:full":"Rue Des Roises 52100 Bettancourt La Ferr\u00e9e Champagne 52100",
    "addr:postcode":"52100;52100",
    "addr:street":"Rue Des Roises",
    "iso:country":"FR",
    "sg:address":"Rue Des Roises 52100 Bettancourt La Ferr\u00e9e",
    "sg:classifiers":[
        {
            "category":"Food & Beverages",
            "subcategory":"Groceries & Convenience Stores",
            "type":"Retail Goods"
        }
    ],
    "sg:phone":"+33 3 25 05 08 49",
    "sg:postcode":"52100",
    "sg:province":"Champagne",
    "sg:tags":[
        "product",
        "related"
    ],
    "wof:name":"Chocogil Etablissements Broisson Sa",
    "wof:placetype":"venue"
},
  "geometry": {"coordinates":[4.96846,48.65596],"type":"Point"}
}