{
  "type": "Feature",
  "properties": {
    "addr:full":"52110 Arnancourt Champagne",
    "addr:postcode":"52110",
    "iso:country":"FR",
    "sg:address":"52110 Arnancourt",
    "sg:classifiers":[
        {
            "category":"Home & Garden",
            "subcategory":"Furniture",
            "type":"Retail Goods"
        }
    ],
    "sg:phone":"+33 3 25 55 43 73",
    "sg:province":"Champagne",
    "sg:tags":[
        "wood"
    ],
    "wof:name":"Tournage Et Manches D'outils",
    "wof:placetype":"venue"
},
  "geometry": {"coordinates":[4.921245,48.352451],"type":"Point"}
}