{
  "type": "Feature",
  "properties": {
    "addr:full":"Zi 37460 Nouans Les Fontaines Beaumont-Village Centre 37460",
    "addr:postcode":"37460;37460",
    "addr:street":"Zi",
    "iso:country":"FR",
    "sg:address":"Zi 37460 Nouans Les Fontaines",
    "sg:city":"Beaumont-Village",
    "sg:classifiers":[
        {
            "category":"Home & Garden",
            "subcategory":"Furniture",
            "type":"Retail Goods"
        }
    ],
    "sg:phone":"+33 2 47 92 69 23",
    "sg:postcode":"37460",
    "sg:province":"Centre",
    "sg:tags":[
        "household",
        "wood"
    ],
    "wof:name":"Arlitec Societe Anonyme",
    "wof:placetype":"venue"
},
  "geometry": {"coordinates":[1.257498,47.05426],"type":"Point"}
}