{
  "type": "Feature",
  "properties": {
    "iso:country":"FR",
    "sg:address":"Chem De La Varenne 63307 Thiers Cedex",
    "sg:classifiers":[
        {
            "category":"Shopping",
            "type":"Retail Goods"
        }
    ],
    "sg:phone":"+33 4 73 80 74 66",
    "sg:province":"Aquitaine",
    "sg:tags":[
        "metallurgy",
        "finished",
        "-",
        "metalworking",
        "metallic"
    ],
    "wof:name":"Forginal Industrie Sa",
    "wof:placetype":"venue"
},
  "geometry": {"coordinates":[3.548272,45.855244],"type":"Point"}
}