{
  "type": "Feature",
  "properties": {
    "addr:full":"70 R Gare 95460 Ezanville Ile de France 95460",
    "addr:housenumber":"70",
    "addr:postcode":"95460;ile;95460",
    "addr:street":"R Gare;France",
    "iso:country":"FR",
    "sg:address":"70 R Gare 95460 Ezanville",
    "sg:classifiers":[
        {
            "category":"Shopping",
            "subcategory":"Hobbies, Toys, & Games",
            "type":"Retail Goods"
        }
    ],
    "sg:phone":"+33 1 39 91 00 58",
    "sg:postcode":"95460",
    "sg:province":"Ile de France",
    "sg:tags":[
        "product",
        "miscellaneous",
        "entertainment"
    ],
    "wof:name":"Glotin Chedeville Lelandais (sa)",
    "wof:placetype":"venue"
},
  "geometry": {"coordinates":[2.359766,49.025356],"type":"Point"}
}