{
  "type": "Feature",
  "properties": {
    "iso:country":"FR",
    "sg:address":"8, Rue Joseph Serlin, 69001 Lyon",
    "sg:orig_category":"Unclassifiable Establishments",
    "sg:phone":"+33 4 72 07 44 90",
    "sg:province":"Rhone-Alpes",
    "wof:name":"Agence Isabelle Dejeux S.a.r.l.",
    "wof:placetype":"venue"
},
  "geometry": {"coordinates":[4.836438,45.767464],"type":"Point"}
}