{
  "type": "Feature",
  "properties": {
    "addr:full":"46, Rue du Bois d'Avaize, 42100 Saint Etienne Rhone-Alpes",
    "addr:housenumber":"46",
    "addr:postcode":"42100",
    "addr:street":"Rue Du Bois D'Avaize",
    "iso:country":"FR",
    "sg:address":"46, Rue du Bois d'Avaize, 42100 Saint Etienne",
    "sg:orig_category":"Non-Classified Establishments",
    "sg:phone":"+33 4 77 32 10 94",
    "sg:province":"Rhone-Alpes",
    "wof:name":"S\u00e9rigraphie Magenta S.a.r.l.",
    "wof:placetype":"venue"
},
  "geometry": {"coordinates":[4.425207,45.439415],"type":"Point"}
}