{
  "type": "Feature",
  "properties": {
    "iso:country":"FR",
    "sg:address":"11 Rue Grimaux",
    "sg:city":"Rochefort",
    "sg:classifiers":[
        {
            "category":"Banks & Credit Unions",
            "subcategory":"Financial Services",
            "type":"Services"
        }
    ],
    "sg:phone":"+33 5 46 87 61 53",
    "sg:postcode":"17300",
    "sg:province":"Poitou-Charentes",
    "sg:tags":[
        "banking",
        "finance",
        "insurance"
    ],
    "wof:name":"Societe De Revision D'expertise De Gestion Et D'organisation (soregor)",
    "wof:placetype":"venue"
},
  "geometry": {"coordinates":[-0.960044,45.934265],"type":"Point"}
}