{
  "type": "Feature",
  "properties": {
    "addr:full":"Rte de Clary Ligny en Cambr\u00e9sis Nord Pas-de-Calais 59191",
    "addr:postcode":"59191",
    "addr:street":"Rte De Clary;Pas-De-Calais",
    "iso:country":"FR",
    "sg:address":"Rte de Clary",
    "sg:city":"Ligny en Cambr\u00e9sis",
    "sg:orig_category":"Unclassifiable Establishments",
    "sg:phone":"+33 3 27 76 60 60",
    "sg:postcode":"59191",
    "sg:province":"Nord Pas-de-Calais",
    "wof:name":"P.c.d. S.a. - Peinture Chimie Distribution",
    "wof:placetype":"venue"
},
  "geometry": {"coordinates":[3.403771,50.102287],"type":"Point"}
}