{
  "type": "Feature",
  "properties": {
    "addr:full":"2127, Chemin de Tanvol, 01440 Viriat Rhone-Alpes 01440",
    "addr:housenumber":"2127",
    "addr:postcode":"01440;01440",
    "addr:street":"Chemin De Tanvol",
    "iso:country":"FR",
    "sg:address":"2127, Chemin de Tanvol, 01440 Viriat",
    "sg:orig_category":"Non-Classified Establishments",
    "sg:phone":"+33 4 74 23 15 12",
    "sg:postcode":"01440",
    "sg:province":"Rhone-Alpes",
    "wof:name":"Entreprise De Carvalho Manuel",
    "wof:placetype":"venue"
},
  "geometry": {"coordinates":[5.257504,46.247776],"type":"Point"}
}