{
  "type": "Feature",
  "properties": {
    "iso:country":"FR",
    "sg:address":"100 Av Du Ch\u00e2teau D'Un 41033 Blois Cedex",
    "sg:classifiers":[
        {
            "category":"Health Services",
            "subcategory":"Medical Lab",
            "type":"Services"
        }
    ],
    "sg:phone":"+33 2 54 56 40 00",
    "sg:province":"Centre",
    "sg:tags":[
        "chemical",
        "pharmaceutical",
        "pharmacy"
    ],
    "wof:name":"Medifa",
    "wof:placetype":"venue"
},
  "geometry": {"coordinates":[1.33011,47.58593],"type":"Point"}
}