{
  "type": "Feature",
  "properties": {
    "addr:full":"9, Rue d'Epinoy, 59100 Roubaix Nord Pas-de-Calais",
    "addr:housenumber":"9",
    "addr:postcode":"59100",
    "addr:street":"Rue D'Epinoy",
    "iso:country":"FR",
    "sg:address":"9, Rue d'Epinoy, 59100 Roubaix",
    "sg:orig_category":"Unclassifiable Establishments",
    "sg:phone":"+33 3 20 75 54 33",
    "sg:province":"Nord Pas-de-Calais",
    "wof:name":"H.w. S.a.",
    "wof:placetype":"venue"
},
  "geometry": {"coordinates":[3.201798,50.674862],"type":"Point"}
}