{
  "type": "Feature",
  "properties": {
    "addr:full":"Rte du Plessis Bouchet Saint Herblain Pays de Loire 44800",
    "addr:postcode":"44800",
    "addr:street":"Rte Du Plessis Bouchet",
    "iso:country":"FR",
    "sg:address":"Rte du Plessis Bouchet",
    "sg:city":"Saint Herblain",
    "sg:orig_category":"Non-Classified Establishments",
    "sg:phone":"+33 2 40 46 39 36",
    "sg:postcode":"44800",
    "sg:province":"Pays de Loire",
    "wof:name":"S.b.c. S.a.r.l. - Soci\u00e9t\u00e9 Des Bras De Comptage",
    "wof:placetype":"venue"
},
  "geometry": {"coordinates":[-1.635003,47.201649],"type":"Point"}
}