{
  "type": "Feature",
  "properties": {
    "iso:country":"FR",
    "sg:address":"3, Chemin de la Nuatte, 89140 Gisy les Nobles",
    "sg:city":"Cuy",
    "sg:orig_category":"Non-Classified Establishments",
    "sg:phone":"+33 3 86 96 36 08",
    "sg:postcode":"89140",
    "sg:province":"Bourgogne",
    "wof:name":"Transma S.a.r.l.",
    "wof:placetype":"venue"
},
  "geometry": {"coordinates":[3.203495,48.286453],"type":"Point"}
}