{
  "type": "Feature",
  "properties": {
    "addr:full":"Rue du Pere Gwenael 29470 PLOUGASTEL DAOULAS Loperhet Bretagne 29470",
    "addr:postcode":"29470;29470",
    "addr:street":"Rue Du Pere Gwenael",
    "iso:country":"FR",
    "sg:address":"Rue du Pere Gwenael 29470 PLOUGASTEL DAOULAS",
    "sg:city":"Loperhet",
    "sg:classifiers":[
        {
            "category":"Food & Beverages",
            "subcategory":"Fruits & Vegetables",
            "type":"Retail Goods"
        }
    ],
    "sg:phone":"+33 2 98 40 36 39",
    "sg:postcode":"29470",
    "sg:province":"Bretagne",
    "wof:name":"Cooperative La Presqu Ile",
    "wof:placetype":"venue"
},
  "geometry": {"coordinates":[-4.358745,48.381878],"type":"Point"}
}