{
  "type": "Feature",
  "properties": {
    "addr:full":"7 Rue Des Essarts 39400 Morez Franche Comt\u00e9 39400",
    "addr:housenumber":"7",
    "addr:postcode":"39400;39400",
    "addr:street":"Rue Des Essarts;Franche Comte\u0301",
    "iso:country":"FR",
    "sg:address":"7 Rue Des Essarts 39400 Morez",
    "sg:classifiers":[
        {
            "category":"Manufacturing",
            "subcategory":"Metals",
            "type":"Manufacturing & Wholesale Goods"
        }
    ],
    "sg:phone":"+33 3 84 33 36 06",
    "sg:postcode":"39400",
    "sg:province":"Franche Comt\u00e9",
    "sg:tags":[
        "metallurgy",
        "metalworking",
        "processing"
    ],
    "wof:name":"Ateliers Des Essarts Sa",
    "wof:placetype":"venue"
},
  "geometry": {"coordinates":[6.018797,46.530689],"type":"Point"}
}