{
  "type": "Feature",
  "properties": {
    "addr:full":"B.P. 60145, 60251 Mouy C\u00e9dex^^211, Rue de l'Abattoir, 60250 Mouy Picardie",
    "addr:postcode":"60251;60250",
    "addr:street":"Rue De L'Abattoir",
    "iso:country":"FR",
    "sg:address":"B.P. 60145, 60251 Mouy C\u00e9dex^^211, Rue de l'Abattoir, 60250 Mouy",
    "sg:orig_category":"Non-Classified Establishments",
    "sg:phone":"+33 3 44 26 87 00",
    "sg:province":"Picardie",
    "wof:name":"Fournival S.a.",
    "wof:placetype":"venue"
},
  "geometry": {"coordinates":[2.321799,49.315434],"type":"Point"}
}