{
  "type": "Feature",
  "properties": {
    "addr:full":"Z Artisanale La Bouysse 12500 ESPALION Midi Pyr\u00e9n\u00e9es 12500",
    "addr:postcode":"12500;12500",
    "iso:country":"FR",
    "sg:address":"Z Artisanale La Bouysse 12500 ESPALION",
    "sg:classifiers":[
        {
            "category":"Professional",
            "subcategory":"Art Services",
            "type":"Services"
        }
    ],
    "sg:phone":"+33 5 65 44 00 39",
    "sg:postcode":"12500",
    "sg:province":"Midi Pyr\u00e9n\u00e9es",
    "sg:tags":[
        "metalwork"
    ],
    "wof:name":"Ferronnerie Pouget Sarl",
    "wof:placetype":"venue"
},
  "geometry": {"coordinates":[2.7415,44.531414],"type":"Point"}
}