{
  "type": "Feature",
  "properties": {
    "iso:country":"FR",
    "sg:address":"Quartier Saint Martin Nord",
    "sg:city":"Loriol sur Dr\u00f4me",
    "sg:orig_category":"Unclassifiable Establishments",
    "sg:phone":"+33 4 75 63 85 55",
    "sg:postcode":"26270",
    "sg:province":"Rhone-Alpes",
    "wof:name":"Procatel S.a.r.l.",
    "wof:placetype":"venue"
},
  "geometry": {"coordinates":[4.797704,44.692307],"type":"Point"}
}