{
  "type": "Feature",
  "properties": {
    "addr:full":"5, Rue Aristide Berg\u00e8s - ZI Nord - L\u00f4t. du Pin, 82000 Montauban Midi Pyr\u00e9n\u00e9es",
    "addr:housenumber":"5",
    "addr:postcode":"82000",
    "addr:street":"Rue Aristide Berge\u0300S Zi Nord Lo\u0302T Du Pin",
    "iso:country":"FR",
    "sg:address":"5, Rue Aristide Berg\u00e8s - ZI Nord - L\u00f4t. du Pin, 82000 Montauban",
    "sg:orig_category":"Non-Classified Establishments",
    "sg:phone":"+33 5 63 63 75 34",
    "sg:province":"Midi Pyr\u00e9n\u00e9es",
    "wof:name":"Normaero S.a.",
    "wof:placetype":"venue"
},
  "geometry": {"coordinates":[1.352205,44.016762],"type":"Point"}
}