{
  "type": "Feature",
  "properties": {
    "iso:country":"FR",
    "sg:address":"Rue Conventionnel; Ajaccio; 20000",
    "sg:classifiers":[
        {
            "category":"Banks & Credit Unions",
            "subcategory":"Bank",
            "type":"Services"
        }
    ],
    "sg:phone":"+33 3395231407",
    "sg:postcode":"20000",
    "sg:province":"Corse",
    "wof:name":"Cr\u00e9dit Foncier De France",
    "wof:placetype":"venue"
},
  "geometry": {"coordinates":[8.732981,41.917076],"type":"Point"}
}