{
  "type": "Feature",
  "properties": {
    "addr:full":"Rte de la Garde - Parc Sainte Claire La Valette du Var Champagne 83160",
    "addr:postcode":"83160",
    "addr:street":"Rte De La Garde Parc Sainte;Champagne",
    "iso:country":"FR",
    "sg:address":"Rte de la Garde - Parc Sainte Claire",
    "sg:city":"La Valette du Var",
    "sg:orig_category":"Non-Classified Establishments",
    "sg:phone":"+33 4 94 75 06 26",
    "sg:postcode":"83160",
    "sg:province":"Champagne",
    "wof:name":"S.i.a. S.a.r.l.",
    "wof:placetype":"venue"
},
  "geometry": {"coordinates":[5.980705,43.136925],"type":"Point"}
}