{
  "type": "Feature",
  "properties": {
    "iso:country":"FR",
    "sg:address":"28 Avenue Charles De Gaulle 36100 Issoudun",
    "sg:city":"Issoudun",
    "sg:classifiers":[
        {
            "category":"Wholesale",
            "subcategory":"Medical Equipment & Supplies",
            "type":"Manufacturing & Wholesale Goods"
        }
    ],
    "sg:phone":"+33 2 54 21 16 18",
    "sg:postcode":"36100",
    "sg:province":"Centre",
    "sg:tags":[
        "instrument",
        "health",
        "-",
        "precision"
    ],
    "wof:name":"Spengler Sa",
    "wof:placetype":"venue"
},
  "geometry": {"coordinates":[2.000976,46.944462],"type":"Point"}
}