{
  "type": "Feature",
  "properties": {
    "addr:full":"66, Rue Combanaire, 36000 Ch\u00e2teauroux Ch\u00e2teauroux Centre 36000",
    "addr:housenumber":"66",
    "addr:postcode":"36000;36000",
    "addr:street":"Rue Combanaire;Cha\u0302Teauroux",
    "iso:country":"FR",
    "sg:address":"66, Rue Combanaire, 36000 Ch\u00e2teauroux",
    "sg:city":"Ch\u00e2teauroux",
    "sg:orig_category":"Unclassifiable Establishments",
    "sg:phone":"+33 2 54 34 25 83",
    "sg:postcode":"36000",
    "sg:province":"Centre",
    "wof:name":"Lory S.a.r.l.",
    "wof:placetype":"venue"
},
  "geometry": {"coordinates":[1.708003,46.806309],"type":"Point"}
}