{
  "type": "Feature",
  "properties": {
    "addr:full":"Rte de Lyon Lamure sur Azergues Rhone-Alpes 69870",
    "addr:postcode":"69870",
    "addr:street":"Rte De Lyon Lamure Sur Azergues Rhone-Alpes",
    "iso:country":"FR",
    "sg:address":"Rte de Lyon",
    "sg:city":"Lamure sur Azergues",
    "sg:orig_category":"Non-Classified Establishments",
    "sg:phone":"+33 4 74 03 14 38",
    "sg:postcode":"69870",
    "sg:province":"Rhone-Alpes",
    "wof:name":"Cofoue S.c.a.",
    "wof:placetype":"venue"
},
  "geometry": {"coordinates":[4.445185,46.002354],"type":"Point"}
}