{
  "type": "Feature",
  "properties": {
    "addr:full":"22, Place de la Libert\u00e9, 59100 Roubaix Nord Pas-de-Calais",
    "addr:housenumber":"22",
    "addr:postcode":"59100",
    "addr:street":"Place De La Liberte\u0301",
    "iso:country":"FR",
    "sg:address":"22, Place de la Libert\u00e9, 59100 Roubaix",
    "sg:orig_category":"Unclassifiable Establishments",
    "sg:phone":"+33 3 20 45 06 16",
    "sg:province":"Nord Pas-de-Calais",
    "wof:name":"A.e.s. Multim\u00e9dia Et D\u00e9veloppement S.a.r.l.",
    "wof:placetype":"venue"
},
  "geometry": {"coordinates":[3.178404,50.69162],"type":"Point"}
}