{
  "type": "Feature",
  "properties": {
    "addr:full":"60 Allee Des Champs Elysees 91080 Courcouronnes Ile de France",
    "addr:housenumber":"60",
    "addr:postcode":"91080",
    "addr:street":"Allee Des Champs Elysees",
    "iso:country":"FR",
    "sg:address":"60 Allee Des Champs Elysees 91080 Courcouronnes",
    "sg:classifiers":[
        {
            "category":"Professional",
            "subcategory":"Printing & Photocopies",
            "type":"Services"
        }
    ],
    "sg:phone":"+33 1 69 47 91 91",
    "sg:province":"Ile de France",
    "sg:tags":[
        "publishing"
    ],
    "wof:name":"Snc Le Parisien Libere",
    "wof:placetype":"venue"
},
  "geometry": {"coordinates":[2.423918,48.628944],"type":"Point"}
}