{
  "type": "Feature",
  "properties": {
    "iso:country":"FR",
    "sg:address":"35, Rue du G\u00e9n\u00e9ral Malterre - ZI, 77000 Vaux le P\u00e9nil",
    "sg:orig_category":"Unclassifiable Establishments",
    "sg:phone":"+33 1 64 39 23 78",
    "sg:province":"Ile de France",
    "wof:name":"Entreprise M\u00e9lunaise Nettoyage Entretien S.a.",
    "wof:placetype":"venue"
},
  "geometry": {"coordinates":[2.664085,48.539577],"type":"Point"}
}