{
  "type": "Feature",
  "properties": {
    "iso:country":"FR",
    "sg:address":"B.P. 58, 59962 Croix C\u00e9dex^^1, Rue du Creusot, 59170 Croix",
    "sg:orig_category":"Non-Classified Establishments",
    "sg:phone":"+33 3 20 66 20 20",
    "sg:province":"Nord Pas-de-Calais",
    "wof:name":"Illochroma France S.a.",
    "wof:placetype":"venue"
},
  "geometry": {"coordinates":[3.15672,50.679729],"type":"Point"}
}