{
  "type": "Feature",
  "properties": {
    "addr:full":"10bis, Av du Lieutenant Gouby, 52400 Bourbonne les Bains Champagne",
    "addr:postcode":"52400",
    "addr:street":"Av Du Lieutenant Gouby",
    "iso:country":"FR",
    "sg:address":"10bis, Av du Lieutenant Gouby, 52400 Bourbonne les Bains",
    "sg:orig_category":"Unclassifiable Establishments",
    "sg:phone":"+33 3 25 90 04 03",
    "sg:province":"Champagne",
    "wof:name":"Lexcellent S.a.",
    "wof:placetype":"venue"
},
  "geometry": {"coordinates":[5.753137,47.954056],"type":"Point"}
}