{
  "type": "Feature",
  "properties": {
    "addr:full":"Quartier la Lauze Cavaillon Provence-Alpes-C\u00f4te d'Azur 84300",
    "addr:postcode":"84300",
    "addr:street":"Quartier La Lauze",
    "iso:country":"FR",
    "sg:address":"Quartier la Lauze",
    "sg:city":"Cavaillon",
    "sg:orig_category":"Non-Classified Establishments",
    "sg:phone":"+33 4 90 71 05 38",
    "sg:postcode":"84300",
    "sg:province":"Provence-Alpes-C\u00f4te d'Azur",
    "wof:name":"Soci\u00e9t\u00e9 D'exploitation Des Etablissements Goudet Et Ferrier S.a.r.l.",
    "wof:placetype":"venue"
},
  "geometry": {"coordinates":[5.048463,43.812431],"type":"Point"}
}