{
  "type": "Feature",
  "properties": {
    "addr:full":"Les Viziers 63700 Montaigut en Combraille Montaigut Auvergne 63700",
    "addr:postcode":"63700;63700",
    "iso:country":"FR",
    "sg:address":"Les Viziers 63700 Montaigut en Combraille",
    "sg:city":"Montaigut",
    "sg:orig_category":"Non-Classified Establishments",
    "sg:phone":"+33 4 73 85 30 84",
    "sg:postcode":"63700",
    "sg:province":"Auvergne",
    "wof:name":"S.l.d. Moulages S.a.r.l.",
    "wof:placetype":"venue"
},
  "geometry": {"coordinates":[2.819335,46.175205],"type":"Point"}
}