{
  "type": "Feature",
  "properties": {
    "addr:full":"175 rte de Vannes; S. Herblain Pays de Loire",
    "addr:housenumber":"175",
    "addr:street":"Rte De Vannes S. Herblain",
    "iso:country":"FR",
    "sg:address":"175 rte de Vannes; S. Herblain",
    "sg:classifiers":[
        {
            "category":"Banks & Credit Unions",
            "subcategory":"Bank",
            "type":"Services"
        }
    ],
    "sg:phone":"+33 3340760258",
    "sg:province":"Pays de Loire",
    "wof:name":"Caisse Regionale De Cr\u00e9dit Agricole",
    "wof:placetype":"venue"
},
  "geometry": {"coordinates":[-1.589907,47.239269],"type":"Point"}
}