{
  "type": "Feature",
  "properties": {
    "addr:full":"36 Route De Bayonne Ccal Carrefour 31300 Toulouse Midi Pyr\u00e9n\u00e9es 31300",
    "addr:housenumber":"36",
    "addr:postcode":"31300;31300",
    "addr:street":"Route De Bayonne;Carrefour",
    "iso:country":"FR",
    "sg:address":"36 Route De Bayonne Ccal Carrefour 31300 Toulouse",
    "sg:classifiers":[
        {
            "category":"Travel",
            "subcategory":"Hotels & Motels",
            "type":"Entertainment"
        }
    ],
    "sg:phone":"+33 5 61 31 80 60",
    "sg:postcode":"31300",
    "sg:province":"Midi Pyr\u00e9n\u00e9es",
    "sg:tags":[
        "hotels",
        "business",
        "restaurant"
    ],
    "wof:name":"Cafeteria Eris",
    "wof:placetype":"venue"
},
  "geometry": {"coordinates":[1.378679,43.609577],"type":"Point"}
}