{
  "type": "Feature",
  "properties": {
    "iso:country":"FR",
    "sg:address":"RN 93",
    "sg:city":"Laval d'Aix",
    "sg:orig_category":"Non-Classified Establishments",
    "sg:phone":"+33 4 75 21 82 64",
    "sg:postcode":"26150",
    "sg:province":"Rhone-Alpes",
    "wof:name":"Etablissements Guillaume Diois Motoculture S.a.r.l.",
    "wof:placetype":"venue"
},
  "geometry": {"coordinates":[5.43087,44.71273],"type":"Point"}
}