{
  "type": "Feature",
  "properties": {
    "addr:full":"B.P. 48 Plaisir C\u00e9dex Ile de France 78371",
    "addr:postcode":"78371",
    "addr:street":"B.P. 48",
    "iso:country":"FR",
    "sg:address":"B.P. 48",
    "sg:city":"Plaisir C\u00e9dex",
    "sg:orig_category":"Non-Classified Establishments",
    "sg:phone":"+33 1 30 81 77 30",
    "sg:postcode":"78371",
    "sg:province":"Ile de France",
    "wof:name":"Sadimato Les Ma\u00eetres D'eau S.a.s.",
    "wof:placetype":"venue"
},
  "geometry": {"coordinates":[-98.97698200000001,27.465981],"type":"Point"}
}