{
  "type": "Feature",
  "properties": {
    "addr:full":"L'Hermitage 17610 Chaniers Poitou-Charentes 17610",
    "addr:postcode":"17610;17610",
    "iso:country":"FR",
    "sg:address":"L'Hermitage 17610 Chaniers",
    "sg:orig_category":"Non-Classified Establishments",
    "sg:phone":"+33 5 46 91 50 54",
    "sg:postcode":"17610",
    "sg:province":"Poitou-Charentes",
    "wof:name":"Etablissements Horticoles Maguy S.a.",
    "wof:placetype":"venue"
},
  "geometry": {"coordinates":[-0.526137,45.733318],"type":"Point"}
}