{
  "type": "Feature",
  "properties": {
    "iso:country":"FR",
    "sg:address":"30, Bd Douaumont, 75017 Paris",
    "sg:orig_category":"Unclassifiable Establishments",
    "sg:phone":"+33 1 47 37 06 00",
    "sg:province":"Ile de France",
    "wof:name":"Mettler Tol\u00e9do Analyse Industrielle S.a.r.l.",
    "wof:placetype":"venue"
},
  "geometry": {"coordinates":[2.306001,48.895264],"type":"Point"}
}