{
  "type": "Feature",
  "properties": {
    "iso:country":"FR",
    "sg:address":"B.P. 38, 31702 Blagnac C\u00e9dex^^Zone de Fr\u00eat Ancienne A\u00e9rogare, 31700 Blagnac",
    "sg:orig_category":"Non-Classified Establishments",
    "sg:phone":"+33 5 61 30 03 44",
    "sg:postcode":"31700",
    "sg:province":"Midi Pyr\u00e9n\u00e9es",
    "wof:name":"Emery Worldwide",
    "wof:placetype":"venue"
},
  "geometry": {"coordinates":[1.39684,43.634586],"type":"Point"}
}