{
  "type": "Feature",
  "properties": {
    "addr:full":"Zac Champ Perier 01700 Neyron Rhone-Alpes 01700",
    "addr:postcode":"01700;01700",
    "addr:street":"Zac Champ Perier",
    "iso:country":"FR",
    "sg:address":"Zac Champ Perier 01700 Neyron",
    "sg:classifiers":[
        {
            "category":"Manufacturing",
            "subcategory":"Tools & Machinery",
            "type":"Manufacturing & Wholesale Goods"
        }
    ],
    "sg:phone":"+33 4 37 85 12 12",
    "sg:postcode":"01700",
    "sg:province":"Rhone-Alpes",
    "sg:tags":[
        "equipment",
        "measurement",
        "-",
        "precision",
        "instrument"
    ],
    "wof:name":"Societe Jeannot",
    "wof:placetype":"venue"
},
  "geometry": {"coordinates":[4.93177,45.81464],"type":"Point"}
}