{
  "type": "Feature",
  "properties": {
    "iso:country":"FR",
    "sg:address":"ZI de Souilly",
    "sg:city":"Claye Souilly",
    "sg:orig_category":"Unclassifiable Establishments",
    "sg:phone":"+33 1 60 26 51 58",
    "sg:postcode":"77410",
    "sg:province":"Ile de France",
    "wof:name":"Sermatech-tourolle S.a.",
    "wof:placetype":"venue"
},
  "geometry": {"coordinates":[2.68843,48.945576],"type":"Point"}
}