{
  "type": "Feature",
  "properties": {
    "iso:country":"FR",
    "sg:address":"2 chemin du G\u00e9nie 69200 VENISSIEUX",
    "sg:orig_category":"Boron Minerals",
    "sg:phone":"+33 4 78 67 33 44",
    "sg:province":"Rhone-Alpes",
    "wof:name":"Les Non Ferreux Sa",
    "wof:placetype":"venue"
},
  "geometry": {"coordinates":[4.859597,45.715469],"type":"Point"}
}