{
  "type": "Feature",
  "properties": {
    "iso:country":"FR",
    "sg:address":"81 Avenue Aristide Briand 33720 Barsac",
    "sg:city":"Barsac",
    "sg:classifiers":[
        {
            "category":"Food Court",
            "type":"Food & Drink"
        }
    ],
    "sg:phone":"+33 5 56 27 16 16",
    "sg:postcode":"33720",
    "sg:province":"Aquitaine",
    "sg:tags":[
        "product",
        "related"
    ],
    "wof:name":"Chateau Nairac",
    "wof:placetype":"venue"
},
  "geometry": {"coordinates":[-0.310618,44.603935],"type":"Point"}
}