{
  "type": "Feature",
  "properties": {
    "addr:full":"B.P. 637, 59506 Douai C\u00e9dex^^Rte d'Auby, 59128 Flers en Escrebieux Nord Pas-de-Calais",
    "addr:housenumber":"b.p. 637",
    "addr:postcode":"59506;59128",
    "addr:street":"D'Auby",
    "iso:country":"FR",
    "sg:address":"B.P. 637, 59506 Douai C\u00e9dex^^Rte d'Auby, 59128 Flers en Escrebieux",
    "sg:orig_category":"Non-Classified Establishments",
    "sg:phone":"+33 3 27 93 70 70",
    "sg:province":"Nord Pas-de-Calais",
    "wof:name":"Imprimerie Nationale S.a",
    "wof:placetype":"venue"
},
  "geometry": {"coordinates":[3.06206,50.386208],"type":"Point"}
}