{
  "type": "Feature",
  "properties": {
    "addr:full":"Le Grand Combeau 38690 Colombe Rhone-Alpes 38690",
    "addr:postcode":"38690;38690",
    "iso:country":"FR",
    "sg:address":"Le Grand Combeau 38690 Colombe",
    "sg:orig_category":"Unclassifiable Establishments",
    "sg:phone":"+33 4 76 55 82 36",
    "sg:postcode":"38690",
    "sg:province":"Rhone-Alpes",
    "wof:name":"Burrial S.a.r.l.",
    "wof:placetype":"venue"
},
  "geometry": {"coordinates":[5.438661,45.39994],"type":"Point"}
}