{
  "type": "Feature",
  "properties": {
    "iso:country":"FR",
    "sg:address":"2, Place du 4 Septembre, 47300 Villeneuve sur Lot",
    "sg:city":"Villeneuve-sur-Lot",
    "sg:orig_category":"Unclassifiable Establishments",
    "sg:phone":"+33 5 53 36 78 78",
    "sg:postcode":"47300",
    "sg:province":"Aquitaine",
    "wof:name":"Jangil S.a.",
    "wof:placetype":"venue"
},
  "geometry": {"coordinates":[0.707999,44.405663],"type":"Point"}
}