{
  "type": "Feature",
  "properties": {
    "iso:country":"FR",
    "sg:address":"2 Rue Paul Sabatier 22300 Lannion",
    "sg:city":"Lannion",
    "sg:classifiers":[
        {
            "category":"Utilities",
            "subcategory":"Telephone",
            "type":"Services"
        }
    ],
    "sg:phone":"+33 2 96 05 78 70",
    "sg:postcode":"22300",
    "sg:province":"Bretagne",
    "sg:tags":[
        "telecommunication"
    ],
    "wof:name":"Radio Frequency Systems France",
    "wof:placetype":"venue"
},
  "geometry": {"coordinates":[-3.469309,48.760334],"type":"Point"}
}