{
  "type": "Feature",
  "properties": {
    "addr:full":"B.P. 17, 57220 Boulay Moselle^^18, Rue du G\u00e9n\u00e9ral de Rascas, 57220 Boulay Moselle Lorraine 57220",
    "addr:postcode":"57220;57220;57220",
    "addr:street":"B.P. 17;Rue Du Ge\u0301Ne\u0301Ral De Rascas",
    "iso:country":"FR",
    "sg:address":"B.P. 17, 57220 Boulay Moselle^^18, Rue du G\u00e9n\u00e9ral de Rascas, 57220 Boulay Moselle",
    "sg:orig_category":"Non-Classified Establishments",
    "sg:phone":"+33 3 87 79 49 00",
    "sg:postcode":"57220",
    "sg:province":"Lorraine",
    "wof:name":"Chaines Zimmermann S.a.",
    "wof:placetype":"venue"
},
  "geometry": {"coordinates":[6.496275,49.1842],"type":"Point"}
}