{
  "type": "Feature",
  "properties": {
    "addr:full":"1\u00e8re Avenue - 3211 m\u00e8tres - ZI Carros Corse 06510",
    "addr:postcode":"3211 me\u0300tres zi;06510",
    "addr:street":"1E\u0300Re Avenue",
    "iso:country":"FR",
    "sg:address":"1\u00e8re Avenue - 3211 m\u00e8tres - ZI",
    "sg:city":"Carros",
    "sg:orig_category":"Unclassifiable Establishments",
    "sg:phone":"+33 4 93 29 23 33",
    "sg:postcode":"06510",
    "sg:province":"Corse",
    "wof:name":"M.e.i. Industries S.a. - M\u00e9canique Electronique Informatique Industries",
    "wof:placetype":"venue"
},
  "geometry": {"coordinates":[7.17573,43.785782],"type":"Point"}
}