{
  "type": "Feature",
  "properties": {
    "addr:full":"30, Rue Eug\u00e8ne H\u00e9naff, 69200 V\u00e9nissieux Rhone-Alpes 69200",
    "addr:housenumber":"30",
    "addr:postcode":"69200;69200",
    "addr:street":"Rue Euge\u0300Ne He\u0301Naff",
    "iso:country":"FR",
    "sg:address":"30, Rue Eug\u00e8ne H\u00e9naff, 69200 V\u00e9nissieux",
    "sg:orig_category":"Unclassifiable Establishments",
    "sg:phone":"+33 4 72 90 13 20",
    "sg:postcode":"69200",
    "sg:province":"Rhone-Alpes",
    "wof:name":"Durand Services Industries S.a.",
    "wof:placetype":"venue"
},
  "geometry": {"coordinates":[4.906196,45.6903],"type":"Point"}
}