{
  "type": "Feature",
  "properties": {
    "addr:full":"16 Av Charles De Gaulle Espace Entreprises 31130 Balma Midi Pyr\u00e9n\u00e9es",
    "addr:postcode":"31130",
    "addr:street":"16 Av Charles De Gaulle;Entreprises",
    "iso:country":"FR",
    "sg:address":"16 Av Charles De Gaulle Espace Entreprises 31130 Balma",
    "sg:classifiers":[
        {
            "category":"Utilities",
            "subcategory":"Telephone",
            "type":"Services"
        }
    ],
    "sg:phone":"+33 5 61 24 76 24",
    "sg:province":"Midi Pyr\u00e9n\u00e9es",
    "sg:tags":[
        "telecommunication"
    ],
    "wof:name":"Tenovis",
    "wof:placetype":"venue"
},
  "geometry": {"coordinates":[1.499115,43.596333],"type":"Point"}
}