{
  "type": "Feature",
  "properties": {
    "addr:full":"7, Rue Saint Louis - ZA Sud, 57150 Creutzwald Lorraine",
    "addr:housenumber":"7",
    "addr:postcode":"57150",
    "addr:street":"Rue Saint Louis Za Sud",
    "iso:country":"FR",
    "sg:address":"7, Rue Saint Louis - ZA Sud, 57150 Creutzwald",
    "sg:orig_category":"Services: Maintenance et installation T\u00e9l\u00e9com",
    "sg:phone":"+33 3 87 29 84 94",
    "sg:province":"Lorraine",
    "wof:name":"M\u00e9tralor S.a.r.l.",
    "wof:placetype":"venue"
},
  "geometry": {"coordinates":[6.694479,49.204865],"type":"Point"}
}