{
  "type": "Feature",
  "properties": {
    "addr:full":"Zac Cabourg 14390 Cabourg Cabourg Basse Normandie 14390",
    "addr:postcode":"14390;14390",
    "addr:street":"Zac Cabourg",
    "iso:country":"FR",
    "sg:address":"Zac Cabourg 14390 Cabourg",
    "sg:city":"Cabourg",
    "sg:classifiers":[
        {
            "category":"Manufacturing",
            "subcategory":"Paper Products",
            "type":"Manufacturing & Wholesale Goods"
        }
    ],
    "sg:phone":"+33 2 31 28 18 80",
    "sg:postcode":"14390",
    "sg:province":"Basse Normandie",
    "sg:tags":[
        "raw",
        "material",
        "-",
        "cardboard"
    ],
    "wof:name":"Normandie Ondule Sa",
    "wof:placetype":"venue"
},
  "geometry": {"coordinates":[-0.116804,49.286865],"type":"Point"}
}