{
  "type": "Feature",
  "properties": {
    "iso:country":"FR",
    "sg:address":"B.P. 5, 63014 Clermont Ferrand C\u00e9dex^^226, Av. Jean Marmoz, 63000 Clermont Ferrand",
    "sg:city":"Clermont-Ferrand",
    "sg:orig_category":"Non-Classified Establishments",
    "sg:phone":"+33 4 73 91 24 46",
    "sg:postcode":"63000",
    "sg:province":"Auvergne",
    "wof:name":"No\u00ebl Cruzillesaubert S.a.",
    "wof:placetype":"venue"
},
  "geometry": {"coordinates":[3.08183,45.777618],"type":"Point"}
}