{
  "type": "Feature",
  "properties": {
    "addr:full":"Les Dutti\u00e8res 85300 Soullans Pays de Loire 85300",
    "addr:postcode":"85300 soullans;85300",
    "iso:country":"FR",
    "sg:address":"Les Dutti\u00e8res 85300 Soullans",
    "sg:classifiers":[
        {
            "category":"Farming",
            "subcategory":"Livestock Farm",
            "type":"Manufacturing & Wholesale Goods"
        }
    ],
    "sg:phone":"+33 2 51 93 26 83",
    "sg:postcode":"85300",
    "sg:province":"Pays de Loire",
    "sg:tags":[
        "breeding",
        "agriculture",
        "animal"
    ],
    "wof:name":"Claude Couthouis Sa",
    "wof:placetype":"venue"
},
  "geometry": {"coordinates":[-1.879939,46.779999],"type":"Point"}
}