{
  "type": "Feature",
  "properties": {
    "addr:full":"Rue des Grisons Auch Midi Pyr\u00e9n\u00e9es 32000",
    "addr:postcode":"32000",
    "addr:street":"Rue Des Grisons",
    "iso:country":"FR",
    "sg:address":"Rue des Grisons",
    "sg:city":"Auch",
    "sg:orig_category":"Non-Classified Establishments",
    "sg:phone":"+33 5 62 60 64 84",
    "sg:postcode":"32000",
    "sg:province":"Midi Pyr\u00e9n\u00e9es",
    "wof:name":"A.b.x. Logistics Sud-ouest S.a.",
    "wof:placetype":"venue"
},
  "geometry": {"coordinates":[0.608705,43.652969],"type":"Point"}
}