{
  "type": "Feature",
  "properties": {
    "iso:country":"FR",
    "sg:address":"Rn 15 27400 Vironvay",
    "sg:classifiers":[
        {
            "category":"Manufacturing",
            "subcategory":"Chemicals & Compounds",
            "type":"Manufacturing & Wholesale Goods"
        }
    ],
    "sg:phone":"+33 2 32 50 25 98",
    "sg:postcode":"27400",
    "sg:province":"Haute Normandie",
    "sg:tags":[
        "pharmaceutical",
        "chemistry",
        "-",
        "by-product"
    ],
    "wof:name":"Laboratoire Yves Rocchia",
    "wof:placetype":"venue"
},
  "geometry": {"coordinates":[1.134962,49.107613],"type":"Point"}
}