{
  "type": "Feature",
  "properties": {
    "addr:full":"Rue Des Moulins 67660 Betschdorf Betschdorf Alsace 67660",
    "addr:postcode":"67660;67660",
    "addr:street":"Rue Des Moulins",
    "iso:country":"FR",
    "sg:address":"Rue Des Moulins 67660 Betschdorf",
    "sg:city":"Betschdorf",
    "sg:classifiers":[
        {
            "category":"Professional",
            "subcategory":"Engineering",
            "type":"Services"
        }
    ],
    "sg:phone":"+33 3 88 54 55 55",
    "sg:postcode":"67660",
    "sg:province":"Alsace",
    "sg:tags":[
        "machine",
        "-",
        "mechanical"
    ],
    "wof:name":"Pilz Production Sarl",
    "wof:placetype":"venue"
},
  "geometry": {"coordinates":[7.901725,48.891861],"type":"Point"}
}