{
  "type": "Feature",
  "properties": {
    "iso:country":"FR",
    "sg:address":"22 Rue Jean Mermoz 28000 Chartres",
    "sg:city":"Chartres",
    "sg:classifiers":[
        {
            "category":"Professional",
            "subcategory":"Engineering",
            "type":"Services"
        }
    ],
    "sg:phone":"+33 2 37 34 09 59",
    "sg:postcode":"28000",
    "sg:province":"Centre",
    "sg:tags":[
        "machine",
        "-",
        "mechanical"
    ],
    "wof:name":"Ets Viaud Froid Services Chartres Sa",
    "wof:placetype":"venue"
},
  "geometry": {"coordinates":[1.504032,48.449078],"type":"Point"}
}