{
  "type": "Feature",
  "properties": {
    "addr:full":"Le Pas Fleury 71700 Tournus Tournus Bourgogne 71700",
    "addr:postcode":"71700;71700",
    "iso:country":"FR",
    "sg:address":"Le Pas Fleury 71700 Tournus",
    "sg:city":"Tournus",
    "sg:orig_category":"Unclassifiable Establishments",
    "sg:phone":"+33 3 85 32 10 14",
    "sg:postcode":"71700",
    "sg:province":"Bourgogne",
    "wof:name":"Repack's S.a.r.l.",
    "wof:placetype":"venue"
},
  "geometry": {"coordinates":[4.830926,46.504631],"type":"Point"}
}