{
  "type": "Feature",
  "properties": {
    "addr:full":"8, Place Mass\u00e9na, 06000 Nice Pays de Loire",
    "addr:housenumber":"8",
    "addr:postcode":"06000",
    "addr:street":"Place Masse\u0301Na",
    "iso:country":"FR",
    "sg:address":"8, Place Mass\u00e9na, 06000 Nice",
    "sg:orig_category":"Unclassifiable Establishments",
    "sg:phone":"+33 4 92 17 65 00",
    "sg:province":"Pays de Loire",
    "wof:name":"Jet Tours Grand Large Voyage S.a.r.l.",
    "wof:placetype":"venue"
},
  "geometry": {"coordinates":[7.267729,43.6978],"type":"Point"}
}