{
  "type": "Feature",
  "properties": {
    "addr:full":"Zi Bd Dambourney 76350 Oissel Haute Normandie 76350",
    "addr:postcode":"76350;76350",
    "addr:street":"Dambourney;Haute Normandie",
    "iso:country":"FR",
    "sg:address":"Zi Bd Dambourney 76350 Oissel",
    "sg:classifiers":[
        {
            "category":"Autos & Motor Vehicles",
            "subcategory":"Automobile Sales",
            "type":"Retail Goods"
        }
    ],
    "sg:phone":"+33 2 35 66 34 30",
    "sg:postcode":"76350",
    "sg:province":"Haute Normandie",
    "sg:tags":[
        "equipment",
        "industrial",
        "transport"
    ],
    "wof:name":"General Trailers Sa",
    "wof:placetype":"venue"
},
  "geometry": {"coordinates":[1.095915,49.341049],"type":"Point"}
}