{
  "type": "Feature",
  "properties": {
    "addr:full":"ZI des Randonnays Voivres les le Mans Pays de Loire 72210",
    "addr:postcode":"72210",
    "addr:street":"Des Randonnays Voivres Les",
    "iso:country":"FR",
    "sg:address":"ZI des Randonnays",
    "sg:city":"Voivres les le Mans",
    "sg:orig_category":"Unclassifiable Establishments",
    "sg:phone":"+33 2 43 88 52 15",
    "sg:postcode":"72210",
    "sg:province":"Pays de Loire",
    "wof:name":"Mercure Boys Manufacture S.a.s.",
    "wof:placetype":"venue"
},
  "geometry": {"coordinates":[0.07198,47.929291],"type":"Point"}
}