{
  "type": "Feature",
  "properties": {
    "iso:country":"FR",
    "sg:address":"R L'Aygueelongue Zi De Berlanne 64160 Morla\u00e0s",
    "sg:city":"Morla\u00e0s",
    "sg:classifiers":[
        {
            "category":"Building & Trades",
            "subcategory":"Construction",
            "type":"Services"
        }
    ],
    "sg:phone":"+33 5 59 30 33 34",
    "sg:postcode":"64160",
    "sg:province":"Aquitaine",
    "sg:tags":[
        "work",
        "public"
    ],
    "wof:name":"Afbtp Sarl",
    "wof:placetype":"venue"
},
  "geometry": {"coordinates":[-0.29369,43.326488],"type":"Point"}
}