{
  "type": "Feature",
  "properties": {
    "addr:full":"39 Rue Saint-Jean 54000 Nancy Lorraine 54000",
    "addr:housenumber":"39",
    "addr:postcode":"54000;54000",
    "addr:street":"Rue Saint-Jean",
    "iso:country":"FR",
    "sg:address":"39 Rue Saint-Jean 54000 Nancy",
    "sg:classifiers":[
        {
            "category":"Shopping",
            "subcategory":"Clothing, Apparel, & Fashions",
            "type":"Retail Goods"
        }
    ],
    "sg:phone":"+33 3 83 32 93 30",
    "sg:postcode":"54000",
    "sg:province":"Lorraine",
    "sg:tags":[
        "textile",
        "clothing",
        "clothes"
    ],
    "wof:name":"La Samaritaine De Nancy Sa",
    "wof:placetype":"venue"
},
  "geometry": {"coordinates":[6.180456,48.690029],"type":"Point"}
}