{
  "type": "Feature",
  "properties": {
    "addr:full":"27 RUE MARCEL DUBOURG 02110 BOHAIN EN VERMANDOIS Picardie",
    "addr:housenumber":"27",
    "addr:postcode":"02110",
    "addr:street":"Rue Marcel Dubourg",
    "iso:country":"FR",
    "sg:address":"27 RUE MARCEL DUBOURG 02110 BOHAIN EN VERMANDOIS",
    "sg:classifiers":[
        {
            "category":"Shopping",
            "subcategory":"Crafts & Fabrics",
            "type":"Retail Goods"
        }
    ],
    "sg:phone":"+33 3 23 07 12 42",
    "sg:province":"Picardie",
    "sg:tags":[
        "synthetic",
        "fabrics",
        "plastic"
    ],
    "wof:name":"Fa\u00e7on Tissage Cr\u00e9ation Sa",
    "wof:placetype":"venue"
},
  "geometry": {"coordinates":[3.45355,49.985893],"type":"Point"}
}