{
  "type": "Feature",
  "properties": {
    "addr:full":"1, Rue Vaniers - ZA Bel Air, 12000 Rodez Midi Pyr\u00e9n\u00e9es",
    "addr:housenumber":"1",
    "addr:postcode":"12000",
    "addr:street":"Rue Vaniers Za Bel Air",
    "iso:country":"FR",
    "sg:address":"1, Rue Vaniers - ZA Bel Air, 12000 Rodez",
    "sg:orig_category":"Non-Classified Establishments",
    "sg:phone":"+33 5 65 42 24 98",
    "sg:province":"Midi Pyr\u00e9n\u00e9es",
    "wof:name":"Meubles Rey S.a.r.l.",
    "wof:placetype":"venue"
},
  "geometry": {"coordinates":[2.57289,44.349735],"type":"Point"}
}