{
  "type": "Feature",
  "properties": {
    "addr:full":"31 Av Mozart 75016 Paris Ile de France 75016",
    "addr:postcode":"75016;75016",
    "addr:street":"31 Av Mozart",
    "iso:country":"FR",
    "sg:address":"31 Av Mozart 75016 Paris",
    "sg:classifiers":[
        {
            "category":"Shopping",
            "subcategory":"Clothing, Apparel, & Fashions",
            "type":"Retail Goods"
        }
    ],
    "sg:phone":"+33 1 45 25 90 31",
    "sg:postcode":"75016",
    "sg:province":"Ile de France",
    "sg:tags":[
        "textile",
        "clothing",
        "clothes"
    ],
    "wof:name":"Ste Gerard Et Raymond Fischelis Sa",
    "wof:placetype":"venue"
},
  "geometry": {"coordinates":[2.270881,48.855778],"type":"Point"}
}