{
  "type": "Feature",
  "properties": {
    "addr:full":"Za 22110 Rostrenen Rostrenen Bretagne 22110",
    "addr:postcode":"22110;22110",
    "addr:street":"Za",
    "iso:country":"FR",
    "sg:address":"Za 22110 Rostrenen",
    "sg:city":"Rostrenen",
    "sg:classifiers":[
        {
            "category":"Banks & Credit Unions",
            "subcategory":"Investment Brokerage",
            "type":"Services"
        }
    ],
    "sg:phone":"+33 2 96 57 43 10",
    "sg:postcode":"22110",
    "sg:province":"Bretagne",
    "sg:tags":[
        "-",
        "transport",
        "related"
    ],
    "wof:name":"Intermarche",
    "wof:placetype":"venue"
},
  "geometry": {"coordinates":[-3.296701,48.174469],"type":"Point"}
}