{
  "type": "Feature",
  "properties": {
    "iso:country":"FR",
    "sg:address":"14, Rue Fernand Forest, 63540 Romagnat",
    "sg:city":"Romagnat",
    "sg:orig_category":"Unclassifiable Establishments",
    "sg:phone":"+33 4 73 26 79 17",
    "sg:postcode":"63540",
    "sg:province":"Auvergne",
    "wof:name":"Pegeon Fils S.a.",
    "wof:placetype":"venue"
},
  "geometry": {"coordinates":[3.09718,45.743462],"type":"Point"}
}