{
  "type": "Feature",
  "properties": {
    "addr:full":"65 Rte Niort 79430 La Chapelle St Laurent Poitou-Charentes 79430",
    "addr:housenumber":"65",
    "addr:postcode":"79430;79430",
    "addr:street":"Rte Niort;La Chapelle St Laurent",
    "iso:country":"FR",
    "sg:address":"65 Rte Niort 79430 La Chapelle St Laurent",
    "sg:classifiers":[
        {
            "category":"Home & Garden",
            "subcategory":"Furniture",
            "type":"Retail Goods"
        }
    ],
    "sg:phone":"+33 5 49 72 06 22",
    "sg:postcode":"79430",
    "sg:province":"Poitou-Charentes",
    "sg:tags":[
        "household",
        "wood"
    ],
    "wof:name":"Les Meubles Celio",
    "wof:placetype":"venue"
},
  "geometry": {"coordinates":[-0.476304,46.745403],"type":"Point"}
}