{
  "type": "Feature",
  "properties": {
    "addr:full":"41, Rte de Feurs, 42600 Montbrison Rhone-Alpes",
    "addr:housenumber":"41",
    "addr:postcode":"42600",
    "addr:street":"Rte De Feurs",
    "iso:country":"FR",
    "sg:address":"41, Rte de Feurs, 42600 Montbrison",
    "sg:orig_category":"Unclassifiable Establishments",
    "sg:phone":"+33 4 77 96 63 00",
    "sg:province":"Rhone-Alpes",
    "wof:name":"Vai Clecim S.a.",
    "wof:placetype":"venue"
},
  "geometry": {"coordinates":[4.067277,45.611694],"type":"Point"}
}