{
  "type": "Feature",
  "properties": {
    "iso:country":"FR",
    "sg:address":"B.P. 7, 37320 Truyes C\u00e9dex^^ZA les Perch\u00e9es, 37320 Truyes",
    "sg:city":"Truyes",
    "sg:orig_category":"Non-Classified Establishments",
    "sg:phone":"+33 2 47 43 04 34",
    "sg:postcode":"37320",
    "sg:province":"Centre",
    "wof:name":"Sotochrome S.a.r.l.",
    "wof:placetype":"venue"
},
  "geometry": {"coordinates":[0.74494,47.185612],"type":"Point"}
}