{
  "type": "Feature",
  "properties": {
    "iso:country":"FR",
    "sg:address":"255, Quai du Midi, 17000 La Rochelle",
    "sg:orig_category":"Unclassifiable Establishments",
    "sg:phone":"+33 5 46 00 30 03",
    "sg:province":"Poitou-Charentes",
    "wof:name":"Laharrague S.a.",
    "wof:placetype":"venue"
},
  "geometry": {"coordinates":[-1.218267,46.14769],"type":"Point"}
}