{
  "type": "Feature",
  "properties": {
    "addr:full":"4, Rue Scatisse, 30934 N\u00eemes Languedoc-Roussillon",
    "addr:housenumber":"4",
    "addr:postcode":"30934",
    "addr:street":"Rue Scatisse",
    "iso:country":"FR",
    "sg:address":"4, Rue Scatisse, 30934 N\u00eemes",
    "sg:orig_category":"Non-Classified Establishments",
    "sg:phone":"+33 4 66 62 70 00",
    "sg:province":"Languedoc-Roussillon",
    "wof:name":"S.a.d.a. S.a.",
    "wof:placetype":"venue"
},
  "geometry": {"coordinates":[4.364394,43.83215],"type":"Point"}
}