{
  "type": "Feature",
  "properties": {
    "addr:full":"Ch\u00e2teau Gabaron - Gabaron La Sauve Aquitaine 33670",
    "addr:housenumber":"sauve",
    "addr:postcode":"33670",
    "iso:country":"FR",
    "sg:address":"Ch\u00e2teau Gabaron - Gabaron",
    "sg:city":"La Sauve",
    "sg:orig_category":"Unclassifiable Establishments",
    "sg:phone":"+33 5 56 23 92 76",
    "sg:postcode":"33670",
    "sg:province":"Aquitaine",
    "wof:name":"Soci\u00e9t\u00e9 Civile Des Vignobles Latorse",
    "wof:placetype":"venue"
},
  "geometry": {"coordinates":[-0.371374,44.751328],"type":"Point"}
}