{
  "type": "Feature",
  "properties": {
    "addr:full":"Rue Bellevue - Dortan Chancia Rhone-Alpes 01590",
    "addr:postcode":"01590",
    "addr:street":"Rue Bellevue;Rhone-Alpes",
    "iso:country":"FR",
    "sg:address":"Rue Bellevue - Dortan",
    "sg:city":"Chancia",
    "sg:orig_category":"MOULES D'INJECTION POUR LA TRANSFORMATION DES MATI\u00c8RES PLASTIQUES sous-traitance \u00e9lectro-\u00e9rosion \u00e0 f",
    "sg:phone":"+33 4 74 77 70 90",
    "sg:postcode":"01590",
    "sg:province":"Rhone-Alpes",
    "wof:name":"Permic S.a.",
    "wof:placetype":"venue"
},
  "geometry": {"coordinates":[5.643693,46.346142],"type":"Point"}
}