{
  "type": "Feature",
  "properties": {
    "addr:full":"42 Rue Sarreguemines 57720 Volmunster Lorraine 57720",
    "addr:housenumber":"42",
    "addr:postcode":"57720;57720",
    "addr:street":"Rue Sarreguemines",
    "iso:country":"FR",
    "sg:address":"42 Rue Sarreguemines 57720 Volmunster",
    "sg:classifiers":[
        {
            "category":"Wholesale",
            "subcategory":"Farm Supplies",
            "type":"Manufacturing & Wholesale Goods"
        }
    ],
    "sg:phone":"+33 3 87 96 71 92",
    "sg:postcode":"57720",
    "sg:province":"Lorraine",
    "sg:tags":[
        "-",
        "machine",
        "equipment",
        "engineering",
        "machinery",
        "mechanical",
        "agriculture"
    ],
    "wof:name":"Etablissements Schaff Machines Agricoles Sarl",
    "wof:placetype":"venue"
},
  "geometry": {"coordinates":[7.3474,49.117149],"type":"Point"}
}