{
  "type": "Feature",
  "properties": {
    "iso:country":"FR",
    "sg:address":"1, Place Jean Mamet, 45000 Orl\u00e9ans",
    "sg:city":"Orl\u00e9ans",
    "sg:orig_category":"Unclassifiable Establishments",
    "sg:phone":"+33 2 38 71 75 29",
    "sg:postcode":"45000",
    "sg:province":"Centre",
    "wof:name":"Gamaf In Extenso S.a.",
    "wof:placetype":"venue"
},
  "geometry": {"coordinates":[1.904965,47.901428],"type":"Point"}
}