{
  "type": "Feature",
  "properties": {
    "addr:full":"ZI de Port Salut Verberie Picardie 60410",
    "addr:postcode":"60410",
    "addr:street":"Zi De Port;Picardie",
    "iso:country":"FR",
    "sg:address":"ZI de Port Salut",
    "sg:city":"Verberie",
    "sg:orig_category":"Unclassifiable Establishments",
    "sg:phone":"+33 3 44 38 30 00",
    "sg:postcode":"60410",
    "sg:province":"Picardie",
    "wof:name":"Granulats Seine Normandie",
    "wof:placetype":"venue"
},
  "geometry": {"coordinates":[2.732145,49.310505],"type":"Point"}
}