{
  "type": "Feature",
  "properties": {
    "addr:full":"Creste 15150 CROS DE MONTVERT Montvert Auvergne 15150",
    "addr:postcode":"15150;15150",
    "addr:street":"Montvert Montvert",
    "iso:country":"FR",
    "sg:address":"Creste 15150 CROS DE MONTVERT",
    "sg:city":"Montvert",
    "sg:orig_category":"Slaughter-Houses, Abattoirs",
    "sg:phone":"+33 4 71 45 01 00",
    "sg:postcode":"15150",
    "sg:province":"Auvergne",
    "wof:name":"Ste Transformation Sous Produits Animaux Sica",
    "wof:placetype":"venue"
},
  "geometry": {"coordinates":[2.181436,44.90173],"type":"Point"}
}