{
  "type": "Feature",
  "properties": {
    "iso:country":"FR",
    "sg:address":"B.P. 1056, 79010 Niort C\u00e9dex 9^^268, Av. de Paris, 79000 Niort",
    "sg:orig_category":"Non-Classified Establishments",
    "sg:phone":"+33 5 49 24 40 51",
    "sg:province":"Poitou-Charentes",
    "wof:name":"R.s.o. S.a.r.l. - Repro Service De L'ouest",
    "wof:placetype":"venue"
},
  "geometry": {"coordinates":[-0.504137,46.298],"type":"Point"}
}