{
  "type": "Feature",
  "properties": {
    "iso:country":"FR",
    "sg:address":"B.P. 7",
    "sg:city":"Pommerit Jaudy^^L'Estivoan 22450 Pommerit Jaudy",
    "sg:orig_category":"Non-Classified Establishments",
    "sg:phone":"+33 2 96 49 50 10",
    "sg:postcode":"22450",
    "sg:province":"Bretagne",
    "wof:name":"Couvoir Perrot S.a",
    "wof:placetype":"venue"
},
  "geometry": {"coordinates":[-3.238452,48.720562],"type":"Point"}
}