{
  "type": "Feature",
  "properties": {
    "iso:country":"FR",
    "sg:address":"30, Grande Rue, 78910 Tacoigni\u00e8res",
    "sg:orig_category":"Unclassifiable Establishments",
    "sg:phone":"+33 1 30 88 35 35",
    "sg:province":"Ile de France",
    "wof:name":"Soci\u00e9t\u00e9 Arblade Et Fils S.a.r.l.",
    "wof:placetype":"venue"
},
  "geometry": {"coordinates":[1.674316,48.836411],"type":"Point"}
}