{
  "type": "Feature",
  "properties": {
    "addr:full":"Rue Neuve Guignicourt Picardie 02190",
    "addr:postcode":"02190",
    "addr:street":"Rue Neuve;Picardie",
    "iso:country":"FR",
    "sg:address":"Rue Neuve",
    "sg:city":"Guignicourt",
    "sg:orig_category":"Unclassifiable Establishments",
    "sg:phone":"+33 3 23 79 80 29",
    "sg:postcode":"02190",
    "sg:province":"Picardie",
    "wof:name":"R.v.s. 02 S.a.r.l.",
    "wof:placetype":"venue"
},
  "geometry": {"coordinates":[3.96687,49.437511],"type":"Point"}
}