{
  "type": "Feature",
  "properties": {
    "iso:country":"FR",
    "sg:address":"21, Rue du G\u00e9n\u00e9ral de Gaulle, 55800 Revigny sur Ornain",
    "sg:orig_category":"Non-Classified Establishments",
    "sg:phone":"+33 3 29 75 18 42",
    "sg:postcode":"55800",
    "sg:province":"Lorraine",
    "wof:name":"Apil E.u.r.l.",
    "wof:placetype":"venue"
},
  "geometry": {"coordinates":[4.984785,48.827148],"type":"Point"}
}