{
  "type": "Feature",
  "properties": {
    "addr:full":"Centre Affaires Paris Nord Tour Amp\u00e8re 3 93153 Le Blanc Mesnil Cedex Champagne",
    "addr:housenumber":"3",
    "addr:postcode":"93153",
    "iso:country":"FR",
    "sg:address":"Centre Affaires Paris Nord Tour Amp\u00e8re 3 93153 Le Blanc Mesnil Cedex",
    "sg:classifiers":[
        {
            "category":"Manufacturing",
            "subcategory":"Chemicals & Compounds",
            "type":"Manufacturing & Wholesale Goods"
        }
    ],
    "sg:phone":"+33 1 48 67 90 33",
    "sg:province":"Champagne",
    "sg:tags":[
        "pharmaceutical",
        "chemistry",
        "-",
        "by-product"
    ],
    "wof:name":"Docteur Weigert France",
    "wof:placetype":"venue"
},
  "geometry": {"coordinates":[2.460765,48.938671],"type":"Point"}
}