{
  "type": "Feature",
  "properties": {
    "iso:country":"FR",
    "sg:address":"11, Av. Dubonnet, 92407 Courbevoie C\u00e9dex",
    "sg:orig_category":"Non-Classified Establishments",
    "sg:phone":"+33 1 49 05 30 00",
    "sg:province":"Rhone-Alpes",
    "wof:name":"Amphenol Air L.b. S.a.s.",
    "wof:placetype":"venue"
},
  "geometry": {"coordinates":[2.260373,48.901592],"type":"Point"}
}