{
  "type": "Feature",
  "properties": {
    "addr:full":"B.P. 643 Le Havre Haute Normandie 76059",
    "addr:housenumber":"b.p. 643",
    "addr:postcode":"76059",
    "iso:country":"FR",
    "sg:address":"B.P. 643",
    "sg:city":"Le Havre",
    "sg:orig_category":"Non-Classified Establishments",
    "sg:phone":"+33 2 35 24 74 74",
    "sg:postcode":"76059",
    "sg:province":"Haute Normandie",
    "wof:name":"Activ. A.c.b. S.a.",
    "wof:placetype":"venue"
},
  "geometry": {"coordinates":[0.101405,49.493511],"type":"Point"}
}