{
  "type": "Feature",
  "properties": {
    "addr:full":"20 Boulevard Marcel Paul 93450 L Ile St Denis Ile de France 93450",
    "addr:housenumber":"20",
    "addr:postcode":"93450;93450",
    "addr:street":"Boulevard Marcel Paul;Ile St Denis Ile De France",
    "iso:country":"FR",
    "sg:address":"20 Boulevard Marcel Paul 93450 L Ile St Denis",
    "sg:classifiers":[
        {
            "category":"Professional",
            "subcategory":"Business Services",
            "type":"Services"
        }
    ],
    "sg:phone":"+33 1 48 20 35 00",
    "sg:postcode":"93450",
    "sg:province":"Ile de France",
    "sg:tags":[
        "advice",
        "fabric",
        "clothes"
    ],
    "wof:name":"Business Supply System",
    "wof:placetype":"venue"
},
  "geometry": {"coordinates":[2.32659,48.920273],"type":"Point"}
}