{
  "type": "Feature",
  "properties": {
    "iso:country":"FR",
    "sg:address":"13 R Pierre Duheim 13090 Aix En Provence",
    "sg:classifiers":[
        {
            "category":"Building & Trades",
            "subcategory":"Electrical",
            "type":"Services"
        }
    ],
    "sg:phone":"+33 4 42 39 41 50",
    "sg:province":"Nord Pas-de-Calais",
    "sg:tags":[
        "electronic",
        "lighting",
        "equipment"
    ],
    "wof:name":"Thorn Europhane",
    "wof:placetype":"venue"
},
  "geometry": {"coordinates":[5.41946,43.55584],"type":"Point"}
}