{
  "type": "Feature",
  "properties": {
    "iso:country":"FR",
    "sg:address":"B.P. 257",
    "sg:city":"Rungis C\u00e9dex",
    "sg:orig_category":"Non-Classified Establishments",
    "sg:phone":"+33 1 46 86 64 26",
    "sg:postcode":"94582",
    "sg:province":"Ile de France",
    "wof:name":"Uno Plus S.a.r.l.",
    "wof:placetype":"venue"
},
  "geometry": {"coordinates":[2.35325,48.751419],"type":"Point"}
}