{
  "type": "Feature",
  "properties": {
    "addr:full":"71/73, Bd des Belges, 76000 Rouen Haute Normandie",
    "addr:housenumber":"71 / 73",
    "addr:postcode":"76000",
    "addr:street":"Bd Des Belges;Haute Normandie",
    "iso:country":"FR",
    "sg:address":"71/73, Bd des Belges, 76000 Rouen",
    "sg:orig_category":"Unclassifiable Establishments",
    "sg:phone":"+33 2 35 71 18 17",
    "sg:province":"Haute Normandie",
    "wof:name":"Guezouli Informatique S.a.",
    "wof:placetype":"venue"
},
  "geometry": {"coordinates":[1.085544,49.444664],"type":"Point"}
}