{
  "type": "Feature",
  "properties": {
    "addr:full":"Rue Emile Arques Reims Champagne 51100",
    "addr:postcode":"51100",
    "addr:street":"Rue Emile Arques;Champagne",
    "iso:country":"FR",
    "sg:address":"Rue Emile Arques",
    "sg:city":"Reims",
    "sg:orig_category":"Unclassifiable Establishments",
    "sg:phone":"+33 3 26 85 50 47",
    "sg:postcode":"51100",
    "sg:province":"Champagne",
    "wof:name":"Qualit\u00e9 Et Sant\u00e9 S.a.",
    "wof:placetype":"venue"
},
  "geometry": {"coordinates":[4.06448,49.235985],"type":"Point"}
}