{
  "type": "Feature",
  "properties": {
    "addr:full":"7 Rue Marcel Dassault 85340 OLONNE SUR MER Pays de Loire 85340",
    "addr:housenumber":"7",
    "addr:postcode":"85340;85340",
    "addr:street":"Rue Marcel Dassault",
    "iso:country":"FR",
    "sg:address":"7 Rue Marcel Dassault 85340 OLONNE SUR MER",
    "sg:orig_category":"Fans, Blowers",
    "sg:phone":"+33 2 51 23 59 33",
    "sg:postcode":"85340",
    "sg:province":"Pays de Loire",
    "wof:name":"Fantronic Composants Sa",
    "wof:placetype":"venue"
},
  "geometry": {"coordinates":[-1.783092,46.520676],"type":"Point"}
}