{
  "type": "Feature",
  "properties": {
    "addr:full":"92 Rue Jean Jaures 42300 Roanne Rhone-Alpes",
    "addr:housenumber":"92",
    "addr:postcode":"42300",
    "addr:street":"Rue Jean Jaures",
    "iso:country":"FR",
    "sg:address":"92 Rue Jean Jaures 42300 Roanne",
    "sg:classifiers":[
        {
            "category":"Banks & Credit Unions",
            "subcategory":"Investment Brokerage",
            "type":"Services"
        }
    ],
    "sg:phone":"+33 4 77 23 03 92",
    "sg:province":"Rhone-Alpes",
    "sg:tags":[
        "-",
        "transport",
        "related"
    ],
    "wof:name":"Comareg Sa",
    "wof:placetype":"venue"
},
  "geometry": {"coordinates":[4.071525,46.035797],"type":"Point"}
}