{
  "type": "Feature",
  "properties": {
    "iso:country":"FR",
    "sg:address":"Avenue du Giniral De Gaulle; BP 90; THIERS Cedex; 63307",
    "sg:classifiers":[
        {
            "category":"Shopping",
            "subcategory":"Computers & Home Electronics",
            "type":"Retail Goods"
        }
    ],
    "sg:phone":"+33 4 73 51 66 50",
    "sg:province":"Auvergne",
    "sg:tags":[
        "chamber",
        "commerce"
    ],
    "wof:name":"Chambre De Commerce De Thiers",
    "wof:placetype":"venue"
},
  "geometry": {"coordinates":[3.54786,45.85339],"type":"Point"}
}