{
  "type": "Feature",
  "properties": {
    "addr:full":"Rue Robert le Beller Lorient Bretagne 56100",
    "addr:postcode":"56100",
    "addr:street":"Rue Robert Le Beller Lorient",
    "iso:country":"FR",
    "sg:address":"Rue Robert le Beller",
    "sg:city":"Lorient",
    "sg:orig_category":"Unclassifiable Establishments",
    "sg:phone":"+33 2 97 87 16 40",
    "sg:postcode":"56100",
    "sg:province":"Bretagne",
    "wof:name":"Peintures Guilloteau S.a.",
    "wof:placetype":"venue"
},
  "geometry": {"coordinates":[-3.367055,47.735676],"type":"Point"}
}