{
  "type": "Feature",
  "properties": {
    "addr:full":"13 Rue De Bretagne 44880 Sautron Pays de Loire 44880",
    "addr:housenumber":"13",
    "addr:postcode":"44880;44880",
    "addr:street":"Rue De Bretagne",
    "iso:country":"FR",
    "sg:address":"13 Rue De Bretagne 44880 Sautron",
    "sg:classifiers":[
        {
            "category":"Autos & Motor Vehicles",
            "subcategory":"Automobile Sales",
            "type":"Retail Goods"
        }
    ],
    "sg:phone":"+33 2 40 63 15 13",
    "sg:postcode":"44880",
    "sg:province":"Pays de Loire",
    "sg:tags":[
        "equipment",
        "motor-cars",
        "transport"
    ],
    "wof:name":"Carrosserie Drouet Sa",
    "wof:placetype":"venue"
},
  "geometry": {"coordinates":[-1.672559,47.26236],"type":"Point"}
}