{
  "type": "Feature",
  "properties": {
    "iso:country":"FR",
    "sg:address":"Technopolis",
    "sg:city":"A Rue Louis De Broglie 53061 Laval Cedex",
    "sg:classifiers":[
        {
            "category":"Manufacturing",
            "subcategory":"Chemicals & Compounds",
            "type":"Manufacturing & Wholesale Goods"
        }
    ],
    "sg:phone":"+33 2 43 49 82 10",
    "sg:province":"Haute Normandie",
    "sg:tags":[
        "pharmaceutical",
        "energy",
        "chemistry",
        "-",
        "by-product"
    ],
    "wof:name":"Combustible De L'ouest Sa",
    "wof:placetype":"venue"
},
  "geometry": {"coordinates":[-0.69942,48.074299],"type":"Point"}
}