{
  "type": "Feature",
  "properties": {
    "addr:full":"6 R Mar\u00e9chal Joffre 35000 Rennes Rennes Bretagne 35000",
    "addr:housenumber":"6",
    "addr:postcode":"35000;35000",
    "addr:street":"R Mare\u0301Chal Joffre",
    "iso:country":"FR",
    "sg:address":"6 R Mar\u00e9chal Joffre 35000 Rennes",
    "sg:city":"Rennes",
    "sg:classifiers":[
        {
            "category":"Travel",
            "subcategory":"Hotels & Motels",
            "type":"Entertainment"
        }
    ],
    "sg:phone":"+33 2 99 79 37 74",
    "sg:postcode":"35000",
    "sg:province":"Bretagne",
    "sg:tags":[
        "hotels",
        "business",
        "restaurant"
    ],
    "wof:name":"Hotel Du Marechal Joffre",
    "wof:placetype":"venue"
},
  "geometry": {"coordinates":[-1.678092,48.10902],"type":"Point"}
}