{
  "type": "Feature",
  "properties": {
    "addr:full":"Av. de l'Europe - ZA de la Maie Rinxent Nord Pas-de-Calais 62720",
    "addr:postcode":"62720",
    "addr:street":"Av. De L'Europe Za De La Maie Rinxent Nord",
    "iso:country":"FR",
    "sg:address":"Av. de l'Europe - ZA de la Maie",
    "sg:city":"Rinxent",
    "sg:orig_category":"Unclassifiable Establishments",
    "sg:phone":"+33 3 21 87 15 15",
    "sg:postcode":"62720",
    "sg:province":"Nord Pas-de-Calais",
    "wof:name":"Solacap S.a.s.",
    "wof:placetype":"venue"
},
  "geometry": {"coordinates":[2.481493,48.891426],"type":"Point"}
}