{
  "type": "Feature",
  "properties": {
    "iso:country":"FR",
    "sg:address":"Les Roseaux 44330 Vallet",
    "sg:orig_category":"Non-Classified Establishments",
    "sg:phone":"+33 2 40 33 70 43",
    "sg:province":"Pays de Loire",
    "wof:name":"Terre Cuite Valletaise S.a.",
    "wof:placetype":"venue"
},
  "geometry": {"coordinates":[-1.241289,47.208393],"type":"Point"}
}