{
  "type": "Feature",
  "properties": {
    "iso:country":"FR",
    "sg:address":"1, Rue du Dronckaert, 59223 Roncq",
    "sg:orig_category":"Unclassifiable Establishments",
    "sg:phone":"+33 3 20 25 90 70",
    "sg:province":"Nord Pas-de-Calais",
    "wof:name":"Grimonprez P\u00e8re Et Fils Transports S.a.",
    "wof:placetype":"venue"
},
  "geometry": {"coordinates":[3.137315,50.74577],"type":"Point"}
}