{
  "type": "Feature",
  "properties": {
    "addr:full":"38, Av. Auber - Palais Hispania, 06000 Nice Basse Normandie",
    "addr:postcode":"06000",
    "addr:street":"38 Av. Auber",
    "iso:country":"FR",
    "sg:address":"38, Av. Auber - Palais Hispania, 06000 Nice",
    "sg:orig_category":"Unclassifiable Establishments",
    "sg:phone":"+33 4 93 87 26 98",
    "sg:province":"Basse Normandie",
    "wof:name":"A.g.sol. S.a.r.l. - Soci\u00e9t\u00e9 Am\u00e9nagement Gen De Sol",
    "wof:placetype":"venue"
},
  "geometry": {"coordinates":[7.27434,43.718231],"type":"Point"}
}