{
  "type": "Feature",
  "properties": {
    "iso:country":"FR",
    "sg:address":"27, Rue de Rinty, 86540 Thur\u00e9",
    "sg:orig_category":"Non-Classified Establishments",
    "sg:phone":"+33 5 49 93 20 73",
    "sg:postcode":"86540",
    "sg:province":"Poitou-Charentes",
    "wof:name":"Kl\u00fcber Lubrication France S.a.",
    "wof:placetype":"venue"
},
  "geometry": {"coordinates":[0.460094,46.831596],"type":"Point"}
}