{
  "type": "Feature",
  "properties": {
    "addr:full":"115, Av. Nationale, 45430 Ch\u00e9cy Ch\u00e9cy Centre 45430",
    "addr:postcode":"45430;45430",
    "addr:street":"115 Av. Nationale",
    "iso:country":"FR",
    "sg:address":"115, Av. Nationale, 45430 Ch\u00e9cy",
    "sg:city":"Ch\u00e9cy",
    "sg:orig_category":"Unclassifiable Establishments",
    "sg:phone":"+33 2 38 91 33 43",
    "sg:postcode":"45430",
    "sg:province":"Centre",
    "wof:name":"S.g.c.f. S.a.r.l.",
    "wof:placetype":"venue"
},
  "geometry": {"coordinates":[2.02344,47.897518],"type":"Point"}
}