{
  "type": "Feature",
  "properties": {
    "iso:country":"FR",
    "sg:address":"rue ampaire 42300 Mably",
    "sg:classifiers":[
        {
            "category":"Bakery",
            "type":"Food & Drink"
        }
    ],
    "sg:phone":"+33 4 77 44 49 60",
    "sg:province":"Rhone-Alpes",
    "sg:tags":[
        "pastry"
    ],
    "wof:name":"Valentin Traiteur Sa",
    "wof:placetype":"venue"
},
  "geometry": {"coordinates":[4.053092,46.06245],"type":"Point"}
}