{
  "type": "Feature",
  "properties": {
    "addr:full":"7 Impasse Anatole Le Bras 56170 Quiberon Quiberon Bretagne 56170",
    "addr:housenumber":"7",
    "addr:postcode":"56170;56170",
    "addr:street":"Impasse Anatole Le Bras",
    "iso:country":"FR",
    "sg:address":"7 Impasse Anatole Le Bras 56170 Quiberon",
    "sg:city":"Quiberon",
    "sg:classifiers":[
        {
            "category":"Food & Beverages",
            "subcategory":"Groceries & Convenience Stores",
            "type":"Retail Goods"
        }
    ],
    "sg:phone":"+33 2 97 50 01 48",
    "sg:postcode":"56170",
    "sg:province":"Bretagne",
    "sg:tags":[
        "product",
        "related"
    ],
    "wof:name":"Jacob Didier",
    "wof:placetype":"venue"
},
  "geometry": {"coordinates":[-3.131477,47.489498],"type":"Point"}
}