{
  "type": "Feature",
  "properties": {
    "iso:country":"FR",
    "sg:address":"Rte de Gen\u00e8ve",
    "sg:city":"Allonzier la Caille",
    "sg:orig_category":"Unclassifiable Establishments",
    "sg:phone":"+33 4 50 46 46 14",
    "sg:postcode":"74350",
    "sg:province":"Rhone-Alpes",
    "wof:name":"Soci\u00e9t\u00e9 Trane S.a.",
    "wof:placetype":"venue"
},
  "geometry": {"coordinates":[6.112133,46.011005],"type":"Point"}
}