{
  "type": "Feature",
  "properties": {
    "addr:full":"5, Rue de Guyenne - ZI les B\u00e9thunes, 95310 Saint Ouen l'Aum\u00f4ne Ile de France",
    "addr:housenumber":"5",
    "addr:postcode":"95310",
    "addr:street":"Rue De Guyenne Zi Les Be\u0301Thunes",
    "iso:country":"FR",
    "sg:address":"5, Rue de Guyenne - ZI les B\u00e9thunes, 95310 Saint Ouen l'Aum\u00f4ne",
    "sg:orig_category":"Non-Classified Establishments",
    "sg:phone":"+33 1 30 37 29 46",
    "sg:province":"Ile de France",
    "wof:name":"Syntaxe Imprimerie S.a.r.l.",
    "wof:placetype":"venue"
},
  "geometry": {"coordinates":[0.490902,48.605492],"type":"Point"}
}