{
  "type": "Feature",
  "properties": {
    "addr:full":"16, Rue Emile Roche, 59940 Estaires Nord Pas-de-Calais",
    "addr:housenumber":"16",
    "addr:postcode":"59940",
    "addr:street":"Rue Emile Roche",
    "iso:country":"FR",
    "sg:address":"16, Rue Emile Roche, 59940 Estaires",
    "sg:orig_category":"Unclassifiable Establishments",
    "sg:phone":"+33 3 28 48 81 26",
    "sg:province":"Nord Pas-de-Calais",
    "wof:name":"B.d. Graphic S.a.r.l. - Bruneau Duhameau Graphic",
    "wof:placetype":"venue"
},
  "geometry": {"coordinates":[2.721545,50.643539],"type":"Point"}
}