{
  "type": "Feature",
  "properties": {
    "addr:full":"Rte de Thuir Ille sur Tet Languedoc-Roussillon 66130",
    "addr:postcode":"66130",
    "addr:street":"Rte De Thuir Ille Sur Tet",
    "iso:country":"FR",
    "sg:address":"Rte de Thuir",
    "sg:city":"Ille sur Tet",
    "sg:orig_category":"Unclassifiable Establishments",
    "sg:phone":"+33 4 68 84 06 07",
    "sg:postcode":"66130",
    "sg:province":"Languedoc-Roussillon",
    "wof:name":"Gaspar S.a.r.l.",
    "wof:placetype":"venue"
},
  "geometry": {"coordinates":[2.625731,42.562313],"type":"Point"}
}