{
  "type": "Feature",
  "properties": {
    "addr:full":"3, Rue du Colombier, 45000 Orl\u00e9ans Orl\u00e9ans Centre 45000",
    "addr:housenumber":"3",
    "addr:postcode":"45000;45000",
    "addr:street":"Rue Du Colombier",
    "iso:country":"FR",
    "sg:address":"3, Rue du Colombier, 45000 Orl\u00e9ans",
    "sg:city":"Orl\u00e9ans",
    "sg:orig_category":"Unclassifiable Establishments",
    "sg:phone":"+33 2 38 70 08 00",
    "sg:postcode":"45000",
    "sg:province":"Centre",
    "wof:name":"Datanet Communication S.a.r.l.",
    "wof:placetype":"venue"
},
  "geometry": {"coordinates":[1.90268,47.903431],"type":"Point"}
}