{
  "type": "Feature",
  "properties": {
    "addr:full":"Rte de Peyrehorade Dax Aquitaine 40100",
    "addr:postcode":"40100",
    "addr:street":"Rte De Peyrehorade",
    "iso:country":"FR",
    "sg:address":"Rte de Peyrehorade",
    "sg:city":"Dax",
    "sg:orig_category":"Unclassifiable Establishments",
    "sg:phone":"+33 5 58 74 89 19",
    "sg:postcode":"40100",
    "sg:province":"Aquitaine",
    "wof:name":"A.b.x. Logistics Sud-ouest S.a.",
    "wof:placetype":"venue"
},
  "geometry": {"coordinates":[-1.044334,43.686642],"type":"Point"}
}