{
  "type": "Feature",
  "properties": {
    "addr:full":"50, Rue du Mourelet - ZI de Courtine, 84000 Avignon Provence-Alpes-C\u00f4te d'Azur",
    "addr:housenumber":"50",
    "addr:postcode":"84000",
    "addr:street":"Rue Du Mourelet Zi De Courtine",
    "iso:country":"FR",
    "sg:address":"50, Rue du Mourelet - ZI de Courtine, 84000 Avignon",
    "sg:orig_category":"Unclassifiable Establishments",
    "sg:phone":"+33 4 90 85 85 00",
    "sg:province":"Provence-Alpes-C\u00f4te d'Azur",
    "wof:name":"S.n.m.i. S.a. - Soci\u00e9t\u00e9 Nouvelle De M\u00e9tallisation Industrie",
    "wof:placetype":"venue"
},
  "geometry": {"coordinates":[4.806015,43.948753],"type":"Point"}
}