{
  "type": "Feature",
  "properties": {
    "addr:full":"39200 La Rixouse Franche Comt\u00e9 39200",
    "addr:housenumber":"39200",
    "addr:postcode":"39200",
    "addr:street":"La;Franche Comte\u0301",
    "iso:country":"FR",
    "sg:address":"39200 La Rixouse",
    "sg:classifiers":[
        {
            "category":"Professional",
            "subcategory":"Engineering",
            "type":"Services"
        }
    ],
    "sg:phone":"+33 3 84 45 20 85",
    "sg:postcode":"39200",
    "sg:province":"Franche Comt\u00e9",
    "sg:tags":[
        "machine",
        "-",
        "mechanical"
    ],
    "wof:name":"Etablissements A Cotter Fils",
    "wof:placetype":"venue"
},
  "geometry": {"coordinates":[5.889481,46.470844],"type":"Point"}
}