{
  "type": "Feature",
  "properties": {
    "iso:country":"FR",
    "sg:address":"4 Chemin De Fer 93800 Epinay Sur Seine",
    "sg:classifiers":[
        {
            "category":"Food & Beverages",
            "subcategory":"Dairy",
            "type":"Retail Goods"
        }
    ],
    "sg:phone":"+33 1 48 27 39 92",
    "sg:postcode":"93800",
    "sg:province":"Ile de France",
    "sg:tags":[
        "product",
        "related"
    ],
    "wof:name":"Le Marsala",
    "wof:placetype":"venue"
},
  "geometry": {"coordinates":[2.31221,48.953159],"type":"Point"}
}