{
  "type": "Feature",
  "properties": {
    "addr:full":"10 Rte De Rib\u00e9rac Pont De La Beauronne 24650 Chancelade Chancelade Aquitaine 24650",
    "addr:housenumber":"10",
    "addr:postcode":"24650;24650",
    "addr:street":"Rte De Ribe\u0301Rac Pont De La Beauronne",
    "iso:country":"FR",
    "sg:address":"10 Rte De Rib\u00e9rac Pont De La Beauronne 24650 Chancelade",
    "sg:city":"Chancelade",
    "sg:classifiers":[
        {
            "category":"Professional",
            "subcategory":"Advertising",
            "type":"Services"
        }
    ],
    "sg:phone":"+33 5 53 03 32 60",
    "sg:postcode":"24650",
    "sg:province":"Aquitaine",
    "sg:tags":[
        "information",
        "medium",
        "communication"
    ],
    "wof:name":"Giraudy",
    "wof:placetype":"venue"
},
  "geometry": {"coordinates":[0.66725,45.20475],"type":"Point"}
}