{
  "type": "Feature",
  "properties": {
    "addr:full":"Zac Puits Gruner 42230 Roche La Moli\u00e8re Rhone-Alpes",
    "addr:postcode":"42230",
    "addr:street":"Zac Puits Gruner",
    "iso:country":"FR",
    "sg:address":"Zac Puits Gruner 42230 Roche La Moli\u00e8re",
    "sg:classifiers":[
        {
            "category":"Shopping",
            "type":"Retail Goods"
        }
    ],
    "sg:phone":"+33 4 77 90 65 52",
    "sg:province":"Rhone-Alpes",
    "sg:tags":[
        "metallurgy",
        "finished",
        "-",
        "metalworking",
        "metallic"
    ],
    "wof:name":"Ets Henri Gilibert",
    "wof:placetype":"venue"
},
  "geometry": {"coordinates":[4.322345,45.432907],"type":"Point"}
}