{
  "type": "Feature",
  "properties": {
    "iso:country":"FR",
    "sg:address":"B.P. 32, 33560 Carbon Blanc C\u00e9dex^^Rue du Cabourney - ZI de la Mouline, 33560 Carbon Blanc",
    "sg:city":"Carbon-Blanc",
    "sg:orig_category":"Non-Classified Establishments",
    "sg:phone":"+33 5 56 38 07 77",
    "sg:postcode":"33560",
    "sg:province":"Aquitaine",
    "wof:name":"D.l.e. - Devin Le Marchand Environnement",
    "wof:placetype":"venue"
},
  "geometry": {"coordinates":[-0.473724,44.908085],"type":"Point"}
}