{
  "type": "Feature",
  "properties": {
    "addr:full":"2, Rue Fecht, 68230 Wihr au Val Soultzbach-les-Bains Alsace 68230",
    "addr:housenumber":"2",
    "addr:postcode":"68230;68230",
    "addr:street":"Rue Fecht;Au Val Soultzbach-Les-Bains",
    "iso:country":"FR",
    "sg:address":"2, Rue Fecht, 68230 Wihr au Val",
    "sg:city":"Soultzbach-les-Bains",
    "sg:orig_category":"Unclassifiable Establishments",
    "sg:phone":"+33 3 89 71 15 33",
    "sg:postcode":"68230",
    "sg:province":"Alsace",
    "wof:name":"Entreprise Picarella Fr\u00e8res S.a.r.l.",
    "wof:placetype":"venue"
},
  "geometry": {"coordinates":[7.205787,48.047192],"type":"Point"}
}