{
  "type": "Feature",
  "properties": {
    "addr:full":"Parc Artisanal De Malan 12510 Olemps Midi Pyr\u00e9n\u00e9es 12510",
    "addr:postcode":"12510;12510",
    "iso:country":"FR",
    "sg:address":"Parc Artisanal De Malan 12510 Olemps",
    "sg:classifiers":[
        {
            "category":"Professional",
            "subcategory":"Engineering",
            "type":"Services"
        }
    ],
    "sg:phone":"+33 5 65 68 58 46",
    "sg:postcode":"12510",
    "sg:province":"Midi Pyr\u00e9n\u00e9es",
    "sg:tags":[
        "machine",
        "-",
        "mechanical"
    ],
    "wof:name":"Societe D'exploitation Des Etablissements Censi (see Censi)",
    "wof:placetype":"venue"
},
  "geometry": {"coordinates":[2.569965,44.321964],"type":"Point"}
}