{
  "type": "Feature",
  "properties": {
    "iso:country":"FR",
    "sg:address":"17 Avenue De Vaudreuilhe 31250 Revel",
    "sg:classifiers":[
        {
            "category":"Home & Garden",
            "subcategory":"Furniture",
            "type":"Retail Goods"
        }
    ],
    "sg:phone":"+33 5 34 66 10 70",
    "sg:postcode":"31250",
    "sg:province":"Midi Pyr\u00e9n\u00e9es",
    "sg:tags":[
        "household",
        "wood"
    ],
    "wof:name":"Mark",
    "wof:placetype":"venue"
},
  "geometry": {"coordinates":[2.001652,43.455238],"type":"Point"}
}