{
  "type": "Feature",
  "properties": {
    "addr:full":"22 Rue D'I\u00e9na 72000 Le Mans Pays de Loire 72000",
    "addr:housenumber":"22",
    "addr:postcode":"72000;72000",
    "addr:street":"Rue D'Ie \u0301Na",
    "iso:country":"FR",
    "sg:address":"22 Rue D'I\u00e9na 72000 Le Mans",
    "sg:classifiers":[
        {
            "category":"Professional",
            "subcategory":"Business Services",
            "type":"Services"
        }
    ],
    "sg:phone":"+33 2 43 39 75 00",
    "sg:postcode":"72000",
    "sg:province":"Pays de Loire",
    "sg:tags":[
        "body",
        "advice"
    ],
    "wof:name":"Srsbs",
    "wof:placetype":"venue"
},
  "geometry": {"coordinates":[0.194585,47.998577],"type":"Point"}
}