{
  "type": "Feature",
  "properties": {
    "addr:full":"7 Rue Drouot 75009 Paris Ile de France",
    "addr:housenumber":"7",
    "addr:postcode":"75009",
    "addr:street":"Rue Drouot",
    "iso:country":"FR",
    "sg:address":"7 Rue Drouot 75009 Paris",
    "sg:classifiers":[
        {
            "category":"Professional",
            "subcategory":"Printing & Photocopies",
            "type":"Services"
        }
    ],
    "sg:phone":"+33 1 53 34 51 00",
    "sg:province":"Ile de France",
    "sg:tags":[
        "publishing"
    ],
    "wof:name":"Trader.com",
    "wof:placetype":"venue"
},
  "geometry": {"coordinates":[2.340253,48.872772],"type":"Point"}
}