{
  "type": "Feature",
  "properties": {
    "addr:full":"34, Traverse Marcel Maridet, 13012 Marseille Poitou-Charentes",
    "addr:housenumber":"34",
    "addr:postcode":"13012",
    "addr:street":"Traverse Marcel Maridet",
    "iso:country":"FR",
    "sg:address":"34, Traverse Marcel Maridet, 13012 Marseille",
    "sg:orig_category":"Unclassifiable Establishments",
    "sg:phone":"+33 4 91 18 04 44",
    "sg:province":"Poitou-Charentes",
    "wof:name":"Somatra S.a.",
    "wof:placetype":"venue"
},
  "geometry": {"coordinates":[5.422307,43.309414],"type":"Point"}
}