{
  "type": "Feature",
  "properties": {
    "addr:full":"Zi \u00c9changeur Nord 73100 Gr\u00e9sy Sur Aix Rhone-Alpes 73100",
    "addr:postcode":"73100;73100",
    "iso:country":"FR",
    "sg:address":"Zi \u00c9changeur Nord 73100 Gr\u00e9sy Sur Aix",
    "sg:classifiers":[
        {
            "category":"Professional",
            "subcategory":"Engineering",
            "type":"Services"
        }
    ],
    "sg:phone":"+33 4 79 34 80 80",
    "sg:postcode":"73100",
    "sg:province":"Rhone-Alpes",
    "sg:tags":[
        "machine",
        "-",
        "mechanical"
    ],
    "wof:name":"Jean Michel (ste) Sa",
    "wof:placetype":"venue"
},
  "geometry": {"coordinates":[5.926914,45.723503],"type":"Point"}
}