{
  "type": "Feature",
  "properties": {
    "iso:country":"FR",
    "sg:address":"21, Rue Auguste Perret - ZAC des Hautes Bruy\u00e8res, 94808 Villejuif C\u00e9dex",
    "sg:city":"Vill\u00e9",
    "sg:orig_category":"Non-Classified Establishments",
    "sg:phone":"+33 1 47 26 60 00",
    "sg:postcode":"67220",
    "sg:province":"Alsace",
    "wof:name":"Actar S\u00e9curit\u00e9 S.a.",
    "wof:placetype":"venue"
},
  "geometry": {"coordinates":[2.36366,48.792385],"type":"Point"}
}