{
  "type": "Feature",
  "properties": {
    "addr:full":"34 Rue De Verdun 69100 Villeurbanne Rhone-Alpes 69100",
    "addr:housenumber":"34",
    "addr:postcode":"69100;69100",
    "addr:street":"Rue De Verdun",
    "iso:country":"FR",
    "sg:address":"34 Rue De Verdun 69100 Villeurbanne",
    "sg:classifiers":[
        {
            "category":"Professional",
            "subcategory":"Advertising",
            "type":"Services"
        }
    ],
    "sg:phone":"+33 4 78 79 56 40",
    "sg:postcode":"69100",
    "sg:province":"Rhone-Alpes",
    "sg:tags":[
        "information",
        "medium",
        "communication"
    ],
    "wof:name":"Archiv'alpha",
    "wof:placetype":"venue"
},
  "geometry": {"coordinates":[4.897248,45.782963],"type":"Point"}
}