{
  "type": "Feature",
  "properties": {
    "iso:country":"FR",
    "sg:address":"64, Rue de la Burelle - Parc Archnim\u00e8de, 45800 Saint Jean de Braye",
    "sg:city":"Combleux",
    "sg:orig_category":"Unclassifiable Establishments",
    "sg:phone":"+33 2 38 24 52 52",
    "sg:postcode":"45800",
    "sg:province":"Centre",
    "wof:name":"Dauphin O.t.a. S.a.s.",
    "wof:placetype":"venue"
},
  "geometry": {"coordinates":[1.94542,47.914551],"type":"Point"}
}