{
  "type": "Feature",
  "properties": {
    "addr:full":"B.P. 10274, 95704 Roissy Charles de Gaulle C\u00e9dex^^Rte du Midi, 93290 Tremblay en France Ile de France 93290",
    "addr:housenumber":"10274",
    "addr:postcode":"95704;93290;93290",
    "iso:country":"FR",
    "sg:address":"B.P. 10274, 95704 Roissy Charles de Gaulle C\u00e9dex^^Rte du Midi, 93290 Tremblay en France",
    "sg:orig_category":"Non-Classified Establishments",
    "sg:phone":"+33 1 48 62 48 00",
    "sg:postcode":"93290",
    "sg:province":"Ile de France",
    "wof:name":"C.a.t. S.a. - Compagnie D'affr\u00e8tement Et De Transport",
    "wof:placetype":"venue"
},
  "geometry": {"coordinates":[2.56727,48.951214],"type":"Point"}
}