{
  "type": "Feature",
  "properties": {
    "addr:full":"29, Chemin du Baron, 31200 Toulouse Midi Pyr\u00e9n\u00e9es",
    "addr:housenumber":"29",
    "addr:postcode":"31200",
    "addr:street":"Chemin Du Baron",
    "iso:country":"FR",
    "sg:address":"29, Chemin du Baron, 31200 Toulouse",
    "sg:orig_category":"Unclassifiable Establishments",
    "sg:phone":"+33 5 61 57 54 80",
    "sg:province":"Midi Pyr\u00e9n\u00e9es",
    "wof:name":"Manutention Toulousaine E.u.r.l.",
    "wof:placetype":"venue"
},
  "geometry": {"coordinates":[1.435907,43.645191],"type":"Point"}
}