{
  "type": "Feature",
  "properties": {
    "iso:country":"FR",
    "sg:address":"RN 38 - ZA de la Haute Bedoule n\u00b033",
    "sg:city":"Septemes les Vallons",
    "sg:orig_category":"Unclassifiable Establishments",
    "sg:phone":"+33 4 91 09 55 85",
    "sg:postcode":"13240",
    "sg:province":"Aquitaine",
    "wof:name":"Burimprim S.a.r.l.",
    "wof:placetype":"venue"
},
  "geometry": {"coordinates":[5.366162,43.398479],"type":"Point"}
}