{
  "type": "Feature",
  "properties": {
    "iso:country":"FR",
    "sg:address":"5 Impasse Des Trois Chaussons Zone Industrielle 69330 Meyzieu",
    "sg:classifiers":[
        {
            "category":"Manufacturing",
            "subcategory":"Rubber & Plastics",
            "type":"Manufacturing & Wholesale Goods"
        }
    ],
    "sg:phone":"+33 4 72 45 08 30",
    "sg:postcode":"69330",
    "sg:province":"Rhone-Alpes",
    "wof:name":"Sofacome",
    "wof:placetype":"venue"
},
  "geometry": {"coordinates":[5.027765,45.771095],"type":"Point"}
}