{
  "type": "Feature",
  "properties": {
    "addr:full":"3/5, Quai Valin, 17088 La Rochelle Poitou-Charentes",
    "addr:housenumber":"3 / 5",
    "addr:postcode":"17088",
    "addr:street":"Quai Valin",
    "iso:country":"FR",
    "sg:address":"3/5, Quai Valin, 17088 La Rochelle",
    "sg:orig_category":"Unclassifiable Establishments",
    "sg:phone":"+33 5 46 34 65 67",
    "sg:province":"Poitou-Charentes",
    "wof:name":"Bonjour",
    "wof:placetype":"venue"
},
  "geometry": {"coordinates":[-1.150473,46.15789],"type":"Point"}
}