{
  "type": "Feature",
  "properties": {
    "iso:country":"FR",
    "sg:address":"Rte de Francescas",
    "sg:city":"N\u00e9rac",
    "sg:orig_category":"Unclassifiable Establishments",
    "sg:phone":"+33 5 53 97 62 00",
    "sg:postcode":"47600",
    "sg:province":"Aquitaine",
    "wof:name":"Syngenta Seeds S.a.s.",
    "wof:placetype":"venue"
},
  "geometry": {"coordinates":[0.37109,44.035454],"type":"Point"}
}