{
  "type": "Feature",
  "properties": {
    "addr:full":"Bd Denis Papin Zi La Bouriette 11000 Carcassonne Languedoc-Roussillon 11000",
    "addr:postcode":"11000;11000",
    "addr:street":"Zi La Bouriette",
    "iso:country":"FR",
    "sg:address":"Bd Denis Papin Zi La Bouriette 11000 Carcassonne",
    "sg:classifiers":[
        {
            "category":"Utilities",
            "subcategory":"Electric",
            "type":"Services"
        }
    ],
    "sg:phone":"+33 4 68 10 21 10",
    "sg:postcode":"11000",
    "sg:province":"Languedoc-Roussillon",
    "sg:tags":[
        "electricity",
        "raw",
        "energy",
        "material"
    ],
    "wof:name":"Cegelec Sud-ouest",
    "wof:placetype":"venue"
},
  "geometry": {"coordinates":[2.306378,43.188465],"type":"Point"}
}