{
  "type": "Feature",
  "properties": {
    "iso:country":"FR",
    "sg:address":"B.P. 77, 91802 Brunoy C\u00e9dex^^Rue Jules Guesde - ZI, 91860 Epinay sous S\u00e9nart",
    "sg:orig_category":"Non-Classified Establishments",
    "sg:phone":"+33 1 60 47 23 31",
    "sg:province":"Ile de France",
    "wof:name":"Rivet For\u00e9 R.c. S.a.",
    "wof:placetype":"venue"
},
  "geometry": {"coordinates":[2.51403,48.69466],"type":"Point"}
}