{
  "type": "Feature",
  "properties": {
    "iso:country":"FR",
    "sg:address":"16, Rue Decauville, 91814 Corbeil Essonnes C\u00e9dex",
    "sg:city":"Vill\u00e9",
    "sg:orig_category":"Non-Classified Establishments",
    "sg:phone":"+33 1 60 90 54 00",
    "sg:postcode":"67220",
    "sg:province":"Alsace",
    "wof:name":"Decauville S.a.",
    "wof:placetype":"venue"
},
  "geometry": {"coordinates":[2.472734,48.619701],"type":"Point"}
}