{
  "type": "Feature",
  "properties": {
    "iso:country":"FR",
    "sg:address":"B.P. 6, 64390 Sauveterre de B\u00e9arn C\u00e9dex^^Quartier Lasbordes, 64390 Sauveterre de B\u00e9arn",
    "sg:city":"Osserain-Rivareyte",
    "sg:orig_category":"Non-Classified Establishments",
    "sg:phone":"+33 5 59 38 33 31",
    "sg:postcode":"64390",
    "sg:province":"Aquitaine",
    "wof:name":"La Fourniture Informatique S.a.",
    "wof:placetype":"venue"
},
  "geometry": {"coordinates":[-0.915781,43.35939],"type":"Point"}
}