{
  "type": "Feature",
  "properties": {
    "addr:full":"Rte De Lyon 69470 Cours La Ville Rhone-Alpes 69470",
    "addr:postcode":"69470;69470",
    "addr:street":"Rte De Lyon;Cours La Ville Rhone-Alpes",
    "iso:country":"FR",
    "sg:address":"Rte De Lyon 69470 Cours La Ville",
    "sg:classifiers":[
        {
            "category":"Professional",
            "subcategory":"Business Services",
            "type":"Services"
        }
    ],
    "sg:phone":"+33 4 74 89 71 63",
    "sg:postcode":"69470",
    "sg:province":"Rhone-Alpes",
    "sg:tags":[
        "advice",
        "fabric",
        "clothes"
    ],
    "wof:name":"Sarl Genestier Malerba",
    "wof:placetype":"venue"
},
  "geometry": {"coordinates":[4.31332,46.096298],"type":"Point"}
}