{
  "type": "Feature",
  "properties": {
    "iso:country":"FR",
    "sg:address":"41, Rue Pasteur, 08320 Vireux Molhain",
    "sg:city":"Aubrives",
    "sg:orig_category":"Unclassifiable Establishments",
    "sg:phone":"+33 3 24 40 53 14",
    "sg:postcode":"08320",
    "sg:province":"Champagne",
    "wof:name":"Etablissements Molk",
    "wof:placetype":"venue"
},
  "geometry": {"coordinates":[4.72088,50.078438],"type":"Point"}
}