{
  "type": "Feature",
  "properties": {
    "addr:full":"53 Bis R De La R\u00e9publique 38300 Bourgoin Jallieu Rhone-Alpes 38300",
    "addr:housenumber":"53 bis",
    "addr:postcode":"38300;38300",
    "addr:street":"R De La Re\u0301Publique;Rhone-Alpes",
    "iso:country":"FR",
    "sg:address":"53 Bis R De La R\u00e9publique 38300 Bourgoin Jallieu",
    "sg:classifiers":[
        {
            "category":"Banks & Credit Unions",
            "subcategory":"Financial Services",
            "type":"Services"
        }
    ],
    "sg:phone":"+33 4 74 28 04 40",
    "sg:postcode":"38300",
    "sg:province":"Rhone-Alpes",
    "sg:tags":[
        "banking",
        "insurance",
        "institution",
        "finance"
    ],
    "wof:name":"Mutuelle Ccm",
    "wof:placetype":"venue"
},
  "geometry": {"coordinates":[5.274005,45.585747],"type":"Point"}
}