{
  "type": "Feature",
  "properties": {
    "iso:country":"FR",
    "sg:address":"B.P. 536, 24105 Bergerac C\u00e9dex^^ZAC de Creysse - La Nauve , 24100 Creysse",
    "sg:city":"Creysse",
    "sg:orig_category":"Non-Classified Establishments",
    "sg:phone":"+33 5 53 27 02 67",
    "sg:postcode":"24100",
    "sg:province":"Aquitaine",
    "wof:name":"Technic' Alu S.a.",
    "wof:placetype":"venue"
},
  "geometry": {"coordinates":[0.45362,44.815235],"type":"Point"}
}