{
  "type": "Feature",
  "properties": {
    "iso:country":"FR",
    "sg:address":"1 R Meyerbeer 75009 Paris",
    "sg:classifiers":[
        {
            "category":"Professional",
            "subcategory":"Advertising",
            "type":"Services"
        }
    ],
    "sg:phone":"+33 1 40 07 38 38",
    "sg:postcode":"75009",
    "sg:province":"Ile de France",
    "sg:tags":[
        "information",
        "medium",
        "communication"
    ],
    "wof:name":"United International Pictures Sarl",
    "wof:placetype":"venue"
},
  "geometry": {"coordinates":[2.33361,48.871624],"type":"Point"}
}