{
  "type": "Feature",
  "properties": {
    "addr:full":"42 bis, Rue de la Paix, 10000 Troyes Champagne 10000",
    "addr:housenumber":"42 bis",
    "addr:postcode":"10000;10000",
    "addr:street":"Rue De La Paix",
    "iso:country":"FR",
    "sg:address":"42 bis, Rue de la Paix, 10000 Troyes",
    "sg:orig_category":"Non-Classified Establishments",
    "sg:phone":"+33 3 25 82 60 52",
    "sg:postcode":"10000",
    "sg:province":"Champagne",
    "wof:name":"C.g.s.t. Save S.a.s. - Compagnie Gazi\u00e8re De Service Technique Save",
    "wof:placetype":"venue"
},
  "geometry": {"coordinates":[4.067448,48.303757],"type":"Point"}
}