{
  "type": "Feature",
  "properties": {
    "iso:country":"FR",
    "sg:address":"Le Presbytere 50420 Gouvets",
    "sg:city":"Gouvets",
    "sg:classifiers":[
        {
            "category":"Professional",
            "subcategory":"Printing & Photocopies",
            "type":"Services"
        }
    ],
    "sg:phone":"+33 2 33 55 51 47",
    "sg:postcode":"50420",
    "sg:province":"Basse Normandie",
    "sg:tags":[
        "publishing"
    ],
    "wof:name":"Normandie Magazine",
    "wof:placetype":"venue"
},
  "geometry": {"coordinates":[-1.086397,48.910404],"type":"Point"}
}