{
  "type": "Feature",
  "properties": {
    "addr:full":"1, Rue de Metz, 75010 Paris Ile de France",
    "addr:housenumber":"1",
    "addr:postcode":"75010",
    "addr:street":"Rue De Metz",
    "iso:country":"FR",
    "sg:address":"1, Rue de Metz, 75010 Paris",
    "sg:orig_category":"Non-Classified Establishments",
    "sg:phone":"+33 1 42 46 23 83",
    "sg:province":"Ile de France",
    "wof:name":"Ete Floex S.a.",
    "wof:placetype":"venue"
},
  "geometry": {"coordinates":[2.354537,48.870556],"type":"Point"}
}