{
  "type": "Feature",
  "properties": {
    "iso:country":"FR",
    "sg:address":"Av Des Mimosas 34360 Berlou",
    "sg:classifiers":[
        {
            "category":"Food Court",
            "type":"Food & Drink"
        }
    ],
    "sg:phone":"+33 4 67 89 58 58",
    "sg:postcode":"34360",
    "sg:province":"Languedoc-Roussillon",
    "sg:tags":[
        "product",
        "related"
    ],
    "wof:name":"Berloup Vins Et Terroir",
    "wof:placetype":"venue"
},
  "geometry": {"coordinates":[2.946445,43.42218],"type":"Point"}
}