{
  "type": "Feature",
  "properties": {
    "addr:full":"304 Rue De F\u00e9rin 59500 Douai Nord Pas-de-Calais",
    "addr:housenumber":"304",
    "addr:postcode":"59500",
    "addr:street":"Rue De Fe\u0301Rin",
    "iso:country":"FR",
    "sg:address":"304 Rue De F\u00e9rin 59500 Douai",
    "sg:classifiers":[
        {
            "category":"Professional",
            "type":"Services"
        }
    ],
    "sg:phone":"+33 3 27 98 01 81",
    "sg:province":"Nord Pas-de-Calais",
    "sg:tags":[
        "transport",
        "road"
    ],
    "wof:name":"Voyages Francois Lolli Sa",
    "wof:placetype":"venue"
},
  "geometry": {"coordinates":[3.076385,50.35857],"type":"Point"}
}