{
  "type": "Feature",
  "properties": {
    "addr:full":"93698 Pantin C\u00e9dex^^24, Rue Davorest, 93500 Pantin Ile de France",
    "addr:postcode":"93698;93500;ile",
    "addr:street":"Rue Davorest",
    "iso:country":"FR",
    "sg:address":"93698 Pantin C\u00e9dex^^24, Rue Davorest, 93500 Pantin",
    "sg:orig_category":"Non-Classified Establishments",
    "sg:phone":"+33 1 48 91 20 66",
    "sg:province":"Ile de France",
    "wof:name":"Mc Donald Multiblitz France S.a.r.l.",
    "wof:placetype":"venue"
},
  "geometry": {"coordinates":[2.40168,48.89658],"type":"Point"}
}