{
  "type": "Feature",
  "properties": {
    "addr:full":"56 Rue Jean Giraudoux Strasbourg Alsace 67200",
    "addr:housenumber":"56",
    "addr:postcode":"67200",
    "addr:street":"Rue Jean Giraudoux Strasbourg",
    "iso:country":"FR",
    "sg:address":"56 Rue Jean Giraudoux",
    "sg:city":"Strasbourg",
    "sg:classifiers":[
        {
            "category":"Banks & Credit Unions",
            "subcategory":"Financial Services",
            "type":"Services"
        }
    ],
    "sg:phone":"+33 3 88 13 30 00",
    "sg:postcode":"67200",
    "sg:province":"Alsace",
    "sg:tags":[
        "banking",
        "finance",
        "insurance"
    ],
    "wof:name":"Steelcase - Strafor",
    "wof:placetype":"venue"
},
  "geometry": {"coordinates":[7.702363,48.58749],"type":"Point"}
}