{
  "type": "Feature",
  "properties": {
    "iso:country":"FR",
    "sg:address":"99, Chemin de l'Etang Neuf, 01000 Saint Denis les Bourg",
    "sg:orig_category":"Non-Classified Establishments",
    "sg:phone":"+33 4 74 23 27 61",
    "sg:postcode":"01000",
    "sg:province":"Rhone-Alpes",
    "wof:name":"Ducrozet Moninot S.a.r.l.",
    "wof:placetype":"venue"
},
  "geometry": {"coordinates":[5.2456,46.191444],"type":"Point"}
}