{
  "type": "Feature",
  "properties": {
    "addr:full":"99, Chemin de l'Etang Neuf, 01000 Saint Denis les Bourg Rhone-Alpes 01000",
    "addr:housenumber":"99",
    "addr:postcode":"01000;01000",
    "addr:street":"Chemin De L'Etang Neuf;Denis Les Bourg Rhone-Alpes",
    "iso:country":"FR",
    "sg:address":"99, Chemin de l'Etang Neuf, 01000 Saint Denis les Bourg",
    "sg:orig_category":"Non-Classified Establishments",
    "sg:phone":"+33 4 74 23 27 61",
    "sg:postcode":"01000",
    "sg:province":"Rhone-Alpes",
    "wof:name":"Ducrozet Moninot S.a.r.l.",
    "wof:placetype":"venue"
},
  "geometry": {"coordinates":[5.2456,46.191444],"type":"Point"}
}