{
  "type": "Feature",
  "properties": {
    "iso:country":"FR",
    "sg:address":"151 bis, Av. Pierre Brossolette, 94170 Le Perreux sur Marne",
    "sg:orig_category":"Non-Classified Establishments",
    "sg:phone":"+33 1 43 24 29 44",
    "sg:province":"Ile de France",
    "wof:name":"Prest\u00e8ve S.a.r.l.",
    "wof:placetype":"venue"
},
  "geometry": {"coordinates":[2.50925,48.834728],"type":"Point"}
}