{
  "type": "Feature",
  "properties": {
    "addr:full":"37, Rue Professeur Patel, 69009 Lyon Rhone-Alpes 69009",
    "addr:housenumber":"37",
    "addr:postcode":"69009;69009",
    "addr:street":"Rue Professeur Patel",
    "iso:country":"FR",
    "sg:address":"37, Rue Professeur Patel, 69009 Lyon",
    "sg:orig_category":"Unclassifiable Establishments",
    "sg:phone":"+33 4 78 36 38 61",
    "sg:postcode":"69009",
    "sg:province":"Rhone-Alpes",
    "wof:name":"Th\u00e9matronic S.a.r.l.",
    "wof:placetype":"venue"
},
  "geometry": {"coordinates":[4.794282,45.76553],"type":"Point"}
}