{
  "type": "Feature",
  "properties": {
    "iso:country":"FR",
    "sg:address":"8 Rue De La Republique",
    "sg:city":"La Charite Sur Loire",
    "sg:classifiers":[
        {
            "category":"Banks & Credit Unions",
            "subcategory":"Financial Services",
            "type":"Services"
        }
    ],
    "sg:phone":"+33 3 86 70 09 89",
    "sg:postcode":"58400",
    "sg:province":"Bourgogne",
    "sg:tags":[
        "banking",
        "finance",
        "insurance"
    ],
    "wof:name":"Societe D'expertise Comptabilite Controle Conseil (e 3 C)",
    "wof:placetype":"venue"
},
  "geometry": {"coordinates":[3.01963,47.176849],"type":"Point"}
}