{
  "type": "Feature",
  "properties": {
    "addr:full":"232 Rue De Vieux Berquin 59190 Hazebrouck Nord Pas-de-Calais 59190",
    "addr:housenumber":"232",
    "addr:postcode":"59190;59190",
    "addr:street":"Rue De Vieux Berquin",
    "iso:country":"FR",
    "sg:address":"232 Rue De Vieux Berquin 59190 Hazebrouck",
    "sg:classifiers":[
        {
            "category":"Home & Garden",
            "subcategory":"Furniture",
            "type":"Retail Goods"
        }
    ],
    "sg:phone":"+33 3 28 50 92 60",
    "sg:postcode":"59190",
    "sg:province":"Nord Pas-de-Calais",
    "sg:tags":[
        "household",
        "wood"
    ],
    "wof:name":"Senelar (ets Andre) Sa",
    "wof:placetype":"venue"
},
  "geometry": {"coordinates":[2.553299,50.716244],"type":"Point"}
}