{
  "type": "Feature",
  "properties": {
    "iso:country":"FR",
    "sg:address":"7 pl Pierre Vauboin; Tassin",
    "sg:classifiers":[
        {
            "category":"Banks & Credit Unions",
            "subcategory":"Bank",
            "type":"Services"
        }
    ],
    "sg:phone":"+33 3372386370",
    "sg:province":"Languedoc-Roussillon",
    "wof:name":"Cr\u00e9dit Lyonnais",
    "wof:placetype":"venue"
},
  "geometry": {"coordinates":[8.813945,41.758347],"type":"Point"}
}