{
  "type": "Feature",
  "properties": {
    "iso:country":"FR",
    "sg:address":"B.P. 5264, 59379 Dunkerque C\u00e9dex 1^^Quai Freycinet 3 - M\u00f4le 1 - B\u00e2t. M1 M2, 59140 Dunkerque",
    "sg:orig_category":"Non-Classified Establishments",
    "sg:phone":"+33 3 28 65 91 80",
    "sg:province":"Nord Pas-de-Calais",
    "wof:name":"Rogers I.d.s. S.a. - International Distribution Services",
    "wof:placetype":"venue"
},
  "geometry": {"coordinates":[2.37693,51.036995],"type":"Point"}
}