{
  "type": "Feature",
  "properties": {
    "addr:full":"76, Rue du 3\u00e8me Zouave, 68130 Altkirch Altkirch Alsace 68130",
    "addr:housenumber":"76",
    "addr:postcode":"68130;68130",
    "addr:street":"Rue Du 3E\u0300Me",
    "iso:country":"FR",
    "sg:address":"76, Rue du 3\u00e8me Zouave, 68130 Altkirch",
    "sg:city":"Altkirch",
    "sg:orig_category":"Unclassifiable Establishments",
    "sg:phone":"+33 3 89 08 31 31",
    "sg:postcode":"68130",
    "sg:province":"Alsace",
    "wof:name":"M.g.i. Coutier S.a.",
    "wof:placetype":"venue"
},
  "geometry": {"coordinates":[7.257308,47.625961],"type":"Point"}
}