{
  "type": "Feature",
  "properties": {
    "iso:country":"FR",
    "sg:address":"8, Rte de Verri\u00e8res, 10800 Buch\u00e8res",
    "sg:orig_category":"Unclassifiable Establishments",
    "sg:phone":"+33 3 25 41 88 02",
    "sg:province":"Champagne",
    "wof:name":"Scieries De Buch\u00e8res S.a.r.l.",
    "wof:placetype":"venue"
},
  "geometry": {"coordinates":[4.137489,48.231319],"type":"Point"}
}