{
  "type": "Feature",
  "properties": {
    "iso:country":"FR",
    "sg:address":"R De L'Etang Neuf 71760 Issy L'Evec",
    "sg:city":"Cressy-sur-Somme",
    "sg:classifiers":[
        {
            "category":"Utilities",
            "subcategory":"Electric",
            "type":"Services"
        }
    ],
    "sg:phone":"+33 3 85 24 95 98",
    "sg:postcode":"71760",
    "sg:province":"Bourgogne",
    "sg:tags":[
        "electricity",
        "raw",
        "energy",
        "material"
    ],
    "wof:name":"Peccaud (anciens Etablissements Charles) Sarl",
    "wof:placetype":"venue"
},
  "geometry": {"coordinates":[3.9734,46.708179],"type":"Point"}
}