{
  "type": "Feature",
  "properties": {
    "iso:country":"FR",
    "sg:address":"49 Rue De La Mare Rouge 76620 Le Havre",
    "sg:city":"Le Havre",
    "sg:classifiers":[
        {
            "category":"Professional",
            "subcategory":"Engineering",
            "type":"Services"
        }
    ],
    "sg:phone":"+33 2 35 54 70 70",
    "sg:postcode":"76600",
    "sg:province":"Haute Normandie",
    "sg:tags":[
        "machine",
        "-",
        "environment",
        "equipment",
        "machinery",
        "mechanical"
    ],
    "wof:name":"Ste Generale De Traitement Des Eaux (sgte)",
    "wof:placetype":"venue"
},
  "geometry": {"coordinates":[0.10854,49.505741],"type":"Point"}
}