{
  "type": "Feature",
  "properties": {
    "addr:full":"8, Rue Mayencin, 38400 Saint Martin d'H\u00e8res Rhone-Alpes 38400",
    "addr:housenumber":"8",
    "addr:postcode":"38400;38400",
    "addr:street":"Rue Mayencin;Rhone-Alpes",
    "iso:country":"FR",
    "sg:address":"8, Rue Mayencin, 38400 Saint Martin d'H\u00e8res",
    "sg:orig_category":"Unclassifiable Establishments",
    "sg:phone":"+33 4 76 51 86 87",
    "sg:postcode":"38400",
    "sg:province":"Rhone-Alpes",
    "wof:name":"V.o.i.r. S.a.",
    "wof:placetype":"venue"
},
  "geometry": {"coordinates":[5.777148,45.186638],"type":"Point"}
}