{
  "type": "Feature",
  "properties": {
    "addr:full":"B.P. 4, 67401 Illkirch Graffenstaden C\u00e9dex^^Rue Sapidus - Immeuble le Platon, 67400 Illkirch Graffen Geispolsheim Alsace 67400",
    "addr:housenumber":"4",
    "addr:postcode":"67401;67400;67400",
    "addr:street":"B.P.",
    "iso:country":"FR",
    "sg:address":"B.P. 4, 67401 Illkirch Graffenstaden C\u00e9dex^^Rue Sapidus - Immeuble le Platon, 67400 Illkirch Graffen",
    "sg:city":"Geispolsheim",
    "sg:orig_category":"Non-Classified Establishments",
    "sg:phone":"+33 3 88 66 52 66",
    "sg:postcode":"67400",
    "sg:province":"Alsace",
    "wof:name":"Fininfor Progiciels Et Syst\u00e8mes S.a.",
    "wof:placetype":"venue"
},
  "geometry": {"coordinates":[7.711838,48.528809],"type":"Point"}
}