{
  "type": "Feature",
  "properties": {
    "addr:full":"13 Za Des 4 Vents 95650 Boissy L Aillerie Ile de France 95650",
    "addr:housenumber":"13",
    "addr:postcode":"95650;95650",
    "addr:street":"Za Des 4 Vents",
    "iso:country":"FR",
    "sg:address":"13 Za Des 4 Vents 95650 Boissy L Aillerie",
    "sg:classifiers":[
        {
            "category":"Shopping",
            "type":"Retail Goods"
        }
    ],
    "sg:phone":"+33 1 34 42 10 70",
    "sg:postcode":"95650",
    "sg:province":"Ile de France",
    "sg:tags":[
        "metallurgy",
        "finished",
        "-",
        "metalworking",
        "metallic"
    ],
    "wof:name":"Atelier Tolerie Prototype Serie (atps)",
    "wof:placetype":"venue"
},
  "geometry": {"coordinates":[-121.16738100000001,38.815128],"type":"Point"}
}