{
  "type": "Feature",
  "properties": {
    "addr:full":"4, Rue des Glairaux, 38120 Saint Egr\u00e8ve Rhone-Alpes 38120",
    "addr:housenumber":"4",
    "addr:postcode":"38120;38120",
    "addr:street":"Rue Des Glairaux;Rhone-Alpes",
    "iso:country":"FR",
    "sg:address":"4, Rue des Glairaux, 38120 Saint Egr\u00e8ve",
    "sg:orig_category":"Non-Classified Establishments",
    "sg:phone":"+33 4 76 58 05 05",
    "sg:postcode":"38120",
    "sg:province":"Rhone-Alpes",
    "wof:name":"Dauphipompe S.a.r.l.",
    "wof:placetype":"venue"
},
  "geometry": {"coordinates":[-89.842308,35.12442],"type":"Point"}
}