{
  "type": "Feature",
  "properties": {
    "addr:full":"15 rue Martel 75010 Paris Ile de France 75010",
    "addr:housenumber":"15",
    "addr:postcode":"75010;75010",
    "addr:street":"Rue Martel",
    "iso:country":"FR",
    "sg:address":"15 rue Martel 75010 Paris",
    "sg:classifiers":[
        {
            "category":"Shopping",
            "subcategory":"Clothing, Apparel, & Fashions",
            "type":"Retail Goods"
        }
    ],
    "sg:phone":"+33 1 47 70 70 03",
    "sg:postcode":"75010",
    "sg:province":"Ile de France",
    "sg:tags":[
        "blouse",
        "ladies'",
        "dress"
    ],
    "wof:name":"St\u00e9 L\u00e9o-minor S.a.r.l.",
    "wof:placetype":"venue"
},
  "geometry": {"coordinates":[2.352962,48.87434],"type":"Point"}
}