{
  "type": "Feature",
  "properties": {
    "iso:country":"FR",
    "sg:address":"122, Rue Anatole France, 45400 Fleury les Aubrais",
    "sg:city":"Chanteau",
    "sg:orig_category":"Non-Classified Establishments",
    "sg:phone":"+33 2 38 86 45 21",
    "sg:postcode":"45400",
    "sg:province":"Centre",
    "wof:name":"Les Aubrais S.a.r.l.",
    "wof:placetype":"venue"
},
  "geometry": {"coordinates":[1.914425,47.940521],"type":"Point"}
}