{
  "type": "Feature",
  "properties": {
    "iso:country":"FR",
    "sg:address":"Av Du Pr\u00e9sident Coty Rte De Paris 10600 La Chapelle St Luc",
    "sg:classifiers":[
        {
            "category":"Manufacturing",
            "subcategory":"Rubber & Plastics",
            "type":"Manufacturing & Wholesale Goods"
        }
    ],
    "sg:phone":"+33 3 25 72 34 00",
    "sg:province":"Champagne",
    "wof:name":"Pneumatiques Kleber",
    "wof:placetype":"venue"
},
  "geometry": {"coordinates":[4.03706,48.318581],"type":"Point"}
}