{
  "type": "Feature",
  "properties": {
    "iso:country":"FR",
    "sg:address":"Parc d'Activit\u00e9",
    "sg:city":"Cambrai",
    "sg:orig_category":"Unclassifiable Establishments",
    "sg:phone":"+33 3 27 82 29 29",
    "sg:postcode":"59400",
    "sg:province":"Nord Pas-de-Calais",
    "wof:name":"Ygnis Industrie S.a.r.l.",
    "wof:placetype":"venue"
},
  "geometry": {"coordinates":[-3.598827,52.910748],"type":"Point"}
}