{
  "type": "Feature",
  "properties": {
    "iso:country":"FR",
    "sg:address":"4 Rue De La Vego 85480 Bournezeau",
    "sg:classifiers":[
        {
            "category":"Wholesale",
            "subcategory":"Farm Supplies",
            "type":"Manufacturing & Wholesale Goods"
        }
    ],
    "sg:phone":"+33 2 51 40 73 02",
    "sg:postcode":"85480",
    "sg:province":"Pays de Loire",
    "sg:tags":[
        "-",
        "machine",
        "equipment",
        "engineering",
        "machinery",
        "mechanical",
        "agriculture"
    ],
    "wof:name":"Guigne Bordage",
    "wof:placetype":"venue"
},
  "geometry": {"coordinates":[-1.165057,46.639294],"type":"Point"}
}