{
  "type": "Feature",
  "properties": {
    "addr:full":"86, Rue du Caduc\u00e9e, 34000 Montpellier Languedoc-Roussillon",
    "addr:housenumber":"86",
    "addr:postcode":"34000",
    "addr:street":"Rue Du Caduce\u0301E",
    "iso:country":"FR",
    "sg:address":"86, Rue du Caduc\u00e9e, 34000 Montpellier",
    "sg:orig_category":"Unclassifiable Establishments",
    "sg:phone":"+33 4 67 91 70 10",
    "sg:province":"Languedoc-Roussillon",
    "wof:name":"W.c.i. S.a.r.l. - Westlake Components International",
    "wof:placetype":"venue"
},
  "geometry": {"coordinates":[3.86095,43.619289],"type":"Point"}
}