{
  "type": "Feature",
  "properties": {
    "iso:country":"FR",
    "sg:address":"24, Av. du Garigliano - ZAC des Gatines, 91600 Savigny sur Orge",
    "sg:orig_category":"Unclassifiable Establishments",
    "sg:phone":"+33 1 69 96 78 33",
    "sg:province":"Ile de France",
    "wof:name":"Ingenica S.a.r.l.",
    "wof:placetype":"venue"
},
  "geometry": {"coordinates":[2.35317,48.675098],"type":"Point"}
}