{
  "type": "Feature",
  "properties": {
    "addr:full":"55 bis, Av. Pierre Piffault - ZI Sud, 72100 Le Mans Pays de Loire",
    "addr:housenumber":"55 bis",
    "addr:postcode":"72100",
    "addr:street":"Av. Pierre Piffault Zi Sud",
    "iso:country":"FR",
    "sg:address":"55 bis, Av. Pierre Piffault - ZI Sud, 72100 Le Mans",
    "sg:orig_category":"Unclassifiable Establishments",
    "sg:phone":"+33 2 43 84 24 27",
    "sg:province":"Pays de Loire",
    "wof:name":"S.i.m. Sarl - Soci\u00e9t\u00e9 Industrielle De Montage",
    "wof:placetype":"venue"
},
  "geometry": {"coordinates":[0.20779,47.981861],"type":"Point"}
}