{
  "type": "Feature",
  "properties": {
    "iso:country":"FR",
    "sg:address":"37, Rue du Mirail, 33000 Bordeaux",
    "sg:city":"Bordeaux",
    "sg:orig_category":"Non-Classified Establishments",
    "sg:phone":"+33 5 56 94 76 00",
    "sg:postcode":"33000",
    "sg:province":"Aquitaine",
    "wof:name":"Ecritures S.a.r.l.",
    "wof:placetype":"venue"
},
  "geometry": {"coordinates":[-0.570847,44.833492],"type":"Point"}
}