{
  "type": "Feature",
  "properties": {
    "iso:country":"FR",
    "sg:address":"B.P. 2, 59540 Inchy^^18, Rue de Troisvilles, 59540 Inchy",
    "sg:orig_category":"Non-Classified Establishments",
    "sg:phone":"+33 3 27 85 61 48",
    "sg:postcode":"59540",
    "sg:province":"Nord Pas-de-Calais",
    "wof:name":"A.c.e.t. S.a. - Atelier Constructions Electriques T\u00e9l\u00e9phoniques",
    "wof:placetype":"venue"
},
  "geometry": {"coordinates":[3.41236,50.124474],"type":"Point"}
}