{
  "type": "Feature",
  "properties": {
    "iso:country":"FR",
    "sg:address":"La Croix Forzy 51220 Berm\u00e9ricourt",
    "sg:classifiers":[
        {
            "category":"Farming",
            "subcategory":"Fish & Marine Products",
            "type":"Manufacturing & Wholesale Goods"
        }
    ],
    "sg:phone":"+33 3 26 61 01 34",
    "sg:postcode":"51220",
    "sg:province":"Champagne",
    "sg:tags":[
        "animal",
        "food",
        "related",
        "grain",
        "cereal",
        "breeding"
    ],
    "wof:name":"Sotexpro",
    "wof:placetype":"venue"
},
  "geometry": {"coordinates":[3.89626,49.370411],"type":"Point"}
}