{
  "type": "Feature",
  "properties": {
    "addr:full":"5 bis, Place de la D\u00e9fense, 75000 Paris \u00cele-de-France",
    "addr:housenumber":"5 bis",
    "addr:postcode":"75000",
    "addr:street":"Place De La De\u0301Fense",
    "iso:country":"FR",
    "sg:address":"5 bis, Place de la D\u00e9fense, 75000 Paris",
    "sg:orig_category":"Unclassifiable Establishments",
    "sg:phone":"+33 1 41 97 45 00",
    "sg:province":"\u00cele-de-France",
    "wof:name":"A.b.b. Energie S.a.",
    "wof:placetype":"venue"
},
  "geometry": {"coordinates":[2.326759,48.885231],"type":"Point"}
}