{
  "type": "Feature",
  "properties": {
    "addr:full":"21270 Vielverge Vielverge Bourgogne 21270",
    "addr:postcode":"21270;21270",
    "iso:country":"FR",
    "sg:address":"21270 Vielverge",
    "sg:city":"Vielverge",
    "sg:orig_category":"EXTRUSION DE PROFILS DE SECTION 7MM \u00c0 200MM barres, joncs, gaines, coextrusion, coupes \u00e0 longueur, s",
    "sg:phone":"+33 3 80 47 20 20",
    "sg:postcode":"21270",
    "sg:province":"Bourgogne",
    "wof:name":"Celtiplast S.a.",
    "wof:placetype":"venue"
},
  "geometry": {"coordinates":[5.45156,47.267231],"type":"Point"}
}