{
  "type": "Feature",
  "properties": {
    "iso:country":"FR",
    "sg:address":"14 Route Du Plessis Bouchet 44800 St Herblain",
    "sg:classifiers":[
        {
            "category":"Bars & Pubs",
            "subcategory":"Gay Bar",
            "type":"Food & Drink"
        }
    ],
    "sg:phone":"+33 2 40 46 38 00",
    "sg:postcode":"44800",
    "sg:province":"Pays de Loire",
    "sg:tags":[
        "chemical",
        "pharmaceutical",
        "product",
        "chemistry",
        "related"
    ],
    "wof:name":"Brenntag Specialite",
    "wof:placetype":"venue"
},
  "geometry": {"coordinates":[-1.639869,47.20208],"type":"Point"}
}