{
  "type": "Feature",
  "properties": {
    "addr:full":"57b, Rue Raymond Poincar\u00e9, 54500 Vandoeuvre l\u00e8s Nancy Lorraine 54500",
    "addr:housenumber":"57b",
    "addr:postcode":"54500;54500",
    "addr:street":"Rue Raymond Poincare\u0301",
    "iso:country":"FR",
    "sg:address":"57b, Rue Raymond Poincar\u00e9, 54500 Vandoeuvre l\u00e8s Nancy",
    "sg:orig_category":"Non-Classified Establishments",
    "sg:phone":"+33 3 83 56 46 64",
    "sg:postcode":"54500",
    "sg:province":"Lorraine",
    "wof:name":"Doerler Mesures S.a.",
    "wof:placetype":"venue"
},
  "geometry": {"coordinates":[6.194313,48.668339],"type":"Point"}
}