{
  "type": "Feature",
  "properties": {
    "iso:country":"FR",
    "sg:address":"99, Av. Marcellin Berthelot, 69520 Grigny",
    "sg:orig_category":"Unclassifiable Establishments",
    "sg:phone":"+33 4 72 24 72 73",
    "sg:postcode":"69520",
    "sg:province":"Rhone-Alpes",
    "wof:name":"G. B. R. S.a.",
    "wof:placetype":"venue"
},
  "geometry": {"coordinates":[4.779573,45.596142],"type":"Point"}
}