{
  "type": "Feature",
  "properties": {
    "addr:full":"331 Rue Du Huit Mai 1945 Lannemezan Midi Pyr\u00e9n\u00e9es 65300",
    "addr:housenumber":"331;lannemezan",
    "addr:postcode":"65300",
    "addr:street":"Rue Du Huit Mai 1945",
    "iso:country":"FR",
    "sg:address":"331 Rue Du Huit Mai 1945",
    "sg:city":"Lannemezan",
    "sg:classifiers":[
        {
            "category":"Banks & Credit Unions",
            "subcategory":"Financial Services",
            "type":"Services"
        }
    ],
    "sg:phone":"+33 5 62 98 01 13",
    "sg:postcode":"65300",
    "sg:province":"Midi Pyr\u00e9n\u00e9es",
    "sg:tags":[
        "banking",
        "finance",
        "insurance"
    ],
    "wof:name":"Societe Francaise D'expertise Comptable (sofec)",
    "wof:placetype":"venue"
},
  "geometry": {"coordinates":[0.38375,43.115097],"type":"Point"}
}