{
  "type": "Feature",
  "properties": {
    "addr:full":"Ld Les Sapins 42510 Nervieux Rhone-Alpes",
    "addr:postcode":"42510",
    "addr:street":"Ld",
    "iso:country":"FR",
    "sg:address":"Ld Les Sapins 42510 Nervieux",
    "sg:classifiers":[
        {
            "category":"Manufacturing",
            "subcategory":"Wood Products",
            "type":"Manufacturing & Wholesale Goods"
        }
    ],
    "sg:phone":"+33 4 77 27 22 41",
    "sg:province":"Rhone-Alpes",
    "sg:tags":[
        "professional",
        "furniture"
    ],
    "wof:name":"Semi Production",
    "wof:placetype":"venue"
},
  "geometry": {"coordinates":[4.15581,45.80595],"type":"Point"}
}