{
  "type": "Feature",
  "properties": {
    "iso:country":"FR",
    "sg:address":"24, Rue de l'Aqueduc - Le Coudray , 27930 Le Vieil Evreux",
    "sg:orig_category":"Non-Classified Establishments",
    "sg:phone":"+33 2 32 39 23 68",
    "sg:province":"Haute Normandie",
    "wof:name":"Suzanne J.f. Transports S.a.r.l.",
    "wof:placetype":"venue"
},
  "geometry": {"coordinates":[1.198988,49.004662],"type":"Point"}
}