{
  "type": "Feature",
  "properties": {
    "iso:country":"FR",
    "sg:address":"Rue Du Commerce Z I Sud 85000 La Roche Sur Yon",
    "sg:classifiers":[
        {
            "category":"Utilities",
            "type":"Services"
        }
    ],
    "sg:phone":"+33 2 51 45 09 20",
    "sg:postcode":"85000",
    "sg:province":"Pays de Loire",
    "sg:tags":[
        "raw",
        "energy",
        "material"
    ],
    "wof:name":"Societe D'amenagement Urbain Et Rural (saur)",
    "wof:placetype":"venue"
},
  "geometry": {"coordinates":[-1.427199,46.67157],"type":"Point"}
}