{
  "type": "Feature",
  "properties": {
    "iso:country":"FR",
    "sg:address":"24 Avenue Joannes Masset Centre Activ Gorge De Loup 69009 Lyon",
    "sg:classifiers":[
        {
            "category":"Wholesale",
            "subcategory":"Machinery & Supplies",
            "type":"Manufacturing & Wholesale Goods"
        }
    ],
    "sg:phone":"+33 4 72 53 60 50",
    "sg:postcode":"69009",
    "sg:province":"Rhone-Alpes",
    "sg:tags":[
        "handling",
        "material",
        "-",
        "machine",
        "equipment",
        "engineering",
        "mechanical"
    ],
    "wof:name":"Franc Sa",
    "wof:placetype":"venue"
},
  "geometry": {"coordinates":[4.805335,45.774105],"type":"Point"}
}