{
  "type": "Feature",
  "properties": {
    "addr:full":"Parc Technologique Delta Sud Varilhes Midi Pyr\u00e9n\u00e9es 09120",
    "addr:postcode":"09120",
    "iso:country":"FR",
    "sg:address":"Parc Technologique Delta Sud",
    "sg:city":"Varilhes",
    "sg:orig_category":"Non-Classified Establishments",
    "sg:phone":"+33 5 61 69 61 00",
    "sg:postcode":"09120",
    "sg:province":"Midi Pyr\u00e9n\u00e9es",
    "wof:name":"Arg\u00e8ne S.a.",
    "wof:placetype":"venue"
},
  "geometry": {"coordinates":[1.63706,43.047939],"type":"Point"}
}