{
  "type": "Feature",
  "properties": {
    "iso:country":"FR",
    "sg:address":"rue Mathieu Vallat 42230 Roche La Moliere",
    "sg:classifiers":[
        {
            "category":"Autos & Motor Vehicles",
            "subcategory":"Auto Supplies",
            "type":"Retail Goods"
        }
    ],
    "sg:phone":"+33 4 77 50 57 00",
    "sg:province":"Rhone-Alpes",
    "sg:tags":[
        "helmet",
        "bicycle"
    ],
    "wof:name":"Pactuco International Sa",
    "wof:placetype":"venue"
},
  "geometry": {"coordinates":[4.325405,45.436565],"type":"Point"}
}