{
  "type": "Feature",
  "properties": {
    "iso:country":"FR",
    "sg:address":"17, Rue Montplaisir, 12100 Millau",
    "sg:orig_category":"Unclassifiable Establishments",
    "sg:phone":"+33 5 65 60 04 41",
    "sg:province":"Midi Pyr\u00e9n\u00e9es",
    "wof:name":"Sud Expert Conseil Aveyron S.a.",
    "wof:placetype":"venue"
},
  "geometry": {"coordinates":[3.07286,44.101562],"type":"Point"}
}