{
  "type": "Feature",
  "properties": {
    "addr:full":"Chez Soujeon 74420 HABERE LULLIN Rhone-Alpes 74420",
    "addr:postcode":"74420;74420",
    "iso:country":"FR",
    "sg:address":"Chez Soujeon 74420 HABERE LULLIN",
    "sg:classifiers":[
        {
            "category":"Manufacturing",
            "subcategory":"Wood Products",
            "type":"Manufacturing & Wholesale Goods"
        }
    ],
    "sg:phone":"+33 4 50 39 50 14",
    "sg:postcode":"74420",
    "sg:province":"Rhone-Alpes",
    "sg:tags":[
        "made",
        "balcony"
    ],
    "wof:name":"Etablissements Duret-cottet Sa",
    "wof:placetype":"venue"
},
  "geometry": {"coordinates":[6.448303,46.229893],"type":"Point"}
}