{
  "type": "Feature",
  "properties": {
    "iso:country":"FR",
    "sg:address":"91 Avenue Victor Hugo 24120 Terrasson Lavilledieu",
    "sg:city":"Beauregard-de-Terrasson",
    "sg:classifiers":[
        {
            "category":"Travel",
            "subcategory":"Hotels & Motels",
            "type":"Entertainment"
        }
    ],
    "sg:phone":"+33 5 53 51 46 46",
    "sg:postcode":"24120",
    "sg:province":"Aquitaine",
    "sg:tags":[
        "hotels",
        "business",
        "restaurant"
    ],
    "wof:name":"Hotel De Retraite Perigourdin",
    "wof:placetype":"venue"
},
  "geometry": {"coordinates":[1.293171,45.130402],"type":"Point"}
}