{
  "type": "Feature",
  "properties": {
    "addr:full":"B.P. Case Postale : 70495, 72025 Le Mans C\u00e9dex^^39, Bd Pierre Lefaucheux, 72000 Le Mans Pays de Loire",
    "addr:housenumber":"b.p.",
    "addr:postcode":"70495 72025;72000",
    "addr:street":"Case Postale;Bd Pierre Lefaucheux",
    "iso:country":"FR",
    "sg:address":"B.P. Case Postale : 70495, 72025 Le Mans C\u00e9dex^^39, Bd Pierre Lefaucheux, 72000 Le Mans",
    "sg:orig_category":"Non-Classified Establishments",
    "sg:phone":"+33 2 43 50 31 50",
    "sg:province":"Pays de Loire",
    "wof:name":"L.v.m. S.a. - Les Viandes Du Mans",
    "wof:placetype":"venue"
},
  "geometry": {"coordinates":[0.197813,48.008095],"type":"Point"}
}