{
  "type": "Feature",
  "properties": {
    "iso:country":"FR",
    "sg:address":"5 rue Cenrale; Malville",
    "sg:city":"Vill\u00e9",
    "sg:classifiers":[
        {
            "category":"Banks & Credit Unions",
            "subcategory":"Bank",
            "type":"Services"
        }
    ],
    "sg:phone":"+33 3340564448",
    "sg:postcode":"67220",
    "sg:province":"Alsace",
    "wof:name":"Cr\u00e9dit Mutuel",
    "wof:placetype":"venue"
},
  "geometry": {"coordinates":[-1.863377,47.360222],"type":"Point"}
}