{
  "type": "Feature",
  "properties": {
    "addr:full":"11, Rue des Cigognes, 68720 Illfurth Illfurth Alsace 68720",
    "addr:housenumber":"11",
    "addr:postcode":"68720;68720",
    "addr:street":"Rue Des Cigognes;Illfurth",
    "iso:country":"FR",
    "sg:address":"11, Rue des Cigognes, 68720 Illfurth",
    "sg:city":"Illfurth",
    "sg:orig_category":"Unclassifiable Establishments",
    "sg:phone":"+33 3 89 25 41 87",
    "sg:postcode":"68720",
    "sg:province":"Alsace",
    "wof:name":"Brender S.a.r.l.",
    "wof:placetype":"venue"
},
  "geometry": {"coordinates":[7.2637,47.673553],"type":"Point"}
}