{
  "type": "Feature",
  "properties": {
    "addr:full":"870, Chemin de la Degaye, 13880 Velaux Provence-Alpes-C\u00f4te d'Azur",
    "addr:housenumber":"870",
    "addr:postcode":"13880",
    "addr:street":"Chemin De La Degaye",
    "iso:country":"FR",
    "sg:address":"870, Chemin de la Degaye, 13880 Velaux",
    "sg:orig_category":"Unclassifiable Establishments",
    "sg:phone":"+33 4 42 74 73 94",
    "sg:province":"Provence-Alpes-C\u00f4te d'Azur",
    "wof:name":"Ch\u00e2teau Beauf\u00e9ran Adam S.c.e.a.",
    "wof:placetype":"venue"
},
  "geometry": {"coordinates":[5.22667,43.519817],"type":"Point"}
}