{
  "type": "Feature",
  "properties": {
    "addr:full":"All\u00e9e Rallu\u00e8res; Mont Louis Aquitaine",
    "addr:street":"Alle\u0301E Rallue\u0300Res Mont Louis Aquitaine",
    "iso:country":"FR",
    "sg:address":"All\u00e9e Rallu\u00e8res; Mont Louis",
    "sg:classifiers":[
        {
            "category":"Banks & Credit Unions",
            "subcategory":"Bank",
            "type":"Services"
        }
    ],
    "sg:phone":"+33 3347450478",
    "sg:province":"Aquitaine",
    "wof:name":"Cr\u00e9dit Agricole",
    "wof:placetype":"venue"
},
  "geometry": {"coordinates":[2.120392,42.507008],"type":"Point"}
}