{
  "type": "Feature",
  "properties": {
    "iso:country":"FR",
    "sg:address":"11, Rue Edouard Belin - Technop\u00f4le Metz 2000, 57070 Metz",
    "sg:orig_category":"Non-Classified Establishments",
    "sg:phone":"+33 3 87 20 33 77",
    "sg:province":"Lorraine",
    "wof:name":"Infomat Alsace S.a.",
    "wof:placetype":"venue"
},
  "geometry": {"coordinates":[6.202294,49.133659],"type":"Point"}
}