{
  "type": "Feature",
  "properties": {
    "iso:country":"FR",
    "sg:address":"Rond-Point de l'Europe",
    "sg:city":"Longueil Sainte Marie",
    "sg:orig_category":"Non-Classified Establishments",
    "sg:phone":"+33 3 44 38 60 00",
    "sg:postcode":"60126",
    "sg:province":"Picardie",
    "wof:name":"Codifrais S.a.",
    "wof:placetype":"venue"
},
  "geometry": {"coordinates":[2.71882,49.355141],"type":"Point"}
}