{
  "type": "Feature",
  "properties": {
    "addr:full":"2 Rue Du Vair 54520 Laxou Lorraine 54520",
    "addr:housenumber":"2",
    "addr:postcode":"54520;54520",
    "addr:street":"Rue Du Vair",
    "iso:country":"FR",
    "sg:address":"2 Rue Du Vair 54520 Laxou",
    "sg:classifiers":[
        {
            "category":"Travel",
            "subcategory":"Hotels & Motels",
            "type":"Entertainment"
        }
    ],
    "sg:phone":"+33 3 83 93 45 45",
    "sg:postcode":"54520",
    "sg:province":"Lorraine",
    "sg:tags":[
        "hotels",
        "business",
        "restaurant"
    ],
    "wof:name":"Novotel Nancy Ouest",
    "wof:placetype":"venue"
},
  "geometry": {"coordinates":[6.124519,48.695415],"type":"Point"}
}