{
  "type": "Feature",
  "properties": {
    "addr:full":"B.P. 7031, 69342 Lyon C\u00e9dex 07^^9, Rue de Fos sur Mer, 69007 Lyon Rhone-Alpes 69007",
    "addr:housenumber":"69342;07 ^ ^ 9",
    "addr:postcode":"69007;69007",
    "addr:street":"B.P. 7031;Ce\u0301Dex;Rue De Fos;Mer",
    "iso:country":"FR",
    "sg:address":"B.P. 7031, 69342 Lyon C\u00e9dex 07^^9, Rue de Fos sur Mer, 69007 Lyon",
    "sg:orig_category":"Non-Classified Establishments",
    "sg:phone":"+33 4 72 73 00 54",
    "sg:postcode":"69007",
    "sg:province":"Rhone-Alpes",
    "wof:name":"Santelli S.a.",
    "wof:placetype":"venue"
},
  "geometry": {"coordinates":[4.842415,45.746235],"type":"Point"}
}