{
  "type": "Feature",
  "properties": {
    "addr:full":"4 ave de la Grande Arm\u00e9e; Paris; 75818 Haute Normandie",
    "addr:postcode":"75818",
    "addr:street":"4 Ave De La Grande Arme\u0301E",
    "iso:country":"FR",
    "sg:address":"4 ave de la Grande Arm\u00e9e; Paris; 75818",
    "sg:classifiers":[
        {
            "category":"Banks & Credit Unions",
            "subcategory":"Bank",
            "type":"Services"
        }
    ],
    "sg:phone":"+33 1 40 53 55 55",
    "sg:province":"Haute Normandie",
    "wof:name":"Banco Do Brasil Sa",
    "wof:placetype":"venue"
},
  "geometry": {"coordinates":[2.29303,48.874844],"type":"Point"}
}