{
  "type": "Feature",
  "properties": {
    "addr:full":"18 rue Gustave Eiffel 44980 Ste Luce Sur Loire Pays de Loire",
    "addr:housenumber":"18",
    "addr:postcode":"44980",
    "addr:street":"Rue Gustave Eiffel;Luce;Loire",
    "iso:country":"FR",
    "sg:address":"18 rue Gustave Eiffel 44980 Ste Luce Sur Loire",
    "sg:classifiers":[
        {
            "category":"Banks & Credit Unions",
            "subcategory":"Investment Brokerage",
            "type":"Services"
        }
    ],
    "sg:phone":"+33 2 40 18 46 00",
    "sg:province":"Pays de Loire",
    "sg:tags":[
        "sweeper",
        "snow"
    ],
    "wof:name":"York Neige Sas",
    "wof:placetype":"venue"
},
  "geometry": {"coordinates":[-1.482786,47.262691],"type":"Point"}
}