{
  "type": "Feature",
  "properties": {
    "addr:full":"Rue C\u00e9lestin Freppaz - R\u00e9sidence l'Avernet Seez Rhone-Alpes 73700",
    "addr:postcode":"73700",
    "addr:street":"Rue Ce\u0301Lestin Freppaz Re\u0301Sidence",
    "iso:country":"FR",
    "sg:address":"Rue C\u00e9lestin Freppaz - R\u00e9sidence l'Avernet",
    "sg:city":"Seez",
    "sg:orig_category":"Non-Classified Establishments",
    "sg:phone":"+33 4 79 07 07 83",
    "sg:postcode":"73700",
    "sg:province":"Rhone-Alpes",
    "wof:name":"G.e.t. S.a.r.l. - Groupe Euro Technique",
    "wof:placetype":"venue"
},
  "geometry": {"coordinates":[6.799068,45.623135],"type":"Point"}
}