{
  "type": "Feature",
  "properties": {
    "addr:full":"3, Rue Marie Curie, 26100 Romans sur Is\u00e8re Rhone-Alpes 26100",
    "addr:housenumber":"3",
    "addr:postcode":"26100;26100",
    "addr:street":"Rue Marie Curie",
    "iso:country":"FR",
    "sg:address":"3, Rue Marie Curie, 26100 Romans sur Is\u00e8re",
    "sg:orig_category":"Unclassifiable Establishments",
    "sg:phone":"+33 4 75 71 08 50",
    "sg:postcode":"26100",
    "sg:province":"Rhone-Alpes",
    "wof:name":"Impuls France S.a.",
    "wof:placetype":"venue"
},
  "geometry": {"coordinates":[5.085317,45.050346],"type":"Point"}
}