{
  "type": "Feature",
  "properties": {
    "iso:country":"FR",
    "sg:address":"31/37, Rue Pix\u00e9r\u00e9court, 75020 Paris",
    "sg:orig_category":"Non-Classified Establishments",
    "sg:phone":"+33 1 44 62 18 18",
    "sg:province":"Ile de France",
    "wof:name":"Supinfor S.a.",
    "wof:placetype":"venue"
},
  "geometry": {"coordinates":[2.395756,48.872093],"type":"Point"}
}