{
  "type": "Feature",
  "properties": {
    "iso:country":"FR",
    "sg:address":"10 Rue Pierre Maillot Zone Industrielle 42120 Le Coteau",
    "sg:classifiers":[
        {
            "category":"Manufacturing",
            "subcategory":"Printing",
            "type":"Manufacturing & Wholesale Goods"
        }
    ],
    "sg:phone":"+33 4 77 71 10 10",
    "sg:postcode":"42120",
    "sg:province":"Rhone-Alpes",
    "sg:tags":[
        "publishing"
    ],
    "wof:name":"Societe Roannaise D'imprimerie Sa",
    "wof:placetype":"venue"
},
  "geometry": {"coordinates":[4.09834,45.991081],"type":"Point"}
}