{
  "type": "Feature",
  "properties": {
    "iso:country":"FR",
    "sg:address":"Rue de la Caravelle - ZI Portuaire",
    "sg:city":"Montoir de Bretagne",
    "sg:orig_category":"Unclassifiable Establishments",
    "sg:phone":"+33 2 40 90 43 00",
    "sg:postcode":"44550",
    "sg:province":"Pays de Loire",
    "wof:name":"Atlantique Stockage S.a.",
    "wof:placetype":"venue"
},
  "geometry": {"coordinates":[-2.177519,47.308414],"type":"Point"}
}