{
  "type": "Feature",
  "properties": {
    "iso:country":"FR",
    "sg:address":"83/85, Bd Vincent Auriol, 75013 Paris",
    "sg:orig_category":"Non-Classified Establishments",
    "sg:phone":"+33 1 42 16 63 63",
    "sg:province":"Ile de France",
    "wof:name":"Harlequin S.a.",
    "wof:placetype":"venue"
},
  "geometry": {"coordinates":[2.36708,48.834335],"type":"Point"}
}