{
  "type": "Feature",
  "properties": {
    "addr:full":"5 Place Croix Paquet 69001 Lyon Rhone-Alpes 69001",
    "addr:housenumber":"5",
    "addr:postcode":"69001;69001",
    "addr:street":"Place Croix Paquet",
    "iso:country":"FR",
    "sg:address":"5 Place Croix Paquet 69001 Lyon",
    "sg:classifiers":[
        {
            "category":"Manufacturing",
            "subcategory":"Jewelry",
            "type":"Manufacturing & Wholesale Goods"
        }
    ],
    "sg:phone":"+33 4 78 39 38 17",
    "sg:postcode":"69001",
    "sg:province":"Rhone-Alpes",
    "sg:tags":[
        "product",
        "miscellaneous",
        "jewellery"
    ],
    "wof:name":"Ddr Serti",
    "wof:placetype":"venue"
},
  "geometry": {"coordinates":[4.836354,45.770096],"type":"Point"}
}