{
  "type": "Feature",
  "properties": {
    "iso:country":"FR",
    "sg:address":"Rte de Flins - ZA de l'Erable",
    "sg:city":"Bouafle",
    "sg:orig_category":"Unclassifiable Establishments",
    "sg:phone":"+33 1 30 90 36 17",
    "sg:postcode":"78410",
    "sg:province":"Ile de France",
    "wof:name":"Univol S.a.r.l.",
    "wof:placetype":"venue"
},
  "geometry": {"coordinates":[1.901379,48.969048],"type":"Point"}
}