{
  "type": "Feature",
  "properties": {
    "addr:full":"Z.A.C. de l'Ecluse des Marots Saint Thibault Champagne 10800",
    "addr:postcode":"10800",
    "addr:street":"Z.A.C. De L'Ecluse Des Marots Saint Thibault Champagne",
    "iso:country":"FR",
    "sg:address":"Z.A.C. de l'Ecluse des Marots",
    "sg:city":"Saint Thibault",
    "sg:orig_category":"Non-Classified Establishments",
    "sg:phone":"+33 3 25 40 69 58",
    "sg:postcode":"10800",
    "sg:province":"Champagne",
    "wof:name":"Astic Emballage S.a.",
    "wof:placetype":"venue"
},
  "geometry": {"coordinates":[4.141426,48.212856],"type":"Point"}
}