{
  "type": "Feature",
  "properties": {
    "iso:country":"FR",
    "sg:address":"Impasse du Pr\u00e9 Bernot - Z.I. N[ 2 - Impasse du Pr\u00e9 Bernot - Z.I. N[ 2 - Impasse du Pr\u00e9 Bernot - Z.I.",
    "sg:city":"Le Meux",
    "sg:orig_category":"Unclassifiable Establishments",
    "sg:phone":"+33 3 44 91 04 05",
    "sg:postcode":"60880",
    "sg:province":"Picardie",
    "wof:name":"Stock France S.a.r.l.",
    "wof:placetype":"venue"
},
  "geometry": {"coordinates":[3.49487,49.866249],"type":"Point"}
}