{
  "type": "Feature",
  "properties": {
    "iso:country":"FR",
    "sg:address":"83, Rue de la Tour, 42000 Saint Etienne",
    "sg:orig_category":"Non-Classified Establishments",
    "sg:phone":"+33 4 77 93 42 19",
    "sg:province":"Rhone-Alpes",
    "wof:name":"T.b. Distribution S.a.r.l.",
    "wof:placetype":"venue"
},
  "geometry": {"coordinates":[4.38815,45.467533],"type":"Point"}
}