{
  "type": "Feature",
  "properties": {
    "addr:full":"71, Rue de Verdun, 80000 Amiens Picardie",
    "addr:housenumber":"71",
    "addr:postcode":"80000",
    "addr:street":"Rue De Verdun",
    "iso:country":"FR",
    "sg:address":"71, Rue de Verdun, 80000 Amiens",
    "sg:orig_category":"Unclassifiable Establishments",
    "sg:phone":"+33 3 22 71 60 00",
    "sg:province":"Picardie",
    "wof:name":"Duval S.a.",
    "wof:placetype":"venue"
},
  "geometry": {"coordinates":[2.311949,49.894115],"type":"Point"}
}