{
  "type": "Feature",
  "properties": {
    "iso:country":"FR",
    "sg:address":"RN 92 La Crois\u00e9e 38160 Chatte",
    "sg:classifiers":[
        {
            "category":"Professional",
            "type":"Services"
        }
    ],
    "sg:phone":"+33 4 76 64 43 11",
    "sg:postcode":"38160",
    "sg:province":"Rhone-Alpes",
    "sg:tags":[
        "transport",
        "road"
    ],
    "wof:name":"Mocellin Transports",
    "wof:placetype":"venue"
},
  "geometry": {"coordinates":[5.32654,45.113235],"type":"Point"}
}