{
  "type": "Feature",
  "properties": {
    "iso:country":"FR",
    "sg:address":"3 bis, Rue Condorcet - Zone Jean Zay, 33155 Cenon C\u00e9dex",
    "sg:orig_category":"Non-Classified Establishments",
    "sg:phone":"+33 5 57 54 15 90",
    "sg:province":"Champagne",
    "wof:name":"Aquitaine De Comptabilit\u00e9 S.a.",
    "wof:placetype":"venue"
},
  "geometry": {"coordinates":[-80.310883,25.736521],"type":"Point"}
}