{
  "type": "Feature",
  "properties": {
    "addr:full":"329 R L\u00e9on Blum La Coupole Antigone 34000 Montpellier Languedoc-Roussillon 34000",
    "addr:housenumber":"329",
    "addr:postcode":"34000;34000",
    "addr:street":"R Le\u0301On Blum La Coupole Antigone",
    "iso:country":"FR",
    "sg:address":"329 R L\u00e9on Blum La Coupole Antigone 34000 Montpellier",
    "sg:classifiers":[
        {
            "category":"Travel",
            "subcategory":"Hotels & Motels",
            "type":"Entertainment"
        }
    ],
    "sg:phone":"+33 4 67 15 80 00",
    "sg:postcode":"34000",
    "sg:province":"Languedoc-Roussillon",
    "sg:tags":[
        "hotels",
        "business",
        "restaurant"
    ],
    "wof:name":"Dexia Credit Local De France",
    "wof:placetype":"venue"
},
  "geometry": {"coordinates":[3.87609,43.610855],"type":"Point"}
}