{
  "type": "Feature",
  "properties": {
    "iso:country":"FR",
    "sg:address":"Rue Paul Emile Victor Zac De La Haute Borne 80136 Rivery",
    "sg:classifiers":[
        {
            "category":"Government",
            "subcategory":"Department Of Motor Vehicles",
            "type":"Public Place"
        }
    ],
    "sg:phone":"+33 3 22 97 70 00",
    "sg:postcode":"80136",
    "sg:province":"Picardie",
    "sg:tags":[
        "equipment",
        "industrial",
        "transport",
        "motor-cars"
    ],
    "wof:name":"Gueudet Sarva Sa",
    "wof:placetype":"venue"
},
  "geometry": {"coordinates":[2.323065,49.902409],"type":"Point"}
}