{
  "type": "Feature",
  "properties": {
    "iso:country":"FR",
    "sg:address":"Chez Bouteillet 16480 ORIOLLES",
    "sg:classifiers":[
        {
            "category":"Manufacturing",
            "subcategory":"Motor Vehicles & Parts",
            "type":"Manufacturing & Wholesale Goods"
        }
    ],
    "sg:phone":"+33 5 45 98 73 29",
    "sg:province":"Poitou-Charentes",
    "sg:tags":[
        "ground",
        "turned",
        "precision",
        "milled"
    ],
    "wof:name":"Sarl G.m Bois Sarl",
    "wof:placetype":"venue"
},
  "geometry": {"coordinates":[-0.153344,45.361721],"type":"Point"}
}