{
  "type": "Feature",
  "properties": {
    "addr:full":"3 Rue Sorgentino 06300 Nice Picardie",
    "addr:housenumber":"3",
    "addr:postcode":"06300",
    "addr:street":"Rue Sorgentino",
    "iso:country":"FR",
    "sg:address":"3 Rue Sorgentino 06300 Nice",
    "sg:classifiers":[
        {
            "category":"Manufacturing",
            "subcategory":"Wood Products",
            "type":"Manufacturing & Wholesale Goods"
        }
    ],
    "sg:phone":"+33 4 93 89 79 27",
    "sg:province":"Picardie",
    "sg:tags":[
        "furniture"
    ],
    "wof:name":"Technipose",
    "wof:placetype":"venue"
},
  "geometry": {"coordinates":[7.286957,43.7075],"type":"Point"}
}