{
  "type": "Feature",
  "properties": {
    "addr:full":"124 Rte De Beaune 21300 Chenove Chen\u00f4ve Bourgogne 21300",
    "addr:housenumber":"124",
    "addr:postcode":"21300;21300",
    "addr:street":"Rte De Beaune",
    "iso:country":"FR",
    "sg:address":"124 Rte De Beaune 21300 Chenove",
    "sg:city":"Chen\u00f4ve",
    "sg:classifiers":[
        {
            "category":"Travel",
            "subcategory":"Hotels & Motels",
            "type":"Entertainment"
        }
    ],
    "sg:phone":"+33 3 80 51 31 24",
    "sg:postcode":"21300",
    "sg:province":"Bourgogne",
    "sg:tags":[
        "hotels",
        "business",
        "restaurant"
    ],
    "wof:name":"Buffalo Grill",
    "wof:placetype":"venue"
},
  "geometry": {"coordinates":[5.004665,47.294296],"type":"Point"}
}