{
  "type": "Feature",
  "properties": {
    "addr:full":"21/23, Rue L\u00e9on Serpollet, 87280 Limoges Limousin",
    "addr:housenumber":"21 / 23",
    "addr:postcode":"87280",
    "addr:street":"Rue Le\u0301On Serpollet",
    "iso:country":"FR",
    "sg:address":"21/23, Rue L\u00e9on Serpollet, 87280 Limoges",
    "sg:orig_category":"Unclassifiable Establishments",
    "sg:phone":"+33 5 55 04 19 87",
    "sg:province":"Limousin",
    "wof:name":"G.e.m. Distribution",
    "wof:placetype":"venue"
},
  "geometry": {"coordinates":[1.281347,45.878769],"type":"Point"}
}