{
  "type": "Feature",
  "properties": {
    "iso:country":"FR",
    "sg:address":"20 rue de Billancourt 92100 Boulogne Billancourt",
    "sg:classifiers":[
        {
            "category":"Wholesale",
            "subcategory":"Books, Periodicals, & Newspapers",
            "type":"Manufacturing & Wholesale Goods"
        }
    ],
    "sg:phone":"+33 1 41 10 13 00",
    "sg:postcode":"92100",
    "sg:province":"Ile de France",
    "sg:tags":[
        "publisher",
        "journal"
    ],
    "wof:name":"Publications Bonnier S.a.",
    "wof:placetype":"venue"
},
  "geometry": {"coordinates":[2.234382,48.842724],"type":"Point"}
}