{
  "type": "Feature",
  "properties": {
    "iso:country":"FR",
    "sg:address":"Quinquis Lech Zi De Bel Air 29800 Landerneau",
    "sg:city":"Landerneau",
    "sg:classifiers":[
        {
            "category":"Building & Trades",
            "subcategory":"Construction",
            "type":"Services"
        }
    ],
    "sg:phone":"+33 2 98 85 03 38",
    "sg:postcode":"29800",
    "sg:province":"Bretagne",
    "sg:tags":[
        "livestock",
        "business",
        "advice",
        "animal",
        "breeding",
        "agriculture"
    ],
    "wof:name":"Electroland",
    "wof:placetype":"venue"
},
  "geometry": {"coordinates":[-4.228497,48.400295],"type":"Point"}
}