{
  "type": "Feature",
  "properties": {
    "addr:full":"Rte De Varengeville 76860 Longueil Haute Normandie",
    "addr:postcode":"76860",
    "addr:street":"Rte De Varengeville;Haute Normandie",
    "iso:country":"FR",
    "sg:address":"Rte De Varengeville 76860 Longueil",
    "sg:classifiers":[
        {
            "category":"Home & Garden",
            "subcategory":"Furniture",
            "type":"Retail Goods"
        }
    ],
    "sg:phone":"+33 2 35 83 12 96",
    "sg:province":"Haute Normandie",
    "sg:tags":[
        "wood"
    ],
    "wof:name":"M. Croise Jean-yves",
    "wof:placetype":"venue"
},
  "geometry": {"coordinates":[0.940301,49.890522],"type":"Point"}
}