{
  "type": "Feature",
  "properties": {
    "iso:country":"FR",
    "sg:address":"12 impasse Cotton 42300 Roanne",
    "sg:orig_category":"Hosiery, Nightwear, Daywear",
    "sg:phone":"+33 4 77 68 81 29",
    "sg:postcode":"42300",
    "sg:province":"Rhone-Alpes",
    "wof:name":"Jean Ruiz S.a.r.l.",
    "wof:placetype":"venue"
},
  "geometry": {"coordinates":[4.056739,46.034973],"type":"Point"}
}