{
  "type": "Feature",
  "properties": {
    "addr:full":"76 Boulevard De La Plage 33120 Arcachon Arcachon Aquitaine 33120",
    "addr:housenumber":"76",
    "addr:postcode":"33120;33120",
    "addr:street":"Boulevard De La Plage",
    "iso:country":"FR",
    "sg:address":"76 Boulevard De La Plage 33120 Arcachon",
    "sg:city":"Arcachon",
    "sg:classifiers":[
        {
            "category":"Autos & Motor Vehicles",
            "subcategory":"Boat Sales",
            "type":"Retail Goods"
        }
    ],
    "sg:phone":"+33 5 56 83 12 96",
    "sg:postcode":"33120",
    "sg:province":"Aquitaine",
    "sg:tags":[
        "equipment",
        "transport"
    ],
    "wof:name":"Bacherie Et Coussinerie D'aquitaine",
    "wof:placetype":"venue"
},
  "geometry": {"coordinates":[-1.153709,44.659805],"type":"Point"}
}