{
  "type": "Feature",
  "properties": {
    "iso:country":"FR",
    "sg:address":"11, Rue Guersant, 75017 Paris",
    "sg:orig_category":"Unclassifiable Establishments",
    "sg:phone":"+33 1 45 74 61 61",
    "sg:province":"Ile de France",
    "wof:name":"Avant Garde S.a.",
    "wof:placetype":"venue"
},
  "geometry": {"coordinates":[2.290237,48.88031],"type":"Point"}
}