{
  "type": "Feature",
  "properties": {
    "iso:country":"FR",
    "sg:address":"Grande Rue 54200 Bruley",
    "sg:classifiers":[
        {
            "category":"Food Court",
            "type":"Food & Drink"
        }
    ],
    "sg:phone":"+33 3 83 43 11 04",
    "sg:postcode":"54200",
    "sg:province":"Lorraine",
    "sg:tags":[
        "product",
        "related"
    ],
    "wof:name":"Laroppe",
    "wof:placetype":"venue"
},
  "geometry": {"coordinates":[5.888195,48.672104],"type":"Point"}
}