{
  "type": "Feature",
  "properties": {
    "addr:full":"67 Av Kennedy Zi Magre 87000 Limoges Limousin 87000",
    "addr:postcode":"87000;87000",
    "addr:street":"67 Av Kennedy Zi",
    "iso:country":"FR",
    "sg:address":"67 Av Kennedy Zi Magre 87000 Limoges",
    "sg:classifiers":[
        {
            "category":"Professional",
            "subcategory":"Engineering",
            "type":"Services"
        }
    ],
    "sg:phone":"+33 5 55 06 23 03",
    "sg:postcode":"87000",
    "sg:province":"Limousin",
    "sg:tags":[
        "machine",
        "-",
        "mechanical"
    ],
    "wof:name":"Elcede France (sa)",
    "wof:placetype":"venue"
},
  "geometry": {"coordinates":[1.26201,45.828785],"type":"Point"}
}