{
  "type": "Feature",
  "properties": {
    "iso:country":"FR",
    "sg:address":"22 allies de Mortarieu; BP 527; MONTAUBAN; 82065 CEDEX",
    "sg:classifiers":[
        {
            "category":"Shopping",
            "subcategory":"Computers & Home Electronics",
            "type":"Retail Goods"
        }
    ],
    "sg:phone":"+33 5 63 22 26 26",
    "sg:province":"Haute Normandie",
    "sg:tags":[
        "chamber",
        "commerce"
    ],
    "wof:name":"Chambre De Commerce De Montauban Et Du Tarn Et Garonne",
    "wof:placetype":"venue"
},
  "geometry": {"coordinates":[1.35891,44.017578],"type":"Point"}
}