{
  "type": "Feature",
  "properties": {
    "iso:country":"FR",
    "sg:address":"11 Bd Du G\u00e9neral Castelnau 67600 S\u00e9lestat",
    "sg:city":"S\u00e9lestat",
    "sg:classifiers":[
        {
            "category":"Wholesale",
            "subcategory":"Machinery & Supplies",
            "type":"Manufacturing & Wholesale Goods"
        }
    ],
    "sg:phone":"+33 3 88 92 35 40",
    "sg:postcode":"67600",
    "sg:province":"Alsace",
    "sg:tags":[
        "food",
        "processing",
        "-",
        "machine",
        "equipment",
        "engineering",
        "mechanical"
    ],
    "wof:name":"Ets Baur Et Cie Sa",
    "wof:placetype":"venue"
},
  "geometry": {"coordinates":[7.457509,48.260979],"type":"Point"}
}