{
  "type": "Feature",
  "properties": {
    "addr:full":"ZAC la Cibole La Chapelle du Bois Pays de Loire 72400",
    "addr:postcode":"72400",
    "addr:street":"Zac La Cibole La Chapelle Du Bois Pays;Loire",
    "iso:country":"FR",
    "sg:address":"ZAC la Cibole",
    "sg:city":"La Chapelle du Bois",
    "sg:orig_category":"Unclassifiable Establishments",
    "sg:phone":"+33 2 43 93 00 05",
    "sg:postcode":"72400",
    "sg:province":"Pays de Loire",
    "wof:name":"I.f. S.a.r.l. - Imprimerie Fertoise",
    "wof:placetype":"venue"
},
  "geometry": {"coordinates":[0.593095,48.22068],"type":"Point"}
}