{
  "type": "Feature",
  "properties": {
    "addr:full":"40, Rue des Peupliers, 60000 Aux Marais Picardie",
    "addr:housenumber":"40",
    "addr:postcode":"60000",
    "addr:street":"Rue Des Peupliers",
    "iso:country":"FR",
    "sg:address":"40, Rue des Peupliers, 60000 Aux Marais",
    "sg:orig_category":"Unclassifiable Establishments",
    "sg:phone":"+33 3 44 48 57 00",
    "sg:province":"Picardie",
    "wof:name":"Jos\u00e9 Horcholle",
    "wof:placetype":"venue"
},
  "geometry": {"coordinates":[2.036575,49.40974],"type":"Point"}
}