{
  "type": "Feature",
  "properties": {
    "addr:full":"19 Rue Eug\u00e8ne Jacquet 59800 Lille Nord Pas-de-Calais 59800",
    "addr:housenumber":"19",
    "addr:postcode":"59800;59800",
    "addr:street":"Rue Euge\u0300Ne Jacquet",
    "iso:country":"FR",
    "sg:address":"19 Rue Eug\u00e8ne Jacquet 59800 Lille",
    "sg:classifiers":[
        {
            "category":"Shopping",
            "subcategory":"Crafts & Fabrics",
            "type":"Retail Goods"
        }
    ],
    "sg:phone":"+33 3 20 15 40 70",
    "sg:postcode":"59800",
    "sg:province":"Nord Pas-de-Calais",
    "sg:tags":[
        "textile",
        "clothing"
    ],
    "wof:name":"Devcot Sa",
    "wof:placetype":"venue"
},
  "geometry": {"coordinates":[3.081902,50.637775],"type":"Point"}
}