{
  "type": "Feature",
  "properties": {
    "addr:full":"260, All\u00e9e des Cypr\u00e8s, 69760 Limonest Rhone-Alpes",
    "addr:housenumber":"260",
    "addr:postcode":"69760",
    "addr:street":"Alle\u0301E Des Cypre\u0300S",
    "iso:country":"FR",
    "sg:address":"260, All\u00e9e des Cypr\u00e8s, 69760 Limonest",
    "sg:orig_category":"Unclassifiable Establishments",
    "sg:phone":"+33 4 72 17 03 33",
    "sg:province":"Rhone-Alpes",
    "wof:name":"Ch\u00e2teau De Sans Souci S.a.r.l.",
    "wof:placetype":"venue"
},
  "geometry": {"coordinates":[4.777418,45.809166],"type":"Point"}
}