{
  "type": "Feature",
  "properties": {
    "iso:country":"FR",
    "sg:address":"B.P. 37824, 21078 Dijon C\u00e9dex^^2, Rond Point de la Nation, 21000 Dijon",
    "sg:city":"Dijon",
    "sg:orig_category":"Non-Classified Establishments",
    "sg:phone":"+33 3 80 73 96 00",
    "sg:postcode":"21000",
    "sg:province":"Bourgogne",
    "wof:name":"C.i.l.c.o. - Comit\u00e9 Interprofessionnel Du Logement De C\u00f4te D'or",
    "wof:placetype":"venue"
},
  "geometry": {"coordinates":[5.044195,47.326458],"type":"Point"}
}