{
  "type": "Feature",
  "properties": {
    "addr:full":"73, Chemin de la Prairie, 74000 Annecy Rhone-Alpes 74000",
    "addr:housenumber":"73",
    "addr:postcode":"74000;74000",
    "addr:street":"Chemin De La Prairie",
    "iso:country":"FR",
    "sg:address":"73, Chemin de la Prairie, 74000 Annecy",
    "sg:orig_category":"Unclassifiable Establishments",
    "sg:phone":"+33 4 50 33 08 33",
    "sg:postcode":"74000",
    "sg:province":"Rhone-Alpes",
    "wof:name":"B.m.r.a. S.a. - Bois Mat\u00e9riaux Rh\u00f4ne-alpes",
    "wof:placetype":"venue"
},
  "geometry": {"coordinates":[6.120962,45.890808],"type":"Point"}
}