{
  "type": "Feature",
  "properties": {
    "addr:full":"Za Les Guillemots 71190 Etang Sur Arroux Brion Bourgogne 71190",
    "addr:postcode":"71190;71190",
    "addr:street":"Za Les Guillemots",
    "iso:country":"FR",
    "sg:address":"Za Les Guillemots 71190 Etang Sur Arroux",
    "sg:city":"Brion",
    "sg:classifiers":[
        {
            "category":"Manufacturing",
            "subcategory":"Chemicals & Compounds",
            "type":"Manufacturing & Wholesale Goods"
        }
    ],
    "sg:phone":"+33 3 85 82 26 65",
    "sg:postcode":"71190",
    "sg:province":"Bourgogne",
    "sg:tags":[
        "pharmaceutical",
        "energy",
        "chemistry",
        "-",
        "by-product"
    ],
    "wof:name":"Td Distribution Thevenin Ducrot Distributionavia",
    "wof:placetype":"venue"
},
  "geometry": {"coordinates":[4.188715,46.866402],"type":"Point"}
}