{
  "type": "Feature",
  "properties": {
    "addr:full":"B.P. 53, 29393 Quimperl\u00e9 C\u00e9dex^^ZI Kergostiou, 29300 Quimperl\u00e9 Quimperl\u00e9 Bretagne 29300",
    "addr:postcode":"29393;29300;29300",
    "addr:street":"B.P. 53;Kergostiou",
    "iso:country":"FR",
    "sg:address":"B.P. 53, 29393 Quimperl\u00e9 C\u00e9dex^^ZI Kergostiou, 29300 Quimperl\u00e9",
    "sg:city":"Quimperl\u00e9",
    "sg:orig_category":"Non-Classified Establishments",
    "sg:phone":"+33 2 98 06 24 24",
    "sg:postcode":"29300",
    "sg:province":"Bretagne",
    "wof:name":"Groupe Bigard S.a.",
    "wof:placetype":"venue"
},
  "geometry": {"coordinates":[-3.461656,47.859921],"type":"Point"}
}