{
  "type": "Feature",
  "properties": {
    "addr:full":"102, Av. Aristide Briand, 92228 Bagneux C\u00e9dex \u00cele-de-France",
    "addr:postcode":"92228",
    "addr:street":"102 Av. Aristide Briand;Ce\u0301Dex",
    "iso:country":"FR",
    "sg:address":"102, Av. Aristide Briand, 92228 Bagneux C\u00e9dex",
    "sg:orig_category":"Unclassifiable Establishments",
    "sg:phone":"+33 1 46 73 61 11",
    "sg:province":"\u00cele-de-France",
    "wof:name":"E.d.f. Et Gaz De France",
    "wof:placetype":"venue"
},
  "geometry": {"coordinates":[2.323042,48.799541],"type":"Point"}
}