{
  "type": "Feature",
  "properties": {
    "iso:country":"FR",
    "sg:address":"Zone Des Graviers Rd 36 91190 Villiers Le Bacle",
    "sg:classifiers":[
        {
            "category":"Banks & Credit Unions",
            "subcategory":"Investment Brokerage",
            "type":"Services"
        }
    ],
    "sg:phone":"+33 1 69 35 17 30",
    "sg:postcode":"91190",
    "sg:province":"Ile de France",
    "sg:tags":[
        "good",
        "business",
        "-",
        "advice",
        "metal",
        "engineering",
        "metallic",
        "machine",
        "finished",
        "mechanical"
    ],
    "wof:name":"Physimeca Technologie",
    "wof:placetype":"venue"
},
  "geometry": {"coordinates":[2.132455,48.702435],"type":"Point"}
}