{
  "type": "Feature",
  "properties": {
    "addr:full":"B.P. 272, 02208 Soissons C\u00e9dex^^16, Bd Gambetta, 02200 Soissons Picardie",
    "addr:housenumber":"b.p. 272",
    "addr:postcode":"02208;ce\u0301dex^^16;02200",
    "addr:street":"Gambetta",
    "iso:country":"FR",
    "sg:address":"B.P. 272, 02208 Soissons C\u00e9dex^^16, Bd Gambetta, 02200 Soissons",
    "sg:orig_category":"Non-Classified Establishments",
    "sg:phone":"+33 800 02 10 14",
    "sg:province":"Picardie",
    "wof:name":"France T\u00e9l\u00e9com S.a.",
    "wof:placetype":"venue"
},
  "geometry": {"coordinates":[3.32451,49.366711],"type":"Point"}
}