{
  "type": "Feature",
  "properties": {
    "iso:country":"FR",
    "sg:address":"Route De La Boissiere Zone Industrielle 85600 Treize Septiers",
    "sg:classifiers":[
        {
            "category":"Manufacturing",
            "subcategory":"Glass & Minerals",
            "type":"Manufacturing & Wholesale Goods"
        }
    ],
    "sg:phone":"+33 2 51 41 66 66",
    "sg:postcode":"85600",
    "sg:province":"Pays de Loire",
    "sg:tags":[
        "building",
        "material"
    ],
    "wof:name":"Style Verre",
    "wof:placetype":"venue"
},
  "geometry": {"coordinates":[-1.226173,46.927738],"type":"Point"}
}