{
  "type": "Feature",
  "properties": {
    "addr:full":"ZI La Rivoire Cour et Buis Rhone-Alpes 38122",
    "addr:postcode":"38122",
    "addr:street":"Zi La Rivoire Cour Et Buis Rhone-Alpes",
    "iso:country":"FR",
    "sg:address":"ZI La Rivoire",
    "sg:city":"Cour et Buis",
    "sg:orig_category":"Non-Classified Establishments",
    "sg:phone":"+33 4 74 78 45 50",
    "sg:postcode":"38122",
    "sg:province":"Rhone-Alpes",
    "wof:name":"S.u.p. S.a. - Soci\u00e9t\u00e9 D'usinage P\u00e9riph\u00e9rique",
    "wof:placetype":"venue"
},
  "geometry": {"coordinates":[5.004614,45.440186],"type":"Point"}
}