{
  "type": "Feature",
  "properties": {
    "iso:country":"FR",
    "sg:address":"Boulevard Pre Pommier Zac Champ Fleuri 38300 Bourgoin Jallieu",
    "sg:classifiers":[
        {
            "category":"Health Services",
            "subcategory":"Medical Lab",
            "type":"Services"
        }
    ],
    "sg:phone":"+33 4 74 93 33 34",
    "sg:postcode":"38300",
    "sg:province":"Rhone-Alpes",
    "sg:tags":[
        "chemical",
        "pharmaceutical",
        "pharmacy"
    ],
    "wof:name":"Ardes Sarl",
    "wof:placetype":"venue"
},
  "geometry": {"coordinates":[5.30075,45.4981],"type":"Point"}
}