{
  "type": "Feature",
  "properties": {
    "iso:country":"FR",
    "sg:address":"Rue Ren\u00e9 Cassin",
    "sg:city":"Champagnole",
    "sg:orig_category":"Unclassifiable Establishments",
    "sg:phone":"+33 3 84 52 01 01",
    "sg:postcode":"39300",
    "sg:province":"Franche Comt\u00e9",
    "wof:name":"Caf\u00e9 R\u00e9gina S.a.",
    "wof:placetype":"venue"
},
  "geometry": {"coordinates":[5.91901,46.748325],"type":"Point"}
}