{
  "type": "Feature",
  "properties": {
    "iso:country":"FR",
    "sg:address":"1325, Rue Louise Michel, 42153 Riorges",
    "sg:orig_category":"Non-Classified Establishments",
    "sg:phone":"+33 4 77 71 20 32",
    "sg:province":"Rhone-Alpes",
    "wof:name":"New'dan S.a.r.l.",
    "wof:placetype":"venue"
},
  "geometry": {"coordinates":[4.044108,46.05864],"type":"Point"}
}