{
  "type": "Feature",
  "properties": {
    "addr:full":"165, Rue des Trois Tilleuls - ZI, 77000 Vaux le Penil Ile de France",
    "addr:housenumber":"165",
    "addr:postcode":"77000",
    "addr:street":"Rue Des Trois Tilleuls Zi",
    "iso:country":"FR",
    "sg:address":"165, Rue des Trois Tilleuls - ZI, 77000 Vaux le Penil",
    "sg:orig_category":"Non-Classified Establishments",
    "sg:phone":"+33 1 64 39 23 16",
    "sg:province":"Ile de France",
    "wof:name":"Someco Sa",
    "wof:placetype":"venue"
},
  "geometry": {"coordinates":[2.686117,48.535389],"type":"Point"}
}