{
  "type": "Feature",
  "properties": {
    "addr:full":"134 Rue De Gen\u00e8ve 73100 Aix Les Bains Rhone-Alpes 73100",
    "addr:housenumber":"134",
    "addr:postcode":"73100;73100",
    "addr:street":"Rue De Gene\u0300Ve",
    "iso:country":"FR",
    "sg:address":"134 Rue De Gen\u00e8ve 73100 Aix Les Bains",
    "sg:classifiers":[
        {
            "category":"Wholesale",
            "subcategory":"Medical Equipment & Supplies",
            "type":"Manufacturing & Wholesale Goods"
        }
    ],
    "sg:phone":"+33 4 79 35 65 78",
    "sg:postcode":"73100",
    "sg:province":"Rhone-Alpes",
    "sg:tags":[
        "instrument",
        "health",
        "-",
        "precision"
    ],
    "wof:name":"Ceram 73 Sarl",
    "wof:placetype":"venue"
},
  "geometry": {"coordinates":[5.91308,45.691196],"type":"Point"}
}