{
  "type": "Feature",
  "properties": {
    "iso:country":"FR",
    "sg:address":"2 rue Wencker 67000 Strasbourg",
    "sg:city":"Strasbourg",
    "sg:classifiers":[
        {
            "category":"Juice Bar",
            "subcategory":"None",
            "type":"Food & Drink"
        }
    ],
    "sg:phone":"+33 3 88 35 46 05",
    "sg:postcode":"67000",
    "sg:province":"Alsace",
    "sg:tags":[
        "apple"
    ],
    "wof:name":"Fructa France Sarl",
    "wof:placetype":"venue"
},
  "geometry": {"coordinates":[7.757443,48.585175],"type":"Point"}
}