{
  "type": "Feature",
  "properties": {
    "iso:country":"FR",
    "sg:address":"153, Rue des H\u00eatres - Z.A. La Saussaye Saint Cyr en Val, 45075 Orl\u00e9ans",
    "sg:orig_category":"Non-Classified Establishments",
    "sg:phone":"+33 2 38 25 05 50",
    "sg:province":"Centre",
    "wof:name":"Starissima S.a.",
    "wof:placetype":"venue"
},
  "geometry": {"coordinates":[1.90398,47.90139],"type":"Point"}
}