{
  "type": "Feature",
  "properties": {
    "addr:full":"39, Rue des Pr\u00e9, 27950 Saint Marcel Haute Normandie",
    "addr:housenumber":"39",
    "addr:postcode":"27950",
    "addr:street":"Rue Des Pre\u0301;Marcel Haute Normandie",
    "iso:country":"FR",
    "sg:address":"39, Rue des Pr\u00e9, 27950 Saint Marcel",
    "sg:orig_category":"Unclassifiable Establishments",
    "sg:phone":"+33 2 32 64 24 24",
    "sg:province":"Haute Normandie",
    "wof:name":"Gil Cartonnage S.a.",
    "wof:placetype":"venue"
},
  "geometry": {"coordinates":[1.44563,49.102982],"type":"Point"}
}