{
  "type": "Feature",
  "properties": {
    "iso:country":"FR",
    "sg:address":"39, Rue des Pr\u00e9, 27950 Saint Marcel",
    "sg:orig_category":"Unclassifiable Establishments",
    "sg:phone":"+33 2 32 64 24 24",
    "sg:province":"Haute Normandie",
    "wof:name":"Gil Cartonnage S.a.",
    "wof:placetype":"venue"
},
  "geometry": {"coordinates":[1.44563,49.102982],"type":"Point"}
}