{
  "type": "Feature",
  "properties": {
    "addr:full":"B.P. 104 Bordeaux C\u00e9dex Aquitaine 33084",
    "addr:housenumber":"b.p. 104",
    "addr:postcode":"33084",
    "iso:country":"FR",
    "sg:address":"B.P. 104",
    "sg:city":"Bordeaux C\u00e9dex",
    "sg:orig_category":"Non-Classified Establishments",
    "sg:phone":"+33 5 56 69 61 70",
    "sg:postcode":"33084",
    "sg:province":"Aquitaine",
    "wof:name":"B.e.t.c.o. S.a.r.l. - Bureau D'etudes Techniques Et Commerciales",
    "wof:placetype":"venue"
},
  "geometry": {"coordinates":[-0.54581,44.8027],"type":"Point"}
}