{
  "type": "Feature",
  "properties": {
    "addr:full":"81200 Aussillon Midi Pyr\u00e9n\u00e9es",
    "addr:postcode":"81200",
    "iso:country":"FR",
    "sg:address":"81200 Aussillon",
    "sg:orig_category":"Non-Classified Establishments",
    "sg:phone":"+33 5 63 61 15 71",
    "sg:province":"Midi Pyr\u00e9n\u00e9es",
    "wof:name":"Soci\u00e9t\u00e9 Laini\u00e8re De Saint Albi S.a.",
    "wof:placetype":"venue"
},
  "geometry": {"coordinates":[2.368825,43.498554],"type":"Point"}
}