{
  "type": "Feature",
  "properties": {
    "addr:full":"B.P. 17, 72250 Challes C\u00e9dex^^14, Chemin Moulin de la Bruy\u00e8re, 72250 Challes Pays de Loire",
    "addr:postcode":"72250;72250;pays",
    "addr:street":"B.P. 17;Chemin Moulin De La Bruye\u0300Re;Challes",
    "iso:country":"FR",
    "sg:address":"B.P. 17, 72250 Challes C\u00e9dex^^14, Chemin Moulin de la Bruy\u00e8re, 72250 Challes",
    "sg:orig_category":"Non-Classified Establishments",
    "sg:phone":"+33 2 43 86 74 10",
    "sg:province":"Pays de Loire",
    "wof:name":"M.t. Packaging S.a.",
    "wof:placetype":"venue"
},
  "geometry": {"coordinates":[0.337375,47.912636],"type":"Point"}
}