{
  "type": "Feature",
  "properties": {
    "iso:country":"FR",
    "sg:address":"6, Rue des Routiers - ZI Jalday 2, 64500 Saint Jean de Luz",
    "sg:city":"Ciboure",
    "sg:orig_category":"Unclassifiable Establishments",
    "sg:phone":"+33 5 59 26 06 99",
    "sg:postcode":"64500",
    "sg:province":"Aquitaine",
    "wof:name":"Soci\u00e9t\u00e9 D'exploitation A.t.c.r.b. S.a. - Association Des Transports En Commun De La R\u00e9gion",
    "wof:placetype":"venue"
},
  "geometry": {"coordinates":[-1.660884,43.38773],"type":"Point"}
}