{
  "type": "Feature",
  "properties": {
    "iso:country":"FR",
    "sg:address":"65, Rue Amp\u00e8re, 77400 Lagny sur Marne",
    "sg:orig_category":"Unclassifiable Establishments",
    "sg:phone":"+33 1 64 02 00 64",
    "sg:province":"Ile de France",
    "wof:name":"Etablissement H. Laurent S.a.",
    "wof:placetype":"venue"
},
  "geometry": {"coordinates":[2.6794,48.872547],"type":"Point"}
}