{
  "type": "Feature",
  "properties": {
    "addr:full":"2, Rue du Paradis, 89100 Maillot Maillot Bourgogne 89100",
    "addr:housenumber":"2",
    "addr:postcode":"89100;89100",
    "addr:street":"Rue Du Paradis",
    "iso:country":"FR",
    "sg:address":"2, Rue du Paradis, 89100 Maillot",
    "sg:city":"Maillot",
    "sg:orig_category":"Unclassifiable Establishments",
    "sg:phone":"+33 3 86 65 68 91",
    "sg:postcode":"89100",
    "sg:province":"Bourgogne",
    "wof:name":"Aity France S.a.r.l.",
    "wof:placetype":"venue"
},
  "geometry": {"coordinates":[3.304736,48.173481],"type":"Point"}
}