{
  "type": "Feature",
  "properties": {
    "addr:full":"Gare Terminal Est - Bureaux 24/26 Calais Nord Pas-de-Calais 62100",
    "addr:housenumber":"24 / 26",
    "addr:postcode":"62100",
    "addr:street":"Calais;Pas-De-Calais",
    "iso:country":"FR",
    "sg:address":"Gare Terminal Est - Bureaux 24/26",
    "sg:city":"Calais",
    "sg:orig_category":"Unclassifiable Establishments",
    "sg:phone":"+33 3 21 96 79 70",
    "sg:postcode":"62100",
    "sg:province":"Nord Pas-de-Calais",
    "wof:name":"Mat Transport S.a.",
    "wof:placetype":"venue"
},
  "geometry": {"coordinates":[1.85305,50.953079],"type":"Point"}
}