{
  "type": "Feature",
  "properties": {
    "addr:full":"7 Rue Principale 67290 Hinsbourg Hinsbourg Alsace 67290",
    "addr:housenumber":"7",
    "addr:postcode":"67290;67290",
    "addr:street":"Rue Principale;Hinsbourg",
    "iso:country":"FR",
    "sg:address":"7 Rue Principale 67290 Hinsbourg",
    "sg:city":"Hinsbourg",
    "sg:classifiers":[
        {
            "category":"Manufacturing",
            "subcategory":"Wood Products",
            "type":"Manufacturing & Wholesale Goods"
        }
    ],
    "sg:phone":"+33 3 88 01 53 82",
    "sg:postcode":"67290",
    "sg:province":"Alsace",
    "sg:tags":[
        "furniture"
    ],
    "wof:name":"Creations Bernhardt Bruno",
    "wof:placetype":"venue"
},
  "geometry": {"coordinates":[7.288521,48.907066],"type":"Point"}
}