{
  "type": "Feature",
  "properties": {
    "addr:full":"B.P. 299, 59019 Lille C\u00e9dex^^53, Rue Jean Jaur\u00e8s, 59000 Lille Nord Pas-de-Calais 59000",
    "addr:housenumber":"b.p. 299",
    "addr:postcode":"59019;59000;pas-de-calais 59000",
    "addr:street":"Rue Jean Jaure\u0300S",
    "iso:country":"FR",
    "sg:address":"B.P. 299, 59019 Lille C\u00e9dex^^53, Rue Jean Jaur\u00e8s, 59000 Lille",
    "sg:orig_category":"Non-Classified Establishments",
    "sg:phone":"+33 3 20 96 54 54",
    "sg:postcode":"59000",
    "sg:province":"Nord Pas-de-Calais",
    "wof:name":"A.n.p.e. - Direction R\u00e9gionale Nord - Pas De Calais",
    "wof:placetype":"venue"
},
  "geometry": {"coordinates":[3.06281,50.637184],"type":"Point"}
}