{
  "type": "Feature",
  "properties": {
    "addr:full":"13, Rue de Guebwiller, 67100 Strasbourg Strasbourg Alsace 67100",
    "addr:housenumber":"13",
    "addr:postcode":"67100;67100",
    "addr:street":"Rue De Guebwiller",
    "iso:country":"FR",
    "sg:address":"13, Rue de Guebwiller, 67100 Strasbourg",
    "sg:city":"Strasbourg",
    "sg:orig_category":"Unclassifiable Establishments",
    "sg:phone":"+33 3 88 34 46 62",
    "sg:postcode":"67100",
    "sg:province":"Alsace",
    "wof:name":"S.i.m.m.h.o. S.a.",
    "wof:placetype":"venue"
},
  "geometry": {"coordinates":[7.76701,48.559177],"type":"Point"}
}