{
  "type": "Feature",
  "properties": {
    "addr:full":"16, Rue Rambuteau, 75003 Paris Ile de France",
    "addr:housenumber":"16",
    "addr:postcode":"75003",
    "addr:street":"Rue Rambuteau",
    "iso:country":"FR",
    "sg:address":"16, Rue Rambuteau, 75003 Paris",
    "sg:orig_category":"Non-Classified Establishments",
    "sg:phone":"+33 1 42 78 19 60",
    "sg:province":"Ile de France",
    "wof:name":"Scao Sib S.a.r.l.",
    "wof:placetype":"venue"
},
  "geometry": {"coordinates":[2.35502,48.860806],"type":"Point"}
}