{
  "type": "Feature",
  "properties": {
    "iso:country":"FR",
    "sg:address":"19, Av. Du Mont F\u00e9lix, 51530 Moussy",
    "sg:orig_category":"Non-Classified Establishments",
    "sg:phone":"+33 3 26 58 48 69",
    "sg:province":"Basse Normandie",
    "wof:name":"Drot P\u00e8re Et Fils S.a.",
    "wof:placetype":"venue"
},
  "geometry": {"coordinates":[3.922598,49.010002],"type":"Point"}
}