{
  "type": "Feature",
  "properties": {
    "addr:full":"ZAC des Pradeaux Saint Cyr sur Mer Provence-Alpes-C\u00f4te d'Azur 83270",
    "addr:housenumber":"zac",
    "addr:postcode":"83270",
    "addr:street":"Des Pradeaux Saint Cyr Sur Mer",
    "iso:country":"FR",
    "sg:address":"ZAC des Pradeaux",
    "sg:city":"Saint Cyr sur Mer",
    "sg:orig_category":"Non-Classified Establishments",
    "sg:phone":"+33 4 94 32 00 26",
    "sg:postcode":"83270",
    "sg:province":"Provence-Alpes-C\u00f4te d'Azur",
    "wof:name":"Morvan Electronique Marine Et Industrie",
    "wof:placetype":"venue"
},
  "geometry": {"coordinates":[5.71089,43.180401],"type":"Point"}
}