{
  "type": "Feature",
  "properties": {
    "addr:full":"1522, Av. de Draguignan - ZI Toulon Est, 83130 La Garde Provence-Alpes-C\u00f4te d'Azur",
    "addr:housenumber":"1522",
    "addr:postcode":"83130",
    "addr:street":"Av. De Draguignan Zi;Est;Garde",
    "iso:country":"FR",
    "sg:address":"1522, Av. de Draguignan - ZI Toulon Est, 83130 La Garde",
    "sg:orig_category":"Unclassifiable Establishments",
    "sg:phone":"+33 4 94 08 47 14",
    "sg:province":"Provence-Alpes-C\u00f4te d'Azur",
    "wof:name":"A.e.p.",
    "wof:placetype":"venue"
},
  "geometry": {"coordinates":[6.009775,43.124866],"type":"Point"}
}