{
  "type": "Feature",
  "properties": {
    "addr:full":"Route D Orleans Le Vieux Moulin 28400 St Jean Pierre Fixte Brunelles Centre 28400",
    "addr:housenumber":"le;brunelles",
    "addr:postcode":"28400;28400",
    "addr:street":"Route D Orleans;Pierre Fixte",
    "iso:country":"FR",
    "sg:address":"Route D Orleans Le Vieux Moulin 28400 St Jean Pierre Fixte",
    "sg:city":"Brunelles",
    "sg:classifiers":[
        {
            "category":"Manufacturing",
            "subcategory":"Metals",
            "type":"Manufacturing & Wholesale Goods"
        }
    ],
    "sg:phone":"+33 2 37 52 19 28",
    "sg:postcode":"28400",
    "sg:province":"Centre",
    "sg:tags":[
        "metallurgy",
        "metalworking"
    ],
    "wof:name":"Trouillard Michel",
    "wof:placetype":"venue"
},
  "geometry": {"coordinates":[0.83732,48.29327],"type":"Point"}
}