{
  "type": "Feature",
  "properties": {
    "addr:full":"185, All\u00e9e des Artisans, 73260 Aigueblanche Rhone-Alpes 73260",
    "addr:housenumber":"185",
    "addr:postcode":"73260;73260",
    "addr:street":"Alle\u0301E Des Artisans;Rhone-Alpes",
    "iso:country":"FR",
    "sg:address":"185, All\u00e9e des Artisans, 73260 Aigueblanche",
    "sg:orig_category":"Non-Classified Establishments",
    "sg:phone":"+33 4 79 24 26 97",
    "sg:postcode":"73260",
    "sg:province":"Rhone-Alpes",
    "wof:name":"C.i.m.s. Fraissard S.a.r.l. - Chaudronnerie Industrielle M\u00e9cano-soudure Fraissard",
    "wof:placetype":"venue"
},
  "geometry": {"coordinates":[6.499545,45.506714],"type":"Point"}
}