{
  "type": "Feature",
  "properties": {
    "addr:full":"26, Rue des Veyettes - ZI Sud Est, 35200 Rennes Rennes Bretagne 35200",
    "addr:housenumber":"26",
    "addr:postcode":"35200;35200",
    "addr:street":"Rue Des Veyettes Zi Sud Est",
    "iso:country":"FR",
    "sg:address":"26, Rue des Veyettes - ZI Sud Est, 35200 Rennes",
    "sg:city":"Rennes",
    "sg:orig_category":"Non-Classified Establishments",
    "sg:phone":"+33 2 99 86 99 44",
    "sg:postcode":"35200",
    "sg:province":"Bretagne",
    "wof:name":"Chaillous",
    "wof:placetype":"venue"
},
  "geometry": {"coordinates":[-1.66606,48.089329],"type":"Point"}
}