{
  "type": "Feature",
  "properties": {
    "addr:full":"ZA V\u00e9ron Bourgogne 89510",
    "addr:postcode":"89510",
    "addr:street":"Za Ve\u0301Ron Bourgogne",
    "iso:country":"FR",
    "sg:address":"ZA",
    "sg:city":"V\u00e9ron",
    "sg:orig_category":"Unclassifiable Establishments",
    "sg:phone":"+33 3 86 97 47 47",
    "sg:postcode":"89510",
    "sg:province":"Bourgogne",
    "wof:name":"Maurice Hu S.a.",
    "wof:placetype":"venue"
},
  "geometry": {"coordinates":[3.3072,48.126461],"type":"Point"}
}