{
  "type": "Feature",
  "properties": {
    "addr:full":"52 rue de Paris; Nemours; 77140 Ile de France 77140",
    "addr:housenumber":"52",
    "addr:postcode":"77140;77140",
    "addr:street":"Rue De Paris;France",
    "iso:country":"FR",
    "sg:address":"52 rue de Paris; Nemours; 77140",
    "sg:classifiers":[
        {
            "category":"Banks & Credit Unions",
            "subcategory":"Bank",
            "type":"Services"
        }
    ],
    "sg:phone":"+33 3364280014",
    "sg:postcode":"77140",
    "sg:province":"Ile de France",
    "wof:name":"Soci\u00e9t\u00e9 G\u00e9n\u00e9rale",
    "wof:placetype":"venue"
},
  "geometry": {"coordinates":[2.694716,48.267326],"type":"Point"}
}