{
  "type": "Feature",
  "properties": {
    "addr:full":"Prony 01960 Peronnas Rhone-Alpes",
    "addr:postcode":"01960",
    "addr:street":"Prony",
    "iso:country":"FR",
    "sg:address":"Prony 01960 Peronnas",
    "sg:classifiers":[
        {
            "category":"Professional",
            "subcategory":"Printing & Photocopies",
            "type":"Services"
        }
    ],
    "sg:phone":"+33 4 74 21 19 28",
    "sg:province":"Rhone-Alpes",
    "sg:tags":[
        "silk-screen"
    ],
    "wof:name":"A.s.t.i. S\u00e9rigraphie Sa",
    "wof:placetype":"venue"
},
  "geometry": {"coordinates":[5.197886,46.169418],"type":"Point"}
}