{
  "type": "Feature",
  "properties": {
    "addr:full":"Lieu Dit Le Petit Coq 72500 Beaumont Pied De Boeuf Pays de Loire",
    "addr:postcode":"72500",
    "addr:street":"Lieu Dit Le Petit Coq;Boeuf",
    "iso:country":"FR",
    "sg:address":"Lieu Dit Le Petit Coq 72500 Beaumont Pied De Boeuf",
    "sg:classifiers":[
        {
            "category":"Manufacturing",
            "subcategory":"Wood Products",
            "type":"Manufacturing & Wholesale Goods"
        }
    ],
    "sg:phone":"+33 2 43 44 15 23",
    "sg:province":"Pays de Loire",
    "sg:tags":[
        "furniture"
    ],
    "wof:name":"Scierie Amy",
    "wof:placetype":"venue"
},
  "geometry": {"coordinates":[0.37174,47.748756],"type":"Point"}
}