{
  "type": "Feature",
  "properties": {
    "iso:country":"FR",
    "sg:address":"13, Av. du G\u00e9n\u00e9ral Leclerc, 94700 Maisons Alfort",
    "sg:orig_category":"Unclassifiable Establishments",
    "sg:phone":"+33 1 58 73 89 73",
    "sg:province":"Ile de France",
    "wof:name":"Varcity",
    "wof:placetype":"venue"
},
  "geometry": {"coordinates":[2.421782,48.815174],"type":"Point"}
}