{
  "type": "Feature",
  "properties": {
    "iso:country":"FR",
    "sg:address":"10 Rue Berthelot 59170 Croix",
    "sg:classifiers":[
        {
            "category":"Manufacturing",
            "subcategory":"Metals",
            "type":"Manufacturing & Wholesale Goods"
        }
    ],
    "sg:phone":"+33 3 20 65 26 58",
    "sg:postcode":"59170",
    "sg:province":"Nord Pas-de-Calais",
    "sg:tags":[
        "metallurgy",
        "metalworking",
        "processing"
    ],
    "wof:name":"Sarl Sb Flandre Affutage",
    "wof:placetype":"venue"
},
  "geometry": {"coordinates":[3.145739,50.672478],"type":"Point"}
}