{
  "type": "Feature",
  "properties": {
    "iso:country":"FR",
    "sg:address":"Rte de Bourges - ZI du Guidon",
    "sg:city":"Aubigny sur N\u00e8re",
    "sg:orig_category":"Non-Classified Establishments",
    "sg:phone":"+33 2 48 58 10 34",
    "sg:postcode":"18700",
    "sg:province":"Centre",
    "wof:name":"Mgm Bain Et Senteur S.a.",
    "wof:placetype":"venue"
},
  "geometry": {"coordinates":[2.50778,47.421684],"type":"Point"}
}