{
  "type": "Feature",
  "properties": {
    "iso:country":"FR",
    "sg:address":"78, Rue du P\u00e8re Gwena\u00ebl, 29470 Plougastel Daoulas",
    "sg:city":"Loperhet",
    "sg:orig_category":"Unclassifiable Establishments",
    "sg:phone":"+33 2 98 37 56 00",
    "sg:postcode":"29470",
    "sg:province":"Bretagne",
    "wof:name":"Caves Montmirel S.a.",
    "wof:placetype":"venue"
},
  "geometry": {"coordinates":[-4.363121,48.381485],"type":"Point"}
}