{
  "type": "Feature",
  "properties": {
    "addr:full":"Qua Beauchamp 84170 Monteux Midi Pyr\u00e9n\u00e9es",
    "addr:postcode":"84170",
    "iso:country":"FR",
    "sg:address":"Qua Beauchamp 84170 Monteux",
    "sg:classifiers":[
        {
            "category":"Professional",
            "type":"Services"
        }
    ],
    "sg:phone":"+33 4 90 66 94 10",
    "sg:province":"Midi Pyr\u00e9n\u00e9es",
    "sg:tags":[
        "transport",
        "road"
    ],
    "wof:name":"Lurit Transports Sa",
    "wof:placetype":"venue"
},
  "geometry": {"coordinates":[4.961545,44.019596],"type":"Point"}
}