{
  "type": "Feature",
  "properties": {
    "addr:full":"12, Rue Paul-Henri Spaak, 77400 Saint Thibault des Vignes Ile de France",
    "addr:housenumber":"12",
    "addr:postcode":"77400;ile",
    "addr:street":"Rue Paul-Henri Spaak",
    "iso:country":"FR",
    "sg:address":"12, Rue Paul-Henri Spaak, 77400 Saint Thibault des Vignes",
    "sg:orig_category":"Unclassifiable Establishments",
    "sg:phone":"+33 1 64 30 81 81",
    "sg:province":"Ile de France",
    "wof:name":"A.p.p. Photogravure De L'est S.a.rl.",
    "wof:placetype":"venue"
},
  "geometry": {"coordinates":[2.675306,48.864902],"type":"Point"}
}