{
  "type": "Feature",
  "properties": {
    "iso:country":"FR",
    "sg:address":"B.P. 63, 80017 Amiens C\u00e9dex 1^^13, Place Alphonse Fiquet - Tour Perret, 80000 Amiens",
    "sg:orig_category":"Non-Classified Establishments",
    "sg:phone":"+33 3 22 91 78 87",
    "sg:postcode":"80000",
    "sg:province":"Picardie",
    "wof:name":"D.r.c.e. - Direction R\u00e9gionale Du Commerce Ext\u00e9rieur",
    "wof:placetype":"venue"
},
  "geometry": {"coordinates":[2.293165,49.894733],"type":"Point"}
}