{
  "type": "Feature",
  "properties": {
    "addr:full":"Les Garinn\u00e9s 69210 Nuelles Rhone-Alpes 69210",
    "addr:postcode":"69210;69210",
    "addr:street":"Rhone-Alpes",
    "iso:country":"FR",
    "sg:address":"Les Garinn\u00e9s 69210 Nuelles",
    "sg:orig_category":"Unclassifiable Establishments",
    "sg:phone":"+33 4 74 72 09 50",
    "sg:postcode":"69210",
    "sg:province":"Rhone-Alpes",
    "wof:name":"A.m.n. S.a. - Ateliers M\u00e9caniques De Nuelles",
    "wof:placetype":"venue"
},
  "geometry": {"coordinates":[4.620877,45.852985],"type":"Point"}
}