{
  "type": "Feature",
  "properties": {
    "iso:country":"FR",
    "sg:address":"Bd de Creac'h Gwen",
    "sg:city":"Quimper C\u00e9dex",
    "sg:orig_category":"Non-Classified Establishments",
    "sg:phone":"+33 2 98 10 18 18",
    "sg:postcode":"29196",
    "sg:province":"Pays de Loire",
    "wof:name":"Adria",
    "wof:placetype":"venue"
},
  "geometry": {"coordinates":[-4.102132,47.981628],"type":"Point"}
}