{
  "type": "Feature",
  "properties": {
    "iso:country":"FR",
    "sg:address":"Za Les Rozais 35550 Sixt Sur Aff",
    "sg:city":"Bruc-sur-Aff",
    "sg:classifiers":[
        {
            "category":"Home & Garden",
            "subcategory":"Furniture",
            "type":"Retail Goods"
        }
    ],
    "sg:phone":"+33 2 99 70 08 13",
    "sg:postcode":"35550",
    "sg:province":"Bretagne",
    "sg:tags":[
        "wood"
    ],
    "wof:name":"J. Dubois",
    "wof:placetype":"venue"
},
  "geometry": {"coordinates":[-2.077669,47.776226],"type":"Point"}
}