{
  "type": "Feature",
  "properties": {
    "addr:full":"Rue Du Clos De La Reine 78410 Aubergenville Ile de France 78410",
    "addr:postcode":"78410;ile;78410",
    "addr:street":"Rue Du Clos De La Reine;France",
    "iso:country":"FR",
    "sg:address":"Rue Du Clos De La Reine 78410 Aubergenville",
    "sg:classifiers":[
        {
            "category":"Manufacturing",
            "subcategory":"Tools & Machinery",
            "type":"Manufacturing & Wholesale Goods"
        }
    ],
    "sg:phone":"+33 1 34 80 51 11",
    "sg:postcode":"78410",
    "sg:province":"Ile de France",
    "sg:tags":[
        "metallurgy",
        "metalworking"
    ],
    "wof:name":"Ateliers Lr Etanco",
    "wof:placetype":"venue"
},
  "geometry": {"coordinates":[1.8494,48.967735],"type":"Point"}
}