{
  "type": "Feature",
  "properties": {
    "addr:full":"5 Rue Albert Thomas Le Forum Besancon Franche Comt\u00e9 25000",
    "addr:housenumber":"5",
    "addr:postcode":"25000",
    "addr:street":"Rue Albert Thomas Le;Franche Comte\u0301",
    "iso:country":"FR",
    "sg:address":"5 Rue Albert Thomas Le Forum",
    "sg:city":"Besancon",
    "sg:classifiers":[
        {
            "category":"Banks & Credit Unions",
            "subcategory":"Financial Services",
            "type":"Services"
        }
    ],
    "sg:phone":"+33 3 81 88 39 87",
    "sg:postcode":"25000",
    "sg:province":"Franche Comt\u00e9",
    "sg:tags":[
        "banking",
        "finance",
        "insurance"
    ],
    "wof:name":"Fidulor Societe D'expertise Comptable",
    "wof:placetype":"venue"
},
  "geometry": {"coordinates":[5.987163,47.241318],"type":"Point"}
}