{
  "type": "Feature",
  "properties": {
    "addr:full":"Rue de la Louvi\u00e8re Bienvillers au Bois Nord Pas-de-Calais 62111",
    "addr:postcode":"62111",
    "addr:street":"Rue De La Louvie\u0300Re Bienvillers;Bois;Pas-De-Calais",
    "iso:country":"FR",
    "sg:address":"Rue de la Louvi\u00e8re",
    "sg:city":"Bienvillers au Bois",
    "sg:orig_category":"Non-Classified Establishments",
    "sg:phone":"+33 3 21 07 71 10",
    "sg:postcode":"62111",
    "sg:province":"Nord Pas-de-Calais",
    "wof:name":"S.p.m. S.a. - Soci\u00e9t\u00e9 Picarde De M\u00e9canique",
    "wof:placetype":"venue"
},
  "geometry": {"coordinates":[2.618341,50.178005],"type":"Point"}
}