{
  "type": "Feature",
  "properties": {
    "iso:country":"FR",
    "sg:address":"35 rue Nationale; Mantes la Jolie; 78200",
    "sg:classifiers":[
        {
            "category":"Banks & Credit Unions",
            "subcategory":"Bank",
            "type":"Services"
        }
    ],
    "sg:phone":"+33 3 30 92 83 00",
    "sg:postcode":"78200",
    "sg:province":"Ile de France",
    "wof:name":"Banque Nationale De Paris",
    "wof:placetype":"venue"
},
  "geometry": {"coordinates":[1.7173,48.990276],"type":"Point"}
}