{
  "type": "Feature",
  "properties": {
    "iso:country":"FR",
    "sg:address":"196, Rue Antoine Primat, 42000 Saint Etienne",
    "sg:orig_category":"Unclassifiable Establishments",
    "sg:phone":"+33 4 77 47 55 79",
    "sg:province":"Rhone-Alpes",
    "wof:name":"Mollart France S.a.r.l.",
    "wof:placetype":"venue"
},
  "geometry": {"coordinates":[4.421434,45.456303],"type":"Point"}
}