{
  "type": "Feature",
  "properties": {
    "addr:full":"4, Rue Sainte Barbe, 22000 Saint Brieuc Saint-Brieuc Bretagne 22000",
    "addr:housenumber":"4",
    "addr:postcode":"22000;22000",
    "addr:street":"Rue Sainte Barbe;Brieuc;Bretagne",
    "iso:country":"FR",
    "sg:address":"4, Rue Sainte Barbe, 22000 Saint Brieuc",
    "sg:city":"Saint-Brieuc",
    "sg:orig_category":"Unclassifiable Establishments",
    "sg:phone":"+33 2 96 68 43 43",
    "sg:postcode":"22000",
    "sg:province":"Bretagne",
    "wof:name":"Cible Marketing Strat\u00e9gie S.a.r.l.",
    "wof:placetype":"venue"
},
  "geometry": {"coordinates":[-2.75972,48.512241],"type":"Point"}
}