{
  "type": "Feature",
  "properties": {
    "addr:full":"6, Av Georges Cl\u00e9menceau, 59300 Valenciennes Nord Pas-de-Calais",
    "addr:postcode":"59300",
    "addr:street":"Av Georges Cle\u0301Menceau",
    "iso:country":"FR",
    "sg:address":"6, Av Georges Cl\u00e9menceau, 59300 Valenciennes",
    "sg:orig_category":"Non-Classified Establishments",
    "sg:phone":"+33 3 27 30 30 28",
    "sg:province":"Nord Pas-de-Calais",
    "wof:name":"Heltex Tissus S.a.",
    "wof:placetype":"venue"
},
  "geometry": {"coordinates":[3.522464,50.359425],"type":"Point"}
}