{
  "type": "Feature",
  "properties": {
    "addr:full":"Rue Du 8 Mai 1945 R\u00e9sidence La Versaillaise 77111 Solers Ile de France 77111",
    "addr:postcode":"77111;77111",
    "addr:street":"Rue Du 8 Mai 1945 Re\u0301Sidence La Versaillaise;Ile De France",
    "iso:country":"FR",
    "sg:address":"Rue Du 8 Mai 1945 R\u00e9sidence La Versaillaise 77111 Solers",
    "sg:classifiers":[
        {
            "category":"Building & Trades",
            "subcategory":"Construction",
            "type":"Services"
        }
    ],
    "sg:phone":"+33 1 64 06 69 69",
    "sg:postcode":"77111",
    "sg:province":"Ile de France",
    "sg:tags":[
        "work",
        "public"
    ],
    "wof:name":"Les Compagnons Paveurs",
    "wof:placetype":"venue"
},
  "geometry": {"coordinates":[2.711135,48.65691],"type":"Point"}
}