{
  "type": "Feature",
  "properties": {
    "iso:country":"FR",
    "sg:address":"B.P. 14, 59541 Caudry C\u00e9dex^^18, Rue Jean Jacques Rousseau, 59541 Caudry C\u00e9dex",
    "sg:orig_category":"Non-Classified Establishments",
    "sg:phone":"+33 3 27 85 01 03",
    "sg:province":"Nord Pas-de-Calais",
    "wof:name":"Dentelles Andr\u00e9 Laude S.a.",
    "wof:placetype":"venue"
},
  "geometry": {"coordinates":[3.41236,50.124474],"type":"Point"}
}