{
  "type": "Feature",
  "properties": {
    "iso:country":"FR",
    "sg:address":"10, Rue Henri Petit, 02400 Ch\u00e2teau Thierry",
    "sg:orig_category":"Unclassifiable Establishments",
    "sg:phone":"+33 3 23 83 87 00",
    "sg:province":"Picardie",
    "wof:name":"Lu S.a.",
    "wof:placetype":"venue"
},
  "geometry": {"coordinates":[3.402582,49.041435],"type":"Point"}
}