{
  "type": "Feature",
  "properties": {
    "iso:country":"FR",
    "sg:address":"92 Rue De Clery 75002 Paris",
    "sg:classifiers":[
        {
            "category":"Shopping",
            "subcategory":"Clothing, Apparel, & Fashions",
            "type":"Retail Goods"
        }
    ],
    "sg:phone":"+33 1 44 82 63 33",
    "sg:postcode":"75002",
    "sg:province":"Ile de France",
    "sg:tags":[
        "textile",
        "clothing",
        "clothes"
    ],
    "wof:name":"Mag",
    "wof:placetype":"venue"
},
  "geometry": {"coordinates":[2.351193,48.869343],"type":"Point"}
}