{
  "type": "Feature",
  "properties": {
    "addr:full":"56, Rue du Chemin de Fer, 59100 Roubaix Nord Pas-de-Calais",
    "addr:housenumber":"56",
    "addr:postcode":"59100",
    "addr:street":"Rue Du Chemin De Fer",
    "iso:country":"FR",
    "sg:address":"56, Rue du Chemin de Fer, 59100 Roubaix",
    "sg:orig_category":"Non-Classified Establishments",
    "sg:phone":"+33 3 20 76 11 16",
    "sg:province":"Nord Pas-de-Calais",
    "wof:name":"Vedior Bis Industrie",
    "wof:placetype":"venue"
},
  "geometry": {"coordinates":[3.163778,50.694542],"type":"Point"}
}