{
  "type": "Feature",
  "properties": {
    "iso:country":"FR",
    "sg:address":"Rte De Foug\u00e8res 49150 Chevir\u00e9 Le Rouge",
    "sg:classifiers":[
        {
            "category":"Home & Garden",
            "subcategory":"Furniture",
            "type":"Retail Goods"
        }
    ],
    "sg:phone":"+33 2 41 90 11 94",
    "sg:province":"Pays de Loire",
    "sg:tags":[
        "wood"
    ],
    "wof:name":"Eurotech Emballages Sarl",
    "wof:placetype":"venue"
},
  "geometry": {"coordinates":[-0.063909,47.46994],"type":"Point"}
}