{
  "type": "Feature",
  "properties": {
    "addr:full":"10 Chem De Vignes BP 1 91660 M\u00e9r\u00e9ville Ile de France",
    "addr:housenumber":"10;1",
    "addr:postcode":"91660;ile",
    "addr:street":"Chem De Vignes Bp",
    "iso:country":"FR",
    "sg:address":"10 Chem De Vignes BP 1 91660 M\u00e9r\u00e9ville",
    "sg:classifiers":[
        {
            "category":"Marine",
            "type":"Transportation"
        }
    ],
    "sg:phone":"+33 1 64 95 08 79",
    "sg:province":"Ile de France",
    "sg:tags":[
        "transport",
        "sea"
    ],
    "wof:name":"Probinord",
    "wof:placetype":"venue"
},
  "geometry": {"coordinates":[2.105688,48.317635],"type":"Point"}
}