{
  "type": "Feature",
  "properties": {
    "iso:country":"FR",
    "sg:address":"24, Rue Condorcet, 95150 Taverny",
    "sg:orig_category":"Unclassifiable Establishments",
    "sg:phone":"+33 1 30 40 74 10",
    "sg:province":"Ile de France",
    "wof:name":"S\u00e9curit\u00e9 Incendie Sia S.a.",
    "wof:placetype":"venue"
},
  "geometry": {"coordinates":[2.189701,49.028191],"type":"Point"}
}