{
  "type": "Feature",
  "properties": {
    "addr:full":"4 rue Charles Cros 95320 St Leu La For\u00eat Ile de France 95320",
    "addr:housenumber":"4",
    "addr:postcode":"95320;95320",
    "addr:street":"Rue Charles Cros;Ile;France",
    "iso:country":"FR",
    "sg:address":"4 rue Charles Cros 95320 St Leu La For\u00eat",
    "sg:classifiers":[
        {
            "category":"Conference Center",
            "type":"Public Place"
        }
    ],
    "sg:phone":"+33 1 34 18 79 80",
    "sg:postcode":"95320",
    "sg:province":"Ile de France",
    "sg:tags":[
        "presentation",
        "system",
        "audio-visual"
    ],
    "wof:name":"Challenge Partners",
    "wof:placetype":"venue"
},
  "geometry": {"coordinates":[2.249553,49.002209],"type":"Point"}
}