{
  "type": "Feature",
  "properties": {
    "addr:full":"305 Rue Giraudeau 37000 Tours Tours Centre 37000",
    "addr:housenumber":"305",
    "addr:postcode":"37000;37000",
    "addr:street":"Rue Giraudeau",
    "iso:country":"FR",
    "sg:address":"305 Rue Giraudeau 37000 Tours",
    "sg:city":"Tours",
    "sg:classifiers":[
        {
            "category":"Wholesale",
            "subcategory":"Medical Equipment & Supplies",
            "type":"Manufacturing & Wholesale Goods"
        }
    ],
    "sg:phone":"+33 2 47 39 65 47",
    "sg:postcode":"37000",
    "sg:province":"Centre",
    "sg:tags":[
        "instrument",
        "health",
        "-",
        "precision"
    ],
    "wof:name":"Ceram Pro",
    "wof:placetype":"venue"
},
  "geometry": {"coordinates":[0.677478,47.37664],"type":"Point"}
}