{
  "type": "Feature",
  "properties": {
    "addr:full":"5, Rue de l'Europe, 59000 Lille Nord Pas-de-Calais",
    "addr:housenumber":"5",
    "addr:postcode":"59000",
    "addr:street":"Rue De L'Europe",
    "iso:country":"FR",
    "sg:address":"5, Rue de l'Europe, 59000 Lille",
    "sg:orig_category":"Unclassifiable Establishments",
    "sg:phone":"+33 3 20 53 64 42",
    "sg:province":"Nord Pas-de-Calais",
    "wof:name":"Delebecque S.a.r.l.",
    "wof:placetype":"venue"
},
  "geometry": {"coordinates":[3.052155,50.613281],"type":"Point"}
}