{
  "type": "Feature",
  "properties": {
    "iso:country":"FR",
    "sg:address":"100 T Av Mouill\u00e8re 45100 Orleans",
    "sg:city":"Orl\u00e9ans",
    "sg:classifiers":[
        {
            "category":"Banks & Credit Unions",
            "subcategory":"Financial Services",
            "type":"Services"
        }
    ],
    "sg:phone":"+33 2 38 66 16 23",
    "sg:postcode":"45100",
    "sg:province":"Centre",
    "sg:tags":[
        "banking",
        "finance",
        "insurance"
    ],
    "wof:name":"Gan Vie Compagnie Francaise D'assurances Sur La Vie",
    "wof:placetype":"venue"
},
  "geometry": {"coordinates":[1.90874,47.88414],"type":"Point"}
}