{
  "type": "Feature",
  "properties": {
    "iso:country":"FR",
    "sg:address":"Rue Henri Potez Zone Industrielle 80300 Albert",
    "sg:classifiers":[
        {
            "category":"Professional",
            "subcategory":"Engineering",
            "type":"Services"
        }
    ],
    "sg:phone":"+33 3 22 75 31 06",
    "sg:postcode":"80300",
    "sg:province":"Picardie",
    "sg:tags":[
        "machine",
        "-",
        "mechanical"
    ],
    "wof:name":"Repmo Nord Picardie",
    "wof:placetype":"venue"
},
  "geometry": {"coordinates":[2.646825,50.00407],"type":"Point"}
}