{
  "type": "Feature",
  "properties": {
    "addr:full":"Le Poliveau 41400 Bourr\u00e9 Bourr\u00e9 Centre 41400",
    "addr:postcode":"41400;41400",
    "addr:street":"Bourre\u0301",
    "iso:country":"FR",
    "sg:address":"Le Poliveau 41400 Bourr\u00e9",
    "sg:city":"Bourr\u00e9",
    "sg:orig_category":"Unclassifiable Establishments",
    "sg:phone":"+33 2 54 71 66 00",
    "sg:postcode":"41400",
    "sg:province":"Centre",
    "wof:name":"Etablissements Guy Briand S.a.",
    "wof:placetype":"venue"
},
  "geometry": {"coordinates":[1.235801,47.356731],"type":"Point"}
}