{
  "type": "Feature",
  "properties": {
    "addr:full":"46 Rue La Boetie 75008 Paris Ile de France",
    "addr:housenumber":"46",
    "addr:postcode":"75008",
    "addr:street":"Rue La Boetie",
    "iso:country":"FR",
    "sg:address":"46 Rue La Boetie 75008 Paris",
    "sg:classifiers":[
        {
            "category":"Manufacturing",
            "subcategory":"Printing",
            "type":"Manufacturing & Wholesale Goods"
        }
    ],
    "sg:phone":"+33 1 42 89 14 43",
    "sg:province":"Ile de France",
    "sg:tags":[
        "publishing"
    ],
    "wof:name":"Imprimerie Bera",
    "wof:placetype":"venue"
},
  "geometry": {"coordinates":[2.313504,48.873634],"type":"Point"}
}