{
  "type": "Feature",
  "properties": {
    "iso:country":"FR",
    "sg:address":"9, Rue d'Escamin, 59780 Baisieux",
    "sg:orig_category":"Non-Classified Establishments",
    "sg:phone":"+33 3 20 84 06 60",
    "sg:province":"Nord Pas-de-Calais",
    "wof:name":"New Bags S.a.",
    "wof:placetype":"venue"
},
  "geometry": {"coordinates":[3.257413,50.612854],"type":"Point"}
}