{
  "type": "Feature",
  "properties": {
    "addr:full":"9, Rue d'Escamin, 59780 Baisieux Nord Pas-de-Calais",
    "addr:housenumber":"9",
    "addr:postcode":"59780",
    "addr:street":"Rue D'Escamin",
    "iso:country":"FR",
    "sg:address":"9, Rue d'Escamin, 59780 Baisieux",
    "sg:orig_category":"Non-Classified Establishments",
    "sg:phone":"+33 3 20 84 06 60",
    "sg:province":"Nord Pas-de-Calais",
    "wof:name":"New Bags S.a.",
    "wof:placetype":"venue"
},
  "geometry": {"coordinates":[3.257413,50.612854],"type":"Point"}
}