{
  "type": "Feature",
  "properties": {
    "iso:country":"FR",
    "sg:address":"Zae Ty Douar 29450 Commana",
    "sg:city":"Commana",
    "sg:classifiers":[
        {
            "category":"Wholesale",
            "subcategory":"Farm Supplies",
            "type":"Manufacturing & Wholesale Goods"
        }
    ],
    "sg:phone":"+33 2 98 78 92 34",
    "sg:postcode":"29450",
    "sg:province":"Bretagne",
    "sg:tags":[
        "-",
        "machine",
        "equipment",
        "engineering",
        "machinery",
        "mechanical",
        "agriculture"
    ],
    "wof:name":"Sparex",
    "wof:placetype":"venue"
},
  "geometry": {"coordinates":[-3.969694,48.412231],"type":"Point"}
}