{
  "type": "Feature",
  "properties": {
    "iso:country":"FR",
    "sg:address":"24, Rue des Ingrains, 36022 Ch\u00e2teauroux C\u00e9dex",
    "sg:orig_category":"Non-Classified Establishments",
    "sg:phone":"+33 2 54 29 20 00",
    "sg:province":"Languedoc-Roussillon",
    "wof:name":"C\u00e9cogefi",
    "wof:placetype":"venue"
},
  "geometry": {"coordinates":[1.713001,46.794319],"type":"Point"}
}