{
  "type": "Feature",
  "properties": {
    "addr:full":"1 bis, Chemin du Buisson Gu\u00e9rin, 78750 Mareil Marly Ile de France 78750",
    "addr:housenumber":"1 bis",
    "addr:postcode":"78750;78750",
    "addr:street":"Chemin Du Buisson Gue\u0301Rin",
    "iso:country":"FR",
    "sg:address":"1 bis, Chemin du Buisson Gu\u00e9rin, 78750 Mareil Marly",
    "sg:orig_category":"Non-Classified Establishments",
    "sg:phone":"+33 1 30 61 42 46",
    "sg:postcode":"78750",
    "sg:province":"Ile de France",
    "wof:name":"Bavaria France S.a.r.l.",
    "wof:placetype":"venue"
},
  "geometry": {"coordinates":[2.07532,48.88649],"type":"Point"}
}