{
  "type": "Feature",
  "properties": {
    "iso:country":"FR",
    "sg:address":"rue de la Bauve 77100 Meaux",
    "sg:classifiers":[
        {
            "category":"Wholesale",
            "subcategory":"Painting Supplies",
            "type":"Manufacturing & Wholesale Goods"
        }
    ],
    "sg:phone":"+33 1 64 36 54 54",
    "sg:postcode":"77100",
    "sg:province":"Ile de France",
    "sg:tags":[
        "paint",
        "industrial"
    ],
    "wof:name":"Cie Applica Chimique A L'industrie S.a.",
    "wof:placetype":"venue"
},
  "geometry": {"coordinates":[2.905512,48.963383],"type":"Point"}
}