{
  "type": "Feature",
  "properties": {
    "addr:full":"182, Bd de Brou, 01000 Bourg en Bresse Rhone-Alpes",
    "addr:housenumber":"182",
    "addr:postcode":"01000",
    "addr:street":"Bd De Brou",
    "iso:country":"FR",
    "sg:address":"182, Bd de Brou, 01000 Bourg en Bresse",
    "sg:orig_category":"Non-Classified Establishments",
    "sg:phone":"+33 4 74 23 20 24",
    "sg:province":"Rhone-Alpes",
    "wof:name":"Jard'ain Loisirs Mainaud S.a.r.l.",
    "wof:placetype":"venue"
},
  "geometry": {"coordinates":[5.236761,46.195999],"type":"Point"}
}