{
  "type": "Feature",
  "properties": {
    "iso:country":"FR",
    "sg:address":"58, Av de Flandre, 59290 Wasquehal",
    "sg:orig_category":"Unclassifiable Establishments",
    "sg:phone":"+33 3 20 65 72 72",
    "sg:province":"Nord Pas-de-Calais",
    "wof:name":"Phonecco S.a.",
    "wof:placetype":"venue"
},
  "geometry": {"coordinates":[3.124593,50.663857],"type":"Point"}
}