{
  "type": "Feature",
  "properties": {
    "iso:country":"FR",
    "sg:address":"Bel Air Za 81230 Lacaune",
    "sg:classifiers":[
        {
            "category":"Farming",
            "subcategory":"Farm & Veterinary Services",
            "type":"Manufacturing & Wholesale Goods"
        }
    ],
    "sg:phone":"+33 5 63 37 02 51",
    "sg:postcode":"81230",
    "sg:province":"Midi Pyr\u00e9n\u00e9es",
    "sg:tags":[
        "pharmaceutical",
        "livestock",
        "-",
        "chemical",
        "animal",
        "breeding",
        "chemistry",
        "agriculture",
        "by-product"
    ],
    "wof:name":"Ragt",
    "wof:placetype":"venue"
},
  "geometry": {"coordinates":[2.706357,43.712364],"type":"Point"}
}