{
  "type": "Feature",
  "properties": {
    "addr:full":"Rue Nicolas Copernic 81000 Albi Midi Pyr\u00e9n\u00e9es",
    "addr:postcode":"81000",
    "addr:street":"Rue Nicolas Copernic",
    "iso:country":"FR",
    "sg:address":"Rue Nicolas Copernic 81000 Albi",
    "sg:classifiers":[
        {
            "category":"Professional",
            "type":"Services"
        }
    ],
    "sg:phone":"+33 5 63 49 19 49",
    "sg:province":"Midi Pyr\u00e9n\u00e9es",
    "sg:tags":[
        "transport",
        "road"
    ],
    "wof:name":"Transports Georges Andrieu Sa",
    "wof:placetype":"venue"
},
  "geometry": {"coordinates":[2.093807,43.918056],"type":"Point"}
}