{
  "type": "Feature",
  "properties": {
    "addr:full":"B.P. 93, 39203 Saint Claude C\u00e9dex^^ZA Etables - Usine du Barrage , 39200 Saint Claude Franche Comt\u00e9",
    "addr:postcode":"39203;39200",
    "addr:street":"B.P. 93;Etables;Saint Claude Franche Comte\u0301",
    "iso:country":"FR",
    "sg:address":"B.P. 93, 39203 Saint Claude C\u00e9dex^^ZA Etables - Usine du Barrage , 39200 Saint Claude",
    "sg:orig_category":"Non-Classified Establishments",
    "sg:phone":"+33 3 84 45 13 72",
    "sg:province":"Franche Comt\u00e9",
    "wof:name":"Pierre Vaux S.a.",
    "wof:placetype":"venue"
},
  "geometry": {"coordinates":[5.820055,46.380642],"type":"Point"}
}