{
  "type": "Feature",
  "properties": {
    "iso:country":"FR",
    "sg:address":"B.P. 4101, 38941 Meylan C\u00e9dex^^39, Chemin du Vieux Ch\u00eane, 38240 Meylan",
    "sg:orig_category":"Non-Classified Establishments",
    "sg:phone":"+33 4 76 90 04 74",
    "sg:province":"Rhone-Alpes",
    "wof:name":"Pixel Pro S.a.r.l.",
    "wof:placetype":"venue"
},
  "geometry": {"coordinates":[5.77846,45.209316],"type":"Point"}
}