{
  "type": "Feature",
  "properties": {
    "addr:full":"32, Rue Caravelle, 31500 Toulouse Midi Pyr\u00e9n\u00e9es",
    "addr:housenumber":"32",
    "addr:postcode":"31500",
    "addr:street":"Rue Caravelle",
    "iso:country":"FR",
    "sg:address":"32, Rue Caravelle, 31500 Toulouse",
    "sg:orig_category":"Non-Classified Establishments",
    "sg:phone":"+33 5 34 25 46 70",
    "sg:province":"Midi Pyr\u00e9n\u00e9es",
    "wof:name":"Uunet France S.a.",
    "wof:placetype":"venue"
},
  "geometry": {"coordinates":[1.462624,43.617092],"type":"Point"}
}