{
  "type": "Feature",
  "properties": {
    "addr:full":"181 avenue des Trois Provinces 49300 Cholet Pays de Loire 49300",
    "addr:housenumber":"181",
    "addr:postcode":"49300;49300",
    "addr:street":"Avenue Des Trois Provinces",
    "iso:country":"FR",
    "sg:address":"181 avenue des Trois Provinces 49300 Cholet",
    "sg:classifiers":[
        {
            "category":"Manufacturing",
            "subcategory":"Chemicals & Compounds",
            "type":"Manufacturing & Wholesale Goods"
        }
    ],
    "sg:phone":"+33 2 41 75 20 80",
    "sg:postcode":"49300",
    "sg:province":"Pays de Loire",
    "sg:tags":[
        "fodder",
        "concentrate",
        "mineral",
        "protein",
        "mixtures"
    ],
    "wof:name":"S.c.d. Chauveau Sa",
    "wof:placetype":"venue"
},
  "geometry": {"coordinates":[-0.933059,47.060089],"type":"Point"}
}