{
  "type": "Feature",
  "properties": {
    "iso:country":"FR",
    "sg:address":"ZAE Tanes Basses",
    "sg:city":"Clermont l'H\u00e9rault",
    "sg:orig_category":"Unclassifiable Establishments",
    "sg:phone":"+33 4 67 96 22 63",
    "sg:postcode":"34800",
    "sg:province":"Languedoc-Roussillon",
    "wof:name":"Midi Etiquettes S.a.r.l.",
    "wof:placetype":"venue"
},
  "geometry": {"coordinates":[3.43383,43.626781],"type":"Point"}
}