{
  "type": "Feature",
  "properties": {
    "iso:country":"FR",
    "sg:address":"Orly Fret 711 Aerogare de Fret 94548 ORLY AEROGARE CEDEX",
    "sg:orig_category":"Heliports",
    "sg:phone":"+33 1 49 75 32 77",
    "sg:province":"Ile de France",
    "wof:name":"Promotion France Exportation",
    "wof:placetype":"venue"
},
  "geometry": {"coordinates":[2.40116,48.742931],"type":"Point"}
}