{
  "type": "Feature",
  "properties": {
    "addr:full":"104 Av Du G\u00e9n\u00e9ral Leclerc 69300 Caluire Et Cuire Rhone-Alpes 69300",
    "addr:postcode":"69300;69300",
    "addr:street":"104 Av Du Ge\u0301Ne\u0301Ral Leclerc",
    "iso:country":"FR",
    "sg:address":"104 Av Du G\u00e9n\u00e9ral Leclerc 69300 Caluire Et Cuire",
    "sg:classifiers":[
        {
            "category":"Professional",
            "subcategory":"Advertising",
            "type":"Services"
        }
    ],
    "sg:phone":"+33 4 72 27 13 95",
    "sg:postcode":"69300",
    "sg:province":"Rhone-Alpes",
    "sg:tags":[
        "communication",
        "medium"
    ],
    "wof:name":"Publicite Decor Sa",
    "wof:placetype":"venue"
},
  "geometry": {"coordinates":[4.867814,45.806465],"type":"Point"}
}