{
  "type": "Feature",
  "properties": {
    "addr:full":"15, Av. de Saint Cloud, 78000 Versailles Ile de France",
    "addr:postcode":"78000",
    "addr:street":"15 Av. De Saint Cloud",
    "iso:country":"FR",
    "sg:address":"15, Av. de Saint Cloud, 78000 Versailles",
    "sg:orig_category":"Unclassifiable Establishments",
    "sg:phone":"+33 1 39 20 13 22",
    "sg:province":"Ile de France",
    "wof:name":"Micronix S.a.",
    "wof:placetype":"venue"
},
  "geometry": {"coordinates":[2.129532,48.805248],"type":"Point"}
}