{
  "type": "Feature",
  "properties": {
    "addr:full":"49, Rue du Village, 59244 Petit Fayt Nord Pas-de-Calais",
    "addr:housenumber":"49",
    "addr:postcode":"59244",
    "addr:street":"Rue Du Village;Fayt Nord",
    "iso:country":"FR",
    "sg:address":"49, Rue du Village, 59244 Petit Fayt",
    "sg:orig_category":"Unclassifiable Establishments",
    "sg:phone":"+33 3 27 56 10 17",
    "sg:province":"Nord Pas-de-Calais",
    "wof:name":"Laiterie Catillonnaise S.a.",
    "wof:placetype":"venue"
},
  "geometry": {"coordinates":[3.814052,50.109409],"type":"Point"}
}