{
  "type": "Feature",
  "properties": {
    "iso:country":"FR",
    "sg:address":"60 rue Ingres 33220 PINEUILH",
    "sg:city":"Pineuilh",
    "sg:classifiers":[
        {
            "category":"Professional",
            "subcategory":"Art Services",
            "type":"Services"
        }
    ],
    "sg:phone":"+33 5 57 46 46 06",
    "sg:postcode":"33220",
    "sg:province":"Aquitaine",
    "sg:tags":[
        "product",
        "design"
    ],
    "wof:name":"Mineral Color S.a.r.l.",
    "wof:placetype":"venue"
},
  "geometry": {"coordinates":[0.243544,44.85157],"type":"Point"}
}