{
  "type": "Feature",
  "properties": {
    "addr:full":"1, Rue Marcel Sallnave, 94200 Ivry sur Seine Ile de France",
    "addr:housenumber":"1",
    "addr:postcode":"94200",
    "addr:street":"Rue Marcel Sallnave",
    "iso:country":"FR",
    "sg:address":"1, Rue Marcel Sallnave, 94200 Ivry sur Seine",
    "sg:orig_category":"Unclassifiable Establishments",
    "sg:phone":"+33 1 46 58 92 92",
    "sg:province":"Ile de France",
    "wof:name":"Ouest Isol S.a.",
    "wof:placetype":"venue"
},
  "geometry": {"coordinates":[2.405835,48.814884],"type":"Point"}
}