{
  "type": "Feature",
  "properties": {
    "iso:country":"FR",
    "sg:address":"36/38, Rte de la Princesse, 78432 Louveciennes C\u00e9dex",
    "sg:orig_category":"Non-Classified Establishments",
    "sg:phone":"+33 1 30 78 48 47",
    "sg:province":"Lorraine",
    "wof:name":"Cise Maintenance S.a.",
    "wof:placetype":"venue"
},
  "geometry": {"coordinates":[2.112504,48.861568],"type":"Point"}
}