{
  "type": "Feature",
  "properties": {
    "iso:country":"FR",
    "sg:address":"Rue du G\u00e9n\u00e9ral Bradley et Rte de Saint Nazaire - ZI",
    "sg:city":"Ch\u00e2teaubriant",
    "sg:orig_category":"Unclassifiable Establishments",
    "sg:phone":"+33 2 40 81 83 03",
    "sg:postcode":"44110",
    "sg:province":"Pays de Loire",
    "wof:name":"Pr\u00e9cifil S.a.",
    "wof:placetype":"venue"
},
  "geometry": {"coordinates":[-1.317649,47.655094],"type":"Point"}
}