{
  "type": "Feature",
  "properties": {
    "addr:full":"B.P. 71, 10303 Sainte Savine C\u00e9dex^^172, Av du G\u00e9n\u00e9ral Leclerc, 10300 Sainte Savine Champagne",
    "addr:postcode":"10303;10300",
    "addr:street":"B.P. 71;Av Du Ge\u0301Ne\u0301Ral Leclerc",
    "iso:country":"FR",
    "sg:address":"B.P. 71, 10303 Sainte Savine C\u00e9dex^^172, Av du G\u00e9n\u00e9ral Leclerc, 10300 Sainte Savine",
    "sg:orig_category":"Non-Classified Establishments",
    "sg:phone":"+33 3 25 71 13 00",
    "sg:province":"Champagne",
    "wof:name":"Val\u00e9o Electronique S.a.s.",
    "wof:placetype":"venue"
},
  "geometry": {"coordinates":[4.056065,48.292885],"type":"Point"}
}