{
  "type": "Feature",
  "properties": {
    "addr:full":"100, Av. Albert Premier, 92500 Rueil Malmaison Ile de France",
    "addr:postcode":"92500",
    "addr:street":"100 Av. Albert Premier",
    "iso:country":"FR",
    "sg:address":"100, Av. Albert Premier, 92500 Rueil Malmaison",
    "sg:orig_category":"Non-Classified Establishments",
    "sg:phone":"+33 1 47 52 39 90",
    "sg:province":"Ile de France",
    "wof:name":"Soci\u00e9t\u00e9 Nationale D'electricit\u00e9 Et De Thermique S.a.",
    "wof:placetype":"venue"
},
  "geometry": {"coordinates":[2.171909,48.88567],"type":"Point"}
}