{
  "type": "Feature",
  "properties": {
    "addr:full":"B.P. 40,^^75, Rte de Lyon, 73160 Cognin Rhone-Alpes 73160",
    "addr:housenumber":"^ 75",
    "addr:postcode":"73160;73160",
    "addr:street":"B.P. 40 ^;Rte De Lyon;Rhone-Alpes",
    "iso:country":"FR",
    "sg:address":"B.P. 40,^^75, Rte de Lyon, 73160 Cognin",
    "sg:orig_category":"Non-Classified Establishments",
    "sg:phone":"+33 4 79 69 57 28",
    "sg:postcode":"73160",
    "sg:province":"Rhone-Alpes",
    "wof:name":"S.t.a.r. S.a.r.l. - Soci\u00e9t\u00e9 Technique Agricoles Routi\u00e8res",
    "wof:placetype":"venue"
},
  "geometry": {"coordinates":[5.823435,45.429111],"type":"Point"}
}