{
  "type": "Feature",
  "properties": {
    "addr:full":"2 Bd Fromenteau 72510 Mansign\u00e9 Pays de Loire 72510",
    "addr:housenumber":"2",
    "addr:postcode":"72510;72510",
    "addr:street":"Bd Fromenteau",
    "iso:country":"FR",
    "sg:address":"2 Bd Fromenteau 72510 Mansign\u00e9",
    "sg:classifiers":[
        {
            "category":"Professional",
            "subcategory":"Engineering",
            "type":"Services"
        }
    ],
    "sg:phone":"+33 2 43 46 15 96",
    "sg:postcode":"72510",
    "sg:province":"Pays de Loire",
    "sg:tags":[
        "machine",
        "-",
        "mechanical"
    ],
    "wof:name":"Cathild Industrie",
    "wof:placetype":"venue"
},
  "geometry": {"coordinates":[0.136317,47.749218],"type":"Point"}
}