{
  "type": "Feature",
  "properties": {
    "iso:country":"FR",
    "sg:address":"1, Rue du Tertre, 25580 Etalans",
    "sg:orig_category":"Non-Classified Establishments",
    "sg:phone":"+33 3 81 59 23 65",
    "sg:province":"Franche Comt\u00e9",
    "wof:name":"Vieille S.a.r.l.",
    "wof:placetype":"venue"
},
  "geometry": {"coordinates":[6.265075,47.156288],"type":"Point"}
}