{
  "type": "Feature",
  "properties": {
    "addr:full":"16, Rue des Entrepreneurs, 86000 Poitiers Poitou-Charentes",
    "addr:housenumber":"16",
    "addr:postcode":"86000",
    "addr:street":"Rue Des Entrepreneurs",
    "iso:country":"FR",
    "sg:address":"16, Rue des Entrepreneurs, 86000 Poitiers",
    "sg:orig_category":"Unclassifiable Establishments",
    "sg:phone":"+33 5 49 37 86 70",
    "sg:province":"Poitou-Charentes",
    "wof:name":"Transitec S.a.",
    "wof:placetype":"venue"
},
  "geometry": {"coordinates":[0.345025,46.616127],"type":"Point"}
}