{
  "type": "Feature",
  "properties": {
    "iso:country":"FR",
    "sg:address":"23 rue du G\u00e9n\u00e9ral Leclerc; Cosne; 58200",
    "sg:city":"Cosne-Cours-sur-Loire",
    "sg:classifiers":[
        {
            "category":"Banks & Credit Unions",
            "subcategory":"Bank",
            "type":"Services"
        }
    ],
    "sg:phone":"+33 3386281555",
    "sg:postcode":"58200",
    "sg:province":"Bourgogne",
    "wof:name":"Soci\u00e9t\u00e9 G\u00e9n\u00e9rale",
    "wof:placetype":"venue"
},
  "geometry": {"coordinates":[2.901115,47.369862],"type":"Point"}
}