{
  "type": "Feature",
  "properties": {
    "addr:full":"198, Av. de verdun, 92130 Issy les Moulineaux Ile de France",
    "addr:postcode":"92130",
    "addr:street":"198 Av. De Verdun",
    "iso:country":"FR",
    "sg:address":"198, Av. de verdun, 92130 Issy les Moulineaux",
    "sg:orig_category":"Non-Classified Establishments",
    "sg:phone":"+33 1 46 42 90 76",
    "sg:province":"Ile de France",
    "wof:name":"Techn-o Tape France S.a.r.l.",
    "wof:placetype":"venue"
},
  "geometry": {"coordinates":[2.245576,48.81855],"type":"Point"}
}