{
  "type": "Feature",
  "properties": {
    "iso:country":"FR",
    "sg:address":"rue Maurice Caullery 59500 Douai",
    "sg:classifiers":[
        {
            "category":"Organizations",
            "subcategory":"Non-profit Organization",
            "type":"Services"
        }
    ],
    "sg:phone":"+33 3 27 94 37 70",
    "sg:postcode":"59500",
    "sg:province":"Nord Pas-de-Calais",
    "sg:tags":[
        "industrial",
        "system",
        "hydraulic"
    ],
    "wof:name":"Cinor Sa",
    "wof:placetype":"venue"
},
  "geometry": {"coordinates":[3.092725,50.393188],"type":"Point"}
}