{
  "type": "Feature",
  "properties": {
    "addr:full":"B.P. 104, 26501 Bourg l\u00e8s Valence C\u00e9dex^^150, Rte de Lyon, 26500 Bourg l\u00e8s Valence Rhone-Alpes 26500",
    "addr:housenumber":"b.p. 104",
    "addr:postcode":"26501;26500;26500",
    "addr:street":"Rte De Lyon",
    "iso:country":"FR",
    "sg:address":"B.P. 104, 26501 Bourg l\u00e8s Valence C\u00e9dex^^150, Rte de Lyon, 26500 Bourg l\u00e8s Valence",
    "sg:orig_category":"Non-Classified Establishments",
    "sg:phone":"+33 4 75 82 20 20",
    "sg:postcode":"26500",
    "sg:province":"Rhone-Alpes",
    "wof:name":"S.p.i.t. S.a.s. - Soci\u00e9t\u00e9 De Prospection Et D'invention Technique",
    "wof:placetype":"venue"
},
  "geometry": {"coordinates":[4.893225,44.947048],"type":"Point"}
}