{
  "type": "Feature",
  "properties": {
    "addr:full":"4 Allee Des Cityses 04400 Barcelonnette Limousin",
    "addr:housenumber":"4",
    "addr:postcode":"04400",
    "addr:street":"Allee Des Cityses",
    "iso:country":"FR",
    "sg:address":"4 Allee Des Cityses 04400 Barcelonnette",
    "sg:classifiers":[
        {
            "category":"Home & Garden",
            "subcategory":"Furniture",
            "type":"Retail Goods"
        }
    ],
    "sg:phone":"+33 4 92 81 03 69",
    "sg:province":"Limousin",
    "sg:tags":[
        "wood"
    ],
    "wof:name":"Meubles De L Ubaye",
    "wof:placetype":"venue"
},
  "geometry": {"coordinates":[6.646104,44.376472],"type":"Point"}
}