{
  "type": "Feature",
  "properties": {
    "addr:full":"27, Bd Charles Moretti, 13014 Marseille Poitou-Charentes",
    "addr:housenumber":"27",
    "addr:postcode":"13014",
    "addr:street":"Bd Charles Moretti",
    "iso:country":"FR",
    "sg:address":"27, Bd Charles Moretti, 13014 Marseille",
    "sg:orig_category":"Unclassifiable Establishments",
    "sg:phone":"+33 4 91 98 56 33",
    "sg:province":"Poitou-Charentes",
    "wof:name":"J.r.b. Diffusion S.a.r.l.",
    "wof:placetype":"venue"
},
  "geometry": {"coordinates":[5.377054,43.326206],"type":"Point"}
}