{
  "type": "Feature",
  "properties": {
    "iso:country":"FR",
    "sg:address":"36 avenue de Bobigny 93130 Noisy le Sec",
    "sg:classifiers":[
        {
            "category":"Government",
            "subcategory":"Post Office",
            "type":"Public Place"
        }
    ],
    "sg:phone":"+33 1 48 10 32 40",
    "sg:postcode":"93130",
    "sg:province":"Ile de France",
    "sg:tags":[
        "blade",
        "saw",
        "circular"
    ],
    "wof:name":"Chaland Et Fils S.a.",
    "wof:placetype":"venue"
},
  "geometry": {"coordinates":[2.450583,48.893513],"type":"Point"}
}