{
  "type": "Feature",
  "properties": {
    "iso:country":"FR",
    "sg:address":"51 Rue De La Poterne 77620 Egreville",
    "sg:classifiers":[
        {
            "category":"Manufacturing",
            "subcategory":"Metals",
            "type":"Manufacturing & Wholesale Goods"
        }
    ],
    "sg:phone":"+33 1 64 45 52 05",
    "sg:postcode":"77620",
    "sg:province":"Ile de France",
    "sg:tags":[
        "metallurgy",
        "steel",
        "metalworking"
    ],
    "wof:name":"Est Roger Sa",
    "wof:placetype":"venue"
},
  "geometry": {"coordinates":[2.87565,48.176941],"type":"Point"}
}