{
  "type": "Feature",
  "properties": {
    "iso:country":"FR",
    "sg:address":"20 mail Joliot-Curie 95310 St Ouen l'Aumone",
    "sg:classifiers":[
        {
            "category":"Building & Trades",
            "subcategory":"Construction",
            "type":"Services"
        }
    ],
    "sg:phone":"+33 1 30 37 64 85",
    "sg:province":"Ile de France",
    "sg:tags":[
        "turning",
        "vertical"
    ],
    "wof:name":"Rafix Sa",
    "wof:placetype":"venue"
},
  "geometry": {"coordinates":[-120.396912,38.051048],"type":"Point"}
}