{
  "type": "Feature",
  "properties": {
    "addr:full":"Rue Paroveix Pontaumur Auvergne 63380",
    "addr:postcode":"63380",
    "addr:street":"Rue Paroveix Pontaumur",
    "iso:country":"FR",
    "sg:address":"Rue Paroveix",
    "sg:city":"Pontaumur",
    "sg:orig_category":"Non-Classified Establishments",
    "sg:phone":"+33 4 73 79 90 23",
    "sg:postcode":"63380",
    "sg:province":"Auvergne",
    "wof:name":"S.i.a. S.a. - Soci\u00e9t\u00e9 Industrielle Arvemmoise",
    "wof:placetype":"venue"
},
  "geometry": {"coordinates":[2.663085,45.813347],"type":"Point"}
}