{
  "type": "Feature",
  "properties": {
    "iso:country":"FR",
    "sg:address":"B.P. 35, 37230 Fondettes Cedex^^44 bis, Rue de la R\u00e9publique, 37230 Fondettes",
    "sg:city":"Fondettes",
    "sg:orig_category":"Non-Classified Establishments",
    "sg:phone":"+33 2 47 42 23 68",
    "sg:postcode":"37230",
    "sg:province":"Centre",
    "wof:name":"D.b.m Publicit\u00e9 S.a.r.l.",
    "wof:placetype":"venue"
},
  "geometry": {"coordinates":[0.516665,47.370476],"type":"Point"}
}