{
  "type": "Feature",
  "properties": {
    "addr:full":"234, Av. du G\u00e9n\u00e9ral Leclerc, 61000 Alen\u00e7on Alen\u00e7on Basse Normandie 61000",
    "addr:postcode":"61000;61000",
    "addr:street":"234 Av. Du Ge\u0301Ne\u0301Ral Leclerc",
    "iso:country":"FR",
    "sg:address":"234, Av. du G\u00e9n\u00e9ral Leclerc, 61000 Alen\u00e7on",
    "sg:city":"Alen\u00e7on",
    "sg:orig_category":"Non-Classified Establishments",
    "sg:phone":"+33 2 33 27 80 50",
    "sg:postcode":"61000",
    "sg:province":"Basse Normandie",
    "wof:name":"Audoin S.a.",
    "wof:placetype":"venue"
},
  "geometry": {"coordinates":[0.083175,48.430626],"type":"Point"}
}