{
  "type": "Feature",
  "properties": {
    "addr:full":"1, All\u00e9e de Coubron, 93390 Clichy sous Bois Ile de France 93390",
    "addr:housenumber":"1",
    "addr:postcode":"93390;93390",
    "addr:street":"Alle\u0301E De Coubron;Bois Ile De France",
    "iso:country":"FR",
    "sg:address":"1, All\u00e9e de Coubron, 93390 Clichy sous Bois",
    "sg:orig_category":"Non-Classified Establishments",
    "sg:phone":"+33 1 45 09 12 12",
    "sg:postcode":"93390",
    "sg:province":"Ile de France",
    "wof:name":"Acmos France S.a.r.l.",
    "wof:placetype":"venue"
},
  "geometry": {"coordinates":[2.549998,48.911888],"type":"Point"}
}