{
  "type": "Feature",
  "properties": {
    "addr:full":"29 boulevard Edgar Quinet 92700 Colombes Ile de France",
    "addr:housenumber":"29",
    "addr:postcode":"92700;ile",
    "addr:street":"Boulevard Edgar Quinet",
    "iso:country":"FR",
    "sg:address":"29 boulevard Edgar Quinet 92700 Colombes",
    "sg:classifiers":[
        {
            "category":"Home & Garden",
            "subcategory":"Carpets & Floor Coverings",
            "type":"Retail Goods"
        }
    ],
    "sg:phone":"+33 1 47 82 27 89",
    "sg:province":"Ile de France",
    "sg:tags":[
        "blind",
        "roller"
    ],
    "wof:name":"Ageda S.a.r.l.",
    "wof:placetype":"venue"
},
  "geometry": {"coordinates":[2.247048,48.925438],"type":"Point"}
}