{
  "type": "Feature",
  "properties": {
    "addr:full":"26, Av. Henri Barbusse - Z.I. Les Vignes, 93012 Bobigny C\u00e9dex \u00cele-de-France",
    "addr:postcode":"93012",
    "addr:street":"26 Av. Henri Barbusse;Les Vignes;Ce\u0301Dex",
    "iso:country":"FR",
    "sg:address":"26, Av. Henri Barbusse - Z.I. Les Vignes, 93012 Bobigny C\u00e9dex",
    "sg:orig_category":"Unclassifiable Establishments",
    "sg:phone":"+33 1 49 15 21 09",
    "sg:province":"\u00cele-de-France",
    "wof:name":"Tech Data France S.n.c.",
    "wof:placetype":"venue"
},
  "geometry": {"coordinates":[2.44049,48.906429],"type":"Point"}
}