{
  "type": "Feature",
  "properties": {
    "addr:full":"31, Rue Paul Lafargue, 59100 Roubaix Nord Pas-de-Calais",
    "addr:housenumber":"31",
    "addr:postcode":"59100",
    "addr:street":"Rue Paul Lafargue",
    "iso:country":"FR",
    "sg:address":"31, Rue Paul Lafargue, 59100 Roubaix",
    "sg:orig_category":"Unclassifiable Establishments",
    "sg:phone":"+33 3 20 69 09 59",
    "sg:province":"Nord Pas-de-Calais",
    "wof:name":"Lecocq S.a.",
    "wof:placetype":"venue"
},
  "geometry": {"coordinates":[3.171792,50.675694],"type":"Point"}
}