{
  "type": "Feature",
  "properties": {
    "addr:full":"3, Rue de Villers en Cauchies, 59198 Haspres Nord Pas-de-Calais",
    "addr:housenumber":"3",
    "addr:postcode":"59198",
    "addr:street":"Rue De Villers En Cauchies",
    "iso:country":"FR",
    "sg:address":"3, Rue de Villers en Cauchies, 59198 Haspres",
    "sg:orig_category":"Unclassifiable Establishments",
    "sg:phone":"+33 3 27 25 79 90",
    "sg:province":"Nord Pas-de-Calais",
    "wof:name":"Cobelak France S.a.",
    "wof:placetype":"venue"
},
  "geometry": {"coordinates":[3.41044,50.245094],"type":"Point"}
}