{
  "type": "Feature",
  "properties": {
    "iso:country":"FR",
    "sg:address":"Bd Des Alouettes 62160 Bully Les Mines",
    "sg:classifiers":[
        {
            "category":"Banks & Credit Unions",
            "subcategory":"Investment Brokerage",
            "type":"Services"
        }
    ],
    "sg:phone":"+33 3 21 45 39 24",
    "sg:province":"Nord Pas-de-Calais",
    "sg:tags":[
        "-",
        "transport",
        "related"
    ],
    "wof:name":"Relais Frigorifique A21 Sa",
    "wof:placetype":"venue"
},
  "geometry": {"coordinates":[2.735715,50.442966],"type":"Point"}
}