{
  "type": "Feature",
  "properties": {
    "addr:full":"B.P. 130 Saumur C\u00e9dex Franche Comt\u00e9 49404",
    "addr:housenumber":"b.p. 130",
    "addr:postcode":"49404",
    "addr:street":"Franche Comte\u0301",
    "iso:country":"FR",
    "sg:address":"B.P. 130",
    "sg:city":"Saumur C\u00e9dex",
    "sg:orig_category":"Non-Classified Establishments",
    "sg:phone":"+33 2 41 40 42 00",
    "sg:postcode":"49404",
    "sg:province":"Franche Comt\u00e9",
    "wof:name":"Vogel M\u00e9cafluid S.a.",
    "wof:placetype":"venue"
},
  "geometry": {"coordinates":[-0.079319,47.259766],"type":"Point"}
}