{
  "type": "Feature",
  "properties": {
    "iso:country":"FR",
    "sg:address":"Centre du Bois des Bordes",
    "sg:city":"Br\u00e9tigny sur Orge",
    "sg:orig_category":"Unclassifiable Establishments",
    "sg:phone":"+33 1 69 88 52 00",
    "sg:postcode":"91220",
    "sg:province":"Ile de France",
    "wof:name":"Parcomatic S.a.",
    "wof:placetype":"venue"
},
  "geometry": {"coordinates":[2.30564,48.604824],"type":"Point"}
}