{
  "type": "Feature",
  "properties": {
    "addr:full":"66, Chemin de Melerat, 18500 Mehun sur Y\u00e8vre Marmagne Centre 18500",
    "addr:housenumber":"66",
    "addr:postcode":"18500;18500",
    "addr:street":"Chemin De Melerat",
    "iso:country":"FR",
    "sg:address":"66, Chemin de Melerat, 18500 Mehun sur Y\u00e8vre",
    "sg:city":"Marmagne",
    "sg:orig_category":"Unclassifiable Establishments",
    "sg:phone":"+33 2 48 57 46 92",
    "sg:postcode":"18500",
    "sg:province":"Centre",
    "wof:name":"G.attefin S.a.",
    "wof:placetype":"venue"
},
  "geometry": {"coordinates":[2.230509,47.144096],"type":"Point"}
}