{
  "type": "Feature",
  "properties": {
    "iso:country":"FR",
    "sg:address":"62 rue Pierre Curie 78130 Les Mureaux",
    "sg:classifiers":[
        {
            "category":"Bars & Pubs",
            "subcategory":"Lounge",
            "type":"Food & Drink"
        }
    ],
    "sg:phone":"+33 1 34 74 39 00",
    "sg:province":"Ile de France",
    "sg:tags":[
        "squab",
        "cushion"
    ],
    "wof:name":"Federale Mogul Tlc S.a.",
    "wof:placetype":"venue"
},
  "geometry": {"coordinates":[1.925242,48.994522],"type":"Point"}
}