{
  "type": "Feature",
  "properties": {
    "addr:full":"21 Rue Charles Didier 08000 Charleville Charleville-M\u00e9zi\u00e8res Champagne 08000",
    "addr:housenumber":"21",
    "addr:postcode":"08000;08000",
    "addr:street":"Rue Charles Didier",
    "iso:country":"FR",
    "sg:address":"21 Rue Charles Didier 08000 Charleville",
    "sg:city":"Charleville-M\u00e9zi\u00e8res",
    "sg:classifiers":[
        {
            "category":"Banks & Credit Unions",
            "subcategory":"Investment Brokerage",
            "type":"Services"
        }
    ],
    "sg:phone":"+33 3 24 57 05 22",
    "sg:postcode":"08000",
    "sg:province":"Champagne",
    "sg:tags":[
        "-",
        "transport",
        "related"
    ],
    "wof:name":"Ardennes Express Pasquier Sarl",
    "wof:placetype":"venue"
},
  "geometry": {"coordinates":[4.7174,49.758801],"type":"Point"}
}