{
  "type": "Feature",
  "properties": {
    "addr:full":"23 Bis Avenue Europe Chatou Ile de France 78400",
    "addr:housenumber":"23 bis",
    "addr:postcode":"78400",
    "addr:street":"Avenue;Ile De France",
    "iso:country":"FR",
    "sg:address":"23 Bis Avenue Europe",
    "sg:city":"Chatou",
    "sg:classifiers":[
        {
            "category":"Banks & Credit Unions",
            "subcategory":"Financial Services",
            "type":"Services"
        }
    ],
    "sg:phone":"+33 1 30 15 38 88",
    "sg:postcode":"78400",
    "sg:province":"Ile de France",
    "sg:tags":[
        "banking",
        "finance",
        "insurance"
    ],
    "wof:name":"Score Conseils Sa",
    "wof:placetype":"venue"
},
  "geometry": {"coordinates":[2.159459,48.906002],"type":"Point"}
}