{
  "type": "Feature",
  "properties": {
    "addr:full":"1bis, Rue des Dimes, 01000 Bourg en Bresse Rhone-Alpes",
    "addr:housenumber":"1bis",
    "addr:postcode":"01000",
    "addr:street":"Rue Des Dimes",
    "iso:country":"FR",
    "sg:address":"1bis, Rue des Dimes, 01000 Bourg en Bresse",
    "sg:orig_category":"Unclassifiable Establishments",
    "sg:phone":"+33 4 74 22 67 04",
    "sg:province":"Rhone-Alpes",
    "wof:name":"Courrier Economie S.a.r.l.",
    "wof:placetype":"venue"
},
  "geometry": {"coordinates":[5.237168,46.205528],"type":"Point"}
}