{
  "type": "Feature",
  "properties": {
    "addr:full":"38, Rue de Laborde, 75008 Paris Ile de France",
    "addr:housenumber":"38",
    "addr:postcode":"75008",
    "addr:street":"Rue De Laborde",
    "iso:country":"FR",
    "sg:address":"38, Rue de Laborde, 75008 Paris",
    "sg:orig_category":"Unclassifiable Establishments",
    "sg:phone":"+33 1 42 93 56 37",
    "sg:province":"Ile de France",
    "wof:name":"B.t.c. S.a. - Business Travel Communication",
    "wof:placetype":"venue"
},
  "geometry": {"coordinates":[2.317203,48.875614],"type":"Point"}
}