{
  "type": "Feature",
  "properties": {
    "addr:full":"12 rue de l'H\u00f4tel de Ville; Riom; 63200 Riom Auvergne 63200",
    "addr:housenumber":"12",
    "addr:postcode":"63200;63200",
    "addr:street":"Rue De L'Ho \u0302Tel De Ville",
    "iso:country":"FR",
    "sg:address":"12 rue de l'H\u00f4tel de Ville; Riom; 63200",
    "sg:city":"Riom",
    "sg:classifiers":[
        {
            "category":"Banks & Credit Unions",
            "subcategory":"Bank",
            "type":"Services"
        }
    ],
    "sg:phone":"+33 3373380028",
    "sg:postcode":"63200",
    "sg:province":"Auvergne",
    "wof:name":"Banque Nationale De Paris",
    "wof:placetype":"venue"
},
  "geometry": {"coordinates":[3.113816,45.894005],"type":"Point"}
}