{
  "type": "Feature",
  "properties": {
    "iso:country":"FR",
    "sg:address":"Rue de Saint Albin",
    "sg:city":"Scey sur Sa\u00f4ne et Saint Albin",
    "sg:orig_category":"Unclassifiable Establishments",
    "sg:phone":"+33 3 84 68 80 80",
    "sg:postcode":"70360",
    "sg:province":"Franche Comt\u00e9",
    "wof:name":"Devaux Max Et Fils S.a.",
    "wof:placetype":"venue"
},
  "geometry": {"coordinates":[5.965243,47.666073],"type":"Point"}
}