{
  "type": "Feature",
  "properties": {
    "iso:country":"FR",
    "sg:address":"Les Thermes 16150 Etagnac",
    "sg:orig_category":"Non-Classified Establishments",
    "sg:phone":"+33 5 45 84 17 02",
    "sg:province":"Poitou-Charentes",
    "wof:name":"Rave Atlantique S.a.",
    "wof:placetype":"venue"
},
  "geometry": {"coordinates":[0.740556,45.825764],"type":"Point"}
}