{
  "type": "Feature",
  "properties": {
    "addr:full":"1, Chemin de la Noue, 21600 Longvic Longvic Bourgogne 21600",
    "addr:housenumber":"1",
    "addr:postcode":"21600;21600",
    "addr:street":"Chemin De La Noue",
    "iso:country":"FR",
    "sg:address":"1, Chemin de la Noue, 21600 Longvic",
    "sg:city":"Longvic",
    "sg:orig_category":"Unclassifiable Establishments",
    "sg:phone":"+33 3 80 68 48 80",
    "sg:postcode":"21600",
    "sg:province":"Bourgogne",
    "wof:name":"C.i.f.c. - Centre Interprofessionnel De Formation Continue",
    "wof:placetype":"venue"
},
  "geometry": {"coordinates":[5.033892,47.292545],"type":"Point"}
}