{
  "type": "Feature",
  "properties": {
    "addr:full":"31 Fauriat 42000 Saint Etienne Rhone-Alpes 42000",
    "addr:housenumber":"31",
    "addr:postcode":"42000;42000",
    "addr:street":"Fauriat",
    "iso:country":"FR",
    "sg:address":"31",
    "sg:city":"Fauriat 42000 Saint Etienne",
    "sg:classifiers":[
        {
            "category":"Manufacturing",
            "subcategory":"Metals",
            "type":"Manufacturing & Wholesale Goods"
        }
    ],
    "sg:phone":"+33 4 77 25 50 07",
    "sg:postcode":"42000",
    "sg:province":"Rhone-Alpes",
    "sg:tags":[
        "metallurgy",
        "metalworking",
        "processing"
    ],
    "wof:name":"Omni Sablage",
    "wof:placetype":"venue"
},
  "geometry": {"coordinates":[4.407506,45.445236],"type":"Point"}
}