{
  "type": "Feature",
  "properties": {
    "iso:country":"FR",
    "sg:address":"86, Rue de Fenouillet - ZI de Fondeyre, 31200 Toulouse",
    "sg:orig_category":"Unclassifiable Establishments",
    "sg:phone":"+33 5 61 47 30 00",
    "sg:province":"Midi Pyr\u00e9n\u00e9es",
    "wof:name":"Produits Chimiques Du Midi S.a.",
    "wof:placetype":"venue"
},
  "geometry": {"coordinates":[1.44954,43.639011],"type":"Point"}
}