{
  "type": "Feature",
  "properties": {
    "addr:full":"86, Rue de Fenouillet - ZI de Fondeyre, 31200 Toulouse Midi Pyr\u00e9n\u00e9es",
    "addr:housenumber":"86",
    "addr:postcode":"31200",
    "addr:street":"Rue De Fenouillet Zi De Fondeyre",
    "iso:country":"FR",
    "sg:address":"86, Rue de Fenouillet - ZI de Fondeyre, 31200 Toulouse",
    "sg:orig_category":"Unclassifiable Establishments",
    "sg:phone":"+33 5 61 47 30 00",
    "sg:province":"Midi Pyr\u00e9n\u00e9es",
    "wof:name":"Produits Chimiques Du Midi S.a.",
    "wof:placetype":"venue"
},
  "geometry": {"coordinates":[1.44954,43.639011],"type":"Point"}
}