{
  "type": "Feature",
  "properties": {
    "addr:full":"18, Rue Haute, 95170 Deuil la Barre Ile de France",
    "addr:housenumber":"18",
    "addr:postcode":"95170",
    "addr:street":"Rue Haute",
    "iso:country":"FR",
    "sg:address":"18, Rue Haute, 95170 Deuil la Barre",
    "sg:orig_category":"Non-Classified Establishments",
    "sg:phone":"+33 1 39 83 98 64",
    "sg:province":"Ile de France",
    "wof:name":"Imprimerie Buignet S.a.",
    "wof:placetype":"venue"
},
  "geometry": {"coordinates":[2.326203,48.977272],"type":"Point"}
}