{
  "type": "Feature",
  "properties": {
    "addr:full":"27, Rue Jarente, 69002 Lyon Rhone-Alpes",
    "addr:housenumber":"27",
    "addr:postcode":"69002",
    "addr:street":"Rue Jarente",
    "iso:country":"FR",
    "sg:address":"27, Rue Jarente, 69002 Lyon",
    "sg:orig_category":"Non-Classified Establishments",
    "sg:phone":"+33 4 78 37 01 13",
    "sg:province":"Rhone-Alpes",
    "wof:name":"Mermet Conseil S.a.",
    "wof:placetype":"venue"
},
  "geometry": {"coordinates":[4.829878,45.753754],"type":"Point"}
}