{
  "type": "Feature",
  "properties": {
    "iso:country":"FR",
    "sg:address":"79, Rue de Neudelange, 57920 Aboncourt",
    "sg:orig_category":"Unclassifiable Establishments",
    "sg:phone":"+33 3 82 83 90 90",
    "sg:province":"Lorraine",
    "wof:name":"H.p.a.2.e. S.a.r.l.",
    "wof:placetype":"venue"
},
  "geometry": {"coordinates":[6.34798,49.25621],"type":"Point"}
}