{
  "type": "Feature",
  "properties": {
    "addr:full":"Les Cornues 87380 Magnac Bourg Limousin",
    "addr:postcode":"87380",
    "addr:street":"Magnac Bourg Limousin",
    "iso:country":"FR",
    "sg:address":"Les Cornues 87380 Magnac Bourg",
    "sg:classifiers":[
        {
            "category":"Professional",
            "type":"Services"
        }
    ],
    "sg:phone":"+33 5 55 00 81 54",
    "sg:province":"Limousin",
    "sg:tags":[
        "transport",
        "road"
    ],
    "wof:name":"Ste Des Transports Rouffignac Sa",
    "wof:placetype":"venue"
},
  "geometry": {"coordinates":[1.438914,45.605106],"type":"Point"}
}