{
  "type": "Feature",
  "properties": {
    "addr:full":"ZI - Le Village Barbi\u00e8res Barbi\u00e8res Rhone-Alpes 26300",
    "addr:postcode":"26300",
    "addr:street":"Zi Le Village;Rhone-Alpes",
    "iso:country":"FR",
    "sg:address":"ZI - Le Village Barbi\u00e8res",
    "sg:city":"Barbi\u00e8res",
    "sg:orig_category":"Unclassifiable Establishments",
    "sg:phone":"+33 4 75 47 43 84",
    "sg:postcode":"26300",
    "sg:province":"Rhone-Alpes",
    "wof:name":"Serfir S.a.r.l.",
    "wof:placetype":"venue"
},
  "geometry": {"coordinates":[5.13875,44.95652],"type":"Point"}
}