{
  "type": "Feature",
  "properties": {
    "iso:country":"FR",
    "sg:address":"2 Rue De L'Oisans Zi Petite Montagne Sud 91090 Lisses",
    "sg:classifiers":[
        {
            "category":"Manufacturing",
            "subcategory":"Tools & Machinery",
            "type":"Manufacturing & Wholesale Goods"
        }
    ],
    "sg:phone":"+33 1 69 11 18 00",
    "sg:postcode":"91090",
    "sg:province":"Ile de France",
    "sg:tags":[
        "environment",
        "equipment",
        "-"
    ],
    "wof:name":"Pressor",
    "wof:placetype":"venue"
},
  "geometry": {"coordinates":[2.428057,48.608768],"type":"Point"}
}