{
  "type": "Feature",
  "properties": {
    "addr:full":"24 Rue Bournes 69004 Lyon Rhone-Alpes 69004",
    "addr:housenumber":"24",
    "addr:postcode":"69004;69004",
    "addr:street":"Rue Bournes",
    "iso:country":"FR",
    "sg:address":"24 Rue Bournes 69004 Lyon",
    "sg:classifiers":[
        {
            "category":"Professional",
            "subcategory":"Business Services",
            "type":"Services"
        }
    ],
    "sg:phone":"+33 4 78 29 14 71",
    "sg:postcode":"69004",
    "sg:province":"Rhone-Alpes",
    "sg:tags":[
        "body",
        "advice"
    ],
    "wof:name":"Aide Personnes Agees 4 Arrondi",
    "wof:placetype":"venue"
},
  "geometry": {"coordinates":[4.821054,45.776772],"type":"Point"}
}