{
  "type": "Feature",
  "properties": {
    "addr:full":"12, Rue Gay Lussac, 94438 Chennevi\u00e8res sur Marne \u00cele-de-France",
    "addr:housenumber":"12",
    "addr:postcode":"94438",
    "addr:street":"Rue Gay Lussac;Marne",
    "iso:country":"FR",
    "sg:address":"12, Rue Gay Lussac, 94438 Chennevi\u00e8res sur Marne",
    "sg:orig_category":"Unclassifiable Establishments",
    "sg:phone":"+33 1 56 86 14 90",
    "sg:province":"\u00cele-de-France",
    "wof:name":"S\u00e9n\u00e9chal Et Compagnie S.a.",
    "wof:placetype":"venue"
},
  "geometry": {"coordinates":[2.540172,48.79763],"type":"Point"}
}