{
  "type": "Feature",
  "properties": {
    "addr:full":"66, Rue Jean-Baptiste Lebas, 59200 Tourcoing Nord Pas-de-Calais 59200",
    "addr:housenumber":"66",
    "addr:postcode":"59200;59200",
    "addr:street":"Rue Jean-Baptiste Lebas",
    "iso:country":"FR",
    "sg:address":"66, Rue Jean-Baptiste Lebas, 59200 Tourcoing",
    "sg:orig_category":"Non-Classified Establishments",
    "sg:phone":"+33 3 20 25 25 05",
    "sg:postcode":"59200",
    "sg:province":"Nord Pas-de-Calais",
    "wof:name":"Activit\u00e9 De Routage Et De Prestation S.a.r.l.",
    "wof:placetype":"venue"
},
  "geometry": {"coordinates":[3.171213,50.724422],"type":"Point"}
}