{
  "type": "Feature",
  "properties": {
    "addr:full":"Rue De Pied De Fond Zi De St Ligaire 79000 Niort Poitou-Charentes 79000",
    "addr:postcode":"79000;79000",
    "addr:street":"Rue De Pied De Fond Zi De St Ligaire",
    "iso:country":"FR",
    "sg:address":"Rue De Pied De Fond Zi De St Ligaire 79000 Niort",
    "sg:classifiers":[
        {
            "category":"Manufacturing",
            "subcategory":"Metals",
            "type":"Manufacturing & Wholesale Goods"
        }
    ],
    "sg:phone":"+33 5 49 17 24 00",
    "sg:postcode":"79000",
    "sg:province":"Poitou-Charentes",
    "sg:tags":[
        "metallurgy",
        "steel",
        "metalworking"
    ],
    "wof:name":"Vendeenne D'approvisionnement Metallurgique Et Agricole (vama)",
    "wof:placetype":"venue"
},
  "geometry": {"coordinates":[-0.504137,46.298],"type":"Point"}
}