{
  "type": "Feature",
  "properties": {
    "iso:country":"FR",
    "sg:address":"Rue de la D\u00e9couverte - Mini Parc - B\u00e2t. 4",
    "sg:city":"Lab\u00e8ge",
    "sg:orig_category":"Unclassifiable Establishments",
    "sg:phone":"+33 5 62 24 62 24",
    "sg:postcode":"31670",
    "sg:province":"Midi Pyr\u00e9n\u00e9es",
    "wof:name":"Bull S.a.",
    "wof:placetype":"venue"
},
  "geometry": {"coordinates":[1.504535,43.546227],"type":"Point"}
}