{
  "type": "Feature",
  "properties": {
    "iso:country":"FR",
    "sg:address":"20 RUE DES GALUREAUX 02600 PUISEUX EN RETZ",
    "sg:classifiers":[
        {
            "category":"Manufacturing",
            "subcategory":"Furniture",
            "type":"Manufacturing & Wholesale Goods"
        }
    ],
    "sg:phone":"+33 3 23 72 71 61",
    "sg:province":"Picardie",
    "sg:tags":[
        "solid",
        "wood"
    ],
    "wof:name":"Dequecker Productions Sa",
    "wof:placetype":"venue"
},
  "geometry": {"coordinates":[3.121504,49.269054],"type":"Point"}
}