{
  "type": "Feature",
  "properties": {
    "iso:country":"FR",
    "sg:address":"5/7, Bd Guigou, 13003 Marseille",
    "sg:orig_category":"Non-Classified Establishments",
    "sg:phone":"+33 4 91 05 85 89",
    "sg:province":"Poitou-Charentes",
    "wof:name":"D.b.d. S.a. - Delta Beaut\u00e9 Distribution",
    "wof:placetype":"venue"
},
  "geometry": {"coordinates":[5.391846,43.314735],"type":"Point"}
}