{
  "type": "Feature",
  "properties": {
    "iso:country":"FR",
    "sg:address":"249 rue du Faubourg de Roubaix 59800 Lille",
    "sg:classifiers":[
        {
            "category":"Wholesale",
            "subcategory":"Construction Materials",
            "type":"Manufacturing & Wholesale Goods"
        }
    ],
    "sg:phone":"+33 3 20 12 11 80",
    "sg:province":"Nord Pas-de-Calais",
    "sg:tags":[
        "sewing",
        "thread"
    ],
    "wof:name":"Ets Vrau Sa",
    "wof:placetype":"venue"
},
  "geometry": {"coordinates":[3.08024,50.636189],"type":"Point"}
}