{
  "type": "Feature",
  "properties": {
    "addr:full":"ZI le Bois Joly Tauxigny Centre 37310",
    "addr:postcode":"37310",
    "addr:street":"Zi Le",
    "iso:country":"FR",
    "sg:address":"ZI le Bois Joly",
    "sg:city":"Tauxigny",
    "sg:orig_category":"Unclassifiable Establishments",
    "sg:phone":"+33 2 47 34 33 43",
    "sg:postcode":"37310",
    "sg:province":"Centre",
    "wof:name":"Reals S.a.",
    "wof:placetype":"venue"
},
  "geometry": {"coordinates":[0.834595,47.212013],"type":"Point"}
}