{
  "type": "Feature",
  "properties": {
    "iso:country":"FR",
    "sg:address":"11 Rue De Garefaure BP 87999 21000 Dijon",
    "sg:city":"Dijon",
    "sg:classifiers":[
        {
            "category":"Professional",
            "subcategory":"Business Services",
            "type":"Services"
        }
    ],
    "sg:phone":"+33 3 80 65 15 90",
    "sg:postcode":"21000",
    "sg:province":"Bourgogne",
    "sg:tags":[
        "training",
        "advice"
    ],
    "wof:name":"Etab Nat Enseignement Sup Agronomique",
    "wof:placetype":"venue"
},
  "geometry": {"coordinates":[5.044195,47.326458],"type":"Point"}
}