{
  "type": "Feature",
  "properties": {
    "iso:country":"FR",
    "sg:address":"Rue de l'Industrie - ZI",
    "sg:city":"Chevry Cossigny",
    "sg:orig_category":"Non-Classified Establishments",
    "sg:phone":"+33 1 60 62 55 80",
    "sg:postcode":"77173",
    "sg:province":"Ile de France",
    "wof:name":"Largillier Etablissements S.a.",
    "wof:placetype":"venue"
},
  "geometry": {"coordinates":[2.654151,48.72599],"type":"Point"}
}