{
  "type": "Feature",
  "properties": {
    "iso:country":"FR",
    "sg:address":"108, Rue de Jouy, 57160 Moulins l\u00e8s Metz",
    "sg:orig_category":"Unclassifiable Establishments",
    "sg:phone":"+33 3 87 63 04 76",
    "sg:province":"Lorraine",
    "wof:name":"C.a.t. - Centre D'aide Par Le Travail - Borny - Moulins - Varize",
    "wof:placetype":"venue"
},
  "geometry": {"coordinates":[6.126823,49.090332],"type":"Point"}
}