{
  "type": "Feature",
  "properties": {
    "iso:country":"FR",
    "sg:address":"79, Rue Faubourg Poissonni\u00e8re, 75009 Paris",
    "sg:orig_category":"Non-Classified Establishments",
    "sg:phone":"+33 1 45 23 47 47",
    "sg:province":"Ile de France",
    "wof:name":"Les Ateliers Tomalet S.a.r.l.",
    "wof:placetype":"venue"
},
  "geometry": {"coordinates":[2.348268,48.876335],"type":"Point"}
}