{
  "type": "Feature",
  "properties": {
    "iso:country":"FR",
    "sg:address":"6, Rue de la Braque, 75003 Paris",
    "sg:orig_category":"Unclassifiable Establishments",
    "sg:phone":"+33 1 44 54 13 13",
    "sg:province":"Ile de France",
    "wof:name":"Internet Quest S.a.",
    "wof:placetype":"venue"
},
  "geometry": {"coordinates":[2.357009,48.86097],"type":"Point"}
}