{
  "type": "Feature",
  "properties": {
    "iso:country":"FR",
    "sg:address":"Le Moulin 72400 Saint Aubin des Coudrais",
    "sg:orig_category":"Unclassifiable Establishments",
    "sg:phone":"+33 2 43 93 20 12",
    "sg:province":"Pays de Loire",
    "wof:name":"Saussereau P\u00e8re Et Fils S.a.",
    "wof:placetype":"venue"
},
  "geometry": {"coordinates":[0.59771,48.16777],"type":"Point"}
}