{
  "type": "Feature",
  "properties": {
    "addr:full":"ZI de Scientrier Scientrier Rhone-Alpes 74930",
    "addr:postcode":"74930",
    "addr:street":"Zi De Scientrier;Rhone-Alpes",
    "iso:country":"FR",
    "sg:address":"ZI de Scientrier",
    "sg:city":"Scientrier",
    "sg:orig_category":"Non-Classified Establishments",
    "sg:phone":"+33 4 50 25 23 23",
    "sg:postcode":"74930",
    "sg:province":"Rhone-Alpes",
    "wof:name":"M\u00e9noni S.a.s.",
    "wof:placetype":"venue"
},
  "geometry": {"coordinates":[6.331081,46.112339],"type":"Point"}
}