{
  "type": "Feature",
  "properties": {
    "iso:country":"FR",
    "sg:address":"65 Chem Salini\u00e9 31100 Toulouse",
    "sg:classifiers":[
        {
            "category":"Professional",
            "subcategory":"Business Services",
            "type":"Services"
        }
    ],
    "sg:phone":"+33 5 62 74 81 50",
    "sg:postcode":"31100",
    "sg:province":"Midi Pyr\u00e9n\u00e9es",
    "sg:tags":[
        "body",
        "advice"
    ],
    "wof:name":"Association Gestion Organismes Prives",
    "wof:placetype":"venue"
},
  "geometry": {"coordinates":[1.380763,43.594028],"type":"Point"}
}