{
  "type": "Feature",
  "properties": {
    "iso:country":"FR",
    "sg:address":"5, Rue Langevin - ZI des Garennes, 78130 Les Mureaux",
    "sg:orig_category":"Unclassifiable Establishments",
    "sg:phone":"+33 1 34 74 02 16",
    "sg:province":"Ile de France",
    "wof:name":"C\u00e2blerie Des Mureaux S.a.",
    "wof:placetype":"venue"
},
  "geometry": {"coordinates":[1.906235,48.99464],"type":"Point"}
}