{
  "type": "Feature",
  "properties": {
    "addr:full":"Carrefour du Christ Saclay Ile de France 91400",
    "addr:postcode":"91400",
    "addr:street":"Carrefour",
    "iso:country":"FR",
    "sg:address":"Carrefour du Christ",
    "sg:city":"Saclay",
    "sg:orig_category":"Non-Classified Establishments",
    "sg:phone":"+33 1 69 41 84 18",
    "sg:postcode":"91400",
    "sg:province":"Ile de France",
    "wof:name":"Locaro S.a.r.l.",
    "wof:placetype":"venue"
},
  "geometry": {"coordinates":[2.163579,48.730877],"type":"Point"}
}