{
  "type": "Feature",
  "properties": {
    "addr:full":"4 Rue Lorival Zi 59473 Seclin Cedex Nord-Pas-de-Calais",
    "addr:housenumber":"4",
    "addr:postcode":"59473;cedex",
    "addr:street":"Rue Lorival Zi",
    "iso:country":"FR",
    "sg:address":"4 Rue Lorival Zi 59473 Seclin Cedex",
    "sg:classifiers":[
        {
            "category":"Professional",
            "type":"Services"
        }
    ],
    "sg:phone":"+33 3 20 90 95 95",
    "sg:province":"Nord-Pas-de-Calais",
    "sg:tags":[
        "transport",
        "road"
    ],
    "wof:name":"Mazet Lille Sa",
    "wof:placetype":"venue"
},
  "geometry": {"coordinates":[3.03058,50.551048],"type":"Point"}
}