{
  "type": "Feature",
  "properties": {
    "iso:country":"FR",
    "sg:address":"Za De L'Aire 12000 Rodez",
    "sg:classifiers":[
        {
            "category":"Shopping",
            "subcategory":"Computers & Home Electronics",
            "type":"Retail Goods"
        }
    ],
    "sg:phone":"+33 5 65 77 36 36",
    "sg:postcode":"12000",
    "sg:province":"Midi Pyr\u00e9n\u00e9es",
    "sg:tags":[
        "electric",
        "electricity",
        "component",
        "equipment",
        "electrical",
        "electronic"
    ],
    "wof:name":"Ste Commerciale Toutelectric",
    "wof:placetype":"venue"
},
  "geometry": {"coordinates":[2.57217,44.345299],"type":"Point"}
}