{
  "type": "Feature",
  "properties": {
    "addr:full":"19 Av Tony Garnier 69007 Lyon Rhone-Alpes",
    "addr:postcode":"69007",
    "addr:street":"19 Av Tony Garnier",
    "iso:country":"FR",
    "sg:address":"19 Av Tony Garnier 69007 Lyon",
    "sg:classifiers":[
        {
            "category":"Health Services",
            "subcategory":"Medical Lab",
            "type":"Services"
        }
    ],
    "sg:phone":"+33 4 72 80 10 10",
    "sg:province":"Rhone-Alpes",
    "sg:tags":[
        "chemical",
        "pharmaceutical",
        "pharmacy"
    ],
    "wof:name":"Laboratoire Marcel Merieux Sa",
    "wof:placetype":"venue"
},
  "geometry": {"coordinates":[4.836677,45.726425],"type":"Point"}
}