{
  "type": "Feature",
  "properties": {
    "addr:full":"Rue du Ch\u00eane Nordhouse Alsace 67150",
    "addr:postcode":"67150",
    "addr:street":"Rue Du Che\u0302Ne",
    "iso:country":"FR",
    "sg:address":"Rue du Ch\u00eane",
    "sg:city":"Nordhouse",
    "sg:orig_category":"Unclassifiable Establishments",
    "sg:phone":"+33 3 88 98 90 02",
    "sg:postcode":"67150",
    "sg:province":"Alsace",
    "wof:name":"Samareh S.a.r.l.",
    "wof:placetype":"venue"
},
  "geometry": {"coordinates":[7.68321,48.448231],"type":"Point"}
}