{
  "type": "Feature",
  "properties": {
    "addr:full":"15 Rue De L'Esp\u00e9rence 59100 Roubaix Nord Pas-de-Calais 59100",
    "addr:housenumber":"15",
    "addr:postcode":"59100;59100",
    "addr:street":"Rue De L'Espe \u0301Rence",
    "iso:country":"FR",
    "sg:address":"15 Rue De L'Esp\u00e9rence 59100 Roubaix",
    "sg:classifiers":[
        {
            "category":"Shopping",
            "subcategory":"Crafts & Fabrics",
            "type":"Retail Goods"
        }
    ],
    "sg:phone":"+33 3 20 70 77 60",
    "sg:postcode":"59100",
    "sg:province":"Nord Pas-de-Calais",
    "sg:tags":[
        "textile",
        "clothing"
    ],
    "wof:name":"Etablissements Peucelle Et Florin Sarl",
    "wof:placetype":"venue"
},
  "geometry": {"coordinates":[3.160883,50.695164],"type":"Point"}
}