{
  "type": "Feature",
  "properties": {
    "iso:country":"FR",
    "sg:address":"Le Petit Passeloup 69400 Liergues",
    "sg:classifiers":[
        {
            "category":"Professional",
            "subcategory":"Engineering",
            "type":"Services"
        }
    ],
    "sg:phone":"+33 4 74 62 80 11",
    "sg:postcode":"69400",
    "sg:province":"Rhone-Alpes",
    "sg:tags":[
        "electric",
        "-",
        "component",
        "machine",
        "mechanical",
        "electronic"
    ],
    "wof:name":"Bobinage Electrique Industriel Bei (bei)",
    "wof:placetype":"venue"
},
  "geometry": {"coordinates":[4.66832,45.960049],"type":"Point"}
}