{
  "type": "Feature",
  "properties": {
    "iso:country":"FR",
    "sg:address":"12, Sente de la Cauchoiserie, 78580 Maule",
    "sg:orig_category":"Unclassifiable Establishments",
    "sg:phone":"+33 1 30 90 90 44",
    "sg:province":"Ile de France",
    "wof:name":"Chocolats Colas S.a.r.l.",
    "wof:placetype":"venue"
},
  "geometry": {"coordinates":[1.858713,48.912159],"type":"Point"}
}