{
  "type": "Feature",
  "properties": {
    "addr:full":"B.P. 1109, 01009 Bourg en Bresse C\u00e9dex^^3, Chemin de Majornas, 01000 Bourg en Bresse Rhone-Alpes",
    "addr:housenumber":"1109",
    "addr:postcode":"01009;01000",
    "addr:street":"B.P.;Chemin De Majornas",
    "iso:country":"FR",
    "sg:address":"B.P. 1109, 01009 Bourg en Bresse C\u00e9dex^^3, Chemin de Majornas, 01000 Bourg en Bresse",
    "sg:orig_category":"Non-Classified Establishments",
    "sg:phone":"+33 4 74 45 94 39",
    "sg:province":"Rhone-Alpes",
    "wof:name":"Sprint M\u00e9tal S.a.",
    "wof:placetype":"venue"
},
  "geometry": {"coordinates":[5.18957,46.199814],"type":"Point"}
}