{
  "type": "Feature",
  "properties": {
    "addr:full":"47, Av. du Mont Saint Michel, 61300 L'Aigle Chandai Basse Normandie 61300",
    "addr:postcode":"61300;61300",
    "addr:street":"47 Av. Du Mont Saint Michel",
    "iso:country":"FR",
    "sg:address":"47, Av. du Mont Saint Michel, 61300 L'Aigle",
    "sg:city":"Chandai",
    "sg:orig_category":"Non-Classified Establishments",
    "sg:phone":"+33 2 33 34 38 38",
    "sg:postcode":"61300",
    "sg:province":"Basse Normandie",
    "wof:name":"R\u00e9gis Location S.a.",
    "wof:placetype":"venue"
},
  "geometry": {"coordinates":[0.609607,48.758183],"type":"Point"}
}