{
  "type": "Feature",
  "properties": {
    "iso:country":"FR",
    "sg:address":"18, Rue de Lyon - Le Belv\u00e9d\u00e8re , 01170 Gex",
    "sg:orig_category":"Unclassifiable Establishments",
    "sg:phone":"+33 4 50 99 03 44",
    "sg:province":"Rhone-Alpes",
    "wof:name":"Entreprise Cuypers Jacques",
    "wof:placetype":"venue"
},
  "geometry": {"coordinates":[6.06008,46.319519],"type":"Point"}
}