{
  "type": "Feature",
  "properties": {
    "addr:full":"1 rue Gustave Eiffel 22360 LANGUEUX Langueux Bretagne 22360",
    "addr:housenumber":"1",
    "addr:postcode":"22360;22360",
    "addr:street":"Rue Gustave Eiffel",
    "iso:country":"FR",
    "sg:address":"1 rue Gustave Eiffel 22360 LANGUEUX",
    "sg:city":"Langueux",
    "sg:classifiers":[
        {
            "category":"Manufacturing",
            "subcategory":"Motor Vehicles & Parts",
            "type":"Manufacturing & Wholesale Goods"
        }
    ],
    "sg:phone":"+33 2 96 61 90 10",
    "sg:postcode":"22360",
    "sg:province":"Bretagne",
    "sg:tags":[
        "precision",
        "mechanic"
    ],
    "wof:name":"Armor Precision Sarl",
    "wof:placetype":"venue"
},
  "geometry": {"coordinates":[-2.734836,48.500759],"type":"Point"}
}