{
  "type": "Feature",
  "properties": {
    "iso:country":"FR",
    "sg:address":"4 bis, Rue Aristide Briand, 78130 Les Mureaux",
    "sg:orig_category":"Unclassifiable Establishments",
    "sg:phone":"+33 1 30 91 91 91",
    "sg:province":"Ile de France",
    "wof:name":"Pointer S.a.r.l.",
    "wof:placetype":"venue"
},
  "geometry": {"coordinates":[1.910457,48.991081],"type":"Point"}
}