{
  "type": "Feature",
  "properties": {
    "addr:full":"58, Grande Rue, 78490 Vicq Ile de France",
    "addr:housenumber":"58",
    "addr:postcode":"78490",
    "addr:street":"Grande Rue;Ile De France",
    "iso:country":"FR",
    "sg:address":"58, Grande Rue, 78490 Vicq",
    "sg:orig_category":"Non-Classified Establishments",
    "sg:phone":"+33 1 34 86 12 15",
    "sg:province":"Ile de France",
    "wof:name":"S\u00e9g\u00e9tec S.a.r.l.",
    "wof:placetype":"venue"
},
  "geometry": {"coordinates":[1.83798,48.813095],"type":"Point"}
}