{
  "type": "Feature",
  "properties": {
    "addr:full":"2 Rixheim Alsace 68170",
    "addr:housenumber":"2",
    "addr:postcode":"68170",
    "addr:street":"Rixheim Alsace",
    "iso:country":"FR",
    "sg:address":"2",
    "sg:city":"Rixheim",
    "sg:classifiers":[
        {
            "category":"Professional",
            "subcategory":"Engineering",
            "type":"Services"
        }
    ],
    "sg:phone":"+33 3 89 65 03 01",
    "sg:postcode":"68170",
    "sg:province":"Alsace",
    "sg:tags":[
        "machine",
        "-",
        "mechanical"
    ],
    "wof:name":"E.r.c.s",
    "wof:placetype":"venue"
},
  "geometry": {"coordinates":[7.422345,47.744915],"type":"Point"}
}