{
  "type": "Feature",
  "properties": {
    "iso:country":"FR",
    "sg:address":"4 Allee De La Seine Batiment B Paryseine 4 5 94200 Ivry Sur Seine",
    "sg:classifiers":[
        {
            "category":"Shopping",
            "subcategory":"Clothing, Apparel, & Fashions",
            "type":"Retail Goods"
        }
    ],
    "sg:phone":"+33 1 49 60 69 00",
    "sg:postcode":"94200",
    "sg:province":"Ile de France",
    "sg:tags":[
        "textile",
        "clothing",
        "clothes"
    ],
    "wof:name":"Laurent Cerrer",
    "wof:placetype":"venue"
},
  "geometry": {"coordinates":[2.399564,48.818554],"type":"Point"}
}