{
  "type": "Feature",
  "properties": {
    "addr:full":"260 route de Combault 94510 La Queue en Brie Ile de France 94510",
    "addr:housenumber":"260",
    "addr:postcode":"94510;94510",
    "addr:street":"Route De Combault;Queue En Brie Ile De France",
    "iso:country":"FR",
    "sg:address":"260 route de Combault 94510 La Queue en Brie",
    "sg:classifiers":[
        {
            "category":"Deli",
            "type":"Food & Drink"
        }
    ],
    "sg:phone":"+33 1 45 76 30 40",
    "sg:postcode":"94510",
    "sg:province":"Ile de France",
    "sg:tags":[
        "delicatessen"
    ],
    "wof:name":"Tradition Et Gourmandise Sa",
    "wof:placetype":"venue"
},
  "geometry": {"coordinates":[2.584003,48.787865],"type":"Point"}
}