{
  "type": "Feature",
  "properties": {
    "addr:full":"B.P. 17, 76270 Neufchatel en Bray^^RN 28, 76270 Qui\u00e8vrecourt Haute Normandie 76270",
    "addr:housenumber":"28",
    "addr:postcode":"76270;76270;76270",
    "addr:street":"B.P. 17;Bray^^Rn;Haute Normandie",
    "iso:country":"FR",
    "sg:address":"B.P. 17, 76270 Neufchatel en Bray^^RN 28, 76270 Qui\u00e8vrecourt",
    "sg:orig_category":"Enherbement, Engazonnement Erosion \u00e9olienne, Contr\u00f4le de l' Jardins et parcs, Am\u00e9nagement et/ou entr",
    "sg:phone":"+33 2 35 93 06 66",
    "sg:postcode":"76270",
    "sg:province":"Haute Normandie",
    "wof:name":"Antalvert S.a.",
    "wof:placetype":"venue"
},
  "geometry": {"coordinates":[1.399665,49.690815],"type":"Point"}
}