{
  "type": "Feature",
  "properties": {
    "addr:full":"B.P. 16, 38380 Entre Deux Guiers C\u00e9dex^^ZI Chartreuse, 38380 Entre Deux Guiers Rhone-Alpes 38380",
    "addr:postcode":"38380;38380;38380",
    "addr:street":"B.P. 16;Ce\u0301Dex^^Zi Chartreuse;Rhone-Alpes",
    "iso:country":"FR",
    "sg:address":"B.P. 16, 38380 Entre Deux Guiers C\u00e9dex^^ZI Chartreuse, 38380 Entre Deux Guiers",
    "sg:orig_category":"Non-Classified Establishments",
    "sg:phone":"+33 4 76 66 08 71",
    "sg:postcode":"38380",
    "sg:province":"Rhone-Alpes",
    "wof:name":"S.b.c.m. S.a.r.l. - Soci\u00e9t\u00e9 Barnier Construtions M\u00e9caniques",
    "wof:placetype":"venue"
},
  "geometry": {"coordinates":[5.790159,45.314697],"type":"Point"}
}