{
  "type": "Feature",
  "properties": {
    "iso:country":"FR",
    "sg:address":"Rue Gay Lussac - Le Champ Male",
    "sg:city":"Varennes Vauzelles",
    "sg:orig_category":"Non-Classified Establishments",
    "sg:phone":"+33 3 86 71 92 12",
    "sg:postcode":"58640",
    "sg:province":"Bourgogne",
    "wof:name":"S.t.d.c. S.a. -soci\u00e9t\u00e9 Technique Dumas Et Colinot",
    "wof:placetype":"venue"
},
  "geometry": {"coordinates":[3.14957,47.015034],"type":"Point"}
}