{
  "type": "Feature",
  "properties": {
    "iso:country":"FR",
    "sg:address":"ZA",
    "sg:city":"Longeville sur Mer",
    "sg:orig_category":"Unclassifiable Establishments",
    "sg:phone":"+33 2 51 33 33 80",
    "sg:postcode":"85560",
    "sg:province":"Pays de Loire",
    "wof:name":"Atomic Protection S.a.r.l.",
    "wof:placetype":"venue"
},
  "geometry": {"coordinates":[-1.470079,46.38797],"type":"Point"}
}