{
  "type": "Feature",
  "properties": {
    "addr:full":"Zi 64680 Ogeu Les Bains Buziet Aquitaine 64680",
    "addr:postcode":"64680;64680",
    "addr:street":"Zi",
    "iso:country":"FR",
    "sg:address":"Zi 64680 Ogeu Les Bains",
    "sg:city":"Buziet",
    "sg:classifiers":[
        {
            "category":"Shopping",
            "subcategory":"Crafts & Fabrics",
            "type":"Retail Goods"
        }
    ],
    "sg:phone":"+33 5 59 34 94 51",
    "sg:postcode":"64680",
    "sg:province":"Aquitaine",
    "sg:tags":[
        "textile",
        "clothing"
    ],
    "wof:name":"Brod Matic",
    "wof:placetype":"venue"
},
  "geometry": {"coordinates":[-0.504156,43.152031],"type":"Point"}
}