{
  "type": "Feature",
  "properties": {
    "iso:country":"FR",
    "sg:address":"P\u00f4le Industriel De Fr\u00e9jus 73500 Modane",
    "sg:classifiers":[
        {
            "category":"Government",
            "subcategory":"Department Of Motor Vehicles",
            "type":"Public Place"
        }
    ],
    "sg:phone":"+33 4 79 05 09 01",
    "sg:postcode":"73500",
    "sg:province":"Rhone-Alpes",
    "sg:tags":[
        "equipment",
        "industrial",
        "transport",
        "motor-cars"
    ],
    "wof:name":"Doppelmayr France",
    "wof:placetype":"venue"
},
  "geometry": {"coordinates":[6.658225,45.179089],"type":"Point"}
}