{
  "type": "Feature",
  "properties": {
    "iso:country":"FR",
    "sg:address":"Av. Georges Pompidou",
    "sg:city":"Saint Amand Montrond",
    "sg:orig_category":"Unclassifiable Establishments",
    "sg:phone":"+33 2 48 61 50 98",
    "sg:postcode":"18200",
    "sg:province":"Centre",
    "wof:name":"Le Verdier",
    "wof:placetype":"venue"
},
  "geometry": {"coordinates":[2.515925,46.716942],"type":"Point"}
}