{
  "type": "Feature",
  "properties": {
    "iso:country":"FR",
    "sg:address":"Rte de Sainte Anne du Portzic",
    "sg:city":"Brest",
    "sg:orig_category":"Unclassifiable Establishments",
    "sg:phone":"+33 2 98 31 37 00",
    "sg:postcode":"29200",
    "sg:province":"Bretagne",
    "wof:name":"Thal\u00e8s Underwater Systems S.a.s.",
    "wof:placetype":"venue"
},
  "geometry": {"coordinates":[-4.547848,48.36747],"type":"Point"}
}