{
  "type": "Feature",
  "properties": {
    "addr:full":"Cap Janet - Port Hangar 17 Marseille Provence-Alpes-C\u00f4te d'Azur 13002",
    "addr:housenumber":"17",
    "addr:postcode":"13002",
    "iso:country":"FR",
    "sg:address":"Cap Janet - Port Hangar 17",
    "sg:city":"Marseille",
    "sg:orig_category":"Non-Classified Establishments",
    "sg:phone":"+33 4 91 03 29 45",
    "sg:postcode":"13002",
    "sg:province":"Provence-Alpes-C\u00f4te d'Azur",
    "wof:name":"F.c. S.a. - Transporteurs R\u00e9unis La Fl\u00e8che Cavaillonnaise",
    "wof:placetype":"venue"
},
  "geometry": {"coordinates":[5.37001,43.296101],"type":"Point"}
}