{
  "type": "Feature",
  "properties": {
    "iso:country":"FR",
    "sg:address":"chemin de Boisiere 73420 DRUMETTAZ CLARAFOND",
    "sg:orig_category":"Material Flow Equipment, Inplant",
    "sg:phone":"+33 4 79 88 08 51",
    "sg:postcode":"73420",
    "sg:province":"Rhone-Alpes",
    "wof:name":"Validex S.a.r.l.",
    "wof:placetype":"venue"
},
  "geometry": {"coordinates":[5.912054,45.652237],"type":"Point"}
}