{
  "type": "Feature",
  "properties": {
    "addr:full":"61 Boulevard Pierre Marie Curie 44151 ANCENIS CEDEX Aquitaine",
    "addr:housenumber":"61",
    "addr:postcode":"44151",
    "addr:street":"Boulevard Pierre Marie Curie",
    "iso:country":"FR",
    "sg:address":"61 Boulevard Pierre Marie Curie 44151 ANCENIS CEDEX",
    "sg:classifiers":[
        {
            "category":"Building & Trades",
            "subcategory":"Equipment Rental",
            "type":"Services"
        }
    ],
    "sg:phone":"+33 2 40 83 22 14",
    "sg:province":"Aquitaine",
    "sg:tags":[
        "first-aid"
    ],
    "wof:name":"Sagelec Sarl",
    "wof:placetype":"venue"
},
  "geometry": {"coordinates":[-1.178869,47.371174],"type":"Point"}
}