{
  "type": "Feature",
  "properties": {
    "addr:full":"31 rue de la R\u00e9publique; Capdenac; 12700 Midi Pyr\u00e9n\u00e9es 12700",
    "addr:housenumber":"31",
    "addr:postcode":"12700;12700",
    "addr:street":"Rue De La Re\u0301Publique",
    "iso:country":"FR",
    "sg:address":"31 rue de la R\u00e9publique; Capdenac; 12700",
    "sg:classifiers":[
        {
            "category":"Banks & Credit Unions",
            "subcategory":"Bank",
            "type":"Services"
        }
    ],
    "sg:phone":"+33 3365647785",
    "sg:postcode":"12700",
    "sg:province":"Midi Pyr\u00e9n\u00e9es",
    "wof:name":"Banque Nationale De Paris",
    "wof:placetype":"venue"
},
  "geometry": {"coordinates":[2.078807,44.576523],"type":"Point"}
}