{
  "type": "Feature",
  "properties": {
    "iso:country":"FR",
    "sg:address":"B.P. 11, 95240 Cormeilles en Parisis^^Rue Danton, 95240 Cormeilles en Parisis",
    "sg:orig_category":"Non-Classified Establishments",
    "sg:phone":"+33 1 39 31 31 31",
    "sg:province":"Ile de France",
    "wof:name":"Georges Borca Et Fils S.a.",
    "wof:placetype":"venue"
},
  "geometry": {"coordinates":[2.199898,48.976402],"type":"Point"}
}