{
  "type": "Feature",
  "properties": {
    "addr:full":"25 Parc Montretout Saint-Cloud 92210 ",
    "addr:housenumber":"25",
    "addr:postcode":"92210",
    "addr:street":"Parc Montretout",
    "iso:country":"FR",
    "sg:address":"25 Parc Montretout",
    "sg:city":"Saint-Cloud",
    "sg:classifiers":[
        {
            "category":"Professional",
            "subcategory":"Computer Services",
            "type":"Services"
        }
    ],
    "sg:postcode":"92210 ",
    "sg:tags":[
        "organizational-charts",
        "org-charts",
        "wiki",
        "contacts",
        "contacts-database"
    ],
    "sg:website":"http://www.theofficialboard.com/",
    "wof:name":"TheOfficialBoard",
    "wof:placetype":"venue"
},
  "geometry": {"coordinates":[2.212889,48.841073],"type":"Point"}
}