{
  "type": "Feature",
  "properties": {
    "iso:country":"FR",
    "sg:address":"14 Rue De La Croix Rouge Za 35770 Vern Sur Seiche",
    "sg:city":"Vern-sur-Seiche",
    "sg:classifiers":[
        {
            "category":"Manufacturing",
            "subcategory":"Chemicals & Compounds",
            "type":"Manufacturing & Wholesale Goods"
        }
    ],
    "sg:phone":"+33 2 99 62 73 33",
    "sg:postcode":"35770",
    "sg:province":"Bretagne",
    "sg:tags":[
        "pharmaceutical",
        "energy",
        "chemistry",
        "-",
        "by-product"
    ],
    "wof:name":"Combustible De L'ouest",
    "wof:placetype":"venue"
},
  "geometry": {"coordinates":[-1.604871,48.050728],"type":"Point"}
}