{
  "type": "Feature",
  "properties": {
    "iso:country":"FR",
    "sg:address":"8, rue Bernard Palissy, 51500 Taissy",
    "sg:orig_category":"Non-Classified Establishments",
    "sg:phone":"+33 3 26 82 53 54",
    "sg:postcode":"51500",
    "sg:province":"Champagne",
    "wof:name":"Emebat S.a.r.l.",
    "wof:placetype":"venue"
},
  "geometry": {"coordinates":[4.07558,49.217209],"type":"Point"}
}