{
  "type": "Feature",
  "properties": {
    "addr:full":"54 Lumbres BP 77 Cedex 62968 Longuenesse Poitou-Charentes",
    "addr:housenumber":"54;bp 77",
    "addr:postcode":"cedex 62968",
    "iso:country":"FR",
    "sg:address":"54",
    "sg:city":"Lumbres BP 77 Cedex 62968 Longuenesse",
    "sg:classifiers":[
        {
            "category":"Shopping",
            "subcategory":"Clothing, Apparel, & Fashions",
            "type":"Retail Goods"
        }
    ],
    "sg:phone":"+33 3 21 98 26 13",
    "sg:province":"Poitou-Charentes",
    "sg:tags":[
        "textile",
        "clothing",
        "clothes"
    ],
    "wof:name":"Singer Freres (sa)",
    "wof:placetype":"venue"
},
  "geometry": {"coordinates":[2.23915,50.73439],"type":"Point"}
}