{
  "type": "Feature",
  "properties": {
    "addr:full":"44, Av. de la Division Leclerc, 92310 S\u00e8vres Ile de France",
    "addr:postcode":"92310",
    "addr:street":"44 Av. De La Division Leclerc",
    "iso:country":"FR",
    "sg:address":"44, Av. de la Division Leclerc, 92310 S\u00e8vres",
    "sg:orig_category":"Non-Classified Establishments",
    "sg:phone":"+33 1 45 07 00 77",
    "sg:province":"Ile de France",
    "wof:name":"Klik Compo S.a.r.l.",
    "wof:placetype":"venue"
},
  "geometry": {"coordinates":[2.224045,48.823177],"type":"Point"}
}