{
  "type": "Feature",
  "properties": {
    "addr:full":"rue du Silo 45340 Beaune la Rolande Auxy Centre 45340",
    "addr:postcode":"45340;45340",
    "addr:street":"Rue Du Silo",
    "iso:country":"FR",
    "sg:address":"rue du Silo 45340 Beaune la Rolande",
    "sg:city":"Auxy",
    "sg:classifiers":[
        {
            "category":"Professional",
            "subcategory":"Advertising",
            "type":"Services"
        }
    ],
    "sg:phone":"+33 2 38 34 54 44",
    "sg:postcode":"45340",
    "sg:province":"Centre",
    "sg:tags":[
        "display",
        "displays"
    ],
    "wof:name":"Etablissements Lebrun S.a.",
    "wof:placetype":"venue"
},
  "geometry": {"coordinates":[2.424045,48.067005],"type":"Point"}
}