{
  "type": "Feature",
  "properties": {
    "iso:country":"FR",
    "sg:address":"57 Rue De Salonique 95100 Argenteuil",
    "sg:classifiers":[
        {
            "category":"Shopping",
            "subcategory":"Computers & Home Electronics",
            "type":"Retail Goods"
        }
    ],
    "sg:phone":"+33 1 34 11 42 00",
    "sg:postcode":"95100",
    "sg:province":"Ile de France",
    "sg:tags":[
        "household",
        "appliance",
        "telecommunication",
        "audio-visual"
    ],
    "wof:name":"Aesd Technologies",
    "wof:placetype":"venue"
},
  "geometry": {"coordinates":[2.20897,48.952221],"type":"Point"}
}