{
  "type": "Feature",
  "properties": {
    "addr:full":"87, Rue de la Gare, 01230 Tenay Rhone-Alpes 01230",
    "addr:housenumber":"87",
    "addr:postcode":"01230;01230",
    "addr:street":"Rue De La Gare;Rhone-Alpes",
    "iso:country":"FR",
    "sg:address":"87, Rue de la Gare, 01230 Tenay",
    "sg:orig_category":"Non-Classified Establishments",
    "sg:phone":"+33 4 74 36 51 22",
    "sg:postcode":"01230",
    "sg:province":"Rhone-Alpes",
    "wof:name":"Galizzi David",
    "wof:placetype":"venue"
},
  "geometry": {"coordinates":[5.505408,45.920864],"type":"Point"}
}