{
  "type": "Feature",
  "properties": {
    "addr:full":"170 Rue Du Fgb St Denis 75010 Paris Ile de France 75010",
    "addr:housenumber":"170",
    "addr:postcode":"75010;75010",
    "addr:street":"Rue Du Fgb St Denis",
    "iso:country":"FR",
    "sg:address":"170 Rue Du Fgb St Denis 75010 Paris",
    "sg:classifiers":[
        {
            "category":"Travel",
            "subcategory":"Hotels & Motels",
            "type":"Entertainment"
        }
    ],
    "sg:phone":"+33 1 40 35 32 45",
    "sg:postcode":"75010",
    "sg:province":"Ile de France",
    "sg:tags":[
        "hotels",
        "business",
        "restaurant"
    ],
    "wof:name":"Bar Brasserie De La Gare",
    "wof:placetype":"venue"
},
  "geometry": {"coordinates":[2.358515,48.87352],"type":"Point"}
}