{
  "type": "Feature",
  "properties": {
    "addr:full":"5 Rue De Verdun 67000 Strasbourg Strasbourg Alsace 67000",
    "addr:housenumber":"5",
    "addr:postcode":"67000;67000",
    "addr:street":"Rue De Verdun",
    "iso:country":"FR",
    "sg:address":"5 Rue De Verdun 67000 Strasbourg",
    "sg:city":"Strasbourg",
    "sg:classifiers":[
        {
            "category":"Bakery",
            "type":"Food & Drink"
        }
    ],
    "sg:phone":"+33 3 88 60 22 67",
    "sg:postcode":"67000",
    "sg:province":"Alsace",
    "sg:tags":[
        "cake",
        "product",
        "related",
        "bread"
    ],
    "wof:name":"Chez Patrick",
    "wof:placetype":"venue"
},
  "geometry": {"coordinates":[7.770417,48.585655],"type":"Point"}
}