{
  "type": "Feature",
  "properties": {
    "addr:full":"20 Rue Louis Desprez 10200 Bar Sur Aube Champagne 10200",
    "addr:housenumber":"20",
    "addr:postcode":"10200;10200",
    "addr:street":"Rue Louis Desprez",
    "iso:country":"FR",
    "sg:address":"20 Rue Louis Desprez 10200 Bar Sur Aube",
    "sg:classifiers":[
        {
            "category":"Manufacturing",
            "subcategory":"Chemicals & Compounds",
            "type":"Manufacturing & Wholesale Goods"
        }
    ],
    "sg:phone":"+33 3 25 27 01 30",
    "sg:postcode":"10200",
    "sg:province":"Champagne",
    "sg:tags":[
        "pharmaceutical",
        "energy",
        "chemistry",
        "-",
        "by-product"
    ],
    "wof:name":"Compagnie Petroliere De L'est (cpe) Ets Lacombe",
    "wof:placetype":"venue"
},
  "geometry": {"coordinates":[4.71094,48.221661],"type":"Point"}
}