{
  "type": "Feature",
  "properties": {
    "addr:full":"3bis, Rte de Neuville, 59250 Halluin Nord Pas-de-Calais",
    "addr:housenumber":"3bis",
    "addr:postcode":"59250",
    "addr:street":"Rte De Neuville",
    "iso:country":"FR",
    "sg:address":"3bis, Rte de Neuville, 59250 Halluin",
    "sg:orig_category":"Non-Classified Establishments",
    "sg:phone":"+33 3 20 37 94 12",
    "sg:province":"Nord Pas-de-Calais",
    "wof:name":"Metalys S.a.r.l.",
    "wof:placetype":"venue"
},
  "geometry": {"coordinates":[3.129802,50.778793],"type":"Point"}
}