{
  "type": "Feature",
  "properties": {
    "iso:country":"FR",
    "sg:address":"21, Av. Grand Cavalier, 06600 Antibes",
    "sg:orig_category":"Non-Classified Establishments",
    "sg:phone":"+33 4 93 34 54 68",
    "sg:province":"Provence-Alpes-C\u00f4te d'Azur",
    "wof:name":"Laser Epil S.a.r.l.",
    "wof:placetype":"venue"
},
  "geometry": {"coordinates":[7.121296,43.581997],"type":"Point"}
}