{
  "type": "Feature",
  "properties": {
    "iso:country":"FR",
    "sg:address":"8 rue Edouard Branly 93600 Aulnay sous Bois",
    "sg:classifiers":[
        {
            "category":"Professional",
            "subcategory":"Engineering",
            "type":"Services"
        }
    ],
    "sg:phone":"+33 1 48 19 87 15",
    "sg:province":"Ile de France",
    "sg:tags":[
        "screw",
        "aircraft",
        "bolt"
    ],
    "wof:name":"Ets J.p. Audinel S.a.",
    "wof:placetype":"venue"
},
  "geometry": {"coordinates":[2.483804,48.944363],"type":"Point"}
}