{
  "type": "Feature",
  "properties": {
    "addr:full":"ZI les Alouettes Saint R\u00e9my Ch\u00e2lon sur Sa\u00f4ne C\u00e9dex Outre-Mer 71103",
    "addr:postcode":"71103",
    "addr:street":"Zi Les Alouettes Saint Re\u0301My Cha\u0302Lon;Outre-Mer",
    "iso:country":"FR",
    "sg:address":"ZI les Alouettes Saint R\u00e9my",
    "sg:city":"Ch\u00e2lon sur Sa\u00f4ne C\u00e9dex",
    "sg:orig_category":"Non-Classified Establishments",
    "sg:phone":"+33 3 85 44 63 33",
    "sg:postcode":"71103",
    "sg:province":"Outre-Mer",
    "wof:name":"Chabert Duval Group S.a.",
    "wof:placetype":"venue"
},
  "geometry": {"coordinates":[-93.77623,32.491989],"type":"Point"}
}