{
  "type": "Feature",
  "properties": {
    "addr:full":"Tour Soci\u00e9t\u00e9 G\u00e9n\u00e9rale; Paris; 92972 Pays de Loire",
    "addr:postcode":"92972",
    "iso:country":"FR",
    "sg:address":"Tour Soci\u00e9t\u00e9 G\u00e9n\u00e9rale; Paris; 92972",
    "sg:classifiers":[
        {
            "category":"Banks & Credit Unions",
            "subcategory":"Bank",
            "type":"Services"
        }
    ],
    "sg:phone":"+33 1 42 14 20 00",
    "sg:province":"Pays de Loire",
    "wof:name":"Soci\u00e9t\u00e9 G\u00e9n\u00e9rale",
    "wof:placetype":"venue"
},
  "geometry": {"coordinates":[2.208,48.896141],"type":"Point"}
}