{
  "type": "Feature",
  "properties": {
    "addr:full":"Av. de la Gare C\u00e9ret Languedoc-Roussillon 66400",
    "addr:postcode":"66400",
    "addr:street":"Av. De La Gare",
    "iso:country":"FR",
    "sg:address":"Av. de la Gare",
    "sg:city":"C\u00e9ret",
    "sg:orig_category":"Non-Classified Establishments",
    "sg:phone":"+33 4 68 87 47 53",
    "sg:postcode":"66400",
    "sg:province":"Languedoc-Roussillon",
    "wof:name":"Dulcesol France S.a.r.l.",
    "wof:placetype":"venue"
},
  "geometry": {"coordinates":[2.741905,42.493114],"type":"Point"}
}