{
  "type": "Feature",
  "properties": {
    "addr:full":"401 Rue Des Champagnes 73290 La Motte Servolex Rhone-Alpes 73290",
    "addr:housenumber":"401",
    "addr:postcode":"73290;73290",
    "addr:street":"Rue Des Champagnes;Rhone-Alpes",
    "iso:country":"FR",
    "sg:address":"401 Rue Des Champagnes 73290 La Motte Servolex",
    "sg:classifiers":[
        {
            "category":"Wholesale",
            "subcategory":"Meat",
            "type":"Manufacturing & Wholesale Goods"
        }
    ],
    "sg:phone":"+33 4 79 62 38 37",
    "sg:postcode":"73290",
    "sg:province":"Rhone-Alpes",
    "sg:tags":[
        "food",
        "cooked",
        "product",
        "related"
    ],
    "wof:name":"Ets Billon Sa",
    "wof:placetype":"venue"
},
  "geometry": {"coordinates":[5.886565,45.59008],"type":"Point"}
}