{
  "type": "Feature",
  "properties": {
    "iso:country":"FR",
    "sg:address":"rue Gruner 42230 ROCHE LA MOLIERE",
    "sg:classifiers":[
        {
            "category":"Building & Trades",
            "subcategory":"Construction",
            "type":"Services"
        }
    ],
    "sg:phone":"+33 4 77 90 65 52",
    "sg:province":"Rhone-Alpes",
    "sg:tags":[
        "bulk",
        "mixing",
        "good",
        "hopper",
        "pourable"
    ],
    "wof:name":"Gilibert Henri Sa",
    "wof:placetype":"venue"
},
  "geometry": {"coordinates":[4.328533,45.438152],"type":"Point"}
}