{
  "type": "Feature",
  "properties": {
    "iso:country":"FR",
    "sg:address":"35 avenue Pierre 1er de Serbie 75008 Paris",
    "sg:classifiers":[
        {
            "category":"Shopping",
            "subcategory":"Clothing, Apparel, & Fashions",
            "type":"Retail Goods"
        }
    ],
    "sg:phone":"+33 1 56 89 08 99",
    "sg:province":"Ile de France",
    "sg:tags":[
        "sportswear"
    ],
    "wof:name":"Concept D Articles Personnalise Cap International S.a.",
    "wof:placetype":"venue"
},
  "geometry": {"coordinates":[2.299405,48.867695],"type":"Point"}
}