{
  "type": "Feature",
  "properties": {
    "iso:country":"FR",
    "sg:address":"8, Rue du 1er Mai, 80460 Friaucourt",
    "sg:orig_category":"Unclassifiable Establishments",
    "sg:phone":"+33 3 22 30 74 26",
    "sg:province":"Picardie",
    "wof:name":"Legay Joostens S.a.r.l.",
    "wof:placetype":"venue"
},
  "geometry": {"coordinates":[1.449713,50.100746],"type":"Point"}
}