{
  "type": "Feature",
  "properties": {
    "addr:full":"ZA Seilhac Limousin 19700",
    "addr:postcode":"19700",
    "addr:street":"Za Seilhac Limousin",
    "iso:country":"FR",
    "sg:address":"ZA",
    "sg:city":"Seilhac",
    "sg:orig_category":"Non-Classified Establishments",
    "sg:phone":"+33 5 55 27 91 63",
    "sg:postcode":"19700",
    "sg:province":"Limousin",
    "wof:name":"Etablissements Badefort Et Fils S.a.",
    "wof:placetype":"venue"
},
  "geometry": {"coordinates":[1.685315,45.34177],"type":"Point"}
}