{
  "type": "Feature",
  "properties": {
    "addr:full":"6, Rue de Ladrie - ZI de la Pilaterie - B\u00e2t. C, 59290 Wasquehal Nord Pas-de-Calais",
    "addr:housenumber":"6;ba\u0302t c",
    "addr:postcode":"59290",
    "addr:street":"Rue De Ladrie Zi De La Pilaterie",
    "iso:country":"FR",
    "sg:address":"6, Rue de Ladrie - ZI de la Pilaterie - B\u00e2t. C, 59290 Wasquehal",
    "sg:orig_category":"Unclassifiable Establishments",
    "sg:phone":"+33 3 20 72 33 00",
    "sg:province":"Nord Pas-de-Calais",
    "wof:name":"Babout S.a.",
    "wof:placetype":"venue"
},
  "geometry": {"coordinates":[3.132085,50.669395],"type":"Point"}
}