{
  "type": "Feature",
  "properties": {
    "addr:full":"Rue Denis Papin - ZI de Brais Saint Nazaire Pays de Loire 44600",
    "addr:postcode":"44600",
    "addr:street":"Rue Denis Papin Zi De Brais Saint Nazaire Pays",
    "iso:country":"FR",
    "sg:address":"Rue Denis Papin - ZI de Brais",
    "sg:city":"Saint Nazaire",
    "sg:orig_category":"Non-Classified Establishments",
    "sg:phone":"+33 2 40 01 26 20",
    "sg:postcode":"44600",
    "sg:province":"Pays de Loire",
    "wof:name":"S.m.a. S.a.r.l. - Sellerie Maroquinerie De L'armor",
    "wof:placetype":"venue"
},
  "geometry": {"coordinates":[-2.278494,47.240322],"type":"Point"}
}