{
  "type": "Feature",
  "properties": {
    "iso:country":"FR",
    "sg:address":"161, Av. Gabriel P\u00e9ri, 69120 Vaulx en Velin",
    "sg:orig_category":"Non-Classified Establishments",
    "sg:phone":"+33 4 78 80 88 25",
    "sg:postcode":"69120",
    "sg:province":"Rhone-Alpes",
    "wof:name":"Mills S.a.",
    "wof:placetype":"venue"
},
  "geometry": {"coordinates":[4.91002,45.771622],"type":"Point"}
}