{
  "type": "Feature",
  "properties": {
    "addr:full":"1, Rue du Gardon, 26700 Pierrelatte Rhone-Alpes 26700",
    "addr:housenumber":"1",
    "addr:postcode":"26700;26700",
    "addr:street":"Rue Du Gardon",
    "iso:country":"FR",
    "sg:address":"1, Rue du Gardon, 26700 Pierrelatte",
    "sg:orig_category":"Non-Classified Establishments",
    "sg:phone":"+33 4 75 96 52 20",
    "sg:postcode":"26700",
    "sg:province":"Rhone-Alpes",
    "wof:name":"Air Liquide",
    "wof:placetype":"venue"
},
  "geometry": {"coordinates":[4.708196,44.367214],"type":"Point"}
}