{
  "type": "Feature",
  "properties": {
    "addr:full":"26 Rue Des Cascades 60500 Chantilly Picardie 60500",
    "addr:housenumber":"26",
    "addr:postcode":"60500;60500",
    "addr:street":"Rue Des Cascades",
    "iso:country":"FR",
    "sg:address":"26 Rue Des Cascades 60500 Chantilly",
    "sg:classifiers":[
        {
            "category":"Utilities",
            "subcategory":"Electric",
            "type":"Services"
        }
    ],
    "sg:phone":"+33 810 24 75 91",
    "sg:postcode":"60500",
    "sg:province":"Picardie",
    "sg:tags":[
        "electricity",
        "raw",
        "energy",
        "material"
    ],
    "wof:name":"Electricite De France (edf)",
    "wof:placetype":"venue"
},
  "geometry": {"coordinates":[2.468997,49.195816],"type":"Point"}
}