{
  "type": "Feature",
  "properties": {
    "addr:full":"23 Boulevard Fran\u00e7ois Grosso Nice Provence-Alpes-C\u00f4te d'Azur 06000",
    "addr:housenumber":"23",
    "addr:postcode":"06000",
    "addr:street":"Boulevard Franc\u0327Ois Grosso Nice",
    "iso:country":"FR",
    "sg:address":"23 Boulevard Fran\u00e7ois Grosso",
    "sg:city":"Nice",
    "sg:classifiers":[
        {
            "category":"Banks & Credit Unions",
            "subcategory":"Financial Services",
            "type":"Services"
        }
    ],
    "sg:phone":"+33 4 93 44 50 53",
    "sg:postcode":"06000",
    "sg:province":"Provence-Alpes-C\u00f4te d'Azur",
    "sg:tags":[
        "banking",
        "finance",
        "insurance"
    ],
    "wof:name":"Boy De La Tour",
    "wof:placetype":"venue"
},
  "geometry": {"coordinates":[7.251554,43.696091],"type":"Point"}
}