{
  "type": "Feature",
  "properties": {
    "iso:country":"FR",
    "sg:address":"B\u00e2t. Fr\u00eat",
    "sg:city":"Lyon",
    "sg:orig_category":"Unclassifiable Establishments",
    "sg:phone":"+33 4 72 22 71 15",
    "sg:postcode":"69120",
    "sg:province":"Rhone-Alpes",
    "wof:name":"Nippon Express S.a.",
    "wof:placetype":"venue"
},
  "geometry": {"coordinates":[4.916895,45.779022],"type":"Point"}
}