{
  "type": "Feature",
  "properties": {
    "addr:full":"7, Rue de l'Artisanat, 42390 Villars Rhone-Alpes",
    "addr:housenumber":"7",
    "addr:postcode":"42390",
    "addr:street":"Rue De L'Artisanat",
    "iso:country":"FR",
    "sg:address":"7, Rue de l'Artisanat, 42390 Villars",
    "sg:orig_category":"Unclassifiable Establishments",
    "sg:phone":"+33 4 77 92 84 20",
    "sg:province":"Rhone-Alpes",
    "wof:name":"S.e.c.a. S.a. - Soci\u00e9t\u00e9 D'expertise Comptable Audit",
    "wof:placetype":"venue"
},
  "geometry": {"coordinates":[4.365364,45.469875],"type":"Point"}
}