{
  "type": "Feature",
  "properties": {
    "addr:full":"37, Av. Gabriel Peri, 92500 Rueil Malmaison Ile de France",
    "addr:postcode":"92500",
    "addr:street":"37 Av. Gabriel Peri",
    "iso:country":"FR",
    "sg:address":"37, Av. Gabriel Peri, 92500 Rueil Malmaison",
    "sg:orig_category":"Non-Classified Establishments",
    "sg:phone":"+33 1 47 08 66 88",
    "sg:province":"Ile de France",
    "wof:name":"Laboratoires Amido S.a.",
    "wof:placetype":"venue"
},
  "geometry": {"coordinates":[2.18954,48.884109],"type":"Point"}
}