{
  "type": "Feature",
  "properties": {
    "iso:country":"FR",
    "sg:address":"B.P. 40203, 57005 Metz C\u00e9dex 1^^7, Rue Clovis, 57000 Metz",
    "sg:orig_category":"Non-Classified Establishments",
    "sg:phone":"+33 3 87 66 41 26",
    "sg:province":"Lorraine",
    "wof:name":"Reprographic S.a.",
    "wof:placetype":"venue"
},
  "geometry": {"coordinates":[6.183995,49.07645],"type":"Point"}
}