{
  "type": "Feature",
  "properties": {
    "addr:full":"Route Nationale 7 Village D Ent Ero 84700 Sorgues Midi Pyr\u00e9n\u00e9es",
    "addr:housenumber":"ero",
    "addr:postcode":"84700",
    "addr:street":"Route Nationale 7 Village D Ent",
    "iso:country":"FR",
    "sg:address":"Route Nationale 7 Village D Ent Ero 84700 Sorgues",
    "sg:classifiers":[
        {
            "category":"Manufacturing",
            "subcategory":"Glass & Minerals",
            "type":"Manufacturing & Wholesale Goods"
        }
    ],
    "sg:phone":"+33 4 90 39 12 88",
    "sg:province":"Midi Pyr\u00e9n\u00e9es",
    "sg:tags":[
        "building",
        "material"
    ],
    "wof:name":"Creation Emballage Conditionnement Design (cecd)",
    "wof:placetype":"venue"
},
  "geometry": {"coordinates":[4.873481,44.00827],"type":"Point"}
}