{
  "type": "Feature",
  "properties": {
    "addr:full":"9 Rue Colbert 13001 Marseille Poitou-Charentes",
    "addr:housenumber":"9",
    "addr:postcode":"13001",
    "addr:street":"Rue Colbert",
    "iso:country":"FR",
    "sg:address":"9 Rue Colbert 13001 Marseille",
    "sg:orig_category":"Business travel Food and Related Products HOTELS: RESTAURANTS",
    "sg:phone":"+33 4 91 90 76 12",
    "sg:province":"Poitou-Charentes",
    "wof:name":"La Truffe Noire Sa",
    "wof:placetype":"venue"
},
  "geometry": {"coordinates":[5.374698,43.299118],"type":"Point"}
}