{
  "type": "Feature",
  "properties": {
    "addr:full":"49 Bd Jean Jaur\u00e8s 91100 Corbeil Essonnes Ile de France",
    "addr:housenumber":"49",
    "addr:postcode":"91100",
    "addr:street":"Bd Jean Jaure\u0300S",
    "iso:country":"FR",
    "sg:address":"49 Bd Jean Jaur\u00e8s 91100 Corbeil Essonnes",
    "sg:classifiers":[
        {
            "category":"Manufacturing",
            "subcategory":"Wood Products",
            "type":"Manufacturing & Wholesale Goods"
        }
    ],
    "sg:phone":"+33 1 64 96 17 04",
    "sg:province":"Ile de France",
    "sg:tags":[
        "professional",
        "furniture"
    ],
    "wof:name":"Goncalves Ets",
    "wof:placetype":"venue"
},
  "geometry": {"coordinates":[2.46414,48.608189],"type":"Point"}
}