{
  "type": "Feature",
  "properties": {
    "addr:full":"10, Rue Pasteur, 74300 Cluses Rhone-Alpes",
    "addr:housenumber":"10",
    "addr:postcode":"74300",
    "addr:street":"Rue Pasteur",
    "iso:country":"FR",
    "sg:address":"10, Rue Pasteur, 74300 Cluses",
    "sg:orig_category":"Non-Classified Establishments",
    "sg:phone":"+33 4 50 98 70 40",
    "sg:province":"Rhone-Alpes",
    "wof:name":"Synergie S.a.",
    "wof:placetype":"venue"
},
  "geometry": {"coordinates":[6.580153,46.058674],"type":"Point"}
}