{
  "type": "Feature",
  "properties": {
    "addr:full":"28, Chemin de Lachat, 73100 Brison Saint Innocent Rhone-Alpes",
    "addr:housenumber":"28",
    "addr:postcode":"73100;innocent rhone-alpes",
    "addr:street":"Chemin De Lachat",
    "iso:country":"FR",
    "sg:address":"28, Chemin de Lachat, 73100 Brison Saint Innocent",
    "sg:orig_category":"Non-Classified Establishments",
    "sg:phone":"+33 4 79 54 33 64",
    "sg:province":"Rhone-Alpes",
    "wof:name":"M\u00e9tallerie Jean Fontaine S.a.r.l.",
    "wof:placetype":"venue"
},
  "geometry": {"coordinates":[5.889152,45.726257],"type":"Point"}
}