{
  "type": "Feature",
  "properties": {
    "addr:full":"76740 La Chapelle sur Dun Haute Normandie 76740",
    "addr:housenumber":"76740",
    "addr:postcode":"76740",
    "addr:street":"La;Normandie",
    "iso:country":"FR",
    "sg:address":"76740 La Chapelle sur Dun",
    "sg:orig_category":"Non-Classified Establishments",
    "sg:phone":"+33 2 35 97 65 18",
    "sg:postcode":"76740",
    "sg:province":"Haute Normandie",
    "wof:name":"Atelier Sottevillais E.u.r.l.",
    "wof:placetype":"venue"
},
  "geometry": {"coordinates":[0.85039,49.865616],"type":"Point"}
}