{
  "type": "Feature",
  "properties": {
    "addr:full":"8, Voie Industrielle - ZI, 60350 Attichy Picardie",
    "addr:housenumber":"8",
    "addr:postcode":"60350",
    "addr:street":"Voie Industrielle Zi",
    "iso:country":"FR",
    "sg:address":"8, Voie Industrielle - ZI, 60350 Attichy",
    "sg:orig_category":"Unclassifiable Establishments",
    "sg:phone":"+33 3 44 42 94 43",
    "sg:province":"Picardie",
    "wof:name":"Open Date France S.a.r.l.",
    "wof:placetype":"venue"
},
  "geometry": {"coordinates":[3.04568,49.413269],"type":"Point"}
}