{
  "type": "Feature",
  "properties": {
    "iso:country":"FR",
    "sg:address":"10/80, Rue des Halles, 75001 Paris",
    "sg:orig_category":"Unclassifiable Establishments",
    "sg:phone":"+33 1 42 33 24 24",
    "sg:province":"Ile de France",
    "wof:name":"Cegma Topo S.a.",
    "wof:placetype":"venue"
},
  "geometry": {"coordinates":[2.346862,48.859707],"type":"Point"}
}