{
  "type": "Feature",
  "properties": {
    "iso:country":"FR",
    "sg:address":"18, Rue de Montbazon, 37260 Monts",
    "sg:city":"Monts",
    "sg:orig_category":"Non-Classified Establishments",
    "sg:phone":"+33 2 47 21 10 10",
    "sg:postcode":"37260",
    "sg:province":"Centre",
    "wof:name":"Astraz\u00e9n\u00e9ca Monts S.a.",
    "wof:placetype":"venue"
},
  "geometry": {"coordinates":[0.676767,47.285732],"type":"Point"}
}