{
  "type": "Feature",
  "properties": {
    "addr:full":"ZA la Poste Saint Romain de Popey Rhone-Alpes 69490",
    "addr:postcode":"69490",
    "addr:street":"Za La;Saint;Rhone-Alpes",
    "iso:country":"FR",
    "sg:address":"ZA la Poste",
    "sg:city":"Saint Romain de Popey",
    "sg:orig_category":"Unclassifiable Establishments",
    "sg:phone":"+33 4 74 05 88 44",
    "sg:postcode":"69490",
    "sg:province":"Rhone-Alpes",
    "wof:name":"Barlerin S.a.",
    "wof:placetype":"venue"
},
  "geometry": {"coordinates":[4.53066,45.847424],"type":"Point"}
}