{
  "type": "Feature",
  "properties": {
    "addr:full":"21, Rue Laffitte, 75317 Paris C\u00e9dex 09 \u00cele-de-France",
    "addr:housenumber":"21",
    "addr:postcode":"75317",
    "addr:street":"Rue Laffitte",
    "iso:country":"FR",
    "sg:address":"21, Rue Laffitte, 75317 Paris C\u00e9dex 09",
    "sg:orig_category":"Non-Classified Establishments",
    "sg:phone":"+33 1 56 03 34 56",
    "sg:province":"\u00cele-de-France",
    "wof:name":"Les Editions M\u00e9deric S.a.r.l.",
    "wof:placetype":"venue"
},
  "geometry": {"coordinates":[2.33764,48.873333],"type":"Point"}
}