{
  "type": "Feature",
  "properties": {
    "iso:country":"FR",
    "sg:address":"65, Rue L\u00e9on Fournier - Villejoint , 41000 Blois",
    "sg:city":"Blois",
    "sg:orig_category":"Unclassifiable Establishments",
    "sg:phone":"+33 2 54 78 50 08",
    "sg:postcode":"41000",
    "sg:province":"Centre",
    "wof:name":"Soci\u00e9t\u00e9 D'exploitation De L'entreprise Baptiste S.a.r.l.",
    "wof:placetype":"venue"
},
  "geometry": {"coordinates":[1.321581,47.612255],"type":"Point"}
}