{
  "type": "Feature",
  "properties": {
    "addr:full":"Rue Des Sables 54425 Pulnoy Lorraine",
    "addr:postcode":"54425",
    "addr:street":"Rue Des Sables",
    "iso:country":"FR",
    "sg:address":"Rue Des Sables 54425 Pulnoy",
    "sg:classifiers":[
        {
            "category":"Professional",
            "subcategory":"Engineering",
            "type":"Services"
        }
    ],
    "sg:phone":"+33 3 83 29 49 79",
    "sg:province":"Lorraine",
    "sg:tags":[
        "machine",
        "-",
        "mechanical"
    ],
    "wof:name":"Compagnie Industrielle D'applications Thermiques (ciat)",
    "wof:placetype":"venue"
},
  "geometry": {"coordinates":[6.252135,48.707119],"type":"Point"}
}