{
  "type": "Feature",
  "properties": {
    "addr:full":"5 Zone Industrielle La Combe 39150 ST PIERRE Franche Comt\u00e9 39150",
    "addr:housenumber":"5",
    "addr:postcode":"39150;39150",
    "addr:street":"Zone Industrielle La Combe;Franche Comte\u0301",
    "iso:country":"FR",
    "sg:address":"5 Zone Industrielle La Combe 39150 ST PIERRE",
    "sg:classifiers":[
        {
            "category":"Manufacturing",
            "subcategory":"Glass & Minerals",
            "type":"Manufacturing & Wholesale Goods"
        }
    ],
    "sg:phone":"+33 3 84 60 82 61",
    "sg:postcode":"39150",
    "sg:province":"Franche Comt\u00e9",
    "sg:tags":[
        "frame"
    ],
    "wof:name":"Lunetterie Blandeau S.a.r.l.",
    "wof:placetype":"venue"
},
  "geometry": {"coordinates":[5.828622,46.495934],"type":"Point"}
}