{
  "type": "Feature",
  "properties": {
    "addr:full":"B.P. 1236, 76177 Rouen C\u00e9dex^^16, Rue Henri Rivi\u00e8re, 76000 Rouen Haute Normandie",
    "addr:postcode":"76177;76000",
    "addr:street":"B.P. 1236;Rue Henri Rivie\u0300Re;Haute Normandie",
    "iso:country":"FR",
    "sg:address":"B.P. 1236, 76177 Rouen C\u00e9dex^^16, Rue Henri Rivi\u00e8re, 76000 Rouen",
    "sg:orig_category":"Non-Classified Establishments",
    "sg:phone":"+33 2 35 52 62 00",
    "sg:province":"Haute Normandie",
    "wof:name":"Gaz De France - Direction Production Transport - R\u00e9gion Normandie",
    "wof:placetype":"venue"
},
  "geometry": {"coordinates":[1.08933,49.44038],"type":"Point"}
}