{
  "type": "Feature",
  "properties": {
    "iso:country":"FR",
    "sg:address":"1320, Rte de Doissin - Les Queux , 38110 Saint Victor de Cessieu",
    "sg:orig_category":"Non-Classified Establishments",
    "sg:phone":"+33 4 74 33 22 20",
    "sg:postcode":"38110",
    "sg:province":"Rhone-Alpes",
    "wof:name":"Cazan S.a.r.l.",
    "wof:placetype":"venue"
},
  "geometry": {"coordinates":[5.454585,45.52478],"type":"Point"}
}