{
  "type": "Feature",
  "properties": {
    "addr:full":"B.P. 8, 79230 Prahecq^^Rte de Niort, 79230 Prahecq Poitou-Charentes 79230",
    "addr:housenumber":"8",
    "addr:postcode":"79230;79230;79230",
    "addr:street":"B.P.;Niort",
    "iso:country":"FR",
    "sg:address":"B.P. 8, 79230 Prahecq^^Rte de Niort, 79230 Prahecq",
    "sg:orig_category":"Non-Classified Establishments",
    "sg:phone":"+33 5 49 26 41 11",
    "sg:postcode":"79230",
    "sg:province":"Poitou-Charentes",
    "wof:name":"Baudouin Mortier S.a.",
    "wof:placetype":"venue"
},
  "geometry": {"coordinates":[-0.320059,46.202774],"type":"Point"}
}