{
  "type": "Feature",
  "properties": {
    "addr:full":"43, Rue de Saint Amand, 59100 Roubaix Nord Pas-de-Calais 59100",
    "addr:housenumber":"43",
    "addr:postcode":"59100;59100",
    "addr:street":"Rue De Saint Amand",
    "iso:country":"FR",
    "sg:address":"43, Rue de Saint Amand, 59100 Roubaix",
    "sg:orig_category":"Non-Classified Establishments",
    "sg:phone":"+33 3 20 73 48 60",
    "sg:postcode":"59100",
    "sg:province":"Nord Pas-de-Calais",
    "wof:name":"Accunord S.a.r.l.",
    "wof:placetype":"venue"
},
  "geometry": {"coordinates":[3.188276,50.687824],"type":"Point"}
}