{
  "type": "Feature",
  "properties": {
    "addr:full":"17, Rue du G\u00e9n\u00e9ral Leclerc, 91160 Longjumeau Ile de France",
    "addr:housenumber":"17",
    "addr:postcode":"91160;ile",
    "addr:street":"Rue Du Ge\u0301Ne\u0301Ral Leclerc",
    "iso:country":"FR",
    "sg:address":"17, Rue du G\u00e9n\u00e9ral Leclerc, 91160 Longjumeau",
    "sg:orig_category":"Unclassifiable Establishments",
    "sg:phone":"+33 1 69 10 15 21",
    "sg:province":"Ile de France",
    "wof:name":"M\u00e9caways S.a.r.l.",
    "wof:placetype":"venue"
},
  "geometry": {"coordinates":[2.298586,48.695988],"type":"Point"}
}