{
  "type": "Feature",
  "properties": {
    "addr:full":"B.P. 29, 45390 Puiseaux C\u00e9dex^^6, Chemin de la Messe, 45390 Puiseaux Aulnay-la-Rivi\u00e8re Centre 45390",
    "addr:housenumber":"aulnay-la-rivie\u0300re",
    "addr:postcode":"45390;45390;45390",
    "addr:street":"B.P. 29;Chemin De La Messe",
    "iso:country":"FR",
    "sg:address":"B.P. 29, 45390 Puiseaux C\u00e9dex^^6, Chemin de la Messe, 45390 Puiseaux",
    "sg:city":"Aulnay-la-Rivi\u00e8re",
    "sg:orig_category":"Non-Classified Establishments",
    "sg:phone":"+33 2 38 33 61 72",
    "sg:postcode":"45390",
    "sg:province":"Centre",
    "wof:name":"Lhuisset Languille S.a.r.l.",
    "wof:placetype":"venue"
},
  "geometry": {"coordinates":[2.469916,48.20422],"type":"Point"}
}