{
  "type": "Feature",
  "properties": {
    "addr:full":"B.P. 90, 01400 Ch\u00e2tillon sur Chalaronne^^Z.I. Sud, 01400 Ch\u00e2tillon sur Chalaronne Rhone-Alpes",
    "addr:postcode":"01400;01400",
    "addr:street":"B.P. 90;Chalaronne^^Z I. Sud",
    "iso:country":"FR",
    "sg:address":"B.P. 90, 01400 Ch\u00e2tillon sur Chalaronne^^Z.I. Sud, 01400 Ch\u00e2tillon sur Chalaronne",
    "sg:orig_category":"Non-Classified Establishments",
    "sg:phone":"+33 4 74 55 01 55",
    "sg:province":"Rhone-Alpes",
    "wof:name":"Gallet S.a.",
    "wof:placetype":"venue"
},
  "geometry": {"coordinates":[4.99054,46.134781],"type":"Point"}
}