{
  "type": "Feature",
  "properties": {
    "addr:full":"1 Rue Paul Sabatier 76120 Le Grand Quevilly Haute Normandie",
    "addr:housenumber":"1",
    "addr:postcode":"76120",
    "addr:street":"Rue Paul Sabatier;Haute Normandie",
    "iso:country":"FR",
    "sg:address":"1 Rue Paul Sabatier 76120 Le Grand Quevilly",
    "sg:classifiers":[
        {
            "category":"Professional",
            "type":"Services"
        }
    ],
    "sg:phone":"+33 2 35 68 50 50",
    "sg:province":"Haute Normandie",
    "sg:tags":[
        "transport",
        "road"
    ],
    "wof:name":"Dms Dca Maury Shipp",
    "wof:placetype":"venue"
},
  "geometry": {"coordinates":[1.051227,49.41708],"type":"Point"}
}