{
  "type": "Feature",
  "properties": {
    "iso:country":"FR",
    "sg:address":"29, Rue Pascal, 01100 Oyonnax",
    "sg:orig_category":"Non-Classified Establishments",
    "sg:phone":"+33 4 74 77 31 25",
    "sg:province":"Rhone-Alpes",
    "wof:name":"Jeamaud S.a.r.l.",
    "wof:placetype":"venue"
},
  "geometry": {"coordinates":[5.65377,46.262421],"type":"Point"}
}