{
  "type": "Feature",
  "properties": {
    "addr:full":"38 Rue De Bassano 75008 Paris Ile de France",
    "addr:housenumber":"38",
    "addr:postcode":"75008",
    "addr:street":"Rue De Bassano",
    "iso:country":"FR",
    "sg:address":"38 Rue De Bassano 75008 Paris",
    "sg:classifiers":[
        {
            "category":"Utilities",
            "subcategory":"Telephone",
            "type":"Services"
        }
    ],
    "sg:phone":"+33 1 45 50 27 70",
    "sg:province":"Ile de France",
    "sg:tags":[
        "telecommunication"
    ],
    "wof:name":"Megacom",
    "wof:placetype":"venue"
},
  "geometry": {"coordinates":[2.298908,48.87011],"type":"Point"}
}