{
  "type": "Feature",
  "properties": {
    "addr:full":"99, Rue Charles Tournemure, 33300 Bordeaux Bordeaux Aquitaine 33300",
    "addr:housenumber":"99",
    "addr:postcode":"33300;33300",
    "addr:street":"Rue Charles Tournemure",
    "iso:country":"FR",
    "sg:address":"99, Rue Charles Tournemure, 33300 Bordeaux",
    "sg:city":"Bordeaux",
    "sg:orig_category":"Unclassifiable Establishments",
    "sg:phone":"+33 5 56 39 80 28",
    "sg:postcode":"33300",
    "sg:province":"Aquitaine",
    "wof:name":"Provost S.a.",
    "wof:placetype":"venue"
},
  "geometry": {"coordinates":[-0.570819,44.873638],"type":"Point"}
}