{
  "type": "Feature",
  "properties": {
    "addr:full":"Rue De Seine Zone D'Activit\u00e9s 78260 Ach\u00e8res Ile de France 78260",
    "addr:postcode":"78260;ile;78260",
    "addr:street":"Rue De Seine Zone D'Activite \u0301S;France",
    "iso:country":"FR",
    "sg:address":"Rue De Seine Zone D'Activit\u00e9s 78260 Ach\u00e8res",
    "sg:classifiers":[
        {
            "category":"Transit Center",
            "subcategory":"Freight",
            "type":"Transportation"
        }
    ],
    "sg:phone":"+33 1 39 11 45 30",
    "sg:postcode":"78260",
    "sg:province":"Ile de France",
    "sg:tags":[
        "metallurgy",
        "pipe",
        "metalworking",
        "sheet"
    ],
    "wof:name":"Etcm Ensemblier",
    "wof:placetype":"venue"
},
  "geometry": {"coordinates":[2.063635,48.966446],"type":"Point"}
}