{
  "type": "Feature",
  "properties": {
    "addr:full":"Avenue Henri Adnot 60200 Compiegne Picardie 60200",
    "addr:postcode":"60200;60200",
    "addr:street":"Avenue Henri Adnot;Picardie",
    "iso:country":"FR",
    "sg:address":"Avenue Henri Adnot 60200 Compiegne",
    "sg:classifiers":[
        {
            "category":"Shopping",
            "subcategory":"Clothing, Apparel, & Fashions",
            "type":"Retail Goods"
        }
    ],
    "sg:phone":"+33 3 44 23 42 45",
    "sg:postcode":"60200",
    "sg:province":"Picardie",
    "sg:tags":[
        "textile",
        "clothing",
        "clothes"
    ],
    "wof:name":"Dginie",
    "wof:placetype":"venue"
},
  "geometry": {"coordinates":[2.787655,49.388321],"type":"Point"}
}