{
  "type": "Feature",
  "properties": {
    "iso:country":"FR",
    "sg:address":"43 Bis, Quai Vauban, 66000 Perpignan",
    "sg:orig_category":"Unclassifiable Establishments",
    "sg:phone":"+33 4 68 85 39 38",
    "sg:province":"Languedoc-Roussillon",
    "wof:name":"Etablissement Espi S.a.r.l.",
    "wof:placetype":"venue"
},
  "geometry": {"coordinates":[2.892583,42.700039],"type":"Point"}
}