{
  "type": "Feature",
  "properties": {
    "iso:country":"FR",
    "sg:address":"Lieu dit la Mare de Caillemare 27310 Saint Ouen de Thouberville",
    "sg:orig_category":"Unclassifiable Establishments",
    "sg:phone":"+33 2 32 56 22 16",
    "sg:province":"Haute Normandie",
    "wof:name":"Mariette S.a.",
    "wof:placetype":"venue"
},
  "geometry": {"coordinates":[0.800651,49.3181],"type":"Point"}
}