{
  "type": "Feature",
  "properties": {
    "iso:country":"FR",
    "sg:address":"16, Rue Charles B\u00e9lign\u00e9, 52200 Langres",
    "sg:orig_category":"Unclassifiable Establishments",
    "sg:phone":"+33 3 25 87 04 45",
    "sg:province":"Champagne",
    "wof:name":"Etablissements H. B\u00e9lign\u00e9 Et Fils S.a.",
    "wof:placetype":"venue"
},
  "geometry": {"coordinates":[5.332345,47.865173],"type":"Point"}
}