{
  "type": "Feature",
  "properties": {
    "addr:full":"655, Rue Marcelle Griffon - ZI de Riorges, 42150 Riorges Rhone-Alpes 42150",
    "addr:housenumber":"655",
    "addr:postcode":"42150;42150",
    "addr:street":"Rue Marcelle Griffon Zi De Riorges;Rhone-Alpes",
    "iso:country":"FR",
    "sg:address":"655, Rue Marcelle Griffon - ZI de Riorges, 42150 Riorges",
    "sg:orig_category":"Unclassifiable Establishments",
    "sg:phone":"+33 4 77 44 80 00",
    "sg:postcode":"42150",
    "sg:province":"Rhone-Alpes",
    "wof:name":"H.p.c. S.a.r.l. - Habillement Production Conseil",
    "wof:placetype":"venue"
},
  "geometry": {"coordinates":[-86.29319,36.802971],"type":"Point"}
}