{
  "type": "Feature",
  "properties": {
    "iso:country":"FR",
    "sg:address":"2 Bis Rue Des Coulons 59420 Mouvaux",
    "sg:classifiers":[
        {
            "category":"Professional",
            "subcategory":"Engineering",
            "type":"Services"
        }
    ],
    "sg:phone":"+33 3 20 24 34 94",
    "sg:postcode":"59420",
    "sg:province":"Nord Pas-de-Calais",
    "sg:tags":[
        "machine",
        "-",
        "mechanical"
    ],
    "wof:name":"Cofrino Froid Et Machines Sa",
    "wof:placetype":"venue"
},
  "geometry": {"coordinates":[3.137404,50.714973],"type":"Point"}
}