{
  "type": "Feature",
  "properties": {
    "iso:country":"FR",
    "sg:address":"23 Rue Gustave Nickles 93170 Bagnolet",
    "sg:classifiers":[
        {
            "category":"Professional",
            "subcategory":"Engineering",
            "type":"Services"
        }
    ],
    "sg:phone":"+33 1 48 58 58 43",
    "sg:postcode":"93170",
    "sg:province":"Ile de France",
    "sg:tags":[
        "machine",
        "-",
        "mechanical"
    ],
    "wof:name":"Service Depannage Frigorifique Sedef (sedef)",
    "wof:placetype":"venue"
},
  "geometry": {"coordinates":[2.41924,48.858223],"type":"Point"}
}