{
  "type": "Feature",
  "properties": {
    "iso:country":"FR",
    "sg:address":"Rue Du Grand Communale 25210 Bonn\u00e9tage",
    "sg:classifiers":[
        {
            "category":"Manufacturing",
            "subcategory":"Metals",
            "type":"Manufacturing & Wholesale Goods"
        }
    ],
    "sg:phone":"+33 3 81 68 94 69",
    "sg:postcode":"25210",
    "sg:province":"Franche Comt\u00e9",
    "sg:tags":[
        "metallurgy",
        "metalworking",
        "processing"
    ],
    "wof:name":"Avipo",
    "wof:placetype":"venue"
},
  "geometry": {"coordinates":[6.726445,47.184029],"type":"Point"}
}