{
  "type": "Feature",
  "properties": {
    "iso:country":"FR",
    "sg:address":"4, Rue du G\u00e9n\u00e9ral Lanrezac, 75017 Paris",
    "sg:orig_category":"Non-Classified Establishments",
    "sg:phone":"+33 1 55 37 24 00",
    "sg:postcode":"75017",
    "sg:province":"Ile de France",
    "wof:name":"Crit\u00e8re S.a.",
    "wof:placetype":"venue"
},
  "geometry": {"coordinates":[2.293871,48.875854],"type":"Point"}
}