{
  "type": "Feature",
  "properties": {
    "addr:full":"rte Toulouse 09290 Mas d'Azil (Le) Midi Pyr\u00e9n\u00e9es 09290",
    "addr:postcode":"09290;09290",
    "addr:street":"Rte Toulouse",
    "iso:country":"FR",
    "sg:address":"rte Toulouse 09290 Mas d'Azil (Le)",
    "sg:classifiers":[
        {
            "category":"Home & Garden",
            "subcategory":"Furniture",
            "type":"Retail Goods"
        }
    ],
    "sg:phone":"+33 5 61 69 90 39",
    "sg:postcode":"09290",
    "sg:province":"Midi Pyr\u00e9n\u00e9es",
    "sg:tags":[
        "household",
        "wood"
    ],
    "wof:name":"Meubles Verge",
    "wof:placetype":"venue"
},
  "geometry": {"coordinates":[0.251594,43.186344],"type":"Point"}
}