{
  "type": "Feature",
  "properties": {
    "addr:full":"Avenue Du Port Nouveau Port 83240 Cavalaire Sur Mer Champagne",
    "addr:postcode":"83240",
    "addr:street":"Avenue Du Port Nouveau Port",
    "iso:country":"FR",
    "sg:address":"Avenue Du Port Nouveau Port 83240 Cavalaire Sur Mer",
    "sg:classifiers":[
        {
            "category":"Autos & Motor Vehicles",
            "subcategory":"Boat Sales",
            "type":"Retail Goods"
        }
    ],
    "sg:phone":"+33 4 94 64 01 32",
    "sg:province":"Champagne",
    "sg:tags":[
        "equipment",
        "transport"
    ],
    "wof:name":"Marine Plaisance",
    "wof:placetype":"venue"
},
  "geometry": {"coordinates":[6.533275,43.17392],"type":"Point"}
}