{
  "type": "Feature",
  "properties": {
    "iso:country":"FR",
    "sg:address":"B.P. 307, 38523 Saint Egr\u00e8ve C\u00e9dex^^ZI la Californie, 38120 Fontanil Cornillon",
    "sg:orig_category":"Non-Classified Establishments",
    "sg:phone":"+33 4 76 58 20 00",
    "sg:postcode":"38120",
    "sg:province":"Rhone-Alpes",
    "wof:name":"Bourgey Montreuil Dauphin\u00e9 S.a.s.",
    "wof:placetype":"venue"
},
  "geometry": {"coordinates":[5.68088,45.232937],"type":"Point"}
}