{
  "type": "Feature",
  "properties": {
    "addr:full":"3 Rue Tilleul 59840 P\u00e9renchies Nord Pas-de-Calais 59840",
    "addr:housenumber":"3",
    "addr:postcode":"59840;59840",
    "addr:street":"Rue Tilleul",
    "iso:country":"FR",
    "sg:address":"3 Rue Tilleul 59840 P\u00e9renchies",
    "sg:classifiers":[
        {
            "category":"Shopping",
            "type":"Retail Goods"
        }
    ],
    "sg:phone":"+33 3 20 22 29 29",
    "sg:postcode":"59840",
    "sg:province":"Nord Pas-de-Calais",
    "sg:tags":[
        "metallurgy",
        "finished",
        "-",
        "metalworking",
        "metallic"
    ],
    "wof:name":"Ets Hector Bouveur Sa",
    "wof:placetype":"venue"
},
  "geometry": {"coordinates":[2.97472,50.660858],"type":"Point"}
}