{
  "type": "Feature",
  "properties": {
    "addr:full":"01330 Lapeyrouse Rhone-Alpes",
    "addr:postcode":"01330",
    "iso:country":"FR",
    "sg:address":"01330 Lapeyrouse",
    "sg:orig_category":"Non-Classified Establishments",
    "sg:phone":"+33 4 74 98 14 51",
    "sg:province":"Rhone-Alpes",
    "wof:name":"Guillemin P\u00e8re Et Fils S.a.r.l.",
    "wof:placetype":"venue"
},
  "geometry": {"coordinates":[4.97581,45.982723],"type":"Point"}
}