{
  "type": "Feature",
  "properties": {
    "addr:full":"1 Avenue Michel Jourdan 06150 Cannes La Bocca Franche Comt\u00e9",
    "addr:housenumber":"1",
    "addr:postcode":"06150",
    "addr:street":"Avenue Michel Jourdan;Franche Comte\u0301",
    "iso:country":"FR",
    "sg:address":"1 Avenue Michel Jourdan 06150 Cannes La Bocca",
    "sg:classifiers":[
        {
            "category":"Professional",
            "subcategory":"Advertising",
            "type":"Services"
        }
    ],
    "sg:phone":"+33 4 92 19 50 55",
    "sg:province":"Franche Comt\u00e9",
    "sg:tags":[
        "communication",
        "medium"
    ],
    "wof:name":"Dif Promotion",
    "wof:placetype":"venue"
},
  "geometry": {"coordinates":[6.979522,43.54948],"type":"Point"}
}