{
  "type": "Feature",
  "properties": {
    "addr:full":"av Pierre de Luxembourg 84230 Ch\u00e2teauneuf du Pape Centre",
    "addr:postcode":"84230",
    "addr:street":"Av Pierre De Luxembourg",
    "iso:country":"FR",
    "sg:address":"av Pierre de Luxembourg 84230 Ch\u00e2teauneuf du Pape",
    "sg:classifiers":[
        {
            "category":"Food Court",
            "type":"Food & Drink"
        }
    ],
    "sg:phone":"+33 4 90 83 58 35",
    "sg:province":"Centre",
    "sg:tags":[
        "product",
        "related"
    ],
    "wof:name":"Bouachon (maison)",
    "wof:placetype":"venue"
},
  "geometry": {"coordinates":[4.835357,44.051167],"type":"Point"}
}