{
  "type": "Feature",
  "properties": {
    "iso:country":"FR",
    "sg:address":"2, Rue du Ried, 68270 Wittenheim",
    "sg:city":"Wittenheim",
    "sg:orig_category":"Unclassifiable Establishments",
    "sg:phone":"+33 3 89 52 22 22",
    "sg:postcode":"68270",
    "sg:province":"Alsace",
    "wof:name":"Triperie Goepper S.a.",
    "wof:placetype":"venue"
},
  "geometry": {"coordinates":[7.310222,47.820763],"type":"Point"}
}