{
  "type": "Feature",
  "properties": {
    "addr:full":"10 Rue Des Metiers Zi Melou 81100 Castres Midi Pyr\u00e9n\u00e9es",
    "addr:housenumber":"10",
    "addr:postcode":"81100",
    "addr:street":"Rue Des Metiers Zi",
    "iso:country":"FR",
    "sg:address":"10 Rue Des Metiers Zi Melou 81100 Castres",
    "sg:classifiers":[
        {
            "category":"Manufacturing",
            "subcategory":"Wood Products",
            "type":"Manufacturing & Wholesale Goods"
        }
    ],
    "sg:phone":"+33 5 63 59 78 28",
    "sg:province":"Midi Pyr\u00e9n\u00e9es",
    "sg:tags":[
        "professional",
        "furniture"
    ],
    "wof:name":"Sarl Sph Societe De Production Hoteliere",
    "wof:placetype":"venue"
},
  "geometry": {"coordinates":[2.257356,43.56094],"type":"Point"}
}