{
  "type": "Feature",
  "properties": {
    "addr:full":"Rue Alfred Dornier Dampierre sur Salon Franche Comt\u00e9 70180",
    "addr:postcode":"70180",
    "addr:street":"Rue Alfred Dornier Dampierre;Comte\u0301",
    "iso:country":"FR",
    "sg:address":"Rue Alfred Dornier",
    "sg:city":"Dampierre sur Salon",
    "sg:orig_category":"Unclassifiable Establishments",
    "sg:phone":"+33 3 84 67 70 70",
    "sg:postcode":"70180",
    "sg:province":"Franche Comt\u00e9",
    "wof:name":"Brisard Dampierre S.a.",
    "wof:placetype":"venue"
},
  "geometry": {"coordinates":[5.6785,47.555706],"type":"Point"}
}