{
  "type": "Feature",
  "properties": {
    "addr:full":"Rue Marc Seguin 57365 Ennery Lorraine",
    "addr:postcode":"57365",
    "addr:street":"Rue Marc Seguin",
    "iso:country":"FR",
    "sg:address":"Rue Marc Seguin 57365 Ennery",
    "sg:classifiers":[
        {
            "category":"Professional",
            "type":"Services"
        }
    ],
    "sg:phone":"+33 3 87 73 64 64",
    "sg:province":"Lorraine",
    "sg:tags":[
        "transport",
        "road"
    ],
    "wof:name":"Logi T R F",
    "wof:placetype":"venue"
},
  "geometry": {"coordinates":[6.212215,49.231831],"type":"Point"}
}