{
  "type": "Feature",
  "properties": {
    "iso:country":"FR",
    "sg:address":"282, Bd Saint Germain, 75007 Paris",
    "sg:orig_category":"Non-Classified Establishments",
    "sg:phone":"+33 1 44 11 05 00",
    "sg:province":"Ile de France",
    "wof:name":"Plaut Consulting S.a.s.",
    "wof:placetype":"venue"
},
  "geometry": {"coordinates":[2.320273,48.861683],"type":"Point"}
}