{
  "type": "Feature",
  "properties": {
    "iso:country":"FR",
    "sg:address":"66 Rue Mar\u00e9chal Vauban 06300 Nice",
    "sg:classifiers":[
        {
            "category":"Professional",
            "subcategory":"Engineering",
            "type":"Services"
        }
    ],
    "sg:phone":"+33 4 93 55 56 61",
    "sg:province":"Outre-Mer",
    "sg:tags":[
        "machine",
        "-",
        "mechanical"
    ],
    "wof:name":"Satgem Sarl",
    "wof:placetype":"venue"
},
  "geometry": {"coordinates":[7.291043,43.710976],"type":"Point"}
}