{
  "type": "Feature",
  "properties": {
    "addr:full":"121, Rue Chanzy Hellemmes, 59260 Lille Nord Pas-de-Calais",
    "addr:housenumber":"121",
    "addr:postcode":"59260",
    "addr:street":"Rue Chanzy Hellemmes",
    "iso:country":"FR",
    "sg:address":"121, Rue Chanzy Hellemmes, 59260 Lille",
    "sg:orig_category":"Unclassifiable Establishments",
    "sg:phone":"+33 3 20 67 59 83",
    "sg:province":"Nord Pas-de-Calais",
    "wof:name":"G\u00e9niop.com S.a.r.l.",
    "wof:placetype":"venue"
},
  "geometry": {"coordinates":[3.11705,50.614567],"type":"Point"}
}