{
  "type": "Feature",
  "properties": {
    "iso:country":"FR",
    "sg:address":"23 R Taine 75012 Paris",
    "sg:classifiers":[
        {
            "category":"Wholesale",
            "subcategory":"Medical Equipment & Supplies",
            "type":"Manufacturing & Wholesale Goods"
        }
    ],
    "sg:phone":"+33 1 53 46 62 72",
    "sg:postcode":"75012",
    "sg:province":"Ile de France",
    "sg:tags":[
        "instrument",
        "health",
        "-",
        "precision"
    ],
    "wof:name":"M. Akoun Sidney",
    "wof:placetype":"venue"
},
  "geometry": {"coordinates":[2.392619,48.838387],"type":"Point"}
}