{
  "type": "Feature",
  "properties": {
    "addr:full":"route de caszaubon 32440 EAUZE Midi Pyr\u00e9n\u00e9es 32440",
    "addr:postcode":"32440;32440",
    "addr:street":"Route De Caszaubon",
    "iso:country":"FR",
    "sg:address":"route de caszaubon 32440 EAUZE",
    "sg:classifiers":[
        {
            "category":"Insurance",
            "subcategory":"Insurance Agent",
            "type":"Services"
        }
    ],
    "sg:phone":"+33 5 62 08 14 14",
    "sg:postcode":"32440",
    "sg:province":"Midi Pyr\u00e9n\u00e9es",
    "sg:tags":[
        "alcohol"
    ],
    "wof:name":"Ste Des Armagnacs Sempe Sa",
    "wof:placetype":"venue"
},
  "geometry": {"coordinates":[0.086315,43.948906],"type":"Point"}
}