{
  "type": "Feature",
  "properties": {
    "addr:full":"12 Rue Des Artisans 21220 Gevrey Chambertin B\u00e9vy Bourgogne 21220",
    "addr:housenumber":"12",
    "addr:postcode":"21220;21220",
    "addr:street":"Rue Des Artisans;Bourgogne",
    "iso:country":"FR",
    "sg:address":"12 Rue Des Artisans 21220 Gevrey Chambertin",
    "sg:city":"B\u00e9vy",
    "sg:classifiers":[
        {
            "category":"Wholesale",
            "subcategory":"Meat",
            "type":"Manufacturing & Wholesale Goods"
        }
    ],
    "sg:phone":"+33 3 80 58 52 52",
    "sg:postcode":"21220",
    "sg:province":"Bourgogne",
    "sg:tags":[
        "food",
        "cooked",
        "product",
        "related"
    ],
    "wof:name":"Roux Et Cie",
    "wof:placetype":"venue"
},
  "geometry": {"coordinates":[4.99828,47.227253],"type":"Point"}
}