{
  "type": "Feature",
  "properties": {
    "addr:full":"7 Rue De T\u00e9h\u00e9ran 75008 Paris Ile de France 75008",
    "addr:housenumber":"7",
    "addr:postcode":"75008;75008",
    "addr:street":"Rue De Te\u0301He\u0301Ran",
    "iso:country":"FR",
    "sg:address":"7 Rue De T\u00e9h\u00e9ran 75008 Paris",
    "sg:orig_category":"Bread and cakes Cereals and grains Drinks Food and Related Products",
    "sg:phone":"+33 1 44 35 20 20",
    "sg:postcode":"75008",
    "sg:province":"Ile de France",
    "wof:name":"Groupe Danone Sa",
    "wof:placetype":"venue"
},
  "geometry": {"coordinates":[2.312569,48.875824],"type":"Point"}
}