{
  "type": "Feature",
  "properties": {
    "iso:country":"FR",
    "sg:address":"B.P. 144, 29105 Quimper C\u00e9dex^^Le Grand Guelen, 29000 Quimper",
    "sg:city":"Quimper",
    "sg:orig_category":"Non-Classified Establishments",
    "sg:phone":"+33 2 98 52 81 81",
    "sg:postcode":"29000",
    "sg:province":"Bretagne",
    "wof:name":"Le Coz Et Mah\u00e9 S.a.",
    "wof:placetype":"venue"
},
  "geometry": {"coordinates":[-4.107947,47.99469],"type":"Point"}
}