{
  "type": "Feature",
  "properties": {
    "iso:country":"FR",
    "sg:address":"77 Bis, Av. de la Lib\u00e9ration, 33440 Ambar\u00e8s et Lagrave",
    "sg:city":"Ambar\u00e8s-et-Lagrave",
    "sg:orig_category":"Unclassifiable Establishments",
    "sg:phone":"+33 5 56 77 78 79",
    "sg:postcode":"33440",
    "sg:province":"Aquitaine",
    "wof:name":"Bernard Paysage S.a.r.l.",
    "wof:placetype":"venue"
},
  "geometry": {"coordinates":[-0.473569,44.932671],"type":"Point"}
}