{
  "type": "Feature",
  "properties": {
    "addr:full":"B.P. 40, 28260 Anet^^Rte Oullins - ZI, 28260 Anet Anet Centre 28260",
    "addr:postcode":"28260;28260;28260",
    "addr:street":"B.P. 40;Zi",
    "iso:country":"FR",
    "sg:address":"B.P. 40, 28260 Anet^^Rte Oullins - ZI, 28260 Anet",
    "sg:city":"Anet",
    "sg:orig_category":"Non-Classified Establishments",
    "sg:phone":"+33 2 37 41 92 76",
    "sg:postcode":"28260",
    "sg:province":"Centre",
    "wof:name":"S.a.c.m. S.a. - Soci\u00e9t\u00e9 Anetaise Constructions M\u00e9talliques",
    "wof:placetype":"venue"
},
  "geometry": {"coordinates":[1.386779,48.824169],"type":"Point"}
}