{
  "type": "Feature",
  "properties": {
    "addr:full":"129 avenue d'aubi\u00e8re 63800 Cournon P\u00e9rignat-sur-Allier Auvergne 63800",
    "addr:housenumber":"129",
    "addr:postcode":"63800;pe\u0301rignat-sur-allier;63800",
    "addr:street":"Avenue D'Aubie \u0300Re",
    "iso:country":"FR",
    "sg:address":"129 avenue d'aubi\u00e8re 63800 Cournon",
    "sg:city":"P\u00e9rignat-sur-Allier",
    "sg:classifiers":[
        {
            "category":"Utilities",
            "subcategory":"Water",
            "type":"Services"
        }
    ],
    "sg:phone":"+33 4 73 26 79 42",
    "sg:postcode":"63800",
    "sg:province":"Auvergne",
    "sg:tags":[
        "drinking",
        "plant",
        "disinfection"
    ],
    "wof:name":"Technimat Entreprise S.a.r.l.",
    "wof:placetype":"venue"
},
  "geometry": {"coordinates":[3.159597,45.749783],"type":"Point"}
}