{
  "type": "Feature",
  "properties": {
    "iso:country":"FR",
    "sg:address":"269 Rue Du Marechal Juin",
    "sg:city":"Industrielle 77000 Vaux Le Penil",
    "sg:classifiers":[
        {
            "category":"Shopping",
            "subcategory":"Computers & Home Electronics",
            "type":"Retail Goods"
        }
    ],
    "sg:phone":"+33 1 60 56 61 26",
    "sg:postcode":"77000",
    "sg:province":"Ile de France",
    "sg:tags":[
        "electronic",
        "electrical",
        "equipment"
    ],
    "wof:name":"Etablissements Henri Peignen Sa",
    "wof:placetype":"venue"
},
  "geometry": {"coordinates":[2.664085,48.539577],"type":"Point"}
}