{
  "type": "Feature",
  "properties": {
    "addr:full":"9 Sebastopol; Toulouse; 31000 Midi Pyr\u00e9n\u00e9es",
    "addr:housenumber":"9",
    "addr:postcode":"31000",
    "addr:street":"Sebastopol Toulouse",
    "iso:country":"FR",
    "sg:address":"9",
    "sg:city":"Sebastopol; Toulouse; 31000",
    "sg:classifiers":[
        {
            "category":"Travel",
            "subcategory":"Travel Agent",
            "type":"Entertainment"
        }
    ],
    "sg:phone":"+33 3356184593",
    "sg:province":"Midi Pyr\u00e9n\u00e9es",
    "wof:name":"Wta",
    "wof:placetype":"venue"
},
  "geometry": {"coordinates":[1.428979,43.612133],"type":"Point"}
}