{
  "type": "Feature",
  "properties": {
    "addr:full":"Rte de Perpignan Narbonne Languedoc-Roussillon 11100",
    "addr:postcode":"11100",
    "addr:street":"Rte De Perpignan",
    "iso:country":"FR",
    "sg:address":"Rte de Perpignan",
    "sg:city":"Narbonne",
    "sg:orig_category":"Unclassifiable Establishments",
    "sg:phone":"+33 4 68 41 75 80",
    "sg:postcode":"11100",
    "sg:province":"Languedoc-Roussillon",
    "wof:name":"Etablissements Gayraud S.a.",
    "wof:placetype":"venue"
},
  "geometry": {"coordinates":[2.98622,43.165375],"type":"Point"}
}