{
  "type": "Feature",
  "properties": {
    "addr:full":"11, Rue du Sentier, 75002 Paris Ile de France 75002",
    "addr:housenumber":"11",
    "addr:postcode":"75002;75002",
    "addr:street":"Rue Du Sentier",
    "iso:country":"FR",
    "sg:address":"11, Rue du Sentier, 75002 Paris",
    "sg:orig_category":"Non-Classified Establishments",
    "sg:phone":"+33 1 40 39 99 99",
    "sg:postcode":"75002",
    "sg:province":"Ile de France",
    "wof:name":"Bernard Textiles S.a.r.l.",
    "wof:placetype":"venue"
},
  "geometry": {"coordinates":[2.345395,48.86842],"type":"Point"}
}