{
  "type": "Feature",
  "properties": {
    "addr:full":"Route Chalain 39570 Vevy Franche Comt\u00e9 39570",
    "addr:postcode":"39570;39570",
    "addr:street":"Route Chalain;Franche Comte\u0301",
    "iso:country":"FR",
    "sg:address":"Route Chalain 39570 Vevy",
    "sg:classifiers":[
        {
            "category":"Food & Beverages",
            "subcategory":"Dairy",
            "type":"Retail Goods"
        }
    ],
    "sg:phone":"+33 3 84 48 48 00",
    "sg:postcode":"39570",
    "sg:province":"Franche Comt\u00e9",
    "sg:tags":[
        "product",
        "related"
    ],
    "wof:name":"Juragruyere Sa",
    "wof:placetype":"venue"
},
  "geometry": {"coordinates":[5.516002,46.599735],"type":"Point"}
}