{
  "type": "Feature",
  "properties": {
    "iso:country":"FR",
    "sg:address":"Rte d'Yvrac",
    "sg:city":"Chasseneuil sur Bonnieure",
    "sg:orig_category":"Unclassifiable Establishments",
    "sg:phone":"+33 5 45 39 58 35",
    "sg:postcode":"16260",
    "sg:province":"Poitou-Charentes",
    "wof:name":"Groupe Pinault Bois Et Mat\u00e9riaux S.a.",
    "wof:placetype":"venue"
},
  "geometry": {"coordinates":[0.4502,45.824471],"type":"Point"}
}