{
  "type": "Feature",
  "properties": {
    "addr:full":"Zone Portuaire Nogent sur Oise C\u00e9dex Picardie 60183",
    "addr:postcode":"60183",
    "addr:street":"Nogent;Picardie",
    "iso:country":"FR",
    "sg:address":"Zone Portuaire",
    "sg:city":"Nogent sur Oise C\u00e9dex",
    "sg:orig_category":"Non-Classified Establishments",
    "sg:phone":"+33 3 44 55 88 88",
    "sg:postcode":"60183",
    "sg:province":"Picardie",
    "wof:name":"Stockhausen S.a.r.l.",
    "wof:placetype":"venue"
},
  "geometry": {"coordinates":[2.493418,49.273518],"type":"Point"}
}