{
  "type": "Feature",
  "properties": {
    "iso:country":"FR",
    "sg:address":"17 avenue de Champagne 51200 Epernay",
    "sg:classifiers":[
        {
            "category":"Food & Beverages",
            "subcategory":"Liquor & Beverages",
            "type":"Retail Goods"
        }
    ],
    "sg:phone":"+33 3 26 59 50 50",
    "sg:postcode":"51200",
    "sg:province":"Champagne",
    "sg:tags":[
        "champagne"
    ],
    "wof:name":"Champagne Charles Lafitte Sa",
    "wof:placetype":"venue"
},
  "geometry": {"coordinates":[3.959064,49.043385],"type":"Point"}
}