{
  "type": "Feature",
  "properties": {
    "addr:full":"23 Rue Cavaillon 94648 Rungis Cedex Languedoc-Roussillon",
    "addr:housenumber":"23",
    "addr:postcode":"94648;cedex",
    "addr:street":"Rue Cavaillon",
    "iso:country":"FR",
    "sg:address":"23 Rue Cavaillon 94648 Rungis Cedex",
    "sg:orig_category":"Games and entertainment Horticulture Miscellaneous Products",
    "sg:phone":"+33 1 46 86 05 20",
    "sg:province":"Languedoc-Roussillon",
    "wof:name":"Renault Distribution",
    "wof:placetype":"venue"
},
  "geometry": {"coordinates":[2.35325,48.751419],"type":"Point"}
}