{
  "type": "Feature",
  "properties": {
    "addr:full":"Rpt Leclerc 47200 Marmande Marmande Aquitaine 47200",
    "addr:postcode":"47200;47200",
    "addr:street":"Rpt Leclerc",
    "iso:country":"FR",
    "sg:address":"Rpt Leclerc 47200 Marmande",
    "sg:city":"Marmande",
    "sg:classifiers":[
        {
            "category":"Manufacturing",
            "subcategory":"Paper Products",
            "type":"Manufacturing & Wholesale Goods"
        }
    ],
    "sg:phone":"+33 5 53 64 04 07",
    "sg:postcode":"47200",
    "sg:province":"Aquitaine",
    "sg:tags":[
        "finished",
        "cardboard",
        "-"
    ],
    "wof:name":"Comptoir Des Peintures Et Revetements Du Marmandais",
    "wof:placetype":"venue"
},
  "geometry": {"coordinates":[0.159371,44.502258],"type":"Point"}
}