{
  "type": "Feature",
  "properties": {
    "iso:country":"FR",
    "sg:address":"5, Rte de la Tuilerie - Marchon , 01100 Oyonnax",
    "sg:orig_category":"Unclassifiable Establishments",
    "sg:phone":"+33 4 74 77 97 07",
    "sg:postcode":"01100",
    "sg:province":"Rhone-Alpes",
    "wof:name":"A.d.a.p.e.i. Atelier Prot\u00e9g\u00e9",
    "wof:placetype":"venue"
},
  "geometry": {"coordinates":[5.64399,46.24971],"type":"Point"}
}