{
  "type": "Feature",
  "properties": {
    "iso:country":"FR",
    "sg:address":"Challes 01140 St Didier Sur Chalaronne",
    "sg:classifiers":[
        {
            "category":"Shopping",
            "type":"Retail Goods"
        }
    ],
    "sg:phone":"+33 4 74 04 03 25",
    "sg:postcode":"01140",
    "sg:province":"Rhone-Alpes",
    "sg:tags":[
        "metallurgy",
        "finished",
        "-",
        "metalworking",
        "metallic"
    ],
    "wof:name":"Chaudronneries Chalaronne Sarl",
    "wof:placetype":"venue"
},
  "geometry": {"coordinates":[4.793405,46.179062],"type":"Point"}
}