{
  "type": "Feature",
  "properties": {
    "addr:full":"42-44 Rue Du 11 Novembre 38200 Vienne Rhone-Alpes 38200",
    "addr:housenumber":"42-44",
    "addr:postcode":"38200;38200",
    "addr:street":"Rue Du 11 Novembre",
    "iso:country":"FR",
    "sg:address":"42-44 Rue Du 11 Novembre 38200 Vienne",
    "sg:classifiers":[
        {
            "category":"Farming",
            "subcategory":"Livestock Farm",
            "type":"Manufacturing & Wholesale Goods"
        }
    ],
    "sg:phone":"+33 4 74 78 82 00",
    "sg:postcode":"38200",
    "sg:province":"Rhone-Alpes",
    "sg:tags":[
        "grain",
        "agriculture",
        "cereal"
    ],
    "wof:name":"La Dauphinoise",
    "wof:placetype":"venue"
},
  "geometry": {"coordinates":[4.867322,45.517544],"type":"Point"}
}