{
  "type": "Feature",
  "properties": {
    "addr:full":"110, Rue Chaynes Aimable, 01540 Vonnas Rhone-Alpes 01540",
    "addr:housenumber":"110",
    "addr:postcode":"01540;01540",
    "addr:street":"Rue Chaynes Aimable",
    "iso:country":"FR",
    "sg:address":"110, Rue Chaynes Aimable, 01540 Vonnas",
    "sg:orig_category":"Non-Classified Establishments",
    "sg:phone":"+33 4 74 50 04 46",
    "sg:postcode":"01540",
    "sg:province":"Rhone-Alpes",
    "wof:name":"Entreprise Daujat Jacques",
    "wof:placetype":"venue"
},
  "geometry": {"coordinates":[4.97927,46.218891],"type":"Point"}
}