{
  "type": "Feature",
  "properties": {
    "iso:country":"FR",
    "sg:address":"Rue du Maine",
    "sg:city":"Wittenheim",
    "sg:orig_category":"Unclassifiable Establishments",
    "sg:phone":"+33 3 89 51 05 00",
    "sg:postcode":"68270",
    "sg:province":"Alsace",
    "wof:name":"3d Eclairage E.u.r.l.",
    "wof:placetype":"venue"
},
  "geometry": {"coordinates":[7.310745,47.811363],"type":"Point"}
}