{
  "type": "Feature",
  "properties": {
    "iso:country":"FR",
    "sg:address":"B.P. 206, 93103 Montreuil C\u00e9dex^^29/31, Rue du Bois Vert, 93100 Montreuil",
    "sg:orig_category":"Non-Classified Establishments",
    "sg:phone":"+33 1 48 70 48 50",
    "sg:province":"Ile de France",
    "wof:name":"Europlex S.a.",
    "wof:placetype":"venue"
},
  "geometry": {"coordinates":[2.442661,48.864525],"type":"Point"}
}