{
  "type": "Feature",
  "properties": {
    "iso:country":"FR",
    "sg:address":"B.P. 68, 55500 Velaines^^Rte de Tronville, 55500 Velaines",
    "sg:orig_category":"Non-Classified Establishments",
    "sg:phone":"+33 3 29 78 18 12",
    "sg:province":"Lorraine",
    "wof:name":"Lormatem S.a.",
    "wof:placetype":"venue"
},
  "geometry": {"coordinates":[5.324955,48.686077],"type":"Point"}
}