{
  "type": "Feature",
  "properties": {
    "addr:full":"35 Boulevard De Beaubourg La Francilienne N 10 77184 Emerainville Ile de France 77184",
    "addr:housenumber":"35;10",
    "addr:postcode":"77184;77184",
    "addr:street":"Boulevard De Beaubourg La Francilienne N;Ile De France",
    "iso:country":"FR",
    "sg:address":"35 Boulevard De Beaubourg La Francilienne N 10 77184 Emerainville",
    "sg:classifiers":[
        {
            "category":"Shopping",
            "subcategory":"Computers & Home Electronics",
            "type":"Retail Goods"
        }
    ],
    "sg:phone":"+33 1 60 95 12 12",
    "sg:postcode":"77184",
    "sg:province":"Ile de France",
    "sg:tags":[
        "electronic",
        "electrical",
        "equipment"
    ],
    "wof:name":"La Mecanique Electrique",
    "wof:placetype":"venue"
},
  "geometry": {"coordinates":[2.622175,48.811619],"type":"Point"}
}