{
  "type": "Feature",
  "properties": {
    "addr:full":"Ch de Scierie Villeneuve de Marsan Aquitaine 40190",
    "addr:postcode":"40190",
    "addr:street":"Ch De Scierie",
    "iso:country":"FR",
    "sg:address":"Ch de Scierie",
    "sg:city":"Villeneuve de Marsan",
    "sg:orig_category":"Unclassifiable Establishments",
    "sg:phone":"+33 5 58 45 21 78",
    "sg:postcode":"40190",
    "sg:province":"Aquitaine",
    "wof:name":"Soci\u00e9t\u00e9 D'exploitation Des Etablissements Bernard S.a.r.l.",
    "wof:placetype":"venue"
},
  "geometry": {"coordinates":[-0.306944,43.884399],"type":"Point"}
}