{
  "type": "Feature",
  "properties": {
    "addr:full":"Zac Roitelet 54730 Gorcy Lorraine 54730",
    "addr:postcode":"54730;54730",
    "addr:street":"Zac Roitelet",
    "iso:country":"FR",
    "sg:address":"Zac Roitelet 54730 Gorcy",
    "sg:classifiers":[
        {
            "category":"Utilities",
            "subcategory":"Electric",
            "type":"Services"
        }
    ],
    "sg:phone":"+33 3 82 26 95 95",
    "sg:postcode":"54730",
    "sg:province":"Lorraine",
    "sg:tags":[
        "electricity",
        "electronic",
        "electrical",
        "equipment"
    ],
    "wof:name":"Conception Cablage Controle Electronique",
    "wof:placetype":"venue"
},
  "geometry": {"coordinates":[5.684655,49.534069],"type":"Point"}
}