{
  "type": "Feature",
  "properties": {
    "addr:full":"B.P. 1 Clermont Cr\u00e9ans C\u00e9dex^^La Baulini\u00e8re 72200 Clermont Cr\u00e9ans Pays de Loire 72200",
    "addr:postcode":"72200;72200",
    "addr:street":"B.P. 1;Baulinie\u0300Re;Cre\u0301Ans",
    "iso:country":"FR",
    "sg:address":"B.P. 1",
    "sg:city":"Clermont Cr\u00e9ans C\u00e9dex^^La Baulini\u00e8re 72200 Clermont Cr\u00e9ans",
    "sg:orig_category":"Non-Classified Establishments",
    "sg:phone":"+33 2 43 94 37 15",
    "sg:postcode":"72200",
    "sg:province":"Pays de Loire",
    "wof:name":"Brunort Productions",
    "wof:placetype":"venue"
},
  "geometry": {"coordinates":[-0.016454,47.717445],"type":"Point"}
}