{
  "type": "Feature",
  "properties": {
    "iso:country":"FR",
    "sg:address":"23, Rue du Chemin Vert, 78610 Le Perray en Yvelines",
    "sg:orig_category":"Unclassifiable Establishments",
    "sg:phone":"+33 1 30 46 35 35",
    "sg:province":"Ile de France",
    "wof:name":"Nordic Pneu S.a.r.l.",
    "wof:placetype":"venue"
},
  "geometry": {"coordinates":[1.856347,48.702583],"type":"Point"}
}