{
  "type": "Feature",
  "properties": {
    "iso:country":"FR",
    "sg:address":"Rue Saint Roch - ZA Roch",
    "sg:city":"Beaumont sur Oise",
    "sg:orig_category":"Non-Classified Establishments",
    "sg:phone":"+33 1 34 70 20 19",
    "sg:postcode":"95260",
    "sg:province":"Ile de France",
    "wof:name":"S.n.j.j. S.a.r.l.",
    "wof:placetype":"venue"
},
  "geometry": {"coordinates":[2.284069,49.144073],"type":"Point"}
}