{
  "type": "Feature",
  "properties": {
    "iso:country":"FR",
    "sg:address":"4 Rue Philibert De La Baume Z I Au Nievre D'En Bas 39160 Saint Amour",
    "sg:classifiers":[
        {
            "category":"Wholesale",
            "subcategory":"Meat",
            "type":"Manufacturing & Wholesale Goods"
        }
    ],
    "sg:phone":"+33 3 84 87 20 21",
    "sg:postcode":"39160",
    "sg:province":"Franche Comt\u00e9",
    "sg:tags":[
        "food",
        "cooked",
        "product",
        "related"
    ],
    "wof:name":"Salaisons Bolard Freres Michel Bolard",
    "wof:placetype":"venue"
},
  "geometry": {"coordinates":[3.454203,47.289532],"type":"Point"}
}