{
  "type": "Feature",
  "properties": {
    "iso:country":"FR",
    "sg:address":"16 rue Donnet Zedel 25300 Pontarlier",
    "sg:classifiers":[
        {
            "category":"Manufacturing",
            "subcategory":"Tools & Machinery",
            "type":"Manufacturing & Wholesale Goods"
        }
    ],
    "sg:phone":"+33 3 81 46 40 99",
    "sg:postcode":"25300",
    "sg:province":"Franche Comt\u00e9",
    "sg:tags":[
        "moulding",
        "extrusion"
    ],
    "wof:name":"Outicables S.a.r.l.",
    "wof:placetype":"venue"
},
  "geometry": {"coordinates":[6.3321,46.906109],"type":"Point"}
}