{
  "type": "Feature",
  "properties": {
    "addr:full":"1109, Rte de la Vall\u00e9e, 69380 Ch\u00e2tillon Rhone-Alpes 69380",
    "addr:housenumber":"1109",
    "addr:postcode":"69380;69380",
    "addr:street":"Rte De La Valle\u0301E",
    "iso:country":"FR",
    "sg:address":"1109, Rte de la Vall\u00e9e, 69380 Ch\u00e2tillon",
    "sg:orig_category":"Non-Classified Establishments",
    "sg:phone":"+33 4 78 43 95 50",
    "sg:postcode":"69380",
    "sg:province":"Rhone-Alpes",
    "wof:name":"Entreprise Jonard S.a.r.l.",
    "wof:placetype":"venue"
},
  "geometry": {"coordinates":[4.64489,45.876831],"type":"Point"}
}