{
  "type": "Feature",
  "properties": {
    "addr:full":"14, Rue Louis Joseph Gay Lussac, 68000 Colmar Colmar Alsace 68000",
    "addr:housenumber":"14",
    "addr:postcode":"68000;68000",
    "addr:street":"Rue Louis Joseph Gay Lussac",
    "iso:country":"FR",
    "sg:address":"14, Rue Louis Joseph Gay Lussac, 68000 Colmar",
    "sg:city":"Colmar",
    "sg:orig_category":"Non-Classified Establishments",
    "sg:phone":"+33 3 89 21 09 80",
    "sg:postcode":"68000",
    "sg:province":"Alsace",
    "wof:name":"Ema S\u00e9curit\u00e9 S.a.r.l.",
    "wof:placetype":"venue"
},
  "geometry": {"coordinates":[7.381533,48.105125],"type":"Point"}
}