{
  "type": "Feature",
  "properties": {
    "addr:full":"ZI Bois des Lots Saint Paul Trois Ch\u00e2teaux Rhone-Alpes 26130",
    "addr:postcode":"26130",
    "addr:street":"Zi Bois Des Lots;Rhone-Alpes",
    "iso:country":"FR",
    "sg:address":"ZI Bois des Lots",
    "sg:city":"Saint Paul Trois Ch\u00e2teaux",
    "sg:orig_category":"Non-Classified Establishments",
    "sg:phone":"+33 4 75 96 76 10",
    "sg:postcode":"26130",
    "sg:province":"Rhone-Alpes",
    "wof:name":"C.i.i. S.a. - Carbone Inox Industrie",
    "wof:placetype":"venue"
},
  "geometry": {"coordinates":[4.76946,44.348251],"type":"Point"}
}