{
  "type": "Feature",
  "properties": {
    "addr:full":"36, Av. de l'Europe, 95335 Domont C\u00e9dex Ile de France",
    "addr:postcode":"95335",
    "addr:street":"36 Av. De L'Europe",
    "iso:country":"FR",
    "sg:address":"36, Av. de l'Europe, 95335 Domont C\u00e9dex",
    "sg:orig_category":"Non-Classified Establishments",
    "sg:phone":"+33 1 39 35 57 00",
    "sg:province":"Ile de France",
    "wof:name":"Avery Berkel S.a.",
    "wof:placetype":"venue"
},
  "geometry": {"coordinates":[2.344992,49.027046],"type":"Point"}
}