{
  "type": "Feature",
  "properties": {
    "addr:full":"131 Rue Des Allies 38000 Grenoble Rhone-Alpes",
    "addr:housenumber":"131",
    "addr:postcode":"38000",
    "addr:street":"Rue Des Allies",
    "iso:country":"FR",
    "sg:address":"131 Rue Des Allies 38000 Grenoble",
    "sg:classifiers":[
        {
            "category":"Home & Garden",
            "subcategory":"Furniture",
            "type":"Retail Goods"
        }
    ],
    "sg:phone":"+33 4 76 21 48 02",
    "sg:province":"Rhone-Alpes",
    "sg:tags":[
        "wood"
    ],
    "wof:name":"Groupement De Professionnels D Emballages Industriels (gpei)",
    "wof:placetype":"venue"
},
  "geometry": {"coordinates":[5.716491,45.17374],"type":"Point"}
}