{
  "type": "Feature",
  "properties": {
    "addr:full":"30, Rue Monsigny, 62200 Boulogne sur Mer Nord Pas-de-Calais",
    "addr:housenumber":"30",
    "addr:postcode":"62200",
    "addr:street":"Rue Monsigny;Sur Mer Nord",
    "iso:country":"FR",
    "sg:address":"30, Rue Monsigny, 62200 Boulogne sur Mer",
    "sg:orig_category":"Non-Classified Establishments",
    "sg:phone":"+33 3 21 83 41 73",
    "sg:province":"Nord Pas-de-Calais",
    "wof:name":"Gestetner S.a.",
    "wof:placetype":"venue"
},
  "geometry": {"coordinates":[1.606142,50.724789],"type":"Point"}
}