{
  "type": "Feature",
  "properties": {
    "iso:country":"FR",
    "sg:address":"Louis Bleriot 56400 Auray",
    "sg:city":"Auray",
    "sg:classifiers":[
        {
            "category":"Professional",
            "subcategory":"Engineering",
            "type":"Services"
        }
    ],
    "sg:phone":"+33 2 97 24 25 25",
    "sg:postcode":"56400",
    "sg:province":"Bretagne",
    "sg:tags":[
        "machine",
        "-",
        "mechanical"
    ],
    "wof:name":"Queguiner Materiaux",
    "wof:placetype":"venue"
},
  "geometry": {"coordinates":[-3.012507,47.663979],"type":"Point"}
}