{
  "type": "Feature",
  "properties": {
    "addr:full":"6, Rue de la Commanderie, 54000 Nancy Lorraine",
    "addr:housenumber":"6",
    "addr:postcode":"54000",
    "addr:street":"Rue De La Commanderie",
    "iso:country":"FR",
    "sg:address":"6, Rue de la Commanderie, 54000 Nancy",
    "sg:orig_category":"Unclassifiable Establishments",
    "sg:phone":"+33 3 83 90 10 00",
    "sg:province":"Lorraine",
    "wof:name":"Prisme Ware S.a.r.l. - Projets Informatiques Sur Mesure",
    "wof:placetype":"venue"
},
  "geometry": {"coordinates":[6.173022,48.687805],"type":"Point"}
}