{
  "type": "Feature",
  "properties": {
    "addr:full":"10 Rue Emile Erckmann 57370 Phalsbourg Lorraine 57370",
    "addr:housenumber":"10",
    "addr:postcode":"57370;57370",
    "addr:street":"Rue Emile Erckmann",
    "iso:country":"FR",
    "sg:address":"10 Rue Emile Erckmann 57370 Phalsbourg",
    "sg:classifiers":[
        {
            "category":"Bakery",
            "type":"Food & Drink"
        }
    ],
    "sg:phone":"+33 3 87 24 20 03",
    "sg:postcode":"57370",
    "sg:province":"Lorraine",
    "sg:tags":[
        "cake",
        "product",
        "related",
        "bread"
    ],
    "wof:name":"Au Pain Dore Sa",
    "wof:placetype":"venue"
},
  "geometry": {"coordinates":[7.259453,48.768162],"type":"Point"}
}