{
  "type": "Feature",
  "properties": {
    "addr:full":"5, Promenade de la Bonnette - Parc des Barbanniers, 92232 Gennevilliers C\u00e9dex Midi Pyr\u00e9n\u00e9es",
    "addr:housenumber":"5",
    "addr:postcode":"92232",
    "addr:street":"Promenade De La Bonnette Parc Des Barbanniers",
    "iso:country":"FR",
    "sg:address":"5, Promenade de la Bonnette - Parc des Barbanniers, 92232 Gennevilliers C\u00e9dex",
    "sg:orig_category":"Non-Classified Establishments",
    "sg:phone":"+33 1 40 85 00 46",
    "sg:province":"Midi Pyr\u00e9n\u00e9es",
    "wof:name":"B.e.c.m. S.a. - Banque De L'economie",
    "wof:placetype":"venue"
},
  "geometry": {"coordinates":[2.305402,48.933689],"type":"Point"}
}