{
  "type": "Feature",
  "properties": {
    "addr:full":"32, Rue du Temple, 75004 Paris Ile de France",
    "addr:housenumber":"32",
    "addr:postcode":"75004",
    "addr:street":"Rue Du Temple",
    "iso:country":"FR",
    "sg:address":"32, Rue du Temple, 75004 Paris",
    "sg:orig_category":"Unclassifiable Establishments",
    "sg:phone":"+33 1 42 78 68 21",
    "sg:province":"Ile de France",
    "wof:name":"M.b.q. Soci\u00e9t\u00e9 S.a.",
    "wof:placetype":"venue"
},
  "geometry": {"coordinates":[2.354144,48.859375],"type":"Point"}
}