{
  "type": "Feature",
  "properties": {
    "addr:full":"RN 519 - ZI le Rival Saint Sim\u00e9on de Bressieux Rhone-Alpes 38870",
    "addr:postcode":"38870",
    "addr:street":"Rn 519 Zi Le Rival Saint Sime\u0301On De Bressieux Rhone-Alpes",
    "iso:country":"FR",
    "sg:address":"RN 519 - ZI le Rival",
    "sg:city":"Saint Sim\u00e9on de Bressieux",
    "sg:orig_category":"Non-Classified Establishments",
    "sg:phone":"+33 4 74 20 41 42",
    "sg:postcode":"38870",
    "sg:province":"Rhone-Alpes",
    "wof:name":"E.b. S.a. - Euro B\u00e9ton",
    "wof:placetype":"venue"
},
  "geometry": {"coordinates":[5.263489,45.348549],"type":"Point"}
}