{
  "type": "Feature",
  "properties": {
    "iso:country":"FR",
    "sg:address":"1, Rue du Point du Jour, 41350 Saint Gervais la For\u00eat",
    "sg:city":"Saint-Gervais-la-For\u00eat",
    "sg:orig_category":"Non-Classified Establishments",
    "sg:phone":"+33 2 54 42 71 05",
    "sg:postcode":"41350",
    "sg:province":"Centre",
    "wof:name":"Dimensions 3 S.a.r.l.",
    "wof:placetype":"venue"
},
  "geometry": {"coordinates":[1.366574,47.566051],"type":"Point"}
}