{
  "type": "Feature",
  "properties": {
    "iso:country":"FR",
    "sg:address":"B.P. 24, 77381 Combs la Ville C\u00e9dex^^2/4, Rue des Fr\u00e8res Lumi\u00e8re - ZA de l'Ormeau, 77380 Combs la Vi",
    "sg:orig_category":"Non-Classified Establishments",
    "sg:phone":"+33 1 60 60 12 12",
    "sg:province":"Ile de France",
    "wof:name":"Matinox D\u00e9cors S.a.r.l.",
    "wof:placetype":"venue"
},
  "geometry": {"coordinates":[2.543376,48.668526],"type":"Point"}
}