{
  "type": "Feature",
  "properties": {
    "iso:country":"FR",
    "sg:address":"B.P. 2, 68140 Munster C\u00e9dex^^48, Grand Rue, 68140 Stosswihr",
    "sg:city":"Stosswihr",
    "sg:orig_category":"Non-Classified Establishments",
    "sg:phone":"+33 3 89 77 36 43",
    "sg:postcode":"68140",
    "sg:province":"Alsace",
    "wof:name":"Nuss Dietrich S.a.r.l.",
    "wof:placetype":"venue"
},
  "geometry": {"coordinates":[7.117455,48.031052],"type":"Point"}
}