{
  "type": "Feature",
  "properties": {
    "iso:country":"FR",
    "sg:address":"Avenue De Verdun 18300 Sancerre",
    "sg:city":"Sancerre",
    "sg:classifiers":[
        {
            "category":"Food Court",
            "type":"Food & Drink"
        }
    ],
    "sg:phone":"+33 2 48 54 02 34",
    "sg:postcode":"18300",
    "sg:province":"Centre",
    "sg:tags":[
        "product",
        "related"
    ],
    "wof:name":"Fouassier Pere Et Fils Sa",
    "wof:placetype":"venue"
},
  "geometry": {"coordinates":[2.832513,47.328743],"type":"Point"}
}