{
  "type": "Feature",
  "properties": {
    "iso:country":"FR",
    "sg:address":"172 Rue De Charonne 75011 Paris",
    "sg:classifiers":[
        {
            "category":"Manufacturing",
            "subcategory":"Tools & Machinery",
            "type":"Manufacturing & Wholesale Goods"
        }
    ],
    "sg:phone":"+33 1 43 48 79 33",
    "sg:postcode":"75011",
    "sg:province":"Ile de France",
    "sg:tags":[
        "equipment",
        "measurement",
        "-",
        "precision",
        "instrument"
    ],
    "wof:name":"Cimel Electronique",
    "wof:placetype":"venue"
},
  "geometry": {"coordinates":[2.393163,48.856003],"type":"Point"}
}