{
  "type": "Feature",
  "properties": {
    "addr:full":"31, Rue Edouard de Pontet - Loubeyres , 33250 Pauillac Pauillac Aquitaine 33250",
    "addr:housenumber":"31",
    "addr:postcode":"33250;33250",
    "addr:street":"Rue Edouard De Pontet Loubeyres",
    "iso:country":"FR",
    "sg:address":"31, Rue Edouard de Pontet - Loubeyres , 33250 Pauillac",
    "sg:city":"Pauillac",
    "sg:orig_category":"Non-Classified Establishments",
    "sg:phone":"+33 5 56 59 11 06",
    "sg:postcode":"33250",
    "sg:province":"Aquitaine",
    "wof:name":"Soci\u00e9t\u00e9 Clastres Et Fils S.a.r.l.",
    "wof:placetype":"venue"
},
  "geometry": {"coordinates":[-0.751305,45.201687],"type":"Point"}
}