{
  "type": "Feature",
  "properties": {
    "addr:full":"1 Route Gare Za 43370 Solignac Sur Loire Bains Auvergne 43370",
    "addr:housenumber":"1",
    "addr:postcode":"43370;bains;43370",
    "addr:street":"Route Gare Za",
    "iso:country":"FR",
    "sg:address":"1 Route Gare Za 43370 Solignac Sur Loire",
    "sg:city":"Bains",
    "sg:classifiers":[
        {
            "category":"Building & Trades",
            "subcategory":"Electrical",
            "type":"Services"
        }
    ],
    "sg:phone":"+33 4 71 03 14 94",
    "sg:postcode":"43370",
    "sg:province":"Auvergne",
    "sg:tags":[
        "electronic",
        "lighting",
        "equipment"
    ],
    "wof:name":"Arc En Ciel Luminaires (acl)",
    "wof:placetype":"venue"
},
  "geometry": {"coordinates":[3.877828,44.970589],"type":"Point"}
}