{
  "type": "Feature",
  "properties": {
    "addr:full":"P.A. Logistiques - Pont de Normandie Le Havre Haute Normandie 76600",
    "addr:postcode":"76600",
    "addr:street":"Pont De Normandie",
    "iso:country":"FR",
    "sg:address":"P.A. Logistiques - Pont de Normandie",
    "sg:city":"Le Havre",
    "sg:orig_category":"Unclassifiable Establishments",
    "sg:phone":"+33 2 32 79 70 00",
    "sg:postcode":"76600",
    "sg:province":"Haute Normandie",
    "wof:name":"Daher Et Compagnie S.a.",
    "wof:placetype":"venue"
},
  "geometry": {"coordinates":[0.101405,49.493511],"type":"Point"}
}