{
  "type": "Feature",
  "properties": {
    "addr:full":"43 Boulevard des Capucines, 75002 Paris, Dept 75 Ile de France 75002",
    "addr:housenumber":"43;75",
    "addr:postcode":"75002;75002",
    "addr:street":"Boulevard Des Capucines;Ile De France",
    "iso:country":"FR",
    "sg:address":"43 Boulevard des Capucines, 75002 Paris, Dept 75",
    "sg:classifiers":[
        {
            "category":"Banks & Credit Unions",
            "subcategory":"Bank",
            "type":"Services"
        }
    ],
    "sg:phone":"+33 1 42 44 70 00",
    "sg:postcode":"75002",
    "sg:province":"Ile de France",
    "wof:name":"Cr\u00e9dit Foncier Banque",
    "wof:placetype":"venue"
},
  "geometry": {"coordinates":[2.328323,48.869835],"type":"Point"}
}