{
  "type": "Feature",
  "properties": {
    "iso:country":"FR",
    "sg:address":"70, Av. Roger Salengro, 69100 Villeurbanne",
    "sg:orig_category":"Non-Classified Establishments",
    "sg:phone":"+33 4 78 93 32 06",
    "sg:postcode":"69100",
    "sg:province":"Rhone-Alpes",
    "wof:name":"Brun S.a.",
    "wof:placetype":"venue"
},
  "geometry": {"coordinates":[4.875771,45.776581],"type":"Point"}
}