{
  "type": "Feature",
  "properties": {
    "addr:full":"70, Av. Roger Salengro, 69100 Villeurbanne Rhone-Alpes 69100",
    "addr:postcode":"69100;69100",
    "addr:street":"70 Av. Roger Salengro",
    "iso:country":"FR",
    "sg:address":"70, Av. Roger Salengro, 69100 Villeurbanne",
    "sg:orig_category":"Non-Classified Establishments",
    "sg:phone":"+33 4 78 93 32 06",
    "sg:postcode":"69100",
    "sg:province":"Rhone-Alpes",
    "wof:name":"Brun S.a.",
    "wof:placetype":"venue"
},
  "geometry": {"coordinates":[4.875771,45.776581],"type":"Point"}
}