{
  "type": "Feature",
  "properties": {
    "addr:full":"44 Bis, Bd F\u00e9lix Faure, 92320 Ch\u00e2tillon Ile de France 92320",
    "addr:housenumber":"44 bis",
    "addr:postcode":"92320;ile;92320",
    "addr:street":"Bd Fe\u0301Lix Faure;France",
    "iso:country":"FR",
    "sg:address":"44 Bis, Bd F\u00e9lix Faure, 92320 Ch\u00e2tillon",
    "sg:orig_category":"Non-Classified Establishments",
    "sg:phone":"+33 1 47 35 15 16",
    "sg:postcode":"92320",
    "sg:province":"Ile de France",
    "wof:name":"Alspace S.a.",
    "wof:placetype":"venue"
},
  "geometry": {"coordinates":[2.28404,48.803062],"type":"Point"}
}