{
  "type": "Feature",
  "properties": {
    "iso:country":"FR",
    "sg:address":"48, Bd de la R\u00e9publique, 35400 Saint Malo",
    "sg:city":"Saint-Malo",
    "sg:orig_category":"Unclassifiable Establishments",
    "sg:phone":"+33 2 99 56 31 61",
    "sg:postcode":"35400",
    "sg:province":"Bretagne",
    "wof:name":"Hertz France S.a.",
    "wof:placetype":"venue"
},
  "geometry": {"coordinates":[-2.00857,48.647816],"type":"Point"}
}