{
  "type": "Feature",
  "properties": {
    "addr:full":"99, Av. de Paris, 41200 Romorantin Lanthenay Villefranche-sur-Cher Centre 41200",
    "addr:postcode":"41200;41200",
    "addr:street":"99 Av. De Paris",
    "iso:country":"FR",
    "sg:address":"99, Av. de Paris, 41200 Romorantin Lanthenay",
    "sg:city":"Villefranche-sur-Cher",
    "sg:orig_category":"Non-Classified Establishments",
    "sg:phone":"+33 2 54 88 24 88",
    "sg:postcode":"41200",
    "sg:province":"Centre",
    "wof:name":"Samicentre Soci\u00e9t\u00e9 D'am\u00e9nagement Et De Construction De Maisons S.a.",
    "wof:placetype":"venue"
},
  "geometry": {"coordinates":[1.737844,47.380913],"type":"Point"}
}