{
  "type": "Feature",
  "properties": {
    "addr:full":"50 Rue Moliere Z A Gazonfier 72000 Le Mans Pays de Loire 72000",
    "addr:housenumber":"50",
    "addr:postcode":"72000;72000",
    "addr:street":"Rue Moliere",
    "iso:country":"FR",
    "sg:address":"50 Rue Moliere Z A Gazonfier 72000 Le Mans",
    "sg:classifiers":[
        {
            "category":"Home & Garden",
            "subcategory":"Furniture",
            "type":"Retail Goods"
        }
    ],
    "sg:phone":"+33 2 43 84 68 07",
    "sg:postcode":"72000",
    "sg:province":"Pays de Loire",
    "sg:tags":[
        "household",
        "wood"
    ],
    "wof:name":"Gadet Frigoriste",
    "wof:placetype":"venue"
},
  "geometry": {"coordinates":[0.197813,48.008095],"type":"Point"}
}