{
  "type": "Feature",
  "properties": {
    "iso:country":"FR",
    "sg:address":"69-71 Bd Fichot 93360 Neuilly Plaisance",
    "sg:classifiers":[
        {
            "category":"Manufacturing",
            "subcategory":"Rubber & Plastics",
            "type":"Manufacturing & Wholesale Goods"
        }
    ],
    "sg:phone":"+33 1 43 00 11 32",
    "sg:province":"Ile de France",
    "wof:name":"Jehere",
    "wof:placetype":"venue"
},
  "geometry": {"coordinates":[2.507735,48.855122],"type":"Point"}
}