{
  "type": "Feature",
  "properties": {
    "addr:full":"9, Rue du Colonnel Chambonnet, 69500 Bron Rhone-Alpes 69500",
    "addr:housenumber":"9",
    "addr:postcode":"69500;69500",
    "addr:street":"Rue Du Colonnel Chambonnet",
    "iso:country":"FR",
    "sg:address":"9, Rue du Colonnel Chambonnet, 69500 Bron",
    "sg:orig_category":"Unclassifiable Establishments",
    "sg:phone":"+33 4 72 14 54 54",
    "sg:postcode":"69500",
    "sg:province":"Rhone-Alpes",
    "wof:name":"G.e. Plastics France S.n.c.",
    "wof:placetype":"venue"
},
  "geometry": {"coordinates":[4.923429,45.726982],"type":"Point"}
}