{
  "type": "Feature",
  "properties": {
    "iso:country":"FR",
    "sg:address":"Quartier Carrel",
    "sg:city":"Castelsarrasin",
    "sg:orig_category":"Unclassifiable Establishments",
    "sg:phone":"+33 5 63 95 12 12",
    "sg:postcode":"82100",
    "sg:province":"Midi Pyr\u00e9n\u00e9es",
    "wof:name":"Qualisol",
    "wof:placetype":"venue"
},
  "geometry": {"coordinates":[1.133739,44.032536],"type":"Point"}
}