{
  "type": "Feature",
  "properties": {
    "addr:full":"Impasse Surcouf - ZI Atlantheix Theix Bretagne 56450",
    "addr:postcode":"56450",
    "addr:street":"Impasse Surcouf Zi Atlantheix Theix Bretagne",
    "iso:country":"FR",
    "sg:address":"Impasse Surcouf - ZI Atlantheix",
    "sg:city":"Theix",
    "sg:orig_category":"Unclassifiable Establishments",
    "sg:phone":"+33 2 97 47 09 07",
    "sg:postcode":"56450",
    "sg:province":"Bretagne",
    "wof:name":"Back Europe France S.a.",
    "wof:placetype":"venue"
},
  "geometry": {"coordinates":[-2.709897,47.572872],"type":"Point"}
}