{
  "type": "Feature",
  "properties": {
    "addr:full":"Ancienne Rte de Gaillon Gravigny Haute Normandie 27930",
    "addr:postcode":"27930",
    "addr:street":"Rte De Gaillon;Haute Normandie",
    "iso:country":"FR",
    "sg:address":"Ancienne Rte de Gaillon",
    "sg:city":"Gravigny",
    "sg:orig_category":"Non-Classified Establishments",
    "sg:phone":"+33 2 32 33 50 00",
    "sg:postcode":"27930",
    "sg:province":"Haute Normandie",
    "wof:name":"D\u00e9m\u00e9nagements Desormeaux S.a.r.l.",
    "wof:placetype":"venue"
},
  "geometry": {"coordinates":[1.165497,49.050564],"type":"Point"}
}