{
  "type": "Feature",
  "properties": {
    "iso:country":"FR",
    "sg:address":"2, Rue des Bonnes Gens, 67210 Obernai",
    "sg:city":"Obernai",
    "sg:orig_category":"Non-Classified Establishments",
    "sg:phone":"+33 3 88 49 47 50",
    "sg:postcode":"67210",
    "sg:province":"Alsace",
    "wof:name":"C.m.o. Obernai S.a.",
    "wof:placetype":"venue"
},
  "geometry": {"coordinates":[7.492744,48.465382],"type":"Point"}
}