{
  "type": "Feature",
  "properties": {
    "addr:full":"6 R Eug\u00e8ne Thomas 17013 La Rochelle Cedex Haute Normandie",
    "addr:housenumber":"6",
    "addr:postcode":"17013",
    "addr:street":"R Euge\u0300Ne Thomas",
    "iso:country":"FR",
    "sg:address":"6 R Eug\u00e8ne Thomas 17013 La Rochelle Cedex",
    "sg:classifiers":[
        {
            "category":"Manufacturing",
            "subcategory":"Chemicals & Compounds",
            "type":"Manufacturing & Wholesale Goods"
        }
    ],
    "sg:phone":"+33 5 46 41 28 33",
    "sg:province":"Haute Normandie",
    "sg:tags":[
        "pharmaceutical",
        "chemistry"
    ],
    "wof:name":"Mhr Industrie Sa",
    "wof:placetype":"venue"
},
  "geometry": {"coordinates":[-1.145802,46.155952],"type":"Point"}
}