{
  "type": "Feature",
  "properties": {
    "iso:country":"FR",
    "sg:address":"132, Av. de la C\u00f4te d'Argent, 33380 Biganos",
    "sg:city":"Biganos",
    "sg:orig_category":"Unclassifiable Establishments",
    "sg:phone":"+33 5 56 82 60 31",
    "sg:postcode":"33380",
    "sg:province":"Aquitaine",
    "wof:name":"Lafon S.a.r.l.",
    "wof:placetype":"venue"
},
  "geometry": {"coordinates":[-0.976074,44.634018],"type":"Point"}
}