{
  "type": "Feature",
  "properties": {
    "addr:full":"1, Rue Claude Chappe, 67120 Duppigheim Duppigheim Alsace 67120",
    "addr:housenumber":"1",
    "addr:postcode":"67120;67120",
    "addr:street":"Rue Claude Chappe;Duppigheim",
    "iso:country":"FR",
    "sg:address":"1, Rue Claude Chappe, 67120 Duppigheim",
    "sg:city":"Duppigheim",
    "sg:orig_category":"Non-Classified Establishments",
    "sg:phone":"+33 3 88 49 36 11",
    "sg:postcode":"67120",
    "sg:province":"Alsace",
    "wof:name":"Egw Maintenance S.a.",
    "wof:placetype":"venue"
},
  "geometry": {"coordinates":[7.582645,48.54195],"type":"Point"}
}