{
  "type": "Feature",
  "properties": {
    "iso:country":"FR",
    "sg:address":"B.P. 53, 38780 Pont Ev\u00eaque^^ZI de l'Abbaye, 38780 Pont Ev\u00eaque",
    "sg:orig_category":"Non-Classified Establishments",
    "sg:phone":"+33 4 74 16 11 00",
    "sg:postcode":"38780",
    "sg:province":"Rhone-Alpes",
    "wof:name":"Deltasacs S.a.",
    "wof:placetype":"venue"
},
  "geometry": {"coordinates":[4.9117,45.53088],"type":"Point"}
}