{
  "type": "Feature",
  "properties": {
    "iso:country":"FR",
    "sg:address":"avenue Am\u00e9d\u00e9o Avagadaro 13127 Vitrolles",
    "sg:orig_category":"Trailers, Semi-Trailers",
    "sg:phone":"+33 4 91 87 61 61",
    "sg:province":"Provence-Alpes-C\u00f4te d'Azur",
    "wof:name":"Coder Sa",
    "wof:placetype":"venue"
},
  "geometry": {"coordinates":[5.236034,43.476521],"type":"Point"}
}