{
  "type": "Feature",
  "properties": {
    "addr:full":"B.P. 113, 85501 Les Herbiers C\u00e9dex^^4, Rue de l'Eglise, 85500 Les Herbiers Pays de Loire",
    "addr:housenumber":"b.p. 113",
    "addr:postcode":"85501;85500",
    "addr:street":"Herbiers;Rue De L'Eglise;Herbiers",
    "iso:country":"FR",
    "sg:address":"B.P. 113, 85501 Les Herbiers C\u00e9dex^^4, Rue de l'Eglise, 85500 Les Herbiers",
    "sg:orig_category":"Non-Classified Establishments",
    "sg:phone":"+33 2 51 66 87 87",
    "sg:province":"Pays de Loire",
    "wof:name":"Ips Atlantique Creyf's Int\u00e9rim",
    "wof:placetype":"venue"
},
  "geometry": {"coordinates":[-1.013835,46.871029],"type":"Point"}
}