{
  "type": "Feature",
  "properties": {
    "iso:country":"FR",
    "sg:address":"B.P. 207, 74320 Sevrier^^40, Impasse des Pontets - Parc d'Activit\u00e9s le Piron, 74320 Sevrier",
    "sg:orig_category":"Non-Classified Establishments",
    "sg:phone":"+33 4 50 52 61 64",
    "sg:postcode":"74320",
    "sg:province":"Rhone-Alpes",
    "wof:name":"D\u00e9colletage Ann\u00e9cien S.a.s.",
    "wof:placetype":"venue"
},
  "geometry": {"coordinates":[6.14032,45.86393],"type":"Point"}
}