{
  "type": "Feature",
  "properties": {
    "addr:full":"Impasse des Fr\u00e8res Montgolfier - Z.I. Albasud Montauban Midi Pyr\u00e9n\u00e9es 82000",
    "addr:postcode":"82000",
    "addr:street":"Impasse Des Fre\u0300Res Montgolfier Z.I. Albasud",
    "iso:country":"FR",
    "sg:address":"Impasse des Fr\u00e8res Montgolfier - Z.I. Albasud",
    "sg:city":"Montauban",
    "sg:orig_category":"Unclassifiable Establishments",
    "sg:phone":"+33 5 63 23 04 04",
    "sg:postcode":"82000",
    "sg:province":"Midi Pyr\u00e9n\u00e9es",
    "wof:name":"Comptec S.a.",
    "wof:placetype":"venue"
},
  "geometry": {"coordinates":[1.352205,44.016762],"type":"Point"}
}