{
  "type": "Feature",
  "properties": {
    "addr:full":"Rue Alain Colas Zi Portuaire 29200 Brest Brest Bretagne 29200",
    "addr:postcode":"29200;29200",
    "addr:street":"Rue Alain Colas Zi Portuaire",
    "iso:country":"FR",
    "sg:address":"Rue Alain Colas Zi Portuaire 29200 Brest",
    "sg:city":"Brest",
    "sg:classifiers":[
        {
            "category":"Shopping",
            "subcategory":"Bicycles & Sporting Goods",
            "type":"Retail Goods"
        }
    ],
    "sg:phone":"+33 2 98 46 11 02",
    "sg:postcode":"29200",
    "sg:province":"Bretagne",
    "sg:tags":[
        "product",
        "sport",
        "miscellaneous"
    ],
    "wof:name":"Seimi",
    "wof:placetype":"venue"
},
  "geometry": {"coordinates":[-4.486228,48.39024],"type":"Point"}
}