{
  "type": "Feature",
  "properties": {
    "iso:country":"FR",
    "sg:address":"13272 Marseille C\u00e9dex 08^^103, Av. des Goumiers, 13008 Marseille",
    "sg:orig_category":"Non-Classified Establishments",
    "sg:phone":"+33 4 91 16 53 53",
    "sg:province":"Poitou-Charentes",
    "wof:name":"I.d.c. S.a. - International Design Cr\u00e9ation",
    "wof:placetype":"venue"
},
  "geometry": {"coordinates":[5.364135,43.238701],"type":"Point"}
}