{
  "type": "Feature",
  "properties": {
    "iso:country":"FR",
    "sg:address":"Chateau De Gourgazaud 34210 La Liviniere",
    "sg:classifiers":[
        {
            "category":"Food Court",
            "type":"Food & Drink"
        }
    ],
    "sg:phone":"+33 4 68 78 10 02",
    "sg:postcode":"34210",
    "sg:province":"Languedoc-Roussillon",
    "sg:tags":[
        "product",
        "related"
    ],
    "wof:name":"Chateau De Gourgazaud",
    "wof:placetype":"venue"
},
  "geometry": {"coordinates":[2.617454,43.29586],"type":"Point"}
}