{
  "type": "Feature",
  "properties": {
    "addr:full":"Le Genet 24360 St Barth\u00e9l\u00e9my De Bussi\u00e8re Busserolles Aquitaine 24360",
    "addr:postcode":"24360;24360",
    "addr:street":"St Barthe\u0301Le\u0301My De Bussie\u0300Re",
    "iso:country":"FR",
    "sg:address":"Le Genet 24360 St Barth\u00e9l\u00e9my De Bussi\u00e8re",
    "sg:city":"Busserolles",
    "sg:classifiers":[
        {
            "category":"Bakery",
            "type":"Food & Drink"
        }
    ],
    "sg:phone":"+33 5 53 56 48 76",
    "sg:postcode":"24360",
    "sg:province":"Aquitaine",
    "sg:tags":[
        "cake",
        "product",
        "related",
        "bread"
    ],
    "wof:name":"Sas Dufour Industrie",
    "wof:placetype":"venue"
},
  "geometry": {"coordinates":[0.613413,45.652458],"type":"Point"}
}