{
  "type": "Feature",
  "properties": {
    "addr:full":"Rue des Claires Querqueville Basse Normandie 50460",
    "addr:postcode":"50460",
    "addr:street":"Rue Des Claires",
    "iso:country":"FR",
    "sg:address":"Rue des Claires",
    "sg:city":"Querqueville",
    "sg:orig_category":"Non-Classified Establishments",
    "sg:phone":"+33 2 33 03 90 90",
    "sg:postcode":"50460",
    "sg:province":"Basse Normandie",
    "wof:name":"I.n.f.r.e.p. S.n.c. - Institut National De Formation Recherches Education Permanente",
    "wof:placetype":"venue"
},
  "geometry": {"coordinates":[-1.692272,49.659676],"type":"Point"}
}