{
  "type": "Feature",
  "properties": {
    "iso:country":"FR",
    "sg:address":"76 Rue D'Aulnay 91180 St Germain Les Arpajon",
    "sg:classifiers":[
        {
            "category":"Building & Trades",
            "subcategory":"Construction",
            "type":"Services"
        }
    ],
    "sg:phone":"+33 1 60 84 83 97",
    "sg:postcode":"91180",
    "sg:province":"Ile de France",
    "sg:tags":[
        "work",
        "public"
    ],
    "wof:name":"Entreprise Bonin Sa",
    "wof:placetype":"venue"
},
  "geometry": {"coordinates":[2.26499,48.598129],"type":"Point"}
}