{
  "type": "Feature",
  "properties": {
    "addr:full":"55, Rue Traversi\u00e8re, 75012 Paris Ile de France",
    "addr:housenumber":"55",
    "addr:postcode":"75012",
    "addr:street":"Rue Traversie\u0300Re",
    "iso:country":"FR",
    "sg:address":"55, Rue Traversi\u00e8re, 75012 Paris",
    "sg:orig_category":"Unclassifiable Establishments",
    "sg:phone":"+33 1 43 46 52 43",
    "sg:province":"Ile de France",
    "wof:name":"Guayapi Tropical S.a.r.l.",
    "wof:placetype":"venue"
},
  "geometry": {"coordinates":[2.374089,48.84861],"type":"Point"}
}