{
  "type": "Feature",
  "properties": {
    "iso:country":"FR",
    "sg:address":"20 Rte St R\u00e9my 13630 Eyragues",
    "sg:classifiers":[
        {
            "category":"Wholesale",
            "subcategory":"Meat",
            "type":"Manufacturing & Wholesale Goods"
        }
    ],
    "sg:phone":"+33 4 90 92 82 58",
    "sg:province":"Nord Pas-de-Calais",
    "sg:tags":[
        "food",
        "cooked",
        "product",
        "related"
    ],
    "wof:name":"Saveurs Salees Scop",
    "wof:placetype":"venue"
},
  "geometry": {"coordinates":[4.844298,43.840519],"type":"Point"}
}