{
  "type": "Feature",
  "properties": {
    "iso:country":"FR",
    "sg:address":"11, Rue Chapon, 75003 Paris",
    "sg:orig_category":"Unclassifiable Establishments",
    "sg:phone":"+33 1 42 77 42 00",
    "sg:province":"Ile de France",
    "wof:name":"Cr\u00e9ative Search S.a.r.l.",
    "wof:placetype":"venue"
},
  "geometry": {"coordinates":[2.356817,48.863056],"type":"Point"}
}