{
  "type": "Feature",
  "properties": {
    "addr:full":"115 rue Pierre Corneille; Lyon; 69003 Rhone-Alpes 69003",
    "addr:housenumber":"115",
    "addr:postcode":"69003;69003",
    "addr:street":"Rue Pierre Corneille",
    "iso:country":"FR",
    "sg:address":"115 rue Pierre Corneille; Lyon; 69003",
    "sg:classifiers":[
        {
            "category":"Banks & Credit Unions",
            "subcategory":"Bank",
            "type":"Services"
        }
    ],
    "sg:phone":"+33 4 72 84 46 46",
    "sg:postcode":"69003",
    "sg:province":"Rhone-Alpes",
    "wof:name":"Banca Popolare Di Bergamo, Credito Varesino Scarl",
    "wof:placetype":"venue"
},
  "geometry": {"coordinates":[4.844421,45.761398],"type":"Point"}
}