{
  "type": "Feature",
  "properties": {
    "addr:full":"9 chemin de Thil 01700 St Maurice de Beynost Rhone-Alpes",
    "addr:housenumber":"9",
    "addr:postcode":"01700",
    "addr:street":"Chemin De Thil",
    "iso:country":"FR",
    "sg:address":"9 chemin de Thil 01700 St Maurice de Beynost",
    "sg:classifiers":[
        {
            "category":"Manufacturing",
            "subcategory":"Rubber & Plastics",
            "type":"Manufacturing & Wholesale Goods"
        }
    ],
    "sg:phone":"+33 4 78 55 79 55",
    "sg:province":"Rhone-Alpes",
    "sg:tags":[
        "machine",
        "industry",
        "special"
    ],
    "wof:name":"Sidel Machines Et Syst\u00e8mes Sa",
    "wof:placetype":"venue"
},
  "geometry": {"coordinates":[4.98174,45.825859],"type":"Point"}
}