{
  "type": "Feature",
  "properties": {
    "iso:country":"FR",
    "sg:address":"1 Rue Du M\u00f4le 29770 Audierne",
    "sg:city":"Audierne",
    "sg:classifiers":[
        {
            "category":"Farming",
            "subcategory":"Livestock Farm",
            "type":"Manufacturing & Wholesale Goods"
        }
    ],
    "sg:phone":"+33 2 98 70 10 04",
    "sg:postcode":"29770",
    "sg:province":"Bretagne",
    "sg:tags":[
        "breeding",
        "agriculture",
        "animal"
    ],
    "wof:name":"Les Viviers Daudierne Sa",
    "wof:placetype":"venue"
},
  "geometry": {"coordinates":[-4.5421,48.012177],"type":"Point"}
}