{
  "type": "Feature",
  "properties": {
    "addr:full":"Le Pr\u00e9 De Dou\u00e9 72650 Aign\u00e9 Pays de Loire 72650",
    "addr:postcode":"72650;72650",
    "addr:street":"Aigne\u0301",
    "iso:country":"FR",
    "sg:address":"Le Pr\u00e9 De Dou\u00e9 72650 Aign\u00e9",
    "sg:classifiers":[
        {
            "category":"Manufacturing",
            "subcategory":"Metals",
            "type":"Manufacturing & Wholesale Goods"
        }
    ],
    "sg:phone":"+33 2 43 51 20 20",
    "sg:postcode":"72650",
    "sg:province":"Pays de Loire",
    "sg:tags":[
        "metallurgy",
        "metalworking",
        "processing"
    ],
    "wof:name":"Tech Laser Sa",
    "wof:placetype":"venue"
},
  "geometry": {"coordinates":[0.098585,48.022373],"type":"Point"}
}