{
  "type": "Feature",
  "properties": {
    "iso:country":"FR",
    "sg:address":"147 Ter Av. Fran\u00e7ois Mitt\u00e9rand 65600 S\u00e9m\u00e9ac",
    "sg:classifiers":[
        {
            "category":"Health Services",
            "subcategory":"Medical Lab",
            "type":"Services"
        }
    ],
    "sg:phone":"+33 5 62 33 99 50",
    "sg:postcode":"65600",
    "sg:province":"Midi Pyr\u00e9n\u00e9es",
    "sg:tags":[
        "chemical",
        "pharmaceutical",
        "pharmacy"
    ],
    "wof:name":"Ocp Repartition",
    "wof:placetype":"venue"
},
  "geometry": {"coordinates":[0.104239,43.221645],"type":"Point"}
}