{
  "type": "Feature",
  "properties": {
    "addr:full":"La Trinite sur Mer 56470 La Trinite sur Mer Saint-Philibert Bretagne 56470",
    "addr:postcode":"56470;56470",
    "addr:street":"La Trinite Sur Mer;Trinite",
    "iso:country":"FR",
    "sg:address":"La Trinite sur Mer 56470 La Trinite sur Mer",
    "sg:city":"Saint-Philibert",
    "sg:classifiers":[
        {
            "category":"Transit Center",
            "subcategory":"Freight",
            "type":"Transportation"
        }
    ],
    "sg:phone":"+33 2 97 55 83 02",
    "sg:postcode":"56470",
    "sg:province":"Bretagne",
    "sg:tags":[
        "technical",
        "equipment",
        "ship"
    ],
    "wof:name":"Technique - Greement Sarl",
    "wof:placetype":"venue"
},
  "geometry": {"coordinates":[-3.051504,47.587311],"type":"Point"}
}