{
  "type": "Feature",
  "properties": {
    "addr:full":"45, Rue Carnot, 78700 Conflans Sainte Honorine Ile de France 78700",
    "addr:housenumber":"45",
    "addr:postcode":"78700;78700",
    "addr:street":"Rue Carnot",
    "iso:country":"FR",
    "sg:address":"45, Rue Carnot, 78700 Conflans Sainte Honorine",
    "sg:orig_category":"Non-Classified Establishments",
    "sg:phone":"+33 1 39 72 55 55",
    "sg:postcode":"78700",
    "sg:province":"Ile de France",
    "wof:name":"Cornil S\u00e9curit\u00e9 S.a.r.l.",
    "wof:placetype":"venue"
},
  "geometry": {"coordinates":[2.093635,48.996998],"type":"Point"}
}