{
  "type": "Feature",
  "properties": {
    "addr:full":"rue Pierre Pascal Fauvelle 66000 Perpignan Languedoc-Roussillon 66000",
    "addr:postcode":"66000;66000",
    "addr:street":"Rue Pierre Pascal Fauvelle",
    "iso:country":"FR",
    "sg:address":"rue Pierre Pascal Fauvelle 66000 Perpignan",
    "sg:classifiers":[
        {
            "category":"Wholesale",
            "subcategory":"Wine & Distilled Alcoholic Beverages",
            "type":"Manufacturing & Wholesale Goods"
        }
    ],
    "sg:phone":"+33 4 68 85 06 07",
    "sg:postcode":"66000",
    "sg:province":"Languedoc-Roussillon",
    "sg:tags":[
        "french"
    ],
    "wof:name":"J.p. Henriques Sa",
    "wof:placetype":"venue"
},
  "geometry": {"coordinates":[2.869984,42.682404],"type":"Point"}
}