{
  "type": "Feature",
  "properties": {
    "iso:country":"FR",
    "sg:address":"13 route du Petit Paradis 88530 Le Tholy",
    "sg:classifiers":[
        {
            "category":"Home & Garden",
            "subcategory":"Furniture",
            "type":"Retail Goods"
        }
    ],
    "sg:phone":"+33 3 29 61 82 66",
    "sg:postcode":"88530",
    "sg:province":"Lorraine",
    "sg:tags":[
        "bathroom"
    ],
    "wof:name":"Ferry S.a.r.l.",
    "wof:placetype":"venue"
},
  "geometry": {"coordinates":[6.748674,48.083447],"type":"Point"}
}