{
  "type": "Feature",
  "properties": {
    "addr:full":"17 Rue De Tournon 75006 Paris Ile de France 75006",
    "addr:housenumber":"17",
    "addr:postcode":"75006;75006",
    "addr:street":"Rue De Tournon",
    "iso:country":"FR",
    "sg:address":"17 Rue De Tournon 75006 Paris",
    "sg:orig_category":"Miscellaneous Products",
    "sg:phone":"+33 1 44 41 19 19",
    "sg:postcode":"75006",
    "sg:province":"Ile de France",
    "wof:name":"Centre De Diffusion De L'edition Sa",
    "wof:placetype":"venue"
},
  "geometry": {"coordinates":[2.337383,48.85033],"type":"Point"}
}