{
  "type": "Feature",
  "properties": {
    "addr:full":"Rte De St Loup 70000 Auxon Les Vesoul Franche Comt\u00e9 70000",
    "addr:postcode":"70000;70000",
    "addr:street":"Rte De St Loup;Franche Comte\u0301",
    "iso:country":"FR",
    "sg:address":"Rte De St Loup 70000 Auxon Les Vesoul",
    "sg:classifiers":[
        {
            "category":"Shopping",
            "type":"Retail Goods"
        }
    ],
    "sg:phone":"+33 3 84 75 28 75",
    "sg:postcode":"70000",
    "sg:province":"Franche Comt\u00e9",
    "sg:tags":[
        "metallurgy",
        "finished",
        "-",
        "metalworking",
        "metallic"
    ],
    "wof:name":"Dalvard Industrie Sa",
    "wof:placetype":"venue"
},
  "geometry": {"coordinates":[6.164452,47.649841],"type":"Point"}
}