{
  "type": "Feature",
  "properties": {
    "addr:full":"63 rue Montlosier; Clermont Ferrand; 63961 Clermont Rhone-Alpes 74270",
    "addr:housenumber":"63",
    "addr:postcode":"63961;74270",
    "addr:street":"Rue Montlosier",
    "iso:country":"FR",
    "sg:address":"63 rue Montlosier; Clermont Ferrand; 63961",
    "sg:city":"Clermont",
    "sg:classifiers":[
        {
            "category":"Banks & Credit Unions",
            "subcategory":"Bank",
            "type":"Services"
        }
    ],
    "sg:phone":"+33 4473985858",
    "sg:postcode":"74270",
    "sg:province":"Rhone-Alpes",
    "wof:name":"Caisse D'epargne, D'auvergne",
    "wof:placetype":"venue"
},
  "geometry": {"coordinates":[3.09024,45.781467],"type":"Point"}
}