{
  "type": "Feature",
  "properties": {
    "addr:full":"6, Rue des Boulets, 75011 Paris Ile de France",
    "addr:housenumber":"6",
    "addr:postcode":"75011",
    "addr:street":"Rue Des Boulets",
    "iso:country":"FR",
    "sg:address":"6, Rue des Boulets, 75011 Paris",
    "sg:orig_category":"Unclassifiable Establishments",
    "sg:phone":"+33 1 43 73 47 83",
    "sg:province":"Ile de France",
    "wof:name":"S\u00e9vec S.a.r.l.",
    "wof:placetype":"venue"
},
  "geometry": {"coordinates":[2.391763,48.849483],"type":"Point"}
}