{
  "type": "Feature",
  "properties": {
    "iso:country":"FR",
    "sg:address":"RN 134",
    "sg:city":"Serres Castet",
    "sg:orig_category":"Non-Classified Establishments",
    "sg:phone":"+33 5 59 33 10 33",
    "sg:postcode":"64121",
    "sg:province":"Aquitaine",
    "wof:name":"Garvite S.a.",
    "wof:placetype":"venue"
},
  "geometry": {"coordinates":[-0.380334,43.376003],"type":"Point"}
}