{
  "type": "Feature",
  "properties": {
    "iso:country":"FR",
    "sg:address":"Rue des M\u00e9tiers - ZI de la Caille",
    "sg:city":"Nuaill\u00e9",
    "sg:orig_category":"Non-Classified Establishments",
    "sg:phone":"+33 2 41 46 41 04",
    "sg:postcode":"49340",
    "sg:province":"Pays de Loire",
    "wof:name":"M.c.e.s. S.a.",
    "wof:placetype":"venue"
},
  "geometry": {"coordinates":[-0.685015,47.095284],"type":"Point"}
}