{
  "type": "Feature",
  "properties": {
    "addr:full":"Le Tremblay 61100 Flers Flers Basse Normandie 61100",
    "addr:postcode":"61100;61100",
    "iso:country":"FR",
    "sg:address":"Le Tremblay 61100 Flers",
    "sg:city":"Flers",
    "sg:classifiers":[
        {
            "category":"Manufacturing",
            "subcategory":"Rubber & Plastics",
            "type":"Manufacturing & Wholesale Goods"
        }
    ],
    "sg:phone":"+33 2 33 66 59 32",
    "sg:postcode":"61100",
    "sg:province":"Basse Normandie",
    "sg:tags":[
        "packaging",
        "material",
        "-"
    ],
    "wof:name":"Plastireve Sa",
    "wof:placetype":"venue"
},
  "geometry": {"coordinates":[-0.57946,48.752209],"type":"Point"}
}