{
  "type": "Feature",
  "properties": {
    "addr:full":"10, All\u00e9e des Acacias, 01440 Viriat Rhone-Alpes",
    "addr:housenumber":"10",
    "addr:postcode":"01440",
    "addr:street":"Alle\u0301E Des Acacias",
    "iso:country":"FR",
    "sg:address":"10, All\u00e9e des Acacias, 01440 Viriat",
    "sg:orig_category":"Unclassifiable Establishments",
    "sg:phone":"+33 4 74 25 36 99",
    "sg:province":"Rhone-Alpes",
    "wof:name":"Entreprise Joly Patrick",
    "wof:placetype":"venue"
},
  "geometry": {"coordinates":[5.225626,46.23867],"type":"Point"}
}