{
  "type": "Feature",
  "properties": {
    "iso:country":"FR",
    "sg:address":"14, Rue de Provigny, 94230 Cachan",
    "sg:orig_category":"Unclassifiable Establishments",
    "sg:phone":"+33 1 47 40 67 90",
    "sg:province":"Ile de France",
    "wof:name":"Datec S.a.r.l.",
    "wof:placetype":"venue"
},
  "geometry": {"coordinates":[2.330956,48.797344],"type":"Point"}
}