{
  "type": "Feature",
  "properties": {
    "addr:full":"68 Bd Malesherbes 75008 Paris Ile de France 75008",
    "addr:housenumber":"68",
    "addr:postcode":"75008;75008",
    "addr:street":"Bd Malesherbes",
    "iso:country":"FR",
    "sg:address":"68 Bd Malesherbes 75008 Paris",
    "sg:classifiers":[
        {
            "category":"Shopping",
            "subcategory":"Gifts & Souvenirs",
            "type":"Retail Goods"
        }
    ],
    "sg:phone":"+33 1 45 22 16 89",
    "sg:postcode":"75008",
    "sg:province":"Ile de France",
    "sg:tags":[
        "product",
        "miscellaneous"
    ],
    "wof:name":"Brame Et Lorenceau",
    "wof:placetype":"venue"
},
  "geometry": {"coordinates":[2.315973,48.87825],"type":"Point"}
}