{
  "type": "Feature",
  "properties": {
    "iso:country":"FR",
    "sg:address":"107, Rte du Plan - ZAC Sainte Marguerite Lot 10, 06130 Grasse",
    "sg:orig_category":"Unclassifiable Establishments",
    "sg:phone":"+33 4 93 70 96 60",
    "sg:province":"Provence-Alpes-C\u00f4te d'Azur",
    "wof:name":"Trabal S.a.",
    "wof:placetype":"venue"
},
  "geometry": {"coordinates":[6.931648,43.649738],"type":"Point"}
}