{
  "type": "Feature",
  "properties": {
    "addr:full":"21, Av. Lamartine - ZA de l'Agavon, 13170 Les Pennes Mirabeau Provence-Alpes-C\u00f4te d'Azur",
    "addr:postcode":"13170",
    "addr:street":"21 Av. Lamartine Za De L'Agavon;Pennes Mirabeau",
    "iso:country":"FR",
    "sg:address":"21, Av. Lamartine - ZA de l'Agavon, 13170 Les Pennes Mirabeau",
    "sg:orig_category":"Non-Classified Establishments",
    "sg:phone":"+33 4 42 02 02 35",
    "sg:province":"Provence-Alpes-C\u00f4te d'Azur",
    "wof:name":"Technipipe S.a.",
    "wof:placetype":"venue"
},
  "geometry": {"coordinates":[5.282638,43.417511],"type":"Point"}
}