{
  "type": "Feature",
  "properties": {
    "iso:country":"FR",
    "sg:address":"6, Rue Demages, 82370 Labastide Saint Pierre",
    "sg:orig_category":"Unclassifiable Establishments",
    "sg:phone":"+33 5 63 64 01 80",
    "sg:province":"Midi Pyr\u00e9n\u00e9es",
    "wof:name":"Arbeau P\u00e8re Et Fils S.a.",
    "wof:placetype":"venue"
},
  "geometry": {"coordinates":[1.367,43.918434],"type":"Point"}
}