{
  "type": "Feature",
  "properties": {
    "addr:full":"5 Quai l'Herminier 44380 PORNICHET Pays de Loire 44380",
    "addr:housenumber":"5",
    "addr:postcode":"44380;44380",
    "addr:street":"Quai L'Herminier",
    "iso:country":"FR",
    "sg:address":"5 Quai l'Herminier 44380 PORNICHET",
    "sg:classifiers":[
        {
            "category":"Food & Beverages",
            "subcategory":"Groceries & Convenience Stores",
            "type":"Retail Goods"
        }
    ],
    "sg:phone":"+33 2 40 82 27 11",
    "sg:postcode":"44380",
    "sg:province":"Pays de Loire",
    "sg:tags":[
        "flour",
        "meal"
    ],
    "wof:name":"Minoterie Laraison Sa",
    "wof:placetype":"venue"
},
  "geometry": {"coordinates":[-2.428184,47.278477],"type":"Point"}
}