{
  "type": "Feature",
  "properties": {
    "addr:full":"14 rue Beauregard 75002 Paris Ile de France 75002",
    "addr:housenumber":"14",
    "addr:postcode":"75002;75002",
    "addr:street":"Rue Beauregard",
    "iso:country":"FR",
    "sg:address":"14 rue Beauregard 75002 Paris",
    "sg:classifiers":[
        {
            "category":"Shopping",
            "subcategory":"Clothing, Apparel, & Fashions",
            "type":"Retail Goods"
        }
    ],
    "sg:phone":"+33 1 42 33 66 42",
    "sg:postcode":"75002",
    "sg:province":"Ile de France",
    "sg:tags":[
        "blouse",
        "ladies'",
        "dress"
    ],
    "wof:name":"Textiles Center Sarl",
    "wof:placetype":"venue"
},
  "geometry": {"coordinates":[2.348766,48.869125],"type":"Point"}
}