{
  "type": "Feature",
  "properties": {
    "iso:country":"FR",
    "sg:address":"Usine de Fimbrune 61600 LA FERTE MACE",
    "sg:city":"Beauvain",
    "sg:classifiers":[
        {
            "category":"Manufacturing",
            "subcategory":"Rubber & Plastics",
            "type":"Manufacturing & Wholesale Goods"
        }
    ],
    "sg:phone":"+33 2 33 30 66 66",
    "sg:postcode":"61600",
    "sg:province":"Basse Normandie",
    "sg:tags":[
        "packaging",
        "mean"
    ],
    "wof:name":"Manuplast Sa",
    "wof:placetype":"venue"
},
  "geometry": {"coordinates":[-0.300768,48.54089],"type":"Point"}
}