{
  "type": "Feature",
  "properties": {
    "addr:full":"5, Av. Descartes, 94450 Limeil Brevannes Ile de France",
    "addr:postcode":"94450",
    "addr:street":"Av. Descartes",
    "iso:country":"FR",
    "sg:address":"5, Av. Descartes, 94450 Limeil Brevannes",
    "sg:orig_category":"Unclassifiable Establishments",
    "sg:phone":"+33 1 45 99 10 10",
    "sg:province":"Ile de France",
    "wof:name":"Air Signs S.a.r.l.",
    "wof:placetype":"venue"
},
  "geometry": {"coordinates":[2.488727,48.740147],"type":"Point"}
}