{
  "type": "Feature",
  "properties": {
    "addr:full":"36 Rue La March\u00e9 23270 Ch\u00e2telus Malvaleix Limousin 23270",
    "addr:housenumber":"36",
    "addr:postcode":"23270;malvaleix;23270",
    "addr:street":"Rue La Marche\u0301",
    "iso:country":"FR",
    "sg:address":"36 Rue La March\u00e9 23270 Ch\u00e2telus Malvaleix",
    "sg:classifiers":[
        {
            "category":"Professional",
            "subcategory":"Business Services",
            "type":"Services"
        }
    ],
    "sg:phone":"+33 5 55 80 70 14",
    "sg:postcode":"23270",
    "sg:province":"Limousin",
    "sg:tags":[
        "training",
        "advice"
    ],
    "wof:name":"College Fran\u00c7oise Dolto",
    "wof:placetype":"venue"
},
  "geometry": {"coordinates":[2.049078,46.248264],"type":"Point"}
}