{
  "type": "Feature",
  "properties": {
    "addr:full":"74, Rue de Bonnel, 69003 Lyon Rhone-Alpes 69003",
    "addr:housenumber":"74",
    "addr:postcode":"69003;69003",
    "addr:street":"Rue De Bonnel",
    "iso:country":"FR",
    "sg:address":"74, Rue de Bonnel, 69003 Lyon",
    "sg:orig_category":"Unclassifiable Establishments",
    "sg:phone":"+33 4 72 84 61 61",
    "sg:postcode":"69003",
    "sg:province":"Rhone-Alpes",
    "wof:name":"Cyber Conseil S.a.r.l.",
    "wof:placetype":"venue"
},
  "geometry": {"coordinates":[4.850818,45.761871],"type":"Point"}
}