{
  "type": "Feature",
  "properties": {
    "addr:full":"B.P. 7 Betton Bretagne 35830",
    "addr:postcode":"35830",
    "addr:street":"B.P. 7",
    "iso:country":"FR",
    "sg:address":"B.P. 7",
    "sg:city":"Betton",
    "sg:orig_category":"Non-Classified Establishments",
    "sg:phone":"+33 2 99 55 07 55",
    "sg:postcode":"35830",
    "sg:province":"Bretagne",
    "wof:name":"Cedricom S.a.r.l. - Conception Etude Et D\u00e9veloppement De R\u00e9seaux Info",
    "wof:placetype":"venue"
},
  "geometry": {"coordinates":[-1.647044,48.18317],"type":"Point"}
}