{
  "type": "Feature",
  "properties": {
    "addr:full":"39, Rue Paul Claudel, 91000 Evry Ile de France",
    "addr:housenumber":"39",
    "addr:postcode":"91000",
    "addr:street":"Rue Paul Claudel",
    "iso:country":"FR",
    "sg:address":"39, Rue Paul Claudel, 91000 Evry",
    "sg:orig_category":"Unclassifiable Establishments",
    "sg:phone":"+33 1 60 77 69 28",
    "sg:province":"Ile de France",
    "wof:name":"Burotec I.d.f. S.a.r.l. - Burotec Ing\u00e9nierie D\u00e9veloppement Formation",
    "wof:placetype":"venue"
},
  "geometry": {"coordinates":[2.430712,48.638309],"type":"Point"}
}