{
  "type": "Feature",
  "properties": {
    "addr:full":"1, Rue du Pont \u00e0 Poissons, 59380 Armbouts Cappel Nord Pas-de-Calais",
    "addr:housenumber":"1",
    "addr:postcode":"59380",
    "addr:street":"Rue Du Pont A\u0300 Poissons;Cappel Nord",
    "iso:country":"FR",
    "sg:address":"1, Rue du Pont \u00e0 Poissons, 59380 Armbouts Cappel",
    "sg:orig_category":"Unclassifiable Establishments",
    "sg:phone":"+33 3 28 27 06 24",
    "sg:province":"Nord Pas-de-Calais",
    "wof:name":"S.m.i.b. S.a.r.l. - Soci\u00e9t\u00e9 De Maintenance Industrielle Et B\u00e2timent",
    "wof:placetype":"venue"
},
  "geometry": {"coordinates":[2.343091,50.977112],"type":"Point"}
}