{
  "type": "Feature",
  "properties": {
    "addr:full":"B.P. 93482, 67456 Mundolsheim C\u00e9dex^^Rue du Chemin de Fer - Zone Industrielle, 67116 Reichstett Reichstett Alsace 67116",
    "addr:postcode":"67456;67116;67116",
    "addr:street":"Chemin De Fer Zone Industrielle",
    "iso:country":"FR",
    "sg:address":"B.P. 93482, 67456 Mundolsheim C\u00e9dex^^Rue du Chemin de Fer - Zone Industrielle, 67116 Reichstett",
    "sg:city":"Reichstett",
    "sg:orig_category":"Non-Classified Establishments",
    "sg:phone":"+33 3 88 81 88 84",
    "sg:postcode":"67116",
    "sg:province":"Alsace",
    "wof:name":"Boreal Services S.a.",
    "wof:placetype":"venue"
},
  "geometry": {"coordinates":[7.753589,48.648308],"type":"Point"}
}