{
  "type": "Feature",
  "properties": {
    "addr:full":"9 rue Desargues Paris 75011",
    "addr:housenumber":"9",
    "addr:postcode":"75011",
    "addr:street":"Rue Desargues",
    "iso:country":"FR",
    "sg:address":"9 rue Desargues",
    "sg:city":"Paris",
    "sg:classifiers":[
        {
            "category":"Professional",
            "subcategory":"Computer Services",
            "type":"Services"
        }
    ],
    "sg:postcode":"75011",
    "sg:tags":[
        "opensource",
        "oss",
        "plone",
        "zope",
        "python",
        "development",
        "virtualization",
        "xen",
        "hosting",
        "collaborative-work",
        "content-management",
        "intranet",
        "wiki-at-work",
        "trackr",
        "apros-plone"
    ],
    "sg:website":"http://www.pilotsystems.net",
    "wof:name":"Pilot Systems",
    "wof:placetype":"venue"
},
  "geometry": {"coordinates":[2.376362,48.869608],"type":"Point"}
}