{
  "type": "Feature",
  "properties": {
    "iso:country":"FR",
    "sg:address":"39, Rue Henri Barbusse, 93300 Aubervilliers",
    "sg:orig_category":"Non-Classified Establishments",
    "sg:phone":"+33 1 48 39 13 10",
    "sg:province":"Ile de France",
    "wof:name":"Narcy Et Compagnie S.a.r.l",
    "wof:placetype":"venue"
},
  "geometry": {"coordinates":[2.388944,48.904346],"type":"Point"}
}