{
  "type": "Feature",
  "properties": {
    "iso:country":"FR",
    "sg:address":"ZAC du Terlon",
    "sg:city":"Montrab\u00e9",
    "sg:orig_category":"Unclassifiable Establishments",
    "sg:phone":"+33 5 61 84 38 02",
    "sg:postcode":"31850",
    "sg:province":"Midi Pyr\u00e9n\u00e9es",
    "wof:name":"S.b.t. S.a. - Soci\u00e9t\u00e9 S\u00e9rigraphie Broderie Toulousaine",
    "wof:placetype":"venue"
},
  "geometry": {"coordinates":[1.52437,43.642906],"type":"Point"}
}