{
  "type": "Feature",
  "properties": {
    "addr:full":"3, Rte de la Tuilerie, 01100 Arbent Rhone-Alpes",
    "addr:housenumber":"3",
    "addr:postcode":"01100",
    "addr:street":"Rte De La Tuilerie",
    "iso:country":"FR",
    "sg:address":"3, Rte de la Tuilerie, 01100 Arbent",
    "sg:orig_category":"Non-Classified Establishments",
    "sg:phone":"+33 4 74 77 04 70",
    "sg:province":"Rhone-Alpes",
    "wof:name":"Plasti Cristal S.a.",
    "wof:placetype":"venue"
},
  "geometry": {"coordinates":[5.666572,46.272892],"type":"Point"}
}