{
  "type": "Feature",
  "properties": {
    "iso:country":"FR",
    "sg:address":"Place Galignani",
    "sg:city":"Corbeil Essonnes",
    "sg:orig_category":"Non-Classified Establishments",
    "sg:phone":"+33 1 60 90 41 00",
    "sg:postcode":"91100",
    "sg:province":"Ile de France",
    "wof:name":"Fran\u00e7aise De Meunerie",
    "wof:placetype":"venue"
},
  "geometry": {"coordinates":[2.48195,48.613609],"type":"Point"}
}