{
  "type": "Feature",
  "properties": {
    "addr:full":"43 Rue Jean Lecanuet Rouen Haute Normandie 76000",
    "addr:housenumber":"43",
    "addr:postcode":"76000",
    "addr:street":"Rue Jean Lecanuet;Haute Normandie",
    "iso:country":"FR",
    "sg:address":"43 Rue Jean Lecanuet",
    "sg:city":"Rouen",
    "sg:classifiers":[
        {
            "category":"Banks & Credit Unions",
            "subcategory":"Financial Services",
            "type":"Services"
        }
    ],
    "sg:phone":"+33 2 35 88 16 52",
    "sg:postcode":"76000",
    "sg:province":"Haute Normandie",
    "sg:tags":[
        "banking",
        "finance",
        "insurance"
    ],
    "wof:name":"Renaud Delubac",
    "wof:placetype":"venue"
},
  "geometry": {"coordinates":[1.092682,49.444519],"type":"Point"}
}