{
  "type": "Feature",
  "properties": {
    "addr:full":"Rte du Faye d'Ajou Thouarc\u00e9 Pays de Loire 49380",
    "addr:postcode":"49380",
    "addr:street":"Rte Du Faye D'Ajou",
    "iso:country":"FR",
    "sg:address":"Rte du Faye d'Ajou",
    "sg:city":"Thouarc\u00e9",
    "sg:orig_category":"Non-Classified Establishments",
    "sg:phone":"+33 2 41 79 43 43",
    "sg:postcode":"49380",
    "sg:province":"Pays de Loire",
    "wof:name":"Anjou Emballages S.a.",
    "wof:placetype":"venue"
},
  "geometry": {"coordinates":[-0.429959,47.233604],"type":"Point"}
}