{
  "type": "Feature",
  "properties": {
    "iso:country":"FR",
    "sg:address":"Zi Le Monge Rn 21 65100 Lourdes",
    "sg:classifiers":[
        {
            "category":"Manufacturing",
            "subcategory":"Rubber & Plastics",
            "type":"Manufacturing & Wholesale Goods"
        }
    ],
    "sg:phone":"+33 5 62 94 60 59",
    "sg:province":"Midi Pyr\u00e9n\u00e9es",
    "wof:name":"Dep",
    "wof:placetype":"venue"
},
  "geometry": {"coordinates":[0.007055,43.032288],"type":"Point"}
}