{
  "type": "Feature",
  "properties": {
    "iso:country":"FR",
    "sg:address":"Le Cormier 49140 Jarz\u00e9",
    "sg:orig_category":"Non-Classified Establishments",
    "sg:phone":"+33 2 41 95 50 55",
    "sg:postcode":"49140",
    "sg:province":"Pays de Loire",
    "wof:name":"Alfalux S.a.r.l.",
    "wof:placetype":"venue"
},
  "geometry": {"coordinates":[-0.210994,47.568054],"type":"Point"}
}