{
  "type": "Feature",
  "properties": {
    "iso:country":"FR",
    "sg:address":"1",
    "sg:city":"Wissembourg",
    "sg:classifiers":[
        {
            "category":"Banks & Credit Unions",
            "subcategory":"Bank",
            "type":"Services"
        }
    ],
    "sg:phone":"+33 3388940998",
    "sg:postcode":"67160",
    "sg:province":"Alsace",
    "wof:name":"Soci\u00e9t\u00e9 G\u00e9n\u00e9rale",
    "wof:placetype":"venue"
},
  "geometry": {"coordinates":[7.94472,49.03672],"type":"Point"}
}