{
  "type": "Feature",
  "properties": {
    "iso:country":"FR",
    "sg:address":"33, Rue de Paris, 59800 Lille",
    "sg:orig_category":"Non-Classified Establishments",
    "sg:phone":"+33 3 20 13 19 09",
    "sg:postcode":"59800",
    "sg:province":"Nord Pas-de-Calais",
    "wof:name":"Agents Doubles S.a.r.l.",
    "wof:placetype":"venue"
},
  "geometry": {"coordinates":[3.066377,50.636082],"type":"Point"}
}