{
  "type": "Feature",
  "properties": {
    "iso:country":"FR",
    "sg:address":"B.P. 102000, 13793 Aix en Provence C\u00e9dex 03^^1030, Av. Guillibert de la Lauzi\u00e8re - ZAC de Pichaury I",
    "sg:orig_category":"Non-Classified Establishments",
    "sg:phone":"+33 4 42 60 70 15",
    "sg:province":"Picardie",
    "wof:name":"I 2 E Diffusion S.a.",
    "wof:placetype":"venue"
},
  "geometry": {"coordinates":[5.4542,43.52494],"type":"Point"}
}