{
  "type": "Feature",
  "properties": {
    "iso:country":"FR",
    "sg:address":"7, Av du G\u00e9n\u00e9ral de Gaulle, 57050 Le Ban Saint Martin",
    "sg:orig_category":"Non-Classified Establishments",
    "sg:phone":"+33 3 87 30 39 76",
    "sg:province":"Lorraine",
    "wof:name":"T.c.s. Informatique S.a.r.l. - Terminal Computer System Informatique",
    "wof:placetype":"venue"
},
  "geometry": {"coordinates":[6.149045,49.12122],"type":"Point"}
}