{
  "type": "Feature",
  "properties": {
    "addr:full":"21 cours Verdun; Bordeaux Bordeaux Aquitaine 33100",
    "addr:housenumber":"21",
    "addr:postcode":"33100",
    "addr:street":"Cours Verdun",
    "iso:country":"FR",
    "sg:address":"21 cours Verdun; Bordeaux",
    "sg:city":"Bordeaux",
    "sg:classifiers":[
        {
            "category":"Banks & Credit Unions",
            "subcategory":"Bank",
            "type":"Services"
        }
    ],
    "sg:phone":"+33 3356528170",
    "sg:postcode":"33100",
    "sg:province":"Aquitaine",
    "wof:name":"Cr\u00e9dit Universel",
    "wof:placetype":"venue"
},
  "geometry": {"coordinates":[-0.577022,44.846886],"type":"Point"}
}