{
  "type": "Feature",
  "properties": {
    "addr:full":"1200, Rte de Lucioles - Espace Beethoven, B\u00e2t 2B, 06560 Valbonne Provence-Alpes-C\u00f4te d'Azur",
    "addr:housenumber":"1200;ba\u0302t 2b",
    "addr:postcode":"06560",
    "addr:street":"Rte De Lucioles Espace Beethoven",
    "iso:country":"FR",
    "sg:address":"1200, Rte de Lucioles - Espace Beethoven, B\u00e2t 2B, 06560 Valbonne",
    "sg:orig_category":"Unclassifiable Establishments",
    "sg:phone":"+33 4 93 00 45 80",
    "sg:province":"Provence-Alpes-C\u00f4te d'Azur",
    "wof:name":"Wimba S.a.",
    "wof:placetype":"venue"
},
  "geometry": {"coordinates":[7.031405,43.631126],"type":"Point"}
}