{
  "type": "Feature",
  "properties": {
    "iso:country":"FR",
    "sg:address":"B.P. 6, 77820 Le Ch\u00e2telet en Brie^^ZI de Chatelet en Brie, 77820 Le Ch\u00e2telet en Brie",
    "sg:orig_category":"Non-Classified Establishments",
    "sg:phone":"+33 1 60 66 50 10",
    "sg:province":"Ile de France",
    "wof:name":"S.e.r.i.c. S.a. - Soci\u00e9t\u00e9 D'etudes R\u00e9alisation Industrielle Commerci",
    "wof:placetype":"venue"
},
  "geometry": {"coordinates":[2.792585,48.504356],"type":"Point"}
}