{
  "type": "Feature",
  "properties": {
    "iso:country":"FR",
    "sg:address":"2Bis rue Foch 62860 RUMAUCOURT",
    "sg:classifiers":[
        {
            "category":"Wholesale",
            "subcategory":"Machinery & Supplies",
            "type":"Manufacturing & Wholesale Goods"
        }
    ],
    "sg:phone":"+33 3 21 73 07 15",
    "sg:postcode":"62860",
    "sg:province":"Nord Pas-de-Calais",
    "sg:tags":[
        "agricultural",
        "equipment"
    ],
    "wof:name":"Usines De Rumaucourt Sa",
    "wof:placetype":"venue"
},
  "geometry": {"coordinates":[3.062956,50.246193],"type":"Point"}
}