{
  "type": "Feature",
  "properties": {
    "iso:country":"FR",
    "sg:address":"8 rue Jean Epivent 22590 Pordic",
    "sg:city":"Pordic",
    "sg:classifiers":[
        {
            "category":"Retail",
            "subcategory":"Event Space",
            "type":"Services"
        }
    ],
    "sg:phone":"+33 2 96 79 17 17",
    "sg:postcode":"22590",
    "sg:province":"Bretagne",
    "sg:tags":[
        "small",
        "leather",
        "good"
    ],
    "wof:name":"Emi Accessoires Mode S.a.r.l.",
    "wof:placetype":"venue"
},
  "geometry": {"coordinates":[-2.809396,48.557068],"type":"Point"}
}