{
  "type": "Feature",
  "properties": {
    "iso:country":"FR",
    "sg:address":"54 bis, Bd Alsace Lorraine, 64000 Pau",
    "sg:city":"Pau",
    "sg:orig_category":"Non-Classified Establishments",
    "sg:phone":"+33 5 59 90 32 32",
    "sg:postcode":"64000",
    "sg:province":"Aquitaine",
    "wof:name":"As Electronique S.a.r.l.",
    "wof:placetype":"venue"
},
  "geometry": {"coordinates":[-0.368611,43.304726],"type":"Point"}
}