{
  "type": "Feature",
  "properties": {
    "iso:country":"FR",
    "sg:address":"Zi 60730 Novillers",
    "sg:classifiers":[
        {
            "category":"Manufacturing",
            "subcategory":"Paper Products",
            "type":"Manufacturing & Wholesale Goods"
        }
    ],
    "sg:phone":"+33 3 44 08 26 40",
    "sg:province":"Picardie",
    "sg:tags":[
        "raw",
        "material",
        "-",
        "cardboard"
    ],
    "wof:name":"Sca Packaging",
    "wof:placetype":"venue"
},
  "geometry": {"coordinates":[2.281035,49.27602],"type":"Point"}
}