{
  "type": "Feature",
  "properties": {
    "addr:full":"18, Rue l'Erboni\u00e8re - ZI Sud Est, 35510 Cesson S\u00e9vign\u00e9 Cesson-S\u00e9vign\u00e9 Bretagne 35510",
    "addr:housenumber":"18",
    "addr:postcode":"35510;se\u0301vigne\u0301 cesson-se\u0301vigne\u0301;35510",
    "addr:street":"Rue L'Erbonie \u0300Re Zi Sud Est",
    "iso:country":"FR",
    "sg:address":"18, Rue l'Erboni\u00e8re - ZI Sud Est, 35510 Cesson S\u00e9vign\u00e9",
    "sg:city":"Cesson-S\u00e9vign\u00e9",
    "sg:orig_category":"Non-Classified Establishments",
    "sg:phone":"+33 2 99 41 80 88",
    "sg:postcode":"35510",
    "sg:province":"Bretagne",
    "wof:name":"Socom Industrie S.a.",
    "wof:placetype":"venue"
},
  "geometry": {"coordinates":[-1.623044,48.102512],"type":"Point"}
}