{
  "type": "Feature",
  "properties": {
    "addr:full":"La Brahigue 61130 Le Gu\u00e9 De La Cha\u00eene Appenai-sous-Bell\u00eame Basse Normandie 61130",
    "addr:postcode":"61130;61130",
    "addr:street":"Gue\u0301 De La Chai\u0302Ne",
    "iso:country":"FR",
    "sg:address":"La Brahigue 61130 Le Gu\u00e9 De La Cha\u00eene",
    "sg:city":"Appenai-sous-Bell\u00eame",
    "sg:classifiers":[
        {
            "category":"Autos & Motor Vehicles",
            "subcategory":"Automobile Sales",
            "type":"Retail Goods"
        }
    ],
    "sg:phone":"+33 2 33 73 00 97",
    "sg:postcode":"61130",
    "sg:province":"Basse Normandie",
    "sg:tags":[
        "equipment",
        "industrial",
        "transport"
    ],
    "wof:name":"C T I Sa",
    "wof:placetype":"venue"
},
  "geometry": {"coordinates":[0.544102,48.268017],"type":"Point"}
}