{
  "type": "Feature",
  "properties": {
    "addr:full":"22 Rue Du Port De L Ancre 49000 Angers Pays de Loire 49000",
    "addr:housenumber":"22",
    "addr:postcode":"49000;49000",
    "addr:street":"Rue Du Port De L Ancre",
    "iso:country":"FR",
    "sg:address":"22 Rue Du Port De L Ancre 49000 Angers",
    "sg:classifiers":[
        {
            "category":"Shopping",
            "subcategory":"Computers & Home Electronics",
            "type":"Retail Goods"
        }
    ],
    "sg:phone":"+33 2 41 88 24 76",
    "sg:postcode":"49000",
    "sg:province":"Pays de Loire",
    "sg:tags":[
        "electronic",
        "electrical",
        "equipment"
    ],
    "wof:name":"Societe D'application Des Techniques Electroniques (satel)",
    "wof:placetype":"venue"
},
  "geometry": {"coordinates":[-0.551966,47.475224],"type":"Point"}
}