{
  "type": "Feature",
  "properties": {
    "addr:full":"Av. Kennedy - ZI de Saint C\u00e9saire N\u00eemes Languedoc-Roussillon 30900",
    "addr:postcode":"30900",
    "addr:street":"Av. Kennedy Zi De Saint Ce\u0301Saire",
    "iso:country":"FR",
    "sg:address":"Av. Kennedy - ZI de Saint C\u00e9saire",
    "sg:city":"N\u00eemes",
    "sg:orig_category":"Unclassifiable Establishments",
    "sg:phone":"+33 4 66 62 68 68",
    "sg:postcode":"30900",
    "sg:province":"Languedoc-Roussillon",
    "wof:name":"Etablissements Baur\u00e8s",
    "wof:placetype":"venue"
},
  "geometry": {"coordinates":[4.356115,43.830025],"type":"Point"}
}