{
  "type": "Feature",
  "properties": {
    "iso:country":"FR",
    "sg:address":"B.P. CE 255, 92637 Gennevilliers C\u00e9dex^^15/19, Rte de la Seine, 92230 Port de Gennevilliers",
    "sg:orig_category":"Non-Classified Establishments",
    "sg:phone":"+33 1 47 94 98 33",
    "sg:province":"Ile de France",
    "wof:name":"Kdi Hardy Ba S.a.s.",
    "wof:placetype":"venue"
},
  "geometry": {"coordinates":[2.29447,48.925026],"type":"Point"}
}