{
  "type": "Feature",
  "properties": {
    "iso:country":"FR",
    "sg:address":"10 rue Joseph Cugnot 31600 Muret",
    "sg:classifiers":[
        {
            "category":"Manufacturing",
            "subcategory":"Rubber & Plastics",
            "type":"Manufacturing & Wholesale Goods"
        }
    ],
    "sg:phone":"+33 5 61 51 13 83",
    "sg:province":"Midi Pyr\u00e9n\u00e9es",
    "sg:tags":[
        "processing"
    ],
    "wof:name":"M\u00e9t\u00e9ore S.a.",
    "wof:placetype":"venue"
},
  "geometry": {"coordinates":[1.341517,43.479748],"type":"Point"}
}