{
  "type": "Feature",
  "properties": {
    "addr:full":"210 Rte Ing\u00e9nieur Sansouble 74800 La Roche Sur Foron Rhone-Alpes 74800",
    "addr:housenumber":"210",
    "addr:postcode":"74800;74800",
    "addr:street":"Rte Inge\u0301Nieur Sansouble",
    "iso:country":"FR",
    "sg:address":"210 Rte Ing\u00e9nieur Sansouble 74800 La Roche Sur Foron",
    "sg:classifiers":[
        {
            "category":"Professional",
            "subcategory":"Business Services",
            "type":"Services"
        }
    ],
    "sg:phone":"+33 4 50 03 03 37",
    "sg:postcode":"74800",
    "sg:province":"Rhone-Alpes",
    "sg:tags":[
        "travel",
        "fair"
    ],
    "wof:name":"Association Foire Exposition Haute Savoie",
    "wof:placetype":"venue"
},
  "geometry": {"coordinates":[6.30206,46.075954],"type":"Point"}
}