{
  "type": "Feature",
  "properties": {
    "iso:country":"FR",
    "sg:address":"116 avenue Gabriel P\u00e9ri 93400 ST OUEN",
    "sg:classifiers":[
        {
            "category":"Manufacturing",
            "subcategory":"Chemicals & Compounds",
            "type":"Manufacturing & Wholesale Goods"
        }
    ],
    "sg:phone":"+33 1 40 11 64 08",
    "sg:postcode":"93400",
    "sg:province":"Ile de France",
    "sg:tags":[
        "base"
    ],
    "wof:name":"Sicolor Sa",
    "wof:placetype":"venue"
},
  "geometry": {"coordinates":[2.330681,48.903313],"type":"Point"}
}