{
  "type": "Feature",
  "properties": {
    "iso:country":"FR",
    "sg:address":"17, All\u00e9e des Foulons - Parc des Tanneries, 67380 Lingolsheim",
    "sg:city":"Lingolsheim",
    "sg:orig_category":"Unclassifiable Establishments",
    "sg:phone":"+33 3 90 20 20 20",
    "sg:postcode":"67380",
    "sg:province":"Alsace",
    "wof:name":"Details S.a.",
    "wof:placetype":"venue"
},
  "geometry": {"coordinates":[7.69436,48.55748],"type":"Point"}
}