{
  "type": "Feature",
  "properties": {
    "addr:full":"1, Rue Bernad Jugault, 92600 Asni\u00e8res sur Seine Ile de France",
    "addr:housenumber":"1",
    "addr:postcode":"92600",
    "addr:street":"Rue Bernad Jugault",
    "iso:country":"FR",
    "sg:address":"1, Rue Bernad Jugault, 92600 Asni\u00e8res sur Seine",
    "sg:orig_category":"Unclassifiable Establishments",
    "sg:phone":"+33 1 47 33 97 10",
    "sg:province":"Ile de France",
    "wof:name":"Etablissements Rey S.a.r.l.",
    "wof:placetype":"venue"
},
  "geometry": {"coordinates":[2.284538,48.908779],"type":"Point"}
}