{
  "type": "Feature",
  "properties": {
    "iso:country":"FR",
    "sg:address":"27, All\u00e9e du Roussillon, 31770 Colomiers",
    "sg:orig_category":"Unclassifiable Establishments",
    "sg:phone":"+33 5 61 15 35 00",
    "sg:province":"Midi Pyr\u00e9n\u00e9es",
    "wof:name":"Prodim S.a.s.",
    "wof:placetype":"venue"
},
  "geometry": {"coordinates":[1.335377,43.609676],"type":"Point"}
}