{
  "type": "Feature",
  "properties": {
    "iso:country":"FR",
    "sg:address":"26, Av. Victor Hugo, 56000 Vannes",
    "sg:city":"Vannes",
    "sg:orig_category":"Non-Classified Establishments",
    "sg:phone":"+33 2 97 42 78 78",
    "sg:postcode":"56000",
    "sg:province":"Bretagne",
    "wof:name":"I.p.s. Atlantique Groupe Creyf's Int\u00e9rim - Int\u00e9rim Poly Services Atlantique",
    "wof:placetype":"venue"
},
  "geometry": {"coordinates":[-2.757457,47.660534],"type":"Point"}
}