{
  "type": "Feature",
  "properties": {
    "addr:full":"13 Rue Louise Michel 38100 Grenoble Rhone-Alpes 38100",
    "addr:housenumber":"13",
    "addr:postcode":"38100;38100",
    "addr:street":"Rue Louise Michel",
    "iso:country":"FR",
    "sg:address":"13 Rue Louise Michel 38100 Grenoble",
    "sg:classifiers":[
        {
            "category":"Professional",
            "subcategory":"Engineering",
            "type":"Services"
        }
    ],
    "sg:phone":"+33 4 76 84 26 30",
    "sg:postcode":"38100",
    "sg:province":"Rhone-Alpes",
    "sg:tags":[
        "machine",
        "-",
        "mechanical"
    ],
    "wof:name":"Cuenod Thermotechnique (ctt)",
    "wof:placetype":"venue"
},
  "geometry": {"coordinates":[5.71067,45.16972],"type":"Point"}
}