{
  "type": "Feature",
  "properties": {
    "iso:country":"FR",
    "sg:address":"7 Rue De Furchhausen Zi Du Kochersberg 67700 Saverne",
    "sg:city":"Saverne",
    "sg:classifiers":[
        {
            "category":"Professional",
            "subcategory":"Engineering",
            "type":"Services"
        }
    ],
    "sg:phone":"+33 3 88 02 12 02",
    "sg:postcode":"67700",
    "sg:province":"Alsace",
    "sg:tags":[
        "machine",
        "-",
        "mechanical"
    ],
    "wof:name":"Tecnopan",
    "wof:placetype":"venue"
},
  "geometry": {"coordinates":[7.366026,48.739471],"type":"Point"}
}