{
  "type": "Feature",
  "properties": {
    "addr:full":"83177 Brignoles C\u00e9dex^^RN 7 - Rue Ambroise Croizat Tourves Provence-Alpes-C\u00f4te d'Azur 83170",
    "addr:housenumber":"7",
    "addr:postcode":"83177;83170",
    "addr:street":"Ce\u0301Dex^^Rn;Rue Ambroise Croizat",
    "iso:country":"FR",
    "sg:address":"83177 Brignoles C\u00e9dex^^RN 7 - Rue Ambroise Croizat",
    "sg:city":"Tourves",
    "sg:orig_category":"Non-Classified Establishments",
    "sg:phone":"+33 4 98 05 17 00",
    "sg:postcode":"83170",
    "sg:province":"Provence-Alpes-C\u00f4te d'Azur",
    "wof:name":"So.te.m. S.c.a. - Soci\u00e9t\u00e9 De Terrassement M\u00e9canique Maurice Garrassin Et Compagnie",
    "wof:placetype":"venue"
},
  "geometry": {"coordinates":[5.853343,43.393883],"type":"Point"}
}