{
  "type": "Feature",
  "properties": {
    "addr:full":"Rte de Guem\u00e9n\u00e9 Scorff Plouray Bretagne 56770",
    "addr:postcode":"56770",
    "addr:street":"Rte De Gueme\u0301Ne\u0301 Scorff Plouray Bretagne",
    "iso:country":"FR",
    "sg:address":"Rte de Guem\u00e9n\u00e9 Scorff",
    "sg:city":"Plouray",
    "sg:orig_category":"Non-Classified Establishments",
    "sg:phone":"+33 2 97 34 81 85",
    "sg:postcode":"56770",
    "sg:province":"Bretagne",
    "wof:name":"Doux Industrie Plouray S.n.c.",
    "wof:placetype":"venue"
},
  "geometry": {"coordinates":[-3.386736,48.145195],"type":"Point"}
}