{
  "type": "Feature",
  "properties": {
    "addr:full":"B.P. 811, 80008 Amiens C\u00e9dex 1^^133, Rue Alexandre Dumas, 80000 Amiens Picardie 80000",
    "addr:housenumber":"b.p. 811;1 ^ ^ 133",
    "addr:postcode":"80008;80000;80000",
    "addr:street":"Ce\u0301Dex;Rue Alexandre Dumas",
    "iso:country":"FR",
    "sg:address":"B.P. 811, 80008 Amiens C\u00e9dex 1^^133, Rue Alexandre Dumas, 80000 Amiens",
    "sg:orig_category":"Non-Classified Establishments",
    "sg:phone":"+33 3 22 53 12 12",
    "sg:postcode":"80000",
    "sg:province":"Picardie",
    "wof:name":"Alcatel R\u00e9seaux D'entreprise R\u00e9gion Nord-est",
    "wof:placetype":"venue"
},
  "geometry": {"coordinates":[2.293165,49.894733],"type":"Point"}
}