{
  "type": "Feature",
  "properties": {
    "addr:full":"Camp Aviation Frejorgues Aeroport Mtp Mediterranee 34130 Mauguio Languedoc-Roussillon 34130",
    "addr:postcode":"34130;34130",
    "addr:street":"Aeroport;Mediterranee",
    "iso:country":"FR",
    "sg:address":"Camp Aviation Frejorgues Aeroport Mtp Mediterranee 34130 Mauguio",
    "sg:classifiers":[
        {
            "category":"Professional",
            "subcategory":"Business Services",
            "type":"Services"
        }
    ],
    "sg:phone":"+33 4 67 15 05 05",
    "sg:postcode":"34130",
    "sg:province":"Languedoc-Roussillon",
    "sg:tags":[
        "training",
        "advice"
    ],
    "wof:name":"Aeoroclub De L'uero",
    "wof:placetype":"venue"
},
  "geometry": {"coordinates":[4.0079,43.617867],"type":"Point"}
}