{
  "type": "Feature",
  "properties": {
    "iso:country":"FR",
    "sg:address":"75 bis, Rue Pasteur, 33185 Le Haillan",
    "sg:city":"Le Haillan",
    "sg:orig_category":"Unclassifiable Establishments",
    "sg:phone":"+33 5 56 57 88 03",
    "sg:postcode":"33185",
    "sg:province":"Aquitaine",
    "wof:name":"Apex S.a.",
    "wof:placetype":"venue"
},
  "geometry": {"coordinates":[-0.67502,44.870708],"type":"Point"}
}