{
  "type": "Feature",
  "properties": {
    "iso:country":"FR",
    "sg:address":"14 RUE D AGEN 94550 Chevilly Larue",
    "sg:classifiers":[
        {
            "category":"Food & Beverages",
            "subcategory":"Fruits & Vegetables",
            "type":"Retail Goods"
        }
    ],
    "sg:phone":"+33 1 45 60 61 40",
    "sg:postcode":"94550",
    "sg:province":"Ile de France",
    "wof:name":"St\u00e9 Pierre Desmettre Et Fils Sa",
    "wof:placetype":"venue"
},
  "geometry": {"coordinates":[2.349525,48.762177],"type":"Point"}
}