{
  "type": "Feature",
  "properties": {
    "iso:country":"FR",
    "sg:address":"12, Rue Bossuet, 57000 Metz",
    "sg:orig_category":"Unclassifiable Establishments",
    "sg:phone":"+33 3 87 55 99 90",
    "sg:province":"Lorraine",
    "wof:name":"Messm\u00e9tallurgie France S.a.r.l.",
    "wof:placetype":"venue"
},
  "geometry": {"coordinates":[6.164845,49.108086],"type":"Point"}
}