{
  "type": "Feature",
  "properties": {
    "addr:full":"La Fontenelle 71290 Cuisery Cuisery Bourgogne 71290",
    "addr:postcode":"71290;71290",
    "addr:street":"La Fontenelle",
    "iso:country":"FR",
    "sg:address":"La Fontenelle 71290 Cuisery",
    "sg:city":"Cuisery",
    "sg:orig_category":"Non-Classified Establishments",
    "sg:phone":"+33 3 85 27 01 50",
    "sg:postcode":"71290",
    "sg:province":"Bourgogne",
    "wof:name":"Transports Cartier S.a.r.l.",
    "wof:placetype":"venue"
},
  "geometry": {"coordinates":[4.99435,46.56918],"type":"Point"}
}