{
  "type": "Feature",
  "properties": {
    "addr:full":"5 Rue Du Stade 10220 Piney Champagne 10220",
    "addr:housenumber":"5",
    "addr:postcode":"10220;10220",
    "addr:street":"Rue Du Stade;Champagne",
    "iso:country":"FR",
    "sg:address":"5 Rue Du Stade 10220 Piney",
    "sg:classifiers":[
        {
            "category":"Wholesale",
            "subcategory":"Medical Equipment & Supplies",
            "type":"Manufacturing & Wholesale Goods"
        }
    ],
    "sg:phone":"+33 3 25 46 32 60",
    "sg:postcode":"10220",
    "sg:province":"Champagne",
    "sg:tags":[
        "instrument",
        "health",
        "-",
        "precision"
    ],
    "wof:name":"Cfc Sn",
    "wof:placetype":"venue"
},
  "geometry": {"coordinates":[4.329514,48.358788],"type":"Point"}
}