{
  "type": "Feature",
  "properties": {
    "addr:full":"La Froide Rue 50760 REVILLE R\u00e9ville Basse Normandie 50760",
    "addr:postcode":"50760;50760",
    "addr:street":"Rue",
    "iso:country":"FR",
    "sg:address":"La Froide Rue 50760 REVILLE",
    "sg:city":"R\u00e9ville",
    "sg:orig_category":"Fresh Vegetables, Lettuces, And Potatoes",
    "sg:phone":"+33 2 33 54 46 55",
    "sg:postcode":"50760",
    "sg:province":"Basse Normandie",
    "wof:name":"Ets Ruel Sa",
    "wof:placetype":"venue"
},
  "geometry": {"coordinates":[-1.249468,49.626358],"type":"Point"}
}