{
  "type": "Feature",
  "properties": {
    "addr:full":"B.P. 3, 59310 Beuvry la For\u00eat^^Chemin Vicinal, 59310 Beuvry la For\u00eat Nord Pas-de-Calais",
    "addr:housenumber":"3",
    "addr:postcode":"59310;59310",
    "addr:street":"B.P.;Vicinal",
    "iso:country":"FR",
    "sg:address":"B.P. 3, 59310 Beuvry la For\u00eat^^Chemin Vicinal, 59310 Beuvry la For\u00eat",
    "sg:orig_category":"Non-Classified Establishments",
    "sg:phone":"+33 3 20 61 62 99",
    "sg:province":"Nord Pas-de-Calais",
    "wof:name":"Saria Industries S.a.",
    "wof:placetype":"venue"
},
  "geometry": {"coordinates":[3.201455,50.452564],"type":"Point"}
}