{
  "type": "Feature",
  "properties": {
    "addr:full":"40, Rue de la Reconnaissance, 62100 Calais Nord Pas-de-Calais",
    "addr:housenumber":"40",
    "addr:postcode":"62100",
    "addr:street":"Rue De La Reconnaissance;Calais;Pas-De-Calais",
    "iso:country":"FR",
    "sg:address":"40, Rue de la Reconnaissance, 62100 Calais",
    "sg:orig_category":"Non-Classified Establishments",
    "sg:phone":"+33 3 21 36 58 40",
    "sg:province":"Nord Pas-de-Calais",
    "wof:name":"Vilet Alu S.a.r.l.",
    "wof:placetype":"venue"
},
  "geometry": {"coordinates":[1.856526,50.943127],"type":"Point"}
}