{
  "type": "Feature",
  "properties": {
    "iso:country":"FR",
    "sg:address":"rue Bardoux; Bouvron",
    "sg:classifiers":[
        {
            "category":"Banks & Credit Unions",
            "subcategory":"Bank",
            "type":"Services"
        }
    ],
    "sg:phone":"+33 3340563143",
    "sg:province":"Limousin",
    "wof:name":"Cr\u00e9dit Agricole",
    "wof:placetype":"venue"
},
  "geometry": {"coordinates":[-75.605957,37.787762],"type":"Point"}
}