{
  "type": "Feature",
  "properties": {
    "iso:country":"FR",
    "sg:address":"352 Bd Marcel Paul 44800 St Herblain",
    "sg:classifiers":[
        {
            "category":"Building & Trades",
            "subcategory":"Electrical",
            "type":"Services"
        }
    ],
    "sg:phone":"+33 2 40 92 13 83",
    "sg:postcode":"44800",
    "sg:province":"Pays de Loire",
    "sg:tags":[
        "electronic",
        "lighting",
        "equipment"
    ],
    "wof:name":"Revimex",
    "wof:placetype":"venue"
},
  "geometry": {"coordinates":[-1.639019,47.22366],"type":"Point"}
}