{
  "type": "Feature",
  "properties": {
    "iso:country":"FR",
    "sg:address":"17, Rue Caulaincourt, 37000 Tours",
    "sg:city":"Tours",
    "sg:orig_category":"Unclassifiable Establishments",
    "sg:phone":"+33 2 47 51 65 00",
    "sg:postcode":"37000",
    "sg:province":"Centre",
    "wof:name":"Proteg S\u00e9curit\u00e9 S.a.r.l.",
    "wof:placetype":"venue"
},
  "geometry": {"coordinates":[0.674208,47.424129],"type":"Point"}
}