{
  "type": "Feature",
  "properties": {
    "addr:full":"Route De Polignac 43770 Chadrac Polignac Auvergne 43770",
    "addr:postcode":"43770;polignac;43770",
    "addr:street":"Route De Polignac",
    "iso:country":"FR",
    "sg:address":"Route De Polignac 43770 Chadrac",
    "sg:city":"Polignac",
    "sg:classifiers":[
        {
            "category":"Food & Beverages",
            "subcategory":"Groceries & Convenience Stores",
            "type":"Retail Goods"
        }
    ],
    "sg:phone":"+33 4 71 04 06 46",
    "sg:postcode":"43770",
    "sg:province":"Auvergne",
    "sg:tags":[
        "product",
        "related"
    ],
    "wof:name":"Genedis-promocash",
    "wof:placetype":"venue"
},
  "geometry": {"coordinates":[3.898947,45.067707],"type":"Point"}
}