{
  "type": "Feature",
  "properties": {
    "addr:full":"4bis, Rue Jean Jaur\u00e8s, 10440 La Rivi\u00e8re de Corps Champagne",
    "addr:housenumber":"4bis",
    "addr:postcode":"10440",
    "addr:street":"Rue Jean Jaure\u0300S",
    "iso:country":"FR",
    "sg:address":"4bis, Rue Jean Jaur\u00e8s, 10440 La Rivi\u00e8re de Corps",
    "sg:orig_category":"Unclassifiable Establishments",
    "sg:phone":"+33 3 25 74 86 20",
    "sg:province":"Champagne",
    "wof:name":"Onet S.a.",
    "wof:placetype":"venue"
},
  "geometry": {"coordinates":[4.037379,48.289051],"type":"Point"}
}