{
  "type": "Feature",
  "properties": {
    "iso:country":"FR",
    "sg:address":"B.P. 2",
    "sg:city":"Montguyon^^Marennes 17270 Montguyon",
    "sg:orig_category":"Non-Classified Establishments",
    "sg:phone":"+33 5 46 04 11 38",
    "sg:postcode":"17270",
    "sg:province":"Poitou-Charentes",
    "wof:name":"Bast\u00e8re Fr\u00e8res S.a.r.l.",
    "wof:placetype":"venue"
},
  "geometry": {"coordinates":[-0.205404,45.124851],"type":"Point"}
}