{
  "type": "Feature",
  "properties": {
    "iso:country":"FR",
    "sg:address":"5, Place de la Libert\u00e9, 33130 B\u00e8gles",
    "sg:city":"B\u00e8gles",
    "sg:orig_category":"Unclassifiable Establishments",
    "sg:phone":"+33 5 56 49 43 11",
    "sg:postcode":"33130",
    "sg:province":"Aquitaine",
    "wof:name":"C.m.f. Cr\u00e9ations S.a.r.l.",
    "wof:placetype":"venue"
},
  "geometry": {"coordinates":[-0.553824,44.807812],"type":"Point"}
}