{
  "type": "Feature",
  "properties": {
    "iso:country":"FR",
    "sg:address":"6 Rue Du Faubourg Des Moulins 39200 St Claude",
    "sg:classifiers":[
        {
            "category":"Manufacturing",
            "subcategory":"Rubber & Plastics",
            "type":"Manufacturing & Wholesale Goods"
        }
    ],
    "sg:phone":"+33 3 84 45 79 00",
    "sg:province":"Franche Comt\u00e9",
    "wof:name":"Jeantet Elastomeres",
    "wof:placetype":"venue"
},
  "geometry": {"coordinates":[5.864386,46.39513],"type":"Point"}
}