{
  "type": "Feature",
  "properties": {
    "addr:full":"Ccal Englos Les G\u00e9ants Autorte Lille D'Ankerk 59482 Haubourdin Cedex Centre",
    "addr:postcode":"59482;cedex",
    "iso:country":"FR",
    "sg:address":"Ccal Englos Les G\u00e9ants Autorte Lille D'Ankerk 59482 Haubourdin Cedex",
    "sg:classifiers":[
        {
            "category":"Home & Garden",
            "subcategory":"Kitchen Supply",
            "type":"Retail Goods"
        }
    ],
    "sg:phone":"+33 3 20 08 56 56",
    "sg:province":"Centre",
    "sg:tags":[
        "telecommunication",
        "household",
        "appliance",
        "equipment",
        "electrical",
        "electronic",
        "audio-visual"
    ],
    "wof:name":"Darty Nord Pas De Calais Snc",
    "wof:placetype":"venue"
},
  "geometry": {"coordinates":[2.972862,50.612518],"type":"Point"}
}