{
  "type": "Feature",
  "properties": {
    "addr:full":"Centre Commercial Jean de la Fontaine Mably Rhone-Alpes 42300",
    "addr:postcode":"42300",
    "addr:street":"Commercial;Fontaine;Rhone-Alpes",
    "iso:country":"FR",
    "sg:address":"Centre Commercial Jean de la Fontaine",
    "sg:city":"Mably",
    "sg:orig_category":"Non-Classified Establishments",
    "sg:phone":"+33 4 77 70 80 37",
    "sg:postcode":"42300",
    "sg:province":"Rhone-Alpes",
    "wof:name":"Icon\u00e9a Photo S.a.",
    "wof:placetype":"venue"
},
  "geometry": {"coordinates":[4.065885,46.085747],"type":"Point"}
}