{
  "type": "Feature",
  "properties": {
    "addr:full":"22, Quai Auguste Pr\u00e9vost, 77500 Chelles Ile de France",
    "addr:housenumber":"22",
    "addr:postcode":"77500;ile",
    "addr:street":"Quai Auguste Pre\u0301Vost",
    "iso:country":"FR",
    "sg:address":"22, Quai Auguste Pr\u00e9vost, 77500 Chelles",
    "sg:orig_category":"Unclassifiable Establishments",
    "sg:phone":"+33 1 60 08 21 52",
    "sg:province":"Ile de France",
    "wof:name":"Au Service Des Jardins S.a.",
    "wof:placetype":"venue"
},
  "geometry": {"coordinates":[2.583526,48.866135],"type":"Point"}
}