{
  "type": "Feature",
  "properties": {
    "iso:country":"FR",
    "sg:address":"Rue Godin - ZA de Troyalac'h",
    "sg:city":"Saint Evarzec",
    "sg:orig_category":"Unclassifiable Establishments",
    "sg:phone":"+33 2 98 94 65 65",
    "sg:postcode":"29170",
    "sg:province":"Bretagne",
    "wof:name":"Gr\u00e9goire Marquages S.a.r.l.",
    "wof:placetype":"venue"
},
  "geometry": {"coordinates":[-3.999947,47.972343],"type":"Point"}
}