{
  "type": "Feature",
  "properties": {
    "iso:country":"FR",
    "sg:address":"Actiparc 1 - B\u00e2t. 4",
    "sg:city":"La Penne sur Huveaune",
    "sg:orig_category":"Unclassifiable Establishments",
    "sg:phone":"+33 4 91 87 81 20",
    "sg:postcode":"13821",
    "sg:province":"Midi Pyr\u00e9n\u00e9es",
    "wof:name":"I.c.l. Sorbus",
    "wof:placetype":"venue"
},
  "geometry": {"coordinates":[5.513221,43.287525],"type":"Point"}
}