{
  "type": "Feature",
  "properties": {
    "addr:full":"Za BP 22 70360 Scey Sur Sa\u00f4ne Franche Comt\u00e9 70360",
    "addr:housenumber":"22",
    "addr:postcode":"70360;70360",
    "addr:street":"Za Bp;Franche Comte\u0301",
    "iso:country":"FR",
    "sg:address":"Za BP 22 70360 Scey Sur Sa\u00f4ne",
    "sg:classifiers":[
        {
            "category":"Wholesale",
            "subcategory":"Farm Supplies",
            "type":"Manufacturing & Wholesale Goods"
        }
    ],
    "sg:phone":"+33 3 84 92 76 76",
    "sg:postcode":"70360",
    "sg:province":"Franche Comt\u00e9",
    "sg:tags":[
        "-",
        "machine",
        "equipment",
        "engineering",
        "machinery",
        "mechanical",
        "agriculture"
    ],
    "wof:name":"Agriest (etablissements) Sa",
    "wof:placetype":"venue"
},
  "geometry": {"coordinates":[5.97174,47.664021],"type":"Point"}
}