{
  "type": "Feature",
  "properties": {
    "addr:full":"109, Bd Richard Lenoir, 75011 Paris Ile de France",
    "addr:housenumber":"109",
    "addr:postcode":"75011",
    "addr:street":"Bd Richard Lenoir",
    "iso:country":"FR",
    "sg:address":"109, Bd Richard Lenoir, 75011 Paris",
    "sg:orig_category":"Unclassifiable Establishments",
    "sg:phone":"+33 1 48 05 88 96",
    "sg:province":"Ile de France",
    "wof:name":"Star Shoes S.a.r.l.",
    "wof:placetype":"venue"
},
  "geometry": {"coordinates":[2.370068,48.864529],"type":"Point"}
}