{
  "type": "Feature",
  "properties": {
    "addr:full":"7, Rue de la Pierre Lev\u00e9e, 75500 Paris \u00cele-de-France",
    "addr:housenumber":"7",
    "addr:postcode":"75500",
    "addr:street":"Rue De La Pierre Leve\u0301E",
    "iso:country":"FR",
    "sg:address":"7, Rue de la Pierre Lev\u00e9e, 75500 Paris",
    "sg:orig_category":"Unclassifiable Establishments",
    "sg:phone":"+33 1 49 23 99 00",
    "sg:province":"\u00cele-de-France",
    "wof:name":"S.m.p. S.a. - Sirona Mat\u00e9riel Dentaire",
    "wof:placetype":"venue"
},
  "geometry": {"coordinates":[2.370575,48.866821],"type":"Point"}
}