{
  "type": "Feature",
  "properties": {
    "addr:full":"4, Rue Marius Vivier Merle - ZI, 69200 V\u00e9nissieux Rhone-Alpes 69200",
    "addr:housenumber":"4",
    "addr:postcode":"69200;69200",
    "addr:street":"Rue Marius Vivier",
    "iso:country":"FR",
    "sg:address":"4, Rue Marius Vivier Merle - ZI, 69200 V\u00e9nissieux",
    "sg:orig_category":"Unclassifiable Establishments",
    "sg:phone":"+33 4 72 50 31 47",
    "sg:postcode":"69200",
    "sg:province":"Rhone-Alpes",
    "wof:name":"Ovako Acier S.a.",
    "wof:placetype":"venue"
},
  "geometry": {"coordinates":[4.901811,45.692963],"type":"Point"}
}