{
  "type": "Feature",
  "properties": {
    "iso:country":"FR",
    "sg:address":"2/4, Rue Gutenberg, 42270 Saint Priest en Jarez",
    "sg:orig_category":"Unclassifiable Establishments",
    "sg:phone":"+33 4 77 92 82 82",
    "sg:province":"Rhone-Alpes",
    "wof:name":"Connexion S.a.",
    "wof:placetype":"venue"
},
  "geometry": {"coordinates":[4.365393,45.477085],"type":"Point"}
}