{
  "type": "Feature",
  "properties": {
    "addr:full":"2, Rue Saint Gilles, 68230 Turckheim Turckheim Alsace 68230",
    "addr:housenumber":"2",
    "addr:postcode":"68230;68230",
    "addr:street":"Rue Saint Gilles",
    "iso:country":"FR",
    "sg:address":"2, Rue Saint Gilles, 68230 Turckheim",
    "sg:city":"Turckheim",
    "sg:orig_category":"Non-Classified Establishments",
    "sg:phone":"+33 3 89 27 77 77",
    "sg:postcode":"68230",
    "sg:province":"Alsace",
    "wof:name":"Staub S.a.",
    "wof:placetype":"venue"
},
  "geometry": {"coordinates":[7.270024,48.084362],"type":"Point"}
}