{
  "type": "Feature",
  "properties": {
    "addr:full":"1, Rue Camille Gu\u00e9rin, 31820 Pibrac Midi Pyr\u00e9n\u00e9es",
    "addr:housenumber":"1",
    "addr:postcode":"31820",
    "addr:street":"Rue Camille Gue\u0301Rin",
    "iso:country":"FR",
    "sg:address":"1, Rue Camille Gu\u00e9rin, 31820 Pibrac",
    "sg:orig_category":"Unclassifiable Establishments",
    "sg:phone":"+33 5 61 06 02 20",
    "sg:province":"Midi Pyr\u00e9n\u00e9es",
    "wof:name":"G\u00e9n\u00e9rale De Logiciels Et D'exploitations S.a.",
    "wof:placetype":"venue"
},
  "geometry": {"coordinates":[1.265407,43.612064],"type":"Point"}
}