{
  "type": "Feature",
  "properties": {
    "iso:country":"FR",
    "sg:address":"ZA Plaine Brunette Ath\u00e9lia II",
    "sg:city":"La Ciotat",
    "sg:orig_category":"Non-Classified Establishments",
    "sg:phone":"+33 4 42 83 29 96",
    "sg:postcode":"13600",
    "sg:province":"Alsace",
    "wof:name":"Reynaud S.a.r.l.",
    "wof:placetype":"venue"
},
  "geometry": {"coordinates":[5.610365,43.174191],"type":"Point"}
}