{
  "type": "Feature",
  "properties": {
    "addr:full":"74, Rue Bouteiller, 69520 Grigny Rhone-Alpes",
    "addr:housenumber":"74",
    "addr:postcode":"69520",
    "addr:street":"Rue Bouteiller",
    "iso:country":"FR",
    "sg:address":"74, Rue Bouteiller, 69520 Grigny",
    "sg:orig_category":"Unclassifiable Establishments",
    "sg:phone":"+33 4 72 24 04 88",
    "sg:province":"Rhone-Alpes",
    "wof:name":"S.a.i.p. S.a.r.l. - Soci\u00e9t\u00e9 Application Industrielle Plastiques",
    "wof:placetype":"venue"
},
  "geometry": {"coordinates":[4.79042,45.60714],"type":"Point"}
}