{
  "type": "Feature",
  "properties": {
    "iso:country":"FR",
    "sg:address":"B.P. 6, 53101 Mayenne C\u00e9dex^^273, Rue de Jouvence, 53100 Mayenne",
    "sg:orig_category":"Non-Classified Establishments",
    "sg:phone":"+33 2 43 04 30 69",
    "sg:postcode":"53100",
    "sg:province":"Pays de Loire",
    "wof:name":"Coulange S.a.",
    "wof:placetype":"venue"
},
  "geometry": {"coordinates":[-0.655999,48.262119],"type":"Point"}
}