{
  "type": "Feature",
  "properties": {
    "addr:full":"19 Av Gare 89160 L\u00e9zinnes L\u00e9zinnes Bourgogne 89160",
    "addr:postcode":"89160;89160",
    "addr:street":"19 Av Gare",
    "iso:country":"FR",
    "sg:address":"19 Av Gare 89160 L\u00e9zinnes",
    "sg:city":"L\u00e9zinnes",
    "sg:classifiers":[
        {
            "category":"Farming",
            "subcategory":"Livestock Farm",
            "type":"Manufacturing & Wholesale Goods"
        }
    ],
    "sg:phone":"+33 3 86 75 63 45",
    "sg:postcode":"89160",
    "sg:province":"Bourgogne",
    "sg:tags":[
        "grain",
        "agriculture",
        "cereal"
    ],
    "wof:name":"Ets Ramel",
    "wof:placetype":"venue"
},
  "geometry": {"coordinates":[4.09813,47.805161],"type":"Point"}
}