{
  "type": "Feature",
  "properties": {
    "iso:country":"FR",
    "sg:address":"5, Rue des Artisants - Zone Industrielle, 67550 Vendenheim",
    "sg:city":"Vendenheim",
    "sg:orig_category":"Non-Classified Establishments",
    "sg:phone":"+33 3 88 18 35 10",
    "sg:postcode":"67550",
    "sg:province":"Alsace",
    "wof:name":"A.d.t. S\u00e9curit\u00e9 Service S.a.",
    "wof:placetype":"venue"
},
  "geometry": {"coordinates":[7.71285,48.669338],"type":"Point"}
}