{
  "type": "Feature",
  "properties": {
    "addr:full":"12 Rue Emile Augier 26000 Valence Rhone-Alpes 26000",
    "addr:housenumber":"12",
    "addr:postcode":"26000;26000",
    "addr:street":"Rue Emile Augier",
    "iso:country":"FR",
    "sg:address":"12 Rue Emile Augier 26000 Valence",
    "sg:classifiers":[
        {
            "category":"Shopping",
            "subcategory":"Clothing, Apparel, & Fashions",
            "type":"Retail Goods"
        }
    ],
    "sg:phone":"+33 4 75 42 80 05",
    "sg:postcode":"26000",
    "sg:province":"Rhone-Alpes",
    "sg:tags":[
        "textile",
        "clothing",
        "clothes"
    ],
    "wof:name":"Promod",
    "wof:placetype":"venue"
},
  "geometry": {"coordinates":[4.891866,44.932159],"type":"Point"}
}