{
  "type": "Feature",
  "properties": {
    "iso:country":"FR",
    "sg:address":"9, Rue de Molsheim, 67380 Lingolsheim",
    "sg:city":"Lingolsheim",
    "sg:orig_category":"Unclassifiable Establishments",
    "sg:phone":"+33 3 88 78 10 45",
    "sg:postcode":"67380",
    "sg:province":"Alsace",
    "wof:name":"M.h.d. S.a.",
    "wof:placetype":"venue"
},
  "geometry": {"coordinates":[7.691219,48.561562],"type":"Point"}
}