{
  "type": "Feature",
  "properties": {
    "iso:country":"FR",
    "sg:address":"31380 Villari\u00e8s",
    "sg:orig_category":"Non-Classified Establishments",
    "sg:phone":"+33 5 61 84 36 98",
    "sg:province":"Midi Pyr\u00e9n\u00e9es",
    "wof:name":"Prod\u00e9ra S.a.r.l.",
    "wof:placetype":"venue"
},
  "geometry": {"coordinates":[1.492285,43.754086],"type":"Point"}
}