{
  "type": "Feature",
  "properties": {
    "iso:country":"FR",
    "sg:address":"15, Chemin du Moulin \u00e0 Vent - ZA du Moulin \u00e0 Vent, 78280 Guyancourt",
    "sg:orig_category":"Non-Classified Establishments",
    "sg:phone":"+33 1 39 30 57 57",
    "sg:postcode":"78280",
    "sg:province":"Ile de France",
    "wof:name":"Abex S.a.",
    "wof:placetype":"venue"
},
  "geometry": {"coordinates":[2.06956,48.771046],"type":"Point"}
}