{
  "type": "Feature",
  "properties": {
    "addr:full":"78, Rue Brauhauban, 65000 Tarbes Midi Pyr\u00e9n\u00e9es 65000",
    "addr:housenumber":"78",
    "addr:postcode":"65000;65000",
    "addr:street":"Rue Brauhauban",
    "iso:country":"FR",
    "sg:address":"78, Rue Brauhauban, 65000 Tarbes",
    "sg:orig_category":"Non-Classified Establishments",
    "sg:phone":"+33 5 62 34 57 78",
    "sg:postcode":"65000",
    "sg:province":"Midi Pyr\u00e9n\u00e9es",
    "wof:name":"Atefo Sigma",
    "wof:placetype":"venue"
},
  "geometry": {"coordinates":[0.080391,43.232544],"type":"Point"}
}