{
  "type": "Feature",
  "properties": {
    "iso:country":"FR",
    "sg:address":"5, Rue du Mouzon, 54520 Laxou",
    "sg:orig_category":"Unclassifiable Establishments",
    "sg:phone":"+33 3 83 95 57 57",
    "sg:province":"Lorraine",
    "wof:name":"Cegelec Nord Et Est S.a.",
    "wof:placetype":"venue"
},
  "geometry": {"coordinates":[6.121153,48.695957],"type":"Point"}
}