{
  "type": "Feature",
  "properties": {
    "iso:country":"FR",
    "sg:address":"10bis, Av de Guise, 60500 Chantilly",
    "sg:orig_category":"Non-Classified Establishments",
    "sg:phone":"+33 3 44 57 01 87",
    "sg:province":"Picardie",
    "wof:name":"Etiquettes Grille S.a.r.l.",
    "wof:placetype":"venue"
},
  "geometry": {"coordinates":[2.459711,49.180103],"type":"Point"}
}