{
  "type": "Feature",
  "properties": {
    "addr:full":"Actipolis R De Lesseps 33170 Gradignan Gradignan Aquitaine 33170",
    "addr:postcode":"33170;33170",
    "iso:country":"FR",
    "sg:address":"Actipolis R De Lesseps 33170 Gradignan",
    "sg:city":"Gradignan",
    "sg:classifiers":[
        {
            "category":"Manufacturing",
            "subcategory":"Metals",
            "type":"Manufacturing & Wholesale Goods"
        }
    ],
    "sg:phone":"+33 5 57 35 40 30",
    "sg:postcode":"33170",
    "sg:province":"Aquitaine",
    "sg:tags":[
        "metallurgy",
        "metalworking"
    ],
    "wof:name":"Etablissements Cance",
    "wof:placetype":"venue"
},
  "geometry": {"coordinates":[-0.614138,44.773132],"type":"Point"}
}