{
  "type": "Feature",
  "properties": {
    "iso:country":"FR",
    "sg:address":"4, Rue Isabelle, 30900 N\u00eemes",
    "sg:orig_category":"Unclassifiable Establishments",
    "sg:phone":"+33 4 66 23 17 79",
    "sg:province":"Languedoc-Roussillon",
    "wof:name":"Lancou",
    "wof:placetype":"venue"
},
  "geometry": {"coordinates":[4.350178,43.835659],"type":"Point"}
}