{
  "type": "Feature",
  "properties": {
    "iso:country":"FR",
    "sg:address":"34 Rue De La Vall\u00e9e Aux Boeufs 41000 Blois",
    "sg:city":"Blois",
    "sg:classifiers":[
        {
            "category":"Professional",
            "subcategory":"Computer Services",
            "type":"Services"
        }
    ],
    "sg:phone":"+33 2 54 57 40 00",
    "sg:postcode":"41000",
    "sg:province":"Centre",
    "sg:tags":[
        "information",
        "technology",
        "software"
    ],
    "wof:name":"Mgs Sarl",
    "wof:placetype":"venue"
},
  "geometry": {"coordinates":[1.325774,47.599442],"type":"Point"}
}