{
  "type": "Feature",
  "properties": {
    "iso:country":"FR",
    "sg:address":"5, Rue de la Butte Celtique - ZA de L\u00e8ves, 28300 L\u00e8ves",
    "sg:city":"L\u00e8ves",
    "sg:orig_category":"Non-Classified Establishments",
    "sg:phone":"+33 2 37 18 58 50",
    "sg:postcode":"28300",
    "sg:province":"Centre",
    "wof:name":"E.t.d.e. S.a. - Entreprise De Transport Et Distribution D'energie",
    "wof:placetype":"venue"
},
  "geometry": {"coordinates":[1.464137,48.448517],"type":"Point"}
}