{
  "type": "Feature",
  "properties": {
    "addr:full":"B.P. 9, 42153 Riorges^^187, Rue Jean Rostand, 42153 Riorges Rhone-Alpes 42153",
    "addr:housenumber":"9",
    "addr:postcode":"42153;42153;42153",
    "addr:street":"B.P.;Rue Jean Rostand;Rhone-Alpes",
    "iso:country":"FR",
    "sg:address":"B.P. 9, 42153 Riorges^^187, Rue Jean Rostand, 42153 Riorges",
    "sg:orig_category":"Non-Classified Establishments",
    "sg:phone":"+33 4 77 44 02 44",
    "sg:postcode":"42153",
    "sg:province":"Rhone-Alpes",
    "wof:name":"A.d.a.p.e.i. - C.a.t. De Riorges",
    "wof:placetype":"venue"
},
  "geometry": {"coordinates":[4.04235,46.039371],"type":"Point"}
}