{
  "type": "Feature",
  "properties": {
    "iso:country":"FR",
    "sg:address":"B.P. 9, 42153 Riorges^^187, Rue Jean Rostand, 42153 Riorges",
    "sg:orig_category":"Non-Classified Establishments",
    "sg:phone":"+33 4 77 44 02 44",
    "sg:postcode":"42153",
    "sg:province":"Rhone-Alpes",
    "wof:name":"A.d.a.p.e.i. - C.a.t. De Riorges",
    "wof:placetype":"venue"
},
  "geometry": {"coordinates":[4.04235,46.039371],"type":"Point"}
}