{
  "type": "Feature",
  "properties": {
    "iso:country":"FR",
    "sg:address":"1 Place Carnot 69002 Lyon",
    "sg:classifiers":[
        {
            "category":"Wholesale",
            "subcategory":"Medical Equipment & Supplies",
            "type":"Manufacturing & Wholesale Goods"
        }
    ],
    "sg:phone":"+33 4 72 41 87 82",
    "sg:postcode":"69002",
    "sg:province":"Rhone-Alpes",
    "sg:tags":[
        "instrument",
        "health",
        "-",
        "precision"
    ],
    "wof:name":"Duodental",
    "wof:placetype":"venue"
},
  "geometry": {"coordinates":[4.827461,45.751904],"type":"Point"}
}