{
  "type": "Feature",
  "properties": {
    "iso:country":"FR",
    "sg:address":"15, Rue de la Banque, 75002 Paris",
    "sg:orig_category":"Unclassifiable Establishments",
    "sg:phone":"+33 1 53 45 80 80",
    "sg:province":"Ile de France",
    "wof:name":"C.p. E. Conseil S.a.",
    "wof:placetype":"venue"
},
  "geometry": {"coordinates":[2.340521,48.867538],"type":"Point"}
}